Workbook
Name zsupermetrics_ru0GDtbZzDLHQOQtJJ6K08MvUDyyp7: #REF!
Name zsupermetrics_DQl8lUbpTRu3fayaJJi7lVfOGKjNU4: 'Data - P&L'!$A$3:$A$4
Name zsupermetrics_BioPyGBzcBsy60UCQmPcTuFReEmghI: 'Data - P&L'!$B$2:$B$3
Name zsupermetrics_refreshAll: SupermetricsQueries!$H$5
Name zsupermetrics_n3GtLgiKpTmd2pYmQNMuq6TPD0qE0b: #REF!
Name zsupermetrics_refreshAllSilent: SupermetricsQueries!$H$6
Name zsupermetrics_Mgms9p0QzysYvrIhnsKACeVBVxfIEO: #REF!
Name zsupermetrics_Mgms9p0QzysYvrIhnsKACeVBVxfIEO: 'Data - P&L'!$A$2:$A$3
Name zsupermetrics_forceRefresh: SupermetricsQueries!$H$4
Name zsupermetrics_wbYMmT0YL9bAN0yhimW0ziPFnia9Dx: #REF!
Name zsupermetrics_iNpyVy90bWCI0yUaFQpxOtzWMa6sW4: #REF!
Name zsupermetrics_xwoIpANxRm908eDp5oKTwQpEI8gvD4: #REF!
Name zsupermetrics_n3GtLgiKpTmd2pYmQNMuq6TPD0qE0b: 'Data - P&L'!$B$4:$B$5
Name rdataslayer_42b112e4e4be4305bb4c1be75e2dd549: 'Data - P&L'!$B$2:$C$3
Name zsupermetrics_9i4W4hgd80uRpQLMeX0eRnESN8gjyv: #REF!
Name zsupermetrics_5bmwtOpHUbSYmDMeuCPkrxaojTprPP: #REF!
Name rdataslayer_3753ddf3234e496aa261974a0222e193: 'Data - P&L'!$H$2:$I$2
Name zsupermetrics_SGBxROnInO9rFyh3H7j2Lldx0Bdc5v: #REF!
Name zsupermetrics_pxuhRTEmIU93xSgKclyxajD0fCZ6rF: #REF!
Name zsupermetrics_ru0GDtbZzDLHQOQtJJ6K08MvUDyyp7: 'Data - P&L'!$B$4:$B$5
Name zsupermetrics_qWp7V908pNEYMtfv8QZvSTeDnBAHOU: 'Data - P&L'!$B$5:$C$13
Name rdataslayer_4a0f150f4f2f4e4f85c890c75b7a1fa4: #REF!
Name zsupermetrics_8xojRjNDjo2jWHGDWjFEhflhyIq3Hq: #REF!
Name zsupermetrics_HgZqhorObHOtZHuyJjpmyYaEPoYntx: #REF!
Name zsupermetrics_YsFuuYtr8vOdNXCCPiFJIO38NP4b2T: #REF!
Name zsupermetrics_DQl8lUbpTRu3fayaJJi7lVfOGKjNU4: #REF!
Name zsupermetrics_YVuzfmsfdurz7Ldl84Rfns8oka6LsS: #REF!
Name zsupermetrics_4VkB7ij7WO0JjKBEgvjB2GHjSy2Egm: #REF!
Name zsupermetrics_9i4W4hgd80uRpQLMeX0eRnESN8gjyv: 'Data - P&L'!$C$13
Name zsupermetrics_lx4cNai7gT6tH4j08ZRkI21Qlpjioi: #REF!
Name rdataslayer_d70e473bcafe40a3aa834ce157fb2ba3: #REF!
Name zsupermetrics_NugLlrQxlKiqhxQae8EFpITBm1pLCj: 'Data - P&L'!$B$6:$C$13
Name zsupermetrics_8xojRjNDjo2jWHGDWjFEhflhyIq3Hq: Summary!$K$9:$K$33
Name zsupermetrics_FEamnpN5FsVYF0RtUTXAwunZ388Tkc: Forecast!$A$113:$C$141
Name rdataslayer_3753ddf3234e496aa261974a0222e193: #REF!
Name zsupermetrics_iNpyVy90bWCI0yUaFQpxOtzWMa6sW4: 'Data - P&L'!$A$2:$A$3
Name rdataslayer_4a0f150f4f2f4e4f85c890c75b7a1fa4: 'Data - P&L'!$D$2:$E$3
Name zsupermetrics_BioPyGBzcBsy60UCQmPcTuFReEmghI: #REF!
Name zsupermetrics_qWp7V908pNEYMtfv8QZvSTeDnBAHOU: #REF!
Name zsupermetrics_wbYMmT0YL9bAN0yhimW0ziPFnia9Dx: 'Data - P&L'!$A$2:$A$3
Name zsupermetrics_4VkB7ij7WO0JjKBEgvjB2GHjSy2Egm: 'Data - P&L'!$B$4:$C$10
Name zsupermetrics_lx4cNai7gT6tH4j08ZRkI21Qlpjioi: 'Data - P&L'!$B$4:$C$13
Name rdataslayer_42b112e4e4be4305bb4c1be75e2dd549: #REF!
Name rdataslayer_adf57e64065742daa5b4161161b1c3ca: #REF!
Name rdataslayer_adf57e64065742daa5b4161161b1c3ca: 'Data - P&L'!$B$4:$D$5
Name zsupermetrics_NugLlrQxlKiqhxQae8EFpITBm1pLCj: #REF!
Name zsupermetrics_xwoIpANxRm908eDp5oKTwQpEI8gvD4: #REF!
Name zsupermetrics_YsFuuYtr8vOdNXCCPiFJIO38NP4b2T: 'Data - P&L'!$B$4:$C$13
Name rdataslayer_d70e473bcafe40a3aa834ce157fb2ba3: 'Data - P&L'!$C$8:$D$9
Name zsupermetrics_HgZqhorObHOtZHuyJjpmyYaEPoYntx: 'Data - P&L'!$B$4:$B$5

Sheet Data_forecast_2024
B1: 45627 | C1: 45628 | D1: 45629 | E1: 45630 | F1: 45631 | G1: 45632 | H1: 45633 | I1: 45634 | J1: 45635 | K1: 45636 | L1: 45637 | M1: 45638 | N1: 45639 | O1: 45640 | P1: 45641 | Q1: 45642 | R1: 45643 | S1: 45644 | T1: 45645 | U1: 45646 | V1: 45647 | W1: 45648 | X1: 45649 | Y1: 45650 | Z1: 45651 | AA1: 45652 | AB1: 45653 | AC1: 45654 | AD1: 45655 | AE1: 45656 | AF1: 45657
A2: Quantities | B2: ='DTC - P&L'!B65+'AMAZON - P&L'!B36+'WALMART - P&L'!B19+'Digital Marketplaces - P&L'!B17+'Digital Marketplaces - P&L'!B129+'Digital Marketplaces - P&L'!B239+'COSTCO - P&L'!B19 -> 124 | C2: ='DTC - P&L'!C65+'AMAZON - P&L'!C36+'WALMART - P&L'!C19+'Digital Marketplaces - P&L'!C17+'Digital Marketplaces - P&L'!C129+'Digital Marketplaces - P&L'!C239+'COSTCO - P&L'!C19 -> 145 | D2: ='DTC - P&L'!D65+'AMAZON - P&L'!D36+'WALMART - P&L'!D19+'Digital Marketplaces - P&L'!D17+'Digital Marketplaces - P&L'!D129+'Digital Marketplaces - P&L'!D239+'COSTCO - P&L'!D19 -> 129 | E2: ='DTC - P&L'!E65+'AMAZON - P&L'!E36+'WALMART - P&L'!E19+'Digital Marketplaces - P&L'!E17+'Digital Marketplaces - P&L'!E129+'Digital Marketplaces - P&L'!E239+'COSTCO - P&L'!E19 -> 151 | F2: ='DTC - P&L'!F65+'AMAZON - P&L'!F36+'WALMART - P&L'!F19+'Digital Marketplaces - P&L'!F17+'Digital Marketplaces - P&L'!F129+'Digital Marketplaces - P&L'!F239+'COSTCO - P&L'!F19 -> 155 | G2: ='DTC - P&L'!G65+'AMAZON - P&L'!G36+'WALMART - P&L'!G19+'Digital Marketplaces - P&L'!G17+'Digital Marketplaces - P&L'!G129+'Digital Marketplaces - P&L'!G239+'COSTCO - P&L'!G19 -> 141 | H2: ='DTC - P&L'!H65+'AMAZON - P&L'!H36+'WALMART - P&L'!H19+'Digital Marketplaces - P&L'!H17+'Digital Marketplaces - P&L'!H129+'Digital Marketplaces - P&L'!H239+'COSTCO - P&L'!H19 -> 142 | I2: ='DTC - P&L'!I65+'AMAZON - P&L'!I36+'WALMART - P&L'!I19+'Digital Marketplaces - P&L'!I17+'Digital Marketplaces - P&L'!I129+'Digital Marketplaces - P&L'!I239+'COSTCO - P&L'!I19 -> 166 | ... AF2: ='DTC - P&L'!AF65+'AMAZON - P&L'!AF36+'WALMART - P&L'!AF19+'Digital Marketplaces - P&L'!AF17+'Digital Marketplaces - P&L'!AF129+'Digital Marketplaces - P&L'!AF239+'COSTCO - P&L'!AF19 -> 211
A3: Sales | B3: =Summary!B33+Summary!B79+Summary!B71+Summary!B45 -> 347569.25 | C3: =Summary!C33+Summary!C79+Summary!C71+Summary!C45 -> 318732.08 | D3: =Summary!D33+Summary!D79+Summary!D71+Summary!D45 -> 274274.49 | E3: =Summary!E33+Summary!E79+Summary!E71+Summary!E45 -> 221829.02 | F3: =Summary!F33+Summary!F79+Summary!F71+Summary!F45 -> 218022.8 | G3: =Summary!G33+Summary!G79+Summary!G71+Summary!G45 -> 172617.41 | H3: =Summary!H33+Summary!H79+Summary!H71+Summary!H45 -> 169640 | I3: =Summary!I33+Summary!I79+Summary!I71+Summary!I45 -> 176385.71 | ... AF3: =Summary!AF33+Summary!AF79+Summary!AF71+Summary!AF45 -> 77205.522

Sheet WALMART_Data_forecast_2024
B1: 45597 | C1: 45598 | D1: 45599 | E1: 45600 | F1: 45601 | G1: 45602 | H1: 45603 | I1: 45604 | J1: 45605 | K1: 45606 | L1: 45607 | M1: 45608 | N1: 45609 | O1: 45610 | P1: 45611 | Q1: 45612 | R1: 45613 | S1: 45614 | T1: 45615 | U1: 45616 | V1: 45617 | W1: 45618 | X1: 45619 | Y1: 45620 | Z1: 45621 | AA1: 45622 | AB1: 45623 | AC1: 45624 | AD1: 45625 | AE1: 45626
A2: Quantities | B2: ='WALMART - P&L'!B19 -> 0 | C2: ='WALMART - P&L'!C19 -> 2 | D2: ='WALMART - P&L'!D19 -> 1 | E2: ='WALMART - P&L'!E19 -> 0 | F2: ='WALMART - P&L'!F19 -> 0 | G2: ='WALMART - P&L'!G19 -> 1 | H2: ='WALMART - P&L'!H19 -> 1 | I2: ='WALMART - P&L'!I19 -> 0 | ... AF2: ='WALMART - P&L'!AF19 -> 0
A3: Sales | B3: =Summary!B53 -> 62.63 | C3: =Summary!C53 -> 635.17 | D3: =Summary!D53 -> 271.93 | E3: =Summary!E53 -> 0 | F3: =Summary!F53 -> 0 | G3: =Summary!G53 -> 382.97 | H3: =Summary!H53 -> 336.83 | I3: =Summary!I53 -> 31.39 | ... AF3: =Summary!AF53 -> 31.32

Sheet COSTCO_Data_forecast_2024
B1: 45627 | C1: 45628 | D1: 45629 | E1: 45630 | F1: 45631 | G1: 45632 | H1: 45633 | I1: 45634 | J1: 45635 | K1: 45636 | L1: 45637 | M1: 45638 | N1: 45639 | O1: 45640 | P1: 45641 | Q1: 45642 | R1: 45643 | S1: 45644 | T1: 45645 | U1: 45646 | V1: 45647 | W1: 45648 | X1: 45649 | Y1: 45650 | Z1: 45651 | AA1: 45652 | AB1: 45653 | AC1: 45654 | AD1: 45655 | AE1: 45656 | AF1: 45657
A2: Quantities | B2: ='COSTCO - P&L'!B19 -> 0 | C2: ='COSTCO - P&L'!C19 -> 0 | D2: ='COSTCO - P&L'!D19 -> 0 | E2: ='COSTCO - P&L'!E19 -> 0 | F2: ='COSTCO - P&L'!F19 -> 0 | G2: ='COSTCO - P&L'!G19 -> 0 | H2: ='COSTCO - P&L'!H19 -> 0 | I2: ='COSTCO - P&L'!I19 -> 0 | ... AF2: ='COSTCO - P&L'!AF19 -> 4
A3: Sales | B3: =Summary!B45 -> 0 | C3: =Summary!C45 -> 0 | D3: =Summary!D45 -> 0 | E3: =Summary!E45 -> 0 | F3: =Summary!F45 -> 0 | G3: =Summary!G45 -> 0 | H3: =Summary!H45 -> 0 | I3: =Summary!I45 -> 0 | ... AF3: =Summary!AF45 -> 1188.7255

Sheet DM_Data_forecast_2024
B1: 45627 | C1: 45628 | D1: 45629 | E1: 45630 | F1: 45631 | G1: 45632 | H1: 45633 | I1: 45634 | J1: 45635 | K1: 45636 | L1: 45637 | M1: 45638 | N1: 45639 | O1: 45640 | P1: 45641 | Q1: 45642 | R1: 45643 | S1: 45644 | T1: 45645 | U1: 45646 | V1: 45647 | W1: 45648 | X1: 45649 | Y1: 45650 | Z1: 45651 | AA1: 45652 | AB1: 45653 | AC1: 45654 | AD1: 45655 | AE1: 45656 | AF1: 45657
A2: Quantities | B2: ='Digital Marketplaces - P&L'!B17+'Digital Marketplaces - P&L'!B129+'Digital Marketplaces - P&L'!B239 -> 0 | C2: ='Digital Marketplaces - P&L'!C17+'Digital Marketplaces - P&L'!C129+'Digital Marketplaces - P&L'!C239 -> 0 | D2: ='Digital Marketplaces - P&L'!D17+'Digital Marketplaces - P&L'!D129+'Digital Marketplaces - P&L'!D239 -> 0 | E2: ='Digital Marketplaces - P&L'!E17+'Digital Marketplaces - P&L'!E129+'Digital Marketplaces - P&L'!E239 -> 0 | F2: ='Digital Marketplaces - P&L'!F17+'Digital Marketplaces - P&L'!F129+'Digital Marketplaces - P&L'!F239 -> 0 | G2: ='Digital Marketplaces - P&L'!G17+'Digital Marketplaces - P&L'!G129+'Digital Marketplaces - P&L'!G239 -> 0 | H2: ='Digital Marketplaces - P&L'!H17+'Digital Marketplaces - P&L'!H129+'Digital Marketplaces - P&L'!H239 -> 0 | I2: ='Digital Marketplaces - P&L'!I17+'Digital Marketplaces - P&L'!I129+'Digital Marketplaces - P&L'!I239 -> 0 | ... AF2: ='Digital Marketplaces - P&L'!AF17+'Digital Marketplaces - P&L'!AF129+'Digital Marketplaces - P&L'!AF239 -> 1
A3: Sales | B3: =Summary!B71 -> 0 | C3: =Summary!C71 -> 0 | D3: =Summary!D71 -> 0 | E3: =Summary!E71 -> 0 | F3: =Summary!F71 -> 0 | G3: =Summary!G71 -> 0 | H3: =Summary!H71 -> 0 | I3: =Summary!I71 -> 0 | ... AF3: =Summary!AF71 -> 254.72539

Sheet AMAZON_Data_forecast_2024
B1: 45597 | C1: 45598 | D1: 45599 | E1: 45600 | F1: 45601 | G1: 45602 | H1: 45603 | I1: 45604 | J1: 45605 | K1: 45606 | L1: 45607 | M1: 45608 | N1: 45609 | O1: 45610 | P1: 45611 | Q1: 45612 | R1: 45613 | S1: 45614 | T1: 45615 | U1: 45616 | V1: 45617 | W1: 45618 | X1: 45619 | Y1: 45620 | Z1: 45621 | AA1: 45622 | AB1: 45623 | AC1: 45624 | AD1: 45625 | AE1: 45626
A2: Quantities | B2: ='AMAZON - P&L'!B36 -> 64 | C2: ='AMAZON - P&L'!C36 -> 90 | D2: ='AMAZON - P&L'!D36 -> 73 | E2: ='AMAZON - P&L'!E36 -> 84 | F2: ='AMAZON - P&L'!F36 -> 86 | G2: ='AMAZON - P&L'!G36 -> 77 | H2: ='AMAZON - P&L'!H36 -> 72 | I2: ='AMAZON - P&L'!I36 -> 92 | ... AE2: ='AMAZON - P&L'!AE36 -> 61
A3: Sales | B3: =Summary!B27 -> 20026.6 | C3: =Summary!C27 -> 28799.1 | D3: =Summary!D27 -> 23958 | E3: =Summary!E27 -> 28901.2 | F3: =Summary!F27 -> 29312.82 | G3: =Summary!G27 -> 25501.91 | H3: =Summary!H27 -> 23405.2 | I3: =Summary!I27 -> 29757.41 | ... AF3: =Summary!AF27 -> 23985.36

Sheet DTC_Data_forecast_2024
B1: 45627 | C1: 45628 | D1: 45629 | E1: 45630 | F1: 45631 | G1: 45632 | H1: 45633 | I1: 45634 | J1: 45635 | K1: 45636 | L1: 45637 | M1: 45638 | N1: 45639 | O1: 45640 | P1: 45641 | Q1: 45642 | R1: 45643 | S1: 45644 | T1: 45645 | U1: 45646 | V1: 45647 | W1: 45648 | X1: 45649 | Y1: 45650 | Z1: 45651 | AA1: 45652 | AB1: 45653 | AC1: 45654 | AD1: 45655 | AE1: 45656 | AF1: 45657
A2: Quantities | B2: ='DTC - P&L'!B65 -> 60 | C2: ='DTC - P&L'!C65 -> 53 | D2: ='DTC - P&L'!D65 -> 55 | E2: ='DTC - P&L'!E65 -> 67 | F2: ='DTC - P&L'!F65 -> 69 | G2: ='DTC - P&L'!G65 -> 63 | H2: ='DTC - P&L'!H65 -> 69 | I2: ='DTC - P&L'!I65 -> 74 | ... AF2: ='DTC - P&L'!AF65 -> 127
A3: Sales | B3: =Summary!B9 -> 138390.47 | C3: =Summary!C9 -> 151225.52 | D3: =Summary!D9 -> 151451.22 | E3: =Summary!E9 -> 99608.559 | F3: =Summary!F9 -> 103556.73 | G3: =Summary!G9 -> 90242.155 | H3: =Summary!H9 -> 90339.034 | I3: =Summary!I9 -> 88015.047 | ... AF3: =Summary!AF9 -> 40433.49

Sheet Summary
B1: 45658 | C1: 45659 | D1: 45660 | E1: 45661 | F1: 45662 | G1: 45663 | H1: 45664 | I1: 45665 | J1: 45666 | K1: 45667 | L1: 45668 | M1: 45669 | N1: 45670 | O1: 45671 | P1: 45672 | Q1: 45673 | R1: 45674 | S1: 45675 | T1: 45676 | U1: 45677 | V1: 45678 | W1: 45679 | X1: 45680 | Y1: 45681 | Z1: 45682 | AA1: 45683 | AB1: 45684 | AC1: 45685 | AD1: 45686 | AE1: 45687 | AF1: 45688
B2: WED | C2: THU | D2: FRI | E2: SAT | F2: SUN | G2: MON | H2: TUE | I2: WED | J2: THU | K2: FRI | L2: SAT | M2: SUN | N2: MON | O2: TUE | P2: WED | Q2: THU | R2: FRI | S2: SAT | T2: SUN | U2: MON | V2: TUE | W2: WED | X2: THU | Y2: FRI | Z2: SAT | AA2: SUN | AB2: MON | AC2: TUE | AD2: WED | AE2: THU | AF2: FRI
A3: Notes | D3: SBF PRO In Stock (/Storefront/US) | I3: Added Add-on Amazon videos on PDPs (US/EU) | O3: VAT # in EU receipt emails | P3: redirect EU users to .eu site and vice versa | Q3: AvaTax Plugin disabled | R3: Shipping to Canada enabled (US) | W3: PayPal Plugin Updated | X3: Weekend Sale Up to 25% OFF | Y3: 3in1 Limited time offer removal (/Cart) | AB3: Winter Sale Up to 30% OFF | AF3: Valentine's Sale
D4: Family Premium Switch functionality EU | O4: WOO - Card functionality - switch order of cards and variations | R4: SKU3 V2 Discount -13% (Weekend Offer) | U4: SKU3 V2 Discount -13% (Winter Sale) | AB4: SKU3 V1 OOS (US)
A9: DTC Revenue | B9: =SUM(B10,B17,B24) -> 138390.47 | C9: =SUM(C10,C17,C24) -> 151225.52 | D9: =SUM(D10,D17,D24) -> 151451.22 | E9: =SUM(E10,E17,E24) -> 99608.559 | F9: =SUM(F10,F17,F24) -> 103556.73 | G9: =SUM(G10,G17,G24) -> 90242.155 | H9: =SUM(H10,H17,H24) -> 90339.034 | I9: =SUM(I10,I17,I24) -> 88015.047 | ... AF9: =SUM(AF10,AF17,AF24) -> 40433.49
A10: - DTC Revenue US&CA | B10: =sum(B11:B16) -> 32513.25 | C10: =sum(C11:C16) -> 27793.37 | D10: =sum(D11:D16) -> 28794.1 | E10: =sum(E11:E16) -> 32011.86 | F10: =sum(F11:F16) -> 33804.54 | G10: =sum(G11:G16) -> 25939.48 | H10: =sum(H11:H16) -> 26740.41 | I10: =sum(I11:I16) -> 28657.92 | ... AF10: =sum(AF11:AF16) -> 35862.51
A11: - Hardware | B11: 12382.12 | C11: 11605 | D11: 12358.05 | E11: 17039.5 | F11: 16960.2 | G11: 14331.3 | H11: 15021 | I11: 17465.6 | J11: 15843.6 | K11: 15047.7 | L11: 25198.6 | M11: 21421.2 | N11: 13093.4 | O11: 15569 | P11: 11748.6 | Q11: 9660.4 | R11: 14207.3 | S11: 20091.2 | T11: 18290.8 | U11: 17758.2 | V11: 19615.8 | W11: 19700.65 | X11: 26633.35 | Y11: 24376.1 | Z11: 23492.55 | AA11: 29612 | AB11: 24275.15 | AC11: 30845.5 | AD11: 26298.85 | AE11: 29790.65 | AF11: 26643.65
A12: - Add-ons | B12: 11484.08 | C12: 8466.2 | D12: 8023.15 | E12: 7842.2 | F12: 9018.4 | G12: 5711.4 | H12: 5676 | I12: 5167.6 | J12: 6817.4 | K12: 6827.9 | L12: 5878.7 | M12: 8233.4 | N12: 4279.4 | O12: 5128.8 | P12: 2789 | Q12: 3011.45 | R12: 3294.1 | S12: 5084.2 | T12: 5376.3 | U12: 3963.2 | V12: 3463.4 | W12: 4752.1 | X12: 6272.2 | Y12: 7388 | Z12: 8210.3 | AA12: 9821.9 | AB12: 5451 | AC12: 4807.1 | AD12: 4501 | AE12: 3853.8 | AF12: 3031
A13: - Merch | B13: 0 | C13: 0 | D13: 0 | E13: 0 | F13: 0 | G13: 0 | H13: 0 | I13: 0 | J13: 0 | K13: 39.99 | L13: 0 | M13: 0 | N13: 39.99 | O13: 0 | P13: 0 | Q13: 0 | R13: 0 | S13: 39.99 | T13: 109.96 | U13: 0 | V13: 0 | W13: 0 | X13: 29.99 | Y13: 39.99 | Z13: 0 | AA13: 0 | AB13: 0 | AC13: 0 | AD13: 0 | AE13: 0 | AF13: 0
A14: - Seeds | B14: 657 | C14: 454.4 | D14: 756.5 | E14: 596.9 | F14: 586.1 | G14: 335.6 | H14: 409.5 | I14: 331.8 | J14: 766.4 | K14: 549.2 | L14: 564.2 | M14: 497.5 | N14: 285.2 | O14: 499.3 | P14: 646.1 | Q14: 589 | R14: 606 | S14: 566.3 | T14: 336.9 | U14: 340.9 | V14: 505.3 | W14: 269.1 | X14: 330 | Y14: 421.5 | Z14: 501.5 | AA14: 466.6 | AB14: 508.1 | AC14: 316.9 | AD14: 440.6 | AE14: 354.9 | AF14: 432.6
A15: - Taxes | B15: 4928.35 | C15: 4728.89 | D15: 5167.52 | E15: 3607.16 | F15: 3951.86 | G15: 3241.54 | H15: 3330.51 | I15: 3154.94 | J15: 3108.9 | K15: 2659.86 | L15: 2968.59 | M15: 3272.94 | N15: 2470.75 | O15: 3150.53 | P15: 2324.83 | Q15: 2192.58 | R15: 2529.88 | S15: 2944.25 | T15: 3115.64 | U15: 2330.51 | V15: 2248.45 | W15: 2185.37 | X15: 2894.57 | Y15: 2533.08 | Z15: 2792.62 | AA15: 3116.51 | AB15: 2429.6 | AC15: 2855.81 | AD15: 2474.51 | AE15: 2606.27 | AF15: 2286.52
A16: - Shipping | B16: 3061.7 | C16: 2538.88 | D16: 2488.88 | E16: 2926.1 | F16: 3287.98 | G16: 2319.64 | H16: 2303.4 | I16: 2537.98 | J16: 2571.22 | K16: 2510.46 | L16: 3062.42 | M16: 3165.2 | N16: 1911.06 | O16: 2320.46 | P16: 1561.36 | Q16: 1493.84 | R16: 1946.7 | S16: 2842.96 | T16: 2637.68 | U16: 2448.57 | V16: 2457.38 | W16: 2668.85 | X16: 3572.8 | Y16: 3348.64 | Z16: 3455.88 | AA16: 4327.47 | AB16: 3476.34 | AC16: 4229.42 | AD16: 3662.69 | AE16: 3989.72 | AF16: 3468.74
A17: - DTC Revenue EU | B17: =SUM(B18:B23) -> 2141.9635 | C17: =SUM(C18:C23) -> 1323.3695 | D17: =SUM(D18:D23) -> 1988.7311 | E17: =SUM(E18:E23) -> 1192.1166 | F17: =SUM(F18:F23) -> 1205.1182 | G17: =SUM(G18:G23) -> 3051.0134 | H17: =SUM(H18:H23) -> 3347.4632 | I17: =SUM(I18:I23) -> 2946.463 | ... AF17: =SUM(AF18:AF23) -> 1516.1459
A18: - Hardware | B18: ='DTC EU - P&L'!B15*B$121 -> 975.37473 | C18: ='DTC EU - P&L'!C15*C$121 -> 257.94352 | D18: ='DTC EU - P&L'!D15*D$121 -> 715.93122 | E18: ='DTC EU - P&L'!E15*E$121 -> 462.44835 | F18: ='DTC EU - P&L'!F15*F$121 -> 511.41654 | G18: ='DTC EU - P&L'!G15*G$121 -> 1724.0245 | H18: ='DTC EU - P&L'!H15*H$121 -> 2031.272 | I18: ='DTC EU - P&L'!I15*I$121 -> 1662.4814 | ... AF18: ='DTC EU - P&L'!AF15*AF$121 -> 799.06035
A19: - Add-ons | B19: ='DTC EU - P&L'!B16*B$121 -> 50.171297 | C19: ='DTC EU - P&L'!C16*C$121 -> 155.47857 | D19: ='DTC EU - P&L'!D16*D$121 -> 316.19686 | E19: ='DTC EU - P&L'!E16*E$121 -> 230.62614 | F19: ='DTC EU - P&L'!F16*F$121 -> 0 | G19: ='DTC EU - P&L'!G16*G$121 -> 157.97735 | H19: ='DTC EU - P&L'!H16*H$121 -> 140.83356 | I19: ='DTC EU - P&L'!I16*I$121 -> 92.089542 | ... AF19: ='DTC EU - P&L'!AF16*AF$121 -> 268.08524
A20: - Merch | B20: ='DTC EU - P&L'!B17*B$121 -> 0 | C20: ='DTC EU - P&L'!C17*C$121 -> 0 | D20: ='DTC EU - P&L'!D17*D$121 -> 0 | E20: ='DTC EU - P&L'!E17*E$121 -> 0 | F20: ='DTC EU - P&L'!F17*F$121 -> 0 | G20: ='DTC EU - P&L'!G17*G$121 -> 0 | H20: ='DTC EU - P&L'!H17*H$121 -> 0 | I20: ='DTC EU - P&L'!I17*I$121 -> 0 | ... AF20: ='DTC EU - P&L'!AF17*AF$121 -> 0
A21: - Seeds | B21: ='DTC EU - P&L'!B18*B$121 -> 0 | C21: ='DTC EU - P&L'!C18*C$121 -> 0 | D21: ='DTC EU - P&L'!D18*D$121 -> 0 | E21: ='DTC EU - P&L'!E18*E$121 -> 0 | F21: ='DTC EU - P&L'!F18*F$121 -> 0 | G21: ='DTC EU - P&L'!G18*G$121 -> 0 | H21: ='DTC EU - P&L'!H18*H$121 -> 0 | I21: ='DTC EU - P&L'!I18*I$121 -> 0 | ... AF21: ='DTC EU - P&L'!AF18*AF$121 -> 0
A22: - Taxes | B22: ='DTC EU - P&L'!B20*B$121 -> 1002.5565 | C22: ='DTC EU - P&L'!C20*C$121 -> 853.48444 | D22: ='DTC EU - P&L'!D20*D$121 -> 827.70299 | E22: ='DTC EU - P&L'!E20*E$121 -> 406.24309 | F22: ='DTC EU - P&L'!F20*F$121 -> 642.17669 | G22: ='DTC EU - P&L'!G20*G$121 -> 1002.8836 | H22: ='DTC EU - P&L'!H20*H$121 -> 921.92969 | I22: ='DTC EU - P&L'!I20*I$121 -> 1001.0276 | ... AF22: ='DTC EU - P&L'!AF20*AF$121 -> 277.89526
A23: - Shipping | B23: ='DTC EU - P&L'!B21*B$121 -> 113.861 | C23: ='DTC EU - P&L'!C21*C$121 -> 56.463 | D23: ='DTC EU - P&L'!D21*D$121 -> 128.9 | E23: ='DTC EU - P&L'!E21*E$121 -> 92.799 | F23: ='DTC EU - P&L'!F21*F$121 -> 51.525 | G23: ='DTC EU - P&L'!G21*G$121 -> 166.128 | H23: ='DTC EU - P&L'!H21*H$121 -> 253.428 | I23: ='DTC EU - P&L'!I21*I$121 -> 190.8645 | ... AF23: ='DTC EU - P&L'!AF21*AF$121 -> 171.105
A24: - Yearly Premium Subscription | B24: =sum(B25:B26) -> 103735.26 | C24: =sum(C25:C26) -> 122108.78 | D24: =sum(D25:D26) -> 120668.38 | E24: =sum(E25:E26) -> 66404.582 | F24: =sum(F25:F26) -> 68547.074 | G24: =sum(G25:G26) -> 61251.662 | H24: =sum(H25:H26) -> 60251.16 | I24: =sum(I25:I26) -> 56410.664 | ... AF24: =sum(AF25:AF26) -> 3054.8346
A25: - Yearly Premium Subscription US&CA | B25: 100033.13 | C25: 118465.39 | D25: 117907.14 | E25: 65256.05 | F25: 66072.06 | G25: 58560.98 | H25: 58317.96 | I25: 53727.14 | J25: 54178.9 | K25: 41571.93 | L25: 36487.14 | M25: 44013.65 | N25: 51106.81 | O25: 59033.86 | P25: 48894.56 | Q25: 45313.83 | R25: 38832.72 | S25: 33186.35 | T25: 39257.71 | U25: 26192.68 | V25: 14413.74 | W25: 9013.77 | X25: 7115.38 | Y25: 8639.03 | Z25: 13258.44 | AA25: 5567.19 | AB25: 4499.49 | AC25: 2689.69 | AD25: 2535.45 | AE25: 2376.81 | AF25: 2977.07
A26: - Yearly Premium Subscription EU | B26: ='DTC EU - P&L'!B19*B$121 -> 3702.1283 | C26: ='DTC EU - P&L'!C19*C$121 -> 3643.3931 | D26: ='DTC EU - P&L'!D19*D$121 -> 2761.2442 | E26: ='DTC EU - P&L'!E19*E$121 -> 1148.532 | F26: ='DTC EU - P&L'!F19*F$121 -> 2475.0137 | G26: ='DTC EU - P&L'!G19*G$121 -> 2690.6818 | H26: ='DTC EU - P&L'!H19*H$121 -> 1933.2005 | I26: ='DTC EU - P&L'!I19*I$121 -> 2683.5239 | ... AF26: ='DTC EU - P&L'!AF19*AF$121 -> 77.76463
A27: Amazon Revenue | B27: =B28+B29+B30+B31+B32 -> 20026.6 | C27: =C28+C29+C30+C31+C32 -> 28799.1 | D27: =D28+D29+D30+D31+D32 -> 23958 | E27: =E28+E29+E30+E31+E32 -> 28901.2 | F27: =F28+F29+F30+F31+F32 -> 29312.82 | G27: =G28+G29+G30+G31+G32 -> 25501.91 | H27: =H28+H29+H30+H31+H32 -> 23405.2 | I27: =I28+I29+I30+I31+I32 -> 29757.41 | ... AF27: =AF28+AF29+AF30+AF31+AF32 -> 23985.36
A28: - Hardware | B28: 16658.38 | C28: 25109.18 | D28: 20102.12 | E28: 23515.24 | F28: 24193.24 | G28: 21565.68 | H28: 19505.8 | I28: 25763.36 | J28: 23692.88 | K28: 21093.8 | L28: 28339.16 | M28: 26259.68 | N28: 19194.12 | O28: 17921.5 | P28: 14673.5 | Q28: 16446.8 | R28: 16779.62 | S28: 17801.8 | T28: 18526.12 | U28: 16525.36 | V28: 15597.6 | W28: 20251.58 | X28: 21065.76 | Y28: 19099.52 | Z28: 26332.28 | AA28: 24356.52 | AB28: 15515.9 | AC28: 18065.38 | AD28: 15675.9 | AE28: 15016.14 | AF28: 19312.9
A29: - Add-ons | B29: 2039 | C29: 1737.3 | D29: 2205.78 | E29: 3405.26 | F29: 3165.26 | G29: 2260.2 | H29: 2355.66 | I29: 2145.84 | J29: 1430.02 | K29: 3003.28 | L29: 3697.26 | M29: 5641.26 | N29: 3363.66 | O29: 4035.66 | P29: 3239.48 | Q29: 3437.9 | R29: 3682.84 | S29: 4599.84 | T29: 4585.14 | U29: 3954.16 | V29: 2494.6 | W29: 2898.78 | X29: 1692.54 | Y29: 1894.2 | Z29: 1776.32 | AA29: 2344.56 | AB29: 2034.22 | AC29: 2820.1 | AD29: 2042 | AE29: 2263.12 | AF29: 3106.88
A30: - Tax | B30: 1328.82 | C30: 1939.15 | D30: 1627.42 | E30: 1940.02 | F30: 1939.6 | G30: 1638.52 | H30: 1533.51 | I30: 1826.25 | J30: 1687.66 | K30: 1593.8 | L30: 2131.74 | M30: 2157.87 | N30: 1623.16 | O30: 1551.46 | P30: 1265.16 | Q30: 1313.16 | R30: 1415.97 | S30: 1612.58 | T30: 1638.57 | U30: 1360.17 | V30: 1174.01 | W30: 1532.1 | X30: 1561.91 | Y30: 1392.98 | Z30: 1959.39 | AA30: 1797.54 | AB30: 1216.92 | AC30: 1404.38 | AD30: 1280.3 | AE30: 1171.66 | AF30: 1559.59
A31: - Shipping | B31: 0.25 | C31: 12.47 | D31: 17.85 | E31: 31.02 | F31: 5.06 | G31: 28.02 | H31: 0.4 | I31: 7.47 | J31: 0.66 | K31: 4.92 | L31: 0.88 | M31: 17.6 | N31: 0.16 | O31: 7.4 | P31: 25.38 | Q31: 23.13 | R31: 9.82 | S31: 46.82 | T31: 18.62 | U31: 2.7 | V31: 3.79 | W31: 1.49 | X31: 31.69 | Y31: 12.82 | Z31: 22.47 | AA31: 7.99 | AB31: 8.24 | AC31: 7.49 | AD31: 1.25 | AE31: 0.75 | AF31: 1.25
A32: - Gift Wrap | B32: 0.15 | C32: 1 | D32: 4.83 | E32: 9.66 | F32: 9.66 | G32: 9.49 | H32: 9.83 | I32: 14.49 | J32: 14.11 | K32: 21.95 | L32: 6.36 | M32: 5.98 | N32: 4.83 | O32: 22.44 | P32: 4.98 | Q32: 0.85 | R32: 0.83 | S32: 27.79 | T32: 9.32 | U32: 5.66 | V32: 10.68 | W32: 18.72 | X32: 13.77 | Y32: 5.09 | Z32: 27.84 | AA32: 5.09 | AB32: 9.73 | AC32: 22.75 | AD32: 5.24 | AE32: 0.45 | AF32: 4.74
A33: Total Revenue | B33: =SUM(B9+B27) -> 158417.07 | C33: =SUM(C9+C27) -> 180024.62 | D33: =SUM(D9+D27) -> 175409.22 | E33: =SUM(E9+E27) -> 128509.76 | F33: =SUM(F9+F27) -> 132869.55 | G33: =SUM(G9+G27) -> 115744.07 | H33: =SUM(H9+H27) -> 113744.23 | I33: =SUM(I9+I27) -> 117772.46 | ... AF33: =SUM(AF9+AF27) -> 64418.85
A35: B2B Revenue
A36: RETAIL Revenue
A37: Best Buy | B37: =iferror(sum(B38:B40),"") -> 910.67059 | C37: =iferror(sum(C38:C40),"") -> 1799.0624 | D37: =iferror(sum(D38:D40),"") -> 2687.4542 | E37: =iferror(sum(E38:E40),"") -> 0 | F37: =iferror(sum(F38:F40),"") -> 0 | G37: =iferror(sum(G38:G40),"") -> 2665.1754 | H37: =iferror(sum(H38:H40),"") -> 2961.306 | I37: =iferror(sum(I38:I40),"") -> 1776.7836 | ... AF37: =iferror(sum(AF38:AF40),"") -> 0
A38: - Hardware | B38: 857.99 | C38: 1694.99 | D38: 2531.99 | E38: 0 | F38: 0 | G38: 2511 | H38: 2790 | I38: 1674 | J38: 1395 | K38: 1415.99 | L38: 837 | M38: 0 | N38: 279 | O38: 837 | P38: 2531.99 | Q38: 1694.99 | R38: 279 | S38: 279 | T38: 0 | U38: 558 | V38: 0 | W38: 837 | X38: 1395 | Y38: 558 | Z38: 558 | AA38: 0 | AB38: 837 | AC38: 558 | AD38: 837 | AE38: 279 | AF38: 0
A39: - Tax | B39: =B38*'Data - P&L'!$U$3 -> 52.680586 | C39: =C38*'Data - P&L'!$U$3 -> 104.07239 | D39: =D38*'Data - P&L'!$U$3 -> 155.46419 | E39: =E38*'Data - P&L'!$U$3 -> 0 | F39: =F38*'Data - P&L'!$U$3 -> 0 | G39: =G38*'Data - P&L'!$U$3 -> 154.1754 | H39: =H38*'Data - P&L'!$U$3 -> 171.306 | I39: =I38*'Data - P&L'!$U$3 -> 102.7836 | ... AF39: =AF38*'Data - P&L'!$U$3 -> 0
A40: - Shipping
A41: Target | B41: =sum(B42:B44) -> 4887.747 | C41: =sum(C42:C44) -> 4781.607 | D41: =sum(D42:D44) -> 3887.9082 | E41: =sum(E42:E44) -> 7842.6846 | F41: =sum(F42:F44) -> 4855.905 | G41: =sum(G42:G44) -> 3156.6036 | H41: =sum(H42:H44) -> 4675.467 | I41: =sum(I42:I44) -> 4370.8452 | ... AF41: =sum(AF42:AF44) -> 2908.236
A42: - Hardware | B42: 4605 | C42: 4505 | D42: 3663 | E42: 7389 | F42: 4575 | G42: 2974 | H42: 4405 | I42: 4118 | J42: 4635 | K42: 3906 | L42: 6774 | M42: 2995 | N42: 3529 | O42: 2169 | P42: 4077 | Q42: 1763 | R42: 2815 | S42: 4743 | T42: 2597 | U42: 1929 | V42: 1622 | W42: 280 | X42: 1376 | Y42: 1330 | Z42: 2936 | AA42: 2384 | AB42: 1072 | AC42: 714 | AD42: 1202 | AE42: 520 | AF42: 2740
A43: - Tax | B43: =B42*'Data - P&L'!$U$3 -> 282.747 | C43: =C42*'Data - P&L'!$U$3 -> 276.607 | D43: =D42*'Data - P&L'!$U$3 -> 224.9082 | E43: =E42*'Data - P&L'!$U$3 -> 453.6846 | F43: =F42*'Data - P&L'!$U$3 -> 280.905 | G43: =G42*'Data - P&L'!$U$3 -> 182.6036 | H43: =H42*'Data - P&L'!$U$3 -> 270.467 | I43: =I42*'Data - P&L'!$U$3 -> 252.8452 | ... AF43: =AF42*'Data - P&L'!$U$3 -> 168.236
A44: - Shipping
A45: Costco | B45: =SUM(B46:B48) -> 0 | C45: =SUM(C46:C48) -> 0 | D45: =SUM(D46:D48) -> 0 | E45: =SUM(E46:E48) -> 0 | F45: =SUM(F46:F48) -> 0 | G45: =SUM(G46:G48) -> 0 | H45: =SUM(H46:H48) -> 0 | I45: =SUM(I46:I48) -> 0 | ... AF45: =SUM(AF46:AF48) -> 1188.7255
A46: - Hardware | AF46: 1119.96
A47: - Tax | B47: =0.0614*B46 -> 0 | C47: =0.0614*C46 -> 0 | D47: =0.0614*D46 -> 0 | E47: =0.0614*E46 -> 0 | F47: =0.0614*F46 -> 0 | G47: =0.0614*G46 -> 0 | H47: =0.0614*H46 -> 0 | I47: =0.0614*I46 -> 0 | ... AF47: =0.0614*AF46 -> 68.765544
A48: - Shipping
A49: Chewy | B49: =SUM(B50:B52) -> 0 | C49: =SUM(C50:C52) -> 2538.8688 | D49: =SUM(D50:D52) -> 1586.793 | E49: =SUM(E50:E52) -> 1904.1516 | F49: =SUM(F50:F52) -> 634.7172 | G49: =SUM(G50:G52) -> 1904.1516 | H49: =SUM(H50:H52) -> 634.7172 | I49: =SUM(I50:I52) -> 952.0758 | ... AF49: =SUM(AF50:AF52) -> 317.3586
A50: - Hardware | B50: 0 | C50: 2392 | D50: 1495 | E50: 1794 | F50: 598 | G50: 1794 | H50: 598 | I50: 897 | J50: 1196 | K50: 1196 | L50: 897 | M50: 598 | N50: 3588 | O50: 1196 | P50: 299 | Q50: 1196 | R50: 2093 | S50: 0 | T50: 598 | U50: 299 | V50: 0 | W50: 598 | X50: 817 | Y50: 1116 | Z50: 777 | AA50: 1295 | AB50: 259 | AC50: 259 | AD50: 558 | AE50: 259 | AF50: 299
A51: - Tax | B51: =0.0614*B50 -> 0 | C51: =0.0614*C50 -> 146.8688 | D51: =0.0614*D50 -> 91.793 | E51: =0.0614*E50 -> 110.1516 | F51: =0.0614*F50 -> 36.7172 | G51: =0.0614*G50 -> 110.1516 | H51: =0.0614*H50 -> 36.7172 | I51: =0.0614*I50 -> 55.0758 | ... AF51: =0.0614*AF50 -> 18.3586
A52: - Shipping
A53: Walmart | B53: =sum(B54:B56) -> 62.63 | C53: =sum(C54:C56) -> 635.17 | D53: =sum(D54:D56) -> 271.93 | E53: =sum(E54:E56) -> 0 | F53: =sum(F54:F56) -> 0 | G53: =sum(G54:G56) -> 382.97 | H53: =sum(H54:H56) -> 336.83 | I53: =sum(I54:I56) -> 31.39 | ... AF53: =sum(AF54:AF56) -> 31.32
A54: - Hardware | B54: 58 | C54: 583 | D54: 248 | E54: 0 | F54: 0 | G54: 376 | H54: 308 | I54: 29 | J54: 0 | K54: 308 | L54: 0 | M54: 366 | N54: 29 | O54: 558 | P54: 0 | Q54: 279 | R54: 279 | S54: 0 | T54: 39 | U54: 0 | V54: 558 | W54: 0 | X54: 0 | Y54: 308 | Z54: 0 | AA54: 219 | AB54: 279 | AC54: 0 | AD54: 239 | AE54: 239 | AF54: 29
A55: - Tax | B55: 4.63 | C55: 45.18 | D55: 16.94 | E55: 0 | F55: 0 | G55: 6.97 | H55: 28.83 | I55: 2.39 | J55: 0 | K55: 28.82 | L55: 0 | M55: 7.31 | N55: 3.05 | O55: 45.34 | P55: 0 | Q55: 0 | R55: 19.53 | S55: 0 | T55: 2.58 | U55: 0 | V55: 35.57 | W55: 0 | X55: 0 | Y55: 28.54 | Z55: 0 | AA55: 11.61 | AB55: 25.11 | AC55: 0 | AD55: 20.91 | AE55: 14.34 | AF55: 2.32
A56: - Shipping | B56: 0 | C56: 6.99 | D56: 6.99 | E56: 0 | F56: 0 | G56: 0 | H56: 0 | I56: 0 | J56: 0 | K56: 6.99 | L56: 0 | M56: 6.99 | N56: 0 | O56: 0 | P56: 0 | Q56: 0 | R56: 0 | S56: 0 | T56: 0 | U56: 0 | V56: 0 | W56: 0 | X56: 0 | Y56: 0 | Z56: 0 | AA56: 0 | AB56: 0 | AC56: 0 | AD56: 0 | AE56: 0 | AF56: 0
A57: DIGITAL MARKETPLACES Revenue
A58: Rachio | B58: =SUM(B59:B60) -> 0 | C58: =SUM(C59:C60) -> 0 | D58: =SUM(D59:D60) -> 0 | E58: =SUM(E59:E60) -> 0 | F58: =SUM(F59:F60) -> 0 | G58: =SUM(G59:G60) -> 0 | H58: =SUM(H59:H60) -> 0 | I58: =SUM(I59:I60) -> 0 | ... AF58: =SUM(AF59:AF60) -> 254.72539
A59: - Hardware | B59: 0 | C59: 0 | D59: 0 | E59: 0 | F59: 0 | G59: 0 | H59: 0 | I59: 0 | J59: 0 | K59: 0 | L59: 299.99 | M59: 0 | N59: 0 | O59: 0 | P59: 0 | Q59: 0 | R59: 0 | S59: 239.99 | T59: 0 | U59: 0 | V59: 0 | W59: 0 | X59: 0 | Y59: 0 | Z59: 0 | AA59: 0 | AB59: 299.99 | AC59: 0 | AD59: 0 | AE59: 0 | AF59: 239.99
A60: - Tax | B60: =0.0614*B59 -> 0 | C60: =0.0614*C59 -> 0 | D60: =0.0614*D59 -> 0 | E60: =0.0614*E59 -> 0 | F60: =0.0614*F59 -> 0 | G60: =0.0614*G59 -> 0 | H60: =0.0614*H59 -> 0 | I60: =0.0614*I59 -> 0 | ... AF60: =0.0614*AF59 -> 14.735386
A61: - Shipping
A62: Weatherflow | B62: =SUM(B63:B65) -> 0 | C62: =SUM(C63:C65) -> 0 | D62: =SUM(D63:D65) -> 0 | E62: =SUM(E63:E65) -> 0 | F62: =SUM(F63:F65) -> 0 | G62: =SUM(G63:G65) -> 0 | H62: =SUM(H63:H65) -> 0 | I62: =SUM(I63:I65) -> 0 | ... AF62: =SUM(AF63:AF65) -> 0
A63: - Hardware | B63: 0 | C63: 0 | D63: 0 | E63: 0 | F63: 0 | G63: 0 | H63: 0 | I63: 0 | J63: 0 | K63: 0 | L63: 0 | M63: 0 | N63: 0 | O63: 0 | P63: 0 | Q63: 0 | R63: 0 | S63: 0 | T63: 0 | U63: 0 | V63: 0 | W63: 0 | X63: 0 | Y63: 0 | Z63: 0 | AA63: 0 | AB63: 0 | AC63: 0 | AD63: 0 | AE63: 0 | AF63: 0
A64: - Tax | B64: =0.0614*B63 -> 0 | C64: =0.0614*C63 -> 0 | D64: =0.0614*D63 -> 0 | E64: =0.0614*E63 -> 0 | F64: =0.0614*F63 -> 0 | G64: =0.0614*G63 -> 0 | H64: =0.0614*H63 -> 0 | I64: =0.0614*I63 -> 0 | ... AF64: =0.0614*AF63 -> 0
A65: - Shipping
A66: Huckberry | B66: =SUM(B67:B69) -> 0 | C66: =SUM(C67:C69) -> 0 | D66: =SUM(D67:D69) -> 0 | E66: =SUM(E67:E69) -> 0 | F66: =SUM(F67:F69) -> 0 | G66: =SUM(G67:G69) -> 0 | H66: =SUM(H67:H69) -> 0 | I66: =SUM(I67:I69) -> 0 | ... AF66: =SUM(AF67:AF69) -> 0
A67: - Hardware
A68: - Tax | B68: =0.0614*B67 -> 0 | C68: =0.0614*C67 -> 0 | D68: =0.0614*D67 -> 0 | E68: =0.0614*E67 -> 0 | F68: =0.0614*F67 -> 0 | G68: =0.0614*G67 -> 0 | H68: =0.0614*H67 -> 0 | I68: =0.0614*I67 -> 0 | ... AF68: =0.0614*AF67 -> 0
A69: - Shipping
A70: Total Retail Revenue | B70: =sum(B37,B41,B45,B49,B53) -> 5861.0476 | C70: =sum(C37,C41,C45,C49,C53) -> 9754.7082 | D70: =sum(D37,D41,D45,D49,D53) -> 8434.0854 | E70: =sum(E37,E41,E45,E49,E53) -> 9746.8362 | F70: =sum(F37,F41,F45,F49,F53) -> 5490.6222 | G70: =sum(G37,G41,G45,G49,G53) -> 8108.9006 | H70: =sum(H37,H41,H45,H49,H53) -> 8608.3202 | I70: =sum(I37,I41,I45,I49,I53) -> 7131.0946 | ... AF70: =sum(AF37,AF41,AF45,AF49,AF53) -> 4445.6401
A71: Total DM Revenue | B71: =sum(B58,B62,B66) -> 0 | C71: =sum(C58,C62,C66) -> 0 | D71: =sum(D58,D62,D66) -> 0 | E71: =sum(E58,E62,E66) -> 0 | F71: =sum(F58,F62,F66) -> 0 | G71: =sum(G58,G62,G66) -> 0 | H71: =sum(H58,H62,H66) -> 0 | I71: =sum(I58,I62,I66) -> 0 | ... AF71: =sum(AF58,AF62,AF66) -> 254.72539
A72: Total B2B Revenue | B72: =B70+B71 -> 5861.0476 | C72: =C70+C71 -> 9754.7082 | D72: =D70+D71 -> 8434.0854 | E72: =E70+E71 -> 9746.8362 | F72: =F70+F71 -> 5490.6222 | G72: =G70+G71 -> 8108.9006 | H72: =H70+H71 -> 8608.3202 | I72: =I70+I71 -> 7131.0946 | ... AF72: =AF70+AF71 -> 4700.3655
A74: App Revenue
A75: - Google Store | B75: ='App - P&L'!B90 -> 23757.747 | C75: ='App - P&L'!C90 -> 18419.747 | D75: ='App - P&L'!D90 -> 12923.952 | E75: ='App - P&L'!E90 -> 12869.706 | F75: ='App - P&L'!F90 -> 10415.807 | G75: ='App - P&L'!G90 -> 7568.6975 | H75: ='App - P&L'!H90 -> 8117.1005 | I75: ='App - P&L'!I90 -> 8745.667 | ... AF75: ='App - P&L'!AF90 -> 1415.029
A76: - Apple Store | B76: ='App - P&L'!B91 -> 112841.32 | C76: ='App - P&L'!C91 -> 81926.019 | D76: ='App - P&L'!D91 -> 58562.435 | E76: ='App - P&L'!E91 -> 54724.9 | F76: ='App - P&L'!F91 -> 51029.548 | G76: ='App - P&L'!G91 -> 33578.299 | H76: ='App - P&L'!H91 -> 32442.362 | I76: ='App - P&L'!I91 -> 33826.962 | ... AF76: ='App - P&L'!AF91 -> 6774.9365
A77: - Comission | B77: ='App - P&L'!B67 -> 52553.11 | C77: ='App - P&L'!C67 -> 38361.694 | D77: ='App - P&L'!D67 -> 27378.884 | E77: ='App - P&L'!E67 -> 25724.653 | F77: ='App - P&L'!F67 -> 23707.89 | G77: ='App - P&L'!G67 -> 15726.352 | H77: ='App - P&L'!H67 -> 15336.299 | I77: ='App - P&L'!I67 -> 16040.622 | ... AF77: ='App - P&L'!AF67 -> 3153.2552
A78: - Tax | B78: ='App - P&L'!B68 -> 0 | C78: ='App - P&L'!C68 -> 0 | D78: ='App - P&L'!D68 -> 0 | E78: ='App - P&L'!E68 -> 0 | F78: ='App - P&L'!F68 -> 0 | G78: ='App - P&L'!G68 -> 0 | H78: ='App - P&L'!H68 -> 0 | I78: ='App - P&L'!I68 -> 0 | ... AF78: ='App - P&L'!AF68 -> 0
A79: Total App Revenue | B79: =sum(B75:B78) -> 189152.18 | C79: =sum(C75:C78) -> 138707.46 | D79: =sum(D75:D78) -> 98865.272 | E79: =sum(E75:E78) -> 93319.259 | F79: =sum(F75:F78) -> 85153.244 | G79: =sum(G75:G78) -> 56873.349 | H79: =sum(H75:H78) -> 55895.762 | I79: =sum(I75:I78) -> 58613.251 | ... AF79: =sum(AF75:AF78) -> 11343.221
A81: Units Sold (DTC + AMZN) | B81: =B84+B90+B96 -> 124 | C81: =C84+C90+C96 -> 144 | D81: =D84+D90+D96 -> 128 | E81: =E84+E90+E96 -> 152 | F81: =F84+F90+F96 -> 156 | G81: =G84+G90+G96 -> 140 | H81: =H84+H90+H96 -> 141 | I81: =I84+I90+I96 -> 166 | ... AF81: =AF84+AF90+AF96 -> 206
A82: DTC Orders | B82: =sum(B83,B89) -> 1432 | C82: =sum(C83,C89) -> 1599 | D82: =sum(D83,D89) -> 1585 | E82: =sum(E83,E89) -> 972 | F82: =sum(F83,F89) -> 1040 | G82: =sum(G83,G89) -> 868 | H82: =sum(H83,H89) -> 855 | I82: =sum(I83,I89) -> 808 | ... AF82: =sum(AF83,AF89) -> 213
A83: - DTC Orders US&CA | B83: 1379 | C83: 1547 | D83: 1538 | E83: 953 | F83: 1005 | G83: 825 | H83: 820 | I83: 766 | J83: 792 | K83: 675 | L83: 588 | M83: 701 | N83: 695 | O83: 818 | P83: 652 | Q83: 620 | R83: 565 | S83: 537 | T83: 595 | U83: 437 | V83: 304 | W83: 250 | X83: 257 | Y83: 266 | Z83: 344 | AA83: 300 | AB83: 231 | AC83: 240 | AD83: 213 | AE83: 217 | AF83: 203
A84: - Hardware (units sold) | B84: =sum('DTC US&CA - P&L'!B33,'DTC US&CA - P&L'!B37) -> 56 | C84: =sum('DTC US&CA - P&L'!C33,'DTC US&CA - P&L'!C37) -> 52 | D84: =sum('DTC US&CA - P&L'!D33,'DTC US&CA - P&L'!D37) -> 52 | E84: =sum('DTC US&CA - P&L'!E33,'DTC US&CA - P&L'!E37) -> 65 | F84: =sum('DTC US&CA - P&L'!F33,'DTC US&CA - P&L'!F37) -> 67 | G84: =sum('DTC US&CA - P&L'!G33,'DTC US&CA - P&L'!G37) -> 56 | H84: =sum('DTC US&CA - P&L'!H33,'DTC US&CA - P&L'!H37) -> 60 | I84: =sum('DTC US&CA - P&L'!I33,'DTC US&CA - P&L'!I37) -> 67 | ... AF84: =sum('DTC US&CA - P&L'!AF33,'DTC US&CA - P&L'!AF37) -> 122
A85: - Add-ons (units sold) | B85: ='DTC US&CA - P&L'!B50 -> 275 | C85: ='DTC US&CA - P&L'!C50 -> 210 | D85: ='DTC US&CA - P&L'!D50 -> 200 | E85: ='DTC US&CA - P&L'!E50 -> 217 | F85: ='DTC US&CA - P&L'!F50 -> 246 | G85: ='DTC US&CA - P&L'!G50 -> 144 | H85: ='DTC US&CA - P&L'!H50 -> 148 | I85: ='DTC US&CA - P&L'!I50 -> 148 | ... AF85: ='DTC US&CA - P&L'!AF50 -> 165
A86: - Merch (units sold) | B86: 0 | C86: 0 | D86: 0 | E86: 0 | F86: 0 | G86: 0 | H86: 0 | I86: 0 | J86: 0 | K86: 1 | L86: 0 | M86: 0 | N86: 1 | O86: 0 | P86: 0 | Q86: 0 | R86: 0 | S86: 1 | T86: 4 | U86: 0 | V86: 0 | W86: 0 | X86: 1 | Y86: 1 | Z86: 0 | AA86: 0 | AB86: 0 | AC86: 0 | AD86: 0 | AE86: 0 | AF86: 0
A87: - Seeds (units sold) | B87: 20 | C87: 16 | D87: 25 | E87: 20 | F87: 19 | G87: 12 | H87: 13 | I87: 12 | J87: 24 | K87: 18 | L87: 18 | M87: 15 | N87: 8 | O87: 17 | P87: 19 | Q87: 20 | R87: 20 | S87: 17 | T87: 11 | U87: 11 | V87: 19 | W87: 10 | X87: 11 | Y87: 15 | Z87: 15 | AA87: 14 | AB87: 17 | AC87: 11 | AD87: 14 | AE87: 11 | AF87: 14
A88: - BB 1 year Pro Subscription | B88: 1157 | C88: 1354 | D88: 1352 | E88: 773 | F88: 786 | G88: 680 | H88: 686 | I88: 640 | J88: 642 | K88: 515 | L88: 462 | M88: 535 | N88: 599 | O88: 687 | P88: 572 | Q88: 525 | R88: 459 | S88: 414 | T88: 479 | U88: 335 | V88: 211 | W88: 147 | X88: 140 | Y88: 157 | Z88: 219 | AA88: 146 | AB88: 114 | AC88: 117 | AD88: 97 | AE88: 110 | AF88: 106
A89: - DTC Orders EUROPE | B89: 53 | C89: 52 | D89: 47 | E89: 19 | F89: 35 | G89: 43 | H89: 35 | I89: 42 | J89: 48 | K89: 32 | L89: 35 | M89: 36 | N89: 30 | O89: 35 | P89: 21 | Q89: 17 | R89: 26 | S89: 25 | T89: 35 | U89: 7 | V89: 10 | W89: 14 | X89: 12 | Y89: 9 | Z89: 9 | AA89: 27 | AB89: 18 | AC89: 7 | AD89: 11 | AE89: 14 | AF89: 10
A90: - Hardware (units sold) | B90: ='DTC EU - P&L'!B33 -> 4 | C90: ='DTC EU - P&L'!C33 -> 1 | D90: ='DTC EU - P&L'!D33 -> 3 | E90: ='DTC EU - P&L'!E33 -> 2 | F90: ='DTC EU - P&L'!F33 -> 2 | G90: ='DTC EU - P&L'!G33 -> 7 | H90: ='DTC EU - P&L'!H33 -> 9 | I90: ='DTC EU - P&L'!I33 -> 7 | ... AF90: ='DTC EU - P&L'!AF33 -> 5
A91: - Add-ons (units sold) | B91: ='DTC EU - P&L'!B50 -> 2 | C91: ='DTC EU - P&L'!C50 -> 7 | D91: ='DTC EU - P&L'!D50 -> 10 | E91: ='DTC EU - P&L'!E50 -> 7 | F91: ='DTC EU - P&L'!F50 -> 0 | G91: ='DTC EU - P&L'!G50 -> 6 | H91: ='DTC EU - P&L'!H50 -> 4 | I91: ='DTC EU - P&L'!I50 -> 2 | ... AF91: ='DTC EU - P&L'!AF50 -> 10
A92: - Merch (units sold) | B92: 0 | C92: 0 | D92: 0 | E92: 0 | F92: 0 | G92: 0 | H92: 0 | I92: 0 | J92: 0 | K92: 0 | L92: 0 | M92: 0 | N92: 0 | O92: 0 | P92: 0 | Q92: 0 | R92: 0 | S92: 0 | T92: 0 | U92: 0 | V92: 0 | W92: 0 | X92: 0 | Y92: 0 | Z92: 0 | AA92: 0 | AB92: 0 | AC92: 0 | AD92: 0 | AE92: 0 | AF92: 0
A93: - Seeds (units sold) | B93: 0 | C93: 0 | D93: 0 | E93: 0 | F93: 0 | G93: 0 | H93: 0 | I93: 0 | J93: 0 | K93: 0 | L93: 0 | M93: 0 | N93: 0 | O93: 0 | P93: 0 | Q93: 0 | R93: 0 | S93: 0 | T93: 0 | U93: 0 | V93: 0 | W93: 0 | X93: 0 | Y93: 0 | Z93: 0 | AA93: 0 | AB93: 0 | AC93: 0 | AD93: 0 | AE93: 0 | AF93: 0
A94: - BB 1 year Pro Subscription | B94: 50 | C94: 49 | D94: 41 | E94: 15 | F94: 33 | G94: 40 | H94: 29 | I94: 40 | J94: 41 | K94: 30 | L94: 34 | M94: 31 | N94: 26 | O94: 33 | P94: 17 | Q94: 15 | R94: 22 | S94: 16 | T94: 19 | U94: 5 | V94: 6 | W94: 10 | X94: 7 | Y94: 5 | Z94: 5 | AA94: 11 | AB94: 6 | AC94: 2 | AD94: 5 | AE94: 6 | AF94: 3
A95: Amazon Orders | B95: 164 | C95: 135 | D95: 147 | E95: 224 | F95: 210 | G95: 149 | H95: 154 | I95: 148 | J95: 149 | K95: 169 | L95: 264 | M95: 286 | N95: 191 | O95: 203 | P95: 150 | Q95: 165 | R95: 189 | S95: 224 | T95: 239 | U95: 161 | V95: 152 | W95: 193 | X95: 124 | Y95: 118 | Z95: 179 | AA95: 163 | AB95: 129 | AC95: 158 | AD95: 143 | AE95: 135 | AF95: 142
A96: - Hardware (units sold) | B96: =SUM('AMAZON - P&L'!B28:B35, 'AMAZON - P&L'!B38:B39) -> 64 | C96: =SUM('AMAZON - P&L'!C28:C35, 'AMAZON - P&L'!C38:C39) -> 91 | D96: =SUM('AMAZON - P&L'!D28:D35, 'AMAZON - P&L'!D38:D39) -> 73 | E96: =SUM('AMAZON - P&L'!E28:E35, 'AMAZON - P&L'!E38:E39) -> 85 | F96: =SUM('AMAZON - P&L'!F28:F35, 'AMAZON - P&L'!F38:F39) -> 87 | G96: =SUM('AMAZON - P&L'!G28:G35, 'AMAZON - P&L'!G38:G39) -> 77 | H96: =SUM('AMAZON - P&L'!H28:H35, 'AMAZON - P&L'!H38:H39) -> 72 | I96: =SUM('AMAZON - P&L'!I28:I35, 'AMAZON - P&L'!I38:I39) -> 92 | ... N96: =SUM('AMAZON - P&L'!N28:N35, 'AMAZON - P&L'!N38:N39) -> 71 | O96: 73 | P96: =SUM('AMAZON - P&L'!P28:P35, 'AMAZON - P&L'!P38:P39) -> 54 | Q96: =SUM('AMAZON - P&L'!Q28:Q35, 'AMAZON - P&L'!Q38:Q39) -> 61 | R96: =SUM('AMAZON - P&L'!R28:R35, 'AMAZON - P&L'!R38:R39) -> 63 | S96: =SUM('AMAZON - P&L'!S28:S35, 'AMAZON - P&L'!S38:S39) -> 66 | T96: =SUM('AMAZON - P&L'!T28:T35, 'AMAZON - P&L'!T38:T39) -> 69 | U96: =SUM('AMAZON - P&L'!U28:U35, 'AMAZON - P&L'!U38:U39) -> 60 | V96: =SUM('AMAZON - P&L'!V28:V35, 'AMAZON - P&L'!V38:V39) -> 58 | W96: =SUM('AMAZON - P&L'!W28:W35, 'AMAZON - P&L'!W38:W39) -> 83 | ... AF96: =SUM('AMAZON - P&L'!AF28:AF35, 'AMAZON - P&L'!AF38:AF39) -> 79
A97: - Add-ons (units sold) | B97: ='AMAZON - P&L'!B51 -> 61 | C97: ='AMAZON - P&L'!C51 -> 58 | D97: ='AMAZON - P&L'!D51 -> 70 | E97: ='AMAZON - P&L'!E51 -> 121 | F97: ='AMAZON - P&L'!F51 -> 111 | G97: ='AMAZON - P&L'!G51 -> 81 | H97: ='AMAZON - P&L'!H51 -> 80 | I97: ='AMAZON - P&L'!I51 -> 65 | ... AF97: ='AMAZON - P&L'!AF51 -> 103
A98: Total Orders | B98: =SUM(B82+B95) -> 1596 | C98: =SUM(C82+C95) -> 1734 | D98: =SUM(D82+D95) -> 1732 | E98: =SUM(E82+E95) -> 1196 | F98: =SUM(F82+F95) -> 1250 | G98: =SUM(G82+G95) -> 1017 | H98: =SUM(H82+H95) -> 1009 | I98: =SUM(I82+I95) -> 956 | ... AF98: =SUM(AF82+AF95) -> 355
B99: =B96+B90+B84 -> 124 | C99: =C96+C90+C84 -> 144 | D99: =D96+D90+D84 -> 128 | E99: =E96+E90+E84 -> 152 | F99: =F96+F90+F84 -> 156 | G99: =G96+G90+G84 -> 140 | H99: =H96+H90+H84 -> 141 | I99: =I96+I90+I84 -> 166 | ... AF99: =AF96+AF90+AF84 -> 206
A100: B2B Orders
A101: RETAIL Orders
A102: Best Buy | B102: 3 | C102: 6 | D102: 9 | E102: 0 | F102: 0 | G102: 9 | H102: 10 | I102: 6 | J102: 5 | K102: 5 | L102: 3 | M102: 0 | N102: 1 | O102: 3 | P102: 9 | Q102: 6 | R102: 1 | S102: 1 | T102: 0 | U102: 2 | V102: 0 | W102: 3 | X102: 5 | Y102: 2 | Z102: 2 | AA102: 0 | AB102: 3 | AC102: 2 | AD102: 3 | AE102: 1 | AF102: 0
A103: Target | B103: 17 | C103: 17 | D103: 14 | E103: 27 | F103: 18 | G103: 12 | H103: 16 | I103: 15 | J103: 18 | K103: 14 | L103: 25 | M103: 11 | N103: 13 | O103: 8 | P103: 15 | Q103: 7 | R103: 11 | S103: 18 | T103: 10 | U103: 7 | V103: 6 | W103: 1 | X103: 5 | Y103: 5 | Z103: 11 | AA103: 9 | AB103: 4 | AC103: 3 | AD103: 5 | AE103: 2 | AF103: 10
A104: Costco | AF104: 4
A105: Chewy | B105: 0 | C105: 8 | D105: 5 | E105: 6 | F105: 2 | G105: 6 | H105: 2 | I105: 3 | J105: 4 | K105: 4 | L105: 3 | M105: 2 | N105: 12 | O105: 4 | P105: 1 | Q105: 4 | R105: 7 | S105: 0 | T105: 2 | U105: 1 | V105: 0 | W105: 2 | X105: 3 | Y105: 4 | Z105: 3 | AA105: 5 | AB105: 1 | AC105: 1 | AD105: 2 | AE105: 1 | AF105: 1
A106: Walmart | B106: 2 | C106: 8 | D106: 2 | E106: 0 | F106: 0 | G106: 5 | H106: 2 | I106: 1 | J106: 0 | K106: 2 | L106: 0 | M106: 4 | N106: 1 | O106: 2 | P106: 0 | Q106: 1 | R106: 1 | S106: 0 | T106: 1 | U106: 0 | V106: 2 | W106: 0 | X106: 0 | Y106: 2 | Z106: 0 | AA106: 1 | AB106: 1 | AC106: 0 | AD106: 1 | AE106: 1 | AF106: 1
A107: DIGITAL MARKETPLACES Orders
...

Sheet DTC - P&L
A1: JANUARY | B1: 45658 | C1: 45659 | D1: 45660 | E1: 45661 | F1: 45662 | G1: 45663 | H1: 45664 | I1: 45665 | J1: 45666 | K1: 45667 | L1: 45668 | M1: 45669 | N1: 45670 | O1: 45671 | P1: 45672 | Q1: 45673 | R1: 45674 | S1: 45675 | T1: 45676 | U1: 45677 | V1: 45678 | W1: 45679 | X1: 45680 | Y1: 45681 | Z1: 45682 | AA1: 45683 | AB1: 45684 | AC1: 45685 | AD1: 45686 | AE1: 45687 | AF1: 45688
A2: DAY | B2: WED | C2: THU | D2: FRI | E2: SAT | F2: SUN | G2: MON | H2: TUE | I2: WED | J2: THU | K2: FRI | L2: SAT | M2: SUN | N2: MON | O2: TUE | P2: WED | Q2: THU | R2: FRI | S2: SAT | T2: SUN | U2: MON | V2: TUE | W2: WED | X2: THU | Y2: FRI | Z2: SAT | AA2: SUN | AB2: MON | AC2: TUE | AD2: WED | AE2: THU | AF2: FRI
A3: COMMENT
A4: Orders
A5: Meta | B5: 265 | C5: 288 | D5: 261 | E5: 149 | F5: 199 | G5: 149 | H5: 116 | I5: 122 | J5: 114 | K5: 108 | L5: 75 | M5: 114 | N5: 130 | O5: 145 | P5: 126 | Q5: 63 | R5: 76 | S5: 83 | T5: 140 | U5: 136 | V5: 92 | W5: 79 | X5: 100 | Y5: 106 | Z5: 126 | AA5: 134 | AB5: 61 | AC5: 97 | AD5: 26 | AE5: 110 | AF5: 78 | AG5: =SUM(B5:AF5) -> 3868
A6: Google | B6: 89 | C6: 76 | D6: 68 | E6: 62 | F6: 76 | G6: 58 | H6: 49 | I6: 54 | J6: 58 | K6: 56 | L6: 56 | M6: 70 | N6: 38 | O6: 52 | P6: 29 | Q6: 35 | R6: 39 | S6: 50 | T6: 53 | U6: 32 | V6: 47 | W6: 54 | X6: 59 | Y6: 53 | Z6: 68 | AA6: 77 | AB6: 59 | AC6: 57 | AD6: 48 | AE6: 48 | AF6: 58 | AG6: =SUM(B6:AF6) -> 1728
A7: TikTok | B7: 0 | C7: 0 | D7: 0 | E7: 0 | F7: 0 | G7: 0 | H7: 0 | I7: 0 | J7: 0 | K7: 0 | L7: 0 | M7: 0 | N7: 0 | O7: 0 | P7: 0 | Q7: 0 | R7: 0 | S7: 0 | T7: 0 | U7: 0 | V7: 0 | W7: 0 | X7: 0 | Y7: 0 | Z7: 0 | AA7: 0 | AB7: 0 | AC7: 0 | AD7: 0 | AE7: 0 | AF7: 0 | AG7: =SUM(B7:AF7) -> 0
A8: Bing | B8: 14 | C8: 12 | D8: 18 | E8: 18 | F8: 34 | G8: 10 | H8: 12 | I8: 8 | J8: 28 | K8: 16 | L8: 26 | M8: 16 | N8: 12 | O8: 18 | P8: 10 | Q8: 10 | R8: 8 | S8: 18 | T8: 6 | U8: 10 | V8: 8 | W8: 2 | X8: 12 | Y8: 18 | Z8: 20 | AA8: 22 | AB8: 24 | AC8: 22 | AD8: 8 | AE8: 20 | AF8: 18 | AG8: =SUM(B8:AF8) -> 478
A9: Email | B9: 0 | C9: 1 | D9: 0 | E9: 0 | F9: 0 | G9: 0 | H9: 0 | I9: 0 | J9: 0 | K9: 0 | L9: 0 | M9: 0 | N9: 0 | O9: 0 | P9: 0 | Q9: 0 | R9: 0 | S9: 0 | T9: 0 | U9: 0 | V9: 0 | W9: 0 | X9: 0 | Y9: 0 | Z9: 0 | AA9: 0 | AB9: 0 | AC9: 0 | AD9: 0 | AE9: 0 | AF9: 0 | AG9: =SUM(B9:AF9) -> 1
A10: Nextdoor | B10: - | C10: - | D10: - | E10: - | F10: - | G10: - | H10: - | I10: - | J10: - | K10: - | L10: - | M10: - | N10: - | O10: - | P10: - | Q10: - | R10: - | S10: - | T10: - | U10: - | V10: - | W10: - | X10: - | Y10: - | Z10: - | AA10: - | AB10: - | AC10: - | AD10: - | AE10: - | AF10: - | AG10: =SUM(B10:AF10) -> 0
A11: Affiliates (Refersion) | B11: - | C11: - | D11: - | E11: - | F11: - | G11: - | H11: - | I11: - | J11: - | K11: - | L11: - | M11: - | N11: - | O11: - | P11: - | Q11: - | R11: - | S11: - | T11: - | U11: - | V11: - | W11: - | X11: - | Y11: - | Z11: - | AA11: - | AB11: - | AC11: - | AD11: - | AE11: - | AF11: - | AG11: =SUM(B11:AF11) -> 0
A12: All | B12: =SUM(B5:B11) -> 368 | C12: =SUM(C5:C11) -> 377 | D12: =SUM(D5:D11) -> 347 | E12: =SUM(E5:E11) -> 229 | F12: =SUM(F5:F11) -> 309 | G12: =SUM(G5:G11) -> 217 | H12: =SUM(H5:H11) -> 177 | I12: =SUM(I5:I11) -> 184 | ... AF12: =SUM(AF5:AF11) -> 154 | AG12: =SUM(B12:AF12) -> 6075
A14: Revenue | B14: 24151.74 | C14: 25955.47 | D14: 25319.02 | E14: 14224.63 | F14: 19860.05 | G14: 15692.06 | H14: 11951.66 | I14: 12862.92 | J14: 11618.75 | K14: 11146.34 | L14: 8520.56 | M14: 14015.63 | N14: 13865.49 | O14: 14099.99 | P14: 12808.42 | Q14: 6710.56 | R14: 10173.04 | S14: 10870.09 | T14: 17827.86 | U14: 15012.41 | V14: 13250.44 | W14: 12235.65 | X14: 18145.52 | Y14: 21256.28 | Z14: 21105.78 | AA14: 25560.15 | AB14: 11697.2 | AC14: 20252.82 | AD14: 5772.79 | AE14: 25336.04 | AF14: 16132.94
A15: Meta | B15: =B14*Summary!B121 -> 24999.466 | C15: =C14*Summary!C121 -> 26645.886 | D15: =D14*Summary!D121 -> 26108.973 | E15: =E14*Summary!E121 -> 14667.016 | F15: =F14*Summary!F121 -> 20465.782 | G15: =G14*Summary!G121 -> 16293.066 | H15: =H14*Summary!H121 -> 12362.797 | I15: =I14*Summary!I121 -> 13270.675 | ... AF15: =AF14*Summary!AF121 -> 16729.859 | AG15: =SUM(B15:AF15) -> 504957.64
A16: Google | B16: 10827.24 | C16: 12049.75 | D16: 9180.54 | E16: 8951.08 | F16: 12049.75 | G16: 9872.94 | H16: 7522.21 | I16: 11202.75 | J16: 10186.53 | K16: 9906.13 | L16: 13712.91 | M16: 13635.17 | N16: 6524.74 | O16: 10388.91 | P16: 6395.6 | Q16: 5748.06 | R16: 7677.03 | S16: 10739.94 | T16: 11907.65 | U16: 7155.26 | V16: 10141.65 | W16: 14230.8 | X16: 15392.32 | Y16: 12961.39 | Z16: 15375.1 | AA16: 15147.65 | AB16: 11275.41 | AC16: 12318.62 | AD16: 10566.51 | AE16: 10566.51 | AF16: 12724.01 | AG16: =SUM(B16:AF16) -> 336334.16
A17: TikTok | B17: 0 | C17: 0 | D17: 0 | E17: 0 | F17: 0 | G17: 0 | H17: 0 | I17: 0 | J17: 0 | K17: 0 | L17: 0 | M17: 0 | N17: 0 | O17: 0 | P17: 0 | Q17: 0 | R17: 0 | S17: 0 | T17: 0 | U17: 0 | V17: 0 | W17: 0 | X17: 0 | Y17: 0 | Z17: 0 | AA17: 0 | AB17: 0 | AC17: 0 | AD17: 0 | AE17: 0 | AF17: 0 | AG17: =SUM(B17:AF17) -> 0
A18: Bing | B18: 1757 | C18: 1506 | D18: 2259 | E18: 2259 | F18: 4267 | G18: 1255 | H18: 1506 | I18: 1004 | J18: 3514 | K18: 2008 | L18: 3263 | M18: 2008 | N18: 1506 | O18: 2259 | P18: 1255 | Q18: 1255 | R18: 1004 | S18: 2259 | T18: 753 | U18: 1255 | V18: 1004 | W18: 251 | X18: 1506 | Y18: 2259 | Z18: 2510 | AA18: 2761 | AB18: 3012 | AC18: 2761 | AD18: 1004 | AE18: 2510 | AF18: 2259 | AG18: =SUM(B18:AF18) -> 59989
A19: Email | B19: 0 | C19: 41.08 | D19: 0 | E19: 0 | F19: 0 | G19: 0 | H19: 0 | I19: 0 | J19: 0 | K19: 0 | L19: 0 | M19: 0 | N19: 0 | O19: 0 | P19: 0 | Q19: 0 | R19: 0 | S19: 0 | T19: 0 | U19: 0 | V19: 0 | W19: 0 | X19: 0 | Y19: 0 | Z19: 0 | AA19: 0 | AB19: 0 | AC19: 0 | AD19: 0 | AE19: 0 | AF19: 0 | AG19: =SUM(B19:AF19) -> 41.08
A20: Nextdoor | B20: - | C20: - | D20: - | E20: - | F20: - | G20: - | H20: - | I20: - | J20: - | K20: - | L20: - | M20: - | N20: - | O20: - | P20: - | Q20: - | R20: - | S20: - | T20: - | U20: - | V20: - | W20: - | X20: - | Y20: - | Z20: - | AA20: - | AB20: - | AC20: - | AD20: - | AE20: - | AF20: -
A21: Affiliates (Refersion) | B21: - | C21: - | D21: - | E21: - | F21: - | G21: - | H21: - | I21: - | J21: - | K21: - | L21: - | M21: - | N21: - | O21: - | P21: - | Q21: - | R21: - | S21: - | T21: - | U21: - | V21: - | W21: - | X21: - | Y21: - | Z21: - | AA21: - | AB21: - | AC21: - | AD21: - | AE21: - | AF21: -
A22: All | B22: =SUM(B15:B21) -> 37583.706 | C22: =SUM(C15:C21) -> 40242.715 | D22: =SUM(D15:D21) -> 37548.513 | E22: =SUM(E15:E21) -> 25877.096 | F22: =SUM(F15:F21) -> 36782.532 | G22: =SUM(G15:G21) -> 27421.006 | H22: =SUM(H15:H21) -> 21391.007 | I22: =SUM(I15:I21) -> 25477.425 | ... AF22: =SUM(AF15:AF21) -> 31712.869 | AG22: =SUM(B22:AF22) -> 901321.88
A24: Media Cost
A25: Meta | B25: =Summary!B122 -> 4984.317 | C25: =Summary!C122 -> 5399.0434 | D25: =Summary!D122 -> 3918.065 | E25: =Summary!E122 -> 4578.5789 | F25: =Summary!F122 -> 5201.3869 | G25: =Summary!G122 -> 5126.9904 | H25: =Summary!H122 -> 5048.4409 | I25: =Summary!I122 -> 4964.7674 | ... AF25: =Summary!AF122 -> 18145.063 | AG25: =SUM(B25:AF25) -> 467833.8
A26: Google | B26: =Summary!B125 -> 3103.99 | C26: =Summary!C125 -> 2165.06 | D26: =Summary!D125 -> 2128.43 | E26: =Summary!E125 -> 2232.05 | F26: =Summary!F125 -> 2200.78 | G26: =Summary!G125 -> 1922.34 | H26: =Summary!H125 -> 2967.68 | I26: =Summary!I125 -> 4036.71 | ... AF26: =Summary!AF125 -> 2301.88 | AG26: =SUM(B26:AF26) -> 70865.77
A27: TikTok | B27: =Summary!B129 -> 0 | C27: =Summary!C129 -> 0 | D27: =Summary!D129 -> 0 | E27: =Summary!E129 -> 0 | F27: =Summary!F129 -> 0 | G27: =Summary!G129 -> 0 | H27: =Summary!H129 -> 0 | I27: =Summary!I129 -> 0 | ... AF27: =Summary!AF129 -> 0 | AG27: =SUM(B27:AF27) -> 0
A28: Bing | B28: =Summary!B128 -> 166.94 | C28: =Summary!C128 -> 194.55 | D28: =Summary!D128 -> 172.16 | E28: =Summary!E128 -> 183.21 | F28: =Summary!F128 -> 210.95 | G28: =Summary!G128 -> 220.19 | H28: =Summary!H128 -> 327.79 | I28: =Summary!I128 -> 331.77 | ... AF28: =Summary!AF128 -> 155.29 | AG28: =SUM(B28:AF28) -> 6300.77
A29: Nextdoor | B29: - | C29: - | D29: - | E29: - | F29: - | G29: - | H29: - | I29: - | J29: - | K29: - | L29: - | M29: - | N29: - | O29: - | P29: - | Q29: - | R29: - | S29: - | T29: - | U29: - | V29: - | W29: - | X29: - | Y29: - | Z29: - | AA29: - | AB29: - | AC29: - | AD29: - | AE29: - | AF29: - | AG29: =SUM(B29:AF29) -> 0
A30: Affiliate Fee (20%) | B30: - | C30: - | D30: - | E30: - | F30: - | G30: - | H30: - | I30: - | J30: - | K30: - | L30: - | M30: - | N30: - | O30: - | P30: - | Q30: - | R30: - | S30: - | T30: - | U30: - | V30: - | W30: - | X30: - | Y30: - | Z30: - | AA30: - | AB30: - | AC30: - | AD30: - | AE30: - | AF30: - | AG30: =SUM(B30:AF30) -> 0
A31: All | B31: =SUM(B25:B30) -> 8255.247 | C31: =SUM(C25:C30) -> 7758.6534 | D31: =SUM(D25:D30) -> 6218.655 | E31: =SUM(E25:E30) -> 6993.8389 | F31: =SUM(F25:F30) -> 7613.1169 | G31: =SUM(G25:G30) -> 7269.5204 | H31: =SUM(H25:H30) -> 8343.9109 | I31: =SUM(I25:I30) -> 9333.2474 | ... AF31: =SUM(AF25:AF30) -> 20602.233 | AG31: =SUM(B31:AF31) -> 545000.34
A36: Revenue
A37: Revenue Woocommerce (Platform) | B37: =Summary!B9 -> 138390.47 | C37: =Summary!C9 -> 151225.52 | D37: =Summary!D9 -> 151451.22 | E37: =Summary!E9 -> 99608.559 | F37: =Summary!F9 -> 103556.73 | G37: =Summary!G9 -> 90242.155 | H37: =Summary!H9 -> 90339.034 | I37: =Summary!I9 -> 88015.047 | ... AF37: =Summary!AF9 -> 40433.49 | AG37: =SUM(B37:AF37) -> 2320738.1
A38: Revenue w/o renewals | B38: ='DTC US&CA - P&L'!B6+'DTC EU - P&L'!B6 -> 30858.567 | C38: ='DTC US&CA - P&L'!C6+'DTC EU - P&L'!C6 -> 25074.981 | D38: ='DTC US&CA - P&L'!D6+'DTC EU - P&L'!D6 -> 26768.824 | E38: ='DTC US&CA - P&L'!E6+'DTC EU - P&L'!E6 -> 31316.638 | F38: ='DTC US&CA - P&L'!F6+'DTC EU - P&L'!F6 -> 32512.392 | G38: ='DTC US&CA - P&L'!G6+'DTC EU - P&L'!G6 -> 26553.964 | H38: ='DTC US&CA - P&L'!H6+'DTC EU - P&L'!H6 -> 27574.692 | I38: ='DTC US&CA - P&L'!I6+'DTC EU - P&L'!I6 -> 29490.513 | ... AF38: ='DTC US&CA - P&L'!AF6+'DTC EU - P&L'!AF6 -> 36952.031 | AG38: =SUM(B38:AF38) -> 999031.54
A39: SUM | B39: =SUM(B37) -> 138390.47 | C39: =SUM(C37) -> 151225.52 | D39: =SUM(D37) -> 151451.22 | E39: =SUM(E37) -> 99608.559 | F39: =SUM(F37) -> 103556.73 | G39: =SUM(G37) -> 90242.155 | H39: =SUM(H37) -> 90339.034 | I39: =SUM(I37) -> 88015.047 | ... AF39: =SUM(AF37) -> 40433.49 | AG39: =SUM(B39:AF39) -> 2320738.1
A41: Orders
A42: Orders Woocommerce (Platform) | B42: =Summary!B82 -> 1432 | C42: =Summary!C82 -> 1599 | D42: =Summary!D82 -> 1585 | E42: =Summary!E82 -> 972 | F42: =Summary!F82 -> 1040 | G42: =Summary!G82 -> 868 | H42: =Summary!H82 -> 855 | I42: =Summary!I82 -> 808 | ... AF42: =Summary!AF82 -> 213 | AG42: =SUM(B42:AF42) -> 20147
A43: Orders w/o renewals | B43: ='DTC US&CA - P&L'!B11+'DTC EU - P&L'!B11 -> 256 | C43: ='DTC US&CA - P&L'!C11+'DTC EU - P&L'!C11 -> 215 | D43: ='DTC US&CA - P&L'!D11+'DTC EU - P&L'!D11 -> 217 | E43: ='DTC US&CA - P&L'!E11+'DTC EU - P&L'!E11 -> 224 | F43: ='DTC US&CA - P&L'!F11+'DTC EU - P&L'!F11 -> 264 | G43: ='DTC US&CA - P&L'!G11+'DTC EU - P&L'!G11 -> 171 | H43: ='DTC US&CA - P&L'!H11+'DTC EU - P&L'!H11 -> 169 | I43: ='DTC US&CA - P&L'!I11+'DTC EU - P&L'!I11 -> 166 | ... AF43: ='DTC US&CA - P&L'!AF11+'DTC EU - P&L'!AF11 -> 168 | AG43: =SUM(B43:AF43) -> 5600
A44: SUM | B44: =SUM(B42) -> 1432 | C44: =SUM(C42) -> 1599 | D44: =SUM(D42) -> 1585 | E44: =SUM(E42) -> 972 | F44: =SUM(F42) -> 1040 | G44: =SUM(G42) -> 868 | H44: =SUM(H42) -> 855 | I44: =SUM(I42) -> 808 | ... AF44: =SUM(AF42) -> 213 | AG44: =SUM(B44:AF44) -> 20147
A46: Breakdown
A47: - Hardware | B47: =Summary!B11+Summary!B18 -> 13357.495 | C47: =Summary!C11+Summary!C18 -> 11862.944 | D47: =Summary!D11+Summary!D18 -> 13073.981 | E47: =Summary!E11+Summary!E18 -> 17501.948 | F47: =Summary!F11+Summary!F18 -> 17471.617 | G47: =Summary!G11+Summary!G18 -> 16055.324 | H47: =Summary!H11+Summary!H18 -> 17052.272 | I47: =Summary!I11+Summary!I18 -> 19128.081 | ... AF47: =Summary!AF11+Summary!AF18 -> 27442.71 | AG47: =SUM(B47:AF47) -> 634926.61
A48: - Add-ons | B48: =Summary!B12+Summary!B19 -> 11534.251 | C48: =Summary!C12+Summary!C19 -> 8621.6786 | D48: =Summary!D12+Summary!D19 -> 8339.3469 | E48: =Summary!E12+Summary!E19 -> 8072.8261 | F48: =Summary!F12+Summary!F19 -> 9018.4 | G48: =Summary!G12+Summary!G19 -> 5869.3773 | H48: =Summary!H12+Summary!H19 -> 5816.8336 | I48: =Summary!I12+Summary!I19 -> 5259.6895 | ... AF48: =Summary!AF12+Summary!AF19 -> 3299.0852 | AG48: =SUM(B48:AF48) -> 190893.33
A49: - Merch | B49: =Summary!B13+Summary!B20 -> 0 | C49: =Summary!C13+Summary!C20 -> 0 | D49: =Summary!D13+Summary!D20 -> 0 | E49: =Summary!E13+Summary!E20 -> 0 | F49: =Summary!F13+Summary!F20 -> 0 | G49: =Summary!G13+Summary!G20 -> 0 | H49: =Summary!H13+Summary!H20 -> 0 | I49: =Summary!I13+Summary!I20 -> 0 | ... AF49: =Summary!AF13+Summary!AF20 -> 0 | AG49: =SUM(B49:AF49) -> 299.91
A50: - Seeds | B50: =Summary!B14+Summary!B21 -> 657 | C50: =Summary!C14+Summary!C21 -> 454.4 | D50: =Summary!D14+Summary!D21 -> 756.5 | E50: =Summary!E14+Summary!E21 -> 596.9 | F50: =Summary!F14+Summary!F21 -> 586.1 | G50: =Summary!G14+Summary!G21 -> 335.6 | H50: =Summary!H14+Summary!H21 -> 409.5 | I50: =Summary!I14+Summary!I21 -> 331.8 | ... AF50: =Summary!AF14+Summary!AF21 -> 432.6 | AG50: =SUM(B50:AF50) -> 14921.9
A51: - Yearly Pro Subscription | B51: ='DTC US&CA - P&L'!B19+Summary!B26 -> 103735.26 | C51: ='DTC US&CA - P&L'!C19+Summary!C26 -> 122108.78 | D51: ='DTC US&CA - P&L'!D19+Summary!D26 -> 120668.38 | E51: ='DTC US&CA - P&L'!E19+Summary!E26 -> 66404.582 | F51: ='DTC US&CA - P&L'!F19+Summary!F26 -> 68547.074 | G51: ='DTC US&CA - P&L'!G19+Summary!G26 -> 61251.662 | H51: ='DTC US&CA - P&L'!H19+Summary!H26 -> 60251.16 | I51: ='DTC US&CA - P&L'!I19+Summary!I26 -> 56410.664 | ... AF51: ='DTC US&CA - P&L'!AF19+Summary!AF26 -> 3054.8346 | AG51: =SUM(B51:AF51) -> 1272156.9
A52: - Taxes | B52: =Summary!B15+Summary!B22 -> 5930.9065 | C52: =Summary!C15+Summary!C22 -> 5582.3744 | D52: =Summary!D15+Summary!D22 -> 5995.223 | E52: =Summary!E15+Summary!E22 -> 4013.4031 | F52: =Summary!F15+Summary!F22 -> 4594.0367 | G52: =Summary!G15+Summary!G22 -> 4244.4236 | H52: =Summary!H15+Summary!H22 -> 4252.4397 | I52: =Summary!I15+Summary!I22 -> 4155.9676 | ... AF52: =Summary!AF15+Summary!AF22 -> 2564.4153 | AG52: =SUM(B52:AF52) -> 113396.3
A53: - Shipping | B53: =Summary!B16+Summary!B23 -> 3175.561 | C53: =Summary!C16+Summary!C23 -> 2595.343 | D53: =Summary!D16+Summary!D23 -> 2617.78 | E53: =Summary!E16+Summary!E23 -> 3018.899 | F53: =Summary!F16+Summary!F23 -> 3339.505 | G53: =Summary!G16+Summary!G23 -> 2485.768 | H53: =Summary!H16+Summary!H23 -> 2556.828 | I53: =Summary!I16+Summary!I23 -> 2728.8445 | ... AF53: =Summary!AF16+Summary!AF23 -> 3639.845 | AG53: =SUM(B53:AF53) -> 94143.125
A54: SUM | B54: =SUM(B47:B53) -> 138390.47 | C54: =SUM(C47:C53) -> 151225.52 | D54: =SUM(D47:D53) -> 151451.22 | E54: =SUM(E47:E53) -> 99608.559 | F54: =SUM(F47:F53) -> 103556.73 | G54: =SUM(G47:G53) -> 90242.155 | H54: =SUM(H47:H53) -> 90339.034 | I54: =SUM(I47:I53) -> 88015.047 | ... AF54: =SUM(AF47:AF53) -> 40433.49 | AG54: =SUM(B54:AF54) -> 2320738.1
A56: Units Sold (Gross)
A57: SKU 1 - Blue | B57: ='DTC US&CA - P&L'!B25+'DTC EU - P&L'!B25 -> 48 | C57: ='DTC US&CA - P&L'!C25+'DTC EU - P&L'!C25 -> 44 | D57: ='DTC US&CA - P&L'!D25+'DTC EU - P&L'!D25 -> 34 | E57: ='DTC US&CA - P&L'!E25+'DTC EU - P&L'!E25 -> 19 | F57: ='DTC US&CA - P&L'!F25+'DTC EU - P&L'!F25 -> 23 | G57: ='DTC US&CA - P&L'!G25+'DTC EU - P&L'!G25 -> 18 | H57: ='DTC US&CA - P&L'!H25+'DTC EU - P&L'!H25 -> 21 | I57: ='DTC US&CA - P&L'!I25+'DTC EU - P&L'!I25 -> 21 | ... AF57: ='DTC US&CA - P&L'!AF25+'DTC EU - P&L'!AF25 -> 14 | AG57: =SUM(B57:AF57) -> 498
A58: SKU 2 - Yellow | B58: ='DTC US&CA - P&L'!B26+'DTC EU - P&L'!B26 -> 0 | C58: ='DTC US&CA - P&L'!C26+'DTC EU - P&L'!C26 -> 0 | D58: ='DTC US&CA - P&L'!D26+'DTC EU - P&L'!D26 -> 0 | E58: ='DTC US&CA - P&L'!E26+'DTC EU - P&L'!E26 -> 0 | F58: ='DTC US&CA - P&L'!F26+'DTC EU - P&L'!F26 -> 0 | G58: ='DTC US&CA - P&L'!G26+'DTC EU - P&L'!G26 -> 0 | H58: ='DTC US&CA - P&L'!H26+'DTC EU - P&L'!H26 -> 0 | I58: ='DTC US&CA - P&L'!I26+'DTC EU - P&L'!I26 -> 0 | ... AF58: ='DTC US&CA - P&L'!AF26+'DTC EU - P&L'!AF26 -> 0 | AG58: =SUM(B58:AF58) -> 0
A59: SKU 3 - Blue w/ Solar | B59: ='DTC US&CA - P&L'!B27+'DTC EU - P&L'!B27 -> 0 | C59: ='DTC US&CA - P&L'!C27+'DTC EU - P&L'!C27 -> 0 | D59: ='DTC US&CA - P&L'!D27+'DTC EU - P&L'!D27 -> 0 | E59: ='DTC US&CA - P&L'!E27+'DTC EU - P&L'!E27 -> 0 | F59: ='DTC US&CA - P&L'!F27+'DTC EU - P&L'!F27 -> 0 | G59: ='DTC US&CA - P&L'!G27+'DTC EU - P&L'!G27 -> 0 | H59: ='DTC US&CA - P&L'!H27+'DTC EU - P&L'!H27 -> 0 | I59: ='DTC US&CA - P&L'!I27+'DTC EU - P&L'!I27 -> 0 | ... AF59: ='DTC US&CA - P&L'!AF27+'DTC EU - P&L'!AF27 -> 0 | AG59: =SUM(B59:AF59) -> 146
A60: SKU 4 - Yellow w/ Solar | B60: ='DTC US&CA - P&L'!B28+'DTC EU - P&L'!B28 -> 7 | C60: ='DTC US&CA - P&L'!C28+'DTC EU - P&L'!C28 -> 8 | D60: ='DTC US&CA - P&L'!D28+'DTC EU - P&L'!D28 -> 7 | E60: ='DTC US&CA - P&L'!E28+'DTC EU - P&L'!E28 -> 12 | F60: ='DTC US&CA - P&L'!F28+'DTC EU - P&L'!F28 -> 9 | G60: ='DTC US&CA - P&L'!G28+'DTC EU - P&L'!G28 -> 6 | H60: ='DTC US&CA - P&L'!H28+'DTC EU - P&L'!H28 -> 4 | I60: ='DTC US&CA - P&L'!I28+'DTC EU - P&L'!I28 -> 4 | ... AF60: ='DTC US&CA - P&L'!AF28+'DTC EU - P&L'!AF28 -> 31 | AG60: =SUM(B60:AF60) -> 334
A61: SKU 1 - Blue PRO | B61: ='DTC US&CA - P&L'!B29+'DTC EU - P&L'!B29 -> 1 | C61: ='DTC US&CA - P&L'!C29+'DTC EU - P&L'!C29 -> 0 | D61: ='DTC US&CA - P&L'!D29+'DTC EU - P&L'!D29 -> 2 | E61: ='DTC US&CA - P&L'!E29+'DTC EU - P&L'!E29 -> 3 | F61: ='DTC US&CA - P&L'!F29+'DTC EU - P&L'!F29 -> 11 | G61: ='DTC US&CA - P&L'!G29+'DTC EU - P&L'!G29 -> 7 | H61: ='DTC US&CA - P&L'!H29+'DTC EU - P&L'!H29 -> 18 | I61: ='DTC US&CA - P&L'!I29+'DTC EU - P&L'!I29 -> 11 | ... AF61: ='DTC US&CA - P&L'!AF29+'DTC EU - P&L'!AF29 -> 22 | AG61: =SUM(B61:AF61) -> 269
A62: SKU 2 - Yellow PRO | B62: ='DTC US&CA - P&L'!B30+'DTC EU - P&L'!B30 -> 0 | C62: ='DTC US&CA - P&L'!C30+'DTC EU - P&L'!C30 -> 0 | D62: ='DTC US&CA - P&L'!D30+'DTC EU - P&L'!D30 -> 0 | E62: ='DTC US&CA - P&L'!E30+'DTC EU - P&L'!E30 -> 0 | F62: ='DTC US&CA - P&L'!F30+'DTC EU - P&L'!F30 -> 0 | G62: ='DTC US&CA - P&L'!G30+'DTC EU - P&L'!G30 -> 0 | H62: ='DTC US&CA - P&L'!H30+'DTC EU - P&L'!H30 -> 0 | I62: ='DTC US&CA - P&L'!I30+'DTC EU - P&L'!I30 -> 0 | ... AF62: ='DTC US&CA - P&L'!AF30+'DTC EU - P&L'!AF30 -> 0 | AG62: =SUM(B62:AF62) -> 0
A63: SKU 3 - Blue w/ Solar PRO | B63: ='DTC US&CA - P&L'!B31+'DTC EU - P&L'!B31 -> 4 | C63: ='DTC US&CA - P&L'!C31+'DTC EU - P&L'!C31 -> 1 | D63: ='DTC US&CA - P&L'!D31+'DTC EU - P&L'!D31 -> 12 | E63: ='DTC US&CA - P&L'!E31+'DTC EU - P&L'!E31 -> 33 | F63: ='DTC US&CA - P&L'!F31+'DTC EU - P&L'!F31 -> 26 | G63: ='DTC US&CA - P&L'!G31+'DTC EU - P&L'!G31 -> 32 | H63: ='DTC US&CA - P&L'!H31+'DTC EU - P&L'!H31 -> 26 | I63: ='DTC US&CA - P&L'!I31+'DTC EU - P&L'!I31 -> 38 | ... AF63: ='DTC US&CA - P&L'!AF31+'DTC EU - P&L'!AF31 -> 60 | AG63: =SUM(B63:AF63) -> 1418
A64: SKU 4 - Yellow w/ Solar PRO | B64: ='DTC US&CA - P&L'!B32+'DTC EU - P&L'!B32 -> 0 | C64: ='DTC US&CA - P&L'!C32+'DTC EU - P&L'!C32 -> 0 | D64: ='DTC US&CA - P&L'!D32+'DTC EU - P&L'!D32 -> 0 | E64: ='DTC US&CA - P&L'!E32+'DTC EU - P&L'!E32 -> 0 | F64: ='DTC US&CA - P&L'!F32+'DTC EU - P&L'!F32 -> 0 | G64: ='DTC US&CA - P&L'!G32+'DTC EU - P&L'!G32 -> 0 | H64: ='DTC US&CA - P&L'!H32+'DTC EU - P&L'!H32 -> 0 | I64: ='DTC US&CA - P&L'!I32+'DTC EU - P&L'!I32 -> 0 | ... AF64: ='DTC US&CA - P&L'!AF32+'DTC EU - P&L'!AF32 -> 0 | AG64: =SUM(B64:AF64) -> 0
A65: SUM (SKU 1 - SKU 4) | B65: =SUM(B57:B64) -> 60 | C65: =SUM(C57:C64) -> 53 | D65: =SUM(D57:D64) -> 55 | E65: =SUM(E57:E64) -> 67 | F65: =SUM(F57:F64) -> 69 | G65: =SUM(G57:G64) -> 63 | H65: =SUM(H57:H64) -> 69 | I65: =SUM(I57:I64) -> 74 | ... AF65: =SUM(AF57:AF64) -> 127 | AG65: =SUM(B65:AF65) -> 2665
A67: SKU 5 - HBF | B67: ='DTC US&CA - P&L'!B35+'DTC EU - P&L'!B35 -> 0 | C67: ='DTC US&CA - P&L'!C35+'DTC EU - P&L'!C35 -> 0 | D67: ='DTC US&CA - P&L'!D35+'DTC EU - P&L'!D35 -> 0 | E67: ='DTC US&CA - P&L'!E35+'DTC EU - P&L'!E35 -> 0 | F67: ='DTC US&CA - P&L'!F35+'DTC EU - P&L'!F35 -> 0 | G67: ='DTC US&CA - P&L'!G35+'DTC EU - P&L'!G35 -> 0 | H67: ='DTC US&CA - P&L'!H35+'DTC EU - P&L'!H35 -> 0 | I67: ='DTC US&CA - P&L'!I35+'DTC EU - P&L'!I35 -> 0 | ... AF67: ='DTC US&CA - P&L'!AF35+'DTC EU - P&L'!AF35 -> 0 | AG67: =SUM(B67:AF67) -> 0
A68: SKU 6 - HBF w/ Solar | B68: ='DTC US&CA - P&L'!B36+'DTC EU - P&L'!B36 -> 0 | C68: ='DTC US&CA - P&L'!C36+'DTC EU - P&L'!C36 -> 0 | D68: ='DTC US&CA - P&L'!D36+'DTC EU - P&L'!D36 -> 0 | E68: ='DTC US&CA - P&L'!E36+'DTC EU - P&L'!E36 -> 0 | F68: ='DTC US&CA - P&L'!F36+'DTC EU - P&L'!F36 -> 0 | G68: ='DTC US&CA - P&L'!G36+'DTC EU - P&L'!G36 -> 0 | H68: ='DTC US&CA - P&L'!H36+'DTC EU - P&L'!H36 -> 0 | I68: ='DTC US&CA - P&L'!I36+'DTC EU - P&L'!I36 -> 0 | ... AF68: ='DTC US&CA - P&L'!AF36+'DTC EU - P&L'!AF36 -> 0 | AG68: =SUM(B68:AF68) -> 0
A69: SUM (SKU 5 - SKU 6) | B69: =SUM(B67:B68) -> 0 | C69: =SUM(C67:C68) -> 0 | D69: =SUM(D67:D68) -> 0 | E69: =SUM(E67:E68) -> 0 | F69: =SUM(F67:F68) -> 0 | G69: =SUM(G67:G68) -> 0 | H69: =SUM(H67:H68) -> 0 | I69: =SUM(I67:I68) -> 0 | ... AF69: =SUM(AF67:AF68) -> 0 | AG69: =SUM(B69:AF69) -> 0
A71: Wall Mount | B71: ='DTC US&CA - P&L'!B39+'DTC EU - P&L'!B39 -> 23 | C71: ='DTC US&CA - P&L'!C39+'DTC EU - P&L'!C39 -> 33 | D71: ='DTC US&CA - P&L'!D39+'DTC EU - P&L'!D39 -> 19 | E71: ='DTC US&CA - P&L'!E39+'DTC EU - P&L'!E39 -> 26 | F71: ='DTC US&CA - P&L'!F39+'DTC EU - P&L'!F39 -> 31 | G71: ='DTC US&CA - P&L'!G39+'DTC EU - P&L'!G39 -> 15 | H71: ='DTC US&CA - P&L'!H39+'DTC EU - P&L'!H39 -> 15 | I71: ='DTC US&CA - P&L'!I39+'DTC EU - P&L'!I39 -> 13 | ... AF71: ='DTC US&CA - P&L'!AF39+'DTC EU - P&L'!AF39 -> 14 | AG71: =SUM(B71:AF71) -> 693
A72: Suet Ball Holder | B72: ='DTC US&CA - P&L'!B40+'DTC EU - P&L'!B40 -> 21 | C72: ='DTC US&CA - P&L'!C40+'DTC EU - P&L'!C40 -> 21 | D72: ='DTC US&CA - P&L'!D40+'DTC EU - P&L'!D40 -> 17 | E72: ='DTC US&CA - P&L'!E40+'DTC EU - P&L'!E40 -> 23 | F72: ='DTC US&CA - P&L'!F40+'DTC EU - P&L'!F40 -> 23 | G72: ='DTC US&CA - P&L'!G40+'DTC EU - P&L'!G40 -> 12 | H72: ='DTC US&CA - P&L'!H40+'DTC EU - P&L'!H40 -> 16 | I72: ='DTC US&CA - P&L'!I40+'DTC EU - P&L'!I40 -> 19 | ... AF72: ='DTC US&CA - P&L'!AF40+'DTC EU - P&L'!AF40 -> 87 | AG72: =SUM(B72:AF72) -> 1236
A73: 3-in-1 Nutrition Set - Blue | B73: ='DTC US&CA - P&L'!B41+'DTC EU - P&L'!B41 -> 20 | C73: ='DTC US&CA - P&L'!C41+'DTC EU - P&L'!C41 -> 7 | D73: ='DTC US&CA - P&L'!D41+'DTC EU - P&L'!D41 -> 15 | E73: ='DTC US&CA - P&L'!E41+'DTC EU - P&L'!E41 -> 22 | F73: ='DTC US&CA - P&L'!F41+'DTC EU - P&L'!F41 -> 19 | G73: ='DTC US&CA - P&L'!G41+'DTC EU - P&L'!G41 -> 9 | H73: ='DTC US&CA - P&L'!H41+'DTC EU - P&L'!H41 -> 14 | I73: ='DTC US&CA - P&L'!I41+'DTC EU - P&L'!I41 -> 7 | ... AF73: ='DTC US&CA - P&L'!AF41+'DTC EU - P&L'!AF41 -> 4 | AG73: =SUM(B73:AF73) -> 562
A74: 3-in-1 Nutrition Set - Yellow | B74: ='DTC US&CA - P&L'!B42+'DTC EU - P&L'!B42 -> 2 | C74: ='DTC US&CA - P&L'!C42+'DTC EU - P&L'!C42 -> 1 | D74: ='DTC US&CA - P&L'!D42+'DTC EU - P&L'!D42 -> 1 | E74: ='DTC US&CA - P&L'!E42+'DTC EU - P&L'!E42 -> 8 | F74: ='DTC US&CA - P&L'!F42+'DTC EU - P&L'!F42 -> 4 | G74: ='DTC US&CA - P&L'!G42+'DTC EU - P&L'!G42 -> 2 | H74: ='DTC US&CA - P&L'!H42+'DTC EU - P&L'!H42 -> 0 | I74: ='DTC US&CA - P&L'!I42+'DTC EU - P&L'!I42 -> 1 | ... AF74: ='DTC US&CA - P&L'!AF42+'DTC EU - P&L'!AF42 -> 4 | AG74: =SUM(B74:AF74) -> 81
A75: Solar Roof Single - Blue | B75: ='DTC US&CA - P&L'!B43+'DTC EU - P&L'!B43 -> 91 | C75: ='DTC US&CA - P&L'!C43+'DTC EU - P&L'!C43 -> 71 | D75: ='DTC US&CA - P&L'!D43+'DTC EU - P&L'!D43 -> 58 | E75: ='DTC US&CA - P&L'!E43+'DTC EU - P&L'!E43 -> 38 | F75: ='DTC US&CA - P&L'!F43+'DTC EU - P&L'!F43 -> 54 | G75: ='DTC US&CA - P&L'!G43+'DTC EU - P&L'!G43 -> 43 | H75: ='DTC US&CA - P&L'!H43+'DTC EU - P&L'!H43 -> 31 | I75: ='DTC US&CA - P&L'!I43+'DTC EU - P&L'!I43 -> 30 | ... AF75: ='DTC US&CA - P&L'!AF43+'DTC EU - P&L'!AF43 -> 19 | AG75: =SUM(B75:AF75) -> 967
A76: Solar Roof Single - Yellow | B76: ='DTC US&CA - P&L'!B44+'DTC EU - P&L'!B44 -> 2 | C76: ='DTC US&CA - P&L'!C44+'DTC EU - P&L'!C44 -> 1 | D76: ='DTC US&CA - P&L'!D44+'DTC EU - P&L'!D44 -> 1 | E76: ='DTC US&CA - P&L'!E44+'DTC EU - P&L'!E44 -> 4 | F76: ='DTC US&CA - P&L'!F44+'DTC EU - P&L'!F44 -> 0 | G76: ='DTC US&CA - P&L'!G44+'DTC EU - P&L'!G44 -> 1 | H76: ='DTC US&CA - P&L'!H44+'DTC EU - P&L'!H44 -> 1 | I76: ='DTC US&CA - P&L'!I44+'DTC EU - P&L'!I44 -> 0 | ... AF76: ='DTC US&CA - P&L'!AF44+'DTC EU - P&L'!AF44 -> 0 | AG76: =SUM(B76:AF76) -> 42
A77: Perch Extender - Blue | B77: ='DTC US&CA - P&L'!B45+'DTC EU - P&L'!B45 -> 93 | C77: ='DTC US&CA - P&L'!C45+'DTC EU - P&L'!C45 -> 70 | D77: ='DTC US&CA - P&L'!D45+'DTC EU - P&L'!D45 -> 80 | E77: ='DTC US&CA - P&L'!E45+'DTC EU - P&L'!E45 -> 81 | F77: ='DTC US&CA - P&L'!F45+'DTC EU - P&L'!F45 -> 102 | G77: ='DTC US&CA - P&L'!G45+'DTC EU - P&L'!G45 -> 59 | H77: ='DTC US&CA - P&L'!H45+'DTC EU - P&L'!H45 -> 63 | I77: ='DTC US&CA - P&L'!I45+'DTC EU - P&L'!I45 -> 69 | ... AF77: ='DTC US&CA - P&L'!AF45+'DTC EU - P&L'!AF45 -> 33 | AG77: =SUM(B77:AF77) -> 1902
A78: Perch Extender - Yellow | B78: ='DTC US&CA - P&L'!B46+'DTC EU - P&L'!B46 -> 16 | C78: ='DTC US&CA - P&L'!C46+'DTC EU - P&L'!C46 -> 10 | D78: ='DTC US&CA - P&L'!D46+'DTC EU - P&L'!D46 -> 13 | E78: ='DTC US&CA - P&L'!E46+'DTC EU - P&L'!E46 -> 17 | F78: ='DTC US&CA - P&L'!F46+'DTC EU - P&L'!F46 -> 10 | G78: ='DTC US&CA - P&L'!G46+'DTC EU - P&L'!G46 -> 6 | H78: ='DTC US&CA - P&L'!H46+'DTC EU - P&L'!H46 -> 8 | I78: ='DTC US&CA - P&L'!I46+'DTC EU - P&L'!I46 -> 9 | ... AF78: ='DTC US&CA - P&L'!AF46+'DTC EU - P&L'!AF46 -> 13 | AG78: =SUM(B78:AF78) -> 330
A79: Solar Roof (HBF) | B79: ='DTC US&CA - P&L'!B47+'DTC EU - P&L'!B47 -> 3 | C79: ='DTC US&CA - P&L'!C47+'DTC EU - P&L'!C47 -> 1 | D79: ='DTC US&CA - P&L'!D47+'DTC EU - P&L'!D47 -> 1 | E79: ='DTC US&CA - P&L'!E47+'DTC EU - P&L'!E47 -> 2 | F79: ='DTC US&CA - P&L'!F47+'DTC EU - P&L'!F47 -> 0 | G79: ='DTC US&CA - P&L'!G47+'DTC EU - P&L'!G47 -> 1 | H79: ='DTC US&CA - P&L'!H47+'DTC EU - P&L'!H47 -> 0 | I79: ='DTC US&CA - P&L'!I47+'DTC EU - P&L'!I47 -> 1 | ... AF79: ='DTC US&CA - P&L'!AF47+'DTC EU - P&L'!AF47 -> 0 | AG79: =SUM(B79:AF79) -> 22
A80: Housing - only (HBF) | B80: ='DTC US&CA - P&L'!B48+'DTC EU - P&L'!B48 -> 0 | C80: ='DTC US&CA - P&L'!C48+'DTC EU - P&L'!C48 -> 0 | D80: ='DTC US&CA - P&L'!D48+'DTC EU - P&L'!D48 -> 0 | E80: ='DTC US&CA - P&L'!E48+'DTC EU - P&L'!E48 -> 0 | F80: ='DTC US&CA - P&L'!F48+'DTC EU - P&L'!F48 -> 0 | G80: ='DTC US&CA - P&L'!G48+'DTC EU - P&L'!G48 -> 0 | H80: ='DTC US&CA - P&L'!H48+'DTC EU - P&L'!H48 -> 0 | I80: ='DTC US&CA - P&L'!I48+'DTC EU - P&L'!I48 -> 0 | ... AF80: ='DTC US&CA - P&L'!AF48+'DTC EU - P&L'!AF48 -> 0 | AG80: =SUM(B80:AF80) -> 0
A81: Nature Cam PRO | B81: ='DTC US&CA - P&L'!B49+'DTC EU - P&L'!B49 -> 6 | C81: ='DTC US&CA - P&L'!C49+'DTC EU - P&L'!C49 -> 2 | D81: ='DTC US&CA - P&L'!D49+'DTC EU - P&L'!D49 -> 5 | E81: ='DTC US&CA - P&L'!E49+'DTC EU - P&L'!E49 -> 3 | F81: ='DTC US&CA - P&L'!F49+'DTC EU - P&L'!F49 -> 3 | G81: ='DTC US&CA - P&L'!G49+'DTC EU - P&L'!G49 -> 2 | H81: ='DTC US&CA - P&L'!H49+'DTC EU - P&L'!H49 -> 4 | I81: ='DTC US&CA - P&L'!I49+'DTC EU - P&L'!I49 -> 1 | ... AF81: ='DTC US&CA - P&L'!AF49+'DTC EU - P&L'!AF49 -> 1 | AG81: =SUM(B81:AF81) -> 96
A82: SUM (Add-ons) | B82: =SUM(B71:B81) -> 277 | C82: =SUM(C71:C81) -> 217 | D82: =SUM(D71:D81) -> 210 | E82: =SUM(E71:E81) -> 224 | F82: =SUM(F71:F81) -> 246 | G82: =SUM(G71:G81) -> 150 | H82: =SUM(H71:H81) -> 152 | I82: =SUM(I71:I81) -> 150 | ... AF82: =SUM(AF71:AF81) -> 175 | AG82: =SUM(B82:AF82) -> 5931
A84: Seasonal Curation - 8lb | B84: ='DTC US&CA - P&L'!B52+'DTC EU - P&L'!B52 -> 15 | C84: ='DTC US&CA - P&L'!C52+'DTC EU - P&L'!C52 -> 14 | D84: ='DTC US&CA - P&L'!D52+'DTC EU - P&L'!D52 -> 24 | E84: ='DTC US&CA - P&L'!E52+'DTC EU - P&L'!E52 -> 11 | F84: ='DTC US&CA - P&L'!F52+'DTC EU - P&L'!F52 -> 15 | G84: ='DTC US&CA - P&L'!G52+'DTC EU - P&L'!G52 -> 9 | H84: ='DTC US&CA - P&L'!H52+'DTC EU - P&L'!H52 -> 10 | I84: ='DTC US&CA - P&L'!I52+'DTC EU - P&L'!I52 -> 7 | ... AF84: ='DTC US&CA - P&L'!AF52+'DTC EU - P&L'!AF52 -> 11 | AG84: =SUM(B84:AF84) -> 338
A85: Seasonal Curation - 20lb | B85: ='DTC US&CA - P&L'!B53+'DTC EU - P&L'!B53 -> 1 | C85: ='DTC US&CA - P&L'!C53+'DTC EU - P&L'!C53 -> 0 | D85: ='DTC US&CA - P&L'!D53+'DTC EU - P&L'!D53 -> 0 | E85: ='DTC US&CA - P&L'!E53+'DTC EU - P&L'!E53 -> 2 | F85: ='DTC US&CA - P&L'!F53+'DTC EU - P&L'!F53 -> 0 | G85: ='DTC US&CA - P&L'!G53+'DTC EU - P&L'!G53 -> 0 | H85: ='DTC US&CA - P&L'!H53+'DTC EU - P&L'!H53 -> 1 | I85: ='DTC US&CA - P&L'!I53+'DTC EU - P&L'!I53 -> 0 | ... AF85: ='DTC US&CA - P&L'!AF53+'DTC EU - P&L'!AF53 -> 1 | AG85: =SUM(B85:AF85) -> 31
A86: Buddy Bites - 8lb | B86: ='DTC US&CA - P&L'!B54+'DTC EU - P&L'!B54 -> 0 | C86: ='DTC US&CA - P&L'!C54+'DTC EU - P&L'!C54 -> 1 | D86: ='DTC US&CA - P&L'!D54+'DTC EU - P&L'!D54 -> 0 | E86: ='DTC US&CA - P&L'!E54+'DTC EU - P&L'!E54 -> 1 | F86: ='DTC US&CA - P&L'!F54+'DTC EU - P&L'!F54 -> 0 | G86: ='DTC US&CA - P&L'!G54+'DTC EU - P&L'!G54 -> 1 | H86: ='DTC US&CA - P&L'!H54+'DTC EU - P&L'!H54 -> 0 | I86: ='DTC US&CA - P&L'!I54+'DTC EU - P&L'!I54 -> 0 | ... AF86: ='DTC US&CA - P&L'!AF54+'DTC EU - P&L'!AF54 -> 0 | AG86: =SUM(B86:AF86) -> 24
A87: Buddy Bites - 20lb | B87: ='DTC US&CA - P&L'!B55+'DTC EU - P&L'!B55 -> 3 | C87: ='DTC US&CA - P&L'!C55+'DTC EU - P&L'!C55 -> 0 | D87: ='DTC US&CA - P&L'!D55+'DTC EU - P&L'!D55 -> 1 | E87: ='DTC US&CA - P&L'!E55+'DTC EU - P&L'!E55 -> 0 | F87: ='DTC US&CA - P&L'!F55+'DTC EU - P&L'!F55 -> 2 | G87: ='DTC US&CA - P&L'!G55+'DTC EU - P&L'!G55 -> 0 | H87: ='DTC US&CA - P&L'!H55+'DTC EU - P&L'!H55 -> 1 | I87: ='DTC US&CA - P&L'!I55+'DTC EU - P&L'!I55 -> 1 | ... AF87: ='DTC US&CA - P&L'!AF55+'DTC EU - P&L'!AF55 -> 0 | AG87: =SUM(B87:AF87) -> 17
A88: Snack n' Soar - 8lb | B88: ='DTC US&CA - P&L'!B56+'DTC EU - P&L'!B56 -> 0 | C88: ='DTC US&CA - P&L'!C56+'DTC EU - P&L'!C56 -> 1 | D88: ='DTC US&CA - P&L'!D56+'DTC EU - P&L'!D56 -> 0 | E88: ='DTC US&CA - P&L'!E56+'DTC EU - P&L'!E56 -> 4 | F88: ='DTC US&CA - P&L'!F56+'DTC EU - P&L'!F56 -> 0 | G88: ='DTC US&CA - P&L'!G56+'DTC EU - P&L'!G56 -> 1 | H88: ='DTC US&CA - P&L'!H56+'DTC EU - P&L'!H56 -> 1 | I88: ='DTC US&CA - P&L'!I56+'DTC EU - P&L'!I56 -> 0 | ... AF88: ='DTC US&CA - P&L'!AF56+'DTC EU - P&L'!AF56 -> 0 | AG88: =SUM(B88:AF88) -> 31
A89: Snack n' Soar - 20lb | B89: ='DTC US&CA - P&L'!B57+'DTC EU - P&L'!B57 -> 0 | C89: ='DTC US&CA - P&L'!C57+'DTC EU - P&L'!C57 -> 0 | D89: ='DTC US&CA - P&L'!D57+'DTC EU - P&L'!D57 -> 0 | E89: ='DTC US&CA - P&L'!E57+'DTC EU - P&L'!E57 -> 0 | F89: ='DTC US&CA - P&L'!F57+'DTC EU - P&L'!F57 -> 0 | G89: ='DTC US&CA - P&L'!G57+'DTC EU - P&L'!G57 -> 0 | H89: ='DTC US&CA - P&L'!H57+'DTC EU - P&L'!H57 -> 0 | I89: ='DTC US&CA - P&L'!I57+'DTC EU - P&L'!I57 -> 0 | ... AF89: ='DTC US&CA - P&L'!AF57+'DTC EU - P&L'!AF57 -> 1 | AG89: =SUM(B89:AF89) -> 6
A90: Avian Choice - 8lb | B90: ='DTC US&CA - P&L'!B58+'DTC EU - P&L'!B58 -> 1 | C90: ='DTC US&CA - P&L'!C58+'DTC EU - P&L'!C58 -> 0 | D90: ='DTC US&CA - P&L'!D58+'DTC EU - P&L'!D58 -> 0 | E90: ='DTC US&CA - P&L'!E58+'DTC EU - P&L'!E58 -> 2 | F90: ='DTC US&CA - P&L'!F58+'DTC EU - P&L'!F58 -> 2 | G90: ='DTC US&CA - P&L'!G58+'DTC EU - P&L'!G58 -> 1 | H90: ='DTC US&CA - P&L'!H58+'DTC EU - P&L'!H58 -> 0 | I90: ='DTC US&CA - P&L'!I58+'DTC EU - P&L'!I58 -> 4 | ... AF90: ='DTC US&CA - P&L'!AF58+'DTC EU - P&L'!AF58 -> 1 | AG90: =SUM(B90:AF90) -> 32
A91: Avian Choice - 20lb | B91: ='DTC US&CA - P&L'!B59+'DTC EU - P&L'!B59 -> 0 | C91: ='DTC US&CA - P&L'!C59+'DTC EU - P&L'!C59 -> 0 | D91: ='DTC US&CA - P&L'!D59+'DTC EU - P&L'!D59 -> 0 | E91: ='DTC US&CA - P&L'!E59+'DTC EU - P&L'!E59 -> 0 | F91: ='DTC US&CA - P&L'!F59+'DTC EU - P&L'!F59 -> 0 | G91: ='DTC US&CA - P&L'!G59+'DTC EU - P&L'!G59 -> 0 | H91: ='DTC US&CA - P&L'!H59+'DTC EU - P&L'!H59 -> 0 | I91: ='DTC US&CA - P&L'!I59+'DTC EU - P&L'!I59 -> 0 | ... AF91: ='DTC US&CA - P&L'!AF59+'DTC EU - P&L'!AF59 -> 0 | AG91: =SUM(B91:AF91) -> 7
A92: SUM (Seeds) | B92: =SUM(B84:B91) -> 20 | C92: =SUM(C84:C91) -> 16 | D92: =SUM(D84:D91) -> 25 | E92: =SUM(E84:E91) -> 20 | F92: =SUM(F84:F91) -> 19 | G92: =SUM(G84:G91) -> 12 | H92: =SUM(H84:H91) -> 13 | I92: =SUM(I84:I91) -> 12 | ... AF92: =SUM(AF84:AF91) -> 14 | AG92: =SUM(B92:AF92) -> 486
A94: Merch Units Sold (Gross)
A95: Merch Units | B95: ='DTC US&CA - P&L'!B63+'DTC EU - P&L'!B63 -> 0 | C95: ='DTC US&CA - P&L'!C63+'DTC EU - P&L'!C63 -> 0 | D95: ='DTC US&CA - P&L'!D63+'DTC EU - P&L'!D63 -> 0 | E95: ='DTC US&CA - P&L'!E63+'DTC EU - P&L'!E63 -> 0 | F95: ='DTC US&CA - P&L'!F63+'DTC EU - P&L'!F63 -> 0 | G95: ='DTC US&CA - P&L'!G63+'DTC EU - P&L'!G63 -> 0 | H95: ='DTC US&CA - P&L'!H63+'DTC EU - P&L'!H63 -> 0 | I95: ='DTC US&CA - P&L'!I63+'DTC EU - P&L'!I63 -> 0 | ... AF95: ='DTC US&CA - P&L'!AF63+'DTC EU - P&L'!AF63 -> 0 | AG95: =SUM(B95:AF95) -> 8
A97: First-time Customers
A98: SKU 1 - Blue | B98: =B57-B126 -> 42 | C98: =C57-C126 -> 42 | D98: =D57-D126 -> 32 | E98: =E57-E126 -> 19 | F98: =F57-F126 -> 19 | G98: =G57-G126 -> 17 | H98: =H57-H126 -> 21 | I98: =I57-I126 -> 21 | ... AF98: =AF57-AF126 -> 13 | AG98: =SUM(B98:AF98) -> 463
A99: SKU 2 - Yellow | B99: =B58-B127 -> 0 | C99: =C58-C127 -> 0 | D99: =D58-D127 -> 0 | E99: =E58-E127 -> 0 | F99: =F58-F127 -> 0 | G99: =G58-G127 -> 0 | H99: =H58-H127 -> 0 | I99: =I58-I127 -> 0 | ... AF99: =AF58-AF127 -> 0 | AG99: =SUM(B99:AF99) -> 0
A100: SKU 3 - Blue w/ Solar | B100: =B59-B128 -> 0 | C100: =C59-C128 -> 0 | D100: =D59-D128 -> 0 | E100: =E59-E128 -> 0 | F100: =F59-F128 -> 0 | G100: =G59-G128 -> 0 | H100: =H59-H128 -> 0 | I100: =I59-I128 -> 0 | ... AF100: =AF59-AF128 -> 0 | AG100: =SUM(B100:AF100) -> 136
A101: SKU 4 - Yellow w/ Solar | B101: =B60-B129 -> 5 | C101: =C60-C129 -> 7 | D101: =D60-D129 -> 7 | E101: =E60-E129 -> 9 | F101: =F60-F129 -> 9 | G101: =G60-G129 -> 5 | H101: =H60-H129 -> 3 | I101: =I60-I129 -> 4 | ... AF101: =AF60-AF129 -> 30 | AG101: =SUM(B101:AF101) -> 305
A102: SKU 1 - Blue PRO | B102: =B61-B130 -> 1 | C102: =C61-C130 -> 0 | D102: =D61-D130 -> 1 | E102: =E61-E130 -> 1 | F102: =F61-F130 -> 9 | G102: =G61-G130 -> 7 | H102: =H61-H130 -> 17 | I102: =I61-I130 -> 11 | ... AF102: =AF61-AF130 -> 20 | AG102: =SUM(B102:AF102) -> 249
A103: SKU 2 - Yellow PRO | B103: =B62-B131 -> 0 | C103: =C62-C131 -> 0 | D103: =D62-D131 -> 0 | E103: =E62-E131 -> 0 | F103: =F62-F131 -> 0 | G103: =G62-G131 -> 0 | H103: =H62-H131 -> 0 | I103: =I62-I131 -> 0 | ... AF103: =AF62-AF131 -> 0 | AG103: =SUM(B103:AF103) -> 0
A104: SKU 3 - Blue w/ Solar PRO | B104: =B63-B132 -> 3 | C104: =C63-C132 -> 1 | D104: =D63-D132 -> 11 | E104: =E63-E132 -> 29 | F104: =F63-F132 -> 25 | G104: =G63-G132 -> 27 | H104: =H63-H132 -> 24 | I104: =I63-I132 -> 34 | ... AF104: =AF63-AF132 -> 53 | AG104: =SUM(B104:AF104) -> 1264
A105: SKU 4 - Yellow w/ Solar PRO | B105: =B64-B133 -> 0 | C105: =C64-C133 -> 0 | D105: =D64-D133 -> 0 | E105: =E64-E133 -> 0 | F105: =F64-F133 -> 0 | G105: =G64-G133 -> 0 | H105: =H64-H133 -> 0 | I105: =I64-I133 -> 0 | ... AF105: =AF64-AF133 -> 0 | AG105: =SUM(B105:AF105) -> 0
A106: SUM (SKU 1 - SKU 4) | B106: =SUM(B98:B105) -> 51 | C106: =SUM(C98:C105) -> 50 | D106: =SUM(D98:D105) -> 51 | E106: =SUM(E98:E105) -> 58 | F106: =SUM(F98:F105) -> 62 | G106: =SUM(G98:G105) -> 56 | H106: =SUM(H98:H105) -> 65 | I106: =SUM(I98:I105) -> 70 | ... AF106: =SUM(AF98:AF105) -> 116 | AG106: =SUM(B106:AF106) -> 2417
A108: SKU 5 - HBF | B108: =B67-B136 -> 0 | C108: =C67-C136 -> 0 | D108: =D67-D136 -> 0 | E108: =E67-E136 -> 0 | F108: =F67-F136 -> 0 | G108: =G67-G136 -> 0 | H108: =H67-H136 -> 0 | I108: =I67-I136 -> 0 | ... AF108: =AF67-AF136 -> 0 | AG108: =SUM(B108:AF108) -> 0
A109: SKU 6 - HBF w/ Solar | B109: =B68-B137 -> 0 | C109: =C68-C137 -> 0 | D109: =D68-D137 -> 0 | E109: =E68-E137 -> 0 | F109: =F68-F137 -> 0 | G109: =G68-G137 -> 0 | H109: =H68-H137 -> 0 | I109: =I68-I137 -> 0 | ... AF109: =AF68-AF137 -> 0 | AG109: =SUM(B109:AF109) -> 0
A110: SUM (SKU 5 - SKU 6) | B110: =SUM(B108:B109) -> 0 | C110: =SUM(C108:C109) -> 0 | D110: =SUM(D108:D109) -> 0 | E110: =SUM(E108:E109) -> 0 | F110: =SUM(F108:F109) -> 0 | G110: =SUM(G108:G109) -> 0 | H110: =SUM(H108:H109) -> 0 | I110: =SUM(I108:I109) -> 0 | ... AF110: =SUM(AF108:AF109) -> 0 | AG110: =SUM(B110:AF110) -> 0
A112: Wall Mount | B112: =B71-B140 -> 17 | C112: =C71-C140 -> 24 | D112: =D71-D140 -> 15 | E112: =E71-E140 -> 21 | F112: =F71-F140 -> 27 | G112: =G71-G140 -> 12 | H112: =H71-H140 -> 13 | I112: =I71-I140 -> 13 | ... AF112: =AF71-AF140 -> 12 | AG112: =SUM(B112:AF112) -> 601
A113: Suet Ball Holder | B113: =B72-B141 -> 14 | C113: =C72-C141 -> 11 | D113: =D72-D141 -> 16 | E113: =E72-E141 -> 18 | F113: =F72-F141 -> 21 | G113: =G72-G141 -> 7 | H113: =H72-H141 -> 12 | I113: =I72-I141 -> 18 | ... AF113: =AF72-AF141 -> 79 | AG113: =SUM(B113:AF113) -> 1060
A114: 3-in-1 Nutrition Set - Blue | B114: =B73-B142 -> 14 | C114: =C73-C142 -> 4 | D114: =D73-D142 -> 12 | E114: =E73-E142 -> 16 | F114: =F73-F142 -> 15 | G114: =G73-G142 -> 7 | H114: =H73-H142 -> 12 | I114: =I73-I142 -> 6 | ... AF114: =AF73-AF142 -> 2 | AG114: =SUM(B114:AF114) -> 464
A115: 3-in-1 Nutrition Set - Yellow | B115: =B74-B143 -> 2 | C115: =C74-C143 -> 1 | D115: =D74-D143 -> 0 | E115: =E74-E143 -> 6 | F115: =F74-F143 -> 2 | G115: =G74-G143 -> 1 | H115: =H74-H143 -> 0 | I115: =I74-I143 -> 1 | ... AF115: =AF74-AF143 -> 3 | AG115: =SUM(B115:AF115) -> 58
A116: Solar Roof Single - Blue | B116: =B75-B144 -> 79 | C116: =C75-C144 -> 66 | D116: =D75-D144 -> 51 | E116: =E75-E144 -> 34 | F116: =F75-F144 -> 45 | G116: =G75-G144 -> 37 | H116: =H75-H144 -> 26 | I116: =I75-I144 -> 25 | ... AF116: =AF75-AF144 -> 15 | AG116: =SUM(B116:AF116) -> 809
...

Sheet DTC US&CA - P&L
A1: JANUARY | B1: 45658 | C1: 45659 | D1: 45660 | E1: 45661 | F1: 45662 | G1: 45663 | H1: 45664 | I1: 45665 | J1: 45666 | K1: 45667 | L1: 45668 | M1: 45669 | N1: 45670 | O1: 45671 | P1: 45672 | Q1: 45673 | R1: 45674 | S1: 45675 | T1: 45676 | U1: 45677 | V1: 45678 | W1: 45679 | X1: 45680 | Y1: 45681 | Z1: 45682 | AA1: 45683 | AB1: 45684 | AC1: 45685 | AD1: 45686 | AE1: 45687 | AF1: 45688
A2: DAY | B2: WED | C2: THU | D2: FRI | E2: SAT | F2: SUN | G2: MON | H2: TUE | I2: WED | J2: THU | K2: FRI | L2: SAT | M2: SUN | N2: MON | O2: TUE | P2: WED | Q2: THU | R2: FRI | S2: SAT | T2: SUN | U2: MON | V2: TUE | W2: WED | X2: THU | Y2: FRI | Z2: SAT | AA2: SUN | AB2: MON | AC2: TUE | AD2: WED | AE2: THU | AF2: FRI
A4: Revenue
A5: Revenue Woocommerce (Platform) | B5: =Summary!B10+Summary!B25 -> 132546.38 | C5: =Summary!C10+Summary!C25 -> 146258.76 | D5: =Summary!D10+Summary!D25 -> 146701.24 | E5: =Summary!E10+Summary!E25 -> 97267.91 | F5: =Summary!F10+Summary!F25 -> 99876.6 | G5: =Summary!G10+Summary!G25 -> 84500.46 | H5: =Summary!H10+Summary!H25 -> 85058.37 | I5: =Summary!I10+Summary!I25 -> 82385.06 | ... AF5: =Summary!AF10+Summary!AF25 -> 38839.58 | AG5: =SUM(B5:AF5) -> 2206917.3
A6: Revenue w/o renewals | B6: 29485.61 | C6: 24511.84 | D6: 25173.96 | E6: 30367.82 | F6: 31799.77 | G6: 24082.55 | H6: 24621.17 | I6: 27110.02 | J6: 27116.1 | K6: 26159.97 | L6: 36501.67 | M6: 35241.49 | N6: 20682.52 | O6: 24504.2 | P6: 17303.63 | Q6: 15406.99 | R6: 21226.42 | S6: 30312.73 | T6: 28726.92 | U6: 25841.5 | V6: 27741.67 | W6: 29196.67 | X6: 39397.46 | Y6: 37662 | Z6: 37828.24 | AA6: 47102.89 | AB6: 35699.31 | AC6: 42729.55 | AD6: 37147.37 | AE6: 40358.76 | AF6: 35451.44 | AG6: =SUM(B6:AF6) -> 936492.24
A7: SUM | B7: =SUM(B5) -> 132546.38 | C7: =SUM(C5) -> 146258.76 | D7: =SUM(D5) -> 146701.24 | E7: =SUM(E5) -> 97267.91 | F7: =SUM(F5) -> 99876.6 | G7: =SUM(G5) -> 84500.46 | H7: =SUM(H5) -> 85058.37 | I7: =SUM(I5) -> 82385.06 | ... AF7: =SUM(AF5) -> 38839.58 | AG7: =SUM(B7:AF7) -> 2206917.3
A9: Orders
A10: Orders Woocommerce (Platform) | B10: =Summary!B83 -> 1379 | C10: =Summary!C83 -> 1547 | D10: =Summary!D83 -> 1538 | E10: =Summary!E83 -> 953 | F10: =Summary!F83 -> 1005 | G10: =Summary!G83 -> 825 | H10: =Summary!H83 -> 820 | I10: =Summary!I83 -> 766 | ... AF10: =Summary!AF83 -> 203 | AG10: =SUM(B10:AF10) -> 19333
A11: Orders w/o renewals | B11: 251 | C11: 211 | D11: 205 | E11: 218 | F11: 261 | G11: 163 | H11: 158 | I11: 159 | J11: 174 | K11: 200 | L11: 171 | M11: 206 | N11: 123 | O11: 145 | P11: 92 | Q11: 101 | R11: 118 | S11: 158 | T11: 158 | U11: 136 | V11: 136 | W11: 142 | X11: 175 | Y11: 162 | Z11: 183 | AA11: 232 | AB11: 173 | AC11: 202 | AD11: 178 | AE11: 184 | AF11: 159 | AG11: =SUM(B11:AF11) -> 5334
A12: SUM | B12: =SUM(B10) -> 1379 | C12: =SUM(C10) -> 1547 | D12: =SUM(D10) -> 1538 | E12: =SUM(E10) -> 953 | F12: =SUM(F10) -> 1005 | G12: =SUM(G10) -> 825 | H12: =SUM(H10) -> 820 | I12: =SUM(I10) -> 766 | ... AF12: =SUM(AF10) -> 203 | AG12: =SUM(B12:AF12) -> 19333
A14: Breakdown
A15: - Hardware | B15: =Summary!B11 -> 12382.12 | C15: =Summary!C11 -> 11605 | D15: =Summary!D11 -> 12358.05 | E15: =Summary!E11 -> 17039.5 | F15: =Summary!F11 -> 16960.2 | G15: =Summary!G11 -> 14331.3 | H15: =Summary!H11 -> 15021 | I15: =Summary!I11 -> 17465.6 | ... AF15: =Summary!AF11 -> 26643.65 | AG15: =SUM(B15:AF15) -> 596377.02
A16: - Add-ons | B16: =Summary!B12 -> 11484.08 | C16: =Summary!C12 -> 8466.2 | D16: =Summary!D12 -> 8023.15 | E16: =Summary!E12 -> 7842.2 | F16: =Summary!F12 -> 9018.4 | G16: =Summary!G12 -> 5711.4 | H16: =Summary!H12 -> 5676 | I16: =Summary!I12 -> 5167.6 | ... AF16: =Summary!AF12 -> 3031 | AG16: =SUM(B16:AF16) -> 183624.68
A17: - Merch | B17: =Summary!B13 -> 0 | C17: =Summary!C13 -> 0 | D17: =Summary!D13 -> 0 | E17: =Summary!E13 -> 0 | F17: =Summary!F13 -> 0 | G17: =Summary!G13 -> 0 | H17: =Summary!H13 -> 0 | I17: =Summary!I13 -> 0 | ... AF17: =Summary!AF13 -> 0 | AG17: =SUM(B17:AF17) -> 299.91
A18: - Seeds | B18: =Summary!B14 -> 657 | C18: =Summary!C14 -> 454.4 | D18: =Summary!D14 -> 756.5 | E18: =Summary!E14 -> 596.9 | F18: =Summary!F14 -> 586.1 | G18: =Summary!G14 -> 335.6 | H18: =Summary!H14 -> 409.5 | I18: =Summary!I14 -> 331.8 | ... AF18: =Summary!AF14 -> 432.6 | AG18: =SUM(B18:AF18) -> 14921.9
A19: - Yearly Pro Subscription | B19: =Summary!B25 -> 100033.13 | C19: =Summary!C25 -> 118465.39 | D19: =Summary!D25 -> 117907.14 | E19: =Summary!E25 -> 65256.05 | F19: =Summary!F25 -> 66072.06 | G19: =Summary!G25 -> 58560.98 | H19: =Summary!H25 -> 58317.96 | I19: =Summary!I25 -> 53727.14 | ... AF19: =Summary!AF25 -> 2977.07 | AG19: =SUM(B19:AF19) -> 1229496.1
A20: - Taxes | B20: =Summary!B15 -> 4928.35 | C20: =Summary!C15 -> 4728.89 | D20: =Summary!D15 -> 5167.52 | E20: =Summary!E15 -> 3607.16 | F20: =Summary!F15 -> 3951.86 | G20: =Summary!G15 -> 3241.54 | H20: =Summary!H15 -> 3330.51 | I20: =Summary!I15 -> 3154.94 | ... AF20: =Summary!AF15 -> 2286.52 | AG20: =SUM(B20:AF20) -> 93603.34
A21: - Shipping | B21: =Summary!B16 -> 3061.7 | C21: =Summary!C16 -> 2538.88 | D21: =Summary!D16 -> 2488.88 | E21: =Summary!E16 -> 2926.1 | F21: =Summary!F16 -> 3287.98 | G21: =Summary!G16 -> 2319.64 | H21: =Summary!H16 -> 2303.4 | I21: =Summary!I16 -> 2537.98 | ... AF21: =Summary!AF16 -> 3468.74 | AG21: =SUM(B21:AF21) -> 88594.42
A22: SUM | B22: =SUM(B15:B21) -> 132546.38 | C22: =SUM(C15:C21) -> 146258.76 | D22: =SUM(D15:D21) -> 146701.24 | E22: =SUM(E15:E21) -> 97267.91 | F22: =SUM(F15:F21) -> 99876.6 | G22: =SUM(G15:G21) -> 84500.46 | H22: =SUM(H15:H21) -> 85058.37 | I22: =SUM(I15:I21) -> 82385.06 | ... AF22: =SUM(AF15:AF21) -> 38839.58 | AG22: =SUM(B22:AF22) -> 2206917.3
A24: Units Sold (Gross)
A25: SKU 1 - Blue | B25: 48 | C25: 44 | D25: 34 | E25: 19 | F25: 23 | G25: 18 | H25: 21 | I25: 21 | J25: 29 | K25: 23 | L25: 22 | M25: 17 | N25: 11 | O25: 10 | P25: 10 | Q25: 6 | R25: 6 | S25: 6 | T25: 5 | U25: 5 | V25: 4 | W25: 10 | X25: 6 | Y25: 4 | Z25: 0 | AA25: 8 | AB25: 12 | AC25: 21 | AD25: 15 | AE25: 16 | AF25: 12 | AG25: =SUM(B25:AF25) -> 486
A26: SKU 2 - Yellow | B26: 0 | C26: 0 | D26: 0 | E26: 0 | F26: 0 | G26: 0 | H26: 0 | I26: 0 | J26: 0 | K26: 0 | L26: 0 | M26: 0 | N26: 0 | O26: 0 | P26: 0 | Q26: 0 | R26: 0 | S26: 0 | T26: 0 | U26: 0 | V26: 0 | W26: 0 | X26: 0 | Y26: 0 | Z26: 0 | AA26: 0 | AB26: 0 | AC26: 0 | AD26: 0 | AE26: 0 | AF26: 0 | AG26: =SUM(B26:AF26) -> 0
A27: SKU 3 - Blue w/ Solar | B27: 0 | C27: 0 | D27: 0 | E27: 0 | F27: 0 | G27: 0 | H27: 0 | I27: 0 | J27: 0 | K27: 0 | L27: 0 | M27: 0 | N27: 5 | O27: 7 | P27: 5 | Q27: 6 | R27: 3 | S27: 3 | T27: 8 | U27: 4 | V27: 4 | W27: 7 | X27: 21 | Y27: 12 | Z27: 25 | AA27: 18 | AB27: 18 | AC27: 0 | AD27: 0 | AE27: 0 | AF27: 0 | AG27: =SUM(B27:AF27) -> 146
A28: SKU 4 - Yellow w/ Solar | B28: 7 | C28: 8 | D28: 7 | E28: 12 | F28: 9 | G28: 6 | H28: 4 | I28: 4 | J28: 6 | K28: 8 | L28: 9 | M28: 11 | N28: 4 | O28: 9 | P28: 8 | Q28: 4 | R28: 2 | S28: 3 | T28: 2 | U28: 2 | V28: 5 | W28: 9 | X28: 11 | Y28: 14 | Z28: 7 | AA28: 9 | AB28: 16 | AC28: 38 | AD28: 28 | AE28: 41 | AF28: 31 | AG28: =SUM(B28:AF28) -> 334
A29: SKU 1 - Blue PRO | B29: 0 | C29: 0 | D29: 1 | E29: 3 | F29: 11 | G29: 7 | H29: 13 | I29: 9 | J29: 5 | K29: 6 | L29: 6 | M29: 9 | N29: 5 | O29: 6 | P29: 3 | Q29: 4 | R29: 2 | S29: 2 | T29: 4 | U29: 3 | V29: 3 | W29: 5 | X29: 8 | Y29: 9 | Z29: 9 | AA29: 15 | AB29: 8 | AC29: 18 | AD29: 10 | AE29: 18 | AF29: 19 | AG29: =SUM(B29:AF29) -> 221
A30: SKU 2 - Yellow PRO | B30: 0 | C30: 0 | D30: 0 | E30: 0 | F30: 0 | G30: 0 | H30: 0 | I30: 0 | J30: 0 | K30: 0 | L30: 0 | M30: 0 | N30: 0 | O30: 0 | P30: 0 | Q30: 0 | R30: 0 | S30: 0 | T30: 0 | U30: 0 | V30: 0 | W30: 0 | X30: 0 | Y30: 0 | Z30: 0 | AA30: 0 | AB30: 0 | AC30: 0 | AD30: 0 | AE30: 0 | AF30: 0 | AG30: =SUM(B30:AF30) -> 0
A31: SKU 3 - Blue w/ Solar PRO | B31: 1 | C31: 0 | D31: 10 | E31: 31 | F31: 24 | G31: 25 | H31: 22 | I31: 33 | J31: 23 | K31: 22 | L31: 56 | M31: 43 | N31: 24 | O31: 27 | P31: 18 | Q31: 16 | R31: 42 | S31: 66 | T31: 53 | U31: 57 | V31: 61 | W31: 51 | X31: 69 | Y31: 67 | Z31: 63 | AA31: 80 | AB31: 57 | AC31: 66 | AD31: 66 | AE31: 63 | AF31: 60 | AG31: =SUM(B31:AF31) -> 1296
A32: SKU 4 - Yellow w/ Solar PRO | B32: 0 | C32: 0 | D32: 0 | E32: 0 | F32: 0 | G32: 0 | H32: 0 | I32: 0 | J32: 0 | K32: 0 | L32: 0 | M32: 0 | N32: 0 | O32: 0 | P32: 0 | Q32: 0 | R32: 0 | S32: 0 | T32: 0 | U32: 0 | V32: 0 | W32: 0 | X32: 0 | Y32: 0 | Z32: 0 | AA32: 0 | AB32: 0 | AC32: 0 | AD32: 0 | AE32: 0 | AF32: 0 | AG32: =SUM(B32:AF32) -> 0
A33: SUM (SKU 1 - SKU 4) | B33: =SUM(B25:B32) -> 56 | C33: =SUM(C25:C32) -> 52 | D33: =SUM(D25:D32) -> 52 | E33: =SUM(E25:E32) -> 65 | F33: =SUM(F25:F32) -> 67 | G33: =SUM(G25:G32) -> 56 | H33: =SUM(H25:H32) -> 60 | I33: =SUM(I25:I32) -> 67 | ... AF33: =SUM(AF25:AF32) -> 122 | AG33: =SUM(B33:AF33) -> 2483
A35: SKU 5 - HBF | B35: 0 | C35: 0 | D35: 0 | E35: 0 | F35: 0 | G35: 0 | H35: 0 | I35: 0 | J35: 0 | K35: 0 | L35: 0 | M35: 0 | N35: 0 | O35: 0 | P35: 0 | Q35: 0 | R35: 0 | S35: 0 | T35: 0 | U35: 0 | V35: 0 | W35: 0 | X35: 0 | Y35: 0 | Z35: 0 | AA35: 0 | AB35: 0 | AC35: 0 | AD35: 0 | AE35: 0 | AF35: 0 | AG35: =SUM(B35:AF35) -> 0
A36: SKU 6 - HBF w/ Solar | B36: 0 | C36: 0 | D36: 0 | E36: 0 | F36: 0 | G36: 0 | H36: 0 | I36: 0 | J36: 0 | K36: 0 | L36: 0 | M36: 0 | N36: 0 | O36: 0 | P36: 0 | Q36: 0 | R36: 0 | S36: 0 | T36: 0 | U36: 0 | V36: 0 | W36: 0 | X36: 0 | Y36: 0 | Z36: 0 | AA36: 0 | AB36: 0 | AC36: 0 | AD36: 0 | AE36: 0 | AF36: 0 | AG36: =SUM(B36:AF36) -> 0
A37: SUM (SKU 5 - SKU 6) | B37: =SUM(B35:B36) -> 0 | C37: =SUM(C35:C36) -> 0 | D37: =SUM(D35:D36) -> 0 | E37: =SUM(E35:E36) -> 0 | F37: =SUM(F35:F36) -> 0 | G37: =SUM(G35:G36) -> 0 | H37: =SUM(H35:H36) -> 0 | I37: =SUM(I35:I36) -> 0 | ... AF37: =SUM(AF35:AF36) -> 0 | AG37: =SUM(B37:AF37) -> 0
A39: Wall Mount | B39: 23 | C39: 31 | D39: 17 | E39: 26 | F39: 31 | G39: 12 | H39: 12 | I39: 12 | J39: 16 | K39: 17 | L39: 13 | M39: 21 | N39: 14 | O39: 17 | P39: 9 | Q39: 7 | R39: 6 | S39: 14 | T39: 16 | U39: 11 | V39: 11 | W39: 21 | X39: 45 | Y39: 47 | Z39: 44 | AA39: 51 | AB39: 22 | AC39: 18 | AD39: 16 | AE39: 15 | AF39: 13 | AG39: =SUM(B39:AF39) -> 628
A40: Suet Ball Holder | B40: 20 | C40: 18 | D40: 14 | E40: 19 | F40: 23 | G40: 11 | H40: 16 | I40: 19 | J40: 12 | K40: 20 | L40: 10 | M40: 19 | N40: 14 | O40: 9 | P40: 5 | Q40: 13 | R40: 8 | S40: 21 | T40: 12 | U40: 26 | V40: 11 | W40: 15 | X40: 68 | Y40: 89 | Z40: 84 | AA40: 111 | AB40: 86 | AC40: 112 | AD40: 95 | AE40: 105 | AF40: 85 | AG40: =SUM(B40:AF40) -> 1170
A41: 3-in-1 Nutrition Set - Blue | B41: 19 | C41: 5 | D41: 12 | E41: 21 | F41: 19 | G41: 7 | H41: 14 | I41: 7 | J41: 17 | K41: 12 | L41: 16 | M41: 19 | N41: 10 | O41: 17 | P41: 7 | Q41: 4 | R41: 5 | S41: 12 | T41: 10 | U41: 16 | V41: 3 | W41: 19 | X41: 40 | Y41: 45 | Z41: 45 | AA41: 51 | AB41: 21 | AC41: 14 | AD41: 10 | AE41: 9 | AF41: 3 | AG41: =SUM(B41:AF41) -> 509
A42: 3-in-1 Nutrition Set - Yellow | B42: 2 | C42: 1 | D42: 1 | E42: 8 | F42: 4 | G42: 2 | H42: 0 | I42: 1 | J42: 0 | K42: 3 | L42: 0 | M42: 4 | N42: 2 | O42: 2 | P42: 3 | Q42: 1 | R42: 2 | S42: 1 | T42: 2 | U42: 2 | V42: 3 | W42: 5 | X42: 5 | Y42: 1 | Z42: 5 | AA42: 5 | AB42: 3 | AC42: 2 | AD42: 2 | AE42: 3 | AF42: 3 | AG42: =SUM(B42:AF42) -> 78
A43: Solar Roof Single - Blue | B43: 91 | C43: 71 | D43: 56 | E43: 36 | F43: 54 | G43: 43 | H43: 30 | I43: 29 | J43: 47 | K43: 34 | L43: 35 | M43: 49 | N43: 25 | O43: 29 | P43: 15 | Q43: 17 | R43: 19 | S43: 22 | T43: 23 | U43: 11 | V43: 15 | W43: 15 | X43: 7 | Y43: 13 | Z43: 21 | AA43: 21 | AB43: 19 | AC43: 26 | AD43: 26 | AE43: 19 | AF43: 17 | AG43: =SUM(B43:AF43) -> 935
A44: Solar Roof Single - Yellow | B44: 2 | C44: 1 | D44: 1 | E44: 4 | F44: 0 | G44: 1 | H44: 1 | I44: 0 | J44: 0 | K44: 1 | L44: 3 | M44: 2 | N44: 0 | O44: 0 | P44: 1 | Q44: 1 | R44: 2 | S44: 1 | T44: 2 | U44: 0 | V44: 1 | W44: 1 | X44: 2 | Y44: 1 | Z44: 2 | AA44: 2 | AB44: 2 | AC44: 2 | AD44: 2 | AE44: 1 | AF44: 0 | AG44: =SUM(B44:AF44) -> 39
A45: Perch Extender - Blue | B45: 93 | C45: 70 | D45: 80 | E45: 81 | F45: 102 | G45: 59 | H45: 63 | I45: 69 | J45: 73 | K45: 70 | L45: 50 | M45: 77 | N45: 48 | O45: 51 | P45: 27 | Q45: 37 | R45: 30 | S45: 50 | T45: 57 | U45: 52 | V45: 34 | W45: 54 | X45: 73 | Y45: 77 | Z45: 96 | AA45: 113 | AB45: 58 | AC45: 36 | AD45: 54 | AE45: 33 | AF45: 33 | AG45: =SUM(B45:AF45) -> 1900
A46: Perch Extender - Yellow | B46: 16 | C46: 10 | D46: 13 | E46: 17 | F46: 10 | G46: 6 | H46: 8 | I46: 9 | J46: 6 | K46: 14 | L46: 11 | M46: 19 | N46: 7 | O46: 10 | P46: 8 | Q46: 7 | R46: 7 | S46: 11 | T46: 9 | U46: 3 | V46: 9 | W46: 10 | X46: 8 | Y46: 8 | Z46: 7 | AA46: 12 | AB46: 6 | AC46: 13 | AD46: 5 | AE46: 11 | AF46: 10 | AG46: =SUM(B46:AF46) -> 300
A47: Solar Roof (HBF) | B47: 3 | C47: 1 | D47: 1 | E47: 2 | F47: 0 | G47: 1 | H47: 0 | I47: 1 | J47: 1 | K47: 0 | L47: 1 | M47: 2 | N47: 1 | O47: 1 | P47: 0 | Q47: 0 | R47: 1 | S47: 0 | T47: 1 | U47: 0 | V47: 0 | W47: 0 | X47: 2 | Y47: 0 | Z47: 0 | AA47: 0 | AB47: 1 | AC47: 1 | AD47: 0 | AE47: 1 | AF47: 0 | AG47: =SUM(B47:AF47) -> 22
A48: Housing - only (HBF) | B48: 0 | C48: 0 | D48: 0 | E48: 0 | F48: 0 | G48: 0 | H48: 0 | I48: 0 | J48: 0 | K48: 0 | L48: 0 | M48: 0 | N48: 0 | O48: 0 | P48: 0 | Q48: 0 | R48: 0 | S48: 0 | T48: 0 | U48: 0 | V48: 0 | W48: 0 | X48: 0 | Y48: 0 | Z48: 0 | AA48: 0 | AB48: 0 | AC48: 0 | AD48: 0 | AE48: 0 | AF48: 0 | AG48: =SUM(B48:AF48) -> 0
A49: Nature Cam PRO | B49: 6 | C49: 2 | D49: 5 | E49: 3 | F49: 3 | G49: 2 | H49: 4 | I49: 1 | J49: 5 | K49: 9 | L49: 4 | M49: 4 | N49: 1 | O49: 2 | P49: 1 | Q49: 1 | R49: 2 | S49: 3 | T49: 3 | U49: 1 | V49: 3 | W49: 1 | X49: 2 | Y49: 5 | Z49: 1 | AA49: 4 | AB49: 6 | AC49: 5 | AD49: 2 | AE49: 4 | AF49: 1 | AG49: =SUM(B49:AF49) -> 96
A50: SUM (Add-ons) | B50: =SUM(B39:B49) -> 275 | C50: =SUM(C39:C49) -> 210 | D50: =SUM(D39:D49) -> 200 | E50: =SUM(E39:E49) -> 217 | F50: =SUM(F39:F49) -> 246 | G50: =SUM(G39:G49) -> 144 | H50: =SUM(H39:H49) -> 148 | I50: =SUM(I39:I49) -> 148 | ... AF50: =SUM(AF39:AF49) -> 165 | AG50: =SUM(B50:AF50) -> 5677
A52: Seasonal Curation - 8lb | B52: 15 | C52: 14 | D52: 24 | E52: 11 | F52: 15 | G52: 9 | H52: 10 | I52: 7 | J52: 15 | K52: 14 | L52: 13 | M52: 9 | N52: 2 | O52: 15 | P52: 12 | Q52: 16 | R52: 15 | S52: 10 | T52: 6 | U52: 9 | V52: 12 | W52: 9 | X52: 6 | Y52: 10 | Z52: 10 | AA52: 9 | AB52: 10 | AC52: 8 | AD52: 6 | AE52: 6 | AF52: 11 | AG52: =SUM(B52:AF52) -> 338
A53: Seasonal Curation - 20lb | B53: 1 | C53: 0 | D53: 0 | E53: 2 | F53: 0 | G53: 0 | H53: 1 | I53: 0 | J53: 3 | K53: 1 | L53: 1 | M53: 2 | N53: 2 | O53: 0 | P53: 3 | Q53: 0 | R53: 1 | S53: 2 | T53: 1 | U53: 0 | V53: 0 | W53: 0 | X53: 2 | Y53: 0 | Z53: 1 | AA53: 3 | AB53: 1 | AC53: 0 | AD53: 2 | AE53: 1 | AF53: 1 | AG53: =SUM(B53:AF53) -> 31
A54: Buddy Bites - 8lb | B54: 0 | C54: 1 | D54: 0 | E54: 1 | F54: 0 | G54: 1 | H54: 0 | I54: 0 | J54: 1 | K54: 1 | L54: 1 | M54: 0 | N54: 1 | O54: 1 | P54: 0 | Q54: 1 | R54: 1 | S54: 2 | T54: 1 | U54: 0 | V54: 1 | W54: 0 | X54: 1 | Y54: 2 | Z54: 1 | AA54: 0 | AB54: 2 | AC54: 1 | AD54: 2 | AE54: 1 | AF54: 0 | AG54: =SUM(B54:AF54) -> 24
A55: Buddy Bites - 20lb | B55: =Summary!B87-B52-B53-B54-B56-B57-B58-B59 -> 3 | C55: =Summary!C87-C52-C53-C54-C56-C57-C58-C59 -> 0 | D55: =Summary!D87-D52-D53-D54-D56-D57-D58-D59 -> 1 | E55: =Summary!E87-E52-E53-E54-E56-E57-E58-E59 -> 0 | F55: =Summary!F87-F52-F53-F54-F56-F57-F58-F59 -> 2 | G55: =Summary!G87-G52-G53-G54-G56-G57-G58-G59 -> 0 | H55: =Summary!H87-H52-H53-H54-H56-H57-H58-H59 -> 1 | I55: =Summary!I87-I52-I53-I54-I56-I57-I58-I59 -> 1 | ... AF55: =Summary!AF87-AF52-AF53-AF54-AF56-AF57-AF58-AF59 -> 0 | AG55: =SUM(B55:AF55) -> 17
A56: Snack n' Soar - 8lb | B56: 0 | C56: 1 | D56: 0 | E56: 4 | F56: 0 | G56: 1 | H56: 1 | I56: 0 | J56: 3 | K56: 1 | L56: 1 | M56: 0 | N56: 2 | O56: 0 | P56: 1 | Q56: 1 | R56: 2 | S56: 0 | T56: 1 | U56: 1 | V56: 3 | W56: 0 | X56: 0 | Y56: 2 | Z56: 0 | AA56: 1 | AB56: 0 | AC56: 1 | AD56: 2 | AE56: 2 | AF56: 0 | AG56: =SUM(B56:AF56) -> 31
A57: Snack n' Soar - 20lb | B57: 0 | C57: 0 | D57: 0 | E57: 0 | F57: 0 | G57: 0 | H57: 0 | I57: 0 | J57: 0 | K57: 1 | L57: 0 | M57: 0 | N57: 0 | O57: 0 | P57: 0 | Q57: 0 | R57: 0 | S57: 0 | T57: 0 | U57: 0 | V57: 2 | W57: 1 | X57: 0 | Y57: 0 | Z57: 1 | AA57: 0 | AB57: 0 | AC57: 0 | AD57: 0 | AE57: 0 | AF57: 1 | AG57: =SUM(B57:AF57) -> 6
A58: Avian Choice - 8lb | B58: 1 | C58: 0 | D58: 0 | E58: 2 | F58: 2 | G58: 1 | H58: 0 | I58: 4 | J58: 1 | K58: 0 | L58: 1 | M58: 2 | N58: 0 | O58: 1 | P58: 1 | Q58: 1 | R58: 1 | S58: 1 | T58: 2 | U58: 0 | V58: 1 | W58: 0 | X58: 1 | Y58: 1 | Z58: 0 | AA58: 1 | AB58: 3 | AC58: 1 | AD58: 2 | AE58: 0 | AF58: 1 | AG58: =SUM(B58:AF58) -> 32
A59: Avian Choice - 20lb | B59: 0 | C59: 0 | D59: 0 | E59: 0 | F59: 0 | G59: 0 | H59: 0 | I59: 0 | J59: 0 | K59: 0 | L59: 0 | M59: 0 | N59: 1 | O59: 0 | P59: 0 | Q59: 1 | R59: 0 | S59: 1 | T59: 0 | U59: 1 | V59: 0 | W59: 0 | X59: 1 | Y59: 0 | Z59: 1 | AA59: 0 | AB59: 1 | AC59: 0 | AD59: 0 | AE59: 0 | AF59: 0 | AG59: =SUM(B59:AF59) -> 7
A60: SUM (Seeds) | B60: =SUM(B52:B59) -> 20 | C60: =SUM(C52:C59) -> 16 | D60: =SUM(D52:D59) -> 25 | E60: =SUM(E52:E59) -> 20 | F60: =SUM(F52:F59) -> 19 | G60: =SUM(G52:G59) -> 12 | H60: =SUM(H52:H59) -> 13 | I60: =SUM(I52:I59) -> 12 | ... AF60: =SUM(AF52:AF59) -> 14 | AG60: =SUM(B60:AF60) -> 486
A62: Merch Units Sold (Gross)
A63: Merch Units | B63: 0 | C63: 0 | D63: 0 | E63: 0 | F63: 0 | G63: 0 | H63: 0 | I63: 0 | J63: 0 | K63: 1 | L63: 0 | M63: 0 | N63: 1 | O63: 0 | P63: 0 | Q63: 0 | R63: 0 | S63: 1 | T63: 3 | U63: 0 | V63: 0 | W63: 0 | X63: 1 | Y63: 1 | Z63: 0 | AA63: 0 | AB63: 0 | AC63: 0 | AD63: 0 | AE63: 0 | AF63: 0 | AG63: =SUM(B63:AF63) -> 8
A65: First-time Customers
A66: SKU 1 - Blue | B66: =B25-B94 -> 42 | C66: =C25-C94 -> 42 | D66: =D25-D94 -> 32 | E66: =E25-E94 -> 19 | F66: =F25-F94 -> 19 | G66: =G25-G94 -> 17 | H66: =H25-H94 -> 21 | I66: =I25-I94 -> 21 | ... AF66: =AF25-AF94 -> 11 | AG66: =SUM(B66:AF66) -> 451
A67: SKU 2 - Yellow | B67: =B26-B95 -> 0 | C67: =C26-C95 -> 0 | D67: =D26-D95 -> 0 | E67: =E26-E95 -> 0 | F67: =F26-F95 -> 0 | G67: =G26-G95 -> 0 | H67: =H26-H95 -> 0 | I67: =I26-I95 -> 0 | ... AF67: =AF26-AF95 -> 0 | AG67: =SUM(B67:AF67) -> 0
A68: SKU 3 - Blue w/ Solar | B68: =B27-B96 -> 0 | C68: =C27-C96 -> 0 | D68: =D27-D96 -> 0 | E68: =E27-E96 -> 0 | F68: =F27-F96 -> 0 | G68: =G27-G96 -> 0 | H68: =H27-H96 -> 0 | I68: =I27-I96 -> 0 | ... AF68: =AF27-AF96 -> 0 | AG68: =SUM(B68:AF68) -> 136
A69: SKU 4 - Yellow w/ Solar | B69: =B28-B97 -> 5 | C69: =C28-C97 -> 7 | D69: =D28-D97 -> 7 | E69: =E28-E97 -> 9 | F69: =F28-F97 -> 9 | G69: =G28-G97 -> 5 | H69: =H28-H97 -> 3 | I69: =I28-I97 -> 4 | ... AF69: =AF28-AF97 -> 30 | AG69: =SUM(B69:AF69) -> 305
A70: SKU 1 - Blue PRO | B70: =B29-B98 -> 0 | C70: =C29-C98 -> 0 | D70: =D29-D98 -> 1 | E70: =E29-E98 -> 1 | F70: =F29-F98 -> 9 | G70: =G29-G98 -> 7 | H70: =H29-H98 -> 12 | I70: =I29-I98 -> 9 | ... AF70: =AF29-AF98 -> 17 | AG70: =SUM(B70:AF70) -> 203
A71: SKU 2 - Yellow PRO | B71: =B30-B99 -> 0 | C71: =C30-C99 -> 0 | D71: =D30-D99 -> 0 | E71: =E30-E99 -> 0 | F71: =F30-F99 -> 0 | G71: =G30-G99 -> 0 | H71: =H30-H99 -> 0 | I71: =I30-I99 -> 0 | ... AF71: =AF30-AF99 -> 0 | AG71: =SUM(B71:AF71) -> 0
A72: SKU 3 - Blue w/ Solar PRO | B72: =B31-B100 -> 0 | C72: =C31-C100 -> 0 | D72: =D31-D100 -> 9 | E72: =E31-E100 -> 27 | F72: =F31-F100 -> 23 | G72: =G31-G100 -> 22 | H72: =H31-H100 -> 20 | I72: =I31-I100 -> 29 | ... AF72: =AF31-AF100 -> 53 | AG72: =SUM(B72:AF72) -> 1157
A73: SKU 4 - Yellow w/ Solar PRO | B73: =B32-B101 -> 0 | C73: =C32-C101 -> 0 | D73: =D32-D101 -> 0 | E73: =E32-E101 -> 0 | F73: =F32-F101 -> 0 | G73: =G32-G101 -> 0 | H73: =H32-H101 -> 0 | I73: =I32-I101 -> 0 | ... AF73: =AF32-AF101 -> 0 | AG73: =SUM(B73:AF73) -> 0
A74: SUM (SKU 1 - SKU 4) | B74: =SUM(B66:B73) -> 47 | C74: =SUM(C66:C73) -> 49 | D74: =SUM(D66:D73) -> 49 | E74: =SUM(E66:E73) -> 56 | F74: =SUM(F66:F73) -> 60 | G74: =SUM(G66:G73) -> 51 | H74: =SUM(H66:H73) -> 56 | I74: =SUM(I66:I73) -> 63 | ... AF74: =SUM(AF66:AF73) -> 111 | AG74: =SUM(B74:AF74) -> 2252
A76: SKU 5 - HBF | B76: =B35-B104 -> 0 | C76: =C35-C104 -> 0 | D76: =D35-D104 -> 0 | E76: =E35-E104 -> 0 | F76: =F35-F104 -> 0 | G76: =G35-G104 -> 0 | H76: =H35-H104 -> 0 | I76: =I35-I104 -> 0 | ... AF76: =AF35-AF104 -> 0 | AG76: =SUM(B76:AF76) -> 0
A77: SKU 6 - HBF w/ Solar | B77: =B36-B105 -> 0 | C77: =C36-C105 -> 0 | D77: =D36-D105 -> 0 | E77: =E36-E105 -> 0 | F77: =F36-F105 -> 0 | G77: =G36-G105 -> 0 | H77: =H36-H105 -> 0 | I77: =I36-I105 -> 0 | ... AF77: =AF36-AF105 -> 0 | AG77: =SUM(B77:AF77) -> 0
A78: SUM (SKU 5 - SKU 6) | B78: =SUM(B76:B77) -> 0 | C78: =SUM(C76:C77) -> 0 | D78: =SUM(D76:D77) -> 0 | E78: =SUM(E76:E77) -> 0 | F78: =SUM(F76:F77) -> 0 | G78: =SUM(G76:G77) -> 0 | H78: =SUM(H76:H77) -> 0 | I78: =SUM(I76:I77) -> 0 | ... AF78: =SUM(AF76:AF77) -> 0 | AG78: =SUM(B78:AF78) -> 0
A80: Wall Mount | B80: =B39-B108 -> 17 | C80: =C39-C108 -> 23 | D80: =D39-D108 -> 13 | E80: =E39-E108 -> 21 | F80: =F39-F108 -> 27 | G80: =G39-G108 -> 11 | H80: =H39-H108 -> 10 | I80: =I39-I108 -> 12 | ... AF80: =AF39-AF108 -> 11 | AG80: =SUM(B80:AF80) -> 542
A81: Suet Ball Holder | B81: =B40-B109 -> 13 | C81: =C40-C109 -> 10 | D81: =D40-D109 -> 14 | E81: =E40-E109 -> 14 | F81: =F40-F109 -> 21 | G81: =G40-G109 -> 6 | H81: =H40-H109 -> 12 | I81: =I40-I109 -> 18 | ... AF81: =AF40-AF109 -> 77 | AG81: =SUM(B81:AF81) -> 1002
A82: 3-in-1 Nutrition Set - Blue | B82: =B41-B110 -> 14 | C82: =C41-C110 -> 3 | D82: =D41-D110 -> 10 | E82: =E41-E110 -> 15 | F82: =F41-F110 -> 15 | G82: =G41-G110 -> 5 | H82: =H41-H110 -> 12 | I82: =I41-I110 -> 6 | ... AF82: =AF41-AF110 -> 2 | AG82: =SUM(B82:AF82) -> 424
A83: 3-in-1 Nutrition Set - Yellow | B83: =B42-B111 -> 2 | C83: =C42-C111 -> 1 | D83: =D42-D111 -> 0 | E83: =E42-E111 -> 6 | F83: =F42-F111 -> 2 | G83: =G42-G111 -> 1 | H83: =H42-H111 -> 0 | I83: =I42-I111 -> 1 | ... AF83: =AF42-AF111 -> 3 | AG83: =SUM(B83:AF83) -> 57
A84: Solar Roof Single - Blue | B84: =B43-B112 -> 79 | C84: =C43-C112 -> 66 | D84: =D43-D112 -> 49 | E84: =E43-E112 -> 33 | F84: =F43-F112 -> 45 | G84: =G43-G112 -> 37 | H84: =H43-H112 -> 25 | I84: =I43-I112 -> 24 | ... AF84: =AF43-AF112 -> 13 | AG84: =SUM(B84:AF84) -> 783
A85: Solar Roof Single - Yellow | B85: =B44-B113 -> 1 | C85: =C44-C113 -> 1 | D85: =D44-D113 -> 1 | E85: =E44-E113 -> 4 | F85: =F44-F113 -> 0 | G85: =G44-G113 -> 1 | H85: =H44-H113 -> 0 | I85: =I44-I113 -> 0 | ... AF85: =AF44-AF113 -> 0 | AG85: =SUM(B85:AF85) -> 25
A86: Perch Extender - Blue | B86: =B45-B114 -> 79 | C86: =C45-C114 -> 64 | D86: =D45-D114 -> 73 | E86: =E45-E114 -> 70 | F86: =F45-F114 -> 86 | G86: =G45-G114 -> 53 | H86: =H45-H114 -> 55 | I86: =I45-I114 -> 62 | ... AF86: =AF45-AF114 -> 22 | AG86: =SUM(B86:AF86) -> 1646
A87: Perch Extender - Yellow | B87: =B46-B115 -> 13 | C87: =C46-C115 -> 9 | D87: =D46-D115 -> 11 | E87: =E46-E115 -> 12 | F87: =F46-F115 -> 6 | G87: =G46-G115 -> 4 | H87: =H46-H115 -> 7 | I87: =I46-I115 -> 8 | ... AF87: =AF46-AF115 -> 8 | AG87: =SUM(B87:AF87) -> 252
A88: Solar Roof (HBF) | B88: =B47-B116 -> 1 | C88: =C47-C116 -> 0 | D88: =D47-D116 -> 1 | E88: =E47-E116 -> 1 | F88: =F47-F116 -> 0 | G88: =G47-G116 -> 0 | H88: =H47-H116 -> 0 | I88: =I47-I116 -> 0 | ... AF88: =AF47-AF116 -> 0 | AG88: =SUM(B88:AF88) -> 11
A89: Housing - only (HBF) | B89: =B48-B117 -> 0 | C89: =C48-C117 -> 0 | D89: =D48-D117 -> 0 | E89: =E48-E117 -> 0 | F89: =F48-F117 -> 0 | G89: =G48-G117 -> 0 | H89: =H48-H117 -> 0 | I89: =I48-I117 -> 0 | ... AF89: =AF48-AF117 -> 0 | AG89: =SUM(B89:AF89) -> 0
A90: Nature Cam PRO | B90: =B49-B118 -> 5 | C90: =C49-C118 -> 2 | D90: =D49-D118 -> 1 | E90: =E49-E118 -> 1 | F90: =F49-F118 -> 1 | G90: =G49-G118 -> 1 | H90: =H49-H118 -> 2 | I90: =I49-I118 -> 1 | ... AF90: =AF49-AF118 -> 1 | AG90: =SUM(B90:AF90) -> 50
A91: SUM (Add-ons) | B91: =SUM(B80:B90) -> 224 | C91: =SUM(C80:C90) -> 179 | D91: =SUM(D80:D90) -> 173 | E91: =SUM(E80:E90) -> 177 | F91: =SUM(F80:F90) -> 203 | G91: =SUM(G80:G90) -> 119 | H91: =SUM(H80:H90) -> 123 | I91: =SUM(I80:I90) -> 132 | ... AF91: =SUM(AF80:AF90) -> 137 | AG91: =SUM(B91:AF91) -> 4792
A93: Returning Customers
A94: SKU 1 - Blue | B94: 6 | C94: 2 | D94: 2 | E94: 0 | F94: 4 | G94: 1 | H94: 0 | I94: 0 | J94: 2 | K94: 0 | L94: 1 | M94: 0 | N94: 0 | O94: 0 | P94: 3 | Q94: 0 | R94: 1 | S94: 0 | T94: 0 | U94: 0 | V94: 0 | W94: 2 | X94: 0 | Y94: 0 | Z94: 0 | AA94: 0 | AB94: 3 | AC94: 2 | AD94: 1 | AE94: 4 | AF94: 1 | AG94: =SUM(B94:AF94) -> 35
A95: SKU 2 - Yellow | B95: 0 | C95: 0 | D95: 0 | E95: 0 | F95: 0 | G95: 0 | H95: 0 | I95: 0 | J95: 0 | K95: 0 | L95: 0 | M95: 0 | N95: 0 | O95: 0 | P95: 0 | Q95: 0 | R95: 0 | S95: 0 | T95: 0 | U95: 0 | V95: 0 | W95: 0 | X95: 0 | Y95: 0 | Z95: 0 | AA95: 0 | AB95: 0 | AC95: 0 | AD95: 0 | AE95: 0 | AF95: 0 | AG95: =SUM(B95:AF95) -> 0
A96: SKU 3 - Blue w/ Solar | B96: 0 | C96: 0 | D96: 0 | E96: 0 | F96: 0 | G96: 0 | H96: 0 | I96: 0 | J96: 0 | K96: 0 | L96: 0 | M96: 0 | N96: 0 | O96: 0 | P96: 0 | Q96: 1 | R96: 2 | S96: 0 | T96: 0 | U96: 0 | V96: 0 | W96: 1 | X96: 0 | Y96: 2 | Z96: 1 | AA96: 0 | AB96: 3 | AC96: 0 | AD96: 0 | AE96: 0 | AF96: 0 | AG96: =SUM(B96:AF96) -> 10
A97: SKU 4 - Yellow w/ Solar | B97: 2 | C97: 1 | D97: 0 | E97: 3 | F97: 0 | G97: 1 | H97: 1 | I97: 0 | J97: 0 | K97: 1 | L97: 2 | M97: 3 | N97: 0 | O97: 0 | P97: 1 | Q97: 0 | R97: 0 | S97: 0 | T97: 1 | U97: 1 | V97: 1 | W97: 1 | X97: 0 | Y97: 1 | Z97: 1 | AA97: 1 | AB97: 1 | AC97: 1 | AD97: 3 | AE97: 1 | AF97: 1 | AG97: =SUM(B97:AF97) -> 29
A98: SKU 1 - Blue PRO | B98: 0 | C98: 0 | D98: 0 | E98: 2 | F98: 2 | G98: 0 | H98: 1 | I98: 0 | J98: 0 | K98: 0 | L98: 1 | M98: 1 | N98: 0 | O98: 0 | P98: 0 | Q98: 0 | R98: 0 | S98: 0 | T98: 1 | U98: 0 | V98: 1 | W98: 0 | X98: 1 | Y98: 0 | Z98: 0 | AA98: 0 | AB98: 1 | AC98: 1 | AD98: 2 | AE98: 2 | AF98: 2 | AG98: =SUM(B98:AF98) -> 18
A99: SKU 2 - Yellow PRO | B99: 0 | C99: 0 | D99: 0 | E99: 0 | F99: 0 | G99: 0 | H99: 0 | I99: 0 | J99: 0 | K99: 0 | L99: 0 | M99: 0 | N99: 0 | O99: 0 | P99: 0 | Q99: 0 | R99: 0 | S99: 0 | T99: 0 | U99: 0 | V99: 0 | W99: 0 | X99: 0 | Y99: 0 | Z99: 0 | AA99: 0 | AB99: 0 | AC99: 0 | AD99: 0 | AE99: 0 | AF99: 0 | AG99: =SUM(B99:AF99) -> 0
A100: SKU 3 - Blue w/ Solar PRO | B100: 1 | C100: 0 | D100: 1 | E100: 4 | F100: 1 | G100: 3 | H100: 2 | I100: 4 | J100: 1 | K100: 3 | L100: 4 | M100: 6 | N100: 4 | O100: 4 | P100: 1 | Q100: 2 | R100: 8 | S100: 9 | T100: 8 | U100: 7 | V100: 9 | W100: 8 | X100: 5 | Y100: 4 | Z100: 5 | AA100: 9 | AB100: 2 | AC100: 4 | AD100: 9 | AE100: 4 | AF100: 7 | AG100: =SUM(B100:AF100) -> 139
A101: SKU 4 - Yellow w/ Solar PRO | B101: 0 | C101: 0 | D101: 0 | E101: 0 | F101: 0 | G101: 0 | H101: 0 | I101: 0 | J101: 0 | K101: 0 | L101: 0 | M101: 0 | N101: 0 | O101: 0 | P101: 0 | Q101: 0 | R101: 0 | S101: 0 | T101: 0 | U101: 0 | V101: 0 | W101: 0 | X101: 0 | Y101: 0 | Z101: 0 | AA101: 0 | AB101: 0 | AC101: 0 | AD101: 0 | AE101: 0 | AF101: 0 | AG101: =SUM(B101:AF101) -> 0
A102: SUM (SKU 1 - SKU 4) | B102: =SUM(B94:B101) -> 9 | C102: =SUM(C94:C101) -> 3 | D102: =SUM(D94:D101) -> 3 | E102: =SUM(E94:E101) -> 9 | F102: =SUM(F94:F101) -> 7 | G102: =SUM(G94:G101) -> 5 | H102: =SUM(H94:H101) -> 4 | I102: =SUM(I94:I101) -> 4 | ... AF102: =SUM(AF94:AF101) -> 11 | AG102: =SUM(B102:AF102) -> 231
A104: SKU 5 - HBF | B104: 0 | C104: 0 | D104: 0 | E104: 0 | F104: 0 | G104: 0 | H104: 0 | I104: 0 | J104: 0 | K104: 0 | L104: 0 | M104: 0 | N104: 0 | O104: 0 | P104: 0 | Q104: 0 | R104: 0 | S104: 0 | T104: 0 | U104: 0 | V104: 0 | W104: 0 | X104: 0 | Y104: 0 | Z104: 0 | AA104: 0 | AB104: 0 | AC104: 0 | AD104: 0 | AE104: 0 | AF104: 0 | AG104: =SUM(B104:AF104) -> 0
A105: SKU 6 - HBF w/ Solar | B105: 0 | C105: 0 | D105: 0 | E105: 0 | F105: 0 | G105: 0 | H105: 0 | I105: 0 | J105: 0 | K105: 0 | L105: 0 | M105: 0 | N105: 0 | O105: 0 | P105: 0 | Q105: 0 | R105: 0 | S105: 0 | T105: 0 | U105: 0 | V105: 0 | W105: 0 | X105: 0 | Y105: 0 | Z105: 0 | AA105: 0 | AB105: 0 | AC105: 0 | AD105: 0 | AE105: 0 | AF105: 0 | AG105: =SUM(B105:AF105) -> 0
A106: SUM (SKU 5 - SKU 6) | B106: =SUM(B104:B105) -> 0 | C106: =SUM(C104:C105) -> 0 | D106: =SUM(D104:D105) -> 0 | E106: =SUM(E104:E105) -> 0 | F106: =SUM(F104:F105) -> 0 | G106: =SUM(G104:G105) -> 0 | H106: =SUM(H104:H105) -> 0 | I106: =SUM(I104:I105) -> 0 | ... AF106: =SUM(AF104:AF105) -> 0 | AG106: =SUM(B106:AF106) -> 0
A108: Wall Mount | B108: 6 | C108: 8 | D108: 4 | E108: 5 | F108: 4 | G108: 1 | H108: 2 | I108: 0 | J108: 1 | K108: 4 | L108: 2 | M108: 3 | N108: 4 | O108: 3 | P108: 0 | Q108: 2 | R108: 2 | S108: 1 | T108: 4 | U108: 2 | V108: 0 | W108: 6 | X108: 1 | Y108: 5 | Z108: 5 | AA108: 4 | AB108: 1 | AC108: 1 | AD108: 2 | AE108: 1 | AF108: 2 | AG108: =SUM(B108:AF108) -> 86
A109: Suet Ball Holder | B109: 7 | C109: 8 | D109: 0 | E109: 5 | F109: 2 | G109: 5 | H109: 4 | I109: 1 | J109: 4 | K109: 5 | L109: 2 | M109: 2 | N109: 5 | O109: 1 | P109: 0 | Q109: 4 | R109: 1 | S109: 9 | T109: 4 | U109: 7 | V109: 5 | W109: 4 | X109: 4 | Y109: 8 | Z109: 10 | AA109: 10 | AB109: 10 | AC109: 10 | AD109: 12 | AE109: 11 | AF109: 8 | AG109: =SUM(B109:AF109) -> 168
A110: 3-in-1 Nutrition Set - Blue | B110: 5 | C110: 2 | D110: 2 | E110: 6 | F110: 4 | G110: 2 | H110: 2 | I110: 1 | J110: 3 | K110: 3 | L110: 2 | M110: 0 | N110: 0 | O110: 5 | P110: 1 | Q110: 2 | R110: 2 | S110: 4 | T110: 5 | U110: 1 | V110: 1 | W110: 3 | X110: 2 | Y110: 6 | Z110: 4 | AA110: 7 | AB110: 2 | AC110: 3 | AD110: 3 | AE110: 1 | AF110: 1 | AG110: =SUM(B110:AF110) -> 85
A111: 3-in-1 Nutrition Set - Yellow | B111: 0 | C111: 0 | D111: 1 | E111: 2 | F111: 2 | G111: 1 | H111: 0 | I111: 0 | J111: 0 | K111: 1 | L111: 0 | M111: 0 | N111: 1 | O111: 0 | P111: 1 | Q111: 0 | R111: 1 | S111: 1 | T111: 0 | U111: 2 | V111: 1 | W111: 3 | X111: 0 | Y111: 0 | Z111: 0 | AA111: 1 | AB111: 0 | AC111: 0 | AD111: 1 | AE111: 2 | AF111: 0 | AG111: =SUM(B111:AF111) -> 21
A112: Solar Roof Single - Blue | B112: 12 | C112: 5 | D112: 7 | E112: 3 | F112: 9 | G112: 6 | H112: 5 | I112: 5 | J112: 5 | K112: 6 | L112: 7 | M112: 5 | N112: 5 | O112: 5 | P112: 4 | Q112: 5 | R112: 2 | S112: 3 | T112: 6 | U112: 1 | V112: 5 | W112: 3 | X112: 1 | Y112: 2 | Z112: 6 | AA112: 5 | AB112: 3 | AC112: 5 | AD112: 8 | AE112: 4 | AF112: 4 | AG112: =SUM(B112:AF112) -> 152
A113: Solar Roof Single - Yellow | B113: 1 | C113: 0 | D113: 0 | E113: 0 | F113: 0 | G113: 0 | H113: 1 | I113: 0 | J113: 0 | K113: 0 | L113: 2 | M113: 1 | N113: 0 | O113: 0 | P113: 0 | Q113: 1 | R113: 0 | S113: 1 | T113: 0 | U113: 0 | V113: 0 | W113: 1 | X113: 0 | Y113: 1 | Z113: 2 | AA113: 0 | AB113: 1 | AC113: 1 | AD113: 1 | AE113: 0 | AF113: 0 | AG113: =SUM(B113:AF113) -> 14
A114: Perch Extender - Blue | B114: 14 | C114: 6 | D114: 7 | E114: 11 | F114: 16 | G114: 6 | H114: 8 | I114: 7 | J114: 6 | K114: 12 | L114: 6 | M114: 5 | N114: 7 | O114: 9 | P114: 4 | Q114: 9 | R114: 9 | S114: 3 | T114: 13 | U114: 7 | V114: 11 | W114: 12 | X114: 6 | Y114: 8 | Z114: 7 | AA114: 15 | AB114: 7 | AC114: 4 | AD114: 5 | AE114: 3 | AF114: 11 | AG114: =SUM(B114:AF114) -> 254
...

Sheet DTC EU - P&L
A1: JANUARY | B1: 45658 | C1: 45659 | D1: 45660 | E1: 45661 | F1: 45662 | G1: 45663 | H1: 45664 | I1: 45665 | J1: 45666 | K1: 45667 | L1: 45668 | M1: 45669 | N1: 45670 | O1: 45671 | P1: 45672 | Q1: 45673 | R1: 45674 | S1: 45675 | T1: 45676 | U1: 45677 | V1: 45678 | W1: 45679 | X1: 45680 | Y1: 45681 | Z1: 45682 | AA1: 45683 | AB1: 45684 | AC1: 45685 | AD1: 45686 | AE1: 45687 | AF1: 45688
A2: DAY | B2: WED | C2: THU | D2: FRI | E2: SAT | F2: SUN | G2: MON | H2: TUE | I2: WED | J2: THU | K2: FRI | L2: SAT | M2: SUN | N2: MON | O2: TUE | P2: WED | Q2: THU | R2: FRI | S2: SAT | T2: SUN | U2: MON | V2: TUE | W2: WED | X2: THU | Y2: FRI | Z2: SAT | AA2: SUN | AB2: MON | AC2: TUE | AD2: WED | AE2: THU | AF2: FRI
A4: Revenue
A5: Revenue Woocommerce (Platform) | B5: =Summary!B17+Summary!B26 -> 5844.0918 | C5: =Summary!C17+Summary!C26 -> 4966.7627 | D5: =Summary!D17+Summary!D26 -> 4749.9753 | E5: =Summary!E17+Summary!E26 -> 2340.6486 | F5: =Summary!F17+Summary!F26 -> 3680.1319 | G5: =Summary!G17+Summary!G26 -> 5741.6952 | H5: =Summary!H17+Summary!H26 -> 5280.6637 | I5: =Summary!I17+Summary!I26 -> 5629.9869 | ... AF5: =Summary!AF17+Summary!AF26 -> 1593.9105 | AG5: =SUM(B5:AF5) -> 113820.79
A6: Revenue w/o renewals | B6: =B8*Summary!B121 -> 1372.9566 | C6: =C8*Summary!C121 -> 563.14143 | D6: =D8*Summary!D121 -> 1594.8642 | E6: =E8*Summary!E121 -> 948.81822 | F6: =F8*Summary!F121 -> 712.62167 | G6: =G8*Summary!G121 -> 2471.4136 | H6: =H8*Summary!H121 -> 2953.5223 | I6: =I8*Summary!I121 -> 2380.493 | ... AF6: =AF8*Summary!AF121 -> 1500.5909
A7: SUM | B7: =SUM(B5) -> 5844.0918 | C7: =SUM(C5) -> 4966.7627 | D7: =SUM(D5) -> 4749.9753 | E7: =SUM(E5) -> 2340.6486 | F7: =SUM(F5) -> 3680.1319 | G7: =SUM(G5) -> 5741.6952 | H7: =SUM(H5) -> 5280.6637 | I7: =SUM(I5) -> 5629.9869 | ... AF7: =SUM(AF5) -> 1593.9105 | AG7: =SUM(B7:AF7) -> 113820.79
A8: Revenue w/o renewals EURO | B8: 1326.4 | C8: 548.55 | D8: 1546.61 | E8: 920.2 | F8: 691.53 | G8: 2380.25 | H8: 2855.3 | I8: 2307.35 | J8: 2743.4 | K8: 908.85 | L8: 1536.2 | M8: 1489.8 | N8: 1376.6 | O8: 2920.75 | P8: 772.9 | Q8: 429.25 | R8: 1655.7 | S8: 2853.16 | T8: 6758.4 | U8: 369.9 | V8: 1183.1 | W8: 1417.13 | X8: 1344.51 | Y8: 1625.13 | Z8: 3130.65 | AA8: 4870.33 | AB8: 3693.08 | AC8: 1327.15 | AD8: 2004.65 | AE8: 1930.35 | AF8: 1447.05
A9: Orders
A10: Orders Woocommerce (Platform) | B10: =Summary!B89 -> 53 | C10: =Summary!C89 -> 52 | D10: =Summary!D89 -> 47 | E10: =Summary!E89 -> 19 | F10: =Summary!F89 -> 35 | G10: =Summary!G89 -> 43 | H10: =Summary!H89 -> 35 | I10: =Summary!I89 -> 42 | ... AF10: =Summary!AF89 -> 10 | AG10: =SUM(B10:AF10) -> 814
A11: Orders w/o renewals | B11: 5 | C11: 4 | D11: 12 | E11: 6 | F11: 3 | G11: 8 | H11: 11 | I11: 7 | J11: 11 | K11: 4 | L11: 5 | M11: 7 | N11: 6 | O11: 5 | P11: 5 | Q11: 3 | R11: 7 | S11: 16 | T11: 28 | U11: 2 | V11: 7 | W11: 6 | X11: 7 | Y11: 7 | Z11: 9 | AA11: 23 | AB11: 16 | AC11: 7 | AD11: 8 | AE11: 12 | AF11: 9
A12: SUM | B12: =SUM(B10) -> 53 | C12: =SUM(C10) -> 52 | D12: =SUM(D10) -> 47 | E12: =SUM(E10) -> 19 | F12: =SUM(F10) -> 35 | G12: =SUM(G10) -> 43 | H12: =SUM(H10) -> 35 | I12: =SUM(I10) -> 42 | ... AF12: =SUM(AF10) -> 10 | AG12: =SUM(B12:AF12) -> 814
A14: Breakdown
A15: - Hardware | B15: 942.3 | C15: 251.26 | D15: 694.27 | E15: 448.5 | F15: 496.28 | G15: 1660.43 | H15: 1963.72 | I15: 1611.4 | J15: 1772.83 | K15: 643.09 | L15: 1098.4 | M15: 976.38 | N15: 881.33 | O15: 2186.04 | P15: 388.62 | Q15: 197.52 | R15: 1077.99 | S15: 1712.77 | T15: 4299.41 | U15: 249.17 | V15: 626.01 | W15: 802.22 | X15: 757.6 | Y15: 1075.03 | Z15: 1879.64 | AA15: 2682.89 | AB15: 2201.77 | AC15: 800.25 | AD15: 1052.11 | AE15: 1020.23 | AF15: 770.55 | AG15: =SUM(B15:AF15) -> 37220.01
A16: - Add-ons | B16: 48.47 | C16: 151.45 | D16: 306.63 | E16: 223.67 | F16: 0 | G16: 152.15 | H16: 136.15 | I16: 89.26 | J16: 256.75 | K16: 23.97 | L16: 48.33 | M16: 111.19 | N16: 127.19 | O16: 15.7 | P16: 162.83 | Q16: 113.33 | R16: 135.02 | S16: 347.25 | T16: 701.97 | U16: 24.37 | V16: 217.86 | W16: 241.52 | X16: 229.89 | Y16: 118.3 | Z16: 441.35 | AA16: 898.8 | AB16: 479.15 | AC16: 155.59 | AD16: 420.83 | AE16: 367.12 | AF16: 258.52 | AG16: =SUM(B16:AF16) -> 7004.61
A17: - Merch | B17: 0 | C17: 0 | D17: 0 | E17: 0 | F17: 0 | G17: 0 | H17: 0 | I17: 0 | J17: 0 | K17: 0 | L17: 0 | M17: 0 | N17: 0 | O17: 0 | P17: 0 | Q17: 0 | R17: 0 | S17: 0 | T17: 0 | U17: 0 | V17: 0 | W17: 0 | X17: 0 | Y17: 0 | Z17: 0 | AA17: 0 | AB17: 0 | AC17: 0 | AD17: 0 | AE17: 0 | AF17: 0 | AG17: =SUM(B17:AF17) -> 0
A18: - Seeds | B18: 0 | C18: 0 | D18: 0 | E18: 0 | F18: 0 | G18: 0 | H18: 0 | I18: 0 | J18: 0 | K18: 0 | L18: 0 | M18: 0 | N18: 0 | O18: 0 | P18: 0 | Q18: 0 | R18: 0 | S18: 0 | T18: 0 | U18: 0 | V18: 0 | W18: 0 | X18: 0 | Y18: 0 | Z18: 0 | AA18: 0 | AB18: 0 | AC18: 0 | AD18: 0 | AE18: 0 | AF18: 0 | AG18: =SUM(B18:AF18) -> 0
A19: - Yearly Pro Subscription | B19: 3576.59 | C19: 3548.99 | D19: 2677.7 | E19: 1113.89 | F19: 2401.76 | G19: 2591.43 | H19: 1868.91 | I19: 2601.07 | J19: 2748.67 | K19: 2074.76 | L19: 2303.65 | M19: 2156.51 | N19: 1793.99 | O19: 2227.15 | P19: 1185.84 | Q19: 1045.62 | R19: 1412.17 | S19: 698.12 | T19: 523.12 | U19: 373.14 | V19: 331.31 | W19: 596.88 | X19: 371.9 | Y19: 147.53 | Z19: 0 | AA19: 327.36 | AB19: 149.38 | AC19: 0 | AD19: 224.4 | AE19: 226.27 | AF19: 74.99 | AG19: =SUM(B19:AF19) -> 41373.1
A20: - Taxes | B20: 968.56 | C20: 831.37 | D20: 802.66 | E20: 393.99 | F20: 623.17 | G20: 965.89 | H20: 891.27 | I20: 970.27 | J20: 1064.78 | K20: 601.75 | L20: 750.51 | M20: 725.43 | N20: 613.85 | O20: 966.56 | P20: 395.45 | Q20: 287.64 | R20: 595.33 | S20: 634.93 | T20: 1268.83 | U20: 138.17 | V20: 262.88 | W20: 376.43 | X20: 305.07 | Y20: 304.25 | Z20: 549.66 | AA20: 891.24 | AB20: 702.76 | AC20: 226.31 | AD20: 392.28 | AE20: 376.7 | AF20: 267.98 | AG20: =SUM(B20:AF20) -> 19145.97
A21: - Shipping | B21: 110 | C21: 55 | D21: 125 | E21: 90 | F21: 50 | G21: 160 | H21: 245 | I21: 185 | J21: 230 | K21: 85 | L21: 125 | M21: 130 | N21: 120 | O21: 225 | P21: 80 | Q21: 45 | R21: 145 | S21: 270 | T21: 595 | U21: 35 | V21: 105 | W21: 120 | X21: 130 | Y21: 160 | Z21: 260 | AA21: 430 | AB21: 340 | AC21: 145 | AD21: 185 | AE21: 210 | AF21: 165 | AG21: =SUM(B21:AF21) -> 5355
A22: SUM | B22: =SUM(B15:B21) -> 5645.92 | C22: =SUM(C15:C21) -> 4838.07 | D22: =SUM(D15:D21) -> 4606.26 | E22: =SUM(E15:E21) -> 2270.05 | F22: =SUM(F15:F21) -> 3571.21 | G22: =SUM(G15:G21) -> 5529.9 | H22: =SUM(H15:H21) -> 5105.05 | I22: =SUM(I15:I21) -> 5457 | ... AF22: =SUM(AF15:AF21) -> 1537.04 | AG22: =SUM(B22:AF22) -> 110098.69
A24: Units Sold (Gross)
A25: SKU 1 - Blue | B25: 0 | C25: 0 | D25: 0 | E25: 0 | F25: 0 | G25: 0 | H25: 0 | I25: 0 | J25: 0 | K25: 0 | L25: 0 | M25: 0 | N25: 0 | O25: 0 | P25: 0 | Q25: 0 | R25: 0 | S25: 0 | T25: 3 | U25: 0 | V25: 0 | W25: 0 | X25: 0 | Y25: 0 | Z25: 0 | AA25: 0 | AB25: 0 | AC25: 1 | AD25: 4 | AE25: 2 | AF25: 2 | AG25: =SUM(B25:AF25) -> 12
A26: SKU 2 - Yellow | B26: 0 | C26: 0 | D26: 0 | E26: 0 | F26: 0 | G26: 0 | H26: 0 | I26: 0 | J26: 0 | K26: 0 | L26: 0 | M26: 0 | N26: 0 | O26: 0 | P26: 0 | Q26: 0 | R26: 0 | S26: 0 | T26: 0 | U26: 0 | V26: 0 | W26: 0 | X26: 0 | Y26: 0 | Z26: 0 | AA26: 0 | AB26: 0 | AC26: 0 | AD26: 0 | AE26: 0 | AF26: 0 | AG26: =SUM(B26:AF26) -> 0
A27: SKU 3 - Blue w/ Solar | B27: 0 | C27: 0 | D27: 0 | E27: 0 | F27: 0 | G27: 0 | H27: 0 | I27: 0 | J27: 0 | K27: 0 | L27: 0 | M27: 0 | N27: 0 | O27: 0 | P27: 0 | Q27: 0 | R27: 0 | S27: 0 | T27: 0 | U27: 0 | V27: 0 | W27: 0 | X27: 0 | Y27: 0 | Z27: 0 | AA27: 0 | AB27: 0 | AC27: 0 | AD27: 0 | AE27: 0 | AF27: 0 | AG27: =SUM(B27:AF27) -> 0
A28: SKU 4 - Yellow w/ Solar | B28: 0 | C28: 0 | D28: 0 | E28: 0 | F28: 0 | G28: 0 | H28: 0 | I28: 0 | J28: 0 | K28: 0 | L28: 0 | M28: 0 | N28: 0 | O28: 0 | P28: 0 | Q28: 0 | R28: 0 | S28: 0 | T28: 0 | U28: 0 | V28: 0 | W28: 0 | X28: 0 | Y28: 0 | Z28: 0 | AA28: 0 | AB28: 0 | AC28: 0 | AD28: 0 | AE28: 0 | AF28: 0 | AG28: =SUM(B28:AF28) -> 0
A29: SKU 1 - Blue PRO | B29: 1 | C29: 0 | D29: 1 | E29: 0 | F29: 0 | G29: 0 | H29: 5 | I29: 2 | J29: 4 | K29: 2 | L29: 2 | M29: 0 | N29: 2 | O29: 1 | P29: 2 | Q29: 1 | R29: 1 | S29: 0 | T29: 1 | U29: 0 | V29: 1 | W29: 0 | X29: 1 | Y29: 2 | Z29: 2 | AA29: 0 | AB29: 5 | AC29: 4 | AD29: 3 | AE29: 2 | AF29: 3 | AG29: =SUM(B29:AF29) -> 48
A30: SKU 2 - Yellow PRO | B30: 0 | C30: 0 | D30: 0 | E30: 0 | F30: 0 | G30: 0 | H30: 0 | I30: 0 | J30: 0 | K30: 0 | L30: 0 | M30: 0 | N30: 0 | O30: 0 | P30: 0 | Q30: 0 | R30: 0 | S30: 0 | T30: 0 | U30: 0 | V30: 0 | W30: 0 | X30: 0 | Y30: 0 | Z30: 0 | AA30: 0 | AB30: 0 | AC30: 0 | AD30: 0 | AE30: 0 | AF30: 0 | AG30: =SUM(B30:AF30) -> 0
A31: SKU 3 - Blue w/ Solar PRO | B31: 3 | C31: 1 | D31: 2 | E31: 2 | F31: 2 | G31: 7 | H31: 4 | I31: 5 | J31: 4 | K31: 1 | L31: 3 | M31: 4 | N31: 2 | O31: 8 | P31: 0 | Q31: 0 | R31: 4 | S31: 8 | T31: 17 | U31: 1 | V31: 2 | W31: 4 | X31: 3 | Y31: 4 | Z31: 8 | AA31: 14 | AB31: 7 | AC31: 0 | AD31: 0 | AE31: 2 | AF31: 0 | AG31: =SUM(B31:AF31) -> 122
A32: SKU 4 - Yellow w/ Solar PRO | B32: 0 | C32: 0 | D32: 0 | E32: 0 | F32: 0 | G32: 0 | H32: 0 | I32: 0 | J32: 0 | K32: 0 | L32: 0 | M32: 0 | N32: 0 | O32: 0 | P32: 0 | Q32: 0 | R32: 0 | S32: 0 | T32: 0 | U32: 0 | V32: 0 | W32: 0 | X32: 0 | Y32: 0 | Z32: 0 | AA32: 0 | AB32: 0 | AC32: 0 | AD32: 0 | AE32: 0 | AF32: 0 | AG32: =SUM(B32:AF32) -> 0
A33: SUM (SKU 1 - SKU 4) | B33: =SUM(B25:B32) -> 4 | C33: =SUM(C25:C32) -> 1 | D33: =SUM(D25:D32) -> 3 | E33: =SUM(E25:E32) -> 2 | F33: =SUM(F25:F32) -> 2 | G33: =SUM(G25:G32) -> 7 | H33: =SUM(H25:H32) -> 9 | I33: =SUM(I25:I32) -> 7 | ... AF33: =SUM(AF25:AF32) -> 5 | AG33: =SUM(B33:AF33) -> 182
A35: SKU 5 - HBF | AG35: =SUM(B35:AF35) -> 0
A36: SKU 6 - HBF w/ Solar | AG36: =SUM(B36:AF36) -> 0
A37: SUM (SKU 5 - SKU 6) | B37: =SUM(B35:B36) -> 0 | C37: =SUM(C35:C36) -> 0 | D37: =SUM(D35:D36) -> 0 | E37: =SUM(E35:E36) -> 0 | F37: =SUM(F35:F36) -> 0 | G37: =SUM(G35:G36) -> 0 | H37: =SUM(H35:H36) -> 0 | I37: =SUM(I35:I36) -> 0 | ... AF37: =SUM(AF35:AF36) -> 0 | AG37: =SUM(B37:AF37) -> 0
A39: Wall Mount | B39: 0 | C39: 2 | D39: 2 | E39: 0 | F39: 0 | G39: 3 | H39: 3 | I39: 1 | J39: 2 | K39: 1 | L39: 0 | M39: 4 | N39: 1 | O39: 0 | P39: 0 | Q39: 0 | R39: 3 | S39: 2 | T39: 6 | U39: 0 | V39: 3 | W39: 3 | X39: 1 | Y39: 1 | Z39: 5 | AA39: 7 | AB39: 5 | AC39: 3 | AD39: 4 | AE39: 2 | AF39: 1 | AG39: =SUM(B39:AF39) -> 65
A40: Suet Ball Holder | B40: 1 | C40: 3 | D40: 3 | E40: 4 | F40: 0 | G40: 1 | H40: 0 | I40: 0 | J40: 3 | K40: 0 | L40: 1 | M40: 1 | N40: 1 | O40: 1 | P40: 0 | Q40: 3 | R40: 2 | S40: 4 | T40: 5 | U40: 0 | V40: 0 | W40: 1 | X40: 5 | Y40: 4 | Z40: 6 | AA40: 10 | AB40: 3 | AC40: 0 | AD40: 1 | AE40: 1 | AF40: 2 | AG40: =SUM(B40:AF40) -> 66
A41: 3-in-1 Nutrition Set - Blue | B41: 1 | C41: 2 | D41: 3 | E41: 1 | F41: 0 | G41: 2 | H41: 0 | I41: 0 | J41: 1 | K41: 0 | L41: 1 | M41: 0 | N41: 1 | O41: 0 | P41: 1 | Q41: 0 | R41: 1 | S41: 3 | T41: 6 | U41: 0 | V41: 1 | W41: 2 | X41: 2 | Y41: 2 | Z41: 5 | AA41: 9 | AB41: 4 | AC41: 0 | AD41: 2 | AE41: 2 | AF41: 1 | AG41: =SUM(B41:AF41) -> 53
A42: 3-in-1 Nutrition Set - Yellow | B42: 0 | C42: 0 | D42: 0 | E42: 0 | F42: 0 | G42: 0 | H42: 0 | I42: 0 | J42: 0 | K42: 0 | L42: 0 | M42: 0 | N42: 0 | O42: 0 | P42: 0 | Q42: 0 | R42: 0 | S42: 1 | T42: 1 | U42: 0 | V42: 0 | W42: 0 | X42: 0 | Y42: 0 | Z42: 0 | AA42: 0 | AB42: 0 | AC42: 0 | AD42: 0 | AE42: 0 | AF42: 1 | AG42: =SUM(B42:AF42) -> 3
A43: Solar Roof Single - Blue | B43: 0 | C43: 0 | D43: 2 | E43: 2 | F43: 0 | G43: 0 | H43: 1 | I43: 1 | J43: 2 | K43: 0 | L43: 0 | M43: 0 | N43: 1 | O43: 0 | P43: 1 | Q43: 0 | R43: 0 | S43: 0 | T43: 2 | U43: 0 | V43: 1 | W43: 1 | X43: 1 | Y43: 0 | Z43: 1 | AA43: 3 | AB43: 2 | AC43: 2 | AD43: 5 | AE43: 2 | AF43: 2 | AG43: =SUM(B43:AF43) -> 32
A44: Solar Roof Single - Yellow | B44: 0 | C44: 0 | D44: 0 | E44: 0 | F44: 0 | G44: 0 | H44: 0 | I44: 0 | J44: 0 | K44: 0 | L44: 0 | M44: 0 | N44: 0 | O44: 0 | P44: 1 | Q44: 1 | R44: 0 | S44: 0 | T44: 0 | U44: 0 | V44: 0 | W44: 0 | X44: 0 | Y44: 0 | Z44: 0 | AA44: 0 | AB44: 0 | AC44: 0 | AD44: 0 | AE44: 1 | AF44: 0 | AG44: =SUM(B44:AF44) -> 3
A45: Perch Extender - Blue | B45: 0 | C45: 0 | D45: 0 | E45: 0 | F45: 0 | G45: 0 | H45: 0 | I45: 0 | J45: 0 | K45: 0 | L45: 0 | M45: 0 | N45: 0 | O45: 0 | P45: 0 | Q45: 0 | R45: 0 | S45: 0 | T45: 0 | U45: 0 | V45: 0 | W45: 0 | X45: 0 | Y45: 0 | Z45: 0 | AA45: 0 | AB45: 2 | AC45: 0 | AD45: 0 | AE45: 0 | AF45: 0 | AG45: =SUM(B45:AF45) -> 2
A46: Perch Extender - Yellow | B46: 0 | C46: 0 | D46: 0 | E46: 0 | F46: 0 | G46: 0 | H46: 0 | I46: 0 | J46: 0 | K46: 0 | L46: 0 | M46: 0 | N46: 0 | O46: 0 | P46: 0 | Q46: 0 | R46: 0 | S46: 5 | T46: 6 | U46: 1 | V46: 2 | W46: 1 | X46: 2 | Y46: 0 | Z46: 0 | AA46: 5 | AB46: 1 | AC46: 0 | AD46: 0 | AE46: 4 | AF46: 3 | AG46: =SUM(B46:AF46) -> 30
A47: Solar Roof (HBF) | AG47: =SUM(B47:AF47) -> 0
A48: Housing - only (HBF) | AG48: =SUM(B48:AF48) -> 0
A49: Nature Cam PRO | AG49: =SUM(B49:AF49) -> 0
A50: SUM (Add-ons) | B50: =SUM(B39:B49) -> 2 | C50: =SUM(C39:C49) -> 7 | D50: =SUM(D39:D49) -> 10 | E50: =SUM(E39:E49) -> 7 | F50: =SUM(F39:F49) -> 0 | G50: =SUM(G39:G49) -> 6 | H50: =SUM(H39:H49) -> 4 | I50: =SUM(I39:I49) -> 2 | ... AF50: =SUM(AF39:AF49) -> 10 | AG50: =SUM(B50:AF50) -> 254
A52: Seasonal Curation - 8lb | AG52: =SUM(B52:AF52) -> 0
A53: Seasonal Curation - 20lb | AG53: =SUM(B53:AF53) -> 0
A54: Buddy Bites - 8lb | AG54: =SUM(B54:AF54) -> 0
A55: Buddy Bites - 20lb | AG55: =SUM(B55:AF55) -> 0
A56: Snack n' Soar - 8lb | AG56: =SUM(B56:AF56) -> 0
A57: Snack n' Soar - 20lb | AG57: =SUM(B57:AF57) -> 0
A58: Avian Choice - 8lb | AG58: =SUM(B58:AF58) -> 0
A59: Avian Choice - 20lb | AG59: =SUM(B59:AF59) -> 0
A60: SUM (Seeds) | B60: =SUM(B52:B59) -> 0 | C60: =SUM(C52:C59) -> 0 | D60: =SUM(D52:D59) -> 0 | E60: =SUM(E52:E59) -> 0 | F60: =SUM(F52:F59) -> 0 | G60: =SUM(G52:G59) -> 0 | H60: =SUM(H52:H59) -> 0 | I60: =SUM(I52:I59) -> 0 | ... AF60: =SUM(AF52:AF59) -> 0 | AG60: =SUM(B60:AF60) -> 0
A62: Merch Units Sold (Gross)
A63: Merch Units | B63: 0 | C63: 0 | D63: 0 | E63: 0 | F63: 0 | G63: 0 | H63: 0 | I63: 0 | J63: 0 | K63: 0 | L63: 0 | M63: 0 | N63: 0 | O63: 0 | P63: 0 | Q63: 0 | R63: 0 | S63: 0 | T63: 0 | U63: 0 | V63: 0 | W63: 0 | X63: 0 | Y63: 0 | Z63: 0 | AA63: 0 | AB63: 0 | AC63: 0 | AD63: 0 | AE63: 0 | AF63: 0 | AG63: =SUM(B63:AF63) -> 0
A65: First-time Customers
A66: SKU 1 - Blue | B66: =B25-B94 -> 0 | C66: =C25-C94 -> 0 | D66: =D25-D94 -> 0 | E66: =E25-E94 -> 0 | F66: =F25-F94 -> 0 | G66: =G25-G94 -> 0 | H66: =H25-H94 -> 0 | I66: =I25-I94 -> 0 | ... AF66: =AF25-AF94 -> 2 | AG66: =SUM(B66:AF66) -> 12
A67: SKU 2 - Yellow | B67: =B26-B95 -> 0 | C67: =C26-C95 -> 0 | D67: =D26-D95 -> 0 | E67: =E26-E95 -> 0 | F67: =F26-F95 -> 0 | G67: =G26-G95 -> 0 | H67: =H26-H95 -> 0 | I67: =I26-I95 -> 0 | ... AF67: =AF26-AF95 -> 0 | AG67: =SUM(B67:AF67) -> 0
A68: SKU 3 - Blue w/ Solar | B68: =B27-B96 -> 0 | C68: =C27-C96 -> 0 | D68: =D27-D96 -> 0 | E68: =E27-E96 -> 0 | F68: =F27-F96 -> 0 | G68: =G27-G96 -> 0 | H68: =H27-H96 -> 0 | I68: =I27-I96 -> 0 | ... AF68: =AF27-AF96 -> 0 | AG68: =SUM(B68:AF68) -> 0
A69: SKU 4 - Yellow w/ Solar | B69: =B28-B97 -> 0 | C69: =C28-C97 -> 0 | D69: =D28-D97 -> 0 | E69: =E28-E97 -> 0 | F69: =F28-F97 -> 0 | G69: =G28-G97 -> 0 | H69: =H28-H97 -> 0 | I69: =I28-I97 -> 0 | ... AF69: =AF28-AF97 -> 0 | AG69: =SUM(B69:AF69) -> 0
A70: SKU 1 - Blue PRO | B70: =B29-B98 -> 1 | C70: =C29-C98 -> 0 | D70: =D29-D98 -> 0 | E70: =E29-E98 -> 0 | F70: =F29-F98 -> 0 | G70: =G29-G98 -> 0 | H70: =H29-H98 -> 5 | I70: =I29-I98 -> 2 | ... AF70: =AF29-AF98 -> 3 | AG70: =SUM(B70:AF70) -> 46
A71: SKU 2 - Yellow PRO | B71: =B30-B99 -> 0 | C71: =C30-C99 -> 0 | D71: =D30-D99 -> 0 | E71: =E30-E99 -> 0 | F71: =F30-F99 -> 0 | G71: =G30-G99 -> 0 | H71: =H30-H99 -> 0 | I71: =I30-I99 -> 0 | ... AF71: =AF30-AF99 -> 0 | AG71: =SUM(B71:AF71) -> 0
A72: SKU 3 - Blue w/ Solar PRO | B72: =B31-B100 -> 3 | C72: =C31-C100 -> 1 | D72: =D31-D100 -> 2 | E72: =E31-E100 -> 2 | F72: =F31-F100 -> 2 | G72: =G31-G100 -> 5 | H72: =H31-H100 -> 4 | I72: =I31-I100 -> 5 | ... AF72: =AF31-AF100 -> 0 | AG72: =SUM(B72:AF72) -> 107
A73: SKU 4 - Yellow w/ Solar PRO | B73: =B32-B101 -> 0 | C73: =C32-C101 -> 0 | D73: =D32-D101 -> 0 | E73: =E32-E101 -> 0 | F73: =F32-F101 -> 0 | G73: =G32-G101 -> 0 | H73: =H32-H101 -> 0 | I73: =I32-I101 -> 0 | ... AF73: =AF32-AF101 -> 0 | AG73: =SUM(B73:AF73) -> 0
A74: SUM (SKU 1 - SKU 4) | B74: =SUM(B66:B73) -> 4 | C74: =SUM(C66:C73) -> 1 | D74: =SUM(D66:D73) -> 2 | E74: =SUM(E66:E73) -> 2 | F74: =SUM(F66:F73) -> 2 | G74: =SUM(G66:G73) -> 5 | H74: =SUM(H66:H73) -> 9 | I74: =SUM(I66:I73) -> 7 | ... AF74: =SUM(AF66:AF73) -> 5 | AG74: =SUM(B74:AF74) -> 165
A76: SKU 5 - HBF | B76: =B35-B104 -> 0 | C76: =C35-C104 -> 0 | D76: =D35-D104 -> 0 | E76: =E35-E104 -> 0 | F76: =F35-F104 -> 0 | G76: =G35-G104 -> 0 | H76: =H35-H104 -> 0 | I76: =I35-I104 -> 0 | ... AF76: =AF35-AF104 -> 0 | AG76: =SUM(B76:AF76) -> 0
A77: SKU 6 - HBF w/ Solar | B77: =B36-B105 -> 0 | C77: =C36-C105 -> 0 | D77: =D36-D105 -> 0 | E77: =E36-E105 -> 0 | F77: =F36-F105 -> 0 | G77: =G36-G105 -> 0 | H77: =H36-H105 -> 0 | I77: =I36-I105 -> 0 | ... AF77: =AF36-AF105 -> 0 | AG77: =SUM(B77:AF77) -> 0
A78: SUM (SKU 5 - SKU 6) | B78: =SUM(B76:B77) -> 0 | C78: =SUM(C76:C77) -> 0 | D78: =SUM(D76:D77) -> 0 | E78: =SUM(E76:E77) -> 0 | F78: =SUM(F76:F77) -> 0 | G78: =SUM(G76:G77) -> 0 | H78: =SUM(H76:H77) -> 0 | I78: =SUM(I76:I77) -> 0 | ... AF78: =SUM(AF76:AF77) -> 0 | AG78: =SUM(B78:AF78) -> 0
A80: Wall Mount | B80: =B39-B108 -> 0 | C80: =C39-C108 -> 1 | D80: =D39-D108 -> 2 | E80: =E39-E108 -> 0 | F80: =F39-F108 -> 0 | G80: =G39-G108 -> 1 | H80: =H39-H108 -> 3 | I80: =I39-I108 -> 1 | ... AF80: =AF39-AF108 -> 1 | AG80: =SUM(B80:AF80) -> 59
A81: Suet Ball Holder | B81: =B40-B109 -> 1 | C81: =C40-C109 -> 1 | D81: =D40-D109 -> 2 | E81: =E40-E109 -> 4 | F81: =F40-F109 -> 0 | G81: =G40-G109 -> 1 | H81: =H40-H109 -> 0 | I81: =I40-I109 -> 0 | ... AF81: =AF40-AF109 -> 2 | AG81: =SUM(B81:AF81) -> 58
A82: 3-in-1 Nutrition Set - Blue | B82: =B41-B110 -> 0 | C82: =C41-C110 -> 1 | D82: =D41-D110 -> 2 | E82: =E41-E110 -> 1 | F82: =F41-F110 -> 0 | G82: =G41-G110 -> 2 | H82: =H41-H110 -> 0 | I82: =I41-I110 -> 0 | ... AF82: =AF41-AF110 -> 0 | AG82: =SUM(B82:AF82) -> 40
A83: 3-in-1 Nutrition Set - Yellow | B83: =B42-B111 -> 0 | C83: =C42-C111 -> 0 | D83: =D42-D111 -> 0 | E83: =E42-E111 -> 0 | F83: =F42-F111 -> 0 | G83: =G42-G111 -> 0 | H83: =H42-H111 -> 0 | I83: =I42-I111 -> 0 | ... AF83: =AF42-AF111 -> 0 | AG83: =SUM(B83:AF83) -> 1
A84: Solar Roof Single - Blue | B84: =B43-B112 -> 0 | C84: =C43-C112 -> 0 | D84: =D43-D112 -> 2 | E84: =E43-E112 -> 1 | F84: =F43-F112 -> 0 | G84: =G43-G112 -> 0 | H84: =H43-H112 -> 1 | I84: =I43-I112 -> 1 | ... AF84: =AF43-AF112 -> 2 | AG84: =SUM(B84:AF84) -> 26
A85: Solar Roof Single - Yellow | B85: =B44-B113 -> 0 | C85: =C44-C113 -> 0 | D85: =D44-D113 -> 0 | E85: =E44-E113 -> 0 | F85: =F44-F113 -> 0 | G85: =G44-G113 -> 0 | H85: =H44-H113 -> 0 | I85: =I44-I113 -> 0 | ... AF85: =AF44-AF113 -> 0 | AG85: =SUM(B85:AF85) -> 3
A86: Perch Extender - Blue | B86: =B45-B114 -> 0 | C86: =C45-C114 -> 0 | D86: =D45-D114 -> 0 | E86: =E45-E114 -> 0 | F86: =F45-F114 -> 0 | G86: =G45-G114 -> 0 | H86: =H45-H114 -> 0 | I86: =I45-I114 -> 0 | ... AF86: =AF45-AF114 -> 0 | AG86: =SUM(B86:AF86) -> 1
A87: Perch Extender - Yellow | B87: =B46-B115 -> 0 | C87: =C46-C115 -> 0 | D87: =D46-D115 -> 0 | E87: =E46-E115 -> 0 | F87: =F46-F115 -> 0 | G87: =G46-G115 -> 0 | H87: =H46-H115 -> 0 | I87: =I46-I115 -> 0 | ... AF87: =AF46-AF115 -> 0 | AG87: =SUM(B87:AF87) -> 20
A88: Solar Roof (HBF) | B88: =B47-B116 -> 0 | C88: =C47-C116 -> 0 | D88: =D47-D116 -> 0 | E88: =E47-E116 -> 0 | F88: =F47-F116 -> 0 | G88: =G47-G116 -> 0 | H88: =H47-H116 -> 0 | I88: =I47-I116 -> 0 | ... AF88: =AF47-AF116 -> 0 | AG88: =SUM(B88:AF88) -> 0
A89: Housing - only (HBF) | B89: =B48-B117 -> 0 | C89: =C48-C117 -> 0 | D89: =D48-D117 -> 0 | E89: =E48-E117 -> 0 | F89: =F48-F117 -> 0 | G89: =G48-G117 -> 0 | H89: =H48-H117 -> 0 | I89: =I48-I117 -> 0 | ... AF89: =AF48-AF117 -> 0 | AG89: =SUM(B89:AF89) -> 0
A90: Nature Cam PRO | B90: =B49-B118 -> 0 | C90: =C49-C118 -> 0 | D90: =D49-D118 -> 0 | E90: =E49-E118 -> 0 | F90: =F49-F118 -> 0 | G90: =G49-G118 -> 0 | H90: =H49-H118 -> 0 | I90: =I49-I118 -> 0 | ... AF90: =AF49-AF118 -> 0 | AG90: =SUM(B90:AF90) -> 0
A91: SUM (Add-ons) | B91: =SUM(B80:B90) -> 1 | C91: =SUM(C80:C90) -> 3 | D91: =SUM(D80:D90) -> 8 | E91: =SUM(E80:E90) -> 6 | F91: =SUM(F80:F90) -> 0 | G91: =SUM(G80:G90) -> 4 | H91: =SUM(H80:H90) -> 4 | I91: =SUM(I80:I90) -> 2 | ... AF91: =SUM(AF80:AF90) -> 5 | AG91: =SUM(B91:AF91) -> 208
A93: Returning Customers
A94: SKU 1 - Blue | B94: 0 | C94: 0 | D94: 0 | E94: 0 | F94: 0 | G94: 0 | H94: 0 | I94: 0 | J94: 0 | K94: 0 | L94: 0 | M94: 0 | N94: 0 | O94: 0 | P94: 0 | Q94: 0 | R94: 0 | S94: 0 | T94: 0 | U94: 0 | V94: 0 | W94: 0 | X94: 0 | Y94: 0 | Z94: 0 | AA94: 0 | AB94: 0 | AC94: 0 | AD94: 0 | AE94: 0 | AF94: 0 | AG94: =SUM(B94:AF94) -> 0
A95: SKU 2 - Yellow | B95: 0 | C95: 0 | D95: 0 | E95: 0 | F95: 0 | G95: 0 | H95: 0 | I95: 0 | J95: 0 | K95: 0 | L95: 0 | M95: 0 | N95: 0 | O95: 0 | P95: 0 | Q95: 0 | R95: 0 | S95: 0 | T95: 0 | U95: 0 | V95: 0 | W95: 0 | X95: 0 | Y95: 0 | Z95: 0 | AA95: 0 | AB95: 0 | AC95: 0 | AD95: 0 | AE95: 0 | AF95: 0 | AG95: =SUM(B95:AF95) -> 0
A96: SKU 3 - Blue w/ Solar | B96: 0 | C96: 0 | D96: 0 | E96: 0 | F96: 0 | G96: 0 | H96: 0 | I96: 0 | J96: 0 | K96: 0 | L96: 0 | M96: 0 | N96: 0 | O96: 0 | P96: 0 | Q96: 0 | R96: 0 | S96: 0 | T96: 0 | U96: 0 | V96: 0 | W96: 0 | X96: 0 | Y96: 0 | Z96: 0 | AA96: 0 | AB96: 0 | AC96: 0 | AD96: 0 | AE96: 0 | AF96: 0 | AG96: =SUM(B96:AF96) -> 0
A97: SKU 4 - Yellow w/ Solar | B97: 0 | C97: 0 | D97: 0 | E97: 0 | F97: 0 | G97: 0 | H97: 0 | I97: 0 | J97: 0 | K97: 0 | L97: 0 | M97: 0 | N97: 0 | O97: 0 | P97: 0 | Q97: 0 | R97: 0 | S97: 0 | T97: 0 | U97: 0 | V97: 0 | W97: 0 | X97: 0 | Y97: 0 | Z97: 0 | AA97: 0 | AB97: 0 | AC97: 0 | AD97: 0 | AE97: 0 | AF97: 0 | AG97: =SUM(B97:AF97) -> 0
A98: SKU 1 - Blue PRO | B98: 0 | C98: 0 | D98: 1 | E98: 0 | F98: 0 | G98: 0 | H98: 0 | I98: 0 | J98: 0 | K98: 0 | L98: 0 | M98: 0 | N98: 0 | O98: 0 | P98: 0 | Q98: 0 | R98: 0 | S98: 0 | T98: 0 | U98: 0 | V98: 0 | W98: 0 | X98: 0 | Y98: 1 | Z98: 0 | AA98: 0 | AB98: 0 | AC98: 0 | AD98: 0 | AE98: 0 | AF98: 0 | AG98: =SUM(B98:AF98) -> 2
A99: SKU 2 - Yellow PRO | B99: 0 | C99: 0 | D99: 0 | E99: 0 | F99: 0 | G99: 0 | H99: 0 | I99: 0 | J99: 0 | K99: 0 | L99: 0 | M99: 0 | N99: 0 | O99: 0 | P99: 0 | Q99: 0 | R99: 0 | S99: 0 | T99: 0 | U99: 0 | V99: 0 | W99: 0 | X99: 0 | Y99: 0 | Z99: 0 | AA99: 0 | AB99: 0 | AC99: 0 | AD99: 0 | AE99: 0 | AF99: 0 | AG99: =SUM(B99:AF99) -> 0
A100: SKU 3 - Blue w/ Solar PRO | B100: 0 | C100: 0 | D100: 0 | E100: 0 | F100: 0 | G100: 2 | H100: 0 | I100: 0 | J100: 4 | K100: 0 | L100: 0 | M100: 0 | N100: 0 | O100: 0 | P100: 0 | Q100: 0 | R100: 1 | S100: 1 | T100: 3 | U100: 0 | V100: 0 | W100: 0 | X100: 0 | Y100: 0 | Z100: 0 | AA100: 1 | AB100: 2 | AC100: 0 | AD100: 0 | AE100: 1 | AF100: 0 | AG100: =SUM(B100:AF100) -> 15
A101: SKU 4 - Yellow w/ Solar PRO | B101: 0 | C101: 0 | D101: 0 | E101: 0 | F101: 0 | G101: 0 | H101: 0 | I101: 0 | J101: 0 | K101: 0 | L101: 0 | M101: 0 | N101: 0 | O101: 0 | P101: 0 | Q101: 0 | R101: 0 | S101: 0 | T101: 0 | U101: 0 | V101: 0 | W101: 0 | X101: 0 | Y101: 0 | Z101: 0 | AA101: 0 | AB101: 0 | AC101: 0 | AD101: 0 | AE101: 0 | AF101: 0 | AG101: =SUM(B101:AF101) -> 0
A102: SUM (SKU 1 - SKU 4) | B102: =SUM(B94:B101) -> 0 | C102: =SUM(C94:C101) -> 0 | D102: =SUM(D94:D101) -> 1 | E102: =SUM(E94:E101) -> 0 | F102: =SUM(F94:F101) -> 0 | G102: =SUM(G94:G101) -> 2 | H102: =SUM(H94:H101) -> 0 | I102: =SUM(I94:I101) -> 0 | ... AF102: =SUM(AF94:AF101) -> 0 | AG102: =SUM(B102:AF102) -> 17
A104: SKU 5 - HBF | AG104: =SUM(B104:AF104) -> 0
A105: SKU 6 - HBF w/ Solar | AG105: =SUM(B105:AF105) -> 0
A106: SUM (SKU 5 - SKU 6) | B106: =SUM(B104:B105) -> 0 | C106: =SUM(C104:C105) -> 0 | D106: =SUM(D104:D105) -> 0 | E106: =SUM(E104:E105) -> 0 | F106: =SUM(F104:F105) -> 0 | G106: =SUM(G104:G105) -> 0 | H106: =SUM(H104:H105) -> 0 | I106: =SUM(I104:I105) -> 0 | ... AF106: =SUM(AF104:AF105) -> 0 | AG106: =SUM(B106:AF106) -> 0
A108: Wall Mount | B108: 0 | C108: 1 | D108: 0 | E108: 0 | F108: 0 | G108: 2 | H108: 0 | I108: 0 | J108: 0 | K108: 0 | L108: 0 | M108: 1 | N108: 0 | O108: 0 | P108: 0 | Q108: 0 | R108: 0 | S108: 0 | T108: 0 | U108: 0 | V108: 1 | W108: 0 | X108: 0 | Y108: 0 | Z108: 0 | AA108: 1 | AB108: 0 | AC108: 0 | AD108: 0 | AE108: 0 | AF108: 0 | AG108: =SUM(B108:AF108) -> 6
A109: Suet Ball Holder | B109: 0 | C109: 2 | D109: 1 | E109: 0 | F109: 0 | G109: 0 | H109: 0 | I109: 0 | J109: 0 | K109: 0 | L109: 0 | M109: 0 | N109: 1 | O109: 0 | P109: 0 | Q109: 0 | R109: 1 | S109: 1 | T109: 1 | U109: 0 | V109: 0 | W109: 0 | X109: 0 | Y109: 0 | Z109: 0 | AA109: 1 | AB109: 0 | AC109: 0 | AD109: 0 | AE109: 0 | AF109: 0 | AG109: =SUM(B109:AF109) -> 8
A110: 3-in-1 Nutrition Set - Blue | B110: 1 | C110: 1 | D110: 1 | E110: 0 | F110: 0 | G110: 0 | H110: 0 | I110: 0 | J110: 0 | K110: 0 | L110: 0 | M110: 0 | N110: 1 | O110: 0 | P110: 1 | Q110: 0 | R110: 1 | S110: 1 | T110: 2 | U110: 0 | V110: 0 | W110: 0 | X110: 0 | Y110: 0 | Z110: 0 | AA110: 1 | AB110: 1 | AC110: 0 | AD110: 0 | AE110: 1 | AF110: 1 | AG110: =SUM(B110:AF110) -> 13
A111: 3-in-1 Nutrition Set - Yellow | B111: 0 | C111: 0 | D111: 0 | E111: 0 | F111: 0 | G111: 0 | H111: 0 | I111: 0 | J111: 0 | K111: 0 | L111: 0 | M111: 0 | N111: 0 | O111: 0 | P111: 0 | Q111: 0 | R111: 0 | S111: 1 | T111: 0 | U111: 0 | V111: 0 | W111: 0 | X111: 0 | Y111: 0 | Z111: 0 | AA111: 0 | AB111: 0 | AC111: 0 | AD111: 0 | AE111: 0 | AF111: 1 | AG111: =SUM(B111:AF111) -> 2
A112: Solar Roof Single - Blue | B112: 0 | C112: 0 | D112: 0 | E112: 1 | F112: 0 | G112: 0 | H112: 0 | I112: 0 | J112: 1 | K112: 0 | L112: 0 | M112: 0 | N112: 0 | O112: 0 | P112: 1 | Q112: 0 | R112: 0 | S112: 0 | T112: 1 | U112: 0 | V112: 0 | W112: 0 | X112: 0 | Y112: 0 | Z112: 0 | AA112: 0 | AB112: 1 | AC112: 1 | AD112: 0 | AE112: 0 | AF112: 0 | AG112: =SUM(B112:AF112) -> 6
A113: Solar Roof Single - Yellow | B113: 0 | C113: 0 | D113: 0 | E113: 0 | F113: 0 | G113: 0 | H113: 0 | I113: 0 | J113: 0 | K113: 0 | L113: 0 | M113: 0 | N113: 0 | O113: 0 | P113: 0 | Q113: 0 | R113: 0 | S113: 0 | T113: 0 | U113: 0 | V113: 0 | W113: 0 | X113: 0 | Y113: 0 | Z113: 0 | AA113: 0 | AB113: 0 | AC113: 0 | AD113: 0 | AE113: 0 | AF113: 0 | AG113: =SUM(B113:AF113) -> 0
...

Sheet AMAZON - P&L
A1: JANUARY | B1: 45658 | C1: 45659 | D1: 45660 | E1: 45661 | F1: 45662 | G1: 45663 | H1: 45664 | I1: 45665 | J1: 45666 | K1: 45667 | L1: 45668 | M1: 45669 | N1: 45670 | O1: 45671 | P1: 45672 | Q1: 45673 | R1: 45674 | S1: 45675 | T1: 45676 | U1: 45677 | V1: 45678 | W1: 45679 | X1: 45680 | Y1: 45681 | Z1: 45682 | AA1: 45683 | AB1: 45684 | AC1: 45685 | AD1: 45686 | AE1: 45687 | AF1: 45688
A2: DAY | B2: WED | C2: THU | D2: FRI | E2: SAT | F2: SUN | G2: MON | H2: TUE | I2: WED | J2: THU | K2: FRI | L2: SAT | M2: SUN | N2: MON | O2: TUE | P2: WED | Q2: THU | R2: FRI | S2: SAT | T2: SUN | U2: MON | V2: TUE | W2: WED | X2: THU | Y2: FRI | Z2: SAT | AA2: SUN | AB2: MON | AC2: TUE | AD2: WED | AE2: THU | AF2: FRI
A3: COMMENT
A4: Orders
A5: Amazon (market place) | B5: =Summary!B95 -> 164 | C5: =Summary!C95 -> 135 | D5: =Summary!D95 -> 147 | E5: =Summary!E95 -> 224 | F5: =Summary!F95 -> 210 | G5: =Summary!G95 -> 149 | H5: =Summary!H95 -> 154 | I5: =Summary!I95 -> 148 | ... AF5: =Summary!AF95 -> 142
A6: All | B6: =SUM(B5) -> 164 | C6: =SUM(C5) -> 135 | D6: =SUM(D5) -> 147 | E6: =SUM(E5) -> 224 | F6: =SUM(F5) -> 210 | G6: =SUM(G5) -> 149 | H6: =SUM(H5) -> 154 | I6: =SUM(I5) -> 148 | ... AF6: =SUM(AF5) -> 142 | AG6: =SUM(B6:AF6) -> 5357
A8: Revenue
A9: Amazon (market place) | B9: =Summary!B27 -> 20026.6 | C9: =Summary!C27 -> 28799.1 | D9: =Summary!D27 -> 23958 | E9: =Summary!E27 -> 28901.2 | F9: =Summary!F27 -> 29312.82 | G9: =Summary!G27 -> 25501.91 | H9: =Summary!H27 -> 23405.2 | I9: =Summary!I27 -> 29757.41 | ... AF9: =Summary!AF27 -> 23985.36
A10: All | B10: =SUM(B9) -> 20026.6 | C10: =SUM(C9) -> 28799.1 | D10: =SUM(D9) -> 23958 | E10: =SUM(E9) -> 28901.2 | F10: =SUM(F9) -> 29312.82 | G10: =SUM(G9) -> 25501.91 | H10: =SUM(H9) -> 23405.2 | I10: =SUM(I9) -> 29757.41 | ... AF10: =SUM(AF9) -> 23985.36 | AG10: =SUM(B10:AF10) -> 763152.48
A12: Media Cost
A13: Amazon Spend | B13: =Summary!B130 -> 5667 | C13: =Summary!C130 -> 4827 | D13: =Summary!D130 -> 4597 | E13: =Summary!E130 -> 4933 | F13: =Summary!F130 -> 4408 | G13: =Summary!G130 -> 3807 | H13: =Summary!H130 -> 4209 | I13: =Summary!I130 -> 5056 | ... AF13: =Summary!AF130 -> 3275 | AG13: =SUM(B13:AF13) -> 135676
A14: Amazon Platform Fee (15 %) | B14: =B9*'Data - P&L'!$C$48 -> 3003.99 | C14: =C9*'Data - P&L'!$C$48 -> 4319.865 | D14: =D9*'Data - P&L'!$C$48 -> 3593.7 | E14: =E9*'Data - P&L'!$C$48 -> 4335.18 | F14: =F9*'Data - P&L'!$C$48 -> 4396.923 | G14: =G9*'Data - P&L'!$C$48 -> 3825.2865 | H14: =H9*'Data - P&L'!$C$48 -> 3510.78 | I14: =I9*'Data - P&L'!$C$48 -> 4463.6115 | ... AF14: =AF9*'Data - P&L'!$C$48 -> 3597.804 | AG14: =SUM(B14:AF14) -> 114472.87
A15: All | B15: =SUM(B13:B14) -> 8670.99 | C15: =SUM(C13:C14) -> 9146.865 | D15: =SUM(D13:D14) -> 8190.7 | E15: =SUM(E13:E14) -> 9268.18 | F15: =SUM(F13:F14) -> 8804.923 | G15: =SUM(G13:G14) -> 7632.2865 | H15: =SUM(H13:H14) -> 7719.78 | I15: =SUM(I13:I14) -> 9519.6115 | ... AF15: =SUM(AF13:AF14) -> 6872.804 | AG15: =SUM(B15:AF15) -> 250148.87
A19: Amazon Orders
A20: Hardware | B20: =Summary!B28 -> 16658.38 | C20: =Summary!C28 -> 25109.18 | D20: =Summary!D28 -> 20102.12 | E20: =Summary!E28 -> 23515.24 | F20: =Summary!F28 -> 24193.24 | G20: =Summary!G28 -> 21565.68 | H20: =Summary!H28 -> 19505.8 | I20: =Summary!I28 -> 25763.36 | ... AF20: =Summary!AF28 -> 19312.9 | AG20: =SUM(B20:AF20) -> 623956.82
A21: Addons | B21: =Summary!B29 -> 2039 | C21: =Summary!C29 -> 1737.3 | D21: =Summary!D29 -> 2205.78 | E21: =Summary!E29 -> 3405.26 | F21: =Summary!F29 -> 3165.26 | G21: =Summary!G29 -> 2260.2 | H21: =Summary!H29 -> 2355.66 | I21: =Summary!I29 -> 2145.84 | ... AF21: =Summary!AF29 -> 3106.88 | AG21: =SUM(B21:AF21) -> 89352.12
A22: Tax | B22: =Summary!B30 -> 1328.82 | C22: =Summary!C30 -> 1939.15 | D22: =Summary!D30 -> 1627.42 | E22: =Summary!E30 -> 1940.02 | F22: =Summary!F30 -> 1939.6 | G22: =Summary!G30 -> 1638.52 | H22: =Summary!H30 -> 1533.51 | I22: =Summary!I30 -> 1826.25 | ... AF22: =Summary!AF30 -> 1559.59 | AG22: =SUM(B22:AF22) -> 49175.37
A23: Shipping | B23: =Summary!B31 -> 0.25 | C23: =Summary!C31 -> 12.47 | D23: =Summary!D31 -> 17.85 | E23: =Summary!E31 -> 31.02 | F23: =Summary!F31 -> 5.06 | G23: =Summary!G31 -> 28.02 | H23: =Summary!H31 -> 0.4 | I23: =Summary!I31 -> 7.47 | ... AF23: =Summary!AF31 -> 1.25 | AG23: =SUM(B23:AF23) -> 359.86
A24: Gift Wrap Price | B24: =Summary!B32 -> 0.15 | C24: =Summary!C32 -> 1 | D24: =Summary!D32 -> 4.83 | E24: =Summary!E32 -> 9.66 | F24: =Summary!F32 -> 9.66 | G24: =Summary!G32 -> 9.49 | H24: =Summary!H32 -> 9.83 | I24: =Summary!I32 -> 14.49 | ... AF24: =Summary!AF32 -> 4.74 | AG24: =SUM(B24:AF24) -> 308.31
A25: All Amazon | B25: =SUM(B20:B24) -> 20026.6 | C25: =SUM(C20:C24) -> 28799.1 | D25: =SUM(D20:D24) -> 23958 | E25: =SUM(E20:E24) -> 28901.2 | F25: =SUM(F20:F24) -> 29312.82 | G25: =SUM(G20:G24) -> 25501.91 | H25: =SUM(H20:H24) -> 23405.2 | I25: =SUM(I20:I24) -> 29757.41 | ... AF25: =SUM(AF20:AF24) -> 23985.36 | AG25: =SUM(B25:AF25) -> 763152.48
A27: Units Sold (Gross)
A28: SKU 1 - Blue | B28: 25 | C28: 16 | D28: 14 | E28: 15 | F28: 15 | G28: 11 | H28: 20 | I28: 15 | J28: 22 | K28: 6 | L28: 19 | M28: 17 | N28: 9 | O28: 10 | P28: 6 | Q28: 11 | R28: 11 | S28: 10 | T28: 12 | U28: 6 | V28: 12 | W28: 7 | X28: 7 | Y28: 5 | Z28: 15 | AA28: 9 | AB28: 10 | AC28: 13 | AD28: 12 | AE28: 8 | AF28: 11 | AG28: =SUM(B28:AF28) -> 379
A29: SKU 2 - Yellow | B29: 0 | C29: 0 | D29: 0 | E29: 0 | F29: 0 | G29: 0 | H29: 0 | I29: 0 | J29: 0 | K29: 0 | L29: 0 | M29: 0 | N29: 0 | O29: 0 | P29: 0 | Q29: 0 | R29: 0 | S29: 0 | T29: 0 | U29: 0 | V29: 0 | W29: 0 | X29: 0 | Y29: 0 | Z29: 0 | AA29: 0 | AB29: 0 | AC29: 0 | AD29: 0 | AE29: 0 | AF29: 0 | AG29: =SUM(B29:AF29) -> 0
A30: SKU 3 - Blue w/ Solar | B30: 6 | C30: 8 | D30: 14 | E30: 11 | F30: 10 | G30: 11 | H30: 4 | I30: 8 | J30: 9 | K30: 14 | L30: 32 | M30: 55 | N30: 32 | O30: 31 | P30: 26 | Q30: 31 | R30: 34 | S30: 36 | T30: 47 | U30: 34 | V30: 24 | W30: 20 | X30: 13 | Y30: 4 | Z30: 5 | AA30: 12 | AB30: 6 | AC30: 8 | AD30: 1 | AE30: 4 | AF30: 4 | AG30: =SUM(B30:AF30) -> 554
A31: SKU 4 - Yellow w/ Solar | B31: 5 | C31: 15 | D31: 7 | E31: 13 | F31: 8 | G31: 12 | H31: 8 | I31: 11 | J31: 7 | K31: 8 | L31: 17 | M31: 17 | N31: 27 | O31: 14 | P31: 9 | Q31: 14 | R31: 13 | S31: 14 | T31: 7 | U31: 12 | V31: 14 | W31: 50 | X31: 65 | Y31: 61 | Z31: 85 | AA31: 80 | AB31: 45 | AC31: 53 | AD31: 37 | AE31: 14 | AF31: 24 | AG31: =SUM(B31:AF31) -> 766
A32: SKU 1 - Blue PRO | B32: 0 | C32: 2 | D32: 1 | E32: 0 | F32: 0 | G32: 0 | H32: 0 | I32: 0 | J32: 0 | K32: 1 | L32: 1 | M32: 1 | N32: 1 | O32: 0 | P32: 3 | Q32: 0 | R32: 2 | S32: 2 | T32: 1 | U32: 0 | V32: 0 | W32: 0 | X32: 1 | Y32: 1 | Z32: 2 | AA32: 0 | AB32: 0 | AC32: 0 | AD32: 0 | AE32: 0 | AF32: 0 | AG32: =SUM(B32:AF32) -> 19
A33: SKU 2 - Yellow PRO | B33: 0 | C33: 0 | D33: 0 | E33: 0 | F33: 0 | G33: 0 | H33: 0 | I33: 0 | J33: 0 | K33: 0 | L33: 0 | M33: 0 | N33: 0 | O33: 0 | P33: 0 | Q33: 0 | R33: 0 | S33: 0 | T33: 0 | U33: 0 | V33: 0 | W33: 0 | X33: 0 | Y33: 0 | Z33: 0 | AA33: 0 | AB33: 0 | AC33: 0 | AD33: 0 | AE33: 0 | AF33: 0 | AG33: =SUM(B33:AF33) -> 0
A34: SKU 3 - Blue w/ Solar PRO | B34: 28 | C34: 49 | D34: 37 | E34: 45 | F34: 53 | G34: 43 | H34: 40 | I34: 58 | J34: 49 | K34: 45 | L34: 35 | M34: 8 | N34: 2 | O34: 11 | P34: 9 | Q34: 5 | R34: 2 | S34: 4 | T34: 2 | U34: 8 | V34: 8 | W34: 6 | X34: 2 | Y34: 9 | Z34: 5 | AA34: 2 | AB34: 4 | AC34: 3 | AD34: 15 | AE34: 35 | AF34: 40 | AG34: =SUM(B34:AF34) -> 662
A35: SKU 4 - Yellow w/ Solar PRO | B35: 0 | C35: 0 | D35: 0 | E35: 0 | F35: 0 | G35: 0 | H35: 0 | I35: 0 | J35: 0 | K35: 0 | L35: 0 | M35: 0 | N35: 0 | O35: 0 | P35: 0 | Q35: 0 | R35: 0 | S35: 0 | T35: 0 | U35: 0 | V35: 0 | W35: 0 | X35: 0 | Y35: 0 | Z35: 0 | AA35: 0 | AB35: 0 | AC35: 0 | AD35: 0 | AE35: 0 | AF35: 0 | AG35: =SUM(B35:AF35) -> 0
A36: SUM (SKU 1 - SKU 4) | B36: =SUM(B28:B35) -> 64 | C36: =SUM(C28:C35) -> 90 | D36: =SUM(D28:D35) -> 73 | E36: =SUM(E28:E35) -> 84 | F36: =SUM(F28:F35) -> 86 | G36: =SUM(G28:G35) -> 77 | H36: =SUM(H28:H35) -> 72 | I36: =SUM(I28:I35) -> 92 | ... AF36: =SUM(AF28:AF35) -> 79 | AG36: =SUM(B36:AF36) -> 2380
A38: SKU 5 - HBF | B38: 0 | C38: 1 | D38: 0 | E38: 0 | F38: 1 | G38: 0 | H38: 0 | I38: 0 | J38: 0 | K38: 0 | L38: 0 | M38: 0 | N38: 0 | O38: 0 | P38: 1 | Q38: 0 | R38: 1 | S38: 0 | T38: 0 | U38: 0 | V38: 0 | W38: 0 | X38: 0 | Y38: 0 | Z38: 0 | AA38: 0 | AB38: 0 | AC38: 0 | AD38: 0 | AE38: 0 | AF38: 0 | AG38: =SUM(B38:AF38) -> 4
A39: SKU 6 - HBF w/ Solar | B39: 0 | C39: 0 | D39: 0 | E39: 1 | F39: 0 | G39: 0 | H39: 0 | I39: 0 | J39: 0 | K39: 0 | L39: 0 | M39: 0 | N39: 0 | O39: 0 | P39: 0 | Q39: 0 | R39: 0 | S39: 0 | T39: 0 | U39: 0 | V39: 0 | W39: 0 | X39: 1 | Y39: 0 | Z39: 0 | AA39: 0 | AB39: 1 | AC39: 0 | AD39: 1 | AE39: 0 | AF39: 0 | AG39: =SUM(B39:AF39) -> 4
A40: SUM (SKU 5 - SKU 6) | B40: =SUM(B38:B39) -> 0 | C40: =SUM(C38:C39) -> 1 | D40: =SUM(D38:D39) -> 0 | E40: =SUM(E38:E39) -> 1 | F40: =SUM(F38:F39) -> 1 | G40: =SUM(G38:G39) -> 0 | H40: =SUM(H38:H39) -> 0 | I40: =SUM(I38:I39) -> 0 | ... AF40: =SUM(AF38:AF39) -> 0 | AG40: =SUM(B40:AF40) -> 8
A42: Wall Mount | B42: 23 | C42: 21 | D42: 25 | E42: 47 | F42: 48 | G42: 30 | H42: 33 | I42: 25 | J42: 17 | K42: 30 | L42: 30 | M42: 39 | N42: 23 | O42: 16 | P42: 14 | Q42: 15 | R42: 22 | S42: 24 | T42: 25 | U42: 23 | V42: 23 | W42: 11 | X42: 10 | Y42: 18 | Z42: 21 | AA42: 25 | AB42: 12 | AC42: 17 | AD42: 8 | AE42: 11 | AF42: 19 | AG42: =SUM(B42:AF42) -> 705
A43: Suet Ball Holder | B43: 21 | C43: 25 | D43: 20 | E43: 41 | F43: 44 | G43: 35 | H43: 26 | I43: 22 | J43: 30 | K43: 34 | L43: 32 | M43: 38 | N43: 19 | O43: 23 | P43: 14 | Q43: 22 | R43: 27 | S43: 37 | T43: 38 | U43: 30 | V43: 15 | W43: 19 | X43: 15 | Y43: 17 | Z43: 26 | AA43: 26 | AB43: 10 | AC43: 14 | AD43: 20 | AE43: 12 | AF43: 26 | AG43: =SUM(B43:AF43) -> 778
A44: 3-in-1 Nutrition Set - Blue | B44: 12 | C44: 9 | D44: 20 | E44: 29 | F44: 13 | G44: 12 | H44: 13 | I44: 9 | J44: 8 | K44: 10 | L44: 9 | M44: 18 | N44: 13 | O44: 26 | P44: 14 | Q44: 15 | R44: 8 | S44: 15 | T44: 12 | U44: 9 | V44: 9 | W44: 12 | X44: 13 | Y44: 14 | Z44: 12 | AA44: 14 | AB44: 12 | AC44: 6 | AD44: 8 | AE44: 11 | AF44: 16 | AG44: =SUM(B44:AF44) -> 401
A45: 3-in-1 Nutrition Set - Yellow | B45: 0 | C45: 0 | D45: 0 | E45: 0 | F45: 0 | G45: 0 | H45: 0 | I45: 0 | J45: 0 | K45: 0 | L45: 0 | M45: 0 | N45: 0 | O45: 0 | P45: 0 | Q45: 0 | R45: 0 | S45: 0 | T45: 0 | U45: 0 | V45: 0 | W45: 0 | X45: 0 | Y45: 0 | Z45: 0 | AA45: 0 | AB45: 0 | AC45: 0 | AD45: 0 | AE45: 0 | AF45: 0 | AG45: =SUM(B45:AF45) -> 0
A46: Solar Roof Single - Blue | B46: 0 | C46: 0 | D46: 0 | E46: 0 | F46: 0 | G46: 0 | H46: 0 | I46: 0 | J46: 0 | K46: 0 | L46: 0 | M46: 0 | N46: 0 | O46: 0 | P46: 0 | Q46: 0 | R46: 0 | S46: 0 | T46: 0 | U46: 0 | V46: 0 | W46: 0 | X46: 0 | Y46: 0 | Z46: 0 | AA46: 0 | AB46: 0 | AC46: 0 | AD46: 0 | AE46: 0 | AF46: 0 | AG46: =SUM(B46:AF46) -> 0
A47: Solar Roof Single - Yellow | B47: 0 | C47: 0 | D47: 0 | E47: 0 | F47: 0 | G47: 0 | H47: 0 | I47: 0 | J47: 0 | K47: 0 | L47: 0 | M47: 0 | N47: 0 | O47: 0 | P47: 0 | Q47: 0 | R47: 0 | S47: 0 | T47: 0 | U47: 0 | V47: 0 | W47: 0 | X47: 0 | Y47: 0 | Z47: 0 | AA47: 0 | AB47: 0 | AC47: 0 | AD47: 0 | AE47: 0 | AF47: 0 | AG47: =SUM(B47:AF47) -> 0
A48: Perch Extender - Blue | B48: 2 | C48: 1 | D48: 3 | E48: 3 | F48: 3 | G48: 2 | H48: 6 | I48: 5 | J48: 0 | K48: 16 | L48: 68 | M48: 110 | N48: 55 | O48: 75 | P48: 56 | Q48: 52 | R48: 69 | S48: 83 | T48: 71 | U48: 69 | V48: 38 | W48: 53 | X48: 13 | Y48: 0 | Z48: 0 | AA48: 4 | AB48: 23 | AC48: 45 | AD48: 36 | AE48: 27 | AF48: 39 | AG48: =SUM(B48:AF48) -> 1027
A49: Perch Extender - Yellow | B49: 0 | C49: 0 | D49: 0 | E49: 0 | F49: 0 | G49: 0 | H49: 0 | I49: 0 | J49: 0 | K49: 0 | L49: 0 | M49: 0 | N49: 0 | O49: 0 | P49: 0 | Q49: 0 | R49: 0 | S49: 0 | T49: 0 | U49: 0 | V49: 0 | W49: 0 | X49: 0 | Y49: 0 | Z49: 0 | AA49: 0 | AB49: 0 | AC49: 0 | AD49: 0 | AE49: 0 | AF49: 0 | AG49: =SUM(B49:AF49) -> 0
A50: Nature Cam PRO | B50: 3 | C50: 2 | D50: 2 | E50: 1 | F50: 3 | G50: 2 | H50: 2 | I50: 4 | J50: 1 | K50: 5 | L50: 0 | M50: 0 | N50: 2 | O50: 0 | P50: 3 | Q50: 4 | R50: 2 | S50: 2 | T50: 5 | U50: 3 | V50: 1 | W50: 2 | X50: 2 | Y50: 4 | Z50: 2 | AA50: 4 | AB50: 3 | AC50: 4 | AD50: 1 | AE50: 4 | AF50: 3 | AG50: =SUM(B50:AF50) -> 76
A51: SUM (Add-ons) | B51: =SUM(B42:B50) -> 61 | C51: =SUM(C42:C50) -> 58 | D51: =SUM(D42:D50) -> 70 | E51: =SUM(E42:E50) -> 121 | F51: =SUM(F42:F50) -> 111 | G51: =SUM(G42:G50) -> 81 | H51: =SUM(H42:H50) -> 80 | I51: =SUM(I42:I50) -> 65 | ... AF51: =SUM(AF42:AF50) -> 103 | AG51: =SUM(B51:AF51) -> 2987
A53: Revenue
A54: SKU 1 - Blue | B54: 5217.38 | C54: 3336.38 | D54: 2926 | E54: 3135 | F54: 3135 | G54: 2299 | H54: 4210 | I54: 3135 | J54: 4582.76 | K54: 1254 | L54: 3971 | M54: 3537.76 | N54: 1881 | O54: 2082.38 | P54: 1314 | Q54: 2406.56 | R54: 2406.56 | S54: 2185.12 | T54: 2628 | U54: 1314 | V54: 2623.12 | W54: 1490.56 | X54: 1463 | Y54: 1045 | Z54: 3119.76 | AA54: 1881 | AB54: 2067.14 | AC54: 2717 | AD54: 2492.76 | AE54: 1672 | AF54: 2291.38 | AG54: =SUM(B54:AF54) -> 79819.62
A55: SKU 2 - Yellow | B55: 0 | C55: 0 | D55: 0 | E55: 0 | F55: 0 | G55: 0 | H55: 0 | I55: 0 | J55: 0 | K55: 0 | L55: 0 | M55: 0 | N55: 0 | O55: 0 | P55: 0 | Q55: 0 | R55: 0 | S55: 0 | T55: 0 | U55: 0 | V55: 0 | W55: 0 | X55: 0 | Y55: 0 | Z55: 0 | AA55: 0 | AB55: 0 | AC55: 0 | AD55: 0 | AE55: 0 | AF55: 0 | AG55: =SUM(B55:AF55) -> 0
A56: SKU 3 - Blue w/ Solar | B56: 1674 | C56: 2229.56 | D56: 3901.12 | E56: 3064.12 | F56: 2790 | G56: 3069 | H56: 1116 | I56: 2229.56 | J56: 2508.56 | K56: 3898.68 | L56: 8923.12 | M56: 15332.8 | N56: 8925.56 | O56: 8646.56 | P56: 7254 | Q56: 8639.24 | R56: 9478.68 | S56: 10041.56 | T56: 13108.12 | U56: 9478.68 | V56: 6686.24 | W56: 4962.32 | X56: 3091.76 | Y56: 956 | Z56: 1195 | AA56: 2860.38 | AB56: 1426.38 | AC56: 1912 | AD56: 239 | AE56: 956 | AF56: 948.38 | AG56: =SUM(B56:AF56) -> 151542.38
A57: SKU 4 - Yellow w/ Solar | B57: 1395 | C57: 4182.56 | D57: 1953 | E57: 3624.56 | F57: 2232 | G57: 3348 | H57: 2232 | I57: 3069 | J57: 1950.56 | K57: 2232 | L57: 4743 | M57: 4743 | N57: 7530.56 | O57: 3906 | P57: 2508.56 | Q57: 3906 | R57: 3627 | S57: 3903.56 | T57: 1953 | U57: 3345.56 | V57: 3906 | W57: 12259.94 | X57: 15535 | Y57: 14556.14 | Z57: 20299.76 | AA57: 19097.14 | AB57: 10747.38 | AC57: 12667 | AD57: 8820.14 | AE57: 3338.38 | AF57: 5720.76 | AG57: =SUM(B57:AF57) -> 193332.56
A58: SKU 1 - Blue PRO | B58: 0 | C58: 515.56 | D58: 259 | E58: 0 | F58: 0 | G58: 0 | H58: 0 | I58: 0 | J58: 0 | K58: 259 | L58: 259 | M58: 259 | N58: 259 | O58: 0 | P58: 709.38 | Q58: 0 | R58: 470.38 | S58: 478 | T58: 239 | U58: 0 | V58: 0 | W58: 0 | X58: 219 | Y58: 219 | Z58: 438 | AA58: 0 | AB58: 0 | AC58: 0 | AD58: 0 | AE58: 0 | AF58: 0 | AG58: =SUM(B58:AF58) -> 4583.32
A59: SKU 2 - Yellow PRO | B59: 0 | C59: 0 | D59: 0 | E59: 0 | F59: 0 | G59: 0 | H59: 0 | I59: 0 | J59: 0 | K59: 0 | L59: 0 | M59: 0 | N59: 0 | O59: 0 | P59: 0 | Q59: 0 | R59: 0 | S59: 0 | T59: 0 | U59: 0 | V59: 0 | W59: 0 | X59: 0 | Y59: 0 | Z59: 0 | AA59: 0 | AB59: 0 | AC59: 0 | AD59: 0 | AE59: 0 | AF59: 0 | AG59: =SUM(B59:AF59) -> 0
A60: SKU 3 - Blue w/ Solar PRO | B60: 8372 | C60: 14646.12 | D60: 11063 | E60: 13452.56 | F60: 15837.24 | G60: 12849.68 | H60: 11947.8 | I60: 17329.8 | J60: 14651 | K60: 13450.12 | L60: 10443.04 | M60: 2387.12 | N60: 598 | O60: 3286.56 | P60: 2688.56 | Q60: 1495 | R60: 598 | S60: 1193.56 | T60: 598 | U60: 2387.12 | V60: 2382.24 | W60: 1538.76 | X60: 518 | Y60: 2323.38 | Z60: 1279.76 | AA60: 518 | AB60: 1036 | AC60: 769.38 | AD60: 3885 | AE60: 9049.76 | AF60: 10352.38 | AG60: =SUM(B60:AF60) -> 192926.94
A61: SKU 4 - Yellow w/ Solar PRO | B61: 0 | C61: 0 | D61: 0 | E61: 0 | F61: 0 | G61: 0 | H61: 0 | I61: 0 | J61: 0 | K61: 0 | L61: 0 | M61: 0 | N61: 0 | O61: 0 | P61: 0 | Q61: 0 | R61: 0 | S61: 0 | T61: 0 | U61: 0 | V61: 0 | W61: 0 | X61: 0 | Y61: 0 | Z61: 0 | AA61: 0 | AB61: 0 | AC61: 0 | AD61: 0 | AE61: 0 | AF61: 0 | AG61: =SUM(B61:AF61) -> 0
A62: SUM (SKU 1 - SKU 4) | B62: =SUM(B54:B61) -> 16658.38 | C62: =SUM(C54:C61) -> 24910.18 | D62: =SUM(D54:D61) -> 20102.12 | E62: =SUM(E54:E61) -> 23276.24 | F62: =SUM(F54:F61) -> 23994.24 | G62: =SUM(G54:G61) -> 21565.68 | H62: =SUM(H54:H61) -> 19505.8 | I62: =SUM(I54:I61) -> 25763.36 | ... AF62: =SUM(AF54:AF61) -> 19312.9 | AG62: =SUM(B62:AF62) -> 622204.82
A64: SKU 5 - HBF | B64: 0 | C64: 199 | D64: 0 | E64: 0 | F64: 199 | G64: 0 | H64: 0 | I64: 0 | J64: 0 | K64: 0 | L64: 0 | M64: 0 | N64: 0 | O64: 0 | P64: 199 | Q64: 199 | R64: 0 | S64: 0 | T64: 0 | U64: 0 | V64: 0 | W64: 0 | X64: 0 | Y64: 0 | Z64: 0 | AA64: 0 | AB64: 0 | AC64: 0 | AD64: 0 | AE64: 0 | AF64: 0 | AG64: =SUM(B64:AF64) -> 796
A65: SKU 6 - HBF w/ Solar | B65: 0 | C65: 0 | D65: 0 | E65: 239 | F65: 0 | G65: 0 | H65: 0 | I65: 0 | J65: 0 | K65: 0 | L65: 0 | M65: 0 | N65: 0 | O65: 0 | P65: 0 | Q65: 0 | R65: 0 | S65: 0 | T65: 0 | U65: 0 | V65: 0 | W65: 0 | X65: 239 | Y65: 0 | Z65: 0 | AA65: 239 | AB65: 0 | AC65: 239 | AD65: 0 | AE65: 0 | AF65: 0 | AG65: =SUM(B65:AF65) -> 956
A66: SUM (SKU 5 - SKU 6) | B66: =SUM(B64:B65) -> 0 | C66: =SUM(C64:C65) -> 199 | D66: =SUM(D64:D65) -> 0 | E66: =SUM(E64:E65) -> 239 | F66: =SUM(F64:F65) -> 199 | G66: =SUM(G64:G65) -> 0 | H66: =SUM(H64:H65) -> 0 | I66: =SUM(I64:I65) -> 0 | ... AF66: =SUM(AF64:AF65) -> 0 | AG66: =SUM(B66:AF66) -> 1752
A68: Wall Mount | B68: 667 | C68: 609 | D68: 725 | E68: 1363 | F68: 1392 | G68: 870 | H68: 957 | I68: 725 | J68: 493 | K68: 870 | L68: 870 | M68: 1131 | N68: 667 | O68: 464 | P68: 406 | Q68: 435 | R68: 638 | S68: 696 | T68: 725 | U68: 667 | V68: 667 | W68: 319 | X68: 290 | Y68: 522 | Z68: 609 | AA68: 725 | AB68: 348 | AC68: 493 | AD68: 232 | AE68: 319 | AF68: 551 | AG68: =SUM(B68:AF68) -> 20445
A69: Suet Ball Holder | B69: 399 | C69: 450.3 | D69: 315.78 | E69: 675.26 | F69: 732.26 | G69: 566.2 | H69: 439.66 | I69: 348.84 | J69: 486.02 | K69: 571.9 | L69: 504.26 | M69: 618.26 | N69: 306.66 | O69: 382.66 | P69: 226.48 | Q69: 343.9 | R69: 443.84 | S69: 633.84 | T69: 628.14 | U69: 505.78 | V69: 235.6 | W69: 296.78 | X69: 240.54 | Y69: 273.6 | Z69: 434.72 | AA69: 414.96 | AB69: 155.42 | AC69: 231.42 | AD69: 330.6 | AE69: 193.42 | AF69: 405.08 | AG69: =SUM(B69:AF69) -> 12791.18
A70: 3-in-1 Nutrition Set - Blue | B70: 468 | C70: 351 | D70: 780 | E70: 1131 | F70: 507 | G70: 468 | H70: 507 | I70: 351 | J70: 312 | K70: 390 | L70: 351 | M70: 702 | N70: 507 | O70: 1014 | P70: 546 | Q70: 585 | R70: 312 | S70: 585 | T70: 468 | U70: 351 | V70: 351 | W70: 468 | X70: 507 | Y70: 522.6 | Z70: 444.6 | AA70: 522.6 | AB70: 436.8 | AC70: 222.3 | AD70: 296.4 | AE70: 401.7 | AF70: 592.8 | AG70: =SUM(B70:AF70) -> 15451.8
A71: 3-in-1 Nutrition Set - Yellow | B71: 0 | C71: 0 | D71: 0 | E71: 0 | F71: 0 | G71: 0 | H71: 0 | I71: 0 | J71: 0 | K71: 0 | L71: 0 | M71: 0 | N71: 0 | O71: 0 | P71: 0 | Q71: 0 | R71: 0 | S71: 0 | T71: 0 | U71: 0 | V71: 0 | W71: 0 | X71: 0 | Y71: 0 | Z71: 0 | AA71: 0 | AB71: 0 | AC71: 0 | AD71: 0 | AE71: 0 | AF71: 0 | AG71: =SUM(B71:AF71) -> 0
A72: Solar Roof Single - Blue | B72: 0 | C72: 0 | D72: 0 | E72: 0 | F72: 0 | G72: 0 | H72: 0 | I72: 0 | J72: 0 | K72: 0 | L72: 0 | M72: 0 | N72: 0 | O72: 0 | P72: 0 | Q72: 0 | R72: 0 | S72: 0 | T72: 0 | U72: 0 | V72: 0 | W72: 0 | X72: 0 | Y72: 0 | Z72: 0 | AA72: 0 | AB72: 0 | AC72: 0 | AD72: 0 | AE72: 0 | AF72: 0 | AG72: =SUM(B72:AF72) -> 0
A73: Solar Roof Single - Yellow | B73: 0 | C73: 0 | D73: 0 | E73: 0 | F73: 0 | G73: 0 | H73: 0 | I73: 0 | J73: 0 | K73: 0 | L73: 0 | M73: 0 | N73: 0 | O73: 0 | P73: 0 | Q73: 0 | R73: 0 | S73: 0 | T73: 0 | U73: 0 | V73: 0 | W73: 0 | X73: 0 | Y73: 0 | Z73: 0 | AA73: 0 | AB73: 0 | AC73: 0 | AD73: 0 | AE73: 0 | AF73: 0 | AG73: =SUM(B73:AF73) -> 0
A74: Perch Extender - Blue | B74: 58 | C74: 29 | D74: 87 | E74: 87 | F74: 87 | G74: 58 | H74: 174 | I74: 145 | J74: 0 | K74: 464 | L74: 1972 | M74: 3190 | N74: 1595 | O74: 2175 | P74: 1624 | Q74: 1508 | R74: 2001 | S74: 2407 | T74: 2059 | U74: 2001 | V74: 1102 | W74: 1537 | X74: 377 | Y74: 0 | Z74: 0 | AA74: 116 | AB74: 667 | AC74: 1305 | AD74: 1044 | AE74: 783 | AF74: 1131 | AG74: =SUM(B74:AF74) -> 29783
A75: Perch Extender - Yellow | B75: 0 | C75: 0 | D75: 0 | E75: 0 | F75: 0 | G75: 0 | H75: 0 | I75: 0 | J75: 0 | K75: 0 | L75: 0 | M75: 0 | N75: 0 | O75: 0 | P75: 0 | Q75: 0 | R75: 0 | S75: 0 | T75: 0 | U75: 0 | V75: 0 | W75: 0 | X75: 0 | Y75: 0 | Z75: 0 | AA75: 0 | AB75: 0 | AC75: 0 | AD75: 0 | AE75: 0 | AF75: 0 | AG75: =SUM(B75:AF75) -> 0
A76: Nature Cam PRO | B76: 447 | C76: 298 | D76: 298 | E76: 149 | F76: 447 | G76: 298 | H76: 278 | I76: 576 | J76: 139 | K76: 707.38 | L76: 0 | M76: 0 | N76: 288 | O76: 0 | P76: 437 | Q76: 566 | R76: 288 | S76: 278 | T76: 705 | U76: 429.38 | V76: 139 | W76: 278 | X76: 278 | Y76: 576 | Z76: 288 | AA76: 566 | AB76: 427 | AC76: 568.38 | AD76: 139 | AE76: 566 | AF76: 427 | AG76: =SUM(B76:AF76) -> 10881.14
A77: SUM (Add-ons) | B77: =SUM(B68:B76) -> 2039 | C77: =SUM(C68:C76) -> 1737.3 | D77: =SUM(D68:D76) -> 2205.78 | E77: =SUM(E68:E76) -> 3405.26 | F77: =SUM(F68:F76) -> 3165.26 | G77: =SUM(G68:G76) -> 2260.2 | H77: =SUM(H68:H76) -> 2355.66 | I77: =SUM(I68:I76) -> 2145.84 | ... AF77: =SUM(AF68:AF76) -> 3106.88 | AG77: =SUM(B77:AF77) -> 89352.12
A79: Units Sold by country (Gross) - Only selling in US | AG79: =SUM(B79:AF79) -> 0
A80: Bird Buddy - Blue - AMAZON.US | AG80: =SUM(B80:AF80) -> 0
A81: Bird Buddy - Yellow - AMAZON.US | AG81: =SUM(B81:AF81) -> 0
A82: Bird Buddy with Solar Roof Blue - AMAZON.US | AG82: =SUM(B82:AF82) -> 0
A83: Bird Buddy with Solar Roof Yellow - AMAZON.US | AG83: =SUM(B83:AF83) -> 0
A84: Bird Buddy - AMAZON.EU | AG84: =SUM(B84:AF84) -> 0
A85: Bird Buddy with Solar Roof - AMAZON.EU | AG85: =SUM(B85:AF85) -> 0
A86: Bird Buddy - AMAZON (OTHER1) | AG86: =SUM(B86:AF86) -> 0
A87: Bird Buddy with Solar Roof - AMAZON (OTHER1) | AG87: =SUM(B87:AF87) -> 0
A88: All Bird Buddy | AG88: =SUM(B88:AF88) -> 0
A89: All Bird Buddy with Solar Roof | AG89: =SUM(B89:AF89) -> 0
AG90: =SUM(B90:AF90) -> 0
A91: Wall Mount - AMAZON.US | AG91: =SUM(B91:AF91) -> 0
A92: Fence Mount - AMAZON.US | AG92: =SUM(B92:AF92) -> 0
A93: Suet Ball Holder - AMAZON.US | AG93: =SUM(B93:AF93) -> 0
A94: 3-in-1 Nutrition Set - AMAZON.US | AG94: =SUM(B94:AF94) -> 0
A95: Solar Roof Single - AMAZON.US | AG95: =SUM(B95:AF95) -> 0
A96: All AMAZON.US | AG96: =SUM(B96:AF96) -> 0
AG97: =SUM(B97:AF97) -> 0
A98: Wall Mount - AMAZON.EU | AG98: =SUM(B98:AF98) -> 0
A99: Fence Mount - AMAZON.EU | AG99: =SUM(B99:AF99) -> 0
A100: Suet Ball Holder - AMAZON.EU | AG100: =SUM(B100:AF100) -> 0
A101: 3-in-1 Nutrition Set - AMAZON.EU | AG101: =SUM(B101:AF101) -> 0
A102: Solar Roof Single - AMAZON.EU | AG102: =SUM(B102:AF102) -> 0
A103: All AMAZON.EU | AG103: =SUM(B103:AF103) -> 0
AG104: =SUM(B104:AF104) -> 0
A105: Wall Mount - AMAZON (OTHER1) | AG105: =SUM(B105:AF105) -> 0
A106: Fence Mount - AMAZON (OTHER1) | AG106: =SUM(B106:AF106) -> 0
A107: Suet Ball Holder - AMAZON (OTHER1) | AG107: =SUM(B107:AF107) -> 0
A108: 3-in-1 Nutrition Set - AMAZON (OTHER1) | AG108: =SUM(B108:AF108) -> 0
A109: Solar Roof Single - AMAZON (OTHER1) | AG109: =SUM(B109:AF109) -> 0
A110: All AMAZON (OTHER1) | AG110: =SUM(B110:AF110) -> 0
AG111: =SUM(B111:AF111) -> 0
A112: Revenue by country (Gross) - Only selling in US | AG112: =SUM(B112:AF112) -> 0
...

Sheet WALMART - P&L
A1: JANUARY | B1: 45658 | C1: 45659 | D1: 45660 | E1: 45661 | F1: 45662 | G1: 45663 | H1: 45664 | I1: 45665 | J1: 45666 | K1: 45667 | L1: 45668 | M1: 45669 | N1: 45670 | O1: 45671 | P1: 45672 | Q1: 45673 | R1: 45674 | S1: 45675 | T1: 45676 | U1: 45677 | V1: 45678 | W1: 45679 | X1: 45680 | Y1: 45681 | Z1: 45682 | AA1: 45683 | AB1: 45684 | AC1: 45685 | AD1: 45686 | AE1: 45687 | AF1: 45688
A2: DAY | B2: WED | C2: THU | D2: FRI | E2: SAT | F2: SUN | G2: MON | H2: TUE | I2: WED | J2: THU | K2: FRI | L2: SAT | M2: SUN | N2: MON | O2: TUE | P2: WED | Q2: THU | R2: FRI | S2: SAT | T2: SUN | U2: MON | V2: TUE | W2: WED | X2: THU | Y2: FRI | Z2: SAT | AA2: SUN | AB2: MON | AC2: TUE | AD2: WED | AE2: THU | AF2: FRI
A3: Walmart
A4: Revenue | B4: =Summary!B53 -> 62.63 | C4: =Summary!C53 -> 635.17 | D4: =Summary!D53 -> 271.93 | E4: =Summary!E53 -> 0 | F4: =Summary!F53 -> 0 | G4: =Summary!G53 -> 382.97 | H4: =Summary!H53 -> 336.83 | I4: =Summary!I53 -> 31.39 | ... AF4: =Summary!AF53 -> 31.32 | AG4: =SUM(B4:AF4) -> 5708.93
A5: Breakdown | AG5: =SUM(B5:AF5) -> 0
A6: - Tax | B6: =Summary!B55 -> 4.63 | C6: =Summary!C55 -> 45.18 | D6: =Summary!D55 -> 16.94 | E6: =Summary!E55 -> 0 | F6: =Summary!F55 -> 0 | G6: =Summary!G55 -> 6.97 | H6: =Summary!H55 -> 28.83 | I6: =Summary!I55 -> 2.39 | ... AF6: =Summary!AF55 -> 2.32 | AG6: =SUM(B6:AF6) -> 349.97
A7: - Shipping | B7: =Summary!B56 -> 0 | C7: =Summary!C56 -> 6.99 | D7: =Summary!D56 -> 6.99 | E7: =Summary!E56 -> 0 | F7: =Summary!F56 -> 0 | G7: =Summary!G56 -> 0 | H7: =Summary!H56 -> 0 | I7: =Summary!I56 -> 0 | ... AF7: =Summary!AF56 -> 0 | AG7: =SUM(B7:AF7) -> 27.96
A8: Orders | B8: =Summary!B106 -> 2 | C8: =Summary!C106 -> 8 | D8: =Summary!D106 -> 2 | E8: =Summary!E106 -> 0 | F8: =Summary!F106 -> 0 | G8: =Summary!G106 -> 5 | H8: =Summary!H106 -> 2 | I8: =Summary!I106 -> 1 | ... AF8: =Summary!AF106 -> 1 | AG8: =SUM(B8:AF8) -> 41
A10: Media Cost
A11: Walmart Spend | B11: =Summary!B134 -> 89.51 | C11: =Summary!C134 -> 52.05 | D11: =Summary!D134 -> 57.88 | E11: =Summary!E134 -> 95.74 | F11: =Summary!F134 -> 137.25 | G11: =Summary!G134 -> 112.61 | H11: =Summary!H134 -> 59.18 | I11: =Summary!I134 -> 81.69 | ... AF11: =Summary!AF134 -> 71.49
A12: Walmart Fees (15%) | B12: =B4*0.15 -> 9.3945 | C12: =C4*0.15 -> 95.2755 | D12: =D4*0.15 -> 40.7895 | E12: =E4*0.15 -> 0 | F12: =F4*0.15 -> 0 | G12: =G4*0.15 -> 57.4455 | H12: =H4*0.15 -> 50.5245 | I12: =I4*0.15 -> 4.7085 | ... AF12: =AF4*0.15 -> 4.698 | AG12: =SUM(B12:AF12) -> 856.3395
A14: Units Sold (Gross) - Walmart
A15: SKU 1 - Blue | B15: 0 | C15: 2 | D15: 1 | E15: 0 | F15: 0 | G15: 0 | H15: 0 | I15: 0 | J15: 0 | K15: 0 | L15: 0 | M15: 0 | N15: 0 | O15: 0 | P15: 0 | Q15: 0 | R15: 0 | S15: 0 | T15: 0 | U15: 0 | V15: 0 | W15: 0 | X15: 0 | Y15: 0 | Z15: 0 | AA15: 1 | AB15: 0 | AC15: 0 | AD15: 0 | AE15: 0 | AF15: 0 | AG15: =SUM(B15:AF15) -> 4
A16: SKU 2 - Yellow | B16: 0 | C16: 0 | D16: 0 | E16: 0 | F16: 0 | G16: 0 | H16: 0 | I16: 0 | J16: 0 | K16: 0 | L16: 0 | M16: 0 | N16: 0 | O16: 0 | P16: 0 | Q16: 0 | R16: 0 | S16: 0 | T16: 0 | U16: 0 | V16: 0 | W16: 0 | X16: 0 | Y16: 0 | Z16: 0 | AA16: 0 | AB16: 0 | AC16: 0 | AD16: 0 | AE16: 0 | AF16: 0 | AG16: =SUM(B16:AF16) -> 0
A17: SKU 3 - Blue w/ Solar | B17: 0 | C17: 0 | D17: 0 | E17: 0 | F17: 0 | G17: 1 | H17: 1 | I17: 0 | J17: 0 | K17: 1 | L17: 0 | M17: 1 | N17: 0 | O17: 2 | P17: 0 | Q17: 1 | R17: 1 | S17: 0 | T17: 0 | U17: 0 | V17: 2 | W17: 0 | X17: 0 | Y17: 1 | Z17: 0 | AA17: 0 | AB17: 1 | AC17: 0 | AD17: 1 | AE17: 1 | AF17: 0 | AG17: =SUM(B17:AF17) -> 14
A18: SKU 4 - Yellow w/ Solar | B18: 0 | C18: 0 | D18: 0 | E18: 0 | F18: 0 | G18: 0 | H18: 0 | I18: 0 | J18: 0 | K18: 0 | L18: 0 | M18: 0 | N18: 0 | O18: 0 | P18: 0 | Q18: 0 | R18: 0 | S18: 0 | T18: 0 | U18: 0 | V18: 0 | W18: 0 | X18: 0 | Y18: 0 | Z18: 0 | AA18: 0 | AB18: 0 | AC18: 0 | AD18: 0 | AE18: 0 | AF18: 0 | AG18: =SUM(B18:AF18) -> 0
A19: SUM (SKU 1 - SKU 4) | B19: =SUM(B15:B18) -> 0 | C19: =SUM(C15:C18) -> 2 | D19: =SUM(D15:D18) -> 1 | E19: =SUM(E15:E18) -> 0 | F19: =SUM(F15:F18) -> 0 | G19: =SUM(G15:G18) -> 1 | H19: =SUM(H15:H18) -> 1 | I19: =SUM(I15:I18) -> 0 | ... AF19: =SUM(AF15:AF18) -> 0 | AG19: =SUM(B19:AF19) -> 18
A21: Wall Mount | B21: 2 | C21: 5 | D21: 1 | E21: 0 | F21: 0 | G21: 2 | H21: 1 | I21: 1 | J21: 0 | K21: 1 | L21: 0 | M21: 3 | N21: 1 | O21: 0 | P21: 0 | Q21: 0 | R21: 0 | S21: 0 | T21: 0 | U21: 0 | V21: 0 | W21: 0 | X21: 0 | Y21: 1 | Z21: 0 | AA21: 0 | AB21: 0 | AC21: 0 | AD21: 0 | AE21: 0 | AF21: 1 | AG21: =SUM(B21:AF21) -> 19
A22: Suet Ball Holder | B22: 0 | C22: 0 | D22: 0 | E22: 0 | F22: 0 | G22: 0 | H22: 0 | I22: 0 | J22: 0 | K22: 0 | L22: 0 | M22: 0 | N22: 0 | O22: 0 | P22: 0 | Q22: 0 | R22: 0 | S22: 0 | T22: 0 | U22: 0 | V22: 0 | W22: 0 | X22: 0 | Y22: 0 | Z22: 0 | AA22: 0 | AB22: 0 | AC22: 0 | AD22: 0 | AE22: 0 | AF22: 0 | AG22: =SUM(B22:AF22) -> 0
A23: 3-in-1 Nutrition Set - Blue | B23: 0 | C23: 0 | D23: 0 | E23: 0 | F23: 0 | G23: 1 | H23: 0 | I23: 0 | J23: 0 | K23: 0 | L23: 0 | M23: 0 | N23: 0 | O23: 0 | P23: 0 | Q23: 0 | R23: 0 | S23: 0 | T23: 1 | U23: 0 | V23: 0 | W23: 0 | X23: 0 | Y23: 0 | Z23: 0 | AA23: 0 | AB23: 0 | AC23: 0 | AD23: 0 | AE23: 0 | AF23: 0 | AG23: =SUM(B23:AF23) -> 2
A24: 3-in-1 Nutrition Set - Yellow | B24: 0 | C24: 0 | D24: 0 | E24: 0 | F24: 0 | G24: 0 | H24: 0 | I24: 0 | J24: 0 | K24: 0 | L24: 0 | M24: 0 | N24: 0 | O24: 0 | P24: 0 | Q24: 0 | R24: 0 | S24: 0 | T24: 0 | U24: 0 | V24: 0 | W24: 0 | X24: 0 | Y24: 0 | Z24: 0 | AA24: 0 | AB24: 0 | AC24: 0 | AD24: 0 | AE24: 0 | AF24: 0 | AG24: =SUM(B24:AF24) -> 0
A25: Solar Roof Single - Blue | B25: 0 | C25: 0 | D25: 0 | E25: 0 | F25: 0 | G25: 0 | H25: 0 | I25: 0 | J25: 0 | K25: 0 | L25: 0 | M25: 0 | N25: 0 | O25: 0 | P25: 0 | Q25: 0 | R25: 0 | S25: 0 | T25: 0 | U25: 0 | V25: 0 | W25: 0 | X25: 0 | Y25: 0 | Z25: 0 | AA25: 0 | AB25: 0 | AC25: 0 | AD25: 0 | AE25: 0 | AF25: 0 | AG25: =SUM(B25:AF25) -> 0
A26: Solar Roof Single - Yellow | B26: 0 | C26: 0 | D26: 0 | E26: 0 | F26: 0 | G26: 0 | H26: 0 | I26: 0 | J26: 0 | K26: 0 | L26: 0 | M26: 0 | N26: 0 | O26: 0 | P26: 0 | Q26: 0 | R26: 0 | S26: 0 | T26: 0 | U26: 0 | V26: 0 | W26: 0 | X26: 0 | Y26: 0 | Z26: 0 | AA26: 0 | AB26: 0 | AC26: 0 | AD26: 0 | AE26: 0 | AF26: 0 | AG26: =SUM(B26:AF26) -> 0
A27: Perch Extender - Blue | B27: 0 | C27: 0 | D27: 0 | E27: 0 | F27: 0 | G27: 0 | H27: 0 | I27: 0 | J27: 0 | K27: 0 | L27: 0 | M27: 0 | N27: 0 | O27: 0 | P27: 0 | Q27: 0 | R27: 0 | S27: 0 | T27: 0 | U27: 0 | V27: 0 | W27: 0 | X27: 0 | Y27: 0 | Z27: 0 | AA27: 0 | AB27: 0 | AC27: 0 | AD27: 0 | AE27: 0 | AF27: 0 | AG27: =SUM(B27:AF27) -> 0
A28: Perch Extender - Yellow | B28: 0 | C28: 0 | D28: 0 | E28: 0 | F28: 0 | G28: 0 | H28: 0 | I28: 0 | J28: 0 | K28: 0 | L28: 0 | M28: 0 | N28: 0 | O28: 0 | P28: 0 | Q28: 0 | R28: 0 | S28: 0 | T28: 0 | U28: 0 | V28: 0 | W28: 0 | X28: 0 | Y28: 0 | Z28: 0 | AA28: 0 | AB28: 0 | AC28: 0 | AD28: 0 | AE28: 0 | AF28: 0 | AG28: =SUM(B28:AF28) -> 0
A29: SUM (Add-ons) | B29: =SUM(B21:B28) -> 2 | C29: =SUM(C21:C28) -> 5 | D29: =SUM(D21:D28) -> 1 | E29: =SUM(E21:E28) -> 0 | F29: =SUM(F21:F28) -> 0 | G29: =SUM(G21:G28) -> 3 | H29: =SUM(H21:H28) -> 1 | I29: =SUM(I21:I28) -> 1 | ... AF29: =SUM(AF21:AF28) -> 1 | AG29: =SUM(B29:AF29) -> 21
A31: Units and Revenue Cancelled & Refunds - Walmart
A33: Units Cancelled (Gross) - Walmart
A34: SKU 1 - Blue | AG34: =SUM(B34:AF34) -> 0
A35: SKU 2 - Yellow | AG35: =SUM(B35:AF35) -> 0
A36: SKU 3 - Blue w/ Solar | AG36: =SUM(B36:AF36) -> 0
A37: SKU 4 - Yellow w/ Solar | AG37: =SUM(B37:AF37) -> 0
A38: SUM (SKU 1 + SKU 2) | B38: =SUM(B34:B35) -> 0 | C38: =SUM(C34:C35) -> 0 | D38: =SUM(D34:D35) -> 0 | E38: =SUM(E34:E35) -> 0 | F38: =SUM(F34:F35) -> 0 | G38: =SUM(G34:G35) -> 0 | H38: =SUM(H34:H35) -> 0 | I38: =SUM(I34:I35) -> 0 | ... AF38: =SUM(AF34:AF35) -> 0 | AG38: =SUM(B38:AF38) -> 0
A39: SUM (SKU 3 + SKU 4) | B39: =SUM(B36:B37) -> 0 | C39: =SUM(C36:C37) -> 0 | D39: =SUM(D36:D37) -> 0 | E39: =SUM(E36:E37) -> 0 | F39: =SUM(F36:F37) -> 0 | G39: =SUM(G36:G37) -> 0 | H39: =SUM(H36:H37) -> 0 | I39: =SUM(I36:I37) -> 0 | ... AF39: =SUM(AF36:AF37) -> 0 | AG39: =SUM(B39:AF39) -> 0
A41: Wall Mount | AG41: =SUM(B41:AF41) -> 0
A42: Suet Ball Holder | AG42: =SUM(B42:AF42) -> 0
A43: 3-in-1 Nutrition Set - Blue | AG43: =SUM(B43:AF43) -> 0
A44: 3-in-1 Nutrition Set - Yellow | AG44: =SUM(B44:AF44) -> 0
A45: Solar Roof Single - Blue | AG45: =SUM(B45:AF45) -> 0
A46: Solar Roof Single - Yellow | AG46: =SUM(B46:AF46) -> 0
A47: Perch Extender - Blue | AG47: =SUM(B47:AF47) -> 0
A48: Perch Extender - Yellow | AG48: =SUM(B48:AF48) -> 0
A49: SUM (Add-ons) | B49: =SUM(B41:B48) -> 0 | C49: =SUM(C41:C48) -> 0 | D49: =SUM(D41:D48) -> 0 | E49: =SUM(E41:E48) -> 0 | F49: =SUM(F41:F48) -> 0 | G49: =SUM(G41:G48) -> 0 | H49: =SUM(H41:H48) -> 0 | I49: =SUM(I41:I48) -> 0 | ... AF49: =SUM(AF41:AF48) -> 0 | AG49: =SUM(B49:AF49) -> 0
A51: Revenue Cancelled (Gross) - Walmart
A52: Hardware | AG52: =SUM(B52:AF52) -> 0
A53: Shipping | AG53: =SUM(B53:AF53) -> 0
A54: Taxes | AG54: =SUM(B54:AF54) -> 0
A55: All NA | B55: =SUM(B52:B54) -> 0 | C55: =SUM(C52:C54) -> 0 | D55: =SUM(D52:D54) -> 0 | E55: =SUM(E52:E54) -> 0 | F55: =SUM(F52:F54) -> 0 | G55: =SUM(G52:G54) -> 0 | H55: =SUM(H52:H54) -> 0 | I55: =SUM(I52:I54) -> 0 | ... AF55: =SUM(AF52:AF54) -> 0 | AG55: =SUM(B55:AF55) -> 0
A57: Hardware - Europe | AG57: =SUM(B57:AF57) -> 0
A58: Shipping - Europe | AG58: =SUM(B58:AF58) -> 0
A59: All EU | B59: =sum(B57:B58) -> 0 | C59: =sum(C57:C58) -> 0 | D59: =sum(D57:D58) -> 0 | E59: =sum(E57:E58) -> 0 | F59: =sum(F57:F58) -> 0 | G59: =sum(G57:G58) -> 0 | H59: =sum(H57:H58) -> 0 | I59: =sum(I57:I58) -> 0 | ... AF59: =sum(AF57:AF58) -> 0 | AG59: =SUM(B59:AF59) -> 0
A61: Units Refund (Gross) - Walmart
A62: SKU 1 - Blue | AG62: =SUM(B62:AF62) -> 0
A63: SKU 2 - Yellow | AG63: =SUM(B63:AF63) -> 0
A64: SKU 3 - Blue w/ Solar | AG64: =SUM(B64:AF64) -> 0
A65: SKU 4 - Yellow w/ Solar | AG65: =SUM(B65:AF65) -> 0
A66: SUM (SKU 1 + SKU 2) | B66: =SUM(B62:B63) -> 0 | C66: =SUM(C62:C63) -> 0 | D66: =SUM(D62:D63) -> 0 | E66: =SUM(E62:E63) -> 0 | F66: =SUM(F62:F63) -> 0 | G66: =SUM(G62:G63) -> 0 | H66: =SUM(H62:H63) -> 0 | I66: =SUM(I62:I63) -> 0 | ... AF66: =SUM(AF62:AF63) -> 0 | AG66: =SUM(B66:AF66) -> 0
A67: SUM (SKU 3 + SKU 4) | B67: =SUM(B64:B65) -> 0 | C67: =SUM(C64:C65) -> 0 | D67: =SUM(D64:D65) -> 0 | E67: =SUM(E64:E65) -> 0 | F67: =SUM(F64:F65) -> 0 | G67: =SUM(G64:G65) -> 0 | H67: =SUM(H64:H65) -> 0 | I67: =SUM(I64:I65) -> 0 | ... AF67: =SUM(AF64:AF65) -> 0 | AG67: =SUM(B67:AF67) -> 0
A69: Wall Mount | AG69: =SUM(B69:AF69) -> 0
A70: Suet Ball Holder | AG70: =SUM(B70:AF70) -> 0
A71: 3-in-1 Nutrition Set - Blue | AG71: =SUM(B71:AF71) -> 0
A72: 3-in-1 Nutrition Set - Yellow | AG72: =SUM(B72:AF72) -> 0
A73: Solar Roof Single - Blue | AG73: =SUM(B73:AF73) -> 0
A74: Solar Roof Single - Yellow | AG74: =SUM(B74:AF74) -> 0
A75: Perch Extender - Blue | AG75: =SUM(B75:AF75) -> 0
A76: Perch Extender - Yellow | AG76: =SUM(B76:AF76) -> 0
A77: SUM (Add-ons) | B77: =SUM(B69:B76) -> 0 | C77: =SUM(C69:C76) -> 0 | D77: =SUM(D69:D76) -> 0 | E77: =SUM(E69:E76) -> 0 | F77: =SUM(F69:F76) -> 0 | G77: =SUM(G69:G76) -> 0 | H77: =SUM(H69:H76) -> 0 | I77: =SUM(I69:I76) -> 0 | ... AF77: =SUM(AF69:AF76) -> 0 | AG77: =SUM(B77:AF77) -> 0
A79: Orders Return for Refund | AG79: =SUM(B79:AF79) -> 0
A81: Revenue Refunded (Gross) - Walmart
A82: Hardware | AG82: =SUM(B82:AF82) -> 0
A83: Shipping | AG83: =SUM(B83:AF83) -> 0
A84: Taxes | AG84: =SUM(B84:AF84) -> 0
A85: All NA | B85: =sum(B82:B84) -> 0 | C85: =sum(C82:C84) -> 0 | D85: =sum(D82:D84) -> 0 | E85: =sum(E82:E84) -> 0 | F85: =sum(F82:F84) -> 0 | G85: =sum(G82:G84) -> 0 | H85: =sum(H82:H84) -> 0 | I85: =sum(I82:I84) -> 0 | ... AF85: =sum(AF82:AF84) -> 0 | AG85: =SUM(B85:AF85) -> 0
A87: Hardware - Europe | AG87: =SUM(B87:AF87) -> 0
A88: Shipping - Europe | AG88: =SUM(B88:AF88) -> 0
A89: All EU | B89: =sum(B87:B88) -> 0 | C89: =sum(C87:C88) -> 0 | D89: =sum(D87:D88) -> 0 | E89: =sum(E87:E88) -> 0 | F89: =sum(F87:F88) -> 0 | G89: =sum(G87:G88) -> 0 | H89: =sum(H87:H88) -> 0 | I89: =sum(I87:I88) -> 0 | ... AF89: =sum(AF87:AF88) -> 0 | AG89: =SUM(B89:AF89) -> 0
A91: RETURN (Replacement Units & Claims) - Walmart
A92: SKU 1 - Blue | B92: 0 | C92: 0 | D92: 0 | E92: 0 | F92: 0 | G92: 0 | H92: 0 | I92: 0 | J92: 0 | K92: 0 | L92: 0 | M92: 0 | N92: 0 | O92: 0 | P92: 0 | Q92: 0 | R92: 0 | S92: 0 | T92: 0 | U92: 0 | V92: 0 | W92: 0 | X92: 0 | Y92: 0 | Z92: 0 | AA92: 0 | AB92: 0 | AC92: 0 | AD92: 0 | AE92: 0 | AF92: 0 | AG92: =SUM(B92:AF92) -> 0
A93: SKU 2 - Yellow | B93: 0 | C93: 0 | D93: 0 | E93: 0 | F93: 0 | G93: 0 | H93: 0 | I93: 0 | J93: 0 | K93: 0 | L93: 0 | M93: 0 | N93: 0 | O93: 0 | P93: 0 | Q93: 0 | R93: 0 | S93: 0 | T93: 0 | U93: 0 | V93: 0 | W93: 0 | X93: 0 | Y93: 0 | Z93: 0 | AA93: 0 | AB93: 0 | AC93: 0 | AD93: 0 | AE93: 0 | AF93: 0 | AG93: =SUM(B93:AF93) -> 0
A94: SKU 3 - Blue w/ Solar | B94: 0 | C94: 0 | D94: 0 | E94: 0 | F94: 0 | G94: 0 | H94: 0 | I94: 0 | J94: 0 | K94: 0 | L94: 0 | M94: 0 | N94: 0 | O94: 0 | P94: 0 | Q94: 0 | R94: 0 | S94: 0 | T94: 0 | U94: 0 | V94: 0 | W94: 0 | X94: 0 | Y94: 0 | Z94: 0 | AA94: 0 | AB94: 0 | AC94: 0 | AD94: 0 | AE94: 0 | AF94: 0 | AG94: =SUM(B94:AF94) -> 0
A95: SKU 4 - Yellow w/ Solar | B95: 0 | C95: 0 | D95: 0 | E95: 0 | F95: 0 | G95: 0 | H95: 0 | I95: 0 | J95: 0 | K95: 0 | L95: 0 | M95: 0 | N95: 0 | O95: 0 | P95: 0 | Q95: 0 | R95: 0 | S95: 0 | T95: 0 | U95: 0 | V95: 0 | W95: 0 | X95: 0 | Y95: 0 | Z95: 0 | AA95: 0 | AB95: 0 | AC95: 0 | AD95: 0 | AE95: 0 | AF95: 0 | AG95: =SUM(B95:AF95) -> 0
A96: SUM (SKU 1 + SKU 2) | B96: 0 | C96: 0 | D96: 0 | E96: 0 | F96: 0 | G96: 0 | H96: 0 | I96: 0 | J96: 0 | K96: 0 | L96: 0 | M96: 0 | N96: 0 | O96: 0 | P96: 0 | Q96: 0 | R96: 0 | S96: 0 | T96: 0 | U96: 0 | V96: 0 | W96: 0 | X96: 0 | Y96: 0 | Z96: 0 | AA96: 0 | AB96: 0 | AC96: 0 | AD96: 0 | AE96: 0 | AF96: 0 | AG96: =SUM(B96:AF96) -> 0
A97: SUM (SKU 3 + SKU 4) | B97: 0 | C97: 0 | D97: 0 | E97: 0 | F97: 0 | G97: 0 | H97: 0 | I97: 0 | J97: 0 | K97: 0 | L97: 0 | M97: 0 | N97: 0 | O97: 0 | P97: 0 | Q97: 0 | R97: 0 | S97: 0 | T97: 0 | U97: 0 | V97: 0 | W97: 0 | X97: 0 | Y97: 0 | Z97: 0 | AA97: 0 | AB97: 0 | AC97: 0 | AD97: 0 | AE97: 0 | AF97: 0 | AG97: =SUM(B97:AF97) -> 0
AG98: =SUM(B98:AF98) -> 0
A99: Wall Mount | B99: 0 | C99: 0 | D99: 0 | E99: 0 | F99: 0 | G99: 0 | H99: 0 | I99: 0 | J99: 0 | K99: 0 | L99: 0 | M99: 0 | N99: 0 | O99: 0 | P99: 0 | Q99: 0 | R99: 0 | S99: 0 | T99: 0 | U99: 0 | V99: 0 | W99: 0 | X99: 0 | Y99: 0 | Z99: 0 | AA99: 0 | AB99: 0 | AC99: 0 | AD99: 0 | AE99: 0 | AF99: 0 | AG99: =SUM(B99:AF99) -> 0
A100: Suet Ball Holder | B100: 0 | C100: 0 | D100: 0 | E100: 0 | F100: 0 | G100: 0 | H100: 0 | I100: 0 | J100: 0 | K100: 0 | L100: 0 | M100: 0 | N100: 0 | O100: 0 | P100: 0 | Q100: 0 | R100: 0 | S100: 0 | T100: 0 | U100: 0 | V100: 0 | W100: 0 | X100: 0 | Y100: 0 | Z100: 0 | AA100: 0 | AB100: 0 | AC100: 0 | AD100: 0 | AE100: 0 | AF100: 0 | AG100: =SUM(B100:AF100) -> 0
A101: 3-in-1 Nutrition Set - Blue | B101: 0 | C101: 0 | D101: 0 | E101: 0 | F101: 0 | G101: 0 | H101: 0 | I101: 0 | J101: 0 | K101: 0 | L101: 0 | M101: 0 | N101: 0 | O101: 0 | P101: 0 | Q101: 0 | R101: 0 | S101: 0 | T101: 0 | U101: 0 | V101: 0 | W101: 0 | X101: 0 | Y101: 0 | Z101: 0 | AA101: 0 | AB101: 0 | AC101: 0 | AD101: 0 | AE101: 0 | AF101: 0 | AG101: =SUM(B101:AF101) -> 0
A102: 3-in-1 Nutrition Set - Yellow | B102: 0 | C102: 0 | D102: 0 | E102: 0 | F102: 0 | G102: 0 | H102: 0 | I102: 0 | J102: 0 | K102: 0 | L102: 0 | M102: 0 | N102: 0 | O102: 0 | P102: 0 | Q102: 0 | R102: 0 | S102: 0 | T102: 0 | U102: 0 | V102: 0 | W102: 0 | X102: 0 | Y102: 0 | Z102: 0 | AA102: 0 | AB102: 0 | AC102: 0 | AD102: 0 | AE102: 0 | AF102: 0 | AG102: =SUM(B102:AF102) -> 0
A103: Solar Roof Single - Blue | B103: 0 | C103: 0 | D103: 0 | E103: 0 | F103: 0 | G103: 0 | H103: 0 | I103: 0 | J103: 0 | K103: 0 | L103: 0 | M103: 0 | N103: 0 | O103: 0 | P103: 0 | Q103: 0 | R103: 0 | S103: 0 | T103: 0 | U103: 0 | V103: 0 | W103: 0 | X103: 0 | Y103: 0 | Z103: 0 | AA103: 0 | AB103: 0 | AC103: 0 | AD103: 0 | AE103: 0 | AF103: 0 | AG103: =SUM(B103:AF103) -> 0
A104: Solar Roof Single - Yellow | B104: 0 | C104: 0 | D104: 0 | E104: 0 | F104: 0 | G104: 0 | H104: 0 | I104: 0 | J104: 0 | K104: 0 | L104: 0 | M104: 0 | N104: 0 | O104: 0 | P104: 0 | Q104: 0 | R104: 0 | S104: 0 | T104: 0 | U104: 0 | V104: 0 | W104: 0 | X104: 0 | Y104: 0 | Z104: 0 | AA104: 0 | AB104: 0 | AC104: 0 | AD104: 0 | AE104: 0 | AF104: 0 | AG104: =SUM(B104:AF104) -> 0
A105: Perch Extender - Blue | B105: 0 | C105: 0 | D105: 0 | E105: 0 | F105: 0 | G105: 0 | H105: 0 | I105: 0 | J105: 0 | K105: 0 | L105: 0 | M105: 0 | N105: 0 | O105: 0 | P105: 0 | Q105: 0 | R105: 0 | S105: 0 | T105: 0 | U105: 0 | V105: 0 | W105: 0 | X105: 0 | Y105: 0 | Z105: 0 | AA105: 0 | AB105: 0 | AC105: 0 | AD105: 0 | AE105: 0 | AF105: 0 | AG105: =SUM(B105:AF105) -> 0
A106: Perch Extender - Yellow | B106: 0 | C106: 0 | D106: 0 | E106: 0 | F106: 0 | G106: 0 | H106: 0 | I106: 0 | J106: 0 | K106: 0 | L106: 0 | M106: 0 | N106: 0 | O106: 0 | P106: 0 | Q106: 0 | R106: 0 | S106: 0 | T106: 0 | U106: 0 | V106: 0 | W106: 0 | X106: 0 | Y106: 0 | Z106: 0 | AA106: 0 | AB106: 0 | AC106: 0 | AD106: 0 | AE106: 0 | AF106: 0 | AG106: =SUM(B106:AF106) -> 0
A107: SUM (Add-ons) | B107: 0 | C107: 0 | D107: 0 | E107: 0 | F107: 0 | G107: 0 | H107: 0 | I107: 0 | J107: 0 | K107: 0 | L107: 0 | M107: 0 | N107: 0 | O107: 0 | P107: 0 | Q107: 0 | R107: 0 | S107: 0 | T107: 0 | U107: 0 | V107: 0 | W107: 0 | X107: 0 | Y107: 0 | Z107: 0 | AA107: 0 | AB107: 0 | AC107: 0 | AD107: 0 | AE107: 0 | AF107: 0 | AG107: =SUM(B107:AF107) -> 0
A109: Parts
A110: Housing - Blue | B110: 0 | C110: 0 | D110: 0 | E110: 0 | F110: 0 | G110: 0 | H110: 0 | I110: 0 | J110: 0 | K110: 0 | L110: 0 | M110: 0 | N110: 0 | O110: 0 | P110: 0 | Q110: 0 | R110: 0 | S110: 0 | T110: 0 | U110: 0 | V110: 0 | W110: 0 | X110: 0 | Y110: 0 | Z110: 0 | AA110: 0 | AB110: 0 | AC110: 0 | AD110: 0 | AE110: 0 | AF110: 0 | AG110: =SUM(B110:AF110) -> 0
A111: Housing - Yellow | B111: 0 | C111: 0 | D111: 0 | E111: 0 | F111: 0 | G111: 0 | H111: 0 | I111: 0 | J111: 0 | K111: 0 | L111: 0 | M111: 0 | N111: 0 | O111: 0 | P111: 0 | Q111: 0 | R111: 0 | S111: 0 | T111: 0 | U111: 0 | V111: 0 | W111: 0 | X111: 0 | Y111: 0 | Z111: 0 | AA111: 0 | AB111: 0 | AC111: 0 | AD111: 0 | AE111: 0 | AF111: 0 | AG111: =SUM(B111:AF111) -> 0
A112: Camera Module | B112: 0 | C112: 0 | D112: 0 | E112: 0 | F112: 0 | G112: 0 | H112: 0 | I112: 0 | J112: 0 | K112: 0 | L112: 0 | M112: 0 | N112: 0 | O112: 0 | P112: 0 | Q112: 0 | R112: 0 | S112: 0 | T112: 0 | U112: 0 | V112: 0 | W112: 0 | X112: 0 | Y112: 0 | Z112: 0 | AA112: 0 | AB112: 0 | AC112: 0 | AD112: 0 | AE112: 0 | AF112: 0 | AG112: =SUM(B112:AF112) -> 0
A114: Orders Replaced NA | B114: 0 | C114: 0 | D114: 0 | E114: 0 | F114: 0 | G114: 0 | H114: 0 | I114: 0 | J114: 0 | K114: 0 | L114: 0 | M114: 0 | N114: 0 | O114: 0 | P114: 0 | Q114: 0 | R114: 0 | S114: 0 | T114: 0 | U114: 0 | V114: 0 | W114: 0 | X114: 0 | Y114: 0 | Z114: 0 | AA114: 0 | AB114: 0 | AC114: 0 | AD114: 0 | AE114: 0 | AF114: 0 | AG114: =SUM(B114:AF114) -> 0
A119: Gross Cost
A120: Media Spend | B120: 0 | C120: 0 | D120: 0 | E120: 0 | F120: 0 | G120: 0 | H120: 0 | I120: 0 | J120: 0 | K120: 0 | L120: 0 | M120: 0 | N120: 0 | O120: 0 | P120: 0 | Q120: 0 | R120: 0 | S120: 0 | T120: 0 | U120: 0 | V120: 0 | W120: 0 | X120: 0 | Y120: 0 | Z120: 0 | AA120: 0 | AB120: 0 | AC120: 0 | AD120: 0 | AE120: 0 | AF120: 0 | AG120: =SUM(B120:AF120) -> 0
...

Sheet COSTCO - P&L
A1: JANUARY | B1: 45658 | C1: 45659 | D1: 45660 | E1: 45661 | F1: 45662 | G1: 45663 | H1: 45664 | I1: 45665 | J1: 45666 | K1: 45667 | L1: 45668 | M1: 45669 | N1: 45670 | O1: 45671 | P1: 45672 | Q1: 45673 | R1: 45674 | S1: 45675 | T1: 45676 | U1: 45677 | V1: 45678 | W1: 45679 | X1: 45680 | Y1: 45681 | Z1: 45682 | AA1: 45683 | AB1: 45684 | AC1: 45685 | AD1: 45686 | AE1: 45687 | AF1: 45688
A2: DAY | B2: WED | C2: THU | D2: FRI | E2: SAT | F2: SUN | G2: MON | H2: TUE | I2: WED | J2: THU | K2: FRI | L2: SAT | M2: SUN | N2: MON | O2: TUE | P2: WED | Q2: THU | R2: FRI | S2: SAT | T2: SUN | U2: MON | V2: TUE | W2: WED | X2: THU | Y2: FRI | Z2: SAT | AA2: SUN | AB2: MON | AC2: TUE | AD2: WED | AE2: THU | AF2: FRI
A3: Costco
A4: Revenue | B4: =Summary!B45 -> 0 | C4: =Summary!C45 -> 0 | D4: =Summary!D45 -> 0 | E4: =Summary!E45 -> 0 | F4: =Summary!F45 -> 0 | G4: =Summary!G45 -> 0 | H4: =Summary!H45 -> 0 | I4: =Summary!I45 -> 0 | ... AF4: =Summary!AF45 -> 1188.7255 | AG4: =SUM(B4:AF4) -> 1188.7255
A5: Breakdown | AG5: =SUM(B5:AF5) -> 0
A6: - Tax | B6: =Summary!B47 -> 0 | C6: =Summary!C47 -> 0 | D6: =Summary!D47 -> 0 | E6: =Summary!E47 -> 0 | F6: =Summary!F47 -> 0 | G6: =Summary!G47 -> 0 | H6: =Summary!H47 -> 0 | I6: =Summary!I47 -> 0 | ... AF6: =Summary!AF47 -> 68.765544 | AG6: =SUM(B6:AF6) -> 68.765544
A7: - Shipping | B7: =Summary!B48 | C7: =Summary!C48 | D7: =Summary!D48 | E7: =Summary!E48 | F7: =Summary!F48 | G7: =Summary!G48 | H7: =Summary!H48 | I7: =Summary!I48 | ... AF7: =Summary!AF48 | AG7: =SUM(B7:AF7) -> 0
A8: Orders | B8: =Summary!B104 | C8: =Summary!C104 | D8: =Summary!D104 | E8: =Summary!E104 | F8: =Summary!F104 | G8: =Summary!G104 | H8: =Summary!H104 | I8: =Summary!I104 | ... AF8: =Summary!AF104 -> 4 | AG8: =SUM(B8:AF8) -> 4
A10: Media Cost
A12: Costco Fees (14%) | AG12: =SUM(B12:AF12) -> 0
A14: Units Sold (Gross) - Costco
A15: SKU 1 - Blue | B15: 0 | C15: 0 | D15: 0 | E15: 0 | F15: 0 | G15: 0 | H15: 0 | I15: 0 | J15: 0 | K15: 0 | L15: 0 | M15: 0 | N15: 0 | O15: 0 | P15: 0 | Q15: 0 | R15: 0 | S15: 0 | T15: 0 | U15: 0 | V15: 0 | W15: 0 | X15: 0 | Y15: 0 | Z15: 0 | AA15: 0 | AB15: 0 | AC15: 0 | AD15: 0 | AE15: 0 | AF15: 0 | AG15: =SUM(B15:AF15) -> 0
A16: SKU 2 - Yellow | B16: 0 | C16: 0 | D16: 0 | E16: 0 | F16: 0 | G16: 0 | H16: 0 | I16: 0 | J16: 0 | K16: 0 | L16: 0 | M16: 0 | N16: 0 | O16: 0 | P16: 0 | Q16: 0 | R16: 0 | S16: 0 | T16: 0 | U16: 0 | V16: 0 | W16: 0 | X16: 0 | Y16: 0 | Z16: 0 | AA16: 0 | AB16: 0 | AC16: 0 | AD16: 0 | AE16: 0 | AF16: 0 | AG16: =SUM(B16:AF16) -> 0
A17: SKU 3 - Blue w/ Solar | B17: 0 | C17: 0 | D17: 0 | E17: 0 | F17: 0 | G17: 0 | H17: 0 | I17: 0 | J17: 0 | K17: 0 | L17: 0 | M17: 0 | N17: 0 | O17: 0 | P17: 0 | Q17: 0 | R17: 0 | S17: 0 | T17: 0 | U17: 0 | V17: 0 | W17: 0 | X17: 0 | Y17: 0 | Z17: 0 | AA17: 0 | AB17: 0 | AC17: 0 | AD17: 0 | AE17: 0 | AF17: 4 | AG17: =SUM(B17:AF17) -> 4
A18: SKU 4 - Yellow w/ Solar | B18: 0 | C18: 0 | D18: 0 | E18: 0 | F18: 0 | G18: 0 | H18: 0 | I18: 0 | J18: 0 | K18: 0 | L18: 0 | M18: 0 | N18: 0 | O18: 0 | P18: 0 | Q18: 0 | R18: 0 | S18: 0 | T18: 0 | U18: 0 | V18: 0 | W18: 0 | X18: 0 | Y18: 0 | Z18: 0 | AA18: 0 | AB18: 0 | AC18: 0 | AD18: 0 | AE18: 0 | AF18: 0 | AG18: =SUM(B18:AF18) -> 0
A19: SUM (SKU 1 - SKU 4) | B19: =SUM(B15:B18) -> 0 | C19: =SUM(C15:C18) -> 0 | D19: =SUM(D15:D18) -> 0 | E19: =SUM(E15:E18) -> 0 | F19: =SUM(F15:F18) -> 0 | G19: =SUM(G15:G18) -> 0 | H19: =SUM(H15:H18) -> 0 | I19: =SUM(I15:I18) -> 0 | ... AF19: =SUM(AF15:AF18) -> 4 | AG19: =SUM(B19:AF19) -> 4
A21: Wall Mount | B21: 0 | C21: 0 | D21: 0 | E21: 0 | F21: 0 | G21: 0 | H21: 0 | I21: 0 | J21: 0 | K21: 0 | L21: 0 | M21: 0 | N21: 0 | O21: 0 | P21: 0 | Q21: 0 | R21: 0 | S21: 0 | T21: 0 | U21: 0 | V21: 0 | W21: 0 | X21: 0 | Y21: 0 | Z21: 0 | AA21: 0 | AB21: 0 | AC21: 0 | AD21: 0 | AE21: 0 | AF21: 0 | AG21: =SUM(B21:AF21) -> 0
A22: Suet Ball Holder | B22: 0 | C22: 0 | D22: 0 | E22: 0 | F22: 0 | G22: 0 | H22: 0 | I22: 0 | J22: 0 | K22: 0 | L22: 0 | M22: 0 | N22: 0 | O22: 0 | P22: 0 | Q22: 0 | R22: 0 | S22: 0 | T22: 0 | U22: 0 | V22: 0 | W22: 0 | X22: 0 | Y22: 0 | Z22: 0 | AA22: 0 | AB22: 0 | AC22: 0 | AD22: 0 | AE22: 0 | AF22: 0 | AG22: =SUM(B22:AF22) -> 0
A23: 3-in-1 Nutrition Set - Blue | B23: 0 | C23: 0 | D23: 0 | E23: 0 | F23: 0 | G23: 0 | H23: 0 | I23: 0 | J23: 0 | K23: 0 | L23: 0 | M23: 0 | N23: 0 | O23: 0 | P23: 0 | Q23: 0 | R23: 0 | S23: 0 | T23: 0 | U23: 0 | V23: 0 | W23: 0 | X23: 0 | Y23: 0 | Z23: 0 | AA23: 0 | AB23: 0 | AC23: 0 | AD23: 0 | AE23: 0 | AF23: 4 | AG23: =SUM(B23:AF23) -> 4
A24: 3-in-1 Nutrition Set - Yellow | B24: 0 | C24: 0 | D24: 0 | E24: 0 | F24: 0 | G24: 0 | H24: 0 | I24: 0 | J24: 0 | K24: 0 | L24: 0 | M24: 0 | N24: 0 | O24: 0 | P24: 0 | Q24: 0 | R24: 0 | S24: 0 | T24: 0 | U24: 0 | V24: 0 | W24: 0 | X24: 0 | Y24: 0 | Z24: 0 | AA24: 0 | AB24: 0 | AC24: 0 | AD24: 0 | AE24: 0 | AF24: 0 | AG24: =SUM(B24:AF24) -> 0
A25: Solar Roof Single - Blue | B25: 0 | C25: 0 | D25: 0 | E25: 0 | F25: 0 | G25: 0 | H25: 0 | I25: 0 | J25: 0 | K25: 0 | L25: 0 | M25: 0 | N25: 0 | O25: 0 | P25: 0 | Q25: 0 | R25: 0 | S25: 0 | T25: 0 | U25: 0 | V25: 0 | W25: 0 | X25: 0 | Y25: 0 | Z25: 0 | AA25: 0 | AB25: 0 | AC25: 0 | AD25: 0 | AE25: 0 | AF25: 0 | AG25: =SUM(B25:AF25) -> 0
A26: Solar Roof Single - Yellow | B26: 0 | C26: 0 | D26: 0 | E26: 0 | F26: 0 | G26: 0 | H26: 0 | I26: 0 | J26: 0 | K26: 0 | L26: 0 | M26: 0 | N26: 0 | O26: 0 | P26: 0 | Q26: 0 | R26: 0 | S26: 0 | T26: 0 | U26: 0 | V26: 0 | W26: 0 | X26: 0 | Y26: 0 | Z26: 0 | AA26: 0 | AB26: 0 | AC26: 0 | AD26: 0 | AE26: 0 | AF26: 0 | AG26: =SUM(B26:AF26) -> 0
A27: Perch Extender - Blue | B27: 0 | C27: 0 | D27: 0 | E27: 0 | F27: 0 | G27: 0 | H27: 0 | I27: 0 | J27: 0 | K27: 0 | L27: 0 | M27: 0 | N27: 0 | O27: 0 | P27: 0 | Q27: 0 | R27: 0 | S27: 0 | T27: 0 | U27: 0 | V27: 0 | W27: 0 | X27: 0 | Y27: 0 | Z27: 0 | AA27: 0 | AB27: 0 | AC27: 0 | AD27: 0 | AE27: 0 | AF27: 0 | AG27: =SUM(B27:AF27) -> 0
A28: Perch Extender - Yellow | B28: 0 | C28: 0 | D28: 0 | E28: 0 | F28: 0 | G28: 0 | H28: 0 | I28: 0 | J28: 0 | K28: 0 | L28: 0 | M28: 0 | N28: 0 | O28: 0 | P28: 0 | Q28: 0 | R28: 0 | S28: 0 | T28: 0 | U28: 0 | V28: 0 | W28: 0 | X28: 0 | Y28: 0 | Z28: 0 | AA28: 0 | AB28: 0 | AC28: 0 | AD28: 0 | AE28: 0 | AF28: 0 | AG28: =SUM(B28:AF28) -> 0
A29: SUM (Add-ons) | B29: =SUM(B21:B28) -> 0 | C29: =SUM(C21:C28) -> 0 | D29: =SUM(D21:D28) -> 0 | E29: =SUM(E21:E28) -> 0 | F29: =SUM(F21:F28) -> 0 | G29: =SUM(G21:G28) -> 0 | H29: =SUM(H21:H28) -> 0 | I29: =SUM(I21:I28) -> 0 | ... AF29: =SUM(AF21:AF28) -> 4 | AG29: =SUM(B29:AF29) -> 4
A31: Units and Revenue Cancelled & Refunds - Costco
A33: Units Cancelled (Gross) - Costco
A34: SKU 1 - Blue | AG34: =SUM(B34:AF34) -> 0
A35: SKU 2 - Yellow | AG35: =SUM(B35:AF35) -> 0
A36: SKU 3 - Blue w/ Solar | AG36: =SUM(B36:AF36) -> 0
A37: SKU 4 - Yellow w/ Solar | AG37: =SUM(B37:AF37) -> 0
A38: SUM (SKU 1 + SKU 2) | B38: =SUM(B34:B35) -> 0 | C38: =SUM(C34:C35) -> 0 | D38: =SUM(D34:D35) -> 0 | E38: =SUM(E34:E35) -> 0 | F38: =SUM(F34:F35) -> 0 | G38: =SUM(G34:G35) -> 0 | H38: =SUM(H34:H35) -> 0 | I38: =SUM(I34:I35) -> 0 | ... AF38: =SUM(AF34:AF35) -> 0 | AG38: =SUM(B38:AF38) -> 0
A39: SUM (SKU 3 + SKU 4) | B39: =SUM(B36:B37) -> 0 | C39: =SUM(C36:C37) -> 0 | D39: =SUM(D36:D37) -> 0 | E39: =SUM(E36:E37) -> 0 | F39: =SUM(F36:F37) -> 0 | G39: =SUM(G36:G37) -> 0 | H39: =SUM(H36:H37) -> 0 | I39: =SUM(I36:I37) -> 0 | ... AF39: =SUM(AF36:AF37) -> 0 | AG39: =SUM(B39:AF39) -> 0
A41: Wall Mount | AG41: =SUM(B41:AF41) -> 0
A42: Suet Ball Holder | AG42: =SUM(B42:AF42) -> 0
A43: 3-in-1 Nutrition Set - Blue | AG43: =SUM(B43:AF43) -> 0
A44: 3-in-1 Nutrition Set - Yellow | AG44: =SUM(B44:AF44) -> 0
A45: Solar Roof Single - Blue | AG45: =SUM(B45:AF45) -> 0
A46: Solar Roof Single - Yellow | AG46: =SUM(B46:AF46) -> 0
A47: Perch Extender - Blue | AG47: =SUM(B47:AF47) -> 0
A48: Perch Extender - Yellow | AG48: =SUM(B48:AF48) -> 0
A49: SUM (Add-ons) | B49: =SUM(B41:B48) -> 0 | C49: =SUM(C41:C48) -> 0 | D49: =SUM(D41:D48) -> 0 | E49: =SUM(E41:E48) -> 0 | F49: =SUM(F41:F48) -> 0 | G49: =SUM(G41:G48) -> 0 | H49: =SUM(H41:H48) -> 0 | I49: =SUM(I41:I48) -> 0 | ... AF49: =SUM(AF41:AF48) -> 0 | AG49: =SUM(B49:AF49) -> 0
A51: Revenue Cancelled (Gross) - Costco
A52: Hardware | AG52: =SUM(B52:AF52) -> 0
A53: Shipping | AG53: =SUM(B53:AF53) -> 0
A54: Taxes | AG54: =SUM(B54:AF54) -> 0
A55: All NA | B55: =SUM(B52:B54) -> 0 | C55: =SUM(C52:C54) -> 0 | D55: =SUM(D52:D54) -> 0 | E55: =SUM(E52:E54) -> 0 | F55: =SUM(F52:F54) -> 0 | G55: =SUM(G52:G54) -> 0 | H55: =SUM(H52:H54) -> 0 | I55: =SUM(I52:I54) -> 0 | ... AF55: =SUM(AF52:AF54) -> 0 | AG55: =SUM(B55:AF55) -> 0
A57: Hardware - Europe | AG57: =SUM(B57:AF57) -> 0
A58: Shipping - Europe | AG58: =SUM(B58:AF58) -> 0
A59: All EU | B59: =sum(B57:B58) -> 0 | C59: =sum(C57:C58) -> 0 | D59: =sum(D57:D58) -> 0 | E59: =sum(E57:E58) -> 0 | F59: =sum(F57:F58) -> 0 | G59: =sum(G57:G58) -> 0 | H59: =sum(H57:H58) -> 0 | I59: =sum(I57:I58) -> 0 | ... AF59: =sum(AF57:AF58) -> 0 | AG59: =SUM(B59:AF59) -> 0
A61: Units Refund (Gross) - Costco
A62: SKU 1 - Blue | AG62: =SUM(B62:AF62) -> 0
A63: SKU 2 - Yellow | AG63: =SUM(B63:AF63) -> 0
A64: SKU 3 - Blue w/ Solar | AG64: =SUM(B64:AF64) -> 0
A65: SKU 4 - Yellow w/ Solar | AG65: =SUM(B65:AF65) -> 0
A66: SUM (SKU 1 + SKU 2) | B66: =SUM(B62:B63) -> 0 | C66: =SUM(C62:C63) -> 0 | D66: =SUM(D62:D63) -> 0 | E66: =SUM(E62:E63) -> 0 | F66: =SUM(F62:F63) -> 0 | G66: =SUM(G62:G63) -> 0 | H66: =SUM(H62:H63) -> 0 | I66: =SUM(I62:I63) -> 0 | ... AF66: =SUM(AF62:AF63) -> 0 | AG66: =SUM(B66:AF66) -> 0
A67: SUM (SKU 3 + SKU 4) | B67: =SUM(B64:B65) -> 0 | C67: =SUM(C64:C65) -> 0 | D67: =SUM(D64:D65) -> 0 | E67: =SUM(E64:E65) -> 0 | F67: =SUM(F64:F65) -> 0 | G67: =SUM(G64:G65) -> 0 | H67: =SUM(H64:H65) -> 0 | I67: =SUM(I64:I65) -> 0 | ... AF67: =SUM(AF64:AF65) -> 0 | AG67: =SUM(B67:AF67) -> 0
A69: Wall Mount | AG69: =SUM(B69:AF69) -> 0
A70: Suet Ball Holder | AG70: =SUM(B70:AF70) -> 0
A71: 3-in-1 Nutrition Set - Blue | AG71: =SUM(B71:AF71) -> 0
A72: 3-in-1 Nutrition Set - Yellow | AG72: =SUM(B72:AF72) -> 0
A73: Solar Roof Single - Blue | AG73: =SUM(B73:AF73) -> 0
A74: Solar Roof Single - Yellow | AG74: =SUM(B74:AF74) -> 0
A75: Perch Extender - Blue | AG75: =SUM(B75:AF75) -> 0
A76: Perch Extender - Yellow | AG76: =SUM(B76:AF76) -> 0
A77: SUM (Add-ons) | B77: =SUM(B69:B76) -> 0 | C77: =SUM(C69:C76) -> 0 | D77: =SUM(D69:D76) -> 0 | E77: =SUM(E69:E76) -> 0 | F77: =SUM(F69:F76) -> 0 | G77: =SUM(G69:G76) -> 0 | H77: =SUM(H69:H76) -> 0 | I77: =SUM(I69:I76) -> 0 | ... AF77: =SUM(AF69:AF76) -> 0 | AG77: =SUM(B77:AF77) -> 0
A79: Orders Return for Refund | AG79: =SUM(B79:AF79) -> 0
A81: Revenue Refunded (Gross) - Costco
A82: Hardware | AG82: =SUM(B82:AF82) -> 0
A83: Shipping | AG83: =SUM(B83:AF83) -> 0
A84: Taxes | AG84: =SUM(B84:AF84) -> 0
A85: All NA | B85: =sum(B82:B84) -> 0 | C85: =sum(C82:C84) -> 0 | D85: =sum(D82:D84) -> 0 | E85: =sum(E82:E84) -> 0 | F85: =sum(F82:F84) -> 0 | G85: =sum(G82:G84) -> 0 | H85: =sum(H82:H84) -> 0 | I85: =sum(I82:I84) -> 0 | ... AF85: =sum(AF82:AF84) -> 0 | AG85: =SUM(B85:AF85) -> 0
A87: Hardware - Europe | AG87: =SUM(B87:AF87) -> 0
A88: Shipping - Europe | AG88: =SUM(B88:AF88) -> 0
A89: All EU | B89: =sum(B87:B88) -> 0 | C89: =sum(C87:C88) -> 0 | D89: =sum(D87:D88) -> 0 | E89: =sum(E87:E88) -> 0 | F89: =sum(F87:F88) -> 0 | G89: =sum(G87:G88) -> 0 | H89: =sum(H87:H88) -> 0 | I89: =sum(I87:I88) -> 0 | ... AF89: =sum(AF87:AF88) -> 0 | AG89: =SUM(B89:AF89) -> 0
A91: RETURN (Replacement Units & Claims) - Costco
A92: SKU 1 - Blue | B92: 0 | C92: 0 | D92: 0 | E92: 0 | F92: 0 | G92: 0 | H92: 0 | I92: 0 | J92: 0 | K92: 0 | L92: 0 | M92: 0 | N92: 0 | O92: 0 | P92: 0 | Q92: 0 | R92: 0 | S92: 0 | T92: 0 | U92: 0 | V92: 0 | W92: 0 | X92: 0 | Y92: 0 | Z92: 0 | AA92: 0 | AB92: 0 | AC92: 0 | AD92: 0 | AE92: 0 | AF92: 0 | AG92: =SUM(B92:AF92) -> 0
A93: SKU 2 - Yellow | B93: 0 | C93: 0 | D93: 0 | E93: 0 | F93: 0 | G93: 0 | H93: 0 | I93: 0 | J93: 0 | K93: 0 | L93: 0 | M93: 0 | N93: 0 | O93: 0 | P93: 0 | Q93: 0 | R93: 0 | S93: 0 | T93: 0 | U93: 0 | V93: 0 | W93: 0 | X93: 0 | Y93: 0 | Z93: 0 | AA93: 0 | AB93: 0 | AC93: 0 | AD93: 0 | AE93: 0 | AF93: 0 | AG93: =SUM(B93:AF93) -> 0
A94: SKU 3 - Blue w/ Solar | B94: 0 | C94: 0 | D94: 0 | E94: 0 | F94: 0 | G94: 0 | H94: 0 | I94: 0 | J94: 0 | K94: 0 | L94: 0 | M94: 0 | N94: 0 | O94: 0 | P94: 0 | Q94: 0 | R94: 0 | S94: 0 | T94: 0 | U94: 0 | V94: 0 | W94: 0 | X94: 0 | Y94: 0 | Z94: 0 | AA94: 0 | AB94: 0 | AC94: 0 | AD94: 0 | AE94: 0 | AF94: 0 | AG94: =SUM(B94:AF94) -> 0
A95: SKU 4 - Yellow w/ Solar | B95: 0 | C95: 0 | D95: 0 | E95: 0 | F95: 0 | G95: 0 | H95: 0 | I95: 0 | J95: 0 | K95: 0 | L95: 0 | M95: 0 | N95: 0 | O95: 0 | P95: 0 | Q95: 0 | R95: 0 | S95: 0 | T95: 0 | U95: 0 | V95: 0 | W95: 0 | X95: 0 | Y95: 0 | Z95: 0 | AA95: 0 | AB95: 0 | AC95: 0 | AD95: 0 | AE95: 0 | AF95: 0 | AG95: =SUM(B95:AF95) -> 0
A96: SUM (SKU 1 + SKU 2) | B96: 0 | C96: 0 | D96: 0 | E96: 0 | F96: 0 | G96: 0 | H96: 0 | I96: 0 | J96: 0 | K96: 0 | L96: 0 | M96: 0 | N96: 0 | O96: 0 | P96: 0 | Q96: 0 | R96: 0 | S96: 0 | T96: 0 | U96: 0 | V96: 0 | W96: 0 | X96: 0 | Y96: 0 | Z96: 0 | AA96: 0 | AB96: 0 | AC96: 0 | AD96: 0 | AE96: 0 | AF96: 0 | AG96: =SUM(B96:AF96) -> 0
A97: SUM (SKU 3 + SKU 4) | B97: 0 | C97: 0 | D97: 0 | E97: 0 | F97: 0 | G97: 0 | H97: 0 | I97: 0 | J97: 0 | K97: 0 | L97: 0 | M97: 0 | N97: 0 | O97: 0 | P97: 0 | Q97: 0 | R97: 0 | S97: 0 | T97: 0 | U97: 0 | V97: 0 | W97: 0 | X97: 0 | Y97: 0 | Z97: 0 | AA97: 0 | AB97: 0 | AC97: 0 | AD97: 0 | AE97: 0 | AF97: 0 | AG97: =SUM(B97:AF97) -> 0
AG98: =SUM(B98:AF98) -> 0
A99: Wall Mount | B99: 0 | C99: 0 | D99: 0 | E99: 0 | F99: 0 | G99: 0 | H99: 0 | I99: 0 | J99: 0 | K99: 0 | L99: 0 | M99: 0 | N99: 0 | O99: 0 | P99: 0 | Q99: 0 | R99: 0 | S99: 0 | T99: 0 | U99: 0 | V99: 0 | W99: 0 | X99: 0 | Y99: 0 | Z99: 0 | AA99: 0 | AB99: 0 | AC99: 0 | AD99: 0 | AE99: 0 | AF99: 0 | AG99: =SUM(B99:AF99) -> 0
A100: Suet Ball Holder | B100: 0 | C100: 0 | D100: 0 | E100: 0 | F100: 0 | G100: 0 | H100: 0 | I100: 0 | J100: 0 | K100: 0 | L100: 0 | M100: 0 | N100: 0 | O100: 0 | P100: 0 | Q100: 0 | R100: 0 | S100: 0 | T100: 0 | U100: 0 | V100: 0 | W100: 0 | X100: 0 | Y100: 0 | Z100: 0 | AA100: 0 | AB100: 0 | AC100: 0 | AD100: 0 | AE100: 0 | AF100: 0 | AG100: =SUM(B100:AF100) -> 0
A101: 3-in-1 Nutrition Set - Blue | B101: 0 | C101: 0 | D101: 0 | E101: 0 | F101: 0 | G101: 0 | H101: 0 | I101: 0 | J101: 0 | K101: 0 | L101: 0 | M101: 0 | N101: 0 | O101: 0 | P101: 0 | Q101: 0 | R101: 0 | S101: 0 | T101: 0 | U101: 0 | V101: 0 | W101: 0 | X101: 0 | Y101: 0 | Z101: 0 | AA101: 0 | AB101: 0 | AC101: 0 | AD101: 0 | AE101: 0 | AF101: 0 | AG101: =SUM(B101:AF101) -> 0
A102: 3-in-1 Nutrition Set - Yellow | B102: 0 | C102: 0 | D102: 0 | E102: 0 | F102: 0 | G102: 0 | H102: 0 | I102: 0 | J102: 0 | K102: 0 | L102: 0 | M102: 0 | N102: 0 | O102: 0 | P102: 0 | Q102: 0 | R102: 0 | S102: 0 | T102: 0 | U102: 0 | V102: 0 | W102: 0 | X102: 0 | Y102: 0 | Z102: 0 | AA102: 0 | AB102: 0 | AC102: 0 | AD102: 0 | AE102: 0 | AF102: 0 | AG102: =SUM(B102:AF102) -> 0
A103: Solar Roof Single - Blue | B103: 0 | C103: 0 | D103: 0 | E103: 0 | F103: 0 | G103: 0 | H103: 0 | I103: 0 | J103: 0 | K103: 0 | L103: 0 | M103: 0 | N103: 0 | O103: 0 | P103: 0 | Q103: 0 | R103: 0 | S103: 0 | T103: 0 | U103: 0 | V103: 0 | W103: 0 | X103: 0 | Y103: 0 | Z103: 0 | AA103: 0 | AB103: 0 | AC103: 0 | AD103: 0 | AE103: 0 | AF103: 0 | AG103: =SUM(B103:AF103) -> 0
A104: Solar Roof Single - Yellow | B104: 0 | C104: 0 | D104: 0 | E104: 0 | F104: 0 | G104: 0 | H104: 0 | I104: 0 | J104: 0 | K104: 0 | L104: 0 | M104: 0 | N104: 0 | O104: 0 | P104: 0 | Q104: 0 | R104: 0 | S104: 0 | T104: 0 | U104: 0 | V104: 0 | W104: 0 | X104: 0 | Y104: 0 | Z104: 0 | AA104: 0 | AB104: 0 | AC104: 0 | AD104: 0 | AE104: 0 | AF104: 0 | AG104: =SUM(B104:AF104) -> 0
A105: Perch Extender - Blue | B105: 0 | C105: 0 | D105: 0 | E105: 0 | F105: 0 | G105: 0 | H105: 0 | I105: 0 | J105: 0 | K105: 0 | L105: 0 | M105: 0 | N105: 0 | O105: 0 | P105: 0 | Q105: 0 | R105: 0 | S105: 0 | T105: 0 | U105: 0 | V105: 0 | W105: 0 | X105: 0 | Y105: 0 | Z105: 0 | AA105: 0 | AB105: 0 | AC105: 0 | AD105: 0 | AE105: 0 | AF105: 0 | AG105: =SUM(B105:AF105) -> 0
A106: Perch Extender - Yellow | B106: 0 | C106: 0 | D106: 0 | E106: 0 | F106: 0 | G106: 0 | H106: 0 | I106: 0 | J106: 0 | K106: 0 | L106: 0 | M106: 0 | N106: 0 | O106: 0 | P106: 0 | Q106: 0 | R106: 0 | S106: 0 | T106: 0 | U106: 0 | V106: 0 | W106: 0 | X106: 0 | Y106: 0 | Z106: 0 | AA106: 0 | AB106: 0 | AC106: 0 | AD106: 0 | AE106: 0 | AF106: 0 | AG106: =SUM(B106:AF106) -> 0
A107: SUM (Add-ons) | B107: 0 | C107: 0 | D107: 0 | E107: 0 | F107: 0 | G107: 0 | H107: 0 | I107: 0 | J107: 0 | K107: 0 | L107: 0 | M107: 0 | N107: 0 | O107: 0 | P107: 0 | Q107: 0 | R107: 0 | S107: 0 | T107: 0 | U107: 0 | V107: 0 | W107: 0 | X107: 0 | Y107: 0 | Z107: 0 | AA107: 0 | AB107: 0 | AC107: 0 | AD107: 0 | AE107: 0 | AF107: 0 | AG107: =SUM(B107:AF107) -> 0
A109: Parts
A110: Housing - Blue | B110: 0 | C110: 0 | D110: 0 | E110: 0 | F110: 0 | G110: 0 | H110: 0 | I110: 0 | J110: 0 | K110: 0 | L110: 0 | M110: 0 | N110: 0 | O110: 0 | P110: 0 | Q110: 0 | R110: 0 | S110: 0 | T110: 0 | U110: 0 | V110: 0 | W110: 0 | X110: 0 | Y110: 0 | Z110: 0 | AA110: 0 | AB110: 0 | AC110: 0 | AD110: 0 | AE110: 0 | AF110: 0 | AG110: =SUM(B110:AF110) -> 0
A111: Housing - Yellow | B111: 0 | C111: 0 | D111: 0 | E111: 0 | F111: 0 | G111: 0 | H111: 0 | I111: 0 | J111: 0 | K111: 0 | L111: 0 | M111: 0 | N111: 0 | O111: 0 | P111: 0 | Q111: 0 | R111: 0 | S111: 0 | T111: 0 | U111: 0 | V111: 0 | W111: 0 | X111: 0 | Y111: 0 | Z111: 0 | AA111: 0 | AB111: 0 | AC111: 0 | AD111: 0 | AE111: 0 | AF111: 0 | AG111: =SUM(B111:AF111) -> 0
A112: Camera Module | B112: 0 | C112: 0 | D112: 0 | E112: 0 | F112: 0 | G112: 0 | H112: 0 | I112: 0 | J112: 0 | K112: 0 | L112: 0 | M112: 0 | N112: 0 | O112: 0 | P112: 0 | Q112: 0 | R112: 0 | S112: 0 | T112: 0 | U112: 0 | V112: 0 | W112: 0 | X112: 0 | Y112: 0 | Z112: 0 | AA112: 0 | AB112: 0 | AC112: 0 | AD112: 0 | AE112: 0 | AF112: 0 | AG112: =SUM(B112:AF112) -> 0
A114: Orders Replaced NA | B114: 0 | C114: 0 | D114: 0 | E114: 0 | F114: 0 | G114: 0 | H114: 0 | I114: 0 | J114: 0 | K114: 0 | L114: 0 | M114: 0 | N114: 0 | O114: 1 | P114: 0 | Q114: 0 | R114: 0 | S114: 0 | T114: 0 | U114: 0 | V114: 0 | W114: 0 | X114: 0 | Y114: 0 | Z114: 0 | AA114: 0 | AB114: 0 | AC114: 0 | AD114: 0 | AE114: 0 | AF114: 0 | AG114: =SUM(B114:AF114) -> 1
A119: Gross Cost
A120: Media Spend | B120: 0 | C120: 0 | D120: 0 | E120: 0 | F120: 0 | G120: 0 | H120: 0 | I120: 0 | J120: 0 | K120: 0 | L120: 0 | M120: 0 | N120: 0 | O120: 0 | P120: 0 | Q120: 0 | R120: 0 | S120: 0 | T120: 0 | U120: 0 | V120: 0 | W120: 0 | X120: 0 | Y120: 0 | Z120: 0 | AA120: 0 | AB120: 0 | AC120: 0 | AD120: 0 | AE120: 0 | AF120: 0 | AG120: =SUM(B120:AF120) -> 0
A121: Marketplace Fees | B121: =B12 | C121: =C12 | D121: =D12 | E121: =E12 | F121: =F12 | G121: =G12 | H121: =H12 | I121: =I12 | ... AF121: =AF12 | AG121: =SUM(B121:AF121) -> 0
...

Sheet Digital Marketplaces - P&L
A1: JANUARY | B1: 45658 | C1: 45659 | D1: 45660 | E1: 45661 | F1: 45662 | G1: 45663 | H1: 45664 | I1: 45665 | J1: 45666 | K1: 45667 | L1: 45668 | M1: 45669 | N1: 45670 | O1: 45671 | P1: 45672 | Q1: 45673 | R1: 45674 | S1: 45675 | T1: 45676 | U1: 45677 | V1: 45678 | W1: 45679 | X1: 45680 | Y1: 45681 | Z1: 45682 | AA1: 45683 | AB1: 45684 | AC1: 45685 | AD1: 45686 | AE1: 45687 | AF1: 45688
A2: DAY | B2: WED | C2: THU | D2: FRI | E2: SAT | F2: SUN | G2: MON | H2: TUE | I2: WED | J2: THU | K2: FRI | L2: SAT | M2: SUN | N2: MON | O2: TUE | P2: WED | Q2: THU | R2: FRI | S2: SAT | T2: SUN | U2: MON | V2: TUE | W2: WED | X2: THU | Y2: FRI | Z2: SAT | AA2: SUN | AB2: MON | AC2: TUE | AD2: WED | AE2: THU | AF2: FRI
A3: Rachio (Shopify)
A4: Revenue | B4: =Summary!B58 -> 0 | C4: =Summary!C58 -> 0 | D4: =Summary!D58 -> 0 | E4: =Summary!E58 -> 0 | F4: =Summary!F58 -> 0 | G4: =Summary!G58 -> 0 | H4: =Summary!H58 -> 0 | I4: =Summary!I58 -> 0 | ... AF4: =Summary!AF58 -> 254.72539 | AG4: =SUM(B4:AF4) -> 1146.2695
A5: Breakdown | AG5: =SUM(B5:AF5) -> 0
