Workbook
Name zsupermetrics_ru0GDtbZzDLHQOQtJJ6K08MvUDyyp7: #REF!
Name zsupermetrics_DQl8lUbpTRu3fayaJJi7lVfOGKjNU4: 'Data - P&L'!$A$3:$A$4
Name zsupermetrics_BioPyGBzcBsy60UCQmPcTuFReEmghI: 'Data - P&L'!$B$2:$B$3
Name zsupermetrics_refreshAll: SupermetricsQueries!$H$5
Name zsupermetrics_n3GtLgiKpTmd2pYmQNMuq6TPD0qE0b: #REF!
Name zsupermetrics_refreshAllSilent: SupermetricsQueries!$H$6
Name zsupermetrics_Mgms9p0QzysYvrIhnsKACeVBVxfIEO: #REF!
Name zsupermetrics_Mgms9p0QzysYvrIhnsKACeVBVxfIEO: 'Data - P&L'!$A$2:$A$3
Name zsupermetrics_forceRefresh: SupermetricsQueries!$H$4
Name zsupermetrics_wbYMmT0YL9bAN0yhimW0ziPFnia9Dx: #REF!
Name zsupermetrics_iNpyVy90bWCI0yUaFQpxOtzWMa6sW4: #REF!
Name zsupermetrics_xwoIpANxRm908eDp5oKTwQpEI8gvD4: #REF!
Name zsupermetrics_n3GtLgiKpTmd2pYmQNMuq6TPD0qE0b: 'Data - P&L'!$B$4:$B$5
Name rdataslayer_42b112e4e4be4305bb4c1be75e2dd549: 'Data - P&L'!$B$2:$C$3
Name zsupermetrics_9i4W4hgd80uRpQLMeX0eRnESN8gjyv: #REF!
Name zsupermetrics_5bmwtOpHUbSYmDMeuCPkrxaojTprPP: #REF!
Name rdataslayer_3753ddf3234e496aa261974a0222e193: 'Data - P&L'!$H$2:$I$2
Name zsupermetrics_SGBxROnInO9rFyh3H7j2Lldx0Bdc5v: #REF!
Name zsupermetrics_pxuhRTEmIU93xSgKclyxajD0fCZ6rF: #REF!
Name zsupermetrics_ru0GDtbZzDLHQOQtJJ6K08MvUDyyp7: 'Data - P&L'!$B$4:$B$5
Name zsupermetrics_qWp7V908pNEYMtfv8QZvSTeDnBAHOU: 'Data - P&L'!$B$5:$C$13
Name rdataslayer_4a0f150f4f2f4e4f85c890c75b7a1fa4: #REF!
Name zsupermetrics_8xojRjNDjo2jWHGDWjFEhflhyIq3Hq: #REF!
Name zsupermetrics_HgZqhorObHOtZHuyJjpmyYaEPoYntx: #REF!
Name zsupermetrics_YsFuuYtr8vOdNXCCPiFJIO38NP4b2T: #REF!
Name zsupermetrics_DQl8lUbpTRu3fayaJJi7lVfOGKjNU4: #REF!
Name zsupermetrics_YVuzfmsfdurz7Ldl84Rfns8oka6LsS: #REF!
Name zsupermetrics_4VkB7ij7WO0JjKBEgvjB2GHjSy2Egm: #REF!
Name zsupermetrics_9i4W4hgd80uRpQLMeX0eRnESN8gjyv: 'Data - P&L'!$C$13
Name zsupermetrics_lx4cNai7gT6tH4j08ZRkI21Qlpjioi: #REF!
Name rdataslayer_d70e473bcafe40a3aa834ce157fb2ba3: #REF!
Name zsupermetrics_NugLlrQxlKiqhxQae8EFpITBm1pLCj: 'Data - P&L'!$B$6:$C$13
Name zsupermetrics_8xojRjNDjo2jWHGDWjFEhflhyIq3Hq: Summary!$K$12:$K$47
Name zsupermetrics_FEamnpN5FsVYF0RtUTXAwunZ388Tkc: Forecast!$A$113:$C$141
Name rdataslayer_3753ddf3234e496aa261974a0222e193: #REF!
Name zsupermetrics_iNpyVy90bWCI0yUaFQpxOtzWMa6sW4: 'Data - P&L'!$A$2:$A$3
Name rdataslayer_4a0f150f4f2f4e4f85c890c75b7a1fa4: 'Data - P&L'!$D$2:$E$3
Name zsupermetrics_BioPyGBzcBsy60UCQmPcTuFReEmghI: #REF!
Name zsupermetrics_qWp7V908pNEYMtfv8QZvSTeDnBAHOU: #REF!
Name zsupermetrics_wbYMmT0YL9bAN0yhimW0ziPFnia9Dx: 'Data - P&L'!$A$2:$A$3
Name zsupermetrics_4VkB7ij7WO0JjKBEgvjB2GHjSy2Egm: 'Data - P&L'!$B$4:$C$10
Name zsupermetrics_lx4cNai7gT6tH4j08ZRkI21Qlpjioi: 'Data - P&L'!$B$4:$C$13
Name rdataslayer_42b112e4e4be4305bb4c1be75e2dd549: #REF!
Name rdataslayer_adf57e64065742daa5b4161161b1c3ca: #REF!
Name rdataslayer_adf57e64065742daa5b4161161b1c3ca: 'Data - P&L'!$B$4:$D$5
Name zsupermetrics_NugLlrQxlKiqhxQae8EFpITBm1pLCj: #REF!
Name zsupermetrics_xwoIpANxRm908eDp5oKTwQpEI8gvD4: #REF!
Name zsupermetrics_YsFuuYtr8vOdNXCCPiFJIO38NP4b2T: 'Data - P&L'!$B$4:$C$13
Name rdataslayer_d70e473bcafe40a3aa834ce157fb2ba3: 'Data - P&L'!$C$8:$D$9
Name zsupermetrics_HgZqhorObHOtZHuyJjpmyYaEPoYntx: 'Data - P&L'!$B$4:$B$5

Sheet Data_forecast_2024
B1: 45809 | C1: 45810 | D1: 45811 | E1: 45812 | F1: 45813 | G1: 45814 | H1: 45815 | I1: 45816 | J1: 45817 | K1: 45818 | L1: 45819 | M1: 45820 | N1: 45821 | O1: 45822 | P1: 45823 | Q1: 45824 | R1: 45825 | S1: 45826 | T1: 45827 | U1: 45828 | V1: 45829 | W1: 45830 | X1: 45831 | Y1: 45832 | Z1: 45833 | AA1: 45834 | AB1: 45835 | AC1: 45836 | AD1: 45837 | AE1: 45838 | AF1: 45839
A2: Quantities | B2: ='DTC - P&L'!B66+'AMAZON US&CA - P&L'!B36+'WALMART - P&L'!B23+'Digital Marketplaces - P&L'!B17+'Digital Marketplaces - P&L'!B129+'Digital Marketplaces - P&L'!B243+'COSTCO - P&L'!B19 -> 38 | C2: ='DTC - P&L'!C66+'AMAZON US&CA - P&L'!C36+'WALMART - P&L'!C23+'Digital Marketplaces - P&L'!C17+'Digital Marketplaces - P&L'!C129+'Digital Marketplaces - P&L'!C243+'COSTCO - P&L'!C19 -> 40 | D2: ='DTC - P&L'!D66+'AMAZON US&CA - P&L'!D36+'WALMART - P&L'!D23+'Digital Marketplaces - P&L'!D17+'Digital Marketplaces - P&L'!D129+'Digital Marketplaces - P&L'!D243+'COSTCO - P&L'!D19 -> 41 | E2: ='DTC - P&L'!E66+'AMAZON US&CA - P&L'!E36+'WALMART - P&L'!E23+'Digital Marketplaces - P&L'!E17+'Digital Marketplaces - P&L'!E129+'Digital Marketplaces - P&L'!E243+'COSTCO - P&L'!E19 -> 32 | F2: ='DTC - P&L'!F66+'AMAZON US&CA - P&L'!F36+'WALMART - P&L'!F23+'Digital Marketplaces - P&L'!F17+'Digital Marketplaces - P&L'!F129+'Digital Marketplaces - P&L'!F243+'COSTCO - P&L'!F19 -> 36 | G2: ='DTC - P&L'!G66+'AMAZON US&CA - P&L'!G36+'WALMART - P&L'!G23+'Digital Marketplaces - P&L'!G17+'Digital Marketplaces - P&L'!G129+'Digital Marketplaces - P&L'!G243+'COSTCO - P&L'!G19 -> 37 | H2: ='DTC - P&L'!H66+'AMAZON US&CA - P&L'!H36+'WALMART - P&L'!H23+'Digital Marketplaces - P&L'!H17+'Digital Marketplaces - P&L'!H129+'Digital Marketplaces - P&L'!H243+'COSTCO - P&L'!H19 -> 161 | I2: ='DTC - P&L'!I66+'AMAZON US&CA - P&L'!I36+'WALMART - P&L'!I23+'Digital Marketplaces - P&L'!I17+'Digital Marketplaces - P&L'!I129+'Digital Marketplaces - P&L'!I243+'COSTCO - P&L'!I19 -> 189 | ... AF2: ='DTC - P&L'!AF66+'AMAZON US&CA - P&L'!AF36+'WALMART - P&L'!AF23+'Digital Marketplaces - P&L'!AF17+'Digital Marketplaces - P&L'!AF129+'Digital Marketplaces - P&L'!AF243+'COSTCO - P&L'!AF19 -> 52
A3: Sales | B3: =Summary!B47+Summary!B93+Summary!B85+Summary!B59 -> 31136.706 | C3: =Summary!C47+Summary!C93+Summary!C85+Summary!C59 -> 30219.791 | D3: =Summary!D47+Summary!D93+Summary!D85+Summary!D59 -> 23249.623 | E3: =Summary!E47+Summary!E93+Summary!E85+Summary!E59 -> 21309.283 | F3: =Summary!F47+Summary!F93+Summary!F85+Summary!F59 -> 24536.862 | G3: =Summary!G47+Summary!G93+Summary!G85+Summary!G59 -> 19523.24 | H3: =Summary!H47+Summary!H93+Summary!H85+Summary!H59 -> 55470.515 | I3: =Summary!I47+Summary!I93+Summary!I85+Summary!I59 -> 60647.394 | ... AF3: =Summary!AF47+Summary!AF93+Summary!AF85+Summary!AF59 -> 24620.701

Sheet WALMART_Data_forecast_2024
B1: 45809 | C1: 45810 | D1: 45811 | E1: 45812 | F1: 45813 | G1: 45814 | H1: 45815 | I1: 45816 | J1: 45817 | K1: 45818 | L1: 45819 | M1: 45820 | N1: 45821 | O1: 45822 | P1: 45823 | Q1: 45824 | R1: 45825 | S1: 45826 | T1: 45827 | U1: 45828 | V1: 45829 | W1: 45830 | X1: 45831 | Y1: 45832 | Z1: 45833 | AA1: 45834 | AB1: 45835 | AC1: 45836 | AD1: 45837 | AE1: 45838 | AF1: 45839
A2: Quantities | B2: ='WALMART - P&L'!B23 -> 0 | C2: ='WALMART - P&L'!C23 -> 1 | D2: ='WALMART - P&L'!D23 -> 0 | E2: ='WALMART - P&L'!E23 -> 0 | F2: ='WALMART - P&L'!F23 -> 0 | G2: ='WALMART - P&L'!G23 -> 0 | H2: ='WALMART - P&L'!H23 -> 0 | I2: ='WALMART - P&L'!I23 -> 0 | ... AF2: ='WALMART - P&L'!AF23 -> 1
A3: Sales | B3: =Summary!B67 -> 0 | C3: =Summary!C67 -> 350.96 | D3: =Summary!D67 -> 0 | E3: =Summary!E67 -> 0 | F3: =Summary!F67 -> 0 | G3: =Summary!G67 -> 0 | H3: =Summary!H67 -> 31.03 | I3: =Summary!I67 -> 0 | ... AF3: =Summary!AF67 -> 321.43

Sheet COSTCO_Data_forecast_2024
B1: 45809 | C1: 45749 | D1: 45750 | E1: 45751 | F1: 45752 | G1: 45753 | H1: 45754 | I1: 45755 | J1: 45756 | K1: 45757 | L1: 45758 | M1: 45759 | N1: 45760 | O1: 45761 | P1: 45762 | Q1: 45763 | R1: 45764 | S1: 45765 | T1: 45766 | U1: 45767 | V1: 45768 | W1: 45769 | X1: 45770 | Y1: 45771 | Z1: 45772 | AA1: 45773 | AB1: 45774 | AC1: 45775 | AD1: 45776 | AE1: 45777 | AF1: 45778
A2: Quantities | B2: ='COSTCO - P&L'!B19 -> 0 | C2: ='COSTCO - P&L'!C19 -> 0 | D2: ='COSTCO - P&L'!D19 -> 0 | E2: ='COSTCO - P&L'!E19 -> 0 | F2: ='COSTCO - P&L'!F19 -> 0 | G2: ='COSTCO - P&L'!G19 -> 0 | H2: ='COSTCO - P&L'!H19 -> 0 | I2: ='COSTCO - P&L'!I19 -> 0 | ... AF2: ='COSTCO - P&L'!AF19 -> 0
A3: Sales | B3: =Summary!B59 -> 0 | C3: =Summary!C59 -> 0 | D3: =Summary!D59 -> 0 | E3: =Summary!E59 -> 0 | F3: =Summary!F59 -> 0 | G3: =Summary!G59 -> 0 | H3: =Summary!H59 -> 0 | I3: =Summary!I59 -> 0 | ... AF3: =Summary!AF59 -> 0

Sheet DM_Data_forecast_2024
B1: 45809 | C1: 45810 | D1: 45811 | E1: 45812 | F1: 45813 | G1: 45814 | H1: 45815 | I1: 45816 | J1: 45817 | K1: 45818 | L1: 45819 | M1: 45820 | N1: 45821 | O1: 45822 | P1: 45823 | Q1: 45824 | R1: 45825 | S1: 45826 | T1: 45827 | U1: 45828 | V1: 45829 | W1: 45830 | X1: 45831 | Y1: 45832 | Z1: 45833 | AA1: 45834 | AB1: 45835 | AC1: 45836 | AD1: 45837 | AE1: 45838 | AF1: 45839
A2: Quantities | B2: ='Digital Marketplaces - P&L'!B17+'Digital Marketplaces - P&L'!B129+'Digital Marketplaces - P&L'!B243 -> 0 | C2: ='Digital Marketplaces - P&L'!C17+'Digital Marketplaces - P&L'!C129+'Digital Marketplaces - P&L'!C243 -> 0 | D2: ='Digital Marketplaces - P&L'!D17+'Digital Marketplaces - P&L'!D129+'Digital Marketplaces - P&L'!D243 -> 0 | E2: ='Digital Marketplaces - P&L'!E17+'Digital Marketplaces - P&L'!E129+'Digital Marketplaces - P&L'!E243 -> 0 | F2: ='Digital Marketplaces - P&L'!F17+'Digital Marketplaces - P&L'!F129+'Digital Marketplaces - P&L'!F243 -> 0 | G2: ='Digital Marketplaces - P&L'!G17+'Digital Marketplaces - P&L'!G129+'Digital Marketplaces - P&L'!G243 -> 0 | H2: ='Digital Marketplaces - P&L'!H17+'Digital Marketplaces - P&L'!H129+'Digital Marketplaces - P&L'!H243 -> 0 | I2: ='Digital Marketplaces - P&L'!I17+'Digital Marketplaces - P&L'!I129+'Digital Marketplaces - P&L'!I243 -> 0 | ... AF2: ='Digital Marketplaces - P&L'!AF17+'Digital Marketplaces - P&L'!AF129+'Digital Marketplaces - P&L'!AF243 -> 0
A3: Sales | B3: =Summary!B85 -> 0 | C3: =Summary!C85 -> 0 | D3: =Summary!D85 -> 0 | E3: =Summary!E85 -> 0 | F3: =Summary!F85 -> 0 | G3: =Summary!G85 -> 0 | H3: =Summary!H85 -> 0 | I3: =Summary!I85 -> 0 | ... AF3: =Summary!AF85 -> 0

Sheet AMAZON_Data_Forecast
A1: US | B1: 45809 | C1: 45810 | D1: 45811 | E1: 45812 | F1: 45813 | G1: 45814 | H1: 45815 | I1: 45816 | J1: 45817 | K1: 45818 | L1: 45819 | M1: 45820 | N1: 45821 | O1: 45822 | P1: 45823 | Q1: 45824 | R1: 45825 | S1: 45826 | T1: 45827 | U1: 45828 | V1: 45829 | W1: 45830 | X1: 45831 | Y1: 45832 | Z1: 45833 | AA1: 45834 | AB1: 45835 | AC1: 45836 | AD1: 45837 | AE1: 45838 | AF1: 45839
A2: Quantities | B2: ='AMAZON US&CA - P&L'!B36+'AMAZON US&CA - P&L'!B40 -> 15 | C2: ='AMAZON US&CA - P&L'!C36+'AMAZON US&CA - P&L'!C40 -> 28 | D2: ='AMAZON US&CA - P&L'!D36+'AMAZON US&CA - P&L'!D40 -> 20 | E2: ='AMAZON US&CA - P&L'!E36+'AMAZON US&CA - P&L'!E40 -> 22 | F2: ='AMAZON US&CA - P&L'!F36+'AMAZON US&CA - P&L'!F40 -> 24 | G2: ='AMAZON US&CA - P&L'!G36+'AMAZON US&CA - P&L'!G40 -> 16 | H2: ='AMAZON US&CA - P&L'!H36+'AMAZON US&CA - P&L'!H40 -> 169 | I2: ='AMAZON US&CA - P&L'!I36+'AMAZON US&CA - P&L'!I40 -> 197 | ... AF2: ='AMAZON US&CA - P&L'!AF36+'AMAZON US&CA - P&L'!AF40 -> 18
A3: Sales | B3: =Summary!B32 -> 4277.26 | C3: =Summary!C32 -> 8057.58 | D3: =Summary!D32 -> 5661.28 | E3: =Summary!E32 -> 6498.59 | F3: =Summary!F32 -> 7048.66 | G3: =Summary!G32 -> 4593.61 | H3: =Summary!H32 -> 41026.28 | I3: =Summary!I32 -> 46178.59 | ... AF3: =Summary!AF32 -> 5819.91
A5: UK
A6: Quantities | B6: ='AMAZON UK, FR, GER - P&L'!B37 -> 0 | C6: ='AMAZON UK, FR, GER - P&L'!C37 -> 0 | D6: ='AMAZON UK, FR, GER - P&L'!D37 -> 0 | E6: ='AMAZON UK, FR, GER - P&L'!E37 -> 2 | F6: ='AMAZON UK, FR, GER - P&L'!F37 -> 0 | G6: ='AMAZON UK, FR, GER - P&L'!G37 -> 0 | H6: ='AMAZON UK, FR, GER - P&L'!H37 -> 0 | I6: ='AMAZON UK, FR, GER - P&L'!I37 -> 0 | ... AF6: ='AMAZON UK, FR, GER - P&L'!AF37 -> 0
A7: Sales | B7: =Summary!B39 -> 136.8 | C7: =Summary!C39 -> 104.88 | D7: =Summary!D39 -> 0 | E7: =Summary!E39 -> 767.29 | F7: =Summary!F39 -> 0 | G7: =Summary!G39 -> 0 | H7: =Summary!H39 -> 45.41 | I7: =Summary!I39 -> 0 | ... AF7: =Summary!AF39 -> 44.5
A9: FR
A10: Quantities | B10: ='AMAZON UK, FR, GER - P&L'!B223 -> 1 | C10: ='AMAZON UK, FR, GER - P&L'!C223 -> 1 | D10: ='AMAZON UK, FR, GER - P&L'!D223 -> 0 | E10: ='AMAZON UK, FR, GER - P&L'!E223 -> 0 | F10: ='AMAZON UK, FR, GER - P&L'!F223 -> 1 | G10: ='AMAZON UK, FR, GER - P&L'!G223 -> 0 | H10: ='AMAZON UK, FR, GER - P&L'!H223 -> 1 | I10: ='AMAZON UK, FR, GER - P&L'!I223 -> 0 | ... AF10: ='AMAZON UK, FR, GER - P&L'!AF223 -> 0
A11: Sales | B11: =Summary!B40 -> 365.55 | C11: =Summary!C40 -> 474.15 | D11: =Summary!D40 -> 40.32 | E11: =Summary!E40 -> 0 | F11: =Summary!F40 -> 381.38 | G11: =Summary!G40 -> 0 | H11: =Summary!H40 -> 383.6 | I11: =Summary!I40 -> 0 | ... AF11: =Summary!AF40 -> 0
A13: GR
A14: Quantities | B14: ='AMAZON UK, FR, GER - P&L'!B409 -> 0 | C14: ='AMAZON UK, FR, GER - P&L'!C409 -> 0 | D14: ='AMAZON UK, FR, GER - P&L'!D409 -> 1 | E14: ='AMAZON UK, FR, GER - P&L'!E409 -> 0 | F14: ='AMAZON UK, FR, GER - P&L'!F409 -> 0 | G14: ='AMAZON UK, FR, GER - P&L'!G409 -> 0 | H14: ='AMAZON UK, FR, GER - P&L'!H409 -> 4 | I14: ='AMAZON UK, FR, GER - P&L'!I409 -> 5 | ... AF14: ='AMAZON UK, FR, GER - P&L'!AF409 -> 0
A15: Sales | B15: =Summary!B41 -> 0 | C15: =Summary!C41 -> 0 | D15: =Summary!D41 -> 379.95 | E15: =Summary!E41 -> 0 | F15: =Summary!F41 -> 0 | G15: =Summary!G41 -> 0 | H15: =Summary!H41 -> 1363.72 | I15: =Summary!I41 -> 1697.58 | ... AF15: =Summary!AF41 -> 0
A17: Spent US | B17: =Summary!B152 -> 2516.45 | C17: =Summary!C152 -> 2084.29 | D17: =Summary!D152 -> 2139.06 | E17: =Summary!E152 -> 2187.44 | F17: =Summary!F152 -> 2242.09 | G17: =Summary!G152 -> 2170.97 | H17: =Summary!H152 -> 8267.02 | I17: =Summary!I152 -> 10880.35 | ... AF17: =Summary!AF152 -> 2618.32
A18: Spent UK | B18: =Summary!B154 -> 103.91 | C18: =Summary!C154 -> 59.24 | D18: =Summary!D154 -> 36.87 | E18: =Summary!E154 -> 34.24 | F18: =Summary!F154 -> 38.27 | G18: =Summary!G154 -> 36.68 | H18: =Summary!H154 -> 49.12 | I18: =Summary!I154 -> 26.91 | ... AF18: =Summary!AF154 -> 87.24
A19: Spent FR | B19: =Summary!B155 -> 57.2 | C19: =Summary!C155 -> 93.11 | D19: =Summary!D155 -> 88.68 | E19: =Summary!E155 -> 132.88 | F19: =Summary!F155 -> 133.27 | G19: =Summary!G155 -> 101.41 | H19: =Summary!H155 -> 106.09 | I19: =Summary!I155 -> 92.64 | ... AF19: =Summary!AF155 -> 90.11
A20: Spent GR | B20: =Summary!B156 -> 50.34 | C20: =Summary!C156 -> 27.94 | D20: =Summary!D156 -> 93.51 | E20: =Summary!E156 -> 41.32 | F20: =Summary!F156 -> 85.55 | G20: =Summary!G156 -> 32.88 | H20: =Summary!H156 -> 87.81 | I20: =Summary!I156 -> 58.8 | ... AF20: =Summary!AF156 -> 105.97

Sheet DTC_Data_Forecast
B1: 45809 | C1: 45810 | D1: 45811 | E1: 45812 | F1: 45813 | G1: 45814 | H1: 45815 | I1: 45816 | J1: 45817 | K1: 45818 | L1: 45819 | M1: 45820 | N1: 45821 | O1: 45822 | P1: 45823 | Q1: 45824 | R1: 45825 | S1: 45826 | T1: 45827 | U1: 45828 | V1: 45829 | W1: 45830 | X1: 45831 | Y1: 45832 | Z1: 45833 | AA1: 45834 | AB1: 45835 | AC1: 45836 | AD1: 45837 | AE1: 45838 | AF1: 45839
A2: Quantities | B2: ='DTC - P&L'!B66 -> 24 | C2: ='DTC - P&L'!C66 -> 16 | D2: ='DTC - P&L'!D66 -> 25 | E2: ='DTC - P&L'!E66 -> 14 | F2: ='DTC - P&L'!F66 -> 24 | G2: ='DTC - P&L'!G66 -> 23 | H2: ='DTC - P&L'!H66 -> 15 | I2: ='DTC - P&L'!I66 -> 17 | ... AF2: ='DTC - P&L'!AF66 -> 34
A3: Sales | B3: =Summary!B12-Summary!B28 -> 8605.7804 | C3: =Summary!C12-Summary!C28 -> 7879.3831 | D3: =Summary!D12-Summary!D28 -> 10324.478 | E3: =Summary!E12-Summary!E28 -> 6222.0866 | F3: =Summary!F12-Summary!F28 -> 8526.0997 | G3: =Summary!G12-Summary!G28 -> 8264.87 | H3: =Summary!H12-Summary!H28 -> 5625.3745 | I3: =Summary!I12-Summary!I28 -> 6852.3095 | ... AF3: =Summary!AF12-Summary!AF28 -> 12980.27
A5: DTC US
A6: Quantities | B6: ='DTC US&CA - P&L'!B34 -> 22 | C6: ='DTC US&CA - P&L'!C34 -> 14 | D6: ='DTC US&CA - P&L'!D34 -> 24 | E6: ='DTC US&CA - P&L'!E34 -> 13 | F6: ='DTC US&CA - P&L'!F34 -> 21 | G6: ='DTC US&CA - P&L'!G34 -> 23 | H6: ='DTC US&CA - P&L'!H34 -> 14 | I6: ='DTC US&CA - P&L'!I34 -> 14 | ... AF6: ='DTC US&CA - P&L'!AF34 -> 32
A7: Sales | B7: =Summary!B13 -> 7970.72 | C7: =Summary!C13 -> 7200.56 | D7: =Summary!D13 -> 9890.75 | E7: =Summary!E13 -> 5880.1 | F7: =Summary!F13 -> 7497.64 | G7: =Summary!G13 -> 8264.87 | H7: =Summary!H13 -> 5198.91 | I7: =Summary!I13 -> 5730.87 | ... AF7: =Summary!AF13 -> 12054.38
A9: DTC EU
A10: Quantities | B10: ='DTC EU - P&L'!B33 -> 2 | C10: ='DTC EU - P&L'!C33 -> 2 | D10: ='DTC EU - P&L'!D33 -> 1 | E10: ='DTC EU - P&L'!E33 -> 1 | F10: ='DTC EU - P&L'!F33 -> 3 | G10: ='DTC EU - P&L'!G33 -> 0 | H10: ='DTC EU - P&L'!H33 -> 1 | I10: ='DTC EU - P&L'!I33 -> 3 | ... AF10: ='DTC EU - P&L'!AF33 -> 2
A11: Sales | B11: =Summary!B21 -> 635.06036 | C11: =Summary!C21 -> 678.82308 | D11: =Summary!D21 -> 433.72771 | E11: =Summary!E21 -> 341.98663 | F11: =Summary!F21 -> 1028.4597 | G11: =Summary!G21 -> 0 | H11: =Summary!H21 -> 426.4645 | I11: =Summary!I21 -> 1121.4395 | ... AF11: =Summary!AF21 -> 925.89039
A14: Spent US | B14: =Summary!B145+Summary!B148+Summary!B150+Summary!B151 -> 3918.03 | C14: =Summary!C145+Summary!C148+Summary!C150+Summary!C151 -> 3419.1 | D14: =Summary!D145+Summary!D148+Summary!D150+Summary!D151 -> 2727.21 | E14: =Summary!E145+Summary!E148+Summary!E150+Summary!E151 -> 2505.73 | F14: =Summary!F145+Summary!F148+Summary!F150+Summary!F151 -> 3418.96 | G14: =Summary!G145+Summary!G148+Summary!G150+Summary!G151 -> 3974.08 | H14: =Summary!H145+Summary!H148+Summary!H150+Summary!H151 -> 2858.83 | I14: =Summary!I145+Summary!I148+Summary!I150+Summary!I151 -> 1161.27 | ... AF14: =Summary!AF145+Summary!AF148+Summary!AF150+Summary!AF151 -> 8523.6
A15: Spent EU | B15: =Summary!B165 -> 0 | C15: =Summary!C165 -> 0 | D15: =Summary!D165 -> 0 | E15: =Summary!E165 -> 0 | F15: =Summary!F165 -> 0 | G15: =Summary!G165 -> 0 | H15: =Summary!H165 -> 0.95 | I15: =Summary!I165 -> 0 | ... AF15: =Summary!AF165 -> 1.14
A17: DTC US
A18: Quantities | B18: ='DTC US&CA - P&L'!B34+'DTC US&CA - P&L'!B38 -> 24 | C18: ='DTC US&CA - P&L'!C34+'DTC US&CA - P&L'!C38 -> 22 | D18: ='DTC US&CA - P&L'!D34+'DTC US&CA - P&L'!D38 -> 29 | E18: ='DTC US&CA - P&L'!E34+'DTC US&CA - P&L'!E38 -> 17 | F18: ='DTC US&CA - P&L'!F34+'DTC US&CA - P&L'!F38 -> 23 | G18: ='DTC US&CA - P&L'!G34+'DTC US&CA - P&L'!G38 -> 27 | H18: ='DTC US&CA - P&L'!H34+'DTC US&CA - P&L'!H38 -> 16 | I18: ='DTC US&CA - P&L'!I34+'DTC US&CA - P&L'!I38 -> 17 | ... AF18: ='DTC US&CA - P&L'!AF34+'DTC US&CA - P&L'!AF38 -> 38
A19: Sales w/o renewals | B19: =Summary!B13 -> 7970.72 | C19: =Summary!C13 -> 7200.56 | D19: =Summary!D13 -> 9890.75 | E19: =Summary!E13 -> 5880.1 | F19: =Summary!F13 -> 7497.64 | G19: =Summary!G13 -> 8264.87 | H19: =Summary!H13 -> 5198.91 | I19: =Summary!I13 -> 5730.87 | ... AF19: =Summary!AF13 -> 12054.38
A20: Sales with renewals | B20: =Summary!B13+Summary!B29 -> 11810.27 | C20: =Summary!C13+Summary!C29 -> 9270.32 | D20: =Summary!D13+Summary!D29 -> 12350.47 | E20: =Summary!E13+Summary!E29 -> 7559.91 | F20: =Summary!F13+Summary!F29 -> 9177.45 | G20: =Summary!G13+Summary!G29 -> 9644.71 | H20: =Summary!H13+Summary!H29 -> 6788.64 | I20: =Summary!I13+Summary!I29 -> 7380.68 | ... AF20: =Summary!AF13+Summary!AF29 -> 13753.17

Sheet Summary
B1: 45931 | C1: 45932 | D1: 45933 | E1: 45934 | F1: 45935 | G1: 45936 | H1: 45937 | I1: 45938 | J1: 45939 | K1: 45940 | L1: 45941 | M1: 45942 | N1: 45943 | O1: 45944 | P1: 45945 | Q1: 45946 | R1: 45947 | S1: 45948 | T1: 45949 | U1: 45950 | V1: 45951 | W1: 45952 | X1: 45953 | Y1: 45954 | Z1: 45955 | AA1: 45956 | AB1: 45957 | AC1: 45958 | AD1: 45959 | AE1: 45960 | AF1: 45961
B2: WED | C2: THU | D2: FRI | E2: SAT | F2: SUN | G2: MON | H2: TUE | I2: WED | J2: THU | K2: FRI | L2: SAT | M2: SUN | N2: MON | O2: TUE | P2: WED | Q2: THU | R2: FRI | S2: SAT | T2: SUN | U2: MON | V2: TUE | W2: WED | X2: THU | Y2: FRI | Z2: SAT | AA2: SUN | AB2: MON | AC2: TUE | AD2: WED | AE2: THU | AF2: FRI
A3: Notes | B3: Halloween Sale | H3: PRIME DAY AMZ | N3: Halloween Sale | X3: Halloween Sale
B4: Halloween Sale New MT Pricing and theme change | D4: Duplicate site with MAP pricing for Tom (Meta ads) (DTC US) | G4: Climate Badge Aquired for: HBF Pro feeders (AMZ US) | I4: Membership page removed (because of FPM Price test) DTC US | J4: Lifetime Warranty A/B test LIVE | K4: Make Add-on widgets clickable (DTC/Cart US/EU) | O4: Woo account transfer Flowout --> Birdbuddy | P4: Membership Page US/EU | Remove Unlimited Storage Information | Q4: BFCM Special lander deployed on production (LP Pricing) | W4: Remove Nature Cam Pro from DTC US/EU | X4: Remove Nature Cam Pro from DTC US/EU | Y4: Birdbuddy Seeds as Add-on: Buddy Bites 20 lbs RRP: $59 LP: $39 Discount: 34% (DTC US/Storefront/add-ons) | AB4: Warranty A/B Pricing Test Active $19.99 vs $39.99 | AC4: Add-on cart A/B test 3 Revenue Goal added(DTC US) | AD4: ApplePay & Google Pay Work on Thank You Page Upsell | AE4: Giftbag Test stopped and deployed on production. 1x SBF in the cart gets a gift bag offer $19.99 at checkout (DTC US/Checkout)
B5: FPM Thank You Page A/B test OFF (DTC US) | D5: Giftwrap Test Convert Recalibration | G5: 'Shipping in October'' and pre-order post-purchase emails removed from: HBF Pro HBF, Pro Solar, Nature Station | I5: BB2 PDP - Shipping info removed | K5: Bird Bath Card live (DTC/Shop US) | P5: Webflow monthly plan enabled ($29/month) for Christmas Advertorial Page | W5: Warranty Test on TYP finished. Lifestyle was set as default DTC US/EU | X5: Add-on cart A/B test 3 (DTC US) | AC5: Convert - Staging tests turned off while tests are running on production (duplicate | AE5: Amazon QR code test stopped. Only SBF will be offered (DTC US)
B6: Add-on Cart A/B test OFF (DTC US) | D6: BB2 Help Page redirect | G6: BB naming updated DTC US | K6: Change CTA buttons on: Buy Now (DTC/pdp's US/EU) | P6: Ultimate Guide Page US/EU - New edits were published | W6: FPM Price set to $98.99 (DTC US/EU) | X6: Remove Audobon mentions/widgets from D2C and Woo emails | AC6: Checkout & Thank You Page Optimization DONE (DTC US/EU) | AE6: Add-on Pop-up A/B test stopped (DTC US/cart)
B7: FPM Pricing Test ON (DTC US /cart) | G7: Woo email naming updated | X7: Holiday Bundle BBS4073AAA Live SKU3 V2 - $399 $239 Family Premium - $98.99 $69.99 Gift Bag - $19.90 FREE ———————————————————————— SUBTOTAL: $517.89 $308.99 Discount: $209 OFF | AE7: New MAPtest2 - updated MAP prices and query string ?MAPtest --> ?MAPtest2
B8: WOO - Order cancelation reason added for CE | AE8: Wall mount OOS (DTC US)
B9: FPM opt-in not included if NS is in the cart (DTC US) | AE9: CA Cookie Banner Implementation (DTC US)
B10: Snapchat Plugin - Active (DTC US)
A12: DTC Revenue | B12: =SUM(B13,B21,B28) -> 12539.758 | C12: =SUM(C13,C21,C28) -> 9949.1431 | D12: =SUM(D13,D21,D28) -> 12784.198 | E12: =SUM(E13,E21,E28) -> 7901.8966 | F12: =SUM(F13,F21,F28) -> 10290.26 | G12: =SUM(G13,G21,G28) -> 9644.71 | H12: =SUM(H13,H21,H28) -> 7215.1045 | I12: =SUM(I13,I21,I28) -> 8589.3703 | ... AF12: =SUM(AF13,AF21,AF28) -> 14679.06
A13: - DTC Revenue US&CA | B13: =sum(B14:B20) -> 7970.72 | C13: =sum(C14:C20) -> 7200.56 | D13: =sum(D14:D20) -> 9890.75 | E13: =sum(E14:E20) -> 5880.1 | F13: =sum(F14:F20) -> 7497.64 | G13: =sum(G14:G20) -> 8264.87 | H13: =sum(H14:H20) -> 5198.91 | I13: =sum(I14:I20) -> 5730.87 | ... AF13: =sum(AF14:AF20) -> 12054.38
A14: - Hardware | B14: 5646 | C14: 5118 | D14: 7031 | E14: 3935.3 | F14: 5527 | G14: 5734.2 | H14: 3674 | I14: 4053 | J14: 6009.2 | K14: 6195 | L14: 4730.99 | M14: 7470.52 | N14: 6464 | O14: 6623 | P14: 5155.65 | Q14: 6155 | R14: 7753.5 | S14: 7258.2 | T14: 9006.33 | U14: 9515.98 | V14: 7888.15 | W14: 14770.3 | X14: 9848.99 | Y14: 8726.28 | Z14: 11457.08 | AA14: 10880.99 | AB14: 10246.99 | AC14: 10195.44 | AD14: 8793.49 | AE14: 7129.18 | AF14: 9072
A15: - Add-ons | B15: 569 | C15: 637 | D15: 820 | E15: 334 | F15: 273 | G15: 715 | H15: 386 | I15: 412 | J15: 723 | K15: 251 | L15: 757 | M15: 954.67 | N15: 706 | O15: 328 | P15: 1280.67 | Q15: 209 | R15: 1070.8 | S15: 868 | T15: 1079.67 | U15: 540 | V15: 1173.6 | W15: 1244.67 | X15: 1054 | Y15: 623.9 | Z15: 1219.5 | AA15: 731 | AB15: 580 | AC15: 332.5 | AD15: 423 | AE15: 273 | AF15: 371
A16: - Merch | B16: 0 | C16: 0 | D16: 0 | E16: 0 | F16: 0 | G16: 0 | H16: 0 | I16: 0 | J16: 0 | K16: 0 | L16: 0 | M16: 0 | N16: 0 | O16: 0 | P16: 0 | Q16: 0 | R16: 0 | S16: 0 | T16: 0 | U16: 0 | V16: 0 | W16: 0 | X16: 0 | Y16: 0 | Z16: 0 | AA16: 0 | AB16: 0 | AC16: 0 | AD16: 0 | AE16: 0 | AF16: 0
A17: - Seeds | B17: 236.2 | C17: 169.5 | D17: 345.9 | E17: 435.7 | F17: 323.9 | G17: 242 | H17: 257.9 | I17: 216.4 | J17: 388.9 | K17: 133.6 | L17: 408.7 | M17: 269.1 | N17: 89.7 | O17: 116.6 | P17: 289.1 | Q17: 244.2 | R17: 119.6 | S17: 119.6 | T17: 229.3 | U17: 179.4 | V17: 216.4 | W17: 89.7 | X17: 186.5 | Y17: 338.65 | Z17: 425.4 | AA17: 456.1 | AB17: 341.2 | AC17: 380.5 | AD17: 207.7 | AE17: 146.9 | AF17: 367.1
A18: - Taxes | B18: 707.8 | C18: 497.34 | D18: 697.65 | E18: 476.16 | F18: 519.22 | G18: 635.71 | H18: 318.27 | I18: 431.09 | J18: 540.24 | K18: 591.25 | L18: 448.45 | M18: 728.76 | N18: 689.27 | O18: 617.91 | P18: 615.41 | Q18: 597.45 | R18: 817.77 | S18: 722.35 | T18: 713.49 | U18: 826.71 | V18: 833.65 | W18: 1236.14 | X18: 966.48 | Y18: 778.49 | Z18: 1078.69 | AA18: 1041.19 | AB18: 969.49 | AC18: 867.46 | AD18: 739.31 | AE18: 1377.52 | AF18: 799.56
A19: - Shipping | B19: 702.42 | C19: 629.62 | D19: 842.2 | E19: 534.31 | F19: 655.62 | G19: 803.76 | H19: 508.04 | I19: 523.98 | J19: 701.5 | K19: 697.74 | L19: 589.8 | M19: 943.21 | N19: 773.38 | O19: 754.38 | P19: 639.62 | Q19: 678.93 | R19: 976.2 | S19: 868.14 | T19: 1097.72 | U19: 1056.79 | V19: 998.1 | W19: 1683.88 | X19: 1225.33 | Y19: 1050.19 | Z19: 1398.47 | AA19: 1202.3 | AB19: 1165.42 | AC19: 1145.42 | AD19: 1012.32 | AE19: 796.37 | AF19: 1046.72
A20: - Gift Bag | B20: 109.3 | C20: 149.1 | D20: 154 | E20: 164.63 | F20: 198.9 | G20: 134.2 | H20: 54.7 | I20: 94.4 | J20: 44.7 | K20: 189 | L20: 89.4 | M20: 188.9 | N20: 89.5 | O20: 59.7 | P20: 86.07 | Q20: 149.2 | R20: 208.8 | S20: 154.1 | T20: 223.8 | U20: 174.1 | V20: 159.2 | W20: 238.8 | X20: 79.6 | Y20: 79.6 | Z20: 113.43 | AA20: 159.2 | AB20: 79.6 | AC20: 89.5 | AD20: 169.1 | AE20: 218.9 | AF20: 398
A21: - DTC Revenue EU | B21: =SUM(B22:B27) -> 635.06036 | C21: =SUM(C22:C27) -> 678.82308 | D21: =SUM(D22:D27) -> 433.72771 | E21: =SUM(E22:E27) -> 341.98663 | F21: =SUM(F22:F27) -> 1028.4597 | G21: =SUM(G22:G27) -> 0 | H21: =SUM(H22:H27) -> 426.4645 | I21: =SUM(I22:I27) -> 1121.4395 | ... AF21: =SUM(AF22:AF27) -> 925.89039
A22: - Hardware | B22: ='DTC EU - P&L'!B15*B$143 -> 500.58844 | C22: ='DTC EU - P&L'!C15*C$143 -> 447.52517 | D22: ='DTC EU - P&L'!D15*D$143 -> 259.95479 | E22: ='DTC EU - P&L'!E15*E$143 -> 196.25936 | F22: ='DTC EU - P&L'!F15*F$143 -> 682.58555 | G22: ='DTC EU - P&L'!G15*G$143 -> 0 | H22: ='DTC EU - P&L'!H15*H$143 -> 245.52462 | I22: ='DTC EU - P&L'!I15*I$143 -> 650.17543 | ... AF22: ='DTC EU - P&L'!AF15*AF$143 -> 501.02776
A23: - Add-ons | B23: ='DTC EU - P&L'!B16*B$143 -> 24.651033 | C23: ='DTC EU - P&L'!C16*C$143 -> 47.649454 | D23: ='DTC EU - P&L'!D16*D$143 -> 66.958586 | E23: ='DTC EU - P&L'!E16*E$143 -> 37.831574 | F23: ='DTC EU - P&L'!F16*F$143 -> 37.763891 | G23: ='DTC EU - P&L'!G16*G$143 -> 0 | H23: ='DTC EU - P&L'!H16*H$143 -> 61.59978 | I23: ='DTC EU - P&L'!I16*I$143 -> 166.10126 | ... AF23: ='DTC EU - P&L'!AF16*AF$143 -> 173.13001
A24: - Merch | B24: ='DTC EU - P&L'!B17*B$143 -> 0 | C24: ='DTC EU - P&L'!C17*C$143 -> 0 | D24: ='DTC EU - P&L'!D17*D$143 -> 0 | E24: ='DTC EU - P&L'!E17*E$143 -> 0 | F24: ='DTC EU - P&L'!F17*F$143 -> 0 | G24: ='DTC EU - P&L'!G17*G$143 -> 0 | H24: ='DTC EU - P&L'!H17*H$143 -> 0 | I24: ='DTC EU - P&L'!I17*I$143 -> 0 | ... AF24: ='DTC EU - P&L'!AF17*AF$143 -> 0
A25: - Seeds | B25: ='DTC EU - P&L'!B18*B$143 -> 0 | C25: ='DTC EU - P&L'!C18*C$143 -> 0 | D25: ='DTC EU - P&L'!D18*D$143 -> 0 | E25: ='DTC EU - P&L'!E18*E$143 -> 0 | F25: ='DTC EU - P&L'!F18*F$143 -> 0 | G25: ='DTC EU - P&L'!G18*G$143 -> 0 | H25: ='DTC EU - P&L'!H18*H$143 -> 0 | I25: ='DTC EU - P&L'!I18*I$143 -> 0 | ... AF25: ='DTC EU - P&L'!AF18*AF$143 -> 0
A26: - Taxes | B26: ='DTC EU - P&L'!B20*B$143 -> 80.48838 | C26: ='DTC EU - P&L'!C20*C$143 -> 125.05345 | D26: ='DTC EU - P&L'!D20*D$143 -> 65.713828 | E26: ='DTC EU - P&L'!E20*E$143 -> 66.812696 | F26: ='DTC EU - P&L'!F20*F$143 -> 220.23273 | G26: ='DTC EU - P&L'!G20*G$143 -> 0 | H26: ='DTC EU - P&L'!H20*H$143 -> 78.5301 | I26: ='DTC EU - P&L'!I20*I$143 -> 206.26528 | ... AF26: ='DTC EU - P&L'!AF20*AF$143 -> 158.87662
A27: - Shipping | B27: ='DTC EU - P&L'!B21*B$143 -> 29.3325 | C27: ='DTC EU - P&L'!C21*C$143 -> 58.595 | D27: ='DTC EU - P&L'!D21*D$143 -> 41.1005 | E27: ='DTC EU - P&L'!E21*E$143 -> 41.083 | F27: ='DTC EU - P&L'!F21*F$143 -> 87.8775 | G27: ='DTC EU - P&L'!G21*G$143 -> 0 | H27: ='DTC EU - P&L'!H21*H$143 -> 40.81 | I27: ='DTC EU - P&L'!I21*I$143 -> 98.8975 | ... AF27: ='DTC EU - P&L'!AF21*AF$143 -> 92.856
A28: - Yearly Premium Subscription | B28: =sum(B29:B30) -> 3933.9772 | C28: =sum(C29:C30) -> 2069.76 | D28: =sum(D29:D30) -> 2459.72 | E28: =sum(E29:E30) -> 1679.81 | F28: =sum(F29:F30) -> 1764.1607 | G28: =sum(G29:G30) -> 1379.84 | H28: =sum(H29:H30) -> 1589.73 | I28: =sum(I29:I30) -> 1737.0609 | ... AF28: =sum(AF29:AF30) -> 1698.79
A29: - Yearly Premium Subscription US&CA | B29: 3839.55 | C29: 2069.76 | D29: 2459.72 | E29: 1679.81 | F29: 1679.81 | G29: 1379.84 | H29: 1589.73 | I29: 1649.81 | J29: 1619.82 | K29: 1409.84 | L29: 959.89 | M29: 2159.75 | N29: 1529.8 | O29: 1799.78 | P29: 1649.72 | Q29: 2459.72 | R29: 2549.61 | S29: 2759.69 | T29: 1349.84 | U29: 1529.81 | V29: 1289.85 | W29: 2369.72 | X29: 1739.79 | Y29: 2308.72 | Z29: 1809.77 | AA29: 3108.62 | AB29: 2988.63 | AC29: 2999.64 | AD29: 1178.86 | AE29: 25149.39 | AF29: 1698.79
A30: - Yearly Premium Subscription EU | B30: ='DTC EU - P&L'!B19*B$143 -> 94.427184 | C30: ='DTC EU - P&L'!C19*C$143 -> 0 | D30: ='DTC EU - P&L'!D19*D$143 -> 0 | E30: ='DTC EU - P&L'!E19*E$143 -> 0 | F30: ='DTC EU - P&L'!F19*F$143 -> 84.350683 | G30: ='DTC EU - P&L'!G19*G$143 -> 0 | H30: ='DTC EU - P&L'!H19*H$143 -> 0 | I30: ='DTC EU - P&L'!I19*I$143 -> 87.250865 | ... AF30: ='DTC EU - P&L'!AF19*AF$143 -> 0
A31: Amazon Revenue | B31: =sum(B32,B38) -> 4779.61 | C31: =sum(C32,C38) -> 8636.61 | D31: =sum(D32,D38) -> 6081.55 | E31: =sum(E32,E38) -> 7265.88 | F31: =sum(F32,F38) -> 7430.04 | G31: =sum(G32,G38) -> 4593.61 | H31: =sum(H32,H38) -> 42819.01 | I31: =sum(I32,I38) -> 47876.17 | ... AF31: =sum(AF32,AF38) -> 5864.41
A32: Amazon Revenue US | B32: =B33+B34+B35+B36+B37 -> 4277.26 | C32: =C33+C34+C35+C36+C37 -> 8057.58 | D32: =D33+D34+D35+D36+D37 -> 5661.28 | E32: =E33+E34+E35+E36+E37 -> 6498.59 | F32: =F33+F34+F35+F36+F37 -> 7048.66 | G32: =G33+G34+G35+G36+G37 -> 4593.61 | H32: =H33+H34+H35+H36+H37 -> 41026.28 | I32: =I33+I34+I35+I36+I37 -> 46178.59 | ... AF32: =AF33+AF34+AF35+AF36+AF37 -> 5819.91
A33: - Hardware | B33: 3885 | C33: 7382 | D33: 5230 | E33: 5848 | F33: 6456 | G33: 4134 | H33: 37960.25 | I33: 42698 | J33: 24350.65 | K33: 5718 | L33: 7820 | M33: 5210 | N33: 5230 | O33: 5031 | P33: 1614 | Q33: 2053 | R33: 4624 | S33: 6219 | T33: 3189 | U33: 5023 | V33: 4126 | W33: 4903 | X33: 7853 | Y33: 7343.04 | Z33: 7355 | AA33: 4365 | AB33: 5322 | AC33: 7415 | AD33: 3827 | AE33: 6478 | AF33: 5322
A34: - Add-ons | B34: 116 | C34: 165 | D34: 68 | E34: 185 | F34: 116 | G34: 136 | H34: 262 | I34: 427 | J34: 223 | K34: 136 | L34: 213 | M34: 87 | N34: 58 | O34: 107 | P34: 87 | Q34: 97 | R34: 58 | S34: 97 | T34: 87 | U34: 126 | V34: 126 | W34: 39 | X34: 146 | Y34: 68 | Z34: 291 | AA34: 204 | AB34: 136 | AC34: 68 | AD34: 68 | AE34: 155 | AF34: 97
A35: - Tax | B35: 259.98 | C35: 506.09 | D35: 358.79 | E35: 458.68 | F35: 476.66 | G35: 319.12 | H35: 2777.09 | I35: 3037.62 | J35: 1711.31 | K35: 414.1 | L35: 602.38 | M35: 392.54 | N35: 383.55 | O35: 352.09 | P35: 94.23 | Q35: 136.91 | R35: 324.96 | S35: 463.7 | T35: 217.07 | U35: 396.78 | V35: 314.57 | W35: 338.82 | X35: 587.73 | Y35: 501.74 | Z35: 571.7 | AA35: 276.61 | AB35: 421.8 | AC35: 525.4 | AD35: 298.31 | AE35: 421.08 | AF35: 400.91
A36: - Shipping | B36: 11.79 | C36: 0 | D36: 0 | E36: 6.91 | F36: 0 | G36: 0 | H36: 8.98 | I36: 6.99 | J36: 0 | K36: 0 | L36: 0 | M36: 0 | N36: 10.7 | O36: 0 | P36: 0 | Q36: 0 | R36: 0 | S36: 0 | T36: 0 | U36: 0 | V36: 0 | W36: 6.99 | X36: 0 | Y36: 0 | Z36: 0 | AA36: 13.98 | AB36: 11.42 | AC36: 0 | AD36: 0 | AE36: 0 | AF36: 0
A37: - Gift Wrap | B37: 4.49 | C37: 4.49 | D37: 4.49 | E37: 0 | F37: 0 | G37: 4.49 | H37: 17.96 | I37: 8.98 | J37: 4.49 | K37: 13.47 | L37: 8.98 | M37: 4.49 | N37: 0 | O37: 8.98 | P37: 0 | Q37: 0 | R37: 8.98 | S37: 8.98 | T37: 0 | U37: 0 | V37: 0 | W37: 0 | X37: 13.47 | Y37: 8.98 | Z37: 4.49 | AA37: 4.49 | AB37: 4.49 | AC37: 0 | AD37: 0 | AE37: 0 | AF37: 0
A38: Amazon Revenue EU | B38: ='AMAZON EU - P&L'!B32 -> 502.35 | C38: ='AMAZON EU - P&L'!C32 -> 579.03 | D38: ='AMAZON EU - P&L'!D32 -> 420.27 | E38: ='AMAZON EU - P&L'!E32 -> 767.29 | F38: ='AMAZON EU - P&L'!F32 -> 381.38 | G38: ='AMAZON EU - P&L'!G32 -> 0 | H38: ='AMAZON EU - P&L'!H32 -> 1792.73 | I38: ='AMAZON EU - P&L'!I32 -> 1697.58 | ... AF38: ='AMAZON EU - P&L'!AF32 -> 44.5
A39: Amazon Revenue UK | B39: ='AMAZON UK, FR, GER - P&L'!B26 -> 136.8 | C39: ='AMAZON UK, FR, GER - P&L'!C26 -> 104.88 | D39: ='AMAZON UK, FR, GER - P&L'!D26 -> 0 | E39: ='AMAZON UK, FR, GER - P&L'!E26 -> 767.29 | F39: ='AMAZON UK, FR, GER - P&L'!F26 -> 0 | G39: ='AMAZON UK, FR, GER - P&L'!G26 -> 0 | H39: ='AMAZON UK, FR, GER - P&L'!H26 -> 45.41 | I39: ='AMAZON UK, FR, GER - P&L'!I26 -> 0 | ... AF39: ='AMAZON UK, FR, GER - P&L'!AF26 -> 44.5
A40: Amazon Revenue FR | B40: ='AMAZON UK, FR, GER - P&L'!B212 -> 365.55 | C40: ='AMAZON UK, FR, GER - P&L'!C212 -> 474.15 | D40: ='AMAZON UK, FR, GER - P&L'!D212 -> 40.32 | E40: ='AMAZON UK, FR, GER - P&L'!E212 -> 0 | F40: ='AMAZON UK, FR, GER - P&L'!F212 -> 381.38 | G40: ='AMAZON UK, FR, GER - P&L'!G212 -> 0 | H40: ='AMAZON UK, FR, GER - P&L'!H212 -> 383.6 | I40: ='AMAZON UK, FR, GER - P&L'!I212 -> 0 | ... AF40: ='AMAZON UK, FR, GER - P&L'!AF212 -> 0
A41: Amazon Revenue GER | B41: ='AMAZON UK, FR, GER - P&L'!B398 -> 0 | C41: ='AMAZON UK, FR, GER - P&L'!C398 -> 0 | D41: ='AMAZON UK, FR, GER - P&L'!D398 -> 379.95 | E41: ='AMAZON UK, FR, GER - P&L'!E398 -> 0 | F41: ='AMAZON UK, FR, GER - P&L'!F398 -> 0 | G41: ='AMAZON UK, FR, GER - P&L'!G398 -> 0 | H41: ='AMAZON UK, FR, GER - P&L'!H398 -> 1363.72 | I41: ='AMAZON UK, FR, GER - P&L'!I398 -> 1697.58 | ... AF41: ='AMAZON UK, FR, GER - P&L'!AF398 -> 0
A42: - Hardware | B42: ='AMAZON EU - P&L'!B27 -> 319.17 | C42: ='AMAZON EU - P&L'!C27 -> 326.96 | D42: ='AMAZON EU - P&L'!D27 -> 327.63 | E42: ='AMAZON EU - P&L'!E27 -> 657.68 | F42: ='AMAZON EU - P&L'!F27 -> 326.9 | G42: ='AMAZON EU - P&L'!G27 -> 0 | H42: ='AMAZON EU - P&L'!H27 -> 1452.31 | I42: ='AMAZON EU - P&L'!I27 -> 1381.95 | ... AF42: ='AMAZON EU - P&L'!AF27 -> 0
A43: - Add-ons | B43: ='AMAZON EU - P&L'!B28 -> 117.27 | C43: ='AMAZON EU - P&L'!C28 -> 149.25 | D43: ='AMAZON EU - P&L'!D28 -> 34.35 | E43: ='AMAZON EU - P&L'!E28 -> 0 | F43: ='AMAZON EU - P&L'!F28 -> 0 | G43: ='AMAZON EU - P&L'!G28 -> 0 | H43: ='AMAZON EU - P&L'!H28 -> 72.74 | I43: ='AMAZON EU - P&L'!I28 -> 79.77 | ... AF43: ='AMAZON EU - P&L'!AF28 -> 38.15
A44: - Tax | B44: ='AMAZON EU - P&L'!B29 -> 65.91 | C44: ='AMAZON EU - P&L'!C29 -> 74.48 | D44: ='AMAZON EU - P&L'!D29 -> 58.29 | E44: ='AMAZON EU - P&L'!E29 -> 109.61 | F44: ='AMAZON EU - P&L'!F29 -> 54.48 | G44: ='AMAZON EU - P&L'!G29 -> 0 | H44: ='AMAZON EU - P&L'!H29 -> 264.19 | I44: ='AMAZON EU - P&L'!I29 -> 235.86 | ... AF44: ='AMAZON EU - P&L'!AF29 -> 6.35
A45: - Shipping | B45: ='AMAZON EU - P&L'!B30 -> 0 | C45: ='AMAZON EU - P&L'!C30 -> 28.34 | D45: ='AMAZON EU - P&L'!D30 -> 0 | E45: ='AMAZON EU - P&L'!E30 -> 0 | F45: ='AMAZON EU - P&L'!F30 -> 0 | G45: ='AMAZON EU - P&L'!G30 -> 0 | H45: ='AMAZON EU - P&L'!H30 -> 0 | I45: ='AMAZON EU - P&L'!I30 -> 0 | ... AF45: ='AMAZON EU - P&L'!AF30 -> 0
A46: - Gift Wrap | B46: ='AMAZON EU - P&L'!B31 -> 0 | C46: ='AMAZON EU - P&L'!C31 -> 0 | D46: ='AMAZON EU - P&L'!D31 -> 0 | E46: ='AMAZON EU - P&L'!E31 -> 0 | F46: ='AMAZON EU - P&L'!F31 -> 0 | G46: ='AMAZON EU - P&L'!G31 -> 0 | H46: ='AMAZON EU - P&L'!H31 -> 3.49 | I46: ='AMAZON EU - P&L'!I31 -> 0 | ... AF46: ='AMAZON EU - P&L'!AF31 -> 0
A47: Total Revenue | B47: =SUM(B12+B31) -> 17319.368 | C47: =SUM(C12+C31) -> 18585.753 | D47: =SUM(D12+D31) -> 18865.748 | E47: =SUM(E12+E31) -> 15167.777 | F47: =SUM(F12+F31) -> 17720.3 | G47: =SUM(G12+G31) -> 14238.32 | H47: =SUM(H12+H31) -> 50034.115 | I47: =SUM(I12+I31) -> 56465.54 | ... AF47: =SUM(AF12+AF31) -> 20543.47
A49: B2B Revenue
A50: RETAIL Revenue
A51: Best Buy | B51: =iferror(sum(B52:B54),"") -> 1485.9069 | C51: =iferror(sum(C52:C54),"") -> 594.36277 | D51: =iferror(sum(D52:D54),"") -> 2377.4511 | E51: =iferror(sum(E52:E54),"") -> 594.36277 | F51: =iferror(sum(F52:F54),"") -> 0 | G51: =iferror(sum(G52:G54),"") -> 859.70216 | H51: =iferror(sum(H52:H54),"") -> 2080.2697 | I51: =iferror(sum(I52:I54),"") -> 859.70216 | ... AF51: =iferror(sum(AF52:AF54),"") -> 1585.7316
A52: - Hardware | B52: 1399.95 | C52: 559.98 | D52: 2239.92 | E52: 559.98 | F52: 0 | G52: 809.97 | H52: 1959.93 | I52: 809.97 | J52: 839.97 | K52: 1089.96 | L52: 1649.94 | M52: 0 | N52: 279.99 | O52: 1869.93 | P52: 2239.92 | Q52: 1399.95 | R52: 809.97 | S52: 1089.96 | T52: 0 | U52: 16551.99 | V52: 2629 | W52: 727.99 | X52: 1434 | Y52: 1733 | Z52: 1793 | AA52: 0 | AB52: 717 | AC52: 1255 | AD52: 717 | AE52: 1972 | AF52: 1494
A53: - Tax | B53: =B52*'Data - P&L'!$U$3 -> 85.95693 | C53: =C52*'Data - P&L'!$U$3 -> 34.382772 | D53: =D52*'Data - P&L'!$U$3 -> 137.53109 | E53: =E52*'Data - P&L'!$U$3 -> 34.382772 | F53: =F52*'Data - P&L'!$U$3 -> 0 | G53: =G52*'Data - P&L'!$U$3 -> 49.732158 | H53: =H52*'Data - P&L'!$U$3 -> 120.3397 | I53: =I52*'Data - P&L'!$U$3 -> 49.732158 | ... AF53: =AF52*'Data - P&L'!$U$3 -> 91.7316
A54: - Shipping
A55: Target | B55: =sum(B56:B58) -> 2220.4488 | C55: =sum(C56:C58) -> 3082.3056 | D55: =sum(D56:D58) -> 3281.8488 | E55: =sum(E56:E58) -> 1775.7222 | F55: =sum(F56:F58) -> 2384.9658 | G55: =sum(G56:G58) -> 1484.8986 | H55: =sum(H56:H58) -> 2808.4644 | I55: =sum(I56:I58) -> 998.7774 | ... AF55: =sum(AF56:AF58) -> 4383.582
A56: - Hardware | B56: 2092 | C56: 2904 | D56: 3092 | E56: 1673 | F56: 2247 | G56: 1399 | H56: 2646 | I56: 941 | J56: 1830 | K56: 1988 | L56: 3590 | M56: 1801 | N56: 932 | O56: 468 | P56: 2512 | Q56: 1126 | R56: 3111 | S56: 3272 | T56: 2549 | U56: 2390 | V56: 2361 | W56: 2750 | X56: 1833 | Y56: 1653 | Z56: 2593 | AA56: 2373 | AB56: 2750 | AC56: 2868 | AD56: 1434 | AE56: 3260 | AF56: 4130
A57: - Tax | B57: =B56*'Data - P&L'!$U$3 -> 128.4488 | C57: =C56*'Data - P&L'!$U$3 -> 178.3056 | D57: =D56*'Data - P&L'!$U$3 -> 189.8488 | E57: =E56*'Data - P&L'!$U$3 -> 102.7222 | F57: =F56*'Data - P&L'!$U$3 -> 137.9658 | G57: =G56*'Data - P&L'!$U$3 -> 85.8986 | H57: =H56*'Data - P&L'!$U$3 -> 162.4644 | I57: =I56*'Data - P&L'!$U$3 -> 57.7774 | ... AF57: =AF56*'Data - P&L'!$U$3 -> 253.582
A58: - Shipping
A59: Costco | B59: =SUM(B60:B62) -> 0 | C59: =SUM(C60:C62) -> 0 | D59: =SUM(D60:D62) -> 0 | E59: =SUM(E60:E62) -> 0 | F59: =SUM(F60:F62) -> 0 | G59: =SUM(G60:G62) -> 0 | H59: =SUM(H60:H62) -> 0 | I59: =SUM(I60:I62) -> 0 | ... AF59: =SUM(AF60:AF62) -> 0
A60: - Hardware | B60: 0 | C60: 0 | D60: 0 | E60: 0 | F60: 0 | G60: 0 | H60: 0 | I60: 0 | J60: 0 | K60: 0 | L60: 0 | M60: 0 | N60: 0 | O60: 0 | P60: 0 | Q60: 0 | R60: 0 | S60: 0 | T60: 0 | U60: 0 | V60: 0 | W60: 0 | X60: 0 | Y60: 0 | Z60: 0 | AA60: 0 | AB60: 0 | AC60: 0 | AD60: 0 | AE60: 0 | AF60: 0
A61: - Tax | B61: =0.0614*B60 -> 0 | C61: =0.0614*C60 -> 0 | D61: =0.0614*D60 -> 0 | E61: =0.0614*E60 -> 0 | F61: =0.0614*F60 -> 0 | G61: =0.0614*G60 -> 0 | H61: =0.0614*H60 -> 0 | I61: =0.0614*I60 -> 0 | ... AF61: =0.0614*AF60 -> 0
A62: - Shipping
A63: Chewy | B63: =SUM(B64:B66) -> 92.3418 | C63: =SUM(C64:C66) -> 0 | D63: =SUM(D64:D66) -> 0 | E63: =SUM(E64:E66) -> 316.2972 | F63: =SUM(F64:F66) -> 30.7806 | G63: =SUM(G64:G66) -> 0 | H63: =SUM(H64:H66) -> 228.201 | I63: =SUM(I64:I66) -> 690.01614 | ... AF63: =SUM(AF64:AF66) -> 348.38332
A64: - Hardware | B64: 87 | C64: 0 | D64: 0 | E64: 298 | F64: 29 | G64: 0 | H64: 215 | I64: 650.1 | J64: 405 | K64: 29 | L64: 766 | M64: 29 | N64: 219 | O64: 269 | P64: 299 | Q64: 299 | R64: 598 | S64: 0 | T64: 0 | U64: 58 | V64: 0 | W64: 0 | X64: 0 | Y64: 299 | Z64: 299 | AA64: 0 | AB64: 0 | AC64: 0 | AD64: 29.23 | AE64: 328.23 | AF64: 328.23
A65: - Tax | B65: =0.0614*B64 -> 5.3418 | C65: =0.0614*C64 -> 0 | D65: =0.0614*D64 -> 0 | E65: =0.0614*E64 -> 18.2972 | F65: =0.0614*F64 -> 1.7806 | G65: =0.0614*G64 -> 0 | H65: =0.0614*H64 -> 13.201 | I65: =0.0614*I64 -> 39.91614 | ... AF65: =0.0614*AF64 -> 20.153322
A66: - Shipping
A67: Walmart | B67: 0 | C67: =sum(C68:C70) -> 350.96 | D67: =sum(D68:D70) -> 0 | E67: =sum(E68:E70) -> 0 | F67: =sum(F68:F70) -> 0 | G67: =sum(G68:G70) -> 0 | H67: =sum(H68:H70) -> 31.03 | I67: =sum(I68:I70) -> 0 | J67: =sum(J68:J70) -> 31.18 | ... AF67: =sum(AF68:AF70) -> 321.43
A68: - Hardware | B68: 0 | C68: 328 | D68: 0 | E68: 0 | F68: 0 | G68: 0 | H68: 29 | I68: 0 | J68: 29 | K68: 219 | L68: 0 | M68: 0 | N68: 0 | O68: 0 | P68: 0 | Q68: 0 | R68: 0 | S68: 0 | T68: 239 | U68: 0 | V68: 239 | W68: 0 | X68: 0 | Y68: 0 | Z68: 0 | AA68: 0 | AB68: 299 | AC68: 0 | AD68: 0 | AE68: 0 | AF68: 299
A69: - Tax | B69: 0 | C69: 22.96 | D69: 0 | E69: 0 | F69: 0 | G69: 0 | H69: 2.03 | I69: 0 | J69: 2.18 | K69: 15.33 | L69: 0 | M69: 0 | N69: 0 | O69: 0 | P69: 0 | Q69: 0 | R69: 0 | S69: 0 | T69: 16.73 | U69: 0 | V69: 0 | W69: 0 | X69: 0 | Y69: 0 | Z69: 0 | AA69: 0 | AB69: 17.94 | AC69: 0 | AD69: 0 | AE69: 0 | AF69: 22.43
A70: - Shipping
A71: DIGITAL MARKETPLACES Revenue
A72: Rachio | B72: =SUM(B73:B74) -> 0 | C72: =SUM(C73:C74) -> 0 | D72: =SUM(D73:D74) -> 0 | E72: =SUM(E73:E74) -> 0 | F72: =SUM(F73:F74) -> 0 | G72: =SUM(G73:G74) -> 0 | H72: =SUM(H73:H74) -> 0 | I72: =SUM(I73:I74) -> 0 | ... AF72: =SUM(AF73:AF74) -> 0
A73: - Hardware
A74: - Tax | B74: =0.0614*B73 -> 0 | C74: =0.0614*C73 -> 0 | D74: =0.0614*D73 -> 0 | E74: =0.0614*E73 -> 0 | F74: =0.0614*F73 -> 0 | G74: =0.0614*G73 -> 0 | H74: =0.0614*H73 -> 0 | I74: =0.0614*I73 -> 0 | ... AF74: =0.0614*AF73 -> 0
A75: - Shipping
A76: Weatherflow | B76: =SUM(B77:B79) -> 0 | C76: =SUM(C77:C79) -> 0 | D76: =SUM(D77:D79) -> 0 | E76: =SUM(E77:E79) -> 0 | F76: =SUM(F77:F79) -> 0 | G76: =SUM(G77:G79) -> 0 | H76: =SUM(H77:H79) -> 0 | I76: =SUM(I77:I79) -> 0 | ... AF76: =SUM(AF77:AF79) -> 0
A77: - Hardware
A78: - Tax | B78: =0.0614*B77 -> 0 | C78: =0.0614*C77 -> 0 | D78: =0.0614*D77 -> 0 | E78: =0.0614*E77 -> 0 | F78: =0.0614*F77 -> 0 | G78: =0.0614*G77 -> 0 | H78: =0.0614*H77 -> 0 | I78: =0.0614*I77 -> 0 | ... AF78: =0.0614*AF77 -> 0
A79: - Shipping
A80: Huckberry | B80: =SUM(B81:B83) -> 0 | C80: =SUM(C81:C83) -> 0 | D80: =SUM(D81:D83) -> 0 | E80: =SUM(E81:E83) -> 0 | F80: =SUM(F81:F83) -> 0 | G80: =SUM(G81:G83) -> 0 | H80: =SUM(H81:H83) -> 0 | I80: =SUM(I81:I83) -> 0 | ... AF80: =SUM(AF81:AF83) -> 0
A81: - Hardware | B81: 0 | C81: 0 | D81: 0 | E81: 0 | F81: 0 | G81: 0 | H81: 0 | I81: 0 | J81: 0 | K81: 0 | L81: 0 | M81: 0 | N81: 0 | O81: 0 | P81: 0 | Q81: 0 | R81: 0 | S81: 0 | T81: 0 | U81: 0 | V81: 0 | W81: 0 | X81: 0 | Y81: 0 | Z81: 0 | AA81: 0 | AB81: 0 | AC81: 0 | AD81: 0 | AE81: 0 | AF81: 0
A82: - Tax | B82: =0.0614*B81 -> 0 | C82: =0.0614*C81 -> 0 | D82: =0.0614*D81 -> 0 | E82: =0.0614*E81 -> 0 | F82: =0.0614*F81 -> 0 | G82: =0.0614*G81 -> 0 | H82: =0.0614*H81 -> 0 | I82: =0.0614*I81 -> 0 | ... AF82: =0.0614*AF81 -> 0
A83: - Shipping
A84: Total Retail Revenue | B84: =sum(B51,B55,B59,B63,B67) -> 3798.6975 | C84: =sum(C51,C55,C59,C63,C67) -> 4027.6284 | D84: =sum(D51,D55,D59,D63,D67) -> 5659.2999 | E84: =sum(E51,E55,E59,E63,E67) -> 2686.3822 | F84: =sum(F51,F55,F59,F63,F67) -> 2415.7464 | G84: =sum(G51,G55,G59,G63,G67) -> 2344.6008 | H84: =sum(H51,H55,H59,H63,H67) -> 5147.9651 | I84: =sum(I51,I55,I59,I63,I67) -> 2548.4957 | ... AF84: =sum(AF51,AF55,AF59,AF63,AF67) -> 6639.1269
A85: Total DM Revenue | B85: =sum(B72,B76,B80) -> 0 | C85: =sum(C72,C76,C80) -> 0 | D85: =sum(D72,D76,D80) -> 0 | E85: =sum(E72,E76,E80) -> 0 | F85: =sum(F72,F76,F80) -> 0 | G85: =sum(G72,G76,G80) -> 0 | H85: =sum(H72,H76,H80) -> 0 | I85: =sum(I72,I76,I80) -> 0 | ... AF85: =sum(AF72,AF76,AF80) -> 0
A86: Total B2B Revenue | B86: =B84+B85 -> 3798.6975 | C86: =C84+C85 -> 4027.6284 | D86: =D84+D85 -> 5659.2999 | E86: =E84+E85 -> 2686.3822 | F86: =F84+F85 -> 2415.7464 | G86: =G84+G85 -> 2344.6008 | H86: =H84+H85 -> 5147.9651 | I86: =I84+I85 -> 2548.4957 | ... AF86: =AF84+AF85 -> 6639.1269
A88: App Revenue
A89: - Google Store | B89: ='App - P&L'!B90 -> 2677.7805 | C89: ='App - P&L'!C90 -> 2792.3945 | D89: ='App - P&L'!D90 -> 705.075 | E89: ='App - P&L'!E90 -> 1004.309 | F89: ='App - P&L'!F90 -> 1126.981 | G89: ='App - P&L'!G90 -> 242.2075 | H89: ='App - P&L'!H90 -> 685.2105 | I89: ='App - P&L'!I90 -> 698.6575 | ... AF89: ='App - P&L'!AF90 -> 785.944
A90: - Apple Store | B90: ='App - P&L'!B91 -> 7466.9062 | C90: ='App - P&L'!C91 -> 5844.2076 | D90: ='App - P&L'!D91 -> 2488.0625 | E90: ='App - P&L'!E91 -> 3471.9762 | F90: ='App - P&L'!F91 -> 3843.4913 | G90: ='App - P&L'!G91 -> 3499.9791 | H90: ='App - P&L'!H91 -> 3241.1893 | I90: ='App - P&L'!I91 -> 2351.9323 | ... AF90: ='App - P&L'!AF91 -> 2206.8131
A91: - Comission | B91: ='App - P&L'!B67 -> 3672.6522 | C91: ='App - P&L'!C67 -> 2997.4359 | D91: ='App - P&L'!D67 -> 1190.7375 | E91: ='App - P&L'!E67 -> 1665.2208 | F91: ='App - P&L'!F67 -> 1846.0895 | G91: ='App - P&L'!G67 -> 1542.7336 | H91: ='App - P&L'!H67 -> 1510.0006 | I91: ='App - P&L'!I67 -> 1131.2635 | ... AF91: ='App - P&L'!AF67 -> 1084.473
A92: - Tax | B92: ='App - P&L'!B68 -> 0 | C92: ='App - P&L'!C68 -> 0 | D92: ='App - P&L'!D68 -> 0 | E92: ='App - P&L'!E68 -> 0 | F92: ='App - P&L'!F68 -> 0 | G92: ='App - P&L'!G68 -> 0 | H92: ='App - P&L'!H68 -> 0 | I92: ='App - P&L'!I68 -> 0 | ... AF92: ='App - P&L'!AF68 -> 0
A93: Total App Revenue | B93: =sum(B89:B92) -> 13817.339 | C93: =sum(C89:C92) -> 11634.038 | D93: =sum(D89:D92) -> 4383.875 | E93: =sum(E89:E92) -> 6141.506 | F93: =sum(F89:F92) -> 6816.5618 | G93: =sum(G89:G92) -> 5284.9202 | H93: =sum(H89:H92) -> 5436.4004 | I93: =sum(I89:I92) -> 4181.8534 | ... AF93: =sum(AF89:AF92) -> 4077.2301
A95: Units Sold (DTC + AMZN) | B95: =B98+B105+B112+B118 -> 42 | C95: =C98+C105+C112+C118 -> 53 | D95: =D98+D105+D112+D118 -> 51 | E95: =E98+E105+E112+E118 -> 42 | F95: =F98+F105+F112+F118 -> 51 | G95: =G98+G105+G112+G118 -> 43 | H95: =H98+H105+H112+H118 -> 191 | I95: =I98+I105+I112+I118 -> 222 | ... AF95: =AF98+AF105+AF112+AF118 -> 58
A96: DTC Orders | B96: =sum(B97,B104) -> 91 | C96: =sum(C97,C104) -> 59 | D96: =sum(D97,D104) -> 79 | E96: =sum(E97,E104) -> 59 | F96: =sum(F97,F104) -> 71 | G96: =sum(G97,G104) -> 63 | H96: =sum(H97,H104) -> 58 | I96: =sum(I97,I104) -> 58 | ... AF96: =sum(AF97,AF104) -> 72
A97: - DTC Orders US&CA | B97: 88 | C97: 57 | D97: 77 | E97: 57 | F97: 67 | G97: 63 | H97: 56 | I97: 53 | J97: 61 | K97: 52 | L97: 51 | M97: 85 | N97: 58 | O97: 53 | P97: 56 | Q97: 65 | R97: 75 | S97: 74 | T97: 71 | U97: 68 | V97: 65 | W97: 86 | X97: 64 | Y97: 71 | Z97: 75 | AA97: 90 | AB97: 84 | AC97: 81 | AD97: 52 | AE97: 297 | AF97: 67
A98: - Hardware (units sold) | B98: =sum('DTC US&CA - P&L'!B34,'DTC US&CA - P&L'!B38,'DTC US&CA - P&L'!B41) -> 24 | C98: =sum('DTC US&CA - P&L'!C34,'DTC US&CA - P&L'!C38,'DTC US&CA - P&L'!C41) -> 22 | D98: =sum('DTC US&CA - P&L'!D34,'DTC US&CA - P&L'!D38,'DTC US&CA - P&L'!D41) -> 29 | E98: =sum('DTC US&CA - P&L'!E34,'DTC US&CA - P&L'!E38,'DTC US&CA - P&L'!E41) -> 17 | F98: =sum('DTC US&CA - P&L'!F34,'DTC US&CA - P&L'!F38,'DTC US&CA - P&L'!F41) -> 23 | G98: =sum('DTC US&CA - P&L'!G34,'DTC US&CA - P&L'!G38,'DTC US&CA - P&L'!G41) -> 27 | H98: =sum('DTC US&CA - P&L'!H34,'DTC US&CA - P&L'!H38,'DTC US&CA - P&L'!H41) -> 16 | I98: =sum('DTC US&CA - P&L'!I34,'DTC US&CA - P&L'!I38,'DTC US&CA - P&L'!I41) -> 17 | ... AF98: =sum('DTC US&CA - P&L'!AF34,'DTC US&CA - P&L'!AF38,'DTC US&CA - P&L'!AF41) -> 38
A99: - Add-ons (units sold) | B99: ='DTC US&CA - P&L'!B55 -> 43 | C99: ='DTC US&CA - P&L'!C55 -> 24 | D99: ='DTC US&CA - P&L'!D55 -> 39 | E99: ='DTC US&CA - P&L'!E55 -> 24 | F99: ='DTC US&CA - P&L'!F55 -> 37 | G99: ='DTC US&CA - P&L'!G55 -> 42 | H99: ='DTC US&CA - P&L'!H55 -> 29 | I99: ='DTC US&CA - P&L'!I55 -> 29 | ... AF99: ='DTC US&CA - P&L'!AF55 -> 33
A100: - Merch (units sold) | B100: 0 | C100: 0 | D100: 0 | E100: 0 | F100: 0 | G100: 0 | H100: 0 | I100: 0 | J100: 0 | K100: 0 | L100: 0 | M100: 0 | N100: 0 | O100: 0 | P100: 0 | Q100: 0 | R100: 0 | S100: 0 | T100: 0 | U100: 0 | V100: 0 | W100: 0 | X100: 0 | Y100: 0 | Z100: 0 | AA100: 0 | AB100: 0 | AC100: 0 | AD100: 0 | AE100: 0 | AF100: 0
A101: - Seeds (units sold) | B101: 8 | C101: 5 | D101: 11 | E101: 12 | F101: 11 | G101: 8 | H101: 9 | I101: 6 | J101: 11 | K101: 4 | L101: 13 | M101: 9 | N101: 3 | O101: 4 | P101: 9 | Q101: 8 | R101: 4 | S101: 4 | T101: 7 | U101: 6 | V101: 6 | W101: 3 | X101: 5 | Y101: 10 | Z101: 12 | AA101: 13 | AB101: 11 | AC101: 11 | AD101: 4 | AE101: 4 | AF101: 11
A102: - BB 1 year Pro Subscription | B102: 69 | C102: 43 | D102: 54 | E102: 38 | F102: 44 | G102: 39 | H102: 35 | I102: 36 | J102: 32 | K102: 35 | L102: 25 | M102: 51 | N102: 46 | O102: 39 | P102: 35 | Q102: 51 | R102: 54 | S102: 58 | T102: 46 | U102: 46 | V102: 44 | W102: 70 | X102: 51 | Y102: 51 | Z102: 56 | AA102: 70 | AB102: 67 | AC102: 62 | AD102: 38 | AE102: 290 | AF102: 48
A103: - Gift Bag | B103: 7 | C103: 9 | D103: 10 | E103: 9 | F103: 11 | G103: 8 | H103: 3 | I103: 6 | J103: 3 | K103: 10 | L103: 6 | M103: 11 | N103: 5 | O103: 3 | P103: 6 | Q103: 8 | R103: 12 | S103: 9 | T103: 12 | U103: 9 | V103: 8 | W103: 12 | X103: 7 | Y103: 9 | Z103: 16 | AA103: 15 | AB103: 14 | AC103: 12 | AD103: 13 | AE103: 18 | AF103: 27
A104: - DTC Orders EUROPE | B104: 3 | C104: 2 | D104: 2 | E104: 2 | F104: 4 | G104: 0 | H104: 2 | I104: 5 | J104: 5 | K104: 2 | L104: 3 | M104: 3 | N104: 3 | O104: 7 | P104: 2 | Q104: 2 | R104: 2 | S104: 6 | T104: 4 | U104: 2 | V104: 3 | W104: 7 | X104: 5 | Y104: 0 | Z104: 3 | AA104: 3 | AB104: 4 | AC104: 3 | AD104: 1 | AE104: 0 | AF104: 5
...

Sheet Chewy P&L
A1: OCTOBER | B1: 45931 | C1: 45932 | D1: 45933 | E1: 45934 | F1: 45935 | G1: 45936 | H1: 45937 | I1: 45938 | J1: 45939 | K1: 45940 | L1: 45941 | M1: 45942 | N1: 45943 | O1: 45944 | P1: 45945 | Q1: 45946 | R1: 45947 | S1: 45948 | T1: 45949 | U1: 45950 | V1: 45951 | W1: 45952 | X1: 45953 | Y1: 45954 | Z1: 45955 | AA1: 45956 | AB1: 45957 | AC1: 45958 | AD1: 45959 | AE1: 45960 | AF1: 45961
A2: DAY | B2: WED | C2: THU | D2: FRI | E2: SAT | F2: SUN | G2: MON | H2: TUE | I2: WED | J2: THU | K2: FRI | L2: SAT | M2: SUN | N2: MON | O2: TUE | P2: WED | Q2: THU | R2: FRI | S2: SAT | T2: SUN | U2: MON | V2: TUE | W2: WED | X2: THU | Y2: FRI | Z2: SAT | AA2: SUN | AB2: MON | AC2: TUE | AD2: WED | AE2: THU | AF2: FRI | AG2: SUM
A3: Orders | B3: =Summary!B127 -> 3 | C3: =Summary!C127 -> 0 | D3: =Summary!D127 -> 0 | E3: =Summary!E127 -> 2 | F3: =Summary!F127 -> 1 | G3: =Summary!G127 -> 0 | H3: =Summary!H127 -> 2 | I3: =Summary!I127 -> 4 | ... AF3: =Summary!AF127 -> 2 | AG3: =SUM(B3:AF3) -> 35
A4: Revenue | B4: =Summary!B63 -> 92.3418 | C4: =Summary!C63 -> 0 | D4: =Summary!D63 -> 0 | E4: =Summary!E63 -> 316.2972 | F4: =Summary!F63 -> 30.7806 | G4: =Summary!G63 -> 0 | H4: =Summary!H63 -> 228.201 | I4: =Summary!I63 -> 690.01614 | ... AF4: =Summary!AF63 -> 348.38332 | AG4: =SUM(B4:AF4) -> 5873.5647
A5: - Hardware | B5: =Summary!B64 -> 87 | C5: =Summary!C64 -> 0 | D5: =Summary!D64 -> 0 | E5: =Summary!E64 -> 298 | F5: =Summary!F64 -> 29 | G5: =Summary!G64 -> 0 | H5: =Summary!H64 -> 215 | I5: =Summary!I64 -> 650.1 | ... AF5: =Summary!AF64 -> 328.23 | AG5: =SUM(B5:AF5) -> 5533.79
A6: - Tax | B6: =Summary!B65 -> 5.3418 | C6: =Summary!C65 -> 0 | D6: =Summary!D65 -> 0 | E6: =Summary!E65 -> 18.2972 | F6: =Summary!F65 -> 1.7806 | G6: =Summary!G65 -> 0 | H6: =Summary!H65 -> 13.201 | I6: =Summary!I65 -> 39.91614 | ... AF6: =Summary!AF65 -> 20.153322 | AG6: =SUM(B6:AF6) -> 339.77471
A7: - Shipping | B7: =Summary!B66 | C7: =Summary!C66 | D7: =Summary!D66 | E7: =Summary!E66 | F7: =Summary!F66 | G7: =Summary!G66 | H7: =Summary!H66 | I7: =Summary!I66 | ... AF7: =Summary!AF66 | AG7: =SUM(B7:AF7) -> 0
A9: FROM ADS MANAGER
A10: - Sales | B10: 0 | C10: 0 | D10: 0 | E10: 0 | F10: 0 | G10: 0 | H10: 0 | I10: 0 | J10: 0 | K10: 0 | L10: 0 | M10: 0 | N10: 0 | O10: 0 | P10: 0 | Q10: 0 | R10: 0 | S10: 0 | T10: 0 | U10: 0 | V10: 0 | W10: 0 | X10: 0 | Y10: 0 | Z10: 0 | AA10: 0 | AB10: 0 | AC10: 0 | AD10: 0 | AE10: 0 | AF10: 0 | AG10: =SUM(B10:AF10) -> 0
A11: - Orders | B11: 0 | C11: 0 | D11: 0 | E11: 0 | F11: 0 | G11: 0 | H11: 0 | I11: 0 | J11: 0 | K11: 0 | L11: 0 | M11: 0 | N11: 0 | O11: 0 | P11: 0 | Q11: 0 | R11: 0 | S11: 0 | T11: 0 | U11: 0 | V11: 0 | W11: 0 | X11: 0 | Y11: 0 | Z11: 0 | AA11: 0 | AB11: 0 | AC11: 0 | AD11: 0 | AE11: 0 | AF11: 0 | AG11: =SUM(B11:AF11) -> 0
A12: - Spend | B12: =Summary!B159 -> 0 | C12: =Summary!C159 -> 0 | D12: =Summary!D159 -> 0 | E12: =Summary!E159 -> 0 | F12: =Summary!F159 -> 0 | G12: =Summary!G159 -> 0 | H12: =Summary!H159 -> 0 | I12: =Summary!I159 -> 0 | ... AF12: =Summary!AF159 -> 0 | AG12: =SUM(B12:AF12) -> 0
A14: Units Sold | B14: =B24+B28 -> 0 | C14: =C24+C28 -> 0 | D14: =D24+D28 -> 0 | E14: =E24+E28 -> 1 | F14: =F24+F28 -> 0 | G14: =G24+G28 -> 0 | H14: =H24+H28 -> 1 | I14: =I24+I28 -> 3 | ... AG14: =AG24+AG28 -> 20
A15: SKU 1 - Blue | B15: 0 | C15: 0 | D15: 0 | E15: 0 | F15: 0 | G15: 0 | H15: 0 | I15: 0 | J15: 0 | K15: 0 | L15: 0 | M15: 0 | N15: 0 | O15: 0 | P15: 0 | Q15: 0 | R15: 0 | S15: 0 | T15: 0 | U15: 0 | V15: 0 | W15: 0 | X15: 0 | Y15: 0 | Z15: 0 | AA15: 0 | AB15: 0 | AC15: 0 | AD15: 0 | AE15: 0 | AF15: 0 | AG15: =sum(B15:AF15) -> 0
A16: SKU 2 - Yellow | B16: 0 | C16: 0 | D16: 0 | E16: 0 | F16: 0 | G16: 0 | H16: 0 | I16: 0 | J16: 0 | K16: 0 | L16: 0 | M16: 0 | N16: 0 | O16: 0 | P16: 0 | Q16: 0 | R16: 0 | S16: 0 | T16: 0 | U16: 0 | V16: 0 | W16: 0 | X16: 0 | Y16: 0 | Z16: 0 | AA16: 0 | AB16: 0 | AC16: 0 | AD16: 0 | AE16: 0 | AF16: 0 | AG16: =sum(B16:AF16) -> 0
A17: SKU 3 - Blue w/ Solar | B17: 0 | C17: 0 | D17: 0 | E17: 0 | F17: 0 | G17: 0 | H17: 0 | I17: 0 | J17: 0 | K17: 0 | L17: 0 | M17: 0 | N17: 0 | O17: 0 | P17: 0 | Q17: 0 | R17: 0 | S17: 0 | T17: 0 | U17: 0 | V17: 0 | W17: 0 | X17: 0 | Y17: 0 | Z17: 0 | AA17: 0 | AB17: 0 | AC17: 0 | AD17: 0 | AE17: 0 | AF17: 0 | AG17: =sum(B17:AF17) -> 0
A18: SKU 4 - Yellow w/ Solar | B18: 0 | C18: 0 | D18: 0 | E18: 0 | F18: 0 | G18: 0 | H18: 0 | I18: 0 | J18: 0 | K18: 0 | L18: 0 | M18: 0 | N18: 0 | O18: 0 | P18: 0 | Q18: 0 | R18: 0 | S18: 0 | T18: 0 | U18: 0 | V18: 0 | W18: 0 | X18: 0 | Y18: 0 | Z18: 0 | AA18: 0 | AB18: 0 | AC18: 0 | AD18: 0 | AE18: 0 | AF18: 0 | AG18: =sum(B18:AF18) -> 0
A19: SKU 1 - Blue PRO | B19: 0 | C19: 0 | D19: 0 | E19: 0 | F19: 0 | G19: 0 | H19: 1 | I19: 1 | J19: 2 | K19: 0 | L19: 2 | M19: 0 | N19: 1 | O19: 0 | P19: 0 | Q19: 0 | R19: 0 | S19: 0 | T19: 0 | U19: 0 | V19: 0 | W19: 0 | X19: 0 | Y19: 0 | Z19: 0 | AA19: 0 | AB19: 0 | AC19: 0 | AD19: 0 | AE19: 0 | AF19: 0 | AG19: =sum(B19:AF19) -> 7
A20: SKU 2 - Yellow PRO | B20: 0 | C20: 0 | D20: 0 | E20: 0 | F20: 0 | G20: 0 | H20: 0 | I20: 0 | J20: 0 | K20: 0 | L20: 0 | M20: 0 | N20: 0 | O20: 0 | P20: 0 | Q20: 0 | R20: 0 | S20: 0 | T20: 0 | U20: 0 | V20: 0 | W20: 0 | X20: 0 | Y20: 0 | Z20: 0 | AA20: 0 | AB20: 0 | AC20: 0 | AD20: 0 | AE20: 0 | AF20: 0 | AG20: =sum(B20:AF20) -> 0
A21: SKU 3 - Blue w/ Solar PRO | B21: 0 | C21: 0 | D21: 0 | E21: 1 | F21: 0 | G21: 0 | H21: 0 | I21: 2 | J21: 0 | K21: 0 | L21: 0 | M21: 0 | N21: 0 | O21: 1 | P21: 0 | Q21: 0 | R21: 1 | S21: 0 | T21: 0 | U21: 0 | V21: 0 | W21: 0 | X21: 0 | Y21: 0 | Z21: 0 | AA21: 0 | AB21: 0 | AC21: 0 | AD21: 0 | AE21: 0 | AF21: 0 | AG21: =sum(B21:AF21) -> 5
A22: SKU 4 - Yellow w/ Solar PRO | B22: 0 | C22: 0 | D22: 0 | E22: 0 | F22: 0 | G22: 0 | H22: 0 | I22: 0 | J22: 0 | K22: 0 | L22: 0 | M22: 0 | N22: 0 | O22: 0 | P22: 0 | Q22: 0 | R22: 0 | S22: 0 | T22: 0 | U22: 0 | V22: 0 | W22: 0 | X22: 0 | Y22: 0 | Z22: 0 | AA22: 0 | AB22: 0 | AC22: 0 | AD22: 0 | AE22: 0 | AF22: 0 | AG22: =sum(B22:AF22) -> 0
A23: BBS4052RAA | B23: 0 | C23: 0 | D23: 0 | E23: 0 | F23: 0 | G23: 0 | H23: 0 | I23: 0 | J23: 0 | K23: 0 | L23: 1 | M23: 0 | N23: 0 | O23: 0 | P23: 1 | Q23: 1 | R23: 1 | S23: 0 | T23: 0 | U23: 0 | V23: 0 | W23: 0 | X23: 0 | Y23: 1 | Z23: 1 | AA23: 0 | AB23: 0 | AC23: 0 | AD23: 0 | AE23: 1 | AF23: 1 | AG23: =sum(B23:AF23) -> 8
A24: SUM (SKU 1 - SKU 4) | B24: =sum(B15:B23) -> 0 | C24: =sum(C15:C23) -> 0 | D24: =sum(D15:D23) -> 0 | E24: =sum(E15:E23) -> 1 | F24: =sum(F15:F23) -> 0 | G24: =sum(G15:G23) -> 0 | H24: =sum(H15:H23) -> 1 | I24: =sum(I15:I23) -> 3 | ... AF24: =sum(AF15:AF23) -> 1 | AG24: =sum(B24:AF24) -> 20
A26: SKU 5 - HBF | B26: 0 | C26: 0 | D26: 0 | E26: 0 | F26: 0 | G26: 0 | H26: 0 | I26: 0 | J26: 0 | K26: 0 | L26: 0 | M26: 0 | N26: 0 | O26: 0 | P26: 0 | Q26: 0 | R26: 0 | S26: 0 | T26: 0 | U26: 0 | V26: 0 | W26: 0 | X26: 0 | Y26: 0 | Z26: 0 | AA26: 0 | AB26: 0 | AC26: 0 | AD26: 0 | AE26: 0 | AF26: 0 | AG26: =sum(B26:AF26) -> 0
A27: SKU 6 - HBF w/ Solar | B27: 0 | C27: 0 | D27: 0 | E27: 0 | F27: 0 | G27: 0 | H27: 0 | I27: 0 | J27: 0 | K27: 0 | L27: 0 | M27: 0 | N27: 0 | O27: 0 | P27: 0 | Q27: 0 | R27: 0 | S27: 0 | T27: 0 | U27: 0 | V27: 0 | W27: 0 | X27: 0 | Y27: 0 | Z27: 0 | AA27: 0 | AB27: 0 | AC27: 0 | AD27: 0 | AE27: 0 | AF27: 0 | AG27: =sum(B27:AF27) -> 0
A28: SUM (SKU 5 - SKU 6) | B28: =SUM(B26:B27) -> 0 | C28: =SUM(C26:C27) -> 0 | D28: =SUM(D26:D27) -> 0 | E28: =SUM(E26:E27) -> 0 | F28: =SUM(F26:F27) -> 0 | G28: =SUM(G26:G27) -> 0 | H28: =SUM(H26:H27) -> 0 | I28: =SUM(I26:I27) -> 0 | ... AF28: =SUM(AF26:AF27) -> 0 | AG28: =sum(B28:AF28) -> 0
A30: Wall Mount | B30: 0 | C30: 0 | D30: 0 | E30: 0 | F30: 0 | G30: 0 | H30: 0 | I30: 0 | J30: 0 | K30: 0 | L30: 0 | M30: 0 | N30: 0 | O30: 0 | P30: 0 | Q30: 0 | R30: 0 | S30: 0 | T30: 0 | U30: 0 | V30: 0 | W30: 0 | X30: 0 | Y30: 0 | Z30: 0 | AA30: 0 | AB30: 0 | AC30: 0 | AD30: 0 | AE30: 0 | AF30: 0 | AG30: =sum(B30:AF30) -> 0
A31: Suet Ball Holder | B31: 0 | C31: 0 | D31: 0 | E31: 0 | F31: 0 | G31: 0 | H31: 0 | I31: 0 | J31: 0 | K31: 0 | L31: 0 | M31: 0 | N31: 0 | O31: 0 | P31: 0 | Q31: 0 | R31: 0 | S31: 0 | T31: 0 | U31: 0 | V31: 0 | W31: 0 | X31: 0 | Y31: 0 | Z31: 0 | AA31: 0 | AB31: 0 | AC31: 0 | AD31: 0 | AE31: 0 | AF31: 0 | AG31: =sum(B31:AF31) -> 0
A32: 3-in-1 Nutrition Set - Blue | B32: 0 | C32: 0 | D32: 0 | E32: 0 | F32: 0 | G32: 0 | H32: 0 | I32: 0 | J32: 0 | K32: 0 | L32: 0 | M32: 0 | N32: 0 | O32: 0 | P32: 0 | Q32: 0 | R32: 0 | S32: 0 | T32: 0 | U32: 0 | V32: 0 | W32: 0 | X32: 0 | Y32: 0 | Z32: 0 | AA32: 0 | AB32: 0 | AC32: 0 | AD32: 0 | AE32: 0 | AF32: 0 | AG32: =sum(B32:AF32) -> 0
A33: 3-in-1 Nutrition Set - Yellow | B33: 0 | C33: 0 | D33: 0 | E33: 0 | F33: 0 | G33: 0 | H33: 0 | I33: 0 | J33: 0 | K33: 0 | L33: 0 | M33: 0 | N33: 0 | O33: 0 | P33: 0 | Q33: 0 | R33: 0 | S33: 0 | T33: 0 | U33: 0 | V33: 0 | W33: 0 | X33: 0 | Y33: 0 | Z33: 0 | AA33: 0 | AB33: 0 | AC33: 0 | AD33: 0 | AE33: 0 | AF33: 0 | AG33: =sum(B33:AF33) -> 0
A34: Solar Roof Single - Blue | B34: 0 | C34: 0 | D34: 0 | E34: 0 | F34: 0 | G34: 0 | H34: 0 | I34: 0 | J34: 0 | K34: 0 | L34: 0 | M34: 0 | N34: 0 | O34: 0 | P34: 0 | Q34: 0 | R34: 0 | S34: 0 | T34: 0 | U34: 0 | V34: 0 | W34: 0 | X34: 0 | Y34: 0 | Z34: 0 | AA34: 0 | AB34: 0 | AC34: 0 | AD34: 0 | AE34: 0 | AF34: 0 | AG34: =sum(B34:AF34) -> 0
A35: Solar Roof Single - Yellow | B35: 0 | C35: 0 | D35: 0 | E35: 0 | F35: 0 | G35: 0 | H35: 0 | I35: 0 | J35: 0 | K35: 0 | L35: 0 | M35: 0 | N35: 0 | O35: 0 | P35: 0 | Q35: 0 | R35: 0 | S35: 0 | T35: 0 | U35: 0 | V35: 0 | W35: 0 | X35: 0 | Y35: 0 | Z35: 0 | AA35: 0 | AB35: 0 | AC35: 0 | AD35: 0 | AE35: 0 | AF35: 0 | AG35: =sum(B35:AF35) -> 0
A36: Perch Extender - Blue | B36: 3 | C36: 0 | D36: 0 | E36: 1 | F36: 1 | G36: 0 | H36: 1 | I36: 1 | J36: 0 | K36: 1 | L36: 1 | M36: 1 | N36: 0 | O36: 0 | P36: 0 | Q36: 0 | R36: 0 | S36: 0 | T36: 0 | U36: 2 | V36: 0 | W36: 0 | X36: 0 | Y36: 0 | Z36: 0 | AA36: 0 | AB36: 0 | AC36: 0 | AD36: 1 | AE36: 1 | AF36: 1 | AG36: =sum(B36:AF36) -> 15
A37: Perch Extender - Yellow | B37: 0 | C37: 0 | D37: 0 | E37: 0 | F37: 0 | G37: 0 | H37: 0 | I37: 0 | J37: 0 | K37: 0 | L37: 0 | M37: 0 | N37: 0 | O37: 0 | P37: 0 | Q37: 0 | R37: 0 | S37: 0 | T37: 0 | U37: 0 | V37: 0 | W37: 0 | X37: 0 | Y37: 0 | Z37: 0 | AA37: 0 | AB37: 0 | AC37: 0 | AD37: 0 | AE37: 0 | AF37: 0 | AG37: =sum(B37:AF37) -> 0
A38: Solar Roof (HBF) | B38: 0 | C38: 0 | D38: 0 | E38: 0 | F38: 0 | G38: 0 | H38: 0 | I38: 0 | J38: 0 | K38: 0 | L38: 0 | M38: 0 | N38: 0 | O38: 0 | P38: 0 | Q38: 0 | R38: 0 | S38: 0 | T38: 0 | U38: 0 | V38: 0 | W38: 0 | X38: 0 | Y38: 0 | Z38: 0 | AA38: 0 | AB38: 0 | AC38: 0 | AD38: 0 | AE38: 0 | AF38: 0 | AG38: =sum(B38:AF38) -> 0
A39: Housing - only (HBF) | B39: 0 | C39: 0 | D39: 0 | E39: 0 | F39: 0 | G39: 0 | H39: 0 | I39: 0 | J39: 0 | K39: 0 | L39: 0 | M39: 0 | N39: 0 | O39: 0 | P39: 0 | Q39: 0 | R39: 0 | S39: 0 | T39: 0 | U39: 0 | V39: 0 | W39: 0 | X39: 0 | Y39: 0 | Z39: 0 | AA39: 0 | AB39: 0 | AC39: 0 | AD39: 0 | AE39: 0 | AF39: 0 | AG39: =sum(B39:AF39) -> 0
A40: Nature Cam PRO | B40: 0 | C40: 0 | D40: 0 | E40: 0 | F40: 0 | G40: 0 | H40: 0 | I40: 0 | J40: 0 | K40: 0 | L40: 0 | M40: 0 | N40: 0 | O40: 0 | P40: 0 | Q40: 0 | R40: 0 | S40: 0 | T40: 0 | U40: 0 | V40: 0 | W40: 0 | X40: 0 | Y40: 0 | Z40: 0 | AA40: 0 | AB40: 0 | AC40: 0 | AD40: 0 | AE40: 0 | AF40: 0 | AG40: =sum(B40:AF40) -> 0
A41: SUM (Add-ons) | B41: =sum(B30:B40) -> 3 | C41: =sum(C30:C40) -> 0 | D41: =sum(D30:D40) -> 0 | E41: =sum(E30:E40) -> 1 | F41: =sum(F30:F40) -> 1 | G41: =sum(G30:G40) -> 0 | H41: =sum(H30:H40) -> 1 | I41: =sum(I30:I40) -> 1 | ... AF41: =sum(AF30:AF40) -> 1 | AG41: =sum(B41:AF41) -> 15

Sheet DTC - P&L
A1: OCTOBER | B1: 45931 | C1: 45932 | D1: 45933 | E1: 45934 | F1: 45935 | G1: 45936 | H1: 45937 | I1: 45938 | J1: 45939 | K1: 45940 | L1: 45941 | M1: 45942 | N1: 45943 | O1: 45944 | P1: 45945 | Q1: 45946 | R1: 45947 | S1: 45948 | T1: 45949 | U1: 45950 | V1: 45951 | W1: 45952 | X1: 45953 | Y1: 45954 | Z1: 45955 | AA1: 45956 | AB1: 45957 | AC1: 45958 | AD1: 45959 | AE1: 45960 | AF1: 45961
A2: DAY | B2: WED | C2: THU | D2: FRI | E2: SAT | F2: SUN | G2: MON | H2: TUE | I2: WED | J2: THU | K2: FRI | L2: SAT | M2: SUN | N2: MON | O2: TUE | P2: WED | Q2: THU | R2: FRI | S2: SAT | T2: SUN | U2: MON | V2: TUE | W2: WED | X2: THU | Y2: FRI | Z2: SAT | AA2: SUN | AB2: MON | AC2: TUE | AD2: WED | AE2: THU | AF2: FRI
A3: COMMENT
A4: Orders
A5: Meta | B5: 9 | C5: 16 | D5: 10 | E5: 4 | F5: 8 | G5: 6 | H5: 6 | I5: 4 | J5: 5 | K5: 2 | L5: 7 | M5: 11 | N5: 8 | O5: 10 | P5: 10 | Q5: 7 | R5: 17 | S5: 16 | T5: 16 | U5: 8 | V5: 10 | W5: 13 | X5: 16 | Y5: 16 | Z5: 24 | AA5: 20 | AB5: 15 | AC5: 15 | AD5: 13 | AE5: 14 | AF5: 18 | AG5: =SUM(B5:AF5) -> 354
A6: Google | B6: 7 | C6: 6 | D6: 22 | E6: 11 | F6: 7 | G6: 13 | H6: 6 | I6: 10 | J6: 5 | K6: 8 | L6: 9 | M6: 11 | N6: 14 | O6: 6 | P6: 5 | Q6: 9 | R6: 14 | S6: 12 | T6: 19 | U6: 17 | V6: 16 | W6: 18 | X6: 12 | Y6: 10 | Z6: 16 | AA6: 21 | AB6: 12 | AC6: 15 | AD6: 12 | AE6: 14 | AF6: 18 | AG6: =SUM(B6:AF6) -> 375
A7: TikTok | B7: 0 | C7: 0 | D7: 0 | E7: 0 | F7: 0 | G7: 0 | H7: 0 | I7: 0 | J7: 0 | K7: 0 | L7: 0 | M7: 0 | N7: 0 | O7: 0 | P7: 0 | Q7: 0 | R7: 0 | S7: 0 | T7: 0 | U7: 0 | V7: 0 | W7: 0 | X7: 0 | Y7: 0 | Z7: 0 | AA7: 0 | AB7: 0 | AC7: 0 | AD7: 0 | AE7: 0 | AF7: 0 | AG7: =SUM(B7:AF7) -> 0
A8: Bing | B8: 0 | C8: 4 | D8: 2 | E8: 2 | F8: 6 | G8: 4 | H8: 0 | I8: 2 | J8: 4 | K8: 2 | L8: 2 | M8: 2 | N8: 2 | O8: 2 | P8: 2 | Q8: 2 | R8: 2 | S8: 0 | T8: 14 | U8: 2 | V8: 2 | W8: 6 | X8: 2 | Y8: 8 | Z8: 6 | AA8: 2 | AB8: 4 | AC8: 2 | AD8: 2 | AE8: 4 | AF8: 4 | AG8: =SUM(B8:AF8) -> 98
A9: Email | B9: 0 | C9: 0 | D9: 0 | E9: 0 | F9: 0 | G9: 0 | H9: 0 | I9: 0 | J9: 0 | K9: 0 | L9: 0 | M9: 0 | N9: 0 | O9: 0 | P9: 0 | Q9: 0 | R9: 0 | S9: 0 | T9: 0 | U9: 0 | V9: 0 | W9: 0 | X9: 0 | Y9: 0 | Z9: 0 | AA9: 0 | AB9: 0 | AC9: 0 | AD9: 0 | AE9: 0 | AF9: 0 | AG9: =SUM(B9:AF9) -> 0
A10: Nextdoor | B10: - | C10: - | D10: - | E10: - | F10: - | G10: - | H10: - | I10: - | J10: - | K10: - | L10: - | M10: - | N10: - | O10: - | P10: - | Q10: - | R10: - | S10: - | T10: - | U10: - | V10: - | W10: - | X10: - | Y10: - | Z10: - | AA10: - | AB10: - | AC10: - | AD10: - | AE10: - | AF10: - | AG10: =SUM(B10:AF10) -> 0
A11: Affiliates (Refersion) | B11: - | C11: - | D11: - | E11: - | F11: - | G11: - | H11: - | I11: - | J11: - | K11: - | L11: - | M11: - | N11: - | O11: - | P11: - | Q11: - | R11: - | S11: - | T11: - | U11: - | V11: - | W11: - | X11: - | Y11: - | Z11: - | AA11: - | AB11: - | AC11: - | AD11: - | AE11: - | AF11: - | AG11: =SUM(B11:AF11) -> 0
A12: All | B12: =SUM(B5:B11) -> 16 | C12: =SUM(C5:C11) -> 26 | D12: =SUM(D5:D11) -> 34 | E12: =SUM(E5:E11) -> 17 | F12: =SUM(F5:F11) -> 21 | G12: =SUM(G5:G11) -> 23 | H12: =SUM(H5:H11) -> 12 | I12: =SUM(I5:I11) -> 16 | ... AF12: =SUM(AF5:AF11) -> 40 | AG12: =SUM(B12:AF12) -> 827
A14: Revenue
A15: Meta | B15: 2592.57 | C15: 2662.87 | D15: 2214.87 | E15: 787.71 | F15: 1918.17 | G15: 1221.27 | H15: 1126.82 | I15: 643.75 | J15: 609.51 | K15: 386.8 | L15: 1318.69 | M15: 2579.83 | N15: 1800.47 | O15: 6322.72 | P15: 6322.72 | Q15: 2167.7 | R15: 4279.44 | S15: 3550.78 | T15: 4840.69 | U15: 3091.32 | V15: 3206.49 | W15: 7543.93 | X15: 5346.76 | Y15: 5450.48 | Z15: 7903.75 | AA15: 6443.44 | AB15: 4586.19 | AC15: 4877.24 | AD15: 4944.58 | AE15: 4467.99 | AF15: 5054.63 | AG15: =SUM(B15:AF15) -> 110264.18
A16: Google | B16: 1445.92 | C16: 1171.36 | D16: 5187.83 | E16: 3219.02 | F16: 1871.47 | G16: 2620.66 | H16: 1929.79 | I16: 2295.87 | J16: 1795.91 | K16: 2398.03 | L16: 2902.92 | M16: 2540.72 | N16: 4093.2 | O16: 1456.6 | P16: 1240.88 | Q16: 3008.8 | R16: 4251.42 | S16: 3287.28 | T16: 4062.02 | U16: 4889.86 | V16: 3774.98 | W16: 5883.2 | X16: 3108.53 | Y16: 3754.96 | Z16: 3362.87 | AA16: 5829.58 | AB16: 2966.91 | AC16: 4841.91 | AD16: 3454.43 | AE16: 4164.09 | AF16: 4592.14 | AG16: =SUM(B16:AF16) -> 101403.16
A17: TikTok | B17: 0 | C17: 0 | D17: 0 | E17: 0 | F17: 0 | G17: 0 | H17: 0 | I17: 0 | J17: 0 | K17: 0 | L17: 0 | M17: 0 | N17: 0 | O17: 0 | P17: 0 | Q17: 0 | R17: 0 | S17: 0 | T17: 0 | U17: 0 | V17: 0 | W17: 0 | X17: 0 | Y17: 0 | Z17: 0 | AA17: 0 | AB17: 0 | AC17: 0 | AD17: 0 | AE17: 0 | AF17: 0 | AG17: =SUM(B17:AF17) -> 0
A18: Bing | B18: 0 | C18: 502 | D18: 251 | E18: 251 | F18: 753 | G18: 502 | H18: 0 | I18: 251 | J18: 502 | K18: 251 | L18: 251 | M18: 251 | N18: 251 | O18: 251 | P18: 251 | Q18: 251 | R18: 251 | S18: 0 | T18: 1757 | U18: 251 | V18: 251 | W18: 753 | X18: 251 | Y18: 1004 | Z18: 753 | AA18: 251 | AB18: 502 | AC18: 251 | AD18: 251 | AE18: 502 | AF18: 502 | AG18: =SUM(B18:AF18) -> 12299
A19: Email | B19: 0 | C19: 0 | D19: 0 | E19: 0 | F19: 0 | G19: 0 | H19: 0 | I19: 0 | J19: 0 | K19: 0 | L19: 0 | M19: 0 | N19: 0 | O19: 0 | P19: 0 | Q19: 0 | R19: 0 | S19: 0 | T19: 0 | U19: 0 | V19: 0 | W19: 0 | X19: 0 | Y19: 0 | Z19: 0 | AA19: 0 | AB19: 0 | AC19: 0 | AD19: 0 | AE19: 0 | AF19: 0 | AG19: =SUM(B19:AF19) -> 0
A20: Nextdoor | B20: - | C20: - | D20: - | E20: - | F20: - | G20: - | H20: - | I20: - | J20: - | K20: - | L20: - | M20: - | N20: - | O20: - | P20: - | Q20: - | R20: - | S20: - | T20: - | U20: - | V20: - | W20: - | X20: - | Y20: - | Z20: - | AA20: - | AB20: - | AC20: - | AD20: - | AE20: - | AF20: -
A21: Affiliates (Refersion) | B21: - | C21: - | D21: - | E21: - | F21: - | G21: - | H21: - | I21: - | J21: - | K21: - | L21: - | M21: - | N21: - | O21: - | P21: - | Q21: - | R21: - | S21: - | T21: - | U21: - | V21: - | W21: - | X21: - | Y21: - | Z21: - | AA21: - | AB21: - | AC21: - | AD21: - | AE21: - | AF21: -
A22: All | B22: =SUM(B15:B21) -> 4038.49 | C22: =SUM(C15:C21) -> 4336.23 | D22: =SUM(D15:D21) -> 7653.7 | E22: =SUM(E15:E21) -> 4257.73 | F22: =SUM(F15:F21) -> 4542.64 | G22: =SUM(G15:G21) -> 4343.93 | H22: =SUM(H15:H21) -> 3056.61 | I22: =SUM(I15:I21) -> 3190.62 | ... AF22: =SUM(AF15:AF21) -> 10148.77 | AG22: =SUM(B22:AF22) -> 223966.34
A24: Media Cost
A25: Meta | B25: =Summary!B144 -> 3578.17 | C25: =Summary!C144 -> 2319.61 | D25: =Summary!D144 -> 1579.22 | E25: =Summary!E144 -> 1331.36 | F25: =Summary!F144 -> 2034.93 | G25: =Summary!G144 -> 2639.58 | H25: =Summary!H144 -> 1643.5 | I25: =Summary!I144 -> 200.94 | ... AF25: =Summary!AF144 -> 7337.42 | AG25: =SUM(B25:AF25) -> 105997.18
A26: Google | B26: =Summary!B147 -> 263.84 | C26: =Summary!C147 -> 226.3 | D26: =Summary!D147 -> 282.72 | E26: =Summary!E147 -> 342.99 | F26: =Summary!F147 -> 552.67 | G26: =Summary!G147 -> 482.37 | H26: =Summary!H147 -> 443.73 | I26: =Summary!I147 -> 466.66 | ... AF26: =Summary!AF147 -> 863.56 | AG26: =SUM(B26:AF26) -> 22602.7
A27: TikTok | B27: =Summary!B151 -> 0 | C27: =Summary!C151 -> 799.88 | D27: =Summary!D151 -> 799.64 | E27: =Summary!E151 -> 769.64 | F27: =Summary!F151 -> 799.48 | G27: =Summary!G151 -> 799.84 | H27: =Summary!H151 -> 727.33 | I27: =Summary!I151 -> 452.81 | ... AF27: =Summary!AF151 -> 219.95 | AG27: =SUM(B27:AF27) -> 11680.77
A28: Bing | B28: =Summary!B150 -> 76.02 | C28: =Summary!C150 -> 73.31 | D28: =Summary!D150 -> 65.63 | E28: =Summary!E150 -> 61.74 | F28: =Summary!F150 -> 31.88 | G28: =Summary!G150 -> 52.29 | H28: =Summary!H150 -> 45.22 | I28: =Summary!I150 -> 40.86 | ... AF28: =Summary!AF150 -> 103.81 | AG28: =SUM(B28:AF28) -> 1716.13
A29: Nextdoor | B29: - | C29: - | D29: - | E29: - | F29: - | G29: - | H29: - | I29: - | J29: - | K29: - | L29: - | M29: - | N29: - | O29: - | P29: - | Q29: - | R29: - | S29: - | T29: - | U29: - | V29: - | W29: - | X29: - | Y29: - | Z29: - | AA29: - | AB29: - | AC29: - | AD29: - | AE29: - | AF29: - | AG29: =SUM(B29:AF29) -> 0
A30: Affiliate Fee (20%) | B30: - | C30: - | D30: - | E30: - | F30: - | G30: - | H30: - | I30: - | J30: - | K30: - | L30: - | M30: - | N30: - | O30: - | P30: - | Q30: - | R30: - | S30: - | T30: - | U30: - | V30: - | W30: - | X30: - | Y30: - | Z30: - | AA30: - | AB30: - | AC30: - | AD30: - | AE30: - | AF30: - | AG30: =SUM(B30:AF30) -> 0
A31: All | B31: =SUM(B25:B30) -> 3918.03 | C31: =SUM(C25:C30) -> 3419.1 | D31: =SUM(D25:D30) -> 2727.21 | E31: =SUM(E25:E30) -> 2505.73 | F31: =SUM(F25:F30) -> 3418.96 | G31: =SUM(G25:G30) -> 3974.08 | H31: =SUM(H25:H30) -> 2859.78 | I31: =SUM(I25:I30) -> 1161.27 | ... AF31: =SUM(AF25:AF30) -> 8524.74 | AG31: =SUM(B31:AF31) -> 141996.78
A36: Revenue
A37: Revenue Woocommerce (Platform) | B37: =Summary!B12 -> 12539.758 | C37: =Summary!C12 -> 9949.1431 | D37: =Summary!D12 -> 12784.198 | E37: =Summary!E12 -> 7901.8966 | F37: =Summary!F12 -> 10290.26 | G37: =Summary!G12 -> 9644.71 | H37: =Summary!H12 -> 7215.1045 | I37: =Summary!I12 -> 8589.3703 | ... AF37: =Summary!AF12 -> 14679.06 | AG37: =SUM(B37:AF37) -> 423370.67
A38: Revenue w/o renewals | B38: ='DTC US&CA - P&L'!B6+'DTC EU - P&L'!B6 -> 8185.9226 | C38: ='DTC US&CA - P&L'!C6+'DTC EU - P&L'!C6 -> 7613.7131 | D38: ='DTC US&CA - P&L'!D6+'DTC EU - P&L'!D6 -> 9894.2777 | E38: ='DTC US&CA - P&L'!E6+'DTC EU - P&L'!E6 -> 5661.0966 | F38: ='DTC US&CA - P&L'!F6+'DTC EU - P&L'!F6 -> 8120.4091 | G38: ='DTC US&CA - P&L'!G6+'DTC EU - P&L'!G6 -> 7937.85 | H38: ='DTC US&CA - P&L'!H6+'DTC EU - P&L'!H6 -> 5296.1145 | I38: ='DTC US&CA - P&L'!I6+'DTC EU - P&L'!I6 -> 6538.317 | ... AF38: ='DTC US&CA - P&L'!AF6+'DTC EU - P&L'!AF6 -> 13108.17 | AG38: =SUM(B38:AF38) -> 331588.16
A39: SUM | B39: =SUM(B37) -> 12539.758 | C39: =SUM(C37) -> 9949.1431 | D39: =SUM(D37) -> 12784.198 | E39: =SUM(E37) -> 7901.8966 | F39: =SUM(F37) -> 10290.26 | G39: =SUM(G37) -> 9644.71 | H39: =SUM(H37) -> 7215.1045 | I39: =SUM(I37) -> 8589.3703 | ... AF39: =SUM(AF37) -> 14679.06 | AG39: =SUM(B39:AF39) -> 423370.67
A41: Orders
A42: Orders Woocommerce (Platform) | B42: =Summary!B96 -> 91 | C42: =Summary!C96 -> 59 | D42: =Summary!D96 -> 79 | E42: =Summary!E96 -> 59 | F42: =Summary!F96 -> 71 | G42: =Summary!G96 -> 63 | H42: =Summary!H96 -> 58 | I42: =Summary!I96 -> 58 | ... AF42: =Summary!AF96 -> 72 | AG42: =SUM(B42:AF42) -> 2414
A43: Orders w/o renewals | B43: ='DTC US&CA - P&L'!B11+'DTC EU - P&L'!B11 -> 37 | C43: ='DTC US&CA - P&L'!C11+'DTC EU - P&L'!C11 -> 30 | D43: ='DTC US&CA - P&L'!D11+'DTC EU - P&L'!D11 -> 40 | E43: ='DTC US&CA - P&L'!E11+'DTC EU - P&L'!E11 -> 28 | F43: ='DTC US&CA - P&L'!F11+'DTC EU - P&L'!F11 -> 40 | G43: ='DTC US&CA - P&L'!G11+'DTC EU - P&L'!G11 -> 39 | H43: ='DTC US&CA - P&L'!H11+'DTC EU - P&L'!H11 -> 31 | I43: ='DTC US&CA - P&L'!I11+'DTC EU - P&L'!I11 -> 32 | ... AF43: ='DTC US&CA - P&L'!AF11+'DTC EU - P&L'!AF11 -> 49 | AG43: =SUM(B43:AF43) -> 1276
A44: SUM | B44: =SUM(B42) -> 91 | C44: =SUM(C42) -> 59 | D44: =SUM(D42) -> 79 | E44: =SUM(E42) -> 59 | F44: =SUM(F42) -> 71 | G44: =SUM(G42) -> 63 | H44: =SUM(H42) -> 58 | I44: =SUM(I42) -> 58 | ... AF44: =SUM(AF42) -> 72 | AG44: =SUM(B44:AF44) -> 2414
A46: Breakdown
A47: - Hardware | B47: =Summary!B14+Summary!B22 -> 6146.5884 | C47: =Summary!C14+Summary!C22 -> 5565.5252 | D47: =Summary!D14+Summary!D22 -> 7290.9548 | E47: =Summary!E14+Summary!E22 -> 4131.5594 | F47: =Summary!F14+Summary!F22 -> 6209.5856 | G47: =Summary!G14+Summary!G22 -> 5734.2 | H47: =Summary!H14+Summary!H22 -> 3919.5246 | I47: =Summary!I14+Summary!I22 -> 4703.1754 | ... AF47: =Summary!AF14+Summary!AF22 -> 9573.0278 | AG47: =SUM(B47:AF47) -> 245439.36
A48: - Add-ons | B48: =Summary!B15+Summary!B23 -> 593.65103 | C48: =Summary!C15+Summary!C23 -> 684.64945 | D48: =Summary!D15+Summary!D23 -> 886.95859 | E48: =Summary!E15+Summary!E23 -> 371.83157 | F48: =Summary!F15+Summary!F23 -> 310.76389 | G48: =Summary!G15+Summary!G23 -> 715 | H48: =Summary!H15+Summary!H23 -> 447.59978 | I48: =Summary!I15+Summary!I23 -> 578.10126 | ... AF48: =Summary!AF15+Summary!AF23 -> 544.13001 | AG48: =SUM(B48:AF48) -> 23254.95
A49: - Merch | B49: =Summary!B16+Summary!B24 -> 0 | C49: =Summary!C16+Summary!C24 -> 0 | D49: =Summary!D16+Summary!D24 -> 0 | E49: =Summary!E16+Summary!E24 -> 0 | F49: =Summary!F16+Summary!F24 -> 0 | G49: =Summary!G16+Summary!G24 -> 0 | H49: =Summary!H16+Summary!H24 -> 0 | I49: =Summary!I16+Summary!I24 -> 0 | ... AF49: =Summary!AF16+Summary!AF24 -> 0 | AG49: =SUM(B49:AF49) -> 0
A50: - Seeds | B50: =Summary!B17+Summary!B25 -> 236.2 | C50: =Summary!C17+Summary!C25 -> 169.5 | D50: =Summary!D17+Summary!D25 -> 345.9 | E50: =Summary!E17+Summary!E25 -> 435.7 | F50: =Summary!F17+Summary!F25 -> 323.9 | G50: =Summary!G17+Summary!G25 -> 242 | H50: =Summary!H17+Summary!H25 -> 257.9 | I50: =Summary!I17+Summary!I25 -> 216.4 | ... AF50: =Summary!AF17+Summary!AF25 -> 367.1 | AG50: =SUM(B50:AF50) -> 7971.45
A51: - Yearly Pro Subscription | B51: ='DTC US&CA - P&L'!B19+Summary!B30 -> 3933.9772 | C51: ='DTC US&CA - P&L'!C19+Summary!C30 -> 2069.76 | D51: ='DTC US&CA - P&L'!D19+Summary!D30 -> 2459.72 | E51: ='DTC US&CA - P&L'!E19+Summary!E30 -> 1679.81 | F51: ='DTC US&CA - P&L'!F19+Summary!F30 -> 1764.1607 | G51: ='DTC US&CA - P&L'!G19+Summary!G30 -> 1379.84 | H51: ='DTC US&CA - P&L'!H19+Summary!H30 -> 1589.73 | I51: ='DTC US&CA - P&L'!I19+Summary!I30 -> 1737.0609 | ... AF51: ='DTC US&CA - P&L'!AF19+Summary!AF30 -> 1698.79 | AG51: =SUM(B51:AF51) -> 85787.642
A52: - Taxes | B52: =Summary!B18+Summary!B26 -> 788.28838 | C52: =Summary!C18+Summary!C26 -> 622.39345 | D52: =Summary!D18+Summary!D26 -> 763.36383 | E52: =Summary!E18+Summary!E26 -> 542.9727 | F52: =Summary!F18+Summary!F26 -> 739.45273 | G52: =Summary!G18+Summary!G26 -> 635.71 | H52: =Summary!H18+Summary!H26 -> 396.8001 | I52: =Summary!I18+Summary!I26 -> 637.35528 | ... AF52: =Summary!AF18+Summary!AF26 -> 958.43662 | AG52: =SUM(B52:AF52) -> 26804.918
A53: - Shipping | B53: =Summary!B19+Summary!B27 -> 731.7525 | C53: =Summary!C19+Summary!C27 -> 688.215 | D53: =Summary!D19+Summary!D27 -> 883.3005 | E53: =Summary!E19+Summary!E27 -> 575.393 | F53: =Summary!F19+Summary!F27 -> 743.4975 | G53: =Summary!G19+Summary!G27 -> 803.76 | H53: =Summary!H19+Summary!H27 -> 548.85 | I53: =Summary!I19+Summary!I27 -> 622.8775 | ... AF53: =Summary!AF19+Summary!AF27 -> 1139.576 | AG53: =SUM(B53:AF53) -> 29610.915
A54: - Gift Bag | B54: =Summary!B20 -> 109.3 | C54: =Summary!C20 -> 149.1 | D54: =Summary!D20 -> 154 | E54: =Summary!E20 -> 164.63 | F54: =Summary!F20 -> 198.9 | G54: =Summary!G20 -> 134.2 | H54: =Summary!H20 -> 54.7 | I54: =Summary!I20 -> 94.4 | ... AF54: =Summary!AF20 -> 398 | AG54: =SUM(B54:AF54) -> 4501.43
A55: SUM | B55: =SUM(B47:B54) -> 12539.758 | C55: =SUM(C47:C54) -> 9949.1431 | D55: =SUM(D47:D54) -> 12784.198 | E55: =SUM(E47:E54) -> 7901.8966 | F55: =SUM(F47:F54) -> 10290.26 | G55: =SUM(G47:G54) -> 9644.71 | H55: =SUM(H47:H54) -> 7215.1045 | I55: =SUM(I47:I54) -> 8589.3703 | ... AF55: =SUM(AF47:AF54) -> 14679.06 | AG55: =SUM(B55:AF55) -> 423370.67
A57: Units Sold (Gross)
A58: SKU 1 - Blue | B58: ='DTC US&CA - P&L'!B26+'DTC EU - P&L'!B25 -> 0 | C58: ='DTC US&CA - P&L'!C26+'DTC EU - P&L'!C25 -> 0 | D58: ='DTC US&CA - P&L'!D26+'DTC EU - P&L'!D25 -> 0 | E58: ='DTC US&CA - P&L'!E26+'DTC EU - P&L'!E25 -> 0 | F58: ='DTC US&CA - P&L'!F26+'DTC EU - P&L'!F25 -> 0 | G58: ='DTC US&CA - P&L'!G26+'DTC EU - P&L'!G25 -> 0 | H58: ='DTC US&CA - P&L'!H26+'DTC EU - P&L'!H25 -> 0 | I58: ='DTC US&CA - P&L'!I26+'DTC EU - P&L'!I25 -> 0 | ... AF58: ='DTC US&CA - P&L'!AF26+'DTC EU - P&L'!AF25 -> 0 | AG58: =SUM(B58:AF58) -> 0
A59: SKU 2 - Yellow | B59: ='DTC US&CA - P&L'!B27+'DTC EU - P&L'!B26 -> 0 | C59: ='DTC US&CA - P&L'!C27+'DTC EU - P&L'!C26 -> 0 | D59: ='DTC US&CA - P&L'!D27+'DTC EU - P&L'!D26 -> 0 | E59: ='DTC US&CA - P&L'!E27+'DTC EU - P&L'!E26 -> 0 | F59: ='DTC US&CA - P&L'!F27+'DTC EU - P&L'!F26 -> 0 | G59: ='DTC US&CA - P&L'!G27+'DTC EU - P&L'!G26 -> 0 | H59: ='DTC US&CA - P&L'!H27+'DTC EU - P&L'!H26 -> 0 | I59: ='DTC US&CA - P&L'!I27+'DTC EU - P&L'!I26 -> 0 | ... AF59: ='DTC US&CA - P&L'!AF27+'DTC EU - P&L'!AF26 -> 0 | AG59: =SUM(B59:AF59) -> 0
A60: SKU 3 - Blue w/ Solar | B60: ='DTC US&CA - P&L'!B28+'DTC EU - P&L'!B27 -> 0 | C60: ='DTC US&CA - P&L'!C28+'DTC EU - P&L'!C27 -> 0 | D60: ='DTC US&CA - P&L'!D28+'DTC EU - P&L'!D27 -> 0 | E60: ='DTC US&CA - P&L'!E28+'DTC EU - P&L'!E27 -> 0 | F60: ='DTC US&CA - P&L'!F28+'DTC EU - P&L'!F27 -> 0 | G60: ='DTC US&CA - P&L'!G28+'DTC EU - P&L'!G27 -> 0 | H60: ='DTC US&CA - P&L'!H28+'DTC EU - P&L'!H27 -> 0 | I60: ='DTC US&CA - P&L'!I28+'DTC EU - P&L'!I27 -> 0 | ... AF60: ='DTC US&CA - P&L'!AF28+'DTC EU - P&L'!AF27 -> 0 | AG60: =SUM(B60:AF60) -> 0
A61: SKU 4 - Yellow w/ Solar | B61: ='DTC US&CA - P&L'!B29+'DTC EU - P&L'!B28 -> 0 | C61: ='DTC US&CA - P&L'!C29+'DTC EU - P&L'!C28 -> 0 | D61: ='DTC US&CA - P&L'!D29+'DTC EU - P&L'!D28 -> 0 | E61: ='DTC US&CA - P&L'!E29+'DTC EU - P&L'!E28 -> 0 | F61: ='DTC US&CA - P&L'!F29+'DTC EU - P&L'!F28 -> 0 | G61: ='DTC US&CA - P&L'!G29+'DTC EU - P&L'!G28 -> 0 | H61: ='DTC US&CA - P&L'!H29+'DTC EU - P&L'!H28 -> 0 | I61: ='DTC US&CA - P&L'!I29+'DTC EU - P&L'!I28 -> 0 | ... AF61: ='DTC US&CA - P&L'!AF29+'DTC EU - P&L'!AF28 -> 0 | AG61: =SUM(B61:AF61) -> 0
A62: SKU 1 - Blue PRO | B62: ='DTC US&CA - P&L'!B30+'DTC EU - P&L'!B29 -> 9 | C62: ='DTC US&CA - P&L'!C30+'DTC EU - P&L'!C29 -> 6 | D62: ='DTC US&CA - P&L'!D30+'DTC EU - P&L'!D29 -> 6 | E62: ='DTC US&CA - P&L'!E30+'DTC EU - P&L'!E29 -> 4 | F62: ='DTC US&CA - P&L'!F30+'DTC EU - P&L'!F29 -> 7 | G62: ='DTC US&CA - P&L'!G30+'DTC EU - P&L'!G29 -> 9 | H62: ='DTC US&CA - P&L'!H30+'DTC EU - P&L'!H29 -> 7 | I62: ='DTC US&CA - P&L'!I30+'DTC EU - P&L'!I29 -> 8 | ... AF62: ='DTC US&CA - P&L'!AF30+'DTC EU - P&L'!AF29 -> 9 | AG62: =SUM(B62:AF62) -> 232
A63: SKU 2 - Yellow PRO | B63: ='DTC US&CA - P&L'!B31+'DTC EU - P&L'!B30 -> 0 | C63: ='DTC US&CA - P&L'!C31+'DTC EU - P&L'!C30 -> 0 | D63: ='DTC US&CA - P&L'!D31+'DTC EU - P&L'!D30 -> 0 | E63: ='DTC US&CA - P&L'!E31+'DTC EU - P&L'!E30 -> 0 | F63: ='DTC US&CA - P&L'!F31+'DTC EU - P&L'!F30 -> 0 | G63: ='DTC US&CA - P&L'!G31+'DTC EU - P&L'!G30 -> 0 | H63: ='DTC US&CA - P&L'!H31+'DTC EU - P&L'!H30 -> 0 | I63: ='DTC US&CA - P&L'!I31+'DTC EU - P&L'!I30 -> 0 | ... AF63: ='DTC US&CA - P&L'!AF31+'DTC EU - P&L'!AF30 -> 0 | AG63: =SUM(B63:AF63) -> 0
A64: SKU 3 - Blue w/ Solar PRO | B64: ='DTC US&CA - P&L'!B32+'DTC EU - P&L'!B31 -> 15 | C64: ='DTC US&CA - P&L'!C32+'DTC EU - P&L'!C31 -> 10 | D64: ='DTC US&CA - P&L'!D32+'DTC EU - P&L'!D31 -> 19 | E64: ='DTC US&CA - P&L'!E32+'DTC EU - P&L'!E31 -> 10 | F64: ='DTC US&CA - P&L'!F32+'DTC EU - P&L'!F31 -> 17 | G64: ='DTC US&CA - P&L'!G32+'DTC EU - P&L'!G31 -> 14 | H64: ='DTC US&CA - P&L'!H32+'DTC EU - P&L'!H31 -> 8 | I64: ='DTC US&CA - P&L'!I32+'DTC EU - P&L'!I31 -> 9 | ... AF64: ='DTC US&CA - P&L'!AF32+'DTC EU - P&L'!AF31 -> 25 | AG64: =SUM(B64:AF64) -> 619
A65: SKU 4 - Yellow w/ Solar PRO | B65: ='DTC US&CA - P&L'!B33+'DTC EU - P&L'!B32 -> 0 | C65: ='DTC US&CA - P&L'!C33+'DTC EU - P&L'!C32 -> 0 | D65: ='DTC US&CA - P&L'!D33+'DTC EU - P&L'!D32 -> 0 | E65: ='DTC US&CA - P&L'!E33+'DTC EU - P&L'!E32 -> 0 | F65: ='DTC US&CA - P&L'!F33+'DTC EU - P&L'!F32 -> 0 | G65: ='DTC US&CA - P&L'!G33+'DTC EU - P&L'!G32 -> 0 | H65: ='DTC US&CA - P&L'!H33+'DTC EU - P&L'!H32 -> 0 | I65: ='DTC US&CA - P&L'!I33+'DTC EU - P&L'!I32 -> 0 | ... AF65: ='DTC US&CA - P&L'!AF33+'DTC EU - P&L'!AF32 -> 0 | AG65: =SUM(B65:AF65) -> 0
A66: SUM (SKU 1 - SKU 4) | B66: =SUM(B58:B65) -> 24 | C66: =SUM(C58:C65) -> 16 | D66: =SUM(D58:D65) -> 25 | E66: =SUM(E58:E65) -> 14 | F66: =SUM(F58:F65) -> 24 | G66: =SUM(G58:G65) -> 23 | H66: =SUM(H58:H65) -> 15 | I66: =SUM(I58:I65) -> 17 | ... AF66: =SUM(AF58:AF65) -> 34 | AG66: =SUM(B66:AF66) -> 851
A68: SKU 5 - HBF PRO | B68: ='DTC US&CA - P&L'!B36+'DTC EU - P&L'!B35 -> 2 | C68: ='DTC US&CA - P&L'!C36+'DTC EU - P&L'!C35 -> 6 | D68: ='DTC US&CA - P&L'!D36+'DTC EU - P&L'!D35 -> 3 | E68: ='DTC US&CA - P&L'!E36+'DTC EU - P&L'!E35 -> 4 | F68: ='DTC US&CA - P&L'!F36+'DTC EU - P&L'!F35 -> 1 | G68: ='DTC US&CA - P&L'!G36+'DTC EU - P&L'!G35 -> 2 | H68: ='DTC US&CA - P&L'!H36+'DTC EU - P&L'!H35 -> 1 | I68: ='DTC US&CA - P&L'!I36+'DTC EU - P&L'!I35 -> 0 | ... AF68: ='DTC US&CA - P&L'!AF36+'DTC EU - P&L'!AF35 -> 3 | AG68: =SUM(B68:AF68) -> 56
A69: SKU 6 - HBF w/ Solar PRO | B69: ='DTC US&CA - P&L'!B37+'DTC EU - P&L'!B36 -> 0 | C69: ='DTC US&CA - P&L'!C37+'DTC EU - P&L'!C36 -> 2 | D69: ='DTC US&CA - P&L'!D37+'DTC EU - P&L'!D36 -> 2 | E69: ='DTC US&CA - P&L'!E37+'DTC EU - P&L'!E36 -> 0 | F69: ='DTC US&CA - P&L'!F37+'DTC EU - P&L'!F36 -> 1 | G69: ='DTC US&CA - P&L'!G37+'DTC EU - P&L'!G36 -> 2 | H69: ='DTC US&CA - P&L'!H37+'DTC EU - P&L'!H36 -> 1 | I69: ='DTC US&CA - P&L'!I37+'DTC EU - P&L'!I36 -> 3 | ... AF69: ='DTC US&CA - P&L'!AF37+'DTC EU - P&L'!AF36 -> 3 | AG69: =SUM(B69:AF69) -> 117
A70: SUM (SKU 5 - SKU 6) | B70: =SUM(B68:B69) -> 2 | C70: =SUM(C68:C69) -> 8 | D70: =SUM(D68:D69) -> 5 | E70: =SUM(E68:E69) -> 4 | F70: =SUM(F68:F69) -> 2 | G70: =SUM(G68:G69) -> 4 | H70: =SUM(H68:H69) -> 2 | I70: =SUM(I68:I69) -> 3 | ... AF70: =SUM(AF68:AF69) -> 6 | AG70: =SUM(B70:AF70) -> 173
A72: Bird Buddy 2 | B72: ='DTC US&CA - P&L'!B40 -> 0 | C72: ='DTC US&CA - P&L'!C40 -> 0 | D72: ='DTC US&CA - P&L'!D40 -> 0 | E72: ='DTC US&CA - P&L'!E40 -> 0 | F72: ='DTC US&CA - P&L'!F40 -> 0 | G72: ='DTC US&CA - P&L'!G40 -> 0 | H72: ='DTC US&CA - P&L'!H40 -> 0 | I72: ='DTC US&CA - P&L'!I40 -> 0 | ... AF72: ='DTC US&CA - P&L'!AF40 -> 0 | AG72: =SUM(B72:AF72) -> 0
A73: SUM (BB2) | B73: =SUM(B71:B72) -> 0 | C73: =SUM(C71:C72) -> 0 | D73: =SUM(D71:D72) -> 0 | E73: =SUM(E71:E72) -> 0 | F73: =SUM(F71:F72) -> 0 | G73: =SUM(G71:G72) -> 0 | H73: =SUM(H71:H72) -> 0 | I73: =SUM(I71:I72) -> 0 | ... AF73: =SUM(AF71:AF72) -> 0 | AG73: =SUM(B73:AF73) -> 0
A75: Wall Mount | B75: ='DTC US&CA - P&L'!B43+'DTC EU - P&L'!B39 -> 5 | C75: ='DTC US&CA - P&L'!C43+'DTC EU - P&L'!C39 -> 2 | D75: ='DTC US&CA - P&L'!D43+'DTC EU - P&L'!D39 -> 6 | E75: ='DTC US&CA - P&L'!E43+'DTC EU - P&L'!E39 -> 4 | F75: ='DTC US&CA - P&L'!F43+'DTC EU - P&L'!F39 -> 2 | G75: ='DTC US&CA - P&L'!G43+'DTC EU - P&L'!G39 -> 8 | H75: ='DTC US&CA - P&L'!H43+'DTC EU - P&L'!H39 -> 2 | I75: ='DTC US&CA - P&L'!I43+'DTC EU - P&L'!I39 -> 3 | ... AF75: ='DTC US&CA - P&L'!AF43+'DTC EU - P&L'!AF39 -> 1 | AG75: =SUM(B75:AF75) -> 124
A76: Suet Ball Holder | B76: ='DTC US&CA - P&L'!B44+'DTC EU - P&L'!B40 -> 20 | C76: ='DTC US&CA - P&L'!C44+'DTC EU - P&L'!C40 -> 16 | D76: ='DTC US&CA - P&L'!D44+'DTC EU - P&L'!D40 -> 21 | E76: ='DTC US&CA - P&L'!E44+'DTC EU - P&L'!E40 -> 11 | F76: ='DTC US&CA - P&L'!F44+'DTC EU - P&L'!F40 -> 29 | G76: ='DTC US&CA - P&L'!G44+'DTC EU - P&L'!G40 -> 15 | H76: ='DTC US&CA - P&L'!H44+'DTC EU - P&L'!H40 -> 14 | I76: ='DTC US&CA - P&L'!I44+'DTC EU - P&L'!I40 -> 14 | ... AF76: ='DTC US&CA - P&L'!AF44+'DTC EU - P&L'!AF40 -> 21 | AG76: =SUM(B76:AF76) -> 622
A77: 3-in-1 Nutrition Set - Blue | B77: ='DTC US&CA - P&L'!B45+'DTC EU - P&L'!B41 -> 3 | C77: ='DTC US&CA - P&L'!C45+'DTC EU - P&L'!C41 -> 0 | D77: ='DTC US&CA - P&L'!D45+'DTC EU - P&L'!D41 -> 2 | E77: ='DTC US&CA - P&L'!E45+'DTC EU - P&L'!E41 -> 1 | F77: ='DTC US&CA - P&L'!F45+'DTC EU - P&L'!F41 -> 0 | G77: ='DTC US&CA - P&L'!G45+'DTC EU - P&L'!G41 -> 1 | H77: ='DTC US&CA - P&L'!H45+'DTC EU - P&L'!H41 -> 2 | I77: ='DTC US&CA - P&L'!I45+'DTC EU - P&L'!I41 -> 3 | ... AF77: ='DTC US&CA - P&L'!AF45+'DTC EU - P&L'!AF41 -> 2 | AG77: =SUM(B77:AF77) -> 66
A78: 3-in-1 Nutrition Set - Yellow | B78: ='DTC US&CA - P&L'!B46+'DTC EU - P&L'!B42 -> 0 | C78: ='DTC US&CA - P&L'!C46+'DTC EU - P&L'!C42 -> 1 | D78: ='DTC US&CA - P&L'!D46+'DTC EU - P&L'!D42 -> 0 | E78: ='DTC US&CA - P&L'!E46+'DTC EU - P&L'!E42 -> 0 | F78: ='DTC US&CA - P&L'!F46+'DTC EU - P&L'!F42 -> 0 | G78: ='DTC US&CA - P&L'!G46+'DTC EU - P&L'!G42 -> 0 | H78: ='DTC US&CA - P&L'!H46+'DTC EU - P&L'!H42 -> 0 | I78: ='DTC US&CA - P&L'!I46+'DTC EU - P&L'!I42 -> 0 | ... AF78: ='DTC US&CA - P&L'!AF46+'DTC EU - P&L'!AF42 -> 0 | AG78: =SUM(B78:AF78) -> 2
A79: Solar Roof Single - Blue | B79: ='DTC US&CA - P&L'!B47+'DTC EU - P&L'!B43 -> 0 | C79: ='DTC US&CA - P&L'!C47+'DTC EU - P&L'!C43 -> 0 | D79: ='DTC US&CA - P&L'!D47+'DTC EU - P&L'!D43 -> 0 | E79: ='DTC US&CA - P&L'!E47+'DTC EU - P&L'!E43 -> 0 | F79: ='DTC US&CA - P&L'!F47+'DTC EU - P&L'!F43 -> 0 | G79: ='DTC US&CA - P&L'!G47+'DTC EU - P&L'!G43 -> 0 | H79: ='DTC US&CA - P&L'!H47+'DTC EU - P&L'!H43 -> 0 | I79: ='DTC US&CA - P&L'!I47+'DTC EU - P&L'!I43 -> 0 | ... AF79: ='DTC US&CA - P&L'!AF47+'DTC EU - P&L'!AF43 -> 0 | AG79: =SUM(B79:AF79) -> 0
A80: Solar Roof Single - Yellow | B80: ='DTC US&CA - P&L'!B48+'DTC EU - P&L'!B44 -> 0 | C80: ='DTC US&CA - P&L'!C48+'DTC EU - P&L'!C44 -> 0 | D80: ='DTC US&CA - P&L'!D48+'DTC EU - P&L'!D44 -> 1 | E80: ='DTC US&CA - P&L'!E48+'DTC EU - P&L'!E44 -> 0 | F80: ='DTC US&CA - P&L'!F48+'DTC EU - P&L'!F44 -> 0 | G80: ='DTC US&CA - P&L'!G48+'DTC EU - P&L'!G44 -> 0 | H80: ='DTC US&CA - P&L'!H48+'DTC EU - P&L'!H44 -> 0 | I80: ='DTC US&CA - P&L'!I48+'DTC EU - P&L'!I44 -> 0 | ... AF80: ='DTC US&CA - P&L'!AF48+'DTC EU - P&L'!AF44 -> 1 | AG80: =SUM(B80:AF80) -> 7
A81: Perch Extender - Blue | B81: ='DTC US&CA - P&L'!B49+'DTC EU - P&L'!B45 -> 15 | C81: ='DTC US&CA - P&L'!C49+'DTC EU - P&L'!C45 -> 7 | D81: ='DTC US&CA - P&L'!D49+'DTC EU - P&L'!D45 -> 10 | E81: ='DTC US&CA - P&L'!E49+'DTC EU - P&L'!E45 -> 10 | F81: ='DTC US&CA - P&L'!F49+'DTC EU - P&L'!F45 -> 9 | G81: ='DTC US&CA - P&L'!G49+'DTC EU - P&L'!G45 -> 18 | H81: ='DTC US&CA - P&L'!H49+'DTC EU - P&L'!H45 -> 12 | I81: ='DTC US&CA - P&L'!I49+'DTC EU - P&L'!I45 -> 16 | ... AF81: ='DTC US&CA - P&L'!AF49+'DTC EU - P&L'!AF45 -> 14 | AG81: =SUM(B81:AF81) -> 394
A82: Perch Extender - Yellow | B82: ='DTC US&CA - P&L'!B50+'DTC EU - P&L'!B46 -> 1 | C82: ='DTC US&CA - P&L'!C50+'DTC EU - P&L'!C46 -> 0 | D82: ='DTC US&CA - P&L'!D50+'DTC EU - P&L'!D46 -> 0 | E82: ='DTC US&CA - P&L'!E50+'DTC EU - P&L'!E46 -> 1 | F82: ='DTC US&CA - P&L'!F50+'DTC EU - P&L'!F46 -> 0 | G82: ='DTC US&CA - P&L'!G50+'DTC EU - P&L'!G46 -> 0 | H82: ='DTC US&CA - P&L'!H50+'DTC EU - P&L'!H46 -> 3 | I82: ='DTC US&CA - P&L'!I50+'DTC EU - P&L'!I46 -> 1 | ... AF82: ='DTC US&CA - P&L'!AF50+'DTC EU - P&L'!AF46 -> 1 | AG82: =SUM(B82:AF82) -> 16
A83: Solar Roof (HBF) | B83: ='DTC US&CA - P&L'!B51+'DTC EU - P&L'!B47 -> 0 | C83: ='DTC US&CA - P&L'!C51+'DTC EU - P&L'!C47 -> 0 | D83: ='DTC US&CA - P&L'!D51+'DTC EU - P&L'!D47 -> 0 | E83: ='DTC US&CA - P&L'!E51+'DTC EU - P&L'!E47 -> 0 | F83: ='DTC US&CA - P&L'!F51+'DTC EU - P&L'!F47 -> 0 | G83: ='DTC US&CA - P&L'!G51+'DTC EU - P&L'!G47 -> 0 | H83: ='DTC US&CA - P&L'!H51+'DTC EU - P&L'!H47 -> 0 | I83: ='DTC US&CA - P&L'!I51+'DTC EU - P&L'!I47 -> 0 | ... AF83: ='DTC US&CA - P&L'!AF51+'DTC EU - P&L'!AF47 -> 0 | AG83: =SUM(B83:AF83) -> 0
A84: Housing - only (HBF) | B84: ='DTC US&CA - P&L'!B52+'DTC EU - P&L'!B48 -> 0 | C84: ='DTC US&CA - P&L'!C52+'DTC EU - P&L'!C48 -> 1 | D84: ='DTC US&CA - P&L'!D52+'DTC EU - P&L'!D48 -> 0 | E84: ='DTC US&CA - P&L'!E52+'DTC EU - P&L'!E48 -> 0 | F84: ='DTC US&CA - P&L'!F52+'DTC EU - P&L'!F48 -> 0 | G84: ='DTC US&CA - P&L'!G52+'DTC EU - P&L'!G48 -> 0 | H84: ='DTC US&CA - P&L'!H52+'DTC EU - P&L'!H48 -> 0 | I84: ='DTC US&CA - P&L'!I52+'DTC EU - P&L'!I48 -> 0 | ... AF84: ='DTC US&CA - P&L'!AF52+'DTC EU - P&L'!AF48 -> 0 | AG84: =SUM(B84:AF84) -> 4
A85: Nature Station | B85: ='DTC US&CA - P&L'!B53+'DTC EU - P&L'!B49 -> 0 | C85: ='DTC US&CA - P&L'!C53+'DTC EU - P&L'!C49 -> 1 | D85: ='DTC US&CA - P&L'!D53+'DTC EU - P&L'!D49 -> 1 | E85: ='DTC US&CA - P&L'!E53+'DTC EU - P&L'!E49 -> 0 | F85: ='DTC US&CA - P&L'!F53+'DTC EU - P&L'!F49 -> 0 | G85: ='DTC US&CA - P&L'!G53+'DTC EU - P&L'!G49 -> 0 | H85: ='DTC US&CA - P&L'!H53+'DTC EU - P&L'!H49 -> 0 | I85: ='DTC US&CA - P&L'!I53+'DTC EU - P&L'!I49 -> 0 | ... AF85: ='DTC US&CA - P&L'!AF53+'DTC EU - P&L'!AF49 -> 0 | AG85: =SUM(B85:AF85) -> 21
A86: Nature Cam PRO | B86: ='DTC US&CA - P&L'!B54+'DTC EU - P&L'!B50 -> 0 | C86: ='DTC US&CA - P&L'!C54+'DTC EU - P&L'!C50 -> 0 | D86: ='DTC US&CA - P&L'!D54+'DTC EU - P&L'!D50 -> 0 | E86: ='DTC US&CA - P&L'!E54+'DTC EU - P&L'!E50 -> 0 | F86: ='DTC US&CA - P&L'!F54+'DTC EU - P&L'!F50 -> 0 | G86: ='DTC US&CA - P&L'!G54+'DTC EU - P&L'!G50 -> 0 | H86: ='DTC US&CA - P&L'!H54+'DTC EU - P&L'!H50 -> 0 | I86: ='DTC US&CA - P&L'!I54+'DTC EU - P&L'!I50 -> 0 | ... AF86: ='DTC US&CA - P&L'!AF54+'DTC EU - P&L'!AF50 -> 0 | AG86: =SUM(B86:AF86) -> 0
A87: SUM (Add-ons) | B87: =SUM(B75:B86) -> 44 | C87: =SUM(C75:C86) -> 28 | D87: =SUM(D75:D86) -> 41 | E87: =SUM(E75:E86) -> 27 | F87: =SUM(F75:F86) -> 40 | G87: =SUM(G75:G86) -> 42 | H87: =SUM(H75:H86) -> 33 | I87: =SUM(I75:I86) -> 37 | ... AF87: =SUM(AF75:AF86) -> 40 | AG87: =SUM(B87:AF87) -> 1256
A89: Seasonal Curation - 8lb | B89: ='DTC US&CA - P&L'!B57+'DTC EU - P&L'!B53 -> 8 | C89: ='DTC US&CA - P&L'!C57+'DTC EU - P&L'!C53 -> 4 | D89: ='DTC US&CA - P&L'!D57+'DTC EU - P&L'!D53 -> 10 | E89: ='DTC US&CA - P&L'!E57+'DTC EU - P&L'!E53 -> 7 | F89: ='DTC US&CA - P&L'!F57+'DTC EU - P&L'!F53 -> 10 | G89: ='DTC US&CA - P&L'!G57+'DTC EU - P&L'!G53 -> 7 | H89: ='DTC US&CA - P&L'!H57+'DTC EU - P&L'!H53 -> 9 | I89: ='DTC US&CA - P&L'!I57+'DTC EU - P&L'!I53 -> 4 | ... AF89: ='DTC US&CA - P&L'!AF57+'DTC EU - P&L'!AF53 -> 8 | AG89: =SUM(B89:AF89) -> 179
A90: Seasonal Curation - 20lb | B90: ='DTC US&CA - P&L'!B58+'DTC EU - P&L'!B54 -> 0 | C90: ='DTC US&CA - P&L'!C58+'DTC EU - P&L'!C54 -> 1 | D90: ='DTC US&CA - P&L'!D58+'DTC EU - P&L'!D54 -> 1 | E90: ='DTC US&CA - P&L'!E58+'DTC EU - P&L'!E54 -> 5 | F90: ='DTC US&CA - P&L'!F58+'DTC EU - P&L'!F54 -> 1 | G90: ='DTC US&CA - P&L'!G58+'DTC EU - P&L'!G54 -> 1 | H90: ='DTC US&CA - P&L'!H58+'DTC EU - P&L'!H54 -> 0 | I90: ='DTC US&CA - P&L'!I58+'DTC EU - P&L'!I54 -> 2 | ... AF90: ='DTC US&CA - P&L'!AF58+'DTC EU - P&L'!AF54 -> 1 | AG90: =SUM(B90:AF90) -> 30
A91: Buddy Bites - 8lb | B91: ='DTC US&CA - P&L'!B59+'DTC EU - P&L'!B55 -> 0 | C91: ='DTC US&CA - P&L'!C59+'DTC EU - P&L'!C55 -> 0 | D91: ='DTC US&CA - P&L'!D59+'DTC EU - P&L'!D55 -> 0 | E91: ='DTC US&CA - P&L'!E59+'DTC EU - P&L'!E55 -> 0 | F91: ='DTC US&CA - P&L'!F59+'DTC EU - P&L'!F55 -> 0 | G91: ='DTC US&CA - P&L'!G59+'DTC EU - P&L'!G55 -> 0 | H91: ='DTC US&CA - P&L'!H59+'DTC EU - P&L'!H55 -> 0 | I91: ='DTC US&CA - P&L'!I59+'DTC EU - P&L'!I55 -> 0 | ... AF91: ='DTC US&CA - P&L'!AF59+'DTC EU - P&L'!AF55 -> 0 | AG91: =SUM(B91:AF91) -> 0
A92: Buddy Bites - 20lb | B92: ='DTC US&CA - P&L'!B60+'DTC EU - P&L'!B56 -> 0 | C92: ='DTC US&CA - P&L'!C60+'DTC EU - P&L'!C56 -> 0 | D92: ='DTC US&CA - P&L'!D60+'DTC EU - P&L'!D56 -> 0 | E92: ='DTC US&CA - P&L'!E60+'DTC EU - P&L'!E56 -> 0 | F92: ='DTC US&CA - P&L'!F60+'DTC EU - P&L'!F56 -> 0 | G92: ='DTC US&CA - P&L'!G60+'DTC EU - P&L'!G56 -> 0 | H92: ='DTC US&CA - P&L'!H60+'DTC EU - P&L'!H56 -> 0 | I92: ='DTC US&CA - P&L'!I60+'DTC EU - P&L'!I56 -> 0 | ... AF92: ='DTC US&CA - P&L'!AF60+'DTC EU - P&L'!AF56 -> 2 | AG92: =SUM(B92:AF92) -> 33
A93: Snack n' Soar - 8lb | B93: ='DTC US&CA - P&L'!B61+'DTC EU - P&L'!B57 -> 0 | C93: ='DTC US&CA - P&L'!C61+'DTC EU - P&L'!C57 -> 0 | D93: ='DTC US&CA - P&L'!D61+'DTC EU - P&L'!D57 -> 0 | E93: ='DTC US&CA - P&L'!E61+'DTC EU - P&L'!E57 -> 0 | F93: ='DTC US&CA - P&L'!F61+'DTC EU - P&L'!F57 -> 0 | G93: ='DTC US&CA - P&L'!G61+'DTC EU - P&L'!G57 -> 0 | H93: ='DTC US&CA - P&L'!H61+'DTC EU - P&L'!H57 -> 0 | I93: ='DTC US&CA - P&L'!I61+'DTC EU - P&L'!I57 -> 0 | ... AF93: ='DTC US&CA - P&L'!AF61+'DTC EU - P&L'!AF57 -> 0 | AG93: =SUM(B93:AF93) -> 0
A94: Snack n' Soar - 20lb | B94: ='DTC US&CA - P&L'!B62+'DTC EU - P&L'!B58 -> 0 | C94: ='DTC US&CA - P&L'!C62+'DTC EU - P&L'!C58 -> 0 | D94: ='DTC US&CA - P&L'!D62+'DTC EU - P&L'!D58 -> 0 | E94: ='DTC US&CA - P&L'!E62+'DTC EU - P&L'!E58 -> 0 | F94: ='DTC US&CA - P&L'!F62+'DTC EU - P&L'!F58 -> 0 | G94: ='DTC US&CA - P&L'!G62+'DTC EU - P&L'!G58 -> 0 | H94: ='DTC US&CA - P&L'!H62+'DTC EU - P&L'!H58 -> 0 | I94: ='DTC US&CA - P&L'!I62+'DTC EU - P&L'!I58 -> 0 | ... AF94: ='DTC US&CA - P&L'!AF62+'DTC EU - P&L'!AF58 -> 0 | AG94: =SUM(B94:AF94) -> 0
A95: Avian Choice - 8lb | B95: ='DTC US&CA - P&L'!B63+'DTC EU - P&L'!B59 -> 0 | C95: ='DTC US&CA - P&L'!C63+'DTC EU - P&L'!C59 -> 0 | D95: ='DTC US&CA - P&L'!D63+'DTC EU - P&L'!D59 -> 0 | E95: ='DTC US&CA - P&L'!E63+'DTC EU - P&L'!E59 -> 0 | F95: ='DTC US&CA - P&L'!F63+'DTC EU - P&L'!F59 -> 0 | G95: ='DTC US&CA - P&L'!G63+'DTC EU - P&L'!G59 -> 0 | H95: ='DTC US&CA - P&L'!H63+'DTC EU - P&L'!H59 -> 0 | I95: ='DTC US&CA - P&L'!I63+'DTC EU - P&L'!I59 -> 0 | ... AF95: ='DTC US&CA - P&L'!AF63+'DTC EU - P&L'!AF59 -> 0 | AG95: =SUM(B95:AF95) -> 0
A96: Avian Choice - 20lb | B96: ='DTC US&CA - P&L'!B64+'DTC EU - P&L'!B60 -> 0 | C96: ='DTC US&CA - P&L'!C64+'DTC EU - P&L'!C60 -> 0 | D96: ='DTC US&CA - P&L'!D64+'DTC EU - P&L'!D60 -> 0 | E96: ='DTC US&CA - P&L'!E64+'DTC EU - P&L'!E60 -> 0 | F96: ='DTC US&CA - P&L'!F64+'DTC EU - P&L'!F60 -> 0 | G96: ='DTC US&CA - P&L'!G64+'DTC EU - P&L'!G60 -> 0 | H96: ='DTC US&CA - P&L'!H64+'DTC EU - P&L'!H60 -> 0 | I96: ='DTC US&CA - P&L'!I64+'DTC EU - P&L'!I60 -> 0 | ... AF96: ='DTC US&CA - P&L'!AF64+'DTC EU - P&L'!AF60 -> 0 | AG96: =SUM(B96:AF96) -> 0
A97: SUM (Seeds) | B97: =SUM(B89:B96) -> 8 | C97: =SUM(C89:C96) -> 5 | D97: =SUM(D89:D96) -> 11 | E97: =SUM(E89:E96) -> 12 | F97: =SUM(F89:F96) -> 11 | G97: =SUM(G89:G96) -> 8 | H97: =SUM(H89:H96) -> 9 | I97: =SUM(I89:I96) -> 6 | ... AF97: =SUM(AF89:AF96) -> 11 | AG97: =SUM(B97:AF97) -> 242
A99: Merch Units Sold (Gross)
A100: Merch Units | B100: ='DTC US&CA - P&L'!B68+'DTC EU - P&L'!B64 -> 0 | C100: ='DTC US&CA - P&L'!C68+'DTC EU - P&L'!C64 -> 0 | D100: ='DTC US&CA - P&L'!D68+'DTC EU - P&L'!D64 -> 0 | E100: ='DTC US&CA - P&L'!E68+'DTC EU - P&L'!E64 -> 0 | F100: ='DTC US&CA - P&L'!F68+'DTC EU - P&L'!F64 -> 0 | G100: ='DTC US&CA - P&L'!G68+'DTC EU - P&L'!G64 -> 0 | H100: ='DTC US&CA - P&L'!H68+'DTC EU - P&L'!H64 -> 0 | I100: ='DTC US&CA - P&L'!I68+'DTC EU - P&L'!I64 -> 0 | ... AF100: ='DTC US&CA - P&L'!AF68+'DTC EU - P&L'!AF64 -> 0 | AG100: =SUM(B100:AF100) -> 3
A102: First-time Customers
A103: SKU 1 - Blue | B103: =B58-B135 -> 0 | C103: =C58-C135 -> 0 | D103: =D58-D135 -> 0 | E103: =E58-E135 -> 0 | F103: =F58-F135 -> 0 | G103: =G58-G135 -> 0 | H103: =H58-H135 -> 0 | I103: =I58-I135 -> 0 | ... AF103: =AF58-AF135 -> 0 | AG103: =SUM(B103:AF103) -> 0
A104: SKU 2 - Yellow | B104: =B59-B136 -> 0 | C104: =C59-C136 -> 0 | D104: =D59-D136 -> 0 | E104: =E59-E136 -> 0 | F104: =F59-F136 -> 0 | G104: =G59-G136 -> 0 | H104: =H59-H136 -> 0 | I104: =I59-I136 -> 0 | ... AF104: =AF59-AF136 -> 0 | AG104: =SUM(B104:AF104) -> 0
A105: SKU 3 - Blue w/ Solar | B105: =B60-B137 -> 0 | C105: =C60-C137 -> 0 | D105: =D60-D137 -> 0 | E105: =E60-E137 -> 0 | F105: =F60-F137 -> 0 | G105: =G60-G137 -> 0 | H105: =H60-H137 -> 0 | I105: =I60-I137 -> 0 | ... AF105: =AF60-AF137 -> 0 | AG105: =SUM(B105:AF105) -> 0
A106: SKU 4 - Yellow w/ Solar | B106: =B61-B138 -> 0 | C106: =C61-C138 -> 0 | D106: =D61-D138 -> 0 | E106: =E61-E138 -> 0 | F106: =F61-F138 -> 0 | G106: =G61-G138 -> 0 | H106: =H61-H138 -> 0 | I106: =I61-I138 -> 0 | ... AF106: =AF61-AF138 -> 0 | AG106: =SUM(B106:AF106) -> 0
A107: SKU 1 - Blue PRO | B107: =B62-B139 -> 8 | C107: =C62-C139 -> 6 | D107: =D62-D139 -> 5 | E107: =E62-E139 -> 4 | F107: =F62-F139 -> 5 | G107: =G62-G139 -> 5 | H107: =H62-H139 -> 6 | I107: =I62-I139 -> 8 | ... AF107: =AF62-AF139 -> 9 | AG107: =SUM(B107:AF107) -> 204
A108: SKU 2 - Yellow PRO | B108: =B63-B140 -> 0 | C108: =C63-C140 -> 0 | D108: =D63-D140 -> 0 | E108: =E63-E140 -> 0 | F108: =F63-F140 -> 0 | G108: =G63-G140 -> 0 | H108: =H63-H140 -> 0 | I108: =I63-I140 -> 0 | ... AF108: =AF63-AF140 -> 0 | AG108: =SUM(B108:AF108) -> 0
A109: SKU 3 - Blue w/ Solar PRO | B109: =B64-B141 -> 14 | C109: =C64-C141 -> 9 | D109: =D64-D141 -> 16 | E109: =E64-E141 -> 9 | F109: =F64-F141 -> 17 | G109: =G64-G141 -> 11 | H109: =H64-H141 -> 8 | I109: =I64-I141 -> 8 | ... AF109: =AF64-AF141 -> 20 | AG109: =SUM(B109:AF109) -> 548
A110: SKU 4 - Yellow w/ Solar PRO | B110: =B65-B142 -> 0 | C110: =C65-C142 -> 0 | D110: =D65-D142 -> 0 | E110: =E65-E142 -> 0 | F110: =F65-F142 -> 0 | G110: =G65-G142 -> 0 | H110: =H65-H142 -> 0 | I110: =I65-I142 -> 0 | ... AF110: =AF65-AF142 -> 0 | AG110: =SUM(B110:AF110) -> 0
A111: SUM (SKU 1 - SKU 4) | B111: =SUM(B103:B110) -> 22 | C111: =SUM(C103:C110) -> 15 | D111: =SUM(D103:D110) -> 21 | E111: =SUM(E103:E110) -> 13 | F111: =SUM(F103:F110) -> 22 | G111: =SUM(G103:G110) -> 16 | H111: =SUM(H103:H110) -> 14 | I111: =SUM(I103:I110) -> 16 | ... AF111: =SUM(AF103:AF110) -> 29 | AG111: =SUM(B111:AF111) -> 752
A113: SKU 5 - HBF PRO | B113: =B68-B145 -> 2 | C113: =C68-C145 -> 3 | D113: =D68-D145 -> 2 | E113: =E68-E145 -> 4 | F113: =F68-F145 -> 1 | G113: =G68-G145 -> 1 | H113: =H68-H145 -> 1 | I113: =I68-I145 -> 0 | ... AF113: =AF68-AF145 -> 2 | AG113: =SUM(B113:AF113) -> 39
A114: SKU 6 - HBF w/ Solar PRO | B114: =B69-B146 -> 0 | C114: =C69-C146 -> 1 | D114: =D69-D146 -> 1 | E114: =E69-E146 -> 0 | F114: =F69-F146 -> 1 | G114: =G69-G146 -> 2 | H114: =H69-H146 -> 1 | I114: =I69-I146 -> 1 | ... AF114: =AF69-AF146 -> 1 | AG114: =SUM(B114:AF114) -> 80
A115: SUM (SKU 5 - SKU 6) | B115: =SUM(B113:B114) -> 2 | C115: =SUM(C113:C114) -> 4 | D115: =SUM(D113:D114) -> 3 | E115: =SUM(E113:E114) -> 4 | F115: =SUM(F113:F114) -> 2 | G115: =SUM(G113:G114) -> 3 | H115: =SUM(H113:H114) -> 2 | I115: =SUM(I113:I114) -> 1 | ... AF115: =SUM(AF113:AF114) -> 3 | AG115: =SUM(B115:AF115) -> 119
A117: Bird Buddy 2 | AG117: =SUM(B117:AF117) -> 0
...

Sheet DTC US&CA - P&L
A1: OCTOBER | B1: 45931 | C1: 45932 | D1: 45933 | E1: 45934 | F1: 45935 | G1: 45936 | H1: 45937 | I1: 45938 | J1: 45939 | K1: 45940 | L1: 45941 | M1: 45942 | N1: 45943 | O1: 45944 | P1: 45945 | Q1: 45946 | R1: 45947 | S1: 45948 | T1: 45949 | U1: 45950 | V1: 45951 | W1: 45952 | X1: 45953 | Y1: 45954 | Z1: 45955 | AA1: 45956 | AB1: 45957 | AC1: 45958 | AD1: 45959 | AE1: 45960 | AF1: 45961
A2: DAY | B2: WED | C2: THU | D2: FRI | E2: SAT | F2: SUN | G2: MON | H2: TUE | I2: WED | J2: THU | K2: FRI | L2: SAT | M2: SUN | N2: MON | O2: TUE | P2: WED | Q2: THU | R2: FRI | S2: SAT | T2: SUN | U2: MON | V2: TUE | W2: WED | X2: THU | Y2: FRI | Z2: SAT | AA2: SUN | AB2: MON | AC2: TUE | AD2: WED | AE2: THU | AF2: FRI
A4: Revenue
A5: Revenue Woocommerce (Platform) | B5: =Summary!B13+Summary!B29 -> 11810.27 | C5: =Summary!C13+Summary!C29 -> 9270.32 | D5: =Summary!D13+Summary!D29 -> 12350.47 | E5: =Summary!E13+Summary!E29 -> 7559.91 | F5: =Summary!F13+Summary!F29 -> 9177.45 | G5: =Summary!G13+Summary!G29 -> 9644.71 | H5: =Summary!H13+Summary!H29 -> 6788.64 | I5: =Summary!I13+Summary!I29 -> 7380.68 | ... AF5: =Summary!AF13+Summary!AF29 -> 13753.17 | AG5: =SUM(B5:AF5) -> 400826.86
A6: Revenue w/o renewals | B6: 7572.58 | C6: 6934.89 | D6: 9460.55 | E6: 5319.11 | F6: 7113.04 | G6: 7937.85 | H6: 4869.65 | I6: 5434.33 | J6: 7945.11 | K6: 7864.73 | L6: 6567.7 | M6: 10196.91 | N6: 8642.88 | O6: 8326.78 | P6: 7689.26 | Q6: 7701.48 | R6: 10722.35 | S6: 9781.04 | T6: 12050.47 | U6: 12055.28 | V6: 10994.88 | W6: 19089.76 | X6: 13315.44 | Y6: 11738.42 | Z6: 16158.39 | AA6: 14565.3 | AB6: 13820.06 | AC6: 13207.82 | AD6: 11386.73 | AE6: 9630.31 | AF6: 12182.28
A7: SUM | B7: =SUM(B5) -> 11810.27 | C7: =SUM(C5) -> 9270.32 | D7: =SUM(D5) -> 12350.47 | E7: =SUM(E5) -> 7559.91 | F7: =SUM(F5) -> 9177.45 | G7: =SUM(G5) -> 9644.71 | H7: =SUM(H5) -> 6788.64 | I7: =SUM(I5) -> 7380.68 | ... AF7: =SUM(AF5) -> 13753.17 | AG7: =SUM(B7:AF7) -> 400826.86
A9: Orders
A10: Orders Woocommerce (Platform) | B10: =Summary!B97 -> 88 | C10: =Summary!C97 -> 57 | D10: =Summary!D97 -> 77 | E10: =Summary!E97 -> 57 | F10: =Summary!F97 -> 67 | G10: =Summary!G97 -> 63 | H10: =Summary!H97 -> 56 | I10: =Summary!I97 -> 53 | ... AF10: =Summary!AF97 -> 67 | AG10: =SUM(B10:AF10) -> 2319
A11: Orders w/o renewals | B11: 35 | C11: 28 | D11: 38 | E11: 26 | F11: 37 | G11: 39 | H11: 29 | I11: 28 | J11: 32 | K11: 32 | L11: 27 | M11: 51 | N11: 35 | O11: 27 | P11: 28 | Q11: 29 | R11: 41 | S11: 39 | T11: 48 | U11: 43 | V11: 44 | W11: 55 | X11: 41 | Y11: 44 | Z11: 56 | AA11: 50 | AB11: 51 | AC11: 46 | AD11: 38 | AE11: 32 | AF11: 44
A12: SUM | B12: =SUM(B10) -> 88 | C12: =SUM(C10) -> 57 | D12: =SUM(D10) -> 77 | E12: =SUM(E10) -> 57 | F12: =SUM(F10) -> 67 | G12: =SUM(G10) -> 63 | H12: =SUM(H10) -> 56 | I12: =SUM(I10) -> 53 | ... AF12: =SUM(AF10) -> 67 | AG12: =SUM(B12:AF12) -> 2319
A14: Breakdown
A15: - Hardware | B15: =Summary!B14 -> 5646 | C15: =Summary!C14 -> 5118 | D15: =Summary!D14 -> 7031 | E15: =Summary!E14 -> 3935.3 | F15: =Summary!F14 -> 5527 | G15: =Summary!G14 -> 5734.2 | H15: =Summary!H14 -> 3674 | I15: =Summary!I14 -> 4053 | ... AF15: =Summary!AF14 -> 9072 | AG15: =SUM(B15:AF15) -> 232064.76
A16: - Add-ons | B16: =Summary!B15 -> 569 | C16: =Summary!C15 -> 637 | D16: =Summary!D15 -> 820 | E16: =Summary!E15 -> 334 | F16: =Summary!F15 -> 273 | G16: =Summary!G15 -> 715 | H16: =Summary!H15 -> 386 | I16: =Summary!I15 -> 412 | ... AF16: =Summary!AF15 -> 371 | AG16: =SUM(B16:AF16) -> 20939.98
A17: - Merch | B17: =Summary!B16 -> 0 | C17: =Summary!C16 -> 0 | D17: =Summary!D16 -> 0 | E17: =Summary!E16 -> 0 | F17: =Summary!F16 -> 0 | G17: =Summary!G16 -> 0 | H17: =Summary!H16 -> 0 | I17: =Summary!I16 -> 0 | ... AF17: =Summary!AF16 -> 0 | AG17: =SUM(B17:AF17) -> 0
A18: - Seeds | B18: =Summary!B17 -> 236.2 | C18: =Summary!C17 -> 169.5 | D18: =Summary!D17 -> 345.9 | E18: =Summary!E17 -> 435.7 | F18: =Summary!F17 -> 323.9 | G18: =Summary!G17 -> 242 | H18: =Summary!H17 -> 257.9 | I18: =Summary!I17 -> 216.4 | ... AF18: =Summary!AF17 -> 367.1 | AG18: =SUM(B18:AF18) -> 7971.45
A19: - Yearly Pro Subscription | B19: =Summary!B29 -> 3839.55 | C19: =Summary!C29 -> 2069.76 | D19: =Summary!D29 -> 2459.72 | E19: =Summary!E29 -> 1679.81 | F19: =Summary!F29 -> 1679.81 | G19: =Summary!G29 -> 1379.84 | H19: =Summary!H29 -> 1589.73 | I19: =Summary!I29 -> 1649.81 | ... AF19: =Summary!AF29 -> 1698.79 | AG19: =SUM(B19:AF19) -> 84767.08
A20: - Taxes | B20: =Summary!B18 -> 707.8 | C20: =Summary!C18 -> 497.34 | D20: =Summary!D18 -> 697.65 | E20: =Summary!E18 -> 476.16 | F20: =Summary!F18 -> 519.22 | G20: =Summary!G18 -> 635.71 | H20: =Summary!H18 -> 318.27 | I20: =Summary!I18 -> 431.09 | ... AF20: =Summary!AF18 -> 799.56 | AG20: =SUM(B20:AF20) -> 22880.28
A21: - Shipping | B21: =Summary!B19 -> 702.42 | C21: =Summary!C19 -> 629.62 | D21: =Summary!D19 -> 842.2 | E21: =Summary!E19 -> 534.31 | F21: =Summary!F19 -> 655.62 | G21: =Summary!G19 -> 803.76 | H21: =Summary!H19 -> 508.04 | I21: =Summary!I19 -> 523.98 | ... AF21: =Summary!AF19 -> 1046.72 | AG21: =SUM(B21:AF21) -> 27701.88
A22: - Gift Bag | B22: =Summary!B20 -> 109.3 | C22: =Summary!C20 -> 149.1 | D22: =Summary!D20 -> 154 | E22: =Summary!E20 -> 164.63 | F22: =Summary!F20 -> 198.9 | G22: =Summary!G20 -> 134.2 | H22: =Summary!H20 -> 54.7 | I22: =Summary!I20 -> 94.4 | ... AF22: =Summary!AF20 -> 398 | AG22: =SUM(B22:AF22) -> 4501.43
A23: SUM | B23: =SUM(B15:B22) -> 11810.27 | C23: =SUM(C15:C22) -> 9270.32 | D23: =SUM(D15:D22) -> 12350.47 | E23: =SUM(E15:E22) -> 7559.91 | F23: =SUM(F15:F22) -> 9177.45 | G23: =SUM(G15:G22) -> 9644.71 | H23: =SUM(H15:H22) -> 6788.64 | I23: =SUM(I15:I22) -> 7380.68 | ... AF23: =SUM(AF15:AF22) -> 13753.17 | AG23: =SUM(B23:AF23) -> 400826.86
A25: Units Sold (Gross)
A26: SKU 1 - Blue | B26: =B178 -> 0 | C26: =C178 -> 0 | D26: =D178 -> 0 | E26: =E178 -> 0 | F26: =F178 -> 0 | G26: =G178 -> 0 | H26: =H178 -> 0 | I26: =I178 -> 0 | ... AF26: =AF178 -> 0 | AG26: =SUM(B26:AF26) -> 0
A27: SKU 2 - Yellow | B27: =B179 -> 0 | C27: =C179 -> 0 | D27: =D179 -> 0 | E27: =E179 -> 0 | F27: =F179 -> 0 | G27: =G179 -> 0 | H27: =H179 -> 0 | I27: =I179 -> 0 | ... AF27: =AF179 -> 0 | AG27: =SUM(B27:AF27) -> 0
A28: SKU 3 - Blue w/ Solar | B28: =B180 -> 0 | C28: =C180 -> 0 | D28: =D180 -> 0 | E28: =E180 -> 0 | F28: =F180 -> 0 | G28: =G180 -> 0 | H28: =H180 -> 0 | I28: =I180 -> 0 | ... AF28: =AF180 -> 0 | AG28: =SUM(B28:AF28) -> 0
A29: SKU 4 - Yellow w/ Solar | B29: =B181 -> 0 | C29: =C181 -> 0 | D29: =D181 -> 0 | E29: =E181 -> 0 | F29: =F181 -> 0 | G29: =G181 -> 0 | H29: =H181 -> 0 | I29: =I181 -> 0 | ... AF29: =AF181 -> 0 | AG29: =SUM(B29:AF29) -> 0
A30: SKU 1 - Blue PRO | B30: =B184 -> 8 | C30: =C184 -> 5 | D30: =D184 -> 6 | E30: =E184 -> 3 | F30: =F184 -> 6 | G30: =G184 -> 9 | H30: =H184 -> 7 | I30: =I184 -> 7 | ... AF30: =AF184 -> 9 | AG30: =SUM(B30:AF30) -> 217
A31: SKU 2 - Yellow PRO | B31: =B185 -> 0 | C31: =C185 -> 0 | D31: =D185 -> 0 | E31: =E185 -> 0 | F31: =F185 -> 0 | G31: =G185 -> 0 | H31: =H185 -> 0 | I31: =I185 -> 0 | ... AF31: =AF185 -> 0 | AG31: =SUM(B31:AF31) -> 0
A32: SKU 3 - Blue w/ Solar PRO | B32: =B186 -> 14 | C32: =C186 -> 9 | D32: =D186 -> 18 | E32: =E186 -> 10 | F32: =F186 -> 15 | G32: =G186 -> 14 | H32: =H186 -> 7 | I32: =I186 -> 7 | ... AF32: =AF186 -> 23 | AG32: =SUM(B32:AF32) -> 577
A33: SKU 4 - Yellow w/ Solar PRO | B33: =B187 -> 0 | C33: =C187 -> 0 | D33: =D187 -> 0 | E33: =E187 -> 0 | F33: =F187 -> 0 | G33: =G187 -> 0 | H33: =H187 -> 0 | I33: =I187 -> 0 | ... AF33: =AF187 -> 0 | AG33: =SUM(B33:AF33) -> 0
A34: SUM (SKU 1 - SKU 4) | B34: =SUM(B26:B33) -> 22 | C34: =SUM(C26:C33) -> 14 | D34: =SUM(D26:D33) -> 24 | E34: =SUM(E26:E33) -> 13 | F34: =SUM(F26:F33) -> 21 | G34: =SUM(G26:G33) -> 23 | H34: =SUM(H26:H33) -> 14 | I34: =SUM(I26:I33) -> 14 | ... AF34: =SUM(AF26:AF33) -> 32 | AG34: =SUM(B34:AF34) -> 794
A36: SKU 5 - HBF PRO | B36: =B182 -> 2 | C36: =C182 -> 6 | D36: =D182 -> 3 | E36: =E182 -> 4 | F36: =F182 -> 1 | G36: =G182 -> 2 | H36: =H182 -> 1 | I36: =I182 -> 0 | ... AF36: =AF182 -> 3 | AG36: =SUM(B36:AF36) -> 56
A37: SKU 6 - HBF w/ Solar PRO | B37: =B183 -> 0 | C37: =C183 -> 2 | D37: =D183 -> 2 | E37: =E183 -> 0 | F37: =F183 -> 1 | G37: =G183 -> 2 | H37: =H183 -> 1 | I37: =I183 -> 3 | ... AF37: =AF183 -> 3 | AG37: =SUM(B37:AF37) -> 117
A38: SUM (SKU 5 - SKU 6) | B38: =SUM(B36:B37) -> 2 | C38: =SUM(C36:C37) -> 8 | D38: =SUM(D36:D37) -> 5 | E38: =SUM(E36:E37) -> 4 | F38: =SUM(F36:F37) -> 2 | G38: =SUM(G36:G37) -> 4 | H38: =SUM(H36:H37) -> 2 | I38: =SUM(I36:I37) -> 3 | ... AF38: =SUM(AF36:AF37) -> 6 | AG38: =SUM(B38:AF38) -> 173
A40: Bird Buddy 2 | B40: =B188 -> 0 | C40: =C188 -> 0 | D40: =D188 -> 0 | E40: =E188 -> 0 | F40: =F188 -> 0 | G40: =G188 -> 0 | H40: =H188 -> 0 | I40: =I188 -> 0 | ... AF40: =AF188 -> 0 | AG40: =SUM(B40:AF40) -> 0
A41: SUM (BB2) | B41: =SUM(B39:B40) -> 0 | C41: =SUM(C39:C40) -> 0 | D41: =SUM(D39:D40) -> 0 | E41: =SUM(E39:E40) -> 0 | F41: =SUM(F39:F40) -> 0 | G41: =SUM(G39:G40) -> 0 | H41: =SUM(H39:H40) -> 0 | I41: =SUM(I39:I40) -> 0 | ... AF41: =SUM(AF39:AF40) -> 0 | AG41: =SUM(B41:AF41) -> 0
A43: Wall Mount | B43: =B206 -> 5 | C43: =C206 -> 1 | D43: =D206 -> 6 | E43: =E206 -> 4 | F43: =F206 -> 2 | G43: =G206 -> 8 | H43: =H206 -> 2 | I43: =I206 -> 2 | ... AF43: =AF206 -> 0 | AG43: =SUM(B43:AF43) -> 108
A44: Suet Ball Holder | B44: =B207 -> 20 | C44: =C207 -> 14 | D44: =D207 -> 20 | E44: =E207 -> 9 | F44: =F207 -> 27 | G44: =G207 -> 15 | H44: =H207 -> 12 | I44: =I207 -> 11 | ... AF44: =AF207 -> 19 | AG44: =SUM(B44:AF44) -> 559
A45: 3-in-1 Nutrition Set - Blue | B45: =B208 -> 3 | C45: =C208 -> 0 | D45: =D208 -> 2 | E45: =E208 -> 1 | F45: =F208 -> 0 | G45: =G208 -> 1 | H45: =H208 -> 2 | I45: =I208 -> 1 | ... AF45: =AF208 -> 2 | AG45: =SUM(B45:AF45) -> 53
A46: 3-in-1 Nutrition Set - Yellow | B46: =B209 -> 0 | C46: =C209 -> 1 | D46: =D209 -> 0 | E46: =E209 -> 0 | F46: =F209 -> 0 | G46: =G209 -> 0 | H46: =H209 -> 0 | I46: =I209 -> 0 | ... AF46: =AF209 -> 0 | AG46: =SUM(B46:AF46) -> 2
A47: Solar Roof Single - Blue | B47: =B210 -> 0 | C47: =C210 -> 0 | D47: =D210 -> 0 | E47: =E210 -> 0 | F47: =F210 -> 0 | G47: =G210 -> 0 | H47: =H210 -> 0 | I47: =I210 -> 0 | ... AF47: =AF210 -> 0 | AG47: =SUM(B47:AF47) -> 0
A48: Solar Roof Single - Yellow | B48: =B211 -> 0 | C48: =C211 -> 0 | D48: =D211 -> 0 | E48: =E211 -> 0 | F48: =F211 -> 0 | G48: =G211 -> 0 | H48: =H211 -> 0 | I48: =I211 -> 0 | ... AF48: =AF211 -> 0 | AG48: =SUM(B48:AF48) -> 0
A49: Perch Extender - Blue | B49: =B212 -> 14 | C49: =C212 -> 6 | D49: =D212 -> 10 | E49: =E212 -> 9 | F49: =F212 -> 8 | G49: =G212 -> 18 | H49: =H212 -> 10 | I49: =I212 -> 14 | ... AF49: =AF212 -> 11 | AG49: =SUM(B49:AF49) -> 363
A50: Perch Extender - Yellow | B50: =B213 -> 1 | C50: =C213 -> 0 | D50: =D213 -> 0 | E50: =E213 -> 1 | F50: =F213 -> 0 | G50: =G213 -> 0 | H50: =H213 -> 3 | I50: =I213 -> 1 | ... AF50: =AF213 -> 1 | AG50: =SUM(B50:AF50) -> 16
A51: Solar Roof (HBF) | B51: =B214 -> 0 | C51: =C214 -> 0 | D51: =D214 -> 0 | E51: =E214 -> 0 | F51: =F214 -> 0 | G51: =G214 -> 0 | H51: =H214 -> 0 | I51: =I214 -> 0 | ... AF51: =AF214 -> 0 | AG51: =SUM(B51:AF51) -> 0
A52: Housing - only (HBF) | B52: =B215 -> 0 | C52: =C215 -> 1 | D52: =D215 -> 0 | E52: =E215 -> 0 | F52: =F215 -> 0 | G52: =G215 -> 0 | H52: =H215 -> 0 | I52: =I215 -> 0 | ... AF52: =AF215 -> 0 | AG52: =SUM(B52:AF52) -> 4
A53: Nature Station | B53: =B216 -> 0 | C53: =C216 -> 1 | D53: =D216 -> 1 | E53: =E216 -> 0 | F53: =F216 -> 0 | G53: =G216 -> 0 | H53: =H216 -> 0 | I53: =I216 -> 0 | ... AF53: =AF216 -> 0 | AG53: =SUM(B53:AF53) -> 21
A54: Nature Cam PRO | B54: =B217 -> 0 | C54: =C217 -> 0 | D54: =D217 -> 0 | E54: =E217 -> 0 | F54: =F217 -> 0 | G54: =G217 -> 0 | H54: =H217 -> 0 | I54: =I217 -> 0 | ... AF54: =AF217 -> 0 | AG54: =SUM(B54:AF54) -> 0
A55: SUM (Add-ons) | B55: =SUM(B43:B54) -> 43 | C55: =SUM(C43:C54) -> 24 | D55: =SUM(D43:D54) -> 39 | E55: =SUM(E43:E54) -> 24 | F55: =SUM(F43:F54) -> 37 | G55: =SUM(G43:G54) -> 42 | H55: =SUM(H43:H54) -> 29 | I55: =SUM(I43:I54) -> 29 | ... AF55: =SUM(AF43:AF54) -> 33 | AG55: =SUM(B55:AF55) -> 1126
A57: Seasonal Curation - 8lb | B57: 8 | C57: 4 | D57: 10 | E57: 7 | F57: 10 | G57: 7 | H57: 9 | I57: 4 | J57: 8 | K57: 3 | L57: 12 | M57: 9 | N57: 3 | O57: 4 | P57: 8 | Q57: 7 | R57: 4 | S57: 4 | T57: 6 | U57: 6 | V57: 4 | W57: 3 | X57: 3 | Y57: 5 | Z57: 5 | AA57: 7 | AB57: 5 | AC57: 5 | AD57: 0 | AE57: 1 | AF57: 8 | AG57: =SUM(B57:AF57) -> 179
A58: Seasonal Curation - 20lb | B58: 0 | C58: 1 | D58: 1 | E58: 5 | F58: 1 | G58: 1 | H58: 0 | I58: 2 | J58: 3 | K58: 1 | L58: 1 | M58: 0 | N58: 0 | O58: 0 | P58: 1 | Q58: 1 | R58: 0 | S58: 0 | T58: 1 | U58: 0 | V58: 2 | W58: 0 | X58: 2 | Y58: 0 | Z58: 1 | AA58: 2 | AB58: 1 | AC58: 0 | AD58: 2 | AE58: 0 | AF58: 1 | AG58: =SUM(B58:AF58) -> 30
A59: Buddy Bites - 8lb | B59: 0 | C59: 0 | D59: 0 | E59: 0 | F59: 0 | G59: 0 | H59: 0 | I59: 0 | J59: 0 | K59: 0 | L59: 0 | M59: 0 | N59: 0 | O59: 0 | P59: 0 | Q59: 0 | R59: 0 | S59: 0 | T59: 0 | U59: 0 | V59: 0 | W59: 0 | X59: 0 | Y59: 0 | Z59: 0 | AA59: 0 | AB59: 0 | AC59: 0 | AD59: 0 | AE59: 0 | AF59: 0 | AG59: =SUM(B59:AF59) -> 0
A60: Buddy Bites - 20lb | B60: 0 | C60: 0 | D60: 0 | E60: 0 | F60: 0 | G60: 0 | H60: 0 | I60: 0 | J60: 0 | K60: 0 | L60: 0 | M60: 0 | N60: 0 | O60: 0 | P60: 0 | Q60: 0 | R60: 0 | S60: 0 | T60: 0 | U60: 0 | V60: 0 | W60: 0 | X60: 0 | Y60: =Summary!Y101-Y57-Y58-Y59-Y61-Y62-Y63-Y64 -> 5 | Z60: =Summary!Z101-Z57-Z58-Z59-Z61-Z62-Z63-Z64 -> 6 | AA60: =Summary!AA101-AA57-AA58-AA59-AA61-AA62-AA63-AA64 -> 4 | AB60: =Summary!AB101-AB57-AB58-AB59-AB61-AB62-AB63-AB64 -> 5 | AC60: 6 | AD60: 2 | AE60: 3 | AF60: 2 | AG60: =SUM(B60:AF60) -> 33
A61: Snack n' Soar - 8lb | B61: 0 | C61: 0 | D61: 0 | E61: 0 | F61: 0 | G61: 0 | H61: 0 | I61: 0 | J61: 0 | K61: 0 | L61: 0 | M61: 0 | N61: 0 | O61: 0 | P61: 0 | Q61: 0 | R61: 0 | S61: 0 | T61: 0 | U61: 0 | V61: 0 | W61: 0 | X61: 0 | Y61: 0 | Z61: 0 | AA61: 0 | AB61: 0 | AC61: 0 | AD61: 0 | AE61: 0 | AF61: 0 | AG61: =SUM(B61:AF61) -> 0
A62: Snack n' Soar - 20lb | B62: 0 | C62: 0 | D62: 0 | E62: 0 | F62: 0 | G62: 0 | H62: 0 | I62: 0 | J62: 0 | K62: 0 | L62: 0 | M62: 0 | N62: 0 | O62: 0 | P62: 0 | Q62: 0 | R62: 0 | S62: 0 | T62: 0 | U62: 0 | V62: 0 | W62: 0 | X62: 0 | Y62: 0 | Z62: 0 | AA62: 0 | AB62: 0 | AC62: 0 | AD62: 0 | AE62: 0 | AF62: 0 | AG62: =SUM(B62:AF62) -> 0
A63: Avian Choice - 8lb | B63: 0 | C63: 0 | D63: 0 | E63: 0 | F63: 0 | G63: 0 | H63: 0 | I63: 0 | J63: 0 | K63: 0 | L63: 0 | M63: 0 | N63: 0 | O63: 0 | P63: 0 | Q63: 0 | R63: 0 | S63: 0 | T63: 0 | U63: 0 | V63: 0 | W63: 0 | X63: 0 | Y63: 0 | Z63: 0 | AA63: 0 | AB63: 0 | AC63: 0 | AD63: 0 | AE63: 0 | AF63: 0 | AG63: =SUM(B63:AF63) -> 0
A64: Avian Choice - 20lb | B64: 0 | C64: 0 | D64: 0 | E64: 0 | F64: 0 | G64: 0 | H64: 0 | I64: 0 | J64: 0 | K64: 0 | L64: 0 | M64: 0 | N64: 0 | O64: 0 | P64: 0 | Q64: 0 | R64: 0 | S64: 0 | T64: 0 | U64: 0 | V64: 0 | W64: 0 | X64: 0 | Y64: 0 | Z64: 0 | AA64: 0 | AB64: 0 | AC64: 0 | AD64: 0 | AE64: 0 | AF64: 0 | AG64: =SUM(B64:AF64) -> 0
A65: SUM (Seeds) | B65: =SUM(B57:B64) -> 8 | C65: =SUM(C57:C64) -> 5 | D65: =SUM(D57:D64) -> 11 | E65: =SUM(E57:E64) -> 12 | F65: =SUM(F57:F64) -> 11 | G65: =SUM(G57:G64) -> 8 | H65: =SUM(H57:H64) -> 9 | I65: =SUM(I57:I64) -> 6 | ... AF65: =SUM(AF57:AF64) -> 11 | AG65: =SUM(B65:AF65) -> 242
A67: Merch Units Sold (Gross)
A68: Merch Units | B68: 0 | C68: 0 | D68: 0 | E68: 0 | F68: 0 | G68: 0 | H68: 0 | I68: 0 | J68: 0 | K68: 0 | L68: 0 | M68: 0 | N68: 0 | O68: 0 | P68: 0 | Q68: 0 | R68: 0 | S68: 0 | T68: 0 | U68: 0 | V68: 0 | W68: 3 | X68: 0 | Y68: 0 | Z68: 0 | AA68: 0 | AB68: 0 | AC68: 0 | AD68: 0 | AE68: 0 | AF68: 0 | AG68: =SUM(B68:AF68) -> 3
A70: First-time Customers
A71: SKU 1 - Blue | B71: =B26-B103 -> 0 | C71: =C26-C103 -> 0 | D71: =D26-D103 -> 0 | E71: =E26-E103 -> 0 | F71: =F26-F103 -> 0 | G71: =G26-G103 -> 0 | H71: =H26-H103 -> 0 | I71: =I26-I103 -> 0 | ... AF71: =AF26-AF103 -> 0 | AG71: =SUM(B71:AF71) -> 0
A72: SKU 2 - Yellow | B72: =B27-B104 -> 0 | C72: =C27-C104 -> 0 | D72: =D27-D104 -> 0 | E72: =E27-E104 -> 0 | F72: =F27-F104 -> 0 | G72: =G27-G104 -> 0 | H72: =H27-H104 -> 0 | I72: =I27-I104 -> 0 | ... AF72: =AF27-AF104 -> 0 | AG72: =SUM(B72:AF72) -> 0
A73: SKU 3 - Blue w/ Solar | B73: =B28-B105 -> 0 | C73: =C28-C105 -> 0 | D73: =D28-D105 -> 0 | E73: =E28-E105 -> 0 | F73: =F28-F105 -> 0 | G73: =G28-G105 -> 0 | H73: =H28-H105 -> 0 | I73: =I28-I105 -> 0 | ... AF73: =AF28-AF105 -> 0 | AG73: =SUM(B73:AF73) -> 0
A74: SKU 4 - Yellow w/ Solar | B74: =B29-B106 -> 0 | C74: =C29-C106 -> 0 | D74: =D29-D106 -> 0 | E74: =E29-E106 -> 0 | F74: =F29-F106 -> 0 | G74: =G29-G106 -> 0 | H74: =H29-H106 -> 0 | I74: =I29-I106 -> 0 | ... AF74: =AF29-AF106 -> 0 | AG74: =SUM(B74:AF74) -> 0
A75: SKU 1 - Blue PRO | B75: =B30-B107 -> 7 | C75: =C30-C107 -> 5 | D75: =D30-D107 -> 5 | E75: =E30-E107 -> 3 | F75: =F30-F107 -> 4 | G75: =G30-G107 -> 5 | H75: =H30-H107 -> 6 | I75: =I30-I107 -> 7 | ... AF75: =AF30-AF107 -> 9 | AG75: =SUM(B75:AF75) -> 190
A76: SKU 2 - Yellow PRO | B76: =B31-B108 -> 0 | C76: =C31-C108 -> 0 | D76: =D31-D108 -> 0 | E76: =E31-E108 -> 0 | F76: =F31-F108 -> 0 | G76: =G31-G108 -> 0 | H76: =H31-H108 -> 0 | I76: =I31-I108 -> 0 | ... AF76: =AF31-AF108 -> 0 | AG76: =SUM(B76:AF76) -> 0
A77: SKU 3 - Blue w/ Solar PRO | B77: =B32-B109 -> 13 | C77: =C32-C109 -> 8 | D77: =D32-D109 -> 15 | E77: =E32-E109 -> 9 | F77: =F32-F109 -> 15 | G77: =G32-G109 -> 11 | H77: =H32-H109 -> 7 | I77: =I32-I109 -> 6 | ... AF77: =AF32-AF109 -> 18 | AG77: =SUM(B77:AF77) -> 506
A78: SKU 4 - Yellow w/ Solar PRO | B78: =B33-B110 -> 0 | C78: =C33-C110 -> 0 | D78: =D33-D110 -> 0 | E78: =E33-E110 -> 0 | F78: =F33-F110 -> 0 | G78: =G33-G110 -> 0 | H78: =H33-H110 -> 0 | I78: =I33-I110 -> 0 | ... AF78: =AF33-AF110 -> 0 | AG78: =SUM(B78:AF78) -> 0
A79: SUM (SKU 1 - SKU 4) | B79: =SUM(B71:B78) -> 20 | C79: =SUM(C71:C78) -> 13 | D79: =SUM(D71:D78) -> 20 | E79: =SUM(E71:E78) -> 12 | F79: =SUM(F71:F78) -> 19 | G79: =SUM(G71:G78) -> 16 | H79: =SUM(H71:H78) -> 13 | I79: =SUM(I71:I78) -> 13 | ... AF79: =SUM(AF71:AF78) -> 27 | AG79: =SUM(B79:AF79) -> 696
A81: SKU 5 - HBF PRO | B81: =B36-B113 -> 2 | C81: =C36-C113 -> 3 | D81: =D36-D113 -> 2 | E81: =E36-E113 -> 4 | F81: =F36-F113 -> 1 | G81: =G36-G113 -> 1 | H81: =H36-H113 -> 1 | I81: =I36-I113 -> 0 | ... AF81: =AF36-AF113 -> 2 | AG81: =SUM(B81:AF81) -> 39
A82: SKU 6 - HBF w/ Solar PRO | B82: =B37-B114 -> 0 | C82: =C37-C114 -> 1 | D82: =D37-D114 -> 1 | E82: =E37-E114 -> 0 | F82: =F37-F114 -> 1 | G82: =G37-G114 -> 2 | H82: =H37-H114 -> 1 | I82: =I37-I114 -> 1 | ... AF82: =AF37-AF114 -> 1 | AG82: =SUM(B82:AF82) -> 80
A83: SUM (SKU 5 - SKU 6) | B83: =SUM(B81:B82) -> 2 | C83: =SUM(C81:C82) -> 4 | D83: =SUM(D81:D82) -> 3 | E83: =SUM(E81:E82) -> 4 | F83: =SUM(F81:F82) -> 2 | G83: =SUM(G81:G82) -> 3 | H83: =SUM(H81:H82) -> 2 | I83: =SUM(I81:I82) -> 1 | ... AF83: =SUM(AF81:AF82) -> 3 | AG83: =SUM(B83:AF83) -> 119
A85: Bird Buddy 2 | AG85: =SUM(B85:AF85) -> 0
A86: SUM (BB2) | B86: =SUM(B84:B85) -> 0 | C86: =SUM(C84:C85) -> 0 | D86: =SUM(D84:D85) -> 0 | E86: =SUM(E84:E85) -> 0 | F86: =SUM(F84:F85) -> 0 | G86: =SUM(G84:G85) -> 0 | H86: =SUM(H84:H85) -> 0 | I86: =SUM(I84:I85) -> 0 | ... AF86: =SUM(AF84:AF85) -> 0 | AG86: =SUM(B86:AF86) -> 0
A88: Wall Mount | B88: =B43-B120 -> 5 | C88: =C43-C120 -> 0 | D88: =D43-D120 -> 5 | E88: =E43-E120 -> 4 | F88: =F43-F120 -> 2 | G88: =G43-G120 -> 8 | H88: =H43-H120 -> 2 | I88: =I43-I120 -> 2 | ... AF88: =AF43-AF120 -> 0 | AG88: =SUM(B88:AF88) -> 95
A89: Suet Ball Holder | B89: =B44-B121 -> 17 | C89: =C44-C121 -> 13 | D89: =D44-D121 -> 15 | E89: =E44-E121 -> 9 | F89: =F44-F121 -> 22 | G89: =G44-G121 -> 11 | H89: =H44-H121 -> 12 | I89: =I44-I121 -> 10 | ... AF89: =AF44-AF121 -> 17 | AG89: =SUM(B89:AF89) -> 476
A90: 3-in-1 Nutrition Set - Blue | B90: =B45-B122 -> 3 | C90: =C45-C122 -> 0 | D90: =D45-D122 -> 2 | E90: =E45-E122 -> 1 | F90: =F45-F122 -> 0 | G90: =G45-G122 -> 0 | H90: =H45-H122 -> 2 | I90: =I45-I122 -> 1 | ... AF90: =AF45-AF122 -> 2 | AG90: =SUM(B90:AF90) -> 37
A91: 3-in-1 Nutrition Set - Yellow | B91: =B46-B123 -> 0 | C91: =C46-C123 -> 0 | D91: =D46-D123 -> 0 | E91: =E46-E123 -> 0 | F91: =F46-F123 -> 0 | G91: =G46-G123 -> 0 | H91: =H46-H123 -> 0 | I91: =I46-I123 -> 0 | ... AF91: =AF46-AF123 -> 0 | AG91: =SUM(B91:AF91) -> 0
A92: Solar Roof Single - Blue | B92: =B47-B124 -> 0 | C92: =C47-C124 -> 0 | D92: =D47-D124 -> 0 | E92: =E47-E124 -> 0 | F92: =F47-F124 -> 0 | G92: =G47-G124 -> 0 | H92: =H47-H124 -> 0 | I92: =I47-I124 -> 0 | ... AF92: =AF47-AF124 -> 0 | AG92: =SUM(B92:AF92) -> 0
A93: Solar Roof Single - Yellow | B93: =B48-B125 -> 0 | C93: =C48-C125 -> 0 | D93: =D48-D125 -> 0 | E93: =E48-E125 -> 0 | F93: =F48-F125 -> 0 | G93: =G48-G125 -> 0 | H93: =H48-H125 -> 0 | I93: =I48-I125 -> 0 | ... AF93: =AF48-AF125 -> 0 | AG93: =SUM(B93:AF93) -> 0
A94: Perch Extender - Blue | B94: =B49-B126 -> 14 | C94: =C49-C126 -> 5 | D94: =D49-D126 -> 7 | E94: =E49-E126 -> 9 | F94: =F49-F126 -> 7 | G94: =G49-G126 -> 12 | H94: =H49-H126 -> 8 | I94: =I49-I126 -> 12 | ... AF94: =AF49-AF126 -> 8 | AG94: =SUM(B94:AF94) -> 284
A95: Perch Extender - Yellow | B95: =B50-B127 -> 0 | C95: =C50-C127 -> 0 | D95: =D50-D127 -> 0 | E95: =E50-E127 -> 1 | F95: =F50-F127 -> 0 | G95: =G50-G127 -> 0 | H95: =H50-H127 -> 2 | I95: =I50-I127 -> 1 | ... AF95: =AF50-AF127 -> 0 | AG95: =SUM(B95:AF95) -> 10
A96: Solar Roof (HBF) | B96: =B51-B128 -> 0 | C96: =C51-C128 -> 0 | D96: =D51-D128 -> 0 | E96: =E51-E128 -> 0 | F96: =F51-F128 -> 0 | G96: =G51-G128 -> 0 | H96: =H51-H128 -> 0 | I96: =I51-I128 -> 0 | ... AF96: =AF51-AF128 -> 0 | AG96: =SUM(B96:AF96) -> 0
A97: Housing - only (HBF) | B97: =B52-B129 -> 0 | C97: =C52-C129 -> 0 | D97: =D52-D129 -> 0 | E97: =E52-E129 -> 0 | F97: =F52-F129 -> 0 | G97: =G52-G129 -> 0 | H97: =H52-H129 -> 0 | I97: =I52-I129 -> 0 | ... AF97: =AF52-AF129 -> 0 | AG97: =SUM(B97:AF97) -> 2
A98: Nature Station | B98: =B53-B130 -> 0 | C98: =C53-C130 -> 1 | D98: =D53-D130 -> 0 | E98: =E53-E130 -> 0 | F98: =F53-F130 -> 0 | G98: =G53-G130 -> 0 | H98: =H53-H130 -> 0 | I98: =I53-I130 -> 0 | ... AF98: =AF53-AF130 -> 0
A99: Nature Cam PRO | B99: =B54-B131 -> 0 | C99: =C54-C131 -> 0 | D99: =D54-D131 -> 0 | E99: =E54-E131 -> 0 | F99: =F54-F131 -> 0 | G99: =G54-G131 -> 0 | H99: =H54-H131 -> 0 | I99: =I54-I131 -> 0 | ... AF99: =AF54-AF131 -> 0 | AG99: =SUM(B99:AF99) -> 0
A100: SUM (Add-ons) | B100: =SUM(B88:B99) -> 39 | C100: =SUM(C88:C99) -> 19 | D100: =SUM(D88:D99) -> 29 | E100: =SUM(E88:E99) -> 24 | F100: =SUM(F88:F99) -> 31 | G100: =SUM(G88:G99) -> 31 | H100: =SUM(H88:H99) -> 26 | I100: =SUM(I88:I99) -> 26 | ... AF100: =SUM(AF88:AF99) -> 27 | AG100: =SUM(B100:AF100) -> 916
A102: Returning Customers
A103: SKU 1 - Blue | B103: 0 | C103: 0 | D103: 0 | E103: 0 | F103: 0 | G103: 0 | H103: 0 | I103: 0 | J103: 0 | K103: 0 | L103: 0 | M103: 0 | N103: 0 | O103: 0 | P103: 0 | Q103: 0 | R103: 0 | S103: 0 | T103: 0 | U103: 0 | V103: 0 | W103: 0 | X103: 0 | Y103: 0 | Z103: 0 | AA103: 0 | AB103: 0 | AC103: 0 | AD103: 0 | AE103: 0 | AF103: 0 | AG103: =SUM(B103:AF103) -> 0
A104: SKU 2 - Yellow | B104: 0 | C104: 0 | D104: 0 | E104: 0 | F104: 0 | G104: 0 | H104: 0 | I104: 0 | J104: 0 | K104: 0 | L104: 0 | M104: 0 | N104: 0 | O104: 0 | P104: 0 | Q104: 0 | R104: 0 | S104: 0 | T104: 0 | U104: 0 | V104: 0 | W104: 0 | X104: 0 | Y104: 0 | Z104: 0 | AA104: 0 | AB104: 0 | AC104: 0 | AD104: 0 | AE104: 0 | AF104: 0 | AG104: =SUM(B104:AF104) -> 0
A105: SKU 3 - Blue w/ Solar | B105: 0 | C105: 0 | D105: 0 | E105: 0 | F105: 0 | G105: 0 | H105: 0 | I105: 0 | J105: 0 | K105: 0 | L105: 0 | M105: 0 | N105: 0 | O105: 0 | P105: 0 | Q105: 0 | R105: 0 | S105: 0 | T105: 0 | U105: 0 | V105: 0 | W105: 0 | X105: 0 | Y105: 0 | Z105: 0 | AA105: 0 | AB105: 0 | AC105: 0 | AD105: 0 | AE105: 0 | AF105: 0 | AG105: =SUM(B105:AF105) -> 0
A106: SKU 4 - Yellow w/ Solar | B106: 0 | C106: 0 | D106: 0 | E106: 0 | F106: 0 | G106: 0 | H106: 0 | I106: 0 | J106: 0 | K106: 0 | L106: 0 | M106: 0 | N106: 0 | O106: 0 | P106: 0 | Q106: 0 | R106: 0 | S106: 0 | T106: 0 | U106: 0 | V106: 0 | W106: 0 | X106: 0 | Y106: 0 | Z106: 0 | AA106: 0 | AB106: 0 | AC106: 0 | AD106: 0 | AE106: 0 | AF106: 0 | AG106: =SUM(B106:AF106) -> 0
A107: SKU 1 - Blue PRO | B107: 1 | C107: 0 | D107: 1 | E107: 0 | F107: 2 | G107: 4 | H107: 1 | I107: 0 | J107: 1 | K107: 0 | L107: 0 | M107: 0 | N107: 0 | O107: 1 | P107: 0 | Q107: 0 | R107: 1 | S107: 0 | T107: 0 | U107: 3 | V107: 2 | W107: 1 | X107: 1 | Y107: 0 | Z107: 1 | AA107: 0 | AB107: 2 | AC107: 3 | AD107: 2 | AE107: 0 | AF107: 0 | AG107: =SUM(B107:AF107) -> 27
A108: SKU 2 - Yellow PRO | B108: 0 | C108: 0 | D108: 0 | E108: 0 | F108: 0 | G108: 0 | H108: 0 | I108: 0 | J108: 0 | K108: 0 | L108: 0 | M108: 0 | N108: 0 | O108: 0 | P108: 0 | Q108: 0 | R108: 0 | S108: 0 | T108: 0 | U108: 0 | V108: 0 | W108: 0 | X108: 0 | Y108: 0 | Z108: 0 | AA108: 0 | AB108: 0 | AC108: 0 | AD108: 0 | AE108: 0 | AF108: 0 | AG108: =SUM(B108:AF108) -> 0
A109: SKU 3 - Blue w/ Solar PRO | B109: 1 | C109: 1 | D109: 3 | E109: 1 | F109: 0 | G109: 3 | H109: 0 | I109: 1 | J109: 3 | K109: 3 | L109: 2 | M109: 2 | N109: 2 | O109: 0 | P109: 4 | Q109: 3 | R109: 2 | S109: 5 | T109: 2 | U109: 5 | V109: 4 | W109: 2 | X109: 1 | Y109: 3 | Z109: 1 | AA109: 3 | AB109: 4 | AC109: 0 | AD109: 2 | AE109: 3 | AF109: 5 | AG109: =SUM(B109:AF109) -> 71
A110: SKU 4 - Yellow w/ Solar PRO | B110: 0 | C110: 0 | D110: 0 | E110: 0 | F110: 0 | G110: 0 | H110: 0 | I110: 0 | J110: 0 | K110: 0 | L110: 0 | M110: 0 | N110: 0 | O110: 0 | P110: 0 | Q110: 0 | R110: 0 | S110: 0 | T110: 0 | U110: 0 | V110: 0 | W110: 0 | X110: 0 | Y110: 0 | Z110: 0 | AA110: 0 | AB110: 0 | AC110: 0 | AD110: 0 | AE110: 0 | AF110: 0 | AG110: =SUM(B110:AF110) -> 0
A111: SUM (SKU 1 - SKU 4) | B111: =SUM(B103:B110) -> 2 | C111: =SUM(C103:C110) -> 1 | D111: =SUM(D103:D110) -> 4 | E111: =SUM(E103:E110) -> 1 | F111: =SUM(F103:F110) -> 2 | G111: =SUM(G103:G110) -> 7 | H111: =SUM(H103:H110) -> 1 | I111: =SUM(I103:I110) -> 1 | ... AF111: =SUM(AF103:AF110) -> 5 | AG111: =SUM(B111:AF111) -> 98
A113: SKU 5 - HBF PRO | B113: 0 | C113: 3 | D113: 1 | E113: 0 | F113: 0 | G113: 1 | H113: 0 | I113: 0 | J113: 0 | K113: 1 | L113: 0 | M113: 0 | N113: 1 | O113: 1 | P113: 1 | Q113: 1 | R113: 0 | S113: 1 | T113: 0 | U113: 1 | V113: 0 | W113: 0 | X113: 2 | Y113: 0 | Z113: 1 | AA113: 0 | AB113: 1 | AC113: 0 | AD113: 0 | AE113: 0 | AF113: 1 | AG113: =SUM(B113:AF113) -> 17
A114: SKU 6 - HBF w/ Solar PRO | B114: 0 | C114: 1 | D114: 1 | E114: 0 | F114: 0 | G114: 0 | H114: 0 | I114: 2 | J114: 1 | K114: 0 | L114: 1 | M114: 3 | N114: 3 | O114: 2 | P114: 1 | Q114: 2 | R114: 3 | S114: 2 | T114: 0 | U114: 0 | V114: 1 | W114: 1 | X114: 1 | Y114: 1 | Z114: 2 | AA114: 1 | AB114: 2 | AC114: 2 | AD114: 0 | AE114: 2 | AF114: 2 | AG114: =SUM(B114:AF114) -> 37
A115: SUM (SKU 5 - SKU 6) | B115: =SUM(B113:B114) -> 0 | C115: =SUM(C113:C114) -> 4 | D115: =SUM(D113:D114) -> 2 | E115: =SUM(E113:E114) -> 0 | F115: =SUM(F113:F114) -> 0 | G115: =SUM(G113:G114) -> 1 | H115: =SUM(H113:H114) -> 0 | I115: =SUM(I113:I114) -> 2 | ... AF115: =SUM(AF113:AF114) -> 3 | AG115: =SUM(B115:AF115) -> 54
...

Sheet DTC EU - P&L
A1: OCTOBER | B1: 45931 | C1: 45932 | D1: 45933 | E1: 45934 | F1: 45935 | G1: 45936 | H1: 45937 | I1: 45938 | J1: 45939 | K1: 45940 | L1: 45941 | M1: 45942 | N1: 45943 | O1: 45944 | P1: 45945 | Q1: 45946 | R1: 45947 | S1: 45948 | T1: 45949 | U1: 45950 | V1: 45951 | W1: 45952 | X1: 45953 | Y1: 45954 | Z1: 45955 | AA1: 45956 | AB1: 45957 | AC1: 45958 | AD1: 45959 | AE1: 45960 | AF1: 45961
A2: DAY | B2: WED | C2: THU | D2: FRI | E2: SAT | F2: SUN | G2: MON | H2: TUE | I2: WED | J2: THU | K2: FRI | L2: SAT | M2: SUN | N2: MON | O2: TUE | P2: WED | Q2: THU | R2: FRI | S2: SAT | T2: SUN | U2: MON | V2: TUE | W2: WED | X2: THU | Y2: FRI | Z2: SAT | AA2: SUN | AB2: MON | AC2: TUE | AD2: WED | AE2: THU | AF2: FRI
A4: Revenue
A5: Revenue Woocommerce (Platform) | B5: =Summary!B21+Summary!B30 -> 729.48754 | C5: =Summary!C21+Summary!C30 -> 678.82308 | D5: =Summary!D21+Summary!D30 -> 433.72771 | E5: =Summary!E21+Summary!E30 -> 341.98663 | F5: =Summary!F21+Summary!F30 -> 1112.8104 | G5: =Summary!G21+Summary!G30 -> 0 | H5: =Summary!H21+Summary!H30 -> 426.4645 | I5: =Summary!I21+Summary!I30 -> 1208.6903 | ... AF5: =Summary!AF21+Summary!AF30 -> 925.89039 | AG5: =SUM(B5:AF5) -> 22543.808
A6: Revenue w/o renewals | B6: =B8*Summary!B143 -> 613.34258 | C6: =C8*Summary!C143 -> 678.82308 | D6: =D8*Summary!D143 -> 433.72771 | E6: =E8*Summary!E143 -> 341.98663 | F6: =F8*Summary!F143 -> 1007.3691 | G6: =G8*Summary!G143 -> 0 | H6: =H8*Summary!H143 -> 426.4645 | I6: =I8*Summary!I143 -> 1103.987 | ... AF6: =AF8*Summary!AF143 -> 925.89039
A7: SUM | B7: =SUM(B5) -> 729.48754 | C7: =SUM(C5) -> 678.82308 | D7: =SUM(D5) -> 433.72771 | E7: =SUM(E5) -> 341.98663 | F7: =SUM(F5) -> 1112.8104 | G7: =SUM(G5) -> 0 | H7: =SUM(H5) -> 426.4645 | I7: =SUM(I5) -> 1208.6903 | ... AF7: =SUM(AF5) -> 925.89039 | AG7: =SUM(B7:AF7) -> 22543.808
A8: Revenue w/o renewals EURO | B8: 522.75 | C8: 579.25 | D8: 369.35 | E8: 291.35 | F8: 859.75 | G8: 0 | H8: 365.75 | I8: 948.85 | J8: 1131 | K8: 51 | L8: 464.95 | M8: 314.25 | N8: 555.2 | O8: 443.75 | P8: 360.5 | Q8: 554 | R8: 166 | S8: 1195.45 | T8: 867.25 | U8: 290.5 | V8: 455.75 | W8: 1617.22 | X8: 1261.2 | Y8: 0 | Z8: 906.25 | AA8: 738.7 | AB8: 1296.95 | AC8: 843 | AD8: 59.9 | AE8: 0 | AF8: 797.7
A9: Orders
A10: Orders Woocommerce (Platform) | B10: =Summary!B104 -> 3 | C10: =Summary!C104 -> 2 | D10: =Summary!D104 -> 2 | E10: =Summary!E104 -> 2 | F10: =Summary!F104 -> 4 | G10: =Summary!G104 -> 0 | H10: =Summary!H104 -> 2 | I10: =Summary!I104 -> 5 | ... AF10: =Summary!AF104 -> 5 | AG10: =SUM(B10:AF10) -> 95
A11: Orders w/o renewals | B11: 2 | C11: 2 | D11: 2 | E11: 2 | F11: 3 | G11: 0 | H11: 2 | I11: 4 | J11: 4 | K11: 2 | L11: 3 | M11: 1 | N11: 3 | O11: 2 | P11: 2 | Q11: 2 | R11: 2 | S11: 6 | T11: 4 | U11: 2 | V11: 3 | W11: 6 | X11: 5 | Y11: 0 | Z11: 3 | AA11: 3 | AB11: 4 | AC11: 3 | AD11: 1 | AE11: 0 | AF11: 5
A12: SUM | B12: =SUM(B10) -> 3 | C12: =SUM(C10) -> 2 | D12: =SUM(D10) -> 2 | E12: =SUM(E10) -> 2 | F12: =SUM(F10) -> 4 | G12: =SUM(G10) -> 0 | H12: =SUM(H10) -> 2 | I12: =SUM(I10) -> 5 | ... AF12: =SUM(AF10) -> 5 | AG12: =SUM(B12:AF12) -> 95
A14: Breakdown
A15: - Hardware | B15: 426.65 | C15: 381.88 | D15: 221.37 | E15: 167.2 | F15: 582.56 | G15: 0 | H15: 210.57 | I15: 558.81 | J15: 821.7 | K15: 0 | L15: 217.65 | M15: 214.05 | N15: 379.93 | O15: 210.57 | P15: 212.3 | Q15: 383.3 | R15: 0 | S15: 771.05 | T15: 603.85 | U15: 171.31 | V15: 210.57 | W15: 1017.62 | X15: 852.91 | Y15: 0 | Z15: 645.78 | AA15: 428.22 | AB15: 766.91 | AC15: 599.41 | AD15: 0 | AE15: 0 | AF15: 431.66 | AG15: =SUM(B15:AF15) -> 11487.83
A16: - Add-ons | B16: 21.01 | C16: 40.66 | D16: 57.02 | E16: 32.23 | F16: 32.23 | G16: 0 | H16: 52.83 | I16: 142.76 | J16: 21.01 | K16: 32.5 | L16: 125.84 | M16: 20.66 | N16: 11.97 | O16: 118.33 | P16: 49.16 | Q16: 20.33 | R16: 118.31 | S16: 93.55 | T16: 41.84 | U16: 32.5 | V16: 118.01 | W16: 169.78 | X16: 76.16 | Y16: 0 | Z16: 32.77 | AA16: 121.18 | AB16: 196.34 | AC16: 20.66 | AD16: 40.33 | AE16: 0 | AF16: 149.16 | AG16: =SUM(B16:AF16) -> 1989.13
A17: - Merch | B17: 0 | C17: 0 | D17: 0 | E17: 0 | F17: 0 | G17: 0 | H17: 0 | I17: 0 | J17: 0 | K17: 0 | L17: 0 | M17: 0 | N17: 0 | O17: 0 | P17: 0 | Q17: 0 | R17: 0 | S17: 0 | T17: 0 | U17: 0 | V17: 0 | W17: 0 | X17: 0 | Y17: 0 | Z17: 0 | AA17: 0 | AB17: 0 | AC17: 0 | AD17: 0 | AE17: 0 | AF17: 0 | AG17: =SUM(B17:AF17) -> 0
A18: - Seeds | B18: 0 | C18: 0 | D18: 0 | E18: 0 | F18: 0 | G18: 0 | H18: 0 | I18: 0 | J18: 0 | K18: 0 | L18: 0 | M18: 0 | N18: 0 | O18: 0 | P18: 0 | Q18: 0 | R18: 0 | S18: 0 | T18: 0 | U18: 0 | V18: 0 | W18: 0 | X18: 0 | Y18: 0 | Z18: 0 | AA18: 0 | AB18: 0 | AC18: 0 | AD18: 0 | AE18: 0 | AF18: 0 | AG18: =SUM(B18:AF18) -> 0
A19: - Yearly Pro Subscription | B19: 80.48 | C19: 0 | D19: 0 | E19: 0 | F19: 71.99 | G19: 0 | H19: 0 | I19: 74.99 | J19: 73.16 | K19: 0 | L19: 0 | M19: 150.61 | N19: 0 | O19: 352.89 | P19: 0 | Q19: 0 | R19: 0 | S19: 0 | T19: 0 | U19: 0 | V19: 0 | W19: 73.76 | X19: 0 | Y19: 0 | Z19: 0 | AA19: 0 | AB19: 0 | AC19: 0 | AD19: 0 | AE19: 0 | AF19: 0 | AG19: =SUM(B19:AF19) -> 877.88
A20: - Taxes | B20: 68.6 | C20: 106.71 | D20: 55.96 | E20: 56.92 | F20: 187.96 | G20: 0 | H20: 67.35 | I20: 177.28 | J20: 205.12 | K20: 8.5 | L20: 76.46 | M20: 83.91 | N20: 103.3 | O20: 146.91 | P20: 64.04 | Q20: 100.37 | R20: 27.69 | S20: 210.85 | T20: 146.56 | U20: 51.69 | V20: 82.17 | W20: 311.05 | X20: 222.13 | Y20: 0 | Z20: 152.7 | AA20: 129.3 | AB20: 233.7 | AC20: 147.93 | AD20: 9.57 | AE20: 0 | AF20: 136.88 | AG20: =SUM(B20:AF20) -> 3371.61
A21: - Shipping | B21: 25 | C21: 50 | D21: 35 | E21: 35 | F21: 75 | G21: 0 | H21: 35 | I21: 85 | J21: 100 | K21: 10 | L21: 45 | M21: 25 | N21: 60 | O21: 35 | P21: 35 | Q21: 50 | R21: 20 | S21: 120 | T21: 75 | U21: 35 | V21: 45 | W21: 135 | X21: 110 | Y21: 0 | Z21: 75 | AA21: 60 | AB21: 100 | AC21: 75 | AD21: 10 | AE21: 0 | AF21: 80 | AG21: =SUM(B21:AF21) -> 1640
A22: SUM | B22: =SUM(B15:B21) -> 621.74 | C22: =SUM(C15:C21) -> 579.25 | D22: =SUM(D15:D21) -> 369.35 | E22: =SUM(E15:E21) -> 291.35 | F22: =SUM(F15:F21) -> 949.74 | G22: =SUM(G15:G21) -> 0 | H22: =SUM(H15:H21) -> 365.75 | I22: =SUM(I15:I21) -> 1038.84 | ... AF22: =SUM(AF15:AF21) -> 797.7 | AG22: =SUM(B22:AF22) -> 19366.45
A24: Units Sold (Gross)
A25: SKU 1 - Blue | B25: =B176 -> 0 | C25: =C176 -> 0 | D25: =D176 -> 0 | E25: =E176 -> 0 | F25: =F176 -> 0 | G25: =G176 -> 0 | H25: =H176 -> 0 | I25: =I176 -> 0 | ... AF25: =AF176 -> 0 | AG25: =SUM(B25:AF25) -> 0
A26: SKU 2 - Yellow | B26: =B177 -> 0 | C26: =C177 -> 0 | D26: =D177 -> 0 | E26: =E177 -> 0 | F26: =F177 -> 0 | G26: =G177 -> 0 | H26: =H177 -> 0 | I26: =I177 -> 0 | ... AF26: =AF177 -> 0 | AG26: =SUM(B26:AF26) -> 0
A27: SKU 3 - Blue w/ Solar | B27: =B178 -> 0 | C27: =C178 -> 0 | D27: =D178 -> 0 | E27: =E178 -> 0 | F27: =F178 -> 0 | G27: =G178 -> 0 | H27: =H178 -> 0 | I27: =I178 -> 0 | ... AF27: =AF178 -> 0 | AG27: =SUM(B27:AF27) -> 0
A28: SKU 4 - Yellow w/ Solar | B28: =B179 -> 0 | C28: =C179 -> 0 | D28: =D179 -> 0 | E28: =E179 -> 0 | F28: =F179 -> 0 | G28: =G179 -> 0 | H28: =H179 -> 0 | I28: =I179 -> 0 | ... AF28: =AF179 -> 0 | AG28: =SUM(B28:AF28) -> 0
A29: SKU 1 - Blue PRO | B29: =B182 -> 1 | C29: =C182 -> 1 | D29: =D182 -> 0 | E29: =E182 -> 1 | F29: =F182 -> 1 | G29: =G182 -> 0 | H29: =H182 -> 0 | I29: =I182 -> 1 | ... AF29: =AF182 -> 0 | AG29: =SUM(B29:AF29) -> 15
A30: SKU 2 - Yellow PRO | B30: =B183 -> 0 | C30: =C183 -> 0 | D30: =D183 -> 0 | E30: =E183 -> 0 | F30: =F183 -> 0 | G30: =G183 -> 0 | H30: =H183 -> 0 | I30: =I183 -> 0 | ... AF30: =AF183 -> 0 | AG30: =SUM(B30:AF30) -> 0
A31: SKU 3 - Blue w/ Solar PRO | B31: =B184 -> 1 | C31: =C184 -> 1 | D31: =D184 -> 1 | E31: =E184 -> 0 | F31: =F184 -> 2 | G31: =G184 -> 0 | H31: =H184 -> 1 | I31: =I184 -> 2 | ... AF31: =AF184 -> 2 | AG31: =SUM(B31:AF31) -> 42
A32: SKU 4 - Yellow w/ Solar PRO | B32: =B185 -> 0 | C32: =C185 -> 0 | D32: =D185 -> 0 | E32: =E185 -> 0 | F32: =F185 -> 0 | G32: =G185 -> 0 | H32: =H185 -> 0 | I32: =I185 -> 0 | ... AF32: =AF185 -> 0 | AG32: =SUM(B32:AF32) -> 0
A33: SUM (SKU 1 - SKU 4) | B33: =SUM(B25:B32) -> 2 | C33: =SUM(C25:C32) -> 2 | D33: =SUM(D25:D32) -> 1 | E33: =SUM(E25:E32) -> 1 | F33: =SUM(F25:F32) -> 3 | G33: =SUM(G25:G32) -> 0 | H33: =SUM(H25:H32) -> 1 | I33: =SUM(I25:I32) -> 3 | ... AF33: =SUM(AF25:AF32) -> 2 | AG33: =SUM(B33:AF33) -> 57
A35: SKU 5 - HBF PRO | AG35: =SUM(B35:AF35) -> 0
A36: SKU 6 - HBF w/ Solar PRO | AG36: =SUM(B36:AF36) -> 0
A37: SUM (SKU 5 - SKU 6) | B37: =SUM(B35:B36) -> 0 | C37: =SUM(C35:C36) -> 0 | D37: =SUM(D35:D36) -> 0 | E37: =SUM(E35:E36) -> 0 | F37: =SUM(F35:F36) -> 0 | G37: =SUM(G35:G36) -> 0 | H37: =SUM(H35:H36) -> 0 | I37: =SUM(I35:I36) -> 0 | ... AF37: =SUM(AF35:AF36) -> 0 | AG37: =SUM(B37:AF37) -> 0
A39: Wall Mount | B39: =B205 -> 0 | C39: =C205 -> 1 | D39: =D205 -> 0 | E39: =E205 -> 0 | F39: =F205 -> 0 | G39: =G205 -> 0 | H39: =H205 -> 0 | I39: =I205 -> 1 | ... AF39: =AF205 -> 1 | AG39: =SUM(B39:AF39) -> 16
A40: Suet Ball Holder | B40: =B206 -> 0 | C40: =C206 -> 2 | D40: =D206 -> 1 | E40: =E206 -> 2 | F40: =F206 -> 2 | G40: =G206 -> 0 | H40: =H206 -> 2 | I40: =I206 -> 3 | ... AF40: =AF206 -> 2 | AG40: =SUM(B40:AF40) -> 63
A41: 3-in-1 Nutrition Set - Blue | B41: =B207 -> 0 | C41: =C207 -> 0 | D41: =D207 -> 0 | E41: =E207 -> 0 | F41: =F207 -> 0 | G41: =G207 -> 0 | H41: =H207 -> 0 | I41: =I207 -> 2 | ... AF41: =AF207 -> 0 | AG41: =SUM(B41:AF41) -> 13
A42: 3-in-1 Nutrition Set - Yellow | B42: =B208 -> 0 | C42: =C208 -> 0 | D42: =D208 -> 0 | E42: =E208 -> 0 | F42: =F208 -> 0 | G42: =G208 -> 0 | H42: =H208 -> 0 | I42: =I208 -> 0 | ... AF42: =AF208 -> 0 | AG42: =SUM(B42:AF42) -> 0
A43: Solar Roof Single - Blue | B43: =B209 -> 0 | C43: =C209 -> 0 | D43: =D209 -> 0 | E43: =E209 -> 0 | F43: =F209 -> 0 | G43: =G209 -> 0 | H43: =H209 -> 0 | I43: =I209 -> 0 | ... AF43: =AF209 -> 0 | AG43: =SUM(B43:AF43) -> 0
A44: Solar Roof Single - Yellow | B44: =B210 -> 0 | C44: =C210 -> 0 | D44: =D210 -> 1 | E44: =E210 -> 0 | F44: =F210 -> 0 | G44: =G210 -> 0 | H44: =H210 -> 0 | I44: =I210 -> 0 | ... AF44: =AF210 -> 1 | AG44: =SUM(B44:AF44) -> 7
A45: Perch Extender - Blue | B45: =B211 -> 1 | C45: =C211 -> 1 | D45: =D211 -> 0 | E45: =E211 -> 1 | F45: =F211 -> 1 | G45: =G211 -> 0 | H45: =H211 -> 2 | I45: =I211 -> 2 | ... AF45: =AF211 -> 3 | AG45: =SUM(B45:AF45) -> 31
A46: Perch Extender - Yellow | B46: =B212 -> 0 | C46: =C212 -> 0 | D46: =D212 -> 0 | E46: =E212 -> 0 | F46: =F212 -> 0 | G46: =G212 -> 0 | H46: =H212 -> 0 | I46: =I212 -> 0 | ... AF46: =AF212 -> 0 | AG46: =SUM(B46:AF46) -> 0
A47: Solar Roof (HBF) | AG47: =SUM(B47:AF47) -> 0
A48: Housing - only (HBF) | AG48: =SUM(B48:AF48) -> 0
A49: Nature Station
A50: Nature Cam PRO | AG50: =SUM(B50:AF50) -> 0
A51: SUM (Add-ons) | B51: =SUM(B39:B50) -> 1 | C51: =SUM(C39:C50) -> 4 | D51: =SUM(D39:D50) -> 2 | E51: =SUM(E39:E50) -> 3 | F51: =SUM(F39:F50) -> 3 | G51: =SUM(G39:G50) -> 0 | H51: =SUM(H39:H50) -> 4 | I51: =SUM(I39:I50) -> 8 | ... AF51: =SUM(AF39:AF50) -> 7 | AG51: =SUM(B51:AF51) -> 130
A53: Seasonal Curation - 8lb | AG53: =SUM(B53:AF53) -> 0
A54: Seasonal Curation - 20lb | AG54: =SUM(B54:AF54) -> 0
A55: Buddy Bites - 8lb | AG55: =SUM(B55:AF55) -> 0
A56: Buddy Bites - 20lb | AG56: =SUM(B56:AF56) -> 0
A57: Snack n' Soar - 8lb | AG57: =SUM(B57:AF57) -> 0
A58: Snack n' Soar - 20lb | AG58: =SUM(B58:AF58) -> 0
A59: Avian Choice - 8lb | AG59: =SUM(B59:AF59) -> 0
A60: Avian Choice - 20lb | AG60: =SUM(B60:AF60) -> 0
A61: SUM (Seeds) | B61: =SUM(B53:B60) -> 0 | C61: =SUM(C53:C60) -> 0 | D61: =SUM(D53:D60) -> 0 | E61: =SUM(E53:E60) -> 0 | F61: =SUM(F53:F60) -> 0 | G61: =SUM(G53:G60) -> 0 | H61: =SUM(H53:H60) -> 0 | I61: =SUM(I53:I60) -> 0 | ... AF61: =SUM(AF53:AF60) -> 0 | AG61: =SUM(B61:AF61) -> 0
A63: Merch Units Sold (Gross)
A64: Merch Units | B64: 0 | C64: 0 | D64: 0 | E64: 0 | F64: 0 | G64: 0 | H64: 0 | I64: 0 | J64: 0 | K64: 0 | L64: 0 | M64: 0 | N64: 0 | O64: 0 | P64: 0 | Q64: 0 | R64: 0 | S64: 0 | T64: 0 | U64: 0 | V64: 0 | W64: 0 | X64: 0 | Y64: 0 | Z64: 0 | AA64: 0 | AB64: 0 | AC64: 0 | AD64: 0 | AE64: 0 | AF64: 0 | AG64: =SUM(B64:AF64) -> 0
A66: First-time Customers
A67: SKU 1 - Blue | B67: =B25-B96 -> 0 | C67: =C25-C96 -> 0 | D67: =D25-D96 -> 0 | E67: =E25-E96 -> 0 | F67: =F25-F96 -> 0 | G67: =G25-G96 -> 0 | H67: =H25-H96 -> 0 | I67: =I25-I96 -> 0 | ... AF67: =AF25-AF96 -> 0 | AG67: =SUM(B67:AF67) -> 0
A68: SKU 2 - Yellow | B68: =B26-B97 -> 0 | C68: =C26-C97 -> 0 | D68: =D26-D97 -> 0 | E68: =E26-E97 -> 0 | F68: =F26-F97 -> 0 | G68: =G26-G97 -> 0 | H68: =H26-H97 -> 0 | I68: =I26-I97 -> 0 | ... AF68: =AF26-AF97 -> 0 | AG68: =SUM(B68:AF68) -> 0
A69: SKU 3 - Blue w/ Solar | B69: =B27-B98 -> 0 | C69: =C27-C98 -> 0 | D69: =D27-D98 -> 0 | E69: =E27-E98 -> 0 | F69: =F27-F98 -> 0 | G69: =G27-G98 -> 0 | H69: =H27-H98 -> 0 | I69: =I27-I98 -> 0 | ... AF69: =AF27-AF98 -> 0 | AG69: =SUM(B69:AF69) -> 0
A70: SKU 4 - Yellow w/ Solar | B70: =B28-B99 -> 0 | C70: =C28-C99 -> 0 | D70: =D28-D99 -> 0 | E70: =E28-E99 -> 0 | F70: =F28-F99 -> 0 | G70: =G28-G99 -> 0 | H70: =H28-H99 -> 0 | I70: =I28-I99 -> 0 | ... AF70: =AF28-AF99 -> 0 | AG70: =SUM(B70:AF70) -> 0
A71: SKU 1 - Blue PRO | B71: =B29-B100 -> 1 | C71: =C29-C100 -> 1 | D71: =D29-D100 -> 0 | E71: =E29-E100 -> 1 | F71: =F29-F100 -> 1 | G71: =G29-G100 -> 0 | H71: =H29-H100 -> 0 | I71: =I29-I100 -> 1 | ... AF71: =AF29-AF100 -> 0 | AG71: =SUM(B71:AF71) -> 14
A72: SKU 2 - Yellow PRO | B72: =B30-B101 -> 0 | C72: =C30-C101 -> 0 | D72: =D30-D101 -> 0 | E72: =E30-E101 -> 0 | F72: =F30-F101 -> 0 | G72: =G30-G101 -> 0 | H72: =H30-H101 -> 0 | I72: =I30-I101 -> 0 | ... AF72: =AF30-AF101 -> 0 | AG72: =SUM(B72:AF72) -> 0
A73: SKU 3 - Blue w/ Solar PRO | B73: =B31-B102 -> 1 | C73: =C31-C102 -> 1 | D73: =D31-D102 -> 1 | E73: =E31-E102 -> 0 | F73: =F31-F102 -> 2 | G73: =G31-G102 -> 0 | H73: =H31-H102 -> 1 | I73: =I31-I102 -> 2 | ... AF73: =AF31-AF102 -> 2 | AG73: =SUM(B73:AF73) -> 42
A74: SKU 4 - Yellow w/ Solar PRO | B74: =B32-B103 -> 0 | C74: =C32-C103 -> 0 | D74: =D32-D103 -> 0 | E74: =E32-E103 -> 0 | F74: =F32-F103 -> 0 | G74: =G32-G103 -> 0 | H74: =H32-H103 -> 0 | I74: =I32-I103 -> 0 | ... AF74: =AF32-AF103 -> 0 | AG74: =SUM(B74:AF74) -> 0
A75: SUM (SKU 1 - SKU 4) | B75: =SUM(B67:B74) -> 2 | C75: =SUM(C67:C74) -> 2 | D75: =SUM(D67:D74) -> 1 | E75: =SUM(E67:E74) -> 1 | F75: =SUM(F67:F74) -> 3 | G75: =SUM(G67:G74) -> 0 | H75: =SUM(H67:H74) -> 1 | I75: =SUM(I67:I74) -> 3 | ... AF75: =SUM(AF67:AF74) -> 2 | AG75: =SUM(B75:AF75) -> 56
A77: SKU 5 - HBF PRO | B77: =B35-B106 -> 0 | C77: =C35-C106 -> 0 | D77: =D35-D106 -> 0 | E77: =E35-E106 -> 0 | F77: =F35-F106 -> 0 | G77: =G35-G106 -> 0 | H77: =H35-H106 -> 0 | I77: =I35-I106 -> 0 | ... AF77: =AF35-AF106 -> 0 | AG77: =SUM(B77:AF77) -> 0
A78: SKU 6 - HBF w/ Solar PRO | B78: =B36-B107 -> 0 | C78: =C36-C107 -> 0 | D78: =D36-D107 -> 0 | E78: =E36-E107 -> 0 | F78: =F36-F107 -> 0 | G78: =G36-G107 -> 0 | H78: =H36-H107 -> 0 | I78: =I36-I107 -> 0 | ... AF78: =AF36-AF107 -> 0 | AG78: =SUM(B78:AF78) -> 0
A79: SUM (SKU 5 - SKU 6) | B79: =SUM(B77:B78) -> 0 | C79: =SUM(C77:C78) -> 0 | D79: =SUM(D77:D78) -> 0 | E79: =SUM(E77:E78) -> 0 | F79: =SUM(F77:F78) -> 0 | G79: =SUM(G77:G78) -> 0 | H79: =SUM(H77:H78) -> 0 | I79: =SUM(I77:I78) -> 0 | ... AF79: =SUM(AF77:AF78) -> 0 | AG79: =SUM(B79:AF79) -> 0
A81: Wall Mount | B81: =B39-B110 -> 0 | C81: =C39-C110 -> 1 | D81: =D39-D110 -> 0 | E81: =E39-E110 -> 0 | F81: =F39-F110 -> 0 | G81: =G39-G110 -> 0 | H81: =H39-H110 -> 0 | I81: =I39-I110 -> 1 | ... AF81: =AF39-AF110 -> 1 | AG81: =SUM(B81:AF81) -> 16
A82: Suet Ball Holder | B82: =B40-B111 -> 0 | C82: =C40-C111 -> 2 | D82: =D40-D111 -> 1 | E82: =E40-E111 -> 2 | F82: =F40-F111 -> 2 | G82: =G40-G111 -> 0 | H82: =H40-H111 -> 2 | I82: =I40-I111 -> 3 | ... AF82: =AF40-AF111 -> 2 | AG82: =SUM(B82:AF82) -> 62
A83: 3-in-1 Nutrition Set - Blue | B83: =B41-B112 -> 0 | C83: =C41-C112 -> 0 | D83: =D41-D112 -> 0 | E83: =E41-E112 -> 0 | F83: =F41-F112 -> 0 | G83: =G41-G112 -> 0 | H83: =H41-H112 -> 0 | I83: =I41-I112 -> 2 | ... AF83: =AF41-AF112 -> 0 | AG83: =SUM(B83:AF83) -> 12
A84: 3-in-1 Nutrition Set - Yellow | B84: =B42-B113 -> 0 | C84: =C42-C113 -> 0 | D84: =D42-D113 -> 0 | E84: =E42-E113 -> 0 | F84: =F42-F113 -> 0 | G84: =G42-G113 -> 0 | H84: =H42-H113 -> 0 | I84: =I42-I113 -> 0 | ... AF84: =AF42-AF113 -> 0 | AG84: =SUM(B84:AF84) -> 0
A85: Solar Roof Single - Blue | B85: =B43-B114 -> 0 | C85: =C43-C114 -> 0 | D85: =D43-D114 -> 0 | E85: =E43-E114 -> 0 | F85: =F43-F114 -> 0 | G85: =G43-G114 -> 0 | H85: =H43-H114 -> 0 | I85: =I43-I114 -> 0 | ... AF85: =AF43-AF114 -> 0 | AG85: =SUM(B85:AF85) -> 0
A86: Solar Roof Single - Yellow | B86: =B44-B115 -> 0 | C86: =C44-C115 -> 0 | D86: =D44-D115 -> 1 | E86: =E44-E115 -> 0 | F86: =F44-F115 -> 0 | G86: =G44-G115 -> 0 | H86: =H44-H115 -> 0 | I86: =I44-I115 -> 0 | ... AF86: =AF44-AF115 -> 1 | AG86: =SUM(B86:AF86) -> 7
A87: Perch Extender - Blue | B87: =B45-B116 -> 1 | C87: =C45-C116 -> 1 | D87: =D45-D116 -> 0 | E87: =E45-E116 -> 1 | F87: =F45-F116 -> 1 | G87: =G45-G116 -> 0 | H87: =H45-H116 -> 2 | I87: =I45-I116 -> 2 | ... AF87: =AF45-AF116 -> 3 | AG87: =SUM(B87:AF87) -> 30
A88: Perch Extender - Yellow | B88: =B46-B117 -> 0 | C88: =C46-C117 -> 0 | D88: =D46-D117 -> 0 | E88: =E46-E117 -> 0 | F88: =F46-F117 -> 0 | G88: =G46-G117 -> 0 | H88: =H46-H117 -> 0 | I88: =I46-I117 -> 0 | ... AF88: =AF46-AF117 -> 0 | AG88: =SUM(B88:AF88) -> 0
A89: Solar Roof (HBF) | B89: =B47-B118 -> 0 | C89: =C47-C118 -> 0 | D89: =D47-D118 -> 0 | E89: =E47-E118 -> 0 | F89: =F47-F118 -> 0 | G89: =G47-G118 -> 0 | H89: =H47-H118 -> 0 | I89: =I47-I118 -> 0 | ... AF89: =AF47-AF118 -> 0 | AG89: =SUM(B89:AF89) -> 0
A90: Housing - only (HBF) | B90: =B48-B119 -> 0 | C90: =C48-C119 -> 0 | D90: =D48-D119 -> 0 | E90: =E48-E119 -> 0 | F90: =F48-F119 -> 0 | G90: =G48-G119 -> 0 | H90: =H48-H119 -> 0 | I90: =I48-I119 -> 0 | ... AF90: =AF48-AF119 -> 0 | AG90: =SUM(B90:AF90) -> 0
A91: Nature Station | B91: =B49-B120 -> 0 | C91: =C49-C120 -> 0 | D91: =D49-D120 -> 0 | E91: =E49-E120 -> 0 | F91: =F49-F120 -> 0 | G91: =G49-G120 -> 0 | H91: =H49-H120 -> 0 | I91: =I49-I120 -> 0 | ... AF91: =AF49-AF120 -> 0
A92: Nature Cam PRO | B92: =B50-B121 -> 0 | C92: =C50-C121 -> 0 | D92: =D50-D121 -> 0 | E92: =E50-E121 -> 0 | F92: =F50-F121 -> 0 | G92: =G50-G121 -> 0 | H92: =H50-H121 -> 0 | I92: =I50-I121 -> 0 | ... AF92: =AF50-AF121 -> 0 | AG92: =SUM(B92:AF92) -> 0
A93: SUM (Add-ons) | B93: =SUM(B81:B92) -> 1 | C93: =SUM(C81:C92) -> 4 | D93: =SUM(D81:D92) -> 2 | E93: =SUM(E81:E92) -> 3 | F93: =SUM(F81:F92) -> 3 | G93: =SUM(G81:G92) -> 0 | H93: =SUM(H81:H92) -> 4 | I93: =SUM(I81:I92) -> 8 | ... AF93: =SUM(AF81:AF92) -> 7 | AG93: =SUM(B93:AF93) -> 127
A95: Returning Customers
A96: SKU 1 - Blue | B96: 0 | C96: 0 | D96: 0 | E96: 0 | F96: 0 | G96: 0 | H96: 0 | I96: 0 | J96: 0 | K96: 0 | L96: 0 | M96: 0 | N96: 0 | O96: 0 | P96: 0 | Q96: 0 | R96: 0 | S96: 0 | T96: 0 | U96: 0 | V96: 0 | W96: 0 | X96: 0 | Y96: 0 | Z96: 0 | AA96: 0 | AB96: 0 | AC96: 0 | AD96: 0 | AE96: 0 | AF96: 0 | AG96: =SUM(B96:AF96) -> 0
A97: SKU 2 - Yellow | B97: 0 | C97: 0 | D97: 0 | E97: 0 | F97: 0 | G97: 0 | H97: 0 | I97: 0 | J97: 0 | K97: 0 | L97: 0 | M97: 0 | N97: 0 | O97: 0 | P97: 0 | Q97: 0 | R97: 0 | S97: 0 | T97: 0 | U97: 0 | V97: 0 | W97: 0 | X97: 0 | Y97: 0 | Z97: 0 | AA97: 0 | AB97: 0 | AC97: 0 | AD97: 0 | AE97: 0 | AF97: 0 | AG97: =SUM(B97:AF97) -> 0
A98: SKU 3 - Blue w/ Solar | B98: 0 | C98: 0 | D98: 0 | E98: 0 | F98: 0 | G98: 0 | H98: 0 | I98: 0 | J98: 0 | K98: 0 | L98: 0 | M98: 0 | N98: 0 | O98: 0 | P98: 0 | Q98: 0 | R98: 0 | S98: 0 | T98: 0 | U98: 0 | V98: 0 | W98: 0 | X98: 0 | Y98: 0 | Z98: 0 | AA98: 0 | AB98: 0 | AC98: 0 | AD98: 0 | AE98: 0 | AF98: 0 | AG98: =SUM(B98:AF98) -> 0
A99: SKU 4 - Yellow w/ Solar | B99: 0 | C99: 0 | D99: 0 | E99: 0 | F99: 0 | G99: 0 | H99: 0 | I99: 0 | J99: 0 | K99: 0 | L99: 0 | M99: 0 | N99: 0 | O99: 0 | P99: 0 | Q99: 0 | R99: 0 | S99: 0 | T99: 0 | U99: 0 | V99: 0 | W99: 0 | X99: 0 | Y99: 0 | Z99: 0 | AA99: 0 | AB99: 0 | AC99: 0 | AD99: 0 | AE99: 0 | AF99: 0 | AG99: =SUM(B99:AF99) -> 0
A100: SKU 1 - Blue PRO | B100: 0 | C100: 0 | D100: 0 | E100: 0 | F100: 0 | G100: 0 | H100: 0 | I100: 0 | J100: 0 | K100: 0 | L100: 0 | M100: 0 | N100: 0 | O100: 0 | P100: 0 | Q100: 0 | R100: 0 | S100: 0 | T100: 0 | U100: 1 | V100: 0 | W100: 0 | X100: 0 | Y100: 0 | Z100: 0 | AA100: 0 | AB100: 0 | AC100: 0 | AD100: 0 | AE100: 0 | AF100: 0 | AG100: =SUM(B100:AF100) -> 1
A101: SKU 2 - Yellow PRO | B101: 0 | C101: 0 | D101: 0 | E101: 0 | F101: 0 | G101: 0 | H101: 0 | I101: 0 | J101: 0 | K101: 0 | L101: 0 | M101: 0 | N101: 0 | O101: 0 | P101: 0 | Q101: 0 | R101: 0 | S101: 0 | T101: 0 | U101: 0 | V101: 0 | W101: 0 | X101: 0 | Y101: 0 | Z101: 0 | AA101: 0 | AB101: 0 | AC101: 0 | AD101: 0 | AE101: 0 | AF101: 0 | AG101: =SUM(B101:AF101) -> 0
A102: SKU 3 - Blue w/ Solar PRO | B102: 0 | C102: 0 | D102: 0 | E102: 0 | F102: 0 | G102: 0 | H102: 0 | I102: 0 | J102: 0 | K102: 0 | L102: 0 | M102: 0 | N102: 0 | O102: 0 | P102: 0 | Q102: 0 | R102: 0 | S102: 0 | T102: 0 | U102: 0 | V102: 0 | W102: 0 | X102: 0 | Y102: 0 | Z102: 0 | AA102: 0 | AB102: 0 | AC102: 0 | AD102: 0 | AE102: 0 | AF102: 0 | AG102: =SUM(B102:AF102) -> 0
A103: SKU 4 - Yellow w/ Solar PRO | B103: 0 | C103: 0 | D103: 0 | E103: 0 | F103: 0 | G103: 0 | H103: 0 | I103: 0 | J103: 0 | K103: 0 | L103: 0 | M103: 0 | N103: 0 | O103: 0 | P103: 0 | Q103: 0 | R103: 0 | S103: 0 | T103: 0 | U103: 0 | V103: 0 | W103: 0 | X103: 0 | Y103: 0 | Z103: 0 | AA103: 0 | AB103: 0 | AC103: 0 | AD103: 0 | AE103: 0 | AF103: 0 | AG103: =SUM(B103:AF103) -> 0
A104: SUM (SKU 1 - SKU 4) | B104: =SUM(B96:B103) -> 0 | C104: =SUM(C96:C103) -> 0 | D104: =SUM(D96:D103) -> 0 | E104: =SUM(E96:E103) -> 0 | F104: =SUM(F96:F103) -> 0 | G104: =SUM(G96:G103) -> 0 | H104: =SUM(H96:H103) -> 0 | I104: =SUM(I96:I103) -> 0 | ... AF104: =SUM(AF96:AF103) -> 0 | AG104: =SUM(B104:AF104) -> 1
A106: SKU 5 - HBF PRO | AG106: =SUM(B106:AF106) -> 0
A107: SKU 6 - HBF w/ Solar PRO | AG107: =SUM(B107:AF107) -> 0
A108: SUM (SKU 5 - SKU 6) | B108: =SUM(B106:B107) -> 0 | C108: =SUM(C106:C107) -> 0 | D108: =SUM(D106:D107) -> 0 | E108: =SUM(E106:E107) -> 0 | F108: =SUM(F106:F107) -> 0 | G108: =SUM(G106:G107) -> 0 | H108: =SUM(H106:H107) -> 0 | I108: =SUM(I106:I107) -> 0 | ... AF108: =SUM(AF106:AF107) -> 0 | AG108: =SUM(B108:AF108) -> 0
A110: Wall Mount | B110: 0 | C110: 0 | D110: 0 | E110: 0 | F110: 0 | G110: 0 | H110: 0 | I110: 0 | J110: 0 | K110: 0 | L110: 0 | M110: 0 | N110: 0 | O110: 0 | P110: 0 | Q110: 0 | R110: 0 | S110: 0 | T110: 0 | U110: 0 | V110: 0 | W110: 0 | X110: 0 | Y110: 0 | Z110: 0 | AA110: 0 | AB110: 0 | AC110: 0 | AD110: 0 | AE110: 0 | AF110: 0 | AG110: =SUM(B110:AF110) -> 0
A111: Suet Ball Holder | B111: 0 | C111: 0 | D111: 0 | E111: 0 | F111: 0 | G111: 0 | H111: 0 | I111: 0 | J111: 0 | K111: 0 | L111: 0 | M111: 0 | N111: 0 | O111: 0 | P111: 0 | Q111: 0 | R111: 0 | S111: 0 | T111: 0 | U111: 1 | V111: 0 | W111: 0 | X111: 0 | Y111: 0 | Z111: 0 | AA111: 0 | AB111: 0 | AC111: 0 | AD111: 0 | AE111: 0 | AF111: 0 | AG111: =SUM(B111:AF111) -> 1
A112: 3-in-1 Nutrition Set - Blue | B112: 0 | C112: 0 | D112: 0 | E112: 0 | F112: 0 | G112: 0 | H112: 0 | I112: 0 | J112: 0 | K112: 0 | L112: 0 | M112: 0 | N112: 0 | O112: 0 | P112: 1 | Q112: 0 | R112: 0 | S112: 0 | T112: 0 | U112: 0 | V112: 0 | W112: 0 | X112: 0 | Y112: 0 | Z112: 0 | AA112: 0 | AB112: 0 | AC112: 0 | AD112: 0 | AE112: 0 | AF112: 0 | AG112: =SUM(B112:AF112) -> 1
A113: 3-in-1 Nutrition Set - Yellow | B113: 0 | C113: 0 | D113: 0 | E113: 0 | F113: 0 | G113: 0 | H113: 0 | I113: 0 | J113: 0 | K113: 0 | L113: 0 | M113: 0 | N113: 0 | O113: 0 | P113: 0 | Q113: 0 | R113: 0 | S113: 0 | T113: 0 | U113: 0 | V113: 0 | W113: 0 | X113: 0 | Y113: 0 | Z113: 0 | AA113: 0 | AB113: 0 | AC113: 0 | AD113: 0 | AE113: 0 | AF113: 0 | AG113: =SUM(B113:AF113) -> 0
...

Sheet IndieGoGo Data
A1: 45870 | B1: 45870 | C1: 45871 | D1: 45872 | E1: 45873 | F1: 45874 | G1: 45875 | H1: 45876 | I1: 45877 | J1: 45878 | K1: 45879 | L1: 45880 | M1: 45881 | N1: 45882 | O1: 45883 | P1: 45884 | Q1: 45885 | R1: 45886 | S1: 45887 | T1: 45888 | U1: 45889 | V1: 45890 | W1: 45891 | X1: 45892 | Y1: 45893 | Z1: 45894 | AA1: 45895 | AB1: 45896 | AC1: 45897 | AD1: 45898 | AE1: 45899 | AF1: 45900
B2: FRI | C2: SAT | D2: SUN | E2: MON | F2: TUE | G2: WED | H2: THU | I2: FRI | J2: SAT | K2: SUN | L2: MON | M2: TUE | N2: WED | O2: THU | P2: FRI | Q2: SAT | R2: SUN | S2: MON | T2: TUE | U2: WED | V2: THU | W2: FRI | X2: SAT | Y2: SUN | Z2: MON | AA2: TUE | AB2: WED | AC2: THU | AD2: FRI | AE2: SAT | AF2: SUN | AG2: TOTAL
A4: IndieGoGo Revenue | B4: =SUM(B5:B9) -> 0 | C4: =SUM(C5:C9) -> 0 | D4: =SUM(D5:D9) -> 0 | E4: =SUM(E5:E9) -> 0 | F4: =SUM(F5:F9) -> 0 | G4: =SUM(G5:G9) -> 0 | H4: =SUM(H5:H9) -> 0 | I4: =SUM(I5:I9) -> 0 | ... AF4: =SUM(AF5:AF9) -> 0 | AG4: =SUM(A4:AE4) -> 0
A5: - Hardware | B5: 0 | C5: 0 | D5: 0 | E5: 0 | F5: 0 | G5: 0 | H5: 0 | I5: 0 | J5: 0 | K5: 0 | L5: 0 | M5: 0 | N5: 0 | O5: 0 | P5: 0 | Q5: 0 | R5: 0 | S5: 0 | T5: 0 | U5: 0 | V5: 0 | W5: 0 | X5: 0 | Y5: 0 | Z5: 0 | AA5: 0 | AB5: 0 | AC5: 0 | AD5: 0 | AE5: 0 | AF5: 0 | AG5: =SUM(A5:AE5) -> 0
A6: - Add-ons | B6: 0 | C6: 0 | D6: 0 | E6: 0 | F6: 0 | G6: 0 | H6: 0 | I6: 0 | J6: 0 | K6: 0 | L6: 0 | M6: 0 | N6: 0 | O6: 0 | P6: 0 | Q6: 0 | R6: 0 | S6: 0 | T6: 0 | U6: 0 | V6: 0 | W6: 0 | X6: 0 | Y6: 0 | Z6: 0 | AA6: 0 | AB6: 0 | AC6: 0 | AD6: 0 | AE6: 0 | AF6: 0 | AG6: =SUM(A6:AE6) -> 0
A7: - Merch | B7: 0 | C7: 0 | D7: 0 | E7: 0 | F7: 0 | G7: 0 | H7: 0 | I7: 0 | J7: 0 | K7: 0 | L7: 0 | M7: 0 | N7: 0 | O7: 0 | P7: 0 | Q7: 0 | R7: 0 | S7: 0 | T7: 0 | U7: 0 | V7: 0 | W7: 0 | X7: 0 | Y7: 0 | Z7: 0 | AA7: 0 | AB7: 0 | AC7: 0 | AD7: 0 | AE7: 0 | AF7: 0 | AG7: =SUM(A7:AE7) -> 0
A8: - Seeds | B8: 0 | C8: 0 | D8: 0 | E8: 0 | F8: 0 | G8: 0 | H8: 0 | I8: 0 | J8: 0 | K8: 0 | L8: 0 | M8: 0 | N8: 0 | O8: 0 | P8: 0 | Q8: 0 | R8: 0 | S8: 0 | T8: 0 | U8: 0 | V8: 0 | W8: 0 | X8: 0 | Y8: 0 | Z8: 0 | AA8: 0 | AB8: 0 | AC8: 0 | AD8: 0 | AE8: 0 | AF8: 0 | AG8: =SUM(A8:AE8) -> 0
A9: - Yearly Pro Subscription | B9: 0 | C9: 0 | D9: 0 | E9: 0 | F9: 0 | G9: 0 | H9: 0 | I9: 0 | J9: 0 | K9: 0 | L9: 0 | M9: 0 | N9: 0 | O9: 0 | P9: 0 | Q9: 0 | R9: 0 | S9: 0 | T9: 0 | U9: 0 | V9: 0 | W9: 0 | X9: 0 | Y9: 0 | Z9: 0 | AA9: 0 | AB9: 0 | AC9: 0 | AD9: 0 | AE9: 0 | AF9: 0 | AG9: =SUM(A9:AE9) -> 0
A11: - Fees | B11: 15 | C11: 0 | D11: 0 | E11: 0 | F11: 0 | G11: 0 | H11: 0 | I11: 0 | J11: 0 | K11: 0 | L11: 0 | M11: 0 | N11: 0 | O11: 0 | P11: 0 | Q11: 0 | R11: 0 | S11: 0 | T11: 0 | U11: 0 | V11: 0 | W11: 0 | X11: 0 | Y11: 0 | Z11: 0 | AA11: 0 | AB11: 0 | AC11: 0 | AD11: 0 | AE11: 0 | AF11: 0 | AG11: =SUM(A11:AE11) -> 15
A13: IndieGoGo Revenue Breakdown
A14: Smart Bird Bath with Solar Roof and Water Pump | B14: 0 | C14: 0 | D14: 0 | E14: 0 | F14: 0 | G14: 0 | H14: 0 | I14: 0 | J14: 0 | K14: 0 | L14: 0 | M14: 0 | N14: 0 | O14: 0 | P14: 0 | Q14: 0 | R14: 0 | S14: 0 | T14: 0 | U14: 0 | V14: 0 | W14: 0 | X14: 0 | Y14: 0 | Z14: 0 | AA14: 0 | AB14: 0 | AC14: 0 | AD14: 0 | AE14: 0 | AF14: 0 | AG14: =SUM(A14:AE14) -> 0
A15: Smart Bird Bath without Solar Roof and Water Pump | B15: 0 | C15: 0 | D15: 0 | E15: 0 | F15: 0 | G15: 0 | H15: 0 | I15: 0 | J15: 0 | K15: 0 | L15: 0 | M15: 0 | N15: 0 | O15: 0 | P15: 0 | Q15: 0 | R15: 0 | S15: 0 | T15: 0 | U15: 0 | V15: 0 | W15: 0 | X15: 0 | Y15: 0 | Z15: 0 | AA15: 0 | AB15: 0 | AC15: 0 | AD15: 0 | AE15: 0 | AF15: 0 | AG15: =SUM(A15:AE15) -> 0
A17: Bird Bath Housing without Solar Roof and Water Pump | B17: 0 | C17: 0 | D17: 0 | E17: 0 | F17: 0 | G17: 0 | H17: 0 | I17: 0 | J17: 0 | K17: 0 | L17: 0 | M17: 0 | N17: 0 | O17: 0 | P17: 0 | Q17: 0 | R17: 0 | S17: 0 | T17: 0 | U17: 0 | V17: 0 | W17: 0 | X17: 0 | Y17: 0 | Z17: 0 | AA17: 0 | AB17: 0 | AC17: 0 | AD17: 0 | AE17: 0 | AF17: 0 | AG17: =SUM(A17:AE17) -> 0
A18: Solar Roof and Water Pump | B18: 0 | C18: 0 | D18: 0 | E18: 0 | F18: 0 | G18: 0 | H18: 0 | I18: 0 | J18: 0 | K18: 0 | L18: 0 | M18: 0 | N18: 0 | O18: 0 | P18: 0 | Q18: 0 | R18: 0 | S18: 0 | T18: 0 | U18: 0 | V18: 0 | W18: 0 | X18: 0 | Y18: 0 | Z18: 0 | AA18: 0 | AB18: 0 | AC18: 0 | AD18: 0 | AE18: 0 | AF18: 0 | AG18: =SUM(A18:AE18) -> 0
A19: Pole Mounting System with Pollinator Base | B19: 0 | C19: 0 | D19: 0 | E19: 0 | F19: 0 | G19: 0 | H19: 0 | I19: 0 | J19: 0 | K19: 0 | L19: 0 | M19: 0 | N19: 0 | O19: 0 | P19: 0 | Q19: 0 | R19: 0 | S19: 0 | T19: 0 | U19: 0 | V19: 0 | W19: 0 | X19: 0 | Y19: 0 | Z19: 0 | AA19: 0 | AB19: 0 | AC19: 0 | AD19: 0 | AE19: 0 | AF19: 0 | AG19: =SUM(A19:AE19) -> 0
A21: IndieGoGo Orders | B21: 1 | C21: 0 | D21: 0 | E21: 0 | F21: 0 | G21: 0 | H21: 0 | I21: 0 | J21: 0 | K21: 0 | L21: 0 | M21: 0 | N21: 0 | O21: 0 | P21: 0 | Q21: 0 | R21: 0 | S21: 0 | T21: 0 | U21: 0 | V21: 0 | W21: 0 | X21: 0 | Y21: 0 | Z21: 0 | AA21: 0 | AB21: 0 | AC21: 0 | AD21: 0 | AE21: 0 | AF21: 0 | AG21: =SUM(A21:AE21) -> 1
A22: IndieGoGo Quantities | B22: =SUM(B23:B27) -> 1 | C22: =SUM(C23:C27) -> 0 | D22: =SUM(D23:D27) -> 0 | E22: =SUM(E23:E27) -> 0 | F22: =SUM(F23:F27) -> 0 | G22: =SUM(G23:G27) -> 0 | H22: =SUM(H23:H27) -> 0 | I22: =SUM(I23:I27) -> 0 | ... AF22: =SUM(AF23:AF27) -> 0 | AG22: =SUM(A22:AE22) -> 1
A23: - Hardware | B23: 1 | C23: 0 | D23: 0 | E23: 0 | F23: 0 | G23: 0 | H23: 0 | I23: 0 | J23: 0 | K23: 0 | L23: 0 | M23: 0 | N23: 0 | O23: 0 | P23: 0 | Q23: 0 | R23: 0 | S23: 0 | T23: 0 | U23: 0 | V23: 0 | W23: 0 | X23: 0 | Y23: 0 | Z23: 0 | AA23: 0 | AB23: 0 | AC23: 0 | AD23: 0 | AE23: 0 | AF23: 0 | AG23: =SUM(A23:AE23) -> 1
A24: - Add-ons | B24: 0 | C24: 0 | D24: 0 | E24: 0 | F24: 0 | G24: 0 | H24: 0 | I24: 0 | J24: 0 | K24: 0 | L24: 0 | M24: 0 | N24: 0 | O24: 0 | P24: 0 | Q24: 0 | R24: 0 | S24: 0 | T24: 0 | U24: 0 | V24: 0 | W24: 0 | X24: 0 | Y24: 0 | Z24: 0 | AA24: 0 | AB24: 0 | AC24: 0 | AD24: 0 | AE24: 0 | AF24: 0 | AG24: =SUM(A24:AE24) -> 0
A25: - Merch | B25: 0 | C25: 0 | D25: 0 | E25: 0 | F25: 0 | G25: 0 | H25: 0 | I25: 0 | J25: 0 | K25: 0 | L25: 0 | M25: 0 | N25: 0 | O25: 0 | P25: 0 | Q25: 0 | R25: 0 | S25: 0 | T25: 0 | U25: 0 | V25: 0 | W25: 0 | X25: 0 | Y25: 0 | Z25: 0 | AA25: 0 | AB25: 0 | AC25: 0 | AD25: 0 | AE25: 0 | AF25: 0 | AG25: =SUM(A25:AE25) -> 0
A26: - Seeds | B26: 0 | C26: 0 | D26: 0 | E26: 0 | F26: 0 | G26: 0 | H26: 0 | I26: 0 | J26: 0 | K26: 0 | L26: 0 | M26: 0 | N26: 0 | O26: 0 | P26: 0 | Q26: 0 | R26: 0 | S26: 0 | T26: 0 | U26: 0 | V26: 0 | W26: 0 | X26: 0 | Y26: 0 | Z26: 0 | AA26: 0 | AB26: 0 | AC26: 0 | AD26: 0 | AE26: 0 | AF26: 0 | AG26: =SUM(A26:AE26) -> 0
A27: - Yearly Pro Subscription | B27: 0 | C27: 0 | D27: 0 | E27: 0 | F27: 0 | G27: 0 | H27: 0 | I27: 0 | J27: 0 | K27: 0 | L27: 0 | M27: 0 | N27: 0 | O27: 0 | P27: 0 | Q27: 0 | R27: 0 | S27: 0 | T27: 0 | U27: 0 | V27: 0 | W27: 0 | X27: 0 | Y27: 0 | Z27: 0 | AA27: 0 | AB27: 0 | AC27: 0 | AD27: 0 | AE27: 0 | AF27: 0 | AG27: =SUM(A27:AE27) -> 0
A29: IndieGoGo Quantities Breakdown (New Products)
A30: Smart Bird Bath with Solar Roof and Water Pump | B30: 0 | C30: 0 | D30: 0 | E30: 0 | F30: 0 | G30: 0 | H30: 0 | I30: 0 | J30: 0 | K30: 0 | L30: 0 | M30: 0 | N30: 0 | O30: 0 | P30: 0 | Q30: 0 | R30: 0 | S30: 0 | T30: 0 | U30: 0 | V30: 0 | W30: 0 | X30: 0 | Y30: 0 | Z30: 0 | AA30: 0 | AB30: 0 | AC30: 0 | AD30: 0 | AE30: 0 | AF30: 0 | AG30: =SUM(A30:AE30) -> 0
A31: Smart Bird Bath without Solar Roof and Water Pump | B31: 0 | C31: 0 | D31: 0 | E31: 0 | F31: 0 | G31: 0 | H31: 0 | I31: 0 | J31: 0 | K31: 0 | L31: 0 | M31: 0 | N31: 0 | O31: 0 | P31: 0 | Q31: 0 | R31: 0 | S31: 0 | T31: 0 | U31: 0 | V31: 0 | W31: 0 | X31: 0 | Y31: 0 | Z31: 0 | AA31: 0 | AB31: 0 | AC31: 0 | AD31: 0 | AE31: 0 | AF31: 0 | AG31: =SUM(A31:AE31) -> 0
AG32: =SUM(A32:AE32) -> 0
A33: Bird Bath Housing without Solar Roof and Water Pump | B33: 0 | C33: 0 | D33: 0 | E33: 0 | F33: 0 | G33: 0 | H33: 0 | I33: 0 | J33: 0 | K33: 0 | L33: 0 | M33: 0 | N33: 0 | O33: 0 | P33: 0 | Q33: 0 | R33: 0 | S33: 0 | T33: 0 | U33: 0 | V33: 0 | W33: 0 | X33: 0 | Y33: 0 | Z33: 0 | AA33: 0 | AB33: 0 | AC33: 0 | AD33: 0 | AE33: 0 | AF33: 0 | AG33: =SUM(A33:AE33) -> 0
A34: Solar Roof and Water Pump | B34: 0 | C34: 0 | D34: 0 | E34: 0 | F34: 0 | G34: 0 | H34: 0 | I34: 0 | J34: 0 | K34: 0 | L34: 0 | M34: 0 | N34: 0 | O34: 0 | P34: 0 | Q34: 0 | R34: 0 | S34: 0 | T34: 0 | U34: 0 | V34: 0 | W34: 0 | X34: 0 | Y34: 0 | Z34: 0 | AA34: 0 | AB34: 0 | AC34: 0 | AD34: 0 | AE34: 0 | AF34: 0 | AG34: =SUM(A34:AE34) -> 0
A35: Pole Mounting System with Pollinator Base | B35: 0 | C35: 0 | D35: 0 | E35: 0 | F35: 0 | G35: 0 | H35: 0 | I35: 0 | J35: 0 | K35: 0 | L35: 0 | M35: 0 | N35: 0 | O35: 0 | P35: 0 | Q35: 0 | R35: 0 | S35: 0 | T35: 0 | U35: 0 | V35: 0 | W35: 0 | X35: 0 | Y35: 0 | Z35: 0 | AA35: 0 | AB35: 0 | AC35: 0 | AD35: 0 | AE35: 0 | AF35: 0 | AG35: =SUM(A35:AE35) -> 0
A37: IndieGoGo Quantities Breakdown (Other Products)
A38: Smart Bird Feeder with Solar Roof | B38: 0 | C38: 0 | D38: 0 | E38: 0 | F38: 0 | G38: 0 | H38: 0 | I38: 0 | J38: 0 | K38: 0 | L38: 0 | M38: 0 | N38: 0 | O38: 0 | P38: 0 | Q38: 0 | R38: 0 | S38: 0 | T38: 0 | U38: 0 | V38: 0 | W38: 0 | X38: 0 | Y38: 0 | Z38: 0 | AA38: 0 | AB38: 0 | AC38: 0 | AD38: 0 | AE38: 0 | AF38: 0 | AG38: =SUM(A38:AE38) -> 0
A39: Smart Bird Feeder | B39: 0 | C39: 0 | D39: 0 | E39: 0 | F39: 0 | G39: 0 | H39: 0 | I39: 0 | J39: 0 | K39: 0 | L39: 0 | M39: 0 | N39: 0 | O39: 0 | P39: 0 | Q39: 0 | R39: 0 | S39: 0 | T39: 0 | U39: 0 | V39: 0 | W39: 0 | X39: 0 | Y39: 0 | Z39: 0 | AA39: 0 | AB39: 0 | AC39: 0 | AD39: 0 | AE39: 0 | AF39: 0 | AG39: =SUM(A39:AE39) -> 0
A40: Smart Hummingbird Feeder | B40: 1 | C40: 0 | D40: 0 | E40: 0 | F40: 0 | G40: 0 | H40: 0 | I40: 0 | J40: 0 | K40: 0 | L40: 0 | M40: 0 | N40: 0 | O40: 0 | P40: 0 | Q40: 0 | R40: 0 | S40: 0 | T40: 0 | U40: 0 | V40: 0 | W40: 0 | X40: 0 | Y40: 0 | Z40: 0 | AA40: 0 | AB40: 0 | AC40: 0 | AD40: 0 | AE40: 0 | AF40: 0 | AG40: =SUM(A40:AE40) -> 1
A41: Smart Hummingbird Feeder with Solar Roof | B41: 0 | C41: 0 | D41: 0 | E41: 0 | F41: 0 | G41: 0 | H41: 0 | I41: 0 | J41: 0 | K41: 0 | L41: 0 | M41: 0 | N41: 0 | O41: 0 | P41: 0 | Q41: 0 | R41: 0 | S41: 0 | T41: 0 | U41: 0 | V41: 0 | W41: 0 | X41: 0 | Y41: 0 | Z41: 0 | AA41: 0 | AB41: 0 | AC41: 0 | AD41: 0 | AE41: 0 | AF41: 0 | AG41: =SUM(A41:AE41) -> 0
A43: Wall Mount | B43: 0 | C43: 0 | D43: 0 | E43: 0 | F43: 0 | G43: 0 | H43: 0 | I43: 0 | J43: 0 | K43: 0 | L43: 0 | M43: 0 | N43: 0 | O43: 0 | P43: 0 | Q43: 0 | R43: 0 | S43: 0 | T43: 0 | U43: 0 | V43: 0 | W43: 0 | X43: 0 | Y43: 0 | Z43: 0 | AA43: 0 | AB43: 0 | AC43: 0 | AD43: 0 | AE43: 0 | AF43: 0 | AG43: =SUM(A43:AE43) -> 0
A44: Suet Ball Holder | B44: 0 | C44: 0 | D44: 0 | E44: 0 | F44: 0 | G44: 0 | H44: 0 | I44: 0 | J44: 0 | K44: 0 | L44: 0 | M44: 0 | N44: 0 | O44: 0 | P44: 0 | Q44: 0 | R44: 0 | S44: 0 | T44: 0 | U44: 0 | V44: 0 | W44: 0 | X44: 0 | Y44: 0 | Z44: 0 | AA44: 0 | AB44: 0 | AC44: 0 | AD44: 0 | AE44: 0 | AF44: 0 | AG44: =SUM(A44:AE44) -> 0
A45: 3-in-1 Nutrition Set | B45: 0 | C45: 0 | D45: 0 | E45: 0 | F45: 0 | G45: 0 | H45: 0 | I45: 0 | J45: 0 | K45: 0 | L45: 0 | M45: 0 | N45: 0 | O45: 0 | P45: 0 | Q45: 0 | R45: 0 | S45: 0 | T45: 0 | U45: 0 | V45: 0 | W45: 0 | X45: 0 | Y45: 0 | Z45: 0 | AA45: 0 | AB45: 0 | AC45: 0 | AD45: 0 | AE45: 0 | AF45: 0 | AG45: =SUM(A45:AE45) -> 0
A46: Solar Roof | B46: 0 | C46: 0 | D46: 0 | E46: 0 | F46: 0 | G46: 0 | H46: 0 | I46: 0 | J46: 0 | K46: 0 | L46: 0 | M46: 0 | N46: 0 | O46: 0 | P46: 0 | Q46: 0 | R46: 0 | S46: 0 | T46: 0 | U46: 0 | V46: 0 | W46: 0 | X46: 0 | Y46: 0 | Z46: 0 | AA46: 0 | AB46: 0 | AC46: 0 | AD46: 0 | AE46: 0 | AF46: 0 | AG46: =SUM(A46:AE46) -> 0
A47: Perch Extender | B47: 0 | C47: 0 | D47: 0 | E47: 0 | F47: 0 | G47: 0 | H47: 0 | I47: 0 | J47: 0 | K47: 0 | L47: 0 | M47: 0 | N47: 0 | O47: 0 | P47: 0 | Q47: 0 | R47: 0 | S47: 0 | T47: 0 | U47: 0 | V47: 0 | W47: 0 | X47: 0 | Y47: 0 | Z47: 0 | AA47: 0 | AB47: 0 | AC47: 0 | AD47: 0 | AE47: 0 | AF47: 0 | AG47: =SUM(A47:AE47) -> 0
A48: Smart Hummingbird Feeder Solar Roof | B48: 0 | C48: 0 | D48: 0 | E48: 0 | F48: 0 | G48: 0 | H48: 0 | I48: 0 | J48: 0 | K48: 0 | L48: 0 | M48: 0 | N48: 0 | O48: 0 | P48: 0 | Q48: 0 | R48: 0 | S48: 0 | T48: 0 | U48: 0 | V48: 0 | W48: 0 | X48: 0 | Y48: 0 | Z48: 0 | AA48: 0 | AB48: 0 | AC48: 0 | AD48: 0 | AE48: 0 | AF48: 0 | AG48: =SUM(A48:AE48) -> 0
A49: Smart Hummingbird Feeder housing | B49: 0 | C49: 0 | D49: 0 | E49: 0 | F49: 0 | G49: 0 | H49: 0 | I49: 0 | J49: 0 | K49: 0 | L49: 0 | M49: 0 | N49: 0 | O49: 0 | P49: 0 | Q49: 0 | R49: 0 | S49: 0 | T49: 0 | U49: 0 | V49: 0 | W49: 0 | X49: 0 | Y49: 0 | Z49: 0 | AA49: 0 | AB49: 0 | AC49: 0 | AD49: 0 | AE49: 0 | AF49: 0 | AG49: =SUM(A49:AE49) -> 0
A51: Avian Choice | B51: 0 | C51: 0 | D51: 0 | E51: 0 | F51: 0 | G51: 0 | H51: 0 | I51: 0 | J51: 0 | K51: 0 | L51: 0 | M51: 0 | N51: 0 | O51: 0 | P51: 0 | Q51: 0 | R51: 0 | S51: 0 | T51: 0 | U51: 0 | V51: 0 | W51: 0 | X51: 0 | Y51: 0 | Z51: 0 | AA51: 0 | AB51: 0 | AC51: 0 | AD51: 0 | AE51: 0 | AF51: 0 | AG51: =SUM(A51:AE51) -> 0
... A56: 1 year Bird Buddy PRO subscription | B56: 0 | C56: 0 | D56: 0 | E56: 0 | F56: 0 | G56: 0 | H56: 0 | I56: 0 | J56: 0 | K56: 0 | L56: 0 | M56: 0 | N56: 0 | O56: 0 | P56: 0 | Q56: 0 | R56: 0 | S56: 0 | T56: 0 | U56: 0 | V56: 0 | W56: 0 | X56: 0 | Y56: 0 | Z56: 0 | AA56: 0 | AB56: 0 | AC56: 0 | AD56: 0 | AE56: 0 | AF56: 0 | AG56: =SUM(A56:AE56) -> 0

Sheet AMAZON US&CA - P&L
A1: OCTOBER | B1: 45931 | C1: 45932 | D1: 45933 | E1: 45934 | F1: 45935 | G1: 45936 | H1: 45937 | I1: 45938 | J1: 45939 | K1: 45940 | L1: 45941 | M1: 45942 | N1: 45943 | O1: 45944 | P1: 45945 | Q1: 45946 | R1: 45947 | S1: 45948 | T1: 45949 | U1: 45950 | V1: 45951 | W1: 45952 | X1: 45953 | Y1: 45954 | Z1: 45955 | AA1: 45956 | AB1: 45957 | AC1: 45958 | AD1: 45959 | AE1: 45960 | AF1: 45961
A2: DAY | B2: WED | C2: THU | D2: FRI | E2: SAT | F2: SUN | G2: MON | H2: TUE | I2: WED | J2: THU | K2: FRI | L2: SAT | M2: SUN | N2: MON | O2: TUE | P2: WED | Q2: THU | R2: FRI | S2: SAT | T2: SUN | U2: MON | V2: TUE | W2: WED | X2: THU | Y2: FRI | Z2: SAT | AA2: SUN | AB2: MON | AC2: TUE | AD2: WED | AE2: THU | AF2: FRI
A3: COMMENT
A4: Orders
A5: Amazon (market place) | B5: =Summary!B111 -> 18 | C5: =Summary!C111 -> 30 | D5: =Summary!D111 -> 22 | E5: =Summary!E111 -> 26 | F5: =Summary!F111 -> 27 | G5: =Summary!G111 -> 20 | H5: =Summary!H111 -> 164 | I5: =Summary!I111 -> 194 | ... AF5: =Summary!AF111 -> 20
A6: All | B6: =SUM(B5) -> 18 | C6: =SUM(C5) -> 30 | D6: =SUM(D5) -> 22 | E6: =SUM(E5) -> 26 | F6: =SUM(F5) -> 27 | G6: =SUM(G5) -> 20 | H6: =SUM(H5) -> 164 | I6: =SUM(I5) -> 194 | ... AF6: =SUM(AF5) -> 20 | AG6: =SUM(B6:AF6) -> 1075
A8: Revenue
A9: Amazon (market place) | B9: =Summary!B32 -> 4277.26 | C9: =Summary!C32 -> 8057.58 | D9: =Summary!D32 -> 5661.28 | E9: =Summary!E32 -> 6498.59 | F9: =Summary!F32 -> 7048.66 | G9: =Summary!G32 -> 4593.61 | H9: =Summary!H32 -> 41026.28 | I9: =Summary!I32 -> 46178.59 | ... AF9: =Summary!AF32 -> 5819.91
A10: All | B10: =SUM(B9) -> 4277.26 | C10: =SUM(C9) -> 8057.58 | D10: =SUM(D9) -> 5661.28 | E10: =SUM(E9) -> 6498.59 | F10: =SUM(F9) -> 7048.66 | G10: =SUM(G9) -> 4593.61 | H10: =SUM(H9) -> 41026.28 | I10: =SUM(I9) -> 46178.59 | ... AF10: =SUM(AF9) -> 5819.91 | AG10: =SUM(B10:AF10) -> 276792.21
A12: Media Cost
A13: Amazon Spend
A14: Amazon Platform Fee (8 %) | B14: =B9*'Data - P&L'!$C$48 -> 342.1808 | C14: =C9*'Data - P&L'!$C$48 -> 644.6064 | D14: =D9*'Data - P&L'!$C$48 -> 452.9024 | E14: =E9*'Data - P&L'!$C$48 -> 519.8872 | F14: =F9*'Data - P&L'!$C$48 -> 563.8928 | G14: =G9*'Data - P&L'!$C$48 -> 367.4888 | H14: =H9*'Data - P&L'!$C$48 -> 3282.1024 | I14: =I9*'Data - P&L'!$C$48 -> 3694.2872 | ... AF14: =AF9*'Data - P&L'!$C$48 -> 465.5928
A15: All | B15: =SUM(B13:B14) -> 342.1808 | C15: =SUM(C13:C14) -> 644.6064 | D15: =SUM(D13:D14) -> 452.9024 | E15: =SUM(E13:E14) -> 519.8872 | F15: =SUM(F13:F14) -> 563.8928 | G15: =SUM(G13:G14) -> 367.4888 | H15: =SUM(H13:H14) -> 3282.1024 | I15: =SUM(I13:I14) -> 3694.2872 | ... AF15: =SUM(AF13:AF14) -> 465.5928 | AG15: =SUM(B15:AF15) -> 22143.377
A19: Amazon Orders
A20: Hardware | B20: =Summary!B33 -> 3885 | C20: =Summary!C33 -> 7382 | D20: =Summary!D33 -> 5230 | E20: =Summary!E33 -> 5848 | F20: =Summary!F33 -> 6456 | G20: =Summary!G33 -> 4134 | H20: =Summary!H33 -> 37960.25 | I20: =Summary!I33 -> 42698 | ... AF20: =Summary!AF33 -> 5322 | AG20: =SUM(B20:AF20) -> 253983.94
A21: Addons | B21: =Summary!B34 -> 116 | C21: =Summary!C34 -> 165 | D21: =Summary!D34 -> 68 | E21: =Summary!E34 -> 185 | F21: =Summary!F34 -> 116 | G21: =Summary!G34 -> 136 | H21: =Summary!H34 -> 262 | I21: =Summary!I34 -> 427 | ... AF21: =Summary!AF34 -> 97 | AG21: =SUM(B21:AF21) -> 4249
A22: Tax | B22: =Summary!B35 -> 259.98 | C22: =Summary!C35 -> 506.09 | D22: =Summary!D35 -> 358.79 | E22: =Summary!E35 -> 458.68 | F22: =Summary!F35 -> 476.66 | G22: =Summary!G35 -> 319.12 | H22: =Summary!H35 -> 2777.09 | I22: =Summary!I35 -> 3037.62 | ... AF22: =Summary!AF35 -> 400.91 | AG22: =SUM(B22:AF22) -> 18342.32
A23: Shipping | B23: =Summary!B36 -> 11.79 | C23: =Summary!C36 -> 0 | D23: =Summary!D36 -> 0 | E23: =Summary!E36 -> 6.91 | F23: =Summary!F36 -> 0 | G23: =Summary!G36 -> 0 | H23: =Summary!H36 -> 8.98 | I23: =Summary!I36 -> 6.99 | ... AF23: =Summary!AF36 -> 0 | AG23: =SUM(B23:AF23) -> 77.76
A24: Gift Wrap Price | B24: =Summary!B37 -> 4.49 | C24: =Summary!C37 -> 4.49 | D24: =Summary!D37 -> 4.49 | E24: =Summary!E37 -> 0 | F24: =Summary!F37 -> 0 | G24: =Summary!G37 -> 4.49 | H24: =Summary!H37 -> 17.96 | I24: =Summary!I37 -> 8.98 | ... AF24: =Summary!AF37 -> 0 | AG24: =SUM(B24:AF24) -> 139.19
A25: All Amazon | B25: =SUM(B20:B24) -> 4277.26 | C25: =SUM(C20:C24) -> 8057.58 | D25: =SUM(D20:D24) -> 5661.28 | E25: =SUM(E20:E24) -> 6498.59 | F25: =SUM(F20:F24) -> 7048.66 | G25: =SUM(G20:G24) -> 4593.61 | H25: =SUM(H20:H24) -> 41026.28 | I25: =SUM(I20:I24) -> 46178.59 | ... AF25: =SUM(AF20:AF24) -> 5819.91 | AG25: =SUM(B25:AF25) -> 276792.21
A27: Units Sold (Gross)
A28: SKU 1 - Blue | B28: 0 | C28: 0 | D28: 0 | E28: 0 | F28: 0 | G28: 0 | H28: 0 | I28: 0 | J28: 0 | K28: 0 | L28: 0 | M28: 0 | N28: 0 | O28: 0 | P28: 0 | Q28: 0 | R28: 0 | S28: 0 | T28: 0 | U28: 0 | V28: 0 | W28: 0 | X28: 0 | Y28: 0 | Z28: 0 | AA28: 0 | AB28: 0 | AC28: 0 | AD28: 0 | AE28: 0 | AF28: 0 | AG28: =SUM(B28:AF28) -> 0
A29: SKU 2 - Yellow | B29: 0 | C29: 0 | D29: 0 | E29: 0 | F29: 0 | G29: 0 | H29: 0 | I29: 0 | J29: 0 | K29: 0 | L29: 0 | M29: 0 | N29: 0 | O29: 0 | P29: 0 | Q29: 0 | R29: 0 | S29: 0 | T29: 0 | U29: 0 | V29: 0 | W29: 0 | X29: 0 | Y29: 0 | Z29: 0 | AA29: 0 | AB29: 0 | AC29: 0 | AD29: 0 | AE29: 0 | AF29: 0 | AG29: =SUM(B29:AF29) -> 0
A30: SKU 3 - Blue w/ Solar | B30: 0 | C30: 0 | D30: 0 | E30: 1 | F30: 0 | G30: 1 | H30: 0 | I30: 0 | J30: 0 | K30: 0 | L30: 0 | M30: 1 | N30: 0 | O30: 0 | P30: 0 | Q30: 0 | R30: 1 | S30: 0 | T30: 1 | U30: 0 | V30: 0 | W30: 0 | X30: 0 | Y30: 0 | Z30: 0 | AA30: 0 | AB30: 0 | AC30: 0 | AD30: 0 | AE30: 1 | AF30: 0 | AG30: =SUM(B30:AF30) -> 6
A31: SKU 4 - Yellow w/ Solar | B31: 0 | C31: 0 | D31: 0 | E31: 0 | F31: 0 | G31: 0 | H31: 0 | I31: 0 | J31: 0 | K31: 0 | L31: 0 | M31: 0 | N31: 0 | O31: 0 | P31: 0 | Q31: 0 | R31: 0 | S31: 0 | T31: 0 | U31: 0 | V31: 0 | W31: 0 | X31: 0 | Y31: 0 | Z31: 0 | AA31: 0 | AB31: 0 | AC31: 0 | AD31: 0 | AE31: 0 | AF31: 0 | AG31: =SUM(B31:AF31) -> 0
A32: SKU 1 - Blue PRO | B32: 3 | C32: 0 | D32: 3 | E32: 0 | F32: 0 | G32: 2 | H32: 16 | I32: 30 | J32: 14 | K32: 3 | L32: 4 | M32: 2 | N32: 2 | O32: 3 | P32: 3 | Q32: 0 | R32: 1 | S32: 1 | T32: 0 | U32: 1 | V32: 1 | W32: 3 | X32: 3 | Y32: 2 | Z32: 1 | AA32: 1 | AB32: 1 | AC32: 0 | AD32: 1 | AE32: 0 | AF32: 1 | AG32: =SUM(B32:AF32) -> 102
A33: SKU 2 - Yellow PRO | B33: 0 | C33: 0 | D33: 0 | E33: 0 | F33: 0 | G33: 0 | H33: 0 | I33: 0 | J33: 0 | K33: 0 | L33: 0 | M33: 0 | N33: 0 | O33: 0 | P33: 0 | Q33: 0 | R33: 0 | S33: 0 | T33: 0 | U33: 0 | V33: 0 | W33: 0 | X33: 0 | Y33: 0 | Z33: 0 | AA33: 0 | AB33: 0 | AC33: 0 | AD33: 0 | AE33: 0 | AF33: 0 | AG33: =SUM(B33:AF33) -> 0
A34: SKU 3 - Blue w/ Solar PRO | B34: 11 | C34: 23 | D34: 13 | E34: 17 | F34: 12 | G34: 11 | H34: 130 | I34: 142 | J34: 83 | K34: 15 | L34: 22 | M34: 14 | N34: 15 | O34: 12 | P34: 2 | Q34: 6 | R34: 11 | S34: 20 | T34: 9 | U34: 14 | V34: 11 | W34: 12 | X34: 20 | Y34: 19 | Z34: 19 | AA34: 12 | AB34: 14 | AC34: 23 | AD34: 10 | AE34: 20 | AF34: 16 | AG34: =SUM(B34:AF34) -> 758
A35: SKU 4 - Yellow w/ Solar PRO | B35: 0 | C35: 0 | D35: 0 | E35: 0 | F35: 0 | G35: 0 | H35: 0 | I35: 0 | J35: 0 | K35: 0 | L35: 0 | M35: 0 | N35: 0 | O35: 0 | P35: 0 | Q35: 0 | R35: 0 | S35: 0 | T35: 0 | U35: 0 | V35: 0 | W35: 0 | X35: 0 | Y35: 0 | Z35: 0 | AA35: 0 | AB35: 0 | AC35: 0 | AD35: 0 | AE35: 0 | AF35: 0 | AG35: =SUM(B35:AF35) -> 0
A36: SUM (SKU 1 - SKU 4) | B36: =SUM(B28:B35) -> 14 | C36: =SUM(C28:C35) -> 23 | D36: =SUM(D28:D35) -> 16 | E36: =SUM(E28:E35) -> 18 | F36: =SUM(F28:F35) -> 12 | G36: =SUM(G28:G35) -> 14 | H36: =SUM(H28:H35) -> 146 | I36: =SUM(I28:I35) -> 172 | ... AF36: =SUM(AF28:AF35) -> 17 | AG36: =SUM(B36:AF36) -> 866
A38: SKU 5 - HBF PRO | B38: 0 | C38: 3 | D38: 0 | E38: 0 | F38: 0 | G38: 0 | H38: 1 | I38: 1 | J38: 0 | K38: 1 | L38: 1 | M38: 0 | N38: 1 | O38: 0 | P38: 0 | Q38: 0 | R38: 0 | S38: 0 | T38: 0 | U38: 0 | V38: 0 | W38: 0 | X38: 0 | Y38: 0 | Z38: 1 | AA38: 1 | AB38: 0 | AC38: 1 | AD38: 0 | AE38: 0 | AF38: 0 | AG38: =SUM(B38:AF38) -> 11
A39: SKU 6 - HBF w/ Solar PRO | B39: 1 | C39: 2 | D39: 4 | E39: 4 | F39: 12 | G39: 2 | H39: 22 | I39: 24 | J39: 10 | K39: 3 | L39: 3 | M39: 3 | N39: 2 | O39: 4 | P39: 1 | Q39: 1 | R39: 3 | S39: 0 | T39: 1 | U39: 2 | V39: 2 | W39: 2 | X39: 4 | Y39: 4 | Z39: 4 | AA39: 1 | AB39: 3 | AC39: 1 | AD39: 2 | AE39: 1 | AF39: 1 | AG39: =SUM(B39:AF39) -> 129
A40: SUM (SKU 5 - SKU 6) | B40: =SUM(B38:B39) -> 1 | C40: =SUM(C38:C39) -> 5 | D40: =SUM(D38:D39) -> 4 | E40: =SUM(E38:E39) -> 4 | F40: =SUM(F38:F39) -> 12 | G40: =SUM(G38:G39) -> 2 | H40: =SUM(H38:H39) -> 23 | I40: =SUM(I38:I39) -> 25 | ... AF40: =SUM(AF38:AF39) -> 1 | AG40: =SUM(B40:AF40) -> 140
A42: Wall Mount | B42: 4 | C42: 3 | D42: 1 | E42: 1 | F42: 3 | G42: 2 | H42: 5 | I42: 8 | J42: 5 | K42: 2 | L42: 6 | M42: 3 | N42: 2 | O42: 1 | P42: 3 | Q42: 2 | R42: 2 | S42: 2 | T42: 3 | U42: 3 | V42: 3 | W42: 0 | X42: 1 | Y42: 1 | Z42: 6 | AA42: 3 | AB42: 2 | AC42: 1 | AD42: 1 | AE42: 4 | AF42: 2 | AG42: =SUM(B42:AF42) -> 85
A43: Suet Ball Holder | B43: 0 | C43: 0 | D43: 0 | E43: 0 | F43: 0 | G43: 0 | H43: 0 | I43: 0 | J43: 0 | K43: 0 | L43: 0 | M43: 0 | N43: 0 | O43: 0 | P43: 0 | Q43: 0 | R43: 0 | S43: 0 | T43: 0 | U43: 0 | V43: 0 | W43: 0 | X43: 0 | Y43: 0 | Z43: 0 | AA43: 0 | AB43: 0 | AC43: 0 | AD43: 0 | AE43: 0 | AF43: 0 | AG43: =SUM(B43:AF43) -> 0
A44: 3-in-1 Nutrition Set - Blue | B44: 0 | C44: 2 | D44: 1 | E44: 4 | F44: 0 | G44: 2 | H44: 3 | I44: 5 | J44: 2 | K44: 2 | L44: 1 | M44: 0 | N44: 0 | O44: 2 | P44: 0 | Q44: 1 | R44: 0 | S44: 1 | T44: 0 | U44: 1 | V44: 1 | W44: 1 | X44: 3 | Y44: 1 | Z44: 3 | AA44: 3 | AB44: 2 | AC44: 1 | AD44: 1 | AE44: 1 | AF44: 1 | AG44: =SUM(B44:AF44) -> 45
A45: 3-in-1 Nutrition Set - Yellow | B45: 0 | C45: 0 | D45: 0 | E45: 0 | F45: 0 | G45: 0 | H45: 0 | I45: 0 | J45: 0 | K45: 0 | L45: 0 | M45: 0 | N45: 0 | O45: 0 | P45: 0 | Q45: 0 | R45: 0 | S45: 0 | T45: 0 | U45: 0 | V45: 0 | W45: 0 | X45: 0 | Y45: 0 | Z45: 0 | AA45: 0 | AB45: 0 | AC45: 0 | AD45: 0 | AE45: 0 | AF45: 0 | AG45: =SUM(B45:AF45) -> 0
A46: Solar Roof Single - Blue | B46: 0 | C46: 0 | D46: 0 | E46: 0 | F46: 0 | G46: 0 | H46: 0 | I46: 0 | J46: 0 | K46: 0 | L46: 0 | M46: 0 | N46: 0 | O46: 0 | P46: 0 | Q46: 0 | R46: 0 | S46: 0 | T46: 0 | U46: 0 | V46: 0 | W46: 0 | X46: 0 | Y46: 0 | Z46: 0 | AA46: 0 | AB46: 0 | AC46: 0 | AD46: 0 | AE46: 0 | AF46: 0 | AG46: =SUM(B46:AF46) -> 0
A47: Solar Roof Single - Yellow | B47: 0 | C47: 0 | D47: 0 | E47: 0 | F47: 0 | G47: 0 | H47: 0 | I47: 0 | J47: 0 | K47: 0 | L47: 0 | M47: 0 | N47: 0 | O47: 0 | P47: 0 | Q47: 0 | R47: 0 | S47: 0 | T47: 0 | U47: 0 | V47: 0 | W47: 0 | X47: 0 | Y47: 0 | Z47: 0 | AA47: 0 | AB47: 0 | AC47: 0 | AD47: 0 | AE47: 0 | AF47: 0 | AG47: =SUM(B47:AF47) -> 0
A48: Perch Extender - Blue | B48: 0 | C48: 0 | D48: 0 | E48: 0 | F48: 1 | G48: 0 | H48: 0 | I48: 0 | J48: 0 | K48: 0 | L48: 0 | M48: 0 | N48: 0 | O48: 0 | P48: 0 | Q48: 0 | R48: 0 | S48: 0 | T48: 0 | U48: 0 | V48: 0 | W48: 0 | X48: 0 | Y48: 0 | Z48: 0 | AA48: 0 | AB48: 0 | AC48: 0 | AD48: 0 | AE48: 0 | AF48: 0 | AG48: =SUM(B48:AF48) -> 1
A49: Perch Extender - Yellow | B49: 0 | C49: 0 | D49: 0 | E49: 0 | F49: 0 | G49: 0 | H49: 0 | I49: 0 | J49: 0 | K49: 0 | L49: 0 | M49: 0 | N49: 0 | O49: 0 | P49: 0 | Q49: 0 | R49: 0 | S49: 0 | T49: 0 | U49: 0 | V49: 0 | W49: 0 | X49: 0 | Y49: 0 | Z49: 0 | AA49: 0 | AB49: 0 | AC49: 0 | AD49: 0 | AE49: 0 | AF49: 0 | AG49: =SUM(B49:AF49) -> 0
A50: Nature Cam PRO | B50: 0 | C50: 0 | D50: 0 | E50: 0 | F50: 0 | G50: 0 | H50: 0 | I50: 0 | J50: 0 | K50: 0 | L50: 0 | M50: 0 | N50: 0 | O50: 0 | P50: 0 | Q50: 0 | R50: 0 | S50: 0 | T50: 0 | U50: 0 | V50: 0 | W50: 0 | X50: 0 | Y50: 0 | Z50: 0 | AA50: 0 | AB50: 0 | AC50: 0 | AD50: 0 | AE50: 0 | AF50: 0 | AG50: =SUM(B50:AF50) -> 0
A51: SUM (Add-ons) | B51: =SUM(B42:B50) -> 4 | C51: =SUM(C42:C50) -> 5 | D51: =SUM(D42:D50) -> 2 | E51: =SUM(E42:E50) -> 5 | F51: =SUM(F42:F50) -> 4 | G51: =SUM(G42:G50) -> 4 | H51: =SUM(H42:H50) -> 8 | I51: =SUM(I42:I50) -> 13 | ... AF51: =SUM(AF42:AF50) -> 3 | AG51: =SUM(B51:AF51) -> 131
A53: Revenue
A54: SKU 1 - Blue | B54: 0 | C54: 0 | D54: 0 | E54: 0 | F54: 0 | G54: 0 | H54: 0 | I54: 0 | J54: 0 | K54: 0 | L54: 0 | M54: 0 | N54: 0 | O54: 0 | P54: 0 | Q54: 0 | R54: 0 | S54: 0 | T54: 0 | U54: 0 | V54: 0 | W54: 0 | X54: 0 | Y54: 0 | Z54: 0 | AA54: 0 | AB54: 0 | AC54: 0 | AD54: 0 | AE54: 0 | AF54: 0
A55: SKU 2 - Yellow | B55: 0 | C55: 0 | D55: 0 | E55: 0 | F55: 0 | G55: 0 | H55: 0 | I55: 0 | J55: 0 | K55: 0 | L55: 0 | M55: 0 | N55: 0 | O55: 0 | P55: 0 | Q55: 0 | R55: 0 | S55: 0 | T55: 0 | U55: 0 | V55: 0 | W55: 0 | X55: 0 | Y55: 0 | Z55: 0 | AA55: 0 | AB55: 0 | AC55: 0 | AD55: 0 | AE55: 0 | AF55: 0
A56: SKU 3 - Blue w/ Solar | B56: 0 | C56: 0 | D56: 0 | E56: 199 | F56: 0 | G56: 199 | H56: 0 | I56: 0 | J56: 0 | K56: 0 | L56: 0 | M56: 199 | N56: 0 | O56: 0 | P56: 0 | Q56: 0 | R56: 199 | S56: 0 | T56: 199 | U56: 0 | V56: 0 | W56: 0 | X56: 0 | Y56: 0 | Z56: 0 | AA56: 0 | AB56: 0 | AC56: 0 | AD56: 0 | AE56: 199 | AF56: 0
A57: SKU 4 - Yellow w/ Solar | B57: 0 | C57: 0 | D57: 0 | E57: 0 | F57: 0 | G57: 0 | H57: 0 | I57: 0 | J57: 0 | K57: 0 | L57: 0 | M57: 0 | N57: 0 | O57: 0 | P57: 0 | Q57: 0 | R57: 0 | S57: 0 | T57: 0 | U57: 0 | V57: 0 | W57: 0 | X57: 0 | Y57: 0 | Z57: 0 | AA57: 0 | AB57: 0 | AC57: 0 | AD57: 0 | AE57: 0 | AF57: 0
A58: SKU 1 - Blue PRO | B58: 657 | C58: 0 | D58: 657 | E58: 0 | F58: 0 | G58: 438 | H58: 2976 | I58: 5580 | J58: 2736 | K58: 657 | L58: 876 | M58: 438 | N58: 438 | O58: 677 | P58: 717 | Q58: 0 | R58: 239 | S58: 239 | T58: 0 | U58: 239 | V58: 239 | W58: 717 | X58: 717 | Y58: 478 | Z58: 239 | AA58: 239 | AB58: 239 | AC58: 0 | AD58: 239 | AE58: 0 | AF58: 239
A59: SKU 2 - Yellow PRO | B59: 0 | C59: 0 | D59: 0 | E59: 0 | F59: 0 | G59: 0 | H59: 0 | I59: 0 | J59: 0 | K59: 0 | L59: 0 | M59: 0 | N59: 0 | O59: 0 | P59: 0 | Q59: 0 | R59: 0 | S59: 0 | T59: 0 | U59: 0 | V59: 0 | W59: 0 | X59: 0 | Y59: 0 | Z59: 0 | AA59: 0 | AB59: 0 | AC59: 0 | AD59: 0 | AE59: 0 | AF59: 0
A60: SKU 3 - Blue w/ Solar PRO | B60: 2959 | C60: 6187 | D60: 3497 | E60: 4573 | F60: 3228 | G60: 2959 | H60: 29307.25 | I60: 30995 | J60: 19085.65 | K60: 4035 | L60: 5918 | M60: 3766 | N60: 4035 | O60: 3288 | P60: 598 | Q60: 1794 | R60: 3289 | S60: 5980 | T60: 2691 | U60: 4186 | V60: 3289 | W60: 3588 | X60: 5980 | Y60: 5669.04 | Z60: 5681 | AA60: 3588 | AB60: 4186 | AC60: 6877 | AD60: 2990 | AE60: 5980 | AF60: 4784
A61: SKU 4 - Yellow w/ Solar PRO | B61: 0 | C61: 0 | D61: 0 | E61: 0 | F61: 0 | G61: 0 | H61: 0 | I61: 0 | J61: 0 | K61: 0 | L61: 0 | M61: 0 | N61: 0 | O61: 0 | P61: 0 | Q61: 0 | R61: 0 | S61: 0 | T61: 0 | U61: 0 | V61: 0 | W61: 0 | X61: 0 | Y61: 0 | Z61: 0 | AA61: 0 | AB61: 0 | AC61: 0 | AD61: 0 | AE61: 0 | AF61: 0
A62: SUM (SKU 1 - SKU 4) | B62: =SUM(B54:B61) -> 3616 | C62: =SUM(C54:C61) -> 6187 | D62: =SUM(D54:D61) -> 4154 | E62: =SUM(E54:E61) -> 4772 | F62: =SUM(F54:F61) -> 3228 | G62: =SUM(G54:G61) -> 3596 | H62: =SUM(H54:H61) -> 32283.25 | I62: =SUM(I54:I61) -> 36575 | ... AF62: =SUM(AF54:AF61) -> 5023 | AG62: =SUM(B62:AF62) -> 217086.94
A64: SKU 5 - HBF PRO | B64: 0 | C64: 657 | D64: 0 | E64: 0 | F64: 0 | G64: 0 | H64: 219 | I64: 219 | J64: 0 | K64: 219 | L64: 219 | M64: 0 | N64: 219 | O64: 0 | P64: 0 | Q64: 0 | R64: 0 | S64: 0 | T64: 0 | U64: 0 | V64: 0 | W64: 0 | X64: 0 | Y64: 0 | Z64: 239 | AA64: 239 | AB64: 0 | AC64: 239 | AD64: 0 | AE64: 0 | AF64: 0
A65: SKU 6 - HBF w/ Solar PRO | B65: 269 | C65: 538 | D65: 1076 | E65: 1076 | F65: 3228 | G65: 538 | H65: 5458 | I65: 5904 | J65: 2529 | K65: 807 | L65: 807 | M65: 807 | N65: 538 | O65: 1066 | P65: 299 | Q65: 259 | R65: 897 | S65: 0 | T65: 299 | U65: 598 | V65: 598 | W65: 598 | X65: 1156 | Y65: 1196 | Z65: 1196 | AA65: 299 | AB65: 897 | AC65: 299 | AD65: 598 | AE65: 299 | AF65: 299
A66: SUM (SKU 5 - SKU 6) | B66: =SUM(B64:B65) -> 269 | C66: =SUM(C64:C65) -> 1195 | D66: =SUM(D64:D65) -> 1076 | E66: =SUM(E64:E65) -> 1076 | F66: =SUM(F64:F65) -> 3228 | G66: =SUM(G64:G65) -> 538 | H66: =SUM(H64:H65) -> 5677 | I66: =SUM(I64:I65) -> 6123 | ... AF66: =SUM(AF64:AF65) -> 299 | AG66: =SUM(B66:AF66) -> 36897
A68: Wall Mount | B68: 116 | C68: 87 | D68: 29 | E68: 29 | F68: 87 | G68: 58 | H68: 145 | I68: 232 | J68: 145 | K68: 58 | L68: 174 | M68: 87 | N68: 58 | O68: 29 | P68: 87 | Q68: 58 | R68: 58 | S68: 58 | T68: 87 | U68: 87 | V68: 87 | W68: 0 | X68: 29 | Y68: 29 | Z68: 174 | AA68: 87 | AB68: 58 | AC68: 29 | AD68: 29 | AE68: 116 | AF68: 58
A69: Suet Ball Holder | B69: 0 | C69: 0 | D69: 0 | E69: 0 | F69: 0 | G69: 0 | H69: 0 | I69: 0 | J69: 0 | K69: 0 | L69: 0 | M69: 0 | N69: 0 | O69: 0 | P69: 0 | Q69: 0 | R69: 0 | S69: 0 | T69: 0 | U69: 0 | V69: 0 | W69: 0 | X69: 0 | Y69: 0 | Z69: 0 | AA69: 0 | AB69: 0 | AC69: 0 | AD69: 0 | AE69: 0 | AF69: 0
A70: 3-in-1 Nutrition Set - Blue | B70: 0 | C70: 78 | D70: 39 | E70: 156 | F70: 0 | G70: 78 | H70: 117 | I70: 195 | J70: 78 | K70: 78 | L70: 39 | M70: 0 | N70: 0 | O70: 78 | P70: 0 | Q70: 39 | R70: 0 | S70: 39 | T70: 0 | U70: 39 | V70: 39 | W70: 39 | X70: 117 | Y70: 39 | Z70: 117 | AA70: 117 | AB70: 78 | AC70: 39 | AD70: 39 | AE70: 39 | AF70: 39
A71: 3-in-1 Nutrition Set - Yellow | B71: 0 | C71: 0 | D71: 0 | E71: 0 | F71: 0 | G71: 0 | H71: 0 | I71: 0 | J71: 0 | K71: 0 | L71: 0 | M71: 0 | N71: 0 | O71: 0 | P71: 0 | Q71: 0 | R71: 0 | S71: 0 | T71: 0 | U71: 0 | V71: 0 | W71: 0 | X71: 0 | Y71: 0 | Z71: 0 | AA71: 0 | AB71: 0 | AC71: 0 | AD71: 0 | AE71: 0 | AF71: 0
A72: Solar Roof Single - Blue | B72: 0 | C72: 0 | D72: 0 | E72: 0 | F72: 0 | G72: 0 | H72: 0 | I72: 0 | J72: 0 | K72: 0 | L72: 0 | M72: 0 | N72: 0 | O72: 0 | P72: 0 | Q72: 0 | R72: 0 | S72: 0 | T72: 0 | U72: 0 | V72: 0 | W72: 0 | X72: 0 | Y72: 0 | Z72: 0 | AA72: 0 | AB72: 0 | AC72: 0 | AD72: 0 | AE72: 0 | AF72: 0
A73: Solar Roof Single - Yellow | B73: 0 | C73: 0 | D73: 0 | E73: 0 | F73: 0 | G73: 0 | H73: 0 | I73: 0 | J73: 0 | K73: 0 | L73: 0 | M73: 0 | N73: 0 | O73: 0 | P73: 0 | Q73: 0 | R73: 0 | S73: 0 | T73: 0 | U73: 0 | V73: 0 | W73: 0 | X73: 0 | Y73: 0 | Z73: 0 | AA73: 0 | AB73: 0 | AC73: 0 | AD73: 0 | AE73: 0 | AF73: 0
A74: Perch Extender - Blue | B74: 0 | C74: 0 | D74: 0 | E74: 0 | F74: 29 | G74: 0 | H74: 0 | I74: 0 | J74: 0 | K74: 0 | L74: 0 | M74: 0 | N74: 0 | O74: 0 | P74: 0 | Q74: 0 | R74: 0 | S74: 0 | T74: 0 | U74: 0 | V74: 0 | W74: 0 | X74: 0 | Y74: 0 | Z74: 0 | AA74: 0 | AB74: 0 | AC74: 0 | AD74: 0 | AE74: 0 | AF74: 0
A75: Perch Extender - Yellow | B75: 0 | C75: 0 | D75: 0 | E75: 0 | F75: 0 | G75: 0 | H75: 0 | I75: 0 | J75: 0 | K75: 0 | L75: 0 | M75: 0 | N75: 0 | O75: 0 | P75: 0 | Q75: 0 | R75: 0 | S75: 0 | T75: 0 | U75: 0 | V75: 0 | W75: 0 | X75: 0 | Y75: 0 | Z75: 0 | AA75: 0 | AB75: 0 | AC75: 0 | AD75: 0 | AE75: 0 | AF75: 0
A76: Nature Cam PRO | B76: 0 | C76: 0 | D76: 0 | E76: 0 | F76: 0 | G76: 0 | H76: 0 | I76: 0 | J76: 0 | K76: 0 | L76: 0 | M76: 0 | N76: 0 | O76: 0 | P76: 0 | Q76: 0 | R76: 0 | S76: 0 | T76: 0 | U76: 0 | V76: 0 | W76: 0 | X76: 0 | Y76: 0 | Z76: 0 | AA76: 0 | AB76: 0 | AC76: 0 | AD76: 0 | AE76: 0 | AF76: 0
A77: SUM (Add-ons) | B77: =SUM(B68:B76) -> 116 | C77: =SUM(C68:C76) -> 165 | D77: =SUM(D68:D76) -> 68 | E77: =SUM(E68:E76) -> 185 | F77: =SUM(F68:F76) -> 116 | G77: =SUM(G68:G76) -> 136 | H77: =SUM(H68:H76) -> 262 | I77: =SUM(I68:I76) -> 427 | ... AF77: =SUM(AF68:AF76) -> 97 | AG77: =SUM(B77:AF77) -> 4249
A79: Units Sold by country (Gross) - Only selling in US | AG79: =SUM(B79:AF79) -> 0
A80: Bird Buddy - Blue - AMAZON.US | AG80: =SUM(B80:AF80) -> 0
A81: Bird Buddy - Yellow - AMAZON.US | AG81: =SUM(B81:AF81) -> 0
A82: Bird Buddy with Solar Roof Blue - AMAZON.US | AG82: =SUM(B82:AF82) -> 0
A83: Bird Buddy with Solar Roof Yellow - AMAZON.US | AG83: =SUM(B83:AF83) -> 0
A84: Bird Buddy - AMAZON.EU | AG84: =SUM(B84:AF84) -> 0
A85: Bird Buddy with Solar Roof - AMAZON.EU | AG85: =SUM(B85:AF85) -> 0
A86: Bird Buddy - AMAZON (OTHER1) | AG86: =SUM(B86:AF86) -> 0
A87: Bird Buddy with Solar Roof - AMAZON (OTHER1) | AG87: =SUM(B87:AF87) -> 0
A88: All Bird Buddy | AG88: =SUM(B88:AF88) -> 0
A89: All Bird Buddy with Solar Roof | AG89: =SUM(B89:AF89) -> 0
AG90: =SUM(B90:AF90) -> 0
A91: Wall Mount - AMAZON.US | AG91: =SUM(B91:AF91) -> 0
A92: Fence Mount - AMAZON.US | AG92: =SUM(B92:AF92) -> 0
A93: Suet Ball Holder - AMAZON.US | AG93: =SUM(B93:AF93) -> 0
A94: 3-in-1 Nutrition Set - AMAZON.US | AG94: =SUM(B94:AF94) -> 0
A95: Solar Roof Single - AMAZON.US | AG95: =SUM(B95:AF95) -> 0
A96: All AMAZON.US | AG96: =SUM(B96:AF96) -> 0
AG97: =SUM(B97:AF97) -> 0
A98: Wall Mount - AMAZON.EU | AG98: =SUM(B98:AF98) -> 0
A99: Fence Mount - AMAZON.EU | AG99: =SUM(B99:AF99) -> 0
A100: Suet Ball Holder - AMAZON.EU | AG100: =SUM(B100:AF100) -> 0
A101: 3-in-1 Nutrition Set - AMAZON.EU | AG101: =SUM(B101:AF101) -> 0
A102: Solar Roof Single - AMAZON.EU | AG102: =SUM(B102:AF102) -> 0
A103: All AMAZON.EU | AG103: =SUM(B103:AF103) -> 0
AG104: =SUM(B104:AF104) -> 0
A105: Wall Mount - AMAZON (OTHER1) | AG105: =SUM(B105:AF105) -> 0
A106: Fence Mount - AMAZON (OTHER1) | AG106: =SUM(B106:AF106) -> 0
A107: Suet Ball Holder - AMAZON (OTHER1) | AG107: =SUM(B107:AF107) -> 0
A108: 3-in-1 Nutrition Set - AMAZON (OTHER1) | AG108: =SUM(B108:AF108) -> 0
A109: Solar Roof Single - AMAZON (OTHER1) | AG109: =SUM(B109:AF109) -> 0
A110: All AMAZON (OTHER1) | AG110: =SUM(B110:AF110) -> 0
AG111: =SUM(B111:AF111) -> 0
A112: Revenue by country (Gross) - Only selling in US | AG112: =SUM(B112:AF112) -> 0
...

Sheet AMAZON EU - P&L
A1: OCTOBER | B1: 45931 | C1: 45932 | D1: 45933 | E1: 45934 | F1: 45935 | G1: 45936 | H1: 45937 | I1: 45938 | J1: 45939 | K1: 45940 | L1: 45941 | M1: 45942 | N1: 45943 | O1: 45944 | P1: 45945 | Q1: 45946 | R1: 45947 | S1: 45948 | T1: 45949 | U1: 45950 | V1: 45951 | W1: 45952 | X1: 45953 | Y1: 45954 | Z1: 45955 | AA1: 45956 | AB1: 45957 | AC1: 45958 | AD1: 45959 | AE1: 45960 | AF1: 45961
A2: DAY | B2: WED | C2: THU | D2: FRI | E2: SAT | F2: SUN | G2: MON | H2: TUE | I2: WED | J2: THU | K2: FRI | L2: SAT | M2: SUN | N2: MON | O2: TUE | P2: WED | Q2: THU | R2: FRI | S2: SAT | T2: SUN | U2: MON | V2: TUE | W2: WED | X2: THU | Y2: FRI | Z2: SAT | AA2: SUN | AB2: MON | AC2: TUE | AD2: WED | AE2: THU | AF2: FRI
A3: COMMENT
A4: Orders
A5: Amazon UK | B5: =Summary!B115 -> 3 | C5: =Summary!C115 -> 2 | D5: =Summary!D115 -> 0 | E5: =Summary!E115 -> 2 | F5: =Summary!F115 -> 0 | G5: =Summary!G115 -> 0 | H5: =Summary!H115 -> 1 | I5: =Summary!I115 -> 0 | ... AF5: =Summary!AF115 -> 1
A6: Amazon FR | B6: =Summary!B116 -> 1 | C6: =Summary!C116 -> 3 | D6: =Summary!D116 -> 1 | E6: =Summary!E116 -> 0 | F6: =Summary!F116 -> 1 | G6: =Summary!G116 -> 0 | H6: =Summary!H116 -> 1 | I6: =Summary!I116 -> 0 | ... AF6: =Summary!AF116 -> 0
A7: Amazon GER | B7: =Summary!B117 -> 0 | C7: =Summary!C117 -> 0 | D7: =Summary!D117 -> 1 | E7: =Summary!E117 -> 0 | F7: =Summary!F117 -> 0 | G7: =Summary!G117 -> 0 | H7: =Summary!H117 -> 5 | I7: =Summary!I117 -> 6 | ... AF7: =Summary!AF117 -> 0
A8: All | B8: =SUM(B5:B7) -> 4 | C8: =SUM(C5:C7) -> 5 | D8: =SUM(D5:D7) -> 2 | E8: =SUM(E5:E7) -> 2 | F8: =SUM(F5:F7) -> 1 | G8: =SUM(G5:G7) -> 0 | H8: =SUM(H5:H7) -> 7 | I8: =SUM(I5:I7) -> 6 | ... AF8: =SUM(AF5:AF7) -> 1 | AG8: =SUM(B8:AF8) -> 109
A10: Revenue
A11: Amazon UK | B11: =Summary!B39 -> 136.8 | C11: =Summary!C39 -> 104.88 | D11: =Summary!D39 -> 0 | E11: =Summary!E39 -> 767.29 | F11: =Summary!F39 -> 0 | G11: =Summary!G39 -> 0 | H11: =Summary!H39 -> 45.41 | I11: =Summary!I39 -> 0 | ... AF11: =Summary!AF39 -> 44.5
A12: Amazon FR | B12: =Summary!B40 -> 365.55 | C12: =Summary!C40 -> 474.15 | D12: =Summary!D40 -> 40.32 | E12: =Summary!E40 -> 0 | F12: =Summary!F40 -> 381.38 | G12: =Summary!G40 -> 0 | H12: =Summary!H40 -> 383.6 | I12: =Summary!I40 -> 0 | ... AF12: =Summary!AF40 -> 0
A13: Amazon GER | B13: =Summary!B41 -> 0 | C13: =Summary!C41 -> 0 | D13: =Summary!D41 -> 379.95 | E13: =Summary!E41 -> 0 | F13: =Summary!F41 -> 0 | G13: =Summary!G41 -> 0 | H13: =Summary!H41 -> 1363.72 | I13: =Summary!I41 -> 1697.58 | ... AF13: =Summary!AF41 -> 0
A14: All | B14: =SUM(B11:B13) -> 502.35 | C14: =SUM(C11:C13) -> 579.03 | D14: =SUM(D11:D13) -> 420.27 | E14: =SUM(E11:E13) -> 767.29 | F14: =SUM(F11:F13) -> 381.38 | G14: =SUM(G11:G13) -> 0 | H14: =SUM(H11:H13) -> 1792.73 | I14: =SUM(I11:I13) -> 1697.58 | ... AF14: =SUM(AF11:AF13) -> 44.5 | AG14: =SUM(B14:AF14) -> 24906.76
A16: Media Cost
A17: Amazon EU Spend | B17: =SUM(B18:B20) -> 211.45 | C17: =SUM(C18:C20) -> 180.29 | D17: =SUM(D18:D20) -> 219.06 | E17: =SUM(E18:E20) -> 208.44 | F17: =SUM(F18:F20) -> 257.09 | G17: =SUM(G18:G20) -> 170.97 | H17: =SUM(H18:H20) -> 243.02 | I17: =SUM(I18:I20) -> 178.35 | ... AF17: =SUM(AF18:AF20) -> 283.32
A18: - Amazon UK Spend | B18: =Summary!B154 -> 103.91 | C18: =Summary!C154 -> 59.24 | D18: =Summary!D154 -> 36.87 | E18: =Summary!E154 -> 34.24 | F18: =Summary!F154 -> 38.27 | G18: =Summary!G154 -> 36.68 | H18: =Summary!H154 -> 49.12 | I18: =Summary!I154 -> 26.91 | ... AF18: =Summary!AF154 -> 87.24
A19: - Amazon FR Spend | B19: =Summary!B155 -> 57.2 | C19: =Summary!C155 -> 93.11 | D19: =Summary!D155 -> 88.68 | E19: =Summary!E155 -> 132.88 | F19: =Summary!F155 -> 133.27 | G19: =Summary!G155 -> 101.41 | H19: =Summary!H155 -> 106.09 | I19: =Summary!I155 -> 92.64 | ... AF19: =Summary!AF155 -> 90.11
A20: - Amazon GER Spend | B20: =Summary!B156 -> 50.34 | C20: =Summary!C156 -> 27.94 | D20: =Summary!D156 -> 93.51 | E20: =Summary!E156 -> 41.32 | F20: =Summary!F156 -> 85.55 | G20: =Summary!G156 -> 32.88 | H20: =Summary!H156 -> 87.81 | I20: =Summary!I156 -> 58.8 | ... AF20: =Summary!AF156 -> 105.97
A21: Amazon EU Platform Fee (? %)
A22: All | B22: =SUM(B18:B21) -> 211.45 | C22: =SUM(C18:C21) -> 180.29 | D22: =SUM(D18:D21) -> 219.06 | E22: =SUM(E18:E21) -> 208.44 | F22: =SUM(F18:F21) -> 257.09 | G22: =SUM(G18:G21) -> 170.97 | H22: =SUM(H18:H21) -> 243.02 | I22: =SUM(I18:I21) -> 178.35 | ... AF22: =SUM(AF18:AF21) -> 283.32 | AG22: =SUM(B22:AF22) -> 8425.82
A26: Amazon EU Orders
A27: Hardware | B27: =SUM('AMAZON UK, FR, GER - P&L'!B21,'AMAZON UK, FR, GER - P&L'!B207,'AMAZON UK, FR, GER - P&L'!B393) -> 319.17 | C27: =SUM('AMAZON UK, FR, GER - P&L'!C21,'AMAZON UK, FR, GER - P&L'!C207,'AMAZON UK, FR, GER - P&L'!C393) -> 326.96 | D27: =SUM('AMAZON UK, FR, GER - P&L'!D21,'AMAZON UK, FR, GER - P&L'!D207,'AMAZON UK, FR, GER - P&L'!D393) -> 327.63 | E27: =SUM('AMAZON UK, FR, GER - P&L'!E21,'AMAZON UK, FR, GER - P&L'!E207,'AMAZON UK, FR, GER - P&L'!E393) -> 657.68 | F27: =SUM('AMAZON UK, FR, GER - P&L'!F21,'AMAZON UK, FR, GER - P&L'!F207,'AMAZON UK, FR, GER - P&L'!F393) -> 326.9 | G27: =SUM('AMAZON UK, FR, GER - P&L'!G21,'AMAZON UK, FR, GER - P&L'!G207,'AMAZON UK, FR, GER - P&L'!G393) -> 0 | H27: =SUM('AMAZON UK, FR, GER - P&L'!H21,'AMAZON UK, FR, GER - P&L'!H207,'AMAZON UK, FR, GER - P&L'!H393) -> 1452.31 | I27: =SUM('AMAZON UK, FR, GER - P&L'!I21,'AMAZON UK, FR, GER - P&L'!I207,'AMAZON UK, FR, GER - P&L'!I393) -> 1381.95 | ... AF27: =SUM('AMAZON UK, FR, GER - P&L'!AF21,'AMAZON UK, FR, GER - P&L'!AF207,'AMAZON UK, FR, GER - P&L'!AF393) -> 0 | AG27: =SUM(B27:AF27) -> 19599.93
A28: Addons | B28: =SUM('AMAZON UK, FR, GER - P&L'!B22,'AMAZON UK, FR, GER - P&L'!B208,'AMAZON UK, FR, GER - P&L'!B394) -> 117.27 | C28: =SUM('AMAZON UK, FR, GER - P&L'!C22,'AMAZON UK, FR, GER - P&L'!C208,'AMAZON UK, FR, GER - P&L'!C394) -> 149.25 | D28: =SUM('AMAZON UK, FR, GER - P&L'!D22,'AMAZON UK, FR, GER - P&L'!D208,'AMAZON UK, FR, GER - P&L'!D394) -> 34.35 | E28: =SUM('AMAZON UK, FR, GER - P&L'!E22,'AMAZON UK, FR, GER - P&L'!E208,'AMAZON UK, FR, GER - P&L'!E394) -> 0 | F28: =SUM('AMAZON UK, FR, GER - P&L'!F22,'AMAZON UK, FR, GER - P&L'!F208,'AMAZON UK, FR, GER - P&L'!F394) -> 0 | G28: =SUM('AMAZON UK, FR, GER - P&L'!G22,'AMAZON UK, FR, GER - P&L'!G208,'AMAZON UK, FR, GER - P&L'!G394) -> 0 | H28: =SUM('AMAZON UK, FR, GER - P&L'!H22,'AMAZON UK, FR, GER - P&L'!H208,'AMAZON UK, FR, GER - P&L'!H394) -> 72.74 | I28: =SUM('AMAZON UK, FR, GER - P&L'!I22,'AMAZON UK, FR, GER - P&L'!I208,'AMAZON UK, FR, GER - P&L'!I394) -> 79.77 | ... AF28: =SUM('AMAZON UK, FR, GER - P&L'!AF22,'AMAZON UK, FR, GER - P&L'!AF208,'AMAZON UK, FR, GER - P&L'!AF394) -> 38.15 | AG28: =SUM(B28:AF28) -> 1620.83
A29: Tax | B29: =SUM('AMAZON UK, FR, GER - P&L'!B23,'AMAZON UK, FR, GER - P&L'!B209,'AMAZON UK, FR, GER - P&L'!B395) -> 65.91 | C29: =SUM('AMAZON UK, FR, GER - P&L'!C23,'AMAZON UK, FR, GER - P&L'!C209,'AMAZON UK, FR, GER - P&L'!C395) -> 74.48 | D29: =SUM('AMAZON UK, FR, GER - P&L'!D23,'AMAZON UK, FR, GER - P&L'!D209,'AMAZON UK, FR, GER - P&L'!D395) -> 58.29 | E29: =SUM('AMAZON UK, FR, GER - P&L'!E23,'AMAZON UK, FR, GER - P&L'!E209,'AMAZON UK, FR, GER - P&L'!E395) -> 109.61 | F29: =SUM('AMAZON UK, FR, GER - P&L'!F23,'AMAZON UK, FR, GER - P&L'!F209,'AMAZON UK, FR, GER - P&L'!F395) -> 54.48 | G29: =SUM('AMAZON UK, FR, GER - P&L'!G23,'AMAZON UK, FR, GER - P&L'!G209,'AMAZON UK, FR, GER - P&L'!G395) -> 0 | H29: =SUM('AMAZON UK, FR, GER - P&L'!H23,'AMAZON UK, FR, GER - P&L'!H209,'AMAZON UK, FR, GER - P&L'!H395) -> 264.19 | I29: =SUM('AMAZON UK, FR, GER - P&L'!I23,'AMAZON UK, FR, GER - P&L'!I209,'AMAZON UK, FR, GER - P&L'!I395) -> 235.86 | ... AF29: =SUM('AMAZON UK, FR, GER - P&L'!AF23,'AMAZON UK, FR, GER - P&L'!AF209,'AMAZON UK, FR, GER - P&L'!AF395) -> 6.35 | AG29: =SUM(B29:AF29) -> 3541.16
A30: Shipping | B30: =SUM('AMAZON UK, FR, GER - P&L'!B24,'AMAZON UK, FR, GER - P&L'!B210,'AMAZON UK, FR, GER - P&L'!B396) -> 0 | C30: =SUM('AMAZON UK, FR, GER - P&L'!C24,'AMAZON UK, FR, GER - P&L'!C210,'AMAZON UK, FR, GER - P&L'!C396) -> 28.34 | D30: =SUM('AMAZON UK, FR, GER - P&L'!D24,'AMAZON UK, FR, GER - P&L'!D210,'AMAZON UK, FR, GER - P&L'!D396) -> 0 | E30: =SUM('AMAZON UK, FR, GER - P&L'!E24,'AMAZON UK, FR, GER - P&L'!E210,'AMAZON UK, FR, GER - P&L'!E396) -> 0 | F30: =SUM('AMAZON UK, FR, GER - P&L'!F24,'AMAZON UK, FR, GER - P&L'!F210,'AMAZON UK, FR, GER - P&L'!F396) -> 0 | G30: =SUM('AMAZON UK, FR, GER - P&L'!G24,'AMAZON UK, FR, GER - P&L'!G210,'AMAZON UK, FR, GER - P&L'!G396) -> 0 | H30: =SUM('AMAZON UK, FR, GER - P&L'!H24,'AMAZON UK, FR, GER - P&L'!H210,'AMAZON UK, FR, GER - P&L'!H396) -> 0 | I30: =SUM('AMAZON UK, FR, GER - P&L'!I24,'AMAZON UK, FR, GER - P&L'!I210,'AMAZON UK, FR, GER - P&L'!I396) -> 0 | ... AF30: =SUM('AMAZON UK, FR, GER - P&L'!AF24,'AMAZON UK, FR, GER - P&L'!AF210,'AMAZON UK, FR, GER - P&L'!AF396) -> 0 | AG30: =SUM(B30:AF30) -> 133.39
A31: Gift Wrap Price | B31: =SUM('AMAZON UK, FR, GER - P&L'!B25,'AMAZON UK, FR, GER - P&L'!B211,'AMAZON UK, FR, GER - P&L'!B397) -> 0 | C31: =SUM('AMAZON UK, FR, GER - P&L'!C25,'AMAZON UK, FR, GER - P&L'!C211,'AMAZON UK, FR, GER - P&L'!C397) -> 0 | D31: =SUM('AMAZON UK, FR, GER - P&L'!D25,'AMAZON UK, FR, GER - P&L'!D211,'AMAZON UK, FR, GER - P&L'!D397) -> 0 | E31: =SUM('AMAZON UK, FR, GER - P&L'!E25,'AMAZON UK, FR, GER - P&L'!E211,'AMAZON UK, FR, GER - P&L'!E397) -> 0 | F31: =SUM('AMAZON UK, FR, GER - P&L'!F25,'AMAZON UK, FR, GER - P&L'!F211,'AMAZON UK, FR, GER - P&L'!F397) -> 0 | G31: =SUM('AMAZON UK, FR, GER - P&L'!G25,'AMAZON UK, FR, GER - P&L'!G211,'AMAZON UK, FR, GER - P&L'!G397) -> 0 | H31: =SUM('AMAZON UK, FR, GER - P&L'!H25,'AMAZON UK, FR, GER - P&L'!H211,'AMAZON UK, FR, GER - P&L'!H397) -> 3.49 | I31: =SUM('AMAZON UK, FR, GER - P&L'!I25,'AMAZON UK, FR, GER - P&L'!I211,'AMAZON UK, FR, GER - P&L'!I397) -> 0 | ... AF31: =SUM('AMAZON UK, FR, GER - P&L'!AF25,'AMAZON UK, FR, GER - P&L'!AF211,'AMAZON UK, FR, GER - P&L'!AF397) -> 0 | AG31: =SUM(B31:AF31) -> 11.45
A32: All Amazon EU | B32: =SUM(B27:B31) -> 502.35 | C32: =SUM(C27:C31) -> 579.03 | D32: =SUM(D27:D31) -> 420.27 | E32: =SUM(E27:E31) -> 767.29 | F32: =SUM(F27:F31) -> 381.38 | G32: =SUM(G27:G31) -> 0 | H32: =SUM(H27:H31) -> 1792.73 | I32: =SUM(I27:I31) -> 1697.58 | ... AF32: =SUM(AF27:AF31) -> 44.5 | AG32: =SUM(B32:AF32) -> 24906.76
A34: Units Sold (Gross)
A35: SKU 1 - Blue | B35: =SUM('AMAZON UK, FR, GER - P&L'!B29,'AMAZON UK, FR, GER - P&L'!B215,'AMAZON UK, FR, GER - P&L'!B401) -> 0 | C35: =SUM('AMAZON UK, FR, GER - P&L'!C29,'AMAZON UK, FR, GER - P&L'!C215,'AMAZON UK, FR, GER - P&L'!C401) -> 0 | D35: =SUM('AMAZON UK, FR, GER - P&L'!D29,'AMAZON UK, FR, GER - P&L'!D215,'AMAZON UK, FR, GER - P&L'!D401) -> 0 | E35: =SUM('AMAZON UK, FR, GER - P&L'!E29,'AMAZON UK, FR, GER - P&L'!E215,'AMAZON UK, FR, GER - P&L'!E401) -> 0 | F35: =SUM('AMAZON UK, FR, GER - P&L'!F29,'AMAZON UK, FR, GER - P&L'!F215,'AMAZON UK, FR, GER - P&L'!F401) -> 0 | G35: =SUM('AMAZON UK, FR, GER - P&L'!G29,'AMAZON UK, FR, GER - P&L'!G215,'AMAZON UK, FR, GER - P&L'!G401) -> 0 | H35: =SUM('AMAZON UK, FR, GER - P&L'!H29,'AMAZON UK, FR, GER - P&L'!H215,'AMAZON UK, FR, GER - P&L'!H401) -> 0 | I35: =SUM('AMAZON UK, FR, GER - P&L'!I29,'AMAZON UK, FR, GER - P&L'!I215,'AMAZON UK, FR, GER - P&L'!I401) -> 0 | ... AF35: =SUM('AMAZON UK, FR, GER - P&L'!AF29,'AMAZON UK, FR, GER - P&L'!AF215,'AMAZON UK, FR, GER - P&L'!AF401) -> 0 | AG35: =SUM(B35:AF35) -> 0
A36: SKU 2 - Yellow | B36: =SUM('AMAZON UK, FR, GER - P&L'!B30,'AMAZON UK, FR, GER - P&L'!B216,'AMAZON UK, FR, GER - P&L'!B402) -> 0 | C36: =SUM('AMAZON UK, FR, GER - P&L'!C30,'AMAZON UK, FR, GER - P&L'!C216,'AMAZON UK, FR, GER - P&L'!C402) -> 0 | D36: =SUM('AMAZON UK, FR, GER - P&L'!D30,'AMAZON UK, FR, GER - P&L'!D216,'AMAZON UK, FR, GER - P&L'!D402) -> 0 | E36: =SUM('AMAZON UK, FR, GER - P&L'!E30,'AMAZON UK, FR, GER - P&L'!E216,'AMAZON UK, FR, GER - P&L'!E402) -> 0 | F36: =SUM('AMAZON UK, FR, GER - P&L'!F30,'AMAZON UK, FR, GER - P&L'!F216,'AMAZON UK, FR, GER - P&L'!F402) -> 0 | G36: =SUM('AMAZON UK, FR, GER - P&L'!G30,'AMAZON UK, FR, GER - P&L'!G216,'AMAZON UK, FR, GER - P&L'!G402) -> 0 | H36: =SUM('AMAZON UK, FR, GER - P&L'!H30,'AMAZON UK, FR, GER - P&L'!H216,'AMAZON UK, FR, GER - P&L'!H402) -> 0 | I36: =SUM('AMAZON UK, FR, GER - P&L'!I30,'AMAZON UK, FR, GER - P&L'!I216,'AMAZON UK, FR, GER - P&L'!I402) -> 0 | ... AF36: =SUM('AMAZON UK, FR, GER - P&L'!AF30,'AMAZON UK, FR, GER - P&L'!AF216,'AMAZON UK, FR, GER - P&L'!AF402) -> 0 | AG36: =SUM(B36:AF36) -> 0
A37: SKU 3 - Blue w/ Solar | B37: =SUM('AMAZON UK, FR, GER - P&L'!B31,'AMAZON UK, FR, GER - P&L'!B217,'AMAZON UK, FR, GER - P&L'!B403) -> 0 | C37: =SUM('AMAZON UK, FR, GER - P&L'!C31,'AMAZON UK, FR, GER - P&L'!C217,'AMAZON UK, FR, GER - P&L'!C403) -> 0 | D37: =SUM('AMAZON UK, FR, GER - P&L'!D31,'AMAZON UK, FR, GER - P&L'!D217,'AMAZON UK, FR, GER - P&L'!D403) -> 0 | E37: =SUM('AMAZON UK, FR, GER - P&L'!E31,'AMAZON UK, FR, GER - P&L'!E217,'AMAZON UK, FR, GER - P&L'!E403) -> 0 | F37: =SUM('AMAZON UK, FR, GER - P&L'!F31,'AMAZON UK, FR, GER - P&L'!F217,'AMAZON UK, FR, GER - P&L'!F403) -> 0 | G37: =SUM('AMAZON UK, FR, GER - P&L'!G31,'AMAZON UK, FR, GER - P&L'!G217,'AMAZON UK, FR, GER - P&L'!G403) -> 0 | H37: =SUM('AMAZON UK, FR, GER - P&L'!H31,'AMAZON UK, FR, GER - P&L'!H217,'AMAZON UK, FR, GER - P&L'!H403) -> 0 | I37: =SUM('AMAZON UK, FR, GER - P&L'!I31,'AMAZON UK, FR, GER - P&L'!I217,'AMAZON UK, FR, GER - P&L'!I403) -> 0 | ... AF37: =SUM('AMAZON UK, FR, GER - P&L'!AF31,'AMAZON UK, FR, GER - P&L'!AF217,'AMAZON UK, FR, GER - P&L'!AF403) -> 0 | AG37: =SUM(B37:AF37) -> 0
A38: SKU 4 - Yellow w/ Solar | B38: =SUM('AMAZON UK, FR, GER - P&L'!B32,'AMAZON UK, FR, GER - P&L'!B218,'AMAZON UK, FR, GER - P&L'!B404) -> 0 | C38: =SUM('AMAZON UK, FR, GER - P&L'!C32,'AMAZON UK, FR, GER - P&L'!C218,'AMAZON UK, FR, GER - P&L'!C404) -> 0 | D38: =SUM('AMAZON UK, FR, GER - P&L'!D32,'AMAZON UK, FR, GER - P&L'!D218,'AMAZON UK, FR, GER - P&L'!D404) -> 0 | E38: =SUM('AMAZON UK, FR, GER - P&L'!E32,'AMAZON UK, FR, GER - P&L'!E218,'AMAZON UK, FR, GER - P&L'!E404) -> 0 | F38: =SUM('AMAZON UK, FR, GER - P&L'!F32,'AMAZON UK, FR, GER - P&L'!F218,'AMAZON UK, FR, GER - P&L'!F404) -> 0 | G38: =SUM('AMAZON UK, FR, GER - P&L'!G32,'AMAZON UK, FR, GER - P&L'!G218,'AMAZON UK, FR, GER - P&L'!G404) -> 0 | H38: =SUM('AMAZON UK, FR, GER - P&L'!H32,'AMAZON UK, FR, GER - P&L'!H218,'AMAZON UK, FR, GER - P&L'!H404) -> 0 | I38: =SUM('AMAZON UK, FR, GER - P&L'!I32,'AMAZON UK, FR, GER - P&L'!I218,'AMAZON UK, FR, GER - P&L'!I404) -> 0 | ... AF38: =SUM('AMAZON UK, FR, GER - P&L'!AF32,'AMAZON UK, FR, GER - P&L'!AF218,'AMAZON UK, FR, GER - P&L'!AF404) -> 0 | AG38: =SUM(B38:AF38) -> 0
A39: SKU 1 - Blue PRO | B39: =SUM('AMAZON UK, FR, GER - P&L'!B33,'AMAZON UK, FR, GER - P&L'!B219,'AMAZON UK, FR, GER - P&L'!B405) -> 0 | C39: =SUM('AMAZON UK, FR, GER - P&L'!C33,'AMAZON UK, FR, GER - P&L'!C219,'AMAZON UK, FR, GER - P&L'!C405) -> 0 | D39: =SUM('AMAZON UK, FR, GER - P&L'!D33,'AMAZON UK, FR, GER - P&L'!D219,'AMAZON UK, FR, GER - P&L'!D405) -> 0 | E39: =SUM('AMAZON UK, FR, GER - P&L'!E33,'AMAZON UK, FR, GER - P&L'!E219,'AMAZON UK, FR, GER - P&L'!E405) -> 1 | F39: =SUM('AMAZON UK, FR, GER - P&L'!F33,'AMAZON UK, FR, GER - P&L'!F219,'AMAZON UK, FR, GER - P&L'!F405) -> 0 | G39: =SUM('AMAZON UK, FR, GER - P&L'!G33,'AMAZON UK, FR, GER - P&L'!G219,'AMAZON UK, FR, GER - P&L'!G405) -> 0 | H39: =SUM('AMAZON UK, FR, GER - P&L'!H33,'AMAZON UK, FR, GER - P&L'!H219,'AMAZON UK, FR, GER - P&L'!H405) -> 0 | I39: =SUM('AMAZON UK, FR, GER - P&L'!I33,'AMAZON UK, FR, GER - P&L'!I219,'AMAZON UK, FR, GER - P&L'!I405) -> 0 | ... AF39: =SUM('AMAZON UK, FR, GER - P&L'!AF33,'AMAZON UK, FR, GER - P&L'!AF219,'AMAZON UK, FR, GER - P&L'!AF405) -> 0 | AG39: =SUM(B39:AF39) -> 6
