Workbook
Name zsupermetrics_ru0GDtbZzDLHQOQtJJ6K08MvUDyyp7: #REF!
Name zsupermetrics_DQl8lUbpTRu3fayaJJi7lVfOGKjNU4: 'Data - P&L'!$A$3:$A$4
Name zsupermetrics_BioPyGBzcBsy60UCQmPcTuFReEmghI: 'Data - P&L'!$B$2:$B$3
Name zsupermetrics_refreshAll: SupermetricsQueries!$H$5
Name zsupermetrics_n3GtLgiKpTmd2pYmQNMuq6TPD0qE0b: #REF!
Name zsupermetrics_refreshAllSilent: SupermetricsQueries!$H$6
Name zsupermetrics_Mgms9p0QzysYvrIhnsKACeVBVxfIEO: #REF!
Name zsupermetrics_Mgms9p0QzysYvrIhnsKACeVBVxfIEO: 'Data - P&L'!$A$2:$A$3
Name zsupermetrics_forceRefresh: SupermetricsQueries!$H$4
Name zsupermetrics_wbYMmT0YL9bAN0yhimW0ziPFnia9Dx: #REF!
Name zsupermetrics_iNpyVy90bWCI0yUaFQpxOtzWMa6sW4: #REF!
Name zsupermetrics_xwoIpANxRm908eDp5oKTwQpEI8gvD4: #REF!
Name zsupermetrics_n3GtLgiKpTmd2pYmQNMuq6TPD0qE0b: 'Data - P&L'!$B$4:$B$5
Name rdataslayer_42b112e4e4be4305bb4c1be75e2dd549: 'Data - P&L'!$B$2:$C$3
Name zsupermetrics_9i4W4hgd80uRpQLMeX0eRnESN8gjyv: #REF!
Name zsupermetrics_5bmwtOpHUbSYmDMeuCPkrxaojTprPP: #REF!
Name rdataslayer_3753ddf3234e496aa261974a0222e193: 'Data - P&L'!$H$2:$I$2
Name zsupermetrics_SGBxROnInO9rFyh3H7j2Lldx0Bdc5v: #REF!
Name zsupermetrics_pxuhRTEmIU93xSgKclyxajD0fCZ6rF: #REF!
Name zsupermetrics_ru0GDtbZzDLHQOQtJJ6K08MvUDyyp7: 'Data - P&L'!$B$4:$B$5
Name zsupermetrics_qWp7V908pNEYMtfv8QZvSTeDnBAHOU: 'Data - P&L'!$B$5:$C$13
Name rdataslayer_4a0f150f4f2f4e4f85c890c75b7a1fa4: #REF!
Name zsupermetrics_8xojRjNDjo2jWHGDWjFEhflhyIq3Hq: #REF!
Name zsupermetrics_HgZqhorObHOtZHuyJjpmyYaEPoYntx: #REF!
Name zsupermetrics_YsFuuYtr8vOdNXCCPiFJIO38NP4b2T: #REF!
Name zsupermetrics_DQl8lUbpTRu3fayaJJi7lVfOGKjNU4: #REF!
Name zsupermetrics_YVuzfmsfdurz7Ldl84Rfns8oka6LsS: #REF!
Name zsupermetrics_4VkB7ij7WO0JjKBEgvjB2GHjSy2Egm: #REF!
Name zsupermetrics_9i4W4hgd80uRpQLMeX0eRnESN8gjyv: 'Data - P&L'!$C$13
Name zsupermetrics_lx4cNai7gT6tH4j08ZRkI21Qlpjioi: #REF!
Name rdataslayer_d70e473bcafe40a3aa834ce157fb2ba3: #REF!
Name zsupermetrics_NugLlrQxlKiqhxQae8EFpITBm1pLCj: 'Data - P&L'!$B$6:$C$13
Name zsupermetrics_8xojRjNDjo2jWHGDWjFEhflhyIq3Hq: Summary!$K$12:$K$48
Name zsupermetrics_FEamnpN5FsVYF0RtUTXAwunZ388Tkc: Forecast!$A$113:$C$141
Name rdataslayer_3753ddf3234e496aa261974a0222e193: #REF!
Name zsupermetrics_iNpyVy90bWCI0yUaFQpxOtzWMa6sW4: 'Data - P&L'!$A$2:$A$3
Name rdataslayer_4a0f150f4f2f4e4f85c890c75b7a1fa4: 'Data - P&L'!$D$2:$E$3
Name zsupermetrics_BioPyGBzcBsy60UCQmPcTuFReEmghI: #REF!
Name zsupermetrics_qWp7V908pNEYMtfv8QZvSTeDnBAHOU: #REF!
Name zsupermetrics_wbYMmT0YL9bAN0yhimW0ziPFnia9Dx: 'Data - P&L'!$A$2:$A$3
Name zsupermetrics_4VkB7ij7WO0JjKBEgvjB2GHjSy2Egm: 'Data - P&L'!$B$4:$C$10
Name zsupermetrics_lx4cNai7gT6tH4j08ZRkI21Qlpjioi: 'Data - P&L'!$B$4:$C$13
Name rdataslayer_42b112e4e4be4305bb4c1be75e2dd549: #REF!
Name rdataslayer_adf57e64065742daa5b4161161b1c3ca: #REF!
Name rdataslayer_adf57e64065742daa5b4161161b1c3ca: 'Data - P&L'!$B$4:$D$5
Name zsupermetrics_NugLlrQxlKiqhxQae8EFpITBm1pLCj: #REF!
Name zsupermetrics_xwoIpANxRm908eDp5oKTwQpEI8gvD4: #REF!
Name zsupermetrics_YsFuuYtr8vOdNXCCPiFJIO38NP4b2T: 'Data - P&L'!$B$4:$C$13
Name rdataslayer_d70e473bcafe40a3aa834ce157fb2ba3: 'Data - P&L'!$C$8:$D$9
Name zsupermetrics_HgZqhorObHOtZHuyJjpmyYaEPoYntx: 'Data - P&L'!$B$4:$B$5

Sheet Data_forecast_2024
B1: 45809 | C1: 45810 | D1: 45811 | E1: 45812 | F1: 45813 | G1: 45814 | H1: 45815 | I1: 45816 | J1: 45817 | K1: 45818 | L1: 45819 | M1: 45820 | N1: 45821 | O1: 45822 | P1: 45823 | Q1: 45824 | R1: 45825 | S1: 45826 | T1: 45827 | U1: 45828 | V1: 45829 | W1: 45830 | X1: 45831 | Y1: 45832 | Z1: 45833 | AA1: 45834 | AB1: 45835 | AC1: 45836 | AD1: 45837 | AE1: 45838 | AF1: 45839
A2: Quantities | B2: ='DTC - P&L'!B59+'AMAZON US&CA - P&L'!B38+'WALMART - P&L'!B25+#REF!+#REF!+'Digital Marketplaces - P&L'!B21+'COSTCO - P&L'!B19 -> #REF! | C2: ='DTC - P&L'!C59+'AMAZON US&CA - P&L'!C38+'WALMART - P&L'!C25+#REF!+#REF!+'Digital Marketplaces - P&L'!C21+'COSTCO - P&L'!C19 -> #REF! | D2: ='DTC - P&L'!D59+'AMAZON US&CA - P&L'!D38+'WALMART - P&L'!D25+#REF!+#REF!+'Digital Marketplaces - P&L'!D21+'COSTCO - P&L'!D19 -> #REF! | E2: ='DTC - P&L'!E59+'AMAZON US&CA - P&L'!E38+'WALMART - P&L'!E25+#REF!+#REF!+'Digital Marketplaces - P&L'!E21+'COSTCO - P&L'!E19 -> #REF! | F2: ='DTC - P&L'!F59+'AMAZON US&CA - P&L'!F38+'WALMART - P&L'!F25+#REF!+#REF!+'Digital Marketplaces - P&L'!F21+'COSTCO - P&L'!F19 -> #REF! | G2: ='DTC - P&L'!G59+'AMAZON US&CA - P&L'!G38+'WALMART - P&L'!G25+#REF!+#REF!+'Digital Marketplaces - P&L'!G21+'COSTCO - P&L'!G19 -> #REF! | H2: ='DTC - P&L'!H59+'AMAZON US&CA - P&L'!H38+'WALMART - P&L'!H25+#REF!+#REF!+'Digital Marketplaces - P&L'!H21+'COSTCO - P&L'!H19 -> #REF! | I2: ='DTC - P&L'!I59+'AMAZON US&CA - P&L'!I38+'WALMART - P&L'!I25+#REF!+#REF!+'Digital Marketplaces - P&L'!I21+'COSTCO - P&L'!I19 -> #REF! | ... AF2: ='DTC - P&L'!AF59+'AMAZON US&CA - P&L'!AF38+'WALMART - P&L'!AF25+#REF!+#REF!+'Digital Marketplaces - P&L'!AF21+'COSTCO - P&L'!AF19 -> #REF!
A3: Sales | B3: =Summary!B48+Summary!B86+Summary!B78+Summary!B60 -> 146142.12 | C3: =Summary!C48+Summary!C86+Summary!C78+Summary!C60 -> 258926.64 | D3: =Summary!D48+Summary!D86+Summary!D78+Summary!D60 -> 311083.39 | E3: =Summary!E48+Summary!E86+Summary!E78+Summary!E60 -> 290191.27 | F3: =Summary!F48+Summary!F86+Summary!F78+Summary!F60 -> 246664.67 | G3: =Summary!G48+Summary!G86+Summary!G78+Summary!G60 -> 195495.82 | H3: =Summary!H48+Summary!H86+Summary!H78+Summary!H60 -> 156845.36 | I3: =Summary!I48+Summary!I86+Summary!I78+Summary!I60 -> 132492.52 | ... AF3: =Summary!AF48+Summary!AF86+Summary!AF78+Summary!AF60 -> 94639.443

Sheet WALMART_Data_forecast_2024
B1: 45809 | C1: 45810 | D1: 45811 | E1: 45812 | F1: 45813 | G1: 45814 | H1: 45815 | I1: 45816 | J1: 45817 | K1: 45818 | L1: 45819 | M1: 45820 | N1: 45821 | O1: 45822 | P1: 45823 | Q1: 45824 | R1: 45825 | S1: 45826 | T1: 45827 | U1: 45828 | V1: 45829 | W1: 45830 | X1: 45831 | Y1: 45832 | Z1: 45833 | AA1: 45834 | AB1: 45835 | AC1: 45836 | AD1: 45837 | AE1: 45838 | AF1: 45839
A2: Quantities | B2: ='WALMART - P&L'!B25 | C2: ='WALMART - P&L'!C25 | D2: ='WALMART - P&L'!D25 | E2: ='WALMART - P&L'!E25 | F2: ='WALMART - P&L'!F25 | G2: ='WALMART - P&L'!G25 | H2: ='WALMART - P&L'!H25 | I2: ='WALMART - P&L'!I25 | ... AF2: ='WALMART - P&L'!AF25
A3: Sales | B3: =Summary!B68 -> 1187.59 | C3: =Summary!C68 -> 1218.97 | D3: =Summary!D68 -> 1927.97 | E3: =Summary!E68 -> 2718.28 | F3: =Summary!F68 -> 1100.4 | G3: =Summary!G68 -> 669.03 | H3: =Summary!H68 -> 339.18 | I3: =Summary!I68 -> 0 | ... AF3: =Summary!AF68 -> 38.96

Sheet COSTCO_Data_forecast_2024
B1: 45809 | C1: 45749 | D1: 45750 | E1: 45751 | F1: 45752 | G1: 45753 | H1: 45754 | I1: 45755 | J1: 45756 | K1: 45757 | L1: 45758 | M1: 45759 | N1: 45760 | O1: 45761 | P1: 45762 | Q1: 45763 | R1: 45764 | S1: 45765 | T1: 45766 | U1: 45767 | V1: 45768 | W1: 45769 | X1: 45770 | Y1: 45771 | Z1: 45772 | AA1: 45773 | AB1: 45774 | AC1: 45775 | AD1: 45776 | AE1: 45777 | AF1: 45778
A2: Quantities | B2: ='COSTCO - P&L'!B19 -> #REF! | C2: ='COSTCO - P&L'!C19 -> #REF! | D2: ='COSTCO - P&L'!D19 -> #REF! | E2: ='COSTCO - P&L'!E19 -> #REF! | F2: ='COSTCO - P&L'!F19 -> #REF! | G2: ='COSTCO - P&L'!G19 -> #REF! | H2: ='COSTCO - P&L'!H19 -> #REF! | I2: ='COSTCO - P&L'!I19 -> #REF! | ... AF2: ='COSTCO - P&L'!AF19 -> #REF!
A3: Sales | B3: =Summary!B60 -> 0 | C3: =Summary!C60 -> 0 | D3: =Summary!D60 -> 0 | E3: =Summary!E60 -> 0 | F3: =Summary!F60 -> 0 | G3: =Summary!G60 -> 0 | H3: =Summary!H60 -> 0 | I3: =Summary!I60 -> 0 | ... AF3: =Summary!AF60 -> 0

Sheet DM_Data_forecast_2024
B1: 45809 | C1: 45810 | D1: 45811 | E1: 45812 | F1: 45813 | G1: 45814 | H1: 45815 | I1: 45816 | J1: 45817 | K1: 45818 | L1: 45819 | M1: 45820 | N1: 45821 | O1: 45822 | P1: 45823 | Q1: 45824 | R1: 45825 | S1: 45826 | T1: 45827 | U1: 45828 | V1: 45829 | W1: 45830 | X1: 45831 | Y1: 45832 | Z1: 45833 | AA1: 45834 | AB1: 45835 | AC1: 45836 | AD1: 45837 | AE1: 45838 | AF1: 45839
A2: Quantities | B2: =#REF!+#REF!+'Digital Marketplaces - P&L'!B21 -> #REF! | C2: =#REF!+#REF!+'Digital Marketplaces - P&L'!C21 -> #REF! | D2: =#REF!+#REF!+'Digital Marketplaces - P&L'!D21 -> #REF! | E2: =#REF!+#REF!+'Digital Marketplaces - P&L'!E21 -> #REF! | F2: =#REF!+#REF!+'Digital Marketplaces - P&L'!F21 -> #REF! | G2: =#REF!+#REF!+'Digital Marketplaces - P&L'!G21 -> #REF! | H2: =#REF!+#REF!+'Digital Marketplaces - P&L'!H21 -> #REF! | I2: =#REF!+#REF!+'Digital Marketplaces - P&L'!I21 -> #REF! | ... AF2: =#REF!+#REF!+'Digital Marketplaces - P&L'!AF21 -> #REF!
A3: Sales | B3: =Summary!B78 -> 0 | C3: =Summary!C78 -> 0 | D3: =Summary!D78 -> 0 | E3: =Summary!E78 -> 0 | F3: =Summary!F78 -> 0 | G3: =Summary!G78 -> 0 | H3: =Summary!H78 -> 0 | I3: =Summary!I78 -> 0 | ... AF3: =Summary!AF78 -> 0

Sheet AMAZON_Data_Forecast
A1: US | B1: 45809 | C1: 45810 | D1: 45811 | E1: 45812 | F1: 45813 | G1: 45814 | H1: 45815 | I1: 45816 | J1: 45817 | K1: 45818 | L1: 45819 | M1: 45820 | N1: 45821 | O1: 45822 | P1: 45823 | Q1: 45824 | R1: 45825 | S1: 45826 | T1: 45827 | U1: 45828 | V1: 45829 | W1: 45830 | X1: 45831 | Y1: 45832 | Z1: 45833 | AA1: 45834 | AB1: 45835 | AC1: 45836 | AD1: 45837 | AE1: 45838 | AF1: 45839
A2: Quantities | B2: ='AMAZON US&CA - P&L'!B38+'AMAZON US&CA - P&L'!B64 -> 0 | C2: ='AMAZON US&CA - P&L'!C38+'AMAZON US&CA - P&L'!C64 -> 0 | D2: ='AMAZON US&CA - P&L'!D38+'AMAZON US&CA - P&L'!D64 -> 0 | E2: ='AMAZON US&CA - P&L'!E38+'AMAZON US&CA - P&L'!E64 -> 0 | F2: ='AMAZON US&CA - P&L'!F38+'AMAZON US&CA - P&L'!F64 -> 0 | G2: ='AMAZON US&CA - P&L'!G38+'AMAZON US&CA - P&L'!G64 -> 0 | H2: ='AMAZON US&CA - P&L'!H38+'AMAZON US&CA - P&L'!H64 -> 0 | I2: ='AMAZON US&CA - P&L'!I38+'AMAZON US&CA - P&L'!I64 -> 0 | ... AF2: ='AMAZON US&CA - P&L'!AF38+'AMAZON US&CA - P&L'!AF64 -> 0
A3: Sales | B3: =Summary!B33 -> 41264.95 | C3: =Summary!C33 -> 59108.3 | D3: =Summary!D33 -> 106923.09 | E3: =Summary!E33 -> 100980.97 | F3: =Summary!F33 -> 90308.03 | G3: =Summary!G33 -> 64294.29 | H3: =Summary!H33 -> 59341.85 | I3: =Summary!I33 -> 38530.94 | ... AF3: =Summary!AF33 -> 18005.48
A5: UK
A6: Quantities | B6: ='AMAZON UK, FR, GER - P&L'!B37 | C6: ='AMAZON UK, FR, GER - P&L'!C37 | D6: ='AMAZON UK, FR, GER - P&L'!D37 | E6: ='AMAZON UK, FR, GER - P&L'!E37 | F6: ='AMAZON UK, FR, GER - P&L'!F37 | G6: ='AMAZON UK, FR, GER - P&L'!G37 | H6: ='AMAZON UK, FR, GER - P&L'!H37 | I6: ='AMAZON UK, FR, GER - P&L'!I37 | ... AF6: ='AMAZON UK, FR, GER - P&L'!AF37
A7: Sales | B7: =Summary!B40 -> 45.94 | C7: =Summary!C40 -> 0 | D7: =Summary!D40 -> 45.97 | E7: =Summary!E40 -> 0 | F7: =Summary!F40 -> 0 | G7: =Summary!G40 -> 45.99 | H7: =Summary!H40 -> 0 | I7: =Summary!I40 -> 0 | ... AF7: =Summary!AF40 -> 45.51
A9: FR
A10: Quantities | B10: ='AMAZON UK, FR, GER - P&L'!B313 | C10: ='AMAZON UK, FR, GER - P&L'!C313 | D10: ='AMAZON UK, FR, GER - P&L'!D313 | E10: ='AMAZON UK, FR, GER - P&L'!E313 | F10: ='AMAZON UK, FR, GER - P&L'!F313 | G10: ='AMAZON UK, FR, GER - P&L'!G313 | H10: ='AMAZON UK, FR, GER - P&L'!H313 | I10: ='AMAZON UK, FR, GER - P&L'!I313 | ... AF10: ='AMAZON UK, FR, GER - P&L'!AF313
A11: Sales | B11: =Summary!B41 -> 0 | C11: =Summary!C41 -> 0 | D11: =Summary!D41 -> 0 | E11: =Summary!E41 -> 39.55 | F11: =Summary!F41 -> 32.88 | G11: =Summary!G41 -> 0 | H11: =Summary!H41 -> 0 | I11: =Summary!I41 -> 0 | ... AF11: =Summary!AF41 -> 238.57
A13: GR
A14: Quantities | B14: ='AMAZON UK, FR, GER - P&L'!B589 | C14: ='AMAZON UK, FR, GER - P&L'!C589 | D14: ='AMAZON UK, FR, GER - P&L'!D589 | E14: ='AMAZON UK, FR, GER - P&L'!E589 | F14: ='AMAZON UK, FR, GER - P&L'!F589 | G14: ='AMAZON UK, FR, GER - P&L'!G589 | H14: ='AMAZON UK, FR, GER - P&L'!H589 | I14: ='AMAZON UK, FR, GER - P&L'!I589 | ... AF14: ='AMAZON UK, FR, GER - P&L'!AF589
A15: Sales | B15: =Summary!B42 -> 0 | C15: =Summary!C42 -> 0 | D15: =Summary!D42 -> 28.6 | E15: =Summary!E42 -> 0 | F15: =Summary!F42 -> 232.93 | G15: =Summary!G42 -> 0 | H15: =Summary!H42 -> 473.42 | I15: =Summary!I42 -> 240.08 | ... AF15: =Summary!AF42 -> 271.13
A17: Spent US | B17: =Summary!B143 -> 2300.7 | C17: =Summary!C143 -> 2354.42 | D17: =Summary!D143 -> 2354.52 | E17: =Summary!E143 -> 7873.04 | F17: =Summary!F143 -> 6577.65 | G17: =Summary!G143 -> 2322.01 | H17: =Summary!H143 -> 2339.76 | I17: =Summary!I143 -> 2097.77 | ... AF17: =Summary!AF143 -> 1435
A18: Spent UK | B18: =Summary!B145 -> 0 | C18: =Summary!C145 -> 0 | D18: =Summary!D145 -> 0 | E18: =Summary!E145 -> 0 | F18: =Summary!F145 -> 0 | G18: =Summary!G145 -> 0 | H18: =Summary!H145 -> 0 | I18: =Summary!I145 -> 0 | ... AF18: =Summary!AF145 -> 0
A19: Spent FR | B19: =Summary!B146 -> 6.25 | C19: =Summary!C146 -> 19.46 | D19: =Summary!D146 -> 16.34 | E19: =Summary!E146 -> 2.74 | F19: =Summary!F146 -> 4.92 | G19: =Summary!G146 -> 10.67 | H19: =Summary!H146 -> 1.53 | I19: =Summary!I146 -> 7.79 | ... AF19: =Summary!AF146 -> 0
A20: Spent GR | B20: =Summary!B147 -> 31.45 | C20: =Summary!C147 -> 42.96 | D20: =Summary!D147 -> 42.18 | E20: =Summary!E147 -> 26.3 | F20: =Summary!F147 -> 58.73 | G20: =Summary!G147 -> 31.34 | H20: =Summary!H147 -> 38.23 | I20: =Summary!I147 -> 26.98 | ... AF20: =Summary!AF147 -> 0

Sheet DTC_Data_Forecast
B1: 45809 | C1: 45810 | D1: 45811 | E1: 45812 | F1: 45813 | G1: 45814 | H1: 45815 | I1: 45816 | J1: 45817 | K1: 45818 | L1: 45819 | M1: 45820 | N1: 45821 | O1: 45822 | P1: 45823 | Q1: 45824 | R1: 45825 | S1: 45826 | T1: 45827 | U1: 45828 | V1: 45829 | W1: 45830 | X1: 45831 | Y1: 45832 | Z1: 45833 | AA1: 45834 | AB1: 45835 | AC1: 45836 | AD1: 45837 | AE1: 45838 | AF1: 45839
A2: Quantities | B2: ='DTC - P&L'!B59 -> 0 | C2: ='DTC - P&L'!C59 -> 0 | D2: ='DTC - P&L'!D59 -> 0 | E2: ='DTC - P&L'!E59 -> 0 | F2: ='DTC - P&L'!F59 -> 0 | G2: ='DTC - P&L'!G59 -> 0 | H2: ='DTC - P&L'!H59 -> 0 | I2: ='DTC - P&L'!I59 -> 0 | ... AF2: ='DTC - P&L'!AF59 -> 0
A3: Sales | B3: =Summary!B12-Summary!B26 -> 75206.646 | C3: =Summary!C12-Summary!C26 -> 117883.78 | D3: =Summary!D12-Summary!D26 -> 152220.85 | E3: =Summary!E12-Summary!E26 -> 142321.68 | F3: =Summary!F12-Summary!F26 -> 98217.24 | G3: =Summary!G12-Summary!G26 -> 91914.923 | H3: =Summary!H12-Summary!H26 -> 66930.777 | I3: =Summary!I12-Summary!I26 -> 60827.036 | ... AF3: =Summary!AF12-Summary!AF26 -> 30594.326
A5: DTC US
A6: Quantities | B6: ='DTC US&CA - P&L'!B31 -> 223 | C6: ='DTC US&CA - P&L'!C31 -> 354 | D6: ='DTC US&CA - P&L'!D31 -> 471 | E6: ='DTC US&CA - P&L'!E31 -> 442 | F6: ='DTC US&CA - P&L'!F31 -> 307 | G6: ='DTC US&CA - P&L'!G31 -> 235 | H6: ='DTC US&CA - P&L'!H31 -> 172 | I6: ='DTC US&CA - P&L'!I31 -> 151 | ... AF6: ='DTC US&CA - P&L'!AF31 -> 66
A7: Sales | B7: =Summary!B13 -> 73595.13 | C7: =Summary!C13 -> 117045.27 | D7: =Summary!D13 -> 151596.87 | E7: =Summary!E13 -> 139862.07 | F7: =Summary!F13 -> 97382.03 | G7: =Summary!G13 -> 91094.02 | H7: =Summary!H13 -> 66230.16 | I7: =Summary!I13 -> 59880.27 | ... AF7: =Summary!AF13 -> 28618.5
A9: DTC EU
A10: Quantities | B10: ='DTC EU - P&L'!B31 | C10: ='DTC EU - P&L'!C31 | D10: ='DTC EU - P&L'!D31 | E10: ='DTC EU - P&L'!E31 | F10: ='DTC EU - P&L'!F31 | G10: ='DTC EU - P&L'!G31 | H10: ='DTC EU - P&L'!H31 | I10: ='DTC EU - P&L'!I31 | ... AF10: ='DTC EU - P&L'!AF31
A11: Sales | B11: =Summary!B20 -> 1178.8734 | C11: =Summary!C20 -> 405.7888 | D11: =Summary!D20 -> 307.19612 | E11: =Summary!E20 -> 1702.1809 | F11: =Summary!F20 -> 322.5898 | G11: =Summary!G20 -> 292.25637 | H11: =Summary!H20 -> 584.5411 | I11: =Summary!I20 -> 653.1553 | ... AF11: =Summary!AF20 -> 1545.8027
A14: Spent US | B14: =Summary!B135+Summary!B138+Summary!B140+Summary!B141 -> 12872.53 | C14: =Summary!C135+Summary!C138+Summary!C140+Summary!C141 -> 26007.25 | D14: =Summary!D135+Summary!D138+Summary!D140+Summary!D141 -> 33843.71 | E14: =Summary!E135+Summary!E138+Summary!E140+Summary!E141 -> 29660.27 | F14: =Summary!F135+Summary!F138+Summary!F140+Summary!F141 -> 27931.62 | G14: =Summary!G135+Summary!G138+Summary!G140+Summary!G141 -> 26780 | H14: =Summary!H135+Summary!H138+Summary!H140+Summary!H141 -> 23159.38 | I14: =Summary!I135+Summary!I138+Summary!I140+Summary!I141 -> 16753.57 | ... AF14: =Summary!AF135+Summary!AF138+Summary!AF140+Summary!AF141 -> 4950.28
A15: Spent EU | B15: =Summary!B154 -> 0.47 | C15: =Summary!C154 -> 0 | D15: =Summary!D154 -> 1.14 | E15: =Summary!E154 -> 1 | F15: =Summary!F154 -> 0 | G15: =Summary!G154 -> 0 | H15: =Summary!H154 -> 0 | I15: =Summary!I154 -> 0.91 | ... AF15: =Summary!AF154 -> 0
A17: DTC US
A18: Quantities | B18: ='DTC US&CA - P&L'!B31+'DTC US&CA - P&L'!B36 -> 300 | C18: ='DTC US&CA - P&L'!C31+'DTC US&CA - P&L'!C36 -> 478 | D18: ='DTC US&CA - P&L'!D31+'DTC US&CA - P&L'!D36 -> 616 | E18: ='DTC US&CA - P&L'!E31+'DTC US&CA - P&L'!E36 -> 562 | F18: ='DTC US&CA - P&L'!F31+'DTC US&CA - P&L'!F36 -> 389 | G18: ='DTC US&CA - P&L'!G31+'DTC US&CA - P&L'!G36 -> 336 | H18: ='DTC US&CA - P&L'!H31+'DTC US&CA - P&L'!H36 -> 240 | I18: ='DTC US&CA - P&L'!I31+'DTC US&CA - P&L'!I36 -> 217 | ... AF18: ='DTC US&CA - P&L'!AF31+'DTC US&CA - P&L'!AF36 -> 104
A19: Sales w/o renewals | B19: =Summary!B13 -> 73595.13 | C19: =Summary!C13 -> 117045.27 | D19: =Summary!D13 -> 151596.87 | E19: =Summary!E13 -> 139862.07 | F19: =Summary!F13 -> 97382.03 | G19: =Summary!G13 -> 91094.02 | H19: =Summary!H13 -> 66230.16 | I19: =Summary!I13 -> 59880.27 | ... AF19: =Summary!AF13 -> 28618.5
A20: Sales with renewals | B20: =Summary!B13+Summary!B27 -> 86764.56 | C20: =Summary!C13+Summary!C27 -> 178074.13 | D20: =Summary!D13+Summary!D27 -> 179866.79 | E20: =Summary!E13+Summary!E27 -> 164614.81 | F20: =Summary!F13+Summary!F27 -> 137221.74 | G20: =Summary!G13+Summary!G27 -> 113105.29 | H20: =Summary!H13+Summary!H27 -> 82074.58 | I20: =Summary!I13+Summary!I27 -> 76359.62 | ... AF20: =Summary!AF13+Summary!AF27 -> 54215.33

Sheet Summary
B1: 46143 | C1: 46144 | D1: 46145 | E1: 46146 | F1: 46147 | G1: 46148 | H1: 46149 | I1: 46150 | J1: 46151 | K1: 46152 | L1: 46153 | M1: 46154 | N1: 46155 | O1: 46156 | P1: 46157 | Q1: 46158 | R1: 46159 | S1: 46160 | T1: 46161 | U1: 46162 | V1: 46163 | W1: 46164 | X1: 46165 | Y1: 46166 | Z1: 46167 | AA1: 46168 | AB1: 46169 | AC1: 46170 | AD1: 46171 | AE1: 46172 | AF1: 46173
B2: FRI | C2: SAT | D2: SUN | E2: MON | F2: TUE | G2: WED | H2: THU | I2: FRI | J2: SAT | K2: SUN | L2: MON | M2: TUE | N2: WED | O2: THU | P2: FRI | Q2: SAT | R2: SUN | S2: MON | T2: TUE | U2: WED | V2: THU | W2: FRI | X2: SAT | Y2: SUN | Z2: MON | AA2: TUE | AB2: WED | AC2: THU | AD2: FRI | AE2: SAT | AF2: SUN
A3: Notes | B3: MOTHER'S DAY SALE | M3: SPRING SALE | W3: SPECIAL OFFER (FATHER'S DAY) | AA3: SPRING SALE
E4: Price Change HBF PRO Solar (DTC/Storefront US at 09:25am CET) Old Price: RRP $339 → LP $239 → 28% OFF New Price: RRP $339 → LP $259 → 24% OFF | F4: Price Change SBF PRO Solar (DTC/Storefront EU at 12:11pm CET) Old Price: RRP $299 → LP $199 → 34% OFF New Price: RRP $299 → LP $219 → 27% OFF | G4: Renamed BB Solar back to to BB PRO Solar due to Amazon (DTC/SHOP/PDP US at 08:29am CEST) | H4: Renamed from BB PRO Solar to BB Solar due to Amazon constraints (DTC/SHOP/PDP US at 15:55pm CEST) | K4: SBF PRO Solar card HIDDEN on the Storefront (DTC/Storefront US 10:10am CEST) | L4: Retail Availability Banner Hidden (DTC/Storefront US 12:17am CEST) | M4: Mother’s Day Bundle (HBF PRO Retail) renamed to Hummingbird Bundle (DTC US 16:20pm CEST) | P4: FPM M1 Retention test turned ON (DTC US at 13.01pm UTC) | T4: Price Change HBF Bundle (HBF PRO Solar Retail) (DTC/Storefront US at 14:51pm CET) Old Price: RRP $339 → LP $259 → 24% OFF New Price: RRP $339 → LP $219 → 35% OFF | U4: Trustpilot Widget Shown (DTC/Footer US at 10:25am CEST) | W4: SKU3 V2 Price change (DTC US 09:00am CEST) - OLD:MSRP $359 LP $179 Discount 50% OFF - NEW: MSRP $349 LP $169 Discount 50% OFF | Z4: Gift Bag opted out (DTC US at 10:15AM CEST) | AA4: SKU3 V2 Price change (DTC US 09:00am CEST) - OLD: MSRP $349 LP $169 Discount 50% OFF - NEW: MSRP $339 LP $219 Discount 35% OFF | AC4: FPM M2 Retention test turned ON (DTC US at 14.11pm CEST)
F5: Show retailer banner (DTC/hp US 12:19pm CEST) | G5: SKU3 V2 Price Change (DTC US 09:20am CEST) OLD: MSRP $339 LP $169 Discount 50% OFF NEW: MSRP $378 LP $189 Discount 50% OFF | K5: Added New storefront card: Smart Bird Feeder Bundle (DTC/Storefront US 10:10am CEST) SKU: BBS4082AAA (same as GOTY Bundle bc. it has same items) ID: 833048 Price: MSRP $389 LP $199 Discount 50% OFF The PDP is turned off for this storefront card | L5: AfterPurchase Upsell Turned ON (DTC/Storefront US 13:04am CEST) | M5: SKU3 V2 card Renamed and shown on storefront (DTC US 16:20pm CEST) - OLD: Birdbuddy PRO Solar - NEW: Smart Bird Feeder | W5: After Purchase turned ON (DTC US 09:00am CEST) | AA5: Birdbuddy PRO Solar + Family premium price: - OLD: MSRP $448 LP $218.5 Discount 51% OFF - NEW: MSRP $438 LP $268.50 Discount 39% OFF
F6: Renamed BB PRO Solar to BB Solar due to Amazon (DTC/SHOP/PDP US at 19:36pm CEST) | M6: SKU3 V2 Price change (DTC US 16:20pm CEST) - OLD: MSRP $378 LP $189 Discount 50% OFF - NEW: MSRP $359 LP $179 Discount 50% OFF
A12: DTC Revenue | B12: =SUM(B13,B20,B26,B29) -> 88749.976 | C12: =SUM(C13,C20,C26,C29) -> 180837.88 | D12: =SUM(D13,D20,D26,D29) -> 181335.67 | E12: =SUM(E13,E20,E26,E29) -> 167865.39 | F12: =SUM(F13,F20,F26,F29) -> 139488.21 | G12: =SUM(G13,G20,G26,G29) -> 114657.39 | H12: =SUM(H13,H20,H26,H29) -> 83199.327 | I12: =SUM(I13,I20,I26,I29) -> 77885.256 | ... AF12: =SUM(AF13,AF20,AF26,AF29) -> 56960.976
A13: - DTC Revenue US&CA (w/o Subscriptions) | B13: =sum(B14:B19) -> 73595.13 | C13: =sum(C14:C19) -> 117045.27 | D13: =sum(D14:D19) -> 151596.87 | E13: =sum(E14:E19) -> 139862.07 | F13: =sum(F14:F19) -> 97382.03 | G13: =sum(G14:G19) -> 91094.02 | H13: =sum(H14:H19) -> 66230.16 | I13: =sum(I14:I19) -> 59880.27 | ... AF13: =sum(AF14:AF19) -> 28618.5
A14: - Hardware | B14: 55904.1 | C14: 89119.9 | D14: 113979.5 | E14: 105630.4 | F14: 72773.79 | G14: 70375.4 | H14: 50044.4 | I14: 45304.8 | J14: 45158.8 | K14: 38508 | L14: 23348 | M14: 26934 | N14: 26574.6 | O14: 361001.2 | P14: 58509.2 | Q14: 41130.1 | R14: 126157.2 | S14: 46624.4 | T14: 92972.7 | U14: 21372.7 | V14: 25308.2 | W14: 32844 | X14: 43204.36 | Y14: 51631.7 | Z14: 49357.9 | AA14: 30211.5 | AB14: 23368.2 | AC14: 15067.2 | AD14: 21131.4 | AE14: 20901 | AF14: 21928.4
A15: - Add-ons | B15: 3219.4 | C15: 5231.8 | D15: 7477.6 | E15: 6096 | F15: 4921.9 | G15: 3488.2 | H15: 3861.2 | I15: 3548.8 | J15: 3149.4 | K15: 9975.4 | L15: 5589 | M15: 3239.4 | N15: 2368.3 | O15: 19475.4 | P15: 3937.2 | Q15: 3081.4 | R15: 6862.2 | S15: 2986.8 | T15: 4486.6 | U15: 1703.4 | V15: 1571.8 | W15: 2682 | X15: 3171.87 | Y15: 3812.6 | Z15: 3965.4 | AA15: 1475.3 | AB15: 1512.6 | AC15: 1074.2 | AD15: 1286.2 | AE15: 1196.4 | AF15: 1990
A16: - Merch | B16: 0 | C16: 0 | D16: 0 | E16: 0 | F16: 0 | G16: 0 | H16: 0 | I16: 0 | J16: 0 | K16: 0 | L16: 0 | M16: 0 | N16: 0 | O16: 0 | P16: 0 | Q16: 0 | R16: 0 | S16: 0 | T16: 0 | U16: 0 | V16: 0 | W16: 0 | X16: 0 | Y16: 0 | Z16: 0 | AA16: 0 | AB16: 0 | AC16: 0 | AD16: 0 | AE16: 0 | AF16: 0
A17: - Taxes | B17: 4574.01 | C17: 7422.04 | D17: 9798.23 | E17: 9005.17 | F17: 6229.59 | G17: 5836.7 | H17: 4164.53 | I17: 3763.32 | J17: 3688.73 | K17: 3891.06 | L17: 2233.2 | M17: 2391.53 | N17: 2315.89 | O17: 29846.05 | P17: 5039.27 | Q17: 3535.73 | R17: 10602.04 | S17: 3819.09 | T17: 7713 | U17: 1893.22 | V17: 2143.34 | W17: 2745.71 | X17: 3701.84 | Y17: 4336.89 | Z17: 4166.22 | AA17: 2490.42 | AB17: 1936.98 | AC17: 1231.92 | AD17: 1649.81 | AE17: 1664.51 | AF17: 1754.62
A18: - Shipping | B18: 8038.55 | C18: 12692.82 | D18: 16363.53 | E18: 14992.57 | F18: 10382.28 | G18: 8914.96 | H18: 6540.84 | I18: 5924.02 | J18: 5831.09 | K18: 6104.58 | L18: 3468.93 | M18: 3783.78 | N18: 3759.08 | O18: 50201.87 | P18: 8074.14 | Q18: 5689.77 | R18: 17561.77 | S18: 6506.11 | T18: 12969.5 | U18: 3100.07 | V18: 3696.71 | W18: 4739.85 | X18: 6268.9 | Y18: 7553.55 | Z18: 7229.2 | AA18: 3775.99 | AB18: 2859.64 | AC18: 1889.86 | AD18: 2709.09 | AE18: 2698.06 | AF18: 2945.48
A19: - Gift Bag | B19: 1859.07 | C19: 2578.71 | D19: 3978.01 | E19: 4137.93 | F19: 3074.47 | G19: 2478.76 | H19: 1619.19 | I19: 1339.33 | J19: 1319.34 | K19: 1419.29 | L19: 839.58 | M19: 879.56 | N19: 819.59 | O19: 1199.4 | P19: 879.56 | Q19: 679.66 | R19: 999.5 | S19: 999.5 | T19: 799.6 | U19: 599.7 | V19: 899.55 | W19: 1159.42 | X19: 1336 | Y19: 1659.17 | Z19: 0 | AA19: 0 | AB19: 0 | AC19: 0 | AD19: 0 | AE19: 0 | AF19: 0
A20: - DTC Revenue EU (w/o Subscriptions) | B20: =SUM(B21:B25) -> 1178.8734 | C20: =SUM(C21:C25) -> 405.7888 | D20: =SUM(D21:D25) -> 307.19612 | E20: =SUM(E21:E25) -> 1702.1809 | F20: =SUM(F21:F25) -> 322.5898 | G20: =SUM(G21:G25) -> 292.25637 | H20: =SUM(H21:H25) -> 584.5411 | I20: =SUM(I21:I25) -> 653.1553 | ... AF20: =SUM(AF21:AF25) -> 1545.8027
A21: - Hardware | B21: ='DTC EU - P&L'!B15*B$133 -> 763.51504 | C21: ='DTC EU - P&L'!C15*C$133 -> 194.48542 | D21: ='DTC EU - P&L'!D15*D$133 -> 191.39327 | E21: ='DTC EU - P&L'!E15*E$133 -> 1150.8337 | F21: ='DTC EU - P&L'!F15*F$133 -> 210.11646 | G21: ='DTC EU - P&L'!G15*G$133 -> 216.21685 | H21: ='DTC EU - P&L'!H15*H$133 -> 424.49293 | I21: ='DTC EU - P&L'!I15*I$133 -> 217.02658 | ... AF21: ='DTC EU - P&L'!AF15*AF$133 -> 836.87562
A22: - Add-ons | B22: ='DTC EU - P&L'!B16*B$133 -> 71.903832 | C22: ='DTC EU - P&L'!C16*C$133 -> 90.751264 | D22: ='DTC EU - P&L'!D16*D$133 -> 19.079484 | E22: ='DTC EU - P&L'!E16*E$133 -> 65.6978 | F22: ='DTC EU - P&L'!F16*F$133 -> 13.542685 | G22: ='DTC EU - P&L'!G16*G$133 -> 0 | H22: ='DTC EU - P&L'!H16*H$133 -> 0 | I22: ='DTC EU - P&L'!I16*I$133 -> 264.58775 | ... AF22: ='DTC EU - P&L'!AF16*AF$133 -> 291.06032
A23: - Merch | B23: ='DTC EU - P&L'!B17*B$133 -> 0 | C23: ='DTC EU - P&L'!C17*C$133 -> 0 | D23: ='DTC EU - P&L'!D17*D$133 -> 0 | E23: ='DTC EU - P&L'!E17*E$133 -> 0 | F23: ='DTC EU - P&L'!F17*F$133 -> 0 | G23: ='DTC EU - P&L'!G17*G$133 -> 0 | H23: ='DTC EU - P&L'!H17*H$133 -> 0 | I23: ='DTC EU - P&L'!I17*I$133 -> 0 | ... AF23: ='DTC EU - P&L'!AF17*AF$133 -> 0
A24: - Taxes | B24: ='DTC EU - P&L'!B20*B$133 -> 214.46854 | C24: ='DTC EU - P&L'!C20*C$133 -> 67.776112 | D24: ='DTC EU - P&L'!D20*D$133 -> 55.654362 | E24: ='DTC EU - P&L'!E20*E$133 -> 298.60936 | F24: ='DTC EU - P&L'!F20*F$133 -> 57.96316 | G24: ='DTC EU - P&L'!G20*G$133 -> 46.667028 | H24: ='DTC EU - P&L'!H20*H$133 -> 101.41817 | I24: ='DTC EU - P&L'!I20*I$133 -> 106.67948 | ... AF24: ='DTC EU - P&L'!AF20*AF$133 -> 278.00671
A25: - Shipping | B25: ='DTC EU - P&L'!B22*B$133 -> 128.986 | C25: ='DTC EU - P&L'!C22*C$133 -> 52.776 | D25: ='DTC EU - P&L'!D22*D$133 -> 41.069 | E25: ='DTC EU - P&L'!E22*E$133 -> 187.04 | F25: ='DTC EU - P&L'!F22*F$133 -> 40.9675 | G25: ='DTC EU - P&L'!G22*G$133 -> 29.3725 | H25: ='DTC EU - P&L'!H22*H$133 -> 58.63 | I25: ='DTC EU - P&L'!I22*I$133 -> 64.8615 | ... AF25: ='DTC EU - P&L'!AF22*AF$133 -> 139.86
A26: - Yearly Premium Subscription US&CA | B26: =SUM(B27:B28) -> 13543.33 | C26: =SUM(C27:C28) -> 62954.1 | D26: =SUM(D27:D28) -> 29114.82 | E26: =SUM(E27:E28) -> 25543.71 | F26: =SUM(F27:F28) -> 41270.97 | G26: =SUM(G27:G28) -> 22742.47 | H26: =SUM(H27:H28) -> 16268.55 | I26: =SUM(I27:I28) -> 17058.22 | ... AF26: =SUM(AF27:AF28) -> 26366.65
A27: - Line Item Total | B27: 13169.43 | C27: 61028.86 | D27: 28269.92 | E27: 24752.74 | F27: 39839.71 | G27: 22011.27 | H27: 15844.42 | I27: 16479.35 | J27: 16506.05 | K27: 17164.54 | L27: 19961.72 | M27: 19177.04 | N27: 19247.53 | O27: 17306.7 | P27: 17093.98 | Q27: 15427.65 | R27: 20185.9 | S27: 17683.18 | T27: 20549.37 | U27: 23478.8 | V27: 16247.86 | W27: 22016.25 | X27: 17056.03 | Y27: 24716.25 | Z27: 27800.7 | AA27: 19684.77 | AB27: 21654.07 | AC27: 20334.41 | AD27: 21997.88 | AE27: 8967.01 | AF27: 25596.83
A28: - Taxes | B28: 373.9 | C28: 1925.24 | D28: 844.9 | E28: 790.97 | F28: 1431.26 | G28: 731.2 | H28: 424.13 | I28: 578.87 | J28: 590.87 | K28: 554.55 | L28: 634.03 | M28: 582.74 | N28: 608.02 | O28: 591.2 | P28: 583.55 | Q28: 526.64 | R28: 638.99 | S28: 611.06 | T28: 698.3 | U28: 692.15 | V28: 416.17 | W28: 717 | X28: 559.66 | Y28: 827.55 | Z28: 866.15 | AA28: 510.73 | AB28: 613.69 | AC28: 659.79 | AD28: 734.88 | AE28: 317.18 | AF28: 769.82
A29: - Yearly Premium Subscription EU | B29: =SUM(B30:B31) -> 432.6425 | C29: =SUM(C30:C31) -> 432.71629 | D29: =SUM(D30:D31) -> 316.7828 | E29: =SUM(E30:E31) -> 757.43017 | F29: =SUM(F30:F31) -> 512.62048 | G29: =SUM(G30:G31) -> 528.64625 | H29: =SUM(H30:H31) -> 116.07567 | I29: =SUM(I30:I31) -> 293.61032 | ... AF29: =SUM(AF30:AF31) -> 430.02288
A30: - Line Item Total | B30: ='DTC EU - P&L'!B18*B$133 -> 358.39346 | C30: ='DTC EU - P&L'!C18*C$133 -> 350.32709 | D30: ='DTC EU - P&L'!D18*D$133 -> 262.53652 | E30: ='DTC EU - P&L'!E18*E$133 -> 625.20458 | F30: ='DTC EU - P&L'!F18*F$133 -> 423.0304 | G30: ='DTC EU - P&L'!G18*G$133 -> 436.21687 | H30: ='DTC EU - P&L'!H18*H$133 -> 92.858194 | I30: ='DTC EU - P&L'!I18*I$133 -> 243.07732 | ... AF30: ='DTC EU - P&L'!AF18*AF$133 -> 356.89941
A31: - Taxes | B31: ='DTC EU - P&L'!B21*B$133 -> 74.249032 | C31: ='DTC EU - P&L'!C21*C$133 -> 82.3892 | D31: ='DTC EU - P&L'!D21*D$133 -> 54.246282 | E31: ='DTC EU - P&L'!E21*E$133 -> 132.22559 | F31: ='DTC EU - P&L'!F21*F$133 -> 89.59007 | G31: ='DTC EU - P&L'!G21*G$133 -> 92.429383 | H31: ='DTC EU - P&L'!H21*H$133 -> 23.21748 | I31: ='DTC EU - P&L'!I21*I$133 -> 50.533005 | ... AF31: ='DTC EU - P&L'!AF21*AF$133 -> 73.12347
A32: Amazon Revenue | B32: =sum(B33,B39) -> 41310.89 | C32: =sum(C33,C39) -> 59108.3 | D32: =sum(D33,D39) -> 106997.66 | E32: =sum(E33,E39) -> 101020.52 | F32: =sum(F33,F39) -> 90573.84 | G32: =sum(G33,G39) -> 64340.28 | H32: =sum(H33,H39) -> 59815.27 | I32: =sum(I33,I39) -> 38771.02 | ... AF32: =sum(AF33,AF39) -> 18560.69
A33: Amazon Revenue US | B33: =sum(B34:B38) -> 41264.95 | C33: =sum(C34:C38) -> 59108.3 | D33: =sum(D34:D38) -> 106923.09 | E33: =sum(E34:E38) -> 100980.97 | F33: =sum(F34:F38) -> 90308.03 | G33: =sum(G34:G38) -> 64294.29 | H33: =sum(H34:H38) -> 59341.85 | I33: =sum(I34:I38) -> 38530.94 | ... AF33: =sum(AF34:AF38) -> 18005.48
A34: - Hardware | B34: 36387 | C34: 52342 | D34: 95619 | E34: 90606 | F34: 81314 | G34: 56474 | H34: 51789.13 | I34: 33011.13 | J34: 30134 | K34: 19116 | L34: 14309.86 | M34: 15329.3 | N34: 18312.72 | O34: 23082.44 | P34: 19028.72 | Q34: 16488.58 | R34: 22271.86 | S34: 16445.86 | T34: 16124.72 | U34: 11766 | V34: 12889.86 | W34: 13119 | X34: 16307 | Y34: 13082 | Z34: 14895 | AA34: 9855 | AB34: 12046 | AC34: 10890 | AD34: 8908 | AE34: 13600 | AF34: 14505
A35: - Add-ons | B35: 2101 | C35: 2798 | D35: 4066.84 | E35: 3593 | F35: 2877 | G35: 3469 | H35: 3475.86 | I35: 2917.43 | J35: 3272 | K35: 5540 | L35: 2732.46 | M35: 2025.3 | N35: 2416.92 | O35: 1759.84 | P35: 2269.92 | Q35: 2833.38 | R35: 2521.46 | S35: 1734.46 | T35: 1687.46 | U35: 1396 | V35: 1329.46 | W35: 1802 | X35: 1453 | Y35: 2120 | Z35: 2003 | AA35: 1356 | AB35: 1376 | AC35: 1064 | AD35: 1269 | AE35: 1782 | AF35: 2287
A36: - Tax | B36: 2734.1 | C36: 3924.55 | D36: 7146.72 | E36: 6649.34 | F36: 5949.08 | G36: 4251.23 | H36: 3996.13 | I36: 2553.24 | J36: 2294.4 | K36: 1702.66 | L36: 1218.64 | M36: 1182.84 | N36: 1379.04 | O36: 1794.82 | P36: 1510.83 | Q36: 1368.97 | R36: 1816.04 | S36: 1206.35 | T36: 1239.48 | U36: 883.74 | V36: 970.43 | W36: 1030.96 | X36: 1279.14 | Y36: 1067.78 | Z36: 1241.63 | AA36: 784.27 | AB36: 982.95 | AC36: 846.84 | AD36: 669.93 | AE36: 1071.03 | AF36: 1199.32
A37: - Shipping | B37: 10.06 | C37: 15.29 | D37: 34.7 | E37: 58.46 | F37: 103.13 | G37: 45.09 | H37: 29.42 | I37: 11.08 | J37: 14.73 | K37: 30.94 | L37: 0.27 | M37: 3.41 | N37: 12.35 | O37: 12.41 | P37: 5.69 | Q37: 14.54 | R37: 10.79 | S37: 18.85 | T37: 0.41 | U37: 7.26 | V37: 11.53 | W37: 28.32 | X37: 6.79 | Y37: 0.41 | Z37: 7.35 | AA37: 11.85 | AB37: 7.45 | AC37: 0.67 | AD37: 5.47 | AE37: 16.92 | AF37: 0.34
A38: - Gift Wrap | B38: 32.79 | C38: 28.46 | D38: 55.83 | E38: 74.17 | F38: 64.82 | G38: 54.97 | H38: 51.31 | I38: 38.06 | J38: 23.79 | K38: 9.62 | L38: 9.58 | M38: 10 | N38: 35.42 | O38: 9.85 | P38: 1.23 | Q38: 10.2 | R38: 23.58 | S38: 9.34 | T38: 18.75 | U38: 17.9 | V38: 9.38 | W38: 17.46 | X38: 18.55 | Y38: 0.99 | Z38: 0.88 | AA38: 22.01 | AB38: 18.57 | AC38: 5.22 | AD38: 0.43 | AE38: 14.09 | AF38: 13.82
A39: Amazon Revenue EU | B39: ='AMAZON EU - P&L'!B32 -> 45.94 | C39: ='AMAZON EU - P&L'!C32 -> 0 | D39: ='AMAZON EU - P&L'!D32 -> 74.57 | E39: ='AMAZON EU - P&L'!E32 -> 39.55 | F39: ='AMAZON EU - P&L'!F32 -> 265.81 | G39: ='AMAZON EU - P&L'!G32 -> 45.99 | H39: ='AMAZON EU - P&L'!H32 -> 473.42 | I39: ='AMAZON EU - P&L'!I32 -> 240.08 | ... AF39: ='AMAZON EU - P&L'!AF32 -> 555.21
A40: Amazon Revenue UK | B40: ='AMAZON UK, FR, GER - P&L'!B24 -> 45.94 | C40: ='AMAZON UK, FR, GER - P&L'!C24 -> 0 | D40: ='AMAZON UK, FR, GER - P&L'!D24 -> 45.97 | E40: ='AMAZON UK, FR, GER - P&L'!E24 -> 0 | F40: ='AMAZON UK, FR, GER - P&L'!F24 -> 0 | G40: ='AMAZON UK, FR, GER - P&L'!G24 -> 45.99 | H40: ='AMAZON UK, FR, GER - P&L'!H24 -> 0 | I40: ='AMAZON UK, FR, GER - P&L'!I24 -> 0 | ... AF40: ='AMAZON UK, FR, GER - P&L'!AF24 -> 45.51
A41: Amazon Revenue FR | B41: ='AMAZON UK, FR, GER - P&L'!B300 -> 0 | C41: ='AMAZON UK, FR, GER - P&L'!C300 -> 0 | D41: ='AMAZON UK, FR, GER - P&L'!D300 -> 0 | E41: ='AMAZON UK, FR, GER - P&L'!E300 -> 39.55 | F41: ='AMAZON UK, FR, GER - P&L'!F300 -> 32.88 | G41: ='AMAZON UK, FR, GER - P&L'!G300 -> 0 | H41: ='AMAZON UK, FR, GER - P&L'!H300 -> 0 | I41: ='AMAZON UK, FR, GER - P&L'!I300 -> 0 | ... AF41: ='AMAZON UK, FR, GER - P&L'!AF300 -> 238.57
A42: Amazon Revenue GER | B42: ='AMAZON UK, FR, GER - P&L'!B576 -> 0 | C42: ='AMAZON UK, FR, GER - P&L'!C576 -> 0 | D42: ='AMAZON UK, FR, GER - P&L'!D576 -> 28.6 | E42: ='AMAZON UK, FR, GER - P&L'!E576 -> 0 | F42: ='AMAZON UK, FR, GER - P&L'!F576 -> 232.93 | G42: ='AMAZON UK, FR, GER - P&L'!G576 -> 0 | H42: ='AMAZON UK, FR, GER - P&L'!H576 -> 473.42 | I42: ='AMAZON UK, FR, GER - P&L'!I576 -> 240.08 | ... AF42: ='AMAZON UK, FR, GER - P&L'!AF576 -> 271.13
A43: - Hardware | B43: ='AMAZON EU - P&L'!B27 -> 0 | C43: ='AMAZON EU - P&L'!C27 -> 0 | D43: ='AMAZON EU - P&L'!D27 -> 0 | E43: ='AMAZON EU - P&L'!E27 -> 0 | F43: ='AMAZON EU - P&L'!F27 -> 232.93 | G43: ='AMAZON EU - P&L'!G27 -> 0 | H43: ='AMAZON EU - P&L'!H27 -> 466.69 | I43: ='AMAZON EU - P&L'!I27 -> 233.35 | ... AF43: ='AMAZON EU - P&L'!AF27 -> 463.77
A44: - Add-ons | B44: ='AMAZON EU - P&L'!B28 -> 39.38 | C44: ='AMAZON EU - P&L'!C28 -> 0 | D44: ='AMAZON EU - P&L'!D28 -> 68.01 | E44: ='AMAZON EU - P&L'!E28 -> 33.9 | F44: ='AMAZON EU - P&L'!F28 -> 30.59 | G44: ='AMAZON EU - P&L'!G28 -> 39.42 | H44: ='AMAZON EU - P&L'!H28 -> 0 | I44: ='AMAZON EU - P&L'!I28 -> 0 | ... AF44: ='AMAZON EU - P&L'!AF28 -> 72.81
A45: - Tax | B45: ='AMAZON EU - P&L'!B29 -> 6.56 | C45: ='AMAZON EU - P&L'!C29 -> 0 | D45: ='AMAZON EU - P&L'!D29 -> 6.56 | E45: ='AMAZON EU - P&L'!E29 -> 5.65 | F45: ='AMAZON EU - P&L'!F29 -> 2.29 | G45: ='AMAZON EU - P&L'!G29 -> 6.57 | H45: ='AMAZON EU - P&L'!H29 -> 6.73 | I45: ='AMAZON EU - P&L'!I29 -> 6.73 | ... AF45: ='AMAZON EU - P&L'!AF29 -> 18.63
A46: - Shipping | B46: ='AMAZON EU - P&L'!B30 -> 0 | C46: ='AMAZON EU - P&L'!C30 -> 0 | D46: ='AMAZON EU - P&L'!D30 -> 0 | E46: ='AMAZON EU - P&L'!E30 -> 0 | F46: ='AMAZON EU - P&L'!F30 -> 0 | G46: ='AMAZON EU - P&L'!G30 -> 0 | H46: ='AMAZON EU - P&L'!H30 -> 0 | I46: ='AMAZON EU - P&L'!I30 -> 0 | ... AF46: ='AMAZON EU - P&L'!AF30 -> 0
A47: - Gift Wrap | B47: ='AMAZON EU - P&L'!B31 -> 0 | C47: ='AMAZON EU - P&L'!C31 -> 0 | D47: ='AMAZON EU - P&L'!D31 -> 0 | E47: ='AMAZON EU - P&L'!E31 -> 0 | F47: ='AMAZON EU - P&L'!F31 -> 0 | G47: ='AMAZON EU - P&L'!G31 -> 0 | H47: ='AMAZON EU - P&L'!H31 -> 0 | I47: ='AMAZON EU - P&L'!I31 -> 0 | ... AF47: ='AMAZON EU - P&L'!AF31 -> 0
A48: Total Revenue | B48: =SUM(B12+B32) -> 130060.87 | C48: =SUM(C12+C32) -> 239946.18 | D48: =SUM(D12+D32) -> 288333.33 | E48: =SUM(E12+E32) -> 268885.91 | F48: =SUM(F12+F32) -> 230062.05 | G48: =SUM(G12+G32) -> 178997.67 | H48: =SUM(H12+H32) -> 143014.6 | I48: =SUM(I12+I32) -> 116656.28 | ... AF48: =SUM(AF12+AF32) -> 75521.666
A50: B2B Revenue
A51: RETAIL Revenue
A52: Best Buy | B52: =iferror(sum(B53:B55),"") -> 4882.1959 | C52: =iferror(sum(C53:C55),"") -> 3396.3102 | D52: =iferror(sum(D53:D55),"") -> 0 | E52: =iferror(sum(E53:E55),"") -> 7429.4285 | F52: =iferror(sum(F53:F55),"") -> 10825.739 | G52: =iferror(sum(G53:G55),"") -> 10825.739 | H52: =iferror(sum(H53:H55),"") -> 22076.016 | I52: =iferror(sum(I53:I55),"") -> 19953.322 | ... AF52: =iferror(sum(AF53:AF55),"") -> 0
A53: - Hardware | B53: 4599.77 | C53: 3199.84 | D53: 0 | E53: 6999.65 | F53: 10199.49 | G53: 10199.49 | H53: 20798.96 | I53: 18799.06 | J53: 24198.79 | K53: 0 | L53: 11999.4 | M53: 3999.8 | N53: 3599.82 | O53: 3599.82 | P53: 2999.85 | Q53: 3999.8 | R53: 0 | S53: 3399.83 | T53: 4399.78 | U53: 3199.84 | V53: 3999.8 | W53: 1999.9 | X53: 3799.81 | Y53: 0 | Z53: 3799.81 | AA53: 2599.87 | AB53: 1799.91 | AC53: 2399.88 | AD53: 2199.89 | AE53: 2399.88 | AF53: 0
A54: - Tax | B54: =B53*'Data - P&L'!$U$3 -> 282.42588 | C54: =C53*'Data - P&L'!$U$3 -> 196.47018 | D54: =D53*'Data - P&L'!$U$3 -> 0 | E54: =E53*'Data - P&L'!$U$3 -> 429.77851 | F54: =F53*'Data - P&L'!$U$3 -> 626.24869 | G54: =G53*'Data - P&L'!$U$3 -> 626.24869 | H54: =H53*'Data - P&L'!$U$3 -> 1277.0561 | I54: =I53*'Data - P&L'!$U$3 -> 1154.2623 | ... AF54: =AF53*'Data - P&L'!$U$3 -> 0
A55: - Shipping
A56: Target | B56: =sum(B57:B59) -> 19063.805 | C56: =sum(C57:C59) -> 28492.222 | D56: =sum(D57:D59) -> 38567.03 | E56: =sum(E57:E59) -> 47497.65 | F56: =sum(F57:F59) -> 55254.361 | G56: =sum(G57:G59) -> 58995.796 | H56: =sum(H57:H59) -> 61287.359 | I56: =sum(I57:I59) -> 63612.886 | ... AF56: =sum(AF57:AF59) -> 6225.111
A57: - Hardware | B57: =IFERROR(__xludf.DUMMYFUNCTION("IMPORTRANGE(""https://docs.google.com/spreadsheets/d/1aRqNG2OzO5TKKUMAG-sA0zhobXUcaxw5F28MzPb9SsI"",""TRANSPOSE!afw3:aha3"")"),17961.0) -> 17961 | C57: =IFERROR(__xludf.DUMMYFUNCTION("""COMPUTED_VALUE"""),26844.0) -> 26844 | D57: =IFERROR(__xludf.DUMMYFUNCTION("""COMPUTED_VALUE"""),36336.0) -> 36336 | E57: =IFERROR(__xludf.DUMMYFUNCTION("""COMPUTED_VALUE"""),44750.0) -> 44750 | F57: =IFERROR(__xludf.DUMMYFUNCTION("""COMPUTED_VALUE"""),52058.0) -> 52058 | G57: =IFERROR(__xludf.DUMMYFUNCTION("""COMPUTED_VALUE"""),55583.0) -> 55583 | H57: =IFERROR(__xludf.DUMMYFUNCTION("""COMPUTED_VALUE"""),57742.0) -> 57742 | I57: =IFERROR(__xludf.DUMMYFUNCTION("""COMPUTED_VALUE"""),59933.0) -> 59933 | J57: =IFERROR(__xludf.DUMMYFUNCTION("""COMPUTED_VALUE"""),78152.0) -> 78152 | K57: =IFERROR(__xludf.DUMMYFUNCTION("""COMPUTED_VALUE"""),49173.0) -> 49173 | L57: =IFERROR(__xludf.DUMMYFUNCTION("""COMPUTED_VALUE"""),22515.0) -> 22515 | M57: =IFERROR(__xludf.DUMMYFUNCTION("""COMPUTED_VALUE"""),13139.0) -> 13139 | N57: =IFERROR(__xludf.DUMMYFUNCTION("""COMPUTED_VALUE"""),13435.0) -> 13435 | O57: =IFERROR(__xludf.DUMMYFUNCTION("""COMPUTED_VALUE"""),12538.0) -> 12538 | P57: =IFERROR(__xludf.DUMMYFUNCTION("""COMPUTED_VALUE"""),12784.0) -> 12784 | Q57: =IFERROR(__xludf.DUMMYFUNCTION("""COMPUTED_VALUE"""),16684.0) -> 16684 | R57: =IFERROR(__xludf.DUMMYFUNCTION("""COMPUTED_VALUE"""),11865.0) -> 11865 | S57: =IFERROR(__xludf.DUMMYFUNCTION("""COMPUTED_VALUE"""),14297.0) -> 14297 | T57: =IFERROR(__xludf.DUMMYFUNCTION("""COMPUTED_VALUE"""),12150.0) -> 12150 | U57: =IFERROR(__xludf.DUMMYFUNCTION("""COMPUTED_VALUE"""),10232.0) -> 10232 | V57: =IFERROR(__xludf.DUMMYFUNCTION("""COMPUTED_VALUE"""),10858.0) -> 10858 | W57: =IFERROR(__xludf.DUMMYFUNCTION("""COMPUTED_VALUE"""),10965.0) -> 10965 | X57: =IFERROR(__xludf.DUMMYFUNCTION("""COMPUTED_VALUE"""),14539.0) -> 14539 | Y57: =IFERROR(__xludf.DUMMYFUNCTION("""COMPUTED_VALUE"""),11095.0) -> 11095 | Z57: =IFERROR(__xludf.DUMMYFUNCTION("""COMPUTED_VALUE"""),10308.0) -> 10308 | AA57: =IFERROR(__xludf.DUMMYFUNCTION("""COMPUTED_VALUE"""),9691.0) -> 9691 | AB57: =IFERROR(__xludf.DUMMYFUNCTION("""COMPUTED_VALUE"""),10030.0) -> 10030 | AC57: =IFERROR(__xludf.DUMMYFUNCTION("""COMPUTED_VALUE"""),7453.0) -> 7453 | AD57: =IFERROR(__xludf.DUMMYFUNCTION("""COMPUTED_VALUE"""),8460.0) -> 8460 | AE57: =IFERROR(__xludf.DUMMYFUNCTION("""COMPUTED_VALUE"""),9668.0) -> 9668 | AF57: =IFERROR(__xludf.DUMMYFUNCTION("""COMPUTED_VALUE"""),5865.0) -> 5865
A58: - Tax | B58: =B57*'Data - P&L'!$U$3 -> 1102.8054 | C58: =C57*'Data - P&L'!$U$3 -> 1648.2216 | D58: =D57*'Data - P&L'!$U$3 -> 2231.0304 | E58: =E57*'Data - P&L'!$U$3 -> 2747.65 | F58: =F57*'Data - P&L'!$U$3 -> 3196.3612 | G58: =G57*'Data - P&L'!$U$3 -> 3412.7962 | H58: =H57*'Data - P&L'!$U$3 -> 3545.3588 | I58: =I57*'Data - P&L'!$U$3 -> 3679.8862 | ... AF58: =AF57*'Data - P&L'!$U$3 -> 360.111
A59: - Shipping
A60: Costco | B60: =SUM(B61:B63) -> 0 | C60: =SUM(C61:C63) -> 0 | D60: =SUM(D61:D63) -> 0 | E60: =SUM(E61:E63) -> 0 | F60: =SUM(F61:F63) -> 0 | G60: =SUM(G61:G63) -> 0 | H60: =SUM(H61:H63) -> 0 | I60: =SUM(I61:I63) -> 0 | ... AF60: =SUM(AF61:AF63) -> 0
A61: - Hardware | B61: 0 | C61: 0 | D61: 0 | E61: 0 | F61: 0 | G61: 0 | H61: 0 | I61: 0 | J61: 0 | K61: 0 | L61: 0 | M61: 0 | N61: 0 | O61: 0 | P61: 0 | Q61: 0 | R61: 0 | S61: 0 | T61: 0 | U61: 0 | V61: 0 | W61: 0 | X61: 0 | Y61: 0 | Z61: 0 | AA61: 0 | AB61: 0 | AC61: 0 | AD61: 0 | AE61: 0 | AF61: 0
A62: - Tax | B62: =0.0614*B61 -> 0 | C62: =0.0614*C61 -> 0 | D62: =0.0614*D61 -> 0 | E62: =0.0614*E61 -> 0 | F62: =0.0614*F61 -> 0 | G62: =0.0614*G61 -> 0 | H62: =0.0614*H61 -> 0 | I62: =0.0614*I61 -> 0 | ... AF62: =0.0614*AF61 -> 0
A63: - Shipping
A64: Chewy | B64: =SUM(B65:B67) -> 8953.9704 | C64: =SUM(C65:C67) -> 9798.8448 | D64: =SUM(D65:D67) -> 11447.199 | E64: =SUM(E65:E67) -> 20586.914 | F64: =SUM(F65:F67) -> 6691.0656 | G64: =SUM(G65:G67) -> 11503.453 | H64: =SUM(H65:H67) -> 11630.821 | I64: =SUM(I65:I67) -> 16042 | ... AF64: =SUM(AF65:AF67) -> 2957.0604
A65: - Hardware | B65: 8436 | C65: 9232 | D65: 10785 | E65: 19396 | F65: 6304 | G65: 10838 | H65: 10958 | I65: 15114 | J65: 5168 | K65: 14935 | L65: 12390 | M65: 7238 | N65: 9308 | O65: 4156 | P65: 5946 | Q65: 2981 | R65: 2008 | S65: 2903 | T65: 3043 | U65: 3043 | V65: 6444 | W65: 6841 | X65: 3401 | Y65: 7456 | Z65: 2148 | AA65: 6919 | AB65: 6522 | AC65: 6324 | AD65: 1970 | AE65: 2587 | AF65: 2786
A66: - Tax | B66: =0.0614*B65 -> 517.9704 | C66: =0.0614*C65 -> 566.8448 | D66: =0.0614*D65 -> 662.199 | E66: =0.0614*E65 -> 1190.9144 | F66: =0.0614*F65 -> 387.0656 | G66: =0.0614*G65 -> 665.4532 | H66: =0.0614*H65 -> 672.8212 | I66: =0.0614*I65 -> 927.9996 | ... AF66: =0.0614*AF65 -> 171.0604
A67: - Shipping
A68: Walmart | B68: =sum(B69:B71) -> 1187.59 | C68: =sum(C69:C71) -> 1218.97 | D68: =sum(D69:D71) -> 1927.97 | E68: =sum(E69:E71) -> 2718.28 | F68: =sum(F69:F71) -> 1100.4 | G68: =sum(G69:G71) -> 669.03 | H68: =sum(H69:H71) -> 339.18 | I68: =sum(I69:I71) -> 0 | ... AF68: =sum(AF69:AF71) -> 38.96
A69: - Hardware | B69: 1103 | C69: 1132 | D69: 1790 | E69: 2535 | F69: 1042 | G69: 626 | H69: 328 | I69: 0 | J69: 29 | K69: 29 | L69: 58 | M69: 29 | N69: 58 | O69: 0 | P69: 270 | Q69: 29 | R69: 29 | S69: 29 | T69: 58 | U69: 0 | V69: 0 | W69: 0 | X69: 0 | Y69: 0 | Z69: 0 | AA69: 29 | AB69: 0 | AC69: 0 | AD69: 0 | AE69: 0 | AF69: 29
A70: - Tax | B70: 84.59 | C70: 79.98 | D70: 137.97 | E70: 183.28 | F70: 58.4 | G70: 43.03 | H70: 4.19 | I70: 0 | J70: 1.89 | K70: 1.74 | L70: 4.92 | M70: 2.88 | N70: 3.62 | O70: 0 | P70: 17.15 | Q70: 2.7 | R70: 2.52 | S70: 2.76 | T70: 4.3 | U70: 0 | V70: 0 | W70: 0 | X70: 0 | Y70: 0 | Z70: 0 | AA70: 2.38 | AB70: 0 | AC70: 0 | AD70: 0 | AE70: 0 | AF70: 2.97
A71: - Shipping | B71: 0 | C71: 6.99 | D71: 0 | E71: 0 | F71: 0 | G71: 0 | H71: 6.99 | I71: 0 | J71: 0 | K71: 0 | L71: 6.99 | M71: 6.99 | N71: 0 | O71: 0 | P71: 0 | Q71: 0 | R71: 6.99 | S71: 0 | T71: 6.99 | U71: 0 | V71: 0 | W71: 0 | X71: 0 | Y71: 0 | Z71: 0 | AA71: 6.99 | AB71: 0 | AC71: 0 | AD71: 0 | AE71: 0 | AF71: 6.99
A72: DIGITAL MARKETPLACES Revenue
A73: Huckberry | B73: =SUM(B74:B76) -> 0 | C73: =SUM(C74:C76) -> 0 | D73: =SUM(D74:D76) -> 0 | E73: =SUM(E74:E76) -> 0 | F73: =SUM(F74:F76) -> 0 | G73: =SUM(G74:G76) -> 0 | H73: =SUM(H74:H76) -> 0 | I73: =SUM(I74:I76) -> 0 | ... AF73: =SUM(AF74:AF76) -> 0
A74: - Hardware | B74: 0 | C74: 0 | D74: 0 | E74: 0 | F74: 0 | G74: 0 | H74: 0 | I74: 0 | J74: 0 | K74: 0 | L74: 0 | M74: 0 | N74: 0 | O74: 0 | P74: 0 | Q74: 0 | R74: 0 | S74: 0 | T74: 0 | U74: 0 | V74: 0 | W74: 0 | X74: 0 | Y74: 0 | Z74: 0 | AA74: 0 | AB74: 0 | AC74: 0 | AD74: 0 | AE74: 0 | AF74: 0
A75: - Tax | B75: =0.0614*B74 -> 0 | C75: =0.0614*C74 -> 0 | D75: =0.0614*D74 -> 0 | E75: =0.0614*E74 -> 0 | F75: =0.0614*F74 -> 0 | G75: =0.0614*G74 -> 0 | H75: =0.0614*H74 -> 0 | I75: =0.0614*I74 -> 0 | ... AF75: =0.0614*AF74 -> 0
A76: - Shipping
A77: Total Retail Revenue | B77: =sum(B52,B56,B60,B64,B68) -> 34087.562 | C77: =sum(C52,C56,C60,C64,C68) -> 42906.347 | D77: =sum(D52,D56,D60,D64,D68) -> 51942.199 | E77: =sum(E52,E56,E60,E64,E68) -> 78232.273 | F77: =sum(F52,F56,F60,F64,F68) -> 73871.565 | G77: =sum(G52,G56,G60,G64,G68) -> 81994.018 | H77: =sum(H52,H56,H60,H64,H68) -> 95333.376 | I77: =sum(I52,I56,I60,I64,I68) -> 99608.208 | ... AF77: =sum(AF52,AF56,AF60,AF64,AF68) -> 9221.1314
A78: Total DM Revenue | B78: =sum(B73) -> 0 | C78: =sum(C73) -> 0 | D78: =sum(D73) -> 0 | E78: =sum(E73) -> 0 | F78: =sum(F73) -> 0 | G78: =sum(G73) -> 0 | H78: =sum(H73) -> 0 | I78: =sum(I73) -> 0 | ... AF78: =sum(AF73) -> 0
A79: Total B2B Revenue | B79: =B77+B78 -> 34087.562 | C79: =C77+C78 -> 42906.347 | D79: =D77+D78 -> 51942.199 | E79: =E77+E78 -> 78232.273 | F79: =F77+F78 -> 73871.565 | G79: =G77+G78 -> 81994.018 | H79: =H77+H78 -> 95333.376 | I79: =I77+I78 -> 99608.208 | ... AF79: =AF77+AF78 -> 9221.1314
A81: App Revenue
A82: - Google Store | B82: ='App - P&L'!B90 -> 2510.356 | C82: ='App - P&L'!C90 -> 3363.11 | D82: ='App - P&L'!D90 -> 3736.7785 | E82: ='App - P&L'!E90 -> 2957.2095 | F82: ='App - P&L'!F90 -> 2654.788 | G82: ='App - P&L'!G90 -> 2665.957 | H82: ='App - P&L'!H90 -> 2569.584 | I82: ='App - P&L'!I90 -> 2407.0895 | ... AF82: ='App - P&L'!AF90 -> 2236.0525
A83: - Apple Store | B83: ='App - P&L'!B91 -> 9189.5273 | C83: ='App - P&L'!C91 -> 10516.702 | D83: ='App - P&L'!D91 -> 12847.699 | E83: ='App - P&L'!E91 -> 12478.4 | F83: ='App - P&L'!F91 -> 9435.538 | G83: ='App - P&L'!G91 -> 9353.2067 | H83: ='App - P&L'!H91 -> 7565.4094 | I83: ='App - P&L'!I91 -> 9103.0647 | ... AF83: ='App - P&L'!AF91 -> 11540.989
A84: - Comission | B84: ='App - P&L'!B67 -> 4381.3729 | C84: ='App - P&L'!C67 -> 5100.6482 | D84: ='App - P&L'!D67 -> 6165.5883 | E84: ='App - P&L'!E67 -> 5869.746 | F84: ='App - P&L'!F67 -> 4512.294 | G84: ='App - P&L'!G67 -> 4478.9802 | H84: ='App - P&L'!H67 -> 3695.7743 | I84: ='App - P&L'!I67 -> 4326.0939 | ... AF84: ='App - P&L'!AF67 -> 5340.7356
A85: - Tax | B85: ='App - P&L'!B68 -> 0 | C85: ='App - P&L'!C68 -> 0 | D85: ='App - P&L'!D68 -> 0 | E85: ='App - P&L'!E68 -> 0 | F85: ='App - P&L'!F68 -> 0 | G85: ='App - P&L'!G68 -> 0 | H85: ='App - P&L'!H68 -> 0 | I85: ='App - P&L'!I68 -> 0 | ... AF85: ='App - P&L'!AF68 -> 0
A86: Total App Revenue | B86: =sum(B82:B85) -> 16081.256 | C86: =sum(C82:C85) -> 18980.461 | D86: =sum(D82:D85) -> 22750.066 | E86: =sum(E82:E85) -> 21305.355 | F86: =sum(F82:F85) -> 16602.62 | G86: =sum(G82:G85) -> 16498.144 | H86: =sum(H82:H85) -> 13830.768 | I86: =sum(I82:I85) -> 15836.248 | ... AF86: =sum(AF82:AF85) -> 19117.777
A88: Units Sold (DTC + AMZN) | B88: =B91+B97+B103+B109 -> 457 | C88: =C91+C97+C103+C109 -> 697 | D88: =D91+D97+D103+D109 -> 1018 | E88: =E91+E97+E103+E109 -> 962 | F88: =F91+F97+F103+F109 -> 757 | G88: =G91+G97+G103+G109 -> 613 | H88: =H91+H97+H103+H109 -> 496 | I88: =I91+I97+I103+I109 -> 379 | ... AF88: =AF91+AF97+AF103+AF109 -> 175
A89: DTC Orders | B89: =sum(B90,B96) -> 455 | C89: =sum(C90,C96) -> 1103 | D89: =sum(D90,D96) -> 926 | E89: =sum(E90,E96) -> 830 | F89: =sum(F90,F96) -> 813 | G89: =sum(G90,G96) -> 578 | H89: =sum(H90,H96) -> 420 | I89: =sum(I90,I96) -> 418 | ... AF89: =sum(AF90,AF96) -> 395
A90: - DTC Orders US&CA | B90: 448 | C90: 1096 | D90: 921 | E90: 816 | F90: 806 | G90: 572 | H90: 417 | I90: 411 | J90: 402 | K90: 421 | L90: 347 | M90: 353 | N90: 352 | O90: 2091 | P90: 496 | Q90: 386 | R90: 842 | S90: 427 | T90: 700 | U90: 369 | V90: 310 | W90: 419 | X90: 420 | Y90: 553 | Z90: 567 | AA90: 334 | AB90: 332 | AC90: 292 | AD90: 335 | AE90: 204 | AF90: 386
A91: - Hardware (units sold) | B91: ='DTC US&CA - P&L'!B26 -> 300 | C91: ='DTC US&CA - P&L'!C26 -> 478 | D91: ='DTC US&CA - P&L'!D26 -> 616 | E91: ='DTC US&CA - P&L'!E26 -> 562 | F91: ='DTC US&CA - P&L'!F26 -> 389 | G91: ='DTC US&CA - P&L'!G26 -> 336 | H91: ='DTC US&CA - P&L'!H26 -> 240 | I91: ='DTC US&CA - P&L'!I26 -> 217 | ... AF91: ='DTC US&CA - P&L'!AF26 -> 104
A92: - Add-ons (units sold) | B92: ='DTC US&CA - P&L'!B66 -> 227 | C92: ='DTC US&CA - P&L'!C66 -> 369 | D92: ='DTC US&CA - P&L'!D66 -> 538 | E92: ='DTC US&CA - P&L'!E66 -> 495 | F92: ='DTC US&CA - P&L'!F66 -> 337 | G92: ='DTC US&CA - P&L'!G66 -> 263 | H92: ='DTC US&CA - P&L'!H66 -> 223 | I92: ='DTC US&CA - P&L'!I66 -> 199 | ... AF92: ='DTC US&CA - P&L'!AF66 -> 95
A93: - Merch (units sold) | B93: 0 | C93: 0 | D93: 0 | E93: 0 | F93: 0 | G93: 0 | H93: 0 | I93: 0 | J93: 0 | K93: 0 | L93: 0 | M93: 0 | N93: 0 | O93: 0 | P93: 0 | Q93: 0 | R93: 0 | S93: 0 | T93: 0 | U93: 0 | V93: 0 | W93: 0 | X93: 0 | Y93: 0 | Z93: 0 | AA93: 0 | AB93: 0 | AC93: 0 | AD93: 0 | AE93: 0 | AF93: 0
A94: - BB 1 year Pro Subscription | B94: 366 | C94: 974 | D94: 782 | E94: 679 | F94: 714 | G94: 501 | H94: 349 | I94: 340 | J94: 340 | K94: 343 | L94: 317 | M94: 300 | N94: 262 | O94: 250 | P94: 232 | Q94: 216 | R94: 279 | S94: 248 | T94: 272 | U94: 279 | V94: 226 | W94: 314 | X94: 281 | Y94: 389 | Z94: 409 | AA94: 266 | AB94: 271 | AC94: 240 | AD94: 275 | AE94: 140 | AF94: 303
A95: - Gift Bag | B95: 93 | C95: 129 | D95: 199 | E95: 207 | F95: 154 | G95: 124 | H95: 81 | I95: 67 | J95: 66 | K95: 71 | L95: 42 | M95: 44 | N95: 41 | O95: 60 | P95: 44 | Q95: 34 | R95: 50 | S95: 50 | T95: 40 | U95: 30 | V95: 45 | W95: 58 | X95: 67 | Y95: 83 | Z95: 0 | AA95: 0 | AB95: 0 | AC95: 0 | AD95: 0 | AE95: 0 | AF95: 0
A96: - DTC Orders EUROPE | B96: 7 | C96: 7 | D96: 5 | E96: 14 | F96: 7 | G96: 6 | H96: 3 | I96: 7 | J96: 3 | K96: 9 | L96: 3 | M96: 4 | N96: 6 | O96: 5 | P96: 7 | Q96: 4 | R96: 4 | S96: 8 | T96: 5 | U96: 4 | V96: 1 | W96: 4 | X96: 8 | Y96: 6 | Z96: 6 | AA96: 4 | AB96: 3 | AC96: 6 | AD96: 2 | AE96: 4 | AF96: 9
A97: - Hardware (units sold) | B97: ='DTC EU - P&L'!B27 -> 4 | C97: ='DTC EU - P&L'!C27 -> 1 | D97: ='DTC EU - P&L'!D27 -> 1 | E97: ='DTC EU - P&L'!E27 -> 6 | F97: ='DTC EU - P&L'!F27 -> 1 | G97: ='DTC EU - P&L'!G27 -> 1 | H97: ='DTC EU - P&L'!H27 -> 2 | I97: ='DTC EU - P&L'!I27 -> 1 | ... AF97: ='DTC EU - P&L'!AF27 -> 4
A98: - Add-ons (units sold) | B98: ='DTC EU - P&L'!B67 -> 5 | C98: ='DTC EU - P&L'!C67 -> 4 | D98: ='DTC EU - P&L'!D67 -> 2 | E98: ='DTC EU - P&L'!E67 -> 8 | F98: ='DTC EU - P&L'!F67 -> 2 | G98: ='DTC EU - P&L'!G67 -> 1 | H98: ='DTC EU - P&L'!H67 -> 1 | I98: ='DTC EU - P&L'!I67 -> 11 | ... AF98: ='DTC EU - P&L'!AF67 -> 13
A99: - Merch (units sold) | B99: 0 | C99: 0 | D99: 0 | E99: 0 | F99: 0 | G99: 0 | H99: 0 | I99: 0 | J99: 0 | K99: 0 | L99: 0 | M99: 0 | N99: 0 | O99: 0 | P99: 0 | Q99: 0 | R99: 0 | S99: 0 | T99: 0 | U99: 0 | V99: 0 | W99: 0 | X99: 0 | Y99: 0 | Z99: 0 | AA99: 0 | AB99: 0 | AC99: 0
A100: - BB 1 year Pro Subscription | B100: 6 | C100: 5 | D100: 4 | E100: 12 | F100: 6 | G100: 6 | H100: 2 | I100: 4 | J100: 2 | K100: 7 | L100: 3 | M100: 1 | N100: 4 | O100: 4 | P100: 2 | Q100: 4 | R100: 2 | S100: 5 | T100: 3 | U100: 2 | V100: 0 | W100: 2 | X100: 6 | Y100: 5 | Z100: 4 | AA100: 4 | AB100: 3 | AC100: 5 | AD100: 2 | AE100: 1 | AF100: 7
A101: Amazon Orders | B101: =SUM(B105,B102) -> 213 | C101: =SUM(C105,C102) -> 286 | D101: =SUM(D105,D102) -> 499 | E101: =SUM(E105,E102) -> 466 | F101: =SUM(F105,F102) -> 430 | G101: =SUM(G105,G102) -> 349 | H101: =SUM(H105,H102) -> 332 | I101: =SUM(I105,I102) -> 227 | ... AF101: =SUM(AF105,AF102) -> 134
A102: - Amazon Orders US | B102: 212 | C102: 286 | D102: 497 | E102: 465 | F102: 428 | G102: 348 | H102: 330 | I102: 226 | J102: 238 | K102: 249 | L102: 144 | M102: 127 | N102: 151 | O102: 143 | P102: 143 | Q102: 158 | R102: 164 | S102: 122 | T102: 119 | U102: 93 | V102: 93 | W102: 107 | X102: 114 | Y102: 114 | Z102: 126 | AA102: 82 | AB102: 95 | AC102: 75 | AD102: 75 | AE102: 113 | AF102: 130
A103: - Hardware (units sold) | B103: ='AMAZON US&CA - P&L'!B29 -> 153 | C103: ='AMAZON US&CA - P&L'!C29 -> 218 | D103: ='AMAZON US&CA - P&L'!D29 -> 401 | E103: ='AMAZON US&CA - P&L'!E29 -> 394 | F103: ='AMAZON US&CA - P&L'!F29 -> 366 | G103: ='AMAZON US&CA - P&L'!G29 -> 276 | H103: ='AMAZON US&CA - P&L'!H29 -> 252 | I103: ='AMAZON US&CA - P&L'!I29 -> 160 | ... AF103: ='AMAZON US&CA - P&L'!AF29 -> 65
A104: - Add-ons (units sold) | B104: ='AMAZON US&CA - P&L'!B69 -> 69 | C104: ='AMAZON US&CA - P&L'!C69 -> 92 | D104: ='AMAZON US&CA - P&L'!D69 -> 132 | E104: ='AMAZON US&CA - P&L'!E69 -> 117 | F104: ='AMAZON US&CA - P&L'!F69 -> 93 | G104: ='AMAZON US&CA - P&L'!G69 -> 111 | H104: ='AMAZON US&CA - P&L'!H69 -> 115 | I104: ='AMAZON US&CA - P&L'!I69 -> 93 | ... AF104: ='AMAZON US&CA - P&L'!AF69 -> 73
A105: - Amazon Orders EU | B105: =SUM(B106:B108) -> 1 | C105: =SUM(C106:C108) -> 0 | D105: =SUM(D106:D108) -> 2 | E105: =SUM(E106:E108) -> 1 | F105: =SUM(F106:F108) -> 2 | G105: =SUM(G106:G108) -> 1 | H105: =SUM(H106:H108) -> 2 | I105: =SUM(I106:I108) -> 1 | ... AF105: =SUM(AF106:AF108) -> 4
A106: Amazon Orders UK | B106: 1 | C106: 0 | D106: 1 | E106: 0 | F106: 0 | G106: 1 | H106: 0 | I106: 0 | J106: 0 | K106: 1 | L106: 0 | M106: 1 | N106: 0 | O106: 1 | P106: 0 | Q106: 1 | R106: 1 | S106: 0 | T106: 1 | U106: 0 | V106: 1 | W106: 0 | X106: 0 | Y106: 0 | Z106: 0 | AA106: 0 | AB106: 0 | AC106: 1 | AD106: 0 | AE106: 0 | AF106: 1
A107: Amazon Orders FR | B107: 0 | C107: 0 | D107: 0 | E107: 1 | F107: 1 | G107: 0 | H107: 0 | I107: 0 | J107: 0 | K107: 1 | L107: 1 | M107: 0 | N107: 0 | O107: 0 | P107: 0 | Q107: 0 | R107: 1 | S107: 0 | T107: 0 | U107: 0 | V107: 0 | W107: 2 | X107: 0 | Y107: 2 | Z107: 0 | AA107: 2 | AB107: 1 | AC107: 1 | AD107: 0 | AE107: 2 | AF107: 1
A108: Amazon Orders GER | B108: 0 | C108: 0 | D108: 1 | E108: 0 | F108: 1 | G108: 0 | H108: 2 | I108: 1 | J108: 1 | K108: 1 | L108: 2 | M108: 0 | N108: 0 | O108: 1 | P108: 0 | Q108: 0 | R108: 1 | S108: 2 | T108: 0 | U108: 4 | V108: 1 | W108: 0 | X108: 1 | Y108: 4 | Z108: 2 | AA108: 2 | AB108: 3 | AC108: 1 | AD108: 0 | AE108: 1 | AF108: 2
...

Sheet DTC - P&L
A1: MAY | B1: 46143 | C1: 46144 | D1: 46145 | E1: 46146 | F1: 46147 | G1: 46148 | H1: 46149 | I1: 46150 | J1: 46151 | K1: 46152 | L1: 46153 | M1: 46154 | N1: 46155 | O1: 46156 | P1: 46157 | Q1: 46158 | R1: 46159 | S1: 46160 | T1: 46161 | U1: 46162 | V1: 46163 | W1: 46164 | X1: 46165 | Y1: 46166 | Z1: 46167 | AA1: 46168 | AB1: 46169 | AC1: 46170 | AD1: 46171 | AE1: 46172 | AF1: 46173
A2: DAY | B2: FRI | C2: SAT | D2: SUN | E2: MON | F2: TUE | G2: WED | H2: THU | I2: FRI | J2: SAT | K2: SUN | L2: MON | M2: TUE | N2: WED | O2: THU | P2: FRI | Q2: SAT | R2: SUN | S2: MON | T2: TUE | U2: WED | V2: THU | W2: FRI | X2: SAT | Y2: SUN | Z2: MON | AA2: TUE | AB2: WED | AC2: THU | AD2: FRI | AE2: SAT | AF2: SUN
A3: COMMENT
A4: Orders
A5: Meta | B5: 109 | C5: 231 | D5: 297 | E5: 281 | F5: 172 | G5: 166 | H5: 109 | I5: 100 | J5: 97 | K5: 103 | L5: 72 | M5: 72 | N5: 68 | O5: 485 | P5: 107 | Q5: 72 | R5: 145 | S5: 73 | T5: 148 | U5: 56 | V5: 42 | W5: 95 | X5: 129 | Y5: 158 | Z5: 160 | AA5: 60 | AB5: 57 | AC5: 33 | AD5: 32 | AE5: 39 | AF5: 29 | AG5: =SUM(B5:AF5) -> 3797
A6: Google | B6: 118 | C6: 146 | D6: 174 | E6: 158 | F6: 105 | G6: 90 | H6: 66 | I6: 78 | J6: 68 | K6: 67 | L6: 38 | M6: 38 | N6: 62 | O6: 132 | P6: 47 | Q6: 58 | R6: 65 | S6: 45 | T6: 47 | U6: 23 | V6: 41 | W6: 65 | X6: 69 | Y6: 81 | Z6: 90 | AA6: 31 | AB6: 31 | AC6: 30 | AD6: 40 | AE6: 55 | AF6: 56 | AG6: =SUM(B6:AF6) -> 2214
A7: TikTok | B7: 0 | C7: 0 | D7: 0 | E7: 0 | F7: 0 | G7: 0 | H7: 0 | I7: 0 | J7: 0 | K7: 0 | L7: 0 | M7: 0 | N7: 0 | O7: 0 | P7: 0 | Q7: 0 | R7: 0 | S7: 0 | T7: 0 | U7: 0 | V7: 0 | W7: 0 | X7: 0 | Y7: 0 | Z7: 0 | AA7: 0 | AB7: 0 | AC7: 0 | AD7: 0 | AE7: 0 | AF7: 0 | AG7: =SUM(B7:AF7) -> 0
A8: Bing | B8: 0 | C8: 0 | D8: 0 | E8: 0 | F8: 0 | G8: 0 | H8: 0 | I8: 0 | J8: 0 | K8: 0 | L8: 0 | M8: 0 | N8: 0 | O8: 0 | P8: 0 | Q8: 0 | R8: 0 | S8: 0 | T8: 0 | U8: 0 | V8: 0 | W8: 0 | X8: 0 | Y8: 0 | Z8: 0 | AA8: 0 | AB8: 0 | AC8: 0 | AD8: 0 | AE8: 0 | AF8: 0 | AG8: =SUM(B8:AF8) -> 0 | AH8: 0
A9: Email | B9: 0 | C9: 0 | D9: 0 | E9: 0 | F9: 0 | G9: 0 | H9: 0 | I9: 0 | J9: 0 | K9: 0 | L9: 0 | M9: 0 | N9: 0 | O9: 0 | P9: 0 | Q9: 0 | R9: 0 | S9: 0 | T9: 0 | U9: 0 | V9: 0 | W9: 0 | X9: 0 | Y9: 0 | Z9: 0 | AA9: 0 | AB9: 0 | AC9: 0 | AD9: 0 | AE9: 0 | AF9: 0 | AG9: =SUM(B9:AF9) -> 0
A10: All | B10: =SUM(B5:B9) -> 227 | C10: =SUM(C5:C9) -> 377 | D10: =SUM(D5:D9) -> 471 | E10: =SUM(E5:E9) -> 439 | F10: =SUM(F5:F9) -> 277 | G10: =SUM(G5:G9) -> 256 | H10: =SUM(H5:H9) -> 175 | I10: =SUM(I5:I9) -> 178 | ... AF10: =SUM(AF5:AF9) -> 85 | AG10: =SUM(B10:AF10) -> 6011
A14: Revenue
A15: Meta | B15: 25615.62 | C15: 56722.29 | D15: 73355.35 | E15: 71596.63 | F15: 42032.19 | G15: 44356.49 | H15: 27859.84 | I15: 26043.36 | J15: 26280.77 | K15: 24620.88 | L15: 17943.98 | M15: 16005.09 | N15: 15768.1 | O15: 115339.77 | P15: 25529 | Q15: 16794.27 | R15: 35542.96 | S15: 18103.3 | T15: 36132.27 | U15: 12698.35 | V15: 10134.97 | W15: 22778.84 | X15: 31347.84 | Y15: 35652.08 | Z15: 37810.73 | AA15: 15138.69 | AB15: 16190.51 | AC15: 7430.86 | AD15: 8026.23 | AE15: 9616.05 | AF15: 7765.19 | AG15: =SUM(B15:AF15) -> 930232.5
A16: Google | B16: 28121.71 | C16: 35894.93 | D16: 42418.39 | E16: 39691.75 | F16: 25877.86 | G16: 23228.08 | H16: 16781.96 | I16: 19509.29 | J16: 16897.91 | K16: 16563.38 | L16: 9077.8 | M16: 8711.5 | N16: 15661.29 | O16: 33314.72 | P16: 10211.6 | Q16: 13068.75 | R16: 15954.72 | S16: 11408.73 | T16: 11786.41 | U16: 4991.17 | V16: 9512.76 | W16: 14982.69 | X16: 16936.1 | Y16: 18304.71 | Z16: 21340.33 | AA16: 7438.27 | AB16: 8786.16 | AC16: 7292 | AD16: 9482.4 | AE16: 13685.34 | AF16: 14223.17 | AG16: =SUM(B16:AF16) -> 541155.88
A17: TikTok | B17: 0 | C17: 0 | D17: 0 | E17: 0 | F17: 0 | G17: 0 | H17: 0 | I17: 0 | J17: 0 | K17: 0 | L17: 0 | M17: 0 | N17: 0 | O17: 0 | P17: 0 | Q17: 0 | R17: 0 | S17: 0 | T17: 0 | U17: 0 | V17: 0 | W17: 0 | X17: 0 | Y17: 0 | Z17: 0 | AA17: 0 | AB17: 0 | AC17: 0 | AD17: 0 | AE17: 0 | AF17: 0 | AG17: =SUM(B17:AF17) -> 0
A18: Bing | B18: 0 | C18: 0 | D18: 0 | E18: 0 | F18: 0 | G18: 0 | H18: 0 | I18: 0 | J18: 0 | K18: 0 | L18: 0 | M18: 0 | N18: 0 | O18: 0 | P18: 0 | Q18: 0 | R18: 0 | S18: 0 | T18: 0 | U18: 0 | V18: 0 | W18: 0 | X18: 0 | Y18: 0 | Z18: 0 | AA18: 0 | AB18: 0 | AC18: 0 | AD18: 0 | AE18: 0 | AF18: 0 | AG18: =SUM(B18:AF18) -> 0
A19: Email | B19: 0 | C19: 0 | D19: 0 | E19: 0 | F19: 0 | G19: 0 | H19: 0 | I19: 0 | J19: 0 | K19: 0 | L19: 0 | M19: 0 | N19: 0 | O19: 0 | P19: 0 | Q19: 0 | R19: 0 | S19: 0 | T19: 0 | U19: 0 | V19: 0 | W19: 0 | X19: 0 | Y19: 0 | Z19: 0 | AA19: 0 | AB19: 0 | AC19: 0 | AD19: 0 | AE19: 0 | AF19: 0 | AG19: =SUM(B19:AF19) -> 0
A20: All | B20: =SUM(B15:B19) -> 53737.33 | C20: =SUM(C15:C19) -> 92617.22 | D20: =SUM(D15:D19) -> 115773.74 | E20: =SUM(E15:E19) -> 111288.38 | F20: =SUM(F15:F19) -> 67910.05 | G20: =SUM(G15:G19) -> 67584.57 | H20: =SUM(H15:H19) -> 44641.8 | I20: =SUM(I15:I19) -> 45552.65 | ... AF20: =SUM(AF15:AF19) -> 21988.36 | AG20: =SUM(B20:AF20) -> 1471388.4
A24: Media Cost
A25: Meta | B25: =Summary!B134 -> 9467.17 | C25: =Summary!C134 -> 21100.71 | D25: =Summary!D134 -> 29005.81 | E25: =Summary!E134 -> 26025 | F25: =Summary!F134 -> 24029.71 | G25: =Summary!G134 -> 22817.76 | H25: =Summary!H134 -> 19778.33 | I25: =Summary!I134 -> 13804.36 | ... AF25: =Summary!AF134 -> 3601.74 | AG25: =SUM(B25:AF25) -> 420259.06
A26: Google | B26: =Summary!B137 -> 3405.83 | C26: =Summary!C137 -> 4906.54 | D26: =Summary!D137 -> 4839.04 | E26: =Summary!E137 -> 3636.27 | F26: =Summary!F137 -> 3901.91 | G26: =Summary!G137 -> 3962.24 | H26: =Summary!H137 -> 3381.05 | I26: =Summary!I137 -> 2950.12 | ... AF26: =Summary!AF137 -> 1348.54 | AG26: =SUM(B26:AF26) -> 84752.31
A27: TikTok | B27: =Summary!B141 -> 0 | C27: =Summary!C141 -> 0 | D27: =Summary!D141 -> 0 | E27: =Summary!E141 -> 0 | F27: =Summary!F141 -> 0 | G27: =Summary!G141 -> 0 | H27: =Summary!H141 -> 0 | I27: =Summary!I141 -> 0 | ... AF27: =Summary!AF141 -> 0 | AG27: =SUM(B27:AF27) -> 1355.06
A28: Bing | B28: =Summary!B140 -> 0 | C28: =Summary!C140 -> 0 | D28: =Summary!D140 -> 0 | E28: =Summary!E140 -> 0 | F28: =Summary!F140 -> 0 | G28: =Summary!G140 -> 0 | H28: =Summary!H140 -> 0 | I28: =Summary!I140 -> 0 | ... AF28: =Summary!AF140 -> 0 | AG28: =SUM(B28:AF28) -> 0
A29: All | B29: =SUM(B25:B28) -> 12873 | C29: =SUM(C25:C28) -> 26007.25 | D29: =SUM(D25:D28) -> 33844.85 | E29: =SUM(E25:E28) -> 29661.27 | F29: =SUM(F25:F28) -> 27931.62 | G29: =SUM(G25:G28) -> 26780 | H29: =SUM(H25:H28) -> 23159.38 | I29: =SUM(I25:I28) -> 16754.48 | ... AF29: =SUM(AF25:AF28) -> 4950.28 | AG29: =SUM(B29:AF29) -> 506366.43
A33: Revenue
A34: Revenue Woocommerce (Platform) | B34: =Summary!B12 -> 88749.976 | C34: =Summary!C12 -> 180837.88 | D34: =Summary!D12 -> 181335.67 | E34: =Summary!E12 -> 167865.39 | F34: =Summary!F12 -> 139488.21 | G34: =Summary!G12 -> 114657.39 | H34: =Summary!H12 -> 83199.327 | I34: =Summary!I12 -> 77885.256 | ... AF34: =Summary!AF12 -> 56960.976 | AG34: =SUM(B34:AF34) -> 3147844.5
A35: Revenue w/o renewals | B35: ='DTC US&CA - P&L'!B6+'DTC EU - P&L'!B6 -> 75232.873 | C35: ='DTC US&CA - P&L'!C6+'DTC EU - P&L'!C6 -> 117808.15 | D35: ='DTC US&CA - P&L'!D6+'DTC EU - P&L'!D6 -> 152360.45 | E35: ='DTC US&CA - P&L'!E6+'DTC EU - P&L'!E6 -> 141719.12 | F35: ='DTC US&CA - P&L'!F6+'DTC EU - P&L'!F6 -> 97806.9 | G35: ='DTC US&CA - P&L'!G6+'DTC EU - P&L'!G6 -> 91646.456 | H35: ='DTC US&CA - P&L'!H6+'DTC EU - P&L'!H6 -> 67272.811 | I35: ='DTC US&CA - P&L'!I6+'DTC EU - P&L'!I6 -> 60837.855 | ... AF35: ='DTC US&CA - P&L'!AF6+'DTC EU - P&L'!AF6 -> 30514.253 | AG35: =SUM(B35:AF35) -> 2452183.5
A37: Orders
A38: Orders Woocommerce (Platform) | B38: =Summary!B89 -> 455 | C38: =Summary!C89 -> 1103 | D38: =Summary!D89 -> 926 | E38: =Summary!E89 -> 830 | F38: =Summary!F89 -> 813 | G38: =Summary!G89 -> 578 | H38: =Summary!H89 -> 420 | I38: =Summary!I89 -> 418 | ... AF38: =Summary!AF89 -> 395 | AG38: =SUM(B38:AF38) -> 16996
A39: Orders w/o renewals | B39: ='DTC US&CA - P&L'!B10+'DTC EU - P&L'!B10 -> 314 | C39: ='DTC US&CA - P&L'!C10+'DTC EU - P&L'!C10 -> 481 | D39: ='DTC US&CA - P&L'!D10+'DTC EU - P&L'!D10 -> 631 | E39: ='DTC US&CA - P&L'!E10+'DTC EU - P&L'!E10 -> 569 | F39: ='DTC US&CA - P&L'!F10+'DTC EU - P&L'!F10 -> 398 | G39: ='DTC US&CA - P&L'!G10+'DTC EU - P&L'!G10 -> 343 | H39: ='DTC US&CA - P&L'!H10+'DTC EU - P&L'!H10 -> 256 | I39: ='DTC US&CA - P&L'!I10+'DTC EU - P&L'!I10 -> 243 | ... AF39: ='DTC US&CA - P&L'!AF10+'DTC EU - P&L'!AF10 -> 125 | AG39: =SUM(B39:AF39) -> 9977
A43: Breakdown
A44: - Hardware | B44: =Summary!B14+Summary!B21 -> 56667.615 | C44: =Summary!C14+Summary!C21 -> 89314.385 | D44: =Summary!D14+Summary!D21 -> 114170.89 | E44: =Summary!E14+Summary!E21 -> 106781.23 | F44: =Summary!F14+Summary!F21 -> 72983.906 | G44: =Summary!G14+Summary!G21 -> 70591.617 | H44: =Summary!H14+Summary!H21 -> 50468.893 | I44: =Summary!I14+Summary!I21 -> 45521.827 | ... AF44: =Summary!AF14+Summary!AF21 -> 22765.276 | AG44: =SUM(B44:AF44) -> 1859965.3
A45: - Add-ons | B45: =Summary!B15+Summary!B22 -> 3291.3038 | C45: =Summary!C15+Summary!C22 -> 5322.5513 | D45: =Summary!D15+Summary!D22 -> 7496.6795 | E45: =Summary!E15+Summary!E22 -> 6161.6978 | F45: =Summary!F15+Summary!F22 -> 4935.4427 | G45: =Summary!G15+Summary!G22 -> 3488.2 | H45: =Summary!H15+Summary!H22 -> 3861.2 | I45: =Summary!I15+Summary!I22 -> 3813.3877 | ... AF45: =Summary!AF15+Summary!AF22 -> 2281.0603 | AG45: =SUM(B45:AF45) -> 130604.03
A46: - Merch | B46: =Summary!B16+Summary!B23 -> 0 | C46: =Summary!C16+Summary!C23 -> 0 | D46: =Summary!D16+Summary!D23 -> 0 | E46: =Summary!E16+Summary!E23 -> 0 | F46: =Summary!F16+Summary!F23 -> 0 | G46: =Summary!G16+Summary!G23 -> 0 | H46: =Summary!H16+Summary!H23 -> 0 | I46: =Summary!I16+Summary!I23 -> 0 | ... AF46: =Summary!AF16+Summary!AF23 -> 0 | AG46: =SUM(B46:AF46) -> 0
A47: - Yearly Pro Subscription | B47: ='DTC US&CA - P&L'!B18+Summary!B30 -> 13527.823 | C47: ='DTC US&CA - P&L'!C18+Summary!C30 -> 61379.187 | D47: ='DTC US&CA - P&L'!D18+Summary!D30 -> 28532.457 | E47: ='DTC US&CA - P&L'!E18+Summary!E30 -> 25377.945 | F47: ='DTC US&CA - P&L'!F18+Summary!F30 -> 40262.74 | G47: ='DTC US&CA - P&L'!G18+Summary!G30 -> 22447.487 | H47: ='DTC US&CA - P&L'!H18+Summary!H30 -> 15937.278 | I47: ='DTC US&CA - P&L'!I18+Summary!I30 -> 16722.427 | ... AF47: ='DTC US&CA - P&L'!AF18+Summary!AF30 -> 25953.729 | AG47: =SUM(B47:AF47) -> 677946.67
A48: - Taxes | B48: =Summary!B17+Summary!B24+Summary!B28+Summary!B31 -> 5236.6276 | C48: =Summary!C17+Summary!C24+Summary!C28+Summary!C31 -> 9497.4453 | D48: =Summary!D17+Summary!D24+Summary!D28+Summary!D31 -> 10753.031 | E48: =Summary!E17+Summary!E24+Summary!E28+Summary!E31 -> 10226.975 | F48: =Summary!F17+Summary!F24+Summary!F28+Summary!F31 -> 7808.4032 | G48: =Summary!G17+Summary!G24+Summary!G28+Summary!G31 -> 6706.9964 | H48: =Summary!H17+Summary!H24+Summary!H28+Summary!H31 -> 4713.2957 | I48: =Summary!I17+Summary!I24+Summary!I28+Summary!I31 -> 4499.4025 | ... AF48: =Summary!AF17+Summary!AF24+Summary!AF28+Summary!AF31 -> 2875.5702 | AG48: =SUM(B48:AF48) -> 182237.46
A49: - Shipping | B49: =Summary!B18+Summary!B25 -> 8167.536 | C49: =Summary!C18+Summary!C25 -> 12745.596 | D49: =Summary!D18+Summary!D25 -> 16404.599 | E49: =Summary!E18+Summary!E25 -> 15179.61 | F49: =Summary!F18+Summary!F25 -> 10423.247 | G49: =Summary!G18+Summary!G25 -> 8944.3325 | H49: =Summary!H18+Summary!H25 -> 6599.47 | I49: =Summary!I18+Summary!I25 -> 5988.8815 | ... AF49: =Summary!AF18+Summary!AF25 -> 3085.34 | AG49: =SUM(B49:AF49) -> 259537.09
A50: - Gift Bag | B50: =Summary!B19 -> 1859.07 | C50: =Summary!C19 -> 2578.71 | D50: =Summary!D19 -> 3978.01 | E50: =Summary!E19 -> 4137.93 | F50: =Summary!F19 -> 3074.47 | G50: =Summary!G19 -> 2478.76 | H50: =Summary!H19 -> 1619.19 | I50: =Summary!I19 -> 1339.33 | ... AF50: =Summary!AF19 -> 0 | AG50: =SUM(B50:AF50) -> 37553.89
A51: SUM | B51: =SUM(B44:B50) -> 88749.976 | C51: =SUM(C44:C50) -> 180837.88 | D51: =SUM(D44:D50) -> 181335.67 | E51: =SUM(E44:E50) -> 167865.39 | F51: =SUM(F44:F50) -> 139488.21 | G51: =SUM(G44:G50) -> 114657.39 | H51: =SUM(H44:H50) -> 83199.327 | I51: =SUM(I44:I50) -> 77885.256 | ... AF51: =SUM(AF44:AF50) -> 56960.976 | AG51: =SUM(B51:AF51) -> 3147844.5
A55: Units Sold (Gross) | B55: =sum(B56,B67) -> 304 | C55: =sum(C56,C67) -> 479 | D55: =sum(D56,D67) -> 617 | E55: =sum(E56,E67) -> 568 | F55: =sum(F56,F67) -> 390 | G55: =sum(G56,G67) -> 337 | H55: =sum(H56,H67) -> 242 | I55: =sum(I56,I67) -> 218 | ... AF55: =sum(AF56,AF67) -> 108 | AG55: =SUM(B55:AF55) -> 9652
A56: BB1 | B56: =sum(B60,B65) -> 304 | C56: =sum(C60,C65) -> 479 | D56: =sum(D60,D65) -> 617 | E56: =sum(E60,E65) -> 568 | F56: =sum(F60,F65) -> 390 | G56: =sum(G60,G65) -> 337 | H56: =sum(H60,H65) -> 242 | I56: =sum(I60,I65) -> 218 | ... AF56: =sum(AF60,AF65) -> 108 | AG56: =SUM(B56:AF56) -> 6702
A57: Smart Bird Feeder PRO | B57: =sum('DTC US&CA - P&L'!B28,'DTC EU - P&L'!B29) -> 0 | C57: =sum('DTC US&CA - P&L'!C28,'DTC EU - P&L'!C29) -> 0 | D57: =sum('DTC US&CA - P&L'!D28,'DTC EU - P&L'!D29) -> 0 | E57: =sum('DTC US&CA - P&L'!E28,'DTC EU - P&L'!E29) -> 0 | F57: =sum('DTC US&CA - P&L'!F28,'DTC EU - P&L'!F29) -> 0 | G57: =sum('DTC US&CA - P&L'!G28,'DTC EU - P&L'!G29) -> 0 | H57: =sum('DTC US&CA - P&L'!H28,'DTC EU - P&L'!H29) -> 0 | I57: =sum('DTC US&CA - P&L'!I28,'DTC EU - P&L'!I29) -> 0 | ... AF57: =sum('DTC US&CA - P&L'!AF28,'DTC EU - P&L'!AF29) -> 0 | AG57: =SUM(B57:AF57) -> 0
A58: Smart Bird Feeder PRO Solar | B58: =sum('DTC US&CA - P&L'!B29,'DTC EU - P&L'!B30) -> 227 | C58: =sum('DTC US&CA - P&L'!C29,'DTC EU - P&L'!C30) -> 355 | D58: =sum('DTC US&CA - P&L'!D29,'DTC EU - P&L'!D30) -> 472 | E58: =sum('DTC US&CA - P&L'!E29,'DTC EU - P&L'!E30) -> 448 | F58: =sum('DTC US&CA - P&L'!F29,'DTC EU - P&L'!F30) -> 308 | G58: =sum('DTC US&CA - P&L'!G29,'DTC EU - P&L'!G30) -> 236 | H58: =sum('DTC US&CA - P&L'!H29,'DTC EU - P&L'!H30) -> 174 | I58: =sum('DTC US&CA - P&L'!I29,'DTC EU - P&L'!I30) -> 152 | ... AF58: =sum('DTC US&CA - P&L'!AF29,'DTC EU - P&L'!AF30) -> 70 | AG58: =SUM(B58:AF58) -> 4880
A59: Smart Bird Feeder PRO Solar with PEX (Retail SKU) | B59: =sum('DTC US&CA - P&L'!B30,'DTC EU - P&L'!B31) -> 0 | C59: =sum('DTC US&CA - P&L'!C30,'DTC EU - P&L'!C31) -> 0 | D59: =sum('DTC US&CA - P&L'!D30,'DTC EU - P&L'!D31) -> 0 | E59: =sum('DTC US&CA - P&L'!E30,'DTC EU - P&L'!E31) -> 0 | F59: =sum('DTC US&CA - P&L'!F30,'DTC EU - P&L'!F31) -> 0 | G59: =sum('DTC US&CA - P&L'!G30,'DTC EU - P&L'!G31) -> 0 | H59: =sum('DTC US&CA - P&L'!H30,'DTC EU - P&L'!H31) -> 0 | I59: =sum('DTC US&CA - P&L'!I30,'DTC EU - P&L'!I31) -> 0 | ... AF59: =sum('DTC US&CA - P&L'!AF30,'DTC EU - P&L'!AF31) -> 0 | AG59: =SUM(B59:AF59) -> 0
A60: SUM (BB1 SBF) | B60: =sum(B57:B59) -> 227 | C60: =sum(C57:C59) -> 355 | D60: =sum(D57:D59) -> 472 | E60: =sum(E57:E59) -> 448 | F60: =sum(F57:F59) -> 308 | G60: =sum(G57:G59) -> 236 | H60: =sum(H57:H59) -> 174 | I60: =sum(I57:I59) -> 152 | ... AF60: =sum(AF57:AF59) -> 70 | AG60: =SUM(B60:AF60) -> 4880
A62: Smart Hummingbird Feeder PRO | B62: =sum('DTC US&CA - P&L'!B33,'DTC EU - P&L'!B34) -> 0 | C62: =sum('DTC US&CA - P&L'!C33,'DTC EU - P&L'!C34) -> 0 | D62: =sum('DTC US&CA - P&L'!D33,'DTC EU - P&L'!D34) -> 0 | E62: =sum('DTC US&CA - P&L'!E33,'DTC EU - P&L'!E34) -> 0 | F62: =sum('DTC US&CA - P&L'!F33,'DTC EU - P&L'!F34) -> 0 | G62: =sum('DTC US&CA - P&L'!G33,'DTC EU - P&L'!G34) -> 0 | H62: =sum('DTC US&CA - P&L'!H33,'DTC EU - P&L'!H34) -> 0 | I62: =sum('DTC US&CA - P&L'!I33,'DTC EU - P&L'!I34) -> 1 | ... AF62: =sum('DTC US&CA - P&L'!AF33,'DTC EU - P&L'!AF34) -> 0 | AG62: =SUM(B62:AF62) -> 2
A63: Smart Hummingbird Feeder PRO Solar | B63: =sum('DTC US&CA - P&L'!B34,'DTC EU - P&L'!B35) -> 5 | C63: =sum('DTC US&CA - P&L'!C34,'DTC EU - P&L'!C35) -> 0 | D63: =sum('DTC US&CA - P&L'!D34,'DTC EU - P&L'!D35) -> 0 | E63: =sum('DTC US&CA - P&L'!E34,'DTC EU - P&L'!E35) -> 4 | F63: =sum('DTC US&CA - P&L'!F34,'DTC EU - P&L'!F35) -> 1 | G63: =sum('DTC US&CA - P&L'!G34,'DTC EU - P&L'!G35) -> 4 | H63: =sum('DTC US&CA - P&L'!H34,'DTC EU - P&L'!H35) -> 0 | I63: =sum('DTC US&CA - P&L'!I34,'DTC EU - P&L'!I35) -> 1 | ... AF63: =sum('DTC US&CA - P&L'!AF34,'DTC EU - P&L'!AF35) -> 0 | AG63: =SUM(B63:AF63) -> 17
A64: Smart Hummingbird Feeder PRO Solar (Retail SKU) | B64: =sum('DTC US&CA - P&L'!B35,'DTC EU - P&L'!B36) -> 72 | C64: =sum('DTC US&CA - P&L'!C35,'DTC EU - P&L'!C36) -> 124 | D64: =sum('DTC US&CA - P&L'!D35,'DTC EU - P&L'!D36) -> 145 | E64: =sum('DTC US&CA - P&L'!E35,'DTC EU - P&L'!E36) -> 116 | F64: =sum('DTC US&CA - P&L'!F35,'DTC EU - P&L'!F36) -> 81 | G64: =sum('DTC US&CA - P&L'!G35,'DTC EU - P&L'!G36) -> 97 | H64: =sum('DTC US&CA - P&L'!H35,'DTC EU - P&L'!H36) -> 68 | I64: =sum('DTC US&CA - P&L'!I35,'DTC EU - P&L'!I36) -> 64 | ... AF64: =sum('DTC US&CA - P&L'!AF35,'DTC EU - P&L'!AF36) -> 38 | AG64: =SUM(B64:AF64) -> 1803
A65: SUM (BB1 HBF) | B65: =sum(B62:B64) -> 77 | C65: =sum(C62:C64) -> 124 | D65: =sum(D62:D64) -> 145 | E65: =sum(E62:E64) -> 120 | F65: =sum(F62:F64) -> 82 | G65: =sum(G62:G64) -> 101 | H65: =sum(H62:H64) -> 68 | I65: =sum(I62:I64) -> 66 | ... AF65: =sum(AF62:AF64) -> 38 | AG65: =SUM(B65:AF65) -> 1822
A67: BB2 | B67: =sum(B71,B75,B80) -> 0 | C67: =sum(C71,C75,C80) -> 0 | D67: =sum(D71,D75,D80) -> 0 | E67: =sum(E71,E75,E80) -> 0 | F67: =sum(F71,F75,F80) -> 0 | G67: =sum(G71,G75,G80) -> 0 | H67: =sum(H71,H75,H80) -> 0 | I67: =sum(I71,I75,I80) -> 0 | ... AF67: =sum(AF71,AF75,AF80) -> 0 | AG67: =SUM(B67:AF67) -> 2950
A68: Birdbuddy 2 | N68: =sum('DTC US&CA - P&L'!N39,'DTC EU - P&L'!N40) -> 22 | O68: =sum('DTC US&CA - P&L'!O39,'DTC EU - P&L'!O40) -> 1728 | P68: =sum('DTC US&CA - P&L'!P39,'DTC EU - P&L'!P40) -> 179 | Q68: =sum('DTC US&CA - P&L'!Q39,'DTC EU - P&L'!Q40) -> 96 | R68: =sum('DTC US&CA - P&L'!R39,'DTC EU - P&L'!R40) -> 475 | S68: =sum('DTC US&CA - P&L'!S39,'DTC EU - P&L'!S40) -> 102 | T68: =sum('DTC US&CA - P&L'!T39,'DTC EU - P&L'!T40) -> 347 | U68: =sum('DTC US&CA - P&L'!U39,'DTC EU - P&L'!U40) -> 1 | ... AF68: =sum('DTC US&CA - P&L'!AF39,'DTC EU - P&L'!AF40) -> 0 | AG68: =SUM(B68:AF68) -> 2950
A69: Birdbuddy 2 PRO | AG69: =SUM(B69:AF69) -> 0
A70: Birdbuddy 2 Retail SKU | AG70: =SUM(B70:AF70) -> 0
A71: SUM (BB2 SBF) | B71: =sum(B68:B70) -> 0 | C71: =sum(C68:C70) -> 0 | D71: =sum(D68:D70) -> 0 | E71: =sum(E68:E70) -> 0 | F71: =sum(F68:F70) -> 0 | G71: =sum(G68:G70) -> 0 | H71: =sum(H68:H70) -> 0 | I71: =sum(I68:I70) -> 0 | ... AF71: =sum(AF68:AF70) -> 0 | AG71: =SUM(B71:AF71) -> 2950
A73: Birdbuddy 2 Nectar | AG73: =SUM(B73:AF73) -> 0
A74: Birdbuddy 2 Nectar PRO | AG74: =SUM(B74:AF74) -> 0
A75: SUM (BB2 HBF) | B75: =sum(B73:B74) -> 0 | C75: =sum(C73:C74) -> 0 | D75: =sum(D73:D74) -> 0 | E75: =sum(E73:E74) -> 0 | F75: =sum(F73:F74) -> 0 | G75: =sum(G73:G74) -> 0 | H75: =sum(H73:H74) -> 0 | I75: =sum(I73:I74) -> 0 | ... AF75: =sum(AF73:AF74) -> 0 | AG75: =SUM(B75:AF75) -> 0
A77: Birdbuddy 2 Mini non Solar | AG77: =SUM(B77:AF77) -> 0
A78: Birdbuddy 2 Mini Solar | AG78: =SUM(B78:AF78) -> 0
A79: BB2 Mini Retail SKU | AG79: =SUM(B79:AF79) -> 0
A80: SUM (BB2 MINI) | B80: =sum(B77:B79) -> 0 | C80: =sum(C77:C79) -> 0 | D80: =sum(D77:D79) -> 0 | E80: =sum(E77:E79) -> 0 | F80: =sum(F77:F79) -> 0 | G80: =sum(G77:G79) -> 0 | H80: =sum(H77:H79) -> 0 | I80: =sum(I77:I79) -> 0 | ... AF80: =sum(AF77:AF79) -> 0 | AG80: =SUM(B80:AF80) -> 0
A82: Wall Mount | B82: =sum('DTC US&CA - P&L'!B53,'DTC EU - P&L'!B54) -> 1 | C82: =sum('DTC US&CA - P&L'!C53,'DTC EU - P&L'!C54) -> 0 | D82: =sum('DTC US&CA - P&L'!D53,'DTC EU - P&L'!D54) -> 1 | E82: =sum('DTC US&CA - P&L'!E53,'DTC EU - P&L'!E54) -> 1 | F82: =sum('DTC US&CA - P&L'!F53,'DTC EU - P&L'!F54) -> 0 | G82: =sum('DTC US&CA - P&L'!G53,'DTC EU - P&L'!G54) -> 0 | H82: =sum('DTC US&CA - P&L'!H53,'DTC EU - P&L'!H54) -> 0 | I82: =sum('DTC US&CA - P&L'!I53,'DTC EU - P&L'!I54) -> 2 | ... AF82: =sum('DTC US&CA - P&L'!AF53,'DTC EU - P&L'!AF54) -> 3 | AG82: =SUM(B82:AF82) -> 25
A83: Suet Ball Holder | B83: =sum('DTC US&CA - P&L'!B54,'DTC EU - P&L'!B55) -> 156 | C83: =sum('DTC US&CA - P&L'!C54,'DTC EU - P&L'!C55) -> 243 | D83: =sum('DTC US&CA - P&L'!D54,'DTC EU - P&L'!D55) -> 359 | E83: =sum('DTC US&CA - P&L'!E54,'DTC EU - P&L'!E55) -> 344 | F83: =sum('DTC US&CA - P&L'!F54,'DTC EU - P&L'!F55) -> 220 | G83: =sum('DTC US&CA - P&L'!G54,'DTC EU - P&L'!G55) -> 180 | H83: =sum('DTC US&CA - P&L'!H54,'DTC EU - P&L'!H55) -> 134 | I83: =sum('DTC US&CA - P&L'!I54,'DTC EU - P&L'!I55) -> 121 | ... AF83: =sum('DTC US&CA - P&L'!AF54,'DTC EU - P&L'!AF55) -> 55 | AG83: =SUM(B83:AF83) -> 3945
A84: 3-in-1 Nutrition Set - Blue | B84: =sum('DTC US&CA - P&L'!B55,'DTC EU - P&L'!B56) -> 5 | C84: =sum('DTC US&CA - P&L'!C55,'DTC EU - P&L'!C56) -> 23 | D84: =sum('DTC US&CA - P&L'!D55,'DTC EU - P&L'!D56) -> 23 | E84: =sum('DTC US&CA - P&L'!E55,'DTC EU - P&L'!E56) -> 29 | F84: =sum('DTC US&CA - P&L'!F55,'DTC EU - P&L'!F56) -> 12 | G84: =sum('DTC US&CA - P&L'!G55,'DTC EU - P&L'!G56) -> 6 | H84: =sum('DTC US&CA - P&L'!H55,'DTC EU - P&L'!H56) -> 21 | I84: =sum('DTC US&CA - P&L'!I55,'DTC EU - P&L'!I56) -> 20 | ... AF84: =sum('DTC US&CA - P&L'!AF55,'DTC EU - P&L'!AF56) -> 10 | AG84: =SUM(B84:AF84) -> 656
A85: 3-in-1 Nutrition Set - Yellow | B85: =sum('DTC US&CA - P&L'!B56,'DTC EU - P&L'!B57) -> 0 | C85: =sum('DTC US&CA - P&L'!C56,'DTC EU - P&L'!C57) -> 1 | D85: =sum('DTC US&CA - P&L'!D56,'DTC EU - P&L'!D57) -> 1 | E85: =sum('DTC US&CA - P&L'!E56,'DTC EU - P&L'!E57) -> 0 | F85: =sum('DTC US&CA - P&L'!F56,'DTC EU - P&L'!F57) -> 0 | G85: =sum('DTC US&CA - P&L'!G56,'DTC EU - P&L'!G57) -> 0 | H85: =sum('DTC US&CA - P&L'!H56,'DTC EU - P&L'!H57) -> 1 | I85: =sum('DTC US&CA - P&L'!I56,'DTC EU - P&L'!I57) -> 0 | ... AF85: =sum('DTC US&CA - P&L'!AF56,'DTC EU - P&L'!AF57) -> 0 | AG85: =SUM(B85:AF85) -> 23
A86: Solar Roof Single - Blue | B86: =sum('DTC US&CA - P&L'!B57,'DTC EU - P&L'!B58) -> 0 | C86: =sum('DTC US&CA - P&L'!C57,'DTC EU - P&L'!C58) -> 0 | D86: =sum('DTC US&CA - P&L'!D57,'DTC EU - P&L'!D58) -> 0 | E86: =sum('DTC US&CA - P&L'!E57,'DTC EU - P&L'!E58) -> 0 | F86: =sum('DTC US&CA - P&L'!F57,'DTC EU - P&L'!F58) -> 0 | G86: =sum('DTC US&CA - P&L'!G57,'DTC EU - P&L'!G58) -> 0 | H86: =sum('DTC US&CA - P&L'!H57,'DTC EU - P&L'!H58) -> 0 | I86: =sum('DTC US&CA - P&L'!I57,'DTC EU - P&L'!I58) -> 0 | ... AF86: =sum('DTC US&CA - P&L'!AF57,'DTC EU - P&L'!AF58) -> 0 | AG86: =SUM(B86:AF86) -> 0
A87: Solar Roof Single - Yellow | B87: =sum('DTC US&CA - P&L'!B58,'DTC EU - P&L'!B59) -> 0 | C87: =sum('DTC US&CA - P&L'!C58,'DTC EU - P&L'!C59) -> 0 | D87: =sum('DTC US&CA - P&L'!D58,'DTC EU - P&L'!D59) -> 0 | E87: =sum('DTC US&CA - P&L'!E58,'DTC EU - P&L'!E59) -> 0 | F87: =sum('DTC US&CA - P&L'!F58,'DTC EU - P&L'!F59) -> 0 | G87: =sum('DTC US&CA - P&L'!G58,'DTC EU - P&L'!G59) -> 0 | H87: =sum('DTC US&CA - P&L'!H58,'DTC EU - P&L'!H59) -> 0 | I87: =sum('DTC US&CA - P&L'!I58,'DTC EU - P&L'!I59) -> 0 | ... AF87: =sum('DTC US&CA - P&L'!AF58,'DTC EU - P&L'!AF59) -> 0 | AG87: =SUM(B87:AF87) -> 0
A88: Perch Extender - Blue | B88: =sum('DTC US&CA - P&L'!B59,'DTC EU - P&L'!B60) -> 58 | C88: =sum('DTC US&CA - P&L'!C59,'DTC EU - P&L'!C60) -> 92 | D88: =sum('DTC US&CA - P&L'!D59,'DTC EU - P&L'!D60) -> 139 | E88: =sum('DTC US&CA - P&L'!E59,'DTC EU - P&L'!E60) -> 120 | F88: =sum('DTC US&CA - P&L'!F59,'DTC EU - P&L'!F60) -> 92 | G88: =sum('DTC US&CA - P&L'!G59,'DTC EU - P&L'!G60) -> 70 | H88: =sum('DTC US&CA - P&L'!H59,'DTC EU - P&L'!H60) -> 59 | I88: =sum('DTC US&CA - P&L'!I59,'DTC EU - P&L'!I60) -> 53 | ... AF88: =sum('DTC US&CA - P&L'!AF59,'DTC EU - P&L'!AF60) -> 34 | AG88: =SUM(B88:AF88) -> 2074
A89: Perch Extender - Yellow | B89: =sum('DTC US&CA - P&L'!B60,'DTC EU - P&L'!B61) -> 3 | C89: =sum('DTC US&CA - P&L'!C60,'DTC EU - P&L'!C61) -> 3 | D89: =sum('DTC US&CA - P&L'!D60,'DTC EU - P&L'!D61) -> 1 | E89: =sum('DTC US&CA - P&L'!E60,'DTC EU - P&L'!E61) -> 1 | F89: =sum('DTC US&CA - P&L'!F60,'DTC EU - P&L'!F61) -> 3 | G89: =sum('DTC US&CA - P&L'!G60,'DTC EU - P&L'!G61) -> 0 | H89: =sum('DTC US&CA - P&L'!H60,'DTC EU - P&L'!H61) -> 0 | I89: =sum('DTC US&CA - P&L'!I60,'DTC EU - P&L'!I61) -> 3 | ... AF89: =sum('DTC US&CA - P&L'!AF60,'DTC EU - P&L'!AF61) -> 1 | AG89: =SUM(B89:AF89) -> 64
A90: Solar Roof (HBF) | B90: =sum('DTC US&CA - P&L'!B61,'DTC EU - P&L'!B62) -> 0 | C90: =sum('DTC US&CA - P&L'!C61,'DTC EU - P&L'!C62) -> 0 | D90: =sum('DTC US&CA - P&L'!D61,'DTC EU - P&L'!D62) -> 0 | E90: =sum('DTC US&CA - P&L'!E61,'DTC EU - P&L'!E62) -> 0 | F90: =sum('DTC US&CA - P&L'!F61,'DTC EU - P&L'!F62) -> 0 | G90: =sum('DTC US&CA - P&L'!G61,'DTC EU - P&L'!G62) -> 0 | H90: =sum('DTC US&CA - P&L'!H61,'DTC EU - P&L'!H62) -> 0 | I90: =sum('DTC US&CA - P&L'!I61,'DTC EU - P&L'!I62) -> 0 | ... AF90: =sum('DTC US&CA - P&L'!AF61,'DTC EU - P&L'!AF62) -> 0 | AG90: =SUM(B90:AF90) -> 0
A91: Housing - only (HBF) | B91: =sum('DTC US&CA - P&L'!B62,'DTC EU - P&L'!B63) -> 9 | C91: =sum('DTC US&CA - P&L'!C62,'DTC EU - P&L'!C63) -> 10 | D91: =sum('DTC US&CA - P&L'!D62,'DTC EU - P&L'!D63) -> 16 | E91: =sum('DTC US&CA - P&L'!E62,'DTC EU - P&L'!E63) -> 8 | F91: =sum('DTC US&CA - P&L'!F62,'DTC EU - P&L'!F63) -> 12 | G91: =sum('DTC US&CA - P&L'!G62,'DTC EU - P&L'!G63) -> 8 | H91: =sum('DTC US&CA - P&L'!H62,'DTC EU - P&L'!H63) -> 9 | I91: =sum('DTC US&CA - P&L'!I62,'DTC EU - P&L'!I63) -> 10 | ... AF91: =sum('DTC US&CA - P&L'!AF62,'DTC EU - P&L'!AF63) -> 5 | AG91: =SUM(B91:AF91) -> 195
A92: Nature Station Bloom | B92: =sum('DTC US&CA - P&L'!B63,'DTC EU - P&L'!B64) -> 0 | C92: =sum('DTC US&CA - P&L'!C63,'DTC EU - P&L'!C64) -> 0 | D92: =sum('DTC US&CA - P&L'!D63,'DTC EU - P&L'!D64) -> 0 | E92: =sum('DTC US&CA - P&L'!E63,'DTC EU - P&L'!E64) -> 0 | F92: =sum('DTC US&CA - P&L'!F63,'DTC EU - P&L'!F64) -> 0 | G92: =sum('DTC US&CA - P&L'!G63,'DTC EU - P&L'!G64) -> 0 | H92: =sum('DTC US&CA - P&L'!H63,'DTC EU - P&L'!H64) -> 0 | I92: =sum('DTC US&CA - P&L'!I63,'DTC EU - P&L'!I64) -> 0 | ... AF92: =sum('DTC US&CA - P&L'!AF63,'DTC EU - P&L'!AF64) -> 0 | AG92: =SUM(B92:AF92) -> 0
A93: Nature Station Essential | B93: =sum('DTC US&CA - P&L'!B64,'DTC EU - P&L'!B65) -> 0 | C93: =sum('DTC US&CA - P&L'!C64,'DTC EU - P&L'!C65) -> 0 | D93: =sum('DTC US&CA - P&L'!D64,'DTC EU - P&L'!D65) -> 0 | E93: =sum('DTC US&CA - P&L'!E64,'DTC EU - P&L'!E65) -> 0 | F93: =sum('DTC US&CA - P&L'!F64,'DTC EU - P&L'!F65) -> 0 | G93: =sum('DTC US&CA - P&L'!G64,'DTC EU - P&L'!G65) -> 0 | H93: =sum('DTC US&CA - P&L'!H64,'DTC EU - P&L'!H65) -> 0 | I93: =sum('DTC US&CA - P&L'!I64,'DTC EU - P&L'!I65) -> 0 | ... AF93: =sum('DTC US&CA - P&L'!AF64,'DTC EU - P&L'!AF65) -> 0 | AG93: =SUM(B93:AF93) -> 0
A94: Pollinator Pot | B94: =sum('DTC US&CA - P&L'!B65,'DTC EU - P&L'!B66) -> 0 | C94: =sum('DTC US&CA - P&L'!C65,'DTC EU - P&L'!C66) -> 1 | D94: =sum('DTC US&CA - P&L'!D65,'DTC EU - P&L'!D66) -> 0 | E94: =sum('DTC US&CA - P&L'!E65,'DTC EU - P&L'!E66) -> 0 | F94: =sum('DTC US&CA - P&L'!F65,'DTC EU - P&L'!F66) -> 0 | G94: =sum('DTC US&CA - P&L'!G65,'DTC EU - P&L'!G66) -> 0 | H94: =sum('DTC US&CA - P&L'!H65,'DTC EU - P&L'!H66) -> 0 | I94: =sum('DTC US&CA - P&L'!I65,'DTC EU - P&L'!I66) -> 1 | ... AF94: =sum('DTC US&CA - P&L'!AF65,'DTC EU - P&L'!AF66) -> 0 | AG94: =SUM(B94:AF94) -> 7
A95: SUM (Add-ons) | B95: =sum(B82:B94) -> 232 | C95: =sum(C82:C94) -> 373 | D95: =sum(D82:D94) -> 540 | E95: =sum(E82:E94) -> 503 | F95: =sum(F82:F94) -> 339 | G95: =sum(G82:G94) -> 264 | H95: =sum(H82:H94) -> 224 | I95: =sum(I82:I94) -> 210 | ... AF95: =sum(AF82:AF94) -> 108 | AG95: =SUM(B95:AF95) -> 6989
A97: Merch Units | B97: =sum('DTC US&CA - P&L'!B68,'DTC EU - P&L'!B69) -> 0 | C97: =sum('DTC US&CA - P&L'!C68,'DTC EU - P&L'!C69) -> 0 | D97: =sum('DTC US&CA - P&L'!D68,'DTC EU - P&L'!D69) -> 0 | E97: =sum('DTC US&CA - P&L'!E68,'DTC EU - P&L'!E69) -> 0 | F97: =sum('DTC US&CA - P&L'!F68,'DTC EU - P&L'!F69) -> 0 | G97: =sum('DTC US&CA - P&L'!G68,'DTC EU - P&L'!G69) -> 0 | H97: =sum('DTC US&CA - P&L'!H68,'DTC EU - P&L'!H69) -> 0 | I97: =sum('DTC US&CA - P&L'!I68,'DTC EU - P&L'!I69) -> 0 | ... AF97: =sum('DTC US&CA - P&L'!AF68,'DTC EU - P&L'!AF69) -> 0 | AG97: =SUM(B97:AF97) -> 0
A101: First-time Customers | B101: =sum(B102,B113) -> 273 | C101: =sum(C102,C113) -> 421 | D101: =sum(D102,D113) -> 555 | E101: =sum(E102,E113) -> 513 | F101: =sum(F102,F113) -> 341 | G101: =sum(G102,G113) -> 299 | H101: =sum(H102,H113) -> 205 | I101: =sum(I102,I113) -> 180 | ... AF101: =sum(AF102,AF113) -> 86 | AG101: =SUM(B101:AF101) -> 7415
A102: BB1 | B102: =sum(B106,B111) -> 273 | C102: =sum(C106,C111) -> 421 | D102: =sum(D106,D111) -> 555 | E102: =sum(E106,E111) -> 513 | F102: =sum(F106,F111) -> 341 | G102: =sum(G106,G111) -> 299 | H102: =sum(H106,H111) -> 205 | I102: =sum(I106,I111) -> 180 | ... AF102: =sum(AF106,AF111) -> 86 | AG102: =SUM(B102:AF102) -> 5714
A103: Smart Bird Feeder PRO | B103: =sum('DTC US&CA - P&L'!B74,'DTC EU - P&L'!B75) -> 0 | C103: =sum('DTC US&CA - P&L'!C74,'DTC EU - P&L'!C75) -> 0 | D103: =sum('DTC US&CA - P&L'!D74,'DTC EU - P&L'!D75) -> 0 | E103: =sum('DTC US&CA - P&L'!E74,'DTC EU - P&L'!E75) -> 0 | F103: =sum('DTC US&CA - P&L'!F74,'DTC EU - P&L'!F75) -> 0 | G103: =sum('DTC US&CA - P&L'!G74,'DTC EU - P&L'!G75) -> 0 | H103: =sum('DTC US&CA - P&L'!H74,'DTC EU - P&L'!H75) -> 0 | I103: =sum('DTC US&CA - P&L'!I74,'DTC EU - P&L'!I75) -> 0 | ... AF103: =sum('DTC US&CA - P&L'!AF74,'DTC EU - P&L'!AF75) -> 0 | AG103: =SUM(B103:AF103) -> 0
A104: Smart Bird Feeder PRO Solar | B104: =sum('DTC US&CA - P&L'!B75,'DTC EU - P&L'!B76) -> 206 | C104: =sum('DTC US&CA - P&L'!C75,'DTC EU - P&L'!C76) -> 322 | D104: =sum('DTC US&CA - P&L'!D75,'DTC EU - P&L'!D76) -> 440 | E104: =sum('DTC US&CA - P&L'!E75,'DTC EU - P&L'!E76) -> 413 | F104: =sum('DTC US&CA - P&L'!F75,'DTC EU - P&L'!F76) -> 272 | G104: =sum('DTC US&CA - P&L'!G75,'DTC EU - P&L'!G76) -> 214 | H104: =sum('DTC US&CA - P&L'!H75,'DTC EU - P&L'!H76) -> 155 | I104: =sum('DTC US&CA - P&L'!I75,'DTC EU - P&L'!I76) -> 132 | ... AF104: =sum('DTC US&CA - P&L'!AF75,'DTC EU - P&L'!AF76) -> 57 | AG104: =SUM(B104:AF104) -> 4271
A105: Smart Bird Feeder PRO Solar with PEX (Retail SKU) | B105: =sum('DTC US&CA - P&L'!B76,'DTC EU - P&L'!B77) -> 0 | C105: =sum('DTC US&CA - P&L'!C76,'DTC EU - P&L'!C77) -> 0 | D105: =sum('DTC US&CA - P&L'!D76,'DTC EU - P&L'!D77) -> 0 | E105: =sum('DTC US&CA - P&L'!E76,'DTC EU - P&L'!E77) -> 0 | F105: =sum('DTC US&CA - P&L'!F76,'DTC EU - P&L'!F77) -> 0 | G105: =sum('DTC US&CA - P&L'!G76,'DTC EU - P&L'!G77) -> 0 | H105: =sum('DTC US&CA - P&L'!H76,'DTC EU - P&L'!H77) -> 0 | I105: =sum('DTC US&CA - P&L'!I76,'DTC EU - P&L'!I77) -> 0 | ... AF105: =sum('DTC US&CA - P&L'!AF76,'DTC EU - P&L'!AF77) -> 0 | AG105: =SUM(B105:AF105) -> 0
A106: SUM (BB1 SBF) | B106: =sum(B103:B105) -> 206 | C106: =sum(C103:C105) -> 322 | D106: =sum(D103:D105) -> 440 | E106: =sum(E103:E105) -> 413 | F106: =sum(F103:F105) -> 272 | G106: =sum(G103:G105) -> 214 | H106: =sum(H103:H105) -> 155 | I106: =sum(I103:I105) -> 132 | ... AF106: =sum(AF103:AF105) -> 57 | AG106: =SUM(B106:AF106) -> 4271
A108: Smart Hummingbird Feeder PRO | B108: =sum('DTC US&CA - P&L'!B79,'DTC EU - P&L'!B80) -> 0 | C108: =sum('DTC US&CA - P&L'!C79,'DTC EU - P&L'!C80) -> 0 | D108: =sum('DTC US&CA - P&L'!D79,'DTC EU - P&L'!D80) -> 0 | E108: =sum('DTC US&CA - P&L'!E79,'DTC EU - P&L'!E80) -> 0 | F108: =sum('DTC US&CA - P&L'!F79,'DTC EU - P&L'!F80) -> 0 | G108: =sum('DTC US&CA - P&L'!G79,'DTC EU - P&L'!G80) -> 0 | H108: =sum('DTC US&CA - P&L'!H79,'DTC EU - P&L'!H80) -> 0 | I108: =sum('DTC US&CA - P&L'!I79,'DTC EU - P&L'!I80) -> 1 | ... AF108: =sum('DTC US&CA - P&L'!AF79,'DTC EU - P&L'!AF80) -> 0 | AG108: =SUM(B108:AF108) -> 2
A109: Smart Hummingbird Feeder PRO Solar | B109: =sum('DTC US&CA - P&L'!B80,'DTC EU - P&L'!B81) -> 5 | C109: =sum('DTC US&CA - P&L'!C80,'DTC EU - P&L'!C81) -> 0 | D109: =sum('DTC US&CA - P&L'!D80,'DTC EU - P&L'!D81) -> 0 | E109: =sum('DTC US&CA - P&L'!E80,'DTC EU - P&L'!E81) -> 3 | F109: =sum('DTC US&CA - P&L'!F80,'DTC EU - P&L'!F81) -> 1 | G109: =sum('DTC US&CA - P&L'!G80,'DTC EU - P&L'!G81) -> 4 | H109: =sum('DTC US&CA - P&L'!H80,'DTC EU - P&L'!H81) -> 0 | I109: =sum('DTC US&CA - P&L'!I80,'DTC EU - P&L'!I81) -> 1 | ... AF109: =sum('DTC US&CA - P&L'!AF80,'DTC EU - P&L'!AF81) -> 0 | AG109: =SUM(B109:AF109) -> 16
A110: Smart Hummingbird Feeder PRO Solar (Retail SKU) | B110: =sum('DTC US&CA - P&L'!B81,'DTC EU - P&L'!B82) -> 62 | C110: =sum('DTC US&CA - P&L'!C81,'DTC EU - P&L'!C82) -> 99 | D110: =sum('DTC US&CA - P&L'!D81,'DTC EU - P&L'!D82) -> 115 | E110: =sum('DTC US&CA - P&L'!E81,'DTC EU - P&L'!E82) -> 97 | F110: =sum('DTC US&CA - P&L'!F81,'DTC EU - P&L'!F82) -> 68 | G110: =sum('DTC US&CA - P&L'!G81,'DTC EU - P&L'!G82) -> 81 | H110: =sum('DTC US&CA - P&L'!H81,'DTC EU - P&L'!H82) -> 50 | I110: =sum('DTC US&CA - P&L'!I81,'DTC EU - P&L'!I82) -> 46 | ... AF110: =sum('DTC US&CA - P&L'!AF81,'DTC EU - P&L'!AF82) -> 29 | AG110: =SUM(B110:AF110) -> 1425
A111: SUM (BB1 HBF) | B111: =sum(B108:B110) -> 67 | C111: =sum(C108:C110) -> 99 | D111: =sum(D108:D110) -> 115 | E111: =sum(E108:E110) -> 100 | F111: =sum(F108:F110) -> 69 | G111: =sum(G108:G110) -> 85 | H111: =sum(H108:H110) -> 50 | I111: =sum(I108:I110) -> 48 | ... AF111: =sum(AF108:AF110) -> 29 | AG111: =SUM(B111:AF111) -> 1443
A113: BB2 | B113: =sum(B117,B121,B126) -> 0 | C113: =sum(C117,C121,C126) -> 0 | D113: =sum(D117,D121,D126) -> 0 | E113: =sum(E117,E121,E126) -> 0 | F113: =sum(F117,F121,F126) -> 0 | G113: =sum(G117,G121,G126) -> 0 | H113: =sum(H117,H121,H126) -> 0 | I113: =sum(I117,I121,I126) -> 0 | ... AF113: =sum(AF117,AF121,AF126) -> 0 | AG113: =SUM(B113:AF113) -> 1701
A114: Birdbuddy 2 | N114: =sum('DTC US&CA - P&L'!N85,'DTC EU - P&L'!N86) -> 13 | O114: =sum('DTC US&CA - P&L'!O85,'DTC EU - P&L'!O86) -> 992 | P114: =sum('DTC US&CA - P&L'!P85,'DTC EU - P&L'!P86) -> 94 | Q114: =sum('DTC US&CA - P&L'!Q85,'DTC EU - P&L'!Q86) -> 58 | R114: =sum('DTC US&CA - P&L'!R85,'DTC EU - P&L'!R86) -> 285 | S114: =sum('DTC US&CA - P&L'!S85,'DTC EU - P&L'!S86) -> 55 | T114: =sum('DTC US&CA - P&L'!T85,'DTC EU - P&L'!T86) -> 204 | U114: =sum('DTC US&CA - P&L'!U85,'DTC EU - P&L'!U86) -> 0 | ... AF114: =sum('DTC US&CA - P&L'!AF85,'DTC EU - P&L'!AF86) -> 0 | AG114: =SUM(B114:AF114) -> 1701
A115: Birdbuddy 2 PRO | AG115: =SUM(B115:AF115) -> 0
A116: Birdbuddy 2 Retail SKU | AG116: =SUM(B116:AF116) -> 0
A117: SUM (BB2 SBF) | B117: =sum(B114:B116) -> 0 | C117: =sum(C114:C116) -> 0 | D117: =sum(D114:D116) -> 0 | E117: =sum(E114:E116) -> 0 | F117: =sum(F114:F116) -> 0 | G117: =sum(G114:G116) -> 0 | H117: =sum(H114:H116) -> 0 | I117: =sum(I114:I116) -> 0 | ... AF117: =sum(AF114:AF116) -> 0 | AG117: =SUM(B117:AF117) -> 1701
A119: Birdbuddy 2 Nectar | AG119: =SUM(B119:AF119) -> 0
A120: Birdbuddy 2 Nectar PRO | AG120: =SUM(B120:AF120) -> 0
A121: SUM (BB2 HBF) | B121: =sum(B119:B120) -> 0 | C121: =sum(C119:C120) -> 0 | D121: =sum(D119:D120) -> 0 | E121: =sum(E119:E120) -> 0 | F121: =sum(F119:F120) -> 0 | G121: =sum(G119:G120) -> 0 | H121: =sum(H119:H120) -> 0 | I121: =sum(I119:I120) -> 0 | ... AF121: =sum(AF119:AF120) -> 0 | AG121: =SUM(B121:AF121) -> 0
A123: Birdbuddy 2 Mini non Solar | AG123: =SUM(B123:AF123) -> 0
A124: Birdbuddy 2 Mini Solar | AG124: =SUM(B124:AF124) -> 0
A125: BB2 Mini Retail SKU | AG125: =SUM(B125:AF125) -> 0
A126: SUM (BB2 MINI) | B126: =sum(B123:B125) -> 0 | C126: =sum(C123:C125) -> 0 | D126: =sum(D123:D125) -> 0 | E126: =sum(E123:E125) -> 0 | F126: =sum(F123:F125) -> 0 | G126: =sum(G123:G125) -> 0 | H126: =sum(H123:H125) -> 0 | I126: =sum(I123:I125) -> 0 | ... AF126: =sum(AF123:AF125) -> 0 | AG126: =SUM(B126:AF126) -> 0
A128: Wall Mount | B128: =sum('DTC US&CA - P&L'!B99,'DTC EU - P&L'!B100) -> 1 | C128: =sum('DTC US&CA - P&L'!C99,'DTC EU - P&L'!C100) -> 0 | D128: =sum('DTC US&CA - P&L'!D99,'DTC EU - P&L'!D100) -> 1 | E128: =sum('DTC US&CA - P&L'!E99,'DTC EU - P&L'!E100) -> 0 | F128: =sum('DTC US&CA - P&L'!F99,'DTC EU - P&L'!F100) -> 0 | G128: =sum('DTC US&CA - P&L'!G99,'DTC EU - P&L'!G100) -> 0 | H128: =sum('DTC US&CA - P&L'!H99,'DTC EU - P&L'!H100) -> 0 | I128: =sum('DTC US&CA - P&L'!I99,'DTC EU - P&L'!I100) -> 0 | ... AF128: =sum('DTC US&CA - P&L'!AF99,'DTC EU - P&L'!AF100) -> 1 | AG128: =SUM(B128:AF128) -> 18
A129: Suet Ball Holder | B129: =sum('DTC US&CA - P&L'!B100,'DTC EU - P&L'!B101) -> 145 | C129: =sum('DTC US&CA - P&L'!C100,'DTC EU - P&L'!C101) -> 227 | D129: =sum('DTC US&CA - P&L'!D100,'DTC EU - P&L'!D101) -> 337 | E129: =sum('DTC US&CA - P&L'!E100,'DTC EU - P&L'!E101) -> 329 | F129: =sum('DTC US&CA - P&L'!F100,'DTC EU - P&L'!F101) -> 197 | G129: =sum('DTC US&CA - P&L'!G100,'DTC EU - P&L'!G101) -> 165 | H129: =sum('DTC US&CA - P&L'!H100,'DTC EU - P&L'!H101) -> 123 | I129: =sum('DTC US&CA - P&L'!I100,'DTC EU - P&L'!I101) -> 107 | ... AF129: =sum('DTC US&CA - P&L'!AF100,'DTC EU - P&L'!AF101) -> 45 | AG129: =SUM(B129:AF129) -> 3369
A130: 3-in-1 Nutrition Set - Blue | B130: =sum('DTC US&CA - P&L'!B101,'DTC EU - P&L'!B102) -> 5 | C130: =sum('DTC US&CA - P&L'!C101,'DTC EU - P&L'!C102) -> 19 | D130: =sum('DTC US&CA - P&L'!D101,'DTC EU - P&L'!D102) -> 20 | E130: =sum('DTC US&CA - P&L'!E101,'DTC EU - P&L'!E102) -> 21 | F130: =sum('DTC US&CA - P&L'!F101,'DTC EU - P&L'!F102) -> 9 | G130: =sum('DTC US&CA - P&L'!G101,'DTC EU - P&L'!G102) -> 5 | H130: =sum('DTC US&CA - P&L'!H101,'DTC EU - P&L'!H102) -> 16 | I130: =sum('DTC US&CA - P&L'!I101,'DTC EU - P&L'!I102) -> 12 | ... AF130: =sum('DTC US&CA - P&L'!AF101,'DTC EU - P&L'!AF102) -> 6 | AG130: =SUM(B130:AF130) -> 425
...

Sheet DTC US&CA - P&L
A1: MAY | B1: 46143 | C1: 46144 | D1: 46145 | E1: 46146 | F1: 46147 | G1: 46148 | H1: 46149 | I1: 46150 | J1: 46151 | K1: 46152 | L1: 46153 | M1: 46154 | N1: 46155 | O1: 46156 | P1: 46157 | Q1: 46158 | R1: 46159 | S1: 46160 | T1: 46161 | U1: 46162 | V1: 46163 | W1: 46164 | X1: 46165 | Y1: 46166 | Z1: 46167 | AA1: 46168 | AB1: 46169 | AC1: 46170 | AD1: 46171 | AE1: 46172 | AF1: 46173
A2: DAY | B2: FRI | C2: SAT | D2: SUN | E2: MON | F2: TUE | G2: WED | H2: THU | I2: FRI | J2: SAT | K2: SUN | L2: MON | M2: TUE | N2: WED | O2: THU | P2: FRI | Q2: SAT | R2: SUN | S2: MON | T2: TUE | U2: WED | V2: THU | W2: FRI | X2: SAT | Y2: SUN | Z2: MON | AA2: TUE | AB2: WED | AC2: THU | AD2: FRI | AE2: SAT | AF2: SUN
A4: Revenue
A5: Revenue Woocommerce (Platform) | B5: =Summary!B13+Summary!B26 -> 87138.46 | C5: =Summary!C13+Summary!C26 -> 179999.37 | D5: =Summary!D13+Summary!D26 -> 180711.69 | E5: =Summary!E13+Summary!E26 -> 165405.78 | F5: =Summary!F13+Summary!F26 -> 138653 | G5: =Summary!G13+Summary!G26 -> 113836.49 | H5: =Summary!H13+Summary!H26 -> 82498.71 | I5: =Summary!I13+Summary!I26 -> 76938.49 | ... AF5: =Summary!AF13+Summary!AF26 -> 54985.15 | AG5: =SUM(B5:AF5) -> 3117875.4
A6: Revenue w/o renewals | B6: 74054 | C6: 117402.36 | D6: 152053.25 | E6: 140016.94 | F6: 97484.31 | G6: 91354.2 | H6: 66688.27 | I6: 60184.7 | J6: 59298.95 | K6: 60469.14 | L6: 35633.63 | M6: 37525.27 | N6: 35988.93 | O6: 461723.92 | P6: 76439.37 | Q6: 54116.66 | R6: 162182.71 | S6: 60935.9 | T6: 118941.4 | U6: 28718.59 | V6: 33672.19 | W6: 44170.98 | X6: 57682.97 | Y6: 68993.91 | Z6: 64718.72 | AA6: 37953.21 | AB6: 29677.42 | AC6: 19403.16 | AD6: 26986.47 | AE6: 26879.91 | AF6: 28968.45 | AG6: =SUM(B6:AF6) -> 2430319.9
A8: Orders
A9: Orders Woocommerce (Platform) | B9: =Summary!B90 -> 448 | C9: =Summary!C90 -> 1096 | D9: =Summary!D90 -> 921 | E9: =Summary!E90 -> 816 | F9: =Summary!F90 -> 806 | G9: =Summary!G90 -> 572 | H9: =Summary!H90 -> 417 | I9: =Summary!I90 -> 411 | ... AF9: =Summary!AF90 -> 386 | AG9: =SUM(B9:AF9) -> 16825
A10: Orders w/o renewals | B10: 311 | C10: 478 | D10: 629 | E10: 562 | F10: 396 | G10: 342 | H10: 254 | I10: 239 | J10: 230 | K10: 245 | L10: 138 | M10: 154 | N10: 150 | O10: 1910 | P10: 318 | Q10: 224 | R10: 632 | S10: 239 | T10: 485 | U10: 123 | V10: 142 | W10: 190 | X10: 244 | Y10: 302 | Z10: 284 | AA10: 132 | AB10: 112 | AC10: 82 | AD10: 104 | AE10: 111 | AF10: 120 | AG10: =SUM(B10:AF10) -> 9882
A14: Breakdown
A15: - Hardware | B15: =Summary!B14 -> 55904.1 | C15: =Summary!C14 -> 89119.9 | D15: =Summary!D14 -> 113979.5 | E15: =Summary!E14 -> 105630.4 | F15: =Summary!F14 -> 72773.79 | G15: =Summary!G14 -> 70375.4 | H15: =Summary!H14 -> 50044.4 | I15: =Summary!I14 -> 45304.8 | ... AF15: =Summary!AF14 -> 21928.4 | AG15: =SUM(B15:AF15) -> 1846377.1
A16: - Add-ons | B16: =Summary!B15 -> 3219.4 | C16: =Summary!C15 -> 5231.8 | D16: =Summary!D15 -> 7477.6 | E16: =Summary!E15 -> 6096 | F16: =Summary!F15 -> 4921.9 | G16: =Summary!G15 -> 3488.2 | H16: =Summary!H15 -> 3861.2 | I16: =Summary!I15 -> 3548.8 | ... AF16: =Summary!AF15 -> 1990 | AG16: =SUM(B16:AF16) -> 128437.77
A17: - Merch | B17: =Summary!B16 -> 0 | C17: =Summary!C16 -> 0 | D17: =Summary!D16 -> 0 | E17: =Summary!E16 -> 0 | F17: =Summary!F16 -> 0 | G17: =Summary!G16 -> 0 | H17: =Summary!H16 -> 0 | I17: =Summary!I16 -> 0 | ... AF17: =Summary!AF16 -> 0 | AG17: =SUM(B17:AF17) -> 0
A18: - Yearly Pro Subscription | B18: =Summary!B27 -> 13169.43 | C18: =Summary!C27 -> 61028.86 | D18: =Summary!D27 -> 28269.92 | E18: =Summary!E27 -> 24752.74 | F18: =Summary!F27 -> 39839.71 | G18: =Summary!G27 -> 22011.27 | H18: =Summary!H27 -> 15844.42 | I18: =Summary!I27 -> 16479.35 | ... AF18: =Summary!AF27 -> 25596.83 | AG18: =SUM(B18:AF18) -> 671250.22
A19: - Taxes | B19: =Summary!B17+Summary!B28 -> 4947.91 | C19: =Summary!C17+Summary!C28 -> 9347.28 | D19: =Summary!D17+Summary!D28 -> 10643.13 | E19: =Summary!E17+Summary!E28 -> 9796.14 | F19: =Summary!F17+Summary!F28 -> 7660.85 | G19: =Summary!G17+Summary!G28 -> 6567.9 | H19: =Summary!H17+Summary!H28 -> 4588.66 | I19: =Summary!I17+Summary!I28 -> 4342.19 | ... AF19: =Summary!AF17+Summary!AF28 -> 2524.44 | AG19: =SUM(B19:AF19) -> 176989.85
A20: - Shipping | B20: =Summary!B18 -> 8038.55 | C20: =Summary!C18 -> 12692.82 | D20: =Summary!D18 -> 16363.53 | E20: =Summary!E18 -> 14992.57 | F20: =Summary!F18 -> 10382.28 | G20: =Summary!G18 -> 8914.96 | H20: =Summary!H18 -> 6540.84 | I20: =Summary!I18 -> 5924.02 | ... AF20: =Summary!AF18 -> 2945.48 | AG20: =SUM(B20:AF20) -> 257266.59
A21: - Gift Bag | B21: =Summary!B19 -> 1859.07 | C21: =Summary!C19 -> 2578.71 | D21: =Summary!D19 -> 3978.01 | E21: =Summary!E19 -> 4137.93 | F21: =Summary!F19 -> 3074.47 | G21: =Summary!G19 -> 2478.76 | H21: =Summary!H19 -> 1619.19 | I21: =Summary!I19 -> 1339.33 | ... AF21: =Summary!AF19 -> 0 | AG21: =SUM(B21:AF21) -> 37553.89
A22: SUM | B22: =SUM(B15:B21) -> 87138.46 | C22: =SUM(C15:C21) -> 179999.37 | D22: =SUM(D15:D21) -> 180711.69 | E22: =SUM(E15:E21) -> 165405.78 | F22: =SUM(F15:F21) -> 138653 | G22: =SUM(G15:G21) -> 113836.49 | H22: =SUM(H15:H21) -> 82498.71 | I22: =SUM(I15:I21) -> 76938.49 | ... AF22: =SUM(AF15:AF21) -> 54985.15 | AG22: =SUM(B22:AF22) -> 3117875.4
A26: Units Sold (Gross) | B26: =sum(B27,B38) -> 300 | C26: =sum(C27,C38) -> 478 | D26: =sum(D27,D38) -> 616 | E26: =sum(E27,E38) -> 562 | F26: =sum(F27,F38) -> 389 | G26: =sum(G27,G38) -> 336 | H26: =sum(H27,H38) -> 240 | I26: =sum(I27,I38) -> 217 | ... AF26: =sum(AF27,AF38) -> 104 | AG26: =SUM(B26:AF26) -> 9585
A27: BB1 | B27: =sum(B31,B36) -> 300 | C27: =sum(C31,C36) -> 478 | D27: =sum(D31,D36) -> 616 | E27: =sum(E31,E36) -> 562 | F27: =sum(F31,F36) -> 389 | G27: =sum(G31,G36) -> 336 | H27: =sum(H31,H36) -> 240 | I27: =sum(I31,I36) -> 217 | ... AF27: =sum(AF31,AF36) -> 104 | AG27: =SUM(B27:AF27) -> 6635
A28: Smart Bird Feeder PRO | B28: 0 | C28: 0 | D28: 0 | E28: 0 | F28: 0 | G28: 0 | H28: 0 | I28: 0 | J28: 0 | K28: 0 | L28: 0 | M28: 0 | N28: 0 | O28: 0 | P28: 0 | Q28: 0 | R28: 0 | S28: 0 | T28: 0 | U28: 0 | V28: 0 | W28: 0 | X28: 0 | Y28: 0 | Z28: 0 | AA28: 0 | AB28: 0 | AC28: 0 | AD28: 0 | AE28: 0 | AF28: 0 | AG28: =SUM(B28:AF28) -> 0
A29: Smart Bird Feeder PRO Solar | B29: 223 | C29: 354 | D29: 471 | E29: 442 | F29: 307 | G29: 235 | H29: 172 | I29: 151 | J29: 155 | K29: 152 | L29: 79 | M29: 101 | N29: 88 | O29: 117 | P29: 91 | Q29: 79 | R29: 132 | S29: 111 | T29: 97 | U29: 73 | V29: 107 | W29: 123 | X29: 169 | Y29: 203 | Z29: 203 | AA29: 89 | AB29: 63 | AC29: 45 | AD29: 55 | AE29: 60 | AF29: 66 | AG29: =SUM(B29:AF29) -> 4813
A30: Smart Bird Feeder PRO Solar with PEX (Retail SKU) | B30: 0 | C30: 0 | D30: 0 | E30: 0 | F30: 0 | G30: 0 | H30: 0 | I30: 0 | J30: 0 | K30: 0 | L30: 0 | M30: 0 | N30: 0 | O30: 0 | P30: 0 | Q30: 0 | R30: 0 | S30: 0 | T30: 0 | U30: 0 | V30: 0 | W30: 0 | X30: 0 | Y30: 0 | Z30: 0 | AA30: 0 | AB30: 0 | AC30: 0 | AD30: 0 | AE30: 0 | AF30: 0 | AG30: =SUM(B30:AF30) -> 0
A31: SUM (BB1 SBF) | B31: =SUM(B28:B30) -> 223 | C31: =SUM(C28:C30) -> 354 | D31: =SUM(D28:D30) -> 471 | E31: =SUM(E28:E30) -> 442 | F31: =SUM(F28:F30) -> 307 | G31: =SUM(G28:G30) -> 235 | H31: =SUM(H28:H30) -> 172 | I31: =SUM(I28:I30) -> 151 | ... AF31: =SUM(AF28:AF30) -> 66 | AG31: =SUM(B31:AF31) -> 4813
A33: Smart Hummingbird Feeder PRO | B33: 0 | C33: 0 | D33: 0 | E33: 0 | F33: 0 | G33: 0 | H33: 0 | I33: 1 | J33: 0 | K33: 0 | L33: 1 | M33: 0 | N33: 0 | O33: 0 | P33: 0 | Q33: 0 | R33: 0 | S33: 0 | T33: 0 | U33: 0 | V33: 0 | W33: 0 | X33: 0 | Y33: 0 | Z33: 0 | AA33: 0 | AB33: 0 | AC33: 0 | AD33: 0 | AE33: 0 | AF33: 0 | AG33: =SUM(B33:AF33) -> 2
A34: Smart Hummingbird Feeder PRO Solar | B34: 5 | C34: 0 | D34: 0 | E34: 4 | F34: 1 | G34: 4 | H34: 0 | I34: 1 | J34: 0 | K34: 0 | L34: 0 | M34: 2 | N34: 0 | O34: 0 | P34: 0 | Q34: 0 | R34: 0 | S34: 0 | T34: 0 | U34: 0 | V34: 0 | W34: 0 | X34: 0 | Y34: 0 | Z34: 0 | AA34: 0 | AB34: 0 | AC34: 0 | AD34: 0 | AE34: 0 | AF34: 0 | AG34: =SUM(B34:AF34) -> 17
A35: Smart Hummingbird Feeder PRO Solar (Retail SKU) | B35: 72 | C35: 124 | D35: 145 | E35: 116 | F35: 81 | G35: 97 | H35: 68 | I35: 64 | J35: 62 | K35: 62 | L35: 45 | M35: 34 | N35: 25 | O35: 53 | P35: 31 | Q35: 34 | R35: 49 | S35: 28 | T35: 45 | U35: 37 | V35: 29 | W35: 53 | X35: 65 | Y35: 78 | Z35: 67 | AA35: 49 | AB35: 43 | AC35: 24 | AD35: 46 | AE35: 39 | AF35: 38 | AG35: =SUM(B35:AF35) -> 1803
A36: SUM (BB1 HBF) | B36: =SUM(B33:B35) -> 77 | C36: =SUM(C33:C35) -> 124 | D36: =SUM(D33:D35) -> 145 | E36: =SUM(E33:E35) -> 120 | F36: =SUM(F33:F35) -> 82 | G36: =SUM(G33:G35) -> 101 | H36: =SUM(H33:H35) -> 68 | I36: =SUM(I33:I35) -> 66 | ... AF36: =SUM(AF33:AF35) -> 38 | AG36: =SUM(B36:AF36) -> 1822
A38: BB2 | B38: =sum(B42,B46,B51) -> 0 | C38: =sum(C42,C46,C51) -> 0 | D38: =sum(D42,D46,D51) -> 0 | E38: =sum(E42,E46,E51) -> 0 | F38: =sum(F42,F46,F51) -> 0 | G38: =sum(G42,G46,G51) -> 0 | H38: =sum(H42,H46,H51) -> 0 | I38: =sum(I42,I46,I51) -> 0 | ... AF38: =sum(AF42,AF46,AF51) -> 0 | AG38: =SUM(B38:AF38) -> 2950
A39: Birdbuddy 2 | B39: 0 | C39: 0 | D39: 0 | E39: 0 | F39: 0 | G39: 0 | H39: 0 | I39: 0 | J39: 0 | K39: 0 | L39: 0 | M39: 0 | N39: 22 | O39: 1728 | P39: 179 | Q39: 96 | R39: 475 | S39: 102 | T39: 347 | U39: 1 | V39: 0 | W39: 0 | X39: 0 | Y39: 0 | Z39: 0 | AA39: 0 | AB39: 0 | AC39: 0 | AD39: 0 | AE39: 0 | AF39: 0 | AG39: =SUM(B39:AF39) -> 2950
A40: Birdbuddy 2 PRO | AG40: =SUM(B40:AF40) -> 0
A41: Birdbuddy 2 Retail SKU | AG41: =SUM(B41:AF41) -> 0
A42: SUM (BB2 SBF) | B42: =SUM(B39:B41) -> 0 | C42: =SUM(C39:C41) -> 0 | D42: =SUM(D39:D41) -> 0 | E42: =SUM(E39:E41) -> 0 | F42: =SUM(F39:F41) -> 0 | G42: =SUM(G39:G41) -> 0 | H42: =SUM(H39:H41) -> 0 | I42: =SUM(I39:I41) -> 0 | ... AF42: =SUM(AF39:AF41) -> 0 | AG42: =SUM(B42:AF42) -> 2950
A44: Birdbuddy 2 Nectar | AG44: =SUM(B44:AF44) -> 0
A45: Birdbuddy 2 Nectar PRO | AG45: =SUM(B45:AF45) -> 0
A46: SUM (BB2 HBF) | B46: =sum(B44:B45) -> 0 | C46: =sum(C44:C45) -> 0 | D46: =sum(D44:D45) -> 0 | E46: =sum(E44:E45) -> 0 | F46: =sum(F44:F45) -> 0 | G46: =sum(G44:G45) -> 0 | H46: =sum(H44:H45) -> 0 | I46: =sum(I44:I45) -> 0 | ... AF46: =sum(AF44:AF45) -> 0 | AG46: =SUM(B46:AF46) -> 0
A48: Birdbuddy 2 Mini non Solar | AG48: =SUM(B48:AF48) -> 0
A49: Birdbuddy 2 Mini Solar | AG49: =SUM(B49:AF49) -> 0
A50: BB2 Mini Retail SKU | AG50: =SUM(B50:AF50) -> 0
A51: SUM (BB2 MINI) | B51: =sum(B48:B50) -> 0 | C51: =sum(C48:C50) -> 0 | D51: =sum(D48:D50) -> 0 | E51: =sum(E48:E50) -> 0 | F51: =sum(F48:F50) -> 0 | G51: =sum(G48:G50) -> 0 | H51: =sum(H48:H50) -> 0 | I51: =sum(I48:I50) -> 0 | ... AF51: =sum(AF48:AF50) -> 0 | AG51: =SUM(B51:AF51) -> 0
A53: Wall Mount | B53: 0 | C53: 0 | D53: 0 | E53: 0 | F53: 0 | G53: 0 | H53: 0 | I53: 0 | J53: 0 | K53: 0 | L53: 0 | M53: 0 | N53: 0 | O53: 0 | P53: 0 | Q53: 0 | R53: 0 | S53: 0 | T53: 0 | U53: 0 | V53: 0 | W53: 0 | X53: 0 | Y53: 0 | Z53: 0 | AA53: 0 | AB53: 0 | AC53: 0 | AD53: 0 | AE53: 0 | AF53: 0 | AG53: =SUM(B53:AF53) -> 0
A54: Suet Ball Holder | B54: 154 | C54: 242 | D54: 358 | E54: 338 | F54: 218 | G54: 179 | H54: 133 | I54: 119 | J54: 119 | K54: 165 | L54: 89 | M54: 84 | N54: 61 | O54: 284 | P54: 99 | Q54: 71 | R54: 143 | S54: 87 | T54: 106 | U54: 48 | V54: 75 | W54: 82 | X54: 95 | Y54: 133 | Z54: 142 | AA54: 54 | AB54: 42 | AC54: 30 | AD54: 37 | AE54: 45 | AF54: 52 | AG54: =SUM(B54:AF54) -> 3884
A55: 3-in-1 Nutrition Set - Blue | B55: 5 | C55: 22 | D55: 23 | E55: 28 | F55: 12 | G55: 6 | H55: 21 | I55: 16 | J55: 10 | K55: 25 | L55: 10 | M55: 9 | N55: 9 | O55: 204 | P55: 31 | Q55: 15 | R55: 50 | S55: 16 | T55: 34 | U55: 10 | V55: 5 | W55: 6 | X55: 19 | Y55: 15 | Z55: 12 | AA55: 4 | AB55: 3 | AC55: 2 | AD55: 6 | AE55: 4 | AF55: 7 | AG55: =SUM(B55:AF55) -> 639
A56: 3-in-1 Nutrition Set - Yellow | B56: 0 | C56: 1 | D56: 1 | E56: 0 | F56: 0 | G56: 0 | H56: 1 | I56: 0 | J56: 1 | K56: 0 | L56: 1 | M56: 0 | N56: 0 | O56: 3 | P56: 1 | Q56: 1 | R56: 4 | S56: 0 | T56: 0 | U56: 0 | V56: 2 | W56: 0 | X56: 3 | Y56: 1 | Z56: 2 | AA56: 0 | AB56: 1 | AC56: 0 | AD56: 0 | AE56: 0 | AF56: 0 | AG56: =SUM(B56:AF56) -> 23
A57: Solar Roof Single - Blue | B57: 0 | C57: 0 | D57: 0 | E57: 0 | F57: 0 | G57: 0 | H57: 0 | I57: 0 | J57: 0 | K57: 0 | L57: 0 | M57: 0 | N57: 0 | O57: 0 | P57: 0 | Q57: 0 | R57: 0 | S57: 0 | T57: 0 | U57: 0 | V57: 0 | W57: 0 | X57: 0 | Y57: 0 | Z57: 0 | AA57: 0 | AB57: 0 | AC57: 0 | AD57: 0 | AE57: 0 | AF57: 0 | AG57: =SUM(B57:AF57) -> 0
A58: Solar Roof Single - Yellow | B58: 0 | C58: 0 | D58: 0 | E58: 0 | F58: 0 | G58: 0 | H58: 0 | I58: 0 | J58: 0 | K58: 0 | L58: 0 | M58: 0 | N58: 0 | O58: 0 | P58: 0 | Q58: 0 | R58: 0 | S58: 0 | T58: 0 | U58: 0 | V58: 0 | W58: 0 | X58: 0 | Y58: 0 | Z58: 0 | AA58: 0 | AB58: 0 | AC58: 0 | AD58: 0 | AE58: 0 | AF58: 0 | AG58: =SUM(B58:AF58) -> 0
A59: Perch Extender - Blue | B59: 56 | C59: 90 | D59: 139 | E59: 120 | F59: 92 | G59: 70 | H59: 59 | I59: 50 | J59: 56 | K59: 161 | L59: 92 | M59: 52 | N59: 32 | O59: 208 | P59: 48 | Q59: 43 | R59: 94 | S59: 50 | T59: 55 | U59: 32 | V59: 29 | W59: 63 | X59: 58 | Y59: 65 | Z59: 74 | AA59: 21 | AB59: 28 | AC59: 17 | AD59: 26 | AE59: 28 | AF59: 30 | AG59: =SUM(B59:AF59) -> 2038
A60: Perch Extender - Yellow | B60: 3 | C60: 3 | D60: 1 | E60: 1 | F60: 3 | G60: 0 | H60: 0 | I60: 3 | J60: 1 | K60: 0 | L60: 0 | M60: 0 | N60: 0 | O60: 12 | P60: 2 | Q60: 3 | R60: 8 | S60: 5 | T60: 2 | U60: 1 | V60: 2 | W60: 0 | X60: 1 | Y60: 2 | Z60: 7 | AA60: 0 | AB60: 2 | AC60: 0 | AD60: 1 | AE60: 0 | AF60: 1 | AG60: =SUM(B60:AF60) -> 64
A61: Solar Roof (HBF) | B61: 0 | C61: 0 | D61: 0 | E61: 0 | F61: 0 | G61: 0 | H61: 0 | I61: 0 | J61: 0 | K61: 0 | L61: 0 | M61: 0 | N61: 0 | O61: 0 | P61: 0 | Q61: 0 | R61: 0 | S61: 0 | T61: 0 | U61: 0 | V61: 0 | W61: 0 | X61: 0 | Y61: 0 | Z61: 0 | AA61: 0 | AB61: 0 | AC61: 0 | AD61: 0 | AE61: 0 | AF61: 0 | AG61: =SUM(B61:AF61) -> 0
A62: Housing - only (HBF) | B62: 9 | C62: 10 | D62: 16 | E62: 8 | F62: 12 | G62: 8 | H62: 9 | I62: 10 | J62: 7 | K62: 6 | L62: 4 | M62: 8 | N62: 8 | O62: 16 | P62: 6 | Q62: 5 | R62: 5 | S62: 3 | T62: 6 | U62: 1 | V62: 2 | W62: 3 | X62: 2 | Y62: 8 | Z62: 5 | AA62: 5 | AB62: 3 | AC62: 4 | AD62: 1 | AE62: 0 | AF62: 5 | AG62: =SUM(B62:AF62) -> 195
A63: Nature Station Bloom | B63: 0 | C63: 0 | D63: 0 | E63: 0 | F63: 0 | G63: 0 | H63: 0 | I63: 0 | J63: 0 | K63: 0 | L63: 0 | M63: 0 | N63: 0 | O63: 0 | P63: 0 | Q63: 0 | R63: 0 | S63: 0 | T63: 0 | U63: 0 | V63: 0 | W63: 0 | X63: 0 | Y63: 0 | Z63: 0 | AA63: 0 | AB63: 0 | AC63: 0 | AD63: 0 | AE63: 0 | AF63: 0 | AG63: =SUM(B63:AF63) -> 0
A64: Nature Station Essential | B64: 0 | C64: 0 | D64: 0 | E64: 0 | F64: 0 | G64: 0 | H64: 0 | I64: 0 | J64: 0 | K64: 0 | L64: 0 | M64: 0 | N64: 0 | O64: 0 | P64: 0 | Q64: 0 | R64: 0 | S64: 0 | T64: 0 | U64: 0 | V64: 0 | W64: 0 | X64: 0 | Y64: 0 | Z64: 0 | AA64: 0 | AB64: 0 | AC64: 0 | AD64: 0 | AE64: 0 | AF64: 0 | AG64: =SUM(B64:AF64) -> 0
A65: Pollinator Pot | B65: 0 | C65: 1 | D65: 0 | E65: 0 | F65: 0 | G65: 0 | H65: 0 | I65: 1 | J65: 0 | K65: 0 | L65: 0 | M65: 0 | N65: 0 | O65: 1 | P65: 0 | Q65: 1 | R65: 2 | S65: 0 | T65: 1 | U65: 0 | V65: 0 | W65: 0 | X65: 0 | Y65: 0 | Z65: 0 | AA65: 0 | AB65: 0 | AC65: 0 | AD65: 0 | AE65: 0 | AF65: 0 | AG65: =SUM(B65:AF65) -> 7
A66: SUM (Add-ons) | B66: =SUM(B53:B65) -> 227 | C66: =SUM(C53:C65) -> 369 | D66: =SUM(D53:D65) -> 538 | E66: =SUM(E53:E65) -> 495 | F66: =SUM(F53:F65) -> 337 | G66: =SUM(G53:G65) -> 263 | H66: =SUM(H53:H65) -> 223 | I66: =SUM(I53:I65) -> 199 | ... AF66: =SUM(AF53:AF65) -> 95 | AG66: =SUM(B66:AF66) -> 6850
A68: Merch Units | B68: 0 | C68: 0 | D68: 0 | E68: 0 | F68: 0 | G68: 0 | H68: 0 | I68: 0 | J68: 0 | K68: 0 | L68: 0 | M68: 0 | N68: 0 | O68: 0 | P68: 0 | Q68: 0 | R68: 0 | S68: 0 | T68: 0 | U68: 0 | V68: 0 | W68: 0 | X68: 0 | Y68: 0 | Z68: 0 | AA68: 0 | AB68: 0 | AC68: 0 | AD68: 0 | AE68: 0 | AF68: 0 | AG68: =SUM(B68:AF68) -> 0
A72: First-time Customers | B72: =sum(B73,B84) -> 269 | C72: =sum(C73,C84) -> 420 | D72: =sum(D73,D84) -> 554 | E72: =sum(E73,E84) -> 508 | F72: =sum(F73,F84) -> 340 | G72: =sum(G73,G84) -> 298 | H72: =sum(H73,H84) -> 203 | I72: =sum(I73,I84) -> 180 | ... AF72: =sum(AF73,AF84) -> 84 | AG72: =SUM(B72:AF72) -> 7353
A73: BB1 | B73: =sum(B77,B82) -> 269 | C73: =sum(C77,C82) -> 420 | D73: =sum(D77,D82) -> 554 | E73: =sum(E77,E82) -> 508 | F73: =sum(F77,F82) -> 340 | G73: =sum(G77,G82) -> 298 | H73: =sum(H77,H82) -> 203 | I73: =sum(I77,I82) -> 180 | ... AF73: =sum(AF77,AF82) -> 84 | AG73: =SUM(B73:AF73) -> 5652
A74: Smart Bird Feeder PRO | B74: =B28-B118 -> 0 | C74: =C28-C118 -> 0 | D74: =D28-D118 -> 0 | E74: =E28-E118 -> 0 | F74: =F28-F118 -> 0 | G74: =G28-G118 -> 0 | H74: =H28-H118 -> 0 | I74: =I28-I118 -> 0 | ... AF74: =AF28-AF118 -> 0 | AG74: =SUM(B74:AF74) -> 0
A75: Smart Bird Feeder PRO Solar | B75: =B29-B119 -> 202 | C75: =C29-C119 -> 321 | D75: =D29-D119 -> 439 | E75: =E29-E119 -> 408 | F75: =F29-F119 -> 271 | G75: =G29-G119 -> 213 | H75: =H29-H119 -> 153 | I75: =I29-I119 -> 132 | ... AF75: =AF29-AF119 -> 55 | AG75: =SUM(B75:AF75) -> 4209
A76: Smart Bird Feeder PRO Solar with PEX (Retail SKU) | B76: =B30-B120 -> 0 | C76: =C30-C120 -> 0 | D76: =D30-D120 -> 0 | E76: =E30-E120 -> 0 | F76: =F30-F120 -> 0 | G76: =G30-G120 -> 0 | H76: =H30-H120 -> 0 | I76: =I30-I120 -> 0 | ... AF76: =AF30-AF120 -> 0 | AG76: =SUM(B76:AF76) -> 0
A77: SUM (BB1 SBF) | B77: =sum(B74:B76) -> 202 | C77: =sum(C74:C76) -> 321 | D77: =sum(D74:D76) -> 439 | E77: =sum(E74:E76) -> 408 | F77: =sum(F74:F76) -> 271 | G77: =sum(G74:G76) -> 213 | H77: =sum(H74:H76) -> 153 | I77: =sum(I74:I76) -> 132 | ... AF77: =sum(AF74:AF76) -> 55 | AG77: =SUM(B77:AF77) -> 4209
A79: Smart Hummingbird Feeder PRO | B79: =B33-B123 -> 0 | C79: =C33-C123 -> 0 | D79: =D33-D123 -> 0 | E79: =E33-E123 -> 0 | F79: =F33-F123 -> 0 | G79: =G33-G123 -> 0 | H79: =H33-H123 -> 0 | I79: =I33-I123 -> 1 | ... AF79: =AF33-AF123 -> 0 | AG79: =SUM(B79:AF79) -> 2
A80: Smart Hummingbird Feeder PRO Solar | B80: =B34-B124 -> 5 | C80: =C34-C124 -> 0 | D80: =D34-D124 -> 0 | E80: =E34-E124 -> 3 | F80: =F34-F124 -> 1 | G80: =G34-G124 -> 4 | H80: =H34-H124 -> 0 | I80: =I34-I124 -> 1 | ... AF80: =AF34-AF124 -> 0 | AG80: =SUM(B80:AF80) -> 16
A81: Smart Hummingbird Feeder PRO Solar (Retail SKU) | B81: =B35-B125 -> 62 | C81: =C35-C125 -> 99 | D81: =D35-D125 -> 115 | E81: =E35-E125 -> 97 | F81: =F35-F125 -> 68 | G81: =G35-G125 -> 81 | H81: =H35-H125 -> 50 | I81: =I35-I125 -> 46 | ... AF81: =AF35-AF125 -> 29 | AG81: =SUM(B81:AF81) -> 1425
A82: SUM (BB1 HBF) | B82: =sum(B79:B81) -> 67 | C82: =sum(C79:C81) -> 99 | D82: =sum(D79:D81) -> 115 | E82: =sum(E79:E81) -> 100 | F82: =sum(F79:F81) -> 69 | G82: =sum(G79:G81) -> 85 | H82: =sum(H79:H81) -> 50 | I82: =sum(I79:I81) -> 48 | ... AF82: =sum(AF79:AF81) -> 29 | AG82: =SUM(B82:AF82) -> 1443
A84: BB2 | B84: =sum(B88,B92,B97) -> 0 | C84: =sum(C88,C92,C97) -> 0 | D84: =sum(D88,D92,D97) -> 0 | E84: =sum(E88,E92,E97) -> 0 | F84: =sum(F88,F92,F97) -> 0 | G84: =sum(G88,G92,G97) -> 0 | H84: =sum(H88,H92,H97) -> 0 | I84: =sum(I88,I92,I97) -> 0 | ... AF84: =sum(AF88,AF92,AF97) -> 0 | AG84: =SUM(B84:AF84) -> 1701
A85: Birdbuddy 2 | N85: =N39-N129 -> 13 | O85: =O39-O129 -> 992 | P85: =P39-P129 -> 94 | Q85: =Q39-Q129 -> 58 | R85: =R39-R129 -> 285 | S85: =S39-S129 -> 55 | T85: =T39-T129 -> 204 | U85: =U39-U129 -> 0 | ... AF85: =AF39-AF129 -> 0 | AG85: =SUM(B85:AF85) -> 1701
A86: Birdbuddy 2 PRO | AG86: =SUM(B86:AF86) -> 0
A87: Birdbuddy 2 Retail SKU | AG87: =SUM(B87:AF87) -> 0
A88: SUM (BB2 SBF) | B88: =sum(B85:B87) -> 0 | C88: =sum(C85:C87) -> 0 | D88: =sum(D85:D87) -> 0 | E88: =sum(E85:E87) -> 0 | F88: =sum(F85:F87) -> 0 | G88: =sum(G85:G87) -> 0 | H88: =sum(H85:H87) -> 0 | I88: =sum(I85:I87) -> 0 | ... AF88: =sum(AF85:AF87) -> 0 | AG88: =SUM(B88:AF88) -> 1701
A90: Birdbuddy 2 Nectar | AG90: =SUM(B90:AF90) -> 0
A91: Birdbuddy 2 Nectar PRO | AG91: =SUM(B91:AF91) -> 0
A92: SUM (BB2 HBF) | B92: =sum(B90:B91) -> 0 | C92: =sum(C90:C91) -> 0 | D92: =sum(D90:D91) -> 0 | E92: =sum(E90:E91) -> 0 | F92: =sum(F90:F91) -> 0 | G92: =sum(G90:G91) -> 0 | H92: =sum(H90:H91) -> 0 | I92: =sum(I90:I91) -> 0 | ... AF92: =sum(AF90:AF91) -> 0 | AG92: =SUM(B92:AF92) -> 0
A94: Birdbuddy 2 Mini non Solar | AG94: =SUM(B94:AF94) -> 0
A95: Birdbuddy 2 Mini Solar | AG95: =SUM(B95:AF95) -> 0
A96: BB2 Mini Retail SKU | AG96: =SUM(B96:AF96) -> 0
A97: SUM (BB2 MINI) | B97: =sum(B94:B96) -> 0 | C97: =sum(C94:C96) -> 0 | D97: =sum(D94:D96) -> 0 | E97: =sum(E94:E96) -> 0 | F97: =sum(F94:F96) -> 0 | G97: =sum(G94:G96) -> 0 | H97: =sum(H94:H96) -> 0 | I97: =sum(I94:I96) -> 0 | ... AF97: =sum(AF94:AF96) -> 0 | AG97: =SUM(B97:AF97) -> 0
A99: Wall Mount | B99: =B53-B143 -> 0 | C99: =C53-C143 -> 0 | D99: =D53-D143 -> 0 | E99: =E53-E143 -> 0 | F99: =F53-F143 -> 0 | G99: =G53-G143 -> 0 | H99: =H53-H143 -> 0 | I99: =I53-I143 -> 0 | ... AF99: =AF53-AF143 -> 0 | AG99: =SUM(B99:AF99) -> 0
A100: Suet Ball Holder | B100: =B54-B144 -> 143 | C100: =C54-C144 -> 226 | D100: =D54-D144 -> 336 | E100: =E54-E144 -> 324 | F100: =F54-F144 -> 195 | G100: =G54-G144 -> 164 | H100: =H54-H144 -> 122 | I100: =I54-I144 -> 106 | ... AF100: =AF54-AF144 -> 43 | AG100: =SUM(B100:AF100) -> 3315
A101: 3-in-1 Nutrition Set - Blue | B101: =B55-B145 -> 5 | C101: =C55-C145 -> 18 | D101: =D55-D145 -> 20 | E101: =E55-E145 -> 20 | F101: =F55-F145 -> 9 | G101: =G55-G145 -> 5 | H101: =H55-H145 -> 16 | I101: =I55-I145 -> 11 | ... AF101: =AF55-AF145 -> 5 | AG101: =SUM(B101:AF101) -> 415
A102: 3-in-1 Nutrition Set - Yellow | B102: =B56-B146 -> 0 | C102: =C56-C146 -> 1 | D102: =D56-D146 -> 1 | E102: =E56-E146 -> 0 | F102: =F56-F146 -> 0 | G102: =G56-G146 -> 0 | H102: =H56-H146 -> 0 | I102: =I56-I146 -> 0 | ... AF102: =AF56-AF146 -> 0 | AG102: =SUM(B102:AF102) -> 12
A103: Solar Roof Single - Blue | B103: =B57-B147 -> 0 | C103: =C57-C147 -> 0 | D103: =D57-D147 -> 0 | E103: =E57-E147 -> 0 | F103: =F57-F147 -> 0 | G103: =G57-G147 -> 0 | H103: =H57-H147 -> 0 | I103: =I57-I147 -> 0 | ... AF103: =AF57-AF147 -> 0 | AG103: =SUM(B103:AF103) -> 0
A104: Solar Roof Single - Yellow | B104: =B58-B148 -> 0 | C104: =C58-C148 -> 0 | D104: =D58-D148 -> 0 | E104: =E58-E148 -> 0 | F104: =F58-F148 -> 0 | G104: =G58-G148 -> 0 | H104: =H58-H148 -> 0 | I104: =I58-I148 -> 0 | ... AF104: =AF58-AF148 -> 0 | AG104: =SUM(B104:AF104) -> 0
A105: Perch Extender - Blue | B105: =B59-B149 -> 45 | C105: =C59-C149 -> 73 | D105: =D59-D149 -> 126 | E105: =E59-E149 -> 105 | F105: =F59-F149 -> 73 | G105: =G59-G149 -> 59 | H105: =H59-H149 -> 49 | I105: =I59-I149 -> 41 | ... AF105: =AF59-AF149 -> 23 | AG105: =SUM(B105:AF105) -> 1559
A106: Perch Extender - Yellow | B106: =B60-B150 -> 3 | C106: =C60-C150 -> 3 | D106: =D60-D150 -> 1 | E106: =E60-E150 -> 1 | F106: =F60-F150 -> 2 | G106: =G60-G150 -> 0 | H106: =H60-H150 -> 0 | I106: =I60-I150 -> 1 | ... AF106: =AF60-AF150 -> 1 | AG106: =SUM(B106:AF106) -> 39
A107: Solar Roof (HBF) | B107: =B61-B151 -> 0 | C107: =C61-C151 -> 0 | D107: =D61-D151 -> 0 | E107: =E61-E151 -> 0 | F107: =F61-F151 -> 0 | G107: =G61-G151 -> 0 | H107: =H61-H151 -> 0 | I107: =I61-I151 -> 0 | ... AF107: =AF61-AF151 -> 0 | AG107: =SUM(B107:AF107) -> 0
A108: Housing - only (HBF) | B108: =B62-B152 -> 4 | C108: =C62-C152 -> 6 | D108: =D62-D152 -> 14 | E108: =E62-E152 -> 6 | F108: =F62-F152 -> 7 | G108: =G62-G152 -> 5 | H108: =H62-H152 -> 6 | I108: =I62-I152 -> 5 | ... AF108: =AF62-AF152 -> 3 | AG108: =SUM(B108:AF108) -> 120
A109: Nature Station Bloom | B109: =B63-B153 -> 0 | C109: =C63-C153 -> 0 | D109: =D63-D153 -> 0 | E109: =E63-E153 -> 0 | F109: =F63-F153 -> 0 | G109: =G63-G153 -> 0 | H109: =H63-H153 -> 0 | I109: =I63-I153 -> 0 | ... AF109: =AF63-AF153 -> 0 | AG109: =SUM(B109:AF109) -> 0
A110: Nature Station Essential | B110: =B64-B154 -> 0 | C110: =C64-C154 -> 0 | D110: =D64-D154 -> 0 | E110: =E64-E154 -> 0 | F110: =F64-F154 -> 0 | G110: =G64-G154 -> 0 | H110: =H64-H154 -> 0 | I110: =I64-I154 -> 0 | ... AF110: =AF64-AF154 -> 0 | AG110: =SUM(B110:AF110) -> 0
A111: Pollinator Pot | B111: =B65-B155 -> 0 | C111: =C65-C155 -> 0 | D111: =D65-D155 -> 0 | E111: =E65-E155 -> 0 | F111: =F65-F155 -> 0 | G111: =G65-G155 -> 0 | H111: =H65-H155 -> 0 | I111: =I65-I155 -> 0 | ... AF111: =AF65-AF155 -> 0 | AG111: =SUM(B111:AF111) -> 1
A112: SUM (Add-ons) | B112: =SUM(B99:B111) -> 200 | C112: =SUM(C99:C111) -> 327 | D112: =SUM(D99:D111) -> 498 | E112: =SUM(E99:E111) -> 456 | F112: =SUM(F99:F111) -> 286 | G112: =SUM(G99:G111) -> 233 | H112: =SUM(H99:H111) -> 193 | I112: =SUM(I99:I111) -> 164 | ... AF112: =SUM(AF99:AF111) -> 75 | AG112: =SUM(B112:AF112) -> 5461
A116: Returning Customers | B116: =sum(B117,B128) -> 31 | C116: =sum(C117,C128) -> 58 | D116: =sum(D117,D128) -> 62 | E116: =sum(E117,E128) -> 54 | F116: =sum(F117,F128) -> 49 | G116: =sum(G117,G128) -> 38 | H116: =sum(H117,H128) -> 37 | I116: =sum(I117,I128) -> 37 | ... AF116: =sum(AF117,AF128) -> 20 | AG116: =SUM(B116:AF116) -> 2232
A117: BB1 | B117: =sum(B126,B121) -> 31 | C117: =sum(C126,C121) -> 58 | D117: =sum(D126,D121) -> 62 | E117: =sum(E126,E121) -> 54 | F117: =sum(F126,F121) -> 49 | G117: =sum(G126,G121) -> 38 | H117: =sum(H126,H121) -> 37 | I117: =sum(I126,I121) -> 37 | ... AF117: =sum(AF126,AF121) -> 20 | AG117: =SUM(B117:AF117) -> 983
A118: Smart Bird Feeder PRO | B118: 0 | C118: 0 | D118: 0 | E118: 0 | F118: 0 | G118: 0 | H118: 0 | I118: 0 | J118: 0 | K118: 0 | L118: 0 | M118: 0 | N118: 0 | O118: 0 | P118: 0 | Q118: 0 | R118: 0 | S118: 0 | T118: 0 | U118: 0 | V118: 0 | W118: 0 | X118: 0 | Y118: 0 | Z118: 0 | AA118: 0 | AB118: 0 | AC118: 0 | AD118: 0 | AE118: 0 | AF118: 0 | AG118: =SUM(B118:AF118) -> 0
A119: Smart Bird Feeder PRO Solar | B119: 21 | C119: 33 | D119: 32 | E119: 34 | F119: 36 | G119: 22 | H119: 19 | I119: 19 | J119: 21 | K119: 20 | L119: 14 | M119: 21 | N119: 11 | O119: 22 | P119: 15 | Q119: 9 | R119: 22 | S119: 13 | T119: 21 | U119: 14 | V119: 17 | W119: 18 | X119: 23 | Y119: 26 | Z119: 27 | AA119: 31 | AB119: 12 | AC119: 7 | AD119: 7 | AE119: 6 | AF119: 11 | AG119: =SUM(B119:AF119) -> 604
A120: Smart Bird Feeder PRO Solar with PEX (Retail SKU) | B120: 0 | C120: 0 | D120: 0 | E120: 0 | F120: 0 | G120: 0 | H120: 0 | I120: 0 | J120: 0 | K120: 0 | L120: 0 | M120: 0 | N120: 0 | O120: 0 | P120: 0 | Q120: 0 | R120: 0 | S120: 0 | T120: 0 | U120: 0 | V120: 0 | W120: 0 | X120: 0 | Y120: 0 | Z120: 0 | AA120: 0 | AB120: 0 | AC120: 0 | AD120: 0 | AE120: 0 | AF120: 0 | AG120: =SUM(B120:AF120) -> 0
A121: SUM (BB1 SBF) | B121: =sum(B118:B120) -> 21 | C121: =sum(C118:C120) -> 33 | D121: =sum(D118:D120) -> 32 | E121: =sum(E118:E120) -> 34 | F121: =sum(F118:F120) -> 36 | G121: =sum(G118:G120) -> 22 | H121: =sum(H118:H120) -> 19 | I121: =sum(I118:I120) -> 19 | ... AF121: =sum(AF118:AF120) -> 11 | AG121: =SUM(B121:AF121) -> 604
A123: Smart Hummingbird Feeder PRO | B123: 0 | C123: 0 | D123: 0 | E123: 0 | F123: 0 | G123: 0 | H123: 0 | I123: 0 | J123: 0 | K123: 0 | L123: 0 | M123: 0 | N123: 0 | O123: 0 | P123: 0 | Q123: 0 | R123: 0 | S123: 0 | T123: 0 | U123: 0 | V123: 0 | W123: 0 | X123: 0 | Y123: 0 | Z123: 0 | AA123: 0 | AB123: 0 | AC123: 0 | AD123: 0 | AE123: 0 | AF123: 0 | AG123: =SUM(B123:AF123) -> 0
A124: Smart Hummingbird Feeder PRO Solar | B124: 0 | C124: 0 | D124: 0 | E124: 1 | F124: 0 | G124: 0 | H124: 0 | I124: 0 | J124: 0 | K124: 0 | L124: 0 | M124: 0 | N124: 0 | O124: 0 | P124: 0 | Q124: 0 | R124: 0 | S124: 0 | T124: 0 | U124: 0 | V124: 0 | W124: 0 | X124: 0 | Y124: 0 | Z124: 0 | AA124: 0 | AB124: 0 | AC124: 0 | AD124: 0 | AE124: 0 | AF124: 0 | AG124: =SUM(B124:AF124) -> 1
A125: Smart Hummingbird Feeder PRO Solar (Retail SKU) | B125: 10 | C125: 25 | D125: 30 | E125: 19 | F125: 13 | G125: 16 | H125: 18 | I125: 18 | J125: 15 | K125: 17 | L125: 6 | M125: 14 | N125: 2 | O125: 12 | P125: 12 | Q125: 10 | R125: 7 | S125: 4 | T125: 20 | U125: 9 | V125: 4 | W125: 15 | X125: 11 | Y125: 17 | Z125: 11 | AA125: 8 | AB125: 8 | AC125: 0 | AD125: 5 | AE125: 13 | AF125: 9 | AG125: =SUM(B125:AF125) -> 378
A126: SUM (BB1 HBF) | B126: =sum(B123:B125) -> 10 | C126: =sum(C123:C125) -> 25 | D126: =sum(D123:D125) -> 30 | E126: =sum(E123:E125) -> 20 | F126: =sum(F123:F125) -> 13 | G126: =sum(G123:G125) -> 16 | H126: =sum(H123:H125) -> 18 | I126: =sum(I123:I125) -> 18 | ... AF126: =sum(AF123:AF125) -> 9 | AG126: =SUM(B126:AF126) -> 379
...

Sheet DTC EU - P&L
A1: MAY | B1: 46143 | C1: 46144 | D1: 46145 | E1: 46146 | F1: 46147 | G1: 46148 | H1: 46149 | I1: 46150 | J1: 46151 | K1: 46152 | L1: 46153 | M1: 46154 | N1: 46155 | O1: 46156 | P1: 46157 | Q1: 46158 | R1: 46159 | S1: 46160 | T1: 46161 | U1: 46162 | V1: 46163 | W1: 46164 | X1: 46165 | Y1: 46166 | Z1: 46167 | AA1: 46168 | AB1: 46169 | AC1: 46170 | AD1: 46171 | AE1: 46172 | AF1: 46173
A2: DAY | B2: FRI | C2: SAT | D2: SUN | E2: MON | F2: TUE | G2: WED | H2: THU | I2: FRI | J2: SAT | K2: SUN | L2: MON | M2: TUE | N2: WED | O2: THU | P2: FRI | Q2: SAT | R2: SUN | S2: MON | T2: TUE | U2: WED | V2: THU | W2: FRI | X2: SAT | Y2: SUN | Z2: MON | AA2: TUE | AB2: WED | AC2: THU | AD2: FRI | AE2: SAT | AF2: SUN
A4: Revenue
A5: Revenue Woocommerce (Platform) | B5: =Summary!B20+Summary!B29 -> 1611.5159 | C5: =Summary!C20+Summary!C29 -> 838.50509 | D5: =Summary!D20+Summary!D29 -> 623.97892 | E5: =Summary!E20+Summary!E29 -> 2459.6111 | F5: =Summary!F20+Summary!F29 -> 835.21028 | G5: =Summary!G20+Summary!G29 -> 820.90263 | H5: =Summary!H20+Summary!H29 -> 700.61677 | I5: =Summary!I20+Summary!I29 -> 946.76563 | ... AF5: =Summary!AF20+Summary!AF29 -> 1975.8255 | AG5: =SUM(B5:AF5) -> 29969.099
A6: Revenue w/o renewals | B6: =B7*Summary!B133 -> 1178.8734 | C6: =C7*Summary!C133 -> 405.7888 | D6: =D7*Summary!D133 -> 307.19612 | E6: =E7*Summary!E133 -> 1702.1809 | F6: =F7*Summary!F133 -> 322.5898 | G6: =G7*Summary!G133 -> 292.25637 | H6: =H7*Summary!H133 -> 584.5411 | I6: =I7*Summary!I133 -> 653.1553 | ... AF6: =AF7*Summary!AF133 -> 1545.8027
A7: Revenue w/o renewals EURO | B7: 1005.35 | C7: 346 | D7: 261.8 | E7: 1456.1 | F7: 275.6 | G7: 248.75 | H7: 498.5 | I7: 553.85 | J7: 549.25 | K7: 640.05 | L7: 249.5 | M7: 179.3 | N7: 573.5 | O7: 523.5 | P7: 1250.9 | Q7: 627 | R7: 563.75 | S7: 469.15 | T7: 576 | U7: 605.55 | V7: 153.3 | W7: 535.15 | X7: 1179.4 | Y7: 1097.5 | Z7: 850.8 | AA7: 274.75 | AB7: 249 | AC7: 784.25 | AD7: 227.35 | AE7: 601.65 | AF7: 1326.3
A8: Orders
A9: Orders Woocommerce (Platform) | B9: =Summary!B96 -> 7 | C9: =Summary!C96 -> 7 | D9: =Summary!D96 -> 5 | E9: =Summary!E96 -> 14 | F9: =Summary!F96 -> 7 | G9: =Summary!G96 -> 6 | H9: =Summary!H96 -> 3 | I9: =Summary!I96 -> 7 | ... AF9: =Summary!AF96 -> 9 | AG9: =SUM(B9:AF9) -> 171
A10: Orders w/o renewals | B10: 3 | C10: 3 | D10: 2 | E10: 7 | F10: 2 | G10: 1 | H10: 2 | I10: 4 | J10: 2 | K10: 4 | L10: 1 | M10: 3 | N10: 4 | O10: 2 | P10: 6 | Q10: 2 | R10: 3 | S10: 4 | T10: 3 | U10: 4 | V10: 1 | W10: 3 | X10: 5 | Y10: 4 | Z10: 4 | AA10: 1 | AB10: 1 | AC10: 4 | AD10: 1 | AE10: 4 | AF10: 5
A14: Breakdown
A15: - Hardware | B15: 651.13 | C15: 165.83 | D15: 163.11 | E15: 984.46 | F15: 179.51 | G15: 184.03 | H15: 362.01 | I15: 184.03 | J15: 357.6 | K15: 363.49 | L15: 179.51 | M15: 0 | N15: 356.1 | O15: 361.98 | P15: 852.66 | Q15: 365.02 | R15: 363.49 | S15: 267.21 | T15: 356.19 | U15: 363.49 | V15: 126.69 | W15: 363.49 | X15: 718.08 | Y15: 721.02 | Z15: 503.65 | AA15: 178.05 | AB15: 182.5 | AC15: 546.01 | AD15: 162.89 | AE15: 363.49 | AF15: 718.04 | AG15: =SUM(B15:AF15) -> 11644.76
A16: - Add-ons | B16: 61.32 | C16: 77.38 | D16: 16.26 | E16: 56.2 | F16: 11.57 | G16: 0 | H16: 0 | I16: 224.36 | J16: 40.32 | K16: 98.54 | L16: 0 | M16: 118.18 | N16: 41.67 | O16: 20.66 | P16: 73.74 | Q16: 107.31 | R16: 43.23 | S16: 43.77 | T16: 51.86 | U16: 68.23 | V16: 0 | W16: 21.01 | X16: 129.41 | Y16: 82.64 | Z16: 110.38 | AA16: 20.33 | AB16: 0 | AC16: 20.83 | AD16: 0 | AE16: 65.22 | AF16: 249.73 | AG16: =SUM(B16:AF16) -> 1854.15
A17: - Merch | B17: 0 | C17: 0 | D17: 0 | E17: 0 | F17: 0 | G17: 0 | H17: 0 | I17: 0 | J17: 0 | K17: 0 | L17: 0 | M17: 0 | N17: 0 | O17: 0 | P17: 0 | Q17: 0 | R17: 0 | S17: 0 | T17: 0 | U17: 0 | V17: 0 | W17: 0 | X17: 0 | Y17: 0 | Z17: 0 | AA17: 0 | AB17: 0 | AC17: 0 | AD17: 0 | AE17: 0 | AF17: 0 | AG17: =SUM(B17:AF17) -> 0
A18: - Yearly Pro Subscription | B18: 305.64 | C18: 298.71 | D18: 223.74 | E18: 534.82 | F18: 361.41 | G18: 371.28 | H18: 79.19 | I18: 206.12 | J18: 74.37 | K18: 380.54 | L18: 164.99 | M18: 71.99 | N18: 149.36 | O18: 224.98 | P18: 75.62 | Q18: 149.36 | R18: 83.18 | S18: 305.05 | T18: 158.17 | U18: 0 | V18: 0 | W18: 73.16 | X18: 222.5 | Y18: 147.53 | Z18: 148.78 | AA18: 223.15 | AB18: 154.85 | AC18: 158.11 | AD18: 74.37 | AE18: 0 | AF18: 306.22 | AG18: =SUM(B18:AF18) -> 5727.19
A19: - Taxes | B19: 246.22 | C19: 128.04 | D19: 93.66 | E19: 368.55 | F19: 126.06 | G19: 118.39 | H19: 106.29 | I19: 133.31 | J19: 116.95 | K19: 186.43 | L19: 77.98 | M19: 49.12 | N19: 136.35 | O19: 135.85 | P19: 228.87 | Q19: 135.29 | R19: 112.84 | S19: 152.08 | T19: 138.76 | U19: 103.83 | V19: 26.61 | W19: 107.48 | X19: 259.38 | Y19: 226.29 | Z19: 182.97 | AA19: 98.19 | AB19: 75.63 | AC19: 163.28 | AD19: 55.08 | AE19: 102.94 | AF19: 301.27 | AG19: =SUM(B19:AF19) -> 4493.99
A20: - Taxes (w/o Subscriptions) | B20: 182.9 | C20: 57.79 | D20: 47.43 | E20: 255.44 | F20: 49.52 | G20: 39.72 | H20: 86.49 | I20: 90.46 | J20: 101.33 | K20: 108.02 | L20: 44.99 | M20: 31.12 | N20: 105.73 | O20: 90.86 | P20: 214.5 | Q20: 104.67 | R20: 97.03 | S20: 88.17 | T20: 107.95 | U20: 103.83 | V20: 26.61 | W20: 90.65 | X20: 211.91 | Y20: 193.84 | Z20: 151.77 | AA20: 51.37 | AB20: 41.5 | AC20: 132.41 | AD20: 39.46 | AE20: 102.94 | AF20: 238.53 | AG20: =SUM(B20:AF20) -> 3288.94
A21: - Taxes (Subscriptions) | B21: 63.32 | C21: 70.25 | D21: 46.23 | E21: 113.11 | F21: 76.54 | G21: 78.67 | H21: 19.8 | I21: 42.85 | J21: 15.62 | K21: 78.41 | L21: 32.99 | M21: 18 | N21: 30.62 | O21: 44.99 | P21: 14.37 | Q21: 30.62 | R21: 15.81 | S21: 63.91 | T21: 30.81 | U21: 0 | V21: 0 | W21: 16.83 | X21: 47.47 | Y21: 32.45 | Z21: 31.2 | AA21: 46.82 | AB21: 34.13 | AC21: 30.87 | AD21: 15.62 | AE21: 0 | AF21: 62.74 | AG21: =SUM(B21:AF21) -> 1205.05
A22: - Shipping | B22: 110 | C22: 45 | D22: 35 | E22: 160 | F22: 35 | G22: 25 | H22: 50 | I22: 55 | J22: 50 | K22: 70 | L22: 25 | M22: 30 | N22: 70 | O22: 50 | P22: 110 | Q22: 50 | R22: 60 | S22: 70 | T22: 60 | U22: 70 | V22: 0 | W22: 60 | X22: 120 | Y22: 100 | Z22: 85 | AA22: 25 | AB22: 25 | AC22: 85 | AD22: 25 | AE22: 70 | AF22: 120 | AG22: =SUM(B22:AF22) -> 1945
A23: SUM | B23: =sum(B15:B19,B22) -> 1374.31 | C23: =sum(C15:C19,C22) -> 714.96 | D23: =sum(D15:D19,D22) -> 531.77 | E23: =sum(E15:E19,E22) -> 2104.03 | F23: =sum(F15:F19,F22) -> 713.55 | G23: =sum(G15:G19,G22) -> 698.7 | H23: =sum(H15:H19,H22) -> 597.49 | I23: =sum(I15:I19,I22) -> 802.82 | ... AF23: =sum(AF15:AF19,AF22) -> 1695.26 | AG23: =SUM(B23:AF23) -> 25665.09
A27: Units Sold (Gross) | B27: =sum(B28,B39) -> 4 | C27: =sum(C28,C39) -> 1 | D27: =sum(D28,D39) -> 1 | E27: =sum(E28,E39) -> 6 | F27: =sum(F28,F39) -> 1 | G27: =sum(G28,G39) -> 1 | H27: =sum(H28,H39) -> 2 | I27: =sum(I28,I39) -> 1 | ... AF27: =sum(AF28,AF39) -> 4 | AG27: =SUM(B27:AF27) -> 67
A28: BB1 | B28: =sum(B32,B37) -> 4 | C28: =sum(C32,C37) -> 1 | D28: =sum(D32,D37) -> 1 | E28: =sum(E32,E37) -> 6 | F28: =sum(F32,F37) -> 1 | G28: =sum(G32,G37) -> 1 | H28: =sum(H32,H37) -> 2 | I28: =sum(I32,I37) -> 1 | ... AF28: =sum(AF32,AF37) -> 4 | AG28: =SUM(B28:AF28) -> 67
A29: Smart Bird Feeder PRO | B29: 0 | C29: 0 | D29: 0 | E29: 0 | F29: 0 | G29: 0 | H29: 0 | I29: 0 | J29: 0 | K29: 0 | L29: 0 | M29: 0 | N29: 0 | O29: 0 | P29: 0 | Q29: 0 | R29: 0 | S29: 0 | T29: 0 | U29: 0 | V29: 0 | W29: 0 | X29: 0 | Y29: 0 | Z29: 0 | AA29: 0 | AB29: 0 | AC29: 0 | AD29: 0 | AE29: 0 | AF29: 0 | AG29: =SUM(B29:AF29) -> 0
A30: Smart Bird Feeder PRO Solar | B30: 4 | C30: 1 | D30: 1 | E30: 6 | F30: 1 | G30: 1 | H30: 2 | I30: 1 | J30: 2 | K30: 2 | L30: 1 | M30: 0 | N30: 2 | O30: 2 | P30: 5 | Q30: 2 | R30: 2 | S30: 2 | T30: 2 | U30: 2 | V30: 1 | W30: 2 | X30: 4 | Y30: 4 | Z30: 3 | AA30: 1 | AB30: 1 | AC30: 3 | AD30: 1 | AE30: 2 | AF30: 4 | AG30: =SUM(B30:AF30) -> 67
A31: Smart Bird Feeder PRO Solar with PEX (Retail SKU) | AG31: =SUM(B31:AF31) -> 0
A32: SUM (BB1 SBF) | B32: =sum(B29:B31) -> 4 | C32: =sum(C29:C31) -> 1 | D32: =sum(D29:D31) -> 1 | E32: =sum(E29:E31) -> 6 | F32: =sum(F29:F31) -> 1 | G32: =sum(G29:G31) -> 1 | H32: =sum(H29:H31) -> 2 | I32: =sum(I29:I31) -> 1 | ... AF32: =sum(AF29:AF31) -> 4 | AG32: =SUM(B32:AF32) -> 67
A34: Smart Hummingbird Feeder PRO | AG34: =SUM(B34:AF34) -> 0
A35: Smart Hummingbird Feeder PRO Solar | AG35: =SUM(B35:AF35) -> 0
A36: Smart Hummingbird Feeder PRO Solar (Retail SKU) | AG36: =SUM(B36:AF36) -> 0
A37: SUM (BB1 HBF) | B37: =sum(B34:B36) -> 0 | C37: =sum(C34:C36) -> 0 | D37: =sum(D34:D36) -> 0 | E37: =sum(E34:E36) -> 0 | F37: =sum(F34:F36) -> 0 | G37: =sum(G34:G36) -> 0 | H37: =sum(H34:H36) -> 0 | I37: =sum(I34:I36) -> 0 | ... AF37: =sum(AF34:AF36) -> 0 | AG37: =SUM(B37:AF37) -> 0
A39: BB2 | B39: =sum(B43,B47,B52) -> 0 | C39: =sum(C43,C47,C52) -> 0 | D39: =sum(D43,D47,D52) -> 0 | E39: =sum(E43,E47,E52) -> 0 | F39: =sum(F43,F47,F52) -> 0 | G39: =sum(G43,G47,G52) -> 0 | H39: =sum(H43,H47,H52) -> 0 | I39: =sum(I43,I47,I52) -> 0 | ... AF39: =sum(AF43,AF47,AF52) -> 0 | AG39: =SUM(B39:AF39) -> 0
A40: Birdbuddy 2 | AG40: =SUM(B40:AF40) -> 0
A41: Birdbuddy 2 PRO | AG41: =SUM(B41:AF41) -> 0
A42: Birdbuddy 2 Retail SKU | AG42: =SUM(B42:AF42) -> 0
A43: SUM (BB2 SBF) | B43: =sum(B40:B42) -> 0 | C43: =sum(C40:C42) -> 0 | D43: =sum(D40:D42) -> 0 | E43: =sum(E40:E42) -> 0 | F43: =sum(F40:F42) -> 0 | G43: =sum(G40:G42) -> 0 | H43: =sum(H40:H42) -> 0 | I43: =sum(I40:I42) -> 0 | ... AF43: =sum(AF40:AF42) -> 0 | AG43: =SUM(B43:AF43) -> 0
A45: Birdbuddy 2 Nectar | AG45: =SUM(B45:AF45) -> 0
A46: Birdbuddy 2 Nectar PRO | AG46: =SUM(B46:AF46) -> 0
A47: SUM (BB2 HBF) | B47: =sum(B45:B46) -> 0 | C47: =sum(C45:C46) -> 0 | D47: =sum(D45:D46) -> 0 | E47: =sum(E45:E46) -> 0 | F47: =sum(F45:F46) -> 0 | G47: =sum(G45:G46) -> 0 | H47: =sum(H45:H46) -> 0 | I47: =sum(I45:I46) -> 0 | ... AF47: =sum(AF45:AF46) -> 0 | AG47: =SUM(B47:AF47) -> 0
A49: Birdbuddy 2 Mini non Solar | AG49: =SUM(B49:AF49) -> 0
A50: Birdbuddy 2 Mini Solar | AG50: =SUM(B50:AF50) -> 0
A51: BB2 Mini Retail SKU | AG51: =SUM(B51:AF51) -> 0
A52: SUM (BB2 MINI) | B52: =sum(B49:B51) -> 0 | C52: =sum(C49:C51) -> 0 | D52: =sum(D49:D51) -> 0 | E52: =sum(E49:E51) -> 0 | F52: =sum(F49:F51) -> 0 | G52: =sum(G49:G51) -> 0 | H52: =sum(H49:H51) -> 0 | I52: =sum(I49:I51) -> 0 | ... AF52: =sum(AF49:AF51) -> 0 | AG52: =SUM(B52:AF52) -> 0
A54: Wall Mount | B54: 1 | C54: 0 | D54: 1 | E54: 1 | F54: 0 | G54: 0 | H54: 0 | I54: 2 | J54: 1 | K54: 1 | L54: 0 | M54: 2 | N54: 1 | O54: 0 | P54: 1 | Q54: 2 | R54: 0 | S54: 1 | T54: 0 | U54: 1 | V54: 0 | W54: 0 | X54: 2 | Y54: 2 | Z54: 2 | AA54: 0 | AB54: 0 | AC54: 0 | AD54: 0 | AE54: 1 | AF54: 3 | AG54: =SUM(B54:AF54) -> 25
A55: Suet Ball Holder | B55: 2 | C55: 1 | D55: 1 | E55: 6 | F55: 2 | G55: 1 | H55: 1 | I55: 2 | J55: 2 | K55: 3 | L55: 0 | M55: 1 | N55: 2 | O55: 2 | P55: 5 | Q55: 2 | R55: 4 | S55: 1 | T55: 3 | U55: 1 | V55: 0 | W55: 1 | X55: 4 | Y55: 4 | Z55: 2 | AA55: 0 | AB55: 0 | AC55: 3 | AD55: 0 | AE55: 2 | AF55: 3 | AG55: =SUM(B55:AF55) -> 61
A56: 3-in-1 Nutrition Set - Blue | B56: 0 | C56: 1 | D56: 0 | E56: 1 | F56: 0 | G56: 0 | H56: 0 | I56: 4 | J56: 0 | K56: 1 | L56: 0 | M56: 1 | N56: 0 | O56: 0 | P56: 0 | Q56: 1 | R56: 0 | S56: 1 | T56: 0 | U56: 2 | V56: 0 | W56: 0 | X56: 1 | Y56: 0 | Z56: 0 | AA56: 0 | AB56: 0 | AC56: 0 | AD56: 0 | AE56: 1 | AF56: 3 | AG56: =SUM(B56:AF56) -> 17
A57: 3-in-1 Nutrition Set - Yellow | B57: 0 | C57: 0 | D57: 0 | E57: 0 | F57: 0 | G57: 0 | H57: 0 | I57: 0 | J57: 0 | K57: 0 | L57: 0 | M57: 0 | N57: 0 | O57: 0 | P57: 0 | Q57: 0 | R57: 0 | S57: 0 | T57: 0 | U57: 0 | V57: 0 | W57: 0 | X57: 0 | Y57: 0 | Z57: 0 | AA57: 0 | AB57: 0 | AC57: 0 | AD57: 0 | AE57: 0 | AF57: 0 | AG57: =SUM(B57:AF57) -> 0
A58: Solar Roof Single - Blue | B58: 0 | C58: 0 | D58: 0 | E58: 0 | F58: 0 | G58: 0 | H58: 0 | I58: 0 | J58: 0 | K58: 0 | L58: 0 | M58: 0 | N58: 0 | O58: 0 | P58: 0 | Q58: 0 | R58: 0 | S58: 0 | T58: 0 | U58: 0 | V58: 0 | W58: 0 | X58: 0 | Y58: 0 | Z58: 0 | AA58: 0 | AB58: 0 | AC58: 0 | AD58: 0 | AE58: 0 | AF58: 0 | AG58: =SUM(B58:AF58) -> 0
A59: Solar Roof Single - Yellow | B59: 0 | C59: 0 | D59: 0 | E59: 0 | F59: 0 | G59: 0 | H59: 0 | I59: 0 | J59: 0 | K59: 0 | L59: 0 | M59: 0 | N59: 0 | O59: 0 | P59: 0 | Q59: 0 | R59: 0 | S59: 0 | T59: 0 | U59: 0 | V59: 0 | W59: 0 | X59: 0 | Y59: 0 | Z59: 0 | AA59: 0 | AB59: 0 | AC59: 0 | AD59: 0 | AE59: 0 | AF59: 0 | AG59: =SUM(B59:AF59) -> 0
A60: Perch Extender - Blue | B60: 2 | C60: 2 | D60: 0 | E60: 0 | F60: 0 | G60: 0 | H60: 0 | I60: 3 | J60: 1 | K60: 2 | L60: 0 | M60: 2 | N60: 1 | O60: 1 | P60: 2 | Q60: 2 | R60: 1 | S60: 0 | T60: 2 | U60: 0 | V60: 0 | W60: 1 | X60: 2 | Y60: 2 | Z60: 3 | AA60: 1 | AB60: 0 | AC60: 1 | AD60: 0 | AE60: 1 | AF60: 4 | AG60: =SUM(B60:AF60) -> 36
A61: Perch Extender - Yellow | B61: 0 | C61: 0 | D61: 0 | E61: 0 | F61: 0 | G61: 0 | H61: 0 | I61: 0 | J61: 0 | K61: 0 | L61: 0 | M61: 0 | N61: 0 | O61: 0 | P61: 0 | Q61: 0 | R61: 0 | S61: 0 | T61: 0 | U61: 0 | V61: 0 | W61: 0 | X61: 0 | Y61: 0 | Z61: 0 | AA61: 0 | AB61: 0 | AC61: 0 | AD61: 0 | AE61: 0 | AF61: 0 | AG61: =SUM(B61:AF61) -> 0
A62: Solar Roof (HBF) | AG62: =SUM(B62:AF62) -> 0
A63: Housing - only (HBF) | AG63: =SUM(B63:AF63) -> 0
A64: Nature Station Bloom | AG64: =SUM(B64:AF64) -> 0
A65: Nature Station Essential | AG65: =SUM(B65:AF65) -> 0
A66: Pollinator Pot | AG66: =SUM(B66:AF66) -> 0
A67: SUM (Add-ons) | B67: =sum(B54:B66) -> 5 | C67: =sum(C54:C66) -> 4 | D67: =sum(D54:D66) -> 2 | E67: =sum(E54:E66) -> 8 | F67: =sum(F54:F66) -> 2 | G67: =sum(G54:G66) -> 1 | H67: =sum(H54:H66) -> 1 | I67: =sum(I54:I66) -> 11 | ... AF67: =sum(AF54:AF66) -> 13 | AG67: =SUM(B67:AF67) -> 139
A69: Merch Units | B69: 0 | C69: 0 | D69: 0 | E69: 0 | F69: 0 | G69: 0 | H69: 0 | I69: 0 | J69: 0 | K69: 0 | L69: 0 | M69: 0 | N69: 0 | O69: 0 | P69: 0 | Q69: 0 | R69: 0 | S69: 0 | T69: 0 | U69: 0 | V69: 0 | W69: 0 | X69: 0 | Y69: 0 | Z69: 0 | AA69: 0 | AB69: 0 | AC69: 0 | AD69: 0 | AE69: 0 | AF69: 0 | AG69: =SUM(B69:AF69) -> 0
A73: First-time Customers | B73: =sum(B74,B85) -> 4 | C73: =sum(C74,C85) -> 1 | D73: =sum(D74,D85) -> 1 | E73: =sum(E74,E85) -> 5 | F73: =sum(F74,F85) -> 1 | G73: =sum(G74,G85) -> 1 | H73: =sum(H74,H85) -> 2 | I73: =sum(I74,I85) -> 0 | ... AF73: =sum(AF74,AF85) -> 2 | AG73: =SUM(B73:AF73) -> 62
A74: BB1 | B74: =sum(B78,B83) -> 4 | C74: =sum(C78,C83) -> 1 | D74: =sum(D78,D83) -> 1 | E74: =sum(E78,E83) -> 5 | F74: =sum(F78,F83) -> 1 | G74: =sum(G78,G83) -> 1 | H74: =sum(H78,H83) -> 2 | I74: =sum(I78,I83) -> 0 | ... AF74: =sum(AF78,AF83) -> 2 | AG74: =SUM(B74:AF74) -> 62
A75: Smart Bird Feeder PRO | B75: =B29-B119 -> 0 | C75: =C29-C119 -> 0 | D75: =D29-D119 -> 0 | E75: =E29-E119 -> 0 | F75: =F29-F119 -> 0 | G75: =G29-G119 -> 0 | H75: =H29-H119 -> 0 | I75: =I29-I119 -> 0 | ... AF75: =AF29-AF119 -> 0 | AG75: =SUM(B75:AF75) -> 0
A76: Smart Bird Feeder PRO Solar | B76: =B30-B120 -> 4 | C76: =C30-C120 -> 1 | D76: =D30-D120 -> 1 | E76: =E30-E120 -> 5 | F76: =F30-F120 -> 1 | G76: =G30-G120 -> 1 | H76: =H30-H120 -> 2 | I76: =I30-I120 -> 0 | ... AF76: =AF30-AF120 -> 2 | AG76: =SUM(B76:AF76) -> 62
A77: Smart Bird Feeder PRO Solar with PEX (Retail SKU) | AG77: =SUM(B77:AF77) -> 0
A78: SUM (BB1 SBF) | B78: =sum(B75:B77) -> 4 | C78: =sum(C75:C77) -> 1 | D78: =sum(D75:D77) -> 1 | E78: =sum(E75:E77) -> 5 | F78: =sum(F75:F77) -> 1 | G78: =sum(G75:G77) -> 1 | H78: =sum(H75:H77) -> 2 | I78: =sum(I75:I77) -> 0 | ... AF78: =sum(AF75:AF77) -> 2 | AG78: =SUM(B78:AF78) -> 62
A80: Smart Hummingbird Feeder PRO | AG80: =SUM(B80:AF80) -> 0
A81: Smart Hummingbird Feeder PRO Solar | AG81: =SUM(B81:AF81) -> 0
A82: Smart Hummingbird Feeder PRO Solar (Retail SKU) | AG82: =SUM(B82:AF82) -> 0
A83: SUM (BB1 HBF) | B83: =sum(B80:B82) -> 0 | C83: =sum(C80:C82) -> 0 | D83: =sum(D80:D82) -> 0 | E83: =sum(E80:E82) -> 0 | F83: =sum(F80:F82) -> 0 | G83: =sum(G80:G82) -> 0 | H83: =sum(H80:H82) -> 0 | I83: =sum(I80:I82) -> 0 | ... AF83: =sum(AF80:AF82) -> 0 | AG83: =SUM(B83:AF83) -> 0
A85: BB2 | B85: =sum(B89,B93,B98) -> 0 | C85: =sum(C89,C93,C98) -> 0 | D85: =sum(D89,D93,D98) -> 0 | E85: =sum(E89,E93,E98) -> 0 | F85: =sum(F89,F93,F98) -> 0 | G85: =sum(G89,G93,G98) -> 0 | H85: =sum(H89,H93,H98) -> 0 | I85: =sum(I89,I93,I98) -> 0 | ... AF85: =sum(AF89,AF93,AF98) -> 0 | AG85: =SUM(B85:AF85) -> 0
A86: Birdbuddy 2 | AG86: =SUM(B86:AF86) -> 0
A87: Birdbuddy 2 PRO | AG87: =SUM(B87:AF87) -> 0
A88: Birdbuddy 2 Retail SKU | AG88: =SUM(B88:AF88) -> 0
A89: SUM (BB2 SBF) | B89: =sum(B86:B88) -> 0 | C89: =sum(C86:C88) -> 0 | D89: =sum(D86:D88) -> 0 | E89: =sum(E86:E88) -> 0 | F89: =sum(F86:F88) -> 0 | G89: =sum(G86:G88) -> 0 | H89: =sum(H86:H88) -> 0 | I89: =sum(I86:I88) -> 0 | ... AF89: =sum(AF86:AF88) -> 0 | AG89: =SUM(B89:AF89) -> 0
A91: Birdbuddy 2 Nectar | AG91: =SUM(B91:AF91) -> 0
A92: Birdbuddy 2 Nectar PRO | AG92: =SUM(B92:AF92) -> 0
A93: SUM (BB2 HBF) | B93: =sum(B91:B92) -> 0 | C93: =sum(C91:C92) -> 0 | D93: =sum(D91:D92) -> 0 | E93: =sum(E91:E92) -> 0 | F93: =sum(F91:F92) -> 0 | G93: =sum(G91:G92) -> 0 | H93: =sum(H91:H92) -> 0 | I93: =sum(I91:I92) -> 0 | ... AF93: =sum(AF91:AF92) -> 0 | AG93: =SUM(B93:AF93) -> 0
A95: Birdbuddy 2 Mini non Solar | AG95: =SUM(B95:AF95) -> 0
A96: Birdbuddy 2 Mini Solar | AG96: =SUM(B96:AF96) -> 0
A97: BB2 Mini Retail SKU | AG97: =SUM(B97:AF97) -> 0
A98: SUM (BB2 MINI) | B98: =sum(B95:B97) -> 0 | C98: =sum(C95:C97) -> 0 | D98: =sum(D95:D97) -> 0 | E98: =sum(E95:E97) -> 0 | F98: =sum(F95:F97) -> 0 | G98: =sum(G95:G97) -> 0 | H98: =sum(H95:H97) -> 0 | I98: =sum(I95:I97) -> 0 | ... AF98: =sum(AF95:AF97) -> 0 | AG98: =SUM(B98:AF98) -> 0
A100: Wall Mount | B100: =B54-B144 -> 1 | C100: =C54-C144 -> 0 | D100: =D54-D144 -> 1 | E100: =E54-E144 -> 0 | F100: =F54-F144 -> 0 | G100: =G54-G144 -> 0 | H100: =H54-H144 -> 0 | I100: =I54-I144 -> 0 | ... AF100: =AF54-AF144 -> 1 | AG100: =SUM(B100:AF100) -> 18
A101: Suet Ball Holder | B101: =B55-B145 -> 2 | C101: =C55-C145 -> 1 | D101: =D55-D145 -> 1 | E101: =E55-E145 -> 5 | F101: =F55-F145 -> 2 | G101: =G55-G145 -> 1 | H101: =H55-H145 -> 1 | I101: =I55-I145 -> 1 | ... AF101: =AF55-AF145 -> 2 | AG101: =SUM(B101:AF101) -> 54
A102: 3-in-1 Nutrition Set - Blue | B102: =B56-B146 -> 0 | C102: =C56-C146 -> 1 | D102: =D56-D146 -> 0 | E102: =E56-E146 -> 1 | F102: =F56-F146 -> 0 | G102: =G56-G146 -> 0 | H102: =H56-H146 -> 0 | I102: =I56-I146 -> 1 | ... AF102: =AF56-AF146 -> 1 | AG102: =SUM(B102:AF102) -> 10
A103: 3-in-1 Nutrition Set - Yellow | B103: =B57-B147 -> 0 | C103: =C57-C147 -> 0 | D103: =D57-D147 -> 0 | E103: =E57-E147 -> 0 | F103: =F57-F147 -> 0 | G103: =G57-G147 -> 0 | H103: =H57-H147 -> 0 | I103: =I57-I147 -> 0 | ... AF103: =AF57-AF147 -> 0 | AG103: =SUM(B103:AF103) -> 0
A104: Solar Roof Single - Blue | B104: =B58-B148 -> 0 | C104: =C58-C148 -> 0 | D104: =D58-D148 -> 0 | E104: =E58-E148 -> 0 | F104: =F58-F148 -> 0 | G104: =G58-G148 -> 0 | H104: =H58-H148 -> 0 | I104: =I58-I148 -> 0 | ... AF104: =AF58-AF148 -> 0 | AG104: =SUM(B104:AF104) -> 0
A105: Solar Roof Single - Yellow | B105: =B59-B149 -> 0 | C105: =C59-C149 -> 0 | D105: =D59-D149 -> 0 | E105: =E59-E149 -> 0 | F105: =F59-F149 -> 0 | G105: =G59-G149 -> 0 | H105: =H59-H149 -> 0 | I105: =I59-I149 -> 0 | ... AF105: =AF59-AF149 -> 0 | AG105: =SUM(B105:AF105) -> 0
A106: Perch Extender - Blue | B106: =B60-B150 -> 1 | C106: =C60-C150 -> 1 | D106: =D60-D150 -> 0 | E106: =E60-E150 -> 0 | F106: =F60-F150 -> 0 | G106: =G60-G150 -> 0 | H106: =H60-H150 -> 0 | I106: =I60-I150 -> 0 | ... AF106: =AF60-AF150 -> 2 | AG106: =SUM(B106:AF106) -> 28
A107: Perch Extender - Yellow | B107: =B61-B151 -> 0 | C107: =C61-C151 -> 0 | D107: =D61-D151 -> 0 | E107: =E61-E151 -> 0 | F107: =F61-F151 -> 0 | G107: =G61-G151 -> 0 | H107: =H61-H151 -> 0 | I107: =I61-I151 -> 0 | ... AF107: =AF61-AF151 -> 0 | AG107: =SUM(B107:AF107) -> 0
A108: Solar Roof (HBF) | AG108: =SUM(B108:AF108) -> 0
A109: Housing - only (HBF) | AG109: =SUM(B109:AF109) -> 0
A110: Nature Station Bloom | AG110: =SUM(B110:AF110) -> 0
A111: Nature Station Essential | AG111: =SUM(B111:AF111) -> 0
A112: Pollinator Pot | AG112: =SUM(B112:AF112) -> 0
A113: SUM (Add-ons) | B113: =sum(B100:B112) -> 4 | C113: =sum(C100:C112) -> 3 | D113: =sum(D100:D112) -> 2 | E113: =sum(E100:E112) -> 6 | F113: =sum(F100:F112) -> 2 | G113: =sum(G100:G112) -> 1 | H113: =sum(H100:H112) -> 1 | I113: =sum(I100:I112) -> 2 | ... AF113: =sum(AF100:AF112) -> 6 | AG113: =SUM(B113:AF113) -> 110
A117: Returning Customers | B117: =sum(B118,B129) -> 0 | C117: =sum(C118,C129) -> 0 | D117: =sum(D118,D129) -> 0 | E117: =sum(E118,E129) -> 1 | F117: =sum(F118,F129) -> 0 | G117: =sum(G118,G129) -> 0 | H117: =sum(H118,H129) -> 0 | I117: =sum(I118,I129) -> 1 | ... AF117: =sum(AF118,AF129) -> 2 | AG117: =SUM(B117:AF117) -> 5
A118: BB1 | B118: =sum(B122,B127) -> 0 | C118: =sum(C122,C127) -> 0 | D118: =sum(D122,D127) -> 0 | E118: =sum(E122,E127) -> 1 | F118: =sum(F122,F127) -> 0 | G118: =sum(G122,G127) -> 0 | H118: =sum(H122,H127) -> 0 | I118: =sum(I122,I127) -> 1 | ... AF118: =sum(AF122,AF127) -> 2 | AG118: =SUM(B118:AF118) -> 5
A119: Smart Bird Feeder PRO | B119: 0 | C119: 0 | D119: 0 | E119: 0 | F119: 0 | G119: 0 | H119: 0 | I119: 0 | J119: 0 | K119: 0 | L119: 0 | M119: 0 | N119: 0 | O119: 0 | P119: 0 | Q119: 0 | R119: 0 | S119: 0 | T119: 0 | U119: 0 | V119: 0 | W119: 0 | X119: 0 | Y119: 0 | Z119: 0 | AA119: 0 | AB119: 0 | AC119: 0 | AD119: 0 | AE119: 0 | AF119: 0 | AG119: =SUM(B119:AF119) -> 0
A120: Smart Bird Feeder PRO Solar | B120: 0 | C120: 0 | D120: 0 | E120: 1 | F120: 0 | G120: 0 | H120: 0 | I120: 1 | J120: 0 | K120: 0 | L120: 0 | M120: 0 | N120: 0 | O120: 0 | P120: 1 | Q120: 0 | R120: 0 | S120: 0 | T120: 0 | U120: 0 | V120: 0 | W120: 0 | X120: 0 | Y120: 0 | Z120: 0 | AA120: 0 | AB120: 0 | AC120: 0 | AD120: 0 | AE120: 0 | AF120: 2 | AG120: =SUM(B120:AF120) -> 5
A121: Smart Bird Feeder PRO Solar with PEX (Retail SKU) | AG121: =SUM(B121:AF121) -> 0
A122: SUM (BB1 SBF) | B122: =sum(B119:B121) -> 0 | C122: =sum(C119:C121) -> 0 | D122: =sum(D119:D121) -> 0 | E122: =sum(E119:E121) -> 1 | F122: =sum(F119:F121) -> 0 | G122: =sum(G119:G121) -> 0 | H122: =sum(H119:H121) -> 0 | I122: =sum(I119:I121) -> 1 | ... AF122: =sum(AF119:AF121) -> 2 | AG122: =SUM(B122:AF122) -> 5
A124: Smart Hummingbird Feeder PRO | AG124: =SUM(B124:AF124) -> 0
A125: Smart Hummingbird Feeder PRO Solar | AG125: =SUM(B125:AF125) -> 0
...

Sheet AMAZON US&CA - P&L
A1: MAY | B1: 46143 | C1: 46144 | D1: 46145 | E1: 46146 | F1: 46147 | G1: 46148 | H1: 46149 | I1: 46150 | J1: 46151 | K1: 46152 | L1: 46153 | M1: 46154 | N1: 46155 | O1: 46156 | P1: 46157 | Q1: 46158 | R1: 46159 | S1: 46160 | T1: 46161 | U1: 46162 | V1: 46163 | W1: 46164 | X1: 46165 | Y1: 46166 | Z1: 46167 | AA1: 46168 | AB1: 46169 | AC1: 46170 | AD1: 46171 | AE1: 46172 | AF1: 46173
A2: DAY | B2: FRI | C2: SAT | D2: SUN | E2: MON | F2: TUE | G2: WED | H2: THU | I2: FRI | J2: SAT | K2: SUN | L2: MON | M2: TUE | N2: WED | O2: THU | P2: FRI | Q2: SAT | R2: SUN | S2: MON | T2: TUE | U2: WED | V2: THU | W2: FRI | X2: SAT | Y2: SUN | Z2: MON | AA2: TUE | AB2: WED | AC2: THU | AD2: FRI | AE2: SAT | AF2: SUN
A3: COMMENT
A4: Orders
A5: Amazon (market place) | B5: =Summary!B102 -> 212 | C5: =Summary!C102 -> 286 | D5: =Summary!D102 -> 497 | E5: =Summary!E102 -> 465 | F5: =Summary!F102 -> 428 | G5: =Summary!G102 -> 348 | H5: =Summary!H102 -> 330 | I5: =Summary!I102 -> 226 | ... AF5: =Summary!AF102 -> 130
A6: All | B6: =SUM(B5) -> 212 | C6: =SUM(C5) -> 286 | D6: =SUM(D5) -> 497 | E6: =SUM(E5) -> 465 | F6: =SUM(F5) -> 428 | G6: =SUM(G5) -> 348 | H6: =SUM(H5) -> 330 | I6: =SUM(I5) -> 226 | ... AF6: =SUM(AF5) -> 130 | AG6: =SUM(B6:AF6) -> 5767
A8: Revenue
A9: Amazon (market place) | B9: =Summary!B33 -> 41264.95 | C9: =Summary!C33 -> 59108.3 | D9: =Summary!D33 -> 106923.09 | E9: =Summary!E33 -> 100980.97 | F9: =Summary!F33 -> 90308.03 | G9: =Summary!G33 -> 64294.29 | H9: =Summary!H33 -> 59341.85 | I9: =Summary!I33 -> 38530.94 | ... AF9: =Summary!AF33 -> 18005.48
A10: All | B10: =SUM(B9) -> 41264.95 | C10: =SUM(C9) -> 59108.3 | D10: =SUM(D9) -> 106923.09 | E10: =SUM(E9) -> 100980.97 | F10: =SUM(F9) -> 90308.03 | G10: =SUM(G9) -> 64294.29 | H10: =SUM(H9) -> 59341.85 | I10: =SUM(I9) -> 38530.94 | ... AF10: =SUM(AF9) -> 18005.48 | AG10: =SUM(B10:AF10) -> 1000561.5
A12: Media Cost
A13: Amazon Spend
A14: Amazon Platform Fee (8 %) | B14: =B9*'Data - P&L'!$C$48 -> 3301.196 | C14: =C9*'Data - P&L'!$C$48 -> 4728.664 | D14: =D9*'Data - P&L'!$C$48 -> 8553.8472 | E14: =E9*'Data - P&L'!$C$48 -> 8078.4776 | F14: =F9*'Data - P&L'!$C$48 -> 7224.6424 | G14: =G9*'Data - P&L'!$C$48 -> 5143.5432 | H14: =H9*'Data - P&L'!$C$48 -> 4747.348 | I14: =I9*'Data - P&L'!$C$48 -> 3082.4752 | ... AF14: =AF9*'Data - P&L'!$C$48 -> 1440.4384
A15: All | B15: =SUM(B13:B14) -> 3301.196 | C15: =SUM(C13:C14) -> 4728.664 | D15: =SUM(D13:D14) -> 8553.8472 | E15: =SUM(E13:E14) -> 8078.4776 | F15: =SUM(F13:F14) -> 7224.6424 | G15: =SUM(G13:G14) -> 5143.5432 | H15: =SUM(H13:H14) -> 4747.348 | I15: =SUM(I13:I14) -> 3082.4752 | ... AF15: =SUM(AF13:AF14) -> 1440.4384 | AG15: =SUM(B15:AF15) -> 80044.92
A19: Amazon Orders
A20: Hardware | B20: =Summary!B34 -> 36387 | C20: =Summary!C34 -> 52342 | D20: =Summary!D34 -> 95619 | E20: =Summary!E34 -> 90606 | F20: =Summary!F34 -> 81314 | G20: =Summary!G34 -> 56474 | H20: =Summary!H34 -> 51789.13 | I20: =Summary!I34 -> 33011.13 | ... AF20: =Summary!AF34 -> 14505 | AG20: =SUM(B20:AF20) -> 860049.18
A21: Addons | B21: =Summary!B35 -> 2101 | C21: =Summary!C35 -> 2798 | D21: =Summary!D35 -> 4066.84 | E21: =Summary!E35 -> 3593 | F21: =Summary!F35 -> 2877 | G21: =Summary!G35 -> 3469 | H21: =Summary!H35 -> 3475.86 | I21: =Summary!I35 -> 2917.43 | ... AF21: =Summary!AF35 -> 2287 | AG21: =SUM(B21:AF21) -> 73328.79
A22: Tax | B22: =Summary!B36 -> 2734.1 | C22: =Summary!C36 -> 3924.55 | D22: =Summary!D36 -> 7146.72 | E22: =Summary!E36 -> 6649.34 | F22: =Summary!F36 -> 5949.08 | G22: =Summary!G36 -> 4251.23 | H22: =Summary!H36 -> 3996.13 | I22: =Summary!I36 -> 2553.24 | ... AF22: =Summary!AF36 -> 1199.32 | AG22: =SUM(B22:AF22) -> 65946.48
A23: Shipping | B23: =Summary!B37 -> 10.06 | C23: =Summary!C37 -> 15.29 | D23: =Summary!D37 -> 34.7 | E23: =Summary!E37 -> 58.46 | F23: =Summary!F37 -> 103.13 | G23: =Summary!G37 -> 45.09 | H23: =Summary!H37 -> 29.42 | I23: =Summary!I37 -> 11.08 | ... AF23: =Summary!AF37 -> 0.34 | AG23: =SUM(B23:AF23) -> 535.98
A24: Gift Wrap Price | B24: =Summary!B38 -> 32.79 | C24: =Summary!C38 -> 28.46 | D24: =Summary!D38 -> 55.83 | E24: =Summary!E38 -> 74.17 | F24: =Summary!F38 -> 64.82 | G24: =Summary!G38 -> 54.97 | H24: =Summary!H38 -> 51.31 | I24: =Summary!I38 -> 38.06 | ... AF24: =Summary!AF38 -> 13.82 | AG24: =SUM(B24:AF24) -> 701.07
A25: All Amazon | B25: =SUM(B20:B24) -> 41264.95 | C25: =SUM(C20:C24) -> 59108.3 | D25: =SUM(D20:D24) -> 106923.09 | E25: =SUM(E20:E24) -> 100980.97 | F25: =SUM(F20:F24) -> 90308.03 | G25: =SUM(G20:G24) -> 64294.29 | H25: =SUM(H20:H24) -> 59341.85 | I25: =SUM(I20:I24) -> 38530.94 | ... AF25: =SUM(AF20:AF24) -> 18005.48 | AG25: =SUM(B25:AF25) -> 1000561.5
A29: Units Sold (Gross) | B29: =sum(B30,B41) -> 153 | C29: =sum(C30,C41) -> 218 | D29: =sum(D30,D41) -> 401 | E29: =sum(E30,E41) -> 394 | F29: =sum(F30,F41) -> 366 | G29: =sum(G30,G41) -> 276 | H29: =sum(H30,H41) -> 252 | I29: =sum(I30,I41) -> 160 | ... AF29: =sum(AF30,AF41) -> 65 | AG29: =SUM(B29:AF29) -> 3866
A30: BB1 | B30: =sum(B34,B39) -> 152 | C30: =sum(C34,C39) -> 211 | D30: =sum(D34,D39) -> 399 | E30: =sum(E34,E39) -> 394 | F30: =sum(F34,F39) -> 366 | G30: =sum(G34,G39) -> 276 | H30: =sum(H34,H39) -> 252 | I30: =sum(I34,I39) -> 160 | ... AF30: =sum(AF34,AF39) -> 65 | AG30: =SUM(B30:AF30) -> 3856
A31: Smart Bird Feeder PRO | B31: 32 | C31: 45 | D31: 69 | E31: 126 | F31: 173 | G31: 180 | H31: 164 | I31: 111 | J31: 107 | K31: 73 | L31: 40 | M31: 39 | N31: 50 | O31: 35 | P31: 50 | Q31: 41 | R31: 47 | S31: 36 | T31: 30 | U31: 34 | V31: 35 | W31: 38 | X31: 42 | Y31: 30 | Z31: 34 | AA31: 22 | AB31: 26 | AC31: 30 | AD31: 29 | AE31: 30 | AF31: 33 | AG31: =SUM(B31:AF31) -> 1831
A32: Smart Bird Feeder PRO Solar | B32: 88 | C32: 107 | D32: 244 | E32: 168 | F32: 106 | G32: 70 | H32: 69 | I32: 38 | J32: 24 | K32: 16 | L32: 23 | M32: 14 | N32: 12 | O32: 39 | P32: 16 | Q32: 20 | R32: 20 | S32: 17 | T32: 28 | U32: 10 | V32: 9 | W32: 15 | X32: 15 | Y32: 14 | Z32: 12 | AA32: 17 | AB32: 17 | AC32: 9 | AD32: 5 | AE32: 11 | AF32: 16 | AG32: =SUM(B32:AF32) -> 1269
A33: Smart Bird Feeder PRO Solar with PEX (Retail SKU) | AG33: =SUM(B33:AF33) -> 0
A34: SUM (BB1 SBF) | B34: =sum(B31:B33) -> 120 | C34: =sum(C31:C33) -> 152 | D34: =sum(D31:D33) -> 313 | E34: =sum(E31:E33) -> 294 | F34: =sum(F31:F33) -> 279 | G34: =sum(G31:G33) -> 250 | H34: =sum(H31:H33) -> 233 | I34: =sum(I31:I33) -> 149 | ... AF34: =sum(AF31:AF33) -> 49 | AG34: =SUM(B34:AF34) -> 3100
A36: Smart Hummingbird Feeder PRO | B36: 2 | C36: 12 | D36: 15 | E36: 23 | F36: 11 | G36: 3 | H36: 2 | I36: 3 | J36: 4 | K36: 0 | L36: 2 | M36: 2 | N36: 1 | O36: 1 | P36: 5 | Q36: 0 | R36: 0 | S36: 0 | T36: 0 | U36: 0 | V36: 0 | W36: 0 | X36: 0 | Y36: 1 | Z36: 1 | AA36: 1 | AB36: 0 | AC36: 0 | AD36: 0 | AE36: 0 | AF36: 0 | AG36: =SUM(B36:AF36) -> 89
A37: Smart Hummingbird Feeder PRO Solar | B37: 30 | C37: 47 | D37: 71 | E37: 77 | F37: 76 | G37: 23 | H37: 17 | I37: 8 | J37: 11 | K37: 5 | L37: 3 | M37: 15 | N37: 20 | O37: 24 | P37: 16 | Q37: 14 | R37: 29 | S37: 19 | T37: 13 | U37: 10 | V37: 14 | W37: 8 | X37: 16 | Y37: 13 | Z37: 18 | AA37: 5 | AB37: 11 | AC37: 11 | AD37: 8 | AE37: 19 | AF37: 16 | AG37: =SUM(B37:AF37) -> 667
A38: Smart Hummingbird Feeder PRO Solar (Retail SKU) | AG38: =SUM(B38:AF38) -> 0
A39: SUM (BB1 HBF) | B39: =sum(B36:B38) -> 32 | C39: =sum(C36:C38) -> 59 | D39: =sum(D36:D38) -> 86 | E39: =sum(E36:E38) -> 100 | F39: =sum(F36:F38) -> 87 | G39: =sum(G36:G38) -> 26 | H39: =sum(H36:H38) -> 19 | I39: =sum(I36:I38) -> 11 | ... AF39: =sum(AF36:AF38) -> 16 | AG39: =SUM(B39:AF39) -> 756
A41: BB2 | B41: =sum(B45,B49,B54) -> 1 | C41: =sum(C45,C49,C54) -> 7 | D41: =sum(D45,D49,D54) -> 2 | E41: =sum(E45,E49,E54) -> 0 | F41: =sum(F45,F49,F54) -> 0 | G41: =sum(G45,G49,G54) -> 0 | H41: =sum(H45,H49,H54) -> 0 | I41: =sum(I45,I49,I54) -> 0 | ... AF41: =sum(AF45,AF49,AF54) -> 0 | AG41: =SUM(B41:AF41) -> 10
A42: Birdbuddy 2 | B42: 1 | C42: 7 | D42: 2 | E42: 0 | F42: 0 | G42: 0 | H42: 0 | I42: 0 | J42: 0 | K42: 0 | L42: 0 | M42: 0 | N42: 0 | O42: 0 | P42: 0 | Q42: 0 | R42: 0 | S42: 0 | T42: 0 | U42: 0 | V42: 0 | W42: 0 | X42: 0 | Y42: 0 | Z42: 0 | AA42: 0 | AB42: 0 | AC42: 0 | AD42: 0 | AE42: 0 | AF42: 0 | AG42: =SUM(B42:AF42) -> 10
A43: Birdbuddy 2 PRO | AG43: =SUM(B43:AF43) -> 0
A44: Birdbuddy 2 Retail SKU | AG44: =SUM(B44:AF44) -> 0
A45: SUM (BB2 SBF) | B45: =sum(B42:B44) -> 1 | C45: =sum(C42:C44) -> 7 | D45: =sum(D42:D44) -> 2 | E45: =sum(E42:E44) -> 0 | F45: =sum(F42:F44) -> 0 | G45: =sum(G42:G44) -> 0 | H45: =sum(H42:H44) -> 0 | I45: =sum(I42:I44) -> 0 | ... AF45: =sum(AF42:AF44) -> 0 | AG45: =SUM(B45:AF45) -> 10
A47: Birdbuddy 2 Nectar | AG47: =SUM(B47:AF47) -> 0
A48: Birdbuddy 2 Nectar PRO | AG48: =SUM(B48:AF48) -> 0
A49: SUM (BB2 HBF) | B49: =sum(B47:B48) -> 0 | C49: =sum(C47:C48) -> 0 | D49: =sum(D47:D48) -> 0 | E49: =sum(E47:E48) -> 0 | F49: =sum(F47:F48) -> 0 | G49: =sum(G47:G48) -> 0 | H49: =sum(H47:H48) -> 0 | I49: =sum(I47:I48) -> 0 | ... AF49: =sum(AF47:AF48) -> 0 | AG49: =SUM(B49:AF49) -> 0
A51: Birdbuddy 2 Mini non Solar | AG51: =SUM(B51:AF51) -> 0
A52: Birdbuddy 2 Mini Solar | AG52: =SUM(B52:AF52) -> 0
A53: BB2 Mini Retail SKU | AG53: =SUM(B53:AF53) -> 0
A54: SUM (BB2 MINI) | B54: =sum(B51:B53) -> 0 | C54: =sum(C51:C53) -> 0 | D54: =sum(D51:D53) -> 0 | E54: =sum(E51:E53) -> 0 | F54: =sum(F51:F53) -> 0 | G54: =sum(G51:G53) -> 0 | H54: =sum(H51:H53) -> 0 | I54: =sum(I51:I53) -> 0 | ... AF54: =sum(AF51:AF53) -> 0 | AG54: =SUM(B54:AF54) -> 0
A56: Wall Mount | B56: 19 | C56: 19 | D56: 29 | E56: 31 | F56: 27 | G56: 26 | H56: 35 | I56: 22 | J56: 34 | K56: 65 | L56: 33 | M56: 18 | N56: 20 | O56: 20 | P56: 28 | Q56: 39 | R56: 21 | S56: 23 | T56: 18 | U56: 10 | V56: 7 | W56: 18 | X56: 14 | Y56: 26 | Z56: 29 | AA56: 15 | AB56: 12 | AC56: 12 | AD56: 16 | AE56: 22 | AF56: 21 | AG56: =SUM(B56:AF56) -> 729
A57: Suet Ball Holder | B57: 0 | C57: 0 | D57: 0 | E57: 0 | F57: 0 | G57: 0 | H57: 0 | I57: 0 | J57: 0 | K57: 0 | L57: 0 | M57: 0 | N57: 0 | O57: 0 | P57: 0 | Q57: 0 | R57: 0 | S57: 0 | T57: 0 | U57: 0 | V57: 0 | W57: 0 | X57: 0 | Y57: 0 | Z57: 0 | AA57: 0 | AB57: 0 | AC57: 0 | AD57: 0 | AE57: 0 | AF57: 0 | AG57: =SUM(B57:AF57) -> 0
A58: 3-in-1 Nutrition Set - Blue | B58: 10 | C58: 13 | D58: 24 | E58: 20 | F58: 18 | G58: 25 | H58: 16 | I58: 23 | J58: 14 | K58: 32 | L58: 13 | M58: 12 | N58: 17 | O58: 5 | P58: 11 | Q58: 13 | R58: 18 | S58: 6 | T58: 10 | U58: 12 | V58: 9 | W58: 12 | X58: 9 | Y58: 9 | Z58: 6 | AA58: 8 | AB58: 10 | AC58: 2 | AD58: 8 | AE58: 10 | AF58: 17 | AG58: =SUM(B58:AF58) -> 412
A59: 3-in-1 Nutrition Set - Yellow | B59: 0 | C59: 0 | D59: 0 | E59: 0 | F59: 0 | G59: 0 | H59: 0 | I59: 0 | J59: 0 | K59: 0 | L59: 0 | M59: 0 | N59: 0 | O59: 0 | P59: 0 | Q59: 0 | R59: 0 | S59: 0 | T59: 0 | U59: 0 | V59: 0 | W59: 0 | X59: 0 | Y59: 0 | Z59: 0 | AA59: 0 | AB59: 0 | AC59: 0 | AD59: 0 | AE59: 0 | AF59: 0 | AG59: =SUM(B59:AF59) -> 0
A60: Solar Roof Single - Blue | B60: 0 | C60: 0 | D60: 0 | E60: 0 | F60: 0 | G60: 0 | H60: 0 | I60: 0 | J60: 0 | K60: 0 | L60: 0 | M60: 0 | N60: 0 | O60: 0 | P60: 0 | Q60: 0 | R60: 0 | S60: 0 | T60: 0 | U60: 0 | V60: 0 | W60: 0 | X60: 0 | Y60: 0 | Z60: 0 | AA60: 0 | AB60: 0 | AC60: 0 | AD60: 0 | AE60: 0 | AF60: 0 | AG60: =SUM(B60:AF60) -> 0
A61: Solar Roof Single - Yellow | B61: 0 | C61: 0 | D61: 0 | E61: 0 | F61: 0 | G61: 0 | H61: 0 | I61: 0 | J61: 0 | K61: 0 | L61: 0 | M61: 0 | N61: 0 | O61: 0 | P61: 0 | Q61: 0 | R61: 0 | S61: 0 | T61: 0 | U61: 0 | V61: 0 | W61: 0 | X61: 0 | Y61: 0 | Z61: 0 | AA61: 0 | AB61: 0 | AC61: 0 | AD61: 0 | AE61: 0 | AF61: 0 | AG61: =SUM(B61:AF61) -> 0
A62: Perch Extender - Blue | B62: 40 | C62: 60 | D62: 79 | E62: 66 | F62: 48 | G62: 60 | H62: 64 | I62: 48 | J62: 60 | K62: 83 | L62: 44 | M62: 37 | N62: 41 | O62: 35 | P62: 36 | Q62: 42 | R62: 42 | S62: 29 | T62: 27 | U62: 22 | V62: 27 | W62: 28 | X62: 24 | Y62: 35 | Z62: 32 | AA62: 21 | AB62: 22 | AC62: 22 | AD62: 17 | AE62: 26 | AF62: 35 | AG62: =SUM(B62:AF62) -> 1252
A63: Perch Extender - Yellow | B63: 0 | C63: 0 | D63: 0 | E63: 0 | F63: 0 | G63: 0 | H63: 0 | I63: 0 | J63: 0 | K63: 0 | L63: 0 | M63: 0 | N63: 0 | O63: 0 | P63: 0 | Q63: 0 | R63: 0 | S63: 0 | T63: 0 | U63: 0 | V63: 0 | W63: 0 | X63: 0 | Y63: 0 | Z63: 0 | AA63: 0 | AB63: 0 | AC63: 0 | AD63: 0 | AE63: 0 | AF63: 0 | AG63: =SUM(B63:AF63) -> 0
A64: Solar Roof (HBF) | AG64: =SUM(B64:AF64) -> 0
A65: Housing - only (HBF) | AG65: =SUM(B65:AF65) -> 0
A66: Nature Station Bloom | AG66: =SUM(B66:AF66) -> 0
A67: Nature Station Essential | AG67: =SUM(B67:AF67) -> 0
A68: Pollinator Pot | AG68: =SUM(B68:AF68) -> 0
A69: SUM (Add-ons) | B69: =sum(B56:B68) -> 69 | C69: =sum(C56:C68) -> 92 | D69: =sum(D56:D68) -> 132 | E69: =sum(E56:E68) -> 117 | F69: =sum(F56:F68) -> 93 | G69: =sum(G56:G68) -> 111 | H69: =sum(H56:H68) -> 115 | I69: =sum(I56:I68) -> 93 | ... AF69: =sum(AF56:AF68) -> 73 | AG69: =SUM(B69:AF69) -> 2393
A73: Revenue | B73: =sum(B74,B85) -> 36387 | C73: =sum(C74,C85) -> 52342 | D73: =sum(D74,D85) -> 95619 | E73: =sum(E74,E85) -> 90606 | F73: =sum(F74,F85) -> 81314 | G73: =sum(G74,G85) -> 56474 | H73: =sum(H74,H85) -> 51789.13 | I73: =sum(I74,I85) -> 33011.13 | ... AF73: =sum(AF74,AF85) -> 14505 | AG73: =SUM(B73:AF73) -> 860049.18
A74: BB1 | B74: =sum(B78,B83) -> 36088 | C74: =sum(C78,C83) -> 50249 | D74: =sum(D78,D83) -> 95021 | E74: =sum(E78,E83) -> 90606 | F74: =sum(F78,F83) -> 81314 | G74: =sum(G78,G83) -> 56474 | H74: =sum(H78,H83) -> 51789.13 | I74: =sum(I78,I83) -> 33011.13 | ... AF74: =sum(AF78,AF83) -> 14505 | AG74: =SUM(B74:AF74) -> 857059.18
A75: Smart Bird Feeder PRO | B75: 5728 | C75: 8055 | D75: 12351 | E75: 22554 | F75: 30967 | G75: 32220 | H75: 30036 | I75: 20979 | J75: 20223 | K75: 13797 | L75: 7560 | M75: 7371 | N75: 9450 | O75: 6615 | P75: 9450 | Q75: 7749 | R75: 8883 | S75: 6804 | T75: 5670 | U75: 6426 | V75: 6615 | W75: 7182 | X75: 7938 | Y75: 5670 | Z75: 6426 | AA75: 4158 | AB75: 4914 | AC75: 5670 | AD75: 5481 | AE75: 5670 | AF75: 6237 | AG75: =SUM(B75:AF75) -> 338849
A76: Smart Bird Feeder PRO Solar | B76: 21032 | C76: 25573 | D76: 58316 | E76: 40152 | F76: 25334 | G76: 16730 | H76: 16412.13 | I76: 9003.13 | J76: 5736 | K76: 3824 | L76: 5434.86 | M76: 3035.3 | N76: 2743.72 | O76: 9072.44 | P76: 3699.72 | Q76: 4593.58 | R76: 4717.86 | S76: 4000.86 | T76: 6567.72 | U76: 2390 | V76: 2088.86 | W76: 3585 | X76: 3585 | Y76: 3346 | Z76: 2868 | AA76: 4063 | AB76: 4063 | AC76: 2151 | AD76: 1195 | AE76: 2629 | AF76: 3824 | AG76: =SUM(B76:AF76) -> 301766.18
A77: Smart Bird Feeder PRO Solar with PEX (Retail SKU) | AG77: =SUM(B77:AF77) -> 0
A78: SUM (BB1 SBF) | B78: =sum(B75:B77) -> 26760 | C78: =sum(C75:C77) -> 33628 | D78: =sum(D75:D77) -> 70667 | E78: =sum(E75:E77) -> 62706 | F78: =sum(F75:F77) -> 56301 | G78: =sum(G75:G77) -> 48950 | H78: =sum(H75:H77) -> 46448.13 | I78: =sum(I75:I77) -> 29982.13 | ... AF78: =sum(AF75:AF77) -> 10061 | AG78: =SUM(B78:AF78) -> 640615.18
A80: Smart Hummingbird Feeder PRO | B80: 438 | C80: 2608 | D80: 3285 | E80: 5037 | F80: 2409 | G80: 657 | H80: 438 | I80: 657 | J80: 876 | K80: 0 | L80: 438 | M80: 438 | N80: 219 | O80: 219 | P80: 1095 | Q80: 0 | R80: 0 | S80: 0 | T80: 0 | U80: 0 | V80: 0 | W80: 0 | X80: 0 | Y80: 219 | Z80: 219 | AA80: 219 | AB80: 0 | AC80: 0 | AD80: 0 | AE80: 0 | AF80: 0 | AG80: =SUM(B80:AF80) -> 19471
A81: Smart Hummingbird Feeder PRO Solar | B81: 8890 | C81: 14013 | D81: 21069 | E81: 22863 | F81: 22604 | G81: 6867 | H81: 4903 | I81: 2372 | J81: 3299 | K81: 1495 | L81: 877 | M81: 4485 | N81: 5900 | O81: 7176 | P81: 4784 | Q81: 4146 | R81: 8671 | S81: 5641 | T81: 3887 | U81: 2950 | V81: 4186 | W81: 2352 | X81: 4784 | Y81: 3847 | Z81: 5382 | AA81: 1415 | AB81: 3069 | AC81: 3069 | AD81: 2232 | AE81: 5301 | AF81: 4444 | AG81: =SUM(B81:AF81) -> 196973
A82: Smart Hummingbird Feeder PRO Solar (Retail SKU) | AG82: =SUM(B82:AF82) -> 0
A83: SUM (BB1 HBF) | B83: =sum(B80:B82) -> 9328 | C83: =sum(C80:C82) -> 16621 | D83: =sum(D80:D82) -> 24354 | E83: =sum(E80:E82) -> 27900 | F83: =sum(F80:F82) -> 25013 | G83: =sum(G80:G82) -> 7524 | H83: =sum(H80:H82) -> 5341 | I83: =sum(I80:I82) -> 3029 | ... AF83: =sum(AF80:AF82) -> 4444 | AG83: =SUM(B83:AF83) -> 216444
A85: BB2 | B85: =sum(B89,B93,B98) -> 299 | C85: =sum(C89,C93,C98) -> 2093 | D85: =sum(D89,D93,D98) -> 598 | E85: =sum(E89,E93,E98) -> 0 | F85: =sum(F89,F93,F98) -> 0 | G85: =sum(G89,G93,G98) -> 0 | H85: =sum(H89,H93,H98) -> 0 | I85: =sum(I89,I93,I98) -> 0 | ... AF85: =sum(AF89,AF93,AF98) -> 0 | AG85: =SUM(B85:AF85) -> 2990
A86: Birdbuddy 2 | B86: 299 | C86: 2093 | D86: 598 | E86: 0 | F86: 0 | G86: 0 | H86: 0 | I86: 0 | J86: 0 | K86: 0 | L86: 0 | M86: 0 | N86: 0 | O86: 0 | P86: 0 | Q86: 0 | R86: 0 | S86: 0 | T86: 0 | U86: 0 | V86: 0 | W86: 0 | X86: 0 | Y86: 0 | Z86: 0 | AA86: 0 | AB86: 0 | AC86: 0 | AD86: 0 | AE86: 0 | AF86: 0 | AG86: =SUM(B86:AF86) -> 2990
A87: Birdbuddy 2 PRO | AG87: =SUM(B87:AF87) -> 0
A88: Birdbuddy 2 Retail SKU | AG88: =SUM(B88:AF88) -> 0
A89: SUM (BB2 SBF) | B89: =sum(B86:B88) -> 299 | C89: =sum(C86:C88) -> 2093 | D89: =sum(D86:D88) -> 598 | E89: =sum(E86:E88) -> 0 | F89: =sum(F86:F88) -> 0 | G89: =sum(G86:G88) -> 0 | H89: =sum(H86:H88) -> 0 | I89: =sum(I86:I88) -> 0 | ... AF89: =sum(AF86:AF88) -> 0 | AG89: =SUM(B89:AF89) -> 2990
A91: Birdbuddy 2 Nectar | AG91: =SUM(B91:AF91) -> 0
A92: Birdbuddy 2 Nectar PRO | AG92: =SUM(B92:AF92) -> 0
A93: SUM (BB2 HBF) | B93: =sum(B91:B92) -> 0 | C93: =sum(C91:C92) -> 0 | D93: =sum(D91:D92) -> 0 | E93: =sum(E91:E92) -> 0 | F93: =sum(F91:F92) -> 0 | G93: =sum(G91:G92) -> 0 | H93: =sum(H91:H92) -> 0 | I93: =sum(I91:I92) -> 0 | ... AF93: =sum(AF91:AF92) -> 0 | AG93: =SUM(B93:AF93) -> 0
A95: Birdbuddy 2 Mini non Solar | AG95: =SUM(B95:AF95) -> 0
A96: Birdbuddy 2 Mini Solar | AG96: =SUM(B96:AF96) -> 0
A97: BB2 Mini Retail SKU | AG97: =SUM(B97:AF97) -> 0
A98: SUM (BB2 MINI) | B98: =sum(B95:B97) -> 0 | C98: =sum(C95:C97) -> 0 | D98: =sum(D95:D97) -> 0 | E98: =sum(E95:E97) -> 0 | F98: =sum(F95:F97) -> 0 | G98: =sum(G95:G97) -> 0 | H98: =sum(H95:H97) -> 0 | I98: =sum(I95:I97) -> 0 | ... AF98: =sum(AF95:AF97) -> 0 | AG98: =SUM(B98:AF98) -> 0
A100: Wall Mount | B100: 551 | C100: 551 | D100: 841 | E100: 899 | F100: 783 | G100: 754 | H100: 1015 | I100: 638 | J100: 986 | K100: 1885 | L100: 957 | M100: 522 | N100: 580 | O100: 580 | P100: 812 | Q100: 1131 | R100: 609 | S100: 667 | T100: 522 | U100: 290 | V100: 203 | W100: 522 | X100: 406 | Y100: 754 | Z100: 841 | AA100: 435 | AB100: 348 | AC100: 348 | AD100: 464 | AE100: 638 | AF100: 609 | AG100: =SUM(B100:AF100) -> 21141
A101: Suet Ball Holder | B101: 0 | C101: 0 | D101: 0 | E101: 0 | F101: 0 | G101: 0 | H101: 0 | I101: 0 | J101: 0 | K101: 0 | L101: 0 | M101: 0 | N101: 0 | O101: 0 | P101: 0 | Q101: 0 | R101: 0 | S101: 0 | T101: 0 | U101: 0 | V101: 0 | W101: 0 | X101: 0 | Y101: 0 | Z101: 0 | AA101: 0 | AB101: 0 | AC101: 0 | AD101: 0 | AE101: 0 | AF101: 0 | AG101: =SUM(B101:AF101) -> 0
A102: 3-in-1 Nutrition Set - Blue | B102: 390 | C102: 507 | D102: 936 | E102: 780 | F102: 702 | G102: 975 | H102: 624 | I102: 897 | J102: 546 | K102: 1248 | L102: 507 | M102: 468 | N102: 663 | O102: 195 | P102: 429 | Q102: 507 | R102: 702 | S102: 234 | T102: 390 | U102: 468 | V102: 351 | W102: 468 | X102: 351 | Y102: 351 | Z102: 234 | AA102: 312 | AB102: 390 | AC102: 78 | AD102: 312 | AE102: 390 | AF102: 663 | AG102: =SUM(B102:AF102) -> 16068
A103: 3-in-1 Nutrition Set - Yellow | B103: 0 | C103: 0 | D103: 0 | E103: 0 | F103: 0 | G103: 0 | H103: 0 | I103: 0 | J103: 0 | K103: 0 | L103: 0 | M103: 0 | N103: 0 | O103: 0 | P103: 0 | Q103: 0 | R103: 0 | S103: 0 | T103: 0 | U103: 0 | V103: 0 | W103: 0 | X103: 0 | Y103: 0 | Z103: 0 | AA103: 0 | AB103: 0 | AC103: 0 | AD103: 0 | AE103: 0 | AF103: 0 | AG103: =SUM(B103:AF103) -> 0
A104: Solar Roof Single - Blue | B104: 0 | C104: 0 | D104: 0 | E104: 0 | F104: 0 | G104: 0 | H104: 0 | I104: 0 | J104: 0 | K104: 0 | L104: 0 | M104: 0 | N104: 0 | O104: 0 | P104: 0 | Q104: 0 | R104: 0 | S104: 0 | T104: 0 | U104: 0 | V104: 0 | W104: 0 | X104: 0 | Y104: 0 | Z104: 0 | AA104: 0 | AB104: 0 | AC104: 0 | AD104: 0 | AE104: 0 | AF104: 0 | AG104: =SUM(B104:AF104) -> 0
A105: Solar Roof Single - Yellow | B105: 0 | C105: 0 | D105: 0 | E105: 0 | F105: 0 | G105: 0 | H105: 0 | I105: 0 | J105: 0 | K105: 0 | L105: 0 | M105: 0 | N105: 0 | O105: 0 | P105: 0 | Q105: 0 | R105: 0 | S105: 0 | T105: 0 | U105: 0 | V105: 0 | W105: 0 | X105: 0 | Y105: 0 | Z105: 0 | AA105: 0 | AB105: 0 | AC105: 0 | AD105: 0 | AE105: 0 | AF105: 0 | AG105: =SUM(B105:AF105) -> 0
A106: Perch Extender - Blue | B106: 1160 | C106: 1740 | D106: 2289.84 | E106: 1914 | F106: 1392 | G106: 1740 | H106: 1836.86 | I106: 1382.43 | J106: 1740 | K106: 2407 | L106: 1268.46 | M106: 1035.3 | N106: 1173.92 | O106: 984.84 | P106: 1028.92 | Q106: 1195.38 | R106: 1210.46 | S106: 833.46 | T106: 775.46 | U106: 638 | V106: 775.46 | W106: 812 | X106: 696 | Y106: 1015 | Z106: 928 | AA106: 609 | AB106: 638 | AC106: 638 | AD106: 493 | AE106: 754 | AF106: 1015 | AG106: =SUM(B106:AF106) -> 36119.79
A107: Perch Extender - Yellow | B107: 0 | C107: 0 | D107: 0 | E107: 0 | F107: 0 | G107: 0 | H107: 0 | I107: 0 | J107: 0 | K107: 0 | L107: 0 | M107: 0 | N107: 0 | O107: 0 | P107: 0 | Q107: 0 | R107: 0 | S107: 0 | T107: 0 | U107: 0 | V107: 0 | W107: 0 | X107: 0 | Y107: 0 | Z107: 0 | AA107: 0 | AB107: 0 | AC107: 0 | AD107: 0 | AE107: 0 | AF107: 0 | AG107: =SUM(B107:AF107) -> 0
A108: Solar Roof (HBF) | AG108: =SUM(B108:AF108) -> 0
A109: Housing - only (HBF) | AG109: =SUM(B109:AF109) -> 0
A110: Nature Station Bloom | AG110: =SUM(B110:AF110) -> 0
A111: Nature Station Essential | AG111: =SUM(B111:AF111) -> 0
A112: Pollinator Pot | AG112: =SUM(B112:AF112) -> 0
A113: SUM (Add-ons) | B113: =sum(B100:B112) -> 2101 | C113: =sum(C100:C112) -> 2798 | D113: =sum(D100:D112) -> 4066.84 | E113: =sum(E100:E112) -> 3593 | F113: =sum(F100:F112) -> 2877 | G113: =sum(G100:G112) -> 3469 | H113: =sum(H100:H112) -> 3475.86 | I113: =sum(I100:I112) -> 2917.43 | ... AF113: =sum(AF100:AF112) -> 2287 | AG113: =SUM(B113:AF113) -> 73328.79
A117: Units Cancelled (Gross) | B117: =sum(B118,B129) -> 8 | C117: =sum(C118,C129) -> 11 | D117: =sum(D118,D129) -> 15 | E117: =sum(E118,E129) -> 14 | F117: =sum(F118,F129) -> 12 | G117: =sum(G118,G129) -> 14 | H117: =sum(H118,H129) -> 10 | I117: =sum(I118,I129) -> 11 | ... AF117: =sum(AF118,AF129) -> 2 | AG117: =SUM(B117:AF117) -> 189
A118: BB1 | B118: =sum(B122,B127) -> 8 | C118: =sum(C122,C127) -> 10 | D118: =sum(D122,D127) -> 15 | E118: =sum(E122,E127) -> 14 | F118: =sum(F122,F127) -> 12 | G118: =sum(G122,G127) -> 14 | H118: =sum(H122,H127) -> 10 | I118: =sum(I122,I127) -> 11 | ... AF118: =sum(AF122,AF127) -> 2 | AG118: =SUM(B118:AF118) -> 188
A119: Smart Bird Feeder PRO | B119: 2 | C119: 1 | D119: 1 | E119: 1 | F119: 4 | G119: 8 | H119: 8 | I119: 10 | J119: 6 | K119: 3 | L119: 2 | M119: 5 | N119: 2 | O119: 2 | P119: 4 | Q119: 6 | R119: 4 | S119: 0 | T119: 3 | U119: 2 | V119: 2 | W119: 2 | X119: 3 | Y119: 4 | Z119: 3 | AA119: 2 | AB119: 2 | AC119: 2 | AD119: 1 | AE119: 2 | AF119: 1 | AG119: =SUM(B119:AF119) -> 98
A120: Smart Bird Feeder PRO Solar | B120: 5 | C120: 4 | D120: 7 | E120: 7 | F120: 4 | G120: 4 | H120: 1 | I120: 1 | J120: 1 | K120: 0 | L120: 0 | M120: 0 | N120: 0 | O120: 2 | P120: 1 | Q120: 0 | R120: 1 | S120: 1 | T120: 1 | U120: 0 | V120: 0 | W120: 0 | X120: 0 | Y120: 0 | Z120: 0 | AA120: 1 | AB120: 1 | AC120: 1 | AD120: 0 | AE120: 0 | AF120: 0 | AG120: =SUM(B120:AF120) -> 43
A121: Smart Bird Feeder PRO Solar with PEX (Retail SKU) | AG121: =SUM(B121:AF121) -> 0
A122: SUM (BB1 SBF) | B122: =sum(B119:B121) -> 7 | C122: =sum(C119:C121) -> 5 | D122: =sum(D119:D121) -> 8 | E122: =sum(E119:E121) -> 8 | F122: =sum(F119:F121) -> 8 | G122: =sum(G119:G121) -> 12 | H122: =sum(H119:H121) -> 9 | I122: =sum(I119:I121) -> 11 | ... AF122: =sum(AF119:AF121) -> 1 | AG122: =SUM(B122:AF122) -> 141
A124: Smart Hummingbird Feeder PRO | B124: 0 | C124: 1 | D124: 3 | E124: 3 | F124: 1 | G124: 1 | H124: 0 | I124: 0 | J124: 2 | K124: 0 | L124: 1 | M124: 0 | N124: 0 | O124: 0 | P124: 1 | Q124: 0 | R124: 0 | S124: 0 | T124: 0 | U124: 0 | V124: 0 | W124: 0 | X124: 0 | Y124: 1 | Z124: 1 | AA124: 0 | AB124: 0 | AC124: 0 | AD124: 0 | AE124: 0 | AF124: 0 | AG124: =SUM(B124:AF124) -> 15
A125: Smart Hummingbird Feeder PRO Solar | B125: 1 | C125: 4 | D125: 4 | E125: 3 | F125: 3 | G125: 1 | H125: 1 | I125: 0 | J125: 1 | K125: 0 | L125: 0 | M125: 0 | N125: 1 | O125: 1 | P125: 2 | Q125: 0 | R125: 1 | S125: 1 | T125: 0 | U125: 0 | V125: 0 | W125: 1 | X125: 0 | Y125: 0 | Z125: 1 | AA125: 0 | AB125: 0 | AC125: 1 | AD125: 2 | AE125: 2 | AF125: 1 | AG125: =SUM(B125:AF125) -> 32
...

Sheet IndieGoGo Data
A1: 45870 | B1: 45870 | C1: 45871 | D1: 45872 | E1: 45873 | F1: 45874 | G1: 45875 | H1: 45876 | I1: 45877 | J1: 45878 | K1: 45879 | L1: 45880 | M1: 45881 | N1: 45882 | O1: 45883 | P1: 45884 | Q1: 45885 | R1: 45886 | S1: 45887 | T1: 45888 | U1: 45889 | V1: 45890 | W1: 45891 | X1: 45892 | Y1: 45893 | Z1: 45894 | AA1: 45895 | AB1: 45896 | AC1: 45897 | AD1: 45898 | AE1: 45899 | AF1: 45900
B2: FRI | C2: SAT | D2: SUN | E2: MON | F2: TUE | G2: WED | H2: THU | I2: FRI | J2: SAT | K2: SUN | L2: MON | M2: TUE | N2: WED | O2: THU | P2: FRI | Q2: SAT | R2: SUN | S2: MON | T2: TUE | U2: WED | V2: THU | W2: FRI | X2: SAT | Y2: SUN | Z2: MON | AA2: TUE | AB2: WED | AC2: THU | AD2: FRI | AE2: SAT | AF2: SUN | AG2: TOTAL
A4: IndieGoGo Revenue | B4: =SUM(B5:B9) -> 0 | C4: =SUM(C5:C9) -> 0 | D4: =SUM(D5:D9) -> 0 | E4: =SUM(E5:E9) -> 0 | F4: =SUM(F5:F9) -> 0 | G4: =SUM(G5:G9) -> 0 | H4: =SUM(H5:H9) -> 0 | I4: =SUM(I5:I9) -> 0 | ... AF4: =SUM(AF5:AF9) -> 0 | AG4: =SUM(A4:AE4) -> 0
A5: - Hardware | B5: 0 | C5: 0 | D5: 0 | E5: 0 | F5: 0 | G5: 0 | H5: 0 | I5: 0 | J5: 0 | K5: 0 | L5: 0 | M5: 0 | N5: 0 | O5: 0 | P5: 0 | Q5: 0 | R5: 0 | S5: 0 | T5: 0 | U5: 0 | V5: 0 | W5: 0 | X5: 0 | Y5: 0 | Z5: 0 | AA5: 0 | AB5: 0 | AC5: 0 | AD5: 0 | AE5: 0 | AF5: 0 | AG5: =SUM(A5:AE5) -> 0
A6: - Add-ons | B6: 0 | C6: 0 | D6: 0 | E6: 0 | F6: 0 | G6: 0 | H6: 0 | I6: 0 | J6: 0 | K6: 0 | L6: 0 | M6: 0 | N6: 0 | O6: 0 | P6: 0 | Q6: 0 | R6: 0 | S6: 0 | T6: 0 | U6: 0 | V6: 0 | W6: 0 | X6: 0 | Y6: 0 | Z6: 0 | AA6: 0 | AB6: 0 | AC6: 0 | AD6: 0 | AE6: 0 | AF6: 0 | AG6: =SUM(A6:AE6) -> 0
A7: - Merch | B7: 0 | C7: 0 | D7: 0 | E7: 0 | F7: 0 | G7: 0 | H7: 0 | I7: 0 | J7: 0 | K7: 0 | L7: 0 | M7: 0 | N7: 0 | O7: 0 | P7: 0 | Q7: 0 | R7: 0 | S7: 0 | T7: 0 | U7: 0 | V7: 0 | W7: 0 | X7: 0 | Y7: 0 | Z7: 0 | AA7: 0 | AB7: 0 | AC7: 0 | AD7: 0 | AE7: 0 | AF7: 0 | AG7: =SUM(A7:AE7) -> 0
A8: - Seeds | B8: 0 | C8: 0 | D8: 0 | E8: 0 | F8: 0 | G8: 0 | H8: 0 | I8: 0 | J8: 0 | K8: 0 | L8: 0 | M8: 0 | N8: 0 | O8: 0 | P8: 0 | Q8: 0 | R8: 0 | S8: 0 | T8: 0 | U8: 0 | V8: 0 | W8: 0 | X8: 0 | Y8: 0 | Z8: 0 | AA8: 0 | AB8: 0 | AC8: 0 | AD8: 0 | AE8: 0 | AF8: 0 | AG8: =SUM(A8:AE8) -> 0
A9: - Yearly Pro Subscription | B9: 0 | C9: 0 | D9: 0 | E9: 0 | F9: 0 | G9: 0 | H9: 0 | I9: 0 | J9: 0 | K9: 0 | L9: 0 | M9: 0 | N9: 0 | O9: 0 | P9: 0 | Q9: 0 | R9: 0 | S9: 0 | T9: 0 | U9: 0 | V9: 0 | W9: 0 | X9: 0 | Y9: 0 | Z9: 0 | AA9: 0 | AB9: 0 | AC9: 0 | AD9: 0 | AE9: 0 | AF9: 0 | AG9: =SUM(A9:AE9) -> 0
A11: - Fees | B11: 15 | C11: 0 | D11: 0 | E11: 0 | F11: 0 | G11: 0 | H11: 0 | I11: 0 | J11: 0 | K11: 0 | L11: 0 | M11: 0 | N11: 0 | O11: 0 | P11: 0 | Q11: 0 | R11: 0 | S11: 0 | T11: 0 | U11: 0 | V11: 0 | W11: 0 | X11: 0 | Y11: 0 | Z11: 0 | AA11: 0 | AB11: 0 | AC11: 0 | AD11: 0 | AE11: 0 | AF11: 0 | AG11: =SUM(A11:AE11) -> 15
A13: IndieGoGo Revenue Breakdown
A14: Smart Bird Bath with Solar Roof and Water Pump | B14: 0 | C14: 0 | D14: 0 | E14: 0 | F14: 0 | G14: 0 | H14: 0 | I14: 0 | J14: 0 | K14: 0 | L14: 0 | M14: 0 | N14: 0 | O14: 0 | P14: 0 | Q14: 0 | R14: 0 | S14: 0 | T14: 0 | U14: 0 | V14: 0 | W14: 0 | X14: 0 | Y14: 0 | Z14: 0 | AA14: 0 | AB14: 0 | AC14: 0 | AD14: 0 | AE14: 0 | AF14: 0 | AG14: =SUM(A14:AE14) -> 0
A15: Smart Bird Bath without Solar Roof and Water Pump | B15: 0 | C15: 0 | D15: 0 | E15: 0 | F15: 0 | G15: 0 | H15: 0 | I15: 0 | J15: 0 | K15: 0 | L15: 0 | M15: 0 | N15: 0 | O15: 0 | P15: 0 | Q15: 0 | R15: 0 | S15: 0 | T15: 0 | U15: 0 | V15: 0 | W15: 0 | X15: 0 | Y15: 0 | Z15: 0 | AA15: 0 | AB15: 0 | AC15: 0 | AD15: 0 | AE15: 0 | AF15: 0 | AG15: =SUM(A15:AE15) -> 0
A17: Bird Bath Housing without Solar Roof and Water Pump | B17: 0 | C17: 0 | D17: 0 | E17: 0 | F17: 0 | G17: 0 | H17: 0 | I17: 0 | J17: 0 | K17: 0 | L17: 0 | M17: 0 | N17: 0 | O17: 0 | P17: 0 | Q17: 0 | R17: 0 | S17: 0 | T17: 0 | U17: 0 | V17: 0 | W17: 0 | X17: 0 | Y17: 0 | Z17: 0 | AA17: 0 | AB17: 0 | AC17: 0 | AD17: 0 | AE17: 0 | AF17: 0 | AG17: =SUM(A17:AE17) -> 0
A18: Solar Roof and Water Pump | B18: 0 | C18: 0 | D18: 0 | E18: 0 | F18: 0 | G18: 0 | H18: 0 | I18: 0 | J18: 0 | K18: 0 | L18: 0 | M18: 0 | N18: 0 | O18: 0 | P18: 0 | Q18: 0 | R18: 0 | S18: 0 | T18: 0 | U18: 0 | V18: 0 | W18: 0 | X18: 0 | Y18: 0 | Z18: 0 | AA18: 0 | AB18: 0 | AC18: 0 | AD18: 0 | AE18: 0 | AF18: 0 | AG18: =SUM(A18:AE18) -> 0
A19: Pole Mounting System with Pollinator Base | B19: 0 | C19: 0 | D19: 0 | E19: 0 | F19: 0 | G19: 0 | H19: 0 | I19: 0 | J19: 0 | K19: 0 | L19: 0 | M19: 0 | N19: 0 | O19: 0 | P19: 0 | Q19: 0 | R19: 0 | S19: 0 | T19: 0 | U19: 0 | V19: 0 | W19: 0 | X19: 0 | Y19: 0 | Z19: 0 | AA19: 0 | AB19: 0 | AC19: 0 | AD19: 0 | AE19: 0 | AF19: 0 | AG19: =SUM(A19:AE19) -> 0
A21: IndieGoGo Orders | B21: 1 | C21: 0 | D21: 0 | E21: 0 | F21: 0 | G21: 0 | H21: 0 | I21: 0 | J21: 0 | K21: 0 | L21: 0 | M21: 0 | N21: 0 | O21: 0 | P21: 0 | Q21: 0 | R21: 0 | S21: 0 | T21: 0 | U21: 0 | V21: 0 | W21: 0 | X21: 0 | Y21: 0 | Z21: 0 | AA21: 0 | AB21: 0 | AC21: 0 | AD21: 0 | AE21: 0 | AF21: 0 | AG21: =SUM(A21:AE21) -> 1
A22: IndieGoGo Quantities | B22: =SUM(B23:B27) -> 1 | C22: =SUM(C23:C27) -> 0 | D22: =SUM(D23:D27) -> 0 | E22: =SUM(E23:E27) -> 0 | F22: =SUM(F23:F27) -> 0 | G22: =SUM(G23:G27) -> 0 | H22: =SUM(H23:H27) -> 0 | I22: =SUM(I23:I27) -> 0 | ... AF22: =SUM(AF23:AF27) -> 0 | AG22: =SUM(A22:AE22) -> 1
A23: - Hardware | B23: 1 | C23: 0 | D23: 0 | E23: 0 | F23: 0 | G23: 0 | H23: 0 | I23: 0 | J23: 0 | K23: 0 | L23: 0 | M23: 0 | N23: 0 | O23: 0 | P23: 0 | Q23: 0 | R23: 0 | S23: 0 | T23: 0 | U23: 0 | V23: 0 | W23: 0 | X23: 0 | Y23: 0 | Z23: 0 | AA23: 0 | AB23: 0 | AC23: 0 | AD23: 0 | AE23: 0 | AF23: 0 | AG23: =SUM(A23:AE23) -> 1
A24: - Add-ons | B24: 0 | C24: 0 | D24: 0 | E24: 0 | F24: 0 | G24: 0 | H24: 0 | I24: 0 | J24: 0 | K24: 0 | L24: 0 | M24: 0 | N24: 0 | O24: 0 | P24: 0 | Q24: 0 | R24: 0 | S24: 0 | T24: 0 | U24: 0 | V24: 0 | W24: 0 | X24: 0 | Y24: 0 | Z24: 0 | AA24: 0 | AB24: 0 | AC24: 0 | AD24: 0 | AE24: 0 | AF24: 0 | AG24: =SUM(A24:AE24) -> 0
A25: - Merch | B25: 0 | C25: 0 | D25: 0 | E25: 0 | F25: 0 | G25: 0 | H25: 0 | I25: 0 | J25: 0 | K25: 0 | L25: 0 | M25: 0 | N25: 0 | O25: 0 | P25: 0 | Q25: 0 | R25: 0 | S25: 0 | T25: 0 | U25: 0 | V25: 0 | W25: 0 | X25: 0 | Y25: 0 | Z25: 0 | AA25: 0 | AB25: 0 | AC25: 0 | AD25: 0 | AE25: 0 | AF25: 0 | AG25: =SUM(A25:AE25) -> 0
A26: - Seeds | B26: 0 | C26: 0 | D26: 0 | E26: 0 | F26: 0 | G26: 0 | H26: 0 | I26: 0 | J26: 0 | K26: 0 | L26: 0 | M26: 0 | N26: 0 | O26: 0 | P26: 0 | Q26: 0 | R26: 0 | S26: 0 | T26: 0 | U26: 0 | V26: 0 | W26: 0 | X26: 0 | Y26: 0 | Z26: 0 | AA26: 0 | AB26: 0 | AC26: 0 | AD26: 0 | AE26: 0 | AF26: 0 | AG26: =SUM(A26:AE26) -> 0
A27: - Yearly Pro Subscription | B27: 0 | C27: 0 | D27: 0 | E27: 0 | F27: 0 | G27: 0 | H27: 0 | I27: 0 | J27: 0 | K27: 0 | L27: 0 | M27: 0 | N27: 0 | O27: 0 | P27: 0 | Q27: 0 | R27: 0 | S27: 0 | T27: 0 | U27: 0 | V27: 0 | W27: 0 | X27: 0 | Y27: 0 | Z27: 0 | AA27: 0 | AB27: 0 | AC27: 0 | AD27: 0 | AE27: 0 | AF27: 0 | AG27: =SUM(A27:AE27) -> 0
A29: IndieGoGo Quantities Breakdown (New Products)
A30: Smart Bird Bath with Solar Roof and Water Pump | B30: 0 | C30: 0 | D30: 0 | E30: 0 | F30: 0 | G30: 0 | H30: 0 | I30: 0 | J30: 0 | K30: 0 | L30: 0 | M30: 0 | N30: 0 | O30: 0 | P30: 0 | Q30: 0 | R30: 0 | S30: 0 | T30: 0 | U30: 0 | V30: 0 | W30: 0 | X30: 0 | Y30: 0 | Z30: 0 | AA30: 0 | AB30: 0 | AC30: 0 | AD30: 0 | AE30: 0 | AF30: 0 | AG30: =SUM(A30:AE30) -> 0
A31: Smart Bird Bath without Solar Roof and Water Pump | B31: 0 | C31: 0 | D31: 0 | E31: 0 | F31: 0 | G31: 0 | H31: 0 | I31: 0 | J31: 0 | K31: 0 | L31: 0 | M31: 0 | N31: 0 | O31: 0 | P31: 0 | Q31: 0 | R31: 0 | S31: 0 | T31: 0 | U31: 0 | V31: 0 | W31: 0 | X31: 0 | Y31: 0 | Z31: 0 | AA31: 0 | AB31: 0 | AC31: 0 | AD31: 0 | AE31: 0 | AF31: 0 | AG31: =SUM(A31:AE31) -> 0
AG32: =SUM(A32:AE32) -> 0
A33: Bird Bath Housing without Solar Roof and Water Pump | B33: 0 | C33: 0 | D33: 0 | E33: 0 | F33: 0 | G33: 0 | H33: 0 | I33: 0 | J33: 0 | K33: 0 | L33: 0 | M33: 0 | N33: 0 | O33: 0 | P33: 0 | Q33: 0 | R33: 0 | S33: 0 | T33: 0 | U33: 0 | V33: 0 | W33: 0 | X33: 0 | Y33: 0 | Z33: 0 | AA33: 0 | AB33: 0 | AC33: 0 | AD33: 0 | AE33: 0 | AF33: 0 | AG33: =SUM(A33:AE33) -> 0
A34: Solar Roof and Water Pump | B34: 0 | C34: 0 | D34: 0 | E34: 0 | F34: 0 | G34: 0 | H34: 0 | I34: 0 | J34: 0 | K34: 0 | L34: 0 | M34: 0 | N34: 0 | O34: 0 | P34: 0 | Q34: 0 | R34: 0 | S34: 0 | T34: 0 | U34: 0 | V34: 0 | W34: 0 | X34: 0 | Y34: 0 | Z34: 0 | AA34: 0 | AB34: 0 | AC34: 0 | AD34: 0 | AE34: 0 | AF34: 0 | AG34: =SUM(A34:AE34) -> 0
A35: Pole Mounting System with Pollinator Base | B35: 0 | C35: 0 | D35: 0 | E35: 0 | F35: 0 | G35: 0 | H35: 0 | I35: 0 | J35: 0 | K35: 0 | L35: 0 | M35: 0 | N35: 0 | O35: 0 | P35: 0 | Q35: 0 | R35: 0 | S35: 0 | T35: 0 | U35: 0 | V35: 0 | W35: 0 | X35: 0 | Y35: 0 | Z35: 0 | AA35: 0 | AB35: 0 | AC35: 0 | AD35: 0 | AE35: 0 | AF35: 0 | AG35: =SUM(A35:AE35) -> 0
A37: IndieGoGo Quantities Breakdown (Other Products)
A38: Smart Bird Feeder with Solar Roof | B38: 0 | C38: 0 | D38: 0 | E38: 0 | F38: 0 | G38: 0 | H38: 0 | I38: 0 | J38: 0 | K38: 0 | L38: 0 | M38: 0 | N38: 0 | O38: 0 | P38: 0 | Q38: 0 | R38: 0 | S38: 0 | T38: 0 | U38: 0 | V38: 0 | W38: 0 | X38: 0 | Y38: 0 | Z38: 0 | AA38: 0 | AB38: 0 | AC38: 0 | AD38: 0 | AE38: 0 | AF38: 0 | AG38: =SUM(A38:AE38) -> 0
A39: Smart Bird Feeder | B39: 0 | C39: 0 | D39: 0 | E39: 0 | F39: 0 | G39: 0 | H39: 0 | I39: 0 | J39: 0 | K39: 0 | L39: 0 | M39: 0 | N39: 0 | O39: 0 | P39: 0 | Q39: 0 | R39: 0 | S39: 0 | T39: 0 | U39: 0 | V39: 0 | W39: 0 | X39: 0 | Y39: 0 | Z39: 0 | AA39: 0 | AB39: 0 | AC39: 0 | AD39: 0 | AE39: 0 | AF39: 0 | AG39: =SUM(A39:AE39) -> 0
A40: Smart Hummingbird Feeder | B40: 1 | C40: 0 | D40: 0 | E40: 0 | F40: 0 | G40: 0 | H40: 0 | I40: 0 | J40: 0 | K40: 0 | L40: 0 | M40: 0 | N40: 0 | O40: 0 | P40: 0 | Q40: 0 | R40: 0 | S40: 0 | T40: 0 | U40: 0 | V40: 0 | W40: 0 | X40: 0 | Y40: 0 | Z40: 0 | AA40: 0 | AB40: 0 | AC40: 0 | AD40: 0 | AE40: 0 | AF40: 0 | AG40: =SUM(A40:AE40) -> 1
A41: Smart Hummingbird Feeder with Solar Roof | B41: 0 | C41: 0 | D41: 0 | E41: 0 | F41: 0 | G41: 0 | H41: 0 | I41: 0 | J41: 0 | K41: 0 | L41: 0 | M41: 0 | N41: 0 | O41: 0 | P41: 0 | Q41: 0 | R41: 0 | S41: 0 | T41: 0 | U41: 0 | V41: 0 | W41: 0 | X41: 0 | Y41: 0 | Z41: 0 | AA41: 0 | AB41: 0 | AC41: 0 | AD41: 0 | AE41: 0 | AF41: 0 | AG41: =SUM(A41:AE41) -> 0
A43: Wall Mount | B43: 0 | C43: 0 | D43: 0 | E43: 0 | F43: 0 | G43: 0 | H43: 0 | I43: 0 | J43: 0 | K43: 0 | L43: 0 | M43: 0 | N43: 0 | O43: 0 | P43: 0 | Q43: 0 | R43: 0 | S43: 0 | T43: 0 | U43: 0 | V43: 0 | W43: 0 | X43: 0 | Y43: 0 | Z43: 0 | AA43: 0 | AB43: 0 | AC43: 0 | AD43: 0 | AE43: 0 | AF43: 0 | AG43: =SUM(A43:AE43) -> 0
A44: Suet Ball Holder | B44: 0 | C44: 0 | D44: 0 | E44: 0 | F44: 0 | G44: 0 | H44: 0 | I44: 0 | J44: 0 | K44: 0 | L44: 0 | M44: 0 | N44: 0 | O44: 0 | P44: 0 | Q44: 0 | R44: 0 | S44: 0 | T44: 0 | U44: 0 | V44: 0 | W44: 0 | X44: 0 | Y44: 0 | Z44: 0 | AA44: 0 | AB44: 0 | AC44: 0 | AD44: 0 | AE44: 0 | AF44: 0 | AG44: =SUM(A44:AE44) -> 0
A45: 3-in-1 Nutrition Set | B45: 0 | C45: 0 | D45: 0 | E45: 0 | F45: 0 | G45: 0 | H45: 0 | I45: 0 | J45: 0 | K45: 0 | L45: 0 | M45: 0 | N45: 0 | O45: 0 | P45: 0 | Q45: 0 | R45: 0 | S45: 0 | T45: 0 | U45: 0 | V45: 0 | W45: 0 | X45: 0 | Y45: 0 | Z45: 0 | AA45: 0 | AB45: 0 | AC45: 0 | AD45: 0 | AE45: 0 | AF45: 0 | AG45: =SUM(A45:AE45) -> 0
A46: Solar Roof | B46: 0 | C46: 0 | D46: 0 | E46: 0 | F46: 0 | G46: 0 | H46: 0 | I46: 0 | J46: 0 | K46: 0 | L46: 0 | M46: 0 | N46: 0 | O46: 0 | P46: 0 | Q46: 0 | R46: 0 | S46: 0 | T46: 0 | U46: 0 | V46: 0 | W46: 0 | X46: 0 | Y46: 0 | Z46: 0 | AA46: 0 | AB46: 0 | AC46: 0 | AD46: 0 | AE46: 0 | AF46: 0 | AG46: =SUM(A46:AE46) -> 0
A47: Perch Extender | B47: 0 | C47: 0 | D47: 0 | E47: 0 | F47: 0 | G47: 0 | H47: 0 | I47: 0 | J47: 0 | K47: 0 | L47: 0 | M47: 0 | N47: 0 | O47: 0 | P47: 0 | Q47: 0 | R47: 0 | S47: 0 | T47: 0 | U47: 0 | V47: 0 | W47: 0 | X47: 0 | Y47: 0 | Z47: 0 | AA47: 0 | AB47: 0 | AC47: 0 | AD47: 0 | AE47: 0 | AF47: 0 | AG47: =SUM(A47:AE47) -> 0
A48: Smart Hummingbird Feeder Solar Roof | B48: 0 | C48: 0 | D48: 0 | E48: 0 | F48: 0 | G48: 0 | H48: 0 | I48: 0 | J48: 0 | K48: 0 | L48: 0 | M48: 0 | N48: 0 | O48: 0 | P48: 0 | Q48: 0 | R48: 0 | S48: 0 | T48: 0 | U48: 0 | V48: 0 | W48: 0 | X48: 0 | Y48: 0 | Z48: 0 | AA48: 0 | AB48: 0 | AC48: 0 | AD48: 0 | AE48: 0 | AF48: 0 | AG48: =SUM(A48:AE48) -> 0
A49: Smart Hummingbird Feeder housing | B49: 0 | C49: 0 | D49: 0 | E49: 0 | F49: 0 | G49: 0 | H49: 0 | I49: 0 | J49: 0 | K49: 0 | L49: 0 | M49: 0 | N49: 0 | O49: 0 | P49: 0 | Q49: 0 | R49: 0 | S49: 0 | T49: 0 | U49: 0 | V49: 0 | W49: 0 | X49: 0 | Y49: 0 | Z49: 0 | AA49: 0 | AB49: 0 | AC49: 0 | AD49: 0 | AE49: 0 | AF49: 0 | AG49: =SUM(A49:AE49) -> 0
A51: Avian Choice | B51: 0 | C51: 0 | D51: 0 | E51: 0 | F51: 0 | G51: 0 | H51: 0 | I51: 0 | J51: 0 | K51: 0 | L51: 0 | M51: 0 | N51: 0 | O51: 0 | P51: 0 | Q51: 0 | R51: 0 | S51: 0 | T51: 0 | U51: 0 | V51: 0 | W51: 0 | X51: 0 | Y51: 0 | Z51: 0 | AA51: 0 | AB51: 0 | AC51: 0 | AD51: 0 | AE51: 0 | AF51: 0 | AG51: =SUM(A51:AE51) -> 0
... A56: 1 year Bird Buddy PRO subscription | B56: 0 | C56: 0 | D56: 0 | E56: 0 | F56: 0 | G56: 0 | H56: 0 | I56: 0 | J56: 0 | K56: 0 | L56: 0 | M56: 0 | N56: 0 | O56: 0 | P56: 0 | Q56: 0 | R56: 0 | S56: 0 | T56: 0 | U56: 0 | V56: 0 | W56: 0 | X56: 0 | Y56: 0 | Z56: 0 | AA56: 0 | AB56: 0 | AC56: 0 | AD56: 0 | AE56: 0 | AF56: 0 | AG56: =SUM(A56:AE56) -> 0

Sheet AMAZON EU - P&L
A1: MAY | B1: 46143 | C1: 46144 | D1: 46145 | E1: 46146 | F1: 46147 | G1: 46148 | H1: 46149 | I1: 46150 | J1: 46151 | K1: 46152 | L1: 46153 | M1: 46154 | N1: 46155 | O1: 46156 | P1: 46157 | Q1: 46158 | R1: 46159 | S1: 46160 | T1: 46161 | U1: 46162 | V1: 46163 | W1: 46164 | X1: 46165 | Y1: 46166 | Z1: 46167 | AA1: 46168 | AB1: 46169 | AC1: 46170 | AD1: 46171 | AE1: 46172 | AF1: 46173
A2: DAY | B2: FRI | C2: SAT | D2: SUN | E2: MON | F2: TUE | G2: WED | H2: THU | I2: FRI | J2: SAT | K2: SUN | L2: MON | M2: TUE | N2: WED | O2: THU | P2: FRI | Q2: SAT | R2: SUN | S2: MON | T2: TUE | U2: WED | V2: THU | W2: FRI | X2: SAT | Y2: SUN | Z2: MON | AA2: TUE | AB2: WED | AC2: THU | AD2: FRI | AE2: SAT | AF2: SUN
A3: COMMENT
A4: Orders
A5: Amazon UK | B5: =Summary!B106 -> 1 | C5: =Summary!C106 -> 0 | D5: =Summary!D106 -> 1 | E5: =Summary!E106 -> 0 | F5: =Summary!F106 -> 0 | G5: =Summary!G106 -> 1 | H5: =Summary!H106 -> 0 | I5: =Summary!I106 -> 0 | ... AF5: =Summary!AF106 -> 1
A6: Amazon FR | B6: =Summary!B107 -> 0 | C6: =Summary!C107 -> 0 | D6: =Summary!D107 -> 0 | E6: =Summary!E107 -> 1 | F6: =Summary!F107 -> 1 | G6: =Summary!G107 -> 0 | H6: =Summary!H107 -> 0 | I6: =Summary!I107 -> 0 | ... AF6: =Summary!AF107 -> 1
A7: Amazon GER | B7: =Summary!B108 -> 0 | C7: =Summary!C108 -> 0 | D7: =Summary!D108 -> 1 | E7: =Summary!E108 -> 0 | F7: =Summary!F108 -> 1 | G7: =Summary!G108 -> 0 | H7: =Summary!H108 -> 2 | I7: =Summary!I108 -> 1 | ... AF7: =Summary!AF108 -> 2
A8: All | B8: =SUM(B5:B7) -> 1 | C8: =SUM(C5:C7) -> 0 | D8: =SUM(D5:D7) -> 2 | E8: =SUM(E5:E7) -> 1 | F8: =SUM(F5:F7) -> 2 | G8: =SUM(G5:G7) -> 1 | H8: =SUM(H5:H7) -> 2 | I8: =SUM(I5:I7) -> 1 | ... AF8: =SUM(AF5:AF7) -> 4 | AG8: =SUM(B8:AF8) -> 62
A10: Revenue
A11: Amazon UK | B11: =Summary!B40 -> 45.94 | C11: =Summary!C40 -> 0 | D11: =Summary!D40 -> 45.97 | E11: =Summary!E40 -> 0 | F11: =Summary!F40 -> 0 | G11: =Summary!G40 -> 45.99 | H11: =Summary!H40 -> 0 | I11: =Summary!I40 -> 0 | ... AF11: =Summary!AF40 -> 45.51
A12: Amazon FR | B12: =Summary!B41 -> 0 | C12: =Summary!C41 -> 0 | D12: =Summary!D41 -> 0 | E12: =Summary!E41 -> 39.55 | F12: =Summary!F41 -> 32.88 | G12: =Summary!G41 -> 0 | H12: =Summary!H41 -> 0 | I12: =Summary!I41 -> 0 | ... AF12: =Summary!AF41 -> 238.57
A13: Amazon GER | B13: =Summary!B42 -> 0 | C13: =Summary!C42 -> 0 | D13: =Summary!D42 -> 28.6 | E13: =Summary!E42 -> 0 | F13: =Summary!F42 -> 232.93 | G13: =Summary!G42 -> 0 | H13: =Summary!H42 -> 473.42 | I13: =Summary!I42 -> 240.08 | ... AF13: =Summary!AF42 -> 271.13
A14: All | B14: =SUM(B11:B13) -> 45.94 | C14: =SUM(C11:C13) -> 0 | D14: =SUM(D11:D13) -> 74.57 | E14: =SUM(E11:E13) -> 39.55 | F14: =SUM(F11:F13) -> 265.81 | G14: =SUM(G11:G13) -> 45.99 | H14: =SUM(H11:H13) -> 473.42 | I14: =SUM(I11:I13) -> 240.08 | ... AF14: =SUM(AF11:AF13) -> 555.21 | AG14: =SUM(B14:AF14) -> 9839.11
A16: Media Cost
A17: Amazon EU Spend | B17: =SUM(B18:B20) -> 37.7 | C17: =SUM(C18:C20) -> 62.42 | D17: =SUM(D18:D20) -> 58.52 | E17: =SUM(E18:E20) -> 29.04 | F17: =SUM(F18:F20) -> 63.65 | G17: =SUM(G18:G20) -> 42.01 | H17: =SUM(H18:H20) -> 39.76 | I17: =SUM(I18:I20) -> 34.77 | ... AF17: =SUM(AF18:AF20) -> 0
A18: - Amazon UK Spend | B18: =Summary!B145 -> 0 | C18: =Summary!C145 -> 0 | D18: =Summary!D145 -> 0 | E18: =Summary!E145 -> 0 | F18: =Summary!F145 -> 0 | G18: =Summary!G145 -> 0 | H18: =Summary!H145 -> 0 | I18: =Summary!I145 -> 0 | ... AF18: =Summary!AF145 -> 0
A19: - Amazon FR Spend | B19: =Summary!B146 -> 6.25 | C19: =Summary!C146 -> 19.46 | D19: =Summary!D146 -> 16.34 | E19: =Summary!E146 -> 2.74 | F19: =Summary!F146 -> 4.92 | G19: =Summary!G146 -> 10.67 | H19: =Summary!H146 -> 1.53 | I19: =Summary!I146 -> 7.79 | ... AF19: =Summary!AF146 -> 0
A20: - Amazon GER Spend | B20: =Summary!B147 -> 31.45 | C20: =Summary!C147 -> 42.96 | D20: =Summary!D147 -> 42.18 | E20: =Summary!E147 -> 26.3 | F20: =Summary!F147 -> 58.73 | G20: =Summary!G147 -> 31.34 | H20: =Summary!H147 -> 38.23 | I20: =Summary!I147 -> 26.98 | ... AF20: =Summary!AF147 -> 0
A21: Amazon EU Platform Fee (? %)
A22: All | B22: =SUM(B18:B21) -> 37.7 | C22: =SUM(C18:C21) -> 62.42 | D22: =SUM(D18:D21) -> 58.52 | E22: =SUM(E18:E21) -> 29.04 | F22: =SUM(F18:F21) -> 63.65 | G22: =SUM(G18:G21) -> 42.01 | H22: =SUM(H18:H21) -> 39.76 | I22: =SUM(I18:I21) -> 34.77 | ... AF22: =SUM(AF18:AF21) -> 0 | AG22: =SUM(B22:AF22) -> 1181.33
A26: Amazon EU Orders
A27: Hardware | B27: =SUM('AMAZON UK, FR, GER - P&L'!B19,'AMAZON UK, FR, GER - P&L'!B295,'AMAZON UK, FR, GER - P&L'!B571) -> 0 | C27: =SUM('AMAZON UK, FR, GER - P&L'!C19,'AMAZON UK, FR, GER - P&L'!C295,'AMAZON UK, FR, GER - P&L'!C571) -> 0 | D27: =SUM('AMAZON UK, FR, GER - P&L'!D19,'AMAZON UK, FR, GER - P&L'!D295,'AMAZON UK, FR, GER - P&L'!D571) -> 0 | E27: =SUM('AMAZON UK, FR, GER - P&L'!E19,'AMAZON UK, FR, GER - P&L'!E295,'AMAZON UK, FR, GER - P&L'!E571) -> 0 | F27: =SUM('AMAZON UK, FR, GER - P&L'!F19,'AMAZON UK, FR, GER - P&L'!F295,'AMAZON UK, FR, GER - P&L'!F571) -> 232.93 | G27: =SUM('AMAZON UK, FR, GER - P&L'!G19,'AMAZON UK, FR, GER - P&L'!G295,'AMAZON UK, FR, GER - P&L'!G571) -> 0 | H27: =SUM('AMAZON UK, FR, GER - P&L'!H19,'AMAZON UK, FR, GER - P&L'!H295,'AMAZON UK, FR, GER - P&L'!H571) -> 466.69 | I27: =SUM('AMAZON UK, FR, GER - P&L'!I19,'AMAZON UK, FR, GER - P&L'!I295,'AMAZON UK, FR, GER - P&L'!I571) -> 233.35 | ... AF27: =SUM('AMAZON UK, FR, GER - P&L'!AF19,'AMAZON UK, FR, GER - P&L'!AF295,'AMAZON UK, FR, GER - P&L'!AF571) -> 463.77 | AG27: =SUM(B27:AF27) -> 8486.48
A28: Addons | B28: =SUM('AMAZON UK, FR, GER - P&L'!B20,'AMAZON UK, FR, GER - P&L'!B296,'AMAZON UK, FR, GER - P&L'!B572) -> 39.38 | C28: =SUM('AMAZON UK, FR, GER - P&L'!C20,'AMAZON UK, FR, GER - P&L'!C296,'AMAZON UK, FR, GER - P&L'!C572) -> 0 | D28: =SUM('AMAZON UK, FR, GER - P&L'!D20,'AMAZON UK, FR, GER - P&L'!D296,'AMAZON UK, FR, GER - P&L'!D572) -> 68.01 | E28: =SUM('AMAZON UK, FR, GER - P&L'!E20,'AMAZON UK, FR, GER - P&L'!E296,'AMAZON UK, FR, GER - P&L'!E572) -> 33.9 | F28: =SUM('AMAZON UK, FR, GER - P&L'!F20,'AMAZON UK, FR, GER - P&L'!F296,'AMAZON UK, FR, GER - P&L'!F572) -> 30.59 | G28: =SUM('AMAZON UK, FR, GER - P&L'!G20,'AMAZON UK, FR, GER - P&L'!G296,'AMAZON UK, FR, GER - P&L'!G572) -> 39.42 | H28: =SUM('AMAZON UK, FR, GER - P&L'!H20,'AMAZON UK, FR, GER - P&L'!H296,'AMAZON UK, FR, GER - P&L'!H572) -> 0 | I28: =SUM('AMAZON UK, FR, GER - P&L'!I20,'AMAZON UK, FR, GER - P&L'!I296,'AMAZON UK, FR, GER - P&L'!I572) -> 0 | ... AF28: =SUM('AMAZON UK, FR, GER - P&L'!AF20,'AMAZON UK, FR, GER - P&L'!AF296,'AMAZON UK, FR, GER - P&L'!AF572) -> 72.81 | AG28: =SUM(B28:AF28) -> 856.98
A29: Tax | B29: =SUM('AMAZON UK, FR, GER - P&L'!B21,'AMAZON UK, FR, GER - P&L'!B297,'AMAZON UK, FR, GER - P&L'!B573) -> 6.56 | C29: =SUM('AMAZON UK, FR, GER - P&L'!C21,'AMAZON UK, FR, GER - P&L'!C297,'AMAZON UK, FR, GER - P&L'!C573) -> 0 | D29: =SUM('AMAZON UK, FR, GER - P&L'!D21,'AMAZON UK, FR, GER - P&L'!D297,'AMAZON UK, FR, GER - P&L'!D573) -> 6.56 | E29: =SUM('AMAZON UK, FR, GER - P&L'!E21,'AMAZON UK, FR, GER - P&L'!E297,'AMAZON UK, FR, GER - P&L'!E573) -> 5.65 | F29: =SUM('AMAZON UK, FR, GER - P&L'!F21,'AMAZON UK, FR, GER - P&L'!F297,'AMAZON UK, FR, GER - P&L'!F573) -> 2.29 | G29: =SUM('AMAZON UK, FR, GER - P&L'!G21,'AMAZON UK, FR, GER - P&L'!G297,'AMAZON UK, FR, GER - P&L'!G573) -> 6.57 | H29: =SUM('AMAZON UK, FR, GER - P&L'!H21,'AMAZON UK, FR, GER - P&L'!H297,'AMAZON UK, FR, GER - P&L'!H573) -> 6.73 | I29: =SUM('AMAZON UK, FR, GER - P&L'!I21,'AMAZON UK, FR, GER - P&L'!I297,'AMAZON UK, FR, GER - P&L'!I573) -> 6.73 | ... AF29: =SUM('AMAZON UK, FR, GER - P&L'!AF21,'AMAZON UK, FR, GER - P&L'!AF297,'AMAZON UK, FR, GER - P&L'!AF573) -> 18.63 | AG29: =SUM(B29:AF29) -> 477.33
A30: Shipping | B30: =SUM('AMAZON UK, FR, GER - P&L'!B22,'AMAZON UK, FR, GER - P&L'!B298,'AMAZON UK, FR, GER - P&L'!B574) -> 0 | C30: =SUM('AMAZON UK, FR, GER - P&L'!C22,'AMAZON UK, FR, GER - P&L'!C298,'AMAZON UK, FR, GER - P&L'!C574) -> 0 | D30: =SUM('AMAZON UK, FR, GER - P&L'!D22,'AMAZON UK, FR, GER - P&L'!D298,'AMAZON UK, FR, GER - P&L'!D574) -> 0 | E30: =SUM('AMAZON UK, FR, GER - P&L'!E22,'AMAZON UK, FR, GER - P&L'!E298,'AMAZON UK, FR, GER - P&L'!E574) -> 0 | F30: =SUM('AMAZON UK, FR, GER - P&L'!F22,'AMAZON UK, FR, GER - P&L'!F298,'AMAZON UK, FR, GER - P&L'!F574) -> 0 | G30: =SUM('AMAZON UK, FR, GER - P&L'!G22,'AMAZON UK, FR, GER - P&L'!G298,'AMAZON UK, FR, GER - P&L'!G574) -> 0 | H30: =SUM('AMAZON UK, FR, GER - P&L'!H22,'AMAZON UK, FR, GER - P&L'!H298,'AMAZON UK, FR, GER - P&L'!H574) -> 0 | I30: =SUM('AMAZON UK, FR, GER - P&L'!I22,'AMAZON UK, FR, GER - P&L'!I298,'AMAZON UK, FR, GER - P&L'!I574) -> 0 | ... AF30: =SUM('AMAZON UK, FR, GER - P&L'!AF22,'AMAZON UK, FR, GER - P&L'!AF298,'AMAZON UK, FR, GER - P&L'!AF574) -> 0 | AG30: =SUM(B30:AF30) -> 18.32
A31: Gift Wrap Price | B31: =SUM('AMAZON UK, FR, GER - P&L'!B23,'AMAZON UK, FR, GER - P&L'!B299,'AMAZON UK, FR, GER - P&L'!B575) -> 0 | C31: =SUM('AMAZON UK, FR, GER - P&L'!C23,'AMAZON UK, FR, GER - P&L'!C299,'AMAZON UK, FR, GER - P&L'!C575) -> 0 | D31: =SUM('AMAZON UK, FR, GER - P&L'!D23,'AMAZON UK, FR, GER - P&L'!D299,'AMAZON UK, FR, GER - P&L'!D575) -> 0 | E31: =SUM('AMAZON UK, FR, GER - P&L'!E23,'AMAZON UK, FR, GER - P&L'!E299,'AMAZON UK, FR, GER - P&L'!E575) -> 0 | F31: =SUM('AMAZON UK, FR, GER - P&L'!F23,'AMAZON UK, FR, GER - P&L'!F299,'AMAZON UK, FR, GER - P&L'!F575) -> 0 | G31: =SUM('AMAZON UK, FR, GER - P&L'!G23,'AMAZON UK, FR, GER - P&L'!G299,'AMAZON UK, FR, GER - P&L'!G575) -> 0 | H31: =SUM('AMAZON UK, FR, GER - P&L'!H23,'AMAZON UK, FR, GER - P&L'!H299,'AMAZON UK, FR, GER - P&L'!H575) -> 0 | I31: =SUM('AMAZON UK, FR, GER - P&L'!I23,'AMAZON UK, FR, GER - P&L'!I299,'AMAZON UK, FR, GER - P&L'!I575) -> 0 | ... AF31: =SUM('AMAZON UK, FR, GER - P&L'!AF23,'AMAZON UK, FR, GER - P&L'!AF299,'AMAZON UK, FR, GER - P&L'!AF575) -> 0 | AG31: =SUM(B31:AF31) -> 0
A32: All Amazon EU | B32: =SUM(B27:B31) -> 45.94 | C32: =SUM(C27:C31) -> 0 | D32: =SUM(D27:D31) -> 74.57 | E32: =SUM(E27:E31) -> 39.55 | F32: =SUM(F27:F31) -> 265.81 | G32: =SUM(G27:G31) -> 45.99 | H32: =SUM(H27:H31) -> 473.42 | I32: =SUM(I27:I31) -> 240.08 | ... AF32: =SUM(AF27:AF31) -> 555.21 | AG32: =SUM(B32:AF32) -> 9839.11
A36: Units Sold (Gross) | B36: =sum(B37,B48) -> 0 | C36: =sum(C37,C48) -> 0 | D36: =sum(D37,D48) -> 0 | E36: =sum(E37,E48) -> 0 | F36: =sum(F37,F48) -> 1 | G36: =sum(G37,G48) -> 0 | H36: =sum(H37,H48) -> 2 | I36: =sum(I37,I48) -> 1 | ... AF36: =sum(AF37,AF48) -> 2 | AG36: =SUM(B36:AF36) -> 37
A37: BB1 | B37: =sum(B41,B46) -> 0 | C37: =sum(C41,C46) -> 0 | D37: =sum(D41,D46) -> 0 | E37: =sum(E41,E46) -> 0 | F37: =sum(F41,F46) -> 1 | G37: =sum(G41,G46) -> 0 | H37: =sum(H41,H46) -> 2 | I37: =sum(I41,I46) -> 1 | ... AF37: =sum(AF41,AF46) -> 2 | AG37: =SUM(B37:AF37) -> 37
A38: Smart Bird Feeder PRO | B38: =sum('AMAZON UK, FR, GER - P&L'!B30,'AMAZON UK, FR, GER - P&L'!B306,'AMAZON UK, FR, GER - P&L'!B582) -> 0 | C38: =sum('AMAZON UK, FR, GER - P&L'!C30,'AMAZON UK, FR, GER - P&L'!C306,'AMAZON UK, FR, GER - P&L'!C582) -> 0 | D38: =sum('AMAZON UK, FR, GER - P&L'!D30,'AMAZON UK, FR, GER - P&L'!D306,'AMAZON UK, FR, GER - P&L'!D582) -> 0 | E38: =sum('AMAZON UK, FR, GER - P&L'!E30,'AMAZON UK, FR, GER - P&L'!E306,'AMAZON UK, FR, GER - P&L'!E582) -> 0 | F38: =sum('AMAZON UK, FR, GER - P&L'!F30,'AMAZON UK, FR, GER - P&L'!F306,'AMAZON UK, FR, GER - P&L'!F582) -> 0 | G38: =sum('AMAZON UK, FR, GER - P&L'!G30,'AMAZON UK, FR, GER - P&L'!G306,'AMAZON UK, FR, GER - P&L'!G582) -> 0 | H38: =sum('AMAZON UK, FR, GER - P&L'!H30,'AMAZON UK, FR, GER - P&L'!H306,'AMAZON UK, FR, GER - P&L'!H582) -> 0 | I38: =sum('AMAZON UK, FR, GER - P&L'!I30,'AMAZON UK, FR, GER - P&L'!I306,'AMAZON UK, FR, GER - P&L'!I582) -> 0 | ... AF38: =sum('AMAZON UK, FR, GER - P&L'!AF30,'AMAZON UK, FR, GER - P&L'!AF306,'AMAZON UK, FR, GER - P&L'!AF582) -> 0 | AG38: =SUM(B38:AF38) -> 4
A39: Smart Bird Feeder PRO Solar | B39: =sum('AMAZON UK, FR, GER - P&L'!B31,'AMAZON UK, FR, GER - P&L'!B307,'AMAZON UK, FR, GER - P&L'!B583) -> 0 | C39: =sum('AMAZON UK, FR, GER - P&L'!C31,'AMAZON UK, FR, GER - P&L'!C307,'AMAZON UK, FR, GER - P&L'!C583) -> 0 | D39: =sum('AMAZON UK, FR, GER - P&L'!D31,'AMAZON UK, FR, GER - P&L'!D307,'AMAZON UK, FR, GER - P&L'!D583) -> 0 | E39: =sum('AMAZON UK, FR, GER - P&L'!E31,'AMAZON UK, FR, GER - P&L'!E307,'AMAZON UK, FR, GER - P&L'!E583) -> 0 | F39: =sum('AMAZON UK, FR, GER - P&L'!F31,'AMAZON UK, FR, GER - P&L'!F307,'AMAZON UK, FR, GER - P&L'!F583) -> 1 | G39: =sum('AMAZON UK, FR, GER - P&L'!G31,'AMAZON UK, FR, GER - P&L'!G307,'AMAZON UK, FR, GER - P&L'!G583) -> 0 | H39: =sum('AMAZON UK, FR, GER - P&L'!H31,'AMAZON UK, FR, GER - P&L'!H307,'AMAZON UK, FR, GER - P&L'!H583) -> 2 | I39: =sum('AMAZON UK, FR, GER - P&L'!I31,'AMAZON UK, FR, GER - P&L'!I307,'AMAZON UK, FR, GER - P&L'!I583) -> 1 | ... AF39: =sum('AMAZON UK, FR, GER - P&L'!AF31,'AMAZON UK, FR, GER - P&L'!AF307,'AMAZON UK, FR, GER - P&L'!AF583) -> 2 | AG39: =SUM(B39:AF39) -> 33
A40: Smart Bird Feeder PRO Solar with PEX (Retail SKU) | AG40: =SUM(B40:AF40) -> 0
A41: SUM (BB1 SBF) | B41: =sum(B38:B40) -> 0 | C41: =sum(C38:C40) -> 0 | D41: =sum(D38:D40) -> 0 | E41: =sum(E38:E40) -> 0 | F41: =sum(F38:F40) -> 1 | G41: =sum(G38:G40) -> 0 | H41: =sum(H38:H40) -> 2 | I41: =sum(I38:I40) -> 1 | ... AF41: =sum(AF38:AF40) -> 2 | AG41: =SUM(B41:AF41) -> 37
A43: Smart Hummingbird Feeder PRO | AG43: =SUM(B43:AF43) -> 0
A44: Smart Hummingbird Feeder PRO Solar | AG44: =SUM(B44:AF44) -> 0
A45: Smart Hummingbird Feeder PRO Solar (Retail SKU) | AG45: =SUM(B45:AF45) -> 0
A46: SUM (BB1 HBF) | B46: =sum(B43:B45) -> 0 | C46: =sum(C43:C45) -> 0 | D46: =sum(D43:D45) -> 0 | E46: =sum(E43:E45) -> 0 | F46: =sum(F43:F45) -> 0 | G46: =sum(G43:G45) -> 0 | H46: =sum(H43:H45) -> 0 | I46: =sum(I43:I45) -> 0 | ... AF46: =sum(AF43:AF45) -> 0 | AG46: =SUM(B46:AF46) -> 0
A48: BB2 | B48: =sum(B52,B56,B61) -> 0 | C48: =sum(C52,C56,C61) -> 0 | D48: =sum(D52,D56,D61) -> 0 | E48: =sum(E52,E56,E61) -> 0 | F48: =sum(F52,F56,F61) -> 0 | G48: =sum(G52,G56,G61) -> 0 | H48: =sum(H52,H56,H61) -> 0 | I48: =sum(I52,I56,I61) -> 0 | ... AF48: =sum(AF52,AF56,AF61) -> 0 | AG48: =SUM(B48:AF48) -> 0
A49: Birdbuddy 2 | AG49: =SUM(B49:AF49) -> 0
A50: Birdbuddy 2 PRO | AG50: =SUM(B50:AF50) -> 0
A51: Birdbuddy 2 Retail SKU | AG51: =SUM(B51:AF51) -> 0
A52: SUM (BB2 SBF) | B52: =sum(B49:B51) -> 0 | C52: =sum(C49:C51) -> 0 | D52: =sum(D49:D51) -> 0 | E52: =sum(E49:E51) -> 0 | F52: =sum(F49:F51) -> 0 | G52: =sum(G49:G51) -> 0 | H52: =sum(H49:H51) -> 0 | I52: =sum(I49:I51) -> 0 | ... AF52: =sum(AF49:AF51) -> 0 | AG52: =SUM(B52:AF52) -> 0
A54: Birdbuddy 2 Nectar | AG54: =SUM(B54:AF54) -> 0
A55: Birdbuddy 2 Nectar PRO | AG55: =SUM(B55:AF55) -> 0
A56: SUM (BB2 HBF) | B56: =sum(B54:B55) -> 0 | C56: =sum(C54:C55) -> 0 | D56: =sum(D54:D55) -> 0 | E56: =sum(E54:E55) -> 0 | F56: =sum(F54:F55) -> 0 | G56: =sum(G54:G55) -> 0 | H56: =sum(H54:H55) -> 0 | I56: =sum(I54:I55) -> 0 | ... AF56: =sum(AF54:AF55) -> 0 | AG56: =SUM(B56:AF56) -> 0
A58: Birdbuddy 2 Mini non Solar | AG58: =SUM(B58:AF58) -> 0
A59: Birdbuddy 2 Mini Solar | AG59: =SUM(B59:AF59) -> 0
A60: BB2 Mini Retail SKU | AG60: =SUM(B60:AF60) -> 0
A61: SUM (BB2 MINI) | B61: =sum(B58:B60) -> 0 | C61: =sum(C58:C60) -> 0 | D61: =sum(D58:D60) -> 0 | E61: =sum(E58:E60) -> 0 | F61: =sum(F58:F60) -> 0 | G61: =sum(G58:G60) -> 0 | H61: =sum(H58:H60) -> 0 | I61: =sum(I58:I60) -> 0 | ... AF61: =sum(AF58:AF60) -> 0 | AG61: =SUM(B61:AF61) -> 0
A63: Wall Mount | B63: =sum('AMAZON UK, FR, GER - P&L'!B55,'AMAZON UK, FR, GER - P&L'!B331,'AMAZON UK, FR, GER - P&L'!B607) -> 0 | C63: =sum('AMAZON UK, FR, GER - P&L'!C55,'AMAZON UK, FR, GER - P&L'!C331,'AMAZON UK, FR, GER - P&L'!C607) -> 0 | D63: =sum('AMAZON UK, FR, GER - P&L'!D55,'AMAZON UK, FR, GER - P&L'!D331,'AMAZON UK, FR, GER - P&L'!D607) -> 0 | E63: =sum('AMAZON UK, FR, GER - P&L'!E55,'AMAZON UK, FR, GER - P&L'!E331,'AMAZON UK, FR, GER - P&L'!E607) -> 0 | F63: =sum('AMAZON UK, FR, GER - P&L'!F55,'AMAZON UK, FR, GER - P&L'!F331,'AMAZON UK, FR, GER - P&L'!F607) -> 0 | G63: =sum('AMAZON UK, FR, GER - P&L'!G55,'AMAZON UK, FR, GER - P&L'!G331,'AMAZON UK, FR, GER - P&L'!G607) -> 0 | H63: =sum('AMAZON UK, FR, GER - P&L'!H55,'AMAZON UK, FR, GER - P&L'!H331,'AMAZON UK, FR, GER - P&L'!H607) -> 0 | I63: =sum('AMAZON UK, FR, GER - P&L'!I55,'AMAZON UK, FR, GER - P&L'!I331,'AMAZON UK, FR, GER - P&L'!I607) -> 0 | ... AF63: =sum('AMAZON UK, FR, GER - P&L'!AF55,'AMAZON UK, FR, GER - P&L'!AF331,'AMAZON UK, FR, GER - P&L'!AF607) -> 0 | AG63: =SUM(B63:AF63) -> 0
A64: Suet Ball Holder | B64: =sum('AMAZON UK, FR, GER - P&L'!B56,'AMAZON UK, FR, GER - P&L'!B332,'AMAZON UK, FR, GER - P&L'!B608) -> 0 | C64: =sum('AMAZON UK, FR, GER - P&L'!C56,'AMAZON UK, FR, GER - P&L'!C332,'AMAZON UK, FR, GER - P&L'!C608) -> 0 | D64: =sum('AMAZON UK, FR, GER - P&L'!D56,'AMAZON UK, FR, GER - P&L'!D332,'AMAZON UK, FR, GER - P&L'!D608) -> 0 | E64: =sum('AMAZON UK, FR, GER - P&L'!E56,'AMAZON UK, FR, GER - P&L'!E332,'AMAZON UK, FR, GER - P&L'!E608) -> 0 | F64: =sum('AMAZON UK, FR, GER - P&L'!F56,'AMAZON UK, FR, GER - P&L'!F332,'AMAZON UK, FR, GER - P&L'!F608) -> 0 | G64: =sum('AMAZON UK, FR, GER - P&L'!G56,'AMAZON UK, FR, GER - P&L'!G332,'AMAZON UK, FR, GER - P&L'!G608) -> 0 | H64: =sum('AMAZON UK, FR, GER - P&L'!H56,'AMAZON UK, FR, GER - P&L'!H332,'AMAZON UK, FR, GER - P&L'!H608) -> 0 | I64: =sum('AMAZON UK, FR, GER - P&L'!I56,'AMAZON UK, FR, GER - P&L'!I332,'AMAZON UK, FR, GER - P&L'!I608) -> 0 | ... AF64: =sum('AMAZON UK, FR, GER - P&L'!AF56,'AMAZON UK, FR, GER - P&L'!AF332,'AMAZON UK, FR, GER - P&L'!AF608) -> 0 | AG64: =SUM(B64:AF64) -> 0
A65: 3-in-1 Nutrition Set - Blue | B65: =sum('AMAZON UK, FR, GER - P&L'!B57,'AMAZON UK, FR, GER - P&L'!B333,'AMAZON UK, FR, GER - P&L'!B609) -> 1 | C65: =sum('AMAZON UK, FR, GER - P&L'!C57,'AMAZON UK, FR, GER - P&L'!C333,'AMAZON UK, FR, GER - P&L'!C609) -> 0 | D65: =sum('AMAZON UK, FR, GER - P&L'!D57,'AMAZON UK, FR, GER - P&L'!D333,'AMAZON UK, FR, GER - P&L'!D609) -> 2 | E65: =sum('AMAZON UK, FR, GER - P&L'!E57,'AMAZON UK, FR, GER - P&L'!E333,'AMAZON UK, FR, GER - P&L'!E609) -> 1 | F65: =sum('AMAZON UK, FR, GER - P&L'!F57,'AMAZON UK, FR, GER - P&L'!F333,'AMAZON UK, FR, GER - P&L'!F609) -> 1 | G65: =sum('AMAZON UK, FR, GER - P&L'!G57,'AMAZON UK, FR, GER - P&L'!G333,'AMAZON UK, FR, GER - P&L'!G609) -> 1 | H65: =sum('AMAZON UK, FR, GER - P&L'!H57,'AMAZON UK, FR, GER - P&L'!H333,'AMAZON UK, FR, GER - P&L'!H609) -> 0 | I65: =sum('AMAZON UK, FR, GER - P&L'!I57,'AMAZON UK, FR, GER - P&L'!I333,'AMAZON UK, FR, GER - P&L'!I609) -> 0 | ... AF65: =sum('AMAZON UK, FR, GER - P&L'!AF57,'AMAZON UK, FR, GER - P&L'!AF333,'AMAZON UK, FR, GER - P&L'!AF609) -> 2 | AG65: =SUM(B65:AF65) -> 25
A66: 3-in-1 Nutrition Set - Yellow | B66: =sum('AMAZON UK, FR, GER - P&L'!B58,'AMAZON UK, FR, GER - P&L'!B334,'AMAZON UK, FR, GER - P&L'!B610) -> 0 | C66: =sum('AMAZON UK, FR, GER - P&L'!C58,'AMAZON UK, FR, GER - P&L'!C334,'AMAZON UK, FR, GER - P&L'!C610) -> 0 | D66: =sum('AMAZON UK, FR, GER - P&L'!D58,'AMAZON UK, FR, GER - P&L'!D334,'AMAZON UK, FR, GER - P&L'!D610) -> 0 | E66: =sum('AMAZON UK, FR, GER - P&L'!E58,'AMAZON UK, FR, GER - P&L'!E334,'AMAZON UK, FR, GER - P&L'!E610) -> 0 | F66: =sum('AMAZON UK, FR, GER - P&L'!F58,'AMAZON UK, FR, GER - P&L'!F334,'AMAZON UK, FR, GER - P&L'!F610) -> 0 | G66: =sum('AMAZON UK, FR, GER - P&L'!G58,'AMAZON UK, FR, GER - P&L'!G334,'AMAZON UK, FR, GER - P&L'!G610) -> 0 | H66: =sum('AMAZON UK, FR, GER - P&L'!H58,'AMAZON UK, FR, GER - P&L'!H334,'AMAZON UK, FR, GER - P&L'!H610) -> 0 | I66: =sum('AMAZON UK, FR, GER - P&L'!I58,'AMAZON UK, FR, GER - P&L'!I334,'AMAZON UK, FR, GER - P&L'!I610) -> 0 | ... AF66: =sum('AMAZON UK, FR, GER - P&L'!AF58,'AMAZON UK, FR, GER - P&L'!AF334,'AMAZON UK, FR, GER - P&L'!AF610) -> 0 | AG66: =SUM(B66:AF66) -> 0
