Workbook
Name zsupermetrics_ru0GDtbZzDLHQOQtJJ6K08MvUDyyp7: #REF!
Name zsupermetrics_DQl8lUbpTRu3fayaJJi7lVfOGKjNU4: 'Data - P&L'!$A$3:$A$4
Name zsupermetrics_BioPyGBzcBsy60UCQmPcTuFReEmghI: 'Data - P&L'!$B$2:$B$3
Name zsupermetrics_refreshAll: SupermetricsQueries!$H$5
Name zsupermetrics_n3GtLgiKpTmd2pYmQNMuq6TPD0qE0b: #REF!
Name zsupermetrics_refreshAllSilent: SupermetricsQueries!$H$6
Name zsupermetrics_Mgms9p0QzysYvrIhnsKACeVBVxfIEO: #REF!
Name zsupermetrics_Mgms9p0QzysYvrIhnsKACeVBVxfIEO: 'Data - P&L'!$A$2:$A$3
Name zsupermetrics_forceRefresh: SupermetricsQueries!$H$4
Name zsupermetrics_wbYMmT0YL9bAN0yhimW0ziPFnia9Dx: #REF!
Name zsupermetrics_iNpyVy90bWCI0yUaFQpxOtzWMa6sW4: #REF!
Name zsupermetrics_xwoIpANxRm908eDp5oKTwQpEI8gvD4: #REF!
Name zsupermetrics_n3GtLgiKpTmd2pYmQNMuq6TPD0qE0b: 'Data - P&L'!$B$4:$B$5
Name rdataslayer_42b112e4e4be4305bb4c1be75e2dd549: 'Data - P&L'!$B$2:$C$3
Name zsupermetrics_9i4W4hgd80uRpQLMeX0eRnESN8gjyv: #REF!
Name zsupermetrics_5bmwtOpHUbSYmDMeuCPkrxaojTprPP: #REF!
Name rdataslayer_3753ddf3234e496aa261974a0222e193: 'Data - P&L'!$H$2:$I$2
Name zsupermetrics_SGBxROnInO9rFyh3H7j2Lldx0Bdc5v: #REF!
Name zsupermetrics_pxuhRTEmIU93xSgKclyxajD0fCZ6rF: #REF!
Name zsupermetrics_ru0GDtbZzDLHQOQtJJ6K08MvUDyyp7: 'Data - P&L'!$B$4:$B$5
Name zsupermetrics_qWp7V908pNEYMtfv8QZvSTeDnBAHOU: 'Data - P&L'!$B$5:$C$13
Name rdataslayer_4a0f150f4f2f4e4f85c890c75b7a1fa4: #REF!
Name zsupermetrics_HgZqhorObHOtZHuyJjpmyYaEPoYntx: #REF!
Name zsupermetrics_YsFuuYtr8vOdNXCCPiFJIO38NP4b2T: #REF!
Name zsupermetrics_DQl8lUbpTRu3fayaJJi7lVfOGKjNU4: #REF!
Name zsupermetrics_YVuzfmsfdurz7Ldl84Rfns8oka6LsS: #REF!
Name zsupermetrics_4VkB7ij7WO0JjKBEgvjB2GHjSy2Egm: #REF!
Name zsupermetrics_9i4W4hgd80uRpQLMeX0eRnESN8gjyv: 'Data - P&L'!$C$13
Name zsupermetrics_lx4cNai7gT6tH4j08ZRkI21Qlpjioi: #REF!
Name rdataslayer_d70e473bcafe40a3aa834ce157fb2ba3: #REF!
Name zsupermetrics_NugLlrQxlKiqhxQae8EFpITBm1pLCj: 'Data - P&L'!$B$6:$C$13
Name zsupermetrics_8xojRjNDjo2jWHGDWjFEhflhyIq3Hq: Summary!$K$8:$K$30
Name rdataslayer_3753ddf3234e496aa261974a0222e193: #REF!
Name zsupermetrics_iNpyVy90bWCI0yUaFQpxOtzWMa6sW4: 'Data - P&L'!$A$2:$A$3
Name rdataslayer_4a0f150f4f2f4e4f85c890c75b7a1fa4: 'Data - P&L'!$D$2:$E$3
Name zsupermetrics_BioPyGBzcBsy60UCQmPcTuFReEmghI: #REF!
Name zsupermetrics_qWp7V908pNEYMtfv8QZvSTeDnBAHOU: #REF!
Name zsupermetrics_8xojRjNDjo2jWHGDWjFEhflhyIq3Hq: #REF!
Name zsupermetrics_wbYMmT0YL9bAN0yhimW0ziPFnia9Dx: 'Data - P&L'!$A$2:$A$3
Name zsupermetrics_4VkB7ij7WO0JjKBEgvjB2GHjSy2Egm: 'Data - P&L'!$B$4:$C$10
Name zsupermetrics_lx4cNai7gT6tH4j08ZRkI21Qlpjioi: 'Data - P&L'!$B$4:$C$13
Name rdataslayer_42b112e4e4be4305bb4c1be75e2dd549: #REF!
Name rdataslayer_adf57e64065742daa5b4161161b1c3ca: #REF!
Name rdataslayer_adf57e64065742daa5b4161161b1c3ca: 'Data - P&L'!$B$4:$D$5
Name zsupermetrics_NugLlrQxlKiqhxQae8EFpITBm1pLCj: #REF!
Name zsupermetrics_xwoIpANxRm908eDp5oKTwQpEI8gvD4: #REF!
Name zsupermetrics_YsFuuYtr8vOdNXCCPiFJIO38NP4b2T: 'Data - P&L'!$B$4:$C$13
Name rdataslayer_d70e473bcafe40a3aa834ce157fb2ba3: 'Data - P&L'!$C$8:$D$9
Name zsupermetrics_HgZqhorObHOtZHuyJjpmyYaEPoYntx: 'Data - P&L'!$B$4:$B$5

Sheet Summary
A1: 45292 | B1: 45292 | C1: 45293 | D1: 45294 | E1: 45295 | F1: 45296 | G1: 45297 | H1: 45298 | I1: 45299 | J1: 45300 | K1: 45301 | L1: 45302 | M1: 45303 | N1: 45304 | O1: 45305 | P1: 45306 | Q1: 45307 | R1: 45308 | S1: 45309 | T1: 45310 | U1: 45311 | V1: 45312 | W1: 45313 | X1: 45314 | Y1: 45315 | Z1: 45316 | AA1: 45317 | AB1: 45318 | AC1: 45319 | AD1: 45320 | AE1: 45321 | AF1: 45322
B2: MON | C2: TUE | D2: WED | E2: THU | F2: FRI | G2: SAT | H2: SUN | I2: MON | J2: TUE | K2: WED | L2: THU | M2: FRI | N2: SAT | O2: SUN | P2: MON | Q2: TUE | R2: WED | S2: THU | T2: FRI | U2: SAT | V2: SUN | W2: MON | X2: TUE | Y2: WED | Z2: THU | AA2: FRI | AB2: SAT | AC2: SUN | AD2: MON | AE2: TUE | AF2: WED
A3: Weekend Work | B3: Peter | C3: Peter | G3: Peter | H3: Peter | N3: Peco | O3: Peco | U3: Peco | V3: Peco | AB3: Peter | AC3: Peter
A4: Notes
H5: Increased SKU4 stock by 50 | I5: 13:20 - SKU1 Amazon button, SKU2 updated to 194 stock, SKU3 back in stock with 393, SKU4 updated to 200 stock. On shop page, we show SKU3 instead of SKU4. | T5: 11:00 - SKU4 out of stock / Pro Bundle, yellow out of stock 13:27 - "20% off" promo ending / Reduced pricing for add-ons | Y5: - First order with new A/B test prices: #131667 (12:31) | AF5: - All yellow units option out of stock (15:37)
P6: Seeds Launch | Y6: Pricing A/B Test
A8: DTC Revenue | B8: 33166.99 | C8: 32204.7 | D8: 37759.59 | E8: 34093.84 | F8: 34903.7 | G8: 37601.7 | H8: 38315 | I8: 31136.13 | J8: 26907.68 | K8: 24059.75 | L8: 28780.21 | M8: 32396.98 | N8: 29630.85 | O8: 27553.58 | P8: 27869.29 | Q8: 25796.31 | R8: 32403.83 | S8: 26914.94 | T8: 27142.16 | U8: 34815.06 | V8: 18881.55 | W8: 20302.32 | X8: 22498.63 | Y8: 18260.61 | Z8: 18187.96 | AA8: 19073.76 | AB8: 20021.17 | AC8: 21449.04 | AD8: 20102.22 | AE8: 14972.58 | AF8: 17850.13
A9: - Hardware | B9: 20897.8 | C9: 21180.8 | D9: 27090.25 | E9: 24278.75 | F9: 23606.1 | G9: 25814.7 | H9: 24168.1 | I9: 21712.3 | J9: 19451.11 | K9: 17573.24 | L9: 20147.05 | M9: 24321.85 | N9: 19256.53 | O9: 17973.25 | P9: 19669.35 | Q9: 18340.13 | R9: 23673.5 | S9: 19148.68 | T9: 19822.35 | U9: 25440.05 | V9: 10620.2 | W9: 13425.9 | X9: 16754.05 | Y9: 13233.25 | Z9: 12355.35 | AA9: 12852.2 | AB9: 13490.2 | AC9: 15059.01 | AD9: 14025.8 | AE9: 10521.8 | AF9: 13440.2
A10: - Add-ons | B10: 8056.4 | C10: 7124.45 | D10: 6099.95 | E10: 5641.95 | F10: 6929.25 | G10: 7182.45 | H10: 9316.05 | I10: 5724.7 | J10: 4332.49 | K10: 3659.35 | L10: 5253.45 | M10: 4228.2 | N10: 6530.02 | O10: 5810 | P10: 4647 | Q10: 4200.82 | R10: 4763.7 | S10: 4177.27 | T10: 3701.15 | U10: 4704.8 | V10: 5101.75 | W10: 3964.65 | X10: 2996.15 | Y10: 2759.5 | Z10: 3347.65 | AA10: 3426.65 | AB10: 3644.4 | AC10: 3290.09 | AD10: 3086.35 | AE10: 2426 | AF10: 2053.65
A11: - Merch | B11: 58.14 | C11: 0 | D11: 76 | E11: 19 | F11: 44.99 | G11: 19 | H11: 130.15 | I11: 0 | J11: 58.99 | K11: 25.5 | L11: 39.99 | M11: 0 | N11: 0 | O11: 0 | P11: 39.99 | Q11: 0 | R11: 0 | S11: 0 | T11: 0 | U11: 0 | V11: 29.99 | W11: 0 | X11: 0 | Y11: 0 | Z11: 0 | AA11: 0 | AB11: 0 | AC11: 0 | AD11: 0 | AE11: 0 | AF11: 0
A12: - Seeds | B12: 0 | C12: 0 | D12: 0 | E12: 0 | F12: 0 | G12: 0 | H12: 0 | I12: 0 | J12: 0 | K12: 0 | L12: 0 | M12: 0 | N12: 0 | O12: 0 | P12: 32.8 | Q12: 91 | R12: 157.8 | S12: 297 | T12: 285.64 | U12: 272.37 | V12: 326.37 | W12: 271.72 | X12: 79.6 | Y12: 39.8 | Z12: 109.6 | AA12: 185.67 | AB12: 181.72 | AC12: 257.3 | AD12: 279.41 | AE12: 76.62 | AF12: 163.2
A13: - Taxes | B13: 1684.65 | C13: 1759.45 | D13: 2003.39 | E13: 1819.14 | F13: 1928.36 | G13: 2080.55 | H13: 1985.7 | I13: 1559.13 | J13: 1380.09 | K13: 1121.66 | L13: 1469.72 | M13: 1786.93 | N13: 1504.3 | O13: 1380.33 | P13: 1460.15 | Q13: 1348.36 | R13: 1757.83 | S13: 1417.99 | T13: 1343.02 | U13: 2054.84 | V13: 1013.24 | W13: 1121.05 | X13: 1175.83 | Y13: 939.06 | Z13: 1036.36 | AA13: 1084.24 | AB13: 1022.85 | AC13: 1131.64 | AD13: 1033.66 | AE13: 620.16 | AF13: 1017.08
A14: - Shipping | B14: 2470 | C14: 2140 | D14: 2490 | E14: 2335 | F14: 2395 | G14: 2505 | H14: 2715 | I14: 2140 | J14: 1685 | K14: 1680 | L14: 1870 | M14: 2060 | N14: 2340 | O14: 2390 | P14: 2020 | Q14: 1816 | R14: 2051 | S14: 1874 | T14: 1990 | U14: 2343 | V14: 1790 | W14: 1519 | X14: 1493 | Y14: 1289 | Z14: 1339 | AA14: 1525 | AB14: 1682 | AC14: 1711 | AD14: 1677 | AE14: 1328 | AF14: 1176
A15: Amazon Revenue | B15: =B16+B17+B18+B19+B20 -> 8259.3 | C15: =C16+C17+C18+C19+C20 -> 8509.69 | D15: =D16+D17+D18+D19+D20 -> 9959.99 | E15: =E16+E17+E18+E19+E20 -> 7222.59 | F15: =F16+F17+F18+F19+F20 -> 7395.73 | G15: =G16+G17+G18+G19+G20 -> 6262.25 | H15: =H16+H17+H18+H19+H20 -> 5480.06 | I15: =I16+I17+I18+I19+I20 -> 8883.31 | ... AF15: =AF16+AF17+AF18+AF19+AF20 -> 14667.91
A16: - Hardware | B16: 7579.26 | C16: 7878.36 | D16: 9382.76 | E16: 6797.99 | F16: 6870.37 | G16: 5854.37 | H16: 5096.37 | I16: 8203.4 | J16: 7081.24 | K16: 5634.26 | L16: 6359.39 | M16: 6559.07 | N16: 6368.68 | O16: 5184.96 | P16: 5980.28 | Q16: 4765.08 | R16: 5087.93 | S16: 6712.04 | T16: 7238.85 | U16: 11009.99 | V16: 13434.09 | W16: 13110.93 | X16: 8315.35 | Y16: 10572.52 | Z16: 6884.22 | AA16: 9832.15 | AB16: 9240.78 | AC16: 13967.45 | AD16: 15532.95 | AE16: 10092.73 | AF16: 13530.04
A17: - Add-ons | B17: 166.38 | C17: 87 | D17: 0 | E17: 0 | F17: 0 | G17: 0 | H17: 58 | I17: 116 | J17: 108.38 | K17: 0 | L17: 29 | M17: 166.38 | N17: 0 | O17: 29 | P17: 29 | Q17: 0 | R17: 87 | S17: 87 | T17: 0 | U17: 166.38 | V17: 290 | W17: 203 | X17: 232 | Y17: 261 | Z17: 232 | AA17: 261 | AB17: 435 | AC17: 754 | AD17: 406 | AE17: 448.76 | AF17: 203
A18: - Tax | B18: 503.88 | C18: 523.33 | D18: 567.45 | E18: 424.6 | F18: 520.47 | G18: 398.03 | H18: 325.29 | I18: 562.31 | J18: 476.34 | K18: 374.44 | L18: 442.43 | M18: 440.97 | N18: 434.23 | O18: 392.69 | P18: 413.92 | Q18: 341.09 | R18: 378.35 | S18: 492.53 | T18: 474.88 | U18: 805.87 | V18: 979.14 | W18: 980.73 | X18: 627.12 | Y18: 737.77 | Z18: 475.86 | AA18: 680.01 | AB18: 681.78 | AC18: 1027.38 | AD18: 1041.16 | AE18: 700.87 | AF18: 917.39
A19: - Shipping | B19: 0.5 | C19: 11.87 | D19: 0.5 | E19: 0 | F19: 0.25 | G19: 5.21 | H19: 0.25 | I19: 1 | J19: 21.15 | K19: 0.25 | L19: 1 | M19: 14.64 | N19: 0.5 | O19: 0 | P19: 6.4 | Q19: 0.75 | R19: 0 | S19: 7.74 | T19: 0 | U19: 11.83 | V19: 7.74 | W19: 0 | X19: 0.25 | Y19: 17.49 | Z19: 25.82 | AA19: 12.16 | AB19: 0 | AC19: 0.5 | AD19: 30.14 | AE19: 0.5 | AF19: 8.35
A20: - Gift Wrap | B20: 9.28 | C20: 9.13 | D20: 9.28 | E20: 0 | F20: 4.64 | G20: 4.64 | H20: 0.15 | I20: 0.6 | J20: 4.79 | K20: 0.15 | L20: 5.09 | M20: 5.09 | N20: 4.79 | O20: 0 | P20: 18.11 | Q20: 0.45 | R20: 0 | S20: 0.45 | T20: 0 | U20: 9.13 | V20: 13.92 | W20: 8.98 | X20: 18.11 | Y20: 0.3 | Z20: 27.09 | AA20: 0.15 | AB20: 0 | AC20: 13.77 | AD20: 26.59 | AE20: 0.3 | AF20: 9.13
A21: Digital Marketplaces Revenue | B21: =SUM(B26,B22) -> 0 | C21: =SUM(C26,C22) -> 0 | D21: =SUM(D26,D22) -> 0 | E21: =SUM(E26,E22) -> 0 | F21: =SUM(F26,F22) -> 0 | G21: =SUM(G26,G22) -> 0 | H21: =SUM(H26,H22) -> 0 | I21: =SUM(I26,I22) -> 0 | ... AF21: =SUM(AF26,AF22) -> 0
A22: Rachio | B22: =SUM(B23:B25) -> 0 | C22: =SUM(C23:C25) -> 0 | D22: =SUM(D23:D25) -> 0 | E22: =SUM(E23:E25) -> 0 | F22: =SUM(F23:F25) -> 0 | G22: =SUM(G23:G25) -> 0 | H22: =SUM(H23:H25) -> 0 | I22: =SUM(I23:I25) -> 0 | ... AF22: =SUM(AF23:AF25) -> 0
A23: - Hardware | B23: 0 | C23: 0 | D23: 0 | E23: 0 | F23: 0 | G23: 0 | H23: 0 | I23: 0 | J23: 0 | K23: 0 | L23: 0 | M23: 0 | N23: 0 | O23: 0 | P23: 0 | Q23: 0 | R23: 299.99 | S23: 0 | T23: 299.99 | U23: 0 | V23: 0 | W23: 0 | X23: 0 | Y23: 0 | Z23: 0 | AA23: 0 | AB23: 0 | AC23: 0 | AD23: 0 | AE23: 299.99 | AF23: 0
A24: - Tax | B24: =0.0614*B23 -> 0 | C24: =0.0614*C23 -> 0 | D24: =0.0614*D23 -> 0 | E24: =0.0614*E23 -> 0 | F24: =0.0614*F23 -> 0 | G24: =0.0614*G23 -> 0 | H24: =0.0614*H23 -> 0 | I24: =0.0614*I23 -> 0 | ... AF24: =0.0614*AF23 -> 0
A25: - Shipping | B25: 0 | C25: 0 | D25: 0 | E25: 0 | F25: 0 | G25: 0 | H25: 0 | I25: 0 | J25: 0 | K25: 0 | L25: 0 | M25: 0 | N25: 0 | O25: 0 | P25: 0 | Q25: 0 | R25: 0 | S25: 0 | T25: 0 | U25: 0 | V25: 0 | W25: 0 | X25: 0 | Y25: 0 | Z25: 0 | AA25: 0 | AB25: 0 | AC25: 0 | AD25: 0 | AE25: 0 | AF25: 0
A26: Weatherflow | B26: 0 | C26: 0 | D26: 0 | E26: 0 | F26: 0 | G26: 0 | H26: 0 | I26: 0 | J26: 0 | K26: 0 | L26: 0 | M26: 0 | N26: 0 | O26: 0 | P26: 0 | Q26: 0 | R26: 299 | S26: 0 | T26: 0 | U26: 0 | V26: 0 | W26: 0 | X26: 0 | Y26: 0 | Z26: 0 | AA26: 0 | AB26: 0 | AC26: 0 | AD26: 0 | AE26: 0 | AF26: 0
A27: - Hardware | B27: 0 | C27: 0 | D27: 0 | E27: 0 | F27: 0 | G27: 0 | H27: 0 | I27: 0 | J27: 0 | K27: 0 | L27: 0 | M27: 0 | N27: 0 | O27: 0 | P27: 0 | Q27: 0 | R27: 0 | S27: 0 | T27: 0 | U27: 0 | V27: 0 | W27: 0 | X27: 0 | Y27: 0 | Z27: 0 | AA27: 0 | AB27: 0 | AC27: 0 | AD27: 0 | AE27: 0 | AF27: 0
A28: - Tax | B28: =0.0614*B27 -> 0 | C28: =0.0614*C27 -> 0 | D28: =0.0614*D27 -> 0 | E28: =0.0614*E27 -> 0 | F28: =0.0614*F27 -> 0 | G28: =0.0614*G27 -> 0 | H28: =0.0614*H27 -> 0 | I28: =0.0614*I27 -> 0 | ... AF28: =0.0614*AF27 -> 0
A29: - Shipping | B29: 0 | C29: 0 | D29: 0 | E29: 0 | F29: 0 | G29: 0 | H29: 0 | I29: 0 | J29: 0 | K29: 0 | L29: 0 | M29: 0 | N29: 0 | O29: 0 | P29: 0 | Q29: 0 | R29: 0 | S29: 0 | T29: 0 | U29: 0 | V29: 0 | W29: 0 | X29: 0 | Y29: 0 | Z29: 0 | AA29: 0 | AB29: 0 | AC29: 0 | AD29: 0 | AE29: 0 | AF29: 0
A30: Total Revenue | B30: =SUM(B8+B15+B21) -> 41426.29 | C30: =SUM(C8+C15+C21) -> 40714.39 | D30: =SUM(D8+D15+D21) -> 47719.58 | E30: =SUM(E8+E15+E21) -> 41316.43 | F30: =SUM(F8+F15+F21) -> 42299.43 | G30: =SUM(G8+G15+G21) -> 43863.95 | H30: =SUM(H8+H15+H21) -> 43795.06 | I30: =SUM(I8+I15+I21) -> 40019.44 | ... AF30: =SUM(AF8+AF15+AF21) -> 32518.04
A32: B2B Revenue
A33: Best Buy | B33: =SUM(B34:B35) -> 2864.7186 | C33: =SUM(C34:C35) -> 0 | D33: =SUM(D34:D35) -> 4260.4596 | E33: =SUM(E34:E35) -> 2196.0366 | F33: =SUM(F34:F35) -> 237.7536 | G33: =SUM(G34:G35) -> 0 | H33: =SUM(H34:H35) -> 3968.5746 | I33: =SUM(I34:I35) -> 730.2432 | ... AF33: =SUM(AF34:AF35) -> 256.33871
A34: - Hardware | B34: 2699 | C34: 0 | D34: 4014 | E34: 2069 | F34: 224 | G34: 0 | H34: 3739 | I34: 688 | J34: 1221 | K34: 1110 | L34: 2211 | M34: 1131 | N34: 450 | O34: 750 | P34: 870 | Q34: 1350 | R34: 1860 | S34: 210 | T34: 3060 | U34: 2250 | V34: 3821.04 | W34: 2824.39 | X34: 1614.39 | Y34: 660 | Z34: 0 | AA34: 0 | AB34: 540 | AC34: 241.51 | AD34: 241.51 | AE34: 241.51 | AF34: 241.51
A35: - Tax | B35: =B34*'Data - P&L'!$U$3 -> 165.7186 | C35: =C34*'Data - P&L'!$U$3 -> 0 | D35: =D34*'Data - P&L'!$U$3 -> 246.4596 | E35: =E34*'Data - P&L'!$U$3 -> 127.0366 | F35: =F34*'Data - P&L'!$U$3 -> 13.7536 | G35: =G34*'Data - P&L'!$U$3 -> 0 | H35: =H34*'Data - P&L'!$U$3 -> 229.5746 | I35: =I34*'Data - P&L'!$U$3 -> 42.2432 | ... AF35: =AF34*'Data - P&L'!$U$3 -> 14.828714
A36: Target | B36: =sum(B37:B38) -> 254.736 | C36: =sum(C37:C38) -> 0 | D36: =sum(D37:D38) -> 241.9992 | E36: =sum(E37:E38) -> 254.736 | F36: =sum(F37:F38) -> 764.208 | G36: =sum(G37:G38) -> 254.736 | H36: =sum(H37:H38) -> 254.736 | I36: =sum(I37:I38) -> 748.287 | ... AF36: =sum(AF37:AF38) -> 0
A37: - Hardware | B37: 240 | C37: 0 | D37: 228 | E37: 240 | F37: 720 | G37: 240 | H37: 240 | I37: 705 | J37: 0 | K37: 684 | L37: 948 | M37: 894 | N37: 240 | O37: 240 | P37: 446 | Q37: 240 | R37: 463 | S37: 468 | T37: 0 | U37: 909 | V37: 252 | W37: 720 | X37: 240 | Y37: 12 | Z37: 228 | AA37: 1428 | AB37: 1198 | AC37: 195 | AD37: 0 | AE37: 1440 | AF37: 0
A38: - Tax | B38: =B37*'Data - P&L'!$U$3 -> 14.736 | C38: =C37*'Data - P&L'!$U$3 -> 0 | D38: =D37*'Data - P&L'!$U$3 -> 13.9992 | E38: =E37*'Data - P&L'!$U$3 -> 14.736 | F38: =F37*'Data - P&L'!$U$3 -> 44.208 | G38: =G37*'Data - P&L'!$U$3 -> 14.736 | H38: =H37*'Data - P&L'!$U$3 -> 14.736 | I38: =I37*'Data - P&L'!$U$3 -> 43.287 | ... AF38: =AF37*'Data - P&L'!$U$3 -> 0
A39: Total Revenue | B39: =B33+B36 -> 3119.4546 | C39: =C33+C36 -> 0 | D39: =D33+D36 -> 4502.4588 | E39: =E33+E36 -> 2450.7726 | F39: =F33+F36 -> 1001.9616 | G39: =G33+G36 -> 254.736 | H39: =H33+H36 -> 4223.3106 | I39: =I33+I36 -> 1478.5302 | ... AF39: =AF33+AF36 -> 256.33871
A41: App Revenue
A42: - Google Store | B42: ='App - P&L'!B90 -> 2765.3985 | C42: ='App - P&L'!C90 -> 1476.308 | D42: ='App - P&L'!D90 -> 1030.7135 | E42: ='App - P&L'!E90 -> 922.865 | F42: ='App - P&L'!F90 -> 1161.0445 | G42: ='App - P&L'!G90 -> 1303.5155 | H42: ='App - P&L'!H90 -> 1438.9295 | I42: ='App - P&L'!I90 -> 1317.493 | ... AF42: ='App - P&L'!AF90 -> 170.374
A43: - Apple Store | B43: ='App - P&L'!B91 -> 9876.4446 | C43: ='App - P&L'!C91 -> 5822.5217 | D43: ='App - P&L'!D91 -> 4519.4913 | E43: ='App - P&L'!E91 -> 4405.7317 | F43: ='App - P&L'!F91 -> 5186.4887 | G43: ='App - P&L'!G91 -> 6618.6471 | H43: ='App - P&L'!H91 -> 6029.4343 | I43: ='App - P&L'!I91 -> 4108.6256 | ... AF43: ='App - P&L'!AF91 -> 986.061
A44: - Comission | B44: ='App - P&L'!B67 -> 4741.8592 | C44: ='App - P&L'!C67 -> 2777.0313 | D44: ='App - P&L'!D67 -> 2134.4356 | E44: ='App - P&L'!E67 -> 2062.97 | F44: ='App - P&L'!F67 -> 2439.2349 | G44: ='App - P&L'!G67 -> 3083.2533 | H44: ='App - P&L'!H67 -> 2862.6081 | I44: ='App - P&L'!I67 -> 2008.6965 | ... AF44: ='App - P&L'!AF67 -> 459.465
A45: - Tax | B45: ='App - P&L'!B68 -> 58.8 | C45: ='App - P&L'!C68 -> 50.75 | D45: ='App - P&L'!D68 -> 37.4 | E45: ='App - P&L'!E68 -> 34.75 | F45: ='App - P&L'!F68 -> 31.1 | G45: ='App - P&L'!G68 -> 55.11 | H45: ='App - P&L'!H68 -> 74.09 | I45: ='App - P&L'!I68 -> 51.73 | ... AF45: ='App - P&L'!AF68 -> 22.77
A46: Total Revenue | B46: =sum(B42:B45) -> 17442.502 | C46: =sum(C42:C45) -> 10126.611 | D46: =sum(D42:D45) -> 7722.0404 | E46: =sum(E42:E45) -> 7426.3167 | F46: =sum(F42:F45) -> 8817.8682 | G46: =sum(G42:G45) -> 11060.526 | H46: =sum(H42:H45) -> 10405.062 | I46: =sum(I42:I45) -> 7486.5452 | ... AF46: =sum(AF42:AF45) -> 1638.67
A49: DTC Orders | B49: 191 | C49: 158 | D49: 179 | E49: 156 | F49: 178 | G49: 187 | H49: 195 | I49: 144 | J49: 113 | K49: 104 | L49: 131 | M49: 138 | N49: 140 | O49: 147 | P49: 128 | Q49: 117 | R49: 134 | S49: 107 | T49: 119 | U49: 150 | V49: 115 | W49: 96 | X49: 91 | Y49: 86 | Z49: 91 | AA49: 96 | AB49: 105 | AC49: 104 | AD49: 104 | AE49: 73 | AF49: 69
A50: - Hardware (units sold) | B50: 77 | C50: 79 | D50: 101 | E50: 90 | F50: 87 | G50: 93 | H50: 86 | I50: 79 | J50: 70 | K50: 63 | L50: 73 | M50: 88 | N50: 68 | O50: 64 | P50: 70 | Q50: 66 | R50: 83 | S50: 67 | T50: 72 | U50: 90 | V50: 39 | W50: 48 | X50: 61 | Y50: 49 | Z50: 48 | AA50: 52 | AB50: 52 | AC50: 59 | AD50: 57 | AE50: 44 | AF50: 49
A51: - Add-ons (units sold) | B51: 262 | C51: 220 | D51: 185 | E51: 194 | F51: 219 | G51: 237 | H51: 290 | I51: 162 | J51: 143 | K51: 119 | L51: 150 | M51: 138 | N51: 187 | O51: 160 | P51: 135 | Q51: 109 | R51: 140 | S51: 123 | T51: 114 | U51: 151 | V51: 158 | W51: 111 | X51: 99 | Y51: 81 | Z51: 104 | AA51: 111 | AB51: 113 | AC51: 101 | AD51: 100 | AE51: 72 | AF51: 68
A52: - Merch (units sold) | B52: 3 | C52: 0 | D52: 4 | E52: 1 | F52: 1 | G52: 1 | H52: 7 | I52: 0 | J52: 2 | K52: 1 | L52: 1 | M52: 0 | N52: 0 | O52: 0 | P52: 1 | Q52: 0 | R52: 0 | S52: 0 | T52: 0 | U52: 0 | V52: 1 | W52: 0 | X52: 0 | Y52: 0 | Z52: 0 | AA52: 0 | AB52: 0 | AC52: 0 | AD52: 0 | AE52: 0 | AF52: 0
A53: - Seeds (units sold) | B53: 0 | C53: 0 | D53: 0 | E53: 0 | F53: 0 | G53: 0 | H53: 0 | I53: 0 | J53: 0 | K53: 0 | L53: 0 | M53: 0 | N53: 0 | O53: 0 | P53: 1 | Q53: 4 | R53: 6 | S53: 14 | T53: 13 | U53: 12 | V53: 14 | W53: 11 | X53: 4 | Y53: 2 | Z53: 4 | AA53: 8 | AB53: 8 | AC53: 11 | AD53: 11 | AE53: 4 | AF53: 6
A54: Amazon Orders | B54: 14 | C54: 30 | D54: 34 | E54: 15 | F54: 23 | G54: 18 | H54: 22 | I54: 40 | J54: 23 | K54: 20 | L54: 26 | M54: 29 | N54: 23 | O54: 19 | P54: 20 | Q54: 23 | R54: 28 | S54: 19 | T54: 30 | U54: 49 | V54: 65 | W54: 52 | X54: 31 | Y54: 42 | Z54: 34 | AA54: 41 | AB54: 56 | AC54: 69 | AD54: 67 | AE54: 47 | AF54: 64
A55: - Hardware (units sold) | B55: ='AMAZON - P&L'!B32 -> 25 | C55: ='AMAZON - P&L'!C32 -> 26 | D55: ='AMAZON - P&L'!D32 -> 32 | E55: ='AMAZON - P&L'!E32 -> 23 | F55: ='AMAZON - P&L'!F32 -> 23 | G55: ='AMAZON - P&L'!G32 -> 19 | H55: ='AMAZON - P&L'!H32 -> 17 | I55: ='AMAZON - P&L'!I32 -> 28 | ... AF55: ='AMAZON - P&L'!AF32 -> 46
A56: - Add-ons (units sold) | B56: ='AMAZON - P&L'!B42 -> 8 | C56: ='AMAZON - P&L'!C42 -> 3 | D56: ='AMAZON - P&L'!D42 -> 0 | E56: ='AMAZON - P&L'!E42 -> 0 | F56: ='AMAZON - P&L'!F42 -> 0 | G56: ='AMAZON - P&L'!G42 -> 0 | H56: ='AMAZON - P&L'!H42 -> 2 | I56: ='AMAZON - P&L'!I42 -> 4 | ... AF56: ='AMAZON - P&L'!AF42 -> 9
A57: Digital Marketplaces Orders | B57: =SUM(B58:B59) -> 0 | C57: =SUM(C58:C59) -> 0 | D57: =SUM(D58:D59) -> 0 | E57: =SUM(E58:E59) -> 0 | F57: =SUM(F58:F59) -> 0 | G57: =SUM(G58:G59) -> 0 | H57: =SUM(H58:H59) -> 0 | I57: =SUM(I58:I59) -> 0 | ... AF57: =SUM(AF58:AF59) -> 0
A58: Rachio Orders | B58: 0 | C58: 0 | D58: 0 | E58: 0 | F58: 0 | G58: 0 | H58: 0 | I58: 0 | J58: 0 | K58: 0 | L58: 0 | M58: 0 | N58: 0 | O58: 0 | P58: 0 | Q58: 0 | R58: 1 | S58: 0 | T58: 1 | U58: 0 | V58: 0 | W58: 0 | X58: 0 | Y58: 0 | Z58: 0 | AA58: 0 | AB58: 0 | AC58: 0 | AD58: 0 | AE58: 1 | AF58: 0
A59: Weatherflow Orders | B59: 0 | C59: 0 | D59: 0 | E59: 0 | F59: 0 | G59: 0 | H59: 0 | I59: 0 | J59: 0 | K59: 0 | L59: 0 | M59: 0 | N59: 0 | O59: 0 | P59: 0 | Q59: 0 | R59: 0 | S59: 0 | T59: 0 | U59: 0 | V59: 0 | W59: 0 | X59: 0 | Y59: 0 | Z59: 0 | AA59: 0 | AB59: 0 | AC59: 0 | AD59: 0 | AE59: 0 | AF59: 0
A60: Total Orders | B60: =SUM(B49+B54+B58+B59) -> 205 | C60: =SUM(C49+C54+C58+C59) -> 188 | D60: =SUM(D49+D54+D58+D59) -> 213 | E60: =SUM(E49+E54+E58+E59) -> 171 | F60: =SUM(F49+F54+F58+F59) -> 201 | G60: =SUM(G49+G54+G58+G59) -> 205 | H60: =SUM(H49+H54+H58+H59) -> 217 | I60: =SUM(I49+I54+I58+I59) -> 184 | ... AF60: =SUM(AF49+AF54+AF58+AF59) -> 133
A62: B2B Orders
A63: Best Buy | B63: 9 | C63: 0 | D63: 13 | E63: 6 | F63: 0 | G63: 0 | H63: 12 | I63: 1 | J63: 3 | K63: 3 | L63: 7 | M63: 2 | N63: 0 | O63: 2 | P63: 2 | Q63: 4 | R63: 6 | S63: 0 | T63: 10 | U63: 7 | V63: 12 | W63: 9 | X63: 5 | Y63: 1 | Z63: 0 | AA63: 0 | AB63: 1 | AC63: 6 | AD63: 6 | AE63: 6 | AF63: 6
A64: Target | B64: 1 | C64: 0 | D64: 1 | E64: 1 | F64: 3 | G64: 1 | H64: 1 | I64: 3 | J64: 0 | K64: 3 | L64: 4 | M64: 4 | N64: 1 | O64: 1 | P64: 2 | Q64: 1 | R64: 2 | S64: 2 | T64: 0 | U64: 4 | V64: 1 | W64: 3 | X64: 1 | Y64: 0 | Z64: 1 | AA64: 6 | AB64: 5 | AC64: 1 | AD64: 0 | AE64: 6 | AF64: 0
A65: Total Orders | B65: =B63+B64 -> 10 | C65: =C63+C64 -> 0 | D65: =D63+D64 -> 14 | E65: =E63+E64 -> 7 | F65: =F63+F64 -> 3 | G65: =G63+G64 -> 1 | H65: =H63+H64 -> 13 | I65: =I63+I64 -> 4 | ... AF65: =AF63+AF64 -> 6
A67: App Orders
A68: - Google Store | B68: ='App - P&L'!B17 -> 80 | C68: ='App - P&L'!C17 -> 51 | D68: ='App - P&L'!D17 -> 36 | E68: ='App - P&L'!E17 -> 34 | F68: ='App - P&L'!F17 -> 35 | G68: ='App - P&L'!G17 -> 41 | H68: ='App - P&L'!H17 -> 49 | I68: ='App - P&L'!I17 -> 34 | ... AF68: ='App - P&L'!AF17 -> 7
A69: - Apple Store | B69: ='App - P&L'!B14 -> 417 | C69: ='App - P&L'!C14 -> 243 | D69: ='App - P&L'!D14 -> 211 | E69: ='App - P&L'!E14 -> 186 | F69: ='App - P&L'!F14 -> 210 | G69: ='App - P&L'!G14 -> 267 | H69: ='App - P&L'!H14 -> 261 | I69: ='App - P&L'!I14 -> 163 | ... AF69: ='App - P&L'!AF14 -> 77
A70: Total Orders | B70: =sum(B68:B69) -> 497 | C70: =sum(C68:C69) -> 294 | D70: =sum(D68:D69) -> 247 | E70: =sum(E68:E69) -> 220 | F70: =sum(F68:F69) -> 245 | G70: =sum(G68:G69) -> 308 | H70: =sum(H68:H69) -> 310 | I70: =sum(I68:I69) -> 197 | ... AF70: =sum(AF68:AF69) -> 84
A71: Meta Spend EUR | B71: =4806.33+518.48 -> 5324.81 | C71: =4433.77+489.76 -> 4923.53 | D71: =4232.17+493.64 -> 4725.81 | E71: =4224.91+495.1 -> 4720.01 | F71: =4244.21+497.25 -> 4741.46 | G71: =4253.36+496.69 -> 4750.05 | H71: =4460.13+519.27 -> 4979.4 | I71: =4413.26+513.03 -> 4926.29 | J71: =4319.26+506.49 -> 4825.75 | K71: =3372.44+474.27 -> 3846.71 | L71: =3542.75+484.34 -> 4027.09 | M71: =5440.92+488.46 -> 5929.38 | N71: =6563.11+514.12 -> 7077.23 | O71: =4772.94+505.15 -> 5278.09 | P71: =3356.3+521.75 -> 3878.05 | Q71: =2605.16+505.39 -> 3110.55 | R71: =2553.75+477.68 -> 3031.43 | S71: =2532.33+498.99 -> 3031.32 | T71: =2490.06+503.25 -> 2993.31 | U71: =4216.28+487.79 -> 4704.07 | V71: =5006.17+508.46 -> 5514.63 | W71: =3933.73+518.8 -> 4452.53 | X71: =3393.26+504.7 -> 3897.96 | Y71: =3107.49+504.33 -> 3611.82 | Z71: =2885.09+477.71 -> 3362.8 | AA71: =3187.95+487.65 -> 3675.6 | AB71: =2811.16+498.35 -> 3309.51 | AC71: =2975.2+549.52 -> 3524.72 | AD71: =2791.59+612.68 -> 3404.27 | AE71: =2665.46+609.73 -> 3275.19 | AF71: =2445.15+588.46 -> 3033.61
A72: Currency rate | B72: 1.1035 | C72: 1.0942 | D72: 1.0925 | E72: 1.0946 | F72: 1.0955 | G72: 1.0955 | H72: 1.0941 | I72: 1.0952 | J72: 1.0932 | K72: 1.0975 | L72: 1.0982 | M72: 1.0965 | N72: 1.0964 | O72: 1.0945 | P72: 1.0945 | Q72: 1.0879 | R72: 1.0885 | S72: 1.0876 | T72: 1.0915 | U72: 1.0905 | V72: 1.0891 | W72: 1.0877 | X72: 1.0857 | Y72: 1.0882 | Z72: 1.0849 | AA72: 1.0863 | AB72: 1.0863 | AC72: 1.0843 | AD72: 1.0833 | AE72: 1.0843 | AF72: 1.0803
A73: Meta Spend | B73: =B71*B72 -> 5875.9278 | C73: =C71*C72 -> 5387.3265 | D73: =D71*D72 -> 5162.9474 | E73: =E71*E72 -> 5166.5229 | F73: =F71*F72 -> 5194.2694 | G73: =G71*G72 -> 5203.6798 | H73: =H71*H72 -> 5447.9615 | I73: =I71*I72 -> 5395.2728 | ... AF73: =AF71*AF72 -> 3277.2089
A74: Google Spend | B74: 2110.5 | C74: 2483.96 | D74: 2246.44 | E74: 2102.96 | F74: 1929.45 | G74: 1781.1 | H74: 1937.55 | I74: 1693.38 | J74: 1540.91 | K74: 1576.04 | L74: 1309.01 | M74: 1489.27 | N74: 1724.12 | O74: 2074 | P74: 1820.73 | Q74: 1864.95 | R74: 1843.23 | S74: 1950.48 | T74: 2375.74 | U74: 2773.66 | V74: 2163.89 | W74: 1611.87 | X74: 1388.18 | Y74: 1565.56 | Z74: 1697.69 | AA74: 1648.68 | AB74: 1938 | AC74: 1950.33 | AD74: 1627.89 | AE74: 1410.82 | AF74: 1435.36
A75: Bing Spend | B75: 154.79 | C75: 206.25 | D75: 204.55 | E75: 163.92 | F75: 125.09 | G75: 91.32 | H75: 100.28 | I75: 119.37 | J75: 114.29 | K75: 164.97 | L75: 168.88 | M75: 198.87 | N75: 107.31 | O75: 226.23 | P75: 179.27 | Q75: 196.13 | R75: 171.38 | S75: 193.48 | T75: 180.95 | U75: 186.29 | V75: 188.49 | W75: 138.4 | X75: 181.91 | Y75: 114.39 | Z75: 118.29 | AA75: 109.18 | AB75: 82.2 | AC75: 108.2 | AD75: 96.26 | AE75: 96.82 | AF75: 96.51
A76: TikTok Spend | B76: 0 | C76: 0 | D76: 0 | E76: 0 | F76: 0 | G76: 0 | H76: 0 | I76: 0 | J76: 0 | K76: 0 | L76: 0 | M76: 0 | N76: 0 | O76: 0 | P76: 0 | Q76: 0 | R76: 0 | S76: 0 | T76: 0 | U76: 0 | V76: 0 | W76: 0 | X76: 0 | Y76: 0 | Z76: 0 | AA76: 0 | AB76: 0 | AC76: 0 | AD76: 0 | AE76: 0 | AF76: 0
A77: Amazon Spend | B77: 2390.92 | C77: 2568.83 | D77: 1913.96 | E77: 1152.11 | F77: 1392.03 | G77: 0 | H77: 0 | I77: 341.24 | J77: 892.25 | K77: 857 | L77: 986.01 | M77: 1180.06 | N77: 867.48 | O77: 1071.76 | P77: 1012.45 | Q77: 977.04 | R77: 936.82 | S77: 995.13 | T77: 1262.59 | U77: 1408.85 | V77: 1380.25 | W77: 672.65 | X77: 709.7 | Y77: 737.2 | Z77: 863.9 | AA77: 1191.1 | AB77: 1856.57 | AC77: 2428.3 | AD77: 1865.18 | AE77: 1736.58 | AF77: 1754.27
A78: Nextdoor Spend | B78: 0 | C78: 0 | D78: 0 | E78: 0 | F78: 0 | G78: 0 | H78: 0 | I78: 0 | J78: 0 | K78: 0 | L78: 0 | M78: 0 | N78: 0 | O78: 0 | P78: 0 | Q78: 0 | R78: 0 | S78: 0 | T78: 0 | U78: 0 | V78: 0 | W78: 0 | X78: 0 | Y78: 0 | Z78: 0 | AA78: 0 | AB78: 0 | AC78: 0 | AD78: 0 | AE78: 0 | AF78: 0
A79: IndieGoGo Spend | B79: 0 | C79: 0 | D79: 0 | E79: 0 | F79: 0 | G79: 0 | H79: 0 | I79: 0 | J79: 0 | K79: 0 | L79: 0 | M79: 0 | N79: 0 | O79: 0 | P79: 0 | Q79: 0 | R79: 0 | S79: 0 | T79: 0 | U79: 0 | V79: 0 | W79: 0 | X79: 0 | Y79: 0 | Z79: 0 | AA79: 0 | AB79: 0 | AC79: 0 | AD79: 0 | AE79: 0 | AF79: 0
A80: Affiliate Fees | B80: 0 | C80: 0 | D80: 0 | E80: 0 | F80: 0 | G80: 0 | H80: 0 | I80: 0 | J80: 68.2 | K80: 0 | L80: 22.91 | M80: 0 | N80: 0 | O80: 0 | P80: 0 | Q80: 0 | R80: 0 | S80: 0 | T80: 78.86 | U80: 0 | V80: 0 | W80: 0 | X80: 0 | Y80: 0 | Z80: 0 | AA80: 0 | AB80: 0 | AC80: 0 | AD80: 0 | AE80: 0 | AF80: 0
A81: Rachio Fees | B81: =B22*0.2 -> 0 | C81: =C22*0.2 -> 0 | D81: =D22*0.2 -> 0 | E81: =E22*0.2 -> 0 | F81: =F22*0.2 -> 0 | G81: =G22*0.2 -> 0 | H81: =H22*0.2 -> 0 | I81: =I22*0.2 -> 0 | ... AF81: =AF22*0.2 -> 0
A82: Weatherflow Fees | B82: =B26*0.15 -> 0 | C82: =C26*0.15 -> 0 | D82: =D26*0.15 -> 0 | E82: =E26*0.15 -> 0 | F82: =F26*0.15 -> 0 | G82: =G26*0.15 -> 0 | H82: =H26*0.15 -> 0 | I82: =I26*0.15 -> 0 | ... AF82: =AF26*0.15 -> 0
A83: Total DTC Spend | B83: =B73+B74+B75+B76+B78+B80 -> 8141.2178 | C83: =C73+C74+C75+C76+C78+C80 -> 8077.5365 | D83: =D73+D74+D75+D76+D78+D80 -> 7613.9374 | E83: =E73+E74+E75+E76+E78+E80 -> 7433.4029 | F83: =F73+F74+F75+F76+F78+F80 -> 7248.8094 | G83: =G73+G74+G75+G76+G78+G80 -> 7076.0998 | H83: =H73+H74+H75+H76+H78+H80 -> 7485.7915 | I83: =I73+I74+I75+I76+I78+I80 -> 7208.0228 | ... AF83: =AF73+AF74+AF75+AF76+AF78+AF80 -> 4809.0789
A84: Total Spend | B84: =SUM(B73:B82) -> 10532.138 | C84: =SUM(C73:C82) -> 10646.367 | D84: =SUM(D73:D82) -> 9527.8974 | E84: =SUM(E73:E82) -> 8585.5129 | F84: =SUM(F73:F82) -> 8640.8394 | G84: =SUM(G73:G82) -> 7076.0998 | H84: =SUM(H73:H82) -> 7485.7915 | I84: =SUM(I73:I82) -> 7549.2628 | ... AF84: =SUM(AF73:AF82) -> 6563.3489
A86: App Spend | AE86: 119.17 | AF86: 273.37
A87: Meta Spend | B87: 0 | C87: 0 | D87: 0 | E87: 0 | F87: 0 | G87: 0 | H87: 0 | I87: 0 | J87: 0 | K87: 0 | L87: 0 | M87: 0 | N87: 0 | O87: 0 | P87: 0 | Q87: 0 | R87: 0 | S87: 0 | T87: 0 | U87: 0 | V87: 0 | W87: 0 | X87: 0 | Y87: 0 | Z87: 0 | AA87: 0 | AB87: 0 | AC87: 0 | AD87: 0 | AE87: =AE86*AE72 -> 129.21603 | AF87: =AF86*AF72 -> 295.32161
A88: Apple Spend | B88: 100.26 | C88: 99.48 | D88: 98.52 | E88: 95.87 | F88: 98.06 | G88: 98.72 | H88: 99.07 | I88: 84.79 | J88: 36.01 | K88: 19.22 | L88: 55.87 | M88: 28.3 | N88: 45.02 | O88: 55.87 | P88: 39.8 | Q88: 38.97 | R88: 19.95 | S88: 18.16 | T88: 30.52 | U88: 42.99 | V88: 51.25 | W88: 44.38 | X88: 25.55 | Y88: 20.45 | Z88: 52.01 | AA88: 47.22 | AB88: 55.62 | AC88: 42.55 | AD88: 45.98 | AE88: 36.18 | AF88: 54.55
A89: Google Spend | B89: 0 | C89: 0 | D89: 0 | E89: 0 | F89: 0 | G89: 0 | H89: 0 | I89: 0 | J89: 0 | K89: 0 | L89: 0 | M89: 0 | N89: 0 | O89: 0 | P89: 0 | Q89: 0 | R89: 0 | S89: 0 | T89: 0 | U89: 0 | V89: 0 | W89: 0 | X89: 0 | Y89: 0 | Z89: 0 | AA89: 0 | AB89: 0 | AC89: 0 | AD89: 0 | AE89: 0 | AF89: 0
A90: Total APP Spend | B90: =SUM(B87:B88) -> 100.26 | C90: =SUM(C87:C88) -> 99.48 | D90: =SUM(D87:D88) -> 98.52 | E90: =SUM(E87:E88) -> 95.87 | F90: =SUM(F87:F88) -> 98.06 | G90: =SUM(G87:G88) -> 98.72 | H90: =SUM(H87:H88) -> 99.07 | I90: =SUM(I87:I88) -> 84.79 | ... AF90: =SUM(AF87:AF88) -> 349.87161
A92: Blended ROAS | B92: =B30/B84 -> 3.9333221 | C92: =C30/C84 -> 3.8242521 | D92: =D30/D84 -> 5.0084061 | E92: =E30/E84 -> 4.8123426 | F92: =F30/F84 -> 4.8952918 | G92: =G30/G84 -> 6.198888 | H92: =H30/H84 -> 5.8504247 | I92: =I30/I84 -> 5.3011057 | ... AF92: =AF30/AF84 -> 4.954489
A93: wROAS | B93: =B8/B83 -> 4.0739593 | C93: =C8/C83 -> 3.9869458 | D93: =D8/D83 -> 4.9592724 | E93: =E8/E83 -> 4.5865723 | F93: =F8/F83 -> 4.8150942 | G93: =G8/G83 -> 5.3139019 | H93: =H8/H83 -> 5.1183632 | I93: =I8/I83 -> 4.3196492 | ... AF93: =AF8/AF83 -> 3.7117565
A94: aROAS | B94: =B15/B77 -> 3.4544443 | C94: =C15/C77 -> 3.3126715 | D94: =D15/D77 -> 5.2038653 | E94: =E15/E77 -> 6.2690108 | F94: =F15/F77 -> 5.3129099 | G94: =G15/G77 -> #DIV/0! | H94: =H15/H77 -> #DIV/0! | I94: =I15/I77 -> 26.032441 | ... AF94: =AF15/AF77 -> 8.3612614
A95: appROAS | B95: =B46/B90 -> 173.97269 | C95: =C46/C90 -> 101.79545 | D95: =D46/D90 -> 78.380435 | E95: =E46/E90 -> 77.462362 | F95: =F46/F90 -> 89.923192 | G95: =G46/G90 -> 112.03936 | H95: =H46/H90 -> 105.02737 | I95: =I46/I90 -> 88.295143 | ... AF95: =AF46/AF90 -> 4.6836324
A97: Blended Spend per Unit | B97: =B84/sum('DTC - P&L'!B58,'AMAZON - P&L'!B32,'Digital Marketplaces - P & L'!B17,'Digital Marketplaces - P & L'!B129) -> 103.25625 | C97: =C84/sum('DTC - P&L'!C58,'AMAZON - P&L'!C32,'Digital Marketplaces - P & L'!C17,'Digital Marketplaces - P & L'!C129) -> 101.39397 | D97: =D84/sum('DTC - P&L'!D58,'AMAZON - P&L'!D32,'Digital Marketplaces - P & L'!D17,'Digital Marketplaces - P & L'!D129) -> 71.638327 | E97: =E84/sum('DTC - P&L'!E58,'AMAZON - P&L'!E32,'Digital Marketplaces - P & L'!E17,'Digital Marketplaces - P & L'!E129) -> 75.977991 | F97: =F84/sum('DTC - P&L'!F58,'AMAZON - P&L'!F32,'Digital Marketplaces - P & L'!F17,'Digital Marketplaces - P & L'!F129) -> 78.553086 | G97: =G84/sum('DTC - P&L'!G58,'AMAZON - P&L'!G32,'Digital Marketplaces - P & L'!G17,'Digital Marketplaces - P & L'!G129) -> 63.179462 | H97: =H84/sum('DTC - P&L'!H58,'AMAZON - P&L'!H32,'Digital Marketplaces - P & L'!H17,'Digital Marketplaces - P & L'!H129) -> 72.677588 | I97: =I84/sum('DTC - P&L'!I58,'AMAZON - P&L'!I32,'Digital Marketplaces - P & L'!I17,'Digital Marketplaces - P & L'!I129) -> 70.553858 | ... AF97: =AF84/sum('DTC - P&L'!AF58,'AMAZON - P&L'!AF32,'Digital Marketplaces - P & L'!AF17,'Digital Marketplaces - P & L'!AF129) -> 69.087883
A98: wSPU | B98: =B83/'DTC - P&L'!B58 -> 105.7301 | C98: =C83/'DTC - P&L'!C58 -> 102.2473 | D98: =D83/'DTC - P&L'!D58 -> 75.385519 | E98: =E83/'DTC - P&L'!E58 -> 82.593366 | F98: =F83/'DTC - P&L'!F58 -> 83.319649 | G98: =G83/'DTC - P&L'!G58 -> 76.087094 | H98: =H83/'DTC - P&L'!H58 -> 87.044088 | I98: =I83/'DTC - P&L'!I58 -> 91.240795 | ... AF98: =AF83/'DTC - P&L'!AF58 -> 98.144467
A99: aSPU | B99: =B77/'AMAZON - P&L'!B32 -> 95.6368 | C99: =C77/'AMAZON - P&L'!C32 -> 98.801154 | D99: =D77/'AMAZON - P&L'!D32 -> 59.81125 | E99: =E77/'AMAZON - P&L'!E32 -> 50.091739 | F99: =F77/'AMAZON - P&L'!F32 -> 60.523043 | G99: =G77/'AMAZON - P&L'!G32 -> 0 | H99: =H77/'AMAZON - P&L'!H32 -> 0 | I99: =I77/'AMAZON - P&L'!I32 -> 12.187143 | ... AF99: =AF77/'AMAZON - P&L'!AF32 -> 38.136304
A100: appCAC | B100: =B90/B70 -> 0.20173038 | C100: =C90/C70 -> 0.33836735 | D100: =D90/D70 -> 0.3988664 | E100: =E90/E70 -> 0.43577273 | F100: =F90/F70 -> 0.4002449 | G100: =G90/G70 -> 0.32051948 | H100: =H90/H70 -> 0.31958065 | I100: =I90/I70 -> 0.43040609 | ... AF100: =AF90/AF70 -> 4.1651382
A102: Web CR | B102: 0.0117 | C102: 0.0102 | D102: 0.011 | E102: 0.0122 | F102: 0.0176 | G102: 0.0178 | H102: 0.0174 | I102: 0.0153 | J102: 0.0132 | K102: 0.014 | L102: 0.0176 | M102: 0.0137 | N102: 0.0139 | O102: 0.0155 | P102: 0.0149 | Q102: 0.0148 | R102: 0.0171 | S102: 0.0132 | T102: 0.009 | U102: 0.0105 | V102: 0.0105 | W102: 0.0124 | X102: 0.0143 | Y102: 0.0136 | Z102: 0.0152 | AA102: 0.0166 | AB102: 0.0154 | AC102: 0.0153 | AD102: 0.0164 | AE102: 0.0119 | AF102: 0.0116
A103: Web AOV | B103: =B8/B49 -> 173.64916 | C103: =C8/C49 -> 203.82722 | D103: =D8/D49 -> 210.94743 | E103: =E8/E49 -> 218.55026 | F103: =F8/F49 -> 196.0882 | G103: =G8/G49 -> 201.07861 | H103: =H8/H49 -> 196.48718 | I103: =I8/I49 -> 216.22313 | ... AF103: =AF8/AF49 -> 258.69754
A104: fAOV | B104: 184.31 | C104: 216.71 | D104: 219.62 | E104: 228.99 | F104: 209.25 | G104: 224.39 | H104: 205.94 | I104: 225.84 | J104: 246.15 | K104: 250.37 | L104: 239.74 | M104: 250.05 | N104: 220.67 | O104: 196.03 | P104: 236.36 | Q104: 228.67 | R104: 249.23 | S104: 280.74 | T104: 230.74 | U104: 253.15 | V104: 183.88 | W104: 227.41 | X104: 266.51 | Y104: 229.05 | Z104: 204.11 | AA104: 195.45 | AB104: 212.27 | AC104: 214.31 | AD104: 214.31 | AE104: 206.49 | AF104: 275.66
A105: rAOV | B105: 125.14 | C105: 156.55 | D105: 145.82 | E105: 116.11 | F105: 119.39 | G105: 131.14 | H105: 130.08 | I105: 157.21 | J105: 111.24 | K105: 133.27 | L105: 134.28 | M105: 160.75 | N105: 169.51 | O105: 131.72 | P105: 134.31 | Q105: 150.49 | R105: 158.05 | S105: 138.58 | T105: 217.42 | U105: 150.05 | V105: 80.15 | W105: 143.38 | X105: 172.61 | Y105: 106.67 | Z105: 124.15 | AA105: 175.75 | AB105: 118.74 | AC105: 126.24 | AD105: 126.24 | AE105: 169.91 | AF105: 106.09
A107: Customers
A108: Returning | B108: 0.144 | C108: 0.162 | D108: 0.088 | E108: 0.134 | F108: 0.155 | G108: 0.214 | H108: 0.13 | I108: 0.162 | J108: 0.083 | K108: 0.17 | L108: 0.159 | M108: 0.123 | N108: 0.154 | O108: 0.139 | P108: 0.168 | Q108: 0.156 | R108: 0.135 | S108: 0.189 | T108: 0.1005 | U108: 0.188 | V108: 0.216 | W108: 0.228 | X108: 0.146 | Y108: 0.111 | Z108: 0.08 | AA108: 0.149 | AB108: 0.243 | AC108: 0.136 | AD108: 0.136 | AE108: 0.139 | AF108: 0.119
A109: First-time | B109: =1-B108 -> 0.856 | C109: =1-C108 -> 0.838 | D109: =1-D108 -> 0.912 | E109: =1-E108 -> 0.866 | F109: =1-F108 -> 0.845 | G109: =1-G108 -> 0.786 | H109: =1-H108 -> 0.87 | I109: =1-I108 -> 0.838 | ... AF109: =1-AF108 -> 0.881
B111: 45292 | C111: Goal | D111: % of Goal
A112: Revenue | B112: =SUM(B30:AF30)+SUM(B46:AF46) -> 1284673.2 | C112: 1200000 | D112: =B112/C112 -> 1.070561
A113: Spend | B113: =SUM(B84:AF84)+SUM(B90:AF90) -> 245563.36 | C113: =C112/C114 -> 300000 | D113: =B113/C113 -> 0.81854454
...

Sheet DTC - P&L
A1: JANUARY | B1: 45292 | C1: 45293 | D1: 45294 | E1: 45295 | F1: 45296 | G1: 45297 | H1: 45298 | I1: 45299 | J1: 45300 | K1: 45301 | L1: 45302 | M1: 45303 | N1: 45304 | O1: 45305 | P1: 45306 | Q1: 45307 | R1: 45308 | S1: 45309 | T1: 45310 | U1: 45311 | V1: 45312 | W1: 45313 | X1: 45314 | Y1: 45315 | Z1: 45316 | AA1: 45317 | AB1: 45318 | AC1: 45319 | AD1: 45320 | AE1: 45321 | AF1: 45322
A2: DAY | B2: MON | C2: TUE | D2: WED | E2: THU | F2: FRI | G2: SAT | H2: SUN | I2: MON | J2: TUE | K2: WED | L2: THU | M2: FRI | N2: SAT | O2: SUN | P2: MON | Q2: TUE | R2: WED | S2: THU | T2: FRI | U2: SAT | V2: SUN | W2: MON | X2: TUE | Y2: WED | Z2: THU | AA2: FRI | AB2: SAT | AC2: SUN | AD2: MON | AE2: TUE | AF2: WED
A3: COMMENT
A4: Orders
A5: Meta | B5: 46 | C5: 40 | D5: 39 | E5: 38 | F5: 40 | G5: 44 | H5: 47 | I5: 42 | J5: 32 | K5: 42 | L5: 25 | M5: 29 | N5: 30 | O5: 38 | P5: 29 | Q5: 15 | R5: 30 | S5: 29 | T5: 31 | U5: 40 | V5: 28 | W5: 27 | X5: 23 | Y5: 23 | Z5: 24 | AA5: 22 | AB5: 26 | AC5: 25 | AD5: 27 | AE5: 23 | AF5: 24 | AG5: =SUM(B5:AF5) -> 978
A6: Google | B6: 75.36 | C6: 44.92 | D6: 51.85 | E6: 52.24 | F6: 57.44 | G6: 63.57 | H6: 68.06 | I6: 42.02 | J6: 35 | K6: 36 | L6: 47.08 | M6: 39 | N6: 42 | O6: 43 | P6: 46 | Q6: 33 | R6: 51 | S6: 40 | T6: 34 | U6: 49 | V6: 42 | W6: 32 | X6: 34 | Y6: 18 | Z6: 27 | AA6: 30 | AB6: 48 | AC6: 31 | AD6: 30 | AE6: 24 | AF6: 25 | AG6: =SUM(B6:AF6) -> 1291.54
A7: TikTok | B7: 0 | C7: 0 | D7: 0 | E7: 0 | F7: 0 | G7: 0 | H7: 0 | I7: 0 | J7: 0 | K7: 0 | L7: 0 | M7: 0 | N7: 0 | O7: 0 | P7: 0 | Q7: 0 | R7: 0 | S7: 0 | T7: 0 | U7: 0 | V7: 0 | W7: 0 | X7: 0 | Y7: 0 | Z7: 0 | AA7: 0 | AB7: 0 | AC7: 0 | AD7: 0 | AE7: 0 | AF7: 0 | AG7: =SUM(B7:AF7) -> 0
A8: Bing | B8: 16 | C8: 4 | D8: 18 | E8: 16 | F8: 8 | G8: 14 | H8: 14 | I8: 14 | J8: 4 | K8: 8 | L8: 8 | M8: 16 | N8: 6 | O8: 4 | P8: 6 | Q8: 10 | R8: 14 | S8: 10 | T8: 8 | U8: 4 | V8: 10 | W8: 2 | X8: 2 | Y8: 10 | Z8: 6 | AA8: 4 | AB8: 6 | AC8: 10 | AD8: 4 | AE8: 2 | AF8: 4 | AG8: =SUM(B8:AF8) -> 262
A9: Nextdoor | B9: 0 | C9: 0 | D9: 0 | E9: 0 | F9: 0 | G9: 0 | H9: 0 | I9: 0 | J9: 0 | K9: 0 | L9: 0 | M9: 0 | N9: 0 | O9: 0 | P9: 0 | Q9: 0 | R9: 0 | S9: 0 | T9: 0 | U9: 0 | V9: 0 | W9: 0 | X9: 0 | Y9: 0 | Z9: 0 | AA9: 0 | AB9: 0 | AC9: 0 | AD9: 0 | AE9: 0 | AF9: 0 | AG9: =SUM(B9:AF9) -> 0
A10: Affiliates (Refersion) | B10: 0 | C10: 0 | D10: 0 | E10: 0 | F10: 0 | G10: 0 | H10: 0 | I10: 0 | J10: 1 | K10: 0 | L10: 1 | M10: 0 | N10: 0 | O10: 0 | P10: 0 | Q10: 0 | R10: 0 | S10: 0 | T10: 1 | U10: 0 | V10: 0 | W10: 0 | X10: 0 | Y10: 0 | AG10: =SUM(B10:AF10) -> 3
A11: Email | B11: 1 | C11: 3 | D11: 2 | E11: 2 | F11: 4 | G11: 3 | H11: 1 | I11: 1 | J11: 4 | K11: 0 | L11: 0 | M11: 0 | N11: 0 | O11: 0 | P11: 2 | Q11: 1 | R11: 0 | S11: 0 | T11: 0 | U11: 0 | V11: 0 | W11: 0 | X11: 0 | Y11: 0 | Z11: 0 | AA11: 0 | AB11: 0 | AC11: 0 | AD11: 0 | AE11: 1 | AF11: 2 | AG11: =SUM(B11:AF11) -> 27
A12: All | B12: =SUM(B5:B11) -> 138.36 | C12: =SUM(C5:C11) -> 91.92 | D12: =SUM(D5:D11) -> 110.85 | E12: =SUM(E5:E11) -> 108.24 | F12: =SUM(F5:F11) -> 109.44 | G12: =SUM(G5:G11) -> 124.57 | H12: =SUM(H5:H11) -> 130.06 | I12: =SUM(I5:I11) -> 99.02 | ... AF12: =SUM(AF5:AF11) -> 55 | AG12: =SUM(B12:AF12) -> 2561.54
A14: Revenue | X14: 3897.41 | Y14: 5024.95 | Z14: 3806.16 | AA14: 3508.79 | AB14: 4514.54 | AC14: 4610.42 | AD14: 3934.98 | AE14: 4850.18 | AF14: 5786.64
A15: Meta | B15: 7702.52 | C15: 7138.57 | D15: 6423.15 | E15: 8526.55 | F15: 8258.93 | G15: 7744.22 | H15: 7829.67 | I15: 9745.49 | J15: 8673.92 | K15: 9781.56 | L15: 5720.11 | M15: 7411.6 | N15: 6010.77 | O15: 6211.61 | P15: 5940.8639 | Q15: 2839.2095 | R15: 7473.512 | S15: 7249.34 | T15: 7038.1 | U15: 8068.47 | V15: 4105.76 | W15: 5139.4 | X15: =X14*Summary!X72 -> 4231.418 | Y15: =Y14*Summary!Y72 -> 5468.1506 | Z15: =Z14*Summary!Z72 -> 4129.303 | AA15: =AA14*Summary!AA72 -> 3811.5986 | AB15: =AB14*Summary!AB72 -> 4904.1448 | AC15: =AC14*Summary!AC72 -> 4999.0784 | AD15: =AD14*Summary!AD72 -> 4262.7638 | AE15: =AE14*Summary!AE72 -> 5259.0502 | AF15: =AF14*Summary!AF72 -> 6251.3072 | AG15: =SUM(B15:AF15) -> 198350.14
A16: Google | B16: 15176.01 | C16: 9959.28 | D16: 11082.87 | E16: 11276.45 | F16: 10964 | G16: 11756.22 | H16: 13968.19 | I16: 10252.98 | J16: 9054 | K16: 8915.82 | L16: 10439.04 | M16: 10492.28 | N16: 8424.68 | O16: 8581.54 | P16: 10279.53 | Q16: 8030.91 | R16: 13839.06 | S16: 9981.81 | T16: 9309.72 | U16: 11501.61 | V16: 7553.1 | W16: 8294.24 | X16: 8946.96 | Y16: 3117.79 | Z16: 6076.85 | AA16: 7215.22 | AB16: 10924.31 | AC16: 7074.07 | AD16: 5895.44 | AE16: 4831.05 | AF16: 5492.07 | AG16: =SUM(B16:AF16) -> 288707.1
A17: TikTok | B17: 0 | C17: 0 | D17: 0 | E17: 0 | F17: 0 | G17: 0 | H17: 0 | I17: 0 | J17: 0 | K17: 0 | L17: 0 | M17: 0 | N17: 0 | O17: 0 | P17: 0 | Q17: 0 | R17: 0 | S17: 0 | T17: 0 | U17: 0 | V17: 0 | W17: 0 | X17: 0 | Y17: 0 | Z17: 0 | AA17: 0 | AB17: 0 | AC17: 0 | AD17: 0 | AE17: 0 | AF17: 0 | AG17: =SUM(B17:AF17) -> 0
A18: Bing | B18: 2008 | C18: 502 | D18: 2259 | E18: 2008 | F18: 1004 | G18: 1757 | H18: 1757 | I18: 1757 | J18: 502 | K18: 1004 | L18: 1004 | M18: 2008 | N18: 753 | O18: 502 | P18: 753 | Q18: 1255 | R18: 1757 | S18: 1255 | T18: 1004 | U18: 502 | V18: 1255 | W18: 251 | X18: 251 | Y18: 1255 | Z18: 753 | AA18: 502 | AB18: 753 | AC18: 1255 | AD18: 502 | AE18: 251 | AF18: 502 | AG18: =SUM(B18:AF18) -> 32881
A19: Nextdoor | B19: 0 | C19: 0 | D19: 0 | E19: 0 | F19: 0 | G19: 0 | H19: 0 | I19: 0 | J19: 0 | K19: 0 | L19: 0 | M19: 0 | N19: 0 | O19: 0 | P19: 0 | Q19: 0 | R19: 0 | S19: 0 | T19: 0 | U19: 0 | V19: 0 | W19: 0 | X19: 0 | Y19: 0 | Z19: 0 | AA19: 0 | AB19: 0 | AC19: 0 | AD19: 0 | AE19: 0 | AF19: 0 | AG19: =SUM(B19:AF19) -> 0
A20: Affiliates (Refersion) | B20: 0 | C20: 0 | D20: 0 | E20: 0 | F20: 0 | G20: 0 | H20: 0 | I20: 0 | J20: 341 | K20: 0 | L20: 92 | M20: 0 | N20: 0 | O20: 0 | P20: 0 | Q20: 0 | R20: 0 | S20: 0 | T20: 394 | U20: 0 | V20: 0 | W20: 0 | X20: 0 | Y20: 0 | AG20: =SUM(B20:AF20) -> 827
A21: Email | B21: 276.11 | C21: 408 | D21: 365.4 | E21: 149.07 | F21: 427.95 | G21: 189.41 | H21: 53.05 | I21: 98 | J21: 161.95 | K21: 0 | L21: 0 | M21: 0 | N21: 0 | O21: 0 | P21: 374.7 | Q21: 50.81 | R21: 0 | S21: 0 | T21: 0 | U21: 0 | V21: 0 | W21: 0 | X21: 0 | Y21: 0 | Z21: 0 | AA21: 0 | AB21: 0 | AC21: 0 | AD21: 0 | AE21: 40.74 | AF21: 675.93 | AG21: =SUM(B21:AF21) -> 3271.12
A22: All | B22: =SUM(B15:B21) -> 25162.64 | C22: =SUM(C15:C21) -> 18007.85 | D22: =SUM(D15:D21) -> 20130.42 | E22: =SUM(E15:E21) -> 21960.07 | F22: =SUM(F15:F21) -> 20654.88 | G22: =SUM(G15:G21) -> 21446.85 | H22: =SUM(H15:H21) -> 23607.91 | I22: =SUM(I15:I21) -> 21853.47 | ... AF22: =SUM(AF15:AF21) -> 12921.307 | AG22: =SUM(B22:AF22) -> 524036.36
A24: Media Cost
A25: Meta | B25: =Summary!B73 -> 5875.9278 | C25: =Summary!C73 -> 5387.3265 | D25: =Summary!D73 -> 5162.9474 | E25: =Summary!E73 -> 5166.5229 | F25: =Summary!F73 -> 5194.2694 | G25: =Summary!G73 -> 5203.6798 | H25: =Summary!H73 -> 5447.9615 | I25: =Summary!I73 -> 5395.2728 | ... AF25: =Summary!AF73 -> 3277.2089 | AG25: =SUM(B25:AF25) -> 143999.52
A26: Google | B26: =Summary!B74 -> 2110.5 | C26: =Summary!C74 -> 2483.96 | D26: =Summary!D74 -> 2246.44 | E26: =Summary!E74 -> 2102.96 | F26: =Summary!F74 -> 1929.45 | G26: =Summary!G74 -> 1781.1 | H26: =Summary!H74 -> 1937.55 | I26: =Summary!I74 -> 1693.38 | ... AF26: =Summary!AF74 -> 1435.36 | AG26: =SUM(B26:AF26) -> 57065.75
A27: TikTok | B27: =Summary!B76 -> 0 | C27: =Summary!C76 -> 0 | D27: =Summary!D76 -> 0 | E27: =Summary!E76 -> 0 | F27: =Summary!F76 -> 0 | G27: =Summary!G76 -> 0 | H27: =Summary!H76 -> 0 | I27: =Summary!I76 -> 0 | ... AF27: =Summary!AF76 -> 0 | AG27: =SUM(B27:AF27) -> 0
A28: Bing | B28: =Summary!B75 -> 154.79 | C28: =Summary!C75 -> 206.25 | D28: =Summary!D75 -> 204.55 | E28: =Summary!E75 -> 163.92 | F28: =Summary!F75 -> 125.09 | G28: =Summary!G75 -> 91.32 | H28: =Summary!H75 -> 100.28 | I28: =Summary!I75 -> 119.37 | ... AF28: =Summary!AF75 -> 96.51 | AG28: =SUM(B28:AF28) -> 4584.27
A29: Nextdoor | B29: =Summary!B78 -> 0 | C29: =Summary!C78 -> 0 | D29: =Summary!D78 -> 0 | E29: =Summary!E78 -> 0 | F29: =Summary!F78 -> 0 | G29: =Summary!G78 -> 0 | H29: =Summary!H78 -> 0 | I29: =Summary!I78 -> 0 | ... AF29: =Summary!AF78 -> 0 | AG29: =SUM(B29:AF29) -> 0
A30: Affiliate Fee (20%) | B30: =Summary!B80 -> 0 | C30: =Summary!C80 -> 0 | D30: =Summary!D80 -> 0 | E30: =Summary!E80 -> 0 | F30: =Summary!F80 -> 0 | G30: =Summary!G80 -> 0 | H30: =Summary!H80 -> 0 | I30: =Summary!I80 -> 0 | ... AF30: =Summary!AF80 -> 0 | AG30: =SUM(B30:AF30) -> 169.97
A31: All | B31: =SUM(B25:B30) -> 8141.2178 | C31: =SUM(C25:C30) -> 8077.5365 | D31: =SUM(D25:D30) -> 7613.9374 | E31: =SUM(E25:E30) -> 7433.4029 | F31: =SUM(F25:F30) -> 7248.8094 | G31: =SUM(G25:G30) -> 7076.0998 | H31: =SUM(H25:H30) -> 7485.7915 | I31: =SUM(I25:I30) -> 7208.0228 | ... AF31: =SUM(AF25:AF30) -> 4809.0789 | AG31: =SUM(B31:AF31) -> 205819.51
A36: Revenue
A37: Revenue Woocommerce (Platform) | B37: =Summary!B8 -> 33166.99 | C37: =Summary!C8 -> 32204.7 | D37: =Summary!D8 -> 37759.59 | E37: =Summary!E8 -> 34093.84 | F37: =Summary!F8 -> 34903.7 | G37: =Summary!G8 -> 37601.7 | H37: =Summary!H8 -> 38315 | I37: =Summary!I8 -> 31136.13 | ... AF37: =Summary!AF8 -> 17850.13 | AG37: =sum(B37:AF37) -> 835052.26
A38: SUM | B38: =SUM(B37) -> 33166.99 | C38: =SUM(C37) -> 32204.7 | D38: =SUM(D37) -> 37759.59 | E38: =SUM(E37) -> 34093.84 | F38: =SUM(F37) -> 34903.7 | G38: =SUM(G37) -> 37601.7 | H38: =SUM(H37) -> 38315 | I38: =SUM(I37) -> 31136.13 | ... AF38: =SUM(AF37) -> 17850.13 | AG38: =sum(B38:AF38) -> 835052.26
A40: Orders
A41: Orders Woocommerce (Platform) | B41: =Summary!B49 -> 191 | C41: =Summary!C49 -> 158 | D41: =Summary!D49 -> 179 | E41: =Summary!E49 -> 156 | F41: =Summary!F49 -> 178 | G41: =Summary!G49 -> 187 | H41: =Summary!H49 -> 195 | I41: =Summary!I49 -> 144 | ... AF41: =Summary!AF49 -> 69 | AG41: =sum(B41:AF41) -> 3946
A42: SUM | B42: =SUM(B41) -> 191 | C42: =SUM(C41) -> 158 | D42: =SUM(D41) -> 179 | E42: =SUM(E41) -> 156 | F42: =SUM(F41) -> 178 | G42: =SUM(G41) -> 187 | H42: =SUM(H41) -> 195 | I42: =SUM(I41) -> 144 | ... AF42: =SUM(AF41) -> 69 | AG42: =sum(B42:AF42) -> 3946
A44: Breakdown
A45: - Hardware | B45: =Summary!B9 -> 20897.8 | C45: =Summary!C9 -> 21180.8 | D45: =Summary!D9 -> 27090.25 | E45: =Summary!E9 -> 24278.75 | F45: =Summary!F9 -> 23606.1 | G45: =Summary!G9 -> 25814.7 | H45: =Summary!H9 -> 24168.1 | I45: =Summary!I9 -> 21712.3 | ... AF45: =Summary!AF9 -> 13440.2 | AG45: =SUM(B45:AF45) -> 579343.85
A46: - Add-ons | B46: =Summary!B10 -> 8056.4 | C46: =Summary!C10 -> 7124.45 | D46: =Summary!D10 -> 6099.95 | E46: =Summary!E10 -> 5641.95 | F46: =Summary!F10 -> 6929.25 | G46: =Summary!G10 -> 7182.45 | H46: =Summary!H10 -> 9316.05 | I46: =Summary!I10 -> 5724.7 | ... AF46: =Summary!AF10 -> 2053.65 | AG46: =SUM(B46:AF46) -> 148180.29
A47: - Merch | B47: =Summary!B11 -> 58.14 | C47: =Summary!C11 -> 0 | D47: =Summary!D11 -> 76 | E47: =Summary!E11 -> 19 | F47: =Summary!F11 -> 44.99 | G47: =Summary!G11 -> 19 | H47: =Summary!H11 -> 130.15 | I47: =Summary!I11 -> 0 | ... AF47: =Summary!AF11 -> 0 | AG47: =SUM(B47:AF47) -> 541.74
A48: - Seeds | B48: =Summary!B12 -> 0 | C48: =Summary!C12 -> 0 | D48: =Summary!D12 -> 0 | E48: =Summary!E12 -> 0 | F48: =Summary!F12 -> 0 | G48: =Summary!G12 -> 0 | H48: =Summary!H12 -> 0 | I48: =Summary!I12 -> 0 | ... AF48: =Summary!AF12 -> 163.2 | AG48: =SUM(B48:AF48) -> 3107.62
A49: - Taxes | B49: =Summary!B13 -> 1684.65 | C49: =Summary!C13 -> 1759.45 | D49: =Summary!D13 -> 2003.39 | E49: =Summary!E13 -> 1819.14 | F49: =Summary!F13 -> 1928.36 | G49: =Summary!G13 -> 2080.55 | H49: =Summary!H13 -> 1985.7 | I49: =Summary!I13 -> 1559.13 | ... AF49: =Summary!AF13 -> 1017.08 | AG49: =SUM(B49:AF49) -> 44040.76
A50: - Shipping | B50: =Summary!B14 -> 2470 | C50: =Summary!C14 -> 2140 | D50: =Summary!D14 -> 2490 | E50: =Summary!E14 -> 2335 | F50: =Summary!F14 -> 2395 | G50: =Summary!G14 -> 2505 | H50: =Summary!H14 -> 2715 | I50: =Summary!I14 -> 2140 | ... AF50: =Summary!AF14 -> 1176 | AG50: =SUM(B50:AF50) -> 59838
A51: SUM | B51: =SUM(B45:B50) -> 33166.99 | C51: =SUM(C45:C50) -> 32204.7 | D51: =SUM(D45:D50) -> 37759.59 | E51: =SUM(E45:E50) -> 34093.84 | F51: =SUM(F45:F50) -> 34903.7 | G51: =SUM(G45:G50) -> 37601.7 | H51: =SUM(H45:H50) -> 38315 | I51: =SUM(I45:I50) -> 31136.13 | ... AF51: =SUM(AF45:AF50) -> 17850.13 | AG51: =SUM(B51:AF51) -> 835052.26
A53: Units Sold (Gross)
A54: SKU 1 - Blue | B54: 0 | C54: 0 | D54: 0 | E54: 0 | F54: 0 | G54: 0 | H54: 0 | I54: 0 | J54: 0 | K54: 0 | L54: 0 | M54: 0 | N54: 0 | O54: 0 | P54: 0 | Q54: 0 | R54: 0 | S54: 0 | T54: 0 | U54: 0 | V54: 0 | W54: 0 | X54: 0 | Y54: 7 | Z54: 9 | AA54: 8 | AB54: 8 | AC54: 10 | AD54: 13 | AE54: 7 | AF54: 10 | AG54: =sum(B54:AF54) -> 72
A55: SKU 2 - Yellow | B55: 17 | C55: 22 | D55: 35 | E55: 28 | F55: 29 | G55: 20 | H55: 15 | I55: 19 | J55: 12 | K55: 9 | L55: 12 | M55: 18 | N55: 10 | O55: 7 | P55: 13 | Q55: 13 | R55: 11 | S55: 7 | T55: 21 | U55: 17 | V55: 11 | W55: 11 | X55: 9 | Y55: 3 | Z55: 4 | AA55: 8 | AB55: 4 | AC55: 12 | AD55: 3 | AE55: 4 | AF55: 1 | AG55: =sum(B55:AF55) -> 405
A56: SKU 3 - Blue w/ Solar | B56: 0 | C56: 0 | D56: 0 | E56: 0 | F56: 0 | G56: 0 | H56: 0 | I56: 19 | J56: 35 | K56: 35 | L56: 44 | M56: 46 | N56: 42 | O56: 41 | P56: 44 | Q56: 37 | R56: 41 | S56: 37 | T56: 47 | U56: 73 | V56: 28 | W56: 37 | X56: 52 | Y56: 28 | Z56: 24 | AA56: 25 | AB56: 32 | AC56: 25 | AD56: 30 | AE56: 23 | AF56: 31 | AG56: =sum(B56:AF56) -> 876
A57: SKU 4 - Yellow w/ Solar | B57: 60 | C57: 57 | D57: 66 | E57: 62 | F57: 58 | G57: 73 | H57: 71 | I57: 41 | J57: 23 | K57: 19 | L57: 17 | M57: 24 | N57: 16 | O57: 16 | P57: 13 | Q57: 16 | R57: 31 | S57: 23 | T57: 4 | U57: 0 | V57: 0 | W57: 0 | X57: 0 | Y57: 11 | Z57: 11 | AA57: 11 | AB57: 8 | AC57: 12 | AD57: 11 | AE57: 10 | AF57: 7 | AG57: =sum(B57:AF57) -> 771
A58: SUM (SKU 1 - SKU 4) | B58: =SUM(B54:B57) -> 77 | C58: =SUM(C54:C57) -> 79 | D58: =SUM(D54:D57) -> 101 | E58: =SUM(E54:E57) -> 90 | F58: =SUM(F54:F57) -> 87 | G58: =SUM(G54:G57) -> 93 | H58: =SUM(H54:H57) -> 86 | I58: =SUM(I54:I57) -> 79 | ... AF58: =SUM(AF54:AF57) -> 49 | AG58: =sum(B58:AF58) -> 2124
A60: Wall Mount | B60: 59 | C60: 51 | D60: 46 | E60: 55 | F60: 43 | G60: 56 | H60: 58 | I60: 31 | J60: 26 | K60: 23 | L60: 27 | M60: 22 | N60: 35 | O60: 34 | P60: 31 | Q60: 20 | R60: 30 | S60: 20 | T60: 23 | U60: 36 | V60: 27 | W60: 23 | X60: 17 | Y60: 11 | Z60: 11 | AA60: 19 | AB60: 17 | AC60: 16 | AD60: 20 | AE60: 13 | AF60: 13 | AG60: =sum(B60:AF60) -> 913
A61: Suet Ball Holder | B61: 56 | C61: 47 | D61: 38 | E61: 35 | F61: 46 | G61: 42 | H61: 51 | I61: 29 | J61: 30 | K61: 31 | L61: 31 | M61: 26 | N61: 35 | O61: 30 | P61: 23 | Q61: 14 | R61: 23 | S61: 21 | T61: 16 | U61: 24 | V61: 26 | W61: 13 | X61: 18 | Y61: 17 | Z61: 23 | AA61: 27 | AB61: 22 | AC61: 19 | AD61: 25 | AE61: 12 | AF61: 10 | AG61: =sum(B61:AF61) -> 860
A62: 3-in-1 Nutrition Set - Blue | B62: 9 | C62: 7 | D62: 4 | E62: 8 | F62: 9 | G62: 6 | H62: 8 | I62: 7 | J62: 8 | K62: 2 | L62: 12 | M62: 5 | N62: 11 | O62: 8 | P62: 14 | Q62: 9 | R62: 9 | S62: 9 | T62: 5 | U62: 12 | V62: 19 | W62: 11 | X62: 11 | Y62: 10 | Z62: 8 | AA62: 10 | AB62: 14 | AC62: 7 | AD62: 11 | AE62: 2 | AF62: 5 | AG62: =sum(B62:AF62) -> 270
A63: 3-in-1 Nutrition Set - Yellow | B63: 27 | C63: 19 | D63: 22 | E63: 27 | F63: 23 | G63: 31 | H63: 34 | I63: 17 | J63: 15 | K63: 12 | L63: 11 | M63: 14 | N63: 17 | O63: 8 | P63: 8 | Q63: 7 | R63: 16 | S63: 11 | T63: 4 | U63: 6 | V63: 4 | W63: 1 | X63: 2 | Y63: 2 | Z63: 4 | AA63: 2 | AB63: 2 | AC63: 1 | AD63: 1 | AE63: 5 | AF63: 3 | AG63: =sum(B63:AF63) -> 356
A64: Solar Roof Single - Blue | B64: 11 | C64: 14 | D64: 7 | E64: 4 | F64: 6 | G64: 11 | H64: 11 | I64: 8 | J64: 4 | K64: 1 | L64: 9 | M64: 8 | N64: 13 | O64: 13 | P64: 6 | Q64: 7 | R64: 6 | S64: 6 | T64: 2 | U64: 7 | V64: 9 | W64: 6 | X64: 4 | Y64: 8 | Z64: 4 | AA64: 7 | AB64: 4 | AC64: 3 | AD64: 4 | AE64: 10 | AF64: 3 | AG64: =sum(B64:AF64) -> 216
A65: Solar Roof Single - Yellow | B65: 9 | C65: 9 | D65: 8 | E65: 6 | F65: 5 | G65: 3 | H65: 12 | I65: 9 | J65: 4 | K65: 6 | L65: 8 | M65: 3 | N65: 5 | O65: 2 | P65: 1 | Q65: 2 | R65: 5 | S65: 5 | T65: 6 | U65: 4 | V65: 5 | W65: 7 | X65: 2 | Y65: 1 | Z65: 5 | AA65: 3 | AB65: 4 | AC65: 7 | AD65: 3 | AE65: 1 | AF65: 1 | AG65: =sum(B65:AF65) -> 151
A66: Perch Extender - Blue | B66: 37 | C66: 31 | D66: 22 | E66: 21 | F66: 42 | G66: 39 | H66: 49 | I66: 33 | J66: 31 | K66: 22 | L66: 27 | M66: 33 | N66: 35 | O66: 44 | P66: 34 | Q66: 30 | R66: 23 | S66: 29 | T66: 42 | U66: 48 | V66: 53 | W66: 39 | X66: 36 | Y66: 20 | Z66: 30 | AA66: 29 | AB66: 35 | AC66: 29 | AD66: 24 | AE66: 24 | AF66: 23 | AG66: =sum(B66:AF66) -> 1014
A67: Perch Extender - Yellow | B67: 54 | C67: 42 | D67: 38 | E67: 38 | F67: 45 | G67: 49 | H67: 67 | I67: 28 | J67: 25 | K67: 22 | L67: 25 | M67: 27 | N67: 36 | O67: 21 | P67: 18 | Q67: 20 | R67: 28 | S67: 22 | T67: 16 | U67: 14 | V67: 15 | W67: 11 | X67: 9 | Y67: 12 | Z67: 19 | AA67: 14 | AB67: 15 | AC67: 19 | AD67: 12 | AE67: 5 | AF67: 10 | AG67: =sum(B67:AF67) -> 776
A68: SUM (Add-ons) | B68: =SUM(B60:B67) -> 262 | C68: =SUM(C60:C67) -> 220 | D68: =SUM(D60:D67) -> 185 | E68: =SUM(E60:E67) -> 194 | F68: =SUM(F60:F67) -> 219 | G68: =SUM(G60:G67) -> 237 | H68: =SUM(H60:H67) -> 290 | I68: =SUM(I60:I67) -> 162 | ... AF68: =SUM(AF60:AF67) -> 68 | AG68: =sum(B68:AF68) -> 4556
A70: Seasonal Curation - 8lb | P70: 0 | Q70: 3 | R70: 2 | S70: 2 | T70: 0 | U70: 1 | V70: 2 | W70: 0 | X70: 0 | Y70: 0 | Z70: 0 | AA70: 1 | AB70: 2 | AC70: 2 | AD70: 1 | AE70: 0 | AF70: 1 | AG70: =sum(B70:AF70) -> 17
A71: Seasonal Curation - 20lb | P71: 1 | Q71: 0 | R71: 2 | S71: 2 | T71: 1 | U71: 0 | V71: 1 | W71: 2 | X71: 0 | Y71: 0 | Z71: 0 | AA71: 2 | AB71: 1 | AC71: 2 | AD71: 1 | AE71: 0 | AF71: 0 | AG71: =sum(B71:AF71) -> 15
A72: Buddy Bites - 8lb | P72: 0 | Q72: 0 | R72: 1 | S72: 6 | T72: 6 | U72: 6 | V72: 7 | W72: 3 | X72: 2 | Y72: 2 | Z72: 2 | AA72: 2 | AB72: 4 | AC72: 3 | AD72: 4 | AE72: 4 | AF72: 1 | AG72: =sum(B72:AF72) -> 53
A73: Buddy Bites - 20lb | P73: 0 | Q73: 0 | R73: 1 | S73: 0 | T73: 1 | U73: 1 | V73: 0 | W73: 1 | X73: 0 | Y73: 0 | Z73: 1 | AA73: 0 | AB73: 1 | AC73: 0 | AD73: 1 | AE73: 0 | AF73: 2 | AG73: =sum(B73:AF73) -> 9
A74: Snack n' Soar - 8lb | P74: 0 | Q74: 0 | R74: 0 | S74: 1 | T74: 1 | U74: 0 | V74: 0 | W74: 1 | X74: 1 | Y74: 1 | Z74: 0 | AA74: 1 | AB74: 0 | AC74: 2 | AD74: 1 | AE74: 0 | AF74: 0 | AG74: =sum(B74:AF74) -> 9
A75: Snack n' Soar - 20lb | P75: 0 | Q75: 0 | R75: 0 | S75: 0 | T75: 1 | U75: 1 | V75: 1 | W75: 0 | X75: 0 | Y75: 0 | Z75: 1 | AA75: 0 | AB75: 0 | AC75: 0 | AD75: 1 | AE75: 0 | AF75: 1 | AG75: =sum(B75:AF75) -> 6
A76: Avian Choice - 8lb | P76: 0 | Q76: 0 | R76: 0 | S76: 3 | T76: 3 | U76: 2 | V76: 1 | W76: 3 | X76: 1 | Y76: 0 | Z76: 0 | AA76: 0 | AB76: 0 | AC76: 1 | AD76: 0 | AE76: 0 | AF76: 1 | AG76: =sum(B76:AF76) -> 15
A77: Avian Choice - 20lb | P77: 0 | Q77: 1 | R77: 0 | S77: 0 | T77: 0 | U77: 1 | V77: 2 | W77: 1 | X77: 0 | Y77: 0 | Z77: 0 | AA77: 1 | AB77: 0 | AC77: 1 | AD77: 2 | AE77: 0 | AF77: 0 | AG77: =sum(B77:AF77) -> 9
A78: SUM (Seeds) | B78: =SUM(B70:B77) -> 0 | C78: =SUM(C70:C77) -> 0 | D78: =SUM(D70:D77) -> 0 | E78: =SUM(E70:E77) -> 0 | F78: =SUM(F70:F77) -> 0 | G78: =SUM(G70:G77) -> 0 | H78: =SUM(H70:H77) -> 0 | I78: =SUM(I70:I77) -> 0 | ... AF78: =SUM(AF70:AF77) -> 6 | AG78: =SUM(B78:AF78) -> 133
A80: Merch Units Sold (Gross)
A81: Merch Units | B81: 3 | C81: 0 | D81: 4 | E81: 1 | F81: 1 | G81: 1 | H81: 7 | I81: 0 | J81: 2 | K81: 1 | L81: 1 | M81: 0 | N81: 0 | O81: 0 | P81: 1 | Q81: 0 | R81: 0 | S81: 0 | T81: 0 | U81: 0 | V81: 1 | W81: 0 | X81: 0 | Y81: 0 | Z81: 0 | AA81: 0 | AB81: 0 | AC81: 0 | AD81: 0 | AE81: 0 | AF81: 0 | AG81: =sum(B81:AF81) -> 23
A83: First-time Customers
A84: SKU 1 - Blue | B84: =B54-B101 -> 0 | C84: =C54-C101 -> 0 | D84: =D54-D101 -> 0 | E84: =E54-E101 -> 0 | F84: =F54-F101 -> 0 | G84: =G54-G101 -> 0 | H84: =H54-H101 -> 0 | I84: =I54-I101 -> 0 | ... AF84: =AF54-AF101 -> 9 | AG84: =sum(B84:AF84) -> 68
A85: SKU 2 - Yellow | B85: =B55-B102 -> 14 | C85: =C55-C102 -> 20 | D85: =D55-D102 -> 33 | E85: =E55-E102 -> 27 | F85: =F55-F102 -> 27 | G85: =G55-G102 -> 16 | H85: =H55-H102 -> 14 | I85: =I55-I102 -> 16 | ... AF85: =AF55-AF102 -> 1 | AG85: =sum(B85:AF85) -> 371
A86: SKU 3 - Blue w/ Solar | B86: =B56-B103 -> 0 | C86: =C56-C103 -> 0 | D86: =D56-D103 -> 0 | E86: =E56-E103 -> 0 | F86: =F56-F103 -> 0 | G86: =G56-G103 -> 0 | H86: =H56-H103 -> 0 | I86: =I56-I103 -> 18 | ... AF86: =AF56-AF103 -> 30 | AG86: =sum(B86:AF86) -> 811
A87: SKU 4 - Yellow w/ Solar | B87: =B57-B104 -> 55 | C87: =C57-C104 -> 50 | D87: =D57-D104 -> 61 | E87: =E57-E104 -> 59 | F87: =F57-F104 -> 54 | G87: =G57-G104 -> 64 | H87: =H57-H104 -> 64 | I87: =I57-I104 -> 37 | ... AF87: =AF57-AF104 -> 7 | AG87: =sum(B87:AF87) -> 698
A88: SUM (SKU 1 - SKU 4) | B88: =SUM(B84:B87) -> 69 | C88: =SUM(C84:C87) -> 70 | D88: =SUM(D84:D87) -> 94 | E88: =SUM(E84:E87) -> 86 | F88: =SUM(F84:F87) -> 81 | G88: =SUM(G84:G87) -> 80 | H88: =SUM(H84:H87) -> 78 | I88: =SUM(I84:I87) -> 71 | ... AF88: =SUM(AF84:AF87) -> 47 | AG88: =sum(B88:AF88) -> 1948
A90: Wall Mount | B90: =B60-B107 -> 52 | C90: =C60-C107 -> 44 | D90: =D60-D107 -> 42 | E90: =E60-E107 -> 46 | F90: =F60-F107 -> 40 | G90: =G60-G107 -> 45 | H90: =H60-H107 -> 47 | I90: =I60-I107 -> 29 | ... AF90: =AF60-AF107 -> 11 | AG90: =sum(B90:AF90) -> 792
A91: Suet Ball Holder | B91: =B61-B108 -> 50 | C91: =C61-C108 -> 32 | D91: =D61-D108 -> 32 | E91: =E61-E108 -> 29 | F91: =F61-F108 -> 39 | G91: =G61-G108 -> 33 | H91: =H61-H108 -> 47 | I91: =I61-I108 -> 24 | ... AF91: =AF61-AF108 -> 9 | AG91: =sum(B91:AF91) -> 673
A92: 3-in-1 Nutrition Set - Blue | B92: =B62-B109 -> 9 | C92: =C62-C109 -> 5 | D92: =D62-D109 -> 3 | E92: =E62-E109 -> 6 | F92: =F62-F109 -> 9 | G92: =G62-G109 -> 3 | H92: =H62-H109 -> 8 | I92: =I62-I109 -> 6 | ... AF92: =AF62-AF109 -> 5 | AG92: =sum(B92:AF92) -> 221
A93: 3-in-1 Nutrition Set - Yellow | B93: =B63-B110 -> 23 | C93: =C63-C110 -> 16 | D93: =D63-D110 -> 18 | E93: =E63-E110 -> 25 | F93: =F63-F110 -> 22 | G93: =G63-G110 -> 25 | H93: =H63-H110 -> 30 | I93: =I63-I110 -> 14 | ... AF93: =AF63-AF110 -> 2 | AG93: =sum(B93:AF93) -> 306
A94: Solar Roof Single - Blue | B94: =B64-B111 -> 9 | C94: =C64-C111 -> 12 | D94: =D64-D111 -> 7 | E94: =E64-E111 -> 4 | F94: =F64-F111 -> 4 | G94: =G64-G111 -> 10 | H94: =H64-H111 -> 11 | I94: =I64-I111 -> 4 | ... AF94: =AF64-AF111 -> 3 | AG94: =sum(B94:AF94) -> 177
A95: Solar Roof Single - Yellow | B95: =B65-B112 -> 8 | C95: =C65-C112 -> 7 | D95: =D65-D112 -> 7 | E95: =E65-E112 -> 5 | F95: =F65-F112 -> 4 | G95: =G65-G112 -> 2 | H95: =H65-H112 -> 9 | I95: =I65-I112 -> 4 | ... AF95: =AF65-AF112 -> 1 | AG95: =sum(B95:AF95) -> 118
A96: Perch Extender - Blue | B96: =B66-B113 -> 32 | C96: =C66-C113 -> 27 | D96: =D66-D113 -> 22 | E96: =E66-E113 -> 21 | F96: =F66-F113 -> 30 | G96: =G66-G113 -> 27 | H96: =H66-H113 -> 42 | I96: =I66-I113 -> 28 | ... AF96: =AF66-AF113 -> 22 | AG96: =sum(B96:AF96) -> 842
A97: Perch Extender - Yellow | B97: =B67-B114 -> 43 | C97: =C67-C114 -> 33 | D97: =D67-D114 -> 30 | E97: =E67-E114 -> 32 | F97: =F67-F114 -> 40 | G97: =G67-G114 -> 37 | H97: =H67-H114 -> 57 | I97: =I67-I114 -> 21 | ... AF97: =AF67-AF114 -> 8 | AG97: =sum(B97:AF97) -> 628
A98: SUM (Add-ons) | B98: =SUM(B90:B97) -> 226 | C98: =SUM(C90:C97) -> 176 | D98: =SUM(D90:D97) -> 161 | E98: =SUM(E90:E97) -> 168 | F98: =SUM(F90:F97) -> 188 | G98: =SUM(G90:G97) -> 182 | H98: =SUM(H90:H97) -> 251 | I98: =SUM(I90:I97) -> 130 | ... AF98: =SUM(AF90:AF97) -> 61 | AG98: =sum(B98:AF98) -> 3757
A100: Returning Customers
A101: SKU 1 - Blue | B101: 0 | C101: 0 | D101: 0 | E101: 0 | F101: 0 | G101: 0 | H101: 0 | I101: 0 | J101: 0 | K101: 0 | L101: 0 | M101: 0 | N101: 0 | O101: 0 | P101: 0 | Q101: 0 | R101: 0 | S101: 0 | T101: 0 | U101: 0 | V101: 0 | W101: 0 | X101: 0 | Y101: 0 | Z101: 1 | AA101: 1 | AB101: 0 | AC101: 1 | AD101: 0 | AE101: 0 | AF101: 1 | AG101: =sum(B101:AF101) -> 4
A102: SKU 2 - Yellow | B102: 3 | C102: 2 | D102: 2 | E102: 1 | F102: 2 | G102: 4 | H102: 1 | I102: 3 | J102: 0 | K102: 1 | L102: 2 | M102: 0 | N102: 1 | O102: 0 | P102: 0 | Q102: 1 | R102: 0 | S102: 0 | T102: 0 | U102: 5 | V102: 3 | W102: 2 | X102: 0 | Y102: 0 | Z102: 0 | AA102: 0 | AB102: 0 | AC102: 1 | AD102: 0 | AE102: 0 | AF102: 0 | AG102: =sum(B102:AF102) -> 34
A103: SKU 3 - Blue w/ Solar | B103: 0 | C103: 0 | D103: 0 | E103: 0 | F103: 0 | G103: 0 | H103: 0 | I103: 1 | J103: 3 | K103: 4 | L103: 1 | M103: 2 | N103: 5 | O103: 3 | P103: 2 | Q103: 1 | R103: 2 | S103: 2 | T103: 6 | U103: 6 | V103: 1 | W103: 4 | X103: 5 | Y103: 1 | Z103: 2 | AA103: 3 | AB103: 5 | AC103: 2 | AD103: 1 | AE103: 2 | AF103: 1 | AG103: =sum(B103:AF103) -> 65
A104: SKU 4 - Yellow w/ Solar | B104: 5 | C104: 7 | D104: 5 | E104: 3 | F104: 4 | G104: 9 | H104: 7 | I104: 4 | J104: 1 | K104: 0 | L104: 1 | M104: 4 | N104: 5 | O104: 1 | P104: 2 | Q104: 3 | R104: 3 | S104: 3 | T104: 1 | U104: 0 | V104: 0 | W104: 0 | X104: 0 | Y104: 1 | Z104: 0 | AA104: 1 | AB104: 1 | AC104: 0 | AD104: 0 | AE104: 2 | AF104: 0 | AG104: =sum(B104:AF104) -> 73
A105: SUM (SKU 1 - SKU 4) | B105: =SUM(B101:B104) -> 8 | C105: =SUM(C101:C104) -> 9 | D105: =SUM(D101:D104) -> 7 | E105: =SUM(E101:E104) -> 4 | F105: =SUM(F101:F104) -> 6 | G105: =SUM(G101:G104) -> 13 | H105: =SUM(H101:H104) -> 8 | I105: =SUM(I101:I104) -> 8 | ... AF105: =SUM(AF101:AF104) -> 2 | AG105: =sum(B105:AF105) -> 176
A107: Wall Mount | B107: 7 | C107: 7 | D107: 4 | E107: 9 | F107: 3 | G107: 11 | H107: 11 | I107: 2 | J107: 0 | K107: 0 | L107: 2 | M107: 3 | N107: 9 | O107: 2 | P107: 5 | Q107: 2 | R107: 5 | S107: 2 | T107: 4 | U107: 5 | V107: 3 | W107: 6 | X107: 2 | Y107: 0 | Z107: 1 | AA107: 3 | AB107: 5 | AC107: 2 | AD107: 2 | AE107: 2 | AF107: 2 | AG107: =sum(B107:AF107) -> 121
A108: Suet Ball Holder | B108: 6 | C108: 15 | D108: 6 | E108: 6 | F108: 7 | G108: 9 | H108: 4 | I108: 5 | J108: 4 | K108: 10 | L108: 8 | M108: 7 | N108: 7 | O108: 8 | P108: 6 | Q108: 3 | R108: 4 | S108: 3 | T108: 7 | U108: 4 | V108: 6 | W108: 3 | X108: 3 | Y108: 5 | Z108: 4 | AA108: 8 | AB108: 9 | AC108: 4 | AD108: 11 | AE108: 4 | AF108: 1 | AG108: =sum(B108:AF108) -> 187
A109: 3-in-1 Nutrition Set - Blue | B109: 0 | C109: 2 | D109: 1 | E109: 2 | F109: 0 | G109: 3 | H109: 0 | I109: 1 | J109: 1 | K109: 0 | L109: 3 | M109: 1 | N109: 2 | O109: 4 | P109: 3 | Q109: 2 | R109: 2 | S109: 0 | T109: 2 | U109: 0 | V109: 2 | W109: 2 | X109: 1 | Y109: 2 | Z109: 1 | AA109: 3 | AB109: 6 | AC109: 1 | AD109: 2 | AE109: 0 | AF109: 0 | AG109: =sum(B109:AF109) -> 49
A110: 3-in-1 Nutrition Set - Yellow | B110: 4 | C110: 3 | D110: 4 | E110: 2 | F110: 1 | G110: 6 | H110: 4 | I110: 3 | J110: 0 | K110: 0 | L110: 1 | M110: 2 | N110: 4 | O110: 0 | P110: 2 | Q110: 3 | R110: 2 | S110: 1 | T110: 3 | U110: 1 | V110: 2 | W110: 0 | X110: 0 | Y110: 0 | Z110: 0 | AA110: 0 | AB110: 0 | AC110: 0 | AD110: 0 | AE110: 1 | AF110: 1 | AG110: =sum(B110:AF110) -> 50
A111: Solar Roof Single - Blue | B111: 2 | C111: 2 | D111: 0 | E111: 0 | F111: 2 | G111: 1 | H111: 0 | I111: 4 | J111: 2 | K111: 0 | L111: 0 | M111: 0 | N111: 1 | O111: 1 | P111: 3 | Q111: 3 | R111: 3 | S111: 0 | T111: 0 | U111: 2 | V111: 4 | W111: 2 | X111: 0 | Y111: 1 | Z111: 0 | AA111: 1 | AB111: 1 | AC111: 0 | AD111: 3 | AE111: 1 | AF111: 0 | AG111: =sum(B111:AF111) -> 39
A112: Solar Roof Single - Yellow | B112: 1 | C112: 2 | D112: 1 | E112: 1 | F112: 1 | G112: 1 | H112: 3 | I112: 5 | J112: 0 | K112: 2 | L112: 6 | M112: 0 | N112: 1 | O112: 0 | P112: 0 | Q112: 0 | R112: 0 | S112: 2 | T112: 1 | U112: 1 | V112: 0 | W112: 1 | X112: 0 | Y112: 1 | Z112: 0 | AA112: 0 | AB112: 0 | AC112: 2 | AD112: 1 | AE112: 0 | AF112: 0 | AG112: =sum(B112:AF112) -> 33
A113: Perch Extender - Blue | B113: 5 | C113: 4 | D113: 0 | E113: 0 | F113: 12 | G113: 12 | H113: 7 | I113: 5 | J113: 1 | K113: 3 | L113: 3 | M113: 7 | N113: 6 | O113: 9 | P113: 8 | Q113: 4 | R113: 3 | S113: 11 | T113: 6 | U113: 4 | V113: 6 | W113: 7 | X113: 10 | Y113: 2 | Z113: 4 | AA113: 7 | AB113: 7 | AC113: 4 | AD113: 6 | AE113: 8 | AF113: 1 | AG113: =sum(B113:AF113) -> 172
A114: Perch Extender - Yellow | B114: 11 | C114: 9 | D114: 8 | E114: 6 | F114: 5 | G114: 12 | H114: 10 | I114: 7 | J114: 0 | K114: 3 | L114: 7 | M114: 6 | N114: 8 | O114: 3 | P114: 3 | Q114: 6 | R114: 5 | S114: 1 | T114: 4 | U114: 5 | V114: 6 | W114: 4 | X114: 1 | Y114: 3 | Z114: 0 | AA114: 2 | AB114: 3 | AC114: 1 | AD114: 7 | AE114: 0 | AF114: 2 | AG114: =sum(B114:AF114) -> 148
A115: SUM (Add-ons) | B115: =SUM(B107:B114) -> 36 | C115: =SUM(C107:C114) -> 44 | D115: =SUM(D107:D114) -> 24 | E115: =SUM(E107:E114) -> 26 | F115: =SUM(F107:F114) -> 31 | G115: =SUM(G107:G114) -> 55 | H115: =SUM(H107:H114) -> 39 | I115: =SUM(I107:I114) -> 32 | ... AF115: =SUM(AF107:AF114) -> 7 | AG115: =sum(B115:AF115) -> 799
A117: Seasonal Curation - 8lb | B117: 0 | C117: 0 | D117: 0 | E117: 0 | F117: 0 | G117: 0 | H117: 0 | I117: 0 | J117: 0 | K117: 0 | L117: 0 | M117: 0 | N117: 0 | O117: 0 | P117: 0 | Q117: 1 | R117: 0 | S117: 2 | T117: 0 | U117: 1 | V117: 2 | W117: 0 | X117: 0 | Y117: 0 | Z117: 0 | AA117: 1 | AB117: 2 | AC117: 1 | AD117: 1 | AE117: 0 | AF117: 1 | AG117: =sum(B117:AF117) -> 12
...

Sheet App - P&L
A1: JANUARY | B1: 45292 | C1: 45293 | D1: 45294 | E1: 45295 | F1: 45296 | G1: 45297 | H1: 45298 | I1: 45299 | J1: 45300 | K1: 45301 | L1: 45302 | M1: 45303 | N1: 45304 | O1: 45305 | P1: 45306 | Q1: 45307 | R1: 45308 | S1: 45309 | T1: 45310 | U1: 45311 | V1: 45312 | W1: 45313 | X1: 45314 | Y1: 45315 | Z1: 45316 | AA1: 45317 | AB1: 45318 | AC1: 45319 | AD1: 45320 | AE1: 45321 | AF1: 45322
A2: DAY | B2: MON | C2: TUE | D2: WED | E2: THU | F2: FRI | G2: SAT | H2: SUN | I2: MON | J2: TUE | K2: WED | L2: THU | M2: FRI | N2: SAT | O2: SUN | P2: MON | Q2: TUE | R2: WED | S2: THU | T2: FRI | U2: SAT | V2: SUN | W2: MON | X2: TUE | Y2: WED | Z2: THU | AA2: FRI | AB2: SAT | AC2: SUN | AD2: MON | AE2: TUE | AF2: WED
A4: Gross Revenue
A5: Apple Store Sales | B5: 14169.892 | C5: 8386.9311 | D5: 6507.5304 | E5: 6326.8167 | F5: 7443.6982 | G5: 9494.4958 | H5: 8678.9918 | I5: 5904.7652 | J5: 4328.5 | K5: 3684.6094 | L5: 2691.1817 | M5: 3367.4772 | N5: 4641.6699 | O5: 5328.9441 | P5: 2693.87 | Q5: 1989.34 | R5: 1725.83 | S5: 2615.57 | T5: 1771.29 | U5: 4311.62 | V5: 4567.71 | W5: 3387.45 | X5: 1868.3 | Y5: 2416.36 | Z5: 2542.11 | AA5: 2283.37 | AB5: 4605.16 | AC5: 4916.1 | AD5: 2194.36 | AE5: 1762.36 | AF5: 1424.43 | AG5: =sum(B5:AF5) -> 138030.73
A6: - Yearly Subscription | B6: 13858.129 | C6: 8199.0915 | D6: 6218.966 | E6: 6121.0701 | F6: 7276.3415 | G6: 9295.2082 | H6: 8403.99 | I6: 5748.1706 | J6: 4143.8726 | K6: 3551.5034 | L6: 2531.6597 | M6: 3220.2332 | N6: 4490.2469 | O6: 5069.804 | P6: 2543.6309 | Q6: 1823.9705 | R6: 1564.27 | S6: 2511.82 | T6: 1628.07 | U6: 4191.4 | V6: 4385.96 | W6: 3212.51 | X6: 1709.61 | Y6: 2225.24 | Z6: 1991 | AA6: 1807.7395 | AB6: 4243.5984 | AC6: 4454.6102 | AD6: 1862.42 | AE6: 1442.4716 | AF6: =365.758815+779.25 -> 1145.0088 | AG6: =sum(B6:AF6) -> 130871.62
A7: - Monthly Subscription | B7: 311.76337 | C7: 187.83951 | D7: 288.56445 | E7: 205.74661 | F7: 167.35666 | G7: 199.28761 | H7: 275.00184 | I7: 156.59459 | J7: 184.63079 | K7: 133.10604 | L7: 159.52208 | M7: 147.24396 | N7: 151.42296 | O7: 259.14 | P7: 150.24 | Q7: 165.3678 | R7: 161.56 | S7: 103.75261 | T7: 143.22 | U7: 120.22 | V7: 181.75459 | W7: 174.94 | X7: 158.68726 | Y7: 191.12034 | Z7: 551.11 | AA7: 475.63121 | AB7: 361.55858 | AC7: 461.48525 | AD7: 331.94 | AE7: 319.88579 | AF7: 279.42461 | AG7: =sum(B7:AF7) -> 7159.1185
A8: Google Store Sales | B8: 3272.61 | C8: 1739.68 | D8: 1214.51 | E8: 1099.5 | F8: 1374.17 | G8: 1566.03 | H8: 1726.07 | I8: 1581.78 | J8: 652.72 | K8: 763.68 | L8: 853.43 | M8: 346.97 | N8: 745.82 | O8: 1131.99 | P8: 641.58 | Q8: 239.88 | R8: 409.43 | S8: 488.17 | T8: 448.32 | U8: 852.95 | V8: 721.04 | W8: 727.48 | X8: 485.25 | Y8: 520.18 | Z8: 227.34 | AA8: 589.11 | AB8: 781.83 | AC8: 598.87 | AD8: 295.96 | AE8: 479.07 | AF8: 214.24 | AG8: =sum(B8:AF8) -> 26789.66
A9: - Yearly Subscription | B9: 3231.08 | C9: 1682.68 | D9: 1178.79 | E9: 1050.29 | F9: 1336.04 | G9: 1525.22 | H9: 47.24 | I9: 1538.38 | J9: 587.23 | K9: 725.92 | L9: 824.84 | M9: 326.96 | N9: 726.3 | O9: 1097.3 | P9: 608.63 | Q9: 220.73 | R9: 400 | S9: 433.79 | T9: 407.04 | U9: 782.62 | V9: 685.83 | W9: 696.15 | X9: 454.24 | Y9: 501.36 | Z9: 124.58 | AA9: 539.44 | AB9: 696.48 | AC9: 503.25 | AD9: 219.75 | AE9: 416.18 | AF9: 189.41 | AG9: =sum(B9:AF9) -> 23757.75
A10: - Monthly Subscription | B10: 41.53 | C10: 57 | D10: 35.72 | E10: 49.21 | F10: 38.13 | G10: 40.81 | H10: 1678.83 | I10: 43.4 | J10: 65.49 | K10: 37.76 | L10: 28.59 | M10: 20.01 | N10: 19.52 | O10: 34.69 | P10: 32.95 | Q10: 19.15 | R10: 9.43 | S10: 54.38 | T10: 41.28 | U10: 70.33 | V10: 35.21 | W10: 31.33 | X10: 31.01 | Y10: 18.82 | Z10: 102.76 | AA10: 49.67 | AB10: 85.35 | AC10: 95.62 | AD10: 75.51 | AE10: 62.89 | AF10: 24.83 | AG10: =sum(B10:AF10) -> 3031.21
A11: SUM | B11: =sum(B5+B8) -> 17442.502 | C11: =sum(C5+C8) -> 10126.611 | D11: =sum(D5+D8) -> 7722.0404 | E11: =sum(E5+E8) -> 7426.3167 | F11: =sum(F5+F8) -> 8817.8682 | G11: =sum(G5+G8) -> 11060.526 | H11: =sum(H5+H8) -> 10405.062 | I11: =sum(I5+I8) -> 7486.5452 | ... AF11: =sum(AF5+AF8) -> 1638.67 | AG11: =sum(B11:AF11) -> 164820.39
A13: Gross Orders
A14: Apple Store Orders | B14: =sum(B15:B16) -> 417 | C14: =sum(C15:C16) -> 243 | D14: =sum(D15:D16) -> 211 | E14: =sum(E15:E16) -> 186 | F14: =sum(F15:F16) -> 210 | G14: =sum(G15:G16) -> 267 | H14: =sum(H15:H16) -> 261 | I14: =sum(I15:I16) -> 163 | ... AF14: =sum(AF15:AF16) -> 77 | AG14: =sum(B14:AF14) -> 4541
A15: - Yearly Subscription | B15: 356 | C15: 203 | D15: 149 | E15: 143 | F15: 170 | G15: 223 | H15: 204 | I15: 127 | J15: 90 | K15: 77 | L15: 57 | M15: 64 | N15: 96 | O15: 106 | P15: 56 | Q15: 41 | R15: 34 | S15: 56 | T15: 41 | U15: 97 | V15: 105 | W15: 76 | X15: 40 | Y15: 52 | Z15: 44 | AA15: 44 | AB15: 101 | AC15: 103 | AD15: 46 | AE15: 36 | AF15: 28 | AG15: =sum(B15:AF15) -> 3065
A16: - Monthly Subscription | B16: 61 | C16: 40 | D16: 62 | E16: 43 | F16: 40 | G16: 44 | H16: 57 | I16: 36 | J16: 43 | K16: 33 | L16: 34 | M16: 34 | N16: 33 | O16: 54 | P16: 33 | Q16: 41 | R16: 37 | S16: 25 | T16: 31 | U16: 26 | V16: 38 | W16: 35 | X16: 32 | Y16: 40 | Z16: 103 | AA16: 92 | AB16: 68 | AC16: 85 | AD16: 64 | AE16: 63 | AF16: 49 | AG16: =sum(B16:AF16) -> 1476
A17: Google Store Orders | B17: =sum(B18:B19) -> 80 | C17: =sum(C18:C19) -> 51 | D17: =sum(D18:D19) -> 36 | E17: =sum(E18:E19) -> 34 | F17: =sum(F18:F19) -> 35 | G17: =sum(G18:G19) -> 41 | H17: =sum(H18:H19) -> 49 | I17: =sum(I18:I19) -> 34 | ... AF17: =sum(AF18:AF19) -> 7 | AG17: =sum(B17:AF17) -> 838
A18: - Yearly Subscription | B18: 73 | C18: 40 | D18: 27 | E18: 23 | F18: 27 | G18: 32 | H18: 39 | I18: 25 | J18: 13 | K18: 16 | L18: 15 | M18: 8 | N18: 14 | O18: 22 | P18: 13 | Q18: 6 | R18: 8 | S18: 8 | T18: 9 | U18: 19 | V18: 19 | W18: 14 | X18: 9 | Y18: 11 | Z18: 3 | AA18: 13 | AB18: 16 | AC18: 10 | AD18: 4 | AE18: 9 | AF18: 3 | AG18: =sum(B18:AF18) -> 548
A19: - Monthly Subscription | B19: 7 | C19: 11 | D19: 9 | E19: 11 | F19: 8 | G19: 9 | H19: 10 | I19: 9 | J19: 13 | K19: 9 | L19: 5 | M19: 5 | N19: 5 | O19: 7 | P19: 9 | Q19: 4 | R19: 3 | S19: 12 | T19: 10 | U19: 15 | V19: 8 | W19: 7 | X19: 7 | Y19: 4 | Z19: 18 | AA19: 11 | AB19: 15 | AC19: 18 | AD19: 15 | AE19: 12 | AF19: 4 | AG19: =sum(B19:AF19) -> 290
A20: SUM | B20: =sum(B14+B17) -> 497 | C20: =sum(C14+C17) -> 294 | D20: =sum(D14+D17) -> 247 | E20: =sum(E14+E17) -> 220 | F20: =sum(F14+F17) -> 245 | G20: =sum(G14+G17) -> 308 | H20: =sum(H14+H17) -> 310 | I20: =sum(I14+I17) -> 197 | ... AF20: =sum(AF14+AF17) -> 84 | AG20: =sum(B20:AF20) -> 5379
A21: - Yearly Subscription | B21: =B15+B18 -> 429 | C21: =C15+C18 -> 243 | D21: =D15+D18 -> 176 | E21: =E15+E18 -> 166 | F21: =F15+F18 -> 197 | G21: =G15+G18 -> 255 | H21: =H15+H18 -> 243 | I21: =I15+I18 -> 152 | ... AF21: =AF15+AF18 -> 31 | AG21: =sum(B21:AF21) -> 3613
A22: - Monthly Subscription | B22: =B16+B19 -> 68 | C22: =C16+C19 -> 51 | D22: =D16+D19 -> 71 | E22: =E16+E19 -> 54 | F22: =F16+F19 -> 48 | G22: =G16+G19 -> 53 | H22: =H16+H19 -> 67 | I22: =I16+I19 -> 45 | ... AF22: =AF16+AF19 -> 53 | AG22: =sum(B22:AF22) -> 1766
A24: Refunded Revenue
A25: Apple Store Sales | B25: =sum(B26:B27) -> 59.73 | C25: =sum(C26:C27) -> 59.99 | D25: =sum(D26:D27) -> 209.9 | E25: =sum(E26:E27) -> 59.98 | F25: =sum(F26:F27) -> 89.98 | G25: =sum(G26:G27) -> 100.64 | H25: =sum(H26:H27) -> 109.65 | I25: =sum(I26:I27) -> 0 | ... AF25: =sum(AF26:AF27) -> 0 | AG25: =sum(B25:AF25) -> 1854.489
A26: - Yearly Subscription | B26: 59.73 | C26: 59.99 | D26: 209.9 | E26: 59.98 | F26: 89.98 | G26: 89.24 | H26: 100.96 | I26: 0 | J26: 149.96 | K26: 89.97 | L26: 59.98 | M26: 29.53 | N26: 59.98 | O26: 118.01 | P26: 89.32 | Q26: 184.089 | R26: 29.99 | S26: 59.99 | T26: 0 | U26: 0 | V26: 29.99 | W26: 0 | X26: 29.99 | Y26: 0 | Z26: 0 | AA26: 119.98 | AB26: 57.49 | AC26: 10.08 | AD26: 0 | AE26: 0 | AF26: 0 | AG26: =sum(B26:AF26) -> 1788.129
A27: - Monthly Subscription | B27: 0 | C27: 0 | D27: 0 | E27: 0 | F27: 0 | G27: 11.4 | H27: 8.69 | I27: 0 | J27: 3.28 | K27: 0 | L27: 0 | M27: 5.99 | N27: 4.64 | O27: 2.99 | P27: 0 | Q27: 5.99 | R27: 0 | S27: 1.55 | T27: 4.64 | U27: 0.97 | V27: 0 | W27: 0 | X27: 5.99 | Y27: 0 | Z27: 0 | AA27: 0 | AB27: 0.96 | AC27: 0 | AD27: 5.99 | AE27: 3.28 | AF27: 0 | AG27: =sum(B27:AF27) -> 66.36
A28: Google Store Sales | B28: =sum(B29:B30) -> 0 | C28: =sum(C29:C30) -> 0 | D28: =sum(D29:D30) -> 0 | E28: =sum(E29:E30) -> 29.99 | F28: =sum(F29:F30) -> 0 | G28: =sum(G29:G30) -> 0 | H28: =sum(H29:H30) -> 0 | I28: =sum(I29:I30) -> 0 | ... AF28: =sum(AF29:AF30) -> 0 | AG28: =sum(B28:AF28) -> 173
A29: - Yearly Subscription | B29: 0 | C29: 0 | D29: 0 | E29: 29.99 | F29: 0 | G29: 0 | H29: 0 | I29: 0 | J29: 0 | K29: 0 | L29: 0 | M29: 42.7 | N29: 0 | O29: 35.52 | P29: 0 | Q29: 64.79 | R29: 0 | S29: 0 | T29: 0 | U29: 0 | V29: 0 | W29: 0 | X29: 0 | Y29: 0 | Z29: 0 | AA29: 0 | AB29: 0 | AC29: 0 | AD29: 0 | AE29: 0 | AF29: 0 | AG29: =sum(B29:AF29) -> 173
A30: - Monthly Subscription | B30: 0 | C30: 0 | D30: 0 | E30: 0 | F30: 0 | G30: 0 | H30: 0 | I30: 0 | J30: 0 | K30: 0 | L30: 0 | M30: 0 | N30: 0 | O30: 0 | P30: 0 | Q30: 0 | R30: 0 | S30: 0 | T30: 0 | U30: 0 | V30: 0 | W30: 0 | X30: 0 | Y30: 0 | Z30: 0 | AA30: 0 | AB30: 0 | AC30: 0 | AD30: 0 | AE30: 0 | AF30: 0 | AG30: =sum(B30:AF30) -> 0
A31: SUM | B31: =B25+B28 -> 59.73 | C31: =C25+C28 -> 59.99 | D31: =D25+D28 -> 209.9 | E31: =E25+E28 -> 89.97 | F31: =F25+F28 -> 89.98 | G31: =G25+G28 -> 100.64 | H31: =H25+H28 -> 109.65 | I31: =I25+I28 -> 0 | ... AF31: =AF25+AF28 -> 0 | AG31: =sum(B31:AF31) -> 2027.489
A33: Refunded Orders
A34: Apple Store orders | B34: =sum(B35:B36) -> 1 | C34: =sum(C35:C36) -> 1 | D34: =sum(D35:D36) -> 5 | E34: =sum(E35:E36) -> 2 | F34: =sum(F35:F36) -> 2 | G34: =sum(G35:G36) -> 2 | H34: =sum(H35:H36) -> 2 | I34: =sum(I35:I36) -> 0 | ... AF34: =sum(AF35:AF36) -> 0 | AG34: =sum(B34:AF34) -> 44
A35: - Yearly Subscription | B35: 1 | C35: 1 | D35: 5 | E35: 2 | F35: 2 | G35: 1 | H35: 1 | I35: 0 | J35: 4 | K35: 3 | L35: 1 | M35: 0 | N35: 2 | O35: 1 | P35: 1 | Q35: 2 | R35: 1 | S35: 1 | T35: 0 | U35: 0 | V35: 1 | W35: 0 | X35: 1 | Y35: 0 | Z35: 0 | AA35: 2 | AB35: 1 | AC35: 0 | AD35: 0 | AE35: 0 | AF35: 0
A36: - Monthly Subscription | B36: 0 | C36: 0 | D36: 0 | E36: 0 | F36: 0 | G36: 1 | H36: 1 | I36: 0 | J36: 1 | K36: 0 | L36: 0 | M36: 1 | N36: 1 | O36: 1 | P36: 0 | Q36: 1 | R36: 0 | S36: 0 | T36: 0 | U36: 0 | V36: 0 | W36: 0 | X36: 1 | Y36: 0 | Z36: 0 | AA36: 0 | AB36: 0 | AC36: 0 | AD36: 1 | AE36: 1 | AF36: 0
A37: Google Store orders | B37: =sum(B38:B39) -> 0 | C37: =sum(C38:C39) -> 0 | D37: =sum(D38:D39) -> 0 | E37: =sum(E38:E39) -> 1 | F37: =sum(F38:F39) -> 0 | G37: =sum(G38:G39) -> 0 | H37: =sum(H38:H39) -> 0 | I37: =sum(I38:I39) -> 0 | ... AF37: =sum(AF38:AF39) -> 0 | AG37: =sum(B37:AF37) -> 4
A38: - Yearly Subscription | B38: 0 | C38: 0 | D38: 0 | E38: 1 | F38: 0 | G38: 0 | H38: 0 | I38: 0 | J38: 0 | K38: 0 | L38: 0 | M38: 1 | N38: 0 | O38: 1 | P38: 0 | Q38: 1 | R38: 0 | S38: 0 | T38: 0 | U38: 0 | V38: 0 | W38: 0 | X38: 0 | Y38: 0 | Z38: 0 | AA38: 0 | AB38: 0 | AC38: 0 | AD38: 0 | AE38: 0 | AF38: 0
A39: - Monthly Subscription | B39: 0 | C39: 0 | D39: 0 | E39: 0 | F39: 0 | G39: 0 | H39: 0 | I39: 0 | J39: 0 | K39: 0 | L39: 0 | M39: 0 | N39: 0 | O39: 0 | P39: 0 | Q39: 0 | R39: 0 | S39: 0 | T39: 0 | U39: 0 | V39: 0 | W39: 0 | X39: 0 | Y39: 0 | Z39: 0 | AA39: 0 | AB39: 0 | AC39: 0 | AD39: 0 | AE39: 0 | AF39: 0
A40: SUM | B40: =B34+B37 -> 1 | C40: =C34+C37 -> 1 | D40: =D34+D37 -> 5 | E40: =E34+E37 -> 3 | F40: =F34+F37 -> 2 | G40: =G34+G37 -> 2 | H40: =H34+H37 -> 2 | I40: =I34+I37 -> 0 | ... AF40: =AF34+AF37 -> 0 | AG40: =sum(B40:AF40) -> 48
A42: Net Revenue
A43: Apple Store | B43: =B5-B25 -> 14110.162 | C43: =C5-C25 -> 8326.9411 | D43: =D5-D25 -> 6297.6304 | E43: =E5-E25 -> 6266.8367 | F43: =F5-F25 -> 7353.7182 | G43: =G5-G25 -> 9393.8558 | H43: =H5-H25 -> 8569.3418 | I43: =I5-I25 -> 5904.7652 | ... AF43: =AF5-AF25 -> 1424.43 | AG43: =sum(B43:AF43) -> 136176.24
A44: - Yearly Subscription | B44: =B6-B26 -> 13798.399 | C44: =C6-C26 -> 8139.1015 | D44: =D6-D26 -> 6009.066 | E44: =E6-E26 -> 6061.0901 | F44: =F6-F26 -> 7186.3615 | G44: =G6-G26 -> 9205.9682 | H44: =H6-H26 -> 8303.03 | I44: =I6-I26 -> 5748.1706 | ... AF44: =AF6-AF26 -> 1145.0088 | AG44: =sum(B44:AF44) -> 129083.49
A45: - Monthly Subscription | B45: =B7-B27 -> 311.76337 | C45: =C7-C27 -> 187.83951 | D45: =D7-D27 -> 288.56445 | E45: =E7-E27 -> 205.74661 | F45: =F7-F27 -> 167.35666 | G45: =G7-G27 -> 187.88761 | H45: =H7-H27 -> 266.31184 | I45: =I7-I27 -> 156.59459 | ... AF45: =AF7-AF27 -> 279.42461 | AG45: =sum(B45:AF45) -> 7092.7585
A46: Google Store | B46: =B8-B28 -> 3272.61 | C46: =C8-C28 -> 1739.68 | D46: =D8-D28 -> 1214.51 | E46: =E8-E28 -> 1069.51 | F46: =F8-F28 -> 1374.17 | G46: =G8-G28 -> 1566.03 | H46: =H8-H28 -> 1726.07 | I46: =I8-I28 -> 1581.78 | ... AF46: =AF8-AF28 -> 214.24 | AG46: =sum(B46:AF46) -> 26616.66
A47: - Yearly Subscription | B47: =B9-B29 -> 3231.08 | C47: =C9-C29 -> 1682.68 | D47: =D9-D29 -> 1178.79 | E47: =E9-E29 -> 1020.3 | F47: =F9-F29 -> 1336.04 | G47: =G9-G29 -> 1525.22 | H47: =H9-H29 -> 47.24 | I47: =I9-I29 -> 1538.38 | ... AF47: =AF9-AF29 -> 189.41 | AG47: =sum(B47:AF47) -> 23584.75
A48: - Monthly Subscription | B48: =B10-B30 -> 41.53 | C48: =C10-C30 -> 57 | D48: =D10-D30 -> 35.72 | E48: =E10-E30 -> 49.21 | F48: =F10-F30 -> 38.13 | G48: =G10-G30 -> 40.81 | H48: =H10-H30 -> 1678.83 | I48: =I10-I30 -> 43.4 | ... AF48: =AF10-AF30 -> 24.83 | AG48: =sum(B48:AF48) -> 3031.21
A49: SUM | B49: =B43+B46 -> 17382.772 | C49: =C43+C46 -> 10066.621 | D49: =D43+D46 -> 7512.1404 | E49: =E43+E46 -> 7336.3467 | F49: =F43+F46 -> 8727.8882 | G49: =G43+G46 -> 10959.886 | H49: =H43+H46 -> 10295.412 | I49: =I43+I46 -> 7486.5452 | ... AF49: =AF43+AF46 -> 1638.67 | AG49: =sum(B49:AF49) -> 162792.9
A51: Net Orders
A52: Apple Store | B52: =B14-B34 -> 416 | C52: =C14-C34 -> 242 | D52: =D14-D34 -> 206 | E52: =E14-E34 -> 184 | F52: =F14-F34 -> 208 | G52: =G14-G34 -> 265 | H52: =H14-H34 -> 259 | I52: =I14-I34 -> 163 | ... AF52: =AF14-AF34 -> 77 | AG52: =sum(B52:AF52) -> 4497
A53: - Yearly Subscription | B53: =B15-B35 -> 355 | C53: =C15-C35 -> 202 | D53: =D15-D35 -> 144 | E53: =E15-E35 -> 141 | F53: =F15-F35 -> 168 | G53: =G15-G35 -> 222 | H53: =H15-H35 -> 203 | I53: =I15-I35 -> 127 | ... AF53: =AF15-AF35 -> 28 | AG53: =sum(B53:AF53) -> 3031
A54: - Monthly Subscription | B54: =B16-B36 -> 61 | C54: =C16-C36 -> 40 | D54: =D16-D36 -> 62 | E54: =E16-E36 -> 43 | F54: =F16-F36 -> 40 | G54: =G16-G36 -> 43 | H54: =H16-H36 -> 56 | I54: =I16-I36 -> 36 | ... AF54: =AF16-AF36 -> 49 | AG54: =sum(B54:AF54) -> 1466
A55: Google Store | B55: =B17-B37 -> 80 | C55: =C17-C37 -> 51 | D55: =D17-D37 -> 36 | E55: =E17-E37 -> 33 | F55: =F17-F37 -> 35 | G55: =G17-G37 -> 41 | H55: =H17-H37 -> 49 | I55: =I17-I37 -> 34 | ... AF55: =AF17-AF37 -> 7 | AG55: =sum(B55:AF55) -> 834
A56: - Yearly Subscription | B56: =B18-B38 -> 73 | C56: =C18-C38 -> 40 | D56: =D18-D38 -> 27 | E56: =E18-E38 -> 22 | F56: =F18-F38 -> 27 | G56: =G18-G38 -> 32 | H56: =H18-H38 -> 39 | I56: =I18-I38 -> 25 | ... AF56: =AF18-AF38 -> 3 | AG56: =sum(B56:AF56) -> 544
A57: - Monthly Subscription | B57: =B19-B39 -> 7 | C57: =C19-C39 -> 11 | D57: =D19-D39 -> 9 | E57: =E19-E39 -> 11 | F57: =F19-F39 -> 8 | G57: =G19-G39 -> 9 | H57: =H19-H39 -> 10 | I57: =I19-I39 -> 9 | ... AF57: =AF19-AF39 -> 4 | AG57: =sum(B57:AF57) -> 290
A58: SUM | B58: =B52+B55 -> 496 | C58: =C52+C55 -> 293 | D58: =D52+D55 -> 242 | E58: =E52+E55 -> 217 | F58: =F52+F55 -> 243 | G58: =G52+G55 -> 306 | H58: =H52+H55 -> 308 | I58: =I52+I55 -> 197 | ... AF58: =AF52+AF55 -> 84 | AG58: =sum(B58:AF58) -> 5331
A62: Commision Fees & Taxes
A63: Estimated Apple Store Commision Fee (30%) --> check again after 1. mil. | B63: =B5*0.3 -> 4250.9677 | C63: =C5*0.3 -> 2516.0793 | D63: =D5*0.3 -> 1952.2591 | E63: =E5*0.3 -> 1898.045 | F63: =F5*0.3 -> 2233.1094 | G63: =G5*0.3 -> 2848.3488 | H63: =H5*0.3 -> 2603.6976 | I63: =I5*0.3 -> 1771.4295 | ... AF63: =AF5*0.3 -> 427.329 | AG63: =SUM(B63:AF63) -> 41409.22
A64: Estimated Apple Store Taxes | B64: 42.48 | C64: 48.33 | D64: 35.78 | E64: 23.04 | F64: 24.1 | G64: 27.5 | H64: 45.86 | I64: 24.71 | J64: 24.45 | K64: 9.53 | L64: 8.67 | M64: 30.89 | N64: 26.94 | O64: 28.67 | P64: 15.09 | Q64: 25.93 | R64: 9.3 | S64: 14.91 | T64: 11.16 | U64: 37.89 | V64: 19.75 | W64: 24.07 | X64: 0 | Y64: 9.62 | Z64: 18.21 | AA64: 13.06 | AB64: 26.09 | AC64: 32.77 | AD64: 7.23 | AE64: 5.58 | AF64: 11.04 | AG64: =SUM(B64:AF64) -> 682.65
A65: Estimated Google Store Commision Fee (15%) --> check again after 1. mil. | B65: =B8*0.15 -> 490.8915 | C65: =C8*0.15 -> 260.952 | D65: =D8*0.15 -> 182.1765 | E65: =E8*0.15 -> 164.925 | F65: =F8*0.15 -> 206.1255 | G65: =G8*0.15 -> 234.9045 | H65: =H8*0.15 -> 258.9105 | I65: =I8*0.15 -> 237.267 | ... AF65: =AF8*0.15 -> 32.136 | AG65: =SUM(B65:AF65) -> 4018.449
A66: Estimated Google Store Taxes | B66: 16.32 | C66: 2.42 | D66: 1.62 | E66: 11.71 | F66: 7 | G66: 27.61 | H66: 28.23 | I66: 27.02 | J66: 29.35 | K66: 7.45 | L66: 6.09 | M66: 1.33 | N66: 17.94 | O66: 0 | P66: 25.77 | Q66: 0.57 | R66: 6.18 | S66: 1.94 | T66: 1.22 | U66: 6.15 | V66: 0.52 | W66: 0 | X66: 31.45 | Y66: 16.38 | Z66: 1.09 | AA66: 0.53 | AB66: 5.66 | AC66: 12.81 | AD66: 2.16 | AE66: 0 | AF66: 11.73 | AG66: =SUM(B66:AF66) -> 308.25
A67: Estimated SUM Store Commision Fees | B67: =B63+B65 -> 4741.8592 | C67: =C63+C65 -> 2777.0313 | D67: =D63+D65 -> 2134.4356 | E67: =E63+E65 -> 2062.97 | F67: =F63+F65 -> 2439.2349 | G67: =G63+G65 -> 3083.2533 | H67: =H63+H65 -> 2862.6081 | I67: =I63+I65 -> 2008.6965 | ... AF67: =AF63+AF65 -> 459.465 | AG67: =SUM(B67:AF67) -> 45427.669
A68: Estimated SUM Store Taxes | B68: =B64+B66 -> 58.8 | C68: =C64+C66 -> 50.75 | D68: =D64+D66 -> 37.4 | E68: =E64+E66 -> 34.75 | F68: =F64+F66 -> 31.1 | G68: =G64+G66 -> 55.11 | H68: =H64+H66 -> 74.09 | I68: =I64+I66 -> 51.73 | ... AF68: =AF64+AF66 -> 22.77 | AG68: =SUM(B68:AF68) -> 990.9
A70: Advertising
A71: Meta Spend | B71: =Summary!B87 -> 0 | C71: =Summary!C87 -> 0 | D71: =Summary!D87 -> 0 | E71: =Summary!E87 -> 0 | F71: =Summary!F87 -> 0 | G71: =Summary!G87 -> 0 | H71: =Summary!H87 -> 0 | I71: =Summary!I87 -> 0 | ... AF71: =Summary!AF87 -> 295.32161
A72: Apple Spend | B72: =Summary!B88 -> 100.26 | C72: =Summary!C88 -> 99.48 | D72: =Summary!D88 -> 98.52 | E72: =Summary!E88 -> 95.87 | F72: =Summary!F88 -> 98.06 | G72: =Summary!G88 -> 98.72 | H72: =Summary!H88 -> 99.07 | I72: =Summary!I88 -> 84.79 | ... AF72: =Summary!AF88 -> 54.55
A73: Google Spend | B73: =Summary!B89 -> 0 | C73: =Summary!C89 -> 0 | D73: =Summary!D89 -> 0 | E73: =Summary!E89 -> 0 | F73: =Summary!F89 -> 0 | G73: =Summary!G89 -> 0 | H73: =Summary!H89 -> 0 | I73: =Summary!I89 -> 0 | ... AF73: =Summary!AF89 -> 0
A74: SUM | B74: =SUM(B71:B73) -> 100.26 | C74: =SUM(C71:C73) -> 99.48 | D74: =SUM(D71:D73) -> 98.52 | E74: =SUM(E71:E73) -> 95.87 | F74: =SUM(F71:F73) -> 98.06 | G74: =SUM(G71:G73) -> 98.72 | H74: =SUM(H71:H73) -> 99.07 | I74: =SUM(I71:I73) -> 84.79 | ... AF74: =SUM(AF71:AF73) -> 349.87161
A76: Estimated Subscription Profit
A77: - Estimated Apple Store profit | B77: =B43-B63-B64-B72-(B71*'Data - P&L'!$I$24) -> 9716.4546 | C77: =C43-C63-C64-C72-(C71*'Data - P&L'!$I$24) -> 5663.0517 | D77: =D43-D63-D64-D72-(D71*'Data - P&L'!$I$24) -> 4211.0713 | E77: =E43-E63-E64-E72-(E71*'Data - P&L'!$I$24) -> 4249.8817 | F77: =F43-F63-F64-F72-(F71*'Data - P&L'!$I$24) -> 4998.4487 | G77: =G43-G63-G64-G72-(G71*'Data - P&L'!$I$24) -> 6419.2871 | H77: =H43-H63-H64-H72-(H71*'Data - P&L'!$I$24) -> 5820.7143 | I77: =I43-I63-I64-I72-(I71*'Data - P&L'!$I$24) -> 4023.8356 | ... AF77: =AF43-AF63-AF64-AF72-(AF71*'Data - P&L'!$I$24) -> 695.25371 | AG77: =sum(B77:AF77) -> 92063.555
A78: - Estimated Google Store profit | B78: =B46-B65-B66-B73-(B71*'Data - P&L'!$I$25) -> 2765.3985 | C78: =C46-C65-C66-C73-(C71*'Data - P&L'!$I$25) -> 1476.308 | D78: =D46-D65-D66-D73-(D71*'Data - P&L'!$I$25) -> 1030.7135 | E78: =E46-E65-E66-E73-(E71*'Data - P&L'!$I$25) -> 892.875 | F78: =F46-F65-F66-F73-(F71*'Data - P&L'!$I$25) -> 1161.0445 | G78: =G46-G65-G66-G73-(G71*'Data - P&L'!$I$25) -> 1303.5155 | H78: =H46-H65-H66-H73-(H71*'Data - P&L'!$I$25) -> 1438.9295 | I78: =I46-I65-I66-I73-(I71*'Data - P&L'!$I$25) -> 1317.493 | ... AF78: =AF46-AF65-AF66-AF73-(AF71*'Data - P&L'!$I$25) -> 111.30968 | AG78: =sum(B78:AF78) -> 22205.053
A79: Estimated SUM Profit | B79: =sum(B77:B78) -> 12481.853 | C79: =sum(C77:C78) -> 7139.3597 | D79: =sum(D77:D78) -> 5241.7848 | E79: =sum(E77:E78) -> 5142.7567 | F79: =sum(F77:F78) -> 6159.4932 | G79: =sum(G77:G78) -> 7722.8026 | H79: =sum(H77:H78) -> 7259.6438 | I79: =sum(I77:I78) -> 5341.3286 | ... AF79: =sum(AF77:AF78) -> 806.56339 | AG79: =sum(B79:AF79) -> 114268.61
A82: Gross Revenue
A83: =SUM(B11:AF11) -> 164820.39
A84: Gross Sales Profit
A85: =SUM(B79:AF79) -> 114268.61
A86: Gross Sales Margin
A87: =A85/A83 -> 0.69329168
A89: For summary
A90: Google | B90: =B8-B65-B66 -> 2765.3985 | C90: =C8-C65-C66 -> 1476.308 | D90: =D8-D65-D66 -> 1030.7135 | E90: =E8-E65-E66 -> 922.865 | F90: =F8-F65-F66 -> 1161.0445 | G90: =G8-G65-G66 -> 1303.5155 | H90: =H8-H65-H66 -> 1438.9295 | I90: =I8-I65-I66 -> 1317.493 | ... AF90: =AF8-AF65-AF66 -> 170.374
A91: Apple | B91: =B5-B63-B64 -> 9876.4446 | C91: =C5-C63-C64 -> 5822.5217 | D91: =D5-D63-D64 -> 4519.4913 | E91: =E5-E63-E64 -> 4405.7317 | F91: =F5-F63-F64 -> 5186.4887 | G91: =G5-G63-G64 -> 6618.6471 | H91: =H5-H63-H64 -> 6029.4343 | I91: =I5-I63-I64 -> 4108.6256 | ... AF91: =AF5-AF63-AF64 -> 986.061

Sheet AMAZON - P&L
A1: JANUARY | B1: 45292 | C1: 45293 | D1: 45294 | E1: 45295 | F1: 45296 | G1: 45297 | H1: 45298 | I1: 45299 | J1: 45300 | K1: 45301 | L1: 45302 | M1: 45303 | N1: 45304 | O1: 45305 | P1: 45306 | Q1: 45307 | R1: 45308 | S1: 45309 | T1: 45310 | U1: 45311 | V1: 45312 | W1: 45313 | X1: 45314 | Y1: 45315 | Z1: 45316 | AA1: 45317 | AB1: 45318 | AC1: 45319 | AD1: 45320 | AE1: 45321 | AF1: 45322
A2: DAY | B2: MON | C2: TUE | D2: WED | E2: THU | F2: FRI | G2: SAT | H2: SUN | I2: MON | J2: TUE | K2: WED | L2: THU | M2: FRI | N2: SAT | O2: SUN | P2: MON | Q2: TUE | R2: WED | S2: THU | T2: FRI | U2: SAT | V2: SUN | W2: MON | X2: TUE | Y2: WED | Z2: THU | AA2: FRI | AB2: SAT | AC2: SUN | AD2: MON | AE2: TUE | AF2: WED
A3: COMMENT
A4: Orders
A5: Amazon (market place) | B5: =Summary!B54 -> 14 | C5: =Summary!C54 -> 30 | D5: =Summary!D54 -> 34 | E5: =Summary!E54 -> 15 | F5: =Summary!F54 -> 23 | G5: =Summary!G54 -> 18 | H5: =Summary!H54 -> 22 | I5: =Summary!I54 -> 40 | ... AF5: =Summary!AF54 -> 64
A6: All | B6: =SUM(B5) -> 14 | C6: =SUM(C5) -> 30 | D6: =SUM(D5) -> 34 | E6: =SUM(E5) -> 15 | F6: =SUM(F5) -> 23 | G6: =SUM(G5) -> 18 | H6: =SUM(H5) -> 22 | I6: =SUM(I5) -> 40 | ... AF6: =SUM(AF5) -> 64 | AG6: =SUM(B6:AF6) -> 1073
A8: Revenue
A9: Amazon (market place) | B9: =Summary!B15 -> 8259.3 | C9: =Summary!C15 -> 8509.69 | D9: =Summary!D15 -> 9959.99 | E9: =Summary!E15 -> 7222.59 | F9: =Summary!F15 -> 7395.73 | G9: =Summary!G15 -> 6262.25 | H9: =Summary!H15 -> 5480.06 | I9: =Summary!I15 -> 8883.31 | ... AF9: =Summary!AF15 -> 14667.91
A10: All | B10: =SUM(B9) -> 8259.3 | C10: =SUM(C9) -> 8509.69 | D10: =SUM(D9) -> 9959.99 | E10: =SUM(E9) -> 7222.59 | F10: =SUM(F9) -> 7395.73 | G10: =SUM(G9) -> 6262.25 | H10: =SUM(H9) -> 5480.06 | I10: =SUM(I9) -> 8883.31 | ... AF10: =SUM(AF9) -> 14667.91 | AG10: =SUM(B10:AF10) -> 283546.35
A12: Media Cost
A13: Amazon Spend | B13: =Summary!B77 -> 2390.92 | C13: =Summary!C77 -> 2568.83 | D13: =Summary!D77 -> 1913.96 | E13: =Summary!E77 -> 1152.11 | F13: =Summary!F77 -> 1392.03 | G13: =Summary!G77 -> 0 | H13: =Summary!H77 -> 0 | I13: =Summary!I77 -> 341.24 | ... AF13: =Summary!AF77 -> 1754.27 | AG13: =SUM(B13:AF13) -> 37402.23
A14: Amazon Platform Fee (15 %) | B14: =B9*'Data - P&L'!$C$48 -> 1238.895 | C14: =C9*'Data - P&L'!$C$48 -> 1276.4535 | D14: =D9*'Data - P&L'!$C$48 -> 1493.9985 | E14: =E9*'Data - P&L'!$C$48 -> 1083.3885 | F14: =F9*'Data - P&L'!$C$48 -> 1109.3595 | G14: =G9*'Data - P&L'!$C$48 -> 939.3375 | H14: =H9*'Data - P&L'!$C$48 -> 822.009 | I14: =I9*'Data - P&L'!$C$48 -> 1332.4965 | ... AF14: =AF9*'Data - P&L'!$C$48 -> 2200.1865
A15: All | B15: =SUM(B13:B14) -> 3629.815 | C15: =SUM(C13:C14) -> 3845.2835 | D15: =SUM(D13:D14) -> 3407.9585 | E15: =SUM(E13:E14) -> 2235.4985 | F15: =SUM(F13:F14) -> 2501.3895 | G15: =SUM(G13:G14) -> 939.3375 | H15: =SUM(H13:H14) -> 822.009 | I15: =SUM(I13:I14) -> 1673.7365 | ... AF15: =SUM(AF13:AF14) -> 3954.4565 | AG15: =SUM(B15:AF15) -> 79934.182
A19: Amazon Orders
A20: Hardware | B20: =Summary!B16 -> 7579.26 | C20: =Summary!C16 -> 7878.36 | D20: =Summary!D16 -> 9382.76 | E20: =Summary!E16 -> 6797.99 | F20: =Summary!F16 -> 6870.37 | G20: =Summary!G16 -> 5854.37 | H20: =Summary!H16 -> 5096.37 | I20: =Summary!I16 -> 8203.4 | ... AF20: =Summary!AF16 -> 13530.04 | AG20: =SUM(B20:AF20) -> 260157.86
A21: Addons | B21: =Summary!B17 -> 166.38 | C21: =Summary!C17 -> 87 | D21: =Summary!D17 -> 0 | E21: =Summary!E17 -> 0 | F21: =Summary!F17 -> 0 | G21: =Summary!G17 -> 0 | H21: =Summary!H17 -> 58 | I21: =Summary!I17 -> 116 | ... AF21: =Summary!AF17 -> 203 | AG21: =SUM(B21:AF21) -> 4855.28
A22: Tax | B22: =Summary!B18 -> 503.88 | C22: =Summary!C18 -> 523.33 | D22: =Summary!D18 -> 567.45 | E22: =Summary!E18 -> 424.6 | F22: =Summary!F18 -> 520.47 | G22: =Summary!G18 -> 398.03 | H22: =Summary!H18 -> 325.29 | I22: =Summary!I18 -> 562.31 | ... AF22: =Summary!AF18 -> 917.39 | AG22: =SUM(B22:AF22) -> 18142.31
A23: Shipping | B23: =Summary!B19 -> 0.5 | C23: =Summary!C19 -> 11.87 | D23: =Summary!D19 -> 0.5 | E23: =Summary!E19 -> 0 | F23: =Summary!F19 -> 0.25 | G23: =Summary!G19 -> 5.21 | H23: =Summary!H19 -> 0.25 | I23: =Summary!I19 -> 1 | ... AF23: =Summary!AF19 -> 8.35 | AG23: =SUM(B23:AF23) -> 186.79
A24: Gift Wrap Price | B24: =Summary!B20 -> 9.28 | C24: =Summary!C20 -> 9.13 | D24: =Summary!D20 -> 9.28 | E24: =Summary!E20 -> 0 | F24: =Summary!F20 -> 4.64 | G24: =Summary!G20 -> 4.64 | H24: =Summary!H20 -> 0.15 | I24: =Summary!I20 -> 0.6 | ... AF24: =Summary!AF20 -> 9.13 | AG24: =SUM(B24:AF24) -> 204.11
A25: All Amazon | B25: =SUM(B20:B24) -> 8259.3 | C25: =SUM(C20:C24) -> 8509.69 | D25: =SUM(D20:D24) -> 9959.99 | E25: =SUM(E20:E24) -> 7222.59 | F25: =SUM(F20:F24) -> 7395.73 | G25: =SUM(G20:G24) -> 6262.25 | H25: =SUM(H20:H24) -> 5480.06 | I25: =SUM(I20:I24) -> 8883.31 | ... AF25: =SUM(AF20:AF24) -> 14667.91 | AG25: =SUM(B25:AF25) -> 283546.35
A27: Units Sold (Gross)
A28: SKU 1 - Blue | B28: 1 | C28: 6 | D28: 8 | E28: 5 | F28: 2 | G28: 1 | H28: 2 | I28: 4 | J28: 7 | K28: 6 | L28: 7 | M28: 15 | N28: 11 | O28: 7 | P28: 9 | Q28: 9 | R28: 8 | S28: 12 | T28: 9 | U28: 18 | V28: 15 | W28: 10 | X28: 11 | Y28: 4 | Z28: 5 | AA28: 1 | AB28: 0 | AC28: 5 | AD28: 1 | AE28: 1 | AF28: 3 | AG28: =sum(B28:AF28) -> 203
A29: SKU 2 - Yellow | B29: 1 | C29: 1 | D29: 1 | E29: 1 | F29: 2 | G29: 0 | H29: 0 | I29: 0 | J29: 1 | K29: 1 | L29: 3 | M29: 4 | N29: 5 | O29: 3 | P29: 3 | Q29: 3 | R29: 4 | S29: 3 | T29: 2 | U29: 7 | V29: 3 | W29: 3 | X29: 2 | Y29: 0 | Z29: 1 | AA29: 0 | AB29: 1 | AC29: 3 | AD29: 0 | AE29: 1 | AF29: 2 | AG29: =sum(B29:AF29) -> 61
A30: SKU 3 - Blue w/ Solar | B30: 16 | C30: 7 | D30: 2 | E30: 3 | F30: 4 | G30: 5 | H30: 3 | I30: 13 | J30: 14 | K30: 12 | L30: 13 | M30: 7 | N30: 8 | O30: 4 | P30: 10 | Q30: 6 | R30: 7 | S30: 10 | T30: 15 | U30: 1 | V30: 5 | W30: 7 | X30: 3 | Y30: 24 | Z30: 16 | AA30: 23 | AB30: 22 | AC30: 31 | AD30: 43 | AE30: 27 | AF30: 34 | AG30: =sum(B30:AF30) -> 395
A31: SKU 4 - Yellow w/ Solar | B31: 7 | C31: 12 | D31: 21 | E31: 14 | F31: 15 | G31: 13 | H31: 12 | I31: 11 | J31: 3 | K31: 1 | L31: 0 | M31: 0 | N31: 0 | O31: 5 | P31: 0 | Q31: 0 | R31: 0 | S31: 0 | T31: 0 | U31: 15 | V31: 25 | W31: 26 | X31: 14 | Y31: 8 | Z31: 2 | AA31: 9 | AB31: 8 | AC31: 9 | AD31: 8 | AE31: 5 | AF31: 7 | AG31: =sum(B31:AF31) -> 250
A32: SUM (SKU 1 - SKU 4) | B32: =SUM(B28:B31) -> 25 | C32: =SUM(C28:C31) -> 26 | D32: =SUM(D28:D31) -> 32 | E32: =SUM(E28:E31) -> 23 | F32: =SUM(F28:F31) -> 23 | G32: =SUM(G28:G31) -> 19 | H32: =SUM(H28:H31) -> 17 | I32: =SUM(I28:I31) -> 28 | ... AF32: =SUM(AF28:AF31) -> 46 | AG32: =sum(B32:AF32) -> 909
A34: Wall Mount | B34: 8 | C34: 3 | D34: 0 | E34: 0 | F34: 0 | G34: 0 | H34: 2 | I34: 4 | J34: 4 | K34: 0 | L34: 1 | M34: 6 | N34: 0 | O34: 1 | P34: 1 | Q34: 0 | R34: 3 | S34: 3 | T34: 0 | U34: 6 | V34: 10 | W34: 7 | X34: 8 | Y34: 9 | Z34: 8 | AA34: 9 | AB34: 15 | AC34: 26 | AD34: 14 | AE34: 16 | AF34: 9 | AG34: =sum(B34:AF34) -> 173
A35: Suet Ball Holder | AG35: =sum(B35:AF35) -> 0
A36: 3-in-1 Nutrition Set - Blue | AG36: =sum(B36:AF36) -> 0
A37: 3-in-1 Nutrition Set - Yellow | AG37: =sum(B37:AF37) -> 0
A38: Solar Roof Single - Blue | AG38: =sum(B38:AF38) -> 0
A39: Solar Roof Single - Yellow | AG39: =sum(B39:AF39) -> 0
A40: Perch Extender - Blue | AG40: =sum(B40:AF40) -> 0
A41: Perch Extender - Yellow | AG41: =sum(B41:AF41) -> 0
A42: SUM (Add-ons) | B42: =SUM(B34:B41) -> 8 | C42: =SUM(C34:C41) -> 3 | D42: =SUM(D34:D41) -> 0 | E42: =SUM(E34:E41) -> 0 | F42: =SUM(F34:F41) -> 0 | G42: =SUM(G34:G41) -> 0 | H42: =SUM(H34:H41) -> 2 | I42: =SUM(I34:I41) -> 4 | ... AF42: =SUM(AF34:AF41) -> 9 | AG42: =sum(B42:AF42) -> 173
A45: Units Sold by country (Gross) - Only selling in US
A46: Bird Buddy - Blue - AMAZON.US | AG46: =sum(B46:AE46) -> 0
A47: Bird Buddy - Yellow - AMAZON.US
A48: Bird Buddy with Solar Roof Blue - AMAZON.US | AB48: =AB31 -> 8 | AC48: =AC31 -> 9 | AD48: =AD31 -> 8 | AE48: =AE31 -> 5 | AG48: =sum(B48:AE48) -> 30
A49: Bird Buddy with Solar Roof Yellow - AMAZON.US
A50: Bird Buddy - AMAZON.EU | AG50: =sum(B50:AE50) -> 0
A51: Bird Buddy with Solar Roof - AMAZON.EU | AG51: =sum(B51:AE51) -> 0
A52: Bird Buddy - AMAZON (OTHER1) | AG52: =sum(B52:AE52) -> 0
A53: Bird Buddy with Solar Roof - AMAZON (OTHER1) | AG53: =sum(B53:AE53) -> 0
A54: All Bird Buddy | B54: =B46+B50+B52 -> 0 | C54: =SUM(C46:C53) -> 0 | D54: =SUM(D46:D53) -> 0 | E54: =SUM(E46:E53) -> 0 | F54: =SUM(F46:F53) -> 0 | G54: =SUM(G46:G53) -> 0 | H54: =SUM(H46:H53) -> 0 | I54: =SUM(I46:I53) -> 0 | J54: =SUM(J46:J53) -> 0 | ... AF54: =SUM(AF46:AF53) -> 0 | AG54: =sum(B54:AE54) -> 30
A55: All Bird Buddy with Solar Roof | B55: =B48+B51+B53 -> 0 | C55: =C48+C51+C53 -> 0 | D55: =D48+D51+D53 -> 0 | E55: =E48+E51+E53 -> 0 | F55: =F48+F51+F53 -> 0 | G55: =G48+G51+G53 -> 0 | H55: =H48+H51+H53 -> 0 | I55: =I48+I51+I53 -> 0 | ... AF55: =AF48+AF51+AF53 -> 0 | AG55: =sum(B55:AE55) -> 30
A57: Wall Mount - AMAZON.US | AG57: =sum(B57:AE57) -> 0
A58: Fence Mount - AMAZON.US | AG58: =sum(B58:AE58) -> 0
A59: Suet Ball Holder - AMAZON.US | AG59: =sum(B59:AE59) -> 0
A60: 3-in-1 Nutrition Set - AMAZON.US | AG60: =sum(B60:AE60) -> 0
A61: Solar Roof Single - AMAZON.US | AG61: =sum(B61:AE61) -> 0
A62: All AMAZON.US | B62: =SUM(B57:B61) -> 0 | C62: =SUM(C57:C61) -> 0 | D62: =SUM(D57:D61) -> 0 | E62: =SUM(E57:E61) -> 0 | F62: =SUM(F57:F61) -> 0 | G62: =SUM(G57:G61) -> 0 | H62: =SUM(H57:H61) -> 0 | I62: =SUM(I57:I61) -> 0 | ... AF62: =SUM(AF57:AF61) -> 0 | AG62: =sum(B62:AE62) -> 0
A64: Wall Mount - AMAZON.EU | AG64: =sum(B64:AE64) -> 0
A65: Fence Mount - AMAZON.EU | AG65: =sum(B65:AE65) -> 0
A66: Suet Ball Holder - AMAZON.EU | AG66: =sum(B66:AE66) -> 0
A67: 3-in-1 Nutrition Set - AMAZON.EU | AG67: =sum(B67:AE67) -> 0
A68: Solar Roof Single - AMAZON.EU | AG68: =sum(B68:AE68) -> 0
A69: All AMAZON.EU | B69: =SUM(B64:B68) -> 0 | C69: =SUM(C64:C68) -> 0 | D69: =SUM(D64:D68) -> 0 | E69: =SUM(E64:E68) -> 0 | F69: =SUM(F64:F68) -> 0 | G69: =SUM(G64:G68) -> 0 | H69: =SUM(H64:H68) -> 0 | I69: =SUM(I64:I68) -> 0 | ... AF69: =SUM(AF64:AF68) -> 0 | AG69: =sum(B69:AE69) -> 0
A71: Wall Mount - AMAZON (OTHER1) | AG71: =sum(B71:AE71) -> 0
A72: Fence Mount - AMAZON (OTHER1) | AG72: =sum(B72:AE72) -> 0
A73: Suet Ball Holder - AMAZON (OTHER1) | AG73: =sum(B73:AE73) -> 0
A74: 3-in-1 Nutrition Set - AMAZON (OTHER1) | AG74: =sum(B74:AE74) -> 0
A75: Solar Roof Single - AMAZON (OTHER1) | AG75: =sum(B75:AE75) -> 0
A76: All AMAZON (OTHER1) | B76: =SUM(B71:B75) -> 0 | C76: =SUM(C71:C74) -> 0 | D76: =SUM(D71:D75) -> 0 | E76: =SUM(E71:E75) -> 0 | F76: =SUM(F71:F75) -> 0 | G76: =SUM(G71:G74) -> 0 | H76: =SUM(H71:H74) -> 0 | I76: =SUM(I71:I74) -> 0 | J76: =SUM(J71:J74) -> 0 | K76: =SUM(K71:K74) -> 0 | L76: =SUM(L71:L74) -> 0 | M76: =SUM(M71:M74) -> 0 | N76: =SUM(N71:N74) -> 0 | ... V76: =SUM(V71:V74) -> 0 | W76: =SUM(W71:W75) -> 0 | X76: =SUM(X71:X74) -> 0 | Y76: =SUM(Y71:Y74) -> 0 | Z76: =SUM(Z71:Z74) -> 0 | AA76: =SUM(AA71:AA74) -> 0 | AB76: =SUM(AB71:AB74) -> 0 | AC76: =SUM(AC71:AC74) -> 0 | AD76: =SUM(AD71:AD74) -> 0 | AE76: =SUM(AE71:AE74) -> 0 | AF76: =SUM(AF71:AF74) -> 0 | AG76: =sum(B76:AE76) -> 0
A78: Revenue by country (Gross) - Only selling in US
A79: Bird Buddy - AMAZON.US | AG79: =SUM(B79:AE79) -> 0
A80: Bird Buddy with Solar Roof - AMAZON.US | AB80: =AB9 -> 10357.56 | AC80: =AC9 -> 15763.1 | AD80: =AD9 -> 17036.84 | AE80: =AE9 -> 11243.16 | AG80: =SUM(B80:AE80) -> 54400.66
A81: Bird Buddy - AMAZON.EU | AG81: =SUM(B81:AE81) -> 0
A82: Bird Buddy with Solar Roof - AMAZON.EU | AG82: =SUM(B82:AE82) -> 0
A83: Bird Buddy - AMAZON (OTHER1) | AG83: =SUM(B83:AE83) -> 0
A84: Bird Buddy with Solar Roof - AMAZON (OTHER1) | AG84: =SUM(B84:AE84) -> 0
A85: All Bird Buddy | B85: =B79+B81+B83 -> 0 | C85: =C79+C81+C83 -> 0 | D85: =D79+D81+D83 -> 0 | E85: =E79+E81+E83 -> 0 | F85: =F79+F81+F83 -> 0 | G85: =G79+G81+G83 -> 0 | H85: =H79+H81+H83 -> 0 | I85: =I79+I81+I83 -> 0 | ... AF85: =AF79+AF81+AF83 -> 0 | AG85: =SUM(B85:AE85) -> 0
A86: All Bird Buddy with Solar Roof | B86: =B80+B82+B84 -> 0 | C86: =C80+C82+C84 -> 0 | D86: =D80+D82+D84 -> 0 | E86: =E80+E82+E84 -> 0 | F86: =F80+F82+F84 -> 0 | G86: =G80+G82+G84 -> 0 | H86: =H80+H82+H84 -> 0 | I86: =I80+I82+I84 -> 0 | ... AF86: =AF80+AF82+AF84 -> 0 | AG86: =SUM(B86:AE86) -> 54400.66
A88: Wall Mount - AMAZON.US | AG88: =SUM(B88:AE88) -> 0
A89: Fence Mount - AMAZON.US | AG89: =SUM(B89:AE89) -> 0
A90: Suet Ball Holder - AMAZON.US | AG90: =SUM(B90:AE90) -> 0
A91: 3-in-1 Nutrition Set - AMAZON.US | AG91: =SUM(B91:AE91) -> 0
A92: Solar Roof Single - AMAZON.US | AG92: =SUM(B92:AE92) -> 0
A93: All AMAZON.US | B93: =SUM(B88:B92) -> 0 | C93: =SUM(C88:C92) -> 0 | D93: =SUM(D88:D92) -> 0 | E93: =SUM(E88:E92) -> 0 | F93: =SUM(F88:F92) -> 0 | G93: =SUM(G88:G92) -> 0 | H93: =SUM(H88:H92) -> 0 | I93: =SUM(I88:I92) -> 0 | ... AF93: =SUM(AF88:AF92) -> 0 | AG93: =SUM(B93:AE93) -> 0
A95: Wall Mount - AMAZON.EU | AG95: =SUM(B95:AE95) -> 0
A96: Fence Mount - AMAZON.EU | AG96: =SUM(B96:AE96) -> 0
A97: Suet Ball Holder - AMAZON.EU | AG97: =SUM(B97:AE97) -> 0
A98: 3-in-1 Nutrition Set - AMAZON.EU | AG98: =SUM(B98:AE98) -> 0
A99: Solar Roof Single - AMAZON.EU | AG99: =SUM(B99:AE99) -> 0
A100: All AMAZON.EU | B100: =SUM(B95:B99) -> 0 | C100: =SUM(C95:C99) -> 0 | D100: =SUM(D95:D99) -> 0 | E100: =SUM(E95:E99) -> 0 | F100: =SUM(F95:F99) -> 0 | G100: =SUM(G95:G99) -> 0 | H100: =SUM(H95:H99) -> 0 | I100: =SUM(I95:I99) -> 0 | ... AF100: =SUM(AF95:AF99) -> 0 | AG100: =SUM(B100:AE100) -> 0
A102: Wall Mount - AMAZON (OTHER1) | AG102: =SUM(B102:AE102) -> 0
A103: Fence Mount - AMAZON (OTHER1) | AG103: =SUM(B103:AE103) -> 0
A104: Suet Ball Holder - AMAZON (OTHER1) | AG104: =SUM(B104:AE104) -> 0
A105: 3-in-1 Nutrition Set - AMAZON (OTHER1) | AG105: =SUM(B105:AE105) -> 0
A106: Solar Roof Single - AMAZON (OTHER1) | AG106: =SUM(B106:AE106) -> 0
A107: All AMAZON (OTHER1) | B107: =SUM(B102:B106) -> 0 | C107: =SUM(C102:C106) -> 0 | D107: =SUM(D102:D106) -> 0 | E107: =SUM(E102:E106) -> 0 | F107: =SUM(F102:F106) -> 0 | G107: =SUM(G102:G106) -> 0 | H107: =SUM(H102:H106) -> 0 | I107: =SUM(I102:I106) -> 0 | ... AF107: =SUM(AF102:AF106) -> 0 | AG107: =SUM(B107:AE107) -> 0
A110: Units Cancelled (Gross)
A111: SKU 1 - Blue | B111: 0 | C111: 0 | D111: 1 | E111: 0 | F111: 0 | G111: 0 | H111: 0 | I111: 1 | J111: 1 | K111: 0 | L111: 0 | M111: 1 | N111: 0 | O111: 0 | P111: 0 | Q111: 0 | R111: 0 | S111: 0 | T111: 0 | U111: 0 | V111: 1 | W111: 0 | X111: 0 | Y111: 0 | Z111: 0 | AA111: 0 | AB111: 0 | AC111: 0 | AD111: 0 | AE111: 0 | AF111: 0 | AG111: =SUM(B111:AF111) -> 5
A112: SKU 2 - Yellow | B112: 0 | C112: 0 | D112: 0 | E112: 0 | F112: 1 | G112: 0 | H112: 0 | I112: 0 | J112: 0 | K112: 0 | L112: 0 | M112: 0 | N112: 0 | O112: 0 | P112: 0 | Q112: 0 | R112: 0 | S112: 1 | T112: 0 | U112: 0 | V112: 0 | W112: 0 | X112: 0 | Y112: 0 | Z112: 0 | AA112: 0 | AB112: 0 | AC112: 1 | AD112: 0 | AE112: 0 | AF112: 0 | AG112: =SUM(B112:AF112) -> 3
A113: SKU 3 - Blue w/ Solar | B113: 0 | C113: 0 | D113: 0 | E113: 0 | F113: 0 | G113: 0 | H113: 2 | I113: 0 | J113: 1 | K113: 1 | L113: 4 | M113: 2 | N113: 2 | O113: 0 | P113: 1 | Q113: 3 | R113: 0 | S113: 2 | T113: 0 | U113: 0 | V113: 0 | W113: 0 | X113: 0 | Y113: 1 | Z113: 1 | AA113: 1 | AB113: 0 | AC113: 0 | AD113: 0 | AE113: 0 | AF113: 1 | AG113: =SUM(B113:AF113) -> 22
A114: SKU 4 - Yellow w/ Solar | B114: 0 | C114: 1 | D114: 1 | E114: 0 | F114: 0 | G114: 0 | H114: 0 | I114: 2 | J114: 0 | K114: 0 | L114: 0 | M114: 0 | N114: 0 | O114: 0 | P114: 0 | Q114: 0 | R114: 0 | S114: 0 | T114: 0 | U114: 0 | V114: 2 | W114: 0 | X114: 1 | Y114: 1 | Z114: 0 | AA114: 0 | AB114: 0 | AC114: 1 | AD114: 1 | AE114: 0 | AF114: 0 | AG114: =SUM(B114:AF114) -> 10
A115: SUM (SKU 1 + SKU 2) | B115: =B111+B112 -> 0 | C115: =C111+C112 -> 0 | D115: =D111+D112 -> 1 | E115: =E111+E112 -> 0 | F115: =F111+F112 -> 1 | G115: =G111+G112 -> 0 | H115: =H111+H112 -> 0 | I115: =I111+I112 -> 1 | ... AF115: =AF111+AF112 -> 0 | AG115: =SUM(B115:AF115) -> 8
A116: SUM (SKU 3 + SKU 4) | B116: =B113+B114 -> 0 | C116: =C113+C114 -> 1 | D116: =D113+D114 -> 1 | E116: =E113+E114 -> 0 | F116: =F113+F114 -> 0 | G116: =G113+G114 -> 0 | H116: =H113+H114 -> 2 | I116: =I113+I114 -> 2 | ... AF116: =AF113+AF114 -> 1 | AG116: =SUM(B116:AF116) -> 32
A118: Wall Mount | B118: 0 | C118: 0 | D118: 0 | E118: 0 | F118: 0 | G118: 0 | H118: 0 | I118: 0 | J118: 1 | K118: 0 | L118: 0 | M118: 1 | N118: 0 | O118: 0 | P118: 0 | Q118: 0 | R118: 0 | S118: 0 | T118: 0 | U118: 1 | V118: 0 | W118: 0 | X118: 0 | Y118: 0 | Z118: 0 | AA118: 0 | AB118: 0 | AC118: 0 | AD118: 0 | AE118: 2 | AF118: 0 | AG118: =SUM(B118:AF118) -> 5
A119: Suet Ball Holder | B119: 0 | C119: 0 | D119: 0 | E119: 0 | F119: 0 | G119: 0 | H119: 0 | I119: 0 | J119: 0 | K119: 0 | L119: 0 | M119: 0 | N119: 0 | O119: 0 | P119: 0 | Q119: 0 | R119: 0 | S119: 0 | T119: 0 | U119: 0 | V119: 0 | W119: 0 | X119: 0 | Y119: 0 | Z119: 0 | AA119: 0 | AB119: 0 | AC119: 0 | AD119: 0 | AE119: 0 | AF119: 0 | AG119: =SUM(B119:AF119) -> 0
...

Sheet Digital Marketplaces - P & L
A1: JANUARY | B1: 45292 | C1: 45293 | D1: 45294 | E1: 45295 | F1: 45296 | G1: 45297 | H1: 45298 | I1: 45299 | J1: 45300 | K1: 45301 | L1: 45302 | M1: 45303 | N1: 45304 | O1: 45305 | P1: 45306 | Q1: 45307 | R1: 45308 | S1: 45309 | T1: 45310 | U1: 45311 | V1: 45312 | W1: 45313 | X1: 45314 | Y1: 45315 | Z1: 45316 | AA1: 45317 | AB1: 45318 | AC1: 45319 | AD1: 45320 | AE1: 45321 | AF1: 45322
A2: DAY | B2: MON | C2: TUE | D2: WED | E2: THU | F2: FRI | G2: SAT | H2: SUN | I2: MON | J2: TUE | K2: WED | L2: THU | M2: FRI | N2: SAT | O2: SUN | P2: MON | Q2: TUE | R2: WED | S2: THU | T2: FRI | U2: SAT | V2: SUN | W2: MON | X2: TUE | Y2: WED | Z2: THU | AA2: FRI | AB2: SAT | AC2: SUN | AD2: MON | AE2: TUE | AF2: WED
A3: Rachio (Shopify)
A4: Revenue | B4: =Summary!B22 -> 0 | C4: =Summary!C22 -> 0 | D4: =Summary!D22 -> 0 | E4: =Summary!E22 -> 0 | F4: =Summary!F22 -> 0 | G4: =Summary!G22 -> 0 | H4: =Summary!H22 -> 0 | I4: =Summary!I22 -> 0 | ... AF4: =Summary!AF22 -> 0 | AG4: =sum(B4:AF4) -> 955.22816
A5: Breakdown
A6: - Tax | B6: =Summary!B24 -> 0 | C6: =Summary!C24 -> 0 | D6: =Summary!D24 -> 0 | E6: =Summary!E24 -> 0 | F6: =Summary!F24 -> 0 | G6: =Summary!G24 -> 0 | H6: =Summary!H24 -> 0 | I6: =Summary!I24 -> 0 | ... AF6: =Summary!AF24 -> 0 | AG6: =sum(B6:AF6) -> 55.258158
A7: - Shipping | B7: =Summary!B25 -> 0 | C7: =Summary!C25 -> 0 | D7: =Summary!D25 -> 0 | E7: =Summary!E25 -> 0 | F7: =Summary!F25 -> 0 | G7: =Summary!G25 -> 0 | H7: =Summary!H25 -> 0 | I7: =Summary!I25 -> 0 | ... AF7: =Summary!AF25 -> 0 | AG7: =sum(B7:AF7) -> 0
A8: Orders | B8: =Summary!B58 -> 0 | C8: =Summary!C58 -> 0 | D8: =Summary!D58 -> 0 | E8: =Summary!E58 -> 0 | F8: =Summary!F58 -> 0 | G8: =Summary!G58 -> 0 | H8: =Summary!H58 -> 0 | I8: =Summary!I58 -> 0 | ... AF8: =Summary!AF58 -> 0 | AG8: =sum(B8:AF8) -> 3
A10: Rachio Fees (20%) | B10: =Summary!B81 -> 0 | C10: =Summary!C81 -> 0 | D10: =Summary!D81 -> 0 | E10: =Summary!E81 -> 0 | F10: =Summary!F81 -> 0 | G10: =Summary!G81 -> 0 | H10: =Summary!H81 -> 0 | I10: =Summary!I81 -> 0 | ... AF10: =Summary!AF81 -> 0 | AG10: =sum(B10:AF10) -> 191.04563
A12: Units Sold (Gross) - Rachio
A13: SKU 1 - Blue | B13: 0 | C13: 0 | D13: 0 | E13: 0 | F13: 0 | G13: 0 | H13: 0 | I13: 0 | J13: 0 | K13: 0 | L13: 0 | M13: 0 | N13: 0 | O13: 0 | P13: 0 | Q13: 0 | R13: 0 | S13: 0 | T13: 0 | U13: 0 | V13: 0 | W13: 0 | X13: 0 | Y13: 0 | Z13: 0 | AA13: 0 | AB13: 0 | AC13: 0 | AD13: 0 | AE13: 0 | AF13: 0 | AG13: =sum(B13:AF13) -> 0
A14: SKU 2 - Yellow | B14: 0 | C14: 0 | D14: 0 | E14: 0 | F14: 0 | G14: 0 | H14: 0 | I14: 0 | J14: 0 | K14: 0 | L14: 0 | M14: 0 | N14: 0 | O14: 0 | P14: 0 | Q14: 0 | R14: 0 | S14: 0 | T14: 0 | U14: 0 | V14: 0 | W14: 0 | X14: 0 | Y14: 0 | Z14: 0 | AA14: 0 | AB14: 0 | AC14: 0 | AD14: 0 | AE14: 0 | AF14: 0 | AG14: =sum(B14:AF14) -> 0
A15: SKU 3 - Blue w/ Solar | B15: 0 | C15: 0 | D15: 0 | E15: 0 | F15: 0 | G15: 0 | H15: 0 | I15: 0 | J15: 0 | K15: 0 | L15: 0 | M15: 0 | N15: 0 | O15: 0 | P15: 0 | Q15: 0 | R15: 1 | S15: 0 | T15: 1 | U15: 0 | V15: 0 | W15: 0 | X15: 0 | Y15: 0 | Z15: 0 | AA15: 0 | AB15: 0 | AC15: 0 | AD15: 0 | AE15: 1 | AF15: 0 | AG15: =sum(B15:AF15) -> 3
A16: SKU 4 - Yellow w/ Solar | B16: 0 | C16: 0 | D16: 0 | E16: 0 | F16: 0 | G16: 0 | H16: 0 | I16: 0 | J16: 0 | K16: 0 | L16: 0 | M16: 0 | N16: 0 | O16: 0 | P16: 0 | Q16: 0 | R16: 0 | S16: 0 | T16: 0 | U16: 0 | V16: 0 | W16: 0 | X16: 0 | Y16: 0 | Z16: 0 | AA16: 0 | AB16: 0 | AC16: 0 | AD16: 0 | AE16: 0 | AF16: 0 | AG16: =sum(B16:AF16) -> 0
A17: SUM (SKU 1 - SKU 4) | B17: =SUM(B13:B16) -> 0 | C17: =SUM(C13:C16) -> 0 | D17: =SUM(D13:D16) -> 0 | E17: =SUM(E13:E16) -> 0 | F17: =SUM(F13:F16) -> 0 | G17: =SUM(G13:G16) -> 0 | H17: =SUM(H13:H16) -> 0 | I17: =SUM(I13:I16) -> 0 | ... AF17: =SUM(AF13:AF16) -> 0 | AG17: =sum(B17:AF17) -> 3
A19: Wall Mount | AG19: =sum(B19:AF19) -> 0
A20: Suet Ball Holder | AG20: =sum(B20:AF20) -> 0
A21: 3-in-1 Nutrition Set - Blue | AG21: =sum(B21:AF21) -> 0
A22: 3-in-1 Nutrition Set - Yellow | AG22: =sum(B22:AF22) -> 0
A23: Solar Roof Single - Blue | AG23: =sum(B23:AF23) -> 0
A24: Solar Roof Single - Yellow | AG24: =sum(B24:AF24) -> 0
A25: Perch Extender - Blue | AG25: =sum(B25:AF25) -> 0
A26: Perch Extender - Yellow | AG26: =sum(B26:AF26) -> 0
A27: SUM (Add-ons) | B27: =SUM(B19:B26) -> 0 | C27: =SUM(C19:C26) -> 0 | D27: =SUM(D19:D26) -> 0 | E27: =SUM(E19:E26) -> 0 | F27: =SUM(F19:F26) -> 0 | G27: =SUM(G19:G26) -> 0 | H27: =SUM(H19:H26) -> 0 | I27: =SUM(I19:I26) -> 0 | ... AF27: =SUM(AF19:AF26) -> 0 | AG27: =sum(B27:AF27) -> 0
A29: Units and Revenue Cancelled & Refunds - Rachio
A31: Units Cancelled (Gross) - Rachio
A32: SKU 1 - Blue | I32: 1 | AG32: =SUM(B32:AF32) -> 1
A33: SKU 2 - Yellow | AG33: =SUM(B33:AF33) -> 0
A34: SKU 3 - Blue w/ Solar | D34: 1 | E34: 1 | L34: 2 | M34: 1 | AG34: =SUM(B34:AF34) -> 5
A35: SKU 4 - Yellow w/ Solar | AG35: =SUM(B35:AF35) -> 0
A36: SUM (SKU 1 + SKU 2) | B36: =SUM(B32:B33) -> 0 | C36: =SUM(C32:C33) -> 0 | D36: =SUM(D32:D33) -> 0 | E36: =SUM(E32:E33) -> 0 | F36: =SUM(F32:F33) -> 0 | G36: =SUM(G32:G33) -> 0 | H36: =SUM(H32:H33) -> 0 | I36: =SUM(I32:I33) -> 1 | ... AF36: =SUM(AF32:AF33) -> 0 | AG36: =SUM(B36:AF36) -> 1
A37: SUM (SKU 3 + SKU 4) | B37: =SUM(B34:B35) -> 0 | C37: =SUM(C34:C35) -> 0 | D37: =SUM(D34:D35) -> 1 | E37: =SUM(E34:E35) -> 1 | F37: =SUM(F34:F35) -> 0 | G37: =SUM(G34:G35) -> 0 | H37: =SUM(H34:H35) -> 0 | I37: =SUM(I34:I35) -> 0 | ... AF37: =SUM(AF34:AF35) -> 0 | AG37: =SUM(B37:AF37) -> 5
A39: Wall Mount | E39: 1 | I39: 1 | AG39: =SUM(B39:AF39) -> 2
A40: Suet Ball Holder | E40: 1 | I40: 1 | L40: 1 | AG40: =SUM(B40:AF40) -> 3
A41: 3-in-1 Nutrition Set - Blue | E41: 1 | I41: 1 | AG41: =SUM(B41:AF41) -> 2
A42: 3-in-1 Nutrition Set - Yellow | AG42: =SUM(B42:AF42) -> 0
A43: Solar Roof Single - Blue | I43: 1 | AG43: =SUM(B43:AF43) -> 1
A44: Solar Roof Single - Yellow | AG44: =SUM(B44:AF44) -> 0
A45: Perch Extender - Blue | AG45: =SUM(B45:AF45) -> 0
A46: Perch Extender - Yellow | AG46: =SUM(B46:AF46) -> 0
A47: SUM (Add-ons) | B47: =SUM(B39:B46) -> 0 | C47: =SUM(C39:C46) -> 0 | D47: =SUM(D39:D46) -> 0 | E47: =SUM(E39:E46) -> 3 | F47: =SUM(F39:F46) -> 0 | G47: =SUM(G39:G46) -> 0 | H47: =SUM(H39:H46) -> 0 | I47: =SUM(I39:I46) -> 4 | ... AF47: =SUM(AF39:AF46) -> 0 | AG47: =SUM(B47:AF47) -> 8
A49: Revenue Cancelled (Gross) - Rachio
A50: Hardware | D50: 302.2 | E50: 357.01 | I50: 367.86 | L50: 599.94 | M50: 309.63 | AG50: =SUM(B50:AF50) -> 1936.64
A51: Shipping | AG51: =SUM(B51:AF51) -> 0
A52: Taxes | AG52: =SUM(B52:AF52) -> 0
A53: All NA | B53: =SUM(B50:B52) -> 0 | C53: =SUM(C50:C52) -> 0 | D53: =SUM(D50:D52) -> 302.2 | E53: =SUM(E50:E52) -> 357.01 | F53: =SUM(F50:F52) -> 0 | G53: =SUM(G50:G52) -> 0 | H53: =SUM(H50:H52) -> 0 | I53: =SUM(I50:I52) -> 367.86 | ... AF53: =SUM(AF50:AF52) -> 0 | AG53: =SUM(B53:AF53) -> 1936.64
A55: Hardware - Europe | AG55: =SUM(B55:AF55) -> 0
A56: Shipping - Europe | AG56: =SUM(B56:AF56) -> 0
A57: All EU | B57: =sum(B55:B56) -> 0 | C57: =sum(C55:C56) -> 0 | D57: =sum(D55:D56) -> 0 | E57: =sum(E55:E56) -> 0 | F57: =sum(F55:F56) -> 0 | G57: =sum(G55:G56) -> 0 | H57: =sum(H55:H56) -> 0 | I57: =sum(I55:I56) -> 0 | ... AF57: =sum(AF55:AF56) -> 0 | AG57: =SUM(B57:AF57) -> 0
A59: Units Refund (Gross) - Rachio
A60: SKU 1 - Blue | AG60: =SUM(B60:AF60) -> 0
A61: SKU 2 - Yellow | AG61: =SUM(B61:AF61) -> 0
A62: SKU 3 - Blue w/ Solar | M62: 1 | AG62: =SUM(B62:AF62) -> 1
A63: SKU 4 - Yellow w/ Solar | AG63: =SUM(B63:AF63) -> 0
A64: SUM (SKU 1 + SKU 2) | B64: =SUM(B60:B61) -> 0 | C64: =SUM(C60:C61) -> 0 | D64: =SUM(D60:D61) -> 0 | E64: =SUM(E60:E61) -> 0 | F64: =SUM(F60:F61) -> 0 | G64: =SUM(G60:G61) -> 0 | H64: =SUM(H60:H61) -> 0 | I64: =SUM(I60:I61) -> 0 | ... AF64: =SUM(AF60:AF61) -> 0 | AG64: =SUM(B64:AF64) -> 0
A65: SUM (SKU 3 + SKU 4) | B65: =SUM(B62:B63) -> 0 | C65: =SUM(C62:C63) -> 0 | D65: =SUM(D62:D63) -> 0 | E65: =SUM(E62:E63) -> 0 | F65: =SUM(F62:F63) -> 0 | G65: =SUM(G62:G63) -> 0 | H65: =SUM(H62:H63) -> 0 | I65: =SUM(I62:I63) -> 0 | ... AF65: =SUM(AF62:AF63) -> 0 | AG65: =SUM(B65:AF65) -> 1
A67: Wall Mount | AG67: =SUM(B67:AF67) -> 0
A68: Suet Ball Holder | AG68: =SUM(B68:AF68) -> 0
A69: 3-in-1 Nutrition Set - Blue | AG69: =SUM(B69:AF69) -> 0
A70: 3-in-1 Nutrition Set - Yellow | AG70: =SUM(B70:AF70) -> 0
A71: Solar Roof Single - Blue | AG71: =SUM(B71:AF71) -> 0
A72: Solar Roof Single - Yellow | AG72: =SUM(B72:AF72) -> 0
A73: Perch Extender - Blue | AG73: =SUM(B73:AF73) -> 0
A74: Perch Extender - Yellow | AG74: =SUM(B74:AF74) -> 0
A75: SUM (Add-ons) | B75: =SUM(B67:B74) -> 0 | C75: =SUM(C67:C74) -> 0 | D75: =SUM(D67:D74) -> 0 | E75: =SUM(E67:E74) -> 0 | F75: =SUM(F67:F74) -> 0 | G75: =SUM(G67:G74) -> 0 | H75: =SUM(H67:H74) -> 0 | I75: =SUM(I67:I74) -> 0 | ... AF75: =SUM(AF67:AF74) -> 0 | AG75: =SUM(B75:AF75) -> 0
A77: Orders Return for Refund
A79: Revenue Refunded (Gross) - Rachio
A80: Hardware | B80: 0 | C80: 0 | D80: 0 | E80: 0 | F80: 0 | G80: 0 | H80: 0 | I80: 0 | J80: 0 | K80: 0 | L80: 0 | M80: 309.63 | N80: 0 | O80: 0 | P80: 0 | Q80: 0 | AG80: =SUM(B80:AF80) -> 309.63
A81: Shipping | M81: 20 | AG81: =SUM(B81:AF81) -> 20
A82: Taxes | AG82: =SUM(B82:AF82) -> 0
A83: All NA | B83: =sum(B80:B82) -> 0 | C83: =sum(C80:C82) -> 0 | D83: =sum(D80:D82) -> 0 | E83: =sum(E80:E82) -> 0 | F83: =sum(F80:F82) -> 0 | G83: =sum(G80:G82) -> 0 | H83: =sum(H80:H82) -> 0 | I83: =sum(I80:I82) -> 0 | ... AF83: =sum(AF80:AF82) -> 0 | AG83: =SUM(B83:AF83) -> 329.63
A85: Hardware - Europe
A86: Shipping - Europe
A87: All EU | B87: =sum(B85:B86) -> 0 | C87: =sum(C85:C86) -> 0 | D87: =sum(D85:D86) -> 0 | E87: =sum(E85:E86) -> 0 | F87: =sum(F85:F86) -> 0 | G87: =sum(G85:G86) -> 0 | H87: =sum(H85:H86) -> 0 | I87: =sum(I85:I86) -> 0 | ... AF87: =sum(AF85:AF86) -> 0
A89: RETURN (Replacement Units & Claims) - Rachio
A90: SKU 1 - Blue | B90: 0 | C90: 0 | D90: 0 | E90: 0 | F90: 0 | G90: 0 | H90: 0 | I90: 0 | J90: 0 | K90: 0 | L90: 0 | M90: 0 | N90: 0 | O90: 0 | P90: 0 | Q90: 0 | R90: 0 | S90: 0 | T90: 0 | U90: 0 | V90: 0 | W90: 0 | X90: 0 | Y90: 0 | Z90: 0 | AA90: 0 | AB90: 0 | AC90: 0 | AD90: 0 | AE90: 0 | AF90: 0
A91: SKU 2 - Yellow | B91: 0 | C91: 0 | D91: 0 | E91: 0 | F91: 0 | G91: 0 | H91: 0 | I91: 0 | J91: 0 | K91: 0 | L91: 0 | M91: 0 | N91: 0 | O91: 0 | P91: 0 | Q91: 0 | R91: 0 | S91: 0 | T91: 0 | U91: 0 | V91: 0 | W91: 0 | X91: 0 | Y91: 0 | Z91: 0 | AA91: 0 | AB91: 0 | AC91: 0 | AD91: 0 | AE91: 0 | AF91: 0
A92: SKU 3 - Blue w/ Solar | B92: 0 | C92: 0 | D92: 0 | E92: 0 | F92: 0 | G92: 0 | H92: 0 | I92: 0 | J92: 0 | K92: 0 | L92: 0 | M92: 0 | N92: 0 | O92: 0 | P92: 0 | Q92: 0 | R92: 0 | S92: 0 | T92: 0 | U92: 0 | V92: 0 | W92: 0 | X92: 0 | Y92: 0 | Z92: 0 | AA92: 0 | AB92: 0 | AC92: 0 | AD92: 0 | AE92: 0 | AF92: 0
A93: SKU 4 - Yellow w/ Solar | B93: 0 | C93: 0 | D93: 0 | E93: 0 | F93: 0 | G93: 0 | H93: 0 | I93: 0 | J93: 0 | K93: 0 | L93: 0 | M93: 0 | N93: 0 | O93: 0 | P93: 0 | Q93: 0 | R93: 0 | S93: 0 | T93: 0 | U93: 0 | V93: 0 | W93: 0 | X93: 0 | Y93: 0 | Z93: 0 | AA93: 0 | AB93: 0 | AC93: 0 | AD93: 0 | AE93: 0 | AF93: 0
A94: SUM (SKU 1 + SKU 2) | B94: =B90+B91 -> 0 | C94: =C90+C91 -> 0 | D94: =D90+D91 -> 0 | E94: =E90+E91 -> 0 | F94: =F90+F91 -> 0 | G94: =G90+G91 -> 0 | H94: =H90+H91 -> 0 | I94: =I90+I91 -> 0 | ... AF94: =AF90+AF91 -> 0
A95: SUM (SKU 3 + SKU 4) | B95: =B92+B93 -> 0 | C95: =C92+C93 -> 0 | D95: =D92+D93 -> 0 | E95: =E92+E93 -> 0 | F95: =F92+F93 -> 0 | G95: =G92+G93 -> 0 | H95: =H92+H93 -> 0 | I95: =I92+I93 -> 0 | ... AF95: =AF92+AF93 -> 0
A97: Wall Mount | B97: 0 | C97: 0 | D97: 0 | E97: 0 | F97: 0 | G97: 0 | H97: 0 | I97: 0 | J97: 0 | K97: 0 | L97: 0 | M97: 0 | N97: 0 | O97: 0 | P97: 0 | Q97: 0 | R97: 0 | S97: 0 | T97: 0 | U97: 0 | V97: 0 | W97: 0 | X97: 0 | Y97: 0 | Z97: 0 | AA97: 0 | AB97: 0 | AC97: 0 | AD97: 0 | AE97: 0 | AF97: 0
A98: Suet Ball Holder | B98: 0 | C98: 0 | D98: 0 | E98: 0 | F98: 0 | G98: 0 | H98: 0 | I98: 0 | J98: 0 | K98: 0 | L98: 0 | M98: 0 | N98: 0 | O98: 0 | P98: 0 | Q98: 0 | R98: 0 | S98: 0 | T98: 0 | U98: 0 | V98: 0 | W98: 0 | X98: 0 | Y98: 0 | Z98: 0 | AA98: 0 | AB98: 0 | AC98: 0 | AD98: 0 | AE98: 0 | AF98: 0
A99: 3-in-1 Nutrition Set - Blue | B99: 0 | C99: 0 | D99: 0 | E99: 0 | F99: 0 | G99: 0 | H99: 0 | I99: 0 | J99: 0 | K99: 0 | L99: 0 | M99: 0 | N99: 0 | O99: 0 | P99: 0 | Q99: 0 | R99: 0 | S99: 0 | T99: 0 | U99: 0 | V99: 0 | W99: 0 | X99: 0 | Y99: 0 | Z99: 0 | AA99: 0 | AB99: 0 | AC99: 0 | AD99: 0 | AE99: 0 | AF99: 0
A100: 3-in-1 Nutrition Set - Yellow | B100: 0 | C100: 0 | D100: 0 | E100: 0 | F100: 0 | G100: 0 | H100: 0 | I100: 0 | J100: 0 | K100: 0 | L100: 0 | M100: 0 | N100: 0 | O100: 0 | P100: 0 | Q100: 0 | R100: 0 | S100: 0 | T100: 0 | U100: 0 | V100: 0 | W100: 0 | X100: 0 | Y100: 0 | Z100: 0 | AA100: 0 | AB100: 0 | AC100: 0 | AD100: 0 | AE100: 0 | AF100: 0
A101: Solar Roof Single - Blue | B101: 0 | C101: 0 | D101: 0 | E101: 0 | F101: 0 | G101: 0 | H101: 0 | I101: 0 | J101: 0 | K101: 0 | L101: 0 | M101: 0 | N101: 0 | O101: 0 | P101: 0 | Q101: 0 | R101: 0 | S101: 0 | T101: 0 | U101: 0 | V101: 0 | W101: 0 | X101: 0 | Y101: 0 | Z101: 0 | AA101: 0 | AB101: 0 | AC101: 0 | AD101: 0 | AE101: 0 | AF101: 0
A102: Solar Roof Single - Yellow | B102: 0 | C102: 0 | D102: 0 | E102: 0 | F102: 0 | G102: 0 | H102: 0 | I102: 0 | J102: 0 | K102: 0 | L102: 0 | M102: 0 | N102: 0 | O102: 0 | P102: 0 | Q102: 0 | R102: 0 | S102: 0 | T102: 0 | U102: 0 | V102: 0 | W102: 0 | X102: 0 | Y102: 0 | Z102: 0 | AA102: 0 | AB102: 0 | AC102: 0 | AD102: 0 | AE102: 0 | AF102: 0
A103: Perch Extender - Blue | B103: 0 | C103: 0 | D103: 0 | E103: 0 | F103: 0 | G103: 0 | H103: 0 | I103: 0 | J103: 0 | K103: 0 | L103: 0 | M103: 0 | N103: 0 | O103: 0 | P103: 0 | Q103: 0 | R103: 0 | S103: 0 | T103: 0 | U103: 0 | V103: 0 | W103: 0 | X103: 0 | Y103: 0 | Z103: 0 | AA103: 0 | AB103: 0 | AC103: 0 | AD103: 0 | AE103: 0 | AF103: 0
A104: Perch Extender - Yellow | B104: 0 | C104: 0 | D104: 0 | E104: 0 | F104: 0 | G104: 0 | H104: 0 | I104: 0 | J104: 0 | K104: 0 | L104: 0 | M104: 0 | N104: 0 | O104: 0 | P104: 0 | Q104: 0 | R104: 0 | S104: 0 | T104: 0 | U104: 0 | V104: 0 | W104: 0 | X104: 0 | Y104: 0 | Z104: 0 | AA104: 0 | AB104: 0 | AC104: 0 | AD104: 0 | AE104: 0 | AF104: 0
A105: SUM (Add-ons) | B105: =SUM(B97:B104) -> 0 | C105: =SUM(C97:C101) -> 0 | D105: =SUM(D97:D101) -> 0 | E105: =SUM(E97:E101) -> 0 | F105: =SUM(F97:F101) -> 0 | G105: =SUM(G97:G101) -> 0 | H105: =SUM(H97:H101) -> 0 | I105: =SUM(I97:I101) -> 0 | J105: =SUM(J97:J101) -> 0 | ... AF105: =SUM(AF97:AF101) -> 0
A107: Parts
A108: Housing - Blue | B108: 0 | C108: 0 | D108: 0 | E108: 0 | F108: 0 | G108: 0 | H108: 0 | I108: 0 | J108: 0 | K108: 0 | L108: 0 | M108: 0 | N108: 0 | O108: 0 | P108: 0 | Q108: 0 | R108: 0 | S108: 0 | T108: 0 | U108: 0 | V108: 0 | W108: 0 | X108: 0 | Y108: 0 | Z108: 0 | AA108: 0 | AB108: 0 | AC108: 0 | AD108: 0 | AE108: 0 | AF108: 0
A109: Housing - Yellow | B109: 0 | C109: 0 | D109: 0 | E109: 0 | F109: 0 | G109: 0 | H109: 0 | I109: 0 | J109: 0 | K109: 0 | L109: 0 | M109: 0 | N109: 0 | O109: 0 | P109: 0 | Q109: 0 | R109: 0 | S109: 0 | T109: 0 | U109: 0 | V109: 0 | W109: 0 | X109: 0 | Y109: 0 | Z109: 0 | AA109: 0 | AB109: 0 | AC109: 0 | AD109: 0 | AE109: 0 | AF109: 0
A110: Camera Module | B110: 0 | C110: 0 | D110: 0 | E110: 0 | F110: 0 | G110: 0 | H110: 0 | I110: 0 | J110: 0 | K110: 0 | L110: 0 | M110: 0 | N110: 0 | O110: 0 | P110: 0 | Q110: 0 | R110: 0 | S110: 0 | T110: 0 | U110: 0 | V110: 0 | W110: 0 | X110: 0 | Y110: 0 | Z110: 0 | AA110: 0 | AB110: 0 | AC110: 0 | AD110: 0 | AE110: 1 | AF110: 0
A112: Orders Replaced NA | B112: 0 | C112: 0 | D112: 0 | E112: 0 | F112: 0 | G112: 0 | H112: 0 | I112: 0 | J112: 0 | K112: 0 | L112: 0 | M112: 0 | N112: 0 | O112: 0 | P112: 0 | Q112: 0 | R112: 0 | S112: 0 | T112: 0 | U112: 0 | V112: 0 | W112: 0 | X112: 0 | Y112: 0 | Z112: 0 | AA112: 0 | AB112: 0 | AC112: 0 | AD112: 0 | AE112: 1 | AF112: 0
X113: 1 undeliverable
A115: Weatherflow (Shopify)
A116: Revenue | B116: =Summary!B26 -> 0 | C116: =Summary!C26 -> 0 | D116: =Summary!D26 -> 0 | E116: =Summary!E26 -> 0 | F116: =Summary!F26 -> 0 | G116: =Summary!G26 -> 0 | H116: =Summary!H26 -> 0 | I116: =Summary!I26 -> 0 | ... AF116: =Summary!AF26 -> 0 | AG116: =SUM(B116:AF116) -> 299
A117: Breakdown
A118: - Tax | B118: =Summary!B28 -> 0 | C118: =Summary!C28 -> 0 | D118: =Summary!D28 -> 0 | E118: =Summary!E28 -> 0 | F118: =Summary!F28 -> 0 | G118: =Summary!G28 -> 0 | H118: =Summary!H28 -> 0 | I118: =Summary!I28 -> 0 | ... AF118: =Summary!AF28 -> 0 | AG118: =SUM(B118:AF118) -> 0
...

Sheet PP - Results
A1: 45261 | B1: 45292 | C1: 45293 | D1: 45294 | E1: 45295 | F1: 45296 | G1: 45297 | H1: 45298 | I1: 45299 | J1: 45300 | K1: 45301 | L1: 45302 | M1: 45303 | N1: 45304 | O1: 45305 | P1: 45306 | Q1: 45307 | R1: 45308 | S1: 45309 | T1: 45310 | U1: 45311 | V1: 45312 | W1: 45313 | X1: 45314 | Y1: 45315 | Z1: 45316 | AA1: 45317 | AB1: 45318 | AC1: 45319 | AD1: 45320 | AE1: 45321 | AF1: 45322
B2: MON | C2: TUE | D2: WED | E2: THU | F2: FRI | G2: SAT | H2: SUN | I2: MON | J2: TUE | K2: WED | L2: THU | M2: FRI | N2: SAT | O2: SUN | P2: MON | Q2: TUE | R2: WED | S2: THU | T2: FRI | U2: SAT | V2: SUN | W2: MON | X2: TUE | Y2: WED | Z2: THU | AA2: FRI | AB2: SAT | AC2: SUN | AD2: MON | AE2: TUE | AF2: WED
A4: Number of participants | B4: ='PP - Data'!B10 -> 114 | C4: ='PP - Data'!C10 -> 101 | D4: ='PP - Data'!D10 -> 111 | E4: ='PP - Data'!E10 -> 95 | F4: ='PP - Data'!F10 -> 116 | G4: ='PP - Data'!G10 -> 115 | H4: ='PP - Data'!H10 -> 133 | I4: ='PP - Data'!I10 -> 93 | ... AF4: ='PP - Data'!AF10 -> 34
A5: Engagement Rate | B5: =B4/Summary!B49 -> 0.59685864 | C5: =C4/Summary!C49 -> 0.63924051 | D5: =D4/Summary!D49 -> 0.62011173 | E5: =E4/Summary!E49 -> 0.60897436 | F5: =F4/Summary!F49 -> 0.65168539 | G5: =G4/Summary!G49 -> 0.61497326 | H5: =H4/Summary!H49 -> 0.68205128 | I5: =I4/Summary!I49 -> 0.64583333 | ... AF5: =AF4/Summary!AF49 -> 0.49275362
A7: Post-purchase Survey
A8: Facebook / Instagram | B8: ='PP - Data'!B12 -> 0.20175439 | C8: ='PP - Data'!C12 -> 0.25742574 | D8: ='PP - Data'!D12 -> 0.33333333 | E8: ='PP - Data'!E12 -> 0.32631579 | F8: ='PP - Data'!F12 -> 0.29310345 | G8: ='PP - Data'!G12 -> 0.29565217 | H8: ='PP - Data'!H12 -> 0.30827068 | I8: ='PP - Data'!I12 -> 0.2688172 | ... AF8: ='PP - Data'!AF12 -> 0.47058824
A9: Where on Facebook/Instagram have you heard about Bird Buddy?
A10: I saw an ad | B10: ='PP - Data'!B28 -> 0.7826087 | C10: ='PP - Data'!C28 -> 0.84615385 | D10: ='PP - Data'!D28 -> 0.59459459 | E10: ='PP - Data'!E28 -> 0.70967742 | F10: ='PP - Data'!F28 -> 0.79411765 | G10: ='PP - Data'!G28 -> 0.58823529 | H10: ='PP - Data'!H28 -> 0.75609756 | I10: ='PP - Data'!I28 -> 0.76 | ... AF10: ='PP - Data'!AF28 -> 0.875
A11: I saw a post about Bird Buddy on my friend's feed | B11: ='PP - Data'!B29 -> 0.043478261 | C11: ='PP - Data'!C29 -> 0.076923077 | D11: ='PP - Data'!D29 -> 0.21621622 | E11: ='PP - Data'!E29 -> 0.22580645 | F11: ='PP - Data'!F29 -> 0.11764706 | G11: ='PP - Data'!G29 -> 0.26470588 | H11: ='PP - Data'!H29 -> 0.12195122 | I11: ='PP - Data'!I29 -> 0.08 | ... AF11: ='PP - Data'!AF29 -> 0.0625
A12: I saw an organic post from Bird Buddy | B12: ='PP - Data'!B30 -> 0.17391304 | C12: ='PP - Data'!C30 -> 0.076923077 | D12: ='PP - Data'!D30 -> 0.18918919 | E12: ='PP - Data'!E30 -> 0.064516129 | F12: ='PP - Data'!F30 -> 0.088235294 | G12: ='PP - Data'!G30 -> 0.14705882 | H12: ='PP - Data'!H30 -> 0.12195122 | I12: ='PP - Data'!I30 -> 0.16 | ... AF12: ='PP - Data'!AF30 -> 0.0625
A13: Friends / Family | B13: ='PP - Data'!B13 -> 0.61403509 | C13: ='PP - Data'!C13 -> 0.55445545 | D13: ='PP - Data'!D13 -> 0.5045045 | E13: ='PP - Data'!E13 -> 0.50526316 | F13: ='PP - Data'!F13 -> 0.5 | G13: ='PP - Data'!G13 -> 0.54782609 | H13: ='PP - Data'!H13 -> 0.52631579 | I13: ='PP - Data'!I13 -> 0.58064516 | ... AF13: ='PP - Data'!AF13 -> 0.41176471
A14: TikTok | B14: ='PP - Data'!B14 -> 0.0087719298 | C14: ='PP - Data'!C14 -> 0.01980198 | D14: ='PP - Data'!D14 -> 0.027027027 | E14: ='PP - Data'!E14 -> 0.010526316 | F14: ='PP - Data'!F14 -> 0 | G14: ='PP - Data'!G14 -> 0.0086956522 | H14: ='PP - Data'!H14 -> 0.007518797 | I14: ='PP - Data'!I14 -> 0.010752688 | ... AF14: ='PP - Data'!AF14 -> 0
A15: TV / Radio | B15: ='PP - Data'!B15 -> 0.0087719298 | C15: ='PP - Data'!C15 -> 0.03960396 | D15: ='PP - Data'!D15 -> 0.018018018 | E15: ='PP - Data'!E15 -> 0.010526316 | F15: ='PP - Data'!F15 -> 0.051724138 | G15: ='PP - Data'!G15 -> 0.017391304 | H15: ='PP - Data'!H15 -> 0.022556391 | I15: ='PP - Data'!I15 -> 0 | ... AF15: ='PP - Data'!AF15 -> 0
A16: Blog / Article | B16: ='PP - Data'!B16 -> 0.070175439 | C16: ='PP - Data'!C16 -> 0.0099009901 | D16: ='PP - Data'!D16 -> 0.036036036 | E16: ='PP - Data'!E16 -> 0.052631579 | F16: ='PP - Data'!F16 -> 0.051724138 | G16: ='PP - Data'!G16 -> 0.052173913 | H16: ='PP - Data'!H16 -> 0.07518797 | I16: ='PP - Data'!I16 -> 0.064516129 | ... AF16: ='PP - Data'!AF16 -> 0.058823529
A17: Reddit | B17: ='PP - Data'!B17 -> 0 | C17: ='PP - Data'!C17 -> 0.0099009901 | D17: ='PP - Data'!D17 -> 0.036036036 | E17: ='PP - Data'!E17 -> 0.021052632 | F17: ='PP - Data'!F17 -> 0 | G17: ='PP - Data'!G17 -> 0 | H17: ='PP - Data'!H17 -> 0.007518797 | I17: ='PP - Data'!I17 -> 0 | ... AF17: ='PP - Data'!AF17 -> 0
A18: Google, Youtube | B18: ='PP - Data'!B18 -> 0.096491228 | C18: ='PP - Data'!C18 -> 0.10891089 | D18: ='PP - Data'!D18 -> 0.045045045 | E18: ='PP - Data'!E18 -> 0.073684211 | F18: ='PP - Data'!F18 -> 0.10344828 | G18: ='PP - Data'!G18 -> 0.069565217 | H18: ='PP - Data'!H18 -> 0.052631579 | I18: ='PP - Data'!I18 -> 0.075268817 | ... AF18: ='PP - Data'!AF18 -> 0.058823529
A19: Yahoo, Bing | B19: ='PP - Data'!B19 -> 0 | C19: ='PP - Data'!C19 -> 0 | D19: ='PP - Data'!D19 -> 0 | E19: ='PP - Data'!E19 -> 0 | F19: ='PP - Data'!F19 -> 0 | G19: ='PP - Data'!G19 -> 0.0086956522 | H19: ='PP - Data'!H19 -> 0 | I19: ='PP - Data'!I19 -> 0 | ... AF19: ='PP - Data'!AF19 -> 0
A24: Number of participants | B24: ='PP - Data'!B60 -> 115 | C24: ='PP - Data'!C60 -> 100 | D24: ='PP - Data'!D60 -> 111 | E24: ='PP - Data'!E60 -> 95 | F24: ='PP - Data'!F60 -> 117 | G24: ='PP - Data'!G60 -> 115 | H24: ='PP - Data'!H60 -> 132 | I24: ='PP - Data'!I60 -> 94 | ... AF24: ='PP - Data'!AF60 -> 34
A25: Engagement Rate | B25: =B24/Summary!B49 -> 0.60209424 | C25: =C24/Summary!C49 -> 0.63291139 | D25: =D24/Summary!D49 -> 0.62011173 | E25: =E24/Summary!E49 -> 0.60897436 | F25: =F24/Summary!F49 -> 0.65730337 | G25: =G24/Summary!G49 -> 0.61497326 | H25: =H24/Summary!H49 -> 0.67692308 | I25: =I24/Summary!I49 -> 0.65277778 | ... AF25: =AF24/Summary!AF49 -> 0.49275362
A27: Who is this for? (sub-question 3)
A28: Just me | B28: ='PP - Data'!B62 -> 0.32173913 | C28: ='PP - Data'!C62 -> 0.31 | D28: ='PP - Data'!D62 -> 0.2972973 | E28: ='PP - Data'!E62 -> 0.30526316 | F28: ='PP - Data'!F62 -> 0.32478632 | G28: ='PP - Data'!G62 -> 0.30434783 | H28: ='PP - Data'!H62 -> 0.28030303 | I28: ='PP - Data'!I62 -> 0.28723404 | ... AF28: ='PP - Data'!AF62 -> 0.32352941
A29: Did you compare us with other smart bird feeders before purchasing? | B29: ='PP - Data'!B63 | C29: ='PP - Data'!C63 | D29: ='PP - Data'!D63 | E29: ='PP - Data'!E63 | F29: ='PP - Data'!F63 | G29: ='PP - Data'!G63 | H29: ='PP - Data'!H63 | I29: ='PP - Data'!I63 | ... AF29: ='PP - Data'!AF63
A30: Yes, I did extensive research | B30: ='PP - Data'!B64 -> 0.56756757 | C30: ='PP - Data'!C64 -> 0.80645161 | D30: ='PP - Data'!D64 -> 0.57575758 | E30: ='PP - Data'!E64 -> 0.55172414 | F30: ='PP - Data'!F64 -> 0.71052632 | G30: ='PP - Data'!G64 -> 0.85714286 | H30: ='PP - Data'!H64 -> 0.64864865 | I30: ='PP - Data'!I64 -> 0.59259259 | ... AF30: ='PP - Data'!AF64 -> 0.36363636
A31: Yes, but very briefly | B31: ='PP - Data'!B65 -> 0.40540541 | C31: ='PP - Data'!C65 -> 0.16129032 | D31: ='PP - Data'!D65 -> 0.39393939 | E31: ='PP - Data'!E65 -> 0.37931034 | F31: ='PP - Data'!F65 -> 0.28947368 | G31: ='PP - Data'!G65 -> 0.085714286 | H31: ='PP - Data'!H65 -> 0.35135135 | I31: ='PP - Data'!I65 -> 0.33333333 | ... AF31: ='PP - Data'!AF65 -> 0.54545455
A32: No, not at all | B32: ='PP - Data'!B66 -> 0.027027027 | C32: ='PP - Data'!C66 -> 0.032258065 | D32: ='PP - Data'!D66 -> 0.03030303 | E32: ='PP - Data'!E66 -> 0.068965517 | F32: ='PP - Data'!F66 -> 0 | G32: ='PP - Data'!G66 -> 0.057142857 | H32: ='PP - Data'!H66 -> 0 | I32: ='PP - Data'!I66 -> 0.074074074 | ... AF32: ='PP - Data'!AF66 -> 0.090909091
B33: ='PP - Data'!B67 | C33: ='PP - Data'!C67 | D33: ='PP - Data'!D67 | E33: ='PP - Data'!E67 | F33: ='PP - Data'!F67 | G33: ='PP - Data'!G67 | H33: ='PP - Data'!H67 | I33: ='PP - Data'!I67 | ... AF33: ='PP - Data'!AF67
A34: I will use with my family | B34: ='PP - Data'!B68 -> 0.31304348 | C34: ='PP - Data'!C68 -> 0.28 | D34: ='PP - Data'!D68 -> 0.27927928 | E34: ='PP - Data'!E68 -> 0.22105263 | F34: ='PP - Data'!F68 -> 0.29059829 | G34: ='PP - Data'!G68 -> 0.36521739 | H34: ='PP - Data'!H68 -> 0.39393939 | I34: ='PP - Data'!I68 -> 0.26595745 | ... AF34: ='PP - Data'!AF68 -> 0.26470588
A35: Did you compare us with other smart bird feeders before purchasing? | B35: ='PP - Data'!B69 | C35: ='PP - Data'!C69 | D35: ='PP - Data'!D69 | E35: ='PP - Data'!E69 | F35: ='PP - Data'!F69 | G35: ='PP - Data'!G69 | H35: ='PP - Data'!H69 | I35: ='PP - Data'!I69 | ... AF35: ='PP - Data'!AF69
A36: Yes, I did extensive research | B36: ='PP - Data'!B70 -> 0.75 | C36: ='PP - Data'!C70 -> 0.64285714 | D36: ='PP - Data'!D70 -> 0.58064516 | E36: ='PP - Data'!E70 -> 0.52380952 | F36: ='PP - Data'!F70 -> 0.55882353 | G36: ='PP - Data'!G70 -> 0.78571429 | H36: ='PP - Data'!H70 -> 0.67307692 | I36: ='PP - Data'!I70 -> 0.48 | ... AF36: ='PP - Data'!AF70 -> 0.66666667
A37: Yes, but very briefly | B37: ='PP - Data'!B71 -> 0.19444444 | C37: ='PP - Data'!C71 -> 0.32142857 | D37: ='PP - Data'!D71 -> 0.32258065 | E37: ='PP - Data'!E71 -> 0.38095238 | F37: ='PP - Data'!F71 -> 0.38235294 | G37: ='PP - Data'!G71 -> 0.21428571 | H37: ='PP - Data'!H71 -> 0.25 | I37: ='PP - Data'!I71 -> 0.32 | ... AF37: ='PP - Data'!AF71 -> 0.33333333
A38: No, not at all | B38: ='PP - Data'!B72 -> 0.055555556 | C38: ='PP - Data'!C72 -> 0.035714286 | D38: ='PP - Data'!D72 -> 0.096774194 | E38: ='PP - Data'!E72 -> 0.095238095 | F38: ='PP - Data'!F72 -> 0.058823529 | G38: ='PP - Data'!G72 -> 0 | H38: ='PP - Data'!H72 -> 0.076923077 | I38: ='PP - Data'!I72 -> 0.2 | ... AF38: ='PP - Data'!AF72 -> 0
B39: ='PP - Data'!B73 | C39: ='PP - Data'!C73 | D39: ='PP - Data'!D73 | E39: ='PP - Data'!E73 | F39: ='PP - Data'!F73 | G39: ='PP - Data'!G73 | H39: ='PP - Data'!H73 | I39: ='PP - Data'!I73 | ... AF39: ='PP - Data'!AF73
A40: My parents | B40: ='PP - Data'!B74 -> 0.1826087 | C40: ='PP - Data'!C74 -> 0.21 | D40: ='PP - Data'!D74 -> 0.1981982 | E40: ='PP - Data'!E74 -> 0.22105263 | F40: ='PP - Data'!F74 -> 0.17948718 | G40: ='PP - Data'!G74 -> 0.1826087 | H40: ='PP - Data'!H74 -> 0.13636364 | I40: ='PP - Data'!I74 -> 0.23404255 | ... AF40: ='PP - Data'!AF74 -> 0.14705882
A41: Did you compare us with other smart bird feeders before purchasing? | B41: ='PP - Data'!B75 | C41: ='PP - Data'!C75 | D41: ='PP - Data'!D75 | E41: ='PP - Data'!E75 | F41: ='PP - Data'!F75 | G41: ='PP - Data'!G75 | H41: ='PP - Data'!H75 | I41: ='PP - Data'!I75 | ... AF41: ='PP - Data'!AF75
A42: Yes, I did extensive research | B42: ='PP - Data'!B76 -> 0.52380952 | C42: ='PP - Data'!C76 -> 0.33333333 | D42: ='PP - Data'!D76 -> 0.54545455 | E42: ='PP - Data'!E76 -> 0.38095238 | F42: ='PP - Data'!F76 -> 0.42857143 | G42: ='PP - Data'!G76 -> 0.33333333 | H42: ='PP - Data'!H76 -> 0.33333333 | I42: ='PP - Data'!I76 -> 0.36363636 | ... AF42: ='PP - Data'!AF76 -> 0.8
A43: Yes, but very briefly | B43: ='PP - Data'!B77 -> 0.42857143 | C43: ='PP - Data'!C77 -> 0.47619048 | D43: ='PP - Data'!D77 -> 0.36363636 | E43: ='PP - Data'!E77 -> 0.38095238 | F43: ='PP - Data'!F77 -> 0.38095238 | G43: ='PP - Data'!G77 -> 0.38095238 | H43: ='PP - Data'!H77 -> 0.5 | I43: ='PP - Data'!I77 -> 0.63636364 | ... AF43: ='PP - Data'!AF77 -> 0.2
A44: No, not at all | B44: ='PP - Data'!B78 -> 0.047619048 | C44: ='PP - Data'!C78 -> 0.19047619 | D44: ='PP - Data'!D78 -> 0.090909091 | E44: ='PP - Data'!E78 -> 0.23809524 | F44: ='PP - Data'!F78 -> 0.19047619 | G44: ='PP - Data'!G78 -> 0.28571429 | H44: ='PP - Data'!H78 -> 0.16666667 | I44: ='PP - Data'!I78 -> 0 | ... AF44: ='PP - Data'!AF78 -> 0
B45: ='PP - Data'!B79 | C45: ='PP - Data'!C79 | D45: ='PP - Data'!D79 | E45: ='PP - Data'!E79 | F45: ='PP - Data'!F79 | G45: ='PP - Data'!G79 | H45: ='PP - Data'!H79 | I45: ='PP - Data'!I79 | ... AF45: ='PP - Data'!AF79
A46: Spouse | B46: ='PP - Data'!B80 -> 0.1826087 | C46: ='PP - Data'!C80 -> 0.2 | D46: ='PP - Data'!D80 -> 0.22522523 | E46: ='PP - Data'!E80 -> 0.25263158 | F46: ='PP - Data'!F80 -> 0.20512821 | G46: ='PP - Data'!G80 -> 0.14782609 | H46: ='PP - Data'!H80 -> 0.18939394 | I46: ='PP - Data'!I80 -> 0.21276596 | ... AF46: ='PP - Data'!AF80 -> 0.26470588
A47: Did you compare us with other smart bird feeders before purchasing?
A48: Yes, I did extensive research | G48: ='PP - Data'!G82 -> 0.64705882 | H48: ='PP - Data'!H82 -> 0.36 | I48: ='PP - Data'!I82 -> 0.4 | J48: ='PP - Data'!J82 -> 0.45 | K48: ='PP - Data'!K82 -> 0.27272727 | L48: ='PP - Data'!L82 -> 0.6875 | M48: ='PP - Data'!M82 -> 0.63636364 | N48: ='PP - Data'!N82 -> 0.84615385 | ... AE48: ='PP - Data'!AE82 -> 0.58823529
A49: Yes, but very briefly | G49: ='PP - Data'!G83 -> 0.29411765 | H49: ='PP - Data'!H83 -> 0.44 | I49: ='PP - Data'!I83 -> 0.5 | J49: ='PP - Data'!J83 -> 0.5 | K49: ='PP - Data'!K83 -> 0.72727273 | L49: ='PP - Data'!L83 -> 0.1875 | M49: ='PP - Data'!M83 -> 0.31818182 | N49: ='PP - Data'!N83 -> 0 | ... AE49: ='PP - Data'!AE83 -> 0.23529412
A50: No, not at all | G50: ='PP - Data'!G84 -> 0.058823529 | H50: ='PP - Data'!H84 -> 0.2 | I50: ='PP - Data'!I84 -> 0.1 | J50: ='PP - Data'!J84 -> 0.05 | K50: ='PP - Data'!K84 -> 0 | L50: ='PP - Data'!L84 -> 0.125 | M50: ='PP - Data'!M84 -> 0.045454545 | N50: ='PP - Data'!N84 -> 0.15384615 | ... AE50: ='PP - Data'!AE84 -> 0.17647059

Sheet Data - P&L
B1: Business Metrics
A2: Source | B2: COGS | E2: Attachment Rates | H2: Marketing Averages (per first-time order) | K2: Fees | N2: VAT Averages | Q2: 30 Day Returns | T2: Digital Market Places & B2B
B3: Bird Buddy | C3: 86.9 | D3: 86.9 | E3: Solar Roof | F3: =(('DTC - P&L'!AG94+'DTC - P&L'!AG95)/'DTC - P&L'!AG88) -> 0.15143737 | H3: COGS | I3: =(C3*F9)+(C4*F8)+(C5*F3)+(C6*F4)+(C7*F5)+(C8*F6)+(C9*F7)+(C10*F10) -> 106.20439 | J3: =(D3*F9)+(D4*F8)+(D5*F3)+(D6*F4)+(D7*F5)+(D8*F6)+(D9*F7) -> 101.67667 | K3: Stripe Processing Fee | L3: 0.029 | N3: Europe | O3: 0.22 | Q3: US Shipping | R3: 15 | T3: Average % tax | U3: 0.0614 | V3: Source
B4: Bird Buddy with Solar Roof | C4: 97.61 | D4: 97.61 | E4: Wall Mount | F4: =('DTC - P&L'!AG90/'DTC - P&L'!AG88) -> 0.40657084 | H4: Inbound Shipping | I4: =C38+('DTC - P&L'!AG98/'DTC - P&L'!AG88)*D38 -> 14.707605 | K4: Duty | L4: 0.034 | N4: ROW | O4: 0.13 | Q4: EU Shipping | R4: 40
B5: Solar Roof Single | C5: 13.44 | D5: 13.44 | E5: Fence Mount | F5: 0 | H5: Outbound Shipping | I5: =C34+('DTC - P&L'!AG98/'DTC - P&L'!AG88)*D34 -> 62.249281 | K5: China Tax | L5: 0.075 | N5: NA | Q5: ROW Shipping | R5: 20
B6: Wall Mount | C6: 5.49 | D6: 5.49 | E6: Suet Ball Holder | F6: =('DTC - P&L'!AG91)/'DTC - P&L'!AG88 -> 0.34548255 | H6: Taxes and VAT | I6: 16.81 | K6: HMF | L6: 0.00125 | Q6: Money Return | R6: 1
B7: Fence Mount | C7: 6.37 | E7: 3-in-1 | F7: =('DTC - P&L'!AG92+'DTC - P&L'!AG93)/'DTC - P&L'!AG88 -> 0.27053388 | H7: China Tax (7.5%) | I7: 0 | K7: MPF | L7: 0.003464
B8: Suet Ball Holder | C8: 1.19 | D8: 1.19 | E8: Bird Buddy w/ Solar | F8: =('DTC - P&L'!AG86+'DTC - P&L'!AG87)/'DTC - P&L'!AG88 -> 0.77464066 | H8: Duty (3.4%) | I8: 0 | K8: Solar Roof China Tax | L8: 0.075
B9: 3-in-1 Nutrition Set | C9: 6.66 | D9: 6.66 | E9: Bird Buddy | F9: =1-F8 -> 0.22535934 | H9: Processing Fee (2,90%) | I9: =Summary!B117*L3 -> 6.1923622 | K9: Solar Roof Duty | L9: 0.025
B10: Perch Extender | C10: 6 | E10: Perch Extender | F10: =('DTC - P&L'!AG96+'DTC - P&L'!AG97)/'DTC - P&L'!AG88 -> 0.75462012 | H10: Transaction Fee ($0.30) | I10: =0.3 -> 0.3 | K10: Chargeback Fee (Stripe) | L10: 15
B11: Avg. Merch Cost | C11: 3.94 | E11: OTHER 2 | H11: OTHER 1
B12: Avg. Merch Cost without Calendar | C12: 14.79 | E12: OTHER 3 | H12: OTHER 2 | K12: Stripe | L12: 0.95
B13: SBF Housing | E13: OTHER 4 | H13: OTHER 3 | K13: Affirm | L13: 0.05
B14: SBF Camera | E14: OTHER 5 | H14: OTHER 4 | K14: Affirm processing fee | L14: 0.0579
H15: All | I15: =SUM(I3:I14) -> 206.46364 | K15: Affirm transaction fee | L15: 0.3
B22: Outbound shipping | C22: Bird buddy | D22: Add-ons | E22: Merch
A23: *w/o CA weight | B23: Outbound (NA) | C23: 43.58 | D23: 9.68 | E23: 5.4 | H23: App Advertising
B24: Outbound (Europe) | C24: 11.94 | D24: 6.16 | H24: Meta Share to Apple Store | I24: 0.8
B25: Outbound (ROW) | C25: 11.94 | D25: 6.16 | H25: Meta Share to Google Store | I25: 0.2
A26: Source | B26: 3PL Costs | C26: 0 | D26: 0
B27: Handling Fee
B28: Serial Capture | C28: 0.1 | D28: 0
B29: Storage | C29: 0.31 | D29: 0.31
B30: Supplies cost | C30: 0 | D30: 0
B31: Pick charge | C31: 0.35 | D31: 0.35
B32: Pollybag cost | C32: 0 | D32: 0
B33: Carton cost | C33: 1.65 | D33: 0.71
B34: Total outbound (NA) | C34: =C26+C23-C27 -> 43.58 | D34: =D26+D23-D27 -> 9.68
B35: Total outbound (Europe) | C35: 15.06 | D35: =D27+D24-D28 -> 6.16
B36: Total outbound (ROW) | C36: 20
A37: Source | B37: Inbound shipping | C37: Bird buddy | D37: Add-ons
B38: Inbound (NA) | C38: 11.94 | D38: 1.435
B39: Inbound (Europe) | C39: 11.94 | D39: 1.44
B40: Inbound (ROW) | C40: 11.94 | D40: 1.44
B42: AMAZON Logistics | C42: Bird buddy | D42: Add-ons
A43: https://docs.google.com/spreadsheets/d/1Dn0q7h1bHxXdG0N9KpcqzFo0tWUWYXOrRX7yxv3G1E0/edit#gid=1264242332 | B43: Inbound | C43: 11.94 | D43: 1.435
A44: =sum(C43:C44) -> 12.18 | B44: Storage Fee | C44: 0.24 | D44: 0.24
A45: =C46 -> 12.94 | B45: AMAZON Fees | C45: Bird buddy
A46: =sum(F43:F45) -> 0 | B46: FBA fee for units | C46: 12.94
B47: FBA fee for addons | C47: 5.7
A48: =C38 -> 11.94 | B48: Sales Fee | C48: 0.15
B49: AMAZON Shipping | C49: Bird buddy
A50: =sum(A43:A48) -> 37.06 | B50: BB units Shipping | C50: 11
B51: Addons Shipping | C51: 6.155
B53: COGS adjustment for DTC
B54: Returns for refunds | C54: 0.25
B55: Returns for replacements | C55: 0.1
B57: COGS adjustment for Amazon
B58: Returns for refunds | C58: 0.5644
B59: Returns for replacements | C59: 0.4603
B61: Amazon Removal Fee
B62: Units | C62: 5.56
B63: Add-ons | C63: 2.2
A66: https://docs.google.com/document/d/1m1D0mcq6_cpIUs4Z2pSMjDX9L4kRSfAwaLu0UKQppIM/edit?usp=sharing | B66: Explanation for Returns, Cancellations, Replacements calculation
A68: https://docs.google.com/spreadsheets/d/1JFD6SusYZSq5MvMm0PnCaYPmLBVKBKvK09yjZIlSFN4/edit#gid=0 | B68: Amazon Modelling for cancelled orders
B69: Full Price Template for cancelled orders
B70: item-tax | C70: 17.58
B71: shipping-price | C71: 0.29
B72: shipping-tax | C72: 0 | I72: 17.58 | J72: 0.29 | K72: 0 | L72: 0.17 | M72: 0.01
B73: gift-wrap-price | C73: 0.17
B74: gift-wrap-tax | C74: 0.01
B75: item-promotion-discount | C75: 2.44
B76: ship-promotion-discount | C76: 0.21
B79: B2B
B80: Agency Fee | C80: 0.05 | D80: NET NET
B81: Agency transportation best buy | C81: *Dejan sporoči

Sheet Working Copy B2B - P&L
A1: JANUARY | B1: 45292 | C1: 45293 | D1: 45294 | E1: 45295 | F1: 45296 | G1: 45297 | H1: 45298 | I1: 45299 | J1: 45300 | K1: 45301 | L1: 45302 | M1: 45303 | N1: 45304 | O1: 45305 | P1: 45306 | Q1: 45307 | R1: 45308 | S1: 45309 | T1: 45310 | U1: 45311 | V1: 45312 | W1: 45313 | X1: 45314 | Y1: 45315 | Z1: 45316 | AA1: 45317 | AB1: 45318 | AC1: 45319 | AD1: 45320 | AE1: 45321 | AF1: 45322
A2: DAY | B2: MON | C2: TUE | D2: WED | E2: THU | F2: FRI | G2: SAT | H2: SUN | I2: MON | J2: TUE | K2: WED | L2: THU | M2: FRI | N2: SAT | O2: SUN | P2: MON | Q2: TUE | R2: WED | S2: THU | T2: FRI | U2: SAT | V2: SUN | W2: MON | X2: TUE | Y2: WED | Z2: THU | AA2: FRI | AB2: SAT | AC2: SUN | AD2: MON | AE2: TUE | AF2: WED
A3: Best Buy 🟡
A4: Revenue | B4: =Summary!B33 -> 2864.7186 | C4: =Summary!C34 -> 0 | D4: =Summary!D34 -> 4014 | E4: =Summary!E34 -> 2069 | F4: =Summary!F34 -> 224 | G4: =Summary!G34 -> 0 | H4: =Summary!H34 -> 3739 | I4: =Summary!I34 -> 688 | J4: =Summary!J34 -> 1221 | ... U4: =Summary!U34 -> 2250 | V4: =Summary!V33 -> 4055.6519 | W4: =Summary!W33 -> 2997.8075 | X4: =Summary!X33 -> 1713.5135 | Y4: =Summary!Y33 -> 700.524 | Z4: =Summary!Z33 -> 0 | AA4: =Summary!AA33 -> 0 | AB4: =Summary!AB33 -> 573.156 | AC4: =Summary!AC33 -> 256.33871 | ... AF4: =Summary!AF33 -> 256.33871 | AG4: =sum(B4:AF4) -> 41137.726
A5: Breakdown
A6: - Tax | B6: =Summary!B35 -> 165.7186 | C6: =Summary!C35 -> 0 | D6: =Summary!D35 -> 246.4596 | E6: =Summary!E35 -> 127.0366 | F6: =Summary!F35 -> 13.7536 | G6: =Summary!G35 -> 0 | H6: =Summary!H35 -> 229.5746 | I6: =Summary!I35 -> 42.2432 | ... AF6: =Summary!AF35 -> 14.828714 | AG6: =sum(B6:AF6) -> 2476.3762
A7: - Shipping | B7: =#REF! -> #REF! | C7: =#REF! -> #REF! | D7: =#REF! -> #REF! | E7: =#REF! -> #REF! | F7: =#REF! -> #REF! | G7: =#REF! -> #REF! | H7: =#REF! -> #REF! | I7: =#REF! -> #REF! | ... AF7: =#REF! -> #REF! | AG7: =sum(B7:AF7) -> #REF!
A8: Orders | B8: =Summary!B63 -> 9 | C8: =Summary!C63 -> 0 | D8: =Summary!D63 -> 13 | E8: =Summary!E63 -> 6 | F8: =Summary!F63 -> 0 | G8: =Summary!G63 -> 0 | H8: =Summary!H63 -> 12 | I8: =Summary!I63 -> 1 | ... AF8: =Summary!AF63 -> 6 | AG8: =sum(B8:AF8) -> 139
A10: Best Buy Commission (17%, pri solar $239 je 15%, pri BF $209 imajo 10%) | AG10: =sum(B10:AF10) -> 0
A11: Agency Comission
A12: Units Sold (Net) - Best Buy
A13: SKU 1 - Blue | AG13: =sum(B13:AF13) -> 0
A14: SKU 2 - Yellow | AG14: =sum(B14:AF14) -> 0
A15: SKU 3 - Blue w/ Solar | B15: =B8 -> 9 | C15: =C8 -> 0 | D15: =D8 -> 13 | E15: =E8 -> 6 | F15: =F8 -> 0 | G15: =G8 -> 0 | H15: =H8 -> 12 | I15: =I8 -> 1 | ... AF15: =AF8 -> 6 | AG15: =sum(B15:AF15) -> 139
A16: SKU 4 - Yellow w/ Solar | AG16: =sum(B16:AF16) -> 0
A17: SUM (SKU 1 - SKU 4) | B17: =SUM(B13:B16) -> 9 | C17: =SUM(C13:C16) -> 0 | D17: =SUM(D13:D16) -> 13 | E17: =SUM(E13:E16) -> 6 | F17: =SUM(F13:F16) -> 0 | G17: =SUM(G13:G16) -> 0 | H17: =SUM(H13:H16) -> 12 | I17: =SUM(I13:I16) -> 1 | ... AF17: =SUM(AF13:AF16) -> 6 | AG17: =sum(B17:AF17) -> 139
A19: Wall Mount | AG19: =sum(B19:AF19) -> 0
A20: Suet Ball Holder | AG20: =sum(B20:AF20) -> 0
A21: 3-in-1 Nutrition Set - Blue | AG21: =sum(B21:AF21) -> 0
A22: 3-in-1 Nutrition Set - Yellow | AG22: =sum(B22:AF22) -> 0
A23: Solar Roof Single - Blue | AG23: =sum(B23:AF23) -> 0
A24: Solar Roof Single - Yellow | AG24: =sum(B24:AF24) -> 0
A25: Perch Extender - Blue | AG25: =sum(B25:AF25) -> 0
A26: Perch Extender - Yellow | AG26: =sum(B26:AF26) -> 0
A27: SUM (Add-ons) | B27: =SUM(B19:B26) -> 0 | C27: =SUM(C19:C26) -> 0 | D27: =SUM(D19:D26) -> 0 | E27: =SUM(E19:E26) -> 0 | F27: =SUM(F19:F26) -> 0 | G27: =SUM(G19:G26) -> 0 | H27: =SUM(H19:H26) -> 0 | I27: =SUM(I19:I26) -> 0 | ... AF27: =SUM(AF19:AF26) -> 0 | AG27: =sum(B27:AF27) -> 0
A29: Units and Revenue Cancelled & Refunds - Best Buy
A31: Units Cancelled (Gross) - Best Buy
A32: SKU 1 - Blue | AG32: =SUM(B32:AF32) -> 0
A33: SKU 2 - Yellow | AG33: =SUM(B33:AF33) -> 0
A34: SKU 3 - Blue w/ Solar | AG34: =SUM(B34:AF34) -> 0
A35: SKU 4 - Yellow w/ Solar | AG35: =SUM(B35:AF35) -> 0
A36: SUM (SKU 1 + SKU 2) | B36: =SUM(B32:B33) -> 0 | C36: =SUM(C32:C33) -> 0 | D36: =SUM(D32:D33) -> 0 | E36: =SUM(E32:E33) -> 0 | F36: =SUM(F32:F33) -> 0 | G36: =SUM(G32:G33) -> 0 | H36: =SUM(H32:H33) -> 0 | I36: =SUM(I32:I33) -> 0 | ... AF36: =SUM(AF32:AF33) -> 0 | AG36: =SUM(B36:AF36) -> 0
A37: SUM (SKU 3 + SKU 4) | B37: =SUM(B34:B35) -> 0 | C37: =SUM(C34:C35) -> 0 | D37: =SUM(D34:D35) -> 0 | E37: =SUM(E34:E35) -> 0 | F37: =SUM(F34:F35) -> 0 | G37: =SUM(G34:G35) -> 0 | H37: =SUM(H34:H35) -> 0 | I37: =SUM(I34:I35) -> 0 | ... AF37: =SUM(AF34:AF35) -> 0 | AG37: =SUM(B37:AF37) -> 0
A39: Wall Mount | AG39: =SUM(B39:AF39) -> 0
A40: Suet Ball Holder | AG40: =SUM(B40:AF40) -> 0
A41: 3-in-1 Nutrition Set - Blue | AG41: =SUM(B41:AF41) -> 0
A42: 3-in-1 Nutrition Set - Yellow | AG42: =SUM(B42:AF42) -> 0
A43: Solar Roof Single - Blue | AG43: =SUM(B43:AF43) -> 0
A44: Solar Roof Single - Yellow | AG44: =SUM(B44:AF44) -> 0
A45: Perch Extender - Blue | AG45: =SUM(B45:AF45) -> 0
A46: Perch Extender - Yellow | AG46: =SUM(B46:AF46) -> 0
A47: SUM (Add-ons) | B47: =SUM(B39:B46) -> 0 | C47: =SUM(C39:C46) -> 0 | D47: =SUM(D39:D46) -> 0 | E47: =SUM(E39:E46) -> 0 | F47: =SUM(F39:F46) -> 0 | G47: =SUM(G39:G46) -> 0 | H47: =SUM(H39:H46) -> 0 | I47: =SUM(I39:I46) -> 0 | ... AF47: =SUM(AF39:AF46) -> 0 | AG47: =SUM(B47:AF47) -> 0
A49: Revenue Cancelled (Gross) - Best Buy
A50: Hardware | AG50: =SUM(B50:AF50) -> 0
A51: Shipping | AG51: =SUM(B51:AF51) -> 0
A52: Taxes | AG52: =SUM(B52:AF52) -> 0
A53: All NA | B53: =SUM(B50:B52) -> 0 | C53: =SUM(C50:C52) -> 0 | D53: =SUM(D50:D52) -> 0 | E53: =SUM(E50:E52) -> 0 | F53: =SUM(F50:F52) -> 0 | G53: =SUM(G50:G52) -> 0 | H53: =SUM(H50:H52) -> 0 | I53: =SUM(I50:I52) -> 0 | ... AF53: =SUM(AF50:AF52) -> 0 | AG53: =SUM(B53:AF53) -> 0
A55: Units Refund (Gross) - Best Buy
A56: SKU 1 - Blue | AG56: =SUM(B56:AF56) -> 0
A57: SKU 2 - Yellow | AG57: =SUM(B57:AF57) -> 0
A58: SKU 3 - Blue w/ Solar | AG58: =SUM(B58:AF58) -> 0
A59: SKU 4 - Yellow w/ Solar | AG59: =SUM(B59:AF59) -> 0
A60: SUM (SKU 1 + SKU 2) | B60: =SUM(B56:B57) -> 0 | C60: =SUM(C56:C57) -> 0 | D60: =SUM(D56:D57) -> 0 | E60: =SUM(E56:E57) -> 0 | F60: =SUM(F56:F57) -> 0 | G60: =SUM(G56:G57) -> 0 | H60: =SUM(H56:H57) -> 0 | I60: =SUM(I56:I57) -> 0 | ... AF60: =SUM(AF56:AF57) -> 0 | AG60: =SUM(B60:AF60) -> 0
A61: SUM (SKU 3 + SKU 4) | B61: =SUM(B58:B59) -> 0 | C61: =SUM(C58:C59) -> 0 | D61: =SUM(D58:D59) -> 0 | E61: =SUM(E58:E59) -> 0 | F61: =SUM(F58:F59) -> 0 | G61: =SUM(G58:G59) -> 0 | H61: =SUM(H58:H59) -> 0 | I61: =SUM(I58:I59) -> 0 | ... AF61: =SUM(AF58:AF59) -> 0 | AG61: =SUM(B61:AF61) -> 0
A63: Wall Mount | AG63: =SUM(B63:AF63) -> 0
A64: Suet Ball Holder | AG64: =SUM(B64:AF64) -> 0
A65: 3-in-1 Nutrition Set - Blue | AG65: =SUM(B65:AF65) -> 0
A66: 3-in-1 Nutrition Set - Yellow | AG66: =SUM(B66:AF66) -> 0
A67: Solar Roof Single - Blue | AG67: =SUM(B67:AF67) -> 0
A68: Solar Roof Single - Yellow | AG68: =SUM(B68:AF68) -> 0
A69: Perch Extender - Blue | AG69: =SUM(B69:AF69) -> 0
A70: Perch Extender - Yellow | AG70: =SUM(B70:AF70) -> 0
A71: SUM (Add-ons) | B71: =SUM(B63:B70) -> 0 | C71: =SUM(C63:C70) -> 0 | D71: =SUM(D63:D70) -> 0 | E71: =SUM(E63:E70) -> 0 | F71: =SUM(F63:F70) -> 0 | G71: =SUM(G63:G70) -> 0 | H71: =SUM(H63:H70) -> 0 | I71: =SUM(I63:I70) -> 0 | ... AF71: =SUM(AF63:AF70) -> 0 | AG71: =SUM(B71:AF71) -> 0
A73: Revenue Refunded (Gross) - Best Buy
A74: Hardware | AG74: =SUM(B74:AF74) -> 0
A75: Shipping | AG75: =SUM(B75:AF75) -> 0
A76: Taxes | AG76: =SUM(B76:AF76) -> 0
A77: All NA | B77: =sum(B74:B76) -> 0 | C77: =sum(C74:C76) -> 0 | D77: =sum(D74:D76) -> 0 | E77: =sum(E74:E76) -> 0 | F77: =sum(F74:F76) -> 0 | G77: =sum(G74:G76) -> 0 | H77: =sum(H74:H76) -> 0 | I77: =sum(I74:I76) -> 0 | ... AF77: =sum(AF74:AF76) -> 0 | AG77: =SUM(B77:AF77) -> 0
A81: Target 🔴
A82: Revenue | B82: =Summary!B36 -> 254.736 | C82: =Summary!C36 -> 0 | D82: =Summary!D36 -> 241.9992 | E82: =Summary!E36 -> 254.736 | F82: =Summary!F36 -> 764.208 | G82: =Summary!G36 -> 254.736 | H82: =Summary!H36 -> 254.736 | I82: =Summary!I36 -> 748.287 | ... AF82: =Summary!AF36 -> 0 | AG82: =sum(B82:AF82) -> 14708.881
A83: Breakdown
A84: - Tax | B84: =Summary!B38 -> 14.736 | C84: =Summary!C38 -> 0 | D84: =Summary!D38 -> 13.9992 | E84: =Summary!E38 -> 14.736 | F84: =Summary!F38 -> 44.208 | G84: =Summary!G38 -> 14.736 | H84: =Summary!H38 -> 14.736 | I84: =Summary!I38 -> 43.287 | ... AF84: =Summary!AF38 -> 0 | AG84: =sum(B84:AF84) -> 850.8812
A85: - Shipping | B85: =#REF! -> #REF! | C85: =#REF! -> #REF! | D85: =#REF! -> #REF! | E85: =#REF! -> #REF! | F85: =#REF! -> #REF! | G85: =#REF! -> #REF! | H85: =#REF! -> #REF! | I85: =#REF! -> #REF! | ... AF85: =#REF! -> #REF! | AG85: =sum(B85:AF85) -> #REF!
A86: Orders | B86: =Summary!B64 -> 1 | C86: =Summary!C64 -> 0 | D86: =Summary!D64 -> 1 | E86: =Summary!E64 -> 1 | F86: =Summary!F64 -> 3 | G86: =Summary!G64 -> 1 | H86: =Summary!H64 -> 1 | I86: =Summary!I64 -> 3 | ... AF86: =Summary!AF64 -> 0 | AG86: =sum(B86:AF86) -> 59
A88: Target Commission (28.75%)
A90: Units Sold (Gross) - Target
A91: SKU 1 - Blue | B91: =B86 -> 1 | C91: =C86 -> 0 | D91: =D86 -> 1 | E91: =E86 -> 1 | F91: =F86 -> 3 | G91: =G86 -> 1 | H91: =H86 -> 1 | I91: =I86 -> 3 | ... AF91: =AF86 -> 0 | AG91: =sum(B91:AF91) -> 59
A92: SKU 2 - Yellow | AG92: =sum(B92:AF92) -> 0
A93: SKU 3 - Blue w/ Solar | AG93: =sum(B93:AF93) -> 0
A94: SKU 4 - Yellow w/ Solar | AG94: =sum(B94:AF94) -> 0
A95: SUM (SKU 1 - SKU 4) | B95: =SUM(B91:B94) -> 1 | C95: =SUM(C91:C94) -> 0 | D95: =SUM(D91:D94) -> 1 | E95: =SUM(E91:E94) -> 1 | F95: =SUM(F91:F94) -> 3 | G95: =SUM(G91:G94) -> 1 | H95: =SUM(H91:H94) -> 1 | I95: =SUM(I91:I94) -> 3 | ... AF95: =SUM(AF91:AF94) -> 0 | AG95: =sum(B95:AF95) -> 59
A97: Wall Mount | AG97: =sum(B97:AF97) -> 0
A98: Suet Ball Holder | AG98: =sum(B98:AF98) -> 0
A99: 3-in-1 Nutrition Set - Blue | AG99: =sum(B99:AF99) -> 0
A100: 3-in-1 Nutrition Set - Yellow | AG100: =sum(B100:AF100) -> 0
A101: Solar Roof Single - Blue | AG101: =sum(B101:AF101) -> 0
A102: Solar Roof Single - Yellow | AG102: =sum(B102:AF102) -> 0
A103: Perch Extender - Blue | AG103: =sum(B103:AF103) -> 0
A104: Perch Extender - Yellow | AG104: =sum(B104:AF104) -> 0
A105: SUM (Add-ons) | B105: =SUM(B97:B104) -> 0 | C105: =SUM(C97:C104) -> 0 | D105: =SUM(D97:D104) -> 0 | E105: =SUM(E97:E104) -> 0 | F105: =SUM(F97:F104) -> 0 | G105: =SUM(G97:G104) -> 0 | H105: =SUM(H97:H104) -> 0 | I105: =SUM(I97:I104) -> 0 | ... AF105: =SUM(AF97:AF104) -> 0 | AG105: =sum(B105:AF105) -> 0
A107: Units and Revenue Cancalled & Refunds - Target
A109: Units Cancelled (Gross) - Target
A110: SKU 1 - Blue | AG110: =SUM(B110:AF110) -> 0
A111: SKU 2 - Yellow | AG111: =SUM(B111:AF111) -> 0
A112: SKU 3 - Blue w/ Solar | AG112: =SUM(B112:AF112) -> 0
A113: SKU 4 - Yellow w/ Solar | AG113: =SUM(B113:AF113) -> 0
A114: SUM (SKU 1 + SKU 2) | B114: =SUM(B110:B111) -> 0 | C114: =SUM(C110:C111) -> 0 | D114: =SUM(D110:D111) -> 0 | E114: =SUM(E110:E111) -> 0 | F114: =SUM(F110:F111) -> 0 | G114: =SUM(G110:G111) -> 0 | H114: =SUM(H110:H111) -> 0 | I114: =SUM(I110:I111) -> 0 | ... AF114: =SUM(AF110:AF111) -> 0 | AG114: =SUM(B114:AF114) -> 0
A115: SUM (SKU 3 + SKU 4) | B115: =SUM(B112:B113) -> 0 | C115: =SUM(C112:C113) -> 0 | D115: =SUM(D112:D113) -> 0 | E115: =SUM(E112:E113) -> 0 | F115: =SUM(F112:F113) -> 0 | G115: =SUM(G112:G113) -> 0 | H115: =SUM(H112:H113) -> 0 | I115: =SUM(I112:I113) -> 0 | ... AF115: =SUM(AF112:AF113) -> 0 | AG115: =SUM(B115:AF115) -> 0
A117: Wall Mount | AG117: =SUM(B117:AF117) -> 0
A118: Suet Ball Holder | AG118: =SUM(B118:AF118) -> 0
...

Sheet OLDB2B - P&L
A1: JANUARY | B1: 45292 | C1: 45293 | D1: 45294 | E1: 45295 | F1: 45296 | G1: 45297 | H1: 45298 | I1: 45299 | J1: 45300 | K1: 45301 | L1: 45302 | M1: 45303 | N1: 45304 | O1: 45305 | P1: 45306 | Q1: 45307 | R1: 45308 | S1: 45309 | T1: 45310 | U1: 45311 | V1: 45312 | W1: 45313 | X1: 45314 | Y1: 45315 | Z1: 45316 | AA1: 45317 | AB1: 45318 | AC1: 45319 | AD1: 45320 | AE1: 45321 | AF1: 45322
A2: DAY | B2: MON | C2: TUE | D2: WED | E2: THU | F2: FRI | G2: SAT | H2: SUN | I2: MON | J2: TUE | K2: WED | L2: THU | M2: FRI | N2: SAT | O2: SUN | P2: MON | Q2: TUE | R2: WED | S2: THU | T2: FRI | U2: SAT | V2: SUN | W2: MON | X2: TUE | Y2: WED | Z2: THU | AA2: FRI | AB2: SAT | AC2: SUN | AD2: MON | AE2: TUE | AF2: WED
A3: Revenue
A4: Revenue Rachio (Shopify) | B4: =Summary!B22 -> 0 | C4: =Summary!C22 -> 0 | D4: =Summary!D22 -> 0 | E4: =Summary!E22 -> 0 | F4: =Summary!F22 -> 0 | G4: =Summary!G22 -> 0 | H4: =Summary!H22 -> 0 | I4: =Summary!I22 -> 0 | ... AF4: =Summary!AF22 -> 0 | AG4: =sum(B4:AF4) -> 955.22816
A5: Revenue Weatherflow (Shopify) | B5: =Summary!B26 -> 0 | C5: =Summary!C26 -> 0 | D5: =Summary!D26 -> 0 | E5: =Summary!E26 -> 0 | F5: =Summary!F26 -> 0 | G5: =Summary!G26 -> 0 | H5: =Summary!H26 -> 0 | I5: =Summary!I26 -> 0 | ... AF5: =Summary!AF26 -> 0 | AG5: =sum(B5:AF5) -> 299
A6: Revenue Best Buy | B6: =Summary!B33 -> 2864.7186 | C6: =Summary!C34 -> 0 | D6: =Summary!D34 -> 4014 | E6: =Summary!E34 -> 2069 | F6: =Summary!F34 -> 224 | G6: =Summary!G34 -> 0 | H6: =Summary!H34 -> 3739 | I6: =Summary!I34 -> 688 | J6: =Summary!J34 -> 1221 | ... U6: =Summary!U34 -> 2250 | V6: =Summary!V33 -> 4055.6519 | W6: =Summary!W33 -> 2997.8075 | X6: =Summary!X33 -> 1713.5135 | Y6: =Summary!Y33 -> 700.524 | Z6: =Summary!Z33 -> 0 | AA6: =Summary!AA33 -> 0 | AB6: =Summary!AB33 -> 573.156 | AC6: =Summary!AC33 -> 256.33871 | ... AF6: =Summary!AF33 -> 256.33871 | AG6: =sum(B6:AF6) -> 41137.726
A7: Revenue - All | B7: =SUM(B4:B6) -> 2864.7186 | C7: =SUM(C4:C6) -> 0 | D7: =SUM(D4:D6) -> 4014 | E7: =SUM(E4:E6) -> 2069 | F7: =SUM(F4:F6) -> 224 | G7: =SUM(G4:G6) -> 0 | H7: =SUM(H4:H6) -> 3739 | I7: =SUM(I4:I6) -> 688 | ... AF7: =SUM(AF4:AF6) -> 256.33871 | AG7: =sum(B7:AF7) -> 42391.955
A9: Orders
A10: Orders Rachio (Shopify) | B10: =Summary!B58 -> 0 | C10: =Summary!C58 -> 0 | D10: =Summary!D58 -> 0 | E10: =Summary!E58 -> 0 | F10: =Summary!F58 -> 0 | G10: =Summary!G58 -> 0 | H10: =Summary!H58 -> 0 | I10: =Summary!I58 -> 0 | ... AF10: =Summary!AF58 -> 0 | AG10: =sum(B10:AF10) -> 3
A11: Orders Weatherflow (Shopify) | B11: =Summary!B59 -> 0 | C11: =Summary!C59 -> 0 | D11: =Summary!D59 -> 0 | E11: =Summary!E59 -> 0 | F11: =Summary!F59 -> 0 | G11: =Summary!G59 -> 0 | H11: =Summary!H59 -> 0 | I11: =Summary!I59 -> 0 | ... AF11: =Summary!AF59 -> 0 | AG11: =sum(B11:AF11) -> 0
A12: Orders Best Buy | B12: =Summary!B63 -> 9 | C12: =Summary!C63 -> 0 | D12: =Summary!D63 -> 13 | E12: =Summary!E63 -> 6 | F12: =Summary!F63 -> 0 | G12: =Summary!G63 -> 0 | H12: =Summary!H63 -> 12 | I12: =Summary!I63 -> 1 | ... AF12: =Summary!AF63 -> 6 | AG12: =sum(B12:AF12) -> 139
A13: Orders - All | B13: =SUM(B10:B12) -> 9 | C13: =SUM(C10:C12) -> 0 | D13: =SUM(D10:D12) -> 13 | E13: =SUM(E10:E12) -> 6 | F13: =SUM(F10:F12) -> 0 | G13: =SUM(G10:G12) -> 0 | H13: =SUM(H10:H12) -> 12 | I13: =SUM(I10:I12) -> 1 | ... AF13: =SUM(AF10:AF12) -> 6 | AG13: =sum(B13:AF13) -> 142
A15: Shopify Platform (Rachio,...)
A16: Revenue Shopify (gross) | B16: =Summary!B22 -> 0 | C16: =Summary!C22 -> 0 | D16: =Summary!D22 -> 0 | E16: =Summary!E22 -> 0 | F16: =Summary!F22 -> 0 | G16: =Summary!G22 -> 0 | H16: =Summary!H22 -> 0 | I16: =Summary!I22 -> 0 | ... AF16: =Summary!AF22 -> 0 | AG16: =SUM(B16:AF16) -> 955.22816
A17: Discounts | B17: 0 | C17: 0 | D17: 0 | E17: 0 | F17: 0 | G17: 0 | H17: 0 | I17: 0 | J17: 0 | K17: 0 | L17: 0 | M17: 0 | N17: 0 | O17: 0 | P17: 0 | Q17: 0 | R17: 0 | S17: 0 | T17: 0 | U17: 0 | V17: 0 | W17: 0 | X17: 0 | Y17: 0 | Z17: 0 | AA17: 0 | AB17: 0 | AG17: =SUM(B17:AF17) -> 0
A18: Shipping Shopify | B18: 0 | C18: 0 | D18: 0 | E18: 0 | F18: 0 | G18: 0 | H18: 0 | I18: 0 | J18: 0 | K18: 0 | L18: 0 | M18: 0 | N18: 0 | O18: 0 | P18: 0 | Q18: 0 | R18: 0 | S18: 0 | T18: 0 | U18: 0 | V18: 0 | W18: 0 | X18: 0 | Y18: 0 | Z18: 0 | AA18: 0 | AB18: 0 | AC18: 0 | AD18: 0 | AE18: 0 | AF18: 0 | AG18: =SUM(B18:AF18) -> 0
A19: Tax Shopify | B19: 0 | C19: 0 | D19: 0 | E19: 0 | F19: 0 | G19: 0 | H19: 0 | I19: 0 | J19: 0 | K19: 0 | L19: 0 | M19: 0 | N19: 0 | O19: 0 | P19: 0 | Q19: 0 | R19: 0 | S19: 0 | T19: 0 | U19: 0 | V19: 0 | W19: 0 | X19: 0 | Y19: 0 | Z19: 0 | AA19: 0 | AB19: 0 | AC19: 0 | AD19: 0 | AE19: 0 | AF19: 0 | AG19: =SUM(B19:AF19) -> 0
A20: All Shopify | B20: =SUM(B16:B19) -> 0 | C20: =SUM(C16:C19) -> 0 | D20: =SUM(D16:D19) -> 0 | E20: =SUM(E16:E19) -> 0 | F20: =SUM(F16:F19) -> 0 | G20: =SUM(G16:G19) -> 0 | H20: =SUM(H16:H19) -> 0 | I20: =SUM(I16:I19) -> 0 | ... AF20: =SUM(AF16:AF19) -> 0 | AG20: =SUM(B20:AF20) -> 955.22816
A22: Units Sold (Gross) - Rachio
A23: Bird Buddy - Blue | B23: =B75-B40 -> 0 | C23: =C75-C40 -> 0 | D23: =D75-D40 -> 0 | E23: =E75-E40 -> 0 | F23: =F75-F40 -> 0 | G23: =G75-G40 -> 0 | H23: =H75-H40 -> 1 | I23: =I75-I40 -> 1 | ... AF23: =AF75-AF40 -> 0 | AG23: =sum(B23:AF23) -> 8
A24: Bird Buddy - Yellow | B24: =B76-B41 -> 0 | C24: =C76-C41 -> 0 | D24: =D76-D41 -> 0 | E24: =E76-E41 -> 0 | F24: =F76-F41 -> 0 | G24: =G76-G41 -> 0 | H24: =H76-H41 -> 1 | I24: =I76-I41 -> 1 | ... AF24: =AF76-AF41 -> 0 | AG24: =sum(B24:AF24) -> 4
A25: Bird Buddy with Solar Roof - Blue | B25: =B77-B42 -> 3 | C25: =C77-C42 -> 0 | D25: =D77-D42 -> 2 | E25: =E77-E42 -> 1 | F25: =F77-F42 -> 1 | G25: =G77-G42 -> 0 | H25: =H77-H42 -> 0 | I25: =I77-I42 -> 2 | ... AF25: =AF77-AF42 -> 0 | AG25: =sum(B25:AF25) -> 98
A26: Bird Buddy with Solar Roof - Yellow | B26: =B78-B43 -> 3 | C26: =C78-C43 -> 1 | D26: =D78-D43 -> 0 | E26: =E78-E43 -> 0 | F26: =F78-F43 -> 0 | G26: =G78-G43 -> 0 | H26: =H78-H43 -> 0 | I26: =I78-I43 -> 6 | ... AF26: =AF78-AF43 -> 0 | AG26: =sum(B26:AF26) -> 40
A27: All Bird Buddy | B27: =SUM(B23:B26) -> 6 | C27: =SUM(C23:C26) -> 1 | D27: =SUM(D23:D26) -> 2 | E27: =SUM(E23:E26) -> 1 | F27: =SUM(F23:F26) -> 1 | G27: =SUM(G23:G26) -> 0 | H27: =SUM(H23:H26) -> 2 | I27: =SUM(I23:I26) -> 10 | ... AF27: =SUM(AF23:AF26) -> 0 | AG27: =sum(B27:AF27) -> 150
A29: Wall Mount | AG29: =sum(B29:AF29) -> 0
A30: Suet Ball Holder | AG30: =sum(B30:AF30) -> 0
A31: 3-in-1 Nutrition Set - Blue | AG31: =sum(B31:AF31) -> 0
A32: 3-in-1 Nutrition Set - Yellow | AG32: =sum(B32:AF32) -> 0
A33: Solar Roof Single - Blue | AG33: =sum(B33:AF33) -> 0
A34: Solar Roof Single - Yellow | AG34: =sum(B34:AF34) -> 0
A35: Perch Extender - Blue | AG35: =sum(B35:AF35) -> 0
A36: Perch Extender - Yellow | AG36: =sum(B36:AF36) -> 0
A37: All | B37: =SUM(B29:B36) -> 0 | C37: =SUM(C29:C36) -> 0 | D37: =SUM(D29:D36) -> 0 | E37: =SUM(E29:E36) -> 0 | F37: =SUM(F29:F36) -> 0 | G37: =SUM(G29:G36) -> 0 | H37: =SUM(H29:H36) -> 0 | I37: =SUM(I29:I36) -> 0 | ... AF37: =SUM(AF29:AF36) -> 0 | AG37: =sum(B37:AF37) -> 0
A39: Units Sold (Gross) - Weatherflow
A40: Bird Buddy - Blue | K40: 1 | M40: 1 | AG40: =sum(B40:AF40) -> 2
A41: Bird Buddy - Yellow | K41: 0 | L41: 1 | M41: 1 | N41: 2 | AG41: =sum(B41:AF41) -> 4
A42: Bird Buddy with Solar Roof - Blue | H42: 3 | I42: 8 | M42: 2 | N42: 1 | R42: 1 | AG42: =sum(B42:AF42) -> 15
A43: Bird Buddy with Solar Roof - Yellow | I43: 1 | M43: 1 | AG43: =sum(B43:AF43) -> 2
A44: All Bird Buddy | B44: =SUM(B40:B43) -> 0 | C44: =SUM(C40:C43) -> 0 | D44: =SUM(D40:D43) -> 0 | E44: =SUM(E40:E43) -> 0 | F44: =SUM(F40:F43) -> 0 | G44: =SUM(G40:G43) -> 0 | H44: =SUM(H40:H43) -> 3 | I44: =SUM(I40:I43) -> 9 | ... AF44: =SUM(AF40:AF43) -> 0 | AG44: =sum(B44:AF44) -> 23
A46: Wall Mount | AG46: =sum(B46:AF46) -> 0
A47: Suet Ball Holder | AG47: =sum(B47:AF47) -> 0
A48: 3-in-1 Nutrition Set - Blue | AG48: =sum(B48:AF48) -> 0
A49: 3-in-1 Nutrition Set - Yellow | AG49: =sum(B49:AF49) -> 0
A50: Solar Roof Single - Blue | AG50: =sum(B50:AF50) -> 0
A51: Solar Roof Single - Yellow | AG51: =sum(B51:AF51) -> 0
A52: Perch Extender - Blue | AG52: =sum(B52:AF52) -> 0
A53: Perch Extender - Yellow | AG53: =sum(B53:AF53) -> 0
A54: All | B54: =SUM(B46:B53) -> 0 | C54: =SUM(C46:C53) -> 0 | D54: =SUM(D46:D53) -> 0 | E54: =SUM(E46:E53) -> 0 | F54: =SUM(F46:F53) -> 0 | G54: =SUM(G46:G53) -> 0 | H54: =SUM(H46:H53) -> 0 | I54: =SUM(I46:I53) -> 0 | ... AF54: =SUM(AF46:AF53) -> 0 | AG54: =sum(B54:AF54) -> 0
A56: Units Sold (Gross) - Best Buy
A57: Bird Buddy - Blue | AG57: =sum(B57:AF57) -> 0
A58: Bird Buddy - Yellow | AG58: =sum(B58:AF58) -> 0
A59: Bird Buddy with Solar Roof - Blue | B59: =Summary!B63 -> 9 | C59: =Summary!C63 -> 0 | D59: =Summary!D63 -> 13 | E59: =Summary!E63 -> 6 | F59: =Summary!F63 -> 0 | G59: =Summary!G63 -> 0 | H59: =Summary!H63 -> 12 | I59: =Summary!I63 -> 1 | ... W59: =Summary!W63 -> 9 | X59: 0 | Y59: =Summary!Y63 -> 1 | Z59: =Summary!Z63 -> 0 | AA59: =Summary!AA63 -> 0 | AB59: =Summary!AB63 -> 1 | AC59: =Summary!AC63 -> 6 | AD59: =Summary!AD63 -> 6 | AE59: =Summary!AE63 -> 6 | AF59: =Summary!AF63 -> 6 | AG59: =sum(B59:AF59) -> 134
A60: Bird Buddy with Solar Roof - Yellow | AG60: =sum(B60:AF60) -> 0
A61: All Bird Buddy | B61: =SUM(B57:B60) -> 9 | C61: =SUM(C57:C60) -> 0 | D61: =SUM(D57:D60) -> 13 | E61: =SUM(E57:E60) -> 6 | F61: =SUM(F57:F60) -> 0 | G61: =SUM(G57:G60) -> 0 | H61: =SUM(H57:H60) -> 12 | I61: =SUM(I57:I60) -> 1 | ... AF61: =SUM(AF57:AF60) -> 6 | AG61: =sum(B61:AF61) -> 134
A63: Wall Mount | AG63: =sum(B63:AF63) -> 0
A64: Suet Ball Holder | AG64: =sum(B64:AF64) -> 0
A65: 3-in-1 Nutrition Set - Blue | AG65: =sum(B65:AF65) -> 0
A66: 3-in-1 Nutrition Set - Yellow | AG66: =sum(B66:AF66) -> 0
A67: Solar Roof Single - Blue | AG67: =sum(B67:AF67) -> 0
A68: Solar Roof Single - Yellow | AG68: =sum(B68:AF68) -> 0
A69: Perch Extender - Blue | AG69: =sum(B69:AF69) -> 0
A70: Perch Extender - Yellow | AG70: =sum(B70:AF70) -> 0
A71: All | B71: =SUM(B63:B70) -> 0 | C71: =SUM(C63:C70) -> 0 | D71: =SUM(D63:D70) -> 0 | E71: =SUM(E63:E70) -> 0 | F71: =SUM(F63:F70) -> 0 | G71: =SUM(G63:G70) -> 0 | H71: =SUM(H63:H70) -> 0 | I71: =SUM(I63:I70) -> 0 | ... AF71: =SUM(AF63:AF70) -> 0 | AG71: =sum(B71:AF71) -> 0
A74: Units Sold (Gross) Total = Rachio + Weatherflow
A75: Bird Buddy - Blue | B75: 0 | C75: 0 | D75: 0 | E75: 0 | F75: 0 | G75: 0 | H75: 1 | I75: 1 | J75: 0 | K75: 2 | L75: 0 | M75: 3 | N75: 3 | O75: 0 | P75: 0 | Q75: 0 | R75: 0 | S75: 0 | T75: 0 | U75: 0 | V75: 0 | W75: 0 | X75: 0 | Y75: 0 | Z75: 0 | AA75: 0 | AB75: 0 | AG75: =sum(B75:AF75) -> 10
A76: Bird Buddy - Yellow | B76: 0 | C76: 0 | D76: 0 | E76: 0 | F76: 0 | G76: 0 | H76: 1 | I76: 1 | J76: 1 | K76: 0 | L76: 1 | M76: 2 | N76: 2 | O76: 0 | P76: 0 | Q76: 0 | R76: 0 | S76: 0 | T76: 0 | U76: 0 | V76: 0 | W76: 0 | X76: 0 | Y76: 0 | Z76: 0 | AA76: 0 | AB76: 0 | AG76: =sum(B76:AF76) -> 8
A77: Bird Buddy with Solar Roof - Blue | B77: 3 | C77: 0 | D77: 2 | E77: 1 | F77: 1 | G77: 0 | H77: 3 | I77: 10 | J77: 2 | K77: 2 | L77: 4 | M77: 66 | N77: 15 | O77: 0 | P77: 0 | Q77: 0 | R77: 2 | S77: 2 | T77: 0 | U77: 0 | V77: 0 | W77: 0 | X77: 0 | Y77: 0 | Z77: 0 | AA77: 0 | AB77: 0 | AG77: =sum(B77:AF77) -> 113
A78: Bird Buddy with Solar Roof - Yellow | B78: 3 | C78: 1 | D78: 0 | E78: 0 | F78: 0 | G78: 0 | H78: 0 | I78: 7 | J78: 0 | K78: 0 | L78: 0 | M78: 21 | N78: 9 | O78: 0 | P78: 0 | Q78: 0 | R78: 1 | S78: 0 | T78: 0 | U78: 0 | V78: 0 | W78: 0 | X78: 0 | Y78: 0 | Z78: 0 | AA78: 0 | AB78: 0 | AG78: =sum(B78:AF78) -> 42
A79: All Bird Buddy | B79: =SUM(B75:B78) -> 6 | C79: =SUM(C75:C78) -> 1 | D79: =SUM(D75:D78) -> 2 | E79: =SUM(E75:E78) -> 1 | F79: =SUM(F75:F78) -> 1 | G79: =SUM(G75:G78) -> 0 | H79: =SUM(H75:H78) -> 5 | I79: =SUM(I75:I78) -> 19 | ... AF79: =SUM(AF75:AF78) -> 0 | AG79: =sum(B79:AF79) -> 173
A81: Wall Mount | B81: 0 | C81: 0 | D81: 0 | E81: 0 | F81: 0 | G81: 0 | H81: 0 | I81: 0 | J81: 0 | K81: 0 | L81: 0 | M81: 0 | N81: 0 | O81: 0 | P81: 0 | Q81: 0 | R81: 0 | S81: 0 | T81: 0 | U81: 0 | V81: 0 | W81: 0 | X81: 0 | Y81: 0 | Z81: 0 | AA81: 0 | AB81: 0 | AG81: =sum(B81:AF81) -> 0
A82: Suet Ball Holder | B82: 0 | C82: 0 | D82: 0 | E82: 0 | F82: 0 | G82: 0 | H82: 0 | I82: 0 | J82: 0 | K82: 0 | L82: 0 | M82: 0 | N82: 0 | O82: 0 | P82: 0 | Q82: 0 | R82: 0 | S82: 0 | T82: 0 | U82: 0 | V82: 0 | W82: 0 | X82: 0 | Y82: 0 | Z82: 0 | AA82: 0 | AB82: 0 | AG82: =sum(B82:AF82) -> 0
A83: 3-in-1 Nutrition Set - Blue | B83: 0 | C83: 0 | D83: 0 | E83: 0 | F83: 0 | G83: 0 | H83: 0 | I83: 0 | J83: 0 | K83: 0 | L83: 0 | M83: 0 | N83: 0 | O83: 0 | P83: 0 | Q83: 0 | R83: 0 | S83: 0 | T83: 0 | U83: 0 | V83: 0 | W83: 0 | X83: 0 | Y83: 0 | Z83: 0 | AA83: 0 | AB83: 0 | AG83: =sum(B83:AF83) -> 0
A84: 3-in-1 Nutrition Set - Yellow | B84: 0 | C84: 0 | D84: 0 | E84: 0 | F84: 0 | G84: 0 | H84: 0 | I84: 0 | J84: 0 | K84: 0 | L84: 0 | M84: 0 | N84: 0 | O84: 0 | P84: 0 | Q84: 0 | R84: 0 | S84: 0 | T84: 0 | U84: 0 | V84: 0 | W84: 0 | X84: 0 | Y84: 0 | Z84: 0 | AA84: 0 | AB84: 0 | AG84: =sum(B84:AF84) -> 0
A85: Solar Roof Single - Blue | B85: 0 | C85: 0 | D85: 0 | E85: 0 | F85: 0 | G85: 0 | H85: 0 | I85: 0 | J85: 0 | K85: 0 | L85: 0 | M85: 0 | N85: 0 | O85: 0 | P85: 0 | Q85: 0 | R85: 0 | S85: 0 | T85: 0 | U85: 0 | V85: 0 | W85: 0 | X85: 0 | Y85: 0 | Z85: 0 | AA85: 0 | AB85: 0 | AG85: =sum(B85:AF85) -> 0
A86: Solar Roof Single - Yellow | B86: 0 | C86: 0 | D86: 0 | E86: 0 | F86: 0 | G86: 0 | H86: 0 | I86: 0 | J86: 0 | K86: 0 | L86: 0 | M86: 0 | N86: 0 | O86: 0 | P86: 0 | Q86: 0 | R86: 0 | S86: 0 | T86: 0 | U86: 0 | V86: 0 | W86: 0 | X86: 0 | Y86: 0 | Z86: 0 | AA86: 0 | AB86: 0 | AG86: =sum(B86:AF86) -> 0
A87: Perch Extender - Blue | B87: 0 | C87: 0 | D87: 0 | E87: 0 | F87: 0 | G87: 0 | H87: 0 | I87: 0 | J87: 0 | K87: 0 | L87: 0 | M87: 0 | N87: 0 | O87: 0 | P87: 0 | Q87: 0 | R87: 0 | S87: 0 | T87: 0 | U87: 0 | V87: 0 | W87: 0 | X87: 0 | Y87: 0 | Z87: 0 | AA87: 0 | AB87: 0 | AG87: =sum(B87:AF87) -> 0
A88: Perch Extender - Yellow | B88: 0 | C88: 0 | D88: 0 | E88: 0 | F88: 0 | G88: 0 | H88: 0 | I88: 0 | J88: 0 | K88: 0 | L88: 0 | M88: 0 | N88: 0 | O88: 0 | P88: 0 | Q88: 0 | R88: 0 | S88: 0 | T88: 0 | U88: 0 | V88: 0 | W88: 0 | X88: 0 | Y88: 0 | Z88: 0 | AA88: 0 | AB88: 0 | AG88: =sum(B88:AF88) -> 0
A89: All | B89: =SUM(B81:B88) -> 0 | C89: =SUM(C81:C88) -> 0 | D89: =SUM(D81:D88) -> 0 | E89: =SUM(E81:E88) -> 0 | F89: =SUM(F81:F88) -> 0 | G89: =SUM(G81:G88) -> 0 | H89: =SUM(H81:H88) -> 0 | I89: =SUM(I81:I88) -> 0 | ... AF89: =SUM(AF81:AF88) -> 0 | AG89: =sum(B89:AF89) -> 0
A92: Units Sold (Net) - Shopify
A93: Bird Buddy - Blue | B93: =(B23+B40)-B110-B138 -> 0 | C93: =(C23+C40)-C110-C138 -> 0 | D93: =(D23+D40)-D110-D138 -> 0 | E93: =(E23+E40)-E110-E138 -> 0 | F93: =(F23+F40)-F110-F138 -> 0 | G93: =(G23+G40)-G110-G138 -> -1 | H93: =(H23+H40)-H110-H138 -> 1 | I93: =(I23+I40)-I110-I138 -> 1 | ... AF93: =(AF23+AF40)-AF110-AF138 -> 0 | AG93: =sum(B93:AF93) -> 8
A94: Bird Buddy - Yellow | B94: =(B24+B41)-B111-B139 -> 0 | C94: =(C24+C41)-C111-C139 -> 0 | D94: =(D24+D41)-D111-D139 -> 0 | E94: =(E24+E41)-E111-E139 -> 0 | F94: =(F24+F41)-F111-F139 -> 0 | G94: =(G24+G41)-G111-G139 -> -1 | H94: =(H24+H41)-H111-H139 -> 1 | I94: =(I24+I41)-I111-I139 -> 1 | ... AF94: =(AF24+AF41)-AF111-AF139 -> 0 | AG94: =sum(B94:AF94) -> 7
A95: Bird Buddy with Solar Roof - Blue | B95: =(B25+B42)-B112-B140 -> 3 | C95: =(C25+C42)-C112-C140 -> 0 | D95: =(D25+D42)-D112-D140 -> 2 | E95: =(E25+E42)-E112-E140 -> 1 | F95: =(F25+F42)-F112-F140 -> 1 | G95: =(G25+G42)-G112-G140 -> -1 | H95: =(H25+H42)-H112-H140 -> 3 | I95: =(I25+I42)-I112-I140 -> 10 | ... AF95: =(AF25+AF42)-AF112-AF140 -> 0 | AG95: =sum(B95:AF95) -> 110
A96: Bird Buddy with Solar Roof - Yellow | B96: =(B26+B43)-B113-B141 -> 3 | C96: =(C26+C43)-C113-C141 -> 1 | D96: =(D26+D43)-D113-D141 -> 0 | E96: =(E26+E43)-E113-E141 -> 0 | F96: =(F26+F43)-F113-F141 -> 0 | G96: =(G26+G43)-G113-G141 -> 0 | H96: =(H26+H43)-H113-H141 -> 0 | I96: =(I26+I43)-I113-I141 -> 7 | ... AF96: =(AF26+AF43)-AF113-AF141 -> 0 | AG96: =sum(B96:AF96) -> 42
A97: All Bird Buddy | B97: =SUM(B93:B96) -> 6 | C97: =SUM(C93:C96) -> 1 | D97: =SUM(D93:D96) -> 2 | E97: =SUM(E93:E96) -> 1 | F97: =SUM(F93:F96) -> 1 | G97: =SUM(G93:G96) -> -3 | H97: =SUM(H93:H96) -> 5 | I97: =SUM(I93:I96) -> 19 | ... AF97: =SUM(AF93:AF96) -> 0 | AG97: =sum(B97:AF97) -> 167
A99: Wall Mount | B99: =(B29+B46)-B117-B145 -> 0 | C99: =(C29+C46)-C117-C145 -> 0 | D99: =(D29+D46)-D117-D145 -> 0 | E99: =(E29+E46)-E117-E145 -> 0 | F99: =(F29+F46)-F117-F145 -> 0 | G99: =(G29+G46)-G117-G145 -> 0 | H99: =(H29+H46)-H117-H145 -> 0 | I99: =(I29+I46)-I117-I145 -> 0 | ... AF99: =(AF29+AF46)-AF117-AF145 -> 0 | AG99: =sum(B99:AF99) -> -1
A100: Suet Ball Holder | B100: =(B30+B47)-B118-B146 -> 0 | C100: =(C30+C47)-C118-C146 -> 0 | D100: =(D30+D47)-D118-D146 -> 0 | E100: =(E30+E47)-E118-E146 -> 0 | F100: =(F30+F47)-F118-F146 -> 0 | G100: =(G30+G47)-G118-G146 -> 0 | H100: =(H30+H47)-H118-H146 -> 0 | I100: =(I30+I47)-I118-I146 -> 0 | ... AF100: =(AF30+AF47)-AF118-AF146 -> 0 | AG100: =sum(B100:AF100) -> -2
A101: 3-in-1 Nutrition Set - Blue | B101: =(B31+B48)-B119-B147 -> 0 | C101: =(C31+C48)-C119-C147 -> 0 | D101: =(D31+D48)-D119-D147 -> 0 | E101: =(E31+E48)-E119-E147 -> 0 | F101: =(F31+F48)-F119-F147 -> 0 | G101: =(G31+G48)-G119-G147 -> 0 | H101: =(H31+H48)-H119-H147 -> 0 | I101: =(I31+I48)-I119-I147 -> 0 | ... AF101: =(AF31+AF48)-AF119-AF147 -> 0 | AG101: =sum(B101:AF101) -> -1
A102: 3-in-1 Nutrition Set - Yellow | B102: =(B32-B49)-B120-B148 -> 0 | C102: =(C32-C49)-C120-C148 -> 0 | D102: =(D32-D49)-D120-D148 -> 0 | E102: =(E32-E49)-E120-E148 -> 0 | F102: =(F32-F49)-F120-F148 -> 0 | G102: =(G32-G49)-G120-G148 -> 0 | H102: =(H32-H49)-H120-H148 -> 0 | I102: =(I32-I49)-I120-I148 -> 0 | ... AF102: =(AF32-AF49)-AF120-AF148 -> 0 | AG102: =sum(B102:AF102) -> 0
A103: Solar Roof Single - Blue | B103: =(B33-B50)-B121-B149 -> 0 | C103: =(C33-C50)-C121-C149 -> 0 | D103: =(D33-D50)-D121-D149 -> 0 | E103: =(E33-E50)-E121-E149 -> 0 | F103: =(F33-F50)-F121-F149 -> 0 | G103: =(G33-G50)-G121-G149 -> -1 | H103: =(H33-H50)-H121-H149 -> 0 | I103: =(I33-I50)-I121-I149 -> 0 | ... AF103: =(AF33-AF50)-AF121-AF149 -> 0 | AG103: =sum(B103:AF103) -> -3
A104: Solar Roof Single - Yellow | B104: =(B34-B51)-B122-B150 -> 0 | C104: =(C34-C51)-C122-C150 -> 0 | D104: =(D34-D51)-D122-D150 -> 0 | E104: =(E34-E51)-E122-E150 -> 0 | F104: =(F34-F51)-F122-F150 -> 0 | G104: =(G34-G51)-G122-G150 -> 0 | H104: =(H34-H51)-H122-H150 -> 0 | I104: =(I34-I51)-I122-I150 -> 0 | ... AF104: =(AF34-AF51)-AF122-AF150 -> 0 | AG104: =sum(B104:AF104) -> 0
A105: Perch Extender - Blue | B105: =(B35-B52)-B123-B151 -> 0 | C105: =(C35-C52)-C123-C151 -> 0 | D105: =(D35-D52)-D123-D151 -> 0 | E105: =(E35-E52)-E123-E151 -> 0 | F105: =(F35-F52)-F123-F151 -> 0 | G105: =(G35-G52)-G123-G151 -> 0 | H105: =(H35-H52)-H123-H151 -> 0 | I105: =(I35-I52)-I123-I151 -> 0 | ... AF105: =(AF35-AF52)-AF123-AF151 -> 0 | AG105: =sum(B105:AF105) -> 0
A106: Perch Extender - Yellow | B106: =(B36-B53)-B124-B152 -> 0 | C106: =(C36-C53)-C124-C152 -> 0 | D106: =(D36-D53)-D124-D152 -> 0 | E106: =(E36-E53)-E124-E152 -> 0 | F106: =(F36-F53)-F124-F152 -> 0 | G106: =(G36-G53)-G124-G152 -> 0 | H106: =(H36-H53)-H124-H152 -> 0 | I106: =(I36-I53)-I124-I152 -> 0 | ... AF106: =(AF36-AF53)-AF124-AF152 -> 0 | AG106: =sum(B106:AF106) -> 0
A107: All | B107: =SUM(B99:B106) -> 0 | C107: =SUM(C99:C106) -> 0 | D107: =SUM(D99:D106) -> 0 | E107: =SUM(E99:E106) -> 0 | F107: =SUM(F99:F106) -> 0 | G107: =SUM(G99:G106) -> -1 | H107: =SUM(H99:H106) -> 0 | I107: =SUM(I99:I106) -> 0 | ... AF107: =SUM(AF99:AF106) -> 0 | AG107: =sum(B107:AF107) -> -7
A109: Units Cancelled by country (Gross) - Shopify
A110: Bird Buddy - Blue - NA (United States + Canada) | B110: 0 | C110: 0 | D110: 0 | E110: 0 | F110: 0 | G110: 0 | H110: 0 | I110: 0 | J110: 0 | K110: 0 | L110: 0 | M110: 0 | N110: 0 | O110: 0 | P110: 0 | Q110: 0 | R110: 0 | S110: 0 | T110: 0 | U110: 0 | V110: 0 | W110: 0 | X110: 0 | Y110: 0 | Z110: 0 | AA110: 0 | AB110: 0 | AG110: =SUM(B110:AF110) -> 0
A111: Bird Buddy - Yellow - NA (United States + Canada) | B111: 0 | C111: 0 | D111: 0 | E111: 0 | F111: 0 | G111: 0 | H111: 0 | I111: 0 | J111: 0 | K111: 0 | L111: 0 | M111: 0 | N111: 0 | O111: 0 | P111: 0 | Q111: 0 | R111: 0 | S111: 0 | T111: 0 | U111: 0 | V111: 0 | W111: 0 | X111: 0 | Y111: 0 | Z111: 0 | AA111: 0 | AB111: 0 | AG111: =SUM(B111:AF111) -> 0
A112: Bird Buddy with Solar Roof - Blue - NA (United States + Canada) | B112: 0 | C112: 0 | D112: 0 | E112: 0 | F112: 0 | G112: 1 | H112: 0 | I112: 0 | J112: 0 | K112: 0 | L112: 0 | M112: 0 | N112: 0 | O112: 0 | P112: 0 | Q112: 0 | R112: 0 | S112: 0 | T112: 0 | U112: 0 | V112: 0 | W112: 0 | X112: 0 | Y112: 0 | Z112: 0 | AA112: 0 | AB112: 0 | AG112: =SUM(B112:AF112) -> 1
A113: Bird Buddy with Solar Roof - Yellow - NA (United States + Canada) | B113: 0 | C113: 0 | D113: 0 | E113: 0 | F113: 0 | G113: 0 | H113: 0 | I113: 0 | J113: 0 | K113: 0 | L113: 0 | M113: 0 | N113: 0 | O113: 0 | P113: 0 | Q113: 0 | R113: 0 | S113: 0 | T113: 0 | U113: 0 | V113: 0 | W113: 0 | X113: 0 | Y113: 0 | Z113: 0 | AA113: 0 | AB113: 0 | AG113: =SUM(B113:AF113) -> 0
A114: All Bird Buddy | B114: =SUM(B110:B111) -> 0 | C114: =SUM(C110:C111) -> 0 | D114: =SUM(D110:D111) -> 0 | E114: =SUM(E110:E111) -> 0 | F114: =SUM(F110:F111) -> 0 | G114: =SUM(G110:G111) -> 0 | H114: =SUM(H110:H111) -> 0 | I114: =SUM(I110:I111) -> 0 | ... AF114: =SUM(AF110:AF111) -> 0 | AG114: =SUM(B114:AF114) -> 0
A115: All Bird Buddy with Solar Roof | B115: =SUM(B112:B113) -> 0 | C115: =SUM(C112:C113) -> 0 | D115: =SUM(D112:D113) -> 0 | E115: =SUM(E112:E113) -> 0 | F115: =SUM(F112:F113) -> 0 | G115: =SUM(G112:G113) -> 1 | H115: =SUM(H112:H113) -> 0 | I115: =SUM(I112:I113) -> 0 | ... AF115: =SUM(AF112:AF113) -> 0 | AG115: =SUM(B115:AF115) -> 1
...

Sheet PP - Data
A1: Post-purchase Survey | B1: 45292 | C1: 45293 | D1: 45294 | E1: 45295 | F1: 45296 | G1: 45297 | H1: 45298 | I1: 45299 | J1: 45300 | K1: 45301 | L1: 45302 | M1: 45303 | N1: 45304 | O1: 45305 | P1: 45306 | Q1: 45307 | R1: 45308 | S1: 45309 | T1: 45310 | U1: 45311 | V1: 45312 | W1: 45313 | X1: 45314 | Y1: 45315 | Z1: 45316 | AA1: 45317 | AB1: 45318 | AC1: 45319 | AD1: 45320 | AE1: 45321 | AF1: 45322 | AG1: Total | AH1: %
A2: Facebook / Instagram | B2: 23 | C2: 26 | D2: 37 | E2: 31 | F2: 34 | G2: 34 | H2: 41 | I2: 25 | J2: 23 | K2: 10 | L2: 24 | M2: 19 | N2: 18 | O2: 28 | P2: 14 | Q2: 12 | R2: 18 | S2: 15 | T2: 19 | U2: 21 | V2: 20 | W2: 16 | X2: 16 | Y2: 8 | Z2: 13 | AA2: 12 | AB2: 15 | AC2: 15 | AD2: 15 | AE2: 10 | AF2: 16 | AG2: =SUM(B2:AF2) -> 628 | AH2: =iferror(AG2/AG$10,"") -> 0.25435399
A3: Friends / Family | B3: 70 | C3: 56 | D3: 56 | E3: 48 | F3: 58 | G3: 63 | H3: 70 | I3: 54 | J3: 39 | K3: 37 | L3: 35 | M3: 55 | N3: 55 | O3: 50 | P3: 46 | Q3: 46 | R3: 51 | S3: 38 | T3: 44 | U3: 54 | V3: 39 | W3: 37 | X3: 35 | Y3: 38 | Z3: 34 | AA3: 36 | AB3: 34 | AC3: 35 | AD3: 44 | AE3: 26 | AF3: 14 | AG3: =SUM(B3:AF3) -> 1397 | AH3: =iferror(AG3/AG$10,"") -> 0.56581612
A4: TikTok | B4: 1 | C4: 2 | D4: 3 | E4: 1 | F4: 0 | G4: 1 | H4: 1 | I4: 1 | J4: 3 | K4: 1 | L4: 0 | M4: 0 | N4: 1 | O4: 1 | P4: 2 | Q4: 1 | R4: 1 | S4: 1 | T4: 6 | U4: 2 | V4: 0 | W4: 1 | X4: 0 | Y4: 0 | Z4: 2 | AA4: 2 | AB4: 1 | AC4: 1 | AD4: 1 | AE4: 0 | AF4: 0 | AG4: =SUM(B4:AF4) -> 37 | AH4: =iferror(AG4/AG$10,"") -> 0.014985824
A5: TV / Radio | B5: 1 | C5: 4 | D5: 2 | E5: 1 | F5: 6 | G5: 2 | H5: 3 | I5: 0 | J5: 0 | K5: 1 | L5: 2 | M5: 3 | N5: 3 | O5: 1 | P5: 3 | Q5: 1 | R5: 4 | S5: 0 | T5: 1 | U5: 1 | V5: 3 | W5: 3 | X5: 2 | Y5: 1 | Z5: 1 | AA5: 2 | AB5: 1 | AC5: 0 | AD5: 1 | AE5: 0 | AF5: 0 | AG5: =SUM(B5:AF5) -> 53 | AH5: =iferror(AG5/AG$10,"") -> 0.021466181
A6: Blog / Article | B6: 8 | C6: 1 | D6: 4 | E6: 5 | F6: 6 | G6: 6 | H6: 10 | I6: 6 | J6: 6 | K6: 2 | L6: 9 | M6: 6 | N6: 7 | O6: 7 | P6: 6 | Q6: 4 | R6: 5 | S6: 3 | T6: 1 | U6: 5 | V6: 6 | W6: 2 | X6: 3 | Y6: 3 | Z6: 3 | AA6: 1 | AB6: 4 | AC6: 7 | AD6: 2 | AE6: 3 | AF6: 2 | AG6: =SUM(B6:AF6) -> 143 | AH6: =iferror(AG6/AG$10,"") -> 0.057918185
A7: Reddit | B7: 0 | C7: 1 | D7: 4 | E7: 2 | F7: 0 | G7: 0 | H7: 1 | I7: 0 | J7: 0 | K7: 2 | L7: 1 | M7: 1 | N7: 1 | O7: 0 | P7: 1 | Q7: 0 | R7: 0 | S7: 1 | T7: 1 | U7: 1 | V7: 1 | W7: 0 | X7: 0 | Y7: 0 | Z7: 1 | AA7: 1 | AB7: 0 | AC7: 1 | AD7: 1 | AE7: 0 | AF7: 0 | AG7: =SUM(B7:AF7) -> 22 | AH7: =iferror(AG7/AG$10,"") -> 0.0089104901
A8: Google, Youtube | B8: 11 | C8: 11 | D8: 5 | E8: 7 | F8: 12 | G8: 8 | H8: 7 | I8: 7 | J8: 8 | K8: 7 | L8: 7 | M8: 3 | N8: 3 | O8: 10 | P8: 7 | Q8: 5 | R8: 4 | S8: 9 | T8: 5 | U8: 8 | V8: 3 | W8: 1 | X8: 3 | Y8: 5 | Z8: 4 | AA8: 2 | AB8: 5 | AC8: 5 | AD8: 5 | AE8: 3 | AF8: 2 | AG8: =SUM(B8:AF8) -> 182 | AH8: =iferror(AG8/AG$10,"") -> 0.073714054
A9: Yahoo, Bing | B9: 0 | C9: 0 | D9: 0 | E9: 0 | F9: 0 | G9: 1 | H9: 0 | I9: 0 | J9: 0 | K9: 0 | L9: 0 | M9: 0 | N9: 0 | O9: 0 | P9: 0 | Q9: 1 | R9: 1 | S9: 0 | T9: 0 | U9: 0 | V9: 0 | W9: 0 | X9: 0 | Y9: 0 | Z9: 1 | AA9: 0 | AB9: 1 | AC9: 0 | AD9: 1 | AE9: 1 | AF9: 0 | AG9: =SUM(B9:AF9) -> 7 | AH9: =iferror(AG9/AG$10,"") -> 0.0028351559
A10: Total submissions: | B10: =SUM(B2:B9) -> 114 | C10: =SUM(C2:C9) -> 101 | D10: =SUM(D2:D9) -> 111 | E10: =SUM(E2:E9) -> 95 | F10: =SUM(F2:F9) -> 116 | G10: =SUM(G2:G9) -> 115 | H10: =SUM(H2:H9) -> 133 | I10: =SUM(I2:I9) -> 93 | ... AF10: =SUM(AF2:AF9) -> 34 | AG10: =SUM(B10:AF10) -> 2469 | AH10: =SUM(AH2:AH9) -> 1
A11: Post-purchase Survey Percentage | B11: 45292 | C11: 45293 | D11: 45294 | E11: 45295 | F11: 45296 | G11: 45297 | H11: 45298 | I11: 45299 | J11: 45300 | K11: 45301 | L11: 45302 | M11: 45303 | N11: 45304 | O11: 45305 | P11: 45306 | Q11: 45307 | R11: 45308 | S11: 45309 | T11: 45310 | U11: 45311 | V11: 45312 | W11: 45313 | X11: 45314 | Y11: 45315 | Z11: 45316 | AA11: 45317 | AB11: 45318 | AC11: 45319 | AD11: 45320 | AE11: 45321 | AF11: 45322
A12: Facebook / Instagram | B12: =iferror(B2/B$10,"") -> 0.20175439 | C12: =iferror(C2/C$10,"") -> 0.25742574 | D12: =iferror(D2/D$10,"") -> 0.33333333 | E12: =iferror(E2/E$10,"") -> 0.32631579 | F12: =iferror(F2/F$10,"") -> 0.29310345 | G12: =iferror(G2/G$10,"") -> 0.29565217 | H12: =iferror(H2/H$10,"") -> 0.30827068 | I12: =iferror(I2/I$10,"") -> 0.2688172 | ... AF12: =iferror(AF2/AF$10,"") -> 0.47058824
A13: Friends / Family | B13: =iferror(B3/B$10,"") -> 0.61403509 | C13: =iferror(C3/C$10,"") -> 0.55445545 | D13: =iferror(D3/D$10,"") -> 0.5045045 | E13: =iferror(E3/E$10,"") -> 0.50526316 | F13: =iferror(F3/F$10,"") -> 0.5 | G13: =iferror(G3/G$10,"") -> 0.54782609 | H13: =iferror(H3/H$10,"") -> 0.52631579 | I13: =iferror(I3/I$10,"") -> 0.58064516 | ... AF13: =iferror(AF3/AF$10,"") -> 0.41176471
A14: TikTok | B14: =iferror(B4/B$10,"") -> 0.0087719298 | C14: =iferror(C4/C$10,"") -> 0.01980198 | D14: =iferror(D4/D$10,"") -> 0.027027027 | E14: =iferror(E4/E$10,"") -> 0.010526316 | F14: =iferror(F4/F$10,"") -> 0 | G14: =iferror(G4/G$10,"") -> 0.0086956522 | H14: =iferror(H4/H$10,"") -> 0.007518797 | I14: =iferror(I4/I$10,"") -> 0.010752688 | ... AF14: =iferror(AF4/AF$10,"") -> 0
A15: TV / Radio | B15: =iferror(B5/B$10,"") -> 0.0087719298 | C15: =iferror(C5/C$10,"") -> 0.03960396 | D15: =iferror(D5/D$10,"") -> 0.018018018 | E15: =iferror(E5/E$10,"") -> 0.010526316 | F15: =iferror(F5/F$10,"") -> 0.051724138 | G15: =iferror(G5/G$10,"") -> 0.017391304 | H15: =iferror(H5/H$10,"") -> 0.022556391 | I15: =iferror(I5/I$10,"") -> 0 | ... AF15: =iferror(AF5/AF$10,"") -> 0
A16: Blog / Article | B16: =iferror(B6/B$10,"") -> 0.070175439 | C16: =iferror(C6/C$10,"") -> 0.0099009901 | D16: =iferror(D6/D$10,"") -> 0.036036036 | E16: =iferror(E6/E$10,"") -> 0.052631579 | F16: =iferror(F6/F$10,"") -> 0.051724138 | G16: =iferror(G6/G$10,"") -> 0.052173913 | H16: =iferror(H6/H$10,"") -> 0.07518797 | I16: =iferror(I6/I$10,"") -> 0.064516129 | ... AF16: =iferror(AF6/AF$10,"") -> 0.058823529
A17: Reddit | B17: =iferror(B7/B$10,"") -> 0 | C17: =iferror(C7/C$10,"") -> 0.0099009901 | D17: =iferror(D7/D$10,"") -> 0.036036036 | E17: =iferror(E7/E$10,"") -> 0.021052632 | F17: =iferror(F7/F$10,"") -> 0 | G17: =iferror(G7/G$10,"") -> 0 | H17: =iferror(H7/H$10,"") -> 0.007518797 | I17: =iferror(I7/I$10,"") -> 0 | ... AF17: =iferror(AF7/AF$10,"") -> 0
A18: Google, Youtube | B18: =iferror(B8/B$10,"") -> 0.096491228 | C18: =iferror(C8/C$10,"") -> 0.10891089 | D18: =iferror(D8/D$10,"") -> 0.045045045 | E18: =iferror(E8/E$10,"") -> 0.073684211 | F18: =iferror(F8/F$10,"") -> 0.10344828 | G18: =iferror(G8/G$10,"") -> 0.069565217 | H18: =iferror(H8/H$10,"") -> 0.052631579 | I18: =iferror(I8/I$10,"") -> 0.075268817 | ... AF18: =iferror(AF8/AF$10,"") -> 0.058823529
A19: Yahoo, Bing | B19: =iferror(B9/B$10,"") -> 0 | C19: =iferror(C9/C$10,"") -> 0 | D19: =iferror(D9/D$10,"") -> 0 | E19: =iferror(E9/E$10,"") -> 0 | F19: =iferror(F9/F$10,"") -> 0 | G19: =iferror(G9/G$10,"") -> 0.0086956522 | H19: =iferror(H9/H$10,"") -> 0 | I19: =iferror(I9/I$10,"") -> 0 | ... AF19: =iferror(AF9/AF$10,"") -> 0
A22: Where on FB/IG have you heard about Bird Buddy? | B22: 45292 | C22: 45293 | D22: 45294 | E22: 45295 | F22: 45296 | G22: 45297 | H22: 45298 | I22: 45299 | J22: 45300 | K22: 45301 | L22: 45302 | M22: 45303 | N22: 45304 | O22: 45305 | P22: 45306 | Q22: 45307 | R22: 45308 | S22: 45309 | T22: 45310 | U22: 45311 | V22: 45312 | W22: 45313 | X22: 45314 | Y22: 45315 | Z22: 45316 | AA22: 45317 | AB22: 45318 | AC22: 45319 | AD22: 45320 | AE22: 45321 | AF22: 45322
A23: I saw an ad | B23: 18 | C23: 22 | D23: 22 | E23: 22 | F23: 27 | G23: 20 | H23: 31 | I23: 19 | J23: 17 | K23: 9 | L23: 20 | M23: 16 | N23: 13 | O23: 23 | P23: 10 | Q23: 7 | R23: 13 | S23: 8 | T23: 16 | U23: 12 | V23: 14 | W23: 11 | X23: 13 | Y23: 4 | Z23: 7 | AA23: 9 | AB23: 11 | AC23: 11 | AD23: 10 | AE23: 6 | AF23: 14 | AG23: =SUM(B23:AF23) -> 455 | AH23: =iferror(AG23/AG$26,"") -> 0.72452229
A24: I saw a post about Bird Buddy on my friend's feed | B24: 1 | C24: 2 | D24: 8 | E24: 7 | F24: 4 | G24: 9 | H24: 5 | I24: 2 | J24: 2 | K24: 1 | L24: 3 | M24: 1 | N24: 0 | O24: 3 | P24: 3 | Q24: 0 | R24: 5 | S24: 2 | T24: 1 | U24: 7 | V24: 1 | W24: 1 | X24: 3 | Y24: 2 | Z24: 3 | AA24: 1 | AB24: 4 | AC24: 2 | AD24: 3 | AE24: 3 | AF24: 1 | AG24: =SUM(B24:AF24) -> 90 | AH24: =iferror(AG24/AG$26,"") -> 0.1433121
A25: I saw an organic post from Bird Buddy | B25: 4 | C25: 2 | D25: 7 | E25: 2 | F25: 3 | G25: 5 | H25: 5 | I25: 4 | J25: 4 | K25: 0 | L25: 1 | M25: 2 | N25: 5 | O25: 2 | P25: 1 | Q25: 5 | R25: 0 | S25: 5 | T25: 2 | U25: 2 | V25: 5 | W25: 4 | X25: 0 | Y25: 2 | Z25: 3 | AA25: 2 | AB25: 0 | AC25: 2 | AD25: 2 | AE25: 1 | AF25: 1 | AG25: =SUM(B25:AF25) -> 83 | AH25: =iferror(AG25/AG$26,"") -> 0.13216561
A26: Total submissions: | B26: =SUM(B23:B25) -> 23 | C26: =SUM(C23:C25) -> 26 | D26: =SUM(D23:D25) -> 37 | E26: =SUM(E23:E25) -> 31 | F26: =SUM(F23:F25) -> 34 | G26: =SUM(G23:G25) -> 34 | H26: =SUM(H23:H25) -> 41 | I26: =SUM(I23:I25) -> 25 | ... AF26: =SUM(AF23:AF25) -> 16 | AG26: =SUM(B26:AF26) -> 628 | AH26: =SUM(AH23:AH25) -> 1
A27: % Where on FB/IG have you heard about Bird Buddy? | B27: 45292 | C27: 45293 | D27: 45294 | E27: 45295 | F27: 45296 | G27: 45297 | H27: 45298 | I27: 45299 | J27: 45300 | K27: 45301 | L27: 45302 | M27: 45303 | N27: 45304 | O27: 45305 | P27: 45306 | Q27: 45307 | R27: 45308 | S27: 45309 | T27: 45310 | U27: 45311 | V27: 45312 | W27: 45313 | X27: 45314 | Y27: 45315 | Z27: 45316 | AA27: 45317 | AB27: 45318 | AC27: 45319 | AD27: 45320 | AE27: 45321 | AF27: 45322
A28: I saw an ad | B28: =iferror(B23/B$26,"") -> 0.7826087 | C28: =iferror(C23/C$26,"") -> 0.84615385 | D28: =iferror(D23/D$26,"") -> 0.59459459 | E28: =iferror(E23/E$26,"") -> 0.70967742 | F28: =iferror(F23/F$26,"") -> 0.79411765 | G28: =iferror(G23/G$26,"") -> 0.58823529 | H28: =iferror(H23/H$26,"") -> 0.75609756 | I28: =iferror(I23/I$26,"") -> 0.76 | ... AF28: =iferror(AF23/AF$26,"") -> 0.875
A29: I saw a post about Bird Buddy on my friend's feed | B29: =iferror(B24/B$26,"") -> 0.043478261 | C29: =iferror(C24/C$26,"") -> 0.076923077 | D29: =iferror(D24/D$26,"") -> 0.21621622 | E29: =iferror(E24/E$26,"") -> 0.22580645 | F29: =iferror(F24/F$26,"") -> 0.11764706 | G29: =iferror(G24/G$26,"") -> 0.26470588 | H29: =iferror(H24/H$26,"") -> 0.12195122 | I29: =iferror(I24/I$26,"") -> 0.08 | ... AF29: =iferror(AF24/AF$26,"") -> 0.0625
A30: I saw an organic post from Bird Buddy | B30: =iferror(B25/B$26,"") -> 0.17391304 | C30: =iferror(C25/C$26,"") -> 0.076923077 | D30: =iferror(D25/D$26,"") -> 0.18918919 | E30: =iferror(E25/E$26,"") -> 0.064516129 | F30: =iferror(F25/F$26,"") -> 0.088235294 | G30: =iferror(G25/G$26,"") -> 0.14705882 | H30: =iferror(H25/H$26,"") -> 0.12195122 | I30: =iferror(I25/I$26,"") -> 0.16 | ... AF30: =iferror(AF25/AF$26,"") -> 0.0625
A35: Who is this for? (sub-question 3) | B35: 45292 | C35: 45293 | D35: 45294 | E35: 45295 | F35: 45296 | G35: 45297 | H35: 45298 | I35: 45299 | J35: 45300 | K35: 45301 | L35: 45302 | M35: 45303 | N35: 45304 | O35: 45305 | P35: 45306 | Q35: 45307 | R35: 45308 | S35: 45309 | T35: 45310 | U35: 45311 | V35: 45312 | W35: 45313 | X35: 45314 | Y35: 45315 | Z35: 45316 | AA35: 45317 | AB35: 45318 | AC35: 45319 | AD35: 45320 | AE35: 45321 | AF35: 45322
A36: Just me | B36: =B41 -> 37 | C36: =C41 -> 31 | D36: =D41 -> 33 | E36: =E41 -> 29 | F36: =F41 -> 38 | G36: =G41 -> 35 | H36: =H41 -> 37 | I36: =I41 -> 27 | ... AF36: =AF41 -> 11
A37: How important do you find acquiring knowledge in bird feeding?
A38: Very, I love learning about birds | B38: 21 | C38: 25 | D38: 19 | E38: 16 | F38: 27 | G38: 30 | H38: 24 | I38: 16 | J38: 16 | K38: 7 | L38: 13 | M38: 15 | N38: 15 | O38: 28 | P38: 13 | Q38: 15 | R38: 17 | S38: 11 | T38: 17 | U38: 13 | V38: 15 | W38: 17 | X38: 12 | Y38: 6 | Z38: 12 | AA38: 10 | AB38: 6 | AC38: 16 | AD38: 11 | AE38: 7 | AF38: 4 | AG38: =SUM(B38:AF38) -> 474 | AH38: =iferror(AG38/AG$41,"") -> 0.66854725
A39: It's not the main point for me, but nice | B39: 15 | C39: 5 | D39: 13 | E39: 11 | F39: 11 | G39: 3 | H39: 13 | I39: 9 | J39: 7 | K39: 2 | L39: 5 | M39: 7 | N39: 11 | O39: 6 | P39: 4 | Q39: 3 | R39: 3 | S39: 5 | T39: 7 | U39: 8 | V39: 15 | W39: 1 | X39: 4 | Y39: 6 | Z39: 3 | AA39: 5 | AB39: 3 | AC39: 6 | AD39: 4 | AE39: 4 | AF39: 6 | AG39: =SUM(B39:AF39) -> 205 | AH39: =iferror(AG39/AG$41,"") -> 0.28913963
A40: Not at all | B40: 1 | C40: 1 | D40: 1 | E40: 2 | F40: 0 | G40: 2 | H40: 0 | I40: 2 | J40: 0 | K40: 3 | L40: 1 | M40: 1 | N40: 1 | O40: 1 | P40: 0 | Q40: 4 | R40: 0 | S40: 1 | T40: 0 | U40: 0 | V40: 0 | W40: 2 | X40: 1 | Y40: 1 | Z40: 1 | AA40: 1 | AB40: 0 | AC40: 1 | AD40: 0 | AE40: 1 | AF40: 1 | AG40: =SUM(B40:AF40) -> 30 | AH40: =iferror(AG40/AG$41,"") -> 0.042313117
A41: Total submissions: | B41: =SUM(B38:B40) -> 37 | C41: =SUM(C38:C40) -> 31 | D41: =SUM(D38:D40) -> 33 | E41: =SUM(E38:E40) -> 29 | F41: =SUM(F38:F40) -> 38 | G41: =SUM(G38:G40) -> 35 | H41: =SUM(H38:H40) -> 37 | I41: =SUM(I38:I40) -> 27 | ... AF41: =SUM(AF38:AF40) -> 11 | AG41: =SUM(B41:AF41) -> 709 | AH41: =SUM(AH38:AH40) -> 1
A42: I will use with my family | B42: =B47 -> 36 | C42: =C47 -> 28 | D42: =D47 -> 31 | E42: =E47 -> 21 | F42: =F47 -> 34 | G42: =G47 -> 42 | H42: =H47 -> 52 | I42: =I47 -> 25 | ... AF42: =AF47 -> 9
A43: How important do you find acquiring knowledge in bird feeding?
A44: Very, I love learning about birds | B44: 27 | C44: 18 | D44: 18 | E44: 11 | F44: 19 | G44: 33 | H44: 35 | I44: 12 | J44: 15 | K44: 15 | L44: 13 | M44: 19 | N44: 24 | O44: 22 | P44: 19 | Q44: 17 | R44: 9 | S44: 14 | T44: 18 | U44: 22 | V44: 9 | W44: 15 | X44: 15 | Y44: 12 | Z44: 11 | AA44: 14 | AB44: 15 | AC44: 11 | AD44: 12 | AE44: 4 | AF44: 6 | AG44: =SUM(B44:AF44) -> 504 | AH44: =iferror(AG44/AG$47,"") -> 0.65539662
A45: It's not the main point for me, but nice | B45: 7 | C45: 9 | D45: 10 | E45: 8 | F45: 13 | G45: 9 | H45: 13 | I45: 8 | J45: 6 | K45: 6 | L45: 6 | M45: 12 | N45: 8 | O45: 11 | P45: 4 | Q45: 10 | R45: 10 | S45: 8 | T45: 8 | U45: 13 | V45: 4 | W45: 2 | X45: 3 | Y45: 6 | Z45: 2 | AA45: 8 | AB45: 6 | AC45: 4 | AD45: 8 | AE45: 1 | AF45: 3 | AG45: =SUM(B45:AF45) -> 226 | AH45: =iferror(AG45/AG$47,"") -> 0.29388817
A46: Not at all | B46: 2 | C46: 1 | D46: 3 | E46: 2 | F46: 2 | G46: 0 | H46: 4 | I46: 5 | J46: 0 | K46: 0 | L46: 3 | M46: 0 | N46: 3 | O46: 2 | P46: 0 | Q46: 1 | R46: 3 | S46: 1 | T46: 0 | U46: 0 | V46: 2 | W46: 0 | X46: 1 | Y46: 1 | Z46: 1 | AA46: 0 | AB46: 1 | AC46: 0 | AD46: 1 | AE46: 0 | AF46: 0 | AG46: =SUM(B46:AF46) -> 39 | AH46: =iferror(AG46/AG$47,"") -> 0.050715215
A47: Total submissions: | B47: =SUM(B44:B46) -> 36 | C47: =SUM(C44:C46) -> 28 | D47: =SUM(D44:D46) -> 31 | E47: =SUM(E44:E46) -> 21 | F47: =SUM(F44:F46) -> 34 | G47: =SUM(G44:G46) -> 42 | H47: =SUM(H44:H46) -> 52 | I47: =SUM(I44:I46) -> 25 | ... AF47: =SUM(AF44:AF46) -> 9 | AG47: =SUM(B47:AF47) -> 769 | AH47: =SUM(AH44:AH46) -> 1
A48: My parents | B48: =B53 -> 21 | C48: =C53 -> 21 | D48: =D53 -> 22 | E48: =E53 -> 21 | F48: =F53 -> 21 | G48: =G53 -> 21 | H48: =H53 -> 18 | I48: =I53 -> 22 | ... AF48: =AF53 -> 5
A49: How important do you find acquiring knowledge in bird feeding?
A50: Very, I love learning about birds | B50: 11 | C50: 7 | D50: 12 | E50: 8 | F50: 9 | G50: 7 | H50: 6 | I50: 8 | J50: 8 | K50: 6 | L50: 10 | M50: 2 | N50: 4 | O50: 10 | P50: 6 | Q50: 5 | R50: 8 | S50: 5 | T50: 4 | U50: 9 | V50: 4 | W50: 4 | X50: 8 | Y50: 3 | Z50: 7 | AA50: 5 | AB50: 11 | AC50: 4 | AD50: 7 | AE50: 2 | AF50: 4 | AG50: =SUM(B50:AF50) -> 204 | AH50: =iferror(AG50/AG$53,"") -> 0.4214876
A51: It's not the main point for me, but nice | B51: 9 | C51: 10 | D51: 8 | E51: 8 | F51: 8 | G51: 8 | H51: 9 | I51: 14 | J51: 7 | K51: 4 | L51: 9 | M51: 6 | N51: 8 | O51: 4 | P51: 12 | Q51: 2 | R51: 5 | S51: 6 | T51: 6 | U51: 7 | V51: 5 | W51: 6 | X51: 6 | Y51: 7 | Z51: 6 | AA51: 3 | AB51: 4 | AC51: 10 | AD51: 4 | AE51: 4 | AF51: 1 | AG51: =SUM(B51:AF51) -> 206 | AH51: =iferror(AG51/AG$53,"") -> 0.42561983
A52: Not at all | B52: 1 | C52: 4 | D52: 2 | E52: 5 | F52: 4 | G52: 6 | H52: 3 | I52: 0 | J52: 0 | K52: 5 | L52: 2 | M52: 3 | N52: 2 | O52: 0 | P52: 3 | Q52: 2 | R52: 4 | S52: 4 | T52: 1 | U52: 2 | V52: 2 | W52: 4 | X52: 0 | Y52: 3 | Z52: 4 | AA52: 1 | AB52: 1 | AC52: 2 | AD52: 1 | AE52: 3 | AF52: 0 | AG52: =SUM(B52:AF52) -> 74 | AH52: =iferror(AG52/AG$53,"") -> 0.15289256
A53: Total submissions: | B53: =SUM(B50:B52) -> 21 | C53: =SUM(C50:C52) -> 21 | D53: =SUM(D50:D52) -> 22 | E53: =SUM(E50:E52) -> 21 | F53: =SUM(F50:F52) -> 21 | G53: =SUM(G50:G52) -> 21 | H53: =SUM(H50:H52) -> 18 | I53: =SUM(I50:I52) -> 22 | ... AF53: =SUM(AF50:AF52) -> 5 | AG53: =SUM(B53:AF53) -> 484 | AH53: =SUM(AH50:AH52) -> 1
A54: Spouse | B54: =B59 -> 21 | C54: =C59 -> 20 | D54: =D59 -> 25 | E54: =E59 -> 24 | F54: =F59 -> 24 | G54: =G59 -> 17 | H54: =H59 -> 25 | I54: =I59 -> 20 | ... AF54: =AF59 -> 9
A55: How important do you find acquiring knowledge in bird feeding?
A56: Very, I love learning about birds | B56: 6 | C56: 6 | D56: 6 | E56: 9 | F56: 10 | G56: 11 | H56: 9 | I56: 8 | J56: 9 | K56: 3 | L56: 11 | M56: 14 | N56: 11 | O56: 6 | P56: 10 | Q56: 6 | R56: 15 | S56: 8 | T56: 8 | U56: 7 | V56: 6 | W56: 4 | X56: 3 | Y56: 3 | Z56: 7 | AA56: 5 | AB56: 9 | AC56: 7 | AD56: 8 | AE56: 10 | AF56: 2 | AG56: =SUM(B56:AF56) -> 237 | AH56: =iferror(AG56/AG$59,"") -> 0.46745562
A57: It's not the main point for me, but nice | B57: 12 | C57: 8 | D57: 17 | E57: 12 | F57: 13 | G57: 5 | H57: 11 | I57: 10 | J57: 10 | K57: 8 | L57: 3 | M57: 7 | N57: 0 | O57: 6 | P57: 6 | Q57: 5 | R57: 9 | S57: 4 | T57: 7 | U57: 9 | V57: 10 | W57: 5 | X57: 4 | Y57: 3 | Z57: 3 | AA57: 3 | AB57: 6 | AC57: 3 | AD57: 8 | AE57: 4 | AF57: 7 | AG57: =SUM(B57:AF57) -> 218 | AH57: =iferror(AG57/AG$59,"") -> 0.42998028
A58: Not at all | B58: 3 | C58: 6 | D58: 2 | E58: 3 | F58: 1 | G58: 1 | H58: 5 | I58: 2 | J58: 1 | K58: 0 | L58: 2 | M58: 1 | N58: 2 | O58: 1 | P58: 1 | Q58: 0 | R58: 1 | S58: 0 | T58: 1 | U58: 2 | V58: 0 | W58: 0 | X58: 2 | Y58: 4 | Z58: 2 | AA58: 1 | AB58: 0 | AC58: 1 | AD58: 4 | AE58: 3 | AF58: 0 | AG58: =SUM(B58:AF58) -> 52 | AH58: =iferror(AG58/AG$59,"") -> 0.1025641
A59: Total submissions: | B59: =SUM(B56:B58) -> 21 | C59: =SUM(C56:C58) -> 20 | D59: =SUM(D56:D58) -> 25 | E59: =SUM(E56:E58) -> 24 | F59: =SUM(F56:F58) -> 24 | G59: =SUM(G56:G58) -> 17 | H59: =SUM(H56:H58) -> 25 | I59: =SUM(I56:I58) -> 20 | ... AF59: =SUM(AF56:AF58) -> 9 | AG59: =SUM(B59:AF59) -> 507 | AH59: =SUM(AH56:AH58) -> 1
A60: Total submissions: | B60: =SUM(B36,B42,B48,B54) -> 115 | C60: =SUM(C36,C42,C48,C54) -> 100 | D60: =SUM(D36,D42,D48,D54) -> 111 | E60: =SUM(E36,E42,E48,E54) -> 95 | F60: =SUM(F36,F42,F48,F54) -> 117 | G60: =SUM(G36,G42,G48,G54) -> 115 | H60: =SUM(H36,H42,H48,H54) -> 132 | I60: =SUM(I36,I42,I48,I54) -> 94 | ... AF60: =SUM(AF36,AF42,AF48,AF54) -> 34
A61: % Who is this for? (sub-question 3) | B61: 45292 | C61: 45293 | D61: 45294 | E61: 45295 | F61: 45296 | G61: 45297 | H61: 45298 | I61: 45299 | J61: 45300 | K61: 45301 | L61: 45302 | M61: 45303 | N61: 45304 | O61: 45305 | P61: 45306 | Q61: 45307 | R61: 45308 | S61: 45309 | T61: 45310 | U61: 45311 | V61: 45312 | W61: 45313 | X61: 45314 | Y61: 45315 | Z61: 45316 | AA61: 45317 | AB61: 45318 | AC61: 45319 | AD61: 45320 | AE61: 45321 | AF61: 45322
A62: Just me | B62: =iferror(B36/B$60,"") -> 0.32173913 | C62: =iferror(C36/C$60,"") -> 0.31 | D62: =iferror(D36/D$60,"") -> 0.2972973 | E62: =iferror(E36/E$60,"") -> 0.30526316 | F62: =iferror(F36/F$60,"") -> 0.32478632 | G62: =iferror(G36/G$60,"") -> 0.30434783 | H62: =iferror(H36/H$60,"") -> 0.28030303 | I62: =iferror(I36/I$60,"") -> 0.28723404 | ... AF62: =iferror(AF36/AF$60,"") -> 0.32352941
A63: How important do you find acquiring knowledge in bird feeding?
A64: Very, I love learning about birds | B64: =iferror(B38/B$41,"") -> 0.56756757 | C64: =iferror(C38/C$41,"") -> 0.80645161 | D64: =iferror(D38/D$41,"") -> 0.57575758 | E64: =iferror(E38/E$41,"") -> 0.55172414 | F64: =iferror(F38/F$41,"") -> 0.71052632 | G64: =iferror(G38/G$41,"") -> 0.85714286 | H64: =iferror(H38/H$41,"") -> 0.64864865 | I64: =iferror(I38/I$41,"") -> 0.59259259 | ... AF64: =iferror(AF38/AF$41,"") -> 0.36363636
A65: It's not the main point for me, but nice | B65: =iferror(B39/B$41,"") -> 0.40540541 | C65: =iferror(C39/C$41,"") -> 0.16129032 | D65: =iferror(D39/D$41,"") -> 0.39393939 | E65: =iferror(E39/E$41,"") -> 0.37931034 | F65: =iferror(F39/F$41,"") -> 0.28947368 | G65: =iferror(G39/G$41,"") -> 0.085714286 | H65: =iferror(H39/H$41,"") -> 0.35135135 | I65: =iferror(I39/I$41,"") -> 0.33333333 | ... AF65: =iferror(AF39/AF$41,"") -> 0.54545455
A66: Not at all | B66: =iferror(B40/B$41,"") -> 0.027027027 | C66: =iferror(C40/C$41,"") -> 0.032258065 | D66: =iferror(D40/D$41,"") -> 0.03030303 | E66: =iferror(E40/E$41,"") -> 0.068965517 | F66: =iferror(F40/F$41,"") -> 0 | G66: =iferror(G40/G$41,"") -> 0.057142857 | H66: =iferror(H40/H$41,"") -> 0 | I66: =iferror(I40/I$41,"") -> 0.074074074 | ... AF66: =iferror(AF40/AF$41,"") -> 0.090909091
H67: =iferror(H41/#REF!,"") | I67: =iferror(I41/#REF!,"") | J67: =iferror(J41/#REF!,"") | K67: =iferror(K41/#REF!,"") | L67: =iferror(L41/#REF!,"") | M67: =iferror(M41/#REF!,"") | N67: =iferror(N41/#REF!,"") | O67: =iferror(O41/#REF!,"") | ... AF67: =iferror(AF41/#REF!,"")
A68: I will use with my family | B68: =iferror(B42/B$60,"") -> 0.31304348 | C68: =iferror(C42/C$60,"") -> 0.28 | D68: =iferror(D42/D$60,"") -> 0.27927928 | E68: =iferror(E42/E$60,"") -> 0.22105263 | F68: =iferror(F42/F$60,"") -> 0.29059829 | G68: =iferror(G42/G$60,"") -> 0.36521739 | H68: =iferror(H42/H$60,"") -> 0.39393939 | I68: =iferror(I42/I$60,"") -> 0.26595745 | ... AF68: =iferror(AF42/AF$60,"") -> 0.26470588
A69: How important do you find acquiring knowledge in bird feeding?
A70: Very, I love learning about birds | B70: =iferror(B44/B$47,"") -> 0.75 | C70: =iferror(C44/C$47,"") -> 0.64285714 | D70: =iferror(D44/D$47,"") -> 0.58064516 | E70: =iferror(E44/E$47,"") -> 0.52380952 | F70: =iferror(F44/F$47,"") -> 0.55882353 | G70: =iferror(G44/G$47,"") -> 0.78571429 | H70: =iferror(H44/H$47,"") -> 0.67307692 | I70: =iferror(I44/I$47,"") -> 0.48 | ... AF70: =iferror(AF44/AF$47,"") -> 0.66666667
A71: It's not the main point for me, but nice | B71: =iferror(B45/B$47,"") -> 0.19444444 | C71: =iferror(C45/C$47,"") -> 0.32142857 | D71: =iferror(D45/D$47,"") -> 0.32258065 | E71: =iferror(E45/E$47,"") -> 0.38095238 | F71: =iferror(F45/F$47,"") -> 0.38235294 | G71: =iferror(G45/G$47,"") -> 0.21428571 | H71: =iferror(H45/H$47,"") -> 0.25 | I71: =iferror(I45/I$47,"") -> 0.32 | ... AF71: =iferror(AF45/AF$47,"") -> 0.33333333
A72: Not at all | B72: =iferror(B46/B$47,"") -> 0.055555556 | C72: =iferror(C46/C$47,"") -> 0.035714286 | D72: =iferror(D46/D$47,"") -> 0.096774194 | E72: =iferror(E46/E$47,"") -> 0.095238095 | F72: =iferror(F46/F$47,"") -> 0.058823529 | G72: =iferror(G46/G$47,"") -> 0 | H72: =iferror(H46/H$47,"") -> 0.076923077 | I72: =iferror(I46/I$47,"") -> 0.2 | ... AF72: =iferror(AF46/AF$47,"") -> 0
A74: My parents | B74: =iferror(B48/B$60,"") -> 0.1826087 | C74: =iferror(C48/C$60,"") -> 0.21 | D74: =iferror(D48/D$60,"") -> 0.1981982 | E74: =iferror(E48/E$60,"") -> 0.22105263 | F74: =iferror(F48/F$60,"") -> 0.17948718 | G74: =iferror(G48/G$60,"") -> 0.1826087 | H74: =iferror(H48/H$60,"") -> 0.13636364 | I74: =iferror(I48/I$60,"") -> 0.23404255 | ... AF74: =iferror(AF48/AF$60,"") -> 0.14705882
A75: How important do you find acquiring knowledge in bird feeding?
A76: Very, I love learning about birds | B76: =iferror(B50/B$53,"") -> 0.52380952 | C76: =iferror(C50/C$53,"") -> 0.33333333 | D76: =iferror(D50/D$53,"") -> 0.54545455 | E76: =iferror(E50/E$53,"") -> 0.38095238 | F76: =iferror(F50/F$53,"") -> 0.42857143 | G76: =iferror(G50/G$53,"") -> 0.33333333 | H76: =iferror(H50/H$53,"") -> 0.33333333 | I76: =iferror(I50/I$53,"") -> 0.36363636 | ... AF76: =iferror(AF50/AF$53,"") -> 0.8
A77: It's not the main point for me, but nice | B77: =iferror(B51/B$53,"") -> 0.42857143 | C77: =iferror(C51/C$53,"") -> 0.47619048 | D77: =iferror(D51/D$53,"") -> 0.36363636 | E77: =iferror(E51/E$53,"") -> 0.38095238 | F77: =iferror(F51/F$53,"") -> 0.38095238 | G77: =iferror(G51/G$53,"") -> 0.38095238 | H77: =iferror(H51/H$53,"") -> 0.5 | I77: =iferror(I51/I$53,"") -> 0.63636364 | ... AF77: =iferror(AF51/AF$53,"") -> 0.2
A78: Not at all | B78: =iferror(B52/B$53,"") -> 0.047619048 | C78: =iferror(C52/C$53,"") -> 0.19047619 | D78: =iferror(D52/D$53,"") -> 0.090909091 | E78: =iferror(E52/E$53,"") -> 0.23809524 | F78: =iferror(F52/F$53,"") -> 0.19047619 | G78: =iferror(G52/G$53,"") -> 0.28571429 | H78: =iferror(H52/H$53,"") -> 0.16666667 | I78: =iferror(I52/I$53,"") -> 0 | ... AF78: =iferror(AF52/AF$53,"") -> 0
A80: Spouse | B80: =iferror(B54/B$60,"") -> 0.1826087 | C80: =iferror(C54/C$60,"") -> 0.2 | D80: =iferror(D54/D$60,"") -> 0.22522523 | E80: =iferror(E54/E$60,"") -> 0.25263158 | F80: =iferror(F54/F$60,"") -> 0.20512821 | G80: =iferror(G54/G$60,"") -> 0.14782609 | H80: =iferror(H54/H$60,"") -> 0.18939394 | I80: =iferror(I54/I$60,"") -> 0.21276596 | ... AF80: =iferror(AF54/AF$60,"") -> 0.26470588
A81: How important do you find acquiring knowledge in bird feeding?
A82: Very, I love learning about birds | B82: =iferror(B56/B$59,"") -> 0.28571429 | C82: =iferror(C56/C$59,"") -> 0.3 | D82: =iferror(D56/D$59,"") -> 0.24 | E82: =iferror(E56/E$59,"") -> 0.375 | F82: =iferror(F56/F$59,"") -> 0.41666667 | G82: =iferror(G56/G$59,"") -> 0.64705882 | H82: =iferror(H56/H$59,"") -> 0.36 | I82: =iferror(I56/I$59,"") -> 0.4 | ... AF82: =iferror(AF56/AF$59,"") -> 0.22222222
A83: It's not the main point for me, but nice | B83: =iferror(B57/B$59,"") -> 0.57142857 | C83: =iferror(C57/C$59,"") -> 0.4 | D83: =iferror(D57/D$59,"") -> 0.68 | E83: =iferror(E57/E$59,"") -> 0.5 | F83: =iferror(F57/F$59,"") -> 0.54166667 | G83: =iferror(G57/G$59,"") -> 0.29411765 | H83: =iferror(H57/H$59,"") -> 0.44 | I83: =iferror(I57/I$59,"") -> 0.5 | ... AF83: =iferror(AF57/AF$59,"") -> 0.77777778
A84: Not at all | B84: =iferror(B58/B$59,"") -> 0.14285714 | C84: =iferror(C58/C$59,"") -> 0.3 | D84: =iferror(D58/D$59,"") -> 0.08 | E84: =iferror(E58/E$59,"") -> 0.125 | F84: =iferror(F58/F$59,"") -> 0.041666667 | G84: =iferror(G58/G$59,"") -> 0.058823529 | H84: =iferror(H58/H$59,"") -> 0.2 | I84: =iferror(I58/I$59,"") -> 0.1 | ... AF84: =iferror(AF58/AF$59,"") -> 0

Sheet SupermetricsQueries
A1: Supermetrics Queries
A3: All the queries created by Supermetrics are stored here, each in its own row.
H4: 16909567
A5: On this sheet you can:
A6: 1. Modify the parameters of a query. Any changes will be visible when you run a refresh.
A8: 2. Remove a query by deleting its row | H8: Europe/Paris
A10: 3. Add new queries: type a range address and query parameters, leave the query ID empty. The query will be added when you run a refresh. (Of course, it's much easier to use the sidebar to add new queries.)
A13: Queries are stored with the authentication of the original user that created the query. If you want to transfer a query to the currently active Google Sheets user, delete its query ID from column A and run a refresh. For complete instructions on transferring queries, see https://support.supermetrics.com/support/solutions/articles/19000050074-how-can-i-transfer-queries-from-one-user-to-another-
A16: Don't delete or rename this sheet. If you delete or rename it, your existing queries can no longer be refreshed. Hiding the sheet is OK. Also, don't delete any rows above row 21.
