Workbook
Name zsupermetrics_ru0GDtbZzDLHQOQtJJ6K08MvUDyyp7: #REF!
Name zsupermetrics_DQl8lUbpTRu3fayaJJi7lVfOGKjNU4: 'Data - P&L'!$A$3:$A$4
Name zsupermetrics_BioPyGBzcBsy60UCQmPcTuFReEmghI: 'Data - P&L'!$B$2:$B$3
Name zsupermetrics_refreshAll: SupermetricsQueries!$H$5
Name zsupermetrics_n3GtLgiKpTmd2pYmQNMuq6TPD0qE0b: #REF!
Name zsupermetrics_refreshAllSilent: SupermetricsQueries!$H$6
Name zsupermetrics_Mgms9p0QzysYvrIhnsKACeVBVxfIEO: #REF!
Name zsupermetrics_Mgms9p0QzysYvrIhnsKACeVBVxfIEO: 'Data - P&L'!$A$2:$A$3
Name zsupermetrics_forceRefresh: SupermetricsQueries!$H$4
Name zsupermetrics_wbYMmT0YL9bAN0yhimW0ziPFnia9Dx: #REF!
Name zsupermetrics_iNpyVy90bWCI0yUaFQpxOtzWMa6sW4: #REF!
Name zsupermetrics_xwoIpANxRm908eDp5oKTwQpEI8gvD4: #REF!
Name zsupermetrics_n3GtLgiKpTmd2pYmQNMuq6TPD0qE0b: 'Data - P&L'!$B$4:$B$5
Name rdataslayer_42b112e4e4be4305bb4c1be75e2dd549: 'Data - P&L'!$B$2:$C$3
Name zsupermetrics_9i4W4hgd80uRpQLMeX0eRnESN8gjyv: #REF!
Name zsupermetrics_5bmwtOpHUbSYmDMeuCPkrxaojTprPP: #REF!
Name rdataslayer_3753ddf3234e496aa261974a0222e193: 'Data - P&L'!$H$2:$I$2
Name zsupermetrics_SGBxROnInO9rFyh3H7j2Lldx0Bdc5v: #REF!
Name zsupermetrics_pxuhRTEmIU93xSgKclyxajD0fCZ6rF: #REF!
Name zsupermetrics_ru0GDtbZzDLHQOQtJJ6K08MvUDyyp7: 'Data - P&L'!$B$4:$B$5
Name zsupermetrics_qWp7V908pNEYMtfv8QZvSTeDnBAHOU: 'Data - P&L'!$B$5:$C$13
Name rdataslayer_4a0f150f4f2f4e4f85c890c75b7a1fa4: #REF!
Name zsupermetrics_8xojRjNDjo2jWHGDWjFEhflhyIq3Hq: #REF!
Name zsupermetrics_HgZqhorObHOtZHuyJjpmyYaEPoYntx: #REF!
Name zsupermetrics_YsFuuYtr8vOdNXCCPiFJIO38NP4b2T: #REF!
Name zsupermetrics_DQl8lUbpTRu3fayaJJi7lVfOGKjNU4: #REF!
Name zsupermetrics_YVuzfmsfdurz7Ldl84Rfns8oka6LsS: #REF!
Name zsupermetrics_4VkB7ij7WO0JjKBEgvjB2GHjSy2Egm: #REF!
Name zsupermetrics_9i4W4hgd80uRpQLMeX0eRnESN8gjyv: 'Data - P&L'!$C$13
Name zsupermetrics_lx4cNai7gT6tH4j08ZRkI21Qlpjioi: #REF!
Name rdataslayer_d70e473bcafe40a3aa834ce157fb2ba3: #REF!
Name zsupermetrics_NugLlrQxlKiqhxQae8EFpITBm1pLCj: 'Data - P&L'!$B$6:$C$13
Name zsupermetrics_8xojRjNDjo2jWHGDWjFEhflhyIq3Hq: Summary!$K$8:$K$48
Name zsupermetrics_FEamnpN5FsVYF0RtUTXAwunZ388Tkc: Forecast!$A$113:$C$141
Name rdataslayer_3753ddf3234e496aa261974a0222e193: #REF!
Name zsupermetrics_iNpyVy90bWCI0yUaFQpxOtzWMa6sW4: 'Data - P&L'!$A$2:$A$3
Name rdataslayer_4a0f150f4f2f4e4f85c890c75b7a1fa4: 'Data - P&L'!$D$2:$E$3
Name zsupermetrics_BioPyGBzcBsy60UCQmPcTuFReEmghI: #REF!
Name zsupermetrics_qWp7V908pNEYMtfv8QZvSTeDnBAHOU: #REF!
Name zsupermetrics_wbYMmT0YL9bAN0yhimW0ziPFnia9Dx: 'Data - P&L'!$A$2:$A$3
Name zsupermetrics_4VkB7ij7WO0JjKBEgvjB2GHjSy2Egm: 'Data - P&L'!$B$4:$C$10
Name zsupermetrics_lx4cNai7gT6tH4j08ZRkI21Qlpjioi: 'Data - P&L'!$B$4:$C$13
Name rdataslayer_42b112e4e4be4305bb4c1be75e2dd549: #REF!
Name rdataslayer_adf57e64065742daa5b4161161b1c3ca: #REF!
Name rdataslayer_adf57e64065742daa5b4161161b1c3ca: 'Data - P&L'!$B$4:$D$5
Name zsupermetrics_NugLlrQxlKiqhxQae8EFpITBm1pLCj: #REF!
Name zsupermetrics_xwoIpANxRm908eDp5oKTwQpEI8gvD4: #REF!
Name zsupermetrics_YsFuuYtr8vOdNXCCPiFJIO38NP4b2T: 'Data - P&L'!$B$4:$C$13
Name rdataslayer_d70e473bcafe40a3aa834ce157fb2ba3: 'Data - P&L'!$C$8:$D$9
Name zsupermetrics_HgZqhorObHOtZHuyJjpmyYaEPoYntx: 'Data - P&L'!$B$4:$B$5

Sheet Data_forecast_2024
B1: 45566 | C1: 45567 | D1: 45568 | E1: 45569 | F1: 45570 | G1: 45571 | H1: 45572 | I1: 45573 | J1: 45574 | K1: 45575 | L1: 45576 | M1: 45577 | N1: 45578 | O1: 45579 | P1: 45580 | Q1: 45581 | R1: 45582 | S1: 45583 | T1: 45584 | U1: 45585 | V1: 45586 | W1: 45587 | X1: 45588 | Y1: 45589 | Z1: 45590 | AA1: 45591 | AB1: 45592 | AC1: 45593 | AD1: 45594 | AE1: 45595 | AF1: 45596
A2: Quantities | B2: ='DTC - P&L'!B63+'AMAZON - P&L'!B36+'WALMART - P&L'!B19+'Digital Marketplaces - P&L'!B17+'Digital Marketplaces - P&L'!B129+'Digital Marketplaces - P&L'!B239 -> 43 | C2: ='DTC - P&L'!C63+'AMAZON - P&L'!C36+'WALMART - P&L'!C19+'Digital Marketplaces - P&L'!C17+'Digital Marketplaces - P&L'!C129+'Digital Marketplaces - P&L'!C239 -> 36 | D2: ='DTC - P&L'!D63+'AMAZON - P&L'!D36+'WALMART - P&L'!D19+'Digital Marketplaces - P&L'!D17+'Digital Marketplaces - P&L'!D129+'Digital Marketplaces - P&L'!D239 -> 40 | E2: ='DTC - P&L'!E63+'AMAZON - P&L'!E36+'WALMART - P&L'!E19+'Digital Marketplaces - P&L'!E17+'Digital Marketplaces - P&L'!E129+'Digital Marketplaces - P&L'!E239 -> 26 | F2: ='DTC - P&L'!F63+'AMAZON - P&L'!F36+'WALMART - P&L'!F19+'Digital Marketplaces - P&L'!F17+'Digital Marketplaces - P&L'!F129+'Digital Marketplaces - P&L'!F239 -> 22 | G2: ='DTC - P&L'!G63+'AMAZON - P&L'!G36+'WALMART - P&L'!G19+'Digital Marketplaces - P&L'!G17+'Digital Marketplaces - P&L'!G129+'Digital Marketplaces - P&L'!G239 -> 27 | H2: ='DTC - P&L'!H63+'AMAZON - P&L'!H36+'WALMART - P&L'!H19+'Digital Marketplaces - P&L'!H17+'Digital Marketplaces - P&L'!H129+'Digital Marketplaces - P&L'!H239 -> 28 | I2: ='DTC - P&L'!I63+'AMAZON - P&L'!I36+'WALMART - P&L'!I19+'Digital Marketplaces - P&L'!I17+'Digital Marketplaces - P&L'!I129+'Digital Marketplaces - P&L'!I239 -> 424 | ... AF2: ='DTC - P&L'!AF63+'AMAZON - P&L'!AF36+'WALMART - P&L'!AF19+'Digital Marketplaces - P&L'!AF17+'Digital Marketplaces - P&L'!AF129+'Digital Marketplaces - P&L'!AF239 -> 208
A3: Sales | B3: =Summary!B8+Summary!B25+Summary!B31+Summary!B35 -> 17178.81 | C3: =Summary!C8+Summary!C25+Summary!C31+Summary!C35 -> 12596.87 | D3: =Summary!D8+Summary!D25+Summary!D31+Summary!D35 -> 14429.86 | E3: =Summary!E8+Summary!E25+Summary!E31+Summary!E35 -> 10171.31 | F3: =Summary!F8+Summary!F25+Summary!F31+Summary!F35 -> 10354.06 | G3: =Summary!G8+Summary!G25+Summary!G31+Summary!G35 -> 10648.64 | H3: =Summary!H8+Summary!H25+Summary!H31+Summary!H35 -> 11126.65 | I3: =Summary!I8+Summary!I25+Summary!I31+Summary!I35 -> 98747.06 | ... AF3: =Summary!AF8+Summary!AF25+Summary!AF31+Summary!AF35 -> 63685.19

Sheet WALMART_Data_forecast_2024
B1: 45566 | C1: 45567 | D1: 45568 | E1: 45569 | F1: 45570 | G1: 45571 | H1: 45572 | I1: 45573 | J1: 45574 | K1: 45575 | L1: 45576 | M1: 45577 | N1: 45578 | O1: 45579 | P1: 45580 | Q1: 45581 | R1: 45582 | S1: 45583 | T1: 45584 | U1: 45585 | V1: 45586 | W1: 45587 | X1: 45588 | Y1: 45589 | Z1: 45590 | AA1: 45591 | AB1: 45592 | AC1: 45593 | AD1: 45594 | AE1: 45595 | AF1: 45596
A2: Quantities | B2: ='WALMART - P&L'!B19 -> 0 | C2: ='WALMART - P&L'!C19 -> 0 | D2: ='WALMART - P&L'!D19 -> 0 | E2: ='WALMART - P&L'!E19 -> 0 | F2: ='WALMART - P&L'!F19 -> 0 | G2: ='WALMART - P&L'!G19 -> 0 | H2: ='WALMART - P&L'!H19 -> 1 | I2: ='WALMART - P&L'!I19 -> 1 | ... AF2: ='WALMART - P&L'!AF19 -> 0
A3: Sales | B3: =Summary!B31 -> 0 | C3: =Summary!C31 -> 0 | D3: =Summary!D31 -> 0 | E3: =Summary!E31 -> 0 | F3: =Summary!F31 -> 0 | G3: =Summary!G31 -> 0 | H3: =Summary!H31 -> 321.43 | I3: =Summary!I31 -> 316.94 | ... AF3: =Summary!AF31 -> 0

Sheet COSTCO_Data_forecast_2024
B1: 45566 | C1: 45567 | D1: 45568 | E1: 45569 | F1: 45570 | G1: 45571 | H1: 45572 | I1: 45573 | J1: 45574 | K1: 45575 | L1: 45576 | M1: 45577 | N1: 45578 | O1: 45579 | P1: 45580 | Q1: 45581 | R1: 45582 | S1: 45583 | T1: 45584 | U1: 45585 | V1: 45586 | W1: 45587 | X1: 45588 | Y1: 45589 | Z1: 45590 | AA1: 45591 | AB1: 45592 | AC1: 45593 | AD1: 45594 | AE1: 45595 | AF1: 45596
A2: Quantities | B2: ='Digital Marketplaces - P&L'!B239 -> 0 | C2: ='Digital Marketplaces - P&L'!C239 -> 0 | D2: ='Digital Marketplaces - P&L'!D239 -> 0 | E2: ='Digital Marketplaces - P&L'!E239 -> 0 | F2: ='Digital Marketplaces - P&L'!F239 -> 0 | G2: ='Digital Marketplaces - P&L'!G239 -> 0 | H2: ='Digital Marketplaces - P&L'!H239 -> 0 | I2: ='Digital Marketplaces - P&L'!I239 -> 0 | ... AF2: ='Digital Marketplaces - P&L'!AF239 -> 4
A3: Sales | B3: =Summary!B44 -> 0 | C3: =Summary!C44 -> 0 | D3: =Summary!D44 -> 0 | E3: =Summary!E44 -> 0 | F3: =Summary!F44 -> 0 | G3: =Summary!G44 -> 0 | H3: =Summary!H44 -> 0 | I3: =Summary!I44 -> 0 | ... AF3: =Summary!AF44 -> 0

Sheet DM_Data_forecast_2024
B1: 45566 | C1: 45567 | D1: 45568 | E1: 45569 | F1: 45570 | G1: 45571 | H1: 45572 | I1: 45573 | J1: 45574 | K1: 45575 | L1: 45576 | M1: 45577 | N1: 45578 | O1: 45579 | P1: 45580 | Q1: 45581 | R1: 45582 | S1: 45583 | T1: 45584 | U1: 45585 | V1: 45586 | W1: 45587 | X1: 45588 | Y1: 45589 | Z1: 45590 | AA1: 45591 | AB1: 45592 | AC1: 45593 | AD1: 45594 | AE1: 45595 | AF1: 45596
A2: Quantities | B2: ='Digital Marketplaces - P&L'!B17+'Digital Marketplaces - P&L'!B129 -> 0 | C2: ='Digital Marketplaces - P&L'!C17+'Digital Marketplaces - P&L'!C129 -> 0 | D2: ='Digital Marketplaces - P&L'!D17+'Digital Marketplaces - P&L'!D129 -> 0 | E2: ='Digital Marketplaces - P&L'!E17+'Digital Marketplaces - P&L'!E129 -> 0 | F2: ='Digital Marketplaces - P&L'!F17+'Digital Marketplaces - P&L'!F129 -> 0 | G2: ='Digital Marketplaces - P&L'!G17+'Digital Marketplaces - P&L'!G129 -> 0 | H2: ='Digital Marketplaces - P&L'!H17+'Digital Marketplaces - P&L'!H129 -> 0 | I2: ='Digital Marketplaces - P&L'!I17+'Digital Marketplaces - P&L'!I129 -> 0 | ... AF2: ='Digital Marketplaces - P&L'!AF17+'Digital Marketplaces - P&L'!AF129 -> 0
A3: Sales | B3: =Summary!B36+Summary!B40 -> 0 | C3: =Summary!C36+Summary!C40 -> 0 | D3: =Summary!D36+Summary!D40 -> 0 | E3: =Summary!E36+Summary!E40 -> 0 | F3: =Summary!F36+Summary!F40 -> 0 | G3: =Summary!G36+Summary!G40 -> 0 | H3: =Summary!H36+Summary!H40 -> 0 | I3: =Summary!I36+Summary!I40 -> 0 | ... AF3: =Summary!AF36+Summary!AF40 -> 0

Sheet AMAZON_Data_forecast_2024
B1: 45566 | C1: 45567 | D1: 45568 | E1: 45569 | F1: 45570 | G1: 45571 | H1: 45572 | I1: 45573 | J1: 45574 | K1: 45575 | L1: 45576 | M1: 45577 | N1: 45578 | O1: 45579 | P1: 45580 | Q1: 45581 | R1: 45582 | S1: 45583 | T1: 45584 | U1: 45585 | V1: 45586 | W1: 45587 | X1: 45588 | Y1: 45589 | Z1: 45590 | AA1: 45591 | AB1: 45592 | AC1: 45593 | AD1: 45594 | AE1: 45595 | AF1: 45596
A2: Quantities | B2: ='AMAZON - P&L'!B36 -> 27 | C2: ='AMAZON - P&L'!C36 -> 23 | D2: ='AMAZON - P&L'!D36 -> 24 | E2: ='AMAZON - P&L'!E36 -> 16 | F2: ='AMAZON - P&L'!F36 -> 8 | G2: ='AMAZON - P&L'!G36 -> 17 | H2: ='AMAZON - P&L'!H36 -> 17 | I2: ='AMAZON - P&L'!I36 -> 412 | ... AF2: ='AMAZON - P&L'!AF36 -> 90
A3: Sales | B3: =Summary!B25 -> 7953.97 | C3: =Summary!C25 -> 6765.07 | D3: =Summary!D25 -> 7698.8 | E3: =Summary!E25 -> 5011.15 | F3: =Summary!F25 -> 2828.44 | G3: =Summary!G25 -> 5401.75 | H3: =Summary!H25 -> 5446.92 | I3: =Summary!I25 -> 93468.46 | ... AF3: =Summary!AF25 -> 22434.14

Sheet DTC_Data_forecast_2024
B1: 45566 | C1: 45567 | D1: 45568 | E1: 45569 | F1: 45570 | G1: 45571 | H1: 45572 | I1: 45573 | J1: 45574 | K1: 45575 | L1: 45576 | M1: 45577 | N1: 45578 | O1: 45579 | P1: 45580 | Q1: 45581 | R1: 45582 | S1: 45583 | T1: 45584 | U1: 45585 | V1: 45586 | W1: 45587 | X1: 45588 | Y1: 45589 | Z1: 45590 | AA1: 45591 | AB1: 45592 | AC1: 45593 | AD1: 45594 | AE1: 45595 | AF1: 45596
A2: Quantities | B2: ='DTC - P&L'!B63 -> 16 | C2: ='DTC - P&L'!C63 -> 13 | D2: ='DTC - P&L'!D63 -> 16 | E2: ='DTC - P&L'!E63 -> 10 | F2: ='DTC - P&L'!F63 -> 14 | G2: ='DTC - P&L'!G63 -> 10 | H2: ='DTC - P&L'!H63 -> 10 | I2: ='DTC - P&L'!I63 -> 11 | ... AF2: ='DTC - P&L'!AF63 -> 114
A3: Sales | B3: =Summary!B8 -> 9224.84 | C3: =Summary!C8 -> 5831.8 | D3: =Summary!D8 -> 6731.06 | E3: =Summary!E8 -> 5160.16 | F3: =Summary!F8 -> 7525.62 | G3: =Summary!G8 -> 5246.89 | H3: =Summary!H8 -> 5358.3 | I3: =Summary!I8 -> 4961.66 | ... AF3: =Summary!AF8 -> 41251.05

Sheet Summary
B1: 45566 | C1: 45567 | D1: 45568 | E1: 45569 | F1: 45570 | G1: 45571 | H1: 45572 | I1: 45573 | J1: 45574 | K1: 45575 | L1: 45576 | M1: 45577 | N1: 45578 | O1: 45579 | P1: 45580 | Q1: 45581 | R1: 45582 | S1: 45583 | T1: 45584 | U1: 45585 | V1: 45586 | W1: 45587 | X1: 45588 | Y1: 45589 | Z1: 45590 | AA1: 45591 | AB1: 45592 | AC1: 45593 | AD1: 45594 | AE1: 45595 | AF1: 45596
B2: TUE | C2: WED | D2: THU | E2: FRI | F2: SAT | G2: SUN | H2: MON | I2: TUE | J2: WED | K2: THU | L2: FRI | M2: SAT | N2: SUN | O2: MON | P2: TUE | Q2: WED | R2: THU | S2: FRI | T2: SAT | U2: SUN | V2: MON | W2: TUE | X2: WED | Y2: THU | Z2: FRI | AA2: SAT | AB2: SUN | AC2: MON | AD2: TUE | AE2: WED | AF2: THU
A4: Notes | B4: Started with popups | C4: SKU1 OOS | D4: Change of popup design | H4: Listicle Landing Page Start | I4: Prime Day MAP | K4: Canada start DTC | L4: EU test order | P4: Nature Cam PRO Launch | Q4: Accelerated spend on Meta ( 6K of "bad spend ") LP Test ( 10/30% discount split start ) EU DTC start | Z4: A/B Test (/convert & /v2) | AC4: Nature Cam PRO Launch Email #2 | AF4: A/B Test (/offer-pro)
A8: DTC Revenue | B8: =SUM(B9,B17) -> 9224.84 | C8: =SUM(C9,C17) -> 5831.8 | D8: =SUM(D9,D17) -> 6731.06 | E8: =SUM(E9,E17) -> 5160.16 | F8: =SUM(F9,F17) -> 7525.62 | G8: =SUM(G9,G17) -> 5246.89 | H8: =SUM(H9,H17) -> 5358.3 | I8: =SUM(I9,I17) -> 4961.66 | ... AF8: =SUM(AF9,AF17) -> 41251.05
A9: - DTC Revenue US&CA | B9: =sum(B10:B16) -> 9224.84 | C9: =sum(C10:C16) -> 5831.8 | D9: =sum(D10:D16) -> 6731.06 | E9: =sum(E10:E16) -> 5160.16 | F9: =sum(F10:F16) -> 7525.62 | G9: =sum(G10:G16) -> 5246.89 | H9: =sum(H10:H16) -> 5358.3 | I9: =sum(I10:I16) -> 4961.66 | ... AF9: =sum(AF10:AF16) -> 34342.97
A10: - Hardware | B10: 4811 | C10: 3876 | D10: 4654.3 | E10: 3588.1 | F10: 5412.2 | G10: 3259 | H10: 3872.1 | I10: 3757.75 | J10: 5611.3 | K10: 3465.6 | L10: 5010.15 | M10: 4547.33 | N10: 5509.5 | O10: 4655.3 | P10: 10914.08 | Q10: 8053.92 | R10: 5712.39 | S10: 5078.73 | T10: 5641.73 | U10: 2441 | V10: 4891.03 | W10: 3616.79 | X10: 7532.83 | Y10: 7031.9 | Z10: 15306.2 | AA10: 31544.15 | AB10: 29064.2 | AC10: 14646.15 | AD10: 15626.2 | AE10: 20290.15 | AF10: 25189.9
A11: - Add-ons | B11: 2000.3 | C11: 485.9 | D11: 519 | E11: 243 | F11: 409.1 | G11: 739.3 | H11: 418.9 | I11: 235.9 | J11: 1190.8 | K11: 841.5 | L11: 1078.1 | M11: 531.57 | N11: 883.2 | O11: 373 | P11: 26637.02 | Q11: 14171.58 | R11: 8502.81 | S11: 5676.69 | T11: 4650.41 | U11: 4263.22 | V11: 2624.12 | W11: 3253.65 | X11: 2763.36 | Y11: 3341.44 | Z11: 6222.2 | AA11: 5600.9 | AB11: 3983.2 | AC11: 5283.29 | AD11: 4530.45 | AE11: 4753.45 | AF11: 3108.63
A12: - Merch | B12: 0 | C12: 0 | D12: 0 | E12: 0 | F12: 0 | G12: 0 | H12: 0 | I12: 0 | J12: 514.79 | K12: 0 | L12: 0 | M12: 0 | N12: 0 | O12: 0 | P12: 0 | Q12: 0 | R12: 0 | S12: 0 | T12: 0 | U12: 0 | V12: 0 | W12: 0 | X12: 0 | Y12: 0 | Z12: 0 | AA12: 0 | AB12: 0 | AC12: 0 | AD12: 24.99 | AE12: 0 | AF12: 0
A13: - Seeds | B13: 710.7 | C13: 439.3 | D13: 555.1 | E13: 621.8 | F13: 672.7 | G13: 477.1 | H13: 344.6 | I13: 256.1 | J13: 389.5 | K13: 415.6 | L13: 400.7 | M13: 209.2 | N13: 246.3 | O13: 221.2 | P13: 620 | Q13: 423.6 | R13: 401.6 | S13: 179.3 | T13: 179.3 | U13: 296 | V13: 455.2 | W13: 233.2 | X13: 235.2 | Y13: 343.8 | Z13: 263.2 | AA13: 409.6 | AB13: 464.2 | AC13: 325.9 | AD13: 203.3 | AE13: 179.4 | AF13: 439.5
A14: - Yearly Pro Subscription | B14: 479.92 | C14: 299.95 | D14: 239.96 | E14: 0 | F14: 59.99 | G14: 59.99 | H14: 0 | I14: 59.99 | J14: 59.99 | K14: 179.97 | L14: 119.98 | M14: 239.96 | N14: 539.91 | O14: 419.93 | P14: 179.97 | Q14: 179.97 | R14: 299.95 | S14: 59.99 | T14: 239.96 | U14: 359.94 | V14: 59.99 | W14: 299.95 | X14: 299.95 | Y14: 179.97 | Z14: 239.96 | AA14: 299.95 | AB14: 299.95 | AC14: 239.96 | AD14: 59.99 | AE14: 0 | AF14: 179.97
A15: - Taxes | B15: 557.92 | C15: 353.65 | D15: 385.26 | E15: 305.76 | F15: 501.63 | G15: 334.5 | H15: 350.7 | I15: 297.71 | J15: 569.74 | K15: 361.64 | L15: 530.35 | M15: 447.54 | N15: 420.75 | O15: 411.75 | P15: 2594.41 | Q15: 1561.32 | R15: 1055.71 | S15: 784.71 | T15: 779.03 | U15: 522.03 | V15: 537.96 | W15: 446.39 | X15: 823.26 | Y15: 745.87 | Z15: 1624.01 | AA15: 2757.99 | AB15: 2514.29 | AC15: 1549.41 | AD15: 1606.93 | AE15: 1800.97 | AF15: 2207.84
A16: - Shipping | B16: 665 | C16: 377 | D16: 377.44 | E16: 401.5 | F16: 470 | G16: 377 | H16: 372 | I16: 354.21 | J16: 740.82 | K16: 429.16 | L16: 661.59 | M16: 400 | N16: 611.46 | O16: 395 | P16: 2880 | Q16: 1903.82 | R16: 1266.37 | S16: 971.54 | T16: 959.82 | U16: 565 | V16: 729.77 | W16: 742.02 | X16: 1141.61 | Y16: 1041 | Z16: 1963.37 | AA16: 3759.93 | AB16: 3343.1 | AC16: 1827.26 | AD16: 2360.23 | AE16: 2814.84 | AF16: 3217.13
A17: - DTC Revenue EU | B17: / | C17: / | D17: / | E17: / | F17: / | G17: / | H17: / | I17: / | J17: / | K17: =SUM(K18:K24) -> 599.19 | L17: / | M17: / | N17: / | O17: / | P17: / | Q17: =SUM(Q18:Q24) -> 1579.99 | R17: =SUM(R18:R24) -> 5894.45 | S17: =SUM(S18:S24) -> 3947.49 | T17: =SUM(T18:T24) -> 2042.12 | U17: =SUM(U18:U24) -> 352.15 | V17: =SUM(V18:V24) -> 1576.04 | W17: =SUM(W18:W24) -> 918.92 | X17: =SUM(X18:X24) -> 0 | ... AF17: =SUM(AF18:AF24) -> 6908.08
A18: - Hardware | K18: 439.2 | Q18: 919.49 | R18: 4182.37 | S18: 2749.13 | T18: 1423.83 | U18: 268.58 | V18: 1106.58 | W18: 661.09 | X18: 0 | Y18: 951.68 | Z18: 751.39 | AA18: 241.08 | AB18: 1360.58 | AC18: 1737.92 | AD18: 4080.63 | AE18: 3749.85 | AF18: 4759.75
A19: - Add-ons | K19: 0 | Q19: 289.11 | R19: 245.13 | S19: 208.74 | T19: 122.68 | U19: 0 | V19: 76.56 | W19: 16.81 | X19: 0 | Y19: 244.45 | Z19: 170.76 | AA19: 33.92 | AB19: 165.2 | AC19: 264.52 | AD19: 242.44 | AE19: 297.85 | AF19: 448.91
A20: - Merch | K20: 0 | Q20: 0 | R20: 0 | S20: 0 | T20: 0 | U20: 0 | V20: 0 | W20: 0 | X20: 0 | Y20: 0 | Z20: 0 | AA20: 0 | AB20: 0 | AC20: 0 | AD20: 0 | AE20: 0 | AF20: 0
A21: - Seeds | K21: 0 | Q21: 0 | R21: 0 | S21: 0 | T21: 0 | U21: 0 | V21: 0 | W21: 0 | X21: 0 | Y21: 0 | Z21: 0 | AA21: 0 | AB21: 0 | AC21: 0 | AD21: 0 | AE21: 0 | AF21: 0
A22: - Yearly Pro Subscription | K22: 0 | Q22: 0 | R22: 0 | S22: 0 | T22: 0 | U22: 0 | V22: 0 | W22: 0 | X22: 0 | Y22: 0 | Z22: 0 | AA22: 0 | AB22: 0 | AC22: 0 | AD22: 0 | AE22: 0 | AF22: 0
A23: - Taxes | K23: 83.45 | Q23: 241.08 | R23: 930.82 | S23: 636.21 | T23: 321.66 | U23: 56.4 | V23: 246.87 | W23: 160.03 | X23: 0 | Y23: 245.16 | Z23: 189.17 | AA23: 67.4 | AB23: 318.34 | AC23: 430.93 | AD23: 911.26 | AE23: 839.93 | AF23: 1100.8
A24: - Shipping | K24: 76.54 | Q24: 130.31 | R24: 536.13 | S24: 353.41 | T24: 173.95 | U24: 27.17 | V24: 146.03 | W24: 80.99 | X24: 0 | Y24: 140.75 | Z24: 91.8 | AA24: 37.8 | AB24: 183.55 | AC24: 200.08 | AD24: 535.64 | AE24: 466.94 | AF24: 598.62
A25: Amazon Revenue | B25: =B26+B27+B28+B29+B30 -> 7953.97 | C25: =C26+C27+C28+C29+C30 -> 6765.07 | D25: =D26+D27+D28+D29+D30 -> 7698.8 | E25: =E26+E27+E28+E29+E30 -> 5011.15 | F25: =F26+F27+F28+F29+F30 -> 2828.44 | G25: =G26+G27+G28+G29+G30 -> 5401.75 | H25: =H26+H27+H28+H29+H30 -> 5446.92 | I25: =I26+I27+I28+I29+I30 -> 93468.46 | ... AF25: =AF26+AF27+AF28+AF29+AF30 -> 22434.14
A26: - Hardware | B26: 7233 | C26: 6157 | D26: 6993.56 | E26: 4539.12 | F26: 2332 | G26: 4840.56 | H26: 4898.12 | I26: 86106.86 | J26: 74056.8 | K26: 23666.54 | L26: 5581.46 | M26: 5121.31 | N26: 4583.31 | O26: 5864.9 | P26: 5648.83 | Q26: 12202.86 | R26: 6977.94 | S26: 6400.65 | T26: 4855.8 | U26: 5597.88 | V26: 4804.65 | W26: 6103.23 | X26: 4677.63 | Y26: 8325.18 | Z26: 8135 | AA26: 23333.14 | AB26: 15867.14 | AC26: 12658.76 | AD26: 7984.94 | AE26: 10435 | AF26: 20447.5
A27: - Add-ons | B27: 213 | C27: 164 | D27: 222 | E27: 154 | F27: 309 | G27: 184 | H27: 203 | I27: 1207.2 | J27: 1096 | K27: 511 | L27: 162.46 | M27: 252 | N27: 375.48 | O27: 242 | P27: 144 | Q27: 146.2 | R27: 174 | S27: 193 | T27: 300 | U27: 271 | V27: 145 | W27: 220.06 | X27: 193 | Y27: 242 | Z27: 242 | AA27: 701.33 | AB27: 233 | AC27: 309 | AD27: 289 | AE27: 415 | AF27: 522
A28: - Tax | B28: 503.48 | C28: 439.58 | D28: 451.32 | E28: 296.65 | F28: 175.96 | G28: 367.96 | H28: 327.34 | I28: 6084.31 | J28: 5208.44 | K28: 1708.17 | L28: 390.58 | M28: 377.7 | N28: 356.62 | O28: 444.54 | P28: 397.33 | Q28: 899.67 | R28: 480.85 | S28: 524.3 | T28: 391.74 | U28: 389.37 | V28: 298.46 | W28: 421.24 | X28: 275.91 | Y28: 490.38 | Z28: 599.4 | AA28: 1694.46 | AB28: 1106.21 | AC28: 776.62 | AD28: 572.79 | AE28: 757.13 | AF28: 1439.98
A29: - Shipping | B29: 0 | C29: 0 | D29: 27.26 | E29: 21.04 | F29: 6.99 | G29: 0.08 | H29: 0.16 | I29: 49.97 | J29: 34.51 | K29: 0.33 | L29: 18.78 | M29: 0.08 | N29: 0.08 | O29: 0 | P29: 30.64 | Q29: 0.5 | R29: 0.75 | S29: 49.42 | T29: 0 | U29: 0.25 | V29: 0 | W29: 0.25 | X29: 0.25 | Y29: 17.19 | Z29: 0 | AA29: 13.28 | AB29: 7.74 | AC29: 12.64 | AD29: 0.33 | AE29: 0 | AF29: 14.89
A30: - Gift Wrap | B30: 4.49 | C30: 4.49 | D30: 4.66 | E30: 0.34 | F30: 4.49 | G30: 9.15 | H30: 18.3 | I30: 20.12 | J30: 37.42 | K30: 4.81 | L30: 0.17 | M30: 4.16 | N30: 4.66 | O30: 4.49 | P30: 4.64 | Q30: 0.3 | R30: 4.94 | S30: 4.49 | T30: 4.49 | U30: 0.15 | V30: 0 | W30: 0.15 | X30: 9.13 | Y30: 9.13 | Z30: 0 | AA30: 4.94 | AB30: 4.94 | AC30: 4.79 | AD30: 9.3 | AE30: 0 | AF30: 9.77
A31: Walmart Revenue | B31: =sum(B32:B34) -> 0 | C31: =sum(C32:C34) -> 0 | D31: =sum(D32:D34) -> 0 | E31: =sum(E32:E34) -> 0 | F31: =sum(F32:F34) -> 0 | G31: =sum(G32:G34) -> 0 | H31: =sum(H32:H34) -> 321.43 | I31: =sum(I32:I34) -> 316.94 | ... AF31: =sum(AF32:AF34) -> 0
A32: - Hardware | B32: 0 | C32: 0 | D32: 0 | E32: 0 | F32: 0 | G32: 0 | H32: 299 | I32: 299 | J32: 0 | K32: 0 | L32: 0 | M32: 0 | N32: 0 | O32: 0 | P32: 0 | Q32: 0 | R32: 0 | S32: 0 | T32: 0 | U32: 279 | V32: 0 | W32: 0 | X32: 0 | Y32: 0 | Z32: 0 | AA32: 239 | AB32: 0 | AC32: 0 | AD32: 239 | AE32: 0 | AF32: 0
A33: - Tax | B33: 0 | C33: 0 | D33: 0 | E33: 0 | F33: 0 | G33: 0 | H33: 22.43 | I33: 17.94 | J33: 0 | K33: 0 | L33: 0 | M33: 0 | N33: 0 | O33: 0 | P33: 0 | Q33: 0 | R33: 0 | S33: 0 | T33: 0 | U33: 19.18 | V33: 0 | W33: 0 | X33: 0 | Y33: 0 | Z33: 0 | AA33: 10.1 | AB33: 0 | AC33: 0 | AD33: 14.94 | AE33: 0 | AF33: 0
A34: - Shipping
A35: Digital Marketplaces Revenue | B35: =SUM(B40,B36) -> 0 | C35: =SUM(C40,C36) -> 0 | D35: =SUM(D40,D36) -> 0 | E35: =SUM(E40,E36) -> 0 | F35: =SUM(F40,F36) -> 0 | G35: =SUM(G40,G36) -> 0 | H35: =SUM(H40,H36) -> 0 | I35: =SUM(I40,I36) -> 0 | ... AF35: =SUM(AF40,AF36) -> 0
A36: Rachio | B36: =SUM(B37:B38) -> 0 | C36: =SUM(C37:C38) -> 0 | D36: =SUM(D37:D38) -> 0 | E36: =SUM(E37:E38) -> 0 | F36: =SUM(F37:F38) -> 0 | G36: =SUM(G37:G38) -> 0 | H36: =SUM(H37:H38) -> 0 | I36: =SUM(I37:I38) -> 0 | ... AF36: =SUM(AF37:AF38) -> 0
A37: - Hardware | B37: 0 | C37: 0 | D37: 0 | E37: 0 | F37: 0 | G37: 0 | H37: 0 | I37: 0 | J37: 0 | K37: 0 | L37: 0 | M37: 0 | N37: 0 | O37: 299.99 | P37: 0 | Q37: 0 | R37: 0 | S37: 0 | T37: 0 | U37: 0 | V37: 299.99 | W37: 0 | X37: 0 | Y37: 0 | Z37: 0 | AA37: 0 | AB37: 0 | AC37: 479.98 | AD37: 0 | AE37: 0 | AF37: 0
A38: - Tax | B38: =0.0614*B37 -> 0 | C38: =0.0614*C37 -> 0 | D38: =0.0614*D37 -> 0 | E38: =0.0614*E37 -> 0 | F38: =0.0614*F37 -> 0 | G38: =0.0614*G37 -> 0 | H38: =0.0614*H37 -> 0 | I38: =0.0614*I37 -> 0 | ... AF38: =0.0614*AF37 -> 0
A39: - Shipping
A40: Weatherflow | B40: =SUM(B41:B43) -> 0 | C40: 0 | D40: =SUM(D41:D43) -> 0 | E40: =SUM(E41:E43) -> 0 | F40: =SUM(F41:F43) -> 0 | G40: =SUM(G41:G43) -> 0 | H40: =SUM(H41:H43) -> 0 | I40: =SUM(I41:I43) -> 0 | J40: =SUM(J41:J43) -> 0 | K40: =SUM(K41:K43) -> 0 | ... AF40: =SUM(AF41:AF43) -> 0
A41: - Hardware | B41: 0 | C41: 0 | D41: 0 | E41: 0 | F41: 0 | G41: 0 | H41: 0 | I41: 0 | J41: 0 | K41: 0 | L41: 0 | M41: 0 | N41: 0 | O41: 0 | P41: 0 | Q41: 0 | R41: 0 | S41: 0 | T41: 0 | U41: 0 | V41: 0 | W41: 0 | X41: 0 | Y41: 0 | Z41: 0 | AA41: 0 | AB41: 0 | AC41: 0 | AD41: 0 | AE41: 0 | AF41: 0
A42: - Tax | B42: =0.0614*B41 -> 0 | C42: =0.0614*C41 -> 0 | D42: =0.0614*D41 -> 0 | E42: =0.0614*E41 -> 0 | F42: =0.0614*F41 -> 0 | G42: =0.0614*G41 -> 0 | H42: =0.0614*H41 -> 0 | I42: =0.0614*I41 -> 0 | ... AF42: =0.0614*AF41 -> 0
A43: - Shipping
A44: Costco | B44: =SUM(B45:B47) -> 0 | C44: =SUM(C45:C47) -> 0 | D44: =SUM(D45:D47) -> 0 | E44: =SUM(E45:E47) -> 0 | F44: =SUM(F45:F47) -> 0 | G44: =SUM(G45:G47) -> 0 | H44: =SUM(H45:H47) -> 0 | I44: =SUM(I45:I47) -> 0 | ... AF44: =SUM(AF45:AF47) -> 0
A45: - Hardware
A46: - Tax | B46: =0.0614*B45 -> 0 | C46: =0.0614*C45 -> 0 | D46: =0.0614*D45 -> 0 | E46: =0.0614*E45 -> 0 | F46: =0.0614*F45 -> 0 | G46: =0.0614*G45 -> 0 | H46: =0.0614*H45 -> 0 | I46: =0.0614*I45 -> 0 | ... AF46: =0.0614*AF45 -> 0
A47: - Shipping
A48: Total Revenue | B48: =SUM(B8+B25+B35) -> 17178.81 | C48: =SUM(C8+C25+C35) -> 12596.87 | D48: =SUM(D8+D25+D35) -> 14429.86 | E48: =SUM(E8+E25+E35) -> 10171.31 | F48: =SUM(F8+F25+F35) -> 10354.06 | G48: =SUM(G8+G25+G35) -> 10648.64 | H48: =SUM(H8+H25+H35) -> 10805.22 | I48: =SUM(I8+I25+I35) -> 98430.12 | ... AF48: =SUM(AF8+AF25+AF35) -> 63685.19
A50: B2B Revenue
A51: Best Buy | B51: =iferror(sum(B52:B54),"") -> 0 | C51: =sum(C52:C54) -> 317.3586 | D51: =sum(D52:D54) -> 317.3586 | E51: =sum(E52:E54) -> 1269.4344 | F51: =sum(F52:F54) -> 1904.1516 | G51: =sum(G52:G54) -> 0 | H51: =sum(H52:H54) -> 317.3586 | I51: =sum(I52:I54) -> 317.3586 | J51: =sum(J52:J54) -> 952.0758 | ... AF51: =sum(AF52:AF54) -> 253.6746
A52: - Hardware | B52: 0 | C52: 299 | D52: 299 | E52: 1196 | F52: 1794 | G52: 0 | H52: 299 | I52: 299 | J52: 897 | K52: 299 | L52: 299 | M52: 1495 | N52: 0 | O52: 0 | P52: 897 | Q52: 598 | R52: 0 | S52: 0 | T52: 0 | U52: 0 | V52: 0 | W52: 1196 | X52: 0 | Y52: 0 | Z52: 956 | AA52: 239 | AB52: 0 | AC52: 239 | AD52: 478 | AE52: 239 | AF52: 239
A53: - Tax | B53: =B52*'Data - P&L'!$U$3 -> 0 | C53: =C52*'Data - P&L'!$U$3 -> 18.3586 | D53: =D52*'Data - P&L'!$U$3 -> 18.3586 | E53: =E52*'Data - P&L'!$U$3 -> 73.4344 | F53: =F52*'Data - P&L'!$U$3 -> 110.1516 | G53: =G52*'Data - P&L'!$U$3 -> 0 | H53: =H52*'Data - P&L'!$U$3 -> 18.3586 | I53: =I52*'Data - P&L'!$U$3 -> 18.3586 | ... AF53: =AF52*'Data - P&L'!$U$3 -> 14.6746
A54: - Shipping
A55: Target | B55: =sum(B56:B58) -> 0 | C55: =sum(C56:C58) -> 0 | D55: =sum(D56:D58) -> 0 | E55: =sum(E56:E58) -> 0 | F55: =sum(F56:F58) -> 0 | G55: =sum(G56:G58) -> 0 | H55: =sum(H56:H58) -> 0 | I55: =sum(I56:I58) -> 0 | ... AF55: =sum(AF56:AF58) -> 246.2448
A56: - Hardware | B56: 0 | C56: 0 | D56: 0 | E56: 0 | F56: 0 | G56: 0 | H56: 0 | I56: 0 | J56: 0 | K56: 0 | L56: 0 | M56: 0 | N56: 0 | O56: 2070 | P56: 1475 | Q56: 600 | R56: 0 | S56: 0 | T56: 0 | U56: 585 | V56: 300 | W56: 300 | X56: 590 | Y56: 0 | Z56: 300 | AA56: 839 | AB56: 1357 | AC56: 1842 | AD56: 1185 | AE56: 433 | AF56: 232
A57: - Tax | B57: =B56*'Data - P&L'!$U$3 -> 0 | C57: =C56*'Data - P&L'!$U$3 -> 0 | D57: =D56*'Data - P&L'!$U$3 -> 0 | E57: =E56*'Data - P&L'!$U$3 -> 0 | F57: =F56*'Data - P&L'!$U$3 -> 0 | G57: =G56*'Data - P&L'!$U$3 -> 0 | H57: =H56*'Data - P&L'!$U$3 -> 0 | I57: =I56*'Data - P&L'!$U$3 -> 0 | ... AF57: =AF56*'Data - P&L'!$U$3 -> 14.2448
A58: - Shipping
A59: Total Revenue | B59: =B51+B55+B44+B31 -> 0 | C59: =C51+C55+C44+C31 -> 317.3586 | D59: =D51+D55+D44+D31 -> 317.3586 | E59: =E51+E55+E44+E31 -> 1269.4344 | F59: =F51+F55+F44+F31 -> 1904.1516 | G59: =G51+G55+G44+G31 -> 0 | H59: =H51+H55+H44+H31 -> 638.7886 | I59: =I51+I55+I44+I31 -> 634.2986 | ... AF59: =AF51+AF55+AF44+AF31 -> 499.9194
A61: App Revenue
A62: - Google Store | B62: ='App - P&L'!B90 -> 2632.28 | C62: ='App - P&L'!C90 -> 2930.3325 | D62: ='App - P&L'!D90 -> 358.411 | E62: ='App - P&L'!E90 -> 224.5105 | F62: ='App - P&L'!F90 -> 197.098 | G62: ='App - P&L'!G90 -> 224.264 | H62: ='App - P&L'!H90 -> 347.463 | I62: ='App - P&L'!I90 -> 187.3995 | ... AF62: ='App - P&L'!AF90 -> 542.232
A63: - Apple Store | B63: ='App - P&L'!B91 -> 6519.6523 | C63: ='App - P&L'!C91 -> 5328.5311 | D63: ='App - P&L'!D91 -> 733.77937 | E63: ='App - P&L'!E91 -> 927.82951 | F63: ='App - P&L'!F91 -> 873.18108 | G63: ='App - P&L'!G91 -> 1086.1573 | H63: ='App - P&L'!H91 -> 851.22588 | I63: ='App - P&L'!I91 -> 884.59175 | ... AF63: ='App - P&L'!AF91 -> 1768.2491
A64: - Comission | B64: ='App - P&L'!B67 -> 3258.6567 | C64: ='App - P&L'!C67 -> 2800.7737 | D64: ='App - P&L'!D67 -> 377.72587 | E64: ='App - P&L'!E67 -> 437.26072 | F64: ='App - P&L'!F67 -> 409.00246 | G64: ='App - P&L'!G67 -> 505.072 | H64: ='App - P&L'!H67 -> 426.12809 | I64: ='App - P&L'!I67 -> 412.18125 | ... AF64: ='App - P&L'!AF67 -> 853.50906
A65: - Tax | B65: ='App - P&L'!B68 -> 0 | C65: ='App - P&L'!C68 -> 0 | D65: ='App - P&L'!D68 -> 0 | E65: ='App - P&L'!E68 -> 0 | F65: ='App - P&L'!F68 -> 0 | G65: ='App - P&L'!G68 -> 0 | H65: ='App - P&L'!H68 -> 0 | I65: ='App - P&L'!I68 -> 0 | ... AF65: ='App - P&L'!AF68 -> 0
A66: Total Revenue | B66: =sum(B62:B65) -> 12410.589 | C66: =sum(C62:C65) -> 11059.637 | D66: =sum(D62:D65) -> 1469.9162 | E66: =sum(E62:E65) -> 1589.6007 | F66: =sum(F62:F65) -> 1479.2815 | G66: =sum(G62:G65) -> 1815.4933 | H66: =sum(H62:H65) -> 1624.817 | I66: =sum(I62:I65) -> 1484.1725 | ... AF66: =sum(AF62:AF65) -> 3163.9902
A69: DTC Orders | B69: =sum(B70,B76) -> 58 | C69: =sum(C70,C76) -> 36 | D69: =sum(D70,D76) -> 35 | E69: =sum(E70,E76) -> 37 | F69: =sum(F70,F76) -> 41 | G69: =sum(G70,G76) -> 39 | H69: =sum(H70,H76) -> 29 | I69: =sum(I70,I76) -> 27 | ... AF69: =sum(AF70,AF76) -> 163
A70: - DTC Orders US&CA | B70: 58 | C70: 36 | D70: 35 | E70: 37 | F70: 41 | G70: 39 | H70: 29 | I70: 27 | J70: 45 | K70: 41 | L70: 41 | M70: 35 | N70: 41 | O70: 36 | P70: 241 | Q70: 156 | R70: 111 | S70: 81 | T70: 72 | U70: 62 | V70: 61 | W70: 60 | X70: 74 | Y70: 75 | Z70: 116 | AA70: 177 | AB70: 159 | AC70: 109 | AD70: 104 | AE70: 121 | AF70: 144
A71: - Hardware (units sold) | B71: =sum('DTC US&CA - P&L'!B23:B30,'DTC US&CA - P&L'!B33:B34) -> 19 | C71: =sum('DTC US&CA - P&L'!C23:C30,'DTC US&CA - P&L'!C33:C34) -> 14 | D71: =sum('DTC US&CA - P&L'!D23:D30,'DTC US&CA - P&L'!D33:D34) -> 16 | E71: =sum('DTC US&CA - P&L'!E23:E30,'DTC US&CA - P&L'!E33:E34) -> 12 | F71: =sum('DTC US&CA - P&L'!F23:F30,'DTC US&CA - P&L'!F33:F34) -> 18 | G71: =sum('DTC US&CA - P&L'!G23:G30,'DTC US&CA - P&L'!G33:G34) -> 11 | H71: =sum('DTC US&CA - P&L'!H23:H30,'DTC US&CA - P&L'!H33:H34) -> 13 | I71: =sum('DTC US&CA - P&L'!I23:I30,'DTC US&CA - P&L'!I33:I34) -> 13 | ... AF71: =sum('DTC US&CA - P&L'!AF23:AF30,'DTC US&CA - P&L'!AF33:AF34) -> 105
A72: - Add-ons (units sold) | B72: =sum('DTC US&CA - P&L'!B37:B47) -> 41 | C72: =sum('DTC US&CA - P&L'!C37:C47) -> 11 | D72: =sum('DTC US&CA - P&L'!D37:D47) -> 11 | E72: =sum('DTC US&CA - P&L'!E37:E47) -> 7 | F72: =sum('DTC US&CA - P&L'!F37:F47) -> 10 | G72: =sum('DTC US&CA - P&L'!G37:G47) -> 14 | H72: =sum('DTC US&CA - P&L'!H37:H47) -> 9 | I72: =sum('DTC US&CA - P&L'!I37:I47) -> 8 | ... AF72: =sum('DTC US&CA - P&L'!AF37:AF47) -> 144
A73: - Merch (units sold) | B73: 0 | C73: 0 | D73: 0 | E73: 0 | F73: 0 | G73: 0 | H73: 0 | I73: 0 | J73: 21 | K73: 0 | L73: 0 | M73: 0 | N73: 0 | O73: 0 | P73: 0 | Q73: 0 | R73: 0 | S73: 0 | T73: 0 | U73: 0 | V73: 0 | W73: 0 | X73: 0 | Y73: 0 | Z73: 0 | AA73: 0 | AB73: 0 | AC73: 0 | AD73: 1 | AE73: 0 | AF73: 0
A74: - Seeds (units sold) | B74: ='DTC US&CA - P&L'!B58 -> 23 | C74: ='DTC US&CA - P&L'!C58 -> 15 | D74: ='DTC US&CA - P&L'!D58 -> 18 | E74: ='DTC US&CA - P&L'!E58 -> 21 | F74: ='DTC US&CA - P&L'!F58 -> 23 | G74: ='DTC US&CA - P&L'!G58 -> 17 | H74: ='DTC US&CA - P&L'!H58 -> 12 | I74: ='DTC US&CA - P&L'!I58 -> 9 | ... AF74: ='DTC US&CA - P&L'!AF58 -> 17
A75: - BB 1 year Pro Subscription | B75: 11 | C75: 8 | D75: 4 | E75: 3 | F75: 2 | G75: 3 | H75: 1 | I75: 1 | J75: 3 | K75: 8 | L75: 2 | M75: 6 | N75: 13 | O75: 9 | P75: 14 | Q75: 13 | R75: 11 | S75: 7 | T75: 6 | U75: 6 | V75: 6 | W75: 9 | X75: 10 | Y75: 9 | Z75: 40 | AA75: 80 | AB75: 64 | AC75: 30 | AD75: 34 | AE75: 50 | AF75: 67
A76: - DTC Orders EUROPE | K76: 1 | Q76: 3 | R76: 16 | S76: 13 | T76: 7 | U76: 1 | V76: 6 | W76: 3 | X76: 0 | Y76: 7 | Z76: 4 | AA76: 2 | AB76: 8 | AC76: 7 | AD76: 21 | AE76: 19 | AF76: 19
A77: - Hardware (units sold) | K77: 2 | Q77: =sum('DTC EU - P&L'!Q23:Q30) -> 4 | R77: =sum('DTC EU - P&L'!R23:R30) -> 19 | S77: =sum('DTC EU - P&L'!S23:S30) -> 13 | T77: =sum('DTC EU - P&L'!T23:T30) -> 6 | U77: =sum('DTC EU - P&L'!U23:U30) -> 1 | V77: =sum('DTC EU - P&L'!V23:V30) -> 5 | W77: =sum('DTC EU - P&L'!W23:W30) -> 3 | X77: =sum('DTC EU - P&L'!X23:X30) -> 0 | ... AF77: =sum('DTC EU - P&L'!AF23:AF30) -> 22
A78: - Add-ons (units sold) | K78: 0 | Q78: =sum('DTC EU - P&L'!Q37:Q44) -> 11 | R78: =sum('DTC EU - P&L'!R37:R44) -> 9 | S78: =sum('DTC EU - P&L'!S37:S44) -> 8 | T78: =sum('DTC EU - P&L'!T37:T44) -> 5 | U78: =sum('DTC EU - P&L'!U37:U44) -> 0 | V78: =sum('DTC EU - P&L'!V37:V44) -> 3 | W78: =sum('DTC EU - P&L'!W37:W44) -> 1 | X78: =sum('DTC EU - P&L'!X37:X44) -> 0 | ... AF78: =sum('DTC EU - P&L'!AF37:AF44) -> 21
A79: - Merch (units sold) | K79: 0 | Q79: 0 | R79: 0 | S79: 0 | T79: 0 | U79: 0 | V79: 0 | W79: 0 | X79: 0 | Y79: 0 | Z79: 0 | AA79: 0 | AB79: 0 | AC79: 0 | AD79: 0 | AE79: 0 | AF79: 0
A80: - Seeds (units sold) | K80: 0 | Q80: 0 | R80: 0 | S80: 0 | T80: 0 | U80: 0 | V80: 0 | W80: 0 | X80: 0 | Y80: 0 | Z80: 0 | AA80: 0 | AB80: 0 | AC80: 0 | AD80: 0 | AE80: 0 | AF80: 0
A81: - BB 1 year Pro Subscription | K81: 0 | Q81: 0 | R81: 0 | S81: 0 | T81: 0 | U81: 0 | V81: 0 | W81: 0 | X81: 0 | Y81: 0 | Z81: 0 | AA81: 0 | AB81: 0 | AC81: 0 | AD81: 0 | AE81: 0 | AF81: 0
A82: Amazon Orders | B82: 40 | C82: 29 | D82: 28 | E82: 20 | F82: 20 | G82: 25 | H82: 21 | I82: 527 | J82: 348 | K82: 24 | L82: 23 | M82: 26 | N82: 30 | O82: 28 | P82: 26 | Q82: 55 | R82: 30 | S82: 29 | T82: 29 | U82: 31 | V82: 21 | W82: 35 | X82: 24 | Y82: 49 | Z82: 42 | AA82: 115 | AB82: 67 | AC82: 56 | AD82: 47 | AE82: 56 | AF82: 101
A83: - Hardware (units sold) | B83: =SUM('AMAZON - P&L'!B28:B35, 'AMAZON - P&L'!B38:B39) -> 27 | C83: =SUM('AMAZON - P&L'!C28:C35, 'AMAZON - P&L'!C38:C39) -> 23 | D83: =SUM('AMAZON - P&L'!D28:D35, 'AMAZON - P&L'!D38:D39) -> 24 | E83: =SUM('AMAZON - P&L'!E28:E35, 'AMAZON - P&L'!E38:E39) -> 16 | F83: =SUM('AMAZON - P&L'!F28:F35, 'AMAZON - P&L'!F38:F39) -> 8 | G83: =SUM('AMAZON - P&L'!G28:G35, 'AMAZON - P&L'!G38:G39) -> 17 | H83: =SUM('AMAZON - P&L'!H28:H35, 'AMAZON - P&L'!H38:H39) -> 17 | I83: =SUM('AMAZON - P&L'!I28:I35, 'AMAZON - P&L'!I38:I39) -> 412 | ... AF83: =SUM('AMAZON - P&L'!AF28:AF35, 'AMAZON - P&L'!AF38:AF39) -> 92
A84: - Add-ons (units sold) | B84: =SUM('AMAZON - P&L'!B42:B49) -> 7 | C84: =SUM('AMAZON - P&L'!C42:C49) -> 6 | D84: =SUM('AMAZON - P&L'!D42:D49) -> 8 | E84: =SUM('AMAZON - P&L'!E42:E49) -> 6 | F84: =SUM('AMAZON - P&L'!F42:F49) -> 11 | G84: =SUM('AMAZON - P&L'!G42:G49) -> 6 | H84: =SUM('AMAZON - P&L'!H42:H49) -> 7 | I84: =SUM('AMAZON - P&L'!I42:I49) -> 43 | ... AF84: =SUM('AMAZON - P&L'!AF42:AF49) -> 18
A85: Walmart Orders | B85: 0 | C85: 0 | D85: 0 | E85: 0 | F85: 0 | G85: 0 | H85: 1 | I85: 1 | J85: 0 | K85: 0 | L85: 0 | M85: 0 | N85: 0 | O85: 0 | P85: 0 | Q85: 0 | R85: 0 | S85: 0 | T85: 0 | U85: 1 | V85: 0 | W85: 0 | X85: 0 | Y85: 0 | Z85: 0 | AA85: 1 | AB85: 0 | AC85: 0 | AD85: 1 | AE85: 0 | AF85: 0
A86: - Hardware (units sold) | B86: 0 | C86: 0 | D86: 0 | E86: 0 | F86: 0 | G86: 0 | H86: 1 | I86: 1 | J86: 0 | K86: 0 | L86: 0 | M86: 0 | N86: 0 | O86: 0 | P86: 0 | Q86: 0 | R86: 0 | S86: 0 | T86: 0 | U86: 1 | V86: 0 | W86: 0 | X86: 0 | Y86: 0 | Z86: 0 | AA86: 1 | AB86: 0 | AC86: 0 | AD86: 1 | AE86: 0 | AF86: 0
A87: Digital Marketplaces Orders | B87: =SUM(B88:B89) -> 0 | C87: =SUM(C88:C89) -> 0 | D87: =SUM(D88:D89) -> 0 | E87: =SUM(E88:E89) -> 0 | F87: =SUM(F88:F89) -> 0 | G87: =SUM(G88:G89) -> 0 | H87: =SUM(H88:H89) -> 0 | I87: =SUM(I88:I89) -> 0 | ... AF87: =SUM(AF88:AF89) -> 0
A88: Rachio Orders | B88: 0 | C88: 0 | D88: 0 | E88: 0 | F88: 0 | G88: 0 | H88: 0 | I88: 0 | J88: 0 | K88: 0 | L88: 0 | M88: 0 | N88: 0 | O88: 1 | P88: 0 | Q88: 0 | R88: 0 | S88: 0 | T88: 0 | U88: 0 | V88: 1 | W88: 0 | X88: 0 | Y88: 0 | Z88: 0 | AA88: 0 | AB88: 0 | AC88: 1 | AD88: 0 | AE88: 0 | AF88: 0
A89: Weatherflow Orders | B89: 0 | C89: 0 | D89: 0 | E89: 0 | F89: 0 | G89: 0 | H89: 0 | I89: 0 | J89: 0 | K89: 0 | L89: 0 | M89: 0 | N89: 0 | O89: 0 | P89: 0 | Q89: 0 | R89: 0 | S89: 0 | T89: 0 | U89: 0 | V89: 0 | W89: 0 | X89: 0 | Y89: 0 | Z89: 0 | AA89: 0 | AB89: 0 | AC89: 0 | AD89: 0 | AE89: 0 | AF89: 0
A90: Costco Orders | AF90: 4
A91: Total Orders | B91: =SUM(B69+B82+B88+B89) -> 98 | C91: =SUM(C69+C82+C88+C89) -> 65 | D91: =SUM(D69+D82+D88+D89) -> 63 | E91: =SUM(E69+E82+E88+E89) -> 57 | F91: =SUM(F69+F82+F88+F89) -> 61 | G91: =SUM(G69+G82+G88+G89) -> 64 | H91: =SUM(H69+H82+H88+H89) -> 50 | I91: =SUM(I69+I82+I88+I89) -> 554 | ... AF91: =SUM(AF69+AF82+AF88+AF89) -> 264
A93: B2B Orders
A94: Best Buy | B94: 0 | C94: 1 | D94: 1 | E94: 4 | F94: 6 | G94: 0 | H94: 1 | I94: 1 | J94: 3 | K94: 1 | L94: 1 | M94: 5 | N94: 0 | O94: 0 | P94: 3 | Q94: 2 | R94: 0 | S94: 0 | T94: 0 | U94: 0 | V94: 0 | W94: 4 | X94: 0 | Y94: 0 | Z94: 4 | AA94: 1 | AB94: 0 | AC94: 1 | AD94: 2 | AE94: 1 | AF94: 1
A95: Target | B95: 0 | C95: 0 | D95: 0 | E95: 0 | F95: 0 | G95: 0 | H95: 0 | I95: 0 | J95: 0 | K95: 0 | L95: 0 | M95: 0 | N95: 0 | O95: 7 | P95: 5 | Q95: 2 | R95: 0 | S95: 0 | T95: 0 | U95: 2 | V95: 1 | W95: 1 | X95: 2 | Y95: 0 | Z95: 1 | AA95: 3 | AB95: 6 | AC95: 8 | AD95: 5 | AE95: 2 | AF95: 1
A96: Total Orders | B96: =B94+B95+B90+B85 -> 0 | C96: =C94+C95+C90+C85 -> 1 | D96: =D94+D95+D90+D85 -> 1 | E96: =E94+E95+E90+E85 -> 4 | F96: =F94+F95+F90+F85 -> 6 | G96: =G94+G95+G90+G85 -> 0 | H96: =H94+H95+H90+H85 -> 2 | I96: =I94+I95+I90+I85 -> 2 | ... AF96: =AF94+AF95+AF90+AF85 -> 6
A98: App Orders
A99: - Google Store | B99: ='App - P&L'!B17 -> 103 | C99: ='App - P&L'!C17 -> 120 | D99: ='App - P&L'!D17 -> 21 | E99: ='App - P&L'!E17 -> 21 | F99: ='App - P&L'!F17 -> 18 | G99: ='App - P&L'!G17 -> 13 | H99: ='App - P&L'!H17 -> 22 | I99: ='App - P&L'!I17 -> 21 | ... AF99: ='App - P&L'!AF17 -> 18
A100: - Apple Store | B100: ='App - P&L'!B14 -> 380 | C100: ='App - P&L'!C14 -> 307 | D100: ='App - P&L'!D14 -> 121 | E100: ='App - P&L'!E14 -> 115 | F100: ='App - P&L'!F14 -> 90 | G100: ='App - P&L'!G14 -> 94 | H100: ='App - P&L'!H14 -> 94 | I100: ='App - P&L'!I14 -> 95 | ... AF100: ='App - P&L'!AF14 -> 118
A101: Total Orders | B101: =sum(B99:B100) -> 483 | C101: =sum(C99:C100) -> 427 | D101: =sum(D99:D100) -> 142 | E101: =sum(E99:E100) -> 136 | F101: =sum(F99:F100) -> 108 | G101: =sum(G99:G100) -> 107 | H101: =sum(H99:H100) -> 116 | I101: =sum(I99:I100) -> 116 | ... AF101: =sum(AF99:AF100) -> 136
A102: - Meta Spend US (EUR) | B102: 1559.32 | C102: 1766.79 | D102: 1415.63 | E102: 1602.44 | F102: 1757.91 | G102: 1950.43 | H102: 1678.55 | I102: 1577 | J102: 2157.98 | K102: 2547.93 | L102: 2306.11 | M102: 1759.03 | N102: 2079.78 | O102: 2330.2 | P102: 2857.78 | Q102: 12113.32 | R102: 6733.74 | S102: 3074.15 | T102: 2868.51 | U102: 2822.46 | V102: 1191.31 | W102: 0 | X102: 3577.05 | Y102: 4724.98 | Z102: 24874.97 | AA102: 26154.52 | AB102: 27814.85 | AC102: 9934.19 | AD102: 8230.84 | AE102: 13937.84 | AF102: 28192.79
A103: - Meta Spend EU (EUR | Q103: 149.19 | R103: 363 | S103: 375.8 | T103: 422.99 | U103: 402.58 | V103: 732.76 | W103: 136.26 | X103: 0 | Y103: 0 | Z103: 0 | AA103: 0 | AB103: 106.41 | AC103: 415.69 | AD103: 1263.43 | AE103: 2128.78 | AF103: 2485.07
A104: Currency rate | B104: 1.1068 | C104: 1.1047 | D104: 1.1035 | E104: 1.098 | F104: 1.0982 | G104: 1.097 | H104: 1.0976 | I104: 1.098 | J104: 1.0941 | K104: 1.0934 | L104: 1.0948 | M104: 1.0943 | N104: 1.0939 | O104: 1.0909 | P104: 1.089 | Q104: 1.0859 | R104: 1.0831 | S104: 1.0874 | T104: 1.0872 | U104: 1.0869 | V104: 1.0817 | W104: 1.0798 | X104: 1.0782 | Y104: 1.0827 | Z104: 1.08 | AA104: 1.0801 | AB104: 1.0797 | AC104: 1.0815 | AD104: 1.0821 | AE104: 1.0859 | AF104: 1.0884
A105: Meta Spend | B105: =sum(B106,B107) -> 1725.8554 | C105: =sum(C106,C107) -> 1951.7729 | D105: =sum(D106,D107) -> 1562.1477 | E105: =sum(E106,E107) -> 1759.4791 | F105: =sum(F106,F107) -> 1930.5368 | G105: =sum(G106,G107) -> 2139.6217 | H105: =sum(H106,H107) -> 1842.3765 | I105: =sum(I106,I107) -> 1731.546 | ... AF105: =sum(AF106,AF107) -> 33389.783
A106: - Meta US | B106: =B102*B104 -> 1725.8554 | C106: =C102*C104 -> 1951.7729 | D106: =D102*D104 -> 1562.1477 | E106: =E102*E104 -> 1759.4791 | F106: =F102*F104 -> 1930.5368 | G106: =G102*G104 -> 2139.6217 | H106: =H102*H104 -> 1842.3765 | I106: =I102*I104 -> 1731.546 | ... AF106: =AF102*AF104 -> 30685.033
A107: - Meta EU | Q107: =Q103*Q104 -> 162.00542 | R107: =R103*R104 -> 393.1653 | S107: =S103*S104 -> 408.64492 | T107: =T103*T104 -> 459.87473 | U107: =U103*U104 -> 437.5642 | V107: =V103*V104 -> 792.62649 | W107: =W103*W104 -> 147.13355 | X107: =X103*X104 -> 0 | ... AF107: =AF103*AF104 -> 2704.7502
A108: Google Spend | B108: 518.87 | C108: 512.42 | D108: 548.46 | E108: 476.27 | F108: 289.02 | G108: 399.65 | H108: 321.04 | I108: 296.38 | J108: 246.17 | K108: 421.23 | L108: 224.42 | M108: 221.06 | N108: 246.04 | O108: 858.46 | P108: 488.67 | Q108: 407.14 | R108: 2334.06 | S108: 637.47 | T108: 848.28 | U108: 1013.32 | V108: 866.82 | W108: 1423.11 | X108: 809.26 | Y108: 983.89 | Z108: 1816.63 | AA108: 5083.5 | AB108: 2664.98 | AC108: 1524.21 | AD108: 1169.38 | AE108: 965.95 | AF108: 1171.76
A109: - Google Spend US | B109: 518.87 | C109: 512.42 | D109: 548.46 | E109: 476.27 | F109: 289.02 | G109: 399.65 | H109: 321.04 | I109: 296.38 | J109: 246.17 | K109: 421.23 | L109: 224.42 | M109: 221.06 | N109: 246.04 | O109: 858.46 | P109: 488.67 | Q109: =Q108-Q110 -> 407.14 | R109: =R108-R110 -> 2334.06 | S109: =S108-S110 -> 637.47 | T109: =T108-T110 -> 845.75 | U109: =U108-U110 -> 1011.6 | V109: =V108-V110 -> 865.57 | W109: =W108-W110 -> 1423.11 | X109: =X108-X110 -> 809.26 | ... AF109: =AF108-AF110 -> 1170.92
A110: - Google Spend EU | Q110: 0 | R110: 0 | S110: 0 | T110: =1.92+0.61 -> 2.53 | U110: =1.72 -> 1.72 | V110: 1.25 | W110: 0 | X110: 0 | Y110: 0 | Z110: 2.04 | AA110: 0 | AB110: 0.38 | AC110: 0 | AD110: 2.15 | AE110: 0.37 | AF110: =0.29+0.55 -> 0.84
...

Sheet DTC - P&L
A1: OCTOBER | B1: 45566 | C1: 45567 | D1: 45568 | E1: 45569 | F1: 45570 | G1: 45571 | H1: 45572 | I1: 45573 | J1: 45574 | K1: 45575 | L1: 45576 | M1: 45577 | N1: 45578 | O1: 45579 | P1: 45580 | Q1: 45581 | R1: 45582 | S1: 45583 | T1: 45584 | U1: 45585 | V1: 45586 | W1: 45587 | X1: 45588 | Y1: 45589 | Z1: 45590 | AA1: 45591 | AB1: 45592 | AC1: 45593 | AD1: 45594 | AE1: 45595 | AF1: 45596
A2: DAY | B2: TUE | C2: WED | D2: THU | E2: FRI | F2: SAT | G2: SUN | H2: MON | I2: TUE | J2: WED | K2: THU | L2: FRI | M2: SAT | N2: SUN | O2: MON | P2: TUE | Q2: WED | R2: THU | S2: FRI | T2: SAT | U2: SUN | V2: MON | W2: TUE | X2: WED | Y2: THU | Z2: FRI | AA2: SAT | AB2: SUN | AC2: MON | AD2: TUE | AE2: WED | AF2: THU
A3: COMMENT
A4: Orders
A5: Meta | B5: 5 | C5: 7 | D5: 5 | E5: 6 | F5: 11 | G5: 4 | H5: 4 | I5: 7 | J5: 5 | K5: 9 | L5: 5 | M5: 3 | N5: 11 | O5: 8 | P5: 90 | Q5: 38 | R5: 26 | S5: 9 | T5: 10 | U5: 6 | V5: 6 | W5: 2 | X5: 24 | Y5: 21 | Z5: 54 | AA5: 78 | AB5: 82 | AC5: 46 | AD5: 40 | AE5: 57 | AF5: 81 | AG5: =SUM(B5:AF5) -> 760
A6: Google | B6: 5 | C6: 2 | D6: 1 | E6: 6 | F6: 2 | G6: 0 | H6: 3 | I6: 6 | J6: 3 | K6: 3 | L6: 4 | M6: 4 | N6: 2 | O6: 7 | P6: 9 | Q6: 11 | R6: 10 | S6: 8 | T6: 10 | U6: 6 | V6: 3 | W6: 15 | X6: 7 | Y6: 9 | Z6: 18 | AA6: 29 | AB6: 23 | AC6: 15 | AD6: 14 | AE6: 18 | AF6: 16 | AG6: =SUM(B6:AF6) -> 269
A7: TikTok | B7: 0 | C7: 0 | D7: 0 | E7: 0 | F7: 0 | G7: 0 | H7: 0 | I7: 0 | J7: 0 | K7: 0 | L7: 0 | M7: 0 | N7: 0 | O7: 0 | P7: 0 | Q7: 0 | R7: 0 | S7: 0 | T7: 0 | U7: 0 | V7: 0 | W7: 0 | X7: 0 | Y7: 0 | Z7: 0 | AA7: 0 | AB7: 0 | AC7: 0 | AD7: 0 | AE7: 0 | AF7: 0 | AG7: =SUM(B7:AF7) -> 0
A8: Bing | B8: 6 | C8: 2 | D8: 0 | E8: 0 | F8: 4 | G8: 2 | H8: 0 | I8: 0 | J8: 2 | K8: 0 | L8: 0 | M8: 0 | N8: 0 | O8: 0 | P8: 0 | Q8: 2 | R8: 2 | S8: 2 | T8: 14 | U8: 2 | V8: 6 | W8: 2 | X8: 0 | Y8: 0 | Z8: 4 | AA8: 18 | AB8: 8 | AC8: 10 | AD8: 12 | AE8: 12 | AF8: 4 | AG8: =SUM(B8:AF8) -> 114
A9: Email | B9: 0 | C9: 0 | D9: 0 | E9: 0 | F9: 0 | G9: 0 | H9: 0 | I9: 0 | J9: 0 | K9: 0 | L9: 0 | M9: 0 | N9: 0 | O9: 0 | P9: 0 | Q9: 0 | R9: 0 | S9: 0 | T9: 0 | U9: 0 | V9: 0 | W9: 0 | X9: 0 | Y9: 0 | Z9: 0 | AA9: 1 | AB9: 0 | AC9: 0 | AD9: 0 | AE9: 0 | AF9: 0 | AG9: =SUM(B9:AF9) -> 1
A10: Nextdoor | B10: - | C10: - | D10: - | E10: - | F10: - | G10: - | H10: - | I10: - | J10: - | K10: - | L10: - | M10: - | N10: - | O10: - | P10: - | Q10: - | R10: - | S10: - | T10: - | U10: - | V10: - | W10: - | X10: - | Y10: - | Z10: - | AA10: - | AB10: - | AC10: - | AD10: - | AE10: - | AF10: - | AG10: =SUM(B10:AF10) -> 0
A11: Affiliates (Refersion) | B11: - | C11: - | D11: - | E11: - | F11: - | G11: - | H11: - | I11: - | J11: - | K11: - | L11: - | M11: - | N11: - | O11: - | P11: - | Q11: - | R11: - | S11: - | T11: - | U11: - | V11: - | W11: - | X11: - | Y11: - | Z11: - | AA11: - | AB11: - | AC11: - | AD11: - | AE11: - | AF11: - | AG11: =SUM(B11:AF11) -> 0
A12: All | B12: =SUM(B5:B11) -> 16 | C12: =SUM(C5:C11) -> 11 | D12: =SUM(D5:D11) -> 6 | E12: =SUM(E5:E11) -> 12 | F12: =SUM(F5:F11) -> 17 | G12: =SUM(G5:G11) -> 6 | H12: =SUM(H5:H11) -> 7 | I12: =SUM(I5:I11) -> 13 | ... AF12: =SUM(AF5:AF11) -> 101 | AG12: =SUM(B12:AF12) -> 1144
A14: Revenue | B14: 1249.67 | C14: 2160.17 | D14: 1262.27 | E14: 1601.25 | F14: 4263.3 | G14: 770.99 | H14: 1212.42 | I14: 2037.42 | J14: 1855.56 | K14: 2119.42 | L14: 2091.83 | M14: 675.23 | N14: 4148.38 | O14: 1610.67 | P14: 16216.21 | Q14: 6608.06 | R14: 4413.13 | S14: 1355.13 | T14: 2593.47 | U14: 871.98 | V14: 1734.46 | W14: 229.76 | X14: 4385.9 | Y14: 3792 | Z14: 12458.26 | AA14: 21772.43 | AB14: 23101.52 | AC14: 11489.8 | AD14: 11706.73 | AE14: 15443.87 | AF14: 20854.99
A15: Meta | B15: =B14*Summary!B104 -> 1383.1348 | C15: =C14*Summary!C104 -> 2386.3398 | D15: =D14*Summary!D104 -> 1392.9149 | E15: =E14*Summary!E104 -> 1758.1725 | F15: =F14*Summary!F104 -> 4681.9561 | G15: =G14*Summary!G104 -> 845.77603 | H15: =H14*Summary!H104 -> 1330.7522 | I15: =I14*Summary!I104 -> 2237.0872 | ... AF15: =AF14*Summary!AF104 -> 22698.571 | AG15: =SUM(B15:AF15) -> 201979.57
A16: Google | B16: 1741.89 | C16: 625.91 | D16: 322.24 | E16: 1739.95 | F16: 1124.36 | G16: 0 | H16: 410.93 | I16: 1386.71 | J16: 924.96 | K16: 372.88 | L16: 688.81 | M16: 1185.66 | N16: 134.57 | O16: 2032.86 | P16: 2330.5 | Q16: 3728.37 | R16: 2872.01 | S16: 1745.14 | T16: 2768.92 | U16: 1388.49 | V16: 697.74 | W16: 2692.7 | X16: 1548.93 | Y16: 1801.58 | Z16: 4996.37 | AA16: 8857.5 | AB16: 5252.25 | AC16: 3933.33 | AD16: 3910.89 | AE16: 3802.57 | AF16: 4672.67 | AG16: =SUM(B16:AF16) -> 69691.69
A17: TikTok | B17: 0 | C17: 0 | D17: 0 | E17: 0 | F17: 0 | G17: 0 | H17: 0 | I17: 0 | J17: 0 | K17: 0 | L17: 0 | M17: 0 | N17: 0 | O17: 0 | P17: 0 | Q17: 0 | R17: 0 | S17: 0 | T17: 0 | U17: 0 | V17: 0 | W17: 0 | X17: 0 | Y17: 0 | Z17: 0 | AA17: 0 | AB17: 0 | AC17: 0 | AD17: 0 | AE17: 0 | AF17: 0 | AG17: =SUM(B17:AF17) -> 0
A18: Bing | B18: 753 | C18: 251 | D18: 0 | E18: 0 | F18: 502 | G18: 251 | H18: 0 | I18: 0 | J18: 251 | K18: 0 | L18: 0 | M18: 0 | N18: 0 | O18: 0 | P18: 0 | Q18: 251 | R18: 251 | S18: 251 | T18: 1757 | U18: 251 | V18: 753 | W18: 251 | X18: 0 | Y18: 0 | Z18: 502 | AA18: 2259 | AB18: 1004 | AC18: 1255 | AD18: 1506 | AE18: 1506 | AF18: 502 | AG18: =SUM(B18:AF18) -> 14307
A19: Email | B19: 0 | C19: 0 | D19: 0 | E19: 0 | F19: 0 | G19: 0 | H19: 0 | I19: 0 | J19: 0 | K19: 0 | L19: 0 | M19: 0 | N19: 0 | O19: 0 | P19: 0 | Q19: 0 | R19: 0 | S19: 0 | T19: 0 | U19: 0 | V19: 0 | W19: 0 | X19: 0 | Y19: 0 | Z19: 0 | AA19: 94.89 | AB19: 0 | AC19: 0 | AD19: 0 | AE19: 0 | AF19: 0 | AG19: =SUM(B19:AF19) -> 94.89
A20: Nextdoor | B20: - | C20: - | D20: - | E20: - | F20: - | G20: - | H20: - | I20: - | J20: - | K20: - | L20: - | M20: - | N20: - | O20: - | P20: - | Q20: - | R20: - | S20: - | T20: - | U20: - | V20: - | W20: - | X20: - | Y20: - | Z20: - | AA20: - | AB20: - | AC20: - | AD20: - | AE20: - | AF20: -
A21: Affiliates (Refersion) | B21: - | C21: - | D21: - | E21: - | F21: - | G21: - | H21: - | I21: - | J21: - | K21: - | L21: - | M21: - | N21: - | O21: - | P21: - | Q21: - | R21: - | S21: - | T21: - | U21: - | V21: - | W21: - | X21: - | Y21: - | Z21: - | AA21: - | AB21: - | AC21: - | AD21: - | AE21: - | AF21: -
A22: All | B22: =SUM(B15:B21) -> 3878.0248 | C22: =SUM(C15:C21) -> 3263.2498 | D22: =SUM(D15:D21) -> 1715.1549 | E22: =SUM(E15:E21) -> 3498.1225 | F22: =SUM(F15:F21) -> 6308.3161 | G22: =SUM(G15:G21) -> 1096.776 | H22: =SUM(H15:H21) -> 1741.6822 | I22: =SUM(I15:I21) -> 3623.7972 | ... AF22: =SUM(AF15:AF21) -> 27873.241 | AG22: =SUM(B22:AF22) -> 286073.15
A24: Media Cost
A25: Meta | B25: =Summary!B105 -> 1725.8554 | C25: =Summary!C105 -> 1951.7729 | D25: =Summary!D105 -> 1562.1477 | E25: =Summary!E105 -> 1759.4791 | F25: =Summary!F105 -> 1930.5368 | G25: =Summary!G105 -> 2139.6217 | H25: =Summary!H105 -> 1842.3765 | I25: =Summary!I105 -> 1731.546 | ... AF25: =Summary!AF105 -> 33389.783 | AG25: =SUM(B25:AF25) -> 232772.39
A26: Google | B26: =Summary!B108 -> 518.87 | C26: =Summary!C108 -> 512.42 | D26: =Summary!D108 -> 548.46 | E26: =Summary!E108 -> 476.27 | F26: =Summary!F108 -> 289.02 | G26: =Summary!G108 -> 399.65 | H26: =Summary!H108 -> 321.04 | I26: =Summary!I108 -> 296.38 | ... AF26: =Summary!AF108 -> 1171.76 | AG26: =SUM(B26:AF26) -> 29787.92
A27: TikTok | B27: =Summary!B112 -> 0 | C27: =Summary!C112 -> 0 | D27: =Summary!D112 -> 0 | E27: =Summary!E112 -> 0 | F27: =Summary!F112 -> 0 | G27: =Summary!G112 -> 0 | H27: =Summary!H112 -> 0 | I27: =Summary!I112 -> 60.58 | ... AF27: =Summary!AF112 -> 199.72 | AG27: =SUM(B27:AF27) -> 4479.69
A28: Bing | B28: =Summary!B111 -> 45.97 | C28: =Summary!C111 -> 49.3 | D28: =Summary!D111 -> 38.61 | E28: =Summary!E111 -> 39.19 | F28: =Summary!F111 -> 45.61 | G28: =Summary!G111 -> 15.91 | H28: =Summary!H111 -> 31.05 | I28: =Summary!I111 -> 43.16 | ... AF28: =Summary!AF111 -> 38.96 | AG28: =SUM(B28:AF28) -> 1557.75
A29: Nextdoor | B29: - | C29: - | D29: - | E29: - | F29: - | G29: - | H29: - | I29: - | J29: - | K29: - | L29: - | M29: - | N29: - | O29: - | P29: - | Q29: - | R29: - | S29: - | T29: - | U29: - | V29: - | W29: - | X29: - | Y29: - | Z29: - | AA29: - | AB29: - | AC29: - | AD29: - | AE29: - | AF29: - | AG29: =SUM(B29:AF29) -> 0
A30: Affiliate Fee (20%) | B30: - | C30: - | D30: - | E30: - | F30: - | G30: - | H30: - | I30: - | J30: - | K30: - | L30: - | M30: - | N30: - | O30: - | P30: - | Q30: - | R30: - | S30: - | T30: - | U30: - | V30: - | W30: - | X30: - | Y30: - | Z30: - | AA30: - | AB30: - | AC30: - | AD30: - | AE30: - | AF30: - | AG30: =SUM(B30:AF30) -> 0
A31: All | B31: =SUM(B25:B30) -> 2290.6954 | C31: =SUM(C25:C30) -> 2513.4929 | D31: =SUM(D25:D30) -> 2149.2177 | E31: =SUM(E25:E30) -> 2274.9391 | F31: =SUM(F25:F30) -> 2265.1668 | G31: =SUM(G25:G30) -> 2555.1817 | H31: =SUM(H25:H30) -> 2194.4665 | I31: =SUM(I25:I30) -> 2131.666 | ... AF31: =SUM(AF25:AF30) -> 34800.223 | AG31: =SUM(B31:AF31) -> 268597.75
A36: Revenue
A37: Revenue Woocommerce (Platform) | B37: =Summary!B8 -> 9224.84 | C37: =Summary!C8 -> 5831.8 | D37: =Summary!D8 -> 6731.06 | E37: =Summary!E8 -> 5160.16 | F37: =Summary!F8 -> 7525.62 | G37: =Summary!G8 -> 5246.89 | H37: =Summary!H8 -> 5358.3 | I37: =Summary!I8 -> 4961.66 | ... AF37: =Summary!AF8 -> 41251.05 | AG37: =SUM(B37:AF37) -> 522947.38
A38: SUM | B38: =SUM(B37) -> 9224.84 | C38: =SUM(C37) -> 5831.8 | D38: =SUM(D37) -> 6731.06 | E38: =SUM(E37) -> 5160.16 | F38: =SUM(F37) -> 7525.62 | G38: =SUM(G37) -> 5246.89 | H38: =SUM(H37) -> 5358.3 | I38: =SUM(I37) -> 4961.66 | ... AF38: =SUM(AF37) -> 41251.05 | AG38: =SUM(B38:AF38) -> 522947.38
A40: Orders
A41: Orders Woocommerce (Platform) | B41: =Summary!B69 -> 58 | C41: =Summary!C69 -> 36 | D41: =Summary!D69 -> 35 | E41: =Summary!E69 -> 37 | F41: =Summary!F69 -> 41 | G41: =Summary!G69 -> 39 | H41: =Summary!H69 -> 29 | I41: =Summary!I69 -> 27 | ... AF41: =Summary!AF69 -> 163 | AG41: =SUM(B41:AF41) -> 2601
A42: SUM | B42: =SUM(B41) -> 58 | C42: =SUM(C41) -> 36 | D42: =SUM(D41) -> 35 | E42: =SUM(E41) -> 37 | F42: =SUM(F41) -> 41 | G42: =SUM(G41) -> 39 | H42: =SUM(H41) -> 29 | I42: =SUM(I41) -> 27 | ... AF42: =SUM(AF41) -> 163 | AG42: =SUM(B42:AF42) -> 2601
A44: Breakdown
A45: - Hardware | B45: =Summary!B10+Summary!B18 -> 4811 | C45: =Summary!C10+Summary!C18 -> 3876 | D45: =Summary!D10+Summary!D18 -> 4654.3 | E45: =Summary!E10+Summary!E18 -> 3588.1 | F45: =Summary!F10+Summary!F18 -> 5412.2 | G45: =Summary!G10+Summary!G18 -> 3259 | H45: =Summary!H10+Summary!H18 -> 3872.1 | I45: =Summary!I10+Summary!I18 -> 3757.75 | ... AF45: =Summary!AF10+Summary!AF18 -> 29949.65 | AG45: =SUM(B45:AF45) -> 303994.13
A46: - Add-ons | B46: =Summary!B11+Summary!B19 -> 2000.3 | C46: =Summary!C11+Summary!C19 -> 485.9 | D46: =Summary!D11+Summary!D19 -> 519 | E46: =Summary!E11+Summary!E19 -> 243 | F46: =Summary!F11+Summary!F19 -> 409.1 | G46: =Summary!G11+Summary!G19 -> 739.3 | H46: =Summary!H11+Summary!H19 -> 418.9 | I46: =Summary!I11+Summary!I19 -> 235.9 | ... AF46: =Summary!AF11+Summary!AF19 -> 3557.54 | AG46: =SUM(B46:AF46) -> 122143.07
A47: - Merch | B47: =Summary!B12+Summary!B20 -> 0 | C47: =Summary!C12+Summary!C20 -> 0 | D47: =Summary!D12+Summary!D20 -> 0 | E47: =Summary!E12+Summary!E20 -> 0 | F47: =Summary!F12+Summary!F20 -> 0 | G47: =Summary!G12+Summary!G20 -> 0 | H47: =Summary!H12+Summary!H20 -> 0 | I47: =Summary!I12+Summary!I20 -> 0 | ... AF47: =Summary!AF12+Summary!AF20 -> 0 | AG47: =SUM(B47:AF47) -> 539.78
A48: - Seeds | B48: =Summary!B13+Summary!B21 -> 710.7 | C48: =Summary!C13+Summary!C21 -> 439.3 | D48: =Summary!D13+Summary!D21 -> 555.1 | E48: =Summary!E13+Summary!E21 -> 621.8 | F48: =Summary!F13+Summary!F21 -> 672.7 | G48: =Summary!G13+Summary!G21 -> 477.1 | H48: =Summary!H13+Summary!H21 -> 344.6 | I48: =Summary!I13+Summary!I21 -> 256.1 | ... AF48: =Summary!AF13+Summary!AF21 -> 439.5 | AG48: =SUM(B48:AF48) -> 11612.2
A49: - Yearly Pro Subscription | B49: =Summary!B14+Summary!B22 -> 479.92 | C49: =Summary!C14+Summary!C22 -> 299.95 | D49: =Summary!D14+Summary!D22 -> 239.96 | E49: =Summary!E14+Summary!E22 -> 0 | F49: =Summary!F14+Summary!F22 -> 59.99 | G49: =Summary!G14+Summary!G22 -> 59.99 | H49: =Summary!H14+Summary!H22 -> 0 | I49: =Summary!I14+Summary!I22 -> 59.99 | ... AF49: =Summary!AF14+Summary!AF22 -> 179.97 | AG49: =SUM(B49:AF49) -> 6238.96
A50: - Taxes | B50: =Summary!B15+Summary!B23 -> 557.92 | C50: =Summary!C15+Summary!C23 -> 353.65 | D50: =Summary!D15+Summary!D23 -> 385.26 | E50: =Summary!E15+Summary!E23 -> 305.76 | F50: =Summary!F15+Summary!F23 -> 501.63 | G50: =Summary!G15+Summary!G23 -> 334.5 | H50: =Summary!H15+Summary!H23 -> 350.7 | I50: =Summary!I15+Summary!I23 -> 297.71 | ... AF50: =Summary!AF15+Summary!AF23 -> 3308.64 | AG50: =SUM(B50:AF50) -> 36520.54
A51: - Shipping | B51: =Summary!B16+Summary!B24 -> 665 | C51: =Summary!C16+Summary!C24 -> 377 | D51: =Summary!D16+Summary!D24 -> 377.44 | E51: =Summary!E16+Summary!E24 -> 401.5 | F51: =Summary!F16+Summary!F24 -> 470 | G51: =Summary!G16+Summary!G24 -> 377 | H51: =Summary!H16+Summary!H24 -> 372 | I51: =Summary!I16+Summary!I24 -> 354.21 | ... AF51: =Summary!AF16+Summary!AF24 -> 3815.75 | AG51: =SUM(B51:AF51) -> 41898.7
A52: SUM | B52: =SUM(B45:B51) -> 9224.84 | C52: =SUM(C45:C51) -> 5831.8 | D52: =SUM(D45:D51) -> 6731.06 | E52: =SUM(E45:E51) -> 5160.16 | F52: =SUM(F45:F51) -> 7525.62 | G52: =SUM(G45:G51) -> 5246.89 | H52: =SUM(H45:H51) -> 5358.3 | I52: =SUM(I45:I51) -> 4961.66 | ... AF52: =SUM(AF45:AF51) -> 41251.05 | AG52: =SUM(B52:AF52) -> 522947.38
A54: Units Sold (Gross)
A55: SKU 1 - Blue | B55: ='DTC US&CA - P&L'!B23+'DTC EU - P&L'!B23 -> 16 | C55: ='DTC US&CA - P&L'!C23+'DTC EU - P&L'!C23 -> 6 | D55: ='DTC US&CA - P&L'!D23+'DTC EU - P&L'!D23 -> 0 | E55: ='DTC US&CA - P&L'!E23+'DTC EU - P&L'!E23 -> 0 | F55: ='DTC US&CA - P&L'!F23+'DTC EU - P&L'!F23 -> 0 | G55: ='DTC US&CA - P&L'!G23+'DTC EU - P&L'!G23 -> 0 | H55: ='DTC US&CA - P&L'!H23+'DTC EU - P&L'!H23 -> 0 | I55: ='DTC US&CA - P&L'!I23+'DTC EU - P&L'!I23 -> 0 | ... AF55: ='DTC US&CA - P&L'!AF23+'DTC EU - P&L'!AF23 -> 21 | AG55: =SUM(B55:AF55) -> 105
A56: SKU 2 - Yellow | B56: ='DTC US&CA - P&L'!B24+'DTC EU - P&L'!B24 -> 0 | C56: ='DTC US&CA - P&L'!C24+'DTC EU - P&L'!C24 -> 0 | D56: ='DTC US&CA - P&L'!D24+'DTC EU - P&L'!D24 -> 0 | E56: ='DTC US&CA - P&L'!E24+'DTC EU - P&L'!E24 -> 0 | F56: ='DTC US&CA - P&L'!F24+'DTC EU - P&L'!F24 -> 0 | G56: ='DTC US&CA - P&L'!G24+'DTC EU - P&L'!G24 -> 0 | H56: ='DTC US&CA - P&L'!H24+'DTC EU - P&L'!H24 -> 0 | I56: ='DTC US&CA - P&L'!I24+'DTC EU - P&L'!I24 -> 0 | ... AF56: ='DTC US&CA - P&L'!AF24+'DTC EU - P&L'!AF24 -> 0 | AG56: =SUM(B56:AF56) -> 0
A57: SKU 3 - Blue w/ Solar | B57: ='DTC US&CA - P&L'!B25+'DTC EU - P&L'!B25 -> 0 | C57: ='DTC US&CA - P&L'!C25+'DTC EU - P&L'!C25 -> 7 | D57: ='DTC US&CA - P&L'!D25+'DTC EU - P&L'!D25 -> 16 | E57: ='DTC US&CA - P&L'!E25+'DTC EU - P&L'!E25 -> 10 | F57: ='DTC US&CA - P&L'!F25+'DTC EU - P&L'!F25 -> 14 | G57: ='DTC US&CA - P&L'!G25+'DTC EU - P&L'!G25 -> 10 | H57: ='DTC US&CA - P&L'!H25+'DTC EU - P&L'!H25 -> 10 | I57: ='DTC US&CA - P&L'!I25+'DTC EU - P&L'!I25 -> 11 | ... AF57: ='DTC US&CA - P&L'!AF25+'DTC EU - P&L'!AF25 -> 28 | AG57: =SUM(B57:AF57) -> 345
A58: SKU 4 - Yellow w/ Solar | B58: ='DTC US&CA - P&L'!B26+'DTC EU - P&L'!B26 -> 0 | C58: ='DTC US&CA - P&L'!C26+'DTC EU - P&L'!C26 -> 0 | D58: ='DTC US&CA - P&L'!D26+'DTC EU - P&L'!D26 -> 0 | E58: ='DTC US&CA - P&L'!E26+'DTC EU - P&L'!E26 -> 0 | F58: ='DTC US&CA - P&L'!F26+'DTC EU - P&L'!F26 -> 0 | G58: ='DTC US&CA - P&L'!G26+'DTC EU - P&L'!G26 -> 0 | H58: ='DTC US&CA - P&L'!H26+'DTC EU - P&L'!H26 -> 0 | I58: ='DTC US&CA - P&L'!I26+'DTC EU - P&L'!I26 -> 0 | ... AF58: ='DTC US&CA - P&L'!AF26+'DTC EU - P&L'!AF26 -> 0 | AG58: =SUM(B58:AF58) -> 0
A59: SKU 1 - Blue PRO | P59: ='DTC US&CA - P&L'!P27+'DTC EU - P&L'!P27 -> 3 | Q59: ='DTC US&CA - P&L'!Q27+'DTC EU - P&L'!Q27 -> 10 | R59: ='DTC US&CA - P&L'!R27+'DTC EU - P&L'!R27 -> 3 | S59: ='DTC US&CA - P&L'!S27+'DTC EU - P&L'!S27 -> 5 | T59: ='DTC US&CA - P&L'!T27+'DTC EU - P&L'!T27 -> 5 | U59: ='DTC US&CA - P&L'!U27+'DTC EU - P&L'!U27 -> 1 | V59: ='DTC US&CA - P&L'!V27+'DTC EU - P&L'!V27 -> 6 | W59: ='DTC US&CA - P&L'!W27+'DTC EU - P&L'!W27 -> 3 | ... AF59: ='DTC US&CA - P&L'!AF27+'DTC EU - P&L'!AF27 -> 18 | AG59: =SUM(B59:AF59) -> 135
A60: SKU 2 - Yellow PRO | P60: ='DTC US&CA - P&L'!P28+'DTC EU - P&L'!P28 -> 0 | Q60: ='DTC US&CA - P&L'!Q28+'DTC EU - P&L'!Q28 -> 0 | R60: ='DTC US&CA - P&L'!R28+'DTC EU - P&L'!R28 -> 0 | S60: ='DTC US&CA - P&L'!S28+'DTC EU - P&L'!S28 -> 0 | T60: ='DTC US&CA - P&L'!T28+'DTC EU - P&L'!T28 -> 0 | U60: ='DTC US&CA - P&L'!U28+'DTC EU - P&L'!U28 -> 0 | V60: ='DTC US&CA - P&L'!V28+'DTC EU - P&L'!V28 -> 0 | W60: ='DTC US&CA - P&L'!W28+'DTC EU - P&L'!W28 -> 0 | ... AF60: ='DTC US&CA - P&L'!AF28+'DTC EU - P&L'!AF28 -> 0 | AG60: =SUM(B60:AF60) -> 0
A61: SKU 3 - Blue w/ Solar PRO | P61: ='DTC US&CA - P&L'!P29+'DTC EU - P&L'!P29 -> 20 | Q61: ='DTC US&CA - P&L'!Q29+'DTC EU - P&L'!Q29 -> 15 | R61: ='DTC US&CA - P&L'!R29+'DTC EU - P&L'!R29 -> 25 | S61: ='DTC US&CA - P&L'!S29+'DTC EU - P&L'!S29 -> 18 | T61: ='DTC US&CA - P&L'!T29+'DTC EU - P&L'!T29 -> 11 | U61: ='DTC US&CA - P&L'!U29+'DTC EU - P&L'!U29 -> 3 | V61: ='DTC US&CA - P&L'!V29+'DTC EU - P&L'!V29 -> 10 | W61: ='DTC US&CA - P&L'!W29+'DTC EU - P&L'!W29 -> 2 | ... AF61: ='DTC US&CA - P&L'!AF29+'DTC EU - P&L'!AF29 -> 47 | AG61: =SUM(B61:AF61) -> 421
A62: SKU 4 - Yellow w/ Solar PRO | P62: ='DTC US&CA - P&L'!P30+'DTC EU - P&L'!P30 -> 0 | Q62: ='DTC US&CA - P&L'!Q30+'DTC EU - P&L'!Q30 -> 0 | R62: ='DTC US&CA - P&L'!R30+'DTC EU - P&L'!R30 -> 0 | S62: ='DTC US&CA - P&L'!S30+'DTC EU - P&L'!S30 -> 0 | T62: ='DTC US&CA - P&L'!T30+'DTC EU - P&L'!T30 -> 0 | U62: ='DTC US&CA - P&L'!U30+'DTC EU - P&L'!U30 -> 0 | V62: ='DTC US&CA - P&L'!V30+'DTC EU - P&L'!V30 -> 0 | W62: ='DTC US&CA - P&L'!W30+'DTC EU - P&L'!W30 -> 0 | ... AF62: ='DTC US&CA - P&L'!AF30+'DTC EU - P&L'!AF30 -> 0 | AG62: =SUM(B62:AF62) -> 0
A63: SUM (SKU 1 - SKU 4) | B63: =SUM(B55:B62) -> 16 | C63: =SUM(C55:C62) -> 13 | D63: =SUM(D55:D62) -> 16 | E63: =SUM(E55:E62) -> 10 | F63: =SUM(F55:F62) -> 14 | G63: =SUM(G55:G62) -> 10 | H63: =SUM(H55:H62) -> 10 | I63: =SUM(I55:I62) -> 11 | ... AF63: =SUM(AF55:AF62) -> 114 | AG63: =SUM(B63:AF63) -> 1006
A65: SKU 5 - HBF | B65: ='DTC US&CA - P&L'!B33+'DTC EU - P&L'!B33 -> 1 | C65: ='DTC US&CA - P&L'!C33+'DTC EU - P&L'!C33 -> 0 | D65: ='DTC US&CA - P&L'!D33+'DTC EU - P&L'!D33 -> 0 | E65: ='DTC US&CA - P&L'!E33+'DTC EU - P&L'!E33 -> 0 | F65: ='DTC US&CA - P&L'!F33+'DTC EU - P&L'!F33 -> 2 | G65: ='DTC US&CA - P&L'!G33+'DTC EU - P&L'!G33 -> 1 | H65: ='DTC US&CA - P&L'!H33+'DTC EU - P&L'!H33 -> 2 | I65: ='DTC US&CA - P&L'!I33+'DTC EU - P&L'!I33 -> 0 | ... AF65: ='DTC US&CA - P&L'!AF33+'DTC EU - P&L'!AF33 -> 1 | AG65: =SUM(B65:AF65) -> 46
A66: SKU 6 - HBF w/ Solar | B66: ='DTC US&CA - P&L'!B34+'DTC EU - P&L'!B34 -> 2 | C66: ='DTC US&CA - P&L'!C34+'DTC EU - P&L'!C34 -> 1 | D66: ='DTC US&CA - P&L'!D34+'DTC EU - P&L'!D34 -> 0 | E66: ='DTC US&CA - P&L'!E34+'DTC EU - P&L'!E34 -> 2 | F66: ='DTC US&CA - P&L'!F34+'DTC EU - P&L'!F34 -> 2 | G66: ='DTC US&CA - P&L'!G34+'DTC EU - P&L'!G34 -> 0 | H66: ='DTC US&CA - P&L'!H34+'DTC EU - P&L'!H34 -> 1 | I66: ='DTC US&CA - P&L'!I34+'DTC EU - P&L'!I34 -> 2 | ... AF66: ='DTC US&CA - P&L'!AF34+'DTC EU - P&L'!AF34 -> 12 | AG66: =SUM(B66:AF66) -> 149
A67: SUM (SKU 5 - SKU 6) | B67: =SUM(B65:B66) -> 3 | C67: =SUM(C65:C66) -> 1 | D67: =SUM(D65:D66) -> 0 | E67: =SUM(E65:E66) -> 2 | F67: =SUM(F65:F66) -> 4 | G67: =SUM(G65:G66) -> 1 | H67: =SUM(H65:H66) -> 3 | I67: =SUM(I65:I66) -> 2 | ... AF67: =SUM(AF65:AF66) -> 13 | AG67: =SUM(B67:AF67) -> 195
A69: Wall Mount | B69: ='DTC US&CA - P&L'!B37+'DTC EU - P&L'!B37 -> 7 | C69: ='DTC US&CA - P&L'!C37+'DTC EU - P&L'!C37 -> 1 | D69: ='DTC US&CA - P&L'!D37+'DTC EU - P&L'!D37 -> 5 | E69: ='DTC US&CA - P&L'!E37+'DTC EU - P&L'!E37 -> 2 | F69: ='DTC US&CA - P&L'!F37+'DTC EU - P&L'!F37 -> 2 | G69: ='DTC US&CA - P&L'!G37+'DTC EU - P&L'!G37 -> 1 | H69: ='DTC US&CA - P&L'!H37+'DTC EU - P&L'!H37 -> 1 | I69: ='DTC US&CA - P&L'!I37+'DTC EU - P&L'!I37 -> 2 | ... AF69: ='DTC US&CA - P&L'!AF37+'DTC EU - P&L'!AF37 -> 85 | AG69: =SUM(B69:AF69) -> 334
A70: Suet Ball Holder | B70: ='DTC US&CA - P&L'!B38+'DTC EU - P&L'!B38 -> 5 | C70: ='DTC US&CA - P&L'!C38+'DTC EU - P&L'!C38 -> 2 | D70: ='DTC US&CA - P&L'!D38+'DTC EU - P&L'!D38 -> 0 | E70: ='DTC US&CA - P&L'!E38+'DTC EU - P&L'!E38 -> 2 | F70: ='DTC US&CA - P&L'!F38+'DTC EU - P&L'!F38 -> 2 | G70: ='DTC US&CA - P&L'!G38+'DTC EU - P&L'!G38 -> 0 | H70: ='DTC US&CA - P&L'!H38+'DTC EU - P&L'!H38 -> 2 | I70: ='DTC US&CA - P&L'!I38+'DTC EU - P&L'!I38 -> 2 | ... AF70: ='DTC US&CA - P&L'!AF38+'DTC EU - P&L'!AF38 -> 12 | AG70: =SUM(B70:AF70) -> 208
A71: 3-in-1 Nutrition Set - Blue | B71: ='DTC US&CA - P&L'!B39+'DTC EU - P&L'!B39 -> 3 | C71: ='DTC US&CA - P&L'!C39+'DTC EU - P&L'!C39 -> 2 | D71: ='DTC US&CA - P&L'!D39+'DTC EU - P&L'!D39 -> 4 | E71: ='DTC US&CA - P&L'!E39+'DTC EU - P&L'!E39 -> 0 | F71: ='DTC US&CA - P&L'!F39+'DTC EU - P&L'!F39 -> 1 | G71: ='DTC US&CA - P&L'!G39+'DTC EU - P&L'!G39 -> 2 | H71: ='DTC US&CA - P&L'!H39+'DTC EU - P&L'!H39 -> 3 | I71: ='DTC US&CA - P&L'!I39+'DTC EU - P&L'!I39 -> 1 | ... AF71: ='DTC US&CA - P&L'!AF39+'DTC EU - P&L'!AF39 -> 20 | AG71: =SUM(B71:AF71) -> 159
A72: 3-in-1 Nutrition Set - Yellow | B72: ='DTC US&CA - P&L'!B40+'DTC EU - P&L'!B40 -> 0 | C72: ='DTC US&CA - P&L'!C40+'DTC EU - P&L'!C40 -> 1 | D72: ='DTC US&CA - P&L'!D40+'DTC EU - P&L'!D40 -> 0 | E72: ='DTC US&CA - P&L'!E40+'DTC EU - P&L'!E40 -> 0 | F72: ='DTC US&CA - P&L'!F40+'DTC EU - P&L'!F40 -> 1 | G72: ='DTC US&CA - P&L'!G40+'DTC EU - P&L'!G40 -> 0 | H72: ='DTC US&CA - P&L'!H40+'DTC EU - P&L'!H40 -> 0 | I72: ='DTC US&CA - P&L'!I40+'DTC EU - P&L'!I40 -> 0 | ... AF72: ='DTC US&CA - P&L'!AF40+'DTC EU - P&L'!AF40 -> 0 | AG72: =SUM(B72:AF72) -> 4
A73: Solar Roof Single - Blue | B73: ='DTC US&CA - P&L'!B41+'DTC EU - P&L'!B41 -> 18 | C73: ='DTC US&CA - P&L'!C41+'DTC EU - P&L'!C41 -> 5 | D73: ='DTC US&CA - P&L'!D41+'DTC EU - P&L'!D41 -> 0 | E73: ='DTC US&CA - P&L'!E41+'DTC EU - P&L'!E41 -> 1 | F73: ='DTC US&CA - P&L'!F41+'DTC EU - P&L'!F41 -> 2 | G73: ='DTC US&CA - P&L'!G41+'DTC EU - P&L'!G41 -> 4 | H73: ='DTC US&CA - P&L'!H41+'DTC EU - P&L'!H41 -> 3 | I73: ='DTC US&CA - P&L'!I41+'DTC EU - P&L'!I41 -> 2 | ... AF73: ='DTC US&CA - P&L'!AF41+'DTC EU - P&L'!AF41 -> 5 | AG73: =SUM(B73:AF73) -> 128
A74: Solar Roof Single - Yellow | B74: ='DTC US&CA - P&L'!B42+'DTC EU - P&L'!B42 -> 1 | C74: ='DTC US&CA - P&L'!C42+'DTC EU - P&L'!C42 -> 0 | D74: ='DTC US&CA - P&L'!D42+'DTC EU - P&L'!D42 -> 0 | E74: ='DTC US&CA - P&L'!E42+'DTC EU - P&L'!E42 -> 0 | F74: ='DTC US&CA - P&L'!F42+'DTC EU - P&L'!F42 -> 0 | G74: ='DTC US&CA - P&L'!G42+'DTC EU - P&L'!G42 -> 2 | H74: ='DTC US&CA - P&L'!H42+'DTC EU - P&L'!H42 -> 0 | I74: ='DTC US&CA - P&L'!I42+'DTC EU - P&L'!I42 -> 0 | ... AF74: ='DTC US&CA - P&L'!AF42+'DTC EU - P&L'!AF42 -> 2 | AG74: =SUM(B74:AF74) -> 27
A75: Perch Extender - Blue | B75: ='DTC US&CA - P&L'!B43+'DTC EU - P&L'!B43 -> 0 | C75: ='DTC US&CA - P&L'!C43+'DTC EU - P&L'!C43 -> 0 | D75: ='DTC US&CA - P&L'!D43+'DTC EU - P&L'!D43 -> 0 | E75: ='DTC US&CA - P&L'!E43+'DTC EU - P&L'!E43 -> 0 | F75: ='DTC US&CA - P&L'!F43+'DTC EU - P&L'!F43 -> 0 | G75: ='DTC US&CA - P&L'!G43+'DTC EU - P&L'!G43 -> 0 | H75: ='DTC US&CA - P&L'!H43+'DTC EU - P&L'!H43 -> 0 | I75: ='DTC US&CA - P&L'!I43+'DTC EU - P&L'!I43 -> 0 | ... AF75: ='DTC US&CA - P&L'!AF43+'DTC EU - P&L'!AF43 -> 24 | AG75: =SUM(B75:AF75) -> 249
A76: Perch Extender - Yellow | B76: ='DTC US&CA - P&L'!B44+'DTC EU - P&L'!B44 -> 3 | C76: ='DTC US&CA - P&L'!C44+'DTC EU - P&L'!C44 -> 0 | D76: ='DTC US&CA - P&L'!D44+'DTC EU - P&L'!D44 -> 0 | E76: ='DTC US&CA - P&L'!E44+'DTC EU - P&L'!E44 -> 2 | F76: ='DTC US&CA - P&L'!F44+'DTC EU - P&L'!F44 -> 1 | G76: ='DTC US&CA - P&L'!G44+'DTC EU - P&L'!G44 -> 5 | H76: ='DTC US&CA - P&L'!H44+'DTC EU - P&L'!H44 -> 0 | I76: ='DTC US&CA - P&L'!I44+'DTC EU - P&L'!I44 -> 1 | ... AF76: ='DTC US&CA - P&L'!AF44+'DTC EU - P&L'!AF44 -> 0 | AG76: =SUM(B76:AF76) -> 31
A77: Solar Roof (HBF) | B77: ='DTC US&CA - P&L'!B45+'DTC EU - P&L'!B45 -> 3 | C77: ='DTC US&CA - P&L'!C45+'DTC EU - P&L'!C45 -> 0 | D77: ='DTC US&CA - P&L'!D45+'DTC EU - P&L'!D45 -> 1 | E77: ='DTC US&CA - P&L'!E45+'DTC EU - P&L'!E45 -> 0 | F77: ='DTC US&CA - P&L'!F45+'DTC EU - P&L'!F45 -> 1 | G77: ='DTC US&CA - P&L'!G45+'DTC EU - P&L'!G45 -> 0 | H77: ='DTC US&CA - P&L'!H45+'DTC EU - P&L'!H45 -> 0 | I77: ='DTC US&CA - P&L'!I45+'DTC EU - P&L'!I45 -> 0 | ... AF77: ='DTC US&CA - P&L'!AF45+'DTC EU - P&L'!AF45 -> 1 | AG77: =SUM(B77:AF77) -> 24
A78: Housing - only (HBF) | B78: ='DTC US&CA - P&L'!B46+'DTC EU - P&L'!B46 -> 1 | C78: ='DTC US&CA - P&L'!C46+'DTC EU - P&L'!C46 -> 0 | D78: ='DTC US&CA - P&L'!D46+'DTC EU - P&L'!D46 -> 1 | E78: ='DTC US&CA - P&L'!E46+'DTC EU - P&L'!E46 -> 0 | F78: ='DTC US&CA - P&L'!F46+'DTC EU - P&L'!F46 -> 0 | G78: ='DTC US&CA - P&L'!G46+'DTC EU - P&L'!G46 -> 0 | H78: ='DTC US&CA - P&L'!H46+'DTC EU - P&L'!H46 -> 0 | I78: ='DTC US&CA - P&L'!I46+'DTC EU - P&L'!I46 -> 0 | ... AF78: ='DTC US&CA - P&L'!AF46+'DTC EU - P&L'!AF46 -> 1 | AG78: =SUM(B78:AF78) -> 14
A79: Nature Cam PRO | P79: ='DTC US&CA - P&L'!P47+'DTC EU - P&L'!P47 -> 212 | Q79: ='DTC US&CA - P&L'!Q47+'DTC EU - P&L'!Q47 -> 117 | R79: ='DTC US&CA - P&L'!R47+'DTC EU - P&L'!R47 -> 68 | S79: ='DTC US&CA - P&L'!S47+'DTC EU - P&L'!S47 -> 46 | T79: ='DTC US&CA - P&L'!T47+'DTC EU - P&L'!T47 -> 34 | U79: ='DTC US&CA - P&L'!U47+'DTC EU - P&L'!U47 -> 34 | V79: ='DTC US&CA - P&L'!V47+'DTC EU - P&L'!V47 -> 18 | W79: ='DTC US&CA - P&L'!W47+'DTC EU - P&L'!W47 -> 23 | ... AF79: ='DTC US&CA - P&L'!AF47+'DTC EU - P&L'!AF47 -> 15 | AG79: =SUM(B79:AF79) -> 806
A80: SUM (Add-ons) | B80: =SUM(B69:B79) -> 41 | C80: =SUM(C69:C79) -> 11 | D80: =SUM(D69:D79) -> 11 | E80: =SUM(E69:E79) -> 7 | F80: =SUM(F69:F79) -> 10 | G80: =SUM(G69:G79) -> 14 | H80: =SUM(H69:H79) -> 9 | I80: =SUM(I69:I79) -> 8 | ... AF80: =SUM(AF69:AF79) -> 165 | AG80: =SUM(B80:AF80) -> 1984
A82: Seasonal Curation - 8lb | B82: ='DTC US&CA - P&L'!B50+'DTC EU - P&L'!B50 -> 19 | C82: ='DTC US&CA - P&L'!C50+'DTC EU - P&L'!C50 -> 13 | D82: ='DTC US&CA - P&L'!D50+'DTC EU - P&L'!D50 -> 16 | E82: ='DTC US&CA - P&L'!E50+'DTC EU - P&L'!E50 -> 20 | F82: ='DTC US&CA - P&L'!F50+'DTC EU - P&L'!F50 -> 18 | G82: ='DTC US&CA - P&L'!G50+'DTC EU - P&L'!G50 -> 14 | H82: ='DTC US&CA - P&L'!H50+'DTC EU - P&L'!H50 -> 12 | I82: ='DTC US&CA - P&L'!I50+'DTC EU - P&L'!I50 -> 7 | ... AF82: ='DTC US&CA - P&L'!AF50+'DTC EU - P&L'!AF50 -> 14 | AG82: =SUM(B82:AF82) -> 350
A83: Seasonal Curation - 20lb | B83: ='DTC US&CA - P&L'!B51+'DTC EU - P&L'!B51 -> 1 | C83: ='DTC US&CA - P&L'!C51+'DTC EU - P&L'!C51 -> 1 | D83: ='DTC US&CA - P&L'!D51+'DTC EU - P&L'!D51 -> 2 | E83: ='DTC US&CA - P&L'!E51+'DTC EU - P&L'!E51 -> 1 | F83: ='DTC US&CA - P&L'!F51+'DTC EU - P&L'!F51 -> 1 | G83: ='DTC US&CA - P&L'!G51+'DTC EU - P&L'!G51 -> 1 | H83: ='DTC US&CA - P&L'!H51+'DTC EU - P&L'!H51 -> 0 | I83: ='DTC US&CA - P&L'!I51+'DTC EU - P&L'!I51 -> 1 | ... AF83: ='DTC US&CA - P&L'!AF51+'DTC EU - P&L'!AF51 -> 0 | AG83: =SUM(B83:AF83) -> 20
A84: Buddy Bites - 8lb | B84: ='DTC US&CA - P&L'!B52+'DTC EU - P&L'!B52 -> 0 | C84: ='DTC US&CA - P&L'!C52+'DTC EU - P&L'!C52 -> 0 | D84: ='DTC US&CA - P&L'!D52+'DTC EU - P&L'!D52 -> 0 | E84: ='DTC US&CA - P&L'!E52+'DTC EU - P&L'!E52 -> 0 | F84: ='DTC US&CA - P&L'!F52+'DTC EU - P&L'!F52 -> 2 | G84: ='DTC US&CA - P&L'!G52+'DTC EU - P&L'!G52 -> 1 | H84: ='DTC US&CA - P&L'!H52+'DTC EU - P&L'!H52 -> 0 | I84: ='DTC US&CA - P&L'!I52+'DTC EU - P&L'!I52 -> 1 | ... AF84: ='DTC US&CA - P&L'!AF52+'DTC EU - P&L'!AF52 -> 1 | AG84: =SUM(B84:AF84) -> 11
A85: Buddy Bites - 20lb | B85: ='DTC US&CA - P&L'!B53+'DTC EU - P&L'!B53 -> 0 | C85: ='DTC US&CA - P&L'!C53+'DTC EU - P&L'!C53 -> 0 | D85: ='DTC US&CA - P&L'!D53+'DTC EU - P&L'!D53 -> 0 | E85: ='DTC US&CA - P&L'!E53+'DTC EU - P&L'!E53 -> 0 | F85: ='DTC US&CA - P&L'!F53+'DTC EU - P&L'!F53 -> 0 | G85: ='DTC US&CA - P&L'!G53+'DTC EU - P&L'!G53 -> 0 | H85: ='DTC US&CA - P&L'!H53+'DTC EU - P&L'!H53 -> 0 | I85: ='DTC US&CA - P&L'!I53+'DTC EU - P&L'!I53 -> 0 | ... AF85: ='DTC US&CA - P&L'!AF53+'DTC EU - P&L'!AF53 -> 0 | AG85: =SUM(B85:AF85) -> 2
A86: Snack n' Soar - 8lb | B86: ='DTC US&CA - P&L'!B54+'DTC EU - P&L'!B54 -> 0 | C86: ='DTC US&CA - P&L'!C54+'DTC EU - P&L'!C54 -> 0 | D86: ='DTC US&CA - P&L'!D54+'DTC EU - P&L'!D54 -> 0 | E86: ='DTC US&CA - P&L'!E54+'DTC EU - P&L'!E54 -> 0 | F86: ='DTC US&CA - P&L'!F54+'DTC EU - P&L'!F54 -> 0 | G86: ='DTC US&CA - P&L'!G54+'DTC EU - P&L'!G54 -> 0 | H86: ='DTC US&CA - P&L'!H54+'DTC EU - P&L'!H54 -> 0 | I86: ='DTC US&CA - P&L'!I54+'DTC EU - P&L'!I54 -> 0 | ... AF86: ='DTC US&CA - P&L'!AF54+'DTC EU - P&L'!AF54 -> 1 | AG86: =SUM(B86:AF86) -> 6
A87: Snack n' Soar - 20lb | B87: ='DTC US&CA - P&L'!B55+'DTC EU - P&L'!B55 -> 1 | C87: ='DTC US&CA - P&L'!C55+'DTC EU - P&L'!C55 -> 0 | D87: ='DTC US&CA - P&L'!D55+'DTC EU - P&L'!D55 -> 0 | E87: ='DTC US&CA - P&L'!E55+'DTC EU - P&L'!E55 -> 0 | F87: ='DTC US&CA - P&L'!F55+'DTC EU - P&L'!F55 -> 0 | G87: ='DTC US&CA - P&L'!G55+'DTC EU - P&L'!G55 -> 0 | H87: ='DTC US&CA - P&L'!H55+'DTC EU - P&L'!H55 -> 0 | I87: ='DTC US&CA - P&L'!I55+'DTC EU - P&L'!I55 -> 0 | ... AF87: ='DTC US&CA - P&L'!AF55+'DTC EU - P&L'!AF55 -> 0 | AG87: =SUM(B87:AF87) -> 2
A88: Avian Choice - 8lb | B88: ='DTC US&CA - P&L'!B56+'DTC EU - P&L'!B56 -> 2 | C88: ='DTC US&CA - P&L'!C56+'DTC EU - P&L'!C56 -> 1 | D88: ='DTC US&CA - P&L'!D56+'DTC EU - P&L'!D56 -> 0 | E88: ='DTC US&CA - P&L'!E56+'DTC EU - P&L'!E56 -> 0 | F88: ='DTC US&CA - P&L'!F56+'DTC EU - P&L'!F56 -> 2 | G88: ='DTC US&CA - P&L'!G56+'DTC EU - P&L'!G56 -> 1 | H88: ='DTC US&CA - P&L'!H56+'DTC EU - P&L'!H56 -> 0 | I88: ='DTC US&CA - P&L'!I56+'DTC EU - P&L'!I56 -> 0 | ... AF88: ='DTC US&CA - P&L'!AF56+'DTC EU - P&L'!AF56 -> 1 | AG88: =SUM(B88:AF88) -> 14
A89: Avian Choice - 20lb | B89: ='DTC US&CA - P&L'!B57+'DTC EU - P&L'!B57 -> 0 | C89: ='DTC US&CA - P&L'!C57+'DTC EU - P&L'!C57 -> 0 | D89: ='DTC US&CA - P&L'!D57+'DTC EU - P&L'!D57 -> 0 | E89: ='DTC US&CA - P&L'!E57+'DTC EU - P&L'!E57 -> 0 | F89: ='DTC US&CA - P&L'!F57+'DTC EU - P&L'!F57 -> 0 | G89: ='DTC US&CA - P&L'!G57+'DTC EU - P&L'!G57 -> 0 | H89: ='DTC US&CA - P&L'!H57+'DTC EU - P&L'!H57 -> 0 | I89: ='DTC US&CA - P&L'!I57+'DTC EU - P&L'!I57 -> 0 | ... AF89: ='DTC US&CA - P&L'!AF57+'DTC EU - P&L'!AF57 -> 0 | AG89: =SUM(B89:AF89) -> 1
A90: SUM (Seeds) | B90: =SUM(B82:B89) -> 23 | C90: =SUM(C82:C89) -> 15 | D90: =SUM(D82:D89) -> 18 | E90: =SUM(E82:E89) -> 21 | F90: =SUM(F82:F89) -> 23 | G90: =SUM(G82:G89) -> 17 | H90: =SUM(H82:H89) -> 12 | I90: =SUM(I82:I89) -> 9 | ... AF90: =SUM(AF82:AF89) -> 17 | AG90: =SUM(B90:AF90) -> 406
A92: Merch Units Sold (Gross)
A93: Merch Units | B93: ='DTC US&CA - P&L'!B61+'DTC EU - P&L'!B61 -> 0 | C93: ='DTC US&CA - P&L'!C61+'DTC EU - P&L'!C61 -> 0 | D93: ='DTC US&CA - P&L'!D61+'DTC EU - P&L'!D61 -> 0 | E93: ='DTC US&CA - P&L'!E61+'DTC EU - P&L'!E61 -> 0 | F93: ='DTC US&CA - P&L'!F61+'DTC EU - P&L'!F61 -> 0 | G93: ='DTC US&CA - P&L'!G61+'DTC EU - P&L'!G61 -> 0 | H93: ='DTC US&CA - P&L'!H61+'DTC EU - P&L'!H61 -> 0 | I93: ='DTC US&CA - P&L'!I61+'DTC EU - P&L'!I61 -> 0 | ... AF93: ='DTC US&CA - P&L'!AF61+'DTC EU - P&L'!AF61 -> 0 | AG93: =SUM(B93:AF93) -> 22
A95: First-time Customers
A96: SKU 1 - Blue | B96: =B55-B124 -> 14 | C96: =C55-C124 -> 4 | D96: =D55-D124 -> 0 | E96: =E55-E124 -> 0 | F96: =F55-F124 -> 0 | G96: =G55-G124 -> 0 | H96: =H55-H124 -> 0 | I96: =I55-I124 -> 0 | ... AF96: =AF55-AF124 -> 21 | AG96: =SUM(B96:AF96) -> 97
A97: SKU 2 - Yellow | B97: =B56-B125 -> 0 | C97: =C56-C125 -> 0 | D97: =D56-D125 -> 0 | E97: =E56-E125 -> 0 | F97: =F56-F125 -> 0 | G97: =G56-G125 -> 0 | H97: =H56-H125 -> 0 | I97: =I56-I125 -> 0 | ... AF97: =AF56-AF125 -> 0 | AG97: =SUM(B97:AF97) -> 0
A98: SKU 3 - Blue w/ Solar | B98: =B57-B126 -> 0 | C98: =C57-C126 -> 7 | D98: =D57-D126 -> 15 | E98: =E57-E126 -> 9 | F98: =F57-F126 -> 11 | G98: =G57-G126 -> 8 | H98: =H57-H126 -> 9 | I98: =I57-I126 -> 11 | ... AF98: =AF57-AF126 -> 27 | AG98: =SUM(B98:AF98) -> 318
A99: SKU 4 - Yellow w/ Solar | B99: =B58-B127 -> 0 | C99: =C58-C127 -> 0 | D99: =D58-D127 -> 0 | E99: =E58-E127 -> 0 | F99: =F58-F127 -> 0 | G99: =G58-G127 -> 0 | H99: =H58-H127 -> 0 | I99: =I58-I127 -> 0 | ... AF99: =AF58-AF127 -> 0 | AG99: =SUM(B99:AF99) -> 0
A100: SKU 1 - Blue PRO | P100: =P59-P128 -> 2 | Q100: =Q59-Q128 -> 9 | R100: =R59-R128 -> 3 | S100: =S59-S128 -> 5 | T100: =T59-T128 -> 5 | U100: =U59-U128 -> 1 | V100: =V59-V128 -> 6 | W100: =W59-W128 -> 2 | ... AF100: =AF59-AF128 -> 17 | AG100: =SUM(B100:AF100) -> 124
A101: SKU 2 - Yellow PRO | P101: =P60-P129 -> 0 | Q101: =Q60-Q129 -> 0 | R101: =R60-R129 -> 0 | S101: =S60-S129 -> 0 | T101: =T60-T129 -> 0 | U101: =U60-U129 -> 0 | V101: =V60-V129 -> 0 | W101: =W60-W129 -> 0 | ... AF101: =AF60-AF129 -> 0 | AG101: =SUM(B101:AF101) -> 0
A102: SKU 3 - Blue w/ Solar PRO | P102: =P61-P130 -> 8 | Q102: =Q61-Q130 -> 11 | R102: =R61-R130 -> 23 | S102: =S61-S130 -> 16 | T102: =T61-T130 -> 9 | U102: =U61-U130 -> 3 | V102: =V61-V130 -> 9 | W102: =W61-W130 -> 2 | ... AF102: =AF61-AF130 -> 46 | AG102: =SUM(B102:AF102) -> 367
A103: SKU 4 - Yellow w/ Solar PRO | P103: =P62-P131 -> 0 | Q103: =Q62-Q131 -> 0 | R103: =R62-R131 -> 0 | S103: =S62-S131 -> 0 | T103: =T62-T131 -> 0 | U103: =U62-U131 -> 0 | V103: =V62-V131 -> 0 | W103: =W62-W131 -> 0 | ... AF103: =AF62-AF131 -> 0 | AG103: =SUM(B103:AF103) -> 0
A104: SUM (SKU 1 - SKU 4) | B104: =SUM(B96:B103) -> 14 | C104: =SUM(C96:C103) -> 11 | D104: =SUM(D96:D103) -> 15 | E104: =SUM(E96:E103) -> 9 | F104: =SUM(F96:F103) -> 11 | G104: =SUM(G96:G103) -> 8 | H104: =SUM(H96:H103) -> 9 | I104: =SUM(I96:I103) -> 11 | ... AF104: =SUM(AF96:AF103) -> 111 | AG104: =SUM(B104:AF104) -> 906
A106: SKU 5 - HBF | B106: =B65-B134 -> 0 | C106: =C65-C134 -> 0 | D106: =D65-D134 -> 0 | E106: =E65-E134 -> 0 | F106: =F65-F134 -> 2 | G106: =G65-G134 -> 1 | H106: =H65-H134 -> 2 | I106: =I65-I134 -> 0 | ... AF106: =AF65-AF134 -> 1 | AG106: =SUM(B106:AF106) -> 40
A107: SKU 6 - HBF w/ Solar | B107: =B66-B135 -> 1 | C107: =C66-C135 -> 1 | D107: =D66-D135 -> 0 | E107: =E66-E135 -> 2 | F107: =F66-F135 -> 0 | G107: =G66-G135 -> 0 | H107: =H66-H135 -> 0 | I107: =I66-I135 -> 0 | ... AF107: =AF66-AF135 -> 11 | AG107: =SUM(B107:AF107) -> 115
A108: SUM (SKU 5 - SKU 6) | B108: =SUM(B106:B107) -> 1 | C108: =SUM(C106:C107) -> 1 | D108: =SUM(D106:D107) -> 0 | E108: =SUM(E106:E107) -> 2 | F108: =SUM(F106:F107) -> 2 | G108: =SUM(G106:G107) -> 1 | H108: =SUM(H106:H107) -> 2 | I108: =SUM(I106:I107) -> 0 | ... AF108: =SUM(AF106:AF107) -> 12 | AG108: =SUM(B108:AF108) -> 155
A110: Wall Mount | B110: =B69-B138 -> 6 | C110: =C69-C138 -> 1 | D110: =D69-D138 -> 4 | E110: =E69-E138 -> 1 | F110: =F69-F138 -> 2 | G110: =G69-G138 -> 1 | H110: =H69-H138 -> 0 | I110: =I69-I138 -> 2 | ... AF110: =AF69-AF138 -> 83 | AG110: =SUM(B110:AF110) -> 308
A111: Suet Ball Holder | B111: =B70-B139 -> 3 | C111: =C70-C139 -> 1 | D111: =D70-D139 -> 0 | E111: =E70-E139 -> 2 | F111: =F70-F139 -> 0 | G111: =G70-G139 -> 0 | H111: =H70-H139 -> 1 | I111: =I70-I139 -> 0 | ... AF111: =AF70-AF139 -> 9 | AG111: =SUM(B111:AF111) -> 110
A112: 3-in-1 Nutrition Set - Blue | B112: =B71-B140 -> 3 | C112: =C71-C140 -> 2 | D112: =D71-D140 -> 4 | E112: =E71-E140 -> 0 | F112: =F71-F140 -> 1 | G112: =G71-G140 -> 2 | H112: =H71-H140 -> 2 | I112: =I71-I140 -> 1 | ... AF112: =AF71-AF140 -> 19 | AG112: =SUM(B112:AF112) -> 138
A113: 3-in-1 Nutrition Set - Yellow | B113: =B72-B141 -> 0 | C113: =C72-C141 -> 1 | D113: =D72-D141 -> 0 | E113: =E72-E141 -> 0 | F113: =F72-F141 -> 1 | G113: =G72-G141 -> 0 | H113: =H72-H141 -> 0 | I113: =I72-I141 -> 0 | ... AF113: =AF72-AF141 -> 0 | AG113: =SUM(B113:AF113) -> 4
A114: Solar Roof Single - Blue | B114: =B73-B142 -> 17 | C114: =C73-C142 -> 5 | D114: =D73-D142 -> 0 | E114: =E73-E142 -> 1 | F114: =F73-F142 -> 2 | G114: =G73-G142 -> 4 | H114: =H73-H142 -> 1 | I114: =I73-I142 -> 2 | ... AF114: =AF73-AF142 -> 5 | AG114: =SUM(B114:AF114) -> 99
A115: Solar Roof Single - Yellow | B115: =B74-B143 -> 1 | C115: =C74-C143 -> 0 | D115: =D74-D143 -> 0 | E115: =E74-E143 -> 0 | F115: =F74-F143 -> 0 | G115: =G74-G143 -> 0 | H115: =H74-H143 -> 0 | I115: =I74-I143 -> 0 | ... AF115: =AF74-AF143 -> 1 | AG115: =SUM(B115:AF115) -> 16
A116: Perch Extender - Blue | B116: =B75-B144 -> 0 | C116: =C75-C144 -> 0 | D116: =D75-D144 -> 0 | E116: =E75-E144 -> 0 | F116: =F75-F144 -> 0 | G116: =G75-G144 -> 0 | H116: =H75-H144 -> 0 | I116: =I75-I144 -> 0 | ... AF116: =AF75-AF144 -> 24 | AG116: =SUM(B116:AF116) -> 208
...

Sheet DTC US&CA - P&L
A1: OCTOBER | B1: 45566 | C1: 45567 | D1: 45568 | E1: 45569 | F1: 45570 | G1: 45571 | H1: 45572 | I1: 45573 | J1: 45574 | K1: 45575 | L1: 45576 | M1: 45577 | N1: 45578 | O1: 45579 | P1: 45580 | Q1: 45581 | R1: 45582 | S1: 45583 | T1: 45584 | U1: 45585 | V1: 45586 | W1: 45587 | X1: 45588 | Y1: 45589 | Z1: 45590 | AA1: 45591 | AB1: 45592 | AC1: 45593 | AD1: 45594 | AE1: 45595 | AF1: 45596
A2: DAY | B2: TUE | C2: WED | D2: THU | E2: FRI | F2: SAT | G2: SUN | H2: MON | I2: TUE | J2: WED | K2: THU | L2: FRI | M2: SAT | N2: SUN | O2: MON | P2: TUE | Q2: WED | R2: THU | S2: FRI | T2: SAT | U2: SUN | V2: MON | W2: TUE | X2: WED | Y2: THU | Z2: FRI | AA2: SAT | AB2: SUN | AC2: MON | AD2: TUE | AE2: WED | AF2: THU
A4: Revenue
A5: Revenue Woocommerce (Platform) | B5: =Summary!B9 -> 9224.84 | C5: =Summary!C9 -> 5831.8 | D5: =Summary!D9 -> 6731.06 | E5: =Summary!E9 -> 5160.16 | F5: =Summary!F9 -> 7525.62 | G5: =Summary!G9 -> 5246.89 | H5: =Summary!H9 -> 5358.3 | I5: =Summary!I9 -> 4961.66 | ... AF5: =Summary!AF9 -> 34342.97 | AG5: =SUM(B5:AF5) -> 480177.93
A6: SUM | B6: =SUM(B5) -> 9224.84 | C6: =SUM(C5) -> 5831.8 | D6: =SUM(D5) -> 6731.06 | E6: =SUM(E5) -> 5160.16 | F6: =SUM(F5) -> 7525.62 | G6: =SUM(G5) -> 5246.89 | H6: =SUM(H5) -> 5358.3 | I6: =SUM(I5) -> 4961.66 | ... AF6: =SUM(AF5) -> 34342.97 | AG6: =SUM(B6:AF6) -> 480177.93
A8: Orders
A9: Orders Woocommerce (Platform) | B9: =Summary!B70 -> 58 | C9: =Summary!C70 -> 36 | D9: =Summary!D70 -> 35 | E9: =Summary!E70 -> 37 | F9: =Summary!F70 -> 41 | G9: =Summary!G70 -> 39 | H9: =Summary!H70 -> 29 | I9: =Summary!I70 -> 27 | ... AF9: =Summary!AF70 -> 144 | AG9: =SUM(B9:AF9) -> 2464
A10: SUM | B10: =SUM(B9) -> 58 | C10: =SUM(C9) -> 36 | D10: =SUM(D9) -> 35 | E10: =SUM(E9) -> 37 | F10: =SUM(F9) -> 41 | G10: =SUM(G9) -> 39 | H10: =SUM(H9) -> 29 | I10: =SUM(I9) -> 27 | ... AF10: =SUM(AF9) -> 144 | AG10: =SUM(B10:AF10) -> 2464
A12: Breakdown
A13: - Hardware | B13: =Summary!B10 -> 4811 | C13: =Summary!C10 -> 3876 | D13: =Summary!D10 -> 4654.3 | E13: =Summary!E10 -> 3588.1 | F13: =Summary!F10 -> 5412.2 | G13: =Summary!G10 -> 3259 | H13: =Summary!H10 -> 3872.1 | I13: =Summary!I10 -> 3757.75 | ... AF13: =Summary!AF10 -> 25189.9 | AG13: =SUM(B13:AF13) -> 274610.98
A14: - Add-ons | B14: =Summary!B11 -> 2000.3 | C14: =Summary!C11 -> 485.9 | D14: =Summary!D11 -> 519 | E14: =Summary!E11 -> 243 | F14: =Summary!F11 -> 409.1 | G14: =Summary!G11 -> 739.3 | H14: =Summary!H11 -> 418.9 | I14: =Summary!I11 -> 235.9 | ... AF14: =Summary!AF11 -> 3108.63 | AG14: =SUM(B14:AF14) -> 119315.99
A15: - Merch | B15: =Summary!B12 -> 0 | C15: =Summary!C12 -> 0 | D15: =Summary!D12 -> 0 | E15: =Summary!E12 -> 0 | F15: =Summary!F12 -> 0 | G15: =Summary!G12 -> 0 | H15: =Summary!H12 -> 0 | I15: =Summary!I12 -> 0 | ... AF15: =Summary!AF12 -> 0 | AG15: =SUM(B15:AF15) -> 539.78
A16: - Seeds | B16: =Summary!B13 -> 710.7 | C16: =Summary!C13 -> 439.3 | D16: =Summary!D13 -> 555.1 | E16: =Summary!E13 -> 621.8 | F16: =Summary!F13 -> 672.7 | G16: =Summary!G13 -> 477.1 | H16: =Summary!H13 -> 344.6 | I16: =Summary!I13 -> 256.1 | ... AF16: =Summary!AF13 -> 439.5 | AG16: =SUM(B16:AF16) -> 11612.2
A17: - Yearly Pro Subscription | B17: =Summary!B14 -> 479.92 | C17: =Summary!C14 -> 299.95 | D17: =Summary!D14 -> 239.96 | E17: =Summary!E14 -> 0 | F17: =Summary!F14 -> 59.99 | G17: =Summary!G14 -> 59.99 | H17: =Summary!H14 -> 0 | I17: =Summary!I14 -> 59.99 | ... AF17: =Summary!AF14 -> 179.97 | AG17: =SUM(B17:AF17) -> 6238.96
A18: - Taxes | B18: =Summary!B15 -> 557.92 | C18: =Summary!C15 -> 353.65 | D18: =Summary!D15 -> 385.26 | E18: =Summary!E15 -> 305.76 | F18: =Summary!F15 -> 501.63 | G18: =Summary!G15 -> 334.5 | H18: =Summary!H15 -> 350.7 | I18: =Summary!I15 -> 297.71 | ... AF18: =Summary!AF15 -> 2207.84 | AG18: =SUM(B18:AF18) -> 29741.03
A19: - Shipping | B19: =Summary!B16 -> 665 | C19: =Summary!C16 -> 377 | D19: =Summary!D16 -> 377.44 | E19: =Summary!E16 -> 401.5 | F19: =Summary!F16 -> 470 | G19: =Summary!G16 -> 377 | H19: =Summary!H16 -> 372 | I19: =Summary!I16 -> 354.21 | ... AF19: =Summary!AF16 -> 3217.13 | AG19: =SUM(B19:AF19) -> 38118.99
A20: SUM | B20: =SUM(B13:B19) -> 9224.84 | C20: =SUM(C13:C19) -> 5831.8 | D20: =SUM(D13:D19) -> 6731.06 | E20: =SUM(E13:E19) -> 5160.16 | F20: =SUM(F13:F19) -> 7525.62 | G20: =SUM(G13:G19) -> 5246.89 | H20: =SUM(H13:H19) -> 5358.3 | I20: =SUM(I13:I19) -> 4961.66 | ... AF20: =SUM(AF13:AF19) -> 34342.97 | AG20: =SUM(B20:AF20) -> 480177.93
A22: Units Sold (Gross)
A23: SKU 1 - Blue | B23: 16 | C23: 6 | D23: 0 | E23: 0 | F23: 0 | G23: 0 | H23: 0 | I23: 0 | J23: 0 | K23: 0 | L23: 0 | M23: 0 | N23: 0 | O23: 0 | P23: 0 | Q23: 0 | R23: 0 | S23: 0 | T23: 0 | U23: 0 | V23: 0 | W23: 0 | X23: 0 | Y23: 1 | Z23: 2 | AA23: 14 | AB23: 11 | AC23: 5 | AD23: 13 | AE23: 7 | AF23: 17 | AG23: =SUM(B23:AF23) -> 92
A24: SKU 2 - Yellow | B24: 0 | C24: 0 | D24: 0 | E24: 0 | F24: 0 | G24: 0 | H24: 0 | I24: 0 | J24: 0 | K24: 0 | L24: 0 | M24: 0 | N24: 0 | O24: 0 | P24: 0 | Q24: 0 | R24: 0 | S24: 0 | T24: 0 | U24: 0 | V24: 0 | W24: 0 | X24: 0 | Y24: 0 | Z24: 0 | AA24: 0 | AB24: 0 | AC24: 0 | AD24: 0 | AE24: 0 | AF24: 0 | AG24: =SUM(B24:AF24) -> 0
A25: SKU 3 - Blue w/ Solar | B25: 0 | C25: 7 | D25: 16 | E25: 10 | F25: 14 | G25: 10 | H25: 10 | I25: 11 | J25: 16 | K25: 12 | L25: 11 | M25: 9 | N25: 14 | O25: 10 | P25: 3 | Q25: 3 | R25: 8 | S25: 6 | T25: 3 | U25: 4 | V25: 4 | W25: 10 | X25: 14 | Y25: 6 | Z25: 10 | AA25: 28 | AB25: 27 | AC25: 11 | AD25: 17 | AE25: 13 | AF25: 28 | AG25: =SUM(B25:AF25) -> 345
A26: SKU 4 - Yellow w/ Solar | B26: 0 | C26: 0 | D26: 0 | E26: 0 | F26: 0 | G26: 0 | H26: 0 | I26: 0 | J26: 0 | K26: 0 | L26: 0 | M26: 0 | N26: 0 | O26: 0 | P26: 0 | Q26: 0 | R26: 0 | S26: 0 | T26: 0 | U26: 0 | V26: 0 | W26: 0 | X26: 0 | Y26: 0 | Z26: 0 | AA26: 0 | AB26: 0 | AC26: 0 | AD26: 0 | AE26: 0 | AF26: 0 | AG26: =SUM(B26:AF26) -> 0
A27: SKU 1 - Blue PRO | P27: 3 | Q27: 7 | R27: 2 | S27: 2 | T27: 4 | U27: 1 | V27: 3 | W27: 1 | X27: 2 | Y27: 4 | Z27: 6 | AA27: 16 | AB27: 8 | AC27: 8 | AD27: 5 | AE27: 22 | AF27: 10 | AG27: =SUM(B27:AF27) -> 104
A28: SKU 2 - Yellow PRO | P28: 0 | Q28: 0 | R28: 0 | S28: 0 | T28: 0 | U28: 0 | V28: 0 | W28: 0 | X28: 0 | Y28: 0 | Z28: 0 | AA28: 0 | AB28: 0 | AC28: 0 | AD28: 0 | AE28: 0 | AF28: 0 | AG28: =SUM(B28:AF28) -> 0
A29: SKU 3 - Blue w/ Solar PRO | P29: 20 | Q29: 14 | R29: 7 | S29: 8 | T29: 6 | U29: 2 | V29: 9 | W29: 1 | X29: 5 | Y29: 10 | Z29: 34 | AA29: 53 | AB29: 50 | AC29: 28 | AD29: 20 | AE29: 30 | AF29: 37 | AG29: =SUM(B29:AF29) -> 334
A30: SKU 4 - Yellow w/ Solar PRO | P30: 0 | Q30: 0 | R30: 0 | S30: 0 | T30: 0 | U30: 0 | V30: 0 | W30: 0 | X30: 0 | Y30: 0 | Z30: 0 | AA30: 0 | AB30: 0 | AC30: 0 | AD30: 0 | AE30: 0 | AF30: 0 | AG30: =SUM(B30:AF30) -> 0
A31: SUM (SKU 1 - SKU 4) | B31: =SUM(B23:B30) -> 16 | C31: =SUM(C23:C30) -> 13 | D31: =SUM(D23:D30) -> 16 | E31: =SUM(E23:E30) -> 10 | F31: =SUM(F23:F30) -> 14 | G31: =SUM(G23:G30) -> 10 | H31: =SUM(H23:H30) -> 10 | I31: =SUM(I23:I30) -> 11 | ... AF31: =SUM(AF23:AF30) -> 92 | AG31: =SUM(B31:AF31) -> 875
A33: SKU 5 - HBF | B33: 1 | C33: 0 | D33: 0 | E33: 0 | F33: 2 | G33: 1 | H33: 2 | I33: 0 | J33: 2 | K33: 0 | L33: 0 | M33: 0 | N33: 1 | O33: 0 | P33: 5 | Q33: 1 | R33: 0 | S33: 0 | T33: 4 | U33: 1 | V33: 2 | W33: 1 | X33: 2 | Y33: 2 | Z33: 0 | AA33: 9 | AB33: 3 | AC33: 1 | AD33: 2 | AE33: 3 | AF33: 1 | AG33: =SUM(B33:AF33) -> 46
A34: SKU 6 - HBF w/ Solar | B34: 2 | C34: 1 | D34: 0 | E34: 2 | F34: 2 | G34: 0 | H34: 1 | I34: 2 | J34: 1 | K34: 0 | L34: 5 | M34: 6 | N34: 3 | O34: 5 | P34: 9 | Q34: 5 | R34: 5 | S34: 3 | T34: 5 | U34: 1 | V34: 1 | W34: 2 | X34: 9 | Y34: 6 | Z34: 7 | AA34: 10 | AB34: 19 | AC34: 6 | AD34: 9 | AE34: 10 | AF34: 12 | AG34: =SUM(B34:AF34) -> 149
A35: SUM (SKU 5 - SKU 6) | B35: =SUM(B33:B34) -> 3 | C35: =SUM(C33:C34) -> 1 | D35: =SUM(D33:D34) -> 0 | E35: =SUM(E33:E34) -> 2 | F35: =SUM(F33:F34) -> 4 | G35: =SUM(G33:G34) -> 1 | H35: =SUM(H33:H34) -> 3 | I35: =SUM(I33:I34) -> 2 | ... AF35: =SUM(AF33:AF34) -> 13 | AG35: =SUM(B35:AF35) -> 195
A37: Wall Mount | B37: 7 | C37: 1 | D37: 5 | E37: 2 | F37: 2 | G37: 1 | H37: 1 | I37: 2 | J37: 3 | K37: 3 | L37: 2 | M37: 2 | N37: 1 | O37: 3 | P37: 2 | Q37: 2 | R37: 1 | S37: 0 | T37: 0 | U37: 2 | V37: 4 | W37: 4 | X37: 6 | Y37: 3 | Z37: 8 | AA37: 15 | AB37: 21 | AC37: 30 | AD37: 35 | AE37: 60 | AF37: 76 | AG37: =SUM(B37:AF37) -> 304
A38: Suet Ball Holder | B38: 5 | C38: 2 | D38: 0 | E38: 2 | F38: 2 | G38: 0 | H38: 2 | I38: 2 | J38: 6 | K38: 9 | L38: 4 | M38: 5 | N38: 4 | O38: 4 | P38: 6 | Q38: 7 | R38: 5 | S38: 3 | T38: 2 | U38: 4 | V38: 4 | W38: 10 | X38: 6 | Y38: 7 | Z38: 7 | AA38: 17 | AB38: 16 | AC38: 10 | AD38: 8 | AE38: 16 | AF38: 9 | AG38: =SUM(B38:AF38) -> 184
A39: 3-in-1 Nutrition Set - Blue | B39: 3 | C39: 2 | D39: 4 | E39: 0 | F39: 1 | G39: 2 | H39: 3 | I39: 1 | J39: 9 | K39: 4 | L39: 5 | M39: 2 | N39: 4 | O39: 3 | P39: 1 | Q39: 2 | R39: 1 | S39: 0 | T39: 0 | U39: 1 | V39: 1 | W39: 5 | X39: 2 | Y39: 7 | Z39: 4 | AA39: 11 | AB39: 16 | AC39: 9 | AD39: 7 | AE39: 9 | AF39: 15 | AG39: =SUM(B39:AF39) -> 134
A40: 3-in-1 Nutrition Set - Yellow | B40: 0 | C40: 1 | D40: 0 | E40: 0 | F40: 1 | G40: 0 | H40: 0 | I40: 0 | J40: 0 | K40: 0 | L40: 0 | M40: 0 | N40: 0 | O40: 0 | P40: 0 | Q40: 0 | R40: 0 | S40: 0 | T40: 0 | U40: 0 | V40: 0 | W40: 1 | X40: 0 | Y40: 0 | Z40: 0 | AA40: 0 | AB40: 0 | AC40: 0 | AD40: 0 | AE40: 0 | AF40: 0 | AG40: =SUM(B40:AF40) -> 3
A41: Solar Roof Single - Blue | B41: 18 | C41: 5 | D41: 0 | E41: 1 | F41: 2 | G41: 4 | H41: 3 | I41: 2 | J41: 7 | K41: 4 | L41: 6 | M41: 1 | N41: 2 | O41: 1 | P41: 2 | Q41: 3 | R41: 7 | S41: 6 | T41: 3 | U41: 2 | V41: 2 | W41: 5 | X41: 3 | Y41: 3 | Z41: 1 | AA41: 11 | AB41: 1 | AC41: 2 | AD41: 8 | AE41: 7 | AF41: 5 | AG41: =SUM(B41:AF41) -> 127
A42: Solar Roof Single - Yellow | B42: 1 | C42: 0 | D42: 0 | E42: 0 | F42: 0 | G42: 2 | H42: 0 | I42: 0 | J42: 2 | K42: 1 | L42: 0 | M42: 1 | N42: 1 | O42: 1 | P42: 0 | Q42: 0 | R42: 1 | S42: 0 | T42: 1 | U42: 1 | V42: 1 | W42: 1 | X42: 0 | Y42: 2 | Z42: 0 | AA42: 1 | AB42: 1 | AC42: 1 | AD42: 1 | AE42: 2 | AF42: 2 | AG42: =SUM(B42:AF42) -> 24
A43: Perch Extender - Blue | B43: 0 | C43: 0 | D43: 0 | E43: 0 | F43: 0 | G43: 0 | H43: 0 | I43: 0 | J43: 0 | K43: 0 | L43: 1 | M43: 4 | N43: 2 | O43: 3 | P43: 8 | Q43: 6 | R43: 5 | S43: 6 | T43: 6 | U43: 4 | V43: 8 | W43: 11 | X43: 6 | Y43: 10 | Z43: 9 | AA43: 27 | AB43: 22 | AC43: 18 | AD43: 17 | AE43: 24 | AF43: 20 | AG43: =SUM(B43:AF43) -> 217
A44: Perch Extender - Yellow | B44: 3 | C44: 0 | D44: 0 | E44: 2 | F44: 1 | G44: 5 | H44: 0 | I44: 1 | J44: 0 | K44: 3 | L44: 1 | M44: 0 | N44: 1 | O44: 0 | P44: 1 | Q44: 0 | R44: 0 | S44: 1 | T44: 2 | U44: 0 | V44: 0 | W44: 0 | X44: 0 | Y44: 2 | Z44: 0 | AA44: 0 | AB44: 1 | AC44: 2 | AD44: 0 | AE44: 2 | AF44: 0 | AG44: =SUM(B44:AF44) -> 28
A45: Solar Roof (HBF) | B45: 3 | C45: 0 | D45: 1 | E45: 0 | F45: 1 | G45: 0 | H45: 0 | I45: 0 | J45: 0 | K45: 0 | L45: 1 | M45: 1 | N45: 1 | O45: 0 | P45: 1 | Q45: 2 | R45: 2 | S45: 0 | T45: 2 | U45: 0 | V45: 0 | W45: 0 | X45: 0 | Y45: 2 | Z45: 1 | AA45: 1 | AB45: 0 | AC45: 0 | AD45: 2 | AE45: 2 | AF45: 1 | AG45: =SUM(B45:AF45) -> 24
A46: Housing - only (HBF) | B46: 1 | C46: 0 | D46: 1 | E46: 0 | F46: 0 | G46: 0 | H46: 0 | I46: 0 | J46: 0 | K46: 0 | L46: 1 | M46: 0 | N46: 2 | O46: 0 | P46: 2 | Q46: 1 | R46: 2 | S46: 0 | T46: 0 | U46: 0 | V46: 0 | W46: 0 | X46: 0 | Y46: 2 | Z46: 0 | AA46: 0 | AB46: 0 | AC46: 0 | AD46: 1 | AE46: 0 | AF46: 1 | AG46: =SUM(B46:AF46) -> 14
A47: Nature Cam PRO | P47: 212 | Q47: 117 | R47: 68 | S47: 46 | T47: 34 | U47: 34 | V47: 18 | W47: 23 | X47: 25 | Y47: 20 | Z47: 52 | AA47: 30 | AB47: 21 | AC47: 36 | AD47: 28 | AE47: 27 | AF47: 15 | AG47: =SUM(B47:AF47) -> 806
A48: SUM (Add-ons) | B48: =SUM(B37:B47) -> 41 | C48: =SUM(C37:C47) -> 11 | D48: =SUM(D37:D47) -> 11 | E48: =SUM(E37:E47) -> 7 | F48: =SUM(F37:F47) -> 10 | G48: =SUM(G37:G47) -> 14 | H48: =SUM(H37:H47) -> 9 | I48: =SUM(I37:I47) -> 8 | ... AF48: =SUM(AF37:AF47) -> 144 | AG48: =SUM(B48:AF48) -> 1865
A50: Seasonal Curation - 8lb | B50: 19 | C50: 13 | D50: 16 | E50: 20 | F50: 18 | G50: 14 | H50: 12 | I50: 7 | J50: 12 | K50: 13 | L50: 12 | M50: 8 | N50: 5 | O50: 8 | P50: 16 | Q50: 13 | R50: 12 | S50: 5 | T50: 5 | U50: 10 | V50: 15 | W50: 8 | X50: 6 | Y50: 11 | Z50: 6 | AA50: 16 | AB50: 16 | AC50: 11 | AD50: 6 | AE50: 3 | AF50: 14 | AG50: =SUM(B50:AF50) -> 350
A51: Seasonal Curation - 20lb | B51: 1 | C51: 1 | D51: 2 | E51: 1 | F51: 1 | G51: 1 | H51: 0 | I51: 1 | J51: 1 | K51: 0 | L51: 1 | M51: 0 | N51: 2 | O51: 0 | P51: 2 | Q51: 1 | R51: 1 | S51: 1 | T51: 1 | U51: 0 | V51: 0 | W51: 0 | X51: 1 | Y51: 0 | Z51: 1 | AA51: 0 | AB51: 0 | AC51: 0 | AD51: 0 | AE51: 0 | AF51: 0 | AG51: =SUM(B51:AF51) -> 20
A52: Buddy Bites - 8lb | B52: 0 | C52: 0 | D52: 0 | E52: 0 | F52: 2 | G52: 1 | H52: 0 | I52: 1 | J52: 0 | K52: 0 | L52: 0 | M52: 0 | N52: 0 | O52: 0 | P52: 1 | Q52: 0 | R52: 0 | S52: 0 | T52: 0 | U52: 0 | V52: 0 | W52: 0 | X52: 0 | Y52: 0 | Z52: 0 | AA52: 0 | AB52: 2 | AC52: 0 | AD52: 0 | AE52: 3 | AF52: 1 | AG52: =SUM(B52:AF52) -> 11
A53: Buddy Bites - 20lb | B53: 0 | C53: 0 | D53: 0 | E53: 0 | F53: 0 | G53: 0 | H53: 0 | I53: 0 | J53: 0 | K53: 1 | L53: 0 | M53: 0 | N53: 0 | O53: 0 | P53: 0 | Q53: 0 | R53: 0 | S53: 0 | T53: 0 | U53: 0 | V53: 0 | W53: 0 | X53: 0 | Y53: 0 | Z53: 0 | AA53: 0 | AB53: 0 | AC53: 0 | AD53: 0 | AE53: 1 | AF53: 0 | AG53: =SUM(B53:AF53) -> 2
A54: Snack n' Soar - 8lb | B54: 0 | C54: 0 | D54: 0 | E54: 0 | F54: 0 | G54: 0 | H54: 0 | I54: 0 | J54: 1 | K54: 0 | L54: 0 | M54: 0 | N54: 1 | O54: 0 | P54: 1 | Q54: 0 | R54: 0 | S54: 0 | T54: 0 | U54: 0 | V54: 0 | W54: 0 | X54: 1 | Y54: 1 | Z54: 0 | AA54: 0 | AB54: 0 | AC54: 0 | AD54: 0 | AE54: 0 | AF54: 1 | AG54: =SUM(B54:AF54) -> 6
A55: Snack n' Soar - 20lb | B55: 1 | C55: 0 | D55: 0 | E55: 0 | F55: 0 | G55: 0 | H55: 0 | I55: 0 | J55: 0 | K55: 0 | L55: 0 | M55: 0 | N55: 0 | O55: 0 | P55: 0 | Q55: 0 | R55: 0 | S55: 0 | T55: 0 | U55: 0 | V55: 0 | W55: 0 | X55: 0 | Y55: 0 | Z55: 1 | AA55: 0 | AB55: 0 | AC55: 0 | AD55: 0 | AE55: 0 | AF55: 0 | AG55: =SUM(B55:AF55) -> 2
A56: Avian Choice - 8lb | B56: 2 | C56: 1 | D56: 0 | E56: 0 | F56: 2 | G56: 1 | H56: 0 | I56: 0 | J56: 0 | K56: 0 | L56: 0 | M56: 0 | N56: 0 | O56: 0 | P56: 1 | Q56: 0 | R56: 1 | S56: 0 | T56: 0 | U56: 0 | V56: 1 | W56: 0 | X56: 0 | Y56: 0 | Z56: 0 | AA56: 0 | AB56: 0 | AC56: 1 | AD56: 2 | AE56: 1 | AF56: 1 | AG56: =SUM(B56:AF56) -> 14
A57: Avian Choice - 20lb | B57: 0 | C57: 0 | D57: 0 | E57: 0 | F57: 0 | G57: 0 | H57: 0 | I57: 0 | J57: 0 | K57: 0 | L57: 0 | M57: 0 | N57: 0 | O57: 0 | P57: 0 | Q57: 0 | R57: 0 | S57: 0 | T57: 0 | U57: 0 | V57: 0 | W57: 0 | X57: 0 | Y57: 0 | Z57: 0 | AA57: 0 | AB57: 1 | AC57: 0 | AD57: 0 | AE57: 0 | AF57: 0 | AG57: =SUM(B57:AF57) -> 1
A58: SUM (Seeds) | B58: =SUM(B50:B57) -> 23 | C58: =SUM(C50:C57) -> 15 | D58: =SUM(D50:D57) -> 18 | E58: =SUM(E50:E57) -> 21 | F58: =SUM(F50:F57) -> 23 | G58: =SUM(G50:G57) -> 17 | H58: =SUM(H50:H57) -> 12 | I58: =SUM(I50:I57) -> 9 | ... AF58: =SUM(AF50:AF57) -> 17 | AG58: =SUM(B58:AF58) -> 406
A60: Merch Units Sold (Gross)
A61: Merch Units | B61: 0 | C61: 0 | D61: 0 | E61: 0 | F61: 0 | G61: 0 | H61: 0 | I61: 0 | J61: 21 | K61: 0 | L61: 0 | M61: 0 | N61: 0 | O61: 0 | P61: 0 | Q61: 0 | R61: 0 | S61: 0 | T61: 0 | U61: 0 | V61: 0 | W61: 0 | X61: 0 | Y61: 0 | Z61: 0 | AA61: 0 | AB61: 0 | AC61: 0 | AD61: 1 | AE61: 0 | AF61: 0 | AG61: =SUM(B61:AF61) -> 22
A63: First-time Customers
A64: SKU 1 - Blue | B64: =B23-B92 -> 14 | C64: =C23-C92 -> 4 | D64: =D23-D92 -> 0 | E64: =E23-E92 -> 0 | F64: =F23-F92 -> 0 | G64: =G23-G92 -> 0 | H64: =H23-H92 -> 0 | I64: =I23-I92 -> 0 | ... AF64: =AF23-AF92 -> 17 | AG64: =SUM(B64:AF64) -> 84
A65: SKU 2 - Yellow | B65: =B24-B93 -> 0 | C65: =C24-C93 -> 0 | D65: =D24-D93 -> 0 | E65: =E24-E93 -> 0 | F65: =F24-F93 -> 0 | G65: =G24-G93 -> 0 | H65: =H24-H93 -> 0 | I65: =I24-I93 -> 0 | ... AF65: =AF24-AF93 -> 0 | AG65: =SUM(B65:AF65) -> 0
A66: SKU 3 - Blue w/ Solar | B66: =B25-B94 -> 0 | C66: =C25-C94 -> 7 | D66: =D25-D94 -> 15 | E66: =E25-E94 -> 9 | F66: =F25-F94 -> 11 | G66: =G25-G94 -> 8 | H66: =H25-H94 -> 9 | I66: =I25-I94 -> 11 | ... AF66: =AF25-AF94 -> 27 | AG66: =SUM(B66:AF66) -> 318
A67: SKU 4 - Yellow w/ Solar | B67: =B26-B95 -> 0 | C67: =C26-C95 -> 0 | D67: =D26-D95 -> 0 | E67: =E26-E95 -> 0 | F67: =F26-F95 -> 0 | G67: =G26-G95 -> 0 | H67: =H26-H95 -> 0 | I67: =I26-I95 -> 0 | ... AF67: =AF26-AF95 -> 0 | AG67: =SUM(B67:AF67) -> 0
A68: SKU 1 - Blue PRO | P68: =P27-P96 -> 2 | Q68: =Q27-Q96 -> 6 | R68: =R27-R96 -> 2 | S68: =S27-S96 -> 2 | T68: =T27-T96 -> 4 | U68: =U27-U96 -> 1 | V68: =V27-V96 -> 3 | W68: =W27-W96 -> 1 | ... AF68: =AF27-AF96 -> 9 | AG68: =SUM(B68:AF68) -> 94
A69: SKU 2 - Yellow PRO | P69: =P28-P97 -> 0 | Q69: =Q28-Q97 -> 0 | R69: =R28-R97 -> 0 | S69: =S28-S97 -> 0 | T69: =T28-T97 -> 0 | U69: =U28-U97 -> 0 | V69: =V28-V97 -> 0 | W69: =W28-W97 -> 0 | ... AF69: =AF28-AF97 -> 0 | AG69: =SUM(B69:AF69) -> 0
A70: SKU 3 - Blue w/ Solar PRO | P70: =P29-P98 -> 8 | Q70: =Q29-Q98 -> 10 | R70: =R29-R98 -> 5 | S70: =S29-S98 -> 6 | T70: =T29-T98 -> 4 | U70: =U29-U98 -> 2 | V70: =V29-V98 -> 8 | W70: =W29-W98 -> 1 | ... AF70: =AF29-AF98 -> 36 | AG70: =SUM(B70:AF70) -> 280
A71: SKU 4 - Yellow w/ Solar PRO | P71: =P30-P99 -> 0 | Q71: =Q30-Q99 -> 0 | R71: =R30-R99 -> 0 | S71: =S30-S99 -> 0 | T71: =T30-T99 -> 0 | U71: =U30-U99 -> 0 | V71: =V30-V99 -> 0 | W71: =W30-W99 -> 0 | ... AF71: =AF30-AF99 -> 0 | AG71: =SUM(B71:AF71) -> 0
A72: SUM (SKU 1 - SKU 4) | B72: =SUM(B64:B71) -> 14 | C72: =SUM(C64:C71) -> 11 | D72: =SUM(D64:D71) -> 15 | E72: =SUM(E64:E71) -> 9 | F72: =SUM(F64:F71) -> 11 | G72: =SUM(G64:G71) -> 8 | H72: =SUM(H64:H71) -> 9 | I72: =SUM(I64:I71) -> 11 | ... AF72: =SUM(AF64:AF71) -> 89 | AG72: =SUM(B72:AF72) -> 776
A74: SKU 5 - HBF | B74: =B33-B102 -> 0 | C74: =C33-C102 -> 0 | D74: =D33-D102 -> 0 | E74: =E33-E102 -> 0 | F74: =F33-F102 -> 2 | G74: =G33-G102 -> 1 | H74: =H33-H102 -> 2 | I74: =I33-I102 -> 0 | ... AF74: =AF33-AF102 -> 1 | AG74: =SUM(B74:AF74) -> 40
A75: SKU 6 - HBF w/ Solar | B75: =B34-B103 -> 1 | C75: =C34-C103 -> 1 | D75: =D34-D103 -> 0 | E75: =E34-E103 -> 2 | F75: =F34-F103 -> 0 | G75: =G34-G103 -> 0 | H75: =H34-H103 -> 0 | I75: =I34-I103 -> 0 | ... AF75: =AF34-AF103 -> 11 | AG75: =SUM(B75:AF75) -> 115
A76: SUM (SKU 5 - SKU 6) | B76: =SUM(B74:B75) -> 1 | C76: =SUM(C74:C75) -> 1 | D76: =SUM(D74:D75) -> 0 | E76: =SUM(E74:E75) -> 2 | F76: =SUM(F74:F75) -> 2 | G76: =SUM(G74:G75) -> 1 | H76: =SUM(H74:H75) -> 2 | I76: =SUM(I74:I75) -> 0 | ... AF76: =SUM(AF74:AF75) -> 12 | AG76: =SUM(B76:AF76) -> 155
A78: Wall Mount | B78: =B37-B106 -> 6 | C78: =C37-C106 -> 1 | D78: =D37-D106 -> 4 | E78: =E37-E106 -> 1 | F78: =F37-F106 -> 2 | G78: =G37-G106 -> 1 | H78: =H37-H106 -> 0 | I78: =I37-I106 -> 2 | ... AF78: =AF37-AF106 -> 74 | AG78: =SUM(B78:AF78) -> 278
A79: Suet Ball Holder | B79: =B38-B107 -> 3 | C79: =C38-C107 -> 1 | D79: =D38-D107 -> 0 | E79: =E38-E107 -> 2 | F79: =F38-F107 -> 0 | G79: =G38-G107 -> 0 | H79: =H38-H107 -> 1 | I79: =I38-I107 -> 0 | ... AF79: =AF38-AF107 -> 6 | AG79: =SUM(B79:AF79) -> 87
A80: 3-in-1 Nutrition Set - Blue | B80: =B39-B108 -> 3 | C80: =C39-C108 -> 2 | D80: =D39-D108 -> 4 | E80: =E39-E108 -> 0 | F80: =F39-F108 -> 1 | G80: =G39-G108 -> 2 | H80: =H39-H108 -> 2 | I80: =I39-I108 -> 1 | ... AF80: =AF39-AF108 -> 14 | AG80: =SUM(B80:AF80) -> 113
A81: 3-in-1 Nutrition Set - Yellow | B81: =B40-B109 -> 0 | C81: =C40-C109 -> 1 | D81: =D40-D109 -> 0 | E81: =E40-E109 -> 0 | F81: =F40-F109 -> 1 | G81: =G40-G109 -> 0 | H81: =H40-H109 -> 0 | I81: =I40-I109 -> 0 | ... AF81: =AF40-AF109 -> 0 | AG81: =SUM(B81:AF81) -> 3
A82: Solar Roof Single - Blue | B82: =B41-B110 -> 17 | C82: =C41-C110 -> 5 | D82: =D41-D110 -> 0 | E82: =E41-E110 -> 1 | F82: =F41-F110 -> 2 | G82: =G41-G110 -> 4 | H82: =H41-H110 -> 1 | I82: =I41-I110 -> 2 | ... AF82: =AF41-AF110 -> 5 | AG82: =SUM(B82:AF82) -> 98
A83: Solar Roof Single - Yellow | B83: =B42-B111 -> 1 | C83: =C42-C111 -> 0 | D83: =D42-D111 -> 0 | E83: =E42-E111 -> 0 | F83: =F42-F111 -> 0 | G83: =G42-G111 -> 0 | H83: =H42-H111 -> 0 | I83: =I42-I111 -> 0 | ... AF83: =AF42-AF111 -> 1 | AG83: =SUM(B83:AF83) -> 13
A84: Perch Extender - Blue | B84: =B43-B112 -> 0 | C84: =C43-C112 -> 0 | D84: =D43-D112 -> 0 | E84: =E43-E112 -> 0 | F84: =F43-F112 -> 0 | G84: =G43-G112 -> 0 | H84: =H43-H112 -> 0 | I84: =I43-I112 -> 0 | ... AF84: =AF43-AF112 -> 20 | AG84: =SUM(B84:AF84) -> 176
A85: Perch Extender - Yellow | B85: =B44-B113 -> 3 | C85: =C44-C113 -> 0 | D85: =D44-D113 -> 0 | E85: =E44-E113 -> 2 | F85: =F44-F113 -> 1 | G85: =G44-G113 -> 3 | H85: =H44-H113 -> 0 | I85: =I44-I113 -> 1 | ... AF85: =AF44-AF113 -> 0 | AG85: =SUM(B85:AF85) -> 23
A86: Solar Roof (HBF) | B86: =B45-B114 -> 1 | C86: =C45-C114 -> 0 | D86: =D45-D114 -> 1 | E86: =E45-E114 -> 0 | F86: =F45-F114 -> 1 | G86: =G45-G114 -> 0 | H86: =H45-H114 -> 0 | I86: =I45-I114 -> 0 | ... AF86: =AF45-AF114 -> 0 | AG86: =SUM(B86:AF86) -> 14
A87: Housing - only (HBF) | B87: =B46-B115 -> 1 | C87: =C46-C115 -> 0 | D87: =D46-D115 -> 1 | E87: =E46-E115 -> 0 | F87: =F46-F115 -> 0 | G87: =G46-G115 -> 0 | H87: =H46-H115 -> 0 | I87: =I46-I115 -> 0 | ... AF87: =AF46-AF115 -> 0 | AG87: =SUM(B87:AF87) -> 10
A88: Nature Cam PRO | P88: =P47-P116 -> 92 | Q88: =Q47-Q116 -> 56 | R88: =R47-R116 -> 23 | S88: =S47-S116 -> 23 | T88: =T47-T116 -> 18 | U88: =U47-U116 -> 17 | V88: =V47-V116 -> 9 | W88: =W47-W116 -> 10 | ... AF88: =AF47-AF116 -> 7 | AG88: =SUM(B88:AF88) -> 365
A89: SUM (Add-ons) | B89: =SUM(B78:B88) -> 35 | C89: =SUM(C78:C88) -> 10 | D89: =SUM(D78:D88) -> 10 | E89: =SUM(E78:E88) -> 6 | F89: =SUM(F78:F88) -> 8 | G89: =SUM(G78:G88) -> 10 | H89: =SUM(H78:H88) -> 4 | I89: =SUM(I78:I88) -> 6 | ... AF89: =SUM(AF78:AF88) -> 127 | AG89: =SUM(B89:AF89) -> 1180
A91: Returning Customers
A92: SKU 1 - Blue | B92: 2 | C92: 2 | D92: 0 | E92: 0 | F92: 0 | G92: 0 | H92: 0 | I92: 0 | J92: 0 | K92: 0 | L92: 0 | M92: 0 | N92: 0 | O92: 0 | P92: 0 | Q92: 0 | R92: 0 | S92: 0 | T92: 0 | U92: 0 | V92: 0 | W92: 0 | X92: 0 | Y92: 0 | Z92: 0 | AA92: 0 | AB92: 1 | AC92: 1 | AD92: 0 | AE92: 2 | AF92: 0 | AG92: =SUM(B92:AF92) -> 8
A93: SKU 2 - Yellow | B93: 0 | C93: 0 | D93: 0 | E93: 0 | F93: 0 | G93: 0 | H93: 0 | I93: 0 | J93: 0 | K93: 0 | L93: 0 | M93: 0 | N93: 0 | O93: 0 | P93: 0 | Q93: 0 | R93: 0 | S93: 0 | T93: 0 | U93: 0 | V93: 0 | W93: 0 | X93: 0 | Y93: 0 | Z93: 0 | AA93: 0 | AB93: 0 | AC93: 0 | AD93: 0 | AE93: 0 | AF93: 0 | AG93: =SUM(B93:AF93) -> 0
A94: SKU 3 - Blue w/ Solar | B94: 0 | C94: 0 | D94: 1 | E94: 1 | F94: 3 | G94: 2 | H94: 1 | I94: 0 | J94: 1 | K94: 1 | L94: 2 | M94: 0 | N94: 0 | O94: 0 | P94: 0 | Q94: 1 | R94: 0 | S94: 2 | T94: 1 | U94: 1 | V94: 1 | W94: 4 | X94: 0 | Y94: 1 | Z94: 0 | AA94: 1 | AB94: 0 | AC94: 0 | AD94: 1 | AE94: 1 | AF94: 1 | AG94: =SUM(B94:AF94) -> 27
A95: SKU 4 - Yellow w/ Solar | B95: 0 | C95: 0 | D95: 0 | E95: 0 | F95: 0 | G95: 0 | H95: 0 | I95: 0 | J95: 0 | K95: 0 | L95: 0 | M95: 0 | N95: 0 | O95: 0 | P95: 0 | Q95: 0 | R95: 0 | S95: 0 | T95: 0 | U95: 0 | V95: 0 | W95: 0 | X95: 0 | Y95: 0 | Z95: 0 | AA95: 0 | AB95: 0 | AC95: 0 | AD95: 0 | AE95: 0 | AF95: 0 | AG95: =SUM(B95:AF95) -> 0
A96: SKU 1 - Blue PRO | P96: 1 | Q96: 1 | R96: 0 | S96: 0 | T96: 0 | U96: 0 | V96: 0 | W96: 0 | X96: 0 | Y96: 0 | Z96: 1 | AA96: 4 | AB96: 0 | AC96: 2 | AD96: 0 | AE96: 0 | AF96: 1 | AG96: =SUM(B96:AF96) -> 10
A97: SKU 2 - Yellow PRO | P97: 0 | Q97: 0 | R97: 0 | S97: 0 | T97: 0 | U97: 0 | V97: 0 | W97: 0 | X97: 0 | Y97: 0 | Z97: 0 | AA97: 0 | AB97: 0 | AC97: 0 | AD97: 0 | AE97: 0 | AF97: 0 | AG97: =SUM(B97:AF97) -> 0
A98: SKU 3 - Blue w/ Solar PRO | P98: 12 | Q98: 4 | R98: 2 | S98: 2 | T98: 2 | U98: 0 | V98: 1 | W98: 0 | X98: 0 | Y98: 3 | Z98: 3 | AA98: 6 | AB98: 3 | AC98: 5 | AD98: 6 | AE98: 4 | AF98: 1 | AG98: =SUM(B98:AF98) -> 54
A99: SKU 4 - Yellow w/ Solar PRO | P99: 0 | Q99: 0 | R99: 0 | S99: 0 | T99: 0 | U99: 0 | V99: 0 | W99: 0 | X99: 0 | Y99: 0 | Z99: 0 | AA99: 0 | AB99: 0 | AC99: 0 | AD99: 0 | AE99: 0 | AF99: 0 | AG99: =SUM(B99:AF99) -> 0
A100: SUM (SKU 1 - SKU 4) | B100: =SUM(B92:B99) -> 2 | C100: =SUM(C92:C99) -> 2 | D100: =SUM(D92:D99) -> 1 | E100: =SUM(E92:E99) -> 1 | F100: =SUM(F92:F99) -> 3 | G100: =SUM(G92:G99) -> 2 | H100: =SUM(H92:H99) -> 1 | I100: =SUM(I92:I99) -> 0 | ... AF100: =SUM(AF92:AF99) -> 3 | AG100: =SUM(B100:AF100) -> 99
A102: SKU 5 - HBF | B102: 1 | C102: 0 | D102: 0 | E102: 0 | F102: 0 | G102: 0 | H102: 0 | I102: 0 | J102: 0 | K102: 0 | L102: 0 | M102: 0 | N102: 1 | O102: 0 | P102: 0 | Q102: 0 | R102: 0 | S102: 0 | T102: 0 | U102: 0 | V102: 1 | W102: 0 | X102: 0 | Y102: 1 | Z102: 0 | AA102: 2 | AB102: 0 | AC102: 0 | AD102: 0 | AE102: 0 | AF102: 0 | AG102: =SUM(B102:AF102) -> 6
A103: SKU 6 - HBF w/ Solar | B103: 1 | C103: 0 | D103: 0 | E103: 0 | F103: 2 | G103: 0 | H103: 1 | I103: 2 | J103: 0 | K103: 0 | L103: 3 | M103: 1 | N103: 1 | O103: 0 | P103: 2 | Q103: 1 | R103: 3 | S103: 0 | T103: 1 | U103: 1 | V103: 0 | W103: 1 | X103: 2 | Y103: 2 | Z103: 0 | AA103: 1 | AB103: 4 | AC103: 1 | AD103: 2 | AE103: 1 | AF103: 1 | AG103: =SUM(B103:AF103) -> 34
A104: SUM (SKU 5 - SKU 6) | B104: =SUM(B102:B103) -> 2 | C104: =SUM(C102:C103) -> 0 | D104: =SUM(D102:D103) -> 0 | E104: =SUM(E102:E103) -> 0 | F104: =SUM(F102:F103) -> 2 | G104: =SUM(G102:G103) -> 0 | H104: =SUM(H102:H103) -> 1 | I104: =SUM(I102:I103) -> 2 | ... AF104: =SUM(AF102:AF103) -> 1 | AG104: =SUM(B104:AF104) -> 40
A106: Wall Mount | B106: 1 | C106: 0 | D106: 1 | E106: 1 | F106: 0 | G106: 0 | H106: 1 | I106: 0 | J106: 1 | K106: 1 | L106: 1 | M106: 0 | N106: 0 | O106: 0 | P106: 0 | Q106: 1 | R106: 0 | S106: 0 | T106: 0 | U106: 0 | V106: 1 | W106: 3 | X106: 0 | Y106: 0 | Z106: 0 | AA106: 2 | AB106: 1 | AC106: 3 | AD106: 1 | AE106: 5 | AF106: 2 | AG106: =SUM(B106:AF106) -> 26
A107: Suet Ball Holder | B107: 2 | C107: 1 | D107: 0 | E107: 0 | F107: 2 | G107: 0 | H107: 1 | I107: 2 | J107: 3 | K107: 6 | L107: 3 | M107: 3 | N107: 4 | O107: 3 | P107: 5 | Q107: 4 | R107: 3 | S107: 3 | T107: 2 | U107: 3 | V107: 4 | W107: 7 | X107: 4 | Y107: 2 | Z107: 2 | AA107: 7 | AB107: 5 | AC107: 6 | AD107: 3 | AE107: 4 | AF107: 3 | AG107: =SUM(B107:AF107) -> 97
A108: 3-in-1 Nutrition Set - Blue | B108: 0 | C108: 0 | D108: 0 | E108: 0 | F108: 0 | G108: 0 | H108: 1 | I108: 0 | J108: 1 | K108: 2 | L108: 4 | M108: 0 | N108: 0 | O108: 0 | P108: 0 | Q108: 0 | R108: 0 | S108: 0 | T108: 0 | U108: 0 | V108: 0 | W108: 3 | X108: 0 | Y108: 0 | Z108: 0 | AA108: 2 | AB108: 1 | AC108: 2 | AD108: 2 | AE108: 2 | AF108: 1 | AG108: =SUM(B108:AF108) -> 21
A109: 3-in-1 Nutrition Set - Yellow | B109: 0 | C109: 0 | D109: 0 | E109: 0 | F109: 0 | G109: 0 | H109: 0 | I109: 0 | J109: 0 | K109: 0 | L109: 0 | M109: 0 | N109: 0 | O109: 0 | P109: 0 | Q109: 0 | R109: 0 | S109: 0 | T109: 0 | U109: 0 | V109: 0 | W109: 0 | X109: 0 | Y109: 0 | Z109: 0 | AA109: 0 | AB109: 0 | AC109: 0 | AD109: 0 | AE109: 0 | AF109: 0 | AG109: =SUM(B109:AF109) -> 0
A110: Solar Roof Single - Blue | B110: 1 | C110: 0 | D110: 0 | E110: 0 | F110: 0 | G110: 0 | H110: 2 | I110: 0 | J110: 3 | K110: 0 | L110: 5 | M110: 0 | N110: 0 | O110: 1 | P110: 1 | Q110: 2 | R110: 2 | S110: 2 | T110: 0 | U110: 0 | V110: 1 | W110: 1 | X110: 0 | Y110: 0 | Z110: 0 | AA110: 2 | AB110: 1 | AC110: 1 | AD110: 3 | AE110: 1 | AF110: 0 | AG110: =SUM(B110:AF110) -> 29
A111: Solar Roof Single - Yellow | B111: 0 | C111: 0 | D111: 0 | E111: 0 | F111: 0 | G111: 2 | H111: 0 | I111: 0 | J111: 0 | K111: 0 | L111: 0 | M111: 1 | N111: 1 | O111: 0 | P111: 0 | Q111: 0 | R111: 1 | S111: 0 | T111: 1 | U111: 1 | V111: 0 | W111: 1 | X111: 0 | Y111: 0 | Z111: 0 | AA111: 0 | AB111: 0 | AC111: 1 | AD111: 1 | AE111: 0 | AF111: 1 | AG111: =SUM(B111:AF111) -> 11
A112: Perch Extender - Blue | B112: 0 | C112: 0 | D112: 0 | E112: 0 | F112: 0 | G112: 0 | H112: 0 | I112: 0 | J112: 0 | K112: 0 | L112: 0 | M112: 2 | N112: 1 | O112: 0 | P112: 4 | Q112: 1 | R112: 0 | S112: 0 | T112: 3 | U112: 1 | V112: 2 | W112: 5 | X112: 1 | Y112: 1 | Z112: 1 | AA112: 7 | AB112: 0 | AC112: 4 | AD112: 4 | AE112: 4 | AF112: 0 | AG112: =SUM(B112:AF112) -> 41
A113: Perch Extender - Yellow | B113: 0 | C113: 0 | D113: 0 | E113: 0 | F113: 0 | G113: 2 | H113: 0 | I113: 0 | J113: 0 | K113: 0 | L113: 0 | M113: 0 | N113: 0 | O113: 0 | P113: 0 | Q113: 0 | R113: 0 | S113: 0 | T113: 1 | U113: 0 | V113: 0 | W113: 0 | X113: 0 | Y113: 0 | Z113: 0 | AA113: 0 | AB113: 0 | AC113: 1 | AD113: 0 | AE113: 1 | AF113: 0 | AG113: =SUM(B113:AF113) -> 5
A114: Solar Roof (HBF) | B114: 2 | C114: 0 | D114: 0 | E114: 0 | F114: 0 | G114: 0 | H114: 0 | I114: 0 | J114: 0 | K114: 0 | L114: 0 | M114: 0 | N114: 1 | O114: 0 | P114: 1 | Q114: 1 | R114: 1 | S114: 0 | T114: 0 | U114: 0 | V114: 0 | W114: 0 | X114: 0 | Y114: 0 | Z114: 0 | AA114: 1 | AB114: 0 | AC114: 0 | AD114: 1 | AE114: 1 | AF114: 1 | AG114: =SUM(B114:AF114) -> 10
...

Sheet DTC EU - P&L
A1: OCTOBER | B1: 45566 | C1: 45567 | D1: 45568 | E1: 45569 | F1: 45570 | G1: 45571 | H1: 45572 | I1: 45573 | J1: 45574 | K1: 45575 | L1: 45576 | M1: 45577 | N1: 45578 | O1: 45579 | P1: 45580 | Q1: 45581 | R1: 45582 | S1: 45583 | T1: 45584 | U1: 45585 | V1: 45586 | W1: 45587 | X1: 45588 | Y1: 45589 | Z1: 45590 | AA1: 45591 | AB1: 45592 | AC1: 45593 | AD1: 45594 | AE1: 45595 | AF1: 45596
A2: DAY | B2: TUE | C2: WED | D2: THU | E2: FRI | F2: SAT | G2: SUN | H2: MON | I2: TUE | J2: WED | K2: THU | L2: FRI | M2: SAT | N2: SUN | O2: MON | P2: TUE | Q2: WED | R2: THU | S2: FRI | T2: SAT | U2: SUN | V2: MON | W2: TUE | X2: WED | Y2: THU | Z2: FRI | AA2: SAT | AB2: SUN | AC2: MON | AD2: TUE | AE2: WED | AF2: THU
A4: Revenue
A5: Revenue Woocommerce (Platform) | B5: =Summary!B17 -> / | C5: =Summary!C17 -> / | D5: =Summary!D17 -> / | E5: =Summary!E17 -> / | F5: =Summary!F17 -> / | G5: =Summary!G17 -> / | H5: =Summary!H17 -> / | I5: =Summary!I17 -> / | ... AF5: =Summary!AF17 -> 6908.08 | AG5: =SUM(B5:AF5) -> 42769.45
A6: SUM | B6: =SUM(B5) -> 0 | C6: =SUM(C5) -> 0 | D6: =SUM(D5) -> 0 | E6: =SUM(E5) -> 0 | F6: =SUM(F5) -> 0 | G6: =SUM(G5) -> 0 | H6: =SUM(H5) -> 0 | I6: =SUM(I5) -> 0 | ... AF6: =SUM(AF5) -> 6908.08 | AG6: =SUM(B6:AF6) -> 42769.45
A8: Orders
A9: Orders Woocommerce (Platform) | B9: =Summary!B76 | C9: =Summary!C76 | D9: =Summary!D76 | E9: =Summary!E76 | F9: =Summary!F76 | G9: =Summary!G76 | H9: =Summary!H76 | I9: =Summary!I76 | ... AF9: =Summary!AF76 -> 19 | AG9: =SUM(B9:AF9) -> 137
A10: SUM | B10: =SUM(B9) -> 0 | C10: =SUM(C9) -> 0 | D10: =SUM(D9) -> 0 | E10: =SUM(E9) -> 0 | F10: =SUM(F9) -> 0 | G10: =SUM(G9) -> 0 | H10: =SUM(H9) -> 0 | I10: =SUM(I9) -> 0 | ... AF10: =SUM(AF9) -> 19 | AG10: =SUM(B10:AF10) -> 137
A12: Breakdown
A13: - Hardware | K13: 401.68 | Q13: 650.85 | R13: 3662.15 | S13: 2528.17 | T13: 1309.63 | U13: 247.11 | V13: 1023 | W13: 612.23 | X13: 0 | Y13: 878.99 | Z13: 695.73 | AA13: 223.2 | AB13: 1260.15 | AC13: 1606.95 | AD13: 3771.03 | AE13: 3453.22 | AF13: 4005.09 | AG13: =SUM(B13:AF13) -> 26329.18
A14: - Add-ons | K14: 0 | Q14: 266.24 | R14: 226.32 | S14: 191.96 | T14: 112.84 | U14: 0 | V14: 70.78 | W14: 15.57 | X14: 0 | Y14: 225.78 | Z14: 158.11 | AA14: 31.4 | AB14: 153.01 | AC14: 244.59 | AD14: 224.05 | AE14: 274.29 | AF14: 412.45 | AG14: =SUM(B14:AF14) -> 2607.39
A15: - Merch | K15: 0 | Q15: 0 | R15: 0 | S15: 0 | T15: 0 | U15: 0 | V15: 0 | W15: 0 | X15: 0 | Y15: 0 | Z15: 0 | AA15: 0 | AB15: 0 | AC15: 0 | AD15: 0 | AE15: 0 | AF15: 0 | AG15: =SUM(B15:AF15) -> 0
A16: - Seeds | K16: 0 | Q16: 0 | R16: 0 | S16: 0 | T16: 0 | U16: 0 | V16: 0 | W16: 0 | X16: 0 | Y16: 0 | Z16: 0 | AA16: 0 | AB16: 0 | AC16: 0 | AD16: 0 | AE16: 0 | AF16: 0 | AG16: =SUM(B16:AF16) -> 0
A17: - Yearly Pro Subscription | K17: 0 | Q17: 0 | R17: 0 | S17: 0 | T17: 0 | U17: 0 | V17: 0 | W17: 0 | X17: 0 | Y17: 0 | Z17: 0 | AA17: 0 | AB17: 0 | AC17: 0 | AD17: 0 | AE17: 0 | AF17: 0 | AG17: =SUM(B17:AF17) -> 0
A18: - Taxes | K18: 76.32 | Q18: 178.91 | R18: 819.53 | S18: 585.07 | T18: 295.86 | U18: 51.89 | V18: 228.22 | W18: 148.2 | X18: 0 | Y18: 226.43 | Z18: 175.16 | AA18: 62.4 | AB18: 294.84 | AC18: 398.46 | AD18: 842.12 | AE18: 773.49 | AF18: 941.46 | AG18: =SUM(B18:AF18) -> 6098.36
A19: - Shipping | K19: 70 | Q19: 85 | R19: 470 | S19: 325 | T19: 160 | U19: 25 | V19: 135 | W19: 75 | X19: 0 | Y19: 130 | Z19: 85 | AA19: 35 | AB19: 170 | AC19: 185 | AD19: 495 | AE19: 430 | AF19: 500 | AG19: =SUM(B19:AF19) -> 3375
A20: SUM | K20: =sum(K13:K19) -> 548 | Q20: =SUM(Q13:Q19) -> 1181 | R20: =SUM(R13:R19) -> 5178 | S20: =SUM(S13:S19) -> 3630.2 | T20: =SUM(T13:T19) -> 1878.33 | U20: =SUM(U13:U19) -> 324 | V20: =SUM(V13:V19) -> 1457 | W20: =SUM(W13:W19) -> 851 | X20: =SUM(X13:X19) -> 0 | ... AF20: =SUM(AF13:AF19) -> 5859 | AG20: =SUM(B20:AF20) -> 38409.93
A22: Units Sold (Gross)
A23: SKU 1 - Blue | K23: 2 | Q23: 0 | R23: 0 | S23: 0 | T23: 0 | U23: 0 | V23: 1 | W23: 0 | X23: 0 | Y23: 0 | Z23: 0 | AA23: 0 | AB23: 1 | AC23: 0 | AD23: 5 | AE23: 0 | AF23: 4 | AG23: =SUM(B23:AF23) -> 13
A24: SKU 2 - Yellow | K24: 0 | Q24: 0 | R24: 0 | S24: 0 | T24: 0 | U24: 0 | V24: 0 | W24: 0 | X24: 0 | Y24: 0 | Z24: 0 | AA24: 0 | AB24: 0 | AC24: 0 | AD24: 0 | AE24: 0 | AF24: 0 | AG24: =SUM(B24:AF24) -> 0
A25: SKU 3 - Blue w/ Solar | K25: 0 | Q25: 0 | R25: 0 | S25: 0 | T25: 0 | U25: 0 | V25: 0 | W25: 0 | X25: 0 | Y25: 0 | Z25: 0 | AA25: 0 | AB25: 0 | AC25: 0 | AD25: 0 | AE25: 0 | AF25: 0 | AG25: =SUM(B25:AF25) -> 0
A26: SKU 4 - Yellow w/ Solar | K26: 0 | Q26: 0 | R26: 0 | S26: 0 | T26: 0 | U26: 0 | V26: 0 | W26: 0 | X26: 0 | Y26: 0 | Z26: 0 | AA26: 0 | AB26: 0 | AC26: 0 | AD26: 0 | AE26: 0 | AF26: 0 | AG26: =SUM(B26:AF26) -> 0
A27: SKU 1 - Blue PRO | Q27: 3 | R27: 1 | S27: 3 | T27: 1 | U27: 0 | V27: 3 | W27: 2 | X27: 0 | Y27: 0 | Z27: 0 | AA27: 0 | AB27: 1 | AC27: 0 | AD27: 4 | AE27: 5 | AF27: 8 | AG27: =SUM(B27:AF27) -> 31
A28: SKU 2 - Yellow PRO | Q28: 0 | R28: 0 | S28: 0 | T28: 0 | U28: 0 | V28: 0 | W28: 0 | X28: 0 | Y28: 0 | Z28: 0 | AA28: 0 | AB28: 0 | AC28: 0 | AD28: 0 | AE28: 0 | AF28: 0 | AG28: =SUM(B28:AF28) -> 0
A29: SKU 3 - Blue w/ Solar PRO | Q29: 1 | R29: 18 | S29: 10 | T29: 5 | U29: 1 | V29: 1 | W29: 1 | X29: 0 | Y29: 4 | Z29: 3 | AA29: 1 | AB29: 4 | AC29: 7 | AD29: 10 | AE29: 11 | AF29: 10 | AG29: =SUM(B29:AF29) -> 87
A30: SKU 4 - Yellow w/ Solar PRO | Q30: 0 | R30: 0 | S30: 0 | T30: 0 | U30: 0 | V30: 0 | W30: 0 | X30: 0 | Y30: 0 | Z30: 0 | AA30: 0 | AB30: 0 | AC30: 0 | AD30: 0 | AE30: 0 | AF30: 0 | AG30: =SUM(B30:AF30) -> 0
A31: SUM (SKU 1 - SKU 4) | B31: =SUM(B23:B30) -> 0 | C31: =SUM(C23:C30) -> 0 | D31: =SUM(D23:D30) -> 0 | E31: =SUM(E23:E30) -> 0 | F31: =SUM(F23:F30) -> 0 | G31: =SUM(G23:G30) -> 0 | H31: =SUM(H23:H30) -> 0 | I31: =SUM(I23:I30) -> 0 | ... AF31: =SUM(AF23:AF30) -> 22 | AG31: =SUM(B31:AF31) -> 131
A33: SKU 5 - HBF | AG33: =SUM(B33:AF33) -> 0
A34: SKU 6 - HBF w/ Solar | AG34: =SUM(B34:AF34) -> 0
A35: SUM (SKU 5 - SKU 6) | B35: =SUM(B33:B34) -> 0 | C35: =SUM(C33:C34) -> 0 | D35: =SUM(D33:D34) -> 0 | E35: =SUM(E33:E34) -> 0 | F35: =SUM(F33:F34) -> 0 | G35: =SUM(G33:G34) -> 0 | H35: =SUM(H33:H34) -> 0 | I35: =SUM(I33:I34) -> 0 | ... AF35: =SUM(AF33:AF34) -> 0 | AG35: =SUM(B35:AF35) -> 0
A37: Wall Mount | Q37: 1 | R37: 3 | S37: 2 | T37: 0 | U37: 0 | V37: 2 | W37: 0 | X37: 0 | Y37: 3 | Z37: 2 | AA37: 1 | AB37: 1 | AC37: 3 | AD37: 0 | AE37: 3 | AF37: 9 | AG37: =SUM(B37:AF37) -> 30
A38: Suet Ball Holder | Q38: 3 | R38: 1 | S38: 2 | T38: 2 | U38: 0 | V38: 0 | W38: 1 | X38: 0 | Y38: 0 | Z38: 1 | AA38: 1 | AB38: 1 | AC38: 3 | AD38: 3 | AE38: 3 | AF38: 3 | AG38: =SUM(B38:AF38) -> 24
A39: 3-in-1 Nutrition Set - Blue | Q39: 2 | R39: 2 | S39: 2 | T39: 1 | U39: 0 | V39: 0 | W39: 0 | X39: 0 | Y39: 2 | Z39: 2 | AA39: 0 | AB39: 1 | AC39: 3 | AD39: 3 | AE39: 2 | AF39: 5 | AG39: =SUM(B39:AF39) -> 25
A40: 3-in-1 Nutrition Set - Yellow | Q40: 1 | R40: 0 | S40: 0 | T40: 0 | U40: 0 | V40: 0 | W40: 0 | X40: 0 | Y40: 0 | Z40: 0 | AA40: 0 | AB40: 0 | AC40: 0 | AD40: 0 | AE40: 0 | AF40: 0 | AG40: =SUM(B40:AF40) -> 1
A41: Solar Roof Single - Blue | Q41: 0 | R41: 0 | S41: 0 | T41: 0 | U41: 0 | V41: 0 | W41: 0 | X41: 0 | Y41: 1 | Z41: 0 | AA41: 0 | AB41: 0 | AC41: 0 | AD41: 0 | AE41: 0 | AF41: 0 | AG41: =SUM(B41:AF41) -> 1
A42: Solar Roof Single - Yellow | Q42: 0 | R42: 0 | S42: 0 | T42: 0 | U42: 0 | V42: 0 | W42: 0 | X42: 0 | Y42: 0 | Z42: 0 | AA42: 0 | AB42: 1 | AC42: 0 | AD42: 1 | AE42: 1 | AF42: 0 | AG42: =SUM(B42:AF42) -> 3
A43: Perch Extender - Blue | Q43: 3 | R43: 3 | S43: 2 | T43: 2 | U43: 0 | V43: 1 | W43: 0 | X43: 0 | Y43: 2 | Z43: 3 | AA43: 0 | AB43: 2 | AC43: 4 | AD43: 3 | AE43: 3 | AF43: 4 | AG43: =SUM(B43:AF43) -> 32
A44: Perch Extender - Yellow | Q44: 1 | R44: 0 | S44: 0 | T44: 0 | U44: 0 | V44: 0 | W44: 0 | X44: 0 | Y44: 1 | Z44: 0 | AA44: 0 | AB44: 0 | AC44: 0 | AD44: 0 | AE44: 1 | AF44: 0 | AG44: =SUM(B44:AF44) -> 3
A45: Solar Roof (HBF) | AG45: =SUM(B45:AF45) -> 0
A46: Housing - only (HBF) | AG46: =SUM(B46:AF46) -> 0
A47: Nature Cam PRO | AG47: =SUM(B47:AF47) -> 0
A48: SUM (Add-ons) | B48: =SUM(B37:B47) -> 0 | C48: =SUM(C37:C47) -> 0 | D48: =SUM(D37:D47) -> 0 | E48: =SUM(E37:E47) -> 0 | F48: =SUM(F37:F47) -> 0 | G48: =SUM(G37:G47) -> 0 | H48: =SUM(H37:H47) -> 0 | I48: =SUM(I37:I47) -> 0 | ... AF48: =SUM(AF37:AF47) -> 21 | AG48: =SUM(B48:AF48) -> 119
A50: Seasonal Curation - 8lb | AG50: =SUM(B50:AF50) -> 0
A51: Seasonal Curation - 20lb | AG51: =SUM(B51:AF51) -> 0
A52: Buddy Bites - 8lb | AG52: =SUM(B52:AF52) -> 0
A53: Buddy Bites - 20lb | AG53: =SUM(B53:AF53) -> 0
A54: Snack n' Soar - 8lb | AG54: =SUM(B54:AF54) -> 0
A55: Snack n' Soar - 20lb | AG55: =SUM(B55:AF55) -> 0
A56: Avian Choice - 8lb | AG56: =SUM(B56:AF56) -> 0
A57: Avian Choice - 20lb | AG57: =SUM(B57:AF57) -> 0
A58: SUM (Seeds) | B58: =SUM(B50:B57) -> 0 | C58: =SUM(C50:C57) -> 0 | D58: =SUM(D50:D57) -> 0 | E58: =SUM(E50:E57) -> 0 | F58: =SUM(F50:F57) -> 0 | G58: =SUM(G50:G57) -> 0 | H58: =SUM(H50:H57) -> 0 | I58: =SUM(I50:I57) -> 0 | ... AF58: =SUM(AF50:AF57) -> 0 | AG58: =SUM(B58:AF58) -> 0
A60: Merch Units Sold (Gross)
A61: Merch Units | B61: 0 | C61: 0 | D61: 0 | E61: 0 | F61: 0 | G61: 0 | H61: 0 | I61: 0 | J61: 0 | K61: 0 | L61: 0 | M61: 0 | N61: 0 | O61: 0 | P61: 0 | Q61: 0 | R61: 0 | S61: 0 | T61: 0 | U61: 0 | V61: 0 | W61: 0 | X61: 0 | Y61: 0 | Z61: 0 | AA61: 0 | AB61: 0 | AC61: 0 | AD61: 0 | AE61: 0 | AF61: 0 | AG61: =SUM(B61:AF61) -> 0
A63: First-time Customers
A64: SKU 1 - Blue | K64: =K23-K92 -> 2 | Q64: =Q23-Q92 -> 0 | R64: =R23-R92 -> 0 | S64: =S23-S92 -> 0 | T64: =T23-T92 -> 0 | U64: =U23-U92 -> 0 | V64: =V23-V92 -> 1 | W64: =W23-W92 -> 0 | X64: =X23-X92 -> 0 | ... AF64: =AF23-AF92 -> 4 | AG64: =SUM(B64:AF64) -> 13
A65: SKU 2 - Yellow | K65: =K24-K93 -> 0 | Q65: =Q24-Q93 -> 0 | R65: =R24-R93 -> 0 | S65: =S24-S93 -> 0 | T65: =T24-T93 -> 0 | U65: =U24-U93 -> 0 | V65: =V24-V93 -> 0 | W65: =W24-W93 -> 0 | X65: =X24-X93 -> 0 | ... AF65: =AF24-AF93 -> 0 | AG65: =SUM(B65:AF65) -> 0
A66: SKU 3 - Blue w/ Solar | K66: =K25-K94 -> 0 | Q66: =Q25-Q94 -> 0 | R66: =R25-R94 -> 0 | S66: =S25-S94 -> 0 | T66: =T25-T94 -> 0 | U66: =U25-U94 -> 0 | V66: =V25-V94 -> 0 | W66: =W25-W94 -> 0 | X66: =X25-X94 -> 0 | ... AF66: =AF25-AF94 -> 0 | AG66: =SUM(B66:AF66) -> 0
A67: SKU 4 - Yellow w/ Solar | K67: =K26-K95 -> 0 | Q67: =Q26-Q95 -> 0 | R67: =R26-R95 -> 0 | S67: =S26-S95 -> 0 | T67: =T26-T95 -> 0 | U67: =U26-U95 -> 0 | V67: =V26-V95 -> 0 | W67: =W26-W95 -> 0 | X67: =X26-X95 -> 0 | ... AF67: =AF26-AF95 -> 0 | AG67: =SUM(B67:AF67) -> 0
A68: SKU 1 - Blue PRO | Q68: =Q27-Q96 -> 3 | R68: =R27-R96 -> 1 | S68: =S27-S96 -> 3 | T68: =T27-T96 -> 1 | U68: =U27-U96 -> 0 | V68: =V27-V96 -> 3 | W68: =W27-W96 -> 1 | X68: =X27-X96 -> 0 | ... AF68: =AF27-AF96 -> 8 | AG68: =SUM(B68:AF68) -> 30
A69: SKU 2 - Yellow PRO | Q69: =Q28-Q97 -> 0 | R69: =R28-R97 -> 0 | S69: =S28-S97 -> 0 | T69: =T28-T97 -> 0 | U69: =U28-U97 -> 0 | V69: =V28-V97 -> 0 | W69: =W28-W97 -> 0 | X69: =X28-X97 -> 0 | ... AF69: =AF28-AF97 -> 0 | AG69: =SUM(B69:AF69) -> 0
A70: SKU 3 - Blue w/ Solar PRO | Q70: =Q29-Q98 -> 1 | R70: =R29-R98 -> 18 | S70: =S29-S98 -> 10 | T70: =T29-T98 -> 5 | U70: =U29-U98 -> 1 | V70: =V29-V98 -> 1 | W70: =W29-W98 -> 1 | X70: =X29-X98 -> 0 | ... AF70: =AF29-AF98 -> 10 | AG70: =SUM(B70:AF70) -> 87
A71: SKU 4 - Yellow w/ Solar PRO | Q71: =Q30-Q99 -> 0 | R71: =R30-R99 -> 0 | S71: =S30-S99 -> 0 | T71: =T30-T99 -> 0 | U71: =U30-U99 -> 0 | V71: =V30-V99 -> 0 | W71: =W30-W99 -> 0 | X71: =X30-X99 -> 0 | ... AF71: =AF30-AF99 -> 0 | AG71: =SUM(B71:AF71) -> 0
A72: SUM (SKU 1 - SKU 4) | B72: =SUM(B64:B71) -> 0 | C72: =SUM(C64:C71) -> 0 | D72: =SUM(D64:D71) -> 0 | E72: =SUM(E64:E71) -> 0 | F72: =SUM(F64:F71) -> 0 | G72: =SUM(G64:G71) -> 0 | H72: =SUM(H64:H71) -> 0 | I72: =SUM(I64:I71) -> 0 | ... AF72: =SUM(AF64:AF71) -> 22 | AG72: =SUM(B72:AF72) -> 130
A74: SKU 5 - HBF | AG74: =SUM(B74:AF74) -> 0
A75: SKU 6 - HBF w/ Solar | AG75: =SUM(B75:AF75) -> 0
A76: SUM (SKU 5 - SKU 6) | B76: =SUM(B74:B75) -> 0 | C76: =SUM(C74:C75) -> 0 | D76: =SUM(D74:D75) -> 0 | E76: =SUM(E74:E75) -> 0 | F76: =SUM(F74:F75) -> 0 | G76: =SUM(G74:G75) -> 0 | H76: =SUM(H74:H75) -> 0 | I76: =SUM(I74:I75) -> 0 | ... AF76: =SUM(AF74:AF75) -> 0 | AG76: =SUM(B76:AF76) -> 0
A78: Wall Mount | Q78: =Q37-Q106 -> 1 | R78: =R37-R106 -> 3 | S78: =S37-S106 -> 2 | T78: =T37-T106 -> 0 | U78: =U37-U106 -> 0 | V78: =V37-V106 -> 2 | W78: =W37-W106 -> 0 | X78: =X37-X106 -> 0 | ... AF78: =AF37-AF106 -> 9 | AG78: =SUM(B78:AF78) -> 30
A79: Suet Ball Holder | Q79: =Q38-Q107 -> 3 | R79: =R38-R107 -> 1 | S79: =S38-S107 -> 2 | T79: =T38-T107 -> 2 | U79: =U38-U107 -> 0 | V79: =V38-V107 -> 0 | W79: =W38-W107 -> 0 | X79: =X38-X107 -> 0 | ... AF79: =AF38-AF107 -> 3 | AG79: =SUM(B79:AF79) -> 23
A80: 3-in-1 Nutrition Set - Blue | Q80: =Q39-Q108 -> 2 | R80: =R39-R108 -> 2 | S80: =S39-S108 -> 2 | T80: =T39-T108 -> 1 | U80: =U39-U108 -> 0 | V80: =V39-V108 -> 0 | W80: =W39-W108 -> 0 | X80: =X39-X108 -> 0 | ... AF80: =AF39-AF108 -> 5 | AG80: =SUM(B80:AF80) -> 25
A81: 3-in-1 Nutrition Set - Yellow | Q81: =Q40-Q109 -> 1 | R81: =R40-R109 -> 0 | S81: =S40-S109 -> 0 | T81: =T40-T109 -> 0 | U81: =U40-U109 -> 0 | V81: =V40-V109 -> 0 | W81: =W40-W109 -> 0 | X81: =X40-X109 -> 0 | ... AF81: =AF40-AF109 -> 0 | AG81: =SUM(B81:AF81) -> 1
A82: Solar Roof Single - Blue | Q82: =Q41-Q110 -> 0 | R82: =R41-R110 -> 0 | S82: =S41-S110 -> 0 | T82: =T41-T110 -> 0 | U82: =U41-U110 -> 0 | V82: =V41-V110 -> 0 | W82: =W41-W110 -> 0 | X82: =X41-X110 -> 0 | ... AF82: =AF41-AF110 -> 0 | AG82: =SUM(B82:AF82) -> 1
A83: Solar Roof Single - Yellow | Q83: =Q42-Q111 -> 0 | R83: =R42-R111 -> 0 | S83: =S42-S111 -> 0 | T83: =T42-T111 -> 0 | U83: =U42-U111 -> 0 | V83: =V42-V111 -> 0 | W83: =W42-W111 -> 0 | X83: =X42-X111 -> 0 | ... AF83: =AF42-AF111 -> 0 | AG83: =SUM(B83:AF83) -> 3
A84: Perch Extender - Blue | Q84: =Q43-Q112 -> 3 | R84: =R43-R112 -> 3 | S84: =S43-S112 -> 2 | T84: =T43-T112 -> 2 | U84: =U43-U112 -> 0 | V84: =V43-V112 -> 1 | W84: =W43-W112 -> 0 | X84: =X43-X112 -> 0 | ... AF84: =AF43-AF112 -> 4 | AG84: =SUM(B84:AF84) -> 32
A85: Perch Extender - Yellow | Q85: =Q44-Q113 -> 1 | R85: =R44-R113 -> 0 | S85: =S44-S113 -> 0 | T85: =T44-T113 -> 0 | U85: =U44-U113 -> 0 | V85: =V44-V113 -> 0 | W85: =W44-W113 -> 0 | X85: =X44-X113 -> 0 | ... AF85: =AF44-AF113 -> 0 | AG85: =SUM(B85:AF85) -> 3
A86: Solar Roof (HBF) | AG86: =SUM(B86:AF86) -> 0
A87: Housing - only (HBF) | AG87: =SUM(B87:AF87) -> 0
A88: Nature Cam PRO | AG88: =SUM(B88:AF88) -> 0
A89: SUM (Add-ons) | B89: =SUM(B78:B88) -> 0 | C89: =SUM(C78:C88) -> 0 | D89: =SUM(D78:D88) -> 0 | E89: =SUM(E78:E88) -> 0 | F89: =SUM(F78:F88) -> 0 | G89: =SUM(G78:G88) -> 0 | H89: =SUM(H78:H88) -> 0 | I89: =SUM(I78:I88) -> 0 | ... AF89: =SUM(AF78:AF88) -> 21 | AG89: =SUM(B89:AF89) -> 118
A91: Returning Customers
A92: SKU 1 - Blue | K92: 0 | Q92: 0 | R92: 0 | S92: 0 | T92: 0 | U92: 0 | V92: 0 | W92: 0 | X92: 0 | Y92: 0 | Z92: 0 | AA92: 0 | AB92: 0 | AC92: 0 | AD92: 0 | AE92: 0 | AF92: 0 | AG92: =SUM(B92:AF92) -> 0
A93: SKU 2 - Yellow | K93: 0 | Q93: 0 | R93: 0 | S93: 0 | T93: 0 | U93: 0 | V93: 0 | W93: 0 | X93: 0 | Y93: 0 | Z93: 0 | AA93: 0 | AB93: 0 | AC93: 0 | AD93: 0 | AE93: 0 | AF93: 0 | AG93: =SUM(B93:AF93) -> 0
A94: SKU 3 - Blue w/ Solar | K94: 0 | Q94: 0 | R94: 0 | S94: 0 | T94: 0 | U94: 0 | V94: 0 | W94: 0 | X94: 0 | Y94: 0 | Z94: 0 | AA94: 0 | AB94: 0 | AC94: 0 | AD94: 0 | AE94: 0 | AF94: 0 | AG94: =SUM(B94:AF94) -> 0
A95: SKU 4 - Yellow w/ Solar | K95: 0 | Q95: 0 | R95: 0 | S95: 0 | T95: 0 | U95: 0 | V95: 0 | W95: 0 | X95: 0 | Y95: 0 | Z95: 0 | AA95: 0 | AB95: 0 | AC95: 0 | AD95: 0 | AE95: 0 | AF95: 0 | AG95: =SUM(B95:AF95) -> 0
A96: Blue PRO | Q96: 0 | R96: 0 | S96: 0 | T96: 0 | U96: 0 | V96: 0 | W96: 1 | X96: 0 | Y96: 0 | Z96: 0 | AA96: 0 | AB96: 0 | AC96: 0 | AD96: 0 | AE96: 0 | AF96: 0 | AG96: =SUM(B96:AF96) -> 1
A97: Yellow PRO | Q97: 0 | R97: 0 | S97: 0 | T97: 0 | U97: 0 | V97: 0 | W97: 0 | X97: 0 | Y97: 0 | Z97: 0 | AA97: 0 | AB97: 0 | AC97: 0 | AD97: 0 | AE97: 0 | AF97: 0 | AG97: =SUM(B97:AF97) -> 0
A98: Blue PRO w/ Solar | Q98: 0 | R98: 0 | S98: 0 | T98: 0 | U98: 0 | V98: 0 | W98: 0 | X98: 0 | Y98: 0 | Z98: 0 | AA98: 0 | AB98: 0 | AC98: 0 | AD98: 0 | AE98: 0 | AF98: 0 | AG98: =SUM(B98:AF98) -> 0
A99: Yellow PRO w/ Solar | Q99: 0 | R99: 0 | S99: 0 | T99: 0 | U99: 0 | V99: 0 | W99: 0 | X99: 0 | Y99: 0 | Z99: 0 | AA99: 0 | AB99: 0 | AC99: 0 | AD99: 0 | AE99: 0 | AF99: 0 | AG99: =SUM(B99:AF99) -> 0
A100: SUM (SKU 1 - SKU 4) | B100: =SUM(B92:B99) -> 0 | C100: =SUM(C92:C99) -> 0 | D100: =SUM(D92:D99) -> 0 | E100: =SUM(E92:E99) -> 0 | F100: =SUM(F92:F99) -> 0 | G100: =SUM(G92:G99) -> 0 | H100: =SUM(H92:H99) -> 0 | I100: =SUM(I92:I99) -> 0 | ... AF100: =SUM(AF92:AF99) -> 0 | AG100: =SUM(B100:AF100) -> 1
A102: SKU 5 - HBF | AG102: =SUM(B102:AF102) -> 0
A103: SKU 6 - HBF w/ Solar | AG103: =SUM(B103:AF103) -> 0
A104: SUM (SKU 5 - SKU 6) | B104: =SUM(B102:B103) -> 0 | C104: =SUM(C102:C103) -> 0 | D104: =SUM(D102:D103) -> 0 | E104: =SUM(E102:E103) -> 0 | F104: =SUM(F102:F103) -> 0 | G104: =SUM(G102:G103) -> 0 | H104: =SUM(H102:H103) -> 0 | I104: =SUM(I102:I103) -> 0 | ... AF104: =SUM(AF102:AF103) -> 0 | AG104: =SUM(B104:AF104) -> 0
A106: Wall Mount | Q106: 0 | R106: 0 | S106: 0 | T106: 0 | U106: 0 | V106: 0 | W106: 0 | X106: 0 | Y106: 0 | Z106: 0 | AA106: 0 | AB106: 0 | AC106: 0 | AD106: 0 | AE106: 0 | AF106: 0 | AG106: =SUM(B106:AF106) -> 0
A107: Suet Ball Holder | Q107: 0 | R107: 0 | S107: 0 | T107: 0 | U107: 0 | V107: 0 | W107: 1 | X107: 0 | Y107: 0 | Z107: 0 | AA107: 0 | AB107: 0 | AC107: 0 | AD107: 0 | AE107: 0 | AF107: 0 | AG107: =SUM(B107:AF107) -> 1
A108: 3-in-1 Nutrition Set - Blue | Q108: 0 | R108: 0 | S108: 0 | T108: 0 | U108: 0 | V108: 0 | W108: 0 | X108: 0 | Y108: 0 | Z108: 0 | AA108: 0 | AB108: 0 | AC108: 0 | AD108: 0 | AE108: 0 | AF108: 0 | AG108: =SUM(B108:AF108) -> 0
A109: 3-in-1 Nutrition Set - Yellow | Q109: 0 | R109: 0 | S109: 0 | T109: 0 | U109: 0 | V109: 0 | W109: 0 | X109: 0 | Y109: 0 | Z109: 0 | AA109: 0 | AB109: 0 | AC109: 0 | AD109: 0 | AE109: 0 | AF109: 0 | AG109: =SUM(B109:AF109) -> 0
A110: Solar Roof Single - Blue | Q110: 0 | R110: 0 | S110: 0 | T110: 0 | U110: 0 | V110: 0 | W110: 0 | X110: 0 | Y110: 0 | Z110: 0 | AA110: 0 | AB110: 0 | AC110: 0 | AD110: 0 | AE110: 0 | AF110: 0 | AG110: =SUM(B110:AF110) -> 0
A111: Solar Roof Single - Yellow | Q111: 0 | R111: 0 | S111: 0 | T111: 0 | U111: 0 | V111: 0 | W111: 0 | X111: 0 | Y111: 0 | Z111: 0 | AA111: 0 | AB111: 0 | AC111: 0 | AD111: 0 | AE111: 0 | AF111: 0 | AG111: =SUM(B111:AF111) -> 0
A112: Perch Extender - Blue | Q112: 0 | R112: 0 | S112: 0 | T112: 0 | U112: 0 | V112: 0 | W112: 0 | X112: 0 | Y112: 0 | Z112: 0 | AA112: 0 | AB112: 0 | AC112: 0 | AD112: 0 | AE112: 0 | AF112: 0 | AG112: =SUM(B112:AF112) -> 0
A113: Perch Extender - Yellow | Q113: 0 | R113: 0 | S113: 0 | T113: 0 | U113: 0 | V113: 0 | W113: 0 | X113: 0 | Y113: 0 | Z113: 0 | AA113: 0 | AB113: 0 | AC113: 0 | AD113: 0 | AE113: 0 | AF113: 0 | AG113: =SUM(B113:AF113) -> 0
A114: Solar Roof (HBF) | AG114: =SUM(B114:AF114) -> 0
...

Sheet AMAZON - P&L
A1: OCTOBER | B1: 45566 | C1: 45567 | D1: 45568 | E1: 45569 | F1: 45570 | G1: 45571 | H1: 45572 | I1: 45573 | J1: 45574 | K1: 45575 | L1: 45576 | M1: 45577 | N1: 45578 | O1: 45579 | P1: 45580 | Q1: 45581 | R1: 45582 | S1: 45583 | T1: 45584 | U1: 45585 | V1: 45586 | W1: 45587 | X1: 45588 | Y1: 45589 | Z1: 45590 | AA1: 45591 | AB1: 45592 | AC1: 45593 | AD1: 45594 | AE1: 45595 | AF1: 45596
A2: DAY | B2: TUE | C2: WED | D2: THU | E2: FRI | F2: SAT | G2: SUN | H2: MON | I2: TUE | J2: WED | K2: THU | L2: FRI | M2: SAT | N2: SUN | O2: MON | P2: TUE | Q2: WED | R2: THU | S2: FRI | T2: SAT | U2: SUN | V2: MON | W2: TUE | X2: WED | Y2: THU | Z2: FRI | AA2: SAT | AB2: SUN | AC2: MON | AD2: TUE | AE2: WED | AF2: THU
A3: COMMENT
A4: Orders
A5: Amazon (market place) | B5: =Summary!B82 -> 40 | C5: =Summary!C82 -> 29 | D5: =Summary!D82 -> 28 | E5: =Summary!E82 -> 20 | F5: =Summary!F82 -> 20 | G5: =Summary!G82 -> 25 | H5: =Summary!H82 -> 21 | I5: =Summary!I82 -> 527 | ... AF5: =Summary!AF82 -> 101
A6: All | B6: =SUM(B5) -> 40 | C6: =SUM(C5) -> 29 | D6: =SUM(D5) -> 28 | E6: =SUM(E5) -> 20 | F6: =SUM(F5) -> 20 | G6: =SUM(G5) -> 25 | H6: =SUM(H5) -> 21 | I6: =SUM(I5) -> 527 | ... AF6: =SUM(AF5) -> 101 | AG6: =SUM(B6:AF6) -> 2002
A8: Revenue
A9: Amazon (market place) | B9: =Summary!B25 -> 7953.97 | C9: =Summary!C25 -> 6765.07 | D9: =Summary!D25 -> 7698.8 | E9: =Summary!E25 -> 5011.15 | F9: =Summary!F25 -> 2828.44 | G9: =Summary!G25 -> 5401.75 | H9: =Summary!H25 -> 5446.92 | I9: =Summary!I25 -> 93468.46 | ... AF9: =Summary!AF25 -> 22434.14
A10: All | B10: =SUM(B9) -> 7953.97 | C10: =SUM(C9) -> 6765.07 | D10: =SUM(D9) -> 7698.8 | E10: =SUM(E9) -> 5011.15 | F10: =SUM(F9) -> 2828.44 | G10: =SUM(G9) -> 5401.75 | H10: =SUM(H9) -> 5446.92 | I10: =SUM(I9) -> 93468.46 | ... AF10: =SUM(AF9) -> 22434.14 | AG10: =SUM(B10:AF10) -> 445614.21
A12: Media Cost
A13: Amazon Spend | B13: =Summary!B113 -> 3291 | C13: =Summary!C113 -> 2157 | D13: =Summary!D113 -> 1863 | E13: =Summary!E113 -> 1730 | F13: =Summary!F113 -> 2039 | G13: =Summary!G113 -> 2372 | H13: =Summary!H113 -> 2533 | I13: =Summary!I113 -> 15403 | ... AF13: =Summary!AF113 -> 4081 | AG13: =SUM(B13:AF13) -> 95556
A14: Amazon Platform Fee (15 %) | B14: =B9*'Data - P&L'!$C$48 -> 1193.0955 | C14: =C9*'Data - P&L'!$C$48 -> 1014.7605 | D14: =D9*'Data - P&L'!$C$48 -> 1154.82 | E14: =E9*'Data - P&L'!$C$48 -> 751.6725 | F14: =F9*'Data - P&L'!$C$48 -> 424.266 | G14: =G9*'Data - P&L'!$C$48 -> 810.2625 | H14: =H9*'Data - P&L'!$C$48 -> 817.038 | I14: =I9*'Data - P&L'!$C$48 -> 14020.269 | ... AF14: =AF9*'Data - P&L'!$C$48 -> 3365.121 | AG14: =SUM(B14:AF14) -> 66842.132
A15: All | B15: =SUM(B13:B14) -> 4484.0955 | C15: =SUM(C13:C14) -> 3171.7605 | D15: =SUM(D13:D14) -> 3017.82 | E15: =SUM(E13:E14) -> 2481.6725 | F15: =SUM(F13:F14) -> 2463.266 | G15: =SUM(G13:G14) -> 3182.2625 | H15: =SUM(H13:H14) -> 3350.038 | I15: =SUM(I13:I14) -> 29423.269 | ... AF15: =SUM(AF13:AF14) -> 7446.121 | AG15: =SUM(B15:AF15) -> 162398.13
A19: Amazon Orders
A20: Hardware | B20: =Summary!B26 -> 7233 | C20: =Summary!C26 -> 6157 | D20: =Summary!D26 -> 6993.56 | E20: =Summary!E26 -> 4539.12 | F20: =Summary!F26 -> 2332 | G20: =Summary!G26 -> 4840.56 | H20: =Summary!H26 -> 4898.12 | I20: =Summary!I26 -> 86106.86 | ... AF20: =Summary!AF26 -> 20447.5 | AG20: =SUM(B20:AF20) -> 406430.67
A21: Addons | B21: =Summary!B27 -> 213 | C21: =Summary!C27 -> 164 | D21: =Summary!D27 -> 222 | E21: =Summary!E27 -> 154 | F21: =Summary!F27 -> 309 | G21: =Summary!G27 -> 184 | H21: =Summary!H27 -> 203 | I21: =Summary!I27 -> 1207.2 | ... AF21: =Summary!AF27 -> 522 | AG21: =SUM(B21:AF21) -> 10034.73
A22: Tax | B22: =Summary!B28 -> 503.48 | C22: =Summary!C28 -> 439.58 | D22: =Summary!D28 -> 451.32 | E22: =Summary!E28 -> 296.65 | F22: =Summary!F28 -> 175.96 | G22: =Summary!G28 -> 367.96 | H22: =Summary!H28 -> 327.34 | I22: =Summary!I28 -> 6084.31 | ... AF22: =Summary!AF28 -> 1439.98 | AG22: =SUM(B22:AF22) -> 28648.49
A23: Shipping | B23: =Summary!B29 -> 0 | C23: =Summary!C29 -> 0 | D23: =Summary!D29 -> 27.26 | E23: =Summary!E29 -> 21.04 | F23: =Summary!F29 -> 6.99 | G23: =Summary!G29 -> 0.08 | H23: =Summary!H29 -> 0.16 | I23: =Summary!I29 -> 49.97 | ... AF23: =Summary!AF29 -> 14.89 | AG23: =SUM(B23:AF23) -> 307.41
A24: Gift Wrap Price | B24: =Summary!B30 -> 4.49 | C24: =Summary!C30 -> 4.49 | D24: =Summary!D30 -> 4.66 | E24: =Summary!E30 -> 0.34 | F24: =Summary!F30 -> 4.49 | G24: =Summary!G30 -> 9.15 | H24: =Summary!H30 -> 18.3 | I24: =Summary!I30 -> 20.12 | ... AF24: =Summary!AF30 -> 9.77 | AG24: =SUM(B24:AF24) -> 192.91
A25: All Amazon | B25: =SUM(B20:B24) -> 7953.97 | C25: =SUM(C20:C24) -> 6765.07 | D25: =SUM(D20:D24) -> 7698.8 | E25: =SUM(E20:E24) -> 5011.15 | F25: =SUM(F20:F24) -> 2828.44 | G25: =SUM(G20:G24) -> 5401.75 | H25: =SUM(H20:H24) -> 5446.92 | I25: =SUM(I20:I24) -> 93468.46 | ... AF25: =SUM(AF20:AF24) -> 22434.14 | AG25: =SUM(B25:AF25) -> 445614.21
A27: Units Sold (Gross)
A28: SKU 1 - Blue | B28: 14 | C28: 12 | D28: 3 | E28: 4 | F28: 1 | G28: 4 | H28: 3 | I28: 34 | J28: 33 | K28: 10 | L28: 8 | M28: 6 | N28: 5 | O28: 8 | P28: 8 | Q28: 11 | R28: 11 | S28: 7 | T28: 4 | U28: 7 | V28: 6 | W28: 7 | X28: 10 | Y28: 8 | Z28: 7 | AA28: 30 | AB28: 24 | AC28: 19 | AD28: 11 | AE28: 10 | AF28: 11 | AG28: =SUM(B28:AF28) -> 336
A29: SKU 2 - Yellow | B29: 0 | C29: 0 | D29: 0 | E29: 0 | F29: 0 | G29: 0 | H29: 0 | I29: 0 | J29: 0 | K29: 0 | L29: 0 | M29: 0 | N29: 0 | O29: 0 | P29: 0 | Q29: 0 | R29: 0 | S29: 0 | T29: 0 | U29: 0 | V29: 0 | W29: 0 | X29: 0 | Y29: 0 | Z29: 0 | AA29: 0 | AB29: 0 | AC29: 0 | AD29: 0 | AE29: 0 | AF29: 0 | AG29: =SUM(B29:AF29) -> 0
A30: SKU 3 - Blue w/ Solar | B30: 13 | C30: 11 | D30: 21 | E30: 12 | F30: 7 | G30: 13 | H30: 14 | I30: 378 | J30: 324 | K30: 100 | L30: 13 | M30: 13 | N30: 12 | O30: 14 | P30: 14 | Q30: 37 | R30: 18 | S30: 19 | T30: 16 | U30: 16 | V30: 14 | W30: 19 | X30: 11 | Y30: 29 | Z30: 28 | AA30: 74 | AB30: 40 | AC30: 34 | AD30: 21 | AE30: 32 | AF30: 64 | AG30: =SUM(B30:AF30) -> 1431
A31: SKU 4 - Yellow w/ Solar | B31: 0 | C31: 0 | D31: 0 | E31: 0 | F31: 0 | G31: 0 | H31: 0 | I31: 0 | J31: 0 | K31: 0 | L31: 0 | M31: 0 | N31: 0 | O31: 0 | P31: 0 | Q31: 0 | R31: 0 | S31: 0 | T31: 0 | U31: 0 | V31: 0 | W31: 0 | X31: 0 | Y31: 0 | Z31: 0 | AA31: 0 | AB31: 0 | AC31: 0 | AD31: 0 | AE31: 0 | AF31: 0 | AG31: =SUM(B31:AF31) -> 0
A32: SKU 1 - Blue PRO | AB32: 0 | AC32: 0 | AD32: 0 | AE32: 0 | AF32: 0 | AG32: =SUM(B32:AF32) -> 0
A33: SKU 2 - Yellow PRO | AB33: 0 | AC33: 0 | AD33: 0 | AE33: 0 | AF33: 0 | AG33: =SUM(B33:AF33) -> 0
A34: SKU 3 - Blue w/ Solar PRO | AB34: 6 | AC34: 3 | AD34: 3 | AE34: 3 | AF34: 15 | AG34: =SUM(B34:AF34) -> 30
A35: SKU 4 - Yellow w/ Solar PRO | AB35: 0 | AC35: 0 | AD35: 0 | AE35: 0 | AF35: 0 | AG35: =SUM(B35:AF35) -> 0
A36: SUM (SKU 1 - SKU 4) | B36: =SUM(B28:B35) -> 27 | C36: =SUM(C28:C35) -> 23 | D36: =SUM(D28:D35) -> 24 | E36: =SUM(E28:E35) -> 16 | F36: =SUM(F28:F35) -> 8 | G36: =SUM(G28:G35) -> 17 | H36: =SUM(H28:H35) -> 17 | I36: =SUM(I28:I35) -> 412 | ... AF36: =SUM(AF28:AF35) -> 90 | AG36: =SUM(B36:AF36) -> 1797
A38: SKU 5 - HBF | AF38: 2 | AG38: =SUM(B38:AF38) -> 2
A39: SKU 6 - HBF w/ Solar | AF39: 0 | AG39: =SUM(B39:AF39) -> 0
A40: SUM (SKU 5 - SKU 6) | B40: =SUM(B38:B39) -> 0 | C40: =SUM(C38:C39) -> 0 | D40: =SUM(D38:D39) -> 0 | E40: =SUM(E38:E39) -> 0 | F40: =SUM(F38:F39) -> 0 | G40: =SUM(G38:G39) -> 0 | H40: =SUM(H38:H39) -> 0 | I40: =SUM(I38:I39) -> 0 | ... AF40: =SUM(AF38:AF39) -> 2 | AG40: =SUM(B40:AF40) -> 2
A42: Wall Mount | B42: 2 | C42: 3 | D42: 3 | E42: 2 | F42: 4 | G42: 5 | H42: 2 | I42: 15 | J42: 14 | K42: 5 | L42: 3 | M42: 4 | N42: 7 | O42: 5 | P42: 1 | Q42: 2 | R42: 4 | S42: 6 | T42: 3 | U42: 4 | V42: 1 | W42: 5 | X42: 4 | Y42: 5 | Z42: 5 | AA42: 13 | AB42: 4 | AC42: 6 | AD42: 4 | AE42: 8 | AF42: 4 | AG42: =SUM(B42:AF42) -> 153
A43: Suet Ball Holder | B43: 2 | C43: 2 | D43: 3 | E43: 3 | F43: 4 | G43: 0 | H43: 2 | I43: 8 | J43: 11 | K43: 5 | L43: 1 | M43: 1 | N43: 4 | O43: 1 | P43: 4 | Q43: 3 | R43: 1 | S43: 1 | T43: 3 | U43: 2 | V43: 2 | W43: 3 | X43: 2 | Y43: 1 | Z43: 1 | AA43: 6 | AB43: 0 | AC43: 3 | AD43: 3 | AE43: 2 | AF43: 4 | AG43: =SUM(B43:AF43) -> 88
A44: 3-in-1 Nutrition Set - Blue | B44: 3 | C44: 1 | D44: 2 | E44: 1 | F44: 3 | G44: 1 | H44: 2 | I44: 20 | J44: 18 | K44: 8 | L44: 1 | M44: 3 | N44: 2 | O44: 2 | P44: 1 | Q44: 1 | R44: 1 | S44: 0 | T44: 4 | U44: 3 | V44: 2 | W44: 0 | X44: 1 | Y44: 2 | Z44: 2 | AA44: 4 | AB44: 3 | AC44: 2 | AD44: 1 | AE44: 0 | AF44: 4 | AG44: =SUM(B44:AF44) -> 98
A45: 3-in-1 Nutrition Set - Yellow | B45: 0 | C45: 0 | D45: 0 | E45: 0 | F45: 0 | G45: 0 | H45: 0 | I45: 0 | J45: 0 | K45: 0 | L45: 0 | M45: 0 | N45: 0 | O45: 0 | P45: 0 | Q45: 0 | R45: 0 | S45: 0 | T45: 0 | U45: 0 | V45: 0 | W45: 0 | X45: 0 | Y45: 0 | Z45: 0 | AA45: 0 | AB45: 0 | AC45: 0 | AD45: 0 | AE45: 0 | AF45: 0 | AG45: =SUM(B45:AF45) -> 0
A46: Solar Roof Single - Blue | B46: 0 | C46: 0 | D46: 0 | E46: 0 | F46: 0 | G46: 0 | H46: 0 | I46: 0 | J46: 0 | K46: 0 | L46: 0 | M46: 0 | N46: 0 | O46: 0 | P46: 0 | Q46: 0 | R46: 0 | S46: 0 | T46: 0 | U46: 0 | V46: 0 | W46: 0 | X46: 0 | Y46: 0 | Z46: 0 | AA46: 0 | AB46: 0 | AC46: 0 | AD46: 0 | AE46: 0 | AF46: 0 | AG46: =SUM(B46:AF46) -> 0
A47: Solar Roof Single - Yellow | B47: 0 | C47: 0 | D47: 0 | E47: 0 | F47: 0 | G47: 0 | H47: 0 | I47: 0 | J47: 0 | K47: 0 | L47: 0 | M47: 0 | N47: 0 | O47: 0 | P47: 0 | Q47: 0 | R47: 0 | S47: 0 | T47: 0 | U47: 0 | V47: 0 | W47: 0 | X47: 0 | Y47: 0 | Z47: 0 | AA47: 0 | AB47: 0 | AC47: 0 | AD47: 0 | AE47: 0 | AF47: 0 | AG47: =SUM(B47:AF47) -> 0
A48: Perch Extender - Blue | B48: 0 | C48: 0 | D48: 0 | E48: 0 | F48: 0 | G48: 0 | H48: 1 | I48: 0 | J48: 0 | K48: 1 | L48: 0 | M48: 0 | N48: 0 | O48: 0 | P48: 0 | Q48: 0 | R48: 0 | S48: 0 | T48: 0 | U48: 0 | V48: 0 | W48: 0 | X48: 0 | Y48: 0 | Z48: 0 | AA48: 0 | AB48: 0 | AC48: 0 | AD48: 4 | AE48: 5 | AF48: 6 | AG48: =SUM(B48:AF48) -> 17
A49: Perch Extender - Yellow | B49: 0 | C49: 0 | D49: 0 | E49: 0 | F49: 0 | G49: 0 | H49: 0 | I49: 0 | J49: 0 | K49: 0 | L49: 0 | M49: 0 | N49: 0 | O49: 0 | P49: 0 | Q49: 0 | R49: 0 | S49: 0 | T49: 0 | U49: 0 | V49: 0 | W49: 0 | X49: 0 | Y49: 0 | Z49: 0 | AA49: 0 | AB49: 0 | AC49: 0 | AD49: 0 | AE49: 0 | AF49: 0 | AG49: =SUM(B49:AF49) -> 0
A50: SUM (Add-ons) | B50: =SUM(B42:B49) -> 7 | C50: =SUM(C42:C49) -> 6 | D50: =SUM(D42:D49) -> 8 | E50: =SUM(E42:E49) -> 6 | F50: =SUM(F42:F49) -> 11 | G50: =SUM(G42:G49) -> 6 | H50: =SUM(H42:H49) -> 7 | I50: =SUM(I42:I49) -> 43 | ... AF50: =SUM(AF42:AF49) -> 18 | AG50: =SUM(B50:AF50) -> 356
A52: Revenue
A53: SKU 1 - Blue | B53: 3346 | C53: 2868 | D53: 717 | E53: 956 | F53: 239 | G53: 956 | H53: 714.56 | I53: 6460.76 | J53: 6229.38 | K53: 2146.6 | L53: 1696.9 | M53: 1326.45 | N53: 1087.45 | O53: 1768.6 | P53: 1730.45 | Q53: 2146.2 | R53: 2146.2 | S53: 1434.45 | T53: 810.3 | U53: 1426.83 | V53: 1149.75 | W53: 1270.2 | X53: 1985.28 | Y53: 1686.3 | Z53: 1443 | AA53: 5670 | AB53: 4528.38 | AC53: 3583.38 | AD53: 2071.38 | AE53: 1890 | AF53: 2031.75 | AG53: =SUM(B53:AF53) -> 67516.55
A54: SKU 2 - Yellow | B54: 0 | C54: 0 | D54: 0 | E54: 0 | F54: 0 | G54: 0 | H54: 0 | I54: 0 | J54: 0 | K54: 0 | L54: 0 | M54: 0 | N54: 0 | O54: 0 | P54: 0 | Q54: 0 | R54: 0 | S54: 0 | T54: 0 | U54: 0 | V54: 0 | W54: 0 | X54: 0 | Y54: 0 | Z54: 0 | AA54: 0 | AB54: 0 | AC54: 0 | AD54: 0 | AE54: 0 | AF54: 0 | AG54: =SUM(B54:AF54) -> 0
A55: SKU 3 - Blue w/ Solar | B55: 3887 | C55: 3289 | D55: 6276.56 | E55: 3583.12 | F55: 2093 | G55: 3884.56 | H55: 4183.56 | I55: 79646.1 | J55: 67827.42 | K55: 21519.94 | L55: 3884.56 | M55: 3794.86 | N55: 3495.86 | O55: 4096.3 | P55: 3918.38 | Q55: 10056.66 | R55: 4831.74 | S55: 4966.2 | T55: 4045.5 | U55: 4171.05 | V55: 3654.9 | W55: 4833.03 | X55: 2692.35 | Y55: 6638.88 | Z55: 6692 | AA55: 17663.14 | AB55: 9544.76 | AC55: 8178.38 | AD55: 5019 | AE55: 7648 | AF55: 13863.14 | AG55: =SUM(B55:AF55) -> 329878.95
A56: SKU 4 - Yellow w/ Solar | B56: 0 | C56: 0 | D56: 0 | E56: 0 | F56: 0 | G56: 0 | H56: 0 | I56: 0 | J56: 0 | K56: 0 | L56: 0 | M56: 0 | N56: 0 | O56: 0 | P56: 0 | Q56: 0 | R56: 0 | S56: 0 | T56: 0 | U56: 0 | V56: 0 | W56: 0 | X56: 0 | Y56: 0 | Z56: 0 | AA56: 0 | AB56: 0 | AC56: 0 | AD56: 0 | AE56: 0 | AF56: 0 | AG56: =SUM(B56:AF56) -> 0
A57: SKU 1 - Blue PRO | AB57: 0 | AC57: 0 | AD57: 0 | AE57: 0 | AF57: 0 | AG57: =SUM(B57:AF57) -> 0
A58: SKU 2 - Yellow PRO | AB58: 0 | AC58: 0 | AD58: 0 | AE58: 0 | AF58: 0 | AG58: =SUM(B58:AF58) -> 0
A59: SKU 3 - Blue w/ Solar PRO | AB59: 1794 | AC59: 897 | AD59: 894.56 | AE59: 897 | AF59: 4336.05 | AG59: =SUM(B59:AF59) -> 8818.61
A60: SKU 4 - Yellow w/ Solar PRO | AB60: 0 | AC60: 0 | AD60: 0 | AE60: 0 | AF60: 0 | AG60: =SUM(B60:AF60) -> 0
A61: SUM (SKU 1 - SKU 4) | B61: =SUM(B53:B60) -> 7233 | C61: =SUM(C53:C60) -> 6157 | D61: =SUM(D53:D60) -> 6993.56 | E61: =SUM(E53:E60) -> 4539.12 | F61: =SUM(F53:F60) -> 2332 | G61: =SUM(G53:G60) -> 4840.56 | H61: =SUM(H53:H60) -> 4898.12 | I61: =SUM(I53:I60) -> 86106.86 | ... AF61: =SUM(AF53:AF60) -> 20230.94 | AG61: =SUM(B61:AF61) -> 406214.11
A63: SKU 5 - HBF | AF63: 216.56 | AG63: =SUM(B63:AF63) -> 216.56
A64: SKU 6 - HBF w/ Solar | AF64: 0 | AG64: =SUM(B64:AF64) -> 0
A65: SUM (SKU 5 - SKU 6) | B65: =SUM(B63:B64) -> 0 | C65: =SUM(C63:C64) -> 0 | D65: =SUM(D63:D64) -> 0 | E65: =SUM(E63:E64) -> 0 | F65: =SUM(F63:F64) -> 0 | G65: =SUM(G63:G64) -> 0 | H65: =SUM(H63:H64) -> 0 | I65: =SUM(I63:I64) -> 0 | ... AF65: =SUM(AF63:AF64) -> 216.56 | AG65: =SUM(B65:AF65) -> 216.56
A67: Wall Mount | B67: 58 | C67: 87 | D67: 87 | E67: 58 | F67: 116 | G67: 145 | H67: 58 | I67: 423.4 | J67: 359.6 | K67: 133.4 | L67: 104.46 | M67: 116 | N67: 221.48 | O67: 145 | P67: 29 | Q67: 58 | R67: 116 | S67: 174 | T67: 87 | U67: 116 | V67: 29 | W67: 163.06 | X67: 116 | Y67: 145 | Z67: 145 | AA67: 431.33 | AB67: 116 | AC67: 174 | AD67: 116 | AE67: 232 | AF67: 116 | AG67: =SUM(B67:AF67) -> 4475.73
A68: Suet Ball Holder | B68: 38 | C68: 38 | D68: 57 | E68: 57 | F68: 76 | G68: 0 | H68: 38 | I68: 152 | J68: 174.8 | K68: 91.2 | L68: 19 | M68: 19 | N68: 76 | O68: 19 | P68: 76 | Q68: 57 | R68: 19 | S68: 19 | T68: 57 | U68: 38 | V68: 38 | W68: 57 | X68: 38 | Y68: 19 | Z68: 19 | AA68: 114 | AB68: 0 | AC68: 57 | AD68: 57 | AE68: 38 | AF68: 76 | AG68: =SUM(B68:AF68) -> 1634
A69: 3-in-1 Nutrition Set - Blue | B69: 117 | C69: 39 | D69: 78 | E69: 39 | F69: 117 | G69: 39 | H69: 78 | I69: 631.8 | J69: 561.6 | K69: 257.4 | L69: 39 | M69: 117 | N69: 78 | O69: 78 | P69: 39 | Q69: 31.2 | R69: 39 | S69: 0 | T69: 156 | U69: 117 | V69: 78 | W69: 0 | X69: 39 | Y69: 78 | Z69: 78 | AA69: 156 | AB69: 117 | AC69: 78 | AD69: 0 | AE69: 0 | AF69: 156 | AG69: =SUM(B69:AF69) -> 3432
A70: 3-in-1 Nutrition Set - Yellow | B70: 0 | C70: 0 | D70: 0 | E70: 0 | F70: 0 | G70: 0 | H70: 0 | I70: 0 | J70: 0 | K70: 0 | L70: 0 | M70: 0 | N70: 0 | O70: 0 | P70: 0 | Q70: 0 | R70: 0 | S70: 0 | T70: 0 | U70: 0 | V70: 0 | W70: 0 | X70: 0 | Y70: 0 | Z70: 0 | AA70: 0 | AB70: 0 | AC70: 0 | AD70: 0 | AE70: 0 | AF70: 0 | AG70: =SUM(B70:AF70) -> 0
A71: Solar Roof Single - Blue | B71: 0 | C71: 0 | D71: 0 | E71: 0 | F71: 0 | G71: 0 | H71: 0 | I71: 0 | J71: 0 | K71: 0 | L71: 0 | M71: 0 | N71: 0 | O71: 0 | P71: 0 | Q71: 0 | R71: 0 | S71: 0 | T71: 0 | U71: 0 | V71: 0 | W71: 0 | X71: 0 | Y71: 0 | Z71: 0 | AA71: 0 | AB71: 0 | AC71: 0 | AD71: 0 | AE71: 0 | AF71: 0 | AG71: =SUM(B71:AF71) -> 0
A72: Solar Roof Single - Yellow | B72: 0 | C72: 0 | D72: 0 | E72: 0 | F72: 0 | G72: 0 | H72: 0 | I72: 0 | J72: 0 | K72: 0 | L72: 0 | M72: 0 | N72: 0 | O72: 0 | P72: 0 | Q72: 0 | R72: 0 | S72: 0 | T72: 0 | U72: 0 | V72: 0 | W72: 0 | X72: 0 | Y72: 0 | Z72: 0 | AA72: 0 | AB72: 0 | AC72: 0 | AD72: 0 | AE72: 0 | AF72: 0 | AG72: =SUM(B72:AF72) -> 0
A73: Perch Extender - Blue | B73: 0 | C73: 0 | D73: 0 | E73: 0 | F73: 0 | G73: 0 | H73: 29 | I73: 0 | J73: 0 | K73: 29 | L73: 0 | M73: 0 | N73: 0 | O73: 0 | P73: 0 | Q73: 0 | R73: 0 | S73: 0 | T73: 0 | U73: 0 | V73: 0 | W73: 0 | X73: 0 | Y73: 0 | Z73: 0 | AA73: 0 | AB73: 0 | AC73: 0 | AD73: 116 | AE73: 145 | AF73: 174 | AG73: =SUM(B73:AF73) -> 493
A74: Perch Extender - Yellow | B74: 0 | C74: 0 | D74: 0 | E74: 0 | F74: 0 | G74: 0 | H74: 0 | I74: 0 | J74: 0 | K74: 0 | L74: 0 | M74: 0 | N74: 0 | O74: 0 | P74: 0 | Q74: 0 | R74: 0 | S74: 0 | T74: 0 | U74: 0 | V74: 0 | W74: 0 | X74: 0 | Y74: 0 | Z74: 0 | AA74: 0 | AB74: 0 | AC74: 0 | AD74: 0 | AE74: 0 | AF74: 0 | AG74: =SUM(B74:AF74) -> 0
A75: SUM (Add-ons) | B75: =SUM(B67:B74) -> 213 | C75: =SUM(C67:C74) -> 164 | D75: =SUM(D67:D74) -> 222 | E75: =SUM(E67:E74) -> 154 | F75: =SUM(F67:F74) -> 309 | G75: =SUM(G67:G74) -> 184 | H75: =SUM(H67:H74) -> 203 | I75: =SUM(I67:I74) -> 1207.2 | ... AF75: =SUM(AF67:AF74) -> 522 | AG75: =SUM(B75:AF75) -> 10034.73
A77: Units Sold by country (Gross) - Only selling in US | AG77: =SUM(B77:AF77) -> 0
A78: Bird Buddy - Blue - AMAZON.US | AG78: =SUM(B78:AF78) -> 0
A79: Bird Buddy - Yellow - AMAZON.US | AG79: =SUM(B79:AF79) -> 0
A80: Bird Buddy with Solar Roof Blue - AMAZON.US | AB80: =AB31 -> 0 | AC80: =AC31 -> 0 | AD80: =AD31 -> 0 | AG80: =SUM(B80:AF80) -> 0
A81: Bird Buddy with Solar Roof Yellow - AMAZON.US | AG81: =SUM(B81:AF81) -> 0
A82: Bird Buddy - AMAZON.EU | AG82: =SUM(B82:AF82) -> 0
A83: Bird Buddy with Solar Roof - AMAZON.EU | AG83: =SUM(B83:AF83) -> 0
A84: Bird Buddy - AMAZON (OTHER1) | AG84: =SUM(B84:AF84) -> 0
A85: Bird Buddy with Solar Roof - AMAZON (OTHER1) | AG85: =SUM(B85:AF85) -> 0
A86: All Bird Buddy | B86: =B78+B82+B84 -> 0 | C86: =SUM(C78:C85) -> 0 | D86: =SUM(D78:D85) -> 0 | E86: =SUM(E78:E85) -> 0 | F86: =SUM(F78:F85) -> 0 | G86: =SUM(G78:G85) -> 0 | H86: =SUM(H78:H85) -> 0 | I86: =SUM(I78:I85) -> 0 | J86: =SUM(J78:J85) -> 0 | ... AD86: =SUM(AD78:AD85) -> 0 | AG86: =SUM(B86:AF86) -> 0
A87: All Bird Buddy with Solar Roof | B87: =B80+B83+B85 -> 0 | C87: =C80+C83+C85 -> 0 | D87: =D80+D83+D85 -> 0 | E87: =E80+E83+E85 -> 0 | F87: =F80+F83+F85 -> 0 | G87: =G80+G83+G85 -> 0 | H87: =H80+H83+H85 -> 0 | I87: =I80+I83+I85 -> 0 | ... AD87: =AD80+AD83+AD85 -> 0 | AG87: =SUM(B87:AF87) -> 0
AG88: =SUM(B88:AF88) -> 0
A89: Wall Mount - AMAZON.US | AG89: =SUM(B89:AF89) -> 0
A90: Fence Mount - AMAZON.US | AG90: =SUM(B90:AF90) -> 0
A91: Suet Ball Holder - AMAZON.US | AG91: =SUM(B91:AF91) -> 0
A92: 3-in-1 Nutrition Set - AMAZON.US | AG92: =SUM(B92:AF92) -> 0
A93: Solar Roof Single - AMAZON.US | AG93: =SUM(B93:AF93) -> 0
A94: All AMAZON.US | B94: =SUM(B89:B93) -> 0 | C94: =SUM(C89:C93) -> 0 | D94: =SUM(D89:D93) -> 0 | E94: =SUM(E89:E93) -> 0 | F94: =SUM(F89:F93) -> 0 | G94: =SUM(G89:G93) -> 0 | H94: =SUM(H89:H93) -> 0 | I94: =SUM(I89:I93) -> 0 | ... AD94: =SUM(AD89:AD93) -> 0 | AG94: =SUM(B94:AF94) -> 0
AG95: =SUM(B95:AF95) -> 0
A96: Wall Mount - AMAZON.EU | AG96: =SUM(B96:AF96) -> 0
A97: Fence Mount - AMAZON.EU | AG97: =SUM(B97:AF97) -> 0
A98: Suet Ball Holder - AMAZON.EU | AG98: =SUM(B98:AF98) -> 0
A99: 3-in-1 Nutrition Set - AMAZON.EU | AG99: =SUM(B99:AF99) -> 0
A100: Solar Roof Single - AMAZON.EU | AG100: =SUM(B100:AF100) -> 0
A101: All AMAZON.EU | B101: =SUM(B96:B100) -> 0 | C101: =SUM(C96:C100) -> 0 | D101: =SUM(D96:D100) -> 0 | E101: =SUM(E96:E100) -> 0 | F101: =SUM(F96:F100) -> 0 | G101: =SUM(G96:G100) -> 0 | H101: =SUM(H96:H100) -> 0 | I101: =SUM(I96:I100) -> 0 | ... AD101: =SUM(AD96:AD100) -> 0 | AG101: =SUM(B101:AF101) -> 0
AG102: =SUM(B102:AF102) -> 0
A103: Wall Mount - AMAZON (OTHER1) | AG103: =SUM(B103:AF103) -> 0
A104: Fence Mount - AMAZON (OTHER1) | AG104: =SUM(B104:AF104) -> 0
A105: Suet Ball Holder - AMAZON (OTHER1) | AG105: =SUM(B105:AF105) -> 0
A106: 3-in-1 Nutrition Set - AMAZON (OTHER1) | AG106: =SUM(B106:AF106) -> 0
A107: Solar Roof Single - AMAZON (OTHER1) | AG107: =SUM(B107:AF107) -> 0
A108: All AMAZON (OTHER1) | B108: =SUM(B103:B107) -> 0 | C108: =SUM(C103:C106) -> 0 | D108: =SUM(D103:D107) -> 0 | E108: =SUM(E103:E107) -> 0 | F108: =SUM(F103:F107) -> 0 | G108: =SUM(G103:G106) -> 0 | H108: =SUM(H103:H106) -> 0 | I108: =SUM(I103:I106) -> 0 | J108: =SUM(J103:J106) -> 0 | K108: =SUM(K103:K106) -> 0 | L108: =SUM(L103:L106) -> 0 | M108: =SUM(M103:M106) -> 0 | N108: =SUM(N103:N106) -> 0 | ... V108: =SUM(V103:V106) -> 0 | W108: =SUM(W103:W107) -> 0 | X108: =SUM(X103:X106) -> 0 | Y108: =SUM(Y103:Y106) -> 0 | Z108: =SUM(Z103:Z106) -> 0 | AA108: =SUM(AA103:AA106) -> 0 | AB108: =SUM(AB103:AB106) -> 0 | AC108: =SUM(AC103:AC106) -> 0 | AD108: =SUM(AD103:AD106) -> 0 | AG108: =SUM(B108:AF108) -> 0
AG109: =SUM(B109:AF109) -> 0
A110: Revenue by country (Gross) - Only selling in US | AG110: =SUM(B110:AF110) -> 0
A111: Bird Buddy - AMAZON.US | AG111: =SUM(B111:AF111) -> 0
A112: Bird Buddy with Solar Roof - AMAZON.US | AB112: =AB9 -> 17219.03 | AC112: =AC9 -> 13761.81 | AD112: =AD9 -> 8856.36 | AG112: =SUM(B112:AF112) -> 39837.2
...

Sheet WALMART - P&L
A1: OCTOBER | B1: 45566 | C1: 45567 | D1: 45568 | E1: 45569 | F1: 45570 | G1: 45571 | H1: 45572 | I1: 45573 | J1: 45574 | K1: 45575 | L1: 45576 | M1: 45577 | N1: 45578 | O1: 45579 | P1: 45580 | Q1: 45581 | R1: 45582 | S1: 45583 | T1: 45584 | U1: 45585 | V1: 45586 | W1: 45587 | X1: 45588 | Y1: 45589 | Z1: 45590 | AA1: 45591 | AB1: 45592 | AC1: 45593 | AD1: 45594 | AE1: 45595 | AF1: 45596
A2: DAY | B2: TUE | C2: WED | D2: THU | E2: FRI | F2: SAT | G2: SUN | H2: MON | I2: TUE | J2: WED | K2: THU | L2: FRI | M2: SAT | N2: SUN | O2: MON | P2: TUE | Q2: WED | R2: THU | S2: FRI | T2: SAT | U2: SUN | V2: MON | W2: TUE | X2: WED | Y2: THU | Z2: FRI | AA2: SAT | AB2: SUN | AC2: MON | AD2: TUE | AE2: WED | AF2: THU
A3: Walmart
A4: Revenue | B4: =Summary!B31 -> 0 | C4: =Summary!C31 -> 0 | D4: =Summary!D31 -> 0 | E4: =Summary!E31 -> 0 | F4: =Summary!F31 -> 0 | G4: =Summary!G31 -> 0 | H4: =Summary!H31 -> 321.43 | I4: =Summary!I31 -> 316.94 | ... AF4: =Summary!AF31 -> 0 | AG4: =SUM(B4:AF4) -> 1439.59
A5: Breakdown | AG5: =SUM(B5:AF5) -> 0
A6: - Tax | B6: =Summary!B33 -> 0 | C6: =Summary!C33 -> 0 | D6: =Summary!D33 -> 0 | E6: =Summary!E33 -> 0 | F6: =Summary!F33 -> 0 | G6: =Summary!G33 -> 0 | H6: =Summary!H33 -> 22.43 | I6: =Summary!I33 -> 17.94 | ... AF6: =Summary!AF33 -> 0 | AG6: =SUM(B6:AF6) -> 84.59
A7: - Shipping | B7: =Summary!B34 | C7: =Summary!C34 | D7: =Summary!D34 | E7: =Summary!E34 | F7: =Summary!F34 | G7: =Summary!G34 | H7: =Summary!H34 | I7: =Summary!I34 | ... AF7: =Summary!AF34 | AG7: =SUM(B7:AF7) -> 0
A8: Orders | B8: =Summary!B85 -> 0 | C8: =Summary!C85 -> 0 | D8: =Summary!D85 -> 0 | E8: =Summary!E85 -> 0 | F8: =Summary!F85 -> 0 | G8: =Summary!G85 -> 0 | H8: =Summary!H85 -> 1 | I8: =Summary!I85 -> 1 | ... AF8: =Summary!AF85 -> 0 | AG8: =SUM(B8:AF8) -> 5
A10: Media Cost
A11: Walmart Spend | B11: =Summary!B119 -> 2.84 | C11: =Summary!C119 -> 16.64 | D11: =Summary!D119 -> 14.49 | E11: =Summary!E119 -> 13.52 | F11: =Summary!F119 -> 46.68 | G11: =Summary!G119 -> 43.87 | H11: =Summary!H119 -> 34.74 | I11: =Summary!I119 -> 30.43 | ... AF11: =Summary!AF119 -> 54.15
A12: Walmart Fees (15%) | B12: =B4*0.15 -> 0 | C12: =C4*0.15 -> 0 | D12: =D4*0.15 -> 0 | E12: =E4*0.15 -> 0 | F12: =F4*0.15 -> 0 | G12: =G4*0.15 -> 0 | H12: =H4*0.15 -> 48.2145 | I12: =I4*0.15 -> 47.541 | ... AF12: =AF4*0.15 -> 0 | AG12: =SUM(B12:AF12) -> 215.9385
A14: Units Sold (Gross) - Walmart
A15: SKU 1 - Blue | B15: 0 | C15: 0 | D15: 0 | E15: 0 | F15: 0 | G15: 0 | H15: 0 | I15: 0 | J15: 0 | K15: 0 | L15: 0 | M15: 0 | N15: 0 | O15: 0 | P15: 0 | Q15: 0 | R15: 0 | S15: 0 | T15: 0 | U15: 0 | V15: 0 | W15: 0 | X15: 0 | Y15: 0 | Z15: 0 | AA15: 0 | AB15: 0 | AC15: 0 | AD15: 0 | AE15: 0 | AF15: 0 | AG15: =SUM(B15:AF15) -> 0
A16: SKU 2 - Yellow | B16: 0 | C16: 0 | D16: 0 | E16: 0 | F16: 0 | G16: 0 | H16: 0 | I16: 0 | J16: 0 | K16: 0 | L16: 0 | M16: 0 | N16: 0 | O16: 0 | P16: 0 | Q16: 0 | R16: 0 | S16: 0 | T16: 0 | U16: 0 | V16: 0 | W16: 0 | X16: 0 | Y16: 0 | Z16: 0 | AA16: 0 | AB16: 0 | AC16: 0 | AD16: 0 | AE16: 0 | AF16: 0 | AG16: =SUM(B16:AF16) -> 0
A17: SKU 3 - Blue w/ Solar | B17: 0 | C17: 0 | D17: 0 | E17: 0 | F17: 0 | G17: 0 | H17: 1 | I17: 1 | J17: 0 | K17: 0 | L17: 0 | M17: 0 | N17: 0 | O17: 0 | P17: 0 | Q17: 0 | R17: 0 | S17: 0 | T17: 0 | U17: 1 | V17: 0 | W17: 0 | X17: 0 | Y17: 0 | Z17: 0 | AA17: 1 | AB17: 0 | AC17: 0 | AD17: 1 | AE17: 0 | AF17: 0 | AG17: =SUM(B17:AF17) -> 5
A18: SKU 4 - Yellow w/ Solar | B18: 0 | C18: 0 | D18: 0 | E18: 0 | F18: 0 | G18: 0 | H18: 0 | I18: 0 | J18: 0 | K18: 0 | L18: 0 | M18: 0 | N18: 0 | O18: 0 | P18: 0 | Q18: 0 | R18: 0 | S18: 0 | T18: 0 | U18: 0 | V18: 0 | W18: 0 | X18: 0 | Y18: 0 | Z18: 0 | AA18: 0 | AB18: 0 | AC18: 0 | AD18: 0 | AE18: 0 | AF18: 0 | AG18: =SUM(B18:AF18) -> 0
A19: SUM (SKU 1 - SKU 4) | B19: =SUM(B15:B18) -> 0 | C19: =SUM(C15:C18) -> 0 | D19: =SUM(D15:D18) -> 0 | E19: =SUM(E15:E18) -> 0 | F19: =SUM(F15:F18) -> 0 | G19: =SUM(G15:G18) -> 0 | H19: =SUM(H15:H18) -> 1 | I19: =SUM(I15:I18) -> 1 | ... AF19: =SUM(AF15:AF18) -> 0 | AG19: =SUM(B19:AF19) -> 5
A21: Wall Mount | AG21: =SUM(B21:AF21) -> 0
A22: Suet Ball Holder | AG22: =SUM(B22:AF22) -> 0
A23: 3-in-1 Nutrition Set - Blue | AG23: =SUM(B23:AF23) -> 0
A24: 3-in-1 Nutrition Set - Yellow | AG24: =SUM(B24:AF24) -> 0
A25: Solar Roof Single - Blue | AG25: =SUM(B25:AF25) -> 0
A26: Solar Roof Single - Yellow | AG26: =SUM(B26:AF26) -> 0
A27: Perch Extender - Blue | AG27: =SUM(B27:AF27) -> 0
A28: Perch Extender - Yellow | AG28: =SUM(B28:AF28) -> 0
A29: SUM (Add-ons) | B29: =SUM(B21:B28) -> 0 | C29: =SUM(C21:C28) -> 0 | D29: =SUM(D21:D28) -> 0 | E29: =SUM(E21:E28) -> 0 | F29: =SUM(F21:F28) -> 0 | G29: =SUM(G21:G28) -> 0 | H29: =SUM(H21:H28) -> 0 | I29: =SUM(I21:I28) -> 0 | ... AF29: =SUM(AF21:AF28) -> 0 | AG29: =SUM(B29:AF29) -> 0
A31: Units and Revenue Cancelled & Refunds - Walmart
A33: Units Cancelled (Gross) - Walmart
A34: SKU 1 - Blue | AG34: =SUM(B34:AF34) -> 0
A35: SKU 2 - Yellow | AG35: =SUM(B35:AF35) -> 0
A36: SKU 3 - Blue w/ Solar | AG36: =SUM(B36:AF36) -> 0
A37: SKU 4 - Yellow w/ Solar | AG37: =SUM(B37:AF37) -> 0
A38: SUM (SKU 1 + SKU 2) | B38: =SUM(B34:B35) -> 0 | C38: =SUM(C34:C35) -> 0 | D38: =SUM(D34:D35) -> 0 | E38: =SUM(E34:E35) -> 0 | F38: =SUM(F34:F35) -> 0 | G38: =SUM(G34:G35) -> 0 | H38: =SUM(H34:H35) -> 0 | I38: =SUM(I34:I35) -> 0 | ... AF38: =SUM(AF34:AF35) -> 0 | AG38: =SUM(B38:AF38) -> 0
A39: SUM (SKU 3 + SKU 4) | B39: =SUM(B36:B37) -> 0 | C39: =SUM(C36:C37) -> 0 | D39: =SUM(D36:D37) -> 0 | E39: =SUM(E36:E37) -> 0 | F39: =SUM(F36:F37) -> 0 | G39: =SUM(G36:G37) -> 0 | H39: =SUM(H36:H37) -> 0 | I39: =SUM(I36:I37) -> 0 | ... AF39: =SUM(AF36:AF37) -> 0 | AG39: =SUM(B39:AF39) -> 0
A41: Wall Mount | AG41: =SUM(B41:AF41) -> 0
A42: Suet Ball Holder | AG42: =SUM(B42:AF42) -> 0
A43: 3-in-1 Nutrition Set - Blue | AG43: =SUM(B43:AF43) -> 0
A44: 3-in-1 Nutrition Set - Yellow | AG44: =SUM(B44:AF44) -> 0
A45: Solar Roof Single - Blue | AG45: =SUM(B45:AF45) -> 0
A46: Solar Roof Single - Yellow | AG46: =SUM(B46:AF46) -> 0
A47: Perch Extender - Blue | AG47: =SUM(B47:AF47) -> 0
A48: Perch Extender - Yellow | AG48: =SUM(B48:AF48) -> 0
A49: SUM (Add-ons) | B49: =SUM(B41:B48) -> 0 | C49: =SUM(C41:C48) -> 0 | D49: =SUM(D41:D48) -> 0 | E49: =SUM(E41:E48) -> 0 | F49: =SUM(F41:F48) -> 0 | G49: =SUM(G41:G48) -> 0 | H49: =SUM(H41:H48) -> 0 | I49: =SUM(I41:I48) -> 0 | ... AF49: =SUM(AF41:AF48) -> 0 | AG49: =SUM(B49:AF49) -> 0
A51: Revenue Cancelled (Gross) - Walmart
A52: Hardware | AG52: =SUM(B52:AF52) -> 0
A53: Shipping | AG53: =SUM(B53:AF53) -> 0
A54: Taxes | AG54: =SUM(B54:AF54) -> 0
A55: All NA | B55: =SUM(B52:B54) -> 0 | C55: =SUM(C52:C54) -> 0 | D55: =SUM(D52:D54) -> 0 | E55: =SUM(E52:E54) -> 0 | F55: =SUM(F52:F54) -> 0 | G55: =SUM(G52:G54) -> 0 | H55: =SUM(H52:H54) -> 0 | I55: =SUM(I52:I54) -> 0 | ... AF55: =SUM(AF52:AF54) -> 0 | AG55: =SUM(B55:AF55) -> 0
A57: Hardware - Europe | AG57: =SUM(B57:AF57) -> 0
A58: Shipping - Europe | AG58: =SUM(B58:AF58) -> 0
A59: All EU | B59: =sum(B57:B58) -> 0 | C59: =sum(C57:C58) -> 0 | D59: =sum(D57:D58) -> 0 | E59: =sum(E57:E58) -> 0 | F59: =sum(F57:F58) -> 0 | G59: =sum(G57:G58) -> 0 | H59: =sum(H57:H58) -> 0 | I59: =sum(I57:I58) -> 0 | ... AF59: =sum(AF57:AF58) -> 0 | AG59: =SUM(B59:AF59) -> 0
A61: Units Refund (Gross) - Walmart
A62: SKU 1 - Blue | AG62: =SUM(B62:AF62) -> 0
A63: SKU 2 - Yellow | AG63: =SUM(B63:AF63) -> 0
A64: SKU 3 - Blue w/ Solar | AG64: =SUM(B64:AF64) -> 0
A65: SKU 4 - Yellow w/ Solar | AG65: =SUM(B65:AF65) -> 0
A66: SUM (SKU 1 + SKU 2) | B66: =SUM(B62:B63) -> 0 | C66: =SUM(C62:C63) -> 0 | D66: =SUM(D62:D63) -> 0 | E66: =SUM(E62:E63) -> 0 | F66: =SUM(F62:F63) -> 0 | G66: =SUM(G62:G63) -> 0 | H66: =SUM(H62:H63) -> 0 | I66: =SUM(I62:I63) -> 0 | ... AF66: =SUM(AF62:AF63) -> 0 | AG66: =SUM(B66:AF66) -> 0
A67: SUM (SKU 3 + SKU 4) | B67: =SUM(B64:B65) -> 0 | C67: =SUM(C64:C65) -> 0 | D67: =SUM(D64:D65) -> 0 | E67: =SUM(E64:E65) -> 0 | F67: =SUM(F64:F65) -> 0 | G67: =SUM(G64:G65) -> 0 | H67: =SUM(H64:H65) -> 0 | I67: =SUM(I64:I65) -> 0 | ... AF67: =SUM(AF64:AF65) -> 0 | AG67: =SUM(B67:AF67) -> 0
A69: Wall Mount | AG69: =SUM(B69:AF69) -> 0
A70: Suet Ball Holder | AG70: =SUM(B70:AF70) -> 0
A71: 3-in-1 Nutrition Set - Blue | AG71: =SUM(B71:AF71) -> 0
A72: 3-in-1 Nutrition Set - Yellow | AG72: =SUM(B72:AF72) -> 0
A73: Solar Roof Single - Blue | AG73: =SUM(B73:AF73) -> 0
A74: Solar Roof Single - Yellow | AG74: =SUM(B74:AF74) -> 0
A75: Perch Extender - Blue | AG75: =SUM(B75:AF75) -> 0
A76: Perch Extender - Yellow | AG76: =SUM(B76:AF76) -> 0
A77: SUM (Add-ons) | B77: =SUM(B69:B76) -> 0 | C77: =SUM(C69:C76) -> 0 | D77: =SUM(D69:D76) -> 0 | E77: =SUM(E69:E76) -> 0 | F77: =SUM(F69:F76) -> 0 | G77: =SUM(G69:G76) -> 0 | H77: =SUM(H69:H76) -> 0 | I77: =SUM(I69:I76) -> 0 | ... AF77: =SUM(AF69:AF76) -> 0 | AG77: =SUM(B77:AF77) -> 0
A79: Orders Return for Refund | AG79: =SUM(B79:AF79) -> 0
A81: Revenue Refunded (Gross) - Walmart
A82: Hardware | AG82: =SUM(B82:AF82) -> 0
A83: Shipping | AG83: =SUM(B83:AF83) -> 0
A84: Taxes | AG84: =SUM(B84:AF84) -> 0
A85: All NA | B85: =sum(B82:B84) -> 0 | C85: =sum(C82:C84) -> 0 | D85: =sum(D82:D84) -> 0 | E85: =sum(E82:E84) -> 0 | F85: =sum(F82:F84) -> 0 | G85: =sum(G82:G84) -> 0 | H85: =sum(H82:H84) -> 0 | I85: =sum(I82:I84) -> 0 | ... AF85: =sum(AF82:AF84) -> 0 | AG85: =SUM(B85:AF85) -> 0
A87: Hardware - Europe | AG87: =SUM(B87:AF87) -> 0
A88: Shipping - Europe | AG88: =SUM(B88:AF88) -> 0
A89: All EU | B89: =sum(B87:B88) -> 0 | C89: =sum(C87:C88) -> 0 | D89: =sum(D87:D88) -> 0 | E89: =sum(E87:E88) -> 0 | F89: =sum(F87:F88) -> 0 | G89: =sum(G87:G88) -> 0 | H89: =sum(H87:H88) -> 0 | I89: =sum(I87:I88) -> 0 | ... AF89: =sum(AF87:AF88) -> 0 | AG89: =SUM(B89:AF89) -> 0
A91: RETURN (Replacement Units & Claims) - Walmart
A92: SKU 1 - Blue | AG92: =SUM(B92:AF92) -> 0
A93: SKU 2 - Yellow | AG93: =SUM(B93:AF93) -> 0
A94: SKU 3 - Blue w/ Solar | AG94: =SUM(B94:AF94) -> 0
A95: SKU 4 - Yellow w/ Solar | AG95: =SUM(B95:AF95) -> 0
A96: SUM (SKU 1 + SKU 2) | B96: =B92+B93 -> 0 | C96: =C92+C93 -> 0 | D96: =D92+D93 -> 0 | E96: =E92+E93 -> 0 | F96: =F92+F93 -> 0 | G96: =G92+G93 -> 0 | H96: =H92+H93 -> 0 | I96: =I92+I93 -> 0 | ... AF96: =AF92+AF93 -> 0 | AG96: =SUM(B96:AF96) -> 0
A97: SUM (SKU 3 + SKU 4) | B97: =B94+B95 -> 0 | C97: =C94+C95 -> 0 | D97: =D94+D95 -> 0 | E97: =E94+E95 -> 0 | F97: =F94+F95 -> 0 | G97: =G94+G95 -> 0 | H97: =H94+H95 -> 0 | I97: =I94+I95 -> 0 | ... AF97: =AF94+AF95 -> 0 | AG97: =SUM(B97:AF97) -> 0
AG98: =SUM(B98:AF98) -> 0
A99: Wall Mount | AG99: =SUM(B99:AF99) -> 0
A100: Suet Ball Holder | AG100: =SUM(B100:AF100) -> 0
A101: 3-in-1 Nutrition Set - Blue | AG101: =SUM(B101:AF101) -> 0
A102: 3-in-1 Nutrition Set - Yellow | AG102: =SUM(B102:AF102) -> 0
A103: Solar Roof Single - Blue | AG103: =SUM(B103:AF103) -> 0
A104: Solar Roof Single - Yellow | AG104: =SUM(B104:AF104) -> 0
A105: Perch Extender - Blue | AG105: =SUM(B105:AF105) -> 0
A106: Perch Extender - Yellow | AG106: =SUM(B106:AF106) -> 0
A107: SUM (Add-ons) | B107: =SUM(B99:B103) -> 0 | C107: =SUM(C99:C103) -> 0 | D107: =SUM(D99:D103) -> 0 | E107: =SUM(E99:E103) -> 0 | F107: =SUM(F99:F103) -> 0 | G107: =SUM(G99:G103) -> 0 | H107: =SUM(H99:H103) -> 0 | I107: =SUM(I99:I103) -> 0 | ... AF107: =SUM(AF99:AF103) -> 0 | AG107: =SUM(B107:AF107) -> 0
A109: Parts
A110: Housing - Blue | AG110: =SUM(B110:AF110) -> 0
A111: Housing - Yellow | AG111: =SUM(B111:AF111) -> 0
A112: Camera Module | AG112: =SUM(B112:AF112) -> 0
A114: Orders Replaced NA | B114: 0 | C114: 0 | D114: 0 | E114: 0 | F114: 0 | G114: 0 | H114: 0 | I114: 0 | J114: 0 | K114: 0 | L114: 0 | M114: 0 | N114: 0 | O114: 0 | P114: 0 | Q114: 0 | R114: 0 | S114: 0 | T114: 0 | U114: 0 | AG114: =SUM(B114:AF114) -> 0
A119: Gross Cost
A120: Media Spend | B120: 0 | C120: 0 | D120: 0 | E120: 0 | F120: 0 | G120: 0 | H120: 0 | I120: 0 | J120: 0 | K120: 0 | L120: 0 | M120: 0 | N120: 0 | O120: 0 | P120: 0 | Q120: 0 | R120: 0 | S120: 0 | T120: 0 | U120: 0 | V120: 0 | W120: 0 | X120: 0 | Y120: 0 | Z120: 0 | AA120: 0 | AB120: 0 | AC120: 0 | AD120: 0 | AE120: 0 | AF120: 0 | AG120: =SUM(B120:AF120) -> 0
...

Sheet App - P&L
A1: OCTOBER | B1: 45566 | C1: 45567 | D1: 45568 | E1: 45569 | F1: 45570 | G1: 45571 | H1: 45572 | I1: 45573 | J1: 45574 | K1: 45575 | L1: 45576 | M1: 45577 | N1: 45578 | O1: 45579 | P1: 45580 | Q1: 45581 | R1: 45582 | S1: 45583 | T1: 45584 | U1: 45585 | V1: 45586 | W1: 45587 | X1: 45588 | Y1: 45589 | Z1: 45590 | AA1: 45591 | AB1: 45592 | AC1: 45593 | AD1: 45594 | AE1: 45595 | AF1: 45596
A2: DAY | B2: TUE | C2: WED | D2: THU | E2: FRI | F2: SAT | G2: SUN | H2: MON | I2: TUE | J2: WED | K2: THU | L2: FRI | M2: SAT | N2: SUN | O2: MON | P2: TUE | Q2: WED | R2: THU | S2: FRI | T2: SAT | U2: SUN | V2: MON | W2: TUE | X2: WED | Y2: THU | Z2: FRI | AA2: SAT | AB2: SUN | AC2: MON | AD2: TUE | AE2: WED | AF2: THU
A4: Gross Revenue
A5: Apple Store Sales | B5: =SUM(B6:B7) -> 9313.7891 | C5: =SUM(C6:C7) -> 7612.1873 | D5: =SUM(D6:D7) -> 1048.2562 | E5: =SUM(E6:E7) -> 1325.4707 | F5: =SUM(F6:F7) -> 1247.4015 | G5: =SUM(G6:G7) -> 1551.6533 | H5: =SUM(H6:H7) -> 1216.037 | I5: =SUM(I6:I7) -> 1263.7025 | ... AF5: =SUM(AF6:AF7) -> 2526.0702 | AG5: =SUM(B5:AF5) -> 65253.865
A6: - Yearly Subscription | B6: 8786.5566 | C6: 7156.1175 | D6: 455.25651 | E6: 779.82 | F6: 903.31881 | G6: 1201.9597 | H6: 804.47716 | I6: 888.20383 | J6: 762.30413 | K6: 1056.3619 | L6: 989.71 | M6: 1373.6755 | N6: 1613.1443 | O6: 1572.359 | P6: 1333.6345 | Q6: 1489.4391 | R6: 749.81 | S6: 1060.1398 | T6: 846.90881 | U6: 1262.7456 | V6: 1524.0452 | W6: 1380.8666 | X6: 1123.9552 | Y6: 689.29424 | Z6: 1155.0152 | AA6: 1434.3962 | AB6: 1400.3206 | AC6: 798.65471 | AD6: 1200.0023 | AE6: 2952.7287 | AF6: 2145.0547 | AG6: =SUM(B6:AF6) -> 50890.276
A7: - Monthly Subscription | B7: 527.23249 | C7: 456.06984 | D7: 592.99973 | E7: 545.65073 | F7: 344.08273 | G7: 349.6936 | H7: 411.55981 | I7: 375.49867 | J7: 393.26088 | K7: 444.21913 | L7: 532.51697 | M7: 478.88628 | N7: 487.56335 | O7: 463.37544 | P7: 433.28533 | Q7: 405.9559 | R7: 357.54471 | S7: 317.21366 | T7: 402.06373 | U7: 321.42766 | V7: 486.55081 | W7: 351.51008 | X7: 424.04411 | Y7: 469.18507 | Z7: 770.93571 | AA7: 748.32577 | AB7: 591.67257 | AC7: 580.02592 | AD7: 528.17946 | AE7: 392.04322 | AF7: 381.01554 | AG7: =SUM(B7:AF7) -> 14363.589
A8: Google Store Sales | B8: =SUM(B9:B10) -> 3096.8 | C8: =SUM(C9:C10) -> 3447.45 | D8: =SUM(D9:D10) -> 421.66 | E8: =SUM(E9:E10) -> 264.13 | F8: =SUM(F9:F10) -> 231.88 | G8: =SUM(G9:G10) -> 263.84 | H8: =SUM(H9:H10) -> 408.78 | I8: =SUM(I9:I10) -> 220.47 | ... AF8: =SUM(AF9:AF10) -> 637.92 | AG8: =SUM(B8:AF8) -> 18607.62
A9: - Yearly Subscription | B9: =2968.63+ 65.62 -> 3034.25 | C9: 3338.19 | D9: =314.74+ 33.9 -> 348.64 | E9: 163.5 | F9: =92.9+62.62 -> 155.52 | G9: =154.51+62.02 -> 216.53 | H9: =260.91+62.1 -> 323.01 | I9: 120.48 | J9: =32.61+62.48 -> 95.09 | K9: =352.06 + 65.59 -> 417.65 | L9: =30+469.66 -> 499.66 | M9: =408.36+32.66 -> 441.02 | N9: =255.94+122.1 -> 378.04 | O9: =140.05 +62.77 -> 202.82 | P9: 254.96 | Q9: =195.24 +95.79 -> 291.03 | R9: =285.3+33.09 -> 318.39 | S9: 225.08 | T9: 321.6 | U9: 121.77 | V9: =192.08+128.19 -> 320.27 | W9: =416.65+96.17 -> 512.82 | X9: =161.37+32.32 -> 193.69 | Y9: =220.93+ 31.99 -> 252.92 | Z9: 286.44 | AA9: 222.12 | AB9: 189.68 | AC9: =312.01 +59.15 -> 371.16 | AD9: =359.47 +32.51+90.85 -> 482.83 | AE9: =812.68 +31.8 -> 844.48 | AF9: 618.97 | AG9: =SUM(B9:AF9) -> 15562.61
A10: - Monthly Subscription | B10: 62.55 | C10: 109.26 | D10: 73.02 | E10: 100.63 | F10: 76.36 | G10: 47.31 | H10: 85.77 | I10: 99.99 | J10: 142.5 | K10: 92.13 | L10: 92.82 | M10: 83.56 | N10: 124.53 | O10: 103.77 | P10: 67.79 | Q10: 98.6 | R10: 57.32 | S10: 66.86 | T10: 119.78 | U10: 92.52 | V10: 122.26 | W10: 63.14 | X10: 107.55 | Y10: 103.92 | Z10: 121.78 | AA10: 110.29 | AB10: 69.02 | AC10: 207.96 | AD10: 241.06 | AE10: 82.01 | AF10: 18.95 | AG10: =SUM(B10:AF10) -> 3045.01
A11: SUM | B11: =sum(B5+B8) -> 12410.589 | C11: =sum(C5+C8) -> 11059.637 | D11: =sum(D5+D8) -> 1469.9162 | E11: =sum(E5+E8) -> 1589.6007 | F11: =sum(F5+F8) -> 1479.2815 | G11: =sum(G5+G8) -> 1815.4933 | H11: =sum(H5+H8) -> 1624.817 | I11: =sum(I5+I8) -> 1484.1725 | ... AF11: =sum(AF5+AF8) -> 3163.9902 | AG11: =SUM(B11:AF11) -> 83861.485
A13: Gross Orders
A14: Apple Store Orders | B14: =sum(B15:B16) -> 380 | C14: =sum(C15:C16) -> 307 | D14: =sum(D15:D16) -> 121 | E14: =sum(E15:E16) -> 115 | F14: =sum(F15:F16) -> 90 | G14: =sum(G15:G16) -> 94 | H14: =sum(H15:H16) -> 94 | I14: =sum(I15:I16) -> 95 | ... AF14: =sum(AF15:AF16) -> 118 | AG14: =SUM(B14:AF14) -> 4061
A15: - Yearly Subscription | B15: 286 | C15: 226 | D15: 13 | E15: 18 | F15: 26 | G15: 30 | H15: 18 | I15: 25 | J15: 21 | K15: 28 | L15: 29 | M15: 37 | N15: 41 | O15: 42 | P15: 47 | Q15: 49 | R15: 19 | S15: 32 | T15: 23 | U15: 33 | V15: 44 | W15: 37 | X15: 32 | Y15: 22 | Z15: 33 | AA15: 40 | AB15: 40 | AC15: 25 | AD15: 36 | AE15: 74 | AF15: 53 | AG15: =SUM(B15:AF15) -> 1479
A16: - Monthly Subscription | B16: 94 | C16: 81 | D16: 108 | E16: 97 | F16: 64 | G16: 64 | H16: 76 | I16: 70 | J16: 75 | K16: 82 | L16: 93 | M16: 86 | N16: 86 | O16: 81 | P16: 75 | Q16: 75 | R16: 68 | S16: 59 | T16: 73 | U16: 57 | V16: 86 | W16: 63 | X16: 75 | Y16: 83 | Z16: 137 | AA16: 136 | AB16: 103 | AC16: 105 | AD16: 94 | AE16: 71 | AF16: 65 | AG16: =SUM(B16:AF16) -> 2582
A17: Google Store Orders | B17: =sum(B18:B19) -> 103 | C17: =sum(C18:C19) -> 120 | D17: =sum(D18:D19) -> 21 | E17: =sum(E18:E19) -> 21 | F17: =sum(F18:F19) -> 18 | G17: =sum(G18:G19) -> 13 | H17: =sum(H18:H19) -> 22 | I17: =sum(I18:I19) -> 21 | ... AF17: =sum(AF18:AF19) -> 18 | AG17: =SUM(B17:AF17) -> 956
A18: - Yearly Subscription | B18: 93 | C18: 102 | D18: 7 | E18: 3 | F18: 4 | G18: 5 | H18: 7 | I18: 2 | J18: 3 | K18: 11 | L18: 11 | M18: 9 | N18: 10 | O18: 6 | P18: 8 | Q18: 7 | R18: 9 | S18: 6 | T18: 9 | U18: 4 | V18: 10 | W18: 14 | X18: 5 | Y18: 7 | Z18: 8 | AA18: 5 | AB18: 5 | AC18: 10 | AD18: 13 | AE18: 20 | AF18: 15 | AG18: =SUM(B18:AF18) -> 428
A19: - Monthly Subscription | B19: 10 | C19: 18 | D19: 14 | E19: 18 | F19: 14 | G19: 8 | H19: 15 | I19: 19 | J19: 24 | K19: 16 | L19: 15 | M19: 14 | N19: 21 | O19: 18 | P19: 14 | Q19: 16 | R19: 9 | S19: 13 | T19: 21 | U19: 17 | V19: 22 | W19: 11 | X19: 18 | Y19: 17 | Z19: 20 | AA19: 19 | AB19: 12 | AC19: 36 | AD19: 43 | AE19: 13 | AF19: 3 | AG19: =SUM(B19:AF19) -> 528
A20: SUM | B20: =sum(B14+B17) -> 483 | C20: =sum(C14+C17) -> 427 | D20: =sum(D14+D17) -> 142 | E20: =sum(E14+E17) -> 136 | F20: =sum(F14+F17) -> 108 | G20: =sum(G14+G17) -> 107 | H20: =sum(H14+H17) -> 116 | I20: =sum(I14+I17) -> 116 | ... AF20: =sum(AF14+AF17) -> 136 | AG20: =SUM(B20:AF20) -> 5017
A21: - Yearly Subscription | B21: =B15+B18 -> 379 | C21: =C15+C18 -> 328 | D21: =D15+D18 -> 20 | E21: =E15+E18 -> 21 | F21: =F15+F18 -> 30 | G21: =G15+G18 -> 35 | H21: =H15+H18 -> 25 | I21: =I15+I18 -> 27 | ... AD21: =AD15+AD18 -> 49 | AG21: =sum(B21:AD21) -> 1745
A22: - Monthly Subscription | B22: =B16+B19 -> 104 | C22: =C16+C19 -> 99 | D22: =D16+D19 -> 122 | E22: =E16+E19 -> 115 | F22: =F16+F19 -> 78 | G22: =G16+G19 -> 72 | H22: =H16+H19 -> 91 | I22: =I16+I19 -> 89 | ... AD22: =AD16+AD19 -> 137 | AG22: =sum(B22:AD22) -> 2958
A24: Refunded Revenue
A25: Apple Store Sales | B25: =sum(B26:B27) -> 29.99 | C25: =sum(C26:C27) -> 29.99 | D25: =sum(D26:D27) -> 65.325675 | E25: =sum(E26:E27) -> 0 | F25: =sum(F26:F27) -> 29.99 | G25: =sum(G26:G27) -> 0 | H25: =sum(H26:H27) -> 0 | I25: =sum(I26:I27) -> 7.05 | ... AF25: =sum(AF26:AF27) -> 27.53 | AG25: =SUM(B25:AF25) -> 1576.9745
A26: - Yearly Subscription | B26: 29.99 | C26: 29.99 | D26: 65.325675 | E26: 0 | F26: 29.99 | G26: 0 | H26: 0 | I26: 7.05 | J26: 196.39881 | K26: 47.48 | L26: 6.23 | M26: 89.98 | N26: 0 | O26: 0 | P26: 455.74 | Q26: 366.66 | R26: 0 | S26: 0 | T26: 0 | U26: 0 | V26: 0 | W26: 59 | X26: 0 | Y26: 29.99 | Z26: 0 | AA26: 59.5 | AB26: 59.99 | AC26: 0 | AD26: 0 | AE26: 0 | AF26: 27.53 | AG26: =SUM(B26:AF26) -> 1560.8445
A27: - Monthly Subscription | B27: 0 | C27: 0 | D27: 0 | E27: 0 | F27: 0 | G27: 0 | H27: 0 | I27: 0 | J27: 9.33 | K27: 0 | L27: 0 | M27: 2.6 | N27: 0 | O27: 0 | P27: 0 | Q27: 2.6 | R27: 0 | S27: 0 | T27: 1.6 | U27: 0 | V27: 0 | W27: 0 | X27: 0 | Y27: 0 | Z27: 0 | AA27: 0 | AB27: 0 | AC27: 0 | AD27: 0 | AE27: 0 | AF27: 0 | AG27: =SUM(B27:AF27) -> 16.13
A28: Google Store Sales | B28: =sum(B29:B30) -> 0 | C28: =sum(C29:C30) -> 0 | D28: =sum(D29:D30) -> 0 | E28: =sum(E29:E30) -> 0 | F28: =sum(F29:F30) -> 0 | G28: =sum(G29:G30) -> 0 | H28: =sum(H29:H30) -> 0 | I28: =sum(I29:I30) -> 0 | ... AF28: =sum(AF29:AF30) -> 0 | AG28: =SUM(B28:AF28) -> 0
A29: - Yearly Subscription | B29: 0 | C29: 0 | D29: 0 | E29: 0 | F29: 0 | G29: 0 | H29: 0 | I29: 0 | J29: 0 | K29: 0 | L29: 0 | M29: 0 | N29: 0 | O29: 0 | P29: 0 | Q29: 0 | R29: 0 | S29: 0 | T29: 0 | U29: 0 | V29: 0 | W29: 0 | X29: 0 | Y29: 0 | Z29: 0 | AA29: 0 | AB29: 0 | AC29: 0 | AD29: 0 | AE29: 0 | AF29: 0 | AG29: =SUM(B29:AF29) -> 0
A30: - Monthly Subscription | B30: 0 | C30: 0 | D30: 0 | E30: 0 | F30: 0 | G30: 0 | H30: 0 | I30: 0 | J30: 0 | K30: 0 | L30: 0 | M30: 0 | N30: 0 | O30: 0 | P30: 0 | Q30: 0 | R30: 0 | S30: 0 | T30: 0 | U30: 0 | V30: 0 | W30: 0 | X30: 0 | Y30: 0 | Z30: 0 | AA30: 0 | AB30: 0 | AC30: 0 | AD30: 0 | AE30: 0 | AF30: 0 | AG30: =SUM(B30:AF30) -> 0
A31: SUM | B31: =B25+B28 -> 29.99 | C31: =C25+C28 -> 29.99 | D31: =D25+D28 -> 65.325675 | E31: =E25+E28 -> 0 | F31: =F25+F28 -> 29.99 | G31: =G25+G28 -> 0 | H31: =H25+H28 -> 0 | I31: =I25+I28 -> 7.05 | ... AF31: =AF25+AF28 -> 27.53 | AG31: =SUM(B31:AF31) -> 1576.9745
A33: Refunded Orders
A34: Apple Store orders | B34: =sum(B35:B36) -> 1 | C34: =sum(C35:C36) -> 1 | D34: =sum(D35:D36) -> 2 | E34: =sum(E35:E36) -> 0 | F34: =sum(F35:F36) -> 1 | G34: =sum(G35:G36) -> 0 | H34: =sum(H35:H36) -> 0 | I34: =sum(I35:I36) -> 1 | ... AF34: =sum(AF35:AF36) -> 0 | AG34: =SUM(B34:AF34) -> 25
A35: - Yearly Subscription | B35: 1 | C35: 1 | D35: 2 | E35: 0 | F35: 1 | G35: 0 | H35: 0 | I35: 1 | J35: 1 | K35: 0 | L35: 0 | M35: 2 | N35: 0 | O35: 0 | P35: 8 | Q35: 6 | R35: 0 | S35: 0 | T35: 0 | U35: 0 | V35: 0 | W35: 0 | X35: 0 | Y35: 1 | Z35: 0 | AA35: 0 | AB35: 1 | AC35: 0 | AD35: 0 | AE35: 0 | AF35: 0
A36: - Monthly Subscription | B36: 0 | C36: 0 | D36: 0 | E36: 0 | F36: 0 | G36: 0 | H36: 0 | I36: 0 | J36: 0 | K36: 0 | L36: 0 | M36: 0 | N36: 0 | O36: 0 | P36: 0 | Q36: 0 | R36: 0 | S36: 0 | T36: 0 | U36: 0 | V36: 0 | W36: 0 | X36: 0 | Y36: 0 | Z36: 0 | AA36: 0 | AB36: 0 | AC36: 0 | AD36: 0 | AE36: 0 | AF36: 0
A37: Google Store orders | B37: =sum(B38:B39) -> 0 | C37: =sum(C38:C39) -> 0 | D37: =sum(D38:D39) -> 0 | E37: =sum(E38:E39) -> 0 | F37: =sum(F38:F39) -> 0 | G37: =sum(G38:G39) -> 0 | H37: =sum(H38:H39) -> 0 | I37: =sum(I38:I39) -> 0 | ... AF37: =sum(AF38:AF39) -> 0 | AG37: =SUM(B37:AF37) -> 0
A38: - Yearly Subscription | B38: 0 | C38: 0 | D38: 0 | E38: 0 | F38: 0 | G38: 0 | H38: 0 | I38: 0 | J38: 0 | K38: 0 | L38: 0 | M38: 0 | N38: 0 | O38: 0 | P38: 0 | Q38: 0 | R38: 0 | S38: 0 | T38: 0 | U38: 0 | V38: 0 | W38: 0 | X38: 0 | Y38: 0 | Z38: 0 | AA38: 0 | AB38: 0 | AC38: 0 | AD38: 0 | AE38: 0 | AF38: 0
A39: - Monthly Subscription | B39: 0 | C39: 0 | D39: 0 | E39: 0 | F39: 0 | G39: 0 | H39: 0 | I39: 0 | J39: 0 | K39: 0 | L39: 0 | M39: 0 | N39: 0 | O39: 0 | P39: 0 | Q39: 0 | R39: 0 | S39: 0 | T39: 0 | U39: 0 | V39: 0 | W39: 0 | X39: 0 | Y39: 0 | Z39: 0 | AA39: 0 | AB39: 0 | AC39: 0 | AD39: 0 | AE39: 0 | AF39: 0
A40: SUM | B40: =B34+B37 -> 1 | C40: =C34+C37 -> 1 | D40: =D34+D37 -> 2 | E40: =E34+E37 -> 0 | F40: =F34+F37 -> 1 | G40: =G34+G37 -> 0 | H40: =H34+H37 -> 0 | I40: =I34+I37 -> 1 | ... AF40: =AF34+AF37 -> 0 | AG40: =SUM(B40:AF40) -> 25
A42: Net Revenue
A43: Apple Store | B43: =B5-B25 -> 9283.7991 | C43: =C5-C25 -> 7582.1973 | D43: =D5-D25 -> 982.93057 | E43: =E5-E25 -> 1325.4707 | F43: =F5-F25 -> 1217.4115 | G43: =G5-G25 -> 1551.6533 | H43: =H5-H25 -> 1216.037 | I43: =I5-I25 -> 1256.6525 | ... AF43: =AF5-AF25 -> 2498.5402 | AG43: =SUM(B43:AF43) -> 63676.891
A44: - Yearly Subscription | B44: =B6-B26 -> 8756.5666 | C44: =C6-C26 -> 7126.1275 | D44: =D6-D26 -> 389.93084 | E44: =E6-E26 -> 779.82 | F44: =F6-F26 -> 873.32881 | G44: =G6-G26 -> 1201.9597 | H44: =H6-H26 -> 804.47716 | I44: =I6-I26 -> 881.15383 | ... AF44: =AF6-AF26 -> 2117.5247 | AG44: =SUM(B44:AF44) -> 49329.432
A45: - Monthly Subscription | B45: =B7-B27 -> 527.23249 | C45: =C7-C27 -> 456.06984 | D45: =D7-D27 -> 592.99973 | E45: =E7-E27 -> 545.65073 | F45: =F7-F27 -> 344.08273 | G45: =G7-G27 -> 349.6936 | H45: =H7-H27 -> 411.55981 | I45: =I7-I27 -> 375.49867 | ... AF45: =AF7-AF27 -> 381.01554 | AG45: =SUM(B45:AF45) -> 14347.459
A46: Google Store | B46: =B8-B28 -> 3096.8 | C46: =C8-C28 -> 3447.45 | D46: =D8-D28 -> 421.66 | E46: =E8-E28 -> 264.13 | F46: =F8-F28 -> 231.88 | G46: =G8-G28 -> 263.84 | H46: =H8-H28 -> 408.78 | I46: =I8-I28 -> 220.47 | ... AF46: =AF8-AF28 -> 637.92 | AG46: =SUM(B46:AF46) -> 18607.62
A47: - Yearly Subscription | B47: =B9-B29 -> 3034.25 | C47: =C9-C29 -> 3338.19 | D47: =D9-D29 -> 348.64 | E47: =E9-E29 -> 163.5 | F47: =F9-F29 -> 155.52 | G47: =G9-G29 -> 216.53 | H47: =H9-H29 -> 323.01 | I47: =I9-I29 -> 120.48 | ... AF47: =AF9-AF29 -> 618.97 | AG47: =SUM(B47:AF47) -> 15562.61
A48: - Monthly Subscription | B48: =B10-B30 -> 62.55 | C48: =C10-C30 -> 109.26 | D48: =D10-D30 -> 73.02 | E48: =E10-E30 -> 100.63 | F48: =F10-F30 -> 76.36 | G48: =G10-G30 -> 47.31 | H48: =H10-H30 -> 85.77 | I48: =I10-I30 -> 99.99 | ... AF48: =AF10-AF30 -> 18.95 | AG48: =SUM(B48:AF48) -> 3045.01
A49: SUM | B49: =B43+B46 -> 12380.599 | C49: =C43+C46 -> 11029.647 | D49: =D43+D46 -> 1404.5906 | E49: =E43+E46 -> 1589.6007 | F49: =F43+F46 -> 1449.2915 | G49: =G43+G46 -> 1815.4933 | H49: =H43+H46 -> 1624.817 | I49: =I43+I46 -> 1477.1225 | ... AF49: =AF43+AF46 -> 3136.4602 | AG49: =SUM(B49:AF49) -> 82284.511
A51: Net Orders
A52: Apple Store | B52: =B14-B34 -> 379 | C52: =C14-C34 -> 306 | D52: =D14-D34 -> 119 | E52: =E14-E34 -> 115 | F52: =F14-F34 -> 89 | G52: =G14-G34 -> 94 | H52: =H14-H34 -> 94 | I52: =I14-I34 -> 94 | ... AF52: =AF14-AF34 -> 118 | AG52: =SUM(B52:AF52) -> 4036
A53: - Yearly Subscription | B53: =B15-B35 -> 285 | C53: =C15-C35 -> 225 | D53: =D15-D35 -> 11 | E53: =E15-E35 -> 18 | F53: =F15-F35 -> 25 | G53: =G15-G35 -> 30 | H53: =H15-H35 -> 18 | I53: =I15-I35 -> 24 | ... AF53: =AF15-AF35 -> 53 | AG53: =SUM(B53:AF53) -> 1454
A54: - Monthly Subscription | B54: =B16-B36 -> 94 | C54: =C16-C36 -> 81 | D54: =D16-D36 -> 108 | E54: =E16-E36 -> 97 | F54: =F16-F36 -> 64 | G54: =G16-G36 -> 64 | H54: =H16-H36 -> 76 | I54: =I16-I36 -> 70 | ... AF54: =AF16-AF36 -> 65 | AG54: =SUM(B54:AF54) -> 2582
A55: Google Store | B55: =B17-B37 -> 103 | C55: =C17-C37 -> 120 | D55: =D17-D37 -> 21 | E55: =E17-E37 -> 21 | F55: =F17-F37 -> 18 | G55: =G17-G37 -> 13 | H55: =H17-H37 -> 22 | I55: =I17-I37 -> 21 | ... AF55: =AF17-AF37 -> 18 | AG55: =SUM(B55:AF55) -> 956
A56: - Yearly Subscription | B56: =B18-B38 -> 93 | C56: =C18-C38 -> 102 | D56: =D18-D38 -> 7 | E56: =E18-E38 -> 3 | F56: =F18-F38 -> 4 | G56: =G18-G38 -> 5 | H56: =H18-H38 -> 7 | I56: =I18-I38 -> 2 | ... AF56: =AF18-AF38 -> 15 | AG56: =SUM(B56:AF56) -> 428
A57: - Monthly Subscription | B57: =B19-B39 -> 10 | C57: =C19-C39 -> 18 | D57: =D19-D39 -> 14 | E57: =E19-E39 -> 18 | F57: =F19-F39 -> 14 | G57: =G19-G39 -> 8 | H57: =H19-H39 -> 15 | I57: =I19-I39 -> 19 | ... AF57: =AF19-AF39 -> 3 | AG57: =SUM(B57:AF57) -> 528
A58: SUM | B58: =B52+B55 -> 482 | C58: =C52+C55 -> 426 | D58: =D52+D55 -> 140 | E58: =E52+E55 -> 136 | F58: =F52+F55 -> 107 | G58: =G52+G55 -> 107 | H58: =H52+H55 -> 116 | I58: =I52+I55 -> 115 | ... AF58: =AF52+AF55 -> 136 | AG58: =SUM(B58:AF58) -> 4992
A62: Commision Fees & Taxes
A63: Estimated Apple Store Commision Fee (30%) --> check again after 1. mil. | B63: =B5*0.3 -> 2794.1367 | C63: =C5*0.3 -> 2283.6562 | D63: =D5*0.3 -> 314.47687 | E63: =E5*0.3 -> 397.64122 | F63: =F5*0.3 -> 374.22046 | G63: =G5*0.3 -> 465.496 | H63: =H5*0.3 -> 364.81109 | I63: =I5*0.3 -> 379.11075 | ... AF63: =AF5*0.3 -> 757.82106 | AG63: =SUM(B63:AF63) -> 19576.16
A64: Estimated Apple Store Taxes | AG64: =SUM(B64:AF64) -> 0
A65: Estimated Google Store Commision Fee (15%) --> check again after 1. mil. | B65: =B8*0.15 -> 464.52 | C65: =C8*0.15 -> 517.1175 | D65: =D8*0.15 -> 63.249 | E65: =E8*0.15 -> 39.6195 | F65: =F8*0.15 -> 34.782 | G65: =G8*0.15 -> 39.576 | H65: =H8*0.15 -> 61.317 | I65: =I8*0.15 -> 33.0705 | ... AF65: =AF8*0.15 -> 95.688 | AG65: =SUM(B65:AF65) -> 2791.143
A66: Estimated Google Store Taxes | AG66: =SUM(B66:AF66) -> 0
A67: Estimated SUM Store Commision Fees | B67: =B63+B65 -> 3258.6567 | C67: =C63+C65 -> 2800.7737 | D67: =D63+D65 -> 377.72587 | E67: =E63+E65 -> 437.26072 | F67: =F63+F65 -> 409.00246 | G67: =G63+G65 -> 505.072 | H67: =H63+H65 -> 426.12809 | I67: =I63+I65 -> 412.18125 | ... AF67: =AF63+AF65 -> 853.50906 | AG67: =SUM(B67:AF67) -> 22367.303
A68: Estimated SUM Store Taxes | B68: =B64+B66 -> 0 | C68: =C64+C66 -> 0 | D68: =D64+D66 -> 0 | E68: =E64+E66 -> 0 | F68: =F64+F66 -> 0 | G68: =G64+G66 -> 0 | H68: =H64+H66 -> 0 | I68: =I64+I66 -> 0 | ... AF68: =AF64+AF66 -> 0 | AG68: =SUM(B68:AF68) -> 0
A70: Advertising
A71: Meta Spend | B71: =Summary!B127 -> 0 | C71: =Summary!C127 -> 0 | D71: =Summary!D127 -> 0 | E71: =Summary!E127 -> 0 | F71: =Summary!F127 -> 0 | G71: =Summary!G127 -> 0 | H71: =Summary!H127 -> 0 | I71: =Summary!I127 -> 0 | ... AF71: =Summary!AF127 -> 0 | AG71: =SUM(B71:AF71) -> 0
A72: Apple Spend | B72: =Summary!B128 -> 0 | C72: =Summary!C128 -> 0 | D72: =Summary!D128 -> 0 | E72: =Summary!E128 -> 0 | F72: =Summary!F128 -> 0 | G72: =Summary!G128 -> 0 | H72: =Summary!H128 -> 0 | I72: =Summary!I128 -> 0 | ... AF72: =Summary!AF128 -> 0 | AG72: =SUM(B72:AF72) -> 0
A73: Google Spend | B73: =Summary!B129 -> 0 | C73: =Summary!C129 -> 0 | D73: =Summary!D129 -> 0 | E73: =Summary!E129 -> 0 | F73: =Summary!F129 -> 0 | G73: =Summary!G129 -> 0 | H73: =Summary!H129 -> 0 | I73: =Summary!I129 -> 0 | ... AF73: =Summary!AF129 -> 0 | AG73: =SUM(B73:AF73) -> 0
A74: SUM | B74: =SUM(B71:B73) -> 0 | C74: =SUM(C71:C73) -> 0 | D74: =SUM(D71:D73) -> 0 | E74: =SUM(E71:E73) -> 0 | F74: =SUM(F71:F73) -> 0 | G74: =SUM(G71:G73) -> 0 | H74: =SUM(H71:H73) -> 0 | I74: =SUM(I71:I73) -> 0 | ... AF74: =SUM(AF71:AF73) -> 0 | AG74: =SUM(B74:AF74) -> 0
A76: Estimated Subscription Profit
A77: - Estimated Apple Store profit | B77: =B43-B63-B64-B72-(B71*'Data - P&L'!$I$24) -> 6489.6623 | C77: =C43-C63-C64-C72-(C71*'Data - P&L'!$I$24) -> 5298.5411 | D77: =D43-D63-D64-D72-(D71*'Data - P&L'!$I$24) -> 668.45369 | E77: =E43-E63-E64-E72-(E71*'Data - P&L'!$I$24) -> 927.82951 | F77: =F43-F63-F64-F72-(F71*'Data - P&L'!$I$24) -> 843.19108 | G77: =G43-G63-G64-G72-(G71*'Data - P&L'!$I$24) -> 1086.1573 | H77: =H43-H63-H64-H72-(H71*'Data - P&L'!$I$24) -> 851.22588 | I77: =I43-I63-I64-I72-(I71*'Data - P&L'!$I$24) -> 877.54175 | ... AF77: =AF43-AF63-AF64-AF72-(AF71*'Data - P&L'!$I$24) -> 1740.7191 | AG77: =SUM(B77:AF77) -> 44100.731
A78: - Estimated Google Store profit | B78: =B46-B65-B66-B73-(B71*'Data - P&L'!$I$25) -> 2632.28 | C78: =C46-C65-C66-C73-(C71*'Data - P&L'!$I$25) -> 2930.3325 | D78: =D46-D65-D66-D73-(D71*'Data - P&L'!$I$25) -> 358.411 | E78: =E46-E65-E66-E73-(E71*'Data - P&L'!$I$25) -> 224.5105 | F78: =F46-F65-F66-F73-(F71*'Data - P&L'!$I$25) -> 197.098 | G78: =G46-G65-G66-G73-(G71*'Data - P&L'!$I$25) -> 224.264 | H78: =H46-H65-H66-H73-(H71*'Data - P&L'!$I$25) -> 347.463 | I78: =I46-I65-I66-I73-(I71*'Data - P&L'!$I$25) -> 187.3995 | ... AF78: =AF46-AF65-AF66-AF73-(AF71*'Data - P&L'!$I$25) -> 542.232 | AG78: =SUM(B78:AF78) -> 15816.477
A79: Estimated SUM Profit | B79: =sum(B77:B78) -> 9121.9423 | C79: =sum(C77:C78) -> 8228.8736 | D79: =sum(D77:D78) -> 1026.8647 | E79: =sum(E77:E78) -> 1152.34 | F79: =sum(F77:F78) -> 1040.2891 | G79: =sum(G77:G78) -> 1310.4213 | H79: =sum(H77:H78) -> 1198.6889 | I79: =sum(I77:I78) -> 1064.9413 | ... AF79: =sum(AF77:AF78) -> 2282.9511 | AG79: =SUM(B79:AF79) -> 59917.208
A82: Gross Revenue
A83: =SUM(B11:AF11) -> 83861.485
A84: Gross Sales Profit
A85: =SUM(B79:AF79) -> 59917.208
A86: Gross Sales Margin
A87: =A85/A83 -> 0.71447826
A89: For summary
A90: Google | B90: =B8-B65-B66 -> 2632.28 | C90: =C8-C65-C66 -> 2930.3325 | D90: =D8-D65-D66 -> 358.411 | E90: =E8-E65-E66 -> 224.5105 | F90: =F8-F65-F66 -> 197.098 | G90: =G8-G65-G66 -> 224.264 | H90: =H8-H65-H66 -> 347.463 | I90: =I8-I65-I66 -> 187.3995 | ... AF90: =AF8-AF65-AF66 -> 542.232
A91: Apple | B91: =B5-B63-B64 -> 6519.6523 | C91: =C5-C63-C64 -> 5328.5311 | D91: =D5-D63-D64 -> 733.77937 | E91: =E5-E63-E64 -> 927.82951 | F91: =F5-F63-F64 -> 873.18108 | G91: =G5-G63-G64 -> 1086.1573 | H91: =H5-H63-H64 -> 851.22588 | I91: =I5-I63-I64 -> 884.59175 | ... AF91: =AF5-AF63-AF64 -> 1768.2491

Sheet Digital Marketplaces - P&L
A1: OCTOBER | B1: 45566 | C1: 45567 | D1: 45568 | E1: 45569 | F1: 45570 | G1: 45571 | H1: 45572 | I1: 45573 | J1: 45574 | K1: 45575 | L1: 45576 | M1: 45577 | N1: 45578 | O1: 45579 | P1: 45580 | Q1: 45581 | R1: 45582 | S1: 45583 | T1: 45584 | U1: 45585 | V1: 45586 | W1: 45587 | X1: 45588 | Y1: 45589 | Z1: 45590 | AA1: 45591 | AB1: 45592 | AC1: 45593 | AD1: 45594 | AE1: 45595 | AF1: 45596
A2: DAY | B2: TUE | C2: WED | D2: THU | E2: FRI | F2: SAT | G2: SUN | H2: MON | I2: TUE | J2: WED | K2: THU | L2: FRI | M2: SAT | N2: SUN | O2: MON | P2: TUE | Q2: WED | R2: THU | S2: FRI | T2: SAT | U2: SUN | V2: MON | W2: TUE | X2: WED | Y2: THU | Z2: FRI | AA2: SAT | AB2: SUN | AC2: MON | AD2: TUE | AE2: WED | AF2: THU
A3: Rachio (Shopify)
A4: Revenue | B4: =Summary!B36 -> 0 | C4: =Summary!C36 -> 0 | D4: =Summary!D36 -> 0 | E4: =Summary!E36 -> 0 | F4: =Summary!F36 -> 0 | G4: =Summary!G36 -> 0 | H4: =Summary!H36 -> 0 | I4: =Summary!I36 -> 0 | ... AF4: =Summary!AF36 -> 0 | AG4: =SUM(B4:AF4) -> 1146.2695
A5: Breakdown | AG5: =SUM(B5:AF5) -> 0
A6: - Tax | B6: =Summary!B38 -> 0 | C6: =Summary!C38 -> 0 | D6: =Summary!D38 -> 0 | E6: =Summary!E38 -> 0 | F6: =Summary!F38 -> 0 | G6: =Summary!G38 -> 0 | H6: =Summary!H38 -> 0 | I6: =Summary!I38 -> 0 | ... AF6: =Summary!AF38 -> 0 | AG6: =SUM(B6:AF6) -> 66.309544
A7: - Shipping | B7: =Summary!B39 | C7: =Summary!C39 | D7: =Summary!D39 | E7: =Summary!E39 | F7: =Summary!F39 | G7: =Summary!G39 | H7: =Summary!H39 | I7: =Summary!I39 | ... AD7: =Summary!AD39 | AG7: =SUM(B7:AF7) -> 0
A8: Orders | B8: =Summary!B88 -> 0 | C8: =Summary!C88 -> 0 | D8: =Summary!D88 -> 0 | E8: =Summary!E88 -> 0 | F8: =Summary!F88 -> 0 | G8: =Summary!G88 -> 0 | H8: =Summary!H88 -> 0 | I8: =Summary!I88 -> 0 | ... AE8: =Summary!AE88 -> 0 | AG8: =SUM(B8:AF8) -> 3
A10: Rachio Fees (20%) | B10: =Summary!B117 -> 0 | C10: =Summary!C117 -> 0 | D10: =Summary!D117 -> 0 | E10: =Summary!E117 -> 0 | F10: =Summary!F117 -> 0 | G10: =Summary!G117 -> 0 | H10: =Summary!H117 -> 0 | I10: =Summary!I117 -> 0 | ... AF10: =Summary!AF117 -> 0 | AG10: =SUM(B10:AF10) -> 229.25391
A12: Units Sold (Gross) - Rachio
A13: SKU 1 - Blue | B13: 0 | C13: 0 | D13: 0 | E13: 0 | F13: 0 | G13: 0 | H13: 0 | I13: 0 | J13: 0 | K13: 0 | L13: 0 | M13: 0 | N13: 0 | O13: 0 | P13: 0 | Q13: 0 | R13: 0 | S13: 0 | T13: 0 | U13: 0 | V13: 0 | W13: 0 | X13: 0 | Y13: 0 | Z13: 0 | AA13: 0 | AB13: 0 | AC13: 2 | AD13: 0 | AE13: 0 | AF13: 0 | AG13: =SUM(B13:AF13) -> 2
A14: SKU 2 - Yellow | B14: 0 | C14: 0 | D14: 0 | E14: 0 | F14: 0 | G14: 0 | H14: 0 | I14: 0 | J14: 0 | K14: 0 | L14: 0 | M14: 0 | N14: 0 | O14: 0 | P14: 0 | Q14: 0 | R14: 0 | S14: 0 | T14: 0 | U14: 0 | V14: 0 | W14: 0 | X14: 0 | Y14: 0 | Z14: 0 | AA14: 0 | AB14: 0 | AC14: 0 | AD14: 0 | AE14: 0 | AF14: 0 | AG14: =SUM(B14:AF14) -> 0
A15: SKU 3 - Blue w/ Solar | B15: 0 | C15: 0 | D15: 0 | E15: 0 | F15: 0 | G15: 0 | H15: 0 | I15: 0 | J15: 0 | K15: 0 | L15: 0 | M15: 0 | N15: 0 | O15: 1 | P15: 0 | Q15: 0 | R15: 0 | S15: 0 | T15: 0 | U15: 0 | V15: 1 | W15: 0 | X15: 0 | Y15: 0 | Z15: 0 | AA15: 0 | AB15: 0 | AC15: 0 | AD15: 0 | AE15: 0 | AF15: 0 | AG15: =SUM(B15:AF15) -> 2
A16: SKU 4 - Yellow w/ Solar | B16: 0 | C16: 0 | D16: 0 | E16: 0 | F16: 0 | G16: 0 | H16: 0 | I16: 0 | J16: 0 | K16: 0 | L16: 0 | M16: 0 | N16: 0 | O16: 0 | P16: 0 | Q16: 0 | R16: 0 | S16: 0 | T16: 0 | U16: 0 | V16: 0 | W16: 0 | X16: 0 | Y16: 0 | Z16: 0 | AA16: 0 | AB16: 0 | AC16: 0 | AD16: 0 | AE16: 0 | AF16: 0 | AG16: =SUM(B16:AF16) -> 0
A17: SUM (SKU 1 - SKU 4) | B17: =SUM(B13:B16) -> 0 | C17: =SUM(C13:C16) -> 0 | D17: =SUM(D13:D16) -> 0 | E17: =SUM(E13:E16) -> 0 | F17: =SUM(F13:F16) -> 0 | G17: =SUM(G13:G16) -> 0 | H17: =SUM(H13:H16) -> 0 | I17: =SUM(I13:I16) -> 0 | ... AF17: =SUM(AF13:AF16) -> 0 | AG17: =SUM(B17:AF17) -> 4
A19: Wall Mount | B19: 0 | C19: 0 | D19: 0 | E19: 0 | F19: 0 | G19: 0 | H19: 0 | I19: 0 | J19: 0 | K19: 0 | L19: 0 | M19: 0 | N19: 0 | O19: 0 | P19: 0 | Q19: 0 | R19: 0 | S19: 0 | T19: 0 | U19: 0 | V19: 0 | W19: 0 | X19: 0 | Y19: 0 | Z19: 0 | AA19: 0 | AB19: 0 | AC19: 0 | AD19: 0 | AE19: 0 | AF19: 0 | AG19: =SUM(B19:AF19) -> 0
A20: Suet Ball Holder | B20: 0 | C20: 0 | D20: 0 | E20: 0 | F20: 0 | G20: 0 | H20: 0 | I20: 0 | J20: 0 | K20: 0 | L20: 0 | M20: 0 | N20: 0 | O20: 0 | P20: 0 | Q20: 0 | R20: 0 | S20: 0 | T20: 0 | U20: 0 | V20: 0 | W20: 0 | X20: 0 | Y20: 0 | Z20: 0 | AA20: 0 | AB20: 0 | AC20: 0 | AD20: 0 | AE20: 0 | AF20: 0 | AG20: =SUM(B20:AF20) -> 0
A21: 3-in-1 Nutrition Set - Blue | B21: 0 | C21: 0 | D21: 0 | E21: 0 | F21: 0 | G21: 0 | H21: 0 | I21: 0 | J21: 0 | K21: 0 | L21: 0 | M21: 0 | N21: 0 | O21: 0 | P21: 0 | Q21: 0 | R21: 0 | S21: 0 | T21: 0 | U21: 0 | V21: 0 | W21: 0 | X21: 0 | Y21: 0 | Z21: 0 | AA21: 0 | AB21: 0 | AC21: 0 | AD21: 0 | AE21: 0 | AF21: 0 | AG21: =SUM(B21:AF21) -> 0
A22: 3-in-1 Nutrition Set - Yellow | B22: 0 | C22: 0 | D22: 0 | E22: 0 | F22: 0 | G22: 0 | H22: 0 | I22: 0 | J22: 0 | K22: 0 | L22: 0 | M22: 0 | N22: 0 | O22: 0 | P22: 0 | Q22: 0 | R22: 0 | S22: 0 | T22: 0 | U22: 0 | V22: 0 | W22: 0 | X22: 0 | Y22: 0 | Z22: 0 | AA22: 0 | AB22: 0 | AC22: 0 | AD22: 0 | AE22: 0 | AF22: 0 | AG22: =SUM(B22:AF22) -> 0
A23: Solar Roof Single - Blue | B23: 0 | C23: 0 | D23: 0 | E23: 0 | F23: 0 | G23: 0 | H23: 0 | I23: 0 | J23: 0 | K23: 0 | L23: 0 | M23: 0 | N23: 0 | O23: 0 | P23: 0 | Q23: 0 | R23: 0 | S23: 0 | T23: 0 | U23: 0 | V23: 0 | W23: 0 | X23: 0 | Y23: 0 | Z23: 0 | AA23: 0 | AB23: 0 | AC23: 0 | AD23: 0 | AE23: 0 | AF23: 0 | AG23: =SUM(B23:AF23) -> 0
A24: Solar Roof Single - Yellow | B24: 0 | C24: 0 | D24: 0 | E24: 0 | F24: 0 | G24: 0 | H24: 0 | I24: 0 | J24: 0 | K24: 0 | L24: 0 | M24: 0 | N24: 0 | O24: 0 | P24: 0 | Q24: 0 | R24: 0 | S24: 0 | T24: 0 | U24: 0 | V24: 0 | W24: 0 | X24: 0 | Y24: 0 | Z24: 0 | AA24: 0 | AB24: 0 | AC24: 0 | AD24: 0 | AE24: 0 | AF24: 0 | AG24: =SUM(B24:AF24) -> 0
A25: Perch Extender - Blue | B25: 0 | C25: 0 | D25: 0 | E25: 0 | F25: 0 | G25: 0 | H25: 0 | I25: 0 | J25: 0 | K25: 0 | L25: 0 | M25: 0 | N25: 0 | O25: 0 | P25: 0 | Q25: 0 | R25: 0 | S25: 0 | T25: 0 | U25: 0 | V25: 0 | W25: 0 | X25: 0 | Y25: 0 | Z25: 0 | AA25: 0 | AB25: 0 | AC25: 0 | AD25: 0 | AE25: 0 | AF25: 0 | AG25: =SUM(B25:AF25) -> 0
A26: Perch Extender - Yellow | B26: 0 | C26: 0 | D26: 0 | E26: 0 | F26: 0 | G26: 0 | H26: 0 | I26: 0 | J26: 0 | K26: 0 | L26: 0 | M26: 0 | N26: 0 | O26: 0 | P26: 0 | Q26: 0 | R26: 0 | S26: 0 | T26: 0 | U26: 0 | V26: 0 | W26: 0 | X26: 0 | Y26: 0 | Z26: 0 | AA26: 0 | AB26: 0 | AC26: 0 | AD26: 0 | AE26: 0 | AF26: 0 | AG26: =SUM(B26:AF26) -> 0
A27: SUM (Add-ons) | B27: =SUM(B19:B26) -> 0 | C27: =SUM(C19:C26) -> 0 | D27: =SUM(D19:D26) -> 0 | E27: =SUM(E19:E26) -> 0 | F27: =SUM(F19:F26) -> 0 | G27: =SUM(G19:G26) -> 0 | H27: =SUM(H19:H26) -> 0 | I27: =SUM(I19:I26) -> 0 | ... AF27: =SUM(AF19:AF26) -> 0 | AG27: =SUM(B27:AF27) -> 0
A29: Units and Revenue Cancelled & Refunds - Rachio
A31: Units Cancelled (Gross) - Rachio
A32: SKU 1 - Blue | AG32: =SUM(B32:AF32) -> 0
A33: SKU 2 - Yellow | AG33: =SUM(B33:AF33) -> 0
A34: SKU 3 - Blue w/ Solar | AG34: =SUM(B34:AF34) -> 0
A35: SKU 4 - Yellow w/ Solar | AG35: =SUM(B35:AF35) -> 0
A36: SUM (SKU 1 + SKU 2) | B36: =SUM(B32:B33) -> 0 | C36: =SUM(C32:C33) -> 0 | D36: =SUM(D32:D33) -> 0 | E36: =SUM(E32:E33) -> 0 | F36: =SUM(F32:F33) -> 0 | G36: =SUM(G32:G33) -> 0 | H36: =SUM(H32:H33) -> 0 | I36: =SUM(I32:I33) -> 0 | ... AF36: =SUM(AF32:AF33) -> 0 | AG36: =SUM(B36:AF36) -> 0
A37: SUM (SKU 3 + SKU 4) | B37: =SUM(B34:B35) -> 0 | C37: =SUM(C34:C35) -> 0 | D37: =SUM(D34:D35) -> 0 | E37: =SUM(E34:E35) -> 0 | F37: =SUM(F34:F35) -> 0 | G37: =SUM(G34:G35) -> 0 | H37: =SUM(H34:H35) -> 0 | I37: =SUM(I34:I35) -> 0 | ... AF37: =SUM(AF34:AF35) -> 0 | AG37: =SUM(B37:AF37) -> 0
A39: Wall Mount | AG39: =SUM(B39:AF39) -> 0
A40: Suet Ball Holder | AG40: =SUM(B40:AF40) -> 0
A41: 3-in-1 Nutrition Set - Blue | AG41: =SUM(B41:AF41) -> 0
A42: 3-in-1 Nutrition Set - Yellow | AG42: =SUM(B42:AF42) -> 0
A43: Solar Roof Single - Blue | AG43: =SUM(B43:AF43) -> 0
A44: Solar Roof Single - Yellow | AG44: =SUM(B44:AF44) -> 0
A45: Perch Extender - Blue | AG45: =SUM(B45:AF45) -> 0
A46: Perch Extender - Yellow | AG46: =SUM(B46:AF46) -> 0
A47: SUM (Add-ons) | B47: =SUM(B39:B46) -> 0 | C47: =SUM(C39:C46) -> 0 | D47: =SUM(D39:D46) -> 0 | E47: =SUM(E39:E46) -> 0 | F47: =SUM(F39:F46) -> 0 | G47: =SUM(G39:G46) -> 0 | H47: =SUM(H39:H46) -> 0 | I47: =SUM(I39:I46) -> 0 | ... AF47: =SUM(AF39:AF46) -> 0 | AG47: =SUM(B47:AF47) -> 0
A49: Revenue Cancelled (Gross) - Rachio
A50: Hardware | AG50: =SUM(B50:AF50) -> 0
A51: Shipping | AG51: =SUM(B51:AF51) -> 0
A52: Taxes | AG52: =SUM(B52:AF52) -> 0
A53: All NA | B53: =SUM(B50:B52) -> 0 | C53: =SUM(C50:C52) -> 0 | D53: =SUM(D50:D52) -> 0 | E53: =SUM(E50:E52) -> 0 | F53: =SUM(F50:F52) -> 0 | G53: =SUM(G50:G52) -> 0 | H53: =SUM(H50:H52) -> 0 | I53: =SUM(I50:I52) -> 0 | ... AF53: =SUM(AF50:AF52) -> 0 | AG53: =SUM(B53:AF53) -> 0
A55: Hardware - Europe | AG55: =SUM(B55:AF55) -> 0
A56: Shipping - Europe | AG56: =SUM(B56:AF56) -> 0
A57: All EU | B57: =sum(B55:B56) -> 0 | C57: =sum(C55:C56) -> 0 | D57: =sum(D55:D56) -> 0 | E57: =sum(E55:E56) -> 0 | F57: =sum(F55:F56) -> 0 | G57: =sum(G55:G56) -> 0 | H57: =sum(H55:H56) -> 0 | I57: =sum(I55:I56) -> 0 | ... AF57: =sum(AF55:AF56) -> 0 | AG57: =SUM(B57:AF57) -> 0
A59: Units Refund (Gross) - Rachio
A60: SKU 1 - Blue | AG60: =SUM(B60:AF60) -> 0
A61: SKU 2 - Yellow | AG61: =SUM(B61:AF61) -> 0
A62: SKU 3 - Blue w/ Solar | AG62: =SUM(B62:AF62) -> 0
A63: SKU 4 - Yellow w/ Solar | AG63: =SUM(B63:AF63) -> 0
A64: SUM (SKU 1 + SKU 2) | B64: =SUM(B60:B61) -> 0 | C64: =SUM(C60:C61) -> 0 | D64: =SUM(D60:D61) -> 0 | E64: =SUM(E60:E61) -> 0 | F64: =SUM(F60:F61) -> 0 | G64: =SUM(G60:G61) -> 0 | H64: =SUM(H60:H61) -> 0 | I64: =SUM(I60:I61) -> 0 | ... AF64: =SUM(AF60:AF61) -> 0 | AG64: =SUM(B64:AF64) -> 0
A65: SUM (SKU 3 + SKU 4) | B65: =SUM(B62:B63) -> 0 | C65: =SUM(C62:C63) -> 0 | D65: =SUM(D62:D63) -> 0 | E65: =SUM(E62:E63) -> 0 | F65: =SUM(F62:F63) -> 0 | G65: =SUM(G62:G63) -> 0 | H65: =SUM(H62:H63) -> 0 | I65: =SUM(I62:I63) -> 0 | ... AF65: =SUM(AF62:AF63) -> 0 | AG65: =SUM(B65:AF65) -> 0
A67: Wall Mount | AG67: =SUM(B67:AF67) -> 0
A68: Suet Ball Holder | AG68: =SUM(B68:AF68) -> 0
A69: 3-in-1 Nutrition Set - Blue | AG69: =SUM(B69:AF69) -> 0
A70: 3-in-1 Nutrition Set - Yellow | AG70: =SUM(B70:AF70) -> 0
A71: Solar Roof Single - Blue | AG71: =SUM(B71:AF71) -> 0
A72: Solar Roof Single - Yellow | AG72: =SUM(B72:AF72) -> 0
A73: Perch Extender - Blue | AG73: =SUM(B73:AF73) -> 0
A74: Perch Extender - Yellow | AG74: =SUM(B74:AF74) -> 0
A75: SUM (Add-ons) | B75: =SUM(B67:B74) -> 0 | C75: =SUM(C67:C74) -> 0 | D75: =SUM(D67:D74) -> 0 | E75: =SUM(E67:E74) -> 0 | F75: =SUM(F67:F74) -> 0 | G75: =SUM(G67:G74) -> 0 | H75: =SUM(H67:H74) -> 0 | I75: =SUM(I67:I74) -> 0 | ... AF75: =SUM(AF67:AF74) -> 0 | AG75: =SUM(B75:AF75) -> 0
A77: Orders Return for Refund | AG77: =SUM(B77:AF77) -> 0
A79: Revenue Refunded (Gross) - Rachio
A80: Hardware | AG80: =SUM(B80:AF80) -> 0
A81: Shipping | AG81: =SUM(B81:AF81) -> 0
A82: Taxes | AG82: =SUM(B82:AF82) -> 0
A83: All NA | B83: =sum(B80:B82) -> 0 | C83: =sum(C80:C82) -> 0 | D83: =sum(D80:D82) -> 0 | E83: =sum(E80:E82) -> 0 | F83: =sum(F80:F82) -> 0 | G83: =sum(G80:G82) -> 0 | H83: =sum(H80:H82) -> 0 | I83: =sum(I80:I82) -> 0 | ... AF83: =sum(AF80:AF82) -> 0 | AG83: =SUM(B83:AF83) -> 0
A85: Hardware - Europe | AG85: =SUM(B85:AF85) -> 0
A86: Shipping - Europe | AG86: =SUM(B86:AF86) -> 0
A87: All EU | B87: =sum(B85:B86) -> 0 | C87: =sum(C85:C86) -> 0 | D87: =sum(D85:D86) -> 0 | E87: =sum(E85:E86) -> 0 | F87: =sum(F85:F86) -> 0 | G87: =sum(G85:G86) -> 0 | H87: =sum(H85:H86) -> 0 | I87: =sum(I85:I86) -> 0 | ... AF87: =sum(AF85:AF86) -> 0 | AG87: =SUM(B87:AF87) -> 0
A89: RETURN (Replacement Units & Claims) - Rachio
A90: SKU 1 - Blue | AG90: =SUM(B90:AF90) -> 0
A91: SKU 2 - Yellow | AG91: =SUM(B91:AF91) -> 0
A92: SKU 3 - Blue w/ Solar | AG92: =SUM(B92:AF92) -> 0
A93: SKU 4 - Yellow w/ Solar | AG93: =SUM(B93:AF93) -> 0
A94: SUM (SKU 1 + SKU 2) | B94: =B90+B91 -> 0 | C94: =C90+C91 -> 0 | D94: =D90+D91 -> 0 | E94: =E90+E91 -> 0 | F94: =F90+F91 -> 0 | G94: =G90+G91 -> 0 | H94: =H90+H91 -> 0 | I94: =I90+I91 -> 0 | ... AF94: =AF90+AF91 -> 0 | AG94: =SUM(B94:AF94) -> 0
A95: SUM (SKU 3 + SKU 4) | B95: =B92+B93 -> 0 | C95: =C92+C93 -> 0 | D95: =D92+D93 -> 0 | E95: =E92+E93 -> 0 | F95: =F92+F93 -> 0 | G95: =G92+G93 -> 0 | H95: =H92+H93 -> 0 | I95: =I92+I93 -> 0 | ... AF95: =AF92+AF93 -> 0 | AG95: =SUM(B95:AF95) -> 0
AG96: =SUM(B96:AF96) -> 0
A97: Wall Mount | AG97: =SUM(B97:AF97) -> 0
A98: Suet Ball Holder | AG98: =SUM(B98:AF98) -> 0
A99: 3-in-1 Nutrition Set - Blue | AG99: =SUM(B99:AF99) -> 0
A100: 3-in-1 Nutrition Set - Yellow | AG100: =SUM(B100:AF100) -> 0
A101: Solar Roof Single - Blue | AG101: =SUM(B101:AF101) -> 0
A102: Solar Roof Single - Yellow | AG102: =SUM(B102:AF102) -> 0
A103: Perch Extender - Blue | AG103: =SUM(B103:AF103) -> 0
A104: Perch Extender - Yellow | AG104: =SUM(B104:AF104) -> 0
A105: SUM (Add-ons) | B105: =SUM(B97:B101) -> 0 | C105: =SUM(C97:C101) -> 0 | D105: =SUM(D97:D101) -> 0 | E105: =SUM(E97:E101) -> 0 | F105: =SUM(F97:F101) -> 0 | G105: =SUM(G97:G101) -> 0 | H105: =SUM(H97:H101) -> 0 | I105: =SUM(I97:I101) -> 0 | ... AF105: =SUM(AF97:AF101) -> 0 | AG105: =SUM(B105:AF105) -> 0
A107: Parts
A108: Housing - Blue | AG108: =SUM(B108:AF108) -> 0
A109: Housing - Yellow | AG109: =SUM(B109:AF109) -> 0
A110: Camera Module | AG110: =SUM(B110:AF110) -> 0
A112: Orders Replaced NA | B112: 0 | C112: 0 | D112: 0 | E112: 0 | F112: 0 | G112: 0 | H112: 0 | I112: 0 | J112: 0 | K112: 0 | L112: 0 | M112: 0 | N112: 0 | O112: 0 | P112: 0 | Q112: 0 | R112: 0 | S112: 0 | T112: 0 | U112: 0 | AG112: =SUM(B112:AF112) -> 0
A115: Weatherflow (Shopify)
A116: Revenue | B116: =Summary!B40 -> 0 | C116: =Summary!C40 -> 0 | D116: =Summary!D40 -> 0 | E116: =Summary!E40 -> 0 | F116: =Summary!F40 -> 0 | G116: =Summary!G40 -> 0 | H116: =Summary!H40 -> 0 | I116: =Summary!I40 -> 0 | ... AF116: =Summary!AF40 -> 0 | AG116: =SUM(B116:AF116) -> 0
A117: Breakdown
A118: - Tax | B118: =Summary!B42 -> 0 | C118: =Summary!C42 -> 0 | D118: =Summary!D42 -> 0 | E118: =Summary!E42 -> 0 | F118: =Summary!F42 -> 0 | G118: =Summary!G42 -> 0 | H118: =Summary!H42 -> 0 | I118: =Summary!I42 -> 0 | ... AF118: =Summary!AF42 -> 0 | AG118: =SUM(B118:AF118) -> 0
...

Sheet Data - P&L
B1: Business Metrics
A2: Source | B2: COGS | E2: Attachment Rates | H2: Marketing Averages (per first-time order) | K2: Fees | N2: VAT Averages | Q2: 30 Day Returns | T2: Digital Market Places & B2B
B3: Bird Buddy | C3: 83.87 | D3: 86.9 | E3: Solar Roof | F3: =(('DTC - P&L'!AG114+'DTC - P&L'!AG115)/'DTC - P&L'!AG104) -> 0.12693157 | H3: COGS | I3: =(C3*F9)+(C4*F8)+(C5*F3)+(C6*F4)+(C7*F5)+(C8*F6)+(C9*F7)+(C10*F10) -> 93.142152 | J3: =(D3*F9)+(D4*F8)+(D5*F3)+(D6*F4)+(D7*F5)+(D8*F6)+(D9*F7) -> 95.419779 | K3: Stripe Processing Fee | L3: 0.029 | N3: Europe | O3: 0.22 | Q3: US Shipping | R3: 15 | T3: Average % tax | U3: 0.0614 | V3: Source
B4: Bird Buddy with Solar Roof | C4: 95.58 | D4: 97.61 | E4: Wall Mount | F4: =('DTC - P&L'!AG110/'DTC - P&L'!AG104) -> 0.33995585 | H4: Inbound Shipping | I4: =C38+('DTC - P&L'!AG121/'DTC - P&L'!AG104)*D38 -> 13.995883 | K4: Duty | L4: 0.034 | N4: ROW | O4: 0.13 | Q4: EU Shipping | R4: 40
B5: Solar Roof Single | C5: 10.49 | D5: 13.44 | E5: Fence Mount | F5: 0 | H5: Outbound Shipping | I5: =C34+('DTC - P&L'!AG121/'DTC - P&L'!AG104)*D34 -> 20.758091 | K5: China Tax | L5: 0.075 | N5: NA | Q5: ROW Shipping | R5: 20
B6: Wall Mount | C6: 4.93 | D6: 5.49 | E6: Suet Ball Holder | F6: =('DTC - P&L'!AG111)/'DTC - P&L'!AG104 -> 0.1214128 | H6: Taxes and VAT | I6: 16.81 | K6: HMF | L6: 0.00125 | Q6: Money Return | R6: 1
B7: Fence Mount | C7: 6.37 | E7: 3-in-1 | F7: =('DTC - P&L'!AG112+'DTC - P&L'!AG113)/'DTC - P&L'!AG104 -> 0.15673289 | H7: China Tax (7.5%) | I7: 0 | K7: MPF | L7: 0.003464
B8: Suet Ball Holder | C8: 1.07 | D8: 1.19 | E8: Bird Buddy w/ Solar | F8: =('DTC - P&L'!AG98+'DTC - P&L'!AG99)/'DTC - P&L'!AG104 -> 0.35099338 | H8: Duty (3.4%) | I8: 0 | K8: Solar Roof China Tax | L8: 0.075
B9: 3-in-1 Nutrition Set | C9: 5.98 | D9: 6.66 | E9: Bird Buddy | F9: =1-F8 -> 0.64900662 | H9: Processing Fee (2,90%) | I9: =Summary!B177*L3 -> 5.4645604 | K9: Solar Roof Duty | L9: 0.025
B10: Perch Extender | C10: 4.21 | E10: Perch Extender | F10: =('DTC - P&L'!AG116+'DTC - P&L'!AG117)/'DTC - P&L'!AG104 -> 0.25827815 | H10: Transaction Fee ($0.30) | I10: =0.3 -> 0.3 | K10: Chargeback Fee (Stripe) | L10: 15
B11: Avg. Merch Cost | C11: 3.94 | E11: OTHER 2 | H11: OTHER 1
B12: Avg. Merch Cost without Calendar | C12: 14.79 | E12: OTHER 3 | H12: OTHER 2 | K12: Stripe | L12: 0.95
B13: SBF Housing | E13: OTHER 4 | H13: OTHER 3 | K13: Affirm | L13: 0.05
B14: SBF Camera | E14: OTHER 5 | H14: OTHER 4 | K14: Affirm processing fee | L14: 0.0579
B15: Hummingbird Feeder | C15: 87.9 | H15: All | I15: =SUM(I3:I14) -> 150.47069 | K15: Affirm transaction fee | L15: 0.3
B16: Hummingbird Feeder with Solar Roof | C16: 97.21
B17: Solar Roof (Hummingbird Feeder) | C17: 13.73
B18: Housing (Hummingbird Feeder) | C18: 26.68
B22: Outbound shipping | C22: Bird buddy | D22: Add-ons | E22: Merch
A23: *w/o CA weight | B23: Outbound (NA) | C23: 11.94 | D23: 6.155 | E23: 5.4 | H23: App Advertising
B24: Outbound (Europe) | C24: 11.94 | D24: 6.16 | H24: Meta Share to Apple Store | I24: 0.8
B25: Outbound (ROW) | C25: 11.94 | D25: 6.16 | H25: Meta Share to Google Store | I25: 0.2
A26: Source | B26: 3PL Costs | C26: 0 | D26: 0
B27: Handling Fee
B28: Serial Capture | C28: 0.1 | D28: 0
B29: Storage | C29: 0.31 | D29: 0.31
B30: Supplies cost | C30: 0 | D30: 0
B31: Pick charge | C31: 0.35 | D31: 0.35
B32: Pollybag cost | C32: 0 | D32: 0
B33: Carton cost | C33: 1.65 | D33: 0.71
B34: Total outbound (NA) | C34: =C26+C23-C27 -> 11.94 | D34: =D26+D23-D27 -> 6.155
B35: Total outbound (Europe) | C35: 15.06 | D35: =D27+D24-D28 -> 6.16
B36: Total outbound (ROW) | C36: 20
A37: Source | B37: Inbound shipping | C37: Bird buddy | D37: Add-ons
B38: Inbound (NA) | C38: 11.94 | D38: 1.435
B39: Inbound (Europe) | C39: 11.94 | D39: 1.44
B40: Inbound (ROW) | C40: 11.94 | D40: 1.44
B42: AMAZON Logistics | C42: Bird buddy | D42: Add-ons
A43: https://docs.google.com/spreadsheets/d/1Dn0q7h1bHxXdG0N9KpcqzFo0tWUWYXOrRX7yxv3G1E0/edit#gid=1264242332 | B43: Inbound | C43: 11.94 | D43: 1.435
A44: =sum(C43:C44) -> 12.18 | B44: Storage Fee | C44: 0.24 | D44: 0.24
A45: =C46 -> 12.94 | B45: AMAZON Fees | C45: Bird buddy
A46: =sum(F43:F45) -> 0 | B46: FBA fee for units | C46: 12.94
B47: FBA fee for addons | C47: 5.7
A48: =C38 -> 11.94 | B48: Sales Fee | C48: 0.15
B49: AMAZON Shipping | C49: Bird buddy
A50: =sum(A43:A48) -> 37.06 | B50: BB units Shipping | C50: 11
B51: Addons Shipping | C51: 6.155
B53: COGS adjustment for DTC
B54: Returns for refunds | C54: 0.25
B55: Returns for replacements | C55: 0.1
B57: COGS adjustment for Amazon
B58: Returns for refunds | C58: 0.5644
B59: Returns for replacements | C59: 0.4603
B61: Amazon Removal Fee
B62: Units | C62: 5.56
B63: Add-ons | C63: 2.2
A66: https://docs.google.com/document/d/1m1D0mcq6_cpIUs4Z2pSMjDX9L4kRSfAwaLu0UKQppIM/edit?usp=sharing | B66: Explanation for Returns, Cancellations, Replacements calculation
A68: https://docs.google.com/spreadsheets/d/1JFD6SusYZSq5MvMm0PnCaYPmLBVKBKvK09yjZIlSFN4/edit#gid=0 | B68: Amazon Modelling for cancelled orders | E68: Regular Price numbers for Amazon Modelling cancelled orders
B69: Full Price Template for cancelled orders | E69: 17.58 | F69: 0.29 | G69: 0 | H69: 0.17 | I69: 0.01 | J69: 2.44 | K69: 0.21
B70: item-tax | C70: 17.58
B71: shipping-price | C71: 0.29 | E71: MAP Price numbers for Amazon Modelling cancelled orders
B72: shipping-tax | C72: 0 | E72: 14.55 | F72: 0.55 | G72: 0.01 | H72: 0.15 | I72: 0.01 | J72: 7.62 | K72: 0.3
B73: gift-wrap-price | C73: 0.17
B74: gift-wrap-tax | C74: 0.01
B75: item-promotion-discount | C75: 2.44 | E75: item-tax | F75: shipping-price | G75: shipping-tax | H75: gift-wrap-price | I75: gift-wrap-tax | J75: item-promotion-discount | K75: ship-promotion-discount
B76: ship-promotion-discount | C76: 0.21
B79: B2B
B80: Agency Fee | C80: 0.05 | D80: NET NET
B81: Agency transportation best buy | C81: *Dejan sporoči

Sheet PP - Results
A1: 45566 | B1: 45566 | C1: 45567 | D1: 45568 | E1: 45569 | F1: 45570 | G1: 45571 | H1: 45572 | I1: 45573 | J1: 45574 | K1: 45575 | L1: 45576 | M1: 45577 | N1: 45578 | O1: 45579 | P1: 45580 | Q1: 45581 | R1: 45582 | S1: 45583 | T1: 45584 | U1: 45585 | V1: 45586 | W1: 45587 | X1: 45588 | Y1: 45589 | Z1: 45590 | AA1: 45591 | AB1: 45592 | AC1: 45593 | AD1: 45594 | AE1: 45595 | AF1: 45596
B2: TUE | C2: WED | D2: THU | E2: FRI | F2: SAT | G2: SUN | H2: MON | I2: TUE | J2: WED | K2: THU | L2: FRI | M2: SAT | N2: SUN | O2: MON | P2: TUE | Q2: WED | R2: THU | S2: FRI | T2: SAT | U2: SUN | V2: MON | W2: TUE | X2: WED | Y2: THU | Z2: FRI | AA2: SAT | AB2: SUN | AC2: MON | AD2: TUE | AE2: WED | AF2: THU
A4: Number of participants | B4: ='PP - Data'!B21 -> 13 | C4: ='PP - Data'!C21 -> 9 | D4: ='PP - Data'!D21 -> 5 | E4: ='PP - Data'!E21 -> 9 | F4: ='PP - Data'!F21 -> 11 | G4: ='PP - Data'!G21 -> 6 | H4: ='PP - Data'!H21 -> 6 | I4: ='PP - Data'!I21 -> 10 | ... AF4: ='PP - Data'!AF21 -> 71
