Workbook
Name zsupermetrics_ru0GDtbZzDLHQOQtJJ6K08MvUDyyp7: #REF!
Name zsupermetrics_DQl8lUbpTRu3fayaJJi7lVfOGKjNU4: 'Data - P&L'!$A$3:$A$4
Name zsupermetrics_BioPyGBzcBsy60UCQmPcTuFReEmghI: 'Data - P&L'!$B$2:$B$3
Name zsupermetrics_refreshAll: SupermetricsQueries!$H$5
Name zsupermetrics_n3GtLgiKpTmd2pYmQNMuq6TPD0qE0b: #REF!
Name zsupermetrics_refreshAllSilent: SupermetricsQueries!$H$6
Name zsupermetrics_Mgms9p0QzysYvrIhnsKACeVBVxfIEO: #REF!
Name zsupermetrics_Mgms9p0QzysYvrIhnsKACeVBVxfIEO: 'Data - P&L'!$A$2:$A$3
Name zsupermetrics_forceRefresh: SupermetricsQueries!$H$4
Name zsupermetrics_wbYMmT0YL9bAN0yhimW0ziPFnia9Dx: #REF!
Name zsupermetrics_iNpyVy90bWCI0yUaFQpxOtzWMa6sW4: #REF!
Name zsupermetrics_xwoIpANxRm908eDp5oKTwQpEI8gvD4: #REF!
Name zsupermetrics_n3GtLgiKpTmd2pYmQNMuq6TPD0qE0b: 'Data - P&L'!$B$4:$B$5
Name rdataslayer_42b112e4e4be4305bb4c1be75e2dd549: 'Data - P&L'!$B$2:$C$3
Name zsupermetrics_9i4W4hgd80uRpQLMeX0eRnESN8gjyv: #REF!
Name zsupermetrics_5bmwtOpHUbSYmDMeuCPkrxaojTprPP: #REF!
Name rdataslayer_3753ddf3234e496aa261974a0222e193: 'Data - P&L'!$H$2:$I$2
Name zsupermetrics_SGBxROnInO9rFyh3H7j2Lldx0Bdc5v: #REF!
Name zsupermetrics_pxuhRTEmIU93xSgKclyxajD0fCZ6rF: #REF!
Name zsupermetrics_ru0GDtbZzDLHQOQtJJ6K08MvUDyyp7: 'Data - P&L'!$B$4:$B$5
Name zsupermetrics_qWp7V908pNEYMtfv8QZvSTeDnBAHOU: 'Data - P&L'!$B$5:$C$13
Name rdataslayer_4a0f150f4f2f4e4f85c890c75b7a1fa4: #REF!
Name zsupermetrics_HgZqhorObHOtZHuyJjpmyYaEPoYntx: #REF!
Name zsupermetrics_YsFuuYtr8vOdNXCCPiFJIO38NP4b2T: #REF!
Name zsupermetrics_DQl8lUbpTRu3fayaJJi7lVfOGKjNU4: #REF!
Name zsupermetrics_YVuzfmsfdurz7Ldl84Rfns8oka6LsS: #REF!
Name zsupermetrics_4VkB7ij7WO0JjKBEgvjB2GHjSy2Egm: #REF!
Name zsupermetrics_9i4W4hgd80uRpQLMeX0eRnESN8gjyv: 'Data - P&L'!$C$13
Name zsupermetrics_lx4cNai7gT6tH4j08ZRkI21Qlpjioi: #REF!
Name rdataslayer_d70e473bcafe40a3aa834ce157fb2ba3: #REF!
Name zsupermetrics_NugLlrQxlKiqhxQae8EFpITBm1pLCj: 'Data - P&L'!$B$6:$C$13
Name zsupermetrics_8xojRjNDjo2jWHGDWjFEhflhyIq3Hq: Summary!$K$8:$K$31
Name zsupermetrics_FEamnpN5FsVYF0RtUTXAwunZ388Tkc: Forecast!$A$113:$C$141
Name rdataslayer_3753ddf3234e496aa261974a0222e193: #REF!
Name zsupermetrics_iNpyVy90bWCI0yUaFQpxOtzWMa6sW4: 'Data - P&L'!$A$2:$A$3
Name rdataslayer_4a0f150f4f2f4e4f85c890c75b7a1fa4: 'Data - P&L'!$D$2:$E$3
Name zsupermetrics_BioPyGBzcBsy60UCQmPcTuFReEmghI: #REF!
Name zsupermetrics_qWp7V908pNEYMtfv8QZvSTeDnBAHOU: #REF!
Name zsupermetrics_8xojRjNDjo2jWHGDWjFEhflhyIq3Hq: #REF!
Name zsupermetrics_wbYMmT0YL9bAN0yhimW0ziPFnia9Dx: 'Data - P&L'!$A$2:$A$3
Name zsupermetrics_4VkB7ij7WO0JjKBEgvjB2GHjSy2Egm: 'Data - P&L'!$B$4:$C$10
Name zsupermetrics_lx4cNai7gT6tH4j08ZRkI21Qlpjioi: 'Data - P&L'!$B$4:$C$13
Name rdataslayer_42b112e4e4be4305bb4c1be75e2dd549: #REF!
Name rdataslayer_adf57e64065742daa5b4161161b1c3ca: #REF!
Name rdataslayer_adf57e64065742daa5b4161161b1c3ca: 'Data - P&L'!$B$4:$D$5
Name zsupermetrics_NugLlrQxlKiqhxQae8EFpITBm1pLCj: #REF!
Name zsupermetrics_xwoIpANxRm908eDp5oKTwQpEI8gvD4: #REF!
Name zsupermetrics_YsFuuYtr8vOdNXCCPiFJIO38NP4b2T: 'Data - P&L'!$B$4:$C$13
Name rdataslayer_d70e473bcafe40a3aa834ce157fb2ba3: 'Data - P&L'!$C$8:$D$9
Name zsupermetrics_HgZqhorObHOtZHuyJjpmyYaEPoYntx: 'Data - P&L'!$B$4:$B$5

Sheet Summary
A1: 45352 | B1: 45352 | C1: 45353 | D1: 45354 | E1: 45355 | F1: 45356 | G1: 45357 | H1: 45358 | I1: 45359 | J1: 45360 | K1: 45361 | L1: 45362 | M1: 45363 | N1: 45364 | O1: 45365 | P1: 45366 | Q1: 45367 | R1: 45368 | S1: 45369 | T1: 45370 | U1: 45371 | V1: 45372 | W1: 45373 | X1: 45374 | Y1: 45375 | Z1: 45376 | AA1: 45377 | AB1: 45378 | AC1: 45379 | AD1: 45380 | AE1: 45381 | AF1: 45382
B2: FRI | C2: SAT | D2: SUN | E2: MON | F2: TUE | G2: WED | H2: THU | I2: FRI | J2: SAT | K2: SUN | L2: MON | M2: TUE | N2: WED | O2: THU | P2: FRI | Q2: SAT | R2: SUN | S2: MON | T2: TUE | U2: WED | V2: THU | W2: FRI | X2: SAT | Y2: SUN | Z2: MON | AA2: TUE | AB2: WED | AC2: THU | AD2: FRI | AE2: SAT | AF2: SUN
A3: Weekend Work
A4: Notes | B4: Women's Day Offer: 30% off (MAP) | T4: A/B Testing - PRO #1
B5: HBF Launch | I5: A/B Testing - Seeds #2 (First bag free & $14.90 Price) | W5: PR - WSJ
B6: A/B Testing - Seeds #1 (First bag free & $26.90 Price) | L6: HBF Price Increase HBF - $289 HBF w/ Solar - $359 | P6: Meta Advertising Stopped | T6: BestBuy - Deal of the day | Z6: Patagonia Checkout Live | AB6: HBF Shipping from June to August
A8: DTC Revenue | B8: 609995.61 | C8: 107937.13 | D8: 92285.37 | E8: 79668.99 | F8: 60001.2 | G8: 52648.98 | H8: 53600.39 | I8: 53298.97 | J8: 65507.46 | K8: 58345.32 | L8: 50106.48 | M8: 34630.63 | N8: 24539.57 | O8: 30839.36 | P8: 23481.39 | Q8: 31403.37 | R8: 24365.3 | S8: 22034.68 | T8: 18596.67 | U8: 19772.38 | V8: 21328.09 | W8: 37898.11 | X8: 30815.28 | Y8: 36859.86 | Z8: 27394.52 | AA8: 19602.23 | AB8: 19436.72 | AC8: 24112.65 | AD8: 17000.55 | AE8: 21890.63 | AF8: 18471.44
A9: - Hardware | B9: 530409.79 | C9: 88002.25 | D9: 75538.45 | E9: 64103.35 | F9: 47621.15 | G9: 40596.8 | H9: 42030.65 | I9: 42613.85 | J9: 50880.3 | K9: 45034.4 | L9: 39398.15 | M9: 26600.8 | N9: 19285.15 | O9: 24270.41 | P9: 17622.85 | Q9: 23523.2 | R9: 18560.9 | S9: 16112 | T9: 14364.78 | U9: 15242.2 | V9: 16516.9 | W9: 29456.48 | X9: 22808.32 | Y9: 27946.78 | Z9: 20592.23 | AA9: 14732.3 | AB9: 14201.2 | AC9: 17713.9 | AD9: 12605.4 | AE9: 16185.45 | AF9: 13825.11
A10: - Add-ons | B10: 9746.98 | C10: 5478.6 | D10: 4169.45 | E10: 4300.95 | F10: 3500.8 | G10: 3624.5 | H10: 3175.6 | I10: 2564.55 | J10: 4382.3 | K10: 4216.4 | L10: 3437.05 | M10: 3063.25 | N10: 1927.25 | O10: 2231.89 | P10: 2344.15 | Q10: 3365.45 | R10: 2138.25 | S10: 2508.2 | T10: 1598.74 | U10: 1579.25 | V10: 1644.9 | W10: 3179.37 | X10: 3285.08 | Y10: 3053.62 | Z10: 2515.22 | AA10: 1697.6 | AB10: 2289.2 | AC10: 2550.1 | AD10: 1848.2 | AE10: 2282.2 | AF10: 1741.99
A11: - Merch | B11: 0 | C11: 0 | D11: 0 | E11: 0 | F11: 0 | G11: 184.94 | H11: 0 | I11: 0 | J11: 0 | K11: 0 | L11: 0 | M11: 0 | N11: 0 | O11: 0 | P11: 0 | Q11: 39.99 | R11: 0 | S11: 0 | T11: 29.99 | U11: 0 | V11: 0 | W11: 0 | X11: 39.99 | Y11: 0 | Z11: 0 | AA11: 0 | AB11: 0 | AC11: 0 | AD11: 0 | AE11: 39.99 | AF11: 0
A12: - Seeds | B12: 434.04 | C12: 310.57 | D12: 225 | E12: 357.48 | F12: 360.4 | G12: 247.87 | H12: 244.33 | I12: 108.94 | J12: 213.14 | K12: 124.07 | L12: 143.4 | M12: 205.81 | N12: 146.4 | O12: 209.87 | P12: 354.81 | Q12: 160.07 | R12: 188.1 | S12: 218.9 | T12: 0 | U12: 182.47 | V12: 225 | W12: 376.6 | X12: 448.4 | Y12: 704.37 | Z12: 476 | AA12: 374.3 | AB12: 368.4 | AC12: 467.1 | AD12: 76.67 | AE12: 180.1 | AF12: 260.1
A13: - Yearly Pro Subscription | S13: 90 | T13: 58.33 | U13: 30 | V13: 0 | W13: 60 | X13: 0 | Y13: 180 | Z13: 90 | AA13: 25 | AB13: 90 | AC13: 180 | AD13: 120 | AE13: 180 | AF13: 120
A14: - Taxes | B14: 37467.8 | C14: 6623.71 | D14: 5640.47 | E14: 4787.21 | F14: 3534.85 | G14: 3154.87 | H14: 3158.81 | I14: 3131.63 | J14: 3951.72 | K14: 3605.45 | L14: 3002.88 | M14: 2120.77 | N14: 1375.77 | O14: 1877.19 | P14: 1399.58 | Q14: 1854.66 | R14: 1538.05 | S14: 1230.58 | T14: 1114.83 | U14: 1166.46 | V14: 1359.29 | W14: 2195.66 | X14: 2008.49 | Y14: 2240.09 | Z14: 1659.07 | AA14: 1266.03 | AB14: 1100.92 | AC14: 1384.55 | AD14: 1050.28 | AE14: 1340.89 | AF14: 1079.24
A15: - Shipping | B15: 31937 | C15: 7522 | D15: 6712 | E15: 6120 | F15: 4984 | G15: 4840 | H15: 4991 | I15: 4880 | J15: 6080 | K15: 5365 | L15: 4125 | M15: 2640 | N15: 1805 | O15: 2250 | P15: 1760 | Q15: 2460 | R15: 1940 | S15: 1875 | T15: 1430 | U15: 1572 | V15: 1582 | W15: 2630 | X15: 2225 | Y15: 2735 | Z15: 2062 | AA15: 1507 | AB15: 1387 | AC15: 1817 | AD15: 1300 | AE15: 1682 | AF15: 1445
A16: Amazon Revenue | B16: =B17+B18+B19+B20+B21 -> 19348.49 | C16: =C17+C18+C19+C20+C21 -> 22322.39 | D16: =D17+D18+D19+D20+D21 -> 16109.48 | E16: =E17+E18+E19+E20+E21 -> 9416.58 | F16: =F17+F18+F19+F20+F21 -> 6365.8 | G16: =G17+G18+G19+G20+G21 -> 11506.81 | H16: =H17+H18+H19+H20+H21 -> 17570.37 | I16: =I17+I18+I19+I20+I21 -> 16642.54 | ... AF16: =AF17+AF18+AF19+AF20+AF21 -> 4451.22
A17: - Hardware | B17: 16689.8 | C17: 18894.12 | D17: 13167.68 | E17: 7392.24 | F17: 4950.56 | G17: 9849 | H17: 15173.56 | I17: 14651.68 | J17: 17400.12 | K17: 19281.12 | L17: 7612.12 | M17: 7593 | N17: 8849 | O17: 10045 | P17: 11655.12 | Q17: 9624.56 | R17: 11836.56 | S17: 5440 | T17: 10463 | U17: 12247.24 | V17: 9084.56 | W17: 7771 | X17: 8962.12 | Y17: 9145 | Z17: 6631.56 | AA17: 7647.12 | AB17: 6745.24 | AC17: 6091.12 | AD17: 5679 | AE17: 5082 | AF17: 2989
A18: - Add-ons | B18: 1424.56 | C18: 1915.56 | D18: 1792.68 | E18: 1421.56 | F18: 1009 | G18: 906 | H18: 1285.56 | I18: 897 | J18: 2501.12 | K18: 1509 | L18: 1082.12 | M18: 966 | N18: 954 | O18: 999.68 | P18: 819 | Q18: 1898.24 | R18: 1582.68 | S18: 974 | T18: 850 | U18: 1110 | V18: 1075.12 | W18: 889 | X18: 1348.56 | Y18: 1547 | Z18: 1146.56 | AA18: 929 | AB18: 724 | AC18: 969.12 | AD18: 889 | AE18: 2055 | AF18: 1130
A19: - Tax | B19: 1193.49 | C19: 1464.05 | D19: 1131.65 | E19: 586.52 | F19: 392.02 | G19: 741.83 | H19: 1064.89 | I19: 1027.39 | J19: 1409.3 | K19: 1407.52 | L19: 554.12 | M19: 553.37 | N19: 641.76 | O19: 827.5 | P19: 790.79 | Q19: 881.92 | R19: 879.12 | S19: 450.62 | T19: 777.17 | U19: 818.35 | V19: 740.37 | W19: 598.37 | X19: 683.95 | Y19: 760.41 | Z19: 571.28 | AA19: 579.31 | AB19: 510.61 | AC19: 493.53 | AD19: 479.38 | AE19: 491.05 | AF19: 320.74
A20: - Shipping | B20: 26.65 | C20: 21.21 | D20: 7.47 | E20: 10.42 | F20: 0.08 | G20: 0 | H20: 29.06 | I20: 51.99 | J20: 10.3 | K20: 56.22 | L20: 0.32 | M20: 12.99 | N20: 0 | O20: 13.41 | P20: 0.16 | Q20: 0.4 | R20: 0.32 | S20: 0 | T20: 0 | U20: 44.42 | V20: 0.24 | W20: 0 | X20: 0.24 | Y20: 31.84 | Z20: 0.95 | AA20: 18.69 | AB20: 7.31 | AC20: 7.31 | AD20: 0 | AE20: 37.42 | AF20: 6.99
A21: - Gift Wrap | B21: 13.99 | C21: 27.45 | D21: 10 | E21: 5.84 | F21: 14.14 | G21: 9.98 | H21: 17.3 | I21: 14.48 | J21: 22.63 | K21: 4.83 | L21: 5.17 | M21: 4.99 | N21: 8.98 | O21: 9.49 | P21: 4.83 | Q21: 9.83 | R21: 19.14 | S21: 0 | T21: 17.96 | U21: 14.65 | V21: 5.5 | W21: 8.48 | X21: 14.48 | Y21: 29.43 | Z21: 0.34 | AA21: 9.32 | AB21: 5.17 | AC21: 9.66 | AD21: 13.47 | AE21: 0 | AF21: 4.49
A22: Digital Marketplaces Revenue | B22: =SUM(B27,B23) -> 403.31077 | C22: =SUM(C27,C23) -> 222.88339 | D22: =SUM(D27,D23) -> 0 | E22: =SUM(E27,E23) -> 0 | F22: =SUM(F27,F23) -> 0 | G22: =SUM(G27,G23) -> 222.88339 | H22: =SUM(H27,H23) -> 317.3586 | I22: =SUM(I27,I23) -> 445.76677 | ... AF22: =SUM(AF27,AF23) -> 0
A23: Rachio | B23: =SUM(B24:B25) -> 403.31077 | C23: =SUM(C24:C25) -> 222.88339 | D23: =SUM(D24:D25) -> 0 | E23: =SUM(E24:E25) -> 0 | F23: =SUM(F24:F25) -> 0 | G23: =SUM(G24:G25) -> 222.88339 | H23: =SUM(H24:H25) -> 0 | I23: =SUM(I24:I25) -> 445.76677 | ... AF23: =SUM(AF24:AF25) -> 0
A24: - Hardware | B24: 379.98 | C24: 209.99 | D24: 0 | E24: 0 | F24: 0 | G24: 209.99 | H24: 0 | I24: 419.98 | J24: 0 | K24: 1009.95 | L24: 209.99 | M24: 209.99 | N24: 0 | O24: 0 | P24: 0 | Q24: 0 | R24: 0 | S24: 0 | T24: 0 | U24: 0 | V24: 0 | W24: 0 | X24: 0 | Y24: 0 | Z24: 0 | AA24: 0 | AB24: 0 | AC24: 299.99 | AD24: 0 | AE24: 0 | AF24: 0
A25: - Tax | B25: =0.0614*B24 -> 23.330772 | C25: =0.0614*C24 -> 12.893386 | D25: =0.0614*D24 -> 0 | E25: =0.0614*E24 -> 0 | F25: =0.0614*F24 -> 0 | G25: =0.0614*G24 -> 12.893386 | H25: =0.0614*H24 -> 0 | I25: =0.0614*I24 -> 25.786772 | ... AF25: =0.0614*AF24 -> 0
A26: - Shipping
A27: Weatherflow | B27: =SUM(B28:B29) -> 0 | C27: =SUM(C28:C29) -> 0 | D27: =SUM(D28:D29) -> 0 | E27: =SUM(E28:E29) -> 0 | F27: =SUM(F28:F29) -> 0 | G27: =SUM(G28:G29) -> 0 | H27: =SUM(H28:H29) -> 317.3586 | I27: =SUM(I28:I29) -> 0 | ... AF27: =SUM(AF28:AF29) -> 0
A28: - Hardware | B28: 0 | C28: 0 | D28: 0 | E28: 0 | F28: 0 | G28: 0 | H28: 299 | I28: 0 | J28: 0 | K28: 0 | L28: 299 | M28: 0 | N28: 0 | O28: 0 | P28: 0 | Q28: 0 | R28: 0 | S28: 0 | T28: 0 | U28: 0 | V28: 0 | W28: 0 | X28: 0 | Y28: 0 | Z28: 478 | AA28: 0 | AB28: 0 | AC28: 0 | AD28: 0 | AE28: 0 | AF28: 0
A29: - Tax | B29: =0.0614*B28 -> 0 | C29: =0.0614*C28 -> 0 | D29: =0.0614*D28 -> 0 | E29: =0.0614*E28 -> 0 | F29: =0.0614*F28 -> 0 | G29: =0.0614*G28 -> 0 | H29: =0.0614*H28 -> 18.3586 | I29: =0.0614*I28 -> 0 | ... AF29: =0.0614*AF28 -> 0
A30: - Shipping
A31: Total Revenue | B31: =SUM(B8+B16+B22) -> 629747.41 | C31: =SUM(C8+C16+C22) -> 130482.4 | D31: =SUM(D8+D16+D22) -> 108394.85 | E31: =SUM(E8+E16+E22) -> 89085.57 | F31: =SUM(F8+F16+F22) -> 66367 | G31: =SUM(G8+G16+G22) -> 64378.673 | H31: =SUM(H8+H16+H22) -> 71488.119 | I31: =SUM(I8+I16+I22) -> 70387.277 | ... AF31: =SUM(AF8+AF16+AF22) -> 22922.66
A33: B2B Revenue
A34: Best Buy | B34: =iferror(sum(B35:B37),"") -> 3992.9868 | C34: =sum(C35:C37) -> 4880.3172 | D34: =sum(D35:D37) -> 0 | E34: =sum(E35:E37) -> 665.4978 | F34: =sum(F35:F37) -> 4658.4846 | G34: =sum(G35:G37) -> 3105.6564 | H34: =sum(H35:H37) -> 2440.1586 | I34: =sum(I35:I37) -> 2440.1586 | J34: =sum(J35:J37) -> 1996.4934 | ... AF34: =sum(AF35:AF37) -> 0
A35: - Hardware | B35: 3762 | C35: 4598 | D35: 0 | E35: 627 | F35: 4389 | G35: 2926 | H35: 2299 | I35: 2299 | J35: 1881 | K35: 0 | L35: 1254 | M35: 5382 | N35: 2990 | O35: 1196 | P35: 2093 | Q35: 1196 | R35: 0 | S35: 2392 | T35: 17940 | U35: 16744 | V35: 3289 | W35: 5382 | X35: 5681 | Y35: 0 | Z35: 2990 | AA35: 8073 | AB35: 6877 | AC35: 7176 | AD35: 11362 | AE35: 11661 | AF35: 0
A36: - Tax | B36: =B35*'Data - P&L'!$U$3 -> 230.9868 | C36: =C35*'Data - P&L'!$U$3 -> 282.3172 | D36: =D35*'Data - P&L'!$U$3 -> 0 | E36: =E35*'Data - P&L'!$U$3 -> 38.4978 | F36: =F35*'Data - P&L'!$U$3 -> 269.4846 | G36: =G35*'Data - P&L'!$U$3 -> 179.6564 | H36: =H35*'Data - P&L'!$U$3 -> 141.1586 | I36: =I35*'Data - P&L'!$U$3 -> 141.1586 | ... AF36: =AF35*'Data - P&L'!$U$3 -> 0
A37: - Shipping
A38: Target | B38: =sum(B39:B41) -> 361.9374 | C38: =sum(C39:C41) -> 1826.6694 | D38: =sum(D39:D41) -> 496.7352 | E38: =sum(E39:E41) -> 254.736 | F38: =sum(F39:F41) -> 254.736 | G38: =sum(G39:G41) -> 241.9992 | H38: =sum(H39:H41) -> 254.736 | I38: =sum(I39:I41) -> 507.3492 | ... AF38: =sum(AF39:AF41) -> 0
A39: - Hardware | B39: 341 | C39: 1721 | D39: 468 | E39: 240 | F39: 240 | G39: 228 | H39: 240 | I39: 478 | J39: 899 | K39: 468 | L39: 240 | M39: 641 | N39: 468 | O39: 718 | P39: 432 | Q39: 1401 | R39: 240 | S39: 472 | T39: 0 | U39: 645 | V39: 801 | W39: 2221 | X39: 3222 | Y39: 2571 | Z39: 2057 | AA39: 2685 | AB39: 2284 | AC39: 1853 | AD39: 2140 | AE39: 2716 | AF39: 0
A40: - Tax | B40: =B39*'Data - P&L'!$U$3 -> 20.9374 | C40: =C39*'Data - P&L'!$U$3 -> 105.6694 | D40: =D39*'Data - P&L'!$U$3 -> 28.7352 | E40: =E39*'Data - P&L'!$U$3 -> 14.736 | F40: =F39*'Data - P&L'!$U$3 -> 14.736 | G40: =G39*'Data - P&L'!$U$3 -> 13.9992 | H40: =H39*'Data - P&L'!$U$3 -> 14.736 | I40: =I39*'Data - P&L'!$U$3 -> 29.3492 | ... AF40: =AF39*'Data - P&L'!$U$3 -> 0
A41: - Shipping
A42: Total Revenue | B42: =B34+B38 -> 4354.9242 | C42: =C34+C38 -> 6706.9866 | D42: =D34+D38 -> 496.7352 | E42: =E34+E38 -> 920.2338 | F42: =F34+F38 -> 4913.2206 | G42: =G34+G38 -> 3347.6556 | H42: =H34+H38 -> 2694.8946 | I42: =I34+I38 -> 2947.5078 | ... AF42: =AF34+AF38 -> 0
A44: App Revenue
A45: - Google Store | B45: ='App - P&L'!B90 -> 1148.99 | C45: ='App - P&L'!C90 -> 1062.7825 | D45: ='App - P&L'!D90 -> 803.7795 | E45: ='App - P&L'!E90 -> 1208.662 | F45: ='App - P&L'!F90 -> 879.806 | G45: ='App - P&L'!G90 -> 423.688 | H45: ='App - P&L'!H90 -> 376.123 | I45: ='App - P&L'!I90 -> 502.873 | ... AF45: ='App - P&L'!AF90 -> 301.444
A46: - Apple Store | B46: ='App - P&L'!B91 -> 4805.3448 | C46: ='App - P&L'!C91 -> 3872.0354 | D46: ='App - P&L'!D91 -> 4707.414 | E46: ='App - P&L'!E91 -> 7576.724 | F46: ='App - P&L'!F91 -> 3176.945 | G46: ='App - P&L'!G91 -> 1647.187 | H46: ='App - P&L'!H91 -> 1655.7516 | I46: ='App - P&L'!I91 -> 1757.7457 | ... AF46: ='App - P&L'!AF91 -> 2474.8939
A47: - Comission | B47: ='App - P&L'!B67 -> 2266.6778 | C47: ='App - P&L'!C67 -> 1852.2312 | D47: ='App - P&L'!D67 -> 2160.7665 | E47: ='App - P&L'!E67 -> 3462.054 | F47: ='App - P&L'!F67 -> 1518.249 | G47: ='App - P&L'!G67 -> 782.805 | H47: ='App - P&L'!H67 -> 779.76197 | I47: ='App - P&L'!I67 -> 846.11085 | ... AF47: ='App - P&L'!AF67 -> 1116.1619
A48: - Tax | B48: ='App - P&L'!B68 -> 17.18 | C48: ='App - P&L'!C68 -> 12.98 | D48: ='App - P&L'!D68 -> 4.63 | E48: ='App - P&L'!E68 -> 4.7 | F48: ='App - P&L'!F68 -> 3.71 | G48: ='App - P&L'!G68 -> 5.91 | H48: ='App - P&L'!H68 -> 9.76 | I48: ='App - P&L'!I68 -> 11.43 | ... AF48: ='App - P&L'!AF68 -> 5.36
A49: Total Revenue | B49: =sum(B45:B48) -> 8238.1926 | C49: =sum(C45:C48) -> 6800.0291 | D49: =sum(D45:D48) -> 7676.59 | E49: =sum(E45:E48) -> 12252.14 | F49: =sum(F45:F48) -> 5578.71 | G49: =sum(G45:G48) -> 2859.59 | H49: =sum(H45:H48) -> 2821.3966 | I49: =sum(I45:I48) -> 3118.1595 | ... AF49: =sum(AF45:AF48) -> 3897.8598
A52: DTC Orders | B52: 1961 | C52: 416 | D52: 347 | E52: 312 | F52: 247 | G52: 214 | H52: 208 | I52: 200 | J52: 269 | K52: 237 | L52: 183 | M52: 125 | N52: 93 | O52: 107 | P52: 90 | Q52: 118 | R52: 91 | S52: 93 | T52: 71 | U52: 82 | V52: 82 | W52: 100 | X52: 117 | Y52: 137 | Z52: 112 | AA52: 79 | AB52: 79 | AC52: 93 | AD52: 57 | AE52: 87 | AF52: 80
A53: - Hardware (units sold) | B53: 1942 | C53: 355 | D53: 314 | E53: 274 | F53: 210 | G53: 180 | H53: 184 | I53: 186 | J53: 221 | K53: 192 | L53: 147 | M53: 88 | N53: 67 | O53: 83 | P53: 64 | Q53: 81 | R53: 64 | S53: 56 | T53: 49 | U53: 54 | V53: 55 | W53: 103 | X53: 80 | Y53: 95 | Z53: 69 | AA53: 51 | AB53: 49 | AC53: 61 | AD53: 44 | AE53: 55 | AF53: 47
A54: - Add-ons (units sold) | B54: 452 | C54: 305 | D54: 286 | E54: 272 | F54: 224 | G54: 228 | H54: 201 | I54: 183 | J54: 256 | K54: 242 | L54: 138 | M54: 83 | N54: 47 | O54: 67 | P54: 60 | Q54: 91 | R54: 65 | S54: 70 | T54: 51 | U54: 47 | V54: 55 | W54: 100 | X54: 86 | Y54: 93 | Z54: 74 | AA54: 53 | AB54: 63 | AC54: 72 | AD54: 58 | AE54: 67 | AF54: 48
A55: - Merch (units sold) | B55: 0 | C55: 0 | D55: 0 | E55: 0 | F55: 0 | G55: 6 | H55: 0 | I55: 0 | J55: 0 | K55: 0 | L55: 0 | M55: 0 | N55: 0 | O55: 0 | P55: 0 | Q55: 1 | R55: 0 | S55: 2 | T55: 1 | U55: 0 | V55: 0 | W55: 0 | X55: 1 | Y55: 0 | Z55: 0 | AA55: 0 | AB55: 0 | AC55: 0 | AD55: 0 | AE55: 1 | AF55: 0
A56: - Seeds (units sold) | B56: 51 | C56: 36 | D56: 31 | E56: 35 | F56: 44 | G56: 29 | H56: 27 | I56: 22 | J56: 33 | K56: 21 | L56: 22 | M56: 17 | N56: 9 | O56: 13 | P56: 23 | Q56: 14 | R56: 9 | S56: 14 | T56: 1 | U56: 6 | V56: 8 | W56: 14 | X56: 16 | Y56: 26 | Z56: 18 | AA56: 14 | AB56: 14 | AC56: 17 | AD56: 3 | AE56: 7 | AF56: 9
A57: - BB 1 year Pro Subscription | S57: 3 | T57: 2 | U57: 2 | V57: 3 | W57: 13 | X57: 4 | Y57: 13 | Z57: 8 | AA57: 6 | AB57: 8 | AC57: 11 | AD57: 14 | AE57: 15 | AF57: 9
A58: Amazon Orders | B58: 153 | C58: 171 | D58: 147 | E58: 97 | F58: 60 | G58: 114 | H58: 121 | I58: 110 | J58: 184 | K58: 175 | L58: 41 | M58: 69 | N58: 66 | O58: 53 | P58: 78 | Q58: 75 | R58: 84 | S58: 53 | T58: 75 | U58: 76 | V58: 62 | W58: 61 | X58: 88 | Y58: 75 | Z58: 56 | AA58: 60 | AB58: 46 | AC58: 54 | AD58: 63 | AE58: 77 | AF58: 56
A59: - Hardware (units sold) | B59: =SUM('AMAZON - P&L'!B28:B31) -> 78 | C59: =SUM('AMAZON - P&L'!C28:C31) -> 91 | D59: =SUM('AMAZON - P&L'!D28:D31) -> 65 | E59: =SUM('AMAZON - P&L'!E28:E31) -> 38 | F59: =SUM('AMAZON - P&L'!F28:F31) -> 27 | G59: =SUM('AMAZON - P&L'!G28:G31) -> 52 | H59: =SUM('AMAZON - P&L'!H28:H31) -> 74 | I59: =SUM('AMAZON - P&L'!I28:I31) -> 71 | ... AF59: =SUM('AMAZON - P&L'!AF28:AF31) -> 11
A60: - Add-ons (units sold) | B60: =SUM('AMAZON - P&L'!B34:B41) -> 58 | C60: =SUM('AMAZON - P&L'!C34:C41) -> 87 | D60: =SUM('AMAZON - P&L'!D34:D41) -> 95 | E60: =SUM('AMAZON - P&L'!E34:E41) -> 61 | F60: =SUM('AMAZON - P&L'!F34:F41) -> 51 | G60: =SUM('AMAZON - P&L'!G34:G41) -> 49 | H60: =SUM('AMAZON - P&L'!H34:H41) -> 52 | I60: =SUM('AMAZON - P&L'!I34:I41) -> 48 | ... K60: =SUM('AMAZON - P&L'!K34:K41) -> 81 | L60: 1 | M60: =SUM('AMAZON - P&L'!M34:M41) -> 34 | N60: =SUM('AMAZON - P&L'!N34:N41) -> 36 | O60: =SUM('AMAZON - P&L'!O34:O41) -> 28 | P60: =SUM('AMAZON - P&L'!P34:P41) -> 31 | Q60: =SUM('AMAZON - P&L'!Q34:Q41) -> 52 | R60: =SUM('AMAZON - P&L'!R34:R41) -> 40 | S60: =SUM('AMAZON - P&L'!S34:S41) -> 36 | T60: 2 | U60: =SUM('AMAZON - P&L'!U34:U41) -> 40 | V60: =SUM('AMAZON - P&L'!V34:V41) -> 40 | W60: =SUM('AMAZON - P&L'!W34:W41) -> 31 | X60: =SUM('AMAZON - P&L'!X34:X41) -> 49 | Y60: =SUM('AMAZON - P&L'!Y34:Y41) -> 54 | Z60: =SUM('AMAZON - P&L'!Z34:Z41) -> 31 | AA60: =SUM('AMAZON - P&L'!AA34:AA41) -> 31 | AB60: =SUM('AMAZON - P&L'!AB34:AB41) -> 26 | ... AF60: =SUM('AMAZON - P&L'!AF34:AF41) -> 40
A61: Digital Marketplaces Orders | B61: =SUM(B62:B63) -> 2 | C61: =SUM(C62:C63) -> 1 | D61: =SUM(D62:D63) -> 0 | E61: =SUM(E62:E63) -> 0 | F61: =SUM(F62:F63) -> 0 | G61: =SUM(G62:G63) -> 1 | H61: =SUM(H62:H63) -> 1 | I61: =SUM(I62:I63) -> 2 | ... AF61: =SUM(AF62:AF63) -> 0
A62: Rachio Orders | B62: 2 | C62: 1 | D62: 0 | E62: 0 | F62: 0 | G62: 1 | H62: 0 | I62: 2 | J62: 0 | K62: 5 | L62: 1 | M62: 1 | N62: 0 | O62: 0 | P62: 0 | Q62: 0 | R62: 0 | S62: 0 | T62: 0 | U62: 0 | V62: 0 | W62: 0 | X62: 0 | Y62: 0 | Z62: 0 | AA62: 0 | AB62: 0 | AC62: 1 | AD62: 0 | AE62: 0 | AF62: 0
A63: Weatherflow Orders | B63: 0 | C63: 0 | D63: 0 | E63: 0 | F63: 0 | G63: 0 | H63: 1 | I63: 0 | J63: 0 | K63: 0 | L63: 1 | M63: 0 | N63: 0 | O63: 0 | P63: 0 | Q63: 0 | R63: 0 | S63: 0 | T63: 0 | U63: 0 | V63: 0 | W63: 0 | X63: 0 | Y63: 0 | Z63: 2 | AA63: 0 | AB63: 0 | AC63: 0 | AD63: 0 | AE63: 0 | AF63: 0
A64: Total Orders | B64: =SUM(B52+B58+B62+B63) -> 2116 | C64: =SUM(C52+C58+C62+C63) -> 588 | D64: =SUM(D52+D58+D62+D63) -> 494 | E64: =SUM(E52+E58+E62+E63) -> 409 | F64: =SUM(F52+F58+F62+F63) -> 307 | G64: =SUM(G52+G58+G62+G63) -> 329 | H64: =SUM(H52+H58+H62+H63) -> 330 | I64: =SUM(I52+I58+I62+I63) -> 312 | ... AF64: =SUM(AF52+AF58+AF62+AF63) -> 136
A66: B2B Orders
A67: Best Buy | B67: 18 | C67: 22 | D67: 0 | E67: 3 | F67: 21 | G67: 14 | H67: 11 | I67: 11 | J67: 9 | K67: 0 | L67: 6 | M67: 18 | N67: 10 | O67: 4 | P67: 7 | Q67: 4 | R67: 0 | S67: 8 | T67: 60 | U67: 56 | V67: 11 | W67: 18 | X67: 19 | Y67: 0 | Z67: 10 | AA67: 27 | AB67: 23 | AC67: 24 | AD67: 38 | AE67: 39 | AF67: 0
A68: Target | B68: 2 | C68: 8 | D68: 2 | E68: 1 | F68: 1 | G68: 1 | H68: 1 | I68: 2 | J68: 4 | K68: 2 | L68: 1 | M68: 3 | N68: 2 | O68: 3 | P68: 2 | Q68: 6 | R68: 1 | S68: 2 | T68: 0 | U68: 3 | V68: 4 | W68: 12 | X68: 17 | Y68: 14 | Z68: 11 | AA68: 14 | AB68: 11 | AC68: 10 | AD68: 11 | AE68: 14 | AF68: 0
A69: Total Orders | B69: =B67+B68 -> 20 | C69: =C67+C68 -> 30 | D69: =D67+D68 -> 2 | E69: =E67+E68 -> 4 | F69: =F67+F68 -> 22 | G69: =G67+G68 -> 15 | H69: =H67+H68 -> 12 | I69: =I67+I68 -> 13 | ... AF69: =AF67+AF68 -> 0
A71: App Orders
A72: - Google Store | B72: ='App - P&L'!B17 -> 35 | C72: ='App - P&L'!C17 -> 39 | D72: ='App - P&L'!D17 -> 39 | E72: ='App - P&L'!E17 -> 51 | F72: ='App - P&L'!F17 -> 32 | G72: ='App - P&L'!G17 -> 20 | H72: ='App - P&L'!H17 -> 20 | I72: ='App - P&L'!I17 -> 31 | ... AF72: ='App - P&L'!AF17 -> 11
A73: - Apple Store | B73: ='App - P&L'!B14 -> 208 | C73: ='App - P&L'!C14 -> 180 | D73: ='App - P&L'!D14 -> 238 | E73: ='App - P&L'!E14 -> 274 | F73: ='App - P&L'!F14 -> 132 | G73: ='App - P&L'!G14 -> 108 | H73: ='App - P&L'!H14 -> 115 | I73: ='App - P&L'!I14 -> 113 | ... AF73: ='App - P&L'!AF14 -> 144
A74: Total Orders | B74: =sum(B72:B73) -> 243 | C74: =sum(C72:C73) -> 219 | D74: =sum(D72:D73) -> 277 | E74: =sum(E72:E73) -> 325 | F74: =sum(F72:F73) -> 164 | G74: =sum(G72:G73) -> 128 | H74: =sum(H72:H73) -> 135 | I74: =sum(I72:I73) -> 144 | ... AF74: =sum(AF72:AF73) -> 155
A75: Meta Spend EUR | B75: 14427 | C75: 13873.35 | D75: 13491.29 | E75: 11066.51 | F75: 8954.58 | G75: 7594.1 | H75: 7442 | I75: 8115.37 | J75: 8470.55 | K75: 8952.74 | L75: 7835.58 | M75: 5980.95 | N75: 5492.61 | O75: 5507.35 | P75: 0 | Q75: 0 | R75: 0 | S75: 0 | U75: 0 | V75: 0 | W75: 0 | X75: 0 | Y75: 0 | Z75: 0 | AA75: 0 | AB75: 0 | AC75: 0 | AD75: 0 | AE75: 0 | AF75: 0
A76: Currency rate | B76: 1.0846 | C76: 1.0846 | D76: 1.0843 | E76: 1.0855 | F76: 1.0855 | G76: 1.0867 | H76: 1.095 | I76: 1.0944 | J76: 1.0944 | K76: 1.0942 | L76: 1.093 | M76: 1.0928 | N76: 1.0952 | O76: 1.0883 | P76: 1.0899 | Q76: 1.0891 | R76: 1.0882 | S76: 1.0871 | T76: 1.0866 | U76: 1.0937 | V76: 1.0862 | W76: 1.0858 | X76: 1.0858 | Y76: 1.0808 | Z76: 1.0838 | AA76: 1.0832 | AB76: 1.0813 | AC76: 1.0792 | AD76: 1.08 | AE76: 1.08 | AF76: 1.0787
A77: Meta Spend | B77: =B75*B76 -> 15647.524 | C77: =C75*C76 -> 15047.035 | D77: =D75*D76 -> 14628.606 | E77: =E75*E76 -> 12012.697 | F77: =F75*F76 -> 9720.1966 | G77: =G75*G76 -> 8252.5085 | H77: =H75*H76 -> 8148.99 | I77: =I75*I76 -> 8881.4609 | ... AF77: =AF75*AF76 -> 0
A78: Google Spend | B78: =3166.71-253.24 -> 2913.47 | C78: =3408.36-100.94 -> 3307.42 | D78: =3986.76-126.99 -> 3859.77 | E78: 3297.42 | F78: =3108.25-211.69 -> 2896.56 | G78: =3273.1-260.09 -> 3013.01 | H78: =3138.61-145.38 -> 2993.23 | I78: =3304.23-236.77 -> 3067.46 | J78: =3922.15-99.19 -> 3822.96 | K78: =3673.48-42.57 -> 3630.91 | L78: =2933.36-60.28 -> 2873.08 | M78: =2865.1-20.16 -> 2844.94 | N78: 2634.7 | O78: 2511.62 | P78: 2617.8 | Q78: 2644.31 | R78: 2301.66 | S78: 2333.56 | T78: 1951.12 | U78: 1644.55 | V78: 2043.91 | W78: 1894.16 | X78: 3309.39 | Y78: 2664.13 | Z78: 1960.13 | AA78: 1425.05 | AB78: 1553.35 | AC78: 1624.95 | AD78: 1566.94 | AE78: 1676.18 | AF78: 1712.75
A79: Bing Spend | B79: 315.68 | C79: 248.85 | D79: 243.12 | E79: 248.21 | F79: 225.84 | G79: 230.1 | H79: 312 | I79: 296.96 | J79: 248.99 | K79: 240.58 | L79: 181.76 | M79: 290.55 | N79: 303.94 | O79: 208.61 | P79: 237.36 | Q79: 173.44 | R79: 179.26 | S79: 176.66 | T79: 172.1 | U79: 170.55 | V79: 206.94 | W79: 150.73 | X79: 159.54 | Y79: 197.9 | Z79: 164.62 | AA79: 131.18 | AB79: 218.82 | AC79: 243.1 | AD79: 153.59 | AE79: 133.01 | AF79: 152.56
A80: TikTok Spend | B80: 0 | C80: 0 | D80: 0 | E80: 0 | F80: 0 | G80: 0 | H80: 0 | I80: 62.08 | J80: 618.21 | K80: 501.33 | L80: 504.13 | M80: 402.38 | N80: 595.27 | O80: 500.22 | P80: 500.48 | Q80: 493.61 | R80: 500.87 | S80: 490.48 | T80: 510.24 | U80: 501.34 | V80: 407.09 | W80: 527.79 | X80: 596.27 | Y80: 491.54 | Z80: 487.15 | AA80: 500.76 | AB80: 562.64 | AC80: 562.7 | AD80: 481.95 | AE80: 247.35 | AF80: 251.21
A81: Amazon Spend | B81: 1348.28 | C81: 1385.43 | D81: 1102.46 | E81: 752.89 | F81: 700.89 | G81: 2163.8 | H81: 3196.98 | I81: 2585.22 | J81: 2860.98 | K81: 2868.07 | L81: 1575.67 | M81: 1813.72 | N81: 1855.46 | O81: 1949.79 | P81: 2177.64 | Q81: 2457 | R81: 2314.72 | S81: 1846.92 | T81: 1591.02 | U81: 2164.62 | V81: 2214.03 | W81: 1993.47 | X81: 2286.97 | Y81: 2110.61 | Z81: 621.13 | AA81: 415.09 | AB81: 390.6 | AC81: 370.26 | AD81: 359.58 | AE81: 443.94 | AF81: 430.21
A82: Nextdoor Spend
A83: IndieGoGo Spend
A84: Affiliate Fees
A85: Rachio Fees | B85: =B23*0.2 -> 80.662154 | C85: =C23*0.2 -> 44.576677 | D85: =D23*0.2 -> 0 | E85: =E23*0.2 -> 0 | F85: =F23*0.2 -> 0 | G85: =G23*0.2 -> 44.576677 | H85: =H23*0.2 -> 0 | I85: =I23*0.2 -> 89.153354 | ... AF85: =AF23*0.2 -> 0
A86: Weatherflow Fees | B86: =B27*0.15 -> 0 | C86: =C27*0.15 -> 0 | D86: =D27*0.15 -> 0 | E86: =E27*0.15 -> 0 | F86: =F27*0.15 -> 0 | G86: =G27*0.15 -> 0 | H86: =H27*0.15 -> 47.60379 | I86: =I27*0.15 -> 0 | ... AF86: =AF27*0.15 -> 0
A87: Total DTC Spend | B87: =B77+B78+B79+B80+B82+B84 -> 18876.674 | C87: =C77+C78+C79+C80+C82+C84 -> 18603.305 | D87: =D77+D78+D79+D80+D82+D84 -> 18731.496 | E87: =E77+E78+E79+E80+E82+E84 -> 15558.327 | F87: =F77+F78+F79+F80+F82+F84 -> 12842.597 | G87: =G77+G78+G79+G80+G82+G84 -> 11495.618 | H87: =H77+H78+H79+H80+H82+H84 -> 11454.22 | I87: =I77+I78+I79+I80+I82+I84 -> 12307.961 | ... AF87: =AF77+AF78+AF79+AF80+AF82+AF84 -> 2116.52
A88: Total Spend | B88: =SUM(B77:B86) -> 20305.616 | C88: =SUM(C77:C86) -> 20033.312 | D88: =SUM(D77:D86) -> 19833.956 | E88: =SUM(E77:E86) -> 16311.217 | F88: =SUM(F77:F86) -> 13543.487 | G88: =SUM(G77:G86) -> 13703.995 | H88: =SUM(H77:H86) -> 14698.804 | I88: =SUM(I77:I86) -> 14982.334 | ... AF88: =SUM(AF77:AF86) -> 2546.73
A90: App Spend | B90: 268.22 | C90: 268.78 | D90: 311.87 | E90: 283.91 | F90: 285.04 | G90: 281.26 | H90: 126.35 | I90: 0 | J90: 0 | K90: 0 | L90: 0 | M90: 0 | N90: 0 | O90: 0 | P90: 0 | Q90: 0 | R90: 0 | S90: 0 | T90: 0 | U90: 0 | V90: 0 | W90: 27.26 | X90: 27.95 | Y90: 28.67
A91: Meta Spend | B91: 0 | C91: 0 | D91: 0 | E91: 0 | F91: 0 | G91: 0 | H91: 0 | I91: 0 | J91: 0 | K91: 0 | L91: 0 | M91: 0 | N91: 0 | O91: 0 | P91: 0 | Q91: 0 | R91: 0 | S91: 0 | T91: 0 | U91: 0 | V91: 0 | W91: =W76*W90 -> 29.598908 | X91: =X76*X90 -> 30.34811 | Y91: =Y76*Y90 -> 30.986536 | Z91: 0 | AA91: 0 | AB91: 0 | AC91: 0 | AD91: 0 | AE91: 0 | AF91: 0
A92: Apple Spend | B92: 83.14 | C92: 58.72 | D92: 50.98 | E92: 64.64 | F92: 61.9 | G92: 51.55 | H92: 81.9 | I92: 87.85 | J92: 69.57 | K92: 80.04 | L92: 73.72 | M92: 69.87 | N92: 54.8 | O92: 42.72 | P92: 52.88 | Q92: 43.23 | R92: 75.69 | S92: 57.04 | T92: 54.35 | U92: 54.19 | V92: 39.68 | W92: 39.36 | X92: 50.1 | Y92: 45.2 | Z92: 53.65 | AA92: 44.75 | AB92: 28.62 | AC92: 38.82 | AD92: 45.95 | AE92: 47.56 | AF92: 52.2
A93: Google Spend | B93: 0 | C93: 0 | D93: 0 | E93: 0 | F93: 0 | G93: 0 | H93: 0 | I93: 0 | J93: 0 | K93: 0 | L93: 0 | M93: 0 | N93: 0 | O93: 0 | P93: 0 | Q93: 0 | R93: 0 | S93: 0 | T93: 0 | U93: 0 | V93: 0 | W93: 0 | X93: 0 | Y93: 0 | Z93: 0 | AA93: 0 | AB93: 0 | AC93: 0 | AD93: 0 | AE93: 0 | AF93: 0
A94: Total APP Spend | B94: =SUM(B91:B92) -> 83.14 | C94: =SUM(C91:C92) -> 58.72 | D94: =SUM(D91:D92) -> 50.98 | E94: =SUM(E91:E92) -> 64.64 | F94: =SUM(F91:F92) -> 61.9 | G94: =SUM(G91:G92) -> 51.55 | H94: =SUM(H91:H92) -> 81.9 | I94: =SUM(I91:I92) -> 87.85 | ... AF94: =SUM(AF91:AF92) -> 52.2
A96: Blended ROAS | B96: =B31/B88 -> 31.01346 | C96: =C31/C88 -> 6.5132716 | D96: =D31/D88 -> 5.465115 | E96: =E31/E88 -> 5.4616141 | F96: =F31/F88 -> 4.9002891 | G96: =G31/G88 -> 4.6978033 | H96: =H31/H88 -> 4.8635331 | I96: =I31/I88 -> 4.698018 | ... AF96: =AF31/AF88 -> 9.0008207
A97: wROAS | B97: =B8/B87 -> 32.314782 | C97: =C8/C87 -> 5.8020404 | D97: =D8/D87 -> 4.9267486 | E97: =E8/E87 -> 5.1206657 | F97: =F8/F87 -> 4.6720458 | G97: =G8/G87 -> 4.5799171 | H97: =H8/H87 -> 4.6795321 | I97: =I8/I87 -> 4.3304468 | ... AF97: =AF8/AF87 -> 8.7272693
A98: aROAS | B98: =B16/B81 -> 14.350498 | C98: =C16/C81 -> 16.112247 | D98: =D16/D81 -> 14.612303 | E98: =E16/E81 -> 12.507245 | F98: =F16/F81 -> 9.0824523 | G98: =G16/G81 -> 5.3178713 | H98: =H16/H81 -> 5.4959274 | I98: =I16/I81 -> 6.437572 | ... AF98: =AF16/AF81 -> 10.346621
A99: appROAS | B99: =B49/B94 -> 99.088195 | C99: =C49/C94 -> 115.80431 | D99: =D49/D94 -> 150.58042 | E99: =E49/E94 -> 189.54424 | F99: =F49/F94 -> 90.124556 | G99: =G49/G94 -> 55.472163 | H99: =H49/H94 -> 34.449287 | I99: =I49/I94 -> 35.494132 | ... AF99: =AF49/AF94 -> 74.671644
A101: Blended Spend per Unit | B101: =B88/SUM('DTC - P&L'!B59,'DTC - P&L'!B63,'AMAZON - P&L'!B32,'Digital Marketplaces - P&L'!B17,'Digital Marketplaces - P&L'!B129) -> 10.042342 | C101: =C88/SUM('DTC - P&L'!C59,'DTC - P&L'!C63,'AMAZON - P&L'!C32,'Digital Marketplaces - P&L'!C17,'Digital Marketplaces - P&L'!C129) -> 44.817253 | D101: =D88/SUM('DTC - P&L'!D59,'DTC - P&L'!D63,'AMAZON - P&L'!D32,'Digital Marketplaces - P&L'!D17,'Digital Marketplaces - P&L'!D129) -> 52.332337 | E101: =E88/SUM('DTC - P&L'!E59,'DTC - P&L'!E63,'AMAZON - P&L'!E32,'Digital Marketplaces - P&L'!E17,'Digital Marketplaces - P&L'!E129) -> 52.27954 | F101: =F88/SUM('DTC - P&L'!F59,'DTC - P&L'!F63,'AMAZON - P&L'!F32,'Digital Marketplaces - P&L'!F17,'Digital Marketplaces - P&L'!F129) -> 57.145513 | G101: =G88/SUM('DTC - P&L'!G59,'DTC - P&L'!G63,'AMAZON - P&L'!G32,'Digital Marketplaces - P&L'!G17,'Digital Marketplaces - P&L'!G129) -> 58.81543 | H101: =H88/SUM('DTC - P&L'!H59,'DTC - P&L'!H63,'AMAZON - P&L'!H32,'Digital Marketplaces - P&L'!H17,'Digital Marketplaces - P&L'!H129) -> 56.752138 | I101: =I88/SUM('DTC - P&L'!I59,'DTC - P&L'!I63,'AMAZON - P&L'!I32,'Digital Marketplaces - P&L'!I17,'Digital Marketplaces - P&L'!I129) -> 57.846851 | ... AF101: =AF88/SUM('DTC - P&L'!AF59,'DTC - P&L'!AF63,'AMAZON - P&L'!AF32,'Digital Marketplaces - P&L'!AF17,'Digital Marketplaces - P&L'!AF129) -> 43.909138
A102: wSPU | B102: =B87/SUM('DTC - P&L'!B59,'DTC - P&L'!B63) -> 9.7202236 | C102: =C87/SUM('DTC - P&L'!C59,'DTC - P&L'!C63) -> 52.403677 | D102: =D87/SUM('DTC - P&L'!D59,'DTC - P&L'!D63) -> 59.654445 | E102: =E87/SUM('DTC - P&L'!E59,'DTC - P&L'!E63) -> 56.782214 | F102: =F87/SUM('DTC - P&L'!F59,'DTC - P&L'!F63) -> 61.155222 | G102: =G87/SUM('DTC - P&L'!G59,'DTC - P&L'!G63) -> 63.864547 | H102: =H87/SUM('DTC - P&L'!H59,'DTC - P&L'!H63) -> 62.251196 | I102: =I87/SUM('DTC - P&L'!I59,'DTC - P&L'!I63) -> 66.171833 | ... AF102: =AF87/SUM('DTC - P&L'!AF59,'DTC - P&L'!AF63) -> 45.03234
A103: aSPU | B103: =B81/'AMAZON - P&L'!B32 -> 17.285641 | C103: =C81/'AMAZON - P&L'!C32 -> 15.224505 | D103: =D81/'AMAZON - P&L'!D32 -> 16.960923 | E103: =E81/'AMAZON - P&L'!E32 -> 19.812895 | F103: =F81/'AMAZON - P&L'!F32 -> 25.958889 | G103: =G81/'AMAZON - P&L'!G32 -> 41.611538 | H103: =H81/'AMAZON - P&L'!H32 -> 43.202432 | I103: =I81/'AMAZON - P&L'!I32 -> 36.411549 | ... AF103: =AF81/'AMAZON - P&L'!AF32 -> 39.11
A104: appCAC | B104: =B94/B74 -> 0.34213992 | C104: =C94/C74 -> 0.26812785 | D104: =D94/D74 -> 0.18404332 | E104: =E94/E74 -> 0.19889231 | F104: =F94/F74 -> 0.37743902 | G104: =G94/G74 -> 0.40273437 | H104: =H94/H74 -> 0.60666667 | I104: =I94/I74 -> 0.61006944 | ... AF104: =AF94/AF74 -> 0.33677419
A106: Web CR | B106: 0.0754 | C106: 0.0272 | D106: 0.0236 | E106: 0.0269 | F106: 0.0264 | G106: 0.026 | H106: 0.0218 | I106: 0.0182 | J106: 0.0224 | K106: 0.0198 | L106: 0.0183 | M106: 0.0148 | N106: 0.0118 | O106: 0.0139 | P106: 0.0167 | Q106: 0.0219 | R106: 0.0177 | S106: 0.0186 | T106: 0.0147 | U106: 0.0193 | V106: 0.0186 | W106: 0.0223 | X106: 0.017 | Y106: 0.0229 | Z106: 0.0234 | AA106: 0.0188 | AB106: 0.019 | AC106: 0.019 | AD106: 0.0134 | AE106: 0.0207 | AF106: 0.0177
A107: Web AOV | B107: =B8/B52 -> 311.06354 | C107: =C8/C52 -> 259.46425 | D107: =D8/D52 -> 265.95207 | E107: =E8/E52 -> 255.34933 | F107: =F8/F52 -> 242.91984 | G107: =G8/G52 -> 246.02327 | H107: =H8/H52 -> 257.69418 | I107: =I8/I52 -> 266.49485 | ... AF107: =AF8/AF52 -> 230.893
A108: fAOV | B108: 310.35 | C108: 255.77 | D108: 262.65 | E108: 265.26 | F108: 252.78 | G108: 249.95 | H108: 258.33 | I108: 274.97 | J108: 252.55 | K108: 251.41 | L108: 292.25 | M108: 307.6 | N108: 290.79 | O108: 306.21 | P108: 296.55 | Q108: 283.33 | R108: 268.14 | S108: 260.28 | T108: 268.81 | U108: 276.66 | V108: 289.45 | W108: 320.68 | X108: 310.36 | Y108: 321.08 | Z108: 283.76 | AA108: 300.9 | AB108: 296.02 | AC108: 282.06 | AD108: 297.1 | AE108: 264.89 | AF108: 255.57
A109: rAOV | B109: 312.09 | C109: 266.27 | D109: 270.41 | E109: 219.33 | F109: 185.21 | G109: 204.46 | H109: 250.83 | I109: 221.62 | J109: 176.91 | K109: 206.29 | L109: 200.47 | M109: 151.35 | N109: 183.84 | O109: 199.96 | P109: 144.2 | Q109: 205.31 | R109: 256.94 | S109: 147.65 | T109: 232.04 | U109: 155.25 | V109: 157.03 | W109: 126.02 | X109: 156.91 | Y109: 135.4 | Z109: 158.43 | AA109: 142.51 | AB109: 118.5 | AC109: 203.58 | AD109: 306.48 | AE109: 192.71 | AF109: 132.19
A111: Customers
A112: Returning | B112: 0.289 | C112: 0.198 | D112: 0.16 | E112: 0.222 | F112: 0.16 | G112: 0.126 | H112: 0.198 | I112: 0.156 | J112: 0.16 | K112: 0.14 | L112: 0.224 | M112: 0.246 | N112: 0.222 | O112: 0.247 | P112: 0.233 | Q112: 0.235 | R112: 0.284 | S112: 0.239 | T112: 0.27 | U112: 0.266 | V112: 0.231 | W112: 0.271 | X112: 0.295 | Y112: 0.285 | Z112: 0.306 | AA112: 0.346 | AB112: 0.286 | AC112: 0.294 | AD112: 0.125 | AE112: 0.184 | AF112: 0.192
...

Sheet DTC - P&L
A1: MARCH | B1: 45352 | C1: 45353 | D1: 45354 | E1: 45355 | F1: 45356 | G1: 45357 | H1: 45358 | I1: 45359 | J1: 45360 | K1: 45361 | L1: 45362 | M1: 45363 | N1: 45364 | O1: 45365 | P1: 45366 | Q1: 45367 | R1: 45368 | S1: 45369 | T1: 45370 | U1: 45371 | V1: 45372 | W1: 45373 | X1: 45374 | Y1: 45375 | Z1: 45376 | AA1: 45377 | AB1: 45378 | AC1: 45379 | AD1: 45380 | AE1: 45381 | AF1: 45382
A2: DAY | B2: FRI | C2: SAT | D2: SUN | E2: MON | F2: TUE | G2: WED | H2: THU | I2: FRI | J2: SAT | K2: SUN | L2: MON | M2: TUE | N2: WED | O2: THU | P2: FRI | Q2: SAT | R2: SUN | S2: MON | T2: TUE | U2: WED | V2: THU | W2: FRI | X2: SAT | Y2: SUN | Z2: MON | AA2: TUE | AB2: WED | AC2: THU | AD2: FRI | AE2: SAT | AF2: SUN
A3: COMMENT
A4: Orders
A5: Meta | B5: 458 | C5: 137 | D5: 146 | E5: 114 | F5: 84 | G5: 70 | H5: 69 | I5: 87 | J5: 86 | K5: 83 | L5: 60 | M5: 39 | N5: 27 | O5: 35 | P5: 18 | Q5: 4 | R5: 5 | S5: 3 | T5: 2 | U5: 3 | V5: 0 | W5: 0 | X5: 0 | Y5: 0 | Z5: 0 | AA5: 0 | AB5: 0 | AC5: 0 | AD5: 0 | AE5: 0 | AF5: 0 | AG5: =SUM(B5:AF5) -> 1530
A6: Google | B6: 137 | C6: 102 | D6: 89 | E6: 79 | F6: 84 | G6: 61 | H6: 49 | I6: 55 | J6: 87 | K6: 76 | L6: 50 | M6: 25 | N6: 22 | O6: 27 | P6: 38 | Q6: 40 | R6: 25 | S6: 31 | T6: 22 | U6: 26 | V6: 23 | W6: 26 | X6: 39 | Y6: 46 | Z6: 37 | AA6: 25 | AB6: 21 | AC6: 27 | AD6: 22 | AE6: 35 | AF6: 28 | AG6: =SUM(B6:AF6) -> 1454
A7: TikTok | B7: 0 | C7: 0 | D7: 0 | E7: 0 | F7: 0 | G7: 0 | H7: 0 | I7: 0 | J7: 0 | K7: 1 | L7: 2 | M7: 2 | N7: 0 | O7: 2 | P7: 0 | Q7: 0 | R7: 2 | S7: 1 | T7: 0 | U7: 1 | V7: 0 | W7: 1 | X7: 0 | Y7: 0 | Z7: 0 | AA7: 0 | AB7: 0 | AC7: 1 | AD7: 0 | AE7: 0 | AF7: 1 | AG7: =SUM(B7:AF7) -> 14
A8: Bing | B8: 40 | C8: 12 | D8: 30 | E8: 24 | F8: 14 | G8: 10 | H8: 4 | I8: 6 | J8: 20 | K8: 4 | L8: 4 | M8: 10 | N8: 8 | O8: 4 | P8: 2 | Q8: 8 | R8: 10 | S8: 0 | T8: 2 | U8: 8 | V8: 14 | W8: 20 | X8: 10 | Y8: 10 | Z8: 6 | AA8: 6 | AB8: 0 | AC8: 6 | AD8: 12 | AE8: 8 | AF8: 10 | AG8: =SUM(B8:AF8) -> 322
A9: Email | B9: 396 | C9: 72 | D9: 25 | E9: 23 | F9: 20 | G9: 12 | H9: 13 | I9: 9 | J9: 4 | K9: 0 | L9: 0 | M9: 1 | N9: 4 | O9: 2 | P9: 1 | Q9: 4 | R9: 1 | S9: 1 | T9: 0 | U9: 3 | V9: 0 | W9: 1 | X9: 4 | Y9: 2 | Z9: 1 | AA9: 0 | AB9: 2 | AC9: 2 | AD9: 2 | AE9: 2 | AF9: 1 | AG9: =SUM(B9:AF9) -> 608
A10: Nextdoor | B10: - | C10: - | D10: - | E10: - | F10: - | G10: - | H10: - | I10: - | J10: - | K10: - | L10: - | M10: - | N10: - | O10: - | P10: - | Q10: - | R10: - | S10: - | T10: - | U10: - | V10: - | W10: - | X10: - | Y10: - | Z10: - | AA10: - | AB10: - | AC10: - | AD10: - | AE10: - | AF10: - | AG10: =SUM(B10:AF10) -> 0
A11: Affiliates (Refersion) | B11: - | C11: - | D11: - | E11: - | F11: - | G11: - | H11: - | I11: - | J11: - | K11: - | L11: - | M11: - | N11: - | O11: - | P11: - | Q11: - | R11: - | S11: - | T11: - | U11: - | V11: - | W11: - | X11: - | Y11: - | Z11: - | AA11: - | AB11: - | AC11: - | AD11: - | AE11: - | AF11: - | AG11: =SUM(B11:AF11) -> 0
A12: All | B12: =SUM(B5:B11) -> 1031 | C12: =SUM(C5:C11) -> 323 | D12: =SUM(D5:D11) -> 290 | E12: =SUM(E5:E11) -> 240 | F12: =SUM(F5:F11) -> 202 | G12: =SUM(G5:G11) -> 153 | H12: =SUM(H5:H11) -> 135 | I12: =SUM(I5:I11) -> 157 | ... AF12: =SUM(AF5:AF11) -> 40 | AG12: =SUM(B12:AF12) -> 3928
A14: Revenue | B14: 130631.13 | C14: 31702.33 | D14: 36663.08 | E14: 26831.34 | F14: 18566.01 | G14: 15077.35 | H14: 16977.97 | I14: 22535.23 | J14: 19812.94 | K14: 21641.23 | L14: 16677.16 | M14: 8900.25 | N14: 7417.65 | O14: 8918.9 | P14: 5019.56 | Q14: 363.27 | R14: 1698.83 | S14: 790.14 | T14: 335.68 | U14: 337.11 | V14: 0 | W14: 0 | X14: 0 | Y14: 0 | Z14: 0 | AA14: 0 | AB14: 0 | AC14: 0 | AD14: 0 | AE14: 0 | AF14: 0
A15: Meta | B15: =B14*Summary!B76 -> 141682.52 | C15: =C14*Summary!C76 -> 34384.347 | D15: =D14*Summary!D76 -> 39753.778 | E15: =E14*Summary!E76 -> 29125.42 | F15: =F14*Summary!F76 -> 20153.404 | G15: =G14*Summary!G76 -> 16384.556 | H15: =H14*Summary!H76 -> 18590.877 | I15: =I14*Summary!I76 -> 24662.556 | ... AF15: =AF14*Summary!AF76 -> 0 | AG15: =SUM(B15:AF15) -> 425192.69
A16: Google | B16: 36240.17 | C16: 24265.81 | D16: 21831.79 | E16: 19070.15 | F16: 18701.99 | G16: 13220.28 | H16: 11961.73 | I16: 13976.93 | J16: 20899.82 | K16: 17653.64 | L16: 15254.03 | M16: 6773.81 | N16: 6500.22 | O16: 8224.43 | P16: 11274.08 | Q16: 11229.61 | R16: 7499.54 | S16: 9101.73 | T16: 7088.92 | U16: 6561.49 | V16: 6688.27 | W16: 7440.97 | X16: 12014.82 | Y16: 13776.81 | Z16: 10611.92 | AA16: 6477.18 | AB16: 6083.17 | AC16: 7892.69 | AD16: 6440.17 | AE16: 9942.06 | AF16: 8835.98 | AG16: =SUM(B16:AF16) -> 383534.21
A17: TikTok | B17: 0 | C17: 0 | D17: 0 | E17: 0 | F17: 0 | G17: 0 | H17: 0 | I17: 0 | J17: 0 | K17: 188 | L17: 697.12 | M17: 357 | N17: 0 | O17: 691.82 | P17: 0 | Q17: 0 | R17: 399.11 | S17: 292.6 | T17: 0 | U17: 27.44 | V17: 0 | W17: 51.19 | X17: 0 | Y17: 0 | Z17: 0 | AA17: 0 | AB17: 0 | AC17: 331.9 | AD17: 0 | AE17: 0 | AF17: 268 | AG17: =SUM(B17:AF17) -> 3304.18
A18: Bing | B18: 5020 | C18: 1506 | D18: 3765 | E18: 3012 | F18: 1757 | G18: 1255 | H18: 502 | I18: 753 | J18: 2510 | K18: 502 | L18: 502 | M18: 1255 | N18: 1004 | O18: 502 | P18: 251 | Q18: 1004 | R18: 1255 | S18: 0 | T18: 251 | U18: 1004 | V18: 1757 | W18: 2510 | X18: 1255 | Y18: 1255 | Z18: 753 | AA18: 753 | AB18: 0 | AC18: 753 | AD18: 1506 | AE18: 1004 | AF18: 1255 | AG18: =SUM(B18:AF18) -> 40411
A19: Email | B19: 127383.34 | C19: 22901.17 | D19: 7704.1 | E19: 6917.28 | F19: 5509.62 | G19: 3963.62 | H19: 4184.23 | I19: 2186.63 | J19: 909.46 | K19: 0 | L19: 0 | M19: 112.25 | N19: 1409.11 | O19: 449.88 | P19: 411.85 | Q19: 1484.01 | R19: 294.34 | S19: 286 | T19: 0 | U19: 1241.79 | V19: 0 | W19: 354.1 | X19: 1488.71 | Y19: 512.85 | Z19: 354.04 | AA19: 0 | AB19: 425.64 | AC19: 106.51 | AD19: 713.03 | AE19: 118.98 | AF19: 41.48 | AG19: =SUM(B19:AF19) -> 191464.02
A20: Nextdoor | B20: - | C20: - | D20: - | E20: - | F20: - | G20: - | H20: - | I20: - | J20: - | K20: - | L20: - | M20: - | N20: - | O20: - | P20: - | Q20: - | R20: - | S20: - | T20: - | U20: - | V20: - | W20: - | X20: - | Y20: - | Z20: - | AA20: - | AB20: - | AC20: - | AD20: - | AE20: - | AF20: - | AG20: =SUM(B20:AF20) -> 0
A21: Affiliates (Refersion) | B21: - | C21: - | D21: - | E21: - | F21: - | G21: - | H21: - | I21: - | J21: - | K21: - | L21: - | M21: - | N21: - | O21: - | P21: - | Q21: - | R21: - | S21: - | T21: - | U21: - | V21: - | W21: - | X21: - | Y21: - | Z21: - | AA21: - | AB21: - | AC21: - | AD21: - | AE21: - | AF21: - | AG21: =SUM(B21:AF21) -> 0
A22: All | B22: =SUM(B15:B21) -> 310326.03 | C22: =SUM(C15:C21) -> 83057.327 | D22: =SUM(D15:D21) -> 73054.668 | E22: =SUM(E15:E21) -> 58124.85 | F22: =SUM(F15:F21) -> 46122.014 | G22: =SUM(G15:G21) -> 34823.456 | H22: =SUM(H15:H21) -> 35238.837 | I22: =SUM(I15:I21) -> 41579.116 | ... AF22: =SUM(AF15:AF21) -> 10400.46 | AG22: =SUM(B22:AF22) -> 1043906.1
A24: Media Cost
A25: Meta | B25: =Summary!B77 -> 15647.524 | C25: =Summary!C77 -> 15047.035 | D25: =Summary!D77 -> 14628.606 | E25: =Summary!E77 -> 12012.697 | F25: =Summary!F77 -> 9720.1966 | G25: =Summary!G77 -> 8252.5085 | H25: =Summary!H77 -> 8148.99 | I25: =Summary!I77 -> 8881.4609 | ... AF25: =Summary!AF77 -> 0 | AG25: =SUM(B25:AF25) -> 138514.7
A26: Google | B26: =Summary!B78 -> 2913.47 | C26: =Summary!C78 -> 3307.42 | D26: =Summary!D78 -> 3859.77 | E26: =Summary!E78 -> 3297.42 | F26: =Summary!F78 -> 2896.56 | G26: =Summary!G78 -> 3013.01 | H26: =Summary!H78 -> 2993.23 | I26: =Summary!I78 -> 3067.46 | ... AF26: =Summary!AF78 -> 1712.75 | AG26: =SUM(B26:AF26) -> 78590.49
A27: TikTok | B27: =Summary!B80 -> 0 | C27: =Summary!C80 -> 0 | D27: =Summary!D80 -> 0 | E27: =Summary!E80 -> 0 | F27: =Summary!F80 -> 0 | G27: =Summary!G80 -> 0 | H27: =Summary!H80 -> 0 | I27: =Summary!I80 -> 62.08 | ... O27: =Summary!O80 -> 500.22 | P27: =Summary!P81 -> 2177.64 | Q27: =Summary!Q80 -> 493.61 | R27: =Summary!R80 -> 500.87 | S27: =Summary!S80 -> 490.48 | T27: =Summary!T80 -> 510.24 | U27: =Summary!U80 -> 501.34 | V27: =Summary!V80 -> 407.09 | W27: =Summary!W80 -> 527.79 | X27: =Summary!X80 -> 596.27 | ... AF27: =Summary!AF80 -> 251.21 | AG27: =SUM(B27:AF27) -> 12974.25
A28: Bing | B28: =Summary!B79 -> 315.68 | C28: =Summary!C79 -> 248.85 | D28: =Summary!D79 -> 243.12 | E28: =Summary!E79 -> 248.21 | F28: =Summary!F79 -> 225.84 | G28: =Summary!G79 -> 230.1 | H28: =Summary!H79 -> 312 | I28: =Summary!I79 -> 296.96 | ... AF28: =Summary!AF79 -> 152.56 | AG28: =SUM(B28:AF28) -> 6616.55
A29: Nextdoor | B29: - | C29: - | D29: - | E29: - | F29: - | G29: - | H29: - | I29: - | J29: - | K29: - | L29: - | M29: - | N29: - | O29: - | P29: - | Q29: - | R29: - | S29: - | T29: - | U29: - | V29: - | W29: - | X29: - | Y29: - | Z29: - | AA29: - | AB29: - | AC29: - | AD29: - | AE29: - | AF29: - | AG29: =SUM(B29:AF29) -> 0
A30: Affiliate Fee (20%) | B30: - | C30: - | D30: - | E30: - | F30: - | G30: - | H30: - | I30: - | J30: - | K30: - | L30: - | M30: - | N30: - | O30: - | P30: - | Q30: - | R30: - | S30: - | T30: - | U30: - | V30: - | W30: - | X30: - | Y30: - | Z30: - | AA30: - | AB30: - | AC30: - | AD30: - | AE30: - | AF30: - | AG30: =SUM(B30:AF30) -> 0
A31: All | B31: =SUM(B25:B30) -> 18876.674 | C31: =SUM(C25:C30) -> 18603.305 | D31: =SUM(D25:D30) -> 18731.496 | E31: =SUM(E25:E30) -> 15558.327 | F31: =SUM(F25:F30) -> 12842.597 | G31: =SUM(G25:G30) -> 11495.618 | H31: =SUM(H25:H30) -> 11454.22 | I31: =SUM(I25:I30) -> 12307.961 | ... AF31: =SUM(AF25:AF30) -> 2116.52 | AG31: =SUM(B31:AF31) -> 236695.99
A36: Revenue
A37: Revenue Woocommerce (Platform) | B37: =Summary!B8 -> 609995.61 | C37: =Summary!C8 -> 107937.13 | D37: =Summary!D8 -> 92285.37 | E37: =Summary!E8 -> 79668.99 | F37: =Summary!F8 -> 60001.2 | G37: =Summary!G8 -> 52648.98 | H37: =Summary!H8 -> 53600.39 | I37: =Summary!I8 -> 53298.97 | ... AF37: =Summary!AF8 -> 18471.44 | AG37: =SUM(B37:AF37) -> 1787869.3
A38: SUM | B38: =SUM(B37) -> 609995.61 | C38: =SUM(C37) -> 107937.13 | D38: =SUM(D37) -> 92285.37 | E38: =SUM(E37) -> 79668.99 | F38: =SUM(F37) -> 60001.2 | G38: =SUM(G37) -> 52648.98 | H38: =SUM(H37) -> 53600.39 | I38: =SUM(I37) -> 53298.97 | ... AF38: =SUM(AF37) -> 18471.44 | AG38: =SUM(B38:AF38) -> 1787869.3
A40: Orders
A41: Orders Woocommerce (Platform) | B41: =Summary!B52 -> 1961 | C41: =Summary!C52 -> 416 | D41: =Summary!D52 -> 347 | E41: =Summary!E52 -> 312 | F41: =Summary!F52 -> 247 | G41: =Summary!G52 -> 214 | H41: =Summary!H52 -> 208 | I41: =Summary!I52 -> 200 | ... AF41: =Summary!AF52 -> 80 | AG41: =SUM(B41:AF41) -> 6487
A42: SUM | B42: =SUM(B41) -> 1961 | C42: =SUM(C41) -> 416 | D42: =SUM(D41) -> 347 | E42: =SUM(E41) -> 312 | F42: =SUM(F41) -> 247 | G42: =SUM(G41) -> 214 | H42: =SUM(H41) -> 208 | I42: =SUM(I41) -> 200 | ... AF42: =SUM(AF41) -> 80 | AG42: =SUM(B42:AF42) -> 6487
A44: Breakdown
A45: - Hardware | B45: =Summary!B9 -> 530409.79 | C45: =Summary!C9 -> 88002.25 | D45: =Summary!D9 -> 75538.45 | E45: =Summary!E9 -> 64103.35 | F45: =Summary!F9 -> 47621.15 | G45: =Summary!G9 -> 40596.8 | H45: =Summary!H9 -> 42030.65 | I45: =Summary!I9 -> 42613.85 | ... AF45: =Summary!AF9 -> 13825.11 | AG45: =SUM(B45:AF45) -> 1448395.5
A46: - Add-ons | B46: =Summary!B10 -> 9746.98 | C46: =Summary!C10 -> 5478.6 | D46: =Summary!D10 -> 4169.45 | E46: =Summary!E10 -> 4300.95 | F46: =Summary!F10 -> 3500.8 | G46: =Summary!G10 -> 3624.5 | H46: =Summary!H10 -> 3175.6 | I46: =Summary!I10 -> 2564.55 | ... AF46: =Summary!AF10 -> 1741.99 | AG46: =SUM(B46:AF46) -> 95441.09
A47: - Merch | B47: =Summary!B11 -> 0 | C47: =Summary!C11 -> 0 | D47: =Summary!D11 -> 0 | E47: =Summary!E11 -> 0 | F47: =Summary!F11 -> 0 | G47: =Summary!G11 -> 184.94 | H47: =Summary!H11 -> 0 | I47: =Summary!I11 -> 0 | ... AF47: =Summary!AF11 -> 0 | AG47: =SUM(B47:AF47) -> 334.9
A48: - Seeds | B48: =Summary!B12 -> 434.04 | C48: =Summary!C12 -> 310.57 | D48: =Summary!D12 -> 225 | E48: =Summary!E12 -> 357.48 | F48: =Summary!F12 -> 360.4 | G48: =Summary!G12 -> 247.87 | H48: =Summary!H12 -> 244.33 | I48: =Summary!I12 -> 108.94 | ... AF48: =Summary!AF12 -> 260.1 | AG48: =SUM(B48:AF48) -> 8392.71
A49: - Yearly Pro Subscription | B49: =Summary!B13 | C49: =Summary!C13 | D49: =Summary!D13 | E49: =Summary!E13 | F49: =Summary!F13 | G49: =Summary!G13 | H49: =Summary!H13 | I49: =Summary!I13 | ... AF49: =Summary!AF13 -> 120 | AG49: =SUM(B49:AF49) -> 1223.33
A50: - Taxes | B50: =Summary!B14 -> 37467.8 | C50: =Summary!C14 -> 6623.71 | D50: =Summary!D14 -> 5640.47 | E50: =Summary!E14 -> 4787.21 | F50: =Summary!F14 -> 3534.85 | G50: =Summary!G14 -> 3154.87 | H50: =Summary!H14 -> 3158.81 | I50: =Summary!I14 -> 3131.63 | ... AF50: =Summary!AF14 -> 1079.24 | AG50: =SUM(B50:AF50) -> 108421.8
A51: - Shipping | B51: =Summary!B15 -> 31937 | C51: =Summary!C15 -> 7522 | D51: =Summary!D15 -> 6712 | E51: =Summary!E15 -> 6120 | F51: =Summary!F15 -> 4984 | G51: =Summary!G15 -> 4840 | H51: =Summary!H15 -> 4991 | I51: =Summary!I15 -> 4880 | ... AF51: =Summary!AF15 -> 1445 | AG51: =SUM(B51:AF51) -> 125660
A52: SUM | B52: =SUM(B45:B51) -> 609995.61 | C52: =SUM(C45:C51) -> 107937.13 | D52: =SUM(D45:D51) -> 92285.37 | E52: =SUM(E45:E51) -> 79668.99 | F52: =SUM(F45:F51) -> 60001.2 | G52: =SUM(G45:G51) -> 52648.98 | H52: =SUM(H45:H51) -> 53600.39 | I52: =SUM(I45:I51) -> 53298.97 | ... AF52: =SUM(AF45:AF51) -> 18471.44 | AG52: =SUM(B52:AF52) -> 1787869.3
A54: Units Sold (Gross)
A55: SKU 1 - Blue | B55: 40 | C55: 37 | D55: 41 | E55: 37 | F55: 28 | G55: 28 | H55: 27 | I55: 23 | J55: 31 | K55: 24 | L55: 22 | M55: 16 | N55: 5 | O55: 11 | P55: 7 | Q55: 9 | R55: 11 | S55: 14 | T55: 6 | U55: 7 | V55: 6 | W55: 9 | X55: 13 | Y55: 16 | Z55: 11 | AA55: 8 | AB55: 7 | AC55: 8 | AD55: 9 | AE55: 6 | AF55: 6 | AG55: =SUM(B55:AF55) -> 523
A56: SKU 2 - Yellow | B56: 0 | C56: 0 | D56: 0 | E56: 0 | F56: 0 | G56: 0 | H56: 0 | I56: 0 | J56: 0 | K56: 0 | L56: 0 | M56: 0 | N56: 0 | O56: 0 | P56: 0 | Q56: 0 | R56: 0 | S56: 0 | T56: 0 | U56: 0 | V56: 0 | W56: 0 | X56: 0 | Y56: 0 | Z56: 0 | AA56: 0 | AB56: 0 | AC56: 0 | AD56: 0 | AE56: 0 | AF56: 0 | AG56: =SUM(B56:AF56) -> 0
A57: SKU 3 - Blue w/ Solar | B57: 125 | C57: 99 | D57: 110 | E57: 114 | F57: 108 | G57: 93 | H57: 83 | I57: 81 | J57: 95 | K57: 79 | L57: 51 | M57: 31 | N57: 31 | O57: 31 | P57: 35 | Q57: 41 | R57: 27 | S57: 24 | T57: 23 | U57: 18 | V57: 32 | W57: 66 | X57: 40 | Y57: 51 | Z57: 32 | AA57: 28 | AB57: 28 | AC57: 40 | AD57: 24 | AE57: 40 | AF57: 34 | AG57: =SUM(B57:AF57) -> 1714
A58: SKU 4 - Yellow w/ Solar | B58: 0 | C58: 0 | D58: 0 | E58: 0 | F58: 0 | G58: 0 | H58: 0 | I58: 0 | J58: 0 | K58: 0 | L58: 0 | M58: 0 | N58: 0 | O58: 0 | P58: 0 | Q58: 0 | R58: 0 | S58: 0 | T58: 0 | U58: 0 | V58: 0 | W58: 0 | X58: 0 | Y58: 0 | Z58: 0 | AA58: 0 | AB58: 0 | AC58: 0 | AD58: 0 | AE58: 0 | AF58: 0 | AG58: =SUM(B58:AF58) -> 0
A59: SUM (SKU 1 - SKU 4) | B59: =SUM(B55:B58) -> 165 | C59: =SUM(C55:C58) -> 136 | D59: =SUM(D55:D58) -> 151 | E59: =SUM(E55:E58) -> 151 | F59: =SUM(F55:F58) -> 136 | G59: =SUM(G55:G58) -> 121 | H59: =SUM(H55:H58) -> 110 | I59: =SUM(I55:I58) -> 104 | ... AF59: =SUM(AF55:AF58) -> 40 | AG59: =SUM(B59:AF59) -> 2237
A61: SKU 5 - HBF | B61: 502 | C61: 56 | D61: 36 | E61: 29 | F61: 19 | G61: 10 | H61: 23 | I61: 32 | J61: 17 | K61: 22 | L61: 26 | M61: 10 | N61: 11 | O61: 8 | P61: 6 | Q61: 6 | R61: 7 | S61: 5 | T61: 6 | U61: 10 | V61: 3 | W61: 6 | X61: 9 | Y61: 5 | Z61: 8 | AA61: 4 | AB61: 2 | AC61: 3 | AD61: 5 | AE61: 2 | AF61: 1 | AG61: =SUM(B61:AF61) -> 889
A62: SKU 6 - HBF w/ Solar | B62: 1275 | C62: 163 | D62: 127 | E62: 94 | F62: 55 | G62: 49 | H62: 51 | I62: 50 | J62: 78 | K62: 67 | L62: 48 | M62: 31 | N62: 20 | O62: 33 | P62: 16 | Q62: 25 | R62: 19 | S62: 13 | T62: 14 | U62: 19 | V62: 14 | W62: 22 | X62: 18 | Y62: 23 | Z62: 18 | AA62: 11 | AB62: 12 | AC62: 10 | AD62: 6 | AE62: 7 | AF62: 6 | AG62: =SUM(B62:AF62) -> 2394
A63: SUM (SKU 5 - SKU 6) | B63: =SUM(B61:B62) -> 1777 | C63: =SUM(C61:C62) -> 219 | D63: =SUM(D61:D62) -> 163 | E63: =SUM(E61:E62) -> 123 | F63: =SUM(F61:F62) -> 74 | G63: =SUM(G61:G62) -> 59 | H63: =SUM(H61:H62) -> 74 | I63: =SUM(I61:I62) -> 82 | ... AF63: =SUM(AF61:AF62) -> 7 | AG63: =SUM(B63:AF63) -> 3283
A65: Wall Mount | B65: 173 | C65: 123 | D65: 143 | E65: 126 | F65: 106 | G65: 107 | H65: 89 | I65: 80 | J65: 99 | K65: 101 | L65: 43 | M65: 16 | N65: 13 | O65: 13 | P65: 9 | Q65: 15 | R65: 16 | S65: 17 | T65: 7 | U65: 6 | V65: 11 | W65: 41 | X65: 21 | Y65: 20 | Z65: 18 | AA65: 9 | AB65: 15 | AC65: 14 | AD65: 15 | AE65: 14 | AF65: 10 | AG65: =SUM(B65:AF65) -> 1490
A66: Suet Ball Holder | B66: 40 | C66: 31 | D66: 24 | E66: 28 | F66: 22 | G66: 22 | H66: 20 | I66: 27 | J66: 26 | K66: 30 | L66: 15 | M66: 11 | N66: 4 | O66: 8 | P66: 5 | Q66: 12 | R66: 8 | S66: 14 | T66: 11 | U66: 11 | V66: 9 | W66: 13 | X66: 12 | Y66: 13 | Z66: 11 | AA66: 11 | AB66: 9 | AC66: 8 | AD66: 9 | AE66: 9 | AF66: 8 | AG66: =SUM(B66:AF66) -> 481
A67: 3-in-1 Nutrition Set - Blue | B67: 45 | C67: 26 | D67: 27 | E67: 22 | F67: 20 | G67: 20 | H67: 21 | I67: 22 | J67: 26 | K67: 25 | L67: 18 | M67: 10 | N67: 2 | O67: 8 | P67: 7 | Q67: 10 | R67: 7 | S67: 8 | T67: 5 | U67: 3 | V67: 5 | W67: 13 | X67: 10 | Y67: 14 | Z67: 5 | AA67: 6 | AB67: 7 | AC67: 9 | AD67: 9 | AE67: 11 | AF67: 4 | AG67: =SUM(B67:AF67) -> 425
A68: 3-in-1 Nutrition Set - Yellow | B68: 2 | C68: 1 | D68: 0 | E68: 1 | F68: 0 | G68: 1 | H68: 4 | I68: 1 | J68: 3 | K68: 1 | L68: 0 | M68: 1 | N68: 0 | O68: 4 | P68: 4 | Q68: 3 | R68: 2 | S68: 0 | T68: 1 | U68: 0 | V68: 2 | W68: 0 | X68: 1 | Y68: 0 | Z68: 1 | AA68: 0 | AB68: 1 | AC68: 3 | AD68: 0 | AE68: 1 | AF68: 1 | AG68: =SUM(B68:AF68) -> 39
A69: Solar Roof Single - Blue | B69: 24 | C69: 14 | D69: 15 | E69: 14 | F69: 14 | G69: 12 | H69: 13 | I69: 8 | J69: 19 | K69: 12 | L69: 13 | M69: 8 | N69: 10 | O69: 3 | P69: 7 | Q69: 7 | R69: 2 | S69: 6 | T69: 4 | U69: 5 | V69: 3 | W69: 6 | X69: 11 | Y69: 5 | Z69: 7 | AA69: 5 | AB69: 10 | AC69: 7 | AD69: 4 | AE69: 5 | AF69: 7 | AG69: =SUM(B69:AF69) -> 280
A70: Solar Roof Single - Yellow | B70: 8 | C70: 6 | D70: 3 | E70: 6 | F70: 4 | G70: 4 | H70: 0 | I70: 0 | J70: 4 | K70: 4 | L70: 2 | M70: 4 | N70: 0 | O70: 1 | P70: 2 | Q70: 5 | R70: 0 | S70: 2 | T70: 2 | U70: 1 | V70: 0 | W70: 2 | X70: 3 | Y70: 0 | Z70: 1 | AA70: 0 | AB70: 1 | AC70: 3 | AD70: 1 | AE70: 1 | AF70: 0 | AG70: =SUM(B70:AF70) -> 70
A71: Perch Extender - Blue | B71: 114 | C71: 82 | D71: 67 | E71: 64 | F71: 52 | G71: 54 | H71: 51 | I71: 43 | J71: 66 | K71: 58 | L71: 43 | M71: 26 | N71: 14 | O71: 22 | P71: 20 | Q71: 27 | R71: 25 | S71: 17 | T71: 19 | U71: 14 | V71: 23 | W71: 22 | X71: 22 | Y71: 36 | Z71: 28 | AA71: 21 | AB71: 19 | AC71: 22 | AD71: 18 | AE71: 22 | AF71: 13 | AG71: =SUM(B71:AF71) -> 1124
A72: Perch Extender - Yellow | B72: 17 | C72: 13 | D72: 6 | E72: 7 | F72: 4 | G72: 6 | H72: 3 | I72: 2 | J72: 10 | K72: 4 | L72: 3 | M72: 5 | N72: 2 | O72: 5 | P72: 4 | Q72: 10 | R72: 3 | S72: 4 | T72: 2 | U72: 6 | V72: 2 | W72: 1 | X72: 5 | Y72: 3 | Z72: 2 | AA72: 1 | AB72: 0 | AC72: 6 | AD72: 2 | AE72: 4 | AF72: 5 | AG72: =SUM(B72:AF72) -> 147
A73: Solar Roof (HBF) | N73: 3 | O73: 3 | P73: 6 | Q73: 3 | R73: 2 | S73: 0 | T73: 2 | U73: 3 | V73: 0 | W73: 5 | X73: 3 | Y73: 2 | Z73: 0 | AA73: 0 | AB73: 1 | AC73: 1 | AD73: 0 | AE73: 0 | AF73: 0 | AG73: =SUM(B73:AF73) -> 34
A74: Housing - only (HBF) | B74: 29 | C74: 9 | D74: 1 | E74: 4 | F74: 2 | G74: 2 | H74: 0 | I74: 0 | J74: 3 | K74: 7 | L74: 1 | M74: 2 | N74: 2 | O74: 3 | P74: 2 | Q74: 2 | R74: 2 | S74: 2 | T74: 0 | U74: 1 | V74: 0 | W74: 2 | X74: 1 | Y74: 2 | Z74: 1 | AA74: 0 | AB74: 1 | AC74: 0 | AD74: 0 | AE74: 0 | AF74: 0 | AG74: =SUM(B74:AF74) -> 81
A75: SUM (Add-ons) | B75: =SUM(B65:B74) -> 452 | C75: =SUM(C65:C74) -> 305 | D75: =SUM(D65:D74) -> 286 | E75: =SUM(E65:E74) -> 272 | F75: =SUM(F65:F74) -> 224 | G75: =SUM(G65:G74) -> 228 | H75: =SUM(H65:H74) -> 201 | I75: =SUM(I65:I74) -> 183 | ... AF75: =SUM(AF65:AF74) -> 48 | AG75: =SUM(B75:AF75) -> 4171
A77: Seasonal Curation - 8lb | B77: 41 | C77: 34 | D77: 29 | E77: 26 | F77: 35 | G77: 24 | H77: 22 | I77: 21 | J77: 25 | K77: 19 | L77: 20 | M77: 11 | N77: 6 | O77: 10 | P77: 18 | Q77: 9 | R77: 4 | S77: 10 | T77: 1 | U77: 3 | V77: 5 | W77: 11 | X77: 14 | Y77: 17 | Z77: 13 | AA77: 11 | AB77: 12 | AC77: 9 | AD77: 2 | AE77: 3 | AF77: 7 | AG77: =SUM(B77:AF77) -> 472
A78: Seasonal Curation - 20lb | B78: 1 | C78: 0 | D78: 0 | E78: 2 | F78: 2 | G78: 0 | H78: 0 | I78: 0 | J78: 3 | K78: 1 | L78: 1 | M78: 1 | N78: 1 | O78: 0 | P78: 1 | Q78: 1 | R78: 2 | S78: 2 | T78: 0 | U78: 2 | V78: 1 | W78: 0 | X78: 1 | Y78: 0 | Z78: 0 | AA78: 1 | AB78: 0 | AC78: 0 | AD78: 0 | AE78: 0 | AF78: 1 | AG78: =SUM(B78:AF78) -> 24
A79: Buddy Bites - 8lb | B79: 1 | C79: 1 | D79: 0 | E79: 1 | F79: 2 | G79: 2 | H79: 1 | I79: 0 | J79: 1 | K79: 0 | L79: 0 | M79: 1 | N79: 0 | O79: 1 | P79: 1 | Q79: 2 | R79: 1 | S79: 0 | T79: 0 | U79: 0 | V79: 0 | W79: 1 | X79: 0 | Y79: 3 | Z79: 1 | AA79: 1 | AB79: 0 | AC79: 1 | AD79: 0 | AE79: 1 | AF79: 0 | AG79: =SUM(B79:AF79) -> 23
A80: Buddy Bites - 20lb | B80: 0 | C80: 0 | D80: 0 | E80: 0 | F80: 0 | G80: 1 | H80: 1 | I80: 0 | J80: 0 | K80: 0 | L80: 0 | M80: 0 | N80: 0 | O80: 0 | P80: 1 | Q80: 0 | R80: 0 | S80: 0 | T80: 0 | U80: 0 | V80: 0 | W80: 0 | X80: 0 | Y80: 0 | Z80: 0 | AA80: 0 | AB80: 0 | AC80: 0 | AD80: 0 | AE80: 0 | AF80: 0 | AG80: =SUM(B80:AF80) -> 3
A81: Snack n' Soar - 8lb | B81: 5 | C81: 1 | D81: 0 | E81: 0 | F81: 1 | G81: 2 | H81: 0 | I81: 1 | J81: 1 | K81: 0 | L81: 1 | M81: 2 | N81: 1 | O81: 1 | P81: 1 | Q81: 0 | R81: 0 | S81: 1 | T81: 0 | U81: 0 | V81: 1 | W81: 1 | X81: 1 | Y81: 3 | Z81: 4 | AA81: 1 | AB81: 0 | AC81: 3 | AD81: 0 | AE81: 1 | AF81: 0 | AG81: =SUM(B81:AF81) -> 33
A82: Snack n' Soar - 20lb | B82: 1 | C82: 0 | D82: 0 | E82: 0 | F82: 1 | G82: 0 | H82: 0 | I82: 0 | J82: 1 | K82: 0 | L82: 0 | M82: 0 | N82: 1 | O82: 1 | P82: 0 | Q82: 0 | R82: 0 | S82: 0 | T82: 0 | U82: 0 | V82: 0 | W82: 0 | X82: 0 | Y82: 1 | Z82: 0 | AA82: 0 | AB82: 0 | AC82: 0 | AD82: 0 | AE82: 0 | AF82: 0 | AG82: =SUM(B82:AF82) -> 6
A83: Avian Choice - 8lb | B83: 2 | C83: 1 | D83: 1 | E83: 5 | F83: 2 | G83: 0 | H83: 3 | I83: 0 | J83: 1 | K83: 1 | L83: 0 | M83: 2 | N83: 0 | O83: 0 | P83: 1 | Q83: 2 | R83: 2 | S83: 1 | T83: 0 | U83: 1 | V83: 1 | W83: 1 | X83: 0 | Y83: 2 | Z83: 0 | AA83: 0 | AB83: 2 | AC83: 3 | AD83: 1 | AE83: 2 | AF83: 1 | AG83: =SUM(B83:AF83) -> 38
A84: Avian Choice - 20lb | B84: 0 | C84: 0 | D84: 1 | E84: 0 | F84: 0 | G84: 0 | H84: 0 | I84: 0 | J84: 1 | K84: 0 | L84: 0 | M84: 0 | N84: 0 | O84: 0 | P84: 0 | Q84: 0 | R84: 0 | S84: 0 | T84: 0 | U84: 0 | V84: 0 | W84: 0 | X84: 0 | Y84: 0 | Z84: 0 | AA84: 0 | AB84: 0 | AC84: 1 | AD84: 0 | AE84: 0 | AF84: 0 | AG84: =SUM(B84:AF84) -> 3
A85: SUM (Seeds) | B85: =SUM(B77:B84) -> 51 | C85: =SUM(C77:C84) -> 37 | D85: =SUM(D77:D84) -> 31 | E85: =SUM(E77:E84) -> 34 | F85: =SUM(F77:F84) -> 43 | G85: =SUM(G77:G84) -> 29 | H85: =SUM(H77:H84) -> 27 | I85: =SUM(I77:I84) -> 22 | ... AF85: =SUM(AF77:AF84) -> 9 | AG85: =SUM(B85:AF85) -> 602
A87: Merch Units Sold (Gross)
A88: Merch Units | B88: 0 | C88: 0 | D88: 0 | E88: 0 | F88: 2 | G88: 7 | H88: 1 | I88: 0 | J88: 1 | K88: 0 | L88: 0 | M88: 0 | N88: 0 | O88: 0 | P88: 1 | Q88: 1 | R88: 0 | S88: 2 | T88: 1 | U88: 0 | V88: 0 | W88: 0 | X88: 1 | Y88: 0 | Z88: 0 | AA88: 0 | AB88: 0 | AC88: 0 | AD88: 0 | AE88: 0 | AF88: 0 | AG88: =SUM(B88:AF88) -> 17
A90: First-time Customers
A91: SKU 1 - Blue | B91: =B55-B114 -> 38 | C91: =C55-C114 -> 34 | D91: =D55-D114 -> 38 | E91: =E55-E114 -> 33 | F91: =F55-F114 -> 25 | G91: =G55-G114 -> 26 | H91: =H55-H114 -> 26 | I91: =I55-I114 -> 22 | ... AF91: =AF55-AF114 -> 5 | AG91: =SUM(B91:AF91) -> 487
A92: SKU 2 - Yellow | B92: =B56-B115 -> 0 | C92: =C56-C115 -> 0 | D92: =D56-D115 -> 0 | E92: =E56-E115 -> 0 | F92: =F56-F115 -> 0 | G92: =G56-G115 -> 0 | H92: =H56-H115 -> 0 | I92: =I56-I115 -> 0 | ... AF92: =AF56-AF115 -> 0 | AG92: =SUM(B92:AF92) -> 0
A93: SKU 3 - Blue w/ Solar | B93: =B57-B116 -> 103 | C93: =C57-C116 -> 90 | D93: =D57-D116 -> 102 | E93: =E57-E116 -> 104 | F93: =F57-F116 -> 99 | G93: =G57-G116 -> 88 | H93: =H57-H116 -> 73 | I93: =I57-I116 -> 76 | ... AF93: =AF57-AF116 -> 29 | AG93: =SUM(B93:AF93) -> 1544
A94: SKU 4 - Yellow w/ Solar | B94: =B58-B117 -> 0 | C94: =C58-C117 -> 0 | D94: =D58-D117 -> 0 | E94: =E58-E117 -> 0 | F94: =F58-F117 -> 0 | G94: =G58-G117 -> 0 | H94: =H58-H117 -> 0 | I94: =I58-I117 -> 0 | ... AF94: =AF58-AF117 -> 0 | AG94: =SUM(B94:AF94) -> 0
A95: SUM (SKU 1 - SKU 4) | B95: =SUM(B91:B94) -> 141 | C95: =SUM(C91:C94) -> 124 | D95: =SUM(D91:D94) -> 140 | E95: =SUM(E91:E94) -> 137 | F95: =SUM(F91:F94) -> 124 | G95: =SUM(G91:G94) -> 114 | H95: =SUM(H91:H94) -> 99 | I95: =SUM(I91:I94) -> 98 | ... AF95: =SUM(AF91:AF94) -> 34 | AG95: =SUM(B95:AF95) -> 2031
A97: SKU 5 - HBF | B97: =B61-B120 -> 369 | C97: =C61-C120 -> 45 | D97: =D61-D120 -> 30 | E97: =E61-E120 -> 23 | F97: =F61-F120 -> 18 | G97: =G61-G120 -> 10 | H97: =H61-H120 -> 14 | I97: =I61-I120 -> 28 | ... AF97: =AF61-AF120 -> 1 | AG97: =SUM(B97:AF97) -> 687
A98: SKU 6 - HBF w/ Solar | B98: =B62-B121 -> 862 | C98: =C62-C121 -> 113 | D98: =D62-D121 -> 94 | E98: =E62-E121 -> 64 | F98: =F62-F121 -> 42 | G98: =G62-G121 -> 38 | H98: =H62-H121 -> 38 | I98: =I62-I121 -> 38 | ... AF98: =AF62-AF121 -> 5 | AG98: =SUM(B98:AF98) -> 1707
A99: SUM (SKU 5 - SKU 6) | B99: =SUM(B97:B98) -> 1231 | C99: =SUM(C97:C98) -> 158 | D99: =SUM(D97:D98) -> 124 | E99: =SUM(E97:E98) -> 87 | F99: =SUM(F97:F98) -> 60 | G99: =SUM(G97:G98) -> 48 | H99: =SUM(H97:H98) -> 52 | I99: =SUM(I97:I98) -> 66 | ... AF99: =SUM(AF97:AF98) -> 6 | AG99: =SUM(B99:AF99) -> 2394
A101: Wall Mount | B101: =B65-B124 -> 134 | C101: =C65-C124 -> 106 | D101: =D65-D124 -> 129 | E101: =E65-E124 -> 110 | F101: =F65-F124 -> 92 | G101: =G65-G124 -> 99 | H101: =H65-H124 -> 80 | I101: =I65-I124 -> 72 | ... AF101: =AF65-AF124 -> 9 | AG101: =SUM(B101:AF101) -> 1288
A102: Suet Ball Holder | B102: =B66-B125 -> 28 | C102: =C66-C125 -> 26 | D102: =D66-D125 -> 22 | E102: =E66-E125 -> 17 | F102: =F66-F125 -> 17 | G102: =G66-G125 -> 19 | H102: =H66-H125 -> 15 | I102: =I66-I125 -> 24 | ... AF102: =AF66-AF125 -> 5 | AG102: =SUM(B102:AF102) -> 347
A103: 3-in-1 Nutrition Set - Blue | B103: =B67-B126 -> 26 | C103: =C67-C126 -> 21 | D103: =D67-D126 -> 22 | E103: =E67-E126 -> 18 | F103: =F67-F126 -> 15 | G103: =G67-G126 -> 17 | H103: =H67-H126 -> 16 | I103: =I67-I126 -> 20 | ... AF103: =AF67-AF126 -> 4 | AG103: =SUM(B103:AF103) -> 325
A104: 3-in-1 Nutrition Set - Yellow | B104: =B68-B127 -> 2 | C104: =C68-C127 -> 1 | D104: =D68-D127 -> 0 | E104: =E68-E127 -> 1 | F104: =F68-F127 -> 0 | G104: =G68-G127 -> 0 | H104: =H68-H127 -> 1 | I104: =I68-I127 -> 1 | ... AF104: =AF68-AF127 -> 1 | AG104: =SUM(B104:AF104) -> 27
A105: Solar Roof Single - Blue | B105: =B69-B128 -> 18 | C105: =C69-C128 -> 14 | D105: =D69-D128 -> 14 | E105: =E69-E128 -> 11 | F105: =F69-F128 -> 12 | G105: =G69-G128 -> 8 | H105: =H69-H128 -> 10 | I105: =I69-I128 -> 7 | ... AF105: =AF69-AF128 -> 7 | AG105: =SUM(B105:AF105) -> 213
A106: Solar Roof Single - Yellow | B106: =B70-B129 -> 6 | C106: =C70-C129 -> 4 | D106: =D70-D129 -> 3 | E106: =E70-E129 -> 3 | F106: =F70-F129 -> 1 | G106: =G70-G129 -> 3 | H106: =H70-H129 -> 0 | I106: =I70-I129 -> 0 | ... AF106: =AF70-AF129 -> 0 | AG106: =SUM(B106:AF106) -> 46
A107: Perch Extender - Blue | B107: =B71-B130 -> 81 | C107: =C71-C130 -> 71 | D107: =D71-D130 -> 57 | E107: =E71-E130 -> 55 | F107: =F71-F130 -> 44 | G107: =G71-G130 -> 48 | H107: =H71-H130 -> 43 | I107: =I71-I130 -> 38 | ... AF107: =AF71-AF130 -> 12 | AG107: =SUM(B107:AF107) -> 911
A108: Perch Extender - Yellow | B108: =B72-B131 -> 15 | C108: =C72-C131 -> 11 | D108: =D72-D131 -> 4 | E108: =E72-E131 -> 5 | F108: =F72-F131 -> 4 | G108: =G72-G131 -> 3 | H108: =H72-H131 -> 1 | I108: =I72-I131 -> 1 | ... AF108: =AF72-AF131 -> 4 | AG108: =SUM(B108:AF108) -> 104
A109: Solar Roof (HBF) | B109: =B73-B132 -> 0 | C109: =C73-C132 -> 0 | D109: =D73-D132 -> 0 | E109: =E73-E132 -> 0 | F109: =F73-F132 -> 0 | G109: =G73-G132 -> 0 | H109: =H73-H132 -> 0 | I109: =I73-I132 -> 0 | ... AF109: =AF73-AF132 -> 0 | AG109: =SUM(B109:AF109) -> 18
A110: Housing - only (HBF) | B110: =B74-B133 -> 21 | C110: =C74-C133 -> 9 | D110: =D74-D133 -> 1 | E110: =E74-E133 -> 3 | F110: =F74-F133 -> 2 | G110: =G74-G133 -> 1 | H110: =H74-H133 -> 0 | I110: =I74-I133 -> 0 | ... AF110: =AF74-AF133 -> 0 | AG110: =SUM(B110:AF110) -> 59
A111: SUM (Add-ons) | B111: =SUM(B101:B110) -> 331 | C111: =SUM(C101:C110) -> 263 | D111: =SUM(D101:D110) -> 252 | E111: =SUM(E101:E110) -> 223 | F111: =SUM(F101:F110) -> 187 | G111: =SUM(G101:G110) -> 198 | H111: =SUM(H101:H110) -> 166 | I111: =SUM(I101:I110) -> 163 | ... AF111: =SUM(AF101:AF110) -> 42 | AG111: =SUM(B111:AF111) -> 3338
A113: Returning Customers
A114: SKU 1 - Blue | B114: 2 | C114: 3 | D114: 3 | E114: 4 | F114: 3 | G114: 2 | H114: 1 | I114: 1 | J114: 3 | K114: 1 | L114: 2 | M114: 0 | N114: 1 | O114: 1 | P114: 0 | Q114: 1 | R114: 0 | S114: 1 | T114: 0 | U114: 1 | V114: 0 | W114: 0 | X114: 2 | Y114: 0 | Z114: 1 | AA114: 0 | AB114: 1 | AC114: 1 | AD114: 0 | AE114: 0 | AF114: 1 | AG114: =SUM(B114:AF114) -> 36
A115: SKU 2 - Yellow | B115: 0 | C115: 0 | D115: 0 | E115: 0 | F115: 0 | G115: 0 | H115: 0 | I115: 0 | J115: 0 | K115: 0 | L115: 0 | M115: 0 | N115: 0 | O115: 0 | P115: 0 | Q115: 0 | R115: 0 | S115: 0 | T115: 0 | U115: 0 | V115: 0 | W115: 0 | X115: 0 | Y115: 0 | Z115: 0 | AA115: 0 | AB115: 0 | AC115: 0 | AD115: 0 | AE115: 0 | AF115: 0 | AG115: =SUM(B115:AF115) -> 0
A116: SKU 3 - Blue w/ Solar | B116: 22 | C116: 9 | D116: 8 | E116: 10 | F116: 9 | G116: 5 | H116: 10 | I116: 5 | J116: 7 | K116: 5 | L116: 4 | M116: 3 | N116: 1 | O116: 2 | P116: 4 | Q116: 3 | R116: 8 | S116: 2 | T116: 2 | U116: 4 | V116: 3 | W116: 3 | X116: 4 | Y116: 8 | Z116: 3 | AA116: 6 | AB116: 3 | AC116: 5 | AD116: 3 | AE116: 4 | AF116: 5 | AG116: =SUM(B116:AF116) -> 170
A117: SKU 4 - Yellow w/ Solar | B117: 0 | C117: 0 | D117: 0 | E117: 0 | F117: 0 | G117: 0 | H117: 0 | I117: 0 | J117: 0 | K117: 0 | L117: 0 | M117: 0 | N117: 0 | O117: 0 | P117: 0 | Q117: 0 | R117: 0 | S117: 0 | T117: 0 | U117: 0 | V117: 0 | W117: 0 | X117: 0 | Y117: 0 | Z117: 0 | AA117: 0 | AB117: 0 | AC117: 0 | AD117: 0 | AE117: 0 | AF117: 0 | AG117: =SUM(B117:AF117) -> 0
...

Sheet AMAZON - P&L
A1: MARCH | B1: 45352 | C1: 45353 | D1: 45354 | E1: 45355 | F1: 45356 | G1: 45357 | H1: 45358 | I1: 45359 | J1: 45360 | K1: 45361 | L1: 45362 | M1: 45363 | N1: 45364 | O1: 45365 | P1: 45366 | Q1: 45367 | R1: 45368 | S1: 45369 | T1: 45370 | U1: 45371 | V1: 45372 | W1: 45373 | X1: 45374 | Y1: 45375 | Z1: 45376 | AA1: 45377 | AB1: 45378 | AC1: 45379 | AD1: 45380 | AE1: 45381 | AF1: 45382
A2: DAY | B2: FRI | C2: SAT | D2: SUN | E2: MON | F2: TUE | G2: WED | H2: THU | I2: FRI | J2: SAT | K2: SUN | L2: MON | M2: TUE | N2: WED | O2: THU | P2: FRI | Q2: SAT | R2: SUN | S2: MON | T2: TUE | U2: WED | V2: THU | W2: FRI | X2: SAT | Y2: SUN | Z2: MON | AA2: TUE | AB2: WED | AC2: THU | AD2: FRI | AE2: SAT | AF2: SUN
A3: COMMENT
A4: Orders
A5: Amazon (market place) | B5: =Summary!B58 -> 153 | C5: =Summary!C58 -> 171 | D5: =Summary!D58 -> 147 | E5: =Summary!E58 -> 97 | F5: =Summary!F58 -> 60 | G5: =Summary!G58 -> 114 | H5: =Summary!H58 -> 121 | I5: =Summary!I58 -> 110 | ... AF5: =Summary!AF58 -> 56
A6: All | B6: =SUM(B5) -> 153 | C6: =SUM(C5) -> 171 | D6: =SUM(D5) -> 147 | E6: =SUM(E5) -> 97 | F6: =SUM(F5) -> 60 | G6: =SUM(G5) -> 114 | H6: =SUM(H5) -> 121 | I6: =SUM(I5) -> 110 | ... AF6: =SUM(AF5) -> 56 | AG6: =SUM(B6:AF6) -> 2700
A8: Revenue
A9: Amazon (market place) | B9: =Summary!B16 -> 19348.49 | C9: =Summary!C16 -> 22322.39 | D9: =Summary!D16 -> 16109.48 | E9: =Summary!E16 -> 9416.58 | F9: =Summary!F16 -> 6365.8 | G9: =Summary!G16 -> 11506.81 | H9: =Summary!H16 -> 17570.37 | I9: =Summary!I16 -> 16642.54 | ... AF9: =Summary!AF16 -> 4451.22
A10: All | B10: =SUM(B9) -> 19348.49 | C10: =SUM(C9) -> 22322.39 | D10: =SUM(D9) -> 16109.48 | E10: =SUM(E9) -> 9416.58 | F10: =SUM(F9) -> 6365.8 | G10: =SUM(G9) -> 11506.81 | H10: =SUM(H9) -> 17570.37 | I10: =SUM(I9) -> 16642.54 | ... AF10: =SUM(AF9) -> 4451.22 | AG10: =SUM(B10:AF10) -> 371798.13
A12: Media Cost
A13: Amazon Spend | B13: =Summary!B81 -> 1348.28 | C13: =Summary!C81 -> 1385.43 | D13: =Summary!D81 -> 1102.46 | E13: =Summary!E81 -> 752.89 | F13: =Summary!F81 -> 700.89 | G13: =Summary!G81 -> 2163.8 | H13: =Summary!H81 -> 3196.98 | I13: =Summary!I81 -> 2585.22 | ... AF13: =Summary!AF81 -> 430.21 | AG13: =SUM(B13:AF13) -> 50347.45
A14: Amazon Platform Fee (15 %) | B14: =B9*'Data - P&L'!$C$48 -> 2902.2735 | C14: =C9*'Data - P&L'!$C$48 -> 3348.3585 | D14: =D9*'Data - P&L'!$C$48 -> 2416.422 | E14: =E9*'Data - P&L'!$C$48 -> 1412.487 | F14: =F9*'Data - P&L'!$C$48 -> 954.87 | G14: =G9*'Data - P&L'!$C$48 -> 1726.0215 | H14: =H9*'Data - P&L'!$C$48 -> 2635.5555 | I14: =I9*'Data - P&L'!$C$48 -> 2496.381 | ... AF14: =AF9*'Data - P&L'!$C$48 -> 667.683
A15: All | B15: =SUM(B13:B14) -> 4250.5535 | C15: =SUM(C13:C14) -> 4733.7885 | D15: =SUM(D13:D14) -> 3518.882 | E15: =SUM(E13:E14) -> 2165.377 | F15: =SUM(F13:F14) -> 1655.76 | G15: =SUM(G13:G14) -> 3889.8215 | H15: =SUM(H13:H14) -> 5832.5355 | I15: =SUM(I13:I14) -> 5081.601 | ... AF15: =SUM(AF13:AF14) -> 1097.893 | AG15: =SUM(B15:AF15) -> 106117.17
A19: Amazon Orders
A20: Hardware | B20: =Summary!B17 -> 16689.8 | C20: =Summary!C17 -> 18894.12 | D20: =Summary!D17 -> 13167.68 | E20: =Summary!E17 -> 7392.24 | F20: =Summary!F17 -> 4950.56 | G20: =Summary!G17 -> 9849 | H20: =Summary!H17 -> 15173.56 | I20: =Summary!I17 -> 14651.68 | ... AF20: =Summary!AF17 -> 2989 | AG20: =SUM(B20:AF20) -> 308643.2
A21: Addons | B21: =Summary!B18 -> 1424.56 | C21: =Summary!C18 -> 1915.56 | D21: =Summary!D18 -> 1792.68 | E21: =Summary!E18 -> 1421.56 | F21: =Summary!F18 -> 1009 | G21: =Summary!G18 -> 906 | H21: =Summary!H18 -> 1285.56 | I21: =Summary!I18 -> 897 | ... AF21: =Summary!AF18 -> 1130 | AG21: =SUM(B21:AF21) -> 38600.12
A22: Tax | B22: =Summary!B19 -> 1193.49 | C22: =Summary!C19 -> 1464.05 | D22: =Summary!D19 -> 1131.65 | E22: =Summary!E19 -> 586.52 | F22: =Summary!F19 -> 392.02 | G22: =Summary!G19 -> 741.83 | H22: =Summary!H19 -> 1064.89 | I22: =Summary!I19 -> 1027.39 | ... AF22: =Summary!AF19 -> 320.74 | AG22: =SUM(B22:AF22) -> 23822.38
A23: Shipping | B23: =Summary!B20 -> 26.65 | C23: =Summary!C20 -> 21.21 | D23: =Summary!D20 -> 7.47 | E23: =Summary!E20 -> 10.42 | F23: =Summary!F20 -> 0.08 | G23: =Summary!G20 -> 0 | H23: =Summary!H20 -> 29.06 | I23: =Summary!I20 -> 51.99 | ... AF23: =Summary!AF20 -> 6.99 | AG23: =SUM(B23:AF23) -> 396.41
A24: Gift Wrap Price | B24: =Summary!B21 -> 13.99 | C24: =Summary!C21 -> 27.45 | D24: =Summary!D21 -> 10 | E24: =Summary!E21 -> 5.84 | F24: =Summary!F21 -> 14.14 | G24: =Summary!G21 -> 9.98 | H24: =Summary!H21 -> 17.3 | I24: =Summary!I21 -> 14.48 | ... AF24: =Summary!AF21 -> 4.49 | AG24: =SUM(B24:AF24) -> 336.02
A25: All Amazon | B25: =SUM(B20:B24) -> 19348.49 | C25: =SUM(C20:C24) -> 22322.39 | D25: =SUM(D20:D24) -> 16109.48 | E25: =SUM(E20:E24) -> 9416.58 | F25: =SUM(F20:F24) -> 6365.8 | G25: =SUM(G20:G24) -> 11506.81 | H25: =SUM(H20:H24) -> 17570.37 | I25: =SUM(I20:I24) -> 16642.54 | ... AF25: =SUM(AF20:AF24) -> 4451.22 | AG25: =SUM(B25:AF25) -> 371798.13
A27: Units Sold (Gross)
A28: SKU 1 - Blue | B28: 4 | C28: 6 | D28: 17 | E28: 22 | F28: 22 | G28: 16 | H28: 11 | I28: 10 | J28: 14 | K28: 15 | L28: 10 | M28: 8 | N28: 7 | O28: 7 | P28: 5 | Q28: 4 | R28: 7 | S28: 8 | T28: 10 | U28: 10 | V28: 12 | W28: 15 | X28: 15 | Y28: 22 | Z28: 19 | AA28: 12 | AB28: 12 | AC28: 18 | AD28: 10 | AE28: 5 | AF28: 5 | AG28: =SUM(B28:AF28) -> 358
A29: SKU 2 - Yellow | B29: 6 | C29: 3 | D29: 7 | E29: 8 | F29: 3 | G29: 11 | H29: 2 | I29: 4 | J29: 4 | K29: 4 | L29: 0 | M29: 0 | N29: 0 | O29: 0 | P29: 0 | Q29: 0 | R29: 0 | S29: 1 | T29: 0 | U29: 0 | V29: 1 | W29: 0 | X29: 0 | Y29: 0 | Z29: 0 | AA29: 0 | AB29: 0 | AC29: 0 | AD29: 0 | AE29: 0 | AF29: 0 | AG29: =SUM(B29:AF29) -> 54
A30: SKU 3 - Blue w/ Solar | B30: 67 | C30: 82 | D30: 40 | E30: 8 | F30: 2 | G30: 25 | H30: 60 | I30: 57 | J30: 68 | K30: 77 | L30: 24 | M30: 18 | N30: 25 | O30: 28 | P30: 38 | Q30: 29 | R30: 34 | S30: 12 | T30: 28 | U30: 32 | V30: 21 | W30: 14 | X30: 18 | Y30: 14 | Z30: 7 | AA30: 16 | AB30: 13 | AC30: 6 | AD30: 11 | AE30: 14 | AF30: 6 | AG30: =SUM(B30:AF30) -> 894
A31: SKU 4 - Yellow w/ Solar | B31: 1 | C31: 0 | D31: 1 | E31: 0 | F31: 0 | G31: 0 | H31: 1 | I31: 0 | J31: 0 | K31: 0 | L31: 1 | M31: 1 | N31: 0 | O31: 0 | P31: 0 | Q31: 0 | R31: 0 | S31: 0 | T31: 0 | U31: 1 | V31: 1 | W31: 0 | X31: 0 | Y31: 0 | Z31: 0 | AA31: 0 | AB31: 0 | AC31: 0 | AD31: 0 | AE31: 0 | AF31: 0 | AG31: =SUM(B31:AF31) -> 7
A32: SUM (SKU 1 - SKU 4) | B32: =SUM(B28:B31) -> 78 | C32: =SUM(C28:C31) -> 91 | D32: =SUM(D28:D31) -> 65 | E32: =SUM(E28:E31) -> 38 | F32: =SUM(F28:F31) -> 27 | G32: =SUM(G28:G31) -> 52 | H32: =SUM(H28:H31) -> 74 | I32: =SUM(I28:I31) -> 71 | ... AF32: =SUM(AF28:AF31) -> 11 | AG32: =SUM(B32:AF32) -> 1313
A34: Wall Mount | B34: 18 | C34: 25 | D34: 28 | E34: 19 | F34: 14 | G34: 17 | H34: 18 | I34: 11 | J34: 32 | K34: 29 | L34: 14 | M34: 10 | N34: 15 | O34: 10 | P34: 17 | Q34: 17 | R34: 15 | S34: 6 | T34: 12 | U34: 11 | V34: 15 | W34: 11 | X34: 10 | Y34: 17 | Z34: 11 | AA34: 6 | AB34: 8 | AC34: 6 | AD34: 10 | AE34: 23 | AF34: 12 | AG34: =SUM(B34:AF34) -> 467
A35: Suet Ball Holder | B35: 15 | C35: 25 | D35: 23 | E35: 15 | F35: 12 | G35: 11 | H35: 12 | I35: 15 | J35: 28 | K35: 20 | L35: 5 | M35: 10 | N35: 11 | O35: 10 | P35: 10 | Q35: 20 | R35: 15 | S35: 14 | T35: 8 | U35: 13 | V35: 13 | W35: 8 | X35: 13 | Y35: 7 | Z35: 6 | AA35: 3 | AB35: 6 | AC35: 13 | AD35: 6 | AE35: 20 | AF35: 5 | AG35: =SUM(B35:AF35) -> 392
A36: 3-in-1 Nutrition Set - Blue | B36: 5 | C36: 11 | D36: 9 | E36: 6 | F36: 10 | G36: 3 | H36: 8 | I36: 6 | J36: 11 | K36: 7 | L36: 3 | M36: 8 | N36: 2 | O36: 3 | P36: 2 | Q36: 7 | R36: 4 | S36: 7 | T36: 6 | U36: 8 | V36: 6 | W36: 7 | X36: 6 | Y36: 8 | Z36: 4 | AA36: 6 | AB36: 3 | AC36: 6 | AD36: 5 | AE36: 8 | AF36: 2 | AG36: =SUM(B36:AF36) -> 187
A37: 3-in-1 Nutrition Set - Yellow | B37: 0 | C37: 0 | D37: 0 | E37: 0 | F37: 0 | G37: 0 | H37: 0 | I37: 0 | J37: 0 | K37: 0 | L37: 0 | M37: 0 | N37: 0 | O37: 0 | P37: 0 | Q37: 0 | R37: 0 | S37: 0 | T37: 0 | U37: 0 | V37: 0 | W37: 0 | X37: 0 | Y37: 0 | Z37: 0 | AA37: 0 | AB37: 0 | AC37: 0 | AD37: 0 | AE37: 0 | AF37: 0 | AG37: =SUM(B37:AF37) -> 0
A38: Solar Roof Single - Blue | B38: 0 | C38: 0 | D38: 0 | E38: 0 | F38: 0 | G38: 0 | H38: 0 | I38: 0 | J38: 0 | K38: 0 | L38: 0 | M38: 0 | N38: 0 | O38: 0 | P38: 0 | Q38: 0 | R38: 0 | S38: 0 | T38: 0 | U38: 0 | V38: 0 | W38: 0 | X38: 0 | Y38: 0 | Z38: 0 | AA38: 0 | AB38: 0 | AC38: 0 | AD38: 0 | AE38: 0 | AF38: 0 | AG38: =SUM(B38:AF38) -> 0
A39: Solar Roof Single - Yellow | B39: 0 | C39: 0 | D39: 0 | E39: 0 | F39: 0 | G39: 0 | H39: 0 | I39: 0 | J39: 0 | K39: 0 | L39: 0 | M39: 0 | N39: 0 | O39: 0 | P39: 0 | Q39: 0 | R39: 0 | S39: 0 | T39: 0 | U39: 0 | V39: 0 | W39: 0 | X39: 0 | Y39: 0 | Z39: 0 | AA39: 0 | AB39: 0 | AC39: 0 | AD39: 0 | AE39: 0 | AF39: 0 | AG39: =SUM(B39:AF39) -> 0
A40: Perch Extender - Blue | B40: 20 | C40: 26 | D40: 35 | E40: 21 | F40: 15 | G40: 18 | H40: 14 | I40: 16 | J40: 33 | K40: 25 | L40: 11 | M40: 6 | N40: 8 | O40: 5 | P40: 2 | Q40: 8 | R40: 6 | S40: 9 | T40: 5 | U40: 8 | V40: 6 | W40: 5 | X40: 20 | Y40: 22 | Z40: 10 | AA40: 16 | AB40: 9 | AC40: 11 | AD40: 10 | AE40: 24 | AF40: 21 | AG40: =SUM(B40:AF40) -> 445
A41: Perch Extender - Yellow | B41: 0 | C41: 0 | D41: 0 | E41: 0 | F41: 0 | G41: 0 | H41: 0 | I41: 0 | J41: 0 | K41: 0 | L41: 0 | M41: 0 | N41: 0 | O41: 0 | P41: 0 | Q41: 0 | R41: 0 | S41: 0 | T41: 0 | U41: 0 | V41: 0 | W41: 0 | X41: 0 | Y41: 0 | Z41: 0 | AA41: 0 | AB41: 0 | AC41: 0 | AD41: 0 | AE41: 0 | AF41: 0 | AG41: =SUM(B41:AF41) -> 0
A42: SUM (Add-ons) | B42: =SUM(B34:B41) -> 58 | C42: =SUM(C34:C41) -> 87 | D42: =SUM(D34:D41) -> 95 | E42: =SUM(E34:E41) -> 61 | F42: =SUM(F34:F41) -> 51 | G42: =SUM(G34:G41) -> 49 | H42: =SUM(H34:H41) -> 52 | I42: =SUM(I34:I41) -> 48 | ... AF42: =SUM(AF34:AF41) -> 40 | AG42: =SUM(B42:AF42) -> 1491
A45: Units Sold by country (Gross) - Only selling in US | AG45: =SUM(B45:AF45) -> 0
A46: Bird Buddy - Blue - AMAZON.US | AG46: =SUM(B46:AF46) -> 0
A47: Bird Buddy - Yellow - AMAZON.US | AG47: =SUM(B47:AF47) -> 0
A48: Bird Buddy with Solar Roof Blue - AMAZON.US | AB48: =AB31 -> 0 | AC48: =AC31 -> 0 | AD48: =AD31 -> 0 | AE48: =AE31 -> 0 | AF48: =AF31 -> 0 | AG48: =SUM(B48:AF48) -> 0
A49: Bird Buddy with Solar Roof Yellow - AMAZON.US | AG49: =SUM(B49:AF49) -> 0
A50: Bird Buddy - AMAZON.EU | AG50: =SUM(B50:AF50) -> 0
A51: Bird Buddy with Solar Roof - AMAZON.EU | AG51: =SUM(B51:AF51) -> 0
A52: Bird Buddy - AMAZON (OTHER1) | AG52: =SUM(B52:AF52) -> 0
A53: Bird Buddy with Solar Roof - AMAZON (OTHER1) | AG53: =SUM(B53:AF53) -> 0
A54: All Bird Buddy | B54: =B46+B50+B52 -> 0 | C54: =SUM(C46:C53) -> 0 | D54: =SUM(D46:D53) -> 0 | E54: =SUM(E46:E53) -> 0 | F54: =SUM(F46:F53) -> 0 | G54: =SUM(G46:G53) -> 0 | H54: =SUM(H46:H53) -> 0 | I54: =SUM(I46:I53) -> 0 | J54: =SUM(J46:J53) -> 0 | ... AF54: =SUM(AF46:AF53) -> 0 | AG54: =SUM(B54:AF54) -> 0
A55: All Bird Buddy with Solar Roof | B55: =B48+B51+B53 -> 0 | C55: =C48+C51+C53 -> 0 | D55: =D48+D51+D53 -> 0 | E55: =E48+E51+E53 -> 0 | F55: =F48+F51+F53 -> 0 | G55: =G48+G51+G53 -> 0 | H55: =H48+H51+H53 -> 0 | I55: =I48+I51+I53 -> 0 | ... AF55: =AF48+AF51+AF53 -> 0 | AG55: =SUM(B55:AF55) -> 0
AG56: =SUM(B56:AF56) -> 0
A57: Wall Mount - AMAZON.US | AG57: =SUM(B57:AF57) -> 0
A58: Fence Mount - AMAZON.US | AG58: =SUM(B58:AF58) -> 0
A59: Suet Ball Holder - AMAZON.US | AG59: =SUM(B59:AF59) -> 0
A60: 3-in-1 Nutrition Set - AMAZON.US | AG60: =SUM(B60:AF60) -> 0
A61: Solar Roof Single - AMAZON.US | AG61: =SUM(B61:AF61) -> 0
A62: All AMAZON.US | B62: =SUM(B57:B61) -> 0 | C62: =SUM(C57:C61) -> 0 | D62: =SUM(D57:D61) -> 0 | E62: =SUM(E57:E61) -> 0 | F62: =SUM(F57:F61) -> 0 | G62: =SUM(G57:G61) -> 0 | H62: =SUM(H57:H61) -> 0 | I62: =SUM(I57:I61) -> 0 | ... AF62: =SUM(AF57:AF61) -> 0 | AG62: =SUM(B62:AF62) -> 0
AG63: =SUM(B63:AF63) -> 0
A64: Wall Mount - AMAZON.EU | AG64: =SUM(B64:AF64) -> 0
A65: Fence Mount - AMAZON.EU | AG65: =SUM(B65:AF65) -> 0
A66: Suet Ball Holder - AMAZON.EU | AG66: =SUM(B66:AF66) -> 0
A67: 3-in-1 Nutrition Set - AMAZON.EU | AG67: =SUM(B67:AF67) -> 0
A68: Solar Roof Single - AMAZON.EU | AG68: =SUM(B68:AF68) -> 0
A69: All AMAZON.EU | B69: =SUM(B64:B68) -> 0 | C69: =SUM(C64:C68) -> 0 | D69: =SUM(D64:D68) -> 0 | E69: =SUM(E64:E68) -> 0 | F69: =SUM(F64:F68) -> 0 | G69: =SUM(G64:G68) -> 0 | H69: =SUM(H64:H68) -> 0 | I69: =SUM(I64:I68) -> 0 | ... AF69: =SUM(AF64:AF68) -> 0 | AG69: =SUM(B69:AF69) -> 0
AG70: =SUM(B70:AF70) -> 0
A71: Wall Mount - AMAZON (OTHER1) | AG71: =SUM(B71:AF71) -> 0
A72: Fence Mount - AMAZON (OTHER1) | AG72: =SUM(B72:AF72) -> 0
A73: Suet Ball Holder - AMAZON (OTHER1) | AG73: =SUM(B73:AF73) -> 0
A74: 3-in-1 Nutrition Set - AMAZON (OTHER1) | AG74: =SUM(B74:AF74) -> 0
A75: Solar Roof Single - AMAZON (OTHER1) | AG75: =SUM(B75:AF75) -> 0
A76: All AMAZON (OTHER1) | B76: =SUM(B71:B75) -> 0 | C76: =SUM(C71:C74) -> 0 | D76: =SUM(D71:D75) -> 0 | E76: =SUM(E71:E75) -> 0 | F76: =SUM(F71:F75) -> 0 | G76: =SUM(G71:G74) -> 0 | H76: =SUM(H71:H74) -> 0 | I76: =SUM(I71:I74) -> 0 | J76: =SUM(J71:J74) -> 0 | K76: =SUM(K71:K74) -> 0 | L76: =SUM(L71:L74) -> 0 | M76: =SUM(M71:M74) -> 0 | N76: =SUM(N71:N74) -> 0 | ... V76: =SUM(V71:V74) -> 0 | W76: =SUM(W71:W75) -> 0 | X76: =SUM(X71:X74) -> 0 | Y76: =SUM(Y71:Y74) -> 0 | Z76: =SUM(Z71:Z74) -> 0 | AA76: =SUM(AA71:AA74) -> 0 | AB76: =SUM(AB71:AB74) -> 0 | AC76: =SUM(AC71:AC74) -> 0 | AD76: =SUM(AD71:AD74) -> 0 | AE76: =SUM(AE71:AE74) -> 0 | AF76: =SUM(AF71:AF74) -> 0 | AG76: =SUM(B76:AF76) -> 0
AG77: =SUM(B77:AF77) -> 0
A78: Revenue by country (Gross) - Only selling in US | AG78: =SUM(B78:AF78) -> 0
A79: Bird Buddy - AMAZON.US | AG79: =SUM(B79:AF79) -> 0
A80: Bird Buddy with Solar Roof - AMAZON.US | AB80: =AB9 -> 7992.33 | AC80: =AC9 -> 7570.74 | AD80: =AD9 -> 7060.85 | AE80: =AE9 -> 7665.47 | AF80: =AF9 -> 4451.22 | AG80: =SUM(B80:AF80) -> 34740.61
A81: Bird Buddy - AMAZON.EU | AG81: =SUM(B81:AF81) -> 0
A82: Bird Buddy with Solar Roof - AMAZON.EU | AG82: =SUM(B82:AF82) -> 0
A83: Bird Buddy - AMAZON (OTHER1) | AG83: =SUM(B83:AF83) -> 0
A84: Bird Buddy with Solar Roof - AMAZON (OTHER1) | AG84: =SUM(B84:AF84) -> 0
A85: All Bird Buddy | B85: =B79+B81+B83 -> 0 | C85: =C79+C81+C83 -> 0 | D85: =D79+D81+D83 -> 0 | E85: =E79+E81+E83 -> 0 | F85: =F79+F81+F83 -> 0 | G85: =G79+G81+G83 -> 0 | H85: =H79+H81+H83 -> 0 | I85: =I79+I81+I83 -> 0 | ... AF85: =AF79+AF81+AF83 -> 0 | AG85: =SUM(B85:AF85) -> 0
A86: All Bird Buddy with Solar Roof | B86: =B80+B82+B84 -> 0 | C86: =C80+C82+C84 -> 0 | D86: =D80+D82+D84 -> 0 | E86: =E80+E82+E84 -> 0 | F86: =F80+F82+F84 -> 0 | G86: =G80+G82+G84 -> 0 | H86: =H80+H82+H84 -> 0 | I86: =I80+I82+I84 -> 0 | ... AF86: =AF80+AF82+AF84 -> 4451.22 | AG86: =SUM(B86:AF86) -> 34740.61
AG87: =SUM(B87:AF87) -> 0
A88: Wall Mount - AMAZON.US | AG88: =SUM(B88:AF88) -> 0
A89: Fence Mount - AMAZON.US | AG89: =SUM(B89:AF89) -> 0
A90: Suet Ball Holder - AMAZON.US | AG90: =SUM(B90:AF90) -> 0
A91: 3-in-1 Nutrition Set - AMAZON.US | AG91: =SUM(B91:AF91) -> 0
A92: Solar Roof Single - AMAZON.US | AG92: =SUM(B92:AF92) -> 0
A93: All AMAZON.US | B93: =SUM(B88:B92) -> 0 | C93: =SUM(C88:C92) -> 0 | D93: =SUM(D88:D92) -> 0 | E93: =SUM(E88:E92) -> 0 | F93: =SUM(F88:F92) -> 0 | G93: =SUM(G88:G92) -> 0 | H93: =SUM(H88:H92) -> 0 | I93: =SUM(I88:I92) -> 0 | ... AF93: =SUM(AF88:AF92) -> 0 | AG93: =SUM(B93:AF93) -> 0
AG94: =SUM(B94:AF94) -> 0
A95: Wall Mount - AMAZON.EU | AG95: =SUM(B95:AF95) -> 0
A96: Fence Mount - AMAZON.EU | AG96: =SUM(B96:AF96) -> 0
A97: Suet Ball Holder - AMAZON.EU | AG97: =SUM(B97:AF97) -> 0
A98: 3-in-1 Nutrition Set - AMAZON.EU | AG98: =SUM(B98:AF98) -> 0
A99: Solar Roof Single - AMAZON.EU | AG99: =SUM(B99:AF99) -> 0
A100: All AMAZON.EU | B100: =SUM(B95:B99) -> 0 | C100: =SUM(C95:C99) -> 0 | D100: =SUM(D95:D99) -> 0 | E100: =SUM(E95:E99) -> 0 | F100: =SUM(F95:F99) -> 0 | G100: =SUM(G95:G99) -> 0 | H100: =SUM(H95:H99) -> 0 | I100: =SUM(I95:I99) -> 0 | ... AF100: =SUM(AF95:AF99) -> 0 | AG100: =SUM(B100:AF100) -> 0
AG101: =SUM(B101:AF101) -> 0
A102: Wall Mount - AMAZON (OTHER1) | AG102: =SUM(B102:AF102) -> 0
A103: Fence Mount - AMAZON (OTHER1) | AG103: =SUM(B103:AF103) -> 0
A104: Suet Ball Holder - AMAZON (OTHER1) | AG104: =SUM(B104:AF104) -> 0
A105: 3-in-1 Nutrition Set - AMAZON (OTHER1) | AG105: =SUM(B105:AF105) -> 0
A106: Solar Roof Single - AMAZON (OTHER1) | AG106: =SUM(B106:AF106) -> 0
A107: All AMAZON (OTHER1) | B107: =SUM(B102:B106) -> 0 | C107: =SUM(C102:C106) -> 0 | D107: =SUM(D102:D106) -> 0 | E107: =SUM(E102:E106) -> 0 | F107: =SUM(F102:F106) -> 0 | G107: =SUM(G102:G106) -> 0 | H107: =SUM(H102:H106) -> 0 | I107: =SUM(I102:I106) -> 0 | ... AF107: =SUM(AF102:AF106) -> 0 | AG107: =SUM(B107:AF107) -> 0
A110: Units Cancelled (Gross)
A111: SKU 1 - Blue | B111: 1 | C111: 1 | D111: 0 | E111: 1 | F111: 0 | G111: 1 | H111: 0 | I111: 1 | J111: 0 | K111: 0 | L111: 0 | M111: 0 | N111: 0 | O111: 0 | P111: 0 | Q111: 0 | R111: 0 | S111: 0 | T111: 0 | U111: 1 | V111: 0 | W111: 0 | X111: 0 | Y111: 1 | Z111: 0 | AA111: 2 | AB111: 1 | AC111: 1 | AD111: 1 | AE111: 0 | AF111: 0 | AG111: =SUM(B111:AF111) -> 12
...

Sheet App - P&L
A1: MARCH | B1: 45352 | C1: 45353 | D1: 45354 | E1: 45355 | F1: 45356 | G1: 45357 | H1: 45358 | I1: 45359 | J1: 45360 | K1: 45361 | L1: 45362 | M1: 45363 | N1: 45364 | O1: 45365 | P1: 45366 | Q1: 45367 | R1: 45368 | S1: 45369 | T1: 45370 | U1: 45371 | V1: 45372 | W1: 45373 | X1: 45374 | Y1: 45375 | Z1: 45376 | AA1: 45377 | AB1: 45378 | AC1: 45379 | AD1: 45380 | AE1: 45381 | AF1: 45382
A2: DAY | B2: FRI | C2: SAT | D2: SUN | E2: MON | F2: TUE | G2: WED | H2: THU | I2: FRI | J2: SAT | K2: SUN | L2: MON | M2: TUE | N2: WED | O2: THU | P2: FRI | Q2: SAT | R2: SUN | S2: MON | T2: TUE | U2: WED | V2: THU | W2: FRI | X2: SAT | Y2: SUN | Z2: MON | AA2: TUE | AB2: WED | AC2: THU | AD2: FRI | AE2: SAT | AF2: SUN
A4: Gross Revenue
A5: Apple Store Sales | B5: 6872.9926 | C5: 5548.1791 | D5: 6728.52 | E5: 10828.22 | F5: 4542.95 | G5: 2359.11 | H5: 2377.0166 | I5: 2522.5795 | J5: 3110.92 | K5: 4379.08 | L5: 2446.622 | M5: 2536.7721 | N5: 2272.88 | O5: 2332.4713 | P5: 2029.4366 | Q5: 3555.8599 | R5: 3284.25 | S5: 2014.88 | T5: 1861.88 | U5: 1898.15 | V5: 1519.9556 | W5: 1998.4023 | X5: 2850.4083 | Y5: 3300.95 | Z5: 2373.83 | AA5: 2834.69 | AB5: 2037.67 | AC5: 1682.7447 | AD5: 2038.5427 | AE5: 2936.3707 | AF5: 3543.2198 | AG5: =SUM(B5:AF5) -> 100619.55
A6: - Yearly Subscription | B6: 6480.4932 | C6: 5249.45 | D6: 6303.7232 | E6: 10439.965 | F6: 4349.11 | G6: 2069.5 | H6: 2070.5367 | I6: 2221.0799 | J6: 2818.6286 | K6: 4065.183 | L6: 2188.3811 | M6: 2277.8533 | N6: 2070.2822 | O6: 1979.46 | P6: 1772.8024 | Q6: 3239.9422 | R6: 2971.0511 | S6: 1804.4892 | T6: 1649.59 | U6: 1678.4311 | V6: 1259.67 | W6: 1803.9661 | X6: 2467.0983 | Y6: 2854.1992 | Z6: 1558.7268 | AA6: 2071.2529 | AB6: 1526.2875 | AC6: 1204.5096 | AD6: 1617.54 | AE6: 2583.414 | AF6: 3209.8548 | AG6: =SUM(B6:AF6) -> 89856.472
A7: - Monthly Subscription | B7: 392.49935 | C7: 298.72912 | D7: 424.79334 | E7: 388.25234 | F7: 193.8388 | G7: 289.61297 | H7: 306.47985 | I7: 301.49965 | J7: 292.29241 | K7: 313.89461 | L7: 258.24085 | M7: 258.91876 | N7: 202.59739 | O7: 353.01132 | P7: 256.63424 | Q7: 315.91776 | R7: 313.1994 | S7: 210.39403 | T7: 212.29462 | U7: 219.72018 | V7: 260.28556 | W7: 194.43625 | X7: 383.31 | Y7: 446.75084 | Z7: 815.0986 | AA7: 763.43598 | AB7: 511.38712 | AC7: 478.2351 | AD7: 421.0027 | AE7: 352.9567 | AF7: 333.36507 | AG7: =SUM(B7:AF7) -> 10763.085
A8: Google Store Sales | B8: 1365.2 | C8: 1251.85 | D8: 948.07 | E8: 1423.92 | F8: 1035.76 | G8: 500.48 | H8: 444.38 | I8: 595.58 | J8: 691.69 | K8: 825.29 | L8: 513.11 | M8: 543.93 | N8: 571.93 | O8: 539.48 | P8: 609.68 | Q8: 743.21 | R8: 970.43 | S8: 476.44 | T8: 482.73 | U8: 288.1 | V8: 467.59 | W8: 169.2 | X8: 355.24 | Y8: 778.43 | Z8: 495.59 | AA8: 339.7 | AB8: 477.5 | AC8: 317.99 | AD8: 628.18 | AE8: 478.16 | AF8: 354.64 | AG8: =SUM(B8:AF8) -> 19683.48
A9: - Yearly Subscription | B9: 1320.71 | C9: 1181.63 | D9: 884.79 | E9: 1346.06 | F9: 973.33 | G9: 446.66 | H9: 384.46 | I9: 505.04 | J9: 600.22 | K9: 758.05 | L9: 471.26 | M9: 508.38 | N9: 536.89 | O9: 476.38 | P9: 542.79 | Q9: 701.27 | R9: 929.12 | S9: 412.54 | T9: 435.15 | U9: =91.84+119.98 -> 211.82 | V9: 407.88 | W9: 122.74 | X9: 283.03 | Y9: =315.01+387.93 -> 702.94 | Z9: 372.15 | AA9: 216.62 | AB9: 342.42 | AC9: 216.2 | AD9: 480.08 | AE9: 443.45 | AF9: 342.04 | AG9: =SUM(B9:AF9) -> 17556.1
A10: - Monthly Subscription | B10: 44.49 | C10: 70.22 | D10: 63.28 | E10: 77.86 | F10: 62.43 | G10: 53.82 | H10: 59.92 | I10: 90.54 | J10: 91.47 | K10: 67.24 | L10: 41.85 | M10: 35.55 | N10: 35.04 | O10: 63.1 | P10: 66.89 | Q10: 41.94 | R10: 41.31 | S10: 63.9 | T10: 47.58 | U10: 76.28 | V10: 59.71 | W10: 46.46 | X10: 72.21 | Y10: 75.49 | Z10: 123.44 | AA10: 123.08 | AB10: 135.08 | AC10: 101.68 | AD10: 148.1 | AE10: 34.71 | AF10: 12.6 | AG10: =SUM(B10:AF10) -> 2127.27
A11: SUM | B11: =sum(B5+B8) -> 8238.1926 | C11: =sum(C5+C8) -> 6800.0291 | D11: =sum(D5+D8) -> 7676.59 | E11: =sum(E5+E8) -> 12252.14 | F11: =sum(F5+F8) -> 5578.71 | G11: =sum(G5+G8) -> 2859.59 | H11: =sum(H5+H8) -> 2821.3966 | I11: =sum(I5+I8) -> 3118.1595 | ... AF11: =sum(AF5+AF8) -> 3897.8598 | AG11: =SUM(B11:AF11) -> 120303.03
A13: Gross Orders
A14: Apple Store Orders | B14: =sum(B15:B16) -> 208 | C14: =sum(C15:C16) -> 180 | D14: =sum(D15:D16) -> 238 | E14: =sum(E15:E16) -> 274 | F14: =sum(F15:F16) -> 132 | G14: =sum(G15:G16) -> 108 | H14: =sum(H15:H16) -> 115 | I14: =sum(I15:I16) -> 113 | ... AF14: =sum(AF15:AF16) -> 144 | AG14: =SUM(B14:AF14) -> 4235
A15: - Yearly Subscription | B15: 135 | C15: 122 | D15: 153 | E15: 201 | F15: 89 | G15: 51 | H15: 52 | I15: 53 | J15: 74 | K15: 107 | L15: 51 | M15: 60 | N15: 54 | O15: 54 | P15: 42 | Q15: 87 | R15: 87 | S15: 47 | T15: 41 | U15: 48 | V15: 33 | W15: 43 | X15: 57 | Y15: 76 | Z15: 42 | AA15: 48 | AB15: 39 | AC15: 34 | AD15: 49 | AE15: 67 | AF15: 86 | AG15: =SUM(B15:AF15) -> 2182
A16: - Monthly Subscription | B16: 73 | C16: 58 | D16: 85 | E16: 73 | F16: 43 | G16: 57 | H16: 63 | I16: 60 | J16: 60 | K16: 61 | L16: 50 | M16: 51 | N16: 39 | O16: 68 | P16: 50 | Q16: 63 | R16: 61 | S16: 42 | T16: 42 | U16: 42 | V16: 51 | W16: 37 | X16: 69 | Y16: 83 | Z16: 148 | AA16: 141 | AB16: 92 | AC16: 89 | AD16: 77 | AE16: 67 | AF16: 58 | AG16: =SUM(B16:AF16) -> 2053
A17: Google Store Orders | B17: =sum(B18:B19) -> 35 | C17: =sum(C18:C19) -> 39 | D17: =sum(D18:D19) -> 39 | E17: =sum(E18:E19) -> 51 | F17: =sum(F18:F19) -> 32 | G17: =sum(G18:G19) -> 20 | H17: =sum(H18:H19) -> 20 | I17: =sum(I18:I19) -> 31 | ... AF17: =sum(AF18:AF19) -> 11 | AG17: =SUM(B17:AF17) -> 818
A18: - Yearly Subscription | B18: 28 | C18: 26 | D18: 25 | E18: 34 | F18: 20 | G18: 9 | H18: 9 | I18: 14 | J18: 14 | K18: 16 | L18: 11 | M18: 14 | N18: 13 | O18: 12 | P18: 14 | Q18: 17 | R18: 24 | S18: 10 | T18: 11 | U18: 5 | V18: 10 | W18: 3 | X18: 6 | Y18: 16 | Z18: 8 | AA18: 5 | AB18: 8 | AC18: 6 | AD18: 10 | AE18: 12 | AF18: 9 | AG18: =SUM(B18:AF18) -> 419
A19: - Monthly Subscription | B19: 7 | C19: 13 | D19: 14 | E19: 17 | F19: 12 | G19: 11 | H19: 11 | I19: 17 | J19: 17 | K19: 12 | L19: 7 | M19: 7 | N19: 7 | O19: 12 | P19: 14 | Q19: 7 | R19: 7 | S19: 13 | T19: 10 | U19: 16 | V19: 12 | W19: 9 | X19: 13 | Y19: 13 | Z19: 21 | AA19: 22 | AB19: 23 | AC19: 19 | AD19: 28 | AE19: 6 | AF19: 2 | AG19: =SUM(B19:AF19) -> 399
A20: SUM | B20: =sum(B14+B17) -> 243 | C20: =sum(C14+C17) -> 219 | D20: =sum(D14+D17) -> 277 | E20: =sum(E14+E17) -> 325 | F20: =sum(F14+F17) -> 164 | G20: =sum(G14+G17) -> 128 | H20: =sum(H14+H17) -> 135 | I20: =sum(I14+I17) -> 144 | ... AF20: =sum(AF14+AF17) -> 155 | AG20: =SUM(B20:AF20) -> 5053
A21: - Yearly Subscription | B21: =B15+B18 -> 163 | C21: =C15+C18 -> 148 | D21: =D15+D18 -> 178 | E21: =E15+E18 -> 235 | F21: =F15+F18 -> 109 | G21: =G15+G18 -> 60 | H21: =H15+H18 -> 61 | I21: =I15+I18 -> 67 | ... AF21: =AF15+AF18 -> 95 | AG21: =sum(A21:AF21) -> 2601
A22: - Monthly Subscription | B22: =B16+B19 -> 80 | C22: =C16+C19 -> 71 | D22: =D16+D19 -> 99 | E22: =E16+E19 -> 90 | F22: =F16+F19 -> 55 | G22: =G16+G19 -> 68 | H22: =H16+H19 -> 74 | I22: =I16+I19 -> 77 | ... AF22: =AF16+AF19 -> 60 | AG22: =sum(B22:AF22) -> 2452
A24: Refunded Revenue
A25: Apple Store Sales | B25: =sum(B26:B27) -> 27.29 | C25: =sum(C26:C27) -> 4.97 | D25: =sum(D26:D27) -> 44.1 | E25: =sum(E26:E27) -> 1.85 | F25: =sum(F26:F27) -> 123.82 | G25: =sum(G26:G27) -> 59.99 | H25: =sum(H26:H27) -> 5.99 | I25: =sum(I26:I27) -> 0.41 | ... AF25: =sum(AF26:AF27) -> 0 | AG25: =SUM(B25:AF25) -> 875.39
A26: - Yearly Subscription | B26: 27.29 | C26: 0 | D26: 38.11 | E26: 0 | F26: 119.89 | G26: 59.99 | H26: 0 | I26: 0 | J26: 0 | K26: 29.99 | L26: 0 | M26: 0 | N26: 59.99 | O26: 20.57 | P26: 0 | Q26: 0 | R26: 0 | S26: 59.99 | T26: 23.43 | U26: 89.98 | V26: 0 | W26: 7.86 | X26: 28.35 | Y26: 29.99 | Z26: 59.99 | AA26: 89.98 | AB26: 0 | AC26: 59.98 | AD26: 0 | AE26: 0 | AF26: 0 | AG26: =SUM(B26:AF26) -> 805.38
A27: - Monthly Subscription | B27: 0 | C27: 4.97 | D27: 5.99 | E27: 1.85 | F27: 3.93 | G27: 0 | H27: 5.99 | I27: 0.41 | J27: 0 | K27: 0 | L27: 1.45 | M27: 5.61 | N27: 4.64 | O27: 0 | P27: 0 | Q27: 5.99 | R27: 0 | S27: 5.99 | T27: 0 | U27: 0 | V27: 0 | W27: 0 | X27: 0 | Y27: 0 | Z27: 5.99 | AA27: 11.21 | AB27: 0 | AC27: 5.99 | AD27: 0 | AE27: 0 | AF27: 0 | AG27: =SUM(B27:AF27) -> 70.01
A28: Google Store Sales | B28: =sum(B29:B30) -> 0 | C28: =sum(C29:C30) -> 0 | D28: =sum(D29:D30) -> 0 | E28: =sum(E29:E30) -> 0 | F28: =sum(F29:F30) -> 0 | G28: =sum(G29:G30) -> 0 | H28: =sum(H29:H30) -> 0 | I28: =sum(I29:I30) -> 0 | ... AF28: =sum(AF29:AF30) -> 0 | AG28: =SUM(B28:AF28) -> 0
A29: - Yearly Subscription | B29: 0 | C29: 0 | D29: 0 | E29: 0 | F29: 0 | G29: 0 | H29: 0 | I29: 0 | J29: 0 | K29: 0 | L29: 0 | M29: 0 | N29: 0 | O29: 0 | P29: 0 | Q29: 0 | R29: 0 | S29: 0 | T29: 0 | U29: 0 | V29: 0 | W29: 0 | X29: 0 | Y29: 0 | Z29: 0 | AA29: 0 | AB29: 0 | AC29: 0 | AD29: 0 | AE29: 0 | AF29: 0 | AG29: =SUM(B29:AF29) -> 0
A30: - Monthly Subscription | B30: 0 | C30: 0 | D30: 0 | E30: 0 | F30: 0 | G30: 0 | H30: 0 | I30: 0 | J30: 0 | K30: 0 | L30: 0 | M30: 0 | N30: 0 | O30: 0 | P30: 0 | Q30: 0 | R30: 0 | S30: 0 | T30: 0 | U30: 0 | V30: 0 | W30: 0 | X30: 0 | Y30: 0 | Z30: 0 | AA30: 0 | AB30: 0 | AC30: 0 | AD30: 0 | AE30: 0 | AF30: 0 | AG30: =SUM(B30:AF30) -> 0
A31: SUM | B31: =B25+B28 -> 27.29 | C31: =C25+C28 -> 4.97 | D31: =D25+D28 -> 44.1 | E31: =E25+E28 -> 1.85 | F31: =F25+F28 -> 123.82 | G31: =G25+G28 -> 59.99 | H31: =H25+H28 -> 5.99 | I31: =I25+I28 -> 0.41 | ... AF31: =AF25+AF28 -> 0 | AG31: =SUM(B31:AF31) -> 875.39
A33: Refunded Orders
A34: Apple Store orders | B34: =sum(B35:B36) -> 1 | C34: =sum(C35:C36) -> 1 | D34: =sum(D35:D36) -> 2 | E34: =sum(E35:E36) -> 1 | F34: =sum(F35:F36) -> 3 | G34: =sum(G35:G36) -> 1 | H34: =sum(H35:H36) -> 1 | I34: =sum(I35:I36) -> 0 | ... AF34: =sum(AF35:AF36) -> 0 | AG34: =SUM(B34:AF34) -> 29
A35: - Yearly Subscription | B35: 1 | C35: 0 | D35: 1 | E35: 0 | F35: 2 | G35: 1 | H35: 0 | I35: 0 | J35: 0 | K35: 1 | L35: 0 | M35: 0 | N35: 1 | O35: 0 | P35: 0 | Q35: 0 | R35: 0 | S35: 1 | T35: 0 | U35: 2 | V35: 0 | W35: 0 | X35: 1 | Y35: 1 | Z35: 1 | AA35: 2 | AB35: 0 | AC35: 2 | AD35: 0 | AE35: 0 | AF35: 0
A36: - Monthly Subscription | B36: 0 | C36: 1 | D36: 1 | E36: 1 | F36: 1 | G36: 0 | H36: 1 | I36: 0 | J36: 0 | K36: 0 | L36: 0 | M36: 1 | N36: 1 | O36: 0 | P36: 0 | Q36: 1 | R36: 0 | S36: 1 | T36: 0 | U36: 0 | V36: 0 | W36: 0 | X36: 0 | Y36: 0 | Z36: 1 | AA36: 1 | AB36: 0 | AC36: 1 | AD36: 0 | AE36: 0 | AF36: 0
A37: Google Store orders | B37: =sum(B38:B39) -> 0 | C37: =sum(C38:C39) -> 0 | D37: =sum(D38:D39) -> 0 | E37: =sum(E38:E39) -> 0 | F37: =sum(F38:F39) -> 0 | G37: =sum(G38:G39) -> 0 | H37: =sum(H38:H39) -> 0 | I37: =sum(I38:I39) -> 0 | ... AF37: =sum(AF38:AF39) -> 0 | AG37: =SUM(B37:AF37) -> 0
A38: - Yearly Subscription | B38: 0 | C38: 0 | D38: 0 | E38: 0 | F38: 0 | G38: 0 | H38: 0 | I38: 0 | J38: 0 | K38: 0 | L38: 0 | M38: 0 | N38: 0 | O38: 0 | P38: 0 | Q38: 0 | R38: 0 | S38: 0 | T38: 0 | U38: 0 | V38: 0 | W38: 0 | X38: 0 | Y38: 0 | Z38: 0 | AA38: 0 | AB38: 0 | AC38: 0 | AD38: 0 | AE38: 0 | AF38: 0
A39: - Monthly Subscription | B39: 0 | C39: 0 | D39: 0 | E39: 0 | F39: 0 | G39: 0 | H39: 0 | I39: 0 | J39: 0 | K39: 0 | L39: 0 | M39: 0 | N39: 0 | O39: 0 | P39: 0 | Q39: 0 | R39: 0 | S39: 0 | T39: 0 | U39: 0 | V39: 0 | W39: 0 | X39: 0 | Y39: 0 | Z39: 0 | AA39: 0 | AB39: 0 | AC39: 0 | AD39: 0 | AE39: 0 | AF39: 0
A40: SUM | B40: =B34+B37 -> 1 | C40: =C34+C37 -> 1 | D40: =D34+D37 -> 2 | E40: =E34+E37 -> 1 | F40: =F34+F37 -> 3 | G40: =G34+G37 -> 1 | H40: =H34+H37 -> 1 | I40: =I34+I37 -> 0 | ... AF40: =AF34+AF37 -> 0 | AG40: =SUM(B40:AF40) -> 29
A42: Net Revenue
A43: Apple Store | B43: =B5-B25 -> 6845.7026 | C43: =C5-C25 -> 5543.2091 | D43: =D5-D25 -> 6684.42 | E43: =E5-E25 -> 10826.37 | F43: =F5-F25 -> 4419.13 | G43: =G5-G25 -> 2299.12 | H43: =H5-H25 -> 2371.0266 | I43: =I5-I25 -> 2522.1695 | ... AF43: =AF5-AF25 -> 3543.2198 | AG43: =SUM(B43:AF43) -> 99744.164
A44: - Yearly Subscription | B44: =B6-B26 -> 6453.2032 | C44: =C6-C26 -> 5249.45 | D44: =D6-D26 -> 6265.6132 | E44: =E6-E26 -> 10439.965 | F44: =F6-F26 -> 4229.22 | G44: =G6-G26 -> 2009.51 | H44: =H6-H26 -> 2070.5367 | I44: =I6-I26 -> 2221.0799 | ... AF44: =AF6-AF26 -> 3209.8548 | AG44: =SUM(B44:AF44) -> 89051.092
A45: - Monthly Subscription | B45: =B7-B27 -> 392.49935 | C45: =C7-C27 -> 293.75912 | D45: =D7-D27 -> 418.80334 | E45: =E7-E27 -> 386.40234 | F45: =F7-F27 -> 189.9088 | G45: =G7-G27 -> 289.61297 | H45: =H7-H27 -> 300.48985 | I45: =I7-I27 -> 301.08965 | ... AF45: =AF7-AF27 -> 333.36507 | AG45: =SUM(B45:AF45) -> 10693.075
A46: Google Store | B46: =B8-B28 -> 1365.2 | C46: =C8-C28 -> 1251.85 | D46: =D8-D28 -> 948.07 | E46: =E8-E28 -> 1423.92 | F46: =F8-F28 -> 1035.76 | G46: =G8-G28 -> 500.48 | H46: =H8-H28 -> 444.38 | I46: =I8-I28 -> 595.58 | ... AF46: =AF8-AF28 -> 354.64 | AG46: =SUM(B46:AF46) -> 19683.48
A47: - Yearly Subscription | B47: =B9-B29 -> 1320.71 | C47: =C9-C29 -> 1181.63 | D47: =D9-D29 -> 884.79 | E47: =E9-E29 -> 1346.06 | F47: =F9-F29 -> 973.33 | G47: =G9-G29 -> 446.66 | H47: =H9-H29 -> 384.46 | I47: =I9-I29 -> 505.04 | ... AF47: =AF9-AF29 -> 342.04 | AG47: =SUM(B47:AF47) -> 17556.1
A48: - Monthly Subscription | B48: =B10-B30 -> 44.49 | C48: =C10-C30 -> 70.22 | D48: =D10-D30 -> 63.28 | E48: =E10-E30 -> 77.86 | F48: =F10-F30 -> 62.43 | G48: =G10-G30 -> 53.82 | H48: =H10-H30 -> 59.92 | I48: =I10-I30 -> 90.54 | ... AF48: =AF10-AF30 -> 12.6 | AG48: =SUM(B48:AF48) -> 2127.27
A49: SUM | B49: =B43+B46 -> 8210.9026 | C49: =C43+C46 -> 6795.0591 | D49: =D43+D46 -> 7632.49 | E49: =E43+E46 -> 12250.29 | F49: =F43+F46 -> 5454.89 | G49: =G43+G46 -> 2799.6 | H49: =H43+H46 -> 2815.4066 | I49: =I43+I46 -> 3117.7495 | ... AF49: =AF43+AF46 -> 3897.8598 | AG49: =SUM(B49:AF49) -> 119427.64
A51: Net Orders
A52: Apple Store | B52: =B14-B34 -> 207 | C52: =C14-C34 -> 179 | D52: =D14-D34 -> 236 | E52: =E14-E34 -> 273 | F52: =F14-F34 -> 129 | G52: =G14-G34 -> 107 | H52: =H14-H34 -> 114 | I52: =I14-I34 -> 113 | ... AF52: =AF14-AF34 -> 144 | AG52: =SUM(B52:AF52) -> 4206
A53: - Yearly Subscription | B53: =B15-B35 -> 134 | C53: =C15-C35 -> 122 | D53: =D15-D35 -> 152 | E53: =E15-E35 -> 201 | F53: =F15-F35 -> 87 | G53: =G15-G35 -> 50 | H53: =H15-H35 -> 52 | I53: =I15-I35 -> 53 | ... AF53: =AF15-AF35 -> 86 | AG53: =SUM(B53:AF53) -> 2165
A54: - Monthly Subscription | B54: =B16-B36 -> 73 | C54: =C16-C36 -> 57 | D54: =D16-D36 -> 84 | E54: =E16-E36 -> 72 | F54: =F16-F36 -> 42 | G54: =G16-G36 -> 57 | H54: =H16-H36 -> 62 | I54: =I16-I36 -> 60 | ... AF54: =AF16-AF36 -> 58 | AG54: =SUM(B54:AF54) -> 2041
A55: Google Store | B55: =B17-B37 -> 35 | C55: =C17-C37 -> 39 | D55: =D17-D37 -> 39 | E55: =E17-E37 -> 51 | F55: =F17-F37 -> 32 | G55: =G17-G37 -> 20 | H55: =H17-H37 -> 20 | I55: =I17-I37 -> 31 | ... AF55: =AF17-AF37 -> 11 | AG55: =SUM(B55:AF55) -> 818
A56: - Yearly Subscription | B56: =B18-B38 -> 28 | C56: =C18-C38 -> 26 | D56: =D18-D38 -> 25 | E56: =E18-E38 -> 34 | F56: =F18-F38 -> 20 | G56: =G18-G38 -> 9 | H56: =H18-H38 -> 9 | I56: =I18-I38 -> 14 | ... AF56: =AF18-AF38 -> 9 | AG56: =SUM(B56:AF56) -> 419
A57: - Monthly Subscription | B57: =B19-B39 -> 7 | C57: =C19-C39 -> 13 | D57: =D19-D39 -> 14 | E57: =E19-E39 -> 17 | F57: =F19-F39 -> 12 | G57: =G19-G39 -> 11 | H57: =H19-H39 -> 11 | I57: =I19-I39 -> 17 | ... AF57: =AF19-AF39 -> 2 | AG57: =SUM(B57:AF57) -> 399
A58: SUM | B58: =B52+B55 -> 242 | C58: =C52+C55 -> 218 | D58: =D52+D55 -> 275 | E58: =E52+E55 -> 324 | F58: =F52+F55 -> 161 | G58: =G52+G55 -> 127 | H58: =H52+H55 -> 134 | I58: =I52+I55 -> 144 | ... AF58: =AF52+AF55 -> 155 | AG58: =SUM(B58:AF58) -> 5024
A62: Commision Fees & Taxes
A63: Estimated Apple Store Commision Fee (30%) --> check again after 1. mil. | B63: =B5*0.3 -> 2061.8978 | C63: =C5*0.3 -> 1664.4537 | D63: =D5*0.3 -> 2018.556 | E63: =E5*0.3 -> 3248.466 | F63: =F5*0.3 -> 1362.885 | G63: =G5*0.3 -> 707.733 | H63: =H5*0.3 -> 713.10497 | I63: =I5*0.3 -> 756.77385 | ... AF63: =AF5*0.3 -> 1062.966 | AG63: =SUM(B63:AF63) -> 30185.866
A64: Estimated Apple Store Taxes | B64: 5.75 | C64: 11.69 | D64: 2.55 | E64: 3.03 | F64: 3.12 | G64: 4.19 | H64: 8.16 | I64: 8.06 | J64: 20.53 | K64: 42 | L64: 1.14 | M64: 9.34 | N64: 15.89 | O64: 4.24 | P64: 9.23 | Q64: 6.92 | R64: 5.87 | S64: 9.99 | T64: 3.53 | U64: 0.97 | V64: 4.81 | W64: 3.45 | X64: 22.75 | Y64: 11.33 | Z64: 12.75 | AA64: 15.11 | AB64: 11.42 | AC64: 15.16 | AD64: 2.7 | AE64: 9.9 | AF64: 5.36 | AG64: =SUM(B64:AF64) -> 290.94
A65: Estimated Google Store Commision Fee (15%) --> check again after 1. mil. | B65: =B8*0.15 -> 204.78 | C65: =C8*0.15 -> 187.7775 | D65: =D8*0.15 -> 142.2105 | E65: =E8*0.15 -> 213.588 | F65: =F8*0.15 -> 155.364 | G65: =G8*0.15 -> 75.072 | H65: =H8*0.15 -> 66.657 | I65: =I8*0.15 -> 89.337 | ... AF65: =AF8*0.15 -> 53.196 | AG65: =SUM(B65:AF65) -> 2952.522
A66: Estimated Google Store Taxes | B66: 11.43 | C66: 1.29 | D66: 2.08 | E66: 1.67 | F66: 0.59 | G66: 1.72 | H66: 1.6 | I66: 3.37 | J66: 1.64 | K66: 2.18 | L66: 0 | M66: 1.32 | N66: 0.54 | O66: 0 | P66: 9.41 | Q66: 29.07 | R66: 11.47 | S66: 0.59 | T66: 1.22 | U66: 6.15 | V66: 1.11 | W66: 1.04 | X66: 16.27 | Y66: 6.61 | Z66: 12.6 | AA66: 0.53 | AB66: 0 | AC66: 2.36 | AD66: 12.68 | AE66: 6.29 | AF66: 0 | AG66: =SUM(B66:AF66) -> 146.83
A67: Estimated SUM Store Commision Fees | B67: =B63+B65 -> 2266.6778 | C67: =C63+C65 -> 1852.2312 | D67: =D63+D65 -> 2160.7665 | E67: =E63+E65 -> 3462.054 | F67: =F63+F65 -> 1518.249 | G67: =G63+G65 -> 782.805 | H67: =H63+H65 -> 779.76197 | I67: =I63+I65 -> 846.11085 | ... AF67: =AF63+AF65 -> 1116.1619 | AG67: =SUM(B67:AF67) -> 33138.388
A68: Estimated SUM Store Taxes | B68: =B64+B66 -> 17.18 | C68: =C64+C66 -> 12.98 | D68: =D64+D66 -> 4.63 | E68: =E64+E66 -> 4.7 | F68: =F64+F66 -> 3.71 | G68: =G64+G66 -> 5.91 | H68: =H64+H66 -> 9.76 | I68: =I64+I66 -> 11.43 | ... AF68: =AF64+AF66 -> 5.36 | AG68: =SUM(B68:AF68) -> 437.77
A70: Advertising
A71: Meta Spend | B71: =Summary!B91 -> 0 | C71: =Summary!C91 -> 0 | D71: =Summary!D91 -> 0 | E71: =Summary!E91 -> 0 | F71: =Summary!F91 -> 0 | G71: =Summary!G91 -> 0 | H71: =Summary!H91 -> 0 | I71: =Summary!I91 -> 0 | ... AF71: =Summary!AF91 -> 0 | AG71: =SUM(B71:AF71) -> 90.933554
A72: Apple Spend | B72: =Summary!B92 -> 83.14 | C72: =Summary!C92 -> 58.72 | D72: =Summary!D92 -> 50.98 | E72: =Summary!E92 -> 64.64 | F72: =Summary!F92 -> 61.9 | G72: =Summary!G92 -> 51.55 | H72: =Summary!H92 -> 81.9 | I72: =Summary!I92 -> 87.85 | ... AF72: =Summary!AF92 -> 52.2 | AG72: =SUM(B72:AF72) -> 1754.67
A73: Google Spend | B73: =Summary!B93 -> 0 | C73: =Summary!C93 -> 0 | D73: =Summary!D93 -> 0 | E73: =Summary!E93 -> 0 | F73: =Summary!F93 -> 0 | G73: =Summary!G93 -> 0 | H73: =Summary!H93 -> 0 | I73: =Summary!I93 -> 0 | ... AF73: =Summary!AF93 -> 0 | AG73: =SUM(B73:AF73) -> 0
A74: SUM | B74: =SUM(B71:B73) -> 83.14 | C74: =SUM(C71:C73) -> 58.72 | D74: =SUM(D71:D73) -> 50.98 | E74: =SUM(E71:E73) -> 64.64 | F74: =SUM(F71:F73) -> 61.9 | G74: =SUM(G71:G73) -> 51.55 | H74: =SUM(H71:H73) -> 81.9 | I74: =SUM(I71:I73) -> 87.85 | ... AF74: =SUM(AF71:AF73) -> 52.2 | AG74: =SUM(B74:AF74) -> 1845.6036
A76: Estimated Subscription Profit
A77: - Estimated Apple Store profit | B77: =B43-B63-B64-B72-(B71*'Data - P&L'!$I$24) -> 4694.9148 | C77: =C43-C63-C64-C72-(C71*'Data - P&L'!$I$24) -> 3808.3454 | D77: =D43-D63-D64-D72-(D71*'Data - P&L'!$I$24) -> 4612.334 | E77: =E43-E63-E64-E72-(E71*'Data - P&L'!$I$24) -> 7510.234 | F77: =F43-F63-F64-F72-(F71*'Data - P&L'!$I$24) -> 2991.225 | G77: =G43-G63-G64-G72-(G71*'Data - P&L'!$I$24) -> 1535.647 | H77: =H43-H63-H64-H72-(H71*'Data - P&L'!$I$24) -> 1567.8616 | I77: =I43-I63-I64-I72-(I71*'Data - P&L'!$I$24) -> 1669.4857 | ... AF77: =AF43-AF63-AF64-AF72-(AF71*'Data - P&L'!$I$24) -> 2422.6939 | AG77: =SUM(B77:AF77) -> 67439.941
A78: - Estimated Google Store profit | B78: =B46-B65-B66-B73-(B71*'Data - P&L'!$I$25) -> 1148.99 | C78: =C46-C65-C66-C73-(C71*'Data - P&L'!$I$25) -> 1062.7825 | D78: =D46-D65-D66-D73-(D71*'Data - P&L'!$I$25) -> 803.7795 | E78: =E46-E65-E66-E73-(E71*'Data - P&L'!$I$25) -> 1208.662 | F78: =F46-F65-F66-F73-(F71*'Data - P&L'!$I$25) -> 879.806 | G78: =G46-G65-G66-G73-(G71*'Data - P&L'!$I$25) -> 423.688 | H78: =H46-H65-H66-H73-(H71*'Data - P&L'!$I$25) -> 376.123 | I78: =I46-I65-I66-I73-(I71*'Data - P&L'!$I$25) -> 502.873 | ... AF78: =AF46-AF65-AF66-AF73-(AF71*'Data - P&L'!$I$25) -> 301.444 | AG78: =SUM(B78:AF78) -> 16565.941
A79: Estimated SUM Profit | B79: =sum(B77:B78) -> 5843.9048 | C79: =sum(C77:C78) -> 4871.1279 | D79: =sum(D77:D78) -> 5416.1135 | E79: =sum(E77:E78) -> 8718.896 | F79: =sum(F77:F78) -> 3871.031 | G79: =sum(G77:G78) -> 1959.335 | H79: =sum(H77:H78) -> 1943.9846 | I79: =sum(I77:I78) -> 2172.3587 | ... AF79: =sum(AF77:AF78) -> 2724.1379 | AG79: =SUM(B79:AF79) -> 84005.882
A82: Gross Revenue
A83: =SUM(B11:AF11) -> 120303.03
A84: Gross Sales Profit
A85: =SUM(B79:AF79) -> 84005.882
A86: Gross Sales Margin
A87: =A85/A83 -> 0.69828565
A89: For summary
A90: Google | B90: =B8-B65-B66 -> 1148.99 | C90: =C8-C65-C66 -> 1062.7825 | D90: =D8-D65-D66 -> 803.7795 | E90: =E8-E65-E66 -> 1208.662 | F90: =F8-F65-F66 -> 879.806 | G90: =G8-G65-G66 -> 423.688 | H90: =H8-H65-H66 -> 376.123 | I90: =I8-I65-I66 -> 502.873 | ... AF90: =AF8-AF65-AF66 -> 301.444
A91: Apple | B91: =B5-B63-B64 -> 4805.3448 | C91: =C5-C63-C64 -> 3872.0354 | D91: =D5-D63-D64 -> 4707.414 | E91: =E5-E63-E64 -> 7576.724 | F91: =F5-F63-F64 -> 3176.945 | G91: =G5-G63-G64 -> 1647.187 | H91: =H5-H63-H64 -> 1655.7516 | I91: =I5-I63-I64 -> 1757.7457 | ... AF91: =AF5-AF63-AF64 -> 2474.8939

Sheet Digital Marketplaces - P&L
A1: MARCH | B1: 45352 | C1: 45353 | D1: 45354 | E1: 45355 | F1: 45356 | G1: 45357 | H1: 45358 | I1: 45359 | J1: 45360 | K1: 45361 | L1: 45362 | M1: 45363 | N1: 45364 | O1: 45365 | P1: 45366 | Q1: 45367 | R1: 45368 | S1: 45369 | T1: 45370 | U1: 45371 | V1: 45372 | W1: 45373 | X1: 45374 | Y1: 45375 | Z1: 45376 | AA1: 45377 | AB1: 45378 | AC1: 45379 | AD1: 45380 | AE1: 45381 | AF1: 45382
A2: DAY | B2: FRI | C2: SAT | D2: SUN | E2: MON | F2: TUE | G2: WED | H2: THU | I2: FRI | J2: SAT | K2: SUN | L2: MON | M2: TUE | N2: WED | O2: THU | P2: FRI | Q2: SAT | R2: SUN | S2: MON | T2: TUE | U2: WED | V2: THU | W2: FRI | X2: SAT | Y2: SUN | Z2: MON | AA2: TUE | AB2: WED | AC2: THU | AD2: FRI | AE2: SAT | AF2: SUN
A3: Rachio (Shopify)
A4: Revenue | B4: =Summary!B23 -> 403.31077 | C4: =Summary!C23 -> 222.88339 | D4: =Summary!D23 -> 0 | E4: =Summary!E23 -> 0 | F4: =Summary!F23 -> 0 | G4: =Summary!G23 -> 222.88339 | H4: =Summary!H23 -> 0 | I4: =Summary!I23 -> 445.76677 | ... AF4: =Summary!AF23 -> 0 | AG4: =SUM(B4:AF4) -> 3130.9814
A5: Breakdown | AG5: =SUM(B5:AF5) -> 0
A6: - Tax | B6: =Summary!B25 -> 23.330772 | C6: =Summary!C25 -> 12.893386 | D6: =Summary!D25 -> 0 | E6: =Summary!E25 -> 0 | F6: =Summary!F25 -> 0 | G6: =Summary!G25 -> 12.893386 | H6: =Summary!H25 -> 0 | I6: =Summary!I25 -> 25.786772 | ... AF6: =Summary!AF25 -> 0 | AG6: =SUM(B6:AF6) -> 181.1214
A7: - Shipping | B7: =Summary!B26 | C7: =Summary!C26 | D7: =Summary!D26 | E7: =Summary!E26 | F7: =Summary!F26 | G7: =Summary!G26 | H7: =Summary!H26 | I7: =Summary!I26 | ... AD7: =Summary!AD26 | AG7: =SUM(B7:AF7) -> 0
A8: Orders | B8: =Summary!B62 -> 2 | C8: =Summary!C62 -> 1 | D8: =Summary!D62 -> 0 | E8: =Summary!E62 -> 0 | F8: =Summary!F62 -> 0 | G8: =Summary!G62 -> 1 | H8: =Summary!H62 -> 0 | I8: =Summary!I62 -> 2 | ... AF8: =Summary!AF62 -> 0 | AG8: =SUM(B8:AF8) -> 14
A10: Rachio Fees (20%) | B10: =Summary!B85 -> 80.662154 | C10: =Summary!C85 -> 44.576677 | D10: =Summary!D85 -> 0 | E10: =Summary!E85 -> 0 | F10: =Summary!F85 -> 0 | G10: =Summary!G85 -> 44.576677 | H10: =Summary!H85 -> 0 | I10: =Summary!I85 -> 89.153354 | ... AF10: =Summary!AF85 -> 0 | AG10: =SUM(B10:AF10) -> 626.19628
A12: Units Sold (Gross) - Rachio
A13: SKU 1 - Blue | B13: 1 | C13: 0 | D13: 0 | E13: 0 | F13: 0 | G13: 0 | H13: 0 | I13: 0 | J13: 0 | K13: 1 | L13: 0 | M13: 0 | N13: 0 | O13: 0 | P13: 0 | Q13: 0 | R13: 0 | S13: 0 | T13: 0 | U13: 0 | V13: 0 | W13: 0 | X13: 0 | Y13: 0 | Z13: 0 | AA13: 0 | AB13: 0 | AC13: 0 | AD13: 0 | AE13: 0 | AF13: 0 | AG13: =SUM(B13:AF13) -> 2
A14: SKU 2 - Yellow | B14: 0 | C14: 0 | D14: 0 | E14: 0 | F14: 0 | G14: 0 | H14: 0 | I14: 0 | J14: 0 | K14: 0 | L14: 0 | M14: 0 | N14: 0 | O14: 0 | P14: 0 | Q14: 0 | R14: 0 | S14: 0 | T14: 0 | U14: 0 | V14: 0 | W14: 0 | X14: 0 | Y14: 0 | Z14: 0 | AA14: 0 | AB14: 0 | AC14: 0 | AD14: 0 | AE14: 0 | AF14: 0 | AG14: =SUM(B14:AF14) -> 0
A15: SKU 3 - Blue w/ Solar | B15: 1 | C15: 1 | D15: 0 | E15: 0 | F15: 0 | G15: 1 | H15: 0 | I15: 2 | J15: 0 | K15: 4 | L15: 2 | M15: 1 | N15: 0 | O15: 0 | P15: 0 | Q15: 0 | R15: 0 | S15: 0 | T15: 0 | U15: 0 | V15: 0 | W15: 0 | X15: 0 | Y15: 0 | Z15: 0 | AA15: 0 | AB15: 0 | AC15: 1 | AD15: 0 | AE15: 0 | AF15: 0 | AG15: =SUM(B15:AF15) -> 13
A16: SKU 4 - Yellow w/ Solar | B16: 0 | C16: 0 | D16: 0 | E16: 0 | F16: 0 | G16: 0 | H16: 0 | I16: 0 | J16: 0 | K16: 0 | L16: 0 | M16: 0 | N16: 0 | O16: 0 | P16: 0 | Q16: 0 | R16: 0 | S16: 0 | T16: 0 | U16: 0 | V16: 0 | W16: 0 | X16: 0 | Y16: 0 | Z16: 0 | AA16: 0 | AB16: 0 | AC16: 0 | AD16: 0 | AE16: 0 | AF16: 0 | AG16: =SUM(B16:AF16) -> 0
A17: SUM (SKU 1 - SKU 4) | B17: =SUM(B13:B16) -> 2 | C17: =SUM(C13:C16) -> 1 | D17: =SUM(D13:D16) -> 0 | E17: =SUM(E13:E16) -> 0 | F17: =SUM(F13:F16) -> 0 | G17: =SUM(G13:G16) -> 1 | H17: =SUM(H13:H16) -> 0 | I17: =SUM(I13:I16) -> 2 | ... AF17: =SUM(AF13:AF16) -> 0 | AG17: =SUM(B17:AF17) -> 15
A19: Wall Mount | AG19: =SUM(B19:AF19) -> 0
A20: Suet Ball Holder | AG20: =SUM(B20:AF20) -> 0
A21: 3-in-1 Nutrition Set - Blue | AG21: =SUM(B21:AF21) -> 0
A22: 3-in-1 Nutrition Set - Yellow | AG22: =SUM(B22:AF22) -> 0
A23: Solar Roof Single - Blue | AG23: =SUM(B23:AF23) -> 0
A24: Solar Roof Single - Yellow | AG24: =SUM(B24:AF24) -> 0
A25: Perch Extender - Blue | AG25: =SUM(B25:AF25) -> 0
A26: Perch Extender - Yellow | AG26: =SUM(B26:AF26) -> 0
A27: SUM (Add-ons) | B27: =SUM(B19:B26) -> 0 | C27: =SUM(C19:C26) -> 0 | D27: =SUM(D19:D26) -> 0 | E27: =SUM(E19:E26) -> 0 | F27: =SUM(F19:F26) -> 0 | G27: =SUM(G19:G26) -> 0 | H27: =SUM(H19:H26) -> 0 | I27: =SUM(I19:I26) -> 0 | ... AF27: =SUM(AF19:AF26) -> 0 | AG27: =SUM(B27:AF27) -> 0
A29: Units and Revenue Cancelled & Refunds - Rachio
A31: Units Cancelled (Gross) - Rachio
A32: SKU 1 - Blue | AG32: =SUM(B32:AF32) -> 0
A33: SKU 2 - Yellow | AG33: =SUM(B33:AF33) -> 0
A34: SKU 3 - Blue w/ Solar | AG34: =SUM(B34:AF34) -> 0
A35: SKU 4 - Yellow w/ Solar | AG35: =SUM(B35:AF35) -> 0
A36: SUM (SKU 1 + SKU 2) | B36: =SUM(B32:B33) -> 0 | C36: =SUM(C32:C33) -> 0 | D36: =SUM(D32:D33) -> 0 | E36: =SUM(E32:E33) -> 0 | F36: =SUM(F32:F33) -> 0 | G36: =SUM(G32:G33) -> 0 | H36: =SUM(H32:H33) -> 0 | I36: =SUM(I32:I33) -> 0 | ... AF36: =SUM(AF32:AF33) -> 0 | AG36: =SUM(B36:AF36) -> 0
A37: SUM (SKU 3 + SKU 4) | B37: =SUM(B34:B35) -> 0 | C37: =SUM(C34:C35) -> 0 | D37: =SUM(D34:D35) -> 0 | E37: =SUM(E34:E35) -> 0 | F37: =SUM(F34:F35) -> 0 | G37: =SUM(G34:G35) -> 0 | H37: =SUM(H34:H35) -> 0 | I37: =SUM(I34:I35) -> 0 | ... AF37: =SUM(AF34:AF35) -> 0 | AG37: =SUM(B37:AF37) -> 0
A39: Wall Mount | AG39: =SUM(B39:AF39) -> 0
A40: Suet Ball Holder | AG40: =SUM(B40:AF40) -> 0
A41: 3-in-1 Nutrition Set - Blue | AG41: =SUM(B41:AF41) -> 0
A42: 3-in-1 Nutrition Set - Yellow | AG42: =SUM(B42:AF42) -> 0
A43: Solar Roof Single - Blue | AG43: =SUM(B43:AF43) -> 0
A44: Solar Roof Single - Yellow | AG44: =SUM(B44:AF44) -> 0
A45: Perch Extender - Blue | AG45: =SUM(B45:AF45) -> 0
A46: Perch Extender - Yellow | AG46: =SUM(B46:AF46) -> 0
A47: SUM (Add-ons) | B47: =SUM(B39:B46) -> 0 | C47: =SUM(C39:C46) -> 0 | D47: =SUM(D39:D46) -> 0 | E47: =SUM(E39:E46) -> 0 | F47: =SUM(F39:F46) -> 0 | G47: =SUM(G39:G46) -> 0 | H47: =SUM(H39:H46) -> 0 | I47: =SUM(I39:I46) -> 0 | ... AF47: =SUM(AF39:AF46) -> 0 | AG47: =SUM(B47:AF47) -> 0
A49: Revenue Cancelled (Gross) - Rachio
A50: Hardware | AG50: =SUM(B50:AF50) -> 0
A51: Shipping | AG51: =SUM(B51:AF51) -> 0
A52: Taxes | AG52: =SUM(B52:AF52) -> 0
A53: All NA | B53: =SUM(B50:B52) -> 0 | C53: =SUM(C50:C52) -> 0 | D53: =SUM(D50:D52) -> 0 | E53: =SUM(E50:E52) -> 0 | F53: =SUM(F50:F52) -> 0 | G53: =SUM(G50:G52) -> 0 | H53: =SUM(H50:H52) -> 0 | I53: =SUM(I50:I52) -> 0 | ... AF53: =SUM(AF50:AF52) -> 0 | AG53: =SUM(B53:AF53) -> 0
A55: Hardware - Europe | AG55: =SUM(B55:AF55) -> 0
A56: Shipping - Europe | AG56: =SUM(B56:AF56) -> 0
A57: All EU | B57: =sum(B55:B56) -> 0 | C57: =sum(C55:C56) -> 0 | D57: =sum(D55:D56) -> 0 | E57: =sum(E55:E56) -> 0 | F57: =sum(F55:F56) -> 0 | G57: =sum(G55:G56) -> 0 | H57: =sum(H55:H56) -> 0 | I57: =sum(I55:I56) -> 0 | ... AF57: =sum(AF55:AF56) -> 0 | AG57: =SUM(B57:AF57) -> 0
A59: Units Refund (Gross) - Rachio
A60: SKU 1 - Blue | AG60: =SUM(B60:AF60) -> 0
A61: SKU 2 - Yellow | AG61: =SUM(B61:AF61) -> 0
A62: SKU 3 - Blue w/ Solar | AG62: =SUM(B62:AF62) -> 0
A63: SKU 4 - Yellow w/ Solar | AG63: =SUM(B63:AF63) -> 0
A64: SUM (SKU 1 + SKU 2) | B64: =SUM(B60:B61) -> 0 | C64: =SUM(C60:C61) -> 0 | D64: =SUM(D60:D61) -> 0 | E64: =SUM(E60:E61) -> 0 | F64: =SUM(F60:F61) -> 0 | G64: =SUM(G60:G61) -> 0 | H64: =SUM(H60:H61) -> 0 | I64: =SUM(I60:I61) -> 0 | ... AF64: =SUM(AF60:AF61) -> 0 | AG64: =SUM(B64:AF64) -> 0
A65: SUM (SKU 3 + SKU 4) | B65: =SUM(B62:B63) -> 0 | C65: =SUM(C62:C63) -> 0 | D65: =SUM(D62:D63) -> 0 | E65: =SUM(E62:E63) -> 0 | F65: =SUM(F62:F63) -> 0 | G65: =SUM(G62:G63) -> 0 | H65: =SUM(H62:H63) -> 0 | I65: =SUM(I62:I63) -> 0 | ... AF65: =SUM(AF62:AF63) -> 0 | AG65: =SUM(B65:AF65) -> 0
A67: Wall Mount | AG67: =SUM(B67:AF67) -> 0
A68: Suet Ball Holder | AG68: =SUM(B68:AF68) -> 0
A69: 3-in-1 Nutrition Set - Blue | AG69: =SUM(B69:AF69) -> 0
A70: 3-in-1 Nutrition Set - Yellow | AG70: =SUM(B70:AF70) -> 0
A71: Solar Roof Single - Blue | AG71: =SUM(B71:AF71) -> 0
A72: Solar Roof Single - Yellow | AG72: =SUM(B72:AF72) -> 0
A73: Perch Extender - Blue | AG73: =SUM(B73:AF73) -> 0
A74: Perch Extender - Yellow | AG74: =SUM(B74:AF74) -> 0
A75: SUM (Add-ons) | B75: =SUM(B67:B74) -> 0 | C75: =SUM(C67:C74) -> 0 | D75: =SUM(D67:D74) -> 0 | E75: =SUM(E67:E74) -> 0 | F75: =SUM(F67:F74) -> 0 | G75: =SUM(G67:G74) -> 0 | H75: =SUM(H67:H74) -> 0 | I75: =SUM(I67:I74) -> 0 | ... AF75: =SUM(AF67:AF74) -> 0 | AG75: =SUM(B75:AF75) -> 0
A77: Orders Return for Refund | AG77: =SUM(B77:AF77) -> 0
A79: Revenue Refunded (Gross) - Rachio
A80: Hardware | AG80: =SUM(B80:AF80) -> 0
A81: Shipping | AG81: =SUM(B81:AF81) -> 0
A82: Taxes | AG82: =SUM(B82:AF82) -> 0
A83: All NA | B83: =sum(B80:B82) -> 0 | C83: =sum(C80:C82) -> 0 | D83: =sum(D80:D82) -> 0 | E83: =sum(E80:E82) -> 0 | F83: =sum(F80:F82) -> 0 | G83: =sum(G80:G82) -> 0 | H83: =sum(H80:H82) -> 0 | I83: =sum(I80:I82) -> 0 | ... AF83: =sum(AF80:AF82) -> 0 | AG83: =SUM(B83:AF83) -> 0
A85: Hardware - Europe | AG85: =SUM(B85:AF85) -> 0
A86: Shipping - Europe | AG86: =SUM(B86:AF86) -> 0
A87: All EU | B87: =sum(B85:B86) -> 0 | C87: =sum(C85:C86) -> 0 | D87: =sum(D85:D86) -> 0 | E87: =sum(E85:E86) -> 0 | F87: =sum(F85:F86) -> 0 | G87: =sum(G85:G86) -> 0 | H87: =sum(H85:H86) -> 0 | I87: =sum(I85:I86) -> 0 | ... AF87: =sum(AF85:AF86) -> 0 | AG87: =SUM(B87:AF87) -> 0
A89: RETURN (Replacement Units & Claims) - Rachio
A90: SKU 1 - Blue | B90: 0 | C90: 0 | D90: 0 | E90: 0 | F90: 0 | G90: 0 | H90: 0 | I90: 0 | J90: 0 | K90: 0 | L90: 0 | M90: 0 | N90: 0 | O90: 0 | P90: 0 | Q90: 0 | R90: 0 | S90: 0 | T90: 0 | U90: 0 | V90: 0 | W90: 0 | X90: 0 | Y90: 0 | Z90: 0 | AA90: 0 | AB90: 0 | AC90: 0 | AD90: 0 | AE90: 0 | AF90: 0 | AG90: =SUM(B90:AF90) -> 0
A91: SKU 2 - Yellow | B91: 0 | C91: 0 | D91: 0 | E91: 0 | F91: 0 | G91: 0 | H91: 0 | I91: 0 | J91: 0 | K91: 0 | L91: 0 | M91: 0 | N91: 0 | O91: 0 | P91: 0 | Q91: 0 | R91: 0 | S91: 0 | T91: 0 | U91: 0 | V91: 0 | W91: 0 | X91: 0 | Y91: 0 | Z91: 0 | AA91: 0 | AB91: 0 | AC91: 0 | AD91: 0 | AE91: 0 | AF91: 0 | AG91: =SUM(B91:AF91) -> 0
A92: SKU 3 - Blue w/ Solar | B92: 0 | C92: 0 | D92: 0 | E92: 1 | F92: 0 | G92: 0 | H92: 0 | I92: 0 | J92: 0 | K92: 0 | L92: 0 | M92: 0 | N92: 0 | O92: 0 | P92: 0 | Q92: 0 | R92: 0 | S92: 0 | T92: 0 | U92: 0 | V92: 0 | W92: 0 | X92: 0 | Y92: 0 | Z92: 0 | AA92: 0 | AB92: 0 | AC92: 0 | AD92: 0 | AE92: 0 | AF92: 0 | AG92: =SUM(B92:AF92) -> 1
A93: SKU 4 - Yellow w/ Solar | B93: 0 | C93: 0 | D93: 0 | E93: 0 | F93: 0 | G93: 0 | H93: 0 | I93: 0 | J93: 0 | K93: 0 | L93: 0 | M93: 0 | N93: 0 | O93: 0 | P93: 0 | Q93: 0 | R93: 0 | S93: 0 | T93: 0 | U93: 0 | V93: 0 | W93: 0 | X93: 0 | Y93: 0 | Z93: 0 | AA93: 0 | AB93: 0 | AC93: 0 | AD93: 0 | AE93: 0 | AF93: 0 | AG93: =SUM(B93:AF93) -> 0
A94: SUM (SKU 1 + SKU 2) | B94: =B90+B91 -> 0 | C94: =C90+C91 -> 0 | D94: =D90+D91 -> 0 | E94: =E90+E91 -> 0 | F94: =F90+F91 -> 0 | G94: 0 | H94: 0 | I94: 0 | J94: 0 | K94: 0 | L94: 0 | M94: 0 | N94: 0 | O94: 0 | P94: =P90+P91 -> 0 | Q94: =Q90+Q91 -> 0 | R94: =R90+R91 -> 0 | S94: =S90+S91 -> 0 | T94: =T90+T91 -> 0 | U94: =U90+U91 -> 0 | V94: =V90+V91 -> 0 | W94: =W90+W91 -> 0 | ... AF94: =AF90+AF91 -> 0 | AG94: =SUM(B94:AF94) -> 0
A95: SUM (SKU 3 + SKU 4) | B95: =B92+B93 -> 0 | C95: =C92+C93 -> 0 | D95: =D92+D93 -> 0 | E95: =E92+E93 -> 1 | F95: =F92+F93 -> 0 | G95: =G92+G93 -> 0 | H95: =H92+H93 -> 0 | I95: =I92+I93 -> 0 | ... AF95: =AF92+AF93 -> 0 | AG95: =SUM(B95:AF95) -> 1
AG96: =SUM(B96:AF96) -> 0
A97: Wall Mount | B97: 0 | C97: 0 | D97: 0 | E97: 0 | F97: 0 | G97: 0 | H97: 0 | I97: 0 | J97: 0 | K97: 0 | L97: 0 | M97: 0 | N97: 0 | O97: 0 | P97: 0 | Q97: 0 | R97: 0 | S97: 0 | T97: 0 | U97: 0 | V97: 0 | W97: 0 | X97: 0 | Y97: 0 | Z97: 0 | AA97: 0 | AB97: 0 | AC97: 0 | AD97: 0 | AE97: 0 | AF97: 0 | AG97: =SUM(B97:AF97) -> 0
A98: Suet Ball Holder | B98: 0 | C98: 0 | D98: 0 | E98: 0 | F98: 0 | G98: 0 | H98: 0 | I98: 0 | J98: 0 | K98: 0 | L98: 0 | M98: 0 | N98: 0 | O98: 0 | P98: 0 | Q98: 0 | R98: 0 | S98: 0 | T98: 0 | U98: 0 | V98: 0 | W98: 0 | X98: 0 | Y98: 0 | Z98: 0 | AA98: 0 | AB98: 0 | AC98: 0 | AD98: 0 | AE98: 0 | AF98: 0 | AG98: =SUM(B98:AF98) -> 0
A99: 3-in-1 Nutrition Set - Blue | B99: 0 | C99: 0 | D99: 0 | E99: 0 | F99: 0 | G99: 0 | H99: 0 | I99: 0 | J99: 0 | K99: 0 | L99: 0 | M99: 0 | N99: 0 | O99: 0 | P99: 0 | Q99: 0 | R99: 0 | S99: 0 | T99: 0 | U99: 0 | V99: 0 | W99: 0 | X99: 0 | Y99: 0 | Z99: 0 | AA99: 0 | AB99: 0 | AC99: 0 | AD99: 0 | AE99: 0 | AF99: 0 | AG99: =SUM(B99:AF99) -> 0
A100: 3-in-1 Nutrition Set - Yellow | B100: 0 | C100: 0 | D100: 0 | E100: 0 | F100: 0 | G100: 0 | H100: 0 | I100: 0 | J100: 0 | K100: 0 | L100: 0 | M100: 0 | N100: 0 | O100: 0 | P100: 0 | Q100: 0 | R100: 0 | S100: 0 | T100: 0 | U100: 0 | V100: 0 | W100: 0 | X100: 0 | Y100: 0 | Z100: 0 | AA100: 0 | AB100: 0 | AC100: 0 | AD100: 0 | AE100: 0 | AF100: 0 | AG100: =SUM(B100:AF100) -> 0
A101: Solar Roof Single - Blue | B101: 0 | C101: 0 | D101: 0 | E101: 0 | F101: 0 | G101: 0 | H101: 0 | I101: 0 | J101: 0 | K101: 0 | L101: 0 | M101: 0 | N101: 0 | O101: 0 | P101: 0 | Q101: 0 | R101: 0 | S101: 0 | T101: 0 | U101: 0 | V101: 0 | W101: 0 | X101: 0 | Y101: 0 | Z101: 0 | AA101: 0 | AB101: 0 | AC101: 0 | AD101: 0 | AE101: 0 | AF101: 0 | AG101: =SUM(B101:AF101) -> 0
A102: Solar Roof Single - Yellow | B102: 0 | C102: 0 | D102: 0 | E102: 0 | F102: 0 | G102: 0 | H102: 0 | I102: 0 | J102: 0 | K102: 0 | L102: 0 | M102: 0 | N102: 0 | O102: 0 | P102: 0 | Q102: 0 | R102: 0 | S102: 0 | T102: 0 | U102: 0 | V102: 0 | W102: 0 | X102: 0 | Y102: 0 | Z102: 0 | AA102: 0 | AB102: 0 | AC102: 0 | AD102: 0 | AE102: 0 | AF102: 0 | AG102: =SUM(B102:AF102) -> 0
A103: Perch Extender - Blue | B103: 0 | C103: 0 | D103: 0 | E103: 0 | F103: 0 | G103: 0 | H103: 0 | I103: 0 | J103: 0 | K103: 0 | L103: 0 | M103: 0 | N103: 0 | O103: 0 | P103: 0 | Q103: 0 | R103: 0 | S103: 0 | T103: 0 | U103: 0 | V103: 0 | W103: 0 | X103: 0 | Y103: 0 | Z103: 0 | AA103: 0 | AB103: 0 | AC103: 0 | AD103: 0 | AE103: 0 | AF103: 0 | AG103: =SUM(B103:AF103) -> 0
A104: Perch Extender - Yellow | B104: 0 | C104: 0 | D104: 0 | E104: 0 | F104: 0 | G104: 0 | H104: 0 | I104: 0 | J104: 0 | K104: 0 | L104: 0 | M104: 0 | N104: 0 | O104: 0 | P104: 0 | Q104: 0 | R104: 0 | S104: 0 | T104: 0 | U104: 0 | V104: 0 | W104: 0 | X104: 0 | Y104: 0 | Z104: 0 | AA104: 0 | AB104: 0 | AC104: 0 | AD104: 0 | AE104: 0 | AF104: 0 | AG104: =SUM(B104:AF104) -> 0
A105: SUM (Add-ons) | B105: =SUM(B97:B101) -> 0 | C105: =SUM(C97:C101) -> 0 | D105: =SUM(D97:D101) -> 0 | E105: =SUM(E97:E101) -> 0 | F105: =SUM(F97:F101) -> 0 | G105: =SUM(G97:G101) -> 0 | H105: =SUM(H97:H101) -> 0 | I105: =SUM(I97:I101) -> 0 | ... AF105: =SUM(AF97:AF101) -> 0 | AG105: =SUM(B105:AF105) -> 0
A107: Parts
A108: Housing - Blue | B108: 0 | C108: 0 | D108: 0 | E108: 0 | F108: 0 | G108: 0 | H108: 0 | I108: 0 | J108: 0 | K108: 0 | L108: 0 | M108: 0 | N108: 0 | O108: 0 | P108: 0 | Q108: 0 | R108: 0 | S108: 0 | T108: 0 | U108: 0 | V108: 0 | W108: 0 | X108: 0 | Y108: 0 | Z108: 0 | AA108: 0 | AB108: 0 | AC108: 0 | AD108: 0 | AE108: 0 | AF108: 0 | AG108: =SUM(B108:AF108) -> 0
A109: Housing - Yellow | B109: 0 | C109: 0 | D109: 0 | E109: 0 | F109: 0 | G109: 0 | H109: 0 | I109: 0 | J109: 0 | K109: 0 | L109: 0 | M109: 0 | N109: 0 | O109: 0 | P109: 0 | Q109: 0 | R109: 0 | S109: 0 | T109: 0 | U109: 0 | V109: 0 | W109: 0 | X109: 0 | Y109: 0 | Z109: 0 | AA109: 0 | AB109: 0 | AC109: 0 | AD109: 0 | AE109: 0 | AF109: 0 | AG109: =SUM(B109:AF109) -> 0
A110: Camera Module | B110: 0 | C110: 0 | D110: 0 | E110: 0 | F110: 1 | G110: 0 | H110: 0 | I110: 0 | J110: 0 | K110: 0 | L110: 0 | M110: 0 | N110: 0 | O110: 0 | P110: 0 | Q110: 0 | R110: 0 | S110: 0 | T110: 0 | U110: 0 | V110: 0 | W110: 0 | X110: 0 | Y110: 0 | Z110: 0 | AA110: 0 | AB110: 0 | AC110: 0 | AD110: 0 | AE110: 0 | AF110: 0 | AG110: =SUM(B110:AF110) -> 1
G111: 0 | H111: 0 | I111: 0 | J111: 0 | K111: 0 | L111: 0 | M111: 0 | N111: 0 | O111: 0
A112: Orders Replaced NA | B112: 0 | C112: 0 | D112: 0 | E112: 1 | F112: 1 | G112: 0 | H112: 0 | I112: 0 | J112: 0 | K112: 0 | L112: 0 | M112: 0 | N112: 0 | O112: 0 | P112: 0 | Q112: 0 | R112: 0 | S112: 0 | T112: 0 | U112: 0 | V112: 0 | W112: 0 | X112: 0 | Y112: 0 | Z112: 0 | AA112: 0 | AB112: 0 | AC112: 0 | AD112: 0 | AE112: 0 | AF112: 0 | AG112: =SUM(B112:AF112) -> 2
A115: Weatherflow (Shopify)
A116: Revenue | B116: =Summary!B27 -> 0 | C116: =Summary!C27 -> 0 | D116: =Summary!D27 -> 0 | E116: =Summary!E27 -> 0 | F116: =Summary!F27 -> 0 | G116: =Summary!G27 -> 0 | H116: =Summary!H27 -> 317.3586 | I116: =Summary!I27 -> 0 | ... AF116: =Summary!AF27 -> 0 | AG116: =SUM(B116:AF116) -> 1142.0664
A117: Breakdown
...

Sheet PP - Results
A1: 45352 | B1: 45352 | C1: 45353 | D1: 45354 | E1: 45355 | F1: 45356 | G1: 45357 | H1: 45358 | I1: 45359 | J1: 45360 | K1: 45361 | L1: 45362 | M1: 45363 | N1: 45364 | O1: 45365 | P1: 45366 | Q1: 45367 | R1: 45368 | S1: 45369 | T1: 45370 | U1: 45371 | V1: 45372 | W1: 45373 | X1: 45374 | Y1: 45375 | Z1: 45376 | AA1: 45377 | AB1: 45378 | AC1: 45379 | AD1: 45380 | AE1: 45381 | AF1: 45382
B2: FRI | C2: SAT | D2: SUN | E2: MON | F2: TUE | G2: WED | H2: THU | I2: FRI | J2: SAT | K2: SUN | L2: MON | M2: TUE | N2: WED | O2: THU | P2: FRI | Q2: SAT | R2: SUN | S2: MON | T2: TUE | U2: WED | V2: THU | W2: FRI | X2: SAT | Y2: SUN | Z2: MON | AA2: TUE | AB2: WED | AC2: THU | AD2: FRI | AE2: SAT | AF2: SUN
A4: Number of participants | B4: ='PP - Data'!B10 -> 1259 | C4: ='PP - Data'!C10 -> 251 | D4: ='PP - Data'!D10 -> 201 | E4: ='PP - Data'!E10 -> 184 | F4: ='PP - Data'!F10 -> 159 | G4: ='PP - Data'!G10 -> 133 | H4: ='PP - Data'!H10 -> 134 | I4: ='PP - Data'!I10 -> 117 | ... AF4: ='PP - Data'!AF10 -> 46
A5: Engagement Rate | B5: =B4/Summary!B52 -> 0.64201938 | C5: =C4/Summary!C52 -> 0.60336538 | D5: =D4/Summary!D52 -> 0.57925072 | E5: =E4/Summary!E52 -> 0.58974359 | F5: =F4/Summary!F52 -> 0.6437247 | G5: =G4/Summary!G52 -> 0.62149533 | H5: =H4/Summary!H52 -> 0.64423077 | I5: =I4/Summary!I52 -> 0.585 | ... AF5: =AF4/Summary!AF52 -> 0.575
A7: Post-purchase Survey
A8: Facebook / Instagram | B8: ='PP - Data'!B12 -> 0.24861001 | C8: ='PP - Data'!C12 -> 0.30278884 | D8: ='PP - Data'!D12 -> 0.3880597 | E8: ='PP - Data'!E12 -> 0.30434783 | F8: ='PP - Data'!F12 -> 0.28301887 | G8: ='PP - Data'!G12 -> 0.28571429 | H8: ='PP - Data'!H12 -> 0.35820896 | I8: ='PP - Data'!I12 -> 0.46153846 | ... AF8: ='PP - Data'!AF12 -> 0.15217391
A9: Where on Facebook/Instagram have you heard about Bird Buddy?
A10: I saw an ad | B10: ='PP - Data'!B28 -> 0.69009585 | C10: ='PP - Data'!C28 -> 0.72368421 | D10: ='PP - Data'!D28 -> 0.75641026 | E10: ='PP - Data'!E28 -> 0.82142857 | F10: ='PP - Data'!F28 -> 0.84444444 | G10: ='PP - Data'!G28 -> 0.78947368 | H10: ='PP - Data'!H28 -> 0.75 | I10: ='PP - Data'!I28 -> 0.83333333 | ... AF10: ='PP - Data'!AF28 -> 0.85714286
A11: I saw a post about Bird Buddy on my friend's feed | B11: ='PP - Data'!B29 -> 0.057507987 | C11: ='PP - Data'!C29 -> 0.092105263 | D11: ='PP - Data'!D29 -> 0.076923077 | E11: ='PP - Data'!E29 -> 0.071428571 | F11: ='PP - Data'!F29 -> 0.088888889 | G11: ='PP - Data'!G29 -> 0.13157895 | H11: ='PP - Data'!H29 -> 0.0625 | I11: ='PP - Data'!I29 -> 0.11111111 | ... AF11: ='PP - Data'!AF29 -> 0.14285714
A12: I saw an organic post from Bird Buddy | B12: ='PP - Data'!B30 -> 0.25239617 | C12: ='PP - Data'!C30 -> 0.18421053 | D12: ='PP - Data'!D30 -> 0.16666667 | E12: ='PP - Data'!E30 -> 0.10714286 | F12: ='PP - Data'!F30 -> 0.066666667 | G12: ='PP - Data'!G30 -> 0.078947368 | H12: ='PP - Data'!H30 -> 0.1875 | I12: ='PP - Data'!I30 -> 0.055555556 | ... AF12: ='PP - Data'!AF30 -> 0
A13: Friends / Family | B13: ='PP - Data'!B13 -> 0.52025417 | C13: ='PP - Data'!C13 -> 0.52191235 | D13: ='PP - Data'!D13 -> 0.48258706 | E13: ='PP - Data'!E13 -> 0.57065217 | F13: ='PP - Data'!F13 -> 0.52201258 | G13: ='PP - Data'!G13 -> 0.56390977 | H13: ='PP - Data'!H13 -> 0.52238806 | I13: ='PP - Data'!I13 -> 0.41880342 | ... AF13: ='PP - Data'!AF13 -> 0.69565217
A14: TikTok | B14: ='PP - Data'!B14 -> 0.0023828435 | C14: ='PP - Data'!C14 -> 0.0039840637 | D14: ='PP - Data'!D14 -> 0.0049751244 | E14: ='PP - Data'!E14 -> 0.010869565 | F14: ='PP - Data'!F14 -> 0.031446541 | G14: ='PP - Data'!G14 -> 0.022556391 | H14: ='PP - Data'!H14 -> 0.014925373 | I14: ='PP - Data'!I14 -> 0.017094017 | ... AF14: ='PP - Data'!AF14 -> 0.02173913
A15: TV / Radio | B15: ='PP - Data'!B15 -> 0.016679905 | C15: ='PP - Data'!C15 -> 0.019920319 | D15: ='PP - Data'!D15 -> 0.014925373 | E15: ='PP - Data'!E15 -> 0.016304348 | F15: ='PP - Data'!F15 -> 0.012578616 | G15: ='PP - Data'!G15 -> 0.022556391 | H15: ='PP - Data'!H15 -> 0.014925373 | I15: ='PP - Data'!I15 -> 0.017094017 | ... AF15: ='PP - Data'!AF15 -> 0
A16: Blog / Article | B16: ='PP - Data'!B16 -> 0.08101668 | C16: ='PP - Data'!C16 -> 0.083665339 | D16: ='PP - Data'!D16 -> 0.044776119 | E16: ='PP - Data'!E16 -> 0.016304348 | F16: ='PP - Data'!F16 -> 0.056603774 | G16: ='PP - Data'!G16 -> 0.052631579 | H16: ='PP - Data'!H16 -> 0.029850746 | I16: ='PP - Data'!I16 -> 0.017094017 | ... AF16: ='PP - Data'!AF16 -> 0.086956522
A17: Reddit | B17: ='PP - Data'!B17 -> 0.0039714059 | C17: ='PP - Data'!C17 -> 0.0079681275 | D17: ='PP - Data'!D17 -> 0 | E17: ='PP - Data'!E17 -> 0.0054347826 | F17: ='PP - Data'!F17 -> 0.0062893082 | G17: ='PP - Data'!G17 -> 0.007518797 | H17: ='PP - Data'!H17 -> 0.0074626866 | I17: ='PP - Data'!I17 -> 0 | ... AF17: ='PP - Data'!AF17 -> 0
A18: Google, Youtube | B18: ='PP - Data'!B18 -> 0.11199365 | C18: ='PP - Data'!C18 -> 0.047808765 | D18: ='PP - Data'!D18 -> 0.059701493 | E18: ='PP - Data'!E18 -> 0.070652174 | F18: ='PP - Data'!F18 -> 0.088050314 | G18: ='PP - Data'!G18 -> 0.045112782 | H18: ='PP - Data'!H18 -> 0.052238806 | I18: ='PP - Data'!I18 -> 0.068376068 | ... AF18: ='PP - Data'!AF18 -> 0.043478261
A19: Yahoo, Bing | B19: ='PP - Data'!B19 -> 0.015091342 | C19: ='PP - Data'!C19 -> 0.011952191 | D19: ='PP - Data'!D19 -> 0.0049751244 | E19: ='PP - Data'!E19 -> 0.0054347826 | F19: ='PP - Data'!F19 -> 0 | G19: ='PP - Data'!G19 -> 0 | H19: ='PP - Data'!H19 -> 0 | I19: ='PP - Data'!I19 -> 0 | ... AF19: ='PP - Data'!AF19 -> 0
A22: Number of participants | B22: ='PP - Data'!B60 -> 1240 | C22: ='PP - Data'!C60 -> 252 | D22: ='PP - Data'!D60 -> 200 | E22: ='PP - Data'!E60 -> 186 | F22: ='PP - Data'!F60 -> 157 | G22: ='PP - Data'!G60 -> 133 | H22: ='PP - Data'!H60 -> 134 | I22: ='PP - Data'!I60 -> 117 | ... AF22: ='PP - Data'!AF60 -> 46
A23: Engagement Rate | B23: =B22/Summary!B52 -> 0.63233044 | C23: =C22/Summary!C52 -> 0.60576923 | D23: =D22/Summary!D52 -> 0.57636888 | E23: =E22/Summary!E52 -> 0.59615385 | F23: =F22/Summary!F52 -> 0.63562753 | G23: =G22/Summary!G52 -> 0.62149533 | H23: =H22/Summary!H52 -> 0.64423077 | I23: =I22/Summary!I52 -> 0.585 | ... AF23: =AF22/Summary!AF52 -> 0.575
A25: Who is this for? (sub-question 3)
A26: Just me | B26: ='PP - Data'!B62 -> 0.31129032 | C26: ='PP - Data'!C62 -> 0.3015873 | D26: ='PP - Data'!D62 -> 0.27 | E26: ='PP - Data'!E62 -> 0.29569892 | F26: ='PP - Data'!F62 -> 0.1910828 | G26: ='PP - Data'!G62 -> 0.32330827 | H26: ='PP - Data'!H62 -> 0.2238806 | I26: ='PP - Data'!I62 -> 0.2991453 | ... AF26: ='PP - Data'!AF62 -> 0.26086957
A27: Did you compare us with other smart bird feeders before purchasing? | B27: ='PP - Data'!B63 | C27: ='PP - Data'!C63 | D27: ='PP - Data'!D63 | E27: ='PP - Data'!E63 | F27: ='PP - Data'!F63 | G27: ='PP - Data'!G63 | H27: ='PP - Data'!H63 | I27: ='PP - Data'!I63 | ... AF27: ='PP - Data'!AF63
A28: Yes, I did extensive research | B28: ='PP - Data'!B64 -> 0.65025907 | C28: ='PP - Data'!C64 -> 0.61842105 | D28: ='PP - Data'!D64 -> 0.68518519 | E28: ='PP - Data'!E64 -> 0.70909091 | F28: ='PP - Data'!F64 -> 0.6 | G28: ='PP - Data'!G64 -> 0.72093023 | H28: ='PP - Data'!H64 -> 0.6 | I28: ='PP - Data'!I64 -> 0.57142857 | ... AF28: ='PP - Data'!AF64 -> 0.66666667
A29: Yes, but very briefly | B29: ='PP - Data'!B65 -> 0.30829016 | C29: ='PP - Data'!C65 -> 0.31578947 | D29: ='PP - Data'!D65 -> 0.2962963 | E29: ='PP - Data'!E65 -> 0.16363636 | F29: ='PP - Data'!F65 -> 0.33333333 | G29: ='PP - Data'!G65 -> 0.25581395 | H29: ='PP - Data'!H65 -> 0.36666667 | I29: ='PP - Data'!I65 -> 0.34285714 | ... AF29: ='PP - Data'!AF65 -> 0.33333333
A30: No, not at all | B30: ='PP - Data'!B66 -> 0.041450777 | C30: ='PP - Data'!C66 -> 0.065789474 | D30: ='PP - Data'!D66 -> 0.018518519 | E30: ='PP - Data'!E66 -> 0.12727273 | F30: ='PP - Data'!F66 -> 0.066666667 | G30: ='PP - Data'!G66 -> 0.023255814 | H30: ='PP - Data'!H66 -> 0.033333333 | I30: ='PP - Data'!I66 -> 0.085714286 | ... AF30: ='PP - Data'!AF66 -> 0
A31: How would you rate your bird knowledge? | B31: ='PP - Data'!B67 | C31: ='PP - Data'!C67 | D31: ='PP - Data'!D67 | E31: ='PP - Data'!E67 | F31: ='PP - Data'!F67 | G31: ='PP - Data'!G67 | H31: ='PP - Data'!H67 | I31: ='PP - Data'!I67 | ... AF31: ='PP - Data'!AF67
A32: Beginner (New to birding) | B32: ='PP - Data'!B119 -> 0.39378238 | C32: ='PP - Data'!C119 -> 0.44736842 | D32: ='PP - Data'!D119 -> 0.46296296 | E32: ='PP - Data'!E119 -> 0.45454545 | F32: ='PP - Data'!F119 -> 0.26666667 | G32: ='PP - Data'!G119 -> 0.46511628 | H32: ='PP - Data'!H119 -> 0.5 | I32: ='PP - Data'!I119 -> 0.42857143 | ... AF32: ='PP - Data'!AF119 -> 0.33333333
A33: Intermediate (Moderate understanding) | B33: ='PP - Data'!B120 -> 0.56994819 | C33: ='PP - Data'!C120 -> 0.47368421 | D33: ='PP - Data'!D120 -> 0.51851852 | E33: ='PP - Data'!E120 -> 0.47272727 | F33: ='PP - Data'!F120 -> 0.7 | G33: ='PP - Data'!G120 -> 0.53488372 | H33: ='PP - Data'!H120 -> 0.43333333 | I33: ='PP - Data'!I120 -> 0.51428571 | ... AF33: ='PP - Data'!AF120 -> 0.5
A34: Advanced (In-depth knowledge) | B34: ='PP - Data'!B121 -> 0.03626943 | C34: ='PP - Data'!C121 -> 0.078947368 | D34: ='PP - Data'!D121 -> 0.018518519 | E34: ='PP - Data'!E121 -> 0.072727273 | F34: ='PP - Data'!F121 -> 0.033333333 | G34: ='PP - Data'!G121 -> 0 | H34: ='PP - Data'!H121 -> 0.066666667 | I34: ='PP - Data'!I121 -> 0.057142857 | ... AF34: ='PP - Data'!AF121 -> 0.16666667
B35: ='PP - Data'!B67 | C35: ='PP - Data'!C67 | D35: ='PP - Data'!D67 | E35: ='PP - Data'!E67 | F35: ='PP - Data'!F67 | G35: ='PP - Data'!G67 | H35: ='PP - Data'!H67 | I35: ='PP - Data'!I67 | ... AF35: ='PP - Data'!AF67
A36: I will use with my family | B36: ='PP - Data'!B68 -> 0.35725806 | C36: ='PP - Data'!C68 -> 0.3968254 | D36: ='PP - Data'!D68 -> 0.355 | E36: ='PP - Data'!E68 -> 0.33870968 | F36: ='PP - Data'!F68 -> 0.38853503 | G36: ='PP - Data'!G68 -> 0.28571429 | H36: ='PP - Data'!H68 -> 0.29850746 | I36: ='PP - Data'!I68 -> 0.26495726 | ... AF36: ='PP - Data'!AF68 -> 0.36956522
A37: Did you compare us with other smart bird feeders before purchasing? | B37: ='PP - Data'!B69 | C37: ='PP - Data'!C69 | D37: ='PP - Data'!D69 | E37: ='PP - Data'!E69 | F37: ='PP - Data'!F69 | G37: ='PP - Data'!G69 | H37: ='PP - Data'!H69 | I37: ='PP - Data'!I69 | ... AF37: ='PP - Data'!AF69
A38: Yes, I did extensive research | B38: ='PP - Data'!B70 -> 0.67042889 | C38: ='PP - Data'!C70 -> 0.56 | D38: ='PP - Data'!D70 -> 0.73239437 | E38: ='PP - Data'!E70 -> 0.42857143 | F38: ='PP - Data'!F70 -> 0.62295082 | G38: ='PP - Data'!G70 -> 0.65789474 | H38: ='PP - Data'!H70 -> 0.675 | I38: ='PP - Data'!I70 -> 0.64516129 | ... AF38: ='PP - Data'!AF70 -> 0.76470588
A39: Yes, but very briefly | B39: ='PP - Data'!B71 -> 0.2979684 | C39: ='PP - Data'!C71 -> 0.4 | D39: ='PP - Data'!D71 -> 0.25352113 | E39: ='PP - Data'!E71 -> 0.52380952 | F39: ='PP - Data'!F71 -> 0.32786885 | G39: ='PP - Data'!G71 -> 0.31578947 | H39: ='PP - Data'!H71 -> 0.325 | I39: ='PP - Data'!I71 -> 0.22580645 | ... AF39: ='PP - Data'!AF71 -> 0.23529412
A40: No, not at all | B40: ='PP - Data'!B72 -> 0.031602709 | C40: ='PP - Data'!C72 -> 0.04 | D40: ='PP - Data'!D72 -> 0.014084507 | E40: ='PP - Data'!E72 -> 0.047619048 | F40: ='PP - Data'!F72 -> 0.049180328 | G40: ='PP - Data'!G72 -> 0.026315789 | H40: ='PP - Data'!H72 -> 0 | I40: ='PP - Data'!I72 -> 0.12903226 | ... AF40: ='PP - Data'!AF72 -> 0
A41: How would you rate your bird knowledge?
A42: Beginner (New to birding) | B42: ='PP - Data'!B124 -> 0.36794582 | C42: ='PP - Data'!C124 -> 0.49 | D42: ='PP - Data'!D124 -> 0.49295775 | E42: ='PP - Data'!E124 -> 0.50793651 | F42: ='PP - Data'!F124 -> 0.52459016 | G42: ='PP - Data'!G124 -> 0.52631579 | H42: ='PP - Data'!H124 -> 0.525 | I42: ='PP - Data'!I124 -> 0.64516129 | ... AF42: ='PP - Data'!AF124 -> 0.52941176
A43: Intermediate (Moderate understanding) | B43: ='PP - Data'!B125 -> 0.56207675 | C43: ='PP - Data'!C125 -> 0.46 | D43: ='PP - Data'!D125 -> 0.43661972 | E43: ='PP - Data'!E125 -> 0.49206349 | F43: ='PP - Data'!F125 -> 0.44262295 | G43: ='PP - Data'!G125 -> 0.44736842 | H43: ='PP - Data'!H125 -> 0.425 | I43: ='PP - Data'!I125 -> 0.35483871 | ... AF43: ='PP - Data'!AF125 -> 0.41176471
A44: Advanced (In-depth knowledge) | B44: ='PP - Data'!B126 -> 0.069977427 | C44: ='PP - Data'!C126 -> 0.05 | D44: ='PP - Data'!D126 -> 0.070422535 | E44: ='PP - Data'!E126 -> 0 | F44: ='PP - Data'!F126 -> 0.032786885 | G44: ='PP - Data'!G126 -> 0.026315789 | H44: ='PP - Data'!H126 -> 0.05 | I44: ='PP - Data'!I126 -> 0 | ... AF44: ='PP - Data'!AF126 -> 0.058823529
B45: ='PP - Data'!B73 | C45: ='PP - Data'!C73 | D45: ='PP - Data'!D73 | E45: ='PP - Data'!E73 | F45: ='PP - Data'!F73 | G45: ='PP - Data'!G73 | H45: ='PP - Data'!H73 | I45: ='PP - Data'!I73 | ... AF45: ='PP - Data'!AF73
A46: My parents | B46: ='PP - Data'!B74 -> 0.11854839 | C46: ='PP - Data'!C74 -> 0.13888889 | D46: ='PP - Data'!D74 -> 0.17 | E46: ='PP - Data'!E74 -> 0.15591398 | F46: ='PP - Data'!F74 -> 0.22929936 | G46: ='PP - Data'!G74 -> 0.21804511 | H46: ='PP - Data'!H74 -> 0.29104478 | I46: ='PP - Data'!I74 -> 0.22222222 | ... AF46: ='PP - Data'!AF74 -> 0.19565217
A47: Did you compare us with other smart bird feeders before purchasing? | B47: ='PP - Data'!B75 | C47: ='PP - Data'!C75 | D47: ='PP - Data'!D75 | E47: ='PP - Data'!E75 | F47: ='PP - Data'!F75 | G47: ='PP - Data'!G75 | H47: ='PP - Data'!H75 | I47: ='PP - Data'!I75 | ... AF47: ='PP - Data'!AF75
A48: Yes, I did extensive research | B48: ='PP - Data'!B76 -> 0.46258503 | C48: ='PP - Data'!C76 -> 0.45714286 | D48: ='PP - Data'!D76 -> 0.5 | E48: ='PP - Data'!E76 -> 0.44827586 | F48: ='PP - Data'!F76 -> 0.41666667 | G48: ='PP - Data'!G76 -> 0.44827586 | H48: ='PP - Data'!H76 -> 0.64102564 | I48: ='PP - Data'!I76 -> 0.46153846 | ... AF48: ='PP - Data'!AF76 -> 0.77777778
A49: Yes, but very briefly | B49: ='PP - Data'!B77 -> 0.42857143 | C49: ='PP - Data'!C77 -> 0.42857143 | D49: ='PP - Data'!D77 -> 0.44117647 | E49: ='PP - Data'!E77 -> 0.37931034 | F49: ='PP - Data'!F77 -> 0.44444444 | G49: ='PP - Data'!G77 -> 0.27586207 | H49: ='PP - Data'!H77 -> 0.28205128 | I49: ='PP - Data'!I77 -> 0.42307692 | ... AF49: ='PP - Data'!AF77 -> 0.22222222
A50: No, not at all | B50: ='PP - Data'!B78 -> 0.10884354 | C50: ='PP - Data'!C78 -> 0.11428571 | D50: ='PP - Data'!D78 -> 0.058823529 | E50: ='PP - Data'!E78 -> 0.17241379 | F50: ='PP - Data'!F78 -> 0.13888889 | G50: ='PP - Data'!G78 -> 0.27586207 | H50: ='PP - Data'!H78 -> 0.076923077 | I50: ='PP - Data'!I78 -> 0.11538462 | ... AF50: ='PP - Data'!AF78 -> 0
A51: How would you rate the bird knowledge of the person receiving the gift?
A52: Beginner (New to birding) | B52: ='PP - Data'!B130 -> 0.34693878 | C52: ='PP - Data'!C130 -> 0.34285714 | D52: ='PP - Data'!D130 -> 0.47058824 | E52: ='PP - Data'!E130 -> 0.31034483 | F52: ='PP - Data'!F130 -> 0.30555556 | G52: ='PP - Data'!G130 -> 0.17241379 | H52: ='PP - Data'!H130 -> 0.28205128 | I52: ='PP - Data'!I130 -> 0.30769231 | ... AF52: ='PP - Data'!AF130 -> 0.44444444
A53: Intermediate (Moderate understanding) | B53: ='PP - Data'!B131 -> 0.54421769 | C53: ='PP - Data'!C131 -> 0.57142857 | D53: ='PP - Data'!D131 -> 0.47058824 | E53: ='PP - Data'!E131 -> 0.51724138 | F53: ='PP - Data'!F131 -> 0.55555556 | G53: ='PP - Data'!G131 -> 0.72413793 | H53: ='PP - Data'!H131 -> 0.48717949 | I53: ='PP - Data'!I131 -> 0.65384615 | ... AF53: ='PP - Data'!AF131 -> 0.44444444
A54: Advanced (In-depth knowledge) | B54: ='PP - Data'!B132 -> 0.10884354 | C54: ='PP - Data'!C132 -> 0.085714286 | D54: ='PP - Data'!D132 -> 0.058823529 | E54: ='PP - Data'!E132 -> 0.17241379 | F54: ='PP - Data'!F132 -> 0.13888889 | G54: ='PP - Data'!G132 -> 0.10344828 | H54: ='PP - Data'!H132 -> 0.23076923 | I54: ='PP - Data'!I132 -> 0.038461538 | ... AF54: ='PP - Data'!AF132 -> 0.11111111
B55: ='PP - Data'!B79 | C55: ='PP - Data'!C79 | D55: ='PP - Data'!D79 | E55: ='PP - Data'!E79 | F55: ='PP - Data'!F79 | G55: ='PP - Data'!G79 | H55: ='PP - Data'!H79 | I55: ='PP - Data'!I79 | ... AF55: ='PP - Data'!AF79
A56: Spouse | B56: ='PP - Data'!B80 -> 0.21290323 | C56: ='PP - Data'!C80 -> 0.16269841 | D56: ='PP - Data'!D80 -> 0.205 | E56: ='PP - Data'!E80 -> 0.20967742 | F56: ='PP - Data'!F80 -> 0.1910828 | G56: ='PP - Data'!G80 -> 0.17293233 | H56: ='PP - Data'!H80 -> 0.18656716 | I56: ='PP - Data'!I80 -> 0.21367521 | ... AF56: ='PP - Data'!AF80 -> 0.17391304
A57: Did you compare us with other smart bird feeders before purchasing?
A58: Yes, I did extensive research | B58: ='PP - Data'!B135 -> 0.25378788 | C58: ='PP - Data'!C135 -> 0.3902439 | D58: ='PP - Data'!D135 -> 0.48780488 | E58: ='PP - Data'!E135 -> 0.43589744 | F58: ='PP - Data'!F135 -> 0.36666667 | G58: ='PP - Data'!G135 -> 0.43478261 | H58: ='PP - Data'!H135 -> 0.44 | I58: ='PP - Data'!I135 -> 0.32 | ... AF58: ='PP - Data'!AF135 -> 0.5
A59: Yes, but very briefly | B59: ='PP - Data'!B136 -> 0.54166667 | C59: ='PP - Data'!C136 -> 0.46341463 | D59: ='PP - Data'!D136 -> 0.43902439 | E59: ='PP - Data'!E136 -> 0.56410256 | F59: ='PP - Data'!F136 -> 0.53333333 | G59: ='PP - Data'!G136 -> 0.52173913 | H59: ='PP - Data'!H136 -> 0.48 | I59: ='PP - Data'!I136 -> 0.64 | ... AF59: ='PP - Data'!AF136 -> 0.5
A60: No, not at all | B60: ='PP - Data'!B137 -> 0.20454545 | C60: ='PP - Data'!C137 -> 0.14634146 | D60: ='PP - Data'!D137 -> 0.073170732 | E60: ='PP - Data'!E137 -> 0 | F60: ='PP - Data'!F137 -> 0.1 | G60: ='PP - Data'!G137 -> 0.043478261 | H60: ='PP - Data'!H137 -> 0.08 | I60: ='PP - Data'!I137 -> 0.04 | ... AF60: ='PP - Data'!AF137 -> 0
A61: How would you rate the bird knowledge of the person receiving the gift?
A62: Beginner (New to birding) | B62: ='PP - Data'!B135 -> 0.25378788 | C62: ='PP - Data'!C135 -> 0.3902439 | D62: ='PP - Data'!D135 -> 0.48780488 | E62: ='PP - Data'!E135 -> 0.43589744 | F62: ='PP - Data'!F135 -> 0.36666667 | G62: ='PP - Data'!G135 -> 0.43478261 | H62: ='PP - Data'!H135 -> 0.44 | I62: ='PP - Data'!I135 -> 0.32 | ... AF62: ='PP - Data'!AF135 -> 0.5
A63: Intermediate (Moderate understanding) | B63: ='PP - Data'!B136 -> 0.54166667 | C63: ='PP - Data'!C136 -> 0.46341463 | D63: ='PP - Data'!D136 -> 0.43902439 | E63: ='PP - Data'!E136 -> 0.56410256 | F63: ='PP - Data'!F136 -> 0.53333333 | G63: ='PP - Data'!G136 -> 0.52173913 | H63: ='PP - Data'!H136 -> 0.48 | I63: ='PP - Data'!I136 -> 0.64 | ... AF63: ='PP - Data'!AF136 -> 0.5
A64: Advanced (In-depth knowledge) | B64: ='PP - Data'!B137 -> 0.20454545 | C64: ='PP - Data'!C137 -> 0.14634146 | D64: ='PP - Data'!D137 -> 0.073170732 | E64: ='PP - Data'!E137 -> 0 | F64: ='PP - Data'!F137 -> 0.1 | G64: ='PP - Data'!G137 -> 0.043478261 | H64: ='PP - Data'!H137 -> 0.08 | I64: ='PP - Data'!I137 -> 0.04 | ... AF64: ='PP - Data'!AF137 -> 0

Sheet PP - Data
A1: Post-purchase Survey | B1: 45352 | C1: 45353 | D1: 45354 | E1: 45355 | F1: 45356 | G1: 45357 | H1: 45358 | I1: 45359 | J1: 45360 | K1: 45361 | L1: 45362 | M1: 45363 | N1: 45364 | O1: 45365 | P1: 45366 | Q1: 45367 | R1: 45368 | S1: 45369 | T1: 45370 | U1: 45371 | V1: 45372 | W1: 45373 | X1: 45374 | Y1: 45375 | Z1: 45376 | AA1: 45377 | AB1: 45378 | AC1: 45379 | AD1: 45380 | AE1: 45381 | AF1: 45382 | AG1: Total | AH1: %
A2: Facebook / Instagram | B2: 313 | C2: 76 | D2: 78 | E2: 56 | F2: 45 | G2: 38 | H2: 48 | I2: 54 | J2: 44 | K2: 47 | L2: 32 | M2: 12 | N2: 14 | O2: 24 | P2: 13 | Q2: 12 | R2: 8 | S2: 8 | T2: 3 | U2: 7 | V2: 7 | W2: 17 | X2: 11 | Y2: 14 | Z2: 10 | AA2: 9 | AB2: 9 | AC2: 12 | AD2: 1 | AE2: 12 | AF2: 7 | AG2: =SUM(B2:AF2) -> 1041 | AH2: =iferror(AG2/AG$10,"") -> 0.26822984
A3: Friends / Family | B3: 655 | C3: 131 | D3: 97 | E3: 105 | F3: 83 | G3: 75 | H3: 70 | I3: 49 | J3: 73 | K3: 80 | L3: 48 | M3: 38 | N3: 34 | O3: 28 | P3: 21 | Q3: 42 | R3: 31 | S3: 35 | T3: 19 | U3: 41 | V3: 28 | W3: 36 | X3: 29 | Y3: 37 | Z3: 38 | AA3: 24 | AB3: 23 | AC3: 31 | AD3: 20 | AE3: 40 | AF3: 32 | AG3: =SUM(B3:AF3) -> 2093 | AH3: =iferror(AG3/AG$10,"") -> 0.539294
A4: TikTok | B4: 3 | C4: 1 | D4: 1 | E4: 2 | F4: 5 | G4: 3 | H4: 2 | I4: 2 | J4: 2 | K4: 3 | L4: 1 | M4: 3 | N4: 1 | O4: 3 | P4: 0 | Q4: 1 | R4: 2 | S4: 1 | T4: 1 | U4: 0 | V4: 1 | W4: 0 | X4: 1 | Y4: 1 | Z4: 4 | AA4: 3 | AB4: 0 | AC4: 0 | AD4: 1 | AE4: 2 | AF4: 1 | AG4: =SUM(B4:AF4) -> 51 | AH4: =iferror(AG4/AG$10,"") -> 0.013140943
A5: TV / Radio | B5: 21 | C5: 5 | D5: 3 | E5: 3 | F5: 2 | G5: 3 | H5: 2 | I5: 2 | J5: 0 | K5: 2 | L5: 3 | M5: 1 | N5: 1 | O5: 0 | P5: 2 | Q5: 1 | R5: 0 | S5: 0 | T5: 0 | U5: 2 | V5: 1 | W5: 0 | X5: 0 | Y5: 2 | Z5: 0 | AA5: 0 | AB5: 2 | AC5: 0 | AD5: 1 | AE5: 0 | AF5: 0 | AG5: =SUM(B5:AF5) -> 59 | AH5: =iferror(AG5/AG$10,"") -> 0.015202267
A6: Blog / Article | B6: 102 | C6: 21 | D6: 9 | E6: 3 | F6: 9 | G6: 7 | H6: 4 | I6: 2 | J6: 10 | K6: 6 | L6: 4 | M6: 6 | N6: 0 | O6: 3 | P6: 2 | Q6: 2 | R6: 2 | S6: 1 | T6: 3 | U6: 2 | V6: 2 | W6: 1 | X6: 14 | Y6: 12 | Z6: 5 | AA6: 6 | AB6: 1 | AC6: 2 | AD6: 0 | AE6: 0 | AF6: 4 | AG6: =SUM(B6:AF6) -> 245 | AH6: =iferror(AG6/AG$10,"") -> 0.06312806
A7: Reddit | B7: 5 | C7: 2 | D7: 0 | E7: 1 | F7: 1 | G7: 1 | H7: 1 | I7: 0 | J7: 3 | K7: 4 | L7: 0 | M7: 2 | N7: 2 | O7: 0 | P7: 1 | Q7: 1 | R7: 0 | S7: 1 | T7: 1 | U7: 0 | V7: 2 | W7: 0 | X7: 1 | Y7: 2 | Z7: 0 | AA7: 0 | AB7: 2 | AC7: 0 | AD7: 1 | AE7: 1 | AF7: 0 | AG7: =SUM(B7:AF7) -> 35 | AH7: =iferror(AG7/AG$10,"") -> 0.0090182943
A8: Google, Youtube | B8: 141 | C8: 12 | D8: 12 | E8: 13 | F8: 14 | G8: 6 | H8: 7 | I8: 8 | J8: 19 | K8: 9 | L8: 9 | M8: 4 | N8: 3 | O8: 3 | P8: 3 | Q8: 6 | R8: 3 | S8: 4 | T8: 3 | U8: 5 | V8: 4 | W8: 2 | X8: 2 | Y8: 4 | Z8: 7 | AA8: 3 | AB8: 6 | AC8: 7 | AD8: 4 | AE8: 4 | AF8: 2 | AG8: =SUM(B8:AF8) -> 329 | AH8: =iferror(AG8/AG$10,"") -> 0.084771966
A9: Yahoo, Bing | B9: 19 | C9: 3 | D9: 1 | E9: 1 | F9: 0 | G9: 0 | H9: 0 | I9: 0 | J9: 2 | K9: 1 | L9: 0 | M9: 0 | N9: 0 | O9: 0 | P9: 0 | Q9: 0 | R9: 0 | S9: 0 | T9: 0 | U9: 0 | V9: 0 | W9: 0 | X9: 0 | Y9: 0 | Z9: 0 | AA9: 0 | AB9: 1 | AC9: 0 | AD9: 0 | AE9: 0 | AF9: 0 | AG9: =SUM(B9:AF9) -> 28 | AH9: =iferror(AG9/AG$10,"") -> 0.0072146354
A10: Total submissions: | B10: =SUM(B2:B9) -> 1259 | C10: =SUM(C2:C9) -> 251 | D10: =SUM(D2:D9) -> 201 | E10: =SUM(E2:E9) -> 184 | F10: =SUM(F2:F9) -> 159 | G10: =SUM(G2:G9) -> 133 | H10: =SUM(H2:H9) -> 134 | I10: =SUM(I2:I9) -> 117 | ... AF10: =SUM(AF2:AF9) -> 46 | AG10: =SUM(B10:AF10) -> 3881 | AH10: =SUM(AH2:AH9) -> 1
A11: Post-purchase Survey Percentage
A12: Facebook / Instagram | B12: =iferror(B2/B$10,"") -> 0.24861001 | C12: =iferror(C2/C$10,"") -> 0.30278884 | D12: =iferror(D2/D$10,"") -> 0.3880597 | E12: =iferror(E2/E$10,"") -> 0.30434783 | F12: =iferror(F2/F$10,"") -> 0.28301887 | G12: =iferror(G2/G$10,"") -> 0.28571429 | H12: =iferror(H2/H$10,"") -> 0.35820896 | I12: =iferror(I2/I$10,"") -> 0.46153846 | ... AF12: =iferror(AF2/AF$10,"") -> 0.15217391
A13: Friends / Family | B13: =iferror(B3/B$10,"") -> 0.52025417 | C13: =iferror(C3/C$10,"") -> 0.52191235 | D13: =iferror(D3/D$10,"") -> 0.48258706 | E13: =iferror(E3/E$10,"") -> 0.57065217 | F13: =iferror(F3/F$10,"") -> 0.52201258 | G13: =iferror(G3/G$10,"") -> 0.56390977 | H13: =iferror(H3/H$10,"") -> 0.52238806 | I13: =iferror(I3/I$10,"") -> 0.41880342 | ... AF13: =iferror(AF3/AF$10,"") -> 0.69565217
A14: TikTok | B14: =iferror(B4/B$10,"") -> 0.0023828435 | C14: =iferror(C4/C$10,"") -> 0.0039840637 | D14: =iferror(D4/D$10,"") -> 0.0049751244 | E14: =iferror(E4/E$10,"") -> 0.010869565 | F14: =iferror(F4/F$10,"") -> 0.031446541 | G14: =iferror(G4/G$10,"") -> 0.022556391 | H14: =iferror(H4/H$10,"") -> 0.014925373 | I14: =iferror(I4/I$10,"") -> 0.017094017 | ... AF14: =iferror(AF4/AF$10,"") -> 0.02173913
A15: TV / Radio | B15: =iferror(B5/B$10,"") -> 0.016679905 | C15: =iferror(C5/C$10,"") -> 0.019920319 | D15: =iferror(D5/D$10,"") -> 0.014925373 | E15: =iferror(E5/E$10,"") -> 0.016304348 | F15: =iferror(F5/F$10,"") -> 0.012578616 | G15: =iferror(G5/G$10,"") -> 0.022556391 | H15: =iferror(H5/H$10,"") -> 0.014925373 | I15: =iferror(I5/I$10,"") -> 0.017094017 | ... AF15: =iferror(AF5/AF$10,"") -> 0
A16: Blog / Article | B16: =iferror(B6/B$10,"") -> 0.08101668 | C16: =iferror(C6/C$10,"") -> 0.083665339 | D16: =iferror(D6/D$10,"") -> 0.044776119 | E16: =iferror(E6/E$10,"") -> 0.016304348 | F16: =iferror(F6/F$10,"") -> 0.056603774 | G16: =iferror(G6/G$10,"") -> 0.052631579 | H16: =iferror(H6/H$10,"") -> 0.029850746 | I16: =iferror(I6/I$10,"") -> 0.017094017 | ... AF16: =iferror(AF6/AF$10,"") -> 0.086956522
A17: Reddit | B17: =iferror(B7/B$10,"") -> 0.0039714059 | C17: =iferror(C7/C$10,"") -> 0.0079681275 | D17: =iferror(D7/D$10,"") -> 0 | E17: =iferror(E7/E$10,"") -> 0.0054347826 | F17: =iferror(F7/F$10,"") -> 0.0062893082 | G17: =iferror(G7/G$10,"") -> 0.007518797 | H17: =iferror(H7/H$10,"") -> 0.0074626866 | I17: =iferror(I7/I$10,"") -> 0 | ... AF17: =iferror(AF7/AF$10,"") -> 0
A18: Google, Youtube | B18: =iferror(B8/B$10,"") -> 0.11199365 | C18: =iferror(C8/C$10,"") -> 0.047808765 | D18: =iferror(D8/D$10,"") -> 0.059701493 | E18: =iferror(E8/E$10,"") -> 0.070652174 | F18: =iferror(F8/F$10,"") -> 0.088050314 | G18: =iferror(G8/G$10,"") -> 0.045112782 | H18: =iferror(H8/H$10,"") -> 0.052238806 | I18: =iferror(I8/I$10,"") -> 0.068376068 | ... AF18: =iferror(AF8/AF$10,"") -> 0.043478261
A19: Yahoo, Bing | B19: =iferror(B9/B$10,"") -> 0.015091342 | C19: =iferror(C9/C$10,"") -> 0.011952191 | D19: =iferror(D9/D$10,"") -> 0.0049751244 | E19: =iferror(E9/E$10,"") -> 0.0054347826 | F19: =iferror(F9/F$10,"") -> 0 | G19: =iferror(G9/G$10,"") -> 0 | H19: =iferror(H9/H$10,"") -> 0 | I19: =iferror(I9/I$10,"") -> 0 | ... AF19: =iferror(AF9/AF$10,"") -> 0
A22: Where on FB/IG have you heard about Bird Buddy?
A23: I saw an ad | B23: 216 | C23: 55 | D23: 59 | E23: 46 | F23: 38 | G23: 30 | H23: 36 | I23: 45 | J23: 34 | K23: 38 | L23: 23 | M23: 10 | N23: 11 | O23: 15 | P23: 12 | Q23: 8 | R23: 4 | S23: 6 | T23: 3 | U23: 5 | V23: 4 | W23: 12 | X23: 4 | Y23: 11 | Z23: 5 | AA23: 7 | AB23: 6 | AC23: 11 | AD23: 1 | AE23: 8 | AF23: 6 | AG23: =SUM(B23:AF23) -> 769 | AH23: =iferror(AG23/AG$26,"") -> 0.73871278
A24: I saw a post about Bird Buddy on my friend's feed | B24: 18 | C24: 7 | D24: 6 | E24: 4 | F24: 4 | G24: 5 | H24: 3 | I24: 6 | J24: 4 | K24: 4 | L24: 5 | M24: 0 | N24: 1 | O24: 5 | P24: 0 | Q24: 1 | R24: 2 | S24: 1 | T24: 0 | U24: 1 | V24: 3 | W24: 2 | X24: 3 | Y24: 3 | Z24: 2 | AA24: 0 | AB24: 3 | AC24: 1 | AD24: 0 | AE24: 2 | AF24: 1 | AG24: =SUM(B24:AF24) -> 97 | AH24: =iferror(AG24/AG$26,"") -> 0.093179635
A25: I saw an organic post from Bird Buddy | B25: 79 | C25: 14 | D25: 13 | E25: 6 | F25: 3 | G25: 3 | H25: 9 | I25: 3 | J25: 6 | K25: 5 | L25: 4 | M25: 2 | N25: 2 | O25: 4 | P25: 1 | Q25: 3 | R25: 2 | S25: 1 | T25: 0 | U25: 1 | V25: 0 | W25: 3 | X25: 4 | Y25: 0 | Z25: 3 | AA25: 2 | AB25: 0 | AC25: 0 | AD25: 0 | AE25: 2 | AF25: 0 | AG25: =SUM(B25:AF25) -> 175 | AH25: =iferror(AG25/AG$26,"") -> 0.16810759
A26: Total submissions: | B26: =SUM(B23:B25) -> 313 | C26: =SUM(C23:C25) -> 76 | D26: =SUM(D23:D25) -> 78 | E26: =SUM(E23:E25) -> 56 | F26: =SUM(F23:F25) -> 45 | G26: =SUM(G23:G25) -> 38 | H26: =SUM(H23:H25) -> 48 | I26: =SUM(I23:I25) -> 54 | ... AF26: =SUM(AF23:AF25) -> 7 | AG26: =SUM(B26:AF26) -> 1041 | AH26: =SUM(AH23:AH25) -> 1
A27: % Where on FB/IG have you heard about Bird Buddy?
A28: I saw an ad | B28: =iferror(B23/B$26,"") -> 0.69009585 | C28: =iferror(C23/C$26,"") -> 0.72368421 | D28: =iferror(D23/D$26,"") -> 0.75641026 | E28: =iferror(E23/E$26,"") -> 0.82142857 | F28: =iferror(F23/F$26,"") -> 0.84444444 | G28: =iferror(G23/G$26,"") -> 0.78947368 | H28: =iferror(H23/H$26,"") -> 0.75 | I28: =iferror(I23/I$26,"") -> 0.83333333 | ... AF28: =iferror(AF23/AF$26,"") -> 0.85714286
A29: I saw a post about Bird Buddy on my friend's feed | B29: =iferror(B24/B$26,"") -> 0.057507987 | C29: =iferror(C24/C$26,"") -> 0.092105263 | D29: =iferror(D24/D$26,"") -> 0.076923077 | E29: =iferror(E24/E$26,"") -> 0.071428571 | F29: =iferror(F24/F$26,"") -> 0.088888889 | G29: =iferror(G24/G$26,"") -> 0.13157895 | H29: =iferror(H24/H$26,"") -> 0.0625 | I29: =iferror(I24/I$26,"") -> 0.11111111 | ... AF29: =iferror(AF24/AF$26,"") -> 0.14285714
A30: I saw an organic post from Bird Buddy | B30: =iferror(B25/B$26,"") -> 0.25239617 | C30: =iferror(C25/C$26,"") -> 0.18421053 | D30: =iferror(D25/D$26,"") -> 0.16666667 | E30: =iferror(E25/E$26,"") -> 0.10714286 | F30: =iferror(F25/F$26,"") -> 0.066666667 | G30: =iferror(G25/G$26,"") -> 0.078947368 | H30: =iferror(H25/H$26,"") -> 0.1875 | I30: =iferror(I25/I$26,"") -> 0.055555556 | ... AF30: =iferror(AF25/AF$26,"") -> 0
A35: Who is this for? (sub-question 3)
A36: Just me | B36: =B41 -> 386 | C36: =C41 -> 76 | D36: =D41 -> 54 | E36: =E41 -> 55 | F36: =F41 -> 30 | G36: =G41 -> 43 | H36: =H41 -> 30 | I36: =I41 -> 35 | ... AF36: =AF41 -> 12
A37: How important do you find acquiring knowledge in bird feeding?
A38: Very, I love learning about birds | B38: 251 | C38: 47 | D38: 37 | E38: 39 | F38: 18 | G38: 31 | H38: 18 | I38: 20 | J38: 23 | K38: 32 | L38: 18 | M38: 14 | N38: 8 | O38: 10 | P38: 7 | Q38: 18 | R38: 15 | S38: 7 | T38: 7 | U38: 12 | V38: 8 | W38: 6 | X38: 12 | Y38: 14 | Z38: 4 | AA38: 12 | AB38: 10 | AC38: 12 | AD38: 4 | AE38: 11 | AF38: 8 | AG38: =SUM(B38:AF38) -> 733 | AH38: =iferror(AG38/AG$41,"") -> 0.66214995
A39: It's not the main point for me, but nice | B39: 119 | C39: 24 | D39: 16 | E39: 9 | F39: 10 | G39: 11 | H39: 11 | I39: 12 | J39: 8 | K39: 16 | L39: 5 | M39: 7 | N39: 7 | O39: 3 | P39: 2 | Q39: 2 | R39: 3 | S39: 5 | T39: 3 | U39: 4 | V39: 2 | W39: 3 | X39: 1 | Y39: 4 | Z39: 8 | AA39: 2 | AB39: 3 | AC39: 5 | AD39: 2 | AE39: 5 | AF39: 4 | AG39: =SUM(B39:AF39) -> 316 | AH39: =iferror(AG39/AG$41,"") -> 0.28545619
A40: Not at all | B40: 16 | C40: 5 | D40: 1 | E40: 7 | F40: 2 | G40: 1 | H40: 1 | I40: 3 | J40: 0 | K40: 7 | L40: 1 | M40: 0 | N40: 1 | O40: 1 | P40: 2 | Q40: 1 | R40: 0 | S40: 0 | T40: 1 | U40: 0 | V40: 1 | W40: 1 | X40: 1 | Y40: 1 | Z40: 0 | AA40: 0 | AB40: 0 | AC40: 1 | AD40: 1 | AE40: 2 | AF40: 0 | AG40: =SUM(B40:AF40) -> 58 | AH40: =iferror(AG40/AG$41,"") -> 0.052393857
A41: Total submissions: | B41: =SUM(B38:B40) -> 386 | C41: =SUM(C38:C40) -> 76 | D41: =SUM(D38:D40) -> 54 | E41: =SUM(E38:E40) -> 55 | F41: =SUM(F38:F40) -> 30 | G41: =SUM(G38:G40) -> 43 | H41: =SUM(H38:H40) -> 30 | I41: =SUM(I38:I40) -> 35 | ... AF41: =SUM(AF38:AF40) -> 12 | AG41: =SUM(B41:AF41) -> 1107 | AH41: =SUM(AH38:AH40) -> 1
A42: I will use with my family | B42: =B47 -> 443 | C42: =C47 -> 100 | D42: =D47 -> 71 | E42: =E47 -> 63 | F42: =F47 -> 61 | G42: =G47 -> 38 | H42: =H47 -> 40 | I42: =I47 -> 31 | ... AF42: =AF47 -> 17
A43: How important do you find acquiring knowledge in bird feeding?
A44: Very, I love learning about birds | B44: 297 | C44: 56 | D44: 52 | E44: 27 | F44: 38 | G44: 25 | H44: 27 | I44: 20 | J44: 33 | K44: 31 | L44: 18 | M44: 17 | N44: 10 | O44: 14 | P44: 7 | Q44: 10 | R44: 9 | S44: 13 | T44: 3 | U44: 12 | V44: 8 | W44: 10 | X44: 12 | Y44: 16 | Z44: 11 | AA44: 4 | AB44: 8 | AC44: 9 | AD44: 2 | AE44: 8 | AF44: 13 | AG44: =SUM(B44:AF44) -> 820 | AH44: =iferror(AG44/AG$47,"") -> 0.625
A45: It's not the main point for me, but nice | B45: 132 | C45: 40 | D45: 18 | E45: 33 | F45: 20 | G45: 12 | H45: 13 | I45: 7 | J45: 24 | K45: 16 | L45: 11 | M45: 2 | N45: 6 | O45: 5 | P45: 4 | Q45: 12 | R45: 3 | S45: 3 | T45: 6 | U45: 7 | V45: 5 | W45: 6 | X45: 6 | Y45: 7 | Z45: 4 | AA45: 8 | AB45: 6 | AC45: 6 | AD45: 2 | AE45: 5 | AF45: 4 | AG45: =SUM(B45:AF45) -> 433 | AH45: =iferror(AG45/AG$47,"") -> 0.33003049
A46: Not at all | B46: 14 | C46: 4 | D46: 1 | E46: 3 | F46: 3 | G46: 1 | H46: 0 | I46: 4 | J46: 5 | K46: 0 | L46: 1 | M46: 2 | N46: 3 | O46: 0 | P46: 2 | Q46: 1 | R46: 1 | S46: 1 | T46: 0 | U46: 0 | V46: 2 | W46: 2 | X46: 2 | Y46: 0 | Z46: 1 | AA46: 4 | AB46: 1 | AC46: 1 | AD46: 0 | AE46: 0 | AF46: 0 | AG46: =SUM(B46:AF46) -> 59 | AH46: =iferror(AG46/AG$47,"") -> 0.044969512
A47: Total submissions: | B47: =SUM(B44:B46) -> 443 | C47: =SUM(C44:C46) -> 100 | D47: =SUM(D44:D46) -> 71 | E47: =SUM(E44:E46) -> 63 | F47: =SUM(F44:F46) -> 61 | G47: =SUM(G44:G46) -> 38 | H47: =SUM(H44:H46) -> 40 | I47: =SUM(I44:I46) -> 31 | ... AF47: =SUM(AF44:AF46) -> 17 | AG47: =SUM(B47:AF47) -> 1312 | AH47: =SUM(AH44:AH46) -> 1
A48: My parents | B48: =B53 -> 147 | C48: =C53 -> 35 | D48: =D53 -> 34 | E48: =E53 -> 29 | F48: =F53 -> 36 | G48: =G53 -> 29 | H48: =H53 -> 39 | I48: =I53 -> 26 | ... AF48: =AF53 -> 9
A49: How important do you find acquiring knowledge in bird feeding?
A50: Very, I love learning about birds | B50: 68 | C50: 16 | D50: 17 | E50: 13 | F50: 15 | G50: 13 | H50: 25 | I50: 12 | J50: 8 | K50: 9 | L50: 12 | M50: 1 | N50: 4 | O50: 7 | P50: 6 | Q50: 4 | R50: 6 | S50: 6 | T50: 4 | U50: 5 | V50: 2 | W50: 10 | X50: 4 | Y50: 3 | Z50: 6 | AA50: 2 | AB50: 2 | AC50: 4 | AD50: 1 | AE50: 8 | AF50: 7 | AG50: =SUM(B50:AF50) -> 300 | AH50: =iferror(AG50/AG$53,"") -> 0.45592705
A51: It's not the main point for me, but nice | B51: 63 | C51: 15 | D51: 15 | E51: 11 | F51: 16 | G51: 8 | H51: 11 | I51: 11 | J51: 18 | K51: 10 | L51: 8 | M51: 4 | N51: 5 | O51: 4 | P51: 3 | Q51: 3 | R51: 8 | S51: 3 | T51: 0 | U51: 5 | V51: 3 | W51: 5 | X51: 4 | Y51: 9 | Z51: 10 | AA51: 2 | AB51: 4 | AC51: 4 | AD51: 2 | AE51: 7 | AF51: 2 | AG51: =SUM(B51:AF51) -> 273 | AH51: =iferror(AG51/AG$53,"") -> 0.41489362
A52: Not at all | B52: 16 | C52: 4 | D52: 2 | E52: 5 | F52: 5 | G52: 8 | H52: 3 | I52: 3 | J52: 2 | K52: 6 | L52: 1 | M52: 4 | N52: 0 | O52: 0 | P52: 2 | Q52: 1 | R52: 0 | S52: 2 | T52: 2 | U52: 2 | V52: 3 | W52: 4 | X52: 3 | Y52: 1 | Z52: 1 | AA52: 1 | AB52: 1 | AC52: 0 | AD52: 2 | AE52: 1 | AF52: 0 | AG52: =SUM(B52:AF52) -> 85 | AH52: =iferror(AG52/AG$53,"") -> 0.12917933
A53: Total submissions: | B53: =SUM(B50:B52) -> 147 | C53: =SUM(C50:C52) -> 35 | D53: =SUM(D50:D52) -> 34 | E53: =SUM(E50:E52) -> 29 | F53: =SUM(F50:F52) -> 36 | G53: =SUM(G50:G52) -> 29 | H53: =SUM(H50:H52) -> 39 | I53: =SUM(I50:I52) -> 26 | ... AF53: =SUM(AF50:AF52) -> 9 | AG53: =SUM(B53:AF53) -> 658 | AH53: =SUM(AH50:AH52) -> 1
A54: Spouse | B54: =B59 -> 264 | C54: =C59 -> 41 | D54: =D59 -> 41 | E54: =E59 -> 39 | F54: =F59 -> 30 | G54: =G59 -> 23 | H54: =H59 -> 25 | I54: =I59 -> 25 | ... AF54: =AF59 -> 8
A55: How important do you find acquiring knowledge in bird feeding?
A56: Very, I love learning about birds | B56: 154 | C56: 18 | D56: 20 | E56: 19 | F56: 11 | G56: 12 | H56: 9 | I56: 9 | J56: 13 | K56: 8 | L56: 8 | M56: 8 | N56: 6 | O56: 7 | P56: 3 | Q56: 8 | R56: 0 | S56: 3 | T56: 4 | U56: 4 | V56: 8 | W56: 7 | X56: 8 | Y56: 8 | Z56: 11 | AA56: 6 | AB56: 4 | AC56: 5 | AD56: 5 | AE56: 3 | AF56: 5 | AG56: =SUM(B56:AF56) -> 394 | AH56: =iferror(AG56/AG$59,"") -> 0.50191083
A57: It's not the main point for me, but nice | B57: 98 | C57: 16 | D57: 17 | E57: 17 | F57: 15 | G57: 10 | H57: 14 | I57: 15 | J57: 11 | K57: 14 | L57: 9 | M57: 6 | N57: 5 | O57: 9 | P57: 6 | Q57: 3 | R57: 2 | S57: 3 | T57: 1 | U57: 3 | V57: 2 | W57: 1 | X57: 3 | Y57: 6 | Z57: 8 | AA57: 3 | AB57: 4 | AC57: 3 | AD57: 4 | AE57: 8 | AF57: 1 | AG57: =SUM(B57:AF57) -> 317 | AH57: =iferror(AG57/AG$59,"") -> 0.40382166
A58: Not at all | B58: 12 | C58: 7 | D58: 4 | E58: 3 | F58: 4 | G58: 1 | H58: 2 | I58: 1 | J58: 9 | K58: 2 | L58: 5 | M58: 1 | N58: 0 | O58: 1 | P58: 0 | Q58: 1 | R58: 0 | S58: 2 | T58: 1 | U58: 1 | V58: 2 | W58: 0 | X58: 2 | Y58: 3 | Z58: 0 | AA58: 1 | AB58: 2 | AC58: 1 | AD58: 3 | AE58: 1 | AF58: 2 | AG58: =SUM(B58:AF58) -> 74 | AH58: =iferror(AG58/AG$59,"") -> 0.094267516
A59: Total submissions: | B59: =SUM(B56:B58) -> 264 | C59: =SUM(C56:C58) -> 41 | D59: =SUM(D56:D58) -> 41 | E59: =SUM(E56:E58) -> 39 | F59: =SUM(F56:F58) -> 30 | G59: =SUM(G56:G58) -> 23 | H59: =SUM(H56:H58) -> 25 | I59: =SUM(I56:I58) -> 25 | ... AF59: =SUM(AF56:AF58) -> 8 | AG59: =SUM(B59:AF59) -> 785 | AH59: =SUM(AH56:AH58) -> 1
A60: Total submissions: | B60: =SUM(B36,B42,B48,B54) -> 1240 | C60: =SUM(C36,C42,C48,C54) -> 252 | D60: =SUM(D36,D42,D48,D54) -> 200 | E60: =SUM(E36,E42,E48,E54) -> 186 | F60: =SUM(F36,F42,F48,F54) -> 157 | G60: =SUM(G36,G42,G48,G54) -> 133 | H60: =SUM(H36,H42,H48,H54) -> 134 | I60: =SUM(I36,I42,I48,I54) -> 117 | ... AF60: =SUM(AF36,AF42,AF48,AF54) -> 46
A61: % Who is this for? (sub-question 3)
A62: Just me | B62: =iferror(B36/B$60,"") -> 0.31129032 | C62: =iferror(C36/C$60,"") -> 0.3015873 | D62: =iferror(D36/D$60,"") -> 0.27 | E62: =iferror(E36/E$60,"") -> 0.29569892 | F62: =iferror(F36/F$60,"") -> 0.1910828 | G62: =iferror(G36/G$60,"") -> 0.32330827 | H62: =iferror(H36/H$60,"") -> 0.2238806 | I62: =iferror(I36/I$60,"") -> 0.2991453 | ... AF62: =iferror(AF36/AF$60,"") -> 0.26086957
A63: How important do you find acquiring knowledge in bird feeding?
A64: Very, I love learning about birds | B64: =iferror(B38/B$41,"") -> 0.65025907 | C64: =iferror(C38/C$41,"") -> 0.61842105 | D64: =iferror(D38/D$41,"") -> 0.68518519 | E64: =iferror(E38/E$41,"") -> 0.70909091 | F64: =iferror(F38/F$41,"") -> 0.6 | G64: =iferror(G38/G$41,"") -> 0.72093023 | H64: =iferror(H38/H$41,"") -> 0.6 | I64: =iferror(I38/I$41,"") -> 0.57142857 | ... AF64: =iferror(AF38/AF$41,"") -> 0.66666667
A65: It's not the main point for me, but nice | B65: =iferror(B39/B$41,"") -> 0.30829016 | C65: =iferror(C39/C$41,"") -> 0.31578947 | D65: =iferror(D39/D$41,"") -> 0.2962963 | E65: =iferror(E39/E$41,"") -> 0.16363636 | F65: =iferror(F39/F$41,"") -> 0.33333333 | G65: =iferror(G39/G$41,"") -> 0.25581395 | H65: =iferror(H39/H$41,"") -> 0.36666667 | I65: =iferror(I39/I$41,"") -> 0.34285714 | ... AF65: =iferror(AF39/AF$41,"") -> 0.33333333
A66: Not at all | B66: =iferror(B40/B$41,"") -> 0.041450777 | C66: =iferror(C40/C$41,"") -> 0.065789474 | D66: =iferror(D40/D$41,"") -> 0.018518519 | E66: =iferror(E40/E$41,"") -> 0.12727273 | F66: =iferror(F40/F$41,"") -> 0.066666667 | G66: =iferror(G40/G$41,"") -> 0.023255814 | H66: =iferror(H40/H$41,"") -> 0.033333333 | I66: =iferror(I40/I$41,"") -> 0.085714286 | ... AF66: =iferror(AF40/AF$41,"") -> 0
H67: =iferror(H41/#REF!,"") | I67: =iferror(I41/#REF!,"") | J67: =iferror(J41/#REF!,"") | K67: =iferror(K41/#REF!,"") | L67: =iferror(L41/#REF!,"") | M67: =iferror(M41/#REF!,"") | N67: =iferror(N41/#REF!,"") | O67: =iferror(O41/#REF!,"") | ... AF67: =iferror(AF41/#REF!,"")
A68: I will use with my family | B68: =iferror(B42/B$60,"") -> 0.35725806 | C68: =iferror(C42/C$60,"") -> 0.3968254 | D68: =iferror(D42/D$60,"") -> 0.355 | E68: =iferror(E42/E$60,"") -> 0.33870968 | F68: =iferror(F42/F$60,"") -> 0.38853503 | G68: =iferror(G42/G$60,"") -> 0.28571429 | H68: =iferror(H42/H$60,"") -> 0.29850746 | I68: =iferror(I42/I$60,"") -> 0.26495726 | ... AF68: =iferror(AF42/AF$60,"") -> 0.36956522
A69: How important do you find acquiring knowledge in bird feeding?
A70: Very, I love learning about birds | B70: =iferror(B44/B$47,"") -> 0.67042889 | C70: =iferror(C44/C$47,"") -> 0.56 | D70: =iferror(D44/D$47,"") -> 0.73239437 | E70: =iferror(E44/E$47,"") -> 0.42857143 | F70: =iferror(F44/F$47,"") -> 0.62295082 | G70: =iferror(G44/G$47,"") -> 0.65789474 | H70: =iferror(H44/H$47,"") -> 0.675 | I70: =iferror(I44/I$47,"") -> 0.64516129 | ... AF70: =iferror(AF44/AF$47,"") -> 0.76470588
A71: It's not the main point for me, but nice | B71: =iferror(B45/B$47,"") -> 0.2979684 | C71: =iferror(C45/C$47,"") -> 0.4 | D71: =iferror(D45/D$47,"") -> 0.25352113 | E71: =iferror(E45/E$47,"") -> 0.52380952 | F71: =iferror(F45/F$47,"") -> 0.32786885 | G71: =iferror(G45/G$47,"") -> 0.31578947 | H71: =iferror(H45/H$47,"") -> 0.325 | I71: =iferror(I45/I$47,"") -> 0.22580645 | ... AF71: =iferror(AF45/AF$47,"") -> 0.23529412
A72: Not at all | B72: =iferror(B46/B$47,"") -> 0.031602709 | C72: =iferror(C46/C$47,"") -> 0.04 | D72: =iferror(D46/D$47,"") -> 0.014084507 | E72: =iferror(E46/E$47,"") -> 0.047619048 | F72: =iferror(F46/F$47,"") -> 0.049180328 | G72: =iferror(G46/G$47,"") -> 0.026315789 | H72: =iferror(H46/H$47,"") -> 0 | I72: =iferror(I46/I$47,"") -> 0.12903226 | ... AF72: =iferror(AF46/AF$47,"") -> 0
A74: My parents | B74: =iferror(B48/B$60,"") -> 0.11854839 | C74: =iferror(C48/C$60,"") -> 0.13888889 | D74: =iferror(D48/D$60,"") -> 0.17 | E74: =iferror(E48/E$60,"") -> 0.15591398 | F74: =iferror(F48/F$60,"") -> 0.22929936 | G74: =iferror(G48/G$60,"") -> 0.21804511 | H74: =iferror(H48/H$60,"") -> 0.29104478 | I74: =iferror(I48/I$60,"") -> 0.22222222 | ... AF74: =iferror(AF48/AF$60,"") -> 0.19565217
A75: How important do you find acquiring knowledge in bird feeding?
A76: Very, I love learning about birds | B76: =iferror(B50/B$53,"") -> 0.46258503 | C76: =iferror(C50/C$53,"") -> 0.45714286 | D76: =iferror(D50/D$53,"") -> 0.5 | E76: =iferror(E50/E$53,"") -> 0.44827586 | F76: =iferror(F50/F$53,"") -> 0.41666667 | G76: =iferror(G50/G$53,"") -> 0.44827586 | H76: =iferror(H50/H$53,"") -> 0.64102564 | I76: =iferror(I50/I$53,"") -> 0.46153846 | ... AF76: =iferror(AF50/AF$53,"") -> 0.77777778
A77: It's not the main point for me, but nice | B77: =iferror(B51/B$53,"") -> 0.42857143 | C77: =iferror(C51/C$53,"") -> 0.42857143 | D77: =iferror(D51/D$53,"") -> 0.44117647 | E77: =iferror(E51/E$53,"") -> 0.37931034 | F77: =iferror(F51/F$53,"") -> 0.44444444 | G77: =iferror(G51/G$53,"") -> 0.27586207 | H77: =iferror(H51/H$53,"") -> 0.28205128 | I77: =iferror(I51/I$53,"") -> 0.42307692 | ... AF77: =iferror(AF51/AF$53,"") -> 0.22222222
A78: Not at all | B78: =iferror(B52/B$53,"") -> 0.10884354 | C78: =iferror(C52/C$53,"") -> 0.11428571 | D78: =iferror(D52/D$53,"") -> 0.058823529 | E78: =iferror(E52/E$53,"") -> 0.17241379 | F78: =iferror(F52/F$53,"") -> 0.13888889 | G78: =iferror(G52/G$53,"") -> 0.27586207 | H78: =iferror(H52/H$53,"") -> 0.076923077 | I78: =iferror(I52/I$53,"") -> 0.11538462 | ... AF78: =iferror(AF52/AF$53,"") -> 0
A80: Spouse | B80: =iferror(B54/B$60,"") -> 0.21290323 | C80: =iferror(C54/C$60,"") -> 0.16269841 | D80: =iferror(D54/D$60,"") -> 0.205 | E80: =iferror(E54/E$60,"") -> 0.20967742 | F80: =iferror(F54/F$60,"") -> 0.1910828 | G80: =iferror(G54/G$60,"") -> 0.17293233 | H80: =iferror(H54/H$60,"") -> 0.18656716 | I80: =iferror(I54/I$60,"") -> 0.21367521 | ... AF80: =iferror(AF54/AF$60,"") -> 0.17391304
A81: How important do you find acquiring knowledge in bird feeding?
A82: Very, I love learning about birds | B82: =iferror(B56/B$59,"") -> 0.58333333 | C82: =iferror(C56/C$59,"") -> 0.43902439 | D82: =iferror(D56/D$59,"") -> 0.48780488 | E82: =iferror(E56/E$59,"") -> 0.48717949 | F82: =iferror(F56/F$59,"") -> 0.36666667 | G82: =iferror(G56/G$59,"") -> 0.52173913 | H82: =iferror(H56/H$59,"") -> 0.36 | I82: =iferror(I56/I$59,"") -> 0.36 | ... AF82: =iferror(AF56/AF$59,"") -> 0.625
A83: It's not the main point for me, but nice | B83: =iferror(B57/B$59,"") -> 0.37121212 | C83: =iferror(C57/C$59,"") -> 0.3902439 | D83: =iferror(D57/D$59,"") -> 0.41463415 | E83: =iferror(E57/E$59,"") -> 0.43589744 | F83: =iferror(F57/F$59,"") -> 0.5 | G83: =iferror(G57/G$59,"") -> 0.43478261 | H83: =iferror(H57/H$59,"") -> 0.56 | I83: =iferror(I57/I$59,"") -> 0.6 | ... AF83: =iferror(AF57/AF$59,"") -> 0.125
A84: Not at all | B84: =iferror(B58/B$59,"") -> 0.045454545 | C84: =iferror(C58/C$59,"") -> 0.17073171 | D84: =iferror(D58/D$59,"") -> 0.097560976 | E84: =iferror(E58/E$59,"") -> 0.076923077 | F84: =iferror(F58/F$59,"") -> 0.13333333 | G84: =iferror(G58/G$59,"") -> 0.043478261 | H84: =iferror(H58/H$59,"") -> 0.08 | I84: =iferror(I58/I$59,"") -> 0.04 | ... AF84: =iferror(AF58/AF$59,"") -> 0.25
A90: How would you rate your bird knowledge?
A91: Just me
A92: Beginner (New to birding) | B92: 152 | C92: 34 | D92: 25 | E92: 25 | F92: 8 | G92: 20 | H92: 15 | I92: 15 | J92: 14 | K92: 26 | L92: 7 | M92: 9 | N92: 4 | O92: 5 | P92: 6 | Q92: 8 | R92: 8 | S92: 8 | T92: 5 | U92: 11 | V92: 4 | W92: 4 | X92: 5 | Y92: 6 | Z92: 7 | AA92: 8 | AB92: 6 | AC92: 9 | AD92: 3 | AE92: 9 | AF92: 4 | AG92: =SUM(B92:AF92) -> 470 | AH92: =iferror(AG92/AG$95,"") -> 0.42457091
A93: Intermediate (Moderate understanding) | B93: 220 | C93: 36 | D93: 28 | E93: 26 | F93: 21 | G93: 23 | H93: 13 | I93: 18 | J93: 16 | K93: 22 | L93: 17 | M93: 12 | N93: 10 | O93: 8 | P93: 4 | Q93: 12 | R93: 8 | S93: 3 | T93: 6 | U93: 5 | V93: 6 | W93: 5 | X93: 9 | Y93: 12 | Z93: 5 | AA93: 6 | AB93: 6 | AC93: 9 | AD93: 4 | AE93: 9 | AF93: 6 | AG93: =SUM(B93:AF93) -> 585 | AH93: =iferror(AG93/AG$95,"") -> 0.52845528
A94: Advanced (In-depth knowledge) | B94: 14 | C94: 6 | D94: 1 | E94: 4 | F94: 1 | G94: 0 | H94: 2 | I94: 2 | J94: 1 | K94: 7 | L94: 0 | M94: 0 | N94: 2 | O94: 1 | P94: 1 | Q94: 1 | R94: 2 | S94: 1 | T94: 0 | U94: 0 | V94: 1 | W94: 1 | X94: 0 | Y94: 1 | Z94: 0 | AA94: 0 | AB94: 1 | AC94: 0 | AD94: 0 | AE94: 0 | AF94: 2 | AG94: =SUM(B94:AF94) -> 52 | AH94: =iferror(AG94/AG$95,"") -> 0.046973803
A95: Total submissions: | B95: =SUM(B92:B94) -> 386 | C95: =SUM(C92:C94) -> 76 | D95: =SUM(D92:D94) -> 54 | E95: =SUM(E92:E94) -> 55 | F95: =SUM(F92:F94) -> 30 | G95: =SUM(G92:G94) -> 43 | H95: =SUM(H92:H94) -> 30 | I95: =SUM(I92:I94) -> 35 | ... AF95: =SUM(AF92:AF94) -> 12 | AG95: =SUM(B95:AF95) -> 1107 | AH95: =SUM(AH92:AH94) -> 1
A97: I will use with my family
A98: Beginner (New to birding) | B98: 163 | C98: 49 | D98: 35 | E98: 32 | F98: 32 | G98: 20 | H98: 21 | I98: 20 | J98: 35 | K98: 24 | L98: 17 | M98: 15 | N98: 9 | O98: 9 | P98: 6 | Q98: 12 | R98: 8 | S98: 13 | T98: 5 | U98: 8 | V98: 6 | W98: 12 | X98: 15 | Y98: 16 | Z98: 12 | AA98: 9 | AB98: 10 | AC98: 11 | AD98: 1 | AE98: 6 | AF98: 9 | AG98: =SUM(B98:AF98) -> 640 | AH98: =iferror(AG98/AG$101,"") -> 0.48780488
A99: Intermediate (Moderate understanding) | B99: 249 | C99: 46 | D99: 31 | E99: 31 | F99: 27 | G99: 17 | H99: 17 | I99: 11 | J99: 23 | K99: 21 | L99: 11 | M99: 5 | N99: 9 | O99: 10 | P99: 5 | Q99: 9 | R99: 5 | S99: 3 | T99: 4 | U99: 10 | V99: 8 | W99: 6 | X99: 5 | Y99: 7 | Z99: 4 | AA99: 6 | AB99: 4 | AC99: 5 | AD99: 3 | AE99: 6 | AF99: 7 | AG99: =SUM(B99:AF99) -> 605 | AH99: =iferror(AG99/AG$101,"") -> 0.46112805
A100: Advanced (In-depth knowledge) | B100: 31 | C100: 5 | D100: 5 | E100: 0 | F100: 2 | G100: 1 | H100: 2 | I100: 0 | J100: 4 | K100: 2 | L100: 2 | M100: 1 | N100: 1 | O100: 0 | P100: 2 | Q100: 2 | R100: 0 | S100: 1 | T100: 0 | U100: 1 | V100: 1 | W100: 0 | X100: 0 | Y100: 0 | Z100: 0 | AA100: 1 | AB100: 1 | AC100: 0 | AD100: 0 | AE100: 1 | AF100: 1 | AG100: =SUM(B100:AF100) -> 67 | AH100: =iferror(AG100/AG$101,"") -> 0.051067073
A101: Total submissions: | B101: =SUM(B98:B100) -> 443 | C101: =SUM(C98:C100) -> 100 | D101: =SUM(D98:D100) -> 71 | E101: =SUM(E98:E100) -> 63 | F101: =SUM(F98:F100) -> 61 | G101: =SUM(G98:G100) -> 38 | H101: =SUM(H98:H100) -> 40 | I101: =SUM(I98:I100) -> 31 | ... AF101: =SUM(AF98:AF100) -> 17 | AG101: =SUM(B101:AF101) -> 1312 | AH101: =SUM(AH98:AH100) -> 1
A103: How would you rate the bird knowledge of the person receiving the gift?
A104: My parents
A105: Beginner (New to birding) | B105: 51 | C105: 12 | D105: 16 | E105: 9 | F105: 11 | G105: 5 | H105: 11 | I105: 8 | J105: 9 | K105: 5 | L105: 7 | M105: 4 | N105: 3 | O105: 3 | P105: 2 | Q105: 3 | R105: 8 | S105: 1 | T105: 5 | U105: 4 | V105: 3 | W105: 9 | X105: 2 | Y105: 8 | Z105: 6 | AA105: 2 | AB105: 3 | AC105: 4 | AD105: 3 | AE105: 6 | AF105: 4 | AG105: =SUM(B105:AF105) -> 227 | AH105: =iferror(AG105/AG$108,"") -> 0.3449848
A106: Intermediate (Moderate understanding) | B106: 80 | C106: 20 | D106: 16 | E106: 15 | F106: 20 | G106: 21 | H106: 19 | I106: 17 | J106: 15 | K106: 16 | L106: 11 | M106: 5 | N106: 4 | O106: 5 | P106: 6 | Q106: 5 | R106: 5 | S106: 9 | T106: 1 | U106: 7 | V106: 5 | W106: 6 | X106: 8 | Y106: 3 | Z106: 9 | AA106: 3 | AB106: 3 | AC106: 2 | AD106: 1 | AE106: 10 | AF106: 4 | AG106: =SUM(B106:AF106) -> 351 | AH106: =iferror(AG106/AG$108,"") -> 0.53343465
A107: Advanced (In-depth knowledge) | B107: 16 | C107: 3 | D107: 2 | E107: 5 | F107: 5 | G107: 3 | H107: 9 | I107: 1 | J107: 4 | K107: 4 | L107: 3 | M107: 0 | N107: 2 | O107: 3 | P107: 3 | Q107: 0 | R107: 1 | S107: 1 | T107: 0 | U107: 1 | V107: 0 | W107: 4 | X107: 1 | Y107: 2 | Z107: 2 | AA107: 0 | AB107: 1 | AC107: 2 | AD107: 1 | AE107: 0 | AF107: 1 | AG107: =SUM(B107:AF107) -> 80 | AH107: =iferror(AG107/AG$108,"") -> 0.12158055
A108: Total submissions: | B108: =SUM(B105:B107) -> 147 | C108: =SUM(C105:C107) -> 35 | D108: =SUM(D105:D107) -> 34 | E108: =SUM(E105:E107) -> 29 | F108: =SUM(F105:F107) -> 36 | G108: =SUM(G105:G107) -> 29 | H108: =SUM(H105:H107) -> 39 | I108: =SUM(I105:I107) -> 26 | ... AF108: =SUM(AF105:AF107) -> 9 | AG108: =SUM(B108:AF108) -> 658 | AH108: =SUM(AH105:AH107) -> 1
A110: Spouse
A111: Beginner (New to birding) | B111: 67 | C111: 16 | D111: 20 | E111: 17 | F111: 11 | G111: 10 | H111: 11 | I111: 8 | J111: 14 | K111: 8 | L111: 8 | M111: 6 | N111: 3 | O111: 4 | P111: 4 | Q111: 4 | R111: 0 | S111: 2 | T111: 1 | U111: 2 | V111: 3 | W111: 1 | X111: 6 | Y111: 5 | Z111: 11 | AA111: 2 | AB111: 7 | AC111: 5 | AD111: 5 | AE111: 6 | AF111: 4 | AG111: =SUM(B111:AF111) -> 271 | AH111: =iferror(AG111/AG$114,"") -> 0.34522293
A112: Intermediate (Moderate understanding) | B112: 143 | C112: 19 | D112: 18 | E112: 22 | F112: 16 | G112: 12 | H112: 12 | I112: 16 | J112: 16 | K112: 13 | L112: 11 | M112: 7 | N112: 6 | O112: 11 | P112: 5 | Q112: 6 | R112: 1 | S112: 4 | T112: 4 | U112: 5 | V112: 7 | W112: 6 | X112: 6 | Y112: 10 | Z112: 7 | AA112: 6 | AB112: 3 | AC112: 1 | AD112: 3 | AE112: 4 | AF112: 4 | AG112: =SUM(B112:AF112) -> 404 | AH112: =iferror(AG112/AG$114,"") -> 0.51464968
A113: Advanced (In-depth knowledge) | B113: 54 | C113: 6 | D113: 3 | E113: 0 | F113: 3 | G113: 1 | H113: 2 | I113: 1 | J113: 3 | K113: 3 | L113: 3 | M113: 2 | N113: 2 | O113: 2 | P113: 0 | Q113: 2 | R113: 1 | S113: 2 | T113: 1 | U113: 1 | V113: 2 | W113: 1 | X113: 1 | Y113: 2 | Z113: 1 | AA113: 2 | AB113: 0 | AC113: 3 | AD113: 4 | AE113: 2 | AF113: 0 | AG113: =SUM(B113:AF113) -> 110 | AH113: =iferror(AG113/AG$114,"") -> 0.14012739
A114: Total submissions: | B114: =SUM(B111:B113) -> 264 | C114: =SUM(C111:C113) -> 41 | D114: =SUM(D111:D113) -> 41 | E114: =SUM(E111:E113) -> 39 | F114: =SUM(F111:F113) -> 30 | G114: =SUM(G111:G113) -> 23 | H114: =SUM(H111:H113) -> 25 | I114: =SUM(I111:I113) -> 25 | ... AF114: =SUM(AF111:AF113) -> 8 | AG114: =SUM(B114:AF114) -> 785 | AH114: =SUM(AH111:AH113) -> 1
A117: % How important do you find acquiring knowledge in bird feeding?
A118: Just me
...

Sheet Data - P&L
B1: Business Metrics
A2: Source | B2: COGS | E2: Attachment Rates | H2: Marketing Averages (per first-time order) | K2: Fees | N2: VAT Averages | Q2: 30 Day Returns | T2: Digital Market Places & B2B
B3: Bird Buddy | C3: 86.9 | D3: 86.9 | E3: Solar Roof | F3: =(('DTC - P&L'!AG105+'DTC - P&L'!AG106)/'DTC - P&L'!AG95) -> 0.12752339 | H3: COGS | I3: =(C3*F9)+(C4*F8)+(C5*F3)+(C6*F4)+(C7*F5)+(C8*F6)+(C9*F7)+(C10*F10) -> 104.59354 | J3: =(D3*F9)+(D4*F8)+(D5*F3)+(D6*F4)+(D7*F5)+(D8*F6)+(D9*F7) -> 101.59501 | K3: Stripe Processing Fee | L3: 0.029 | N3: Europe | O3: 0.22 | Q3: US Shipping | R3: 15 | T3: Average % tax | U3: 0.0614 | V3: Source
B4: Bird Buddy with Solar Roof | C4: 97.61 | D4: 97.61 | E4: Wall Mount | F4: =('DTC - P&L'!AG101/'DTC - P&L'!AG95) -> 0.63417036 | H4: Inbound Shipping | I4: =C38+('DTC - P&L'!AG111/'DTC - P&L'!AG95)*D38 -> 14.298459 | K4: Duty | L4: 0.034 | N4: ROW | O4: 0.13 | Q4: EU Shipping | R4: 40
B5: Solar Roof Single | C5: 13.44 | D5: 13.44 | E5: Fence Mount | F5: 0 | H5: Outbound Shipping | I5: =C34+('DTC - P&L'!AG111/'DTC - P&L'!AG95)*D34 -> 45.742797 | K5: China Tax | L5: 0.075 | N5: NA | Q5: ROW Shipping | R5: 20
B6: Wall Mount | C6: 5.49 | D6: 5.49 | E6: Suet Ball Holder | F6: =('DTC - P&L'!AG102)/'DTC - P&L'!AG95 -> 0.1708518 | H6: Taxes and VAT | I6: 16.81 | K6: HMF | L6: 0.00125 | Q6: Money Return | R6: 1
B7: Fence Mount | C7: 6.37 | E7: 3-in-1 | F7: =('DTC - P&L'!AG103+'DTC - P&L'!AG104)/'DTC - P&L'!AG95 -> 0.17331364 | H7: China Tax (7.5%) | I7: 0 | K7: MPF | L7: 0.003464
B8: Suet Ball Holder | C8: 1.19 | D8: 1.19 | E8: Bird Buddy w/ Solar | F8: =('DTC - P&L'!AG93+'DTC - P&L'!AG94)/'DTC - P&L'!AG95 -> 0.76021664 | H8: Duty (3.4%) | I8: 0 | K8: Solar Roof China Tax | L8: 0.075
B9: 3-in-1 Nutrition Set | C9: 6.66 | D9: 6.66 | E9: Bird Buddy | F9: =1-F8 -> 0.23978336 | H9: Processing Fee (2,90%) | I9: =Summary!B121*L3 -> 7.6547626 | K9: Solar Roof Duty | L9: 0.025
B10: Perch Extender | C10: 6 | E10: Perch Extender | F10: =('DTC - P&L'!AG107+'DTC - P&L'!AG108)/'DTC - P&L'!AG95 -> 0.49975382 | H10: Transaction Fee ($0.30) | I10: =0.3 -> 0.3 | K10: Chargeback Fee (Stripe) | L10: 15
B11: Avg. Merch Cost | C11: 3.94 | E11: OTHER 2 | H11: OTHER 1
B12: Avg. Merch Cost without Calendar | C12: 14.79 | E12: OTHER 3 | H12: OTHER 2 | K12: Stripe | L12: 0.95
B13: SBF Housing | E13: OTHER 4 | H13: OTHER 3 | K13: Affirm | L13: 0.05
B14: SBF Camera | E14: OTHER 5 | H14: OTHER 4 | K14: Affirm processing fee | L14: 0.0579
B15: Hummingbird Feeder | C15: 87.9 | H15: All | I15: =SUM(I3:I14) -> 189.39955 | K15: Affirm transaction fee | L15: 0.3
B16: Hummingbird Feeder with Solar Roof | C16: 97.21
B17: Solar Roof (Hummingbird Feeder) | C17: 13.73
B18: Housing (Hummingbird Feeder) | C18: 26.68
B22: Outbound shipping | C22: Bird buddy | D22: Add-ons | E22: Merch
A23: *w/o CA weight | B23: Outbound (NA) | C23: 30.08 | D23: 9.53 | E23: 5.4 | H23: App Advertising
B24: Outbound (Europe) | C24: 11.94 | D24: 6.16 | H24: Meta Share to Apple Store | I24: 0.8
B25: Outbound (ROW) | C25: 11.94 | D25: 6.16 | H25: Meta Share to Google Store | I25: 0.2
A26: Source | B26: 3PL Costs | C26: 0 | D26: 0
B27: Handling Fee
B28: Serial Capture | C28: 0.1 | D28: 0
B29: Storage | C29: 0.31 | D29: 0.31
B30: Supplies cost | C30: 0 | D30: 0
B31: Pick charge | C31: 0.35 | D31: 0.35
B32: Pollybag cost | C32: 0 | D32: 0
B33: Carton cost | C33: 1.65 | D33: 0.71
B34: Total outbound (NA) | C34: =C26+C23-C27 -> 30.08 | D34: =D26+D23-D27 -> 9.53
B35: Total outbound (Europe) | C35: 15.06 | D35: =D27+D24-D28 -> 6.16
B36: Total outbound (ROW) | C36: 20
A37: Source | B37: Inbound shipping | C37: Bird buddy | D37: Add-ons
B38: Inbound (NA) | C38: 11.94 | D38: 1.435
B39: Inbound (Europe) | C39: 11.94 | D39: 1.44
B40: Inbound (ROW) | C40: 11.94 | D40: 1.44
B42: AMAZON Logistics | C42: Bird buddy | D42: Add-ons
A43: https://docs.google.com/spreadsheets/d/1Dn0q7h1bHxXdG0N9KpcqzFo0tWUWYXOrRX7yxv3G1E0/edit#gid=1264242332 | B43: Inbound | C43: 11.94 | D43: 1.435
A44: =sum(C43:C44) -> 12.18 | B44: Storage Fee | C44: 0.24 | D44: 0.24
A45: =C46 -> 12.94 | B45: AMAZON Fees | C45: Bird buddy
A46: =sum(F43:F45) -> 0 | B46: FBA fee for units | C46: 12.94
B47: FBA fee for addons | C47: 5.7
A48: =C38 -> 11.94 | B48: Sales Fee | C48: 0.15
B49: AMAZON Shipping | C49: Bird buddy
A50: =sum(A43:A48) -> 37.06 | B50: BB units Shipping | C50: 11
B51: Addons Shipping | C51: 6.155
B53: COGS adjustment for DTC
B54: Returns for refunds | C54: 0.25
B55: Returns for replacements | C55: 0.1
B57: COGS adjustment for Amazon
B58: Returns for refunds | C58: 0.5644
B59: Returns for replacements | C59: 0.4603
B61: Amazon Removal Fee
B62: Units | C62: 5.56
B63: Add-ons | C63: 2.2
A66: https://docs.google.com/document/d/1m1D0mcq6_cpIUs4Z2pSMjDX9L4kRSfAwaLu0UKQppIM/edit?usp=sharing | B66: Explanation for Returns, Cancellations, Replacements calculation
A68: https://docs.google.com/spreadsheets/d/1JFD6SusYZSq5MvMm0PnCaYPmLBVKBKvK09yjZIlSFN4/edit#gid=0 | B68: Amazon Modelling for cancelled orders | E68: Regular Price numbers for Amazon Modelling cancelled orders
B69: Full Price Template for cancelled orders | E69: 17.58 | F69: 0.29 | G69: 0 | H69: 0.17 | I69: 0.01 | J69: 2.44 | K69: 0.21
B70: item-tax | C70: 17.58
B71: shipping-price | C71: 0.29 | E71: MAP Price numbers for Amazon Modelling cancelled orders
B72: shipping-tax | C72: 0 | E72: 14.55 | F72: 0.55 | G72: 0.01 | H72: 0.15 | I72: 0.01 | J72: 7.62 | K72: 0.3
B73: gift-wrap-price | C73: 0.17
B74: gift-wrap-tax | C74: 0.01
B75: item-promotion-discount | C75: 2.44 | E75: item-tax | F75: shipping-price | G75: shipping-tax | H75: gift-wrap-price | I75: gift-wrap-tax | J75: item-promotion-discount | K75: ship-promotion-discount
B76: ship-promotion-discount | C76: 0.21
B79: B2B
B80: Agency Fee | C80: 0.05 | D80: NET NET
B81: Agency transportation best buy | C81: *Dejan sporoči

Sheet SupermetricsQueries
A1: Supermetrics Queries
A3: All the queries created by Supermetrics are stored here, each in its own row.
H4: 17091262
A5: On this sheet you can:
A6: 1. Modify the parameters of a query. Any changes will be visible when you run a refresh.
A8: 2. Remove a query by deleting its row | H8: Europe/Paris
A10: 3. Add new queries: type a range address and query parameters, leave the query ID empty. The query will be added when you run a refresh. (Of course, it's much easier to use the sidebar to add new queries.)
A13: Queries are stored with the authentication of the original user that created the query. If you want to transfer a query to the currently active Google Sheets user, delete its query ID from column A and run a refresh. For complete instructions on transferring queries, see https://support.supermetrics.com/support/solutions/articles/19000050074-how-can-i-transfer-queries-from-one-user-to-another-
A16: Don't delete or rename this sheet. If you delete or rename it, your existing queries can no longer be refreshed. Hiding the sheet is OK. Also, don't delete any rows above row 21.
A19: Query ID | D19: Sheet name | E19: Range address | G19: Created | H19: Updated | I19: Last status | J19: Last refresh ID | K19: Results contain sampled data | L19: Execution time (sec) | M19: Object type | N19: Linked chart ID | O19: Data source | Q19: Date range type | R19: Start date | S19: End date | T19: Compare to | U19: Comparison value type | W19: Accounts/views | X19: Metrics | Y19: Dimensions | Z19: Pivot dimensions | AA19: Filters | AB19: Segment ID | AC19: Sort | AD19: Max rows | AE19: Max pivot categories | AF19: Special settings | AG19: Other parameters | AJ19: Result type | AK19: Language/country | AL19: Translate to | AN19: SQL | AO19: Database name | AP19: Range address (static) | AQ19: Report type | AT19: Highlight with colour | AU19: Refresh with user account | AV19: Returned data | AW19: Refresh button number
A20: paramsID | C20: ssID | D20: sheetName | E20: rangeAddress | G20: created | H20: updated | I20: lastStatus | J20: lastqueryID | K20: sampled | L20: runtime_sec | M20: objType | N20: linkedChartID | O20: dataSource | Q20: dateRangeType | R20: startDateString | S20: endDateString | T20: comp | U20: cvt | W20: profiles | X20: metrics | Y20: dimensions | Z20: sd | AA20: filterArr | AB20: segment | AC20: sort | AD20: maxResults | AE20: maxCategories | AF20: specialSettings | AG20: otherParams | AJ20: sds_result_type | AK20: sds_lang | AL20: sds_tolang | AN20: sql | AO20: db_name | AP20: rangeAddressStatic | AQ20: rt | AR20: scopeMZ | AS20: sortMZ | AT20: condform | AU20: authUser | AV20: metaDataToUser | AW20: refreshButtonNumber
A21: FEamnpN5FsVYF0RtUTXAwunZ388Tkc | D21: =IFERROR(__xludf.DUMMYFUNCTION("ARRAY_CONSTRAIN(split(CELL(""ADDRESS"",zsupermetrics_FEamnpN5FsVYF0RtUTXAwunZ388Tkc),""!""),1,1)"),"Forecast") -> Forecast | E21: =CELL("ADDRESS",zsupermetrics_FEamnpN5FsVYF0RtUTXAwunZ388Tkc)&":"&address(row(zsupermetrics_FEamnpN5FsVYF0RtUTXAwunZ388Tkc)+rows(zsupermetrics_FEamnpN5FsVYF0RtUTXAwunZ388Tkc)-1,column(zsupermetrics_FEamnpN5FsVYF0RtUTXAwunZ388Tkc)+COLUMNS(zsupermetrics_FEamnpN5FsVYF0RtUTXAwunZ388Tkc)-1) -> Forecast!$A$113:$C$141 | G21: 45336.379 | H21: 45350.594 | I21: Refreshed successfully | J21: 1709126144659 | K21: FALSE | L21: 2 | M21: TABLE | O21: GAWA | Q21: thismonth | W21: ["388437373`Bird Buddy - WooCommerce"] | X21: ["sessions","activeUsers"] | Y21: ["date"] | Z21: [] | AA21: [] | AB21: [] | AD21: 10000 | AF21: [] | AG21: {} | AP21: Forecast'!A113:C141 | AU21: ziga.skrabl@mybirdbuddy.com | AW21: 1

Sheet Forecast
A2: Start date: | B2: 45293 | D2: End date: | E2: 28/02/2024 | G2: 2023 benchmark per month | I2: 2023 benchmark per day
A3: Days | B3: 29 | C3: REVENUE | G3: AVG revenue per month | I3: AVG revenue per day
A4: Current day | B4: =count(Summary!B52:AD52) -> 29 | G4: AVG orders per month | I4: AVG orders per day
B5: ACTUALS | D5: Linear Projection | G5: AVG investments per month | I5: AVG investments per day
A6: DAYS | B6: REVENUE PLAN | C6: Current day | D6: Linear Projection | E6: % Plan (linear projection) | F6: Linear Projection GAP | G6: Avg users per month | I6: Avg users per day (cca.)
A7: 1 | B7: =$B$36/$B$3 -> 41379.31 | C7: =Summary!B31+Summary!B49 -> 637985.6 | D7: =C7/$B$4*$B$3 -> 637985.6 | E7: =D7/B7-1 -> 14.417985 | F7: =D7-B7 -> 596606.29 | G7: AVG ROAS per month
A8: 2 | B8: =$B$36/$B$3 -> 41379.31 | C8: =Summary!C31+Summary!C49 -> 137282.43 | D8: =C8/$B$4*$B$3 -> 137282.43 | E8: =D8/B8-1 -> 2.3176588 | F8: =D8-B8 -> 95903.122 | G8: AVG CPO per month
A9: 3 | B9: =$B$36/$B$3 -> 41379.31 | C9: =Summary!D31+Summary!D49 -> 116071.44 | D9: =C9/$B$4*$B$3 -> 116071.44 | E9: =D9/B9-1 -> 1.8050598 | F9: =D9-B9 -> 74692.13 | G9: AVG CR per month
A10: 4 | B10: =$B$36/$B$3 -> 41379.31 | C10: =Summary!E31+Summary!E49 -> 101337.71 | D10: =C10/$B$4*$B$3 -> 101337.71 | E10: =D10/B10-1 -> 1.4489947 | F10: =D10-B10 -> 59958.4 | G10: AVG AOV per month
A11: 5 | B11: =$B$36/$B$3 -> 41379.31 | C11: =Summary!F31+Summary!F49 -> 71945.71 | D11: =C11/$B$4*$B$3 -> 71945.71 | E11: =D11/B11-1 -> 0.73868799 | F11: =D11-B11 -> 30566.4
A12: 6 | B12: =$B$36/$B$3 -> 41379.31 | C12: =Summary!G31+Summary!G49 -> 67238.263 | D12: =C12/$B$4*$B$3 -> 67238.263 | E12: =D12/B12-1 -> 0.6249247 | F12: =D12-B12 -> 25858.953 | G12: How can we achieve the plan? (KPI-s perspective) - MTD | H12: Planned MTD | I12: Actuals MTD | J12: Realization %
A13: 7 | B13: =$B$36/$B$3 -> 41379.31 | C13: =Summary!H31+Summary!H49 -> 74309.515 | D13: =C13/$B$4*$B$3 -> 74309.515 | E13: =D13/B13-1 -> 0.79581328 | F13: =D13-B13 -> 32930.205 | G13: Planned revenue | H13: 1200000 | I13: =C36 -> 2224452.4 | J13: =I13/H13-1 -> 0.85371033
A14: 8 | B14: =$B$36/$B$3 -> 41379.31 | C14: =Summary!I31+Summary!I49 -> 73505.436 | D14: =C14/$B$4*$B$3 -> 73505.436 | E14: =D14/B14-1 -> 0.77638138 | F14: =D14-B14 -> 32126.126 | G14: Planned orders | H14: 4000 | I14: =sum(Summary!B64:AD64) -> 8905 | J14: =I14/H14-1 -> 1.22625
A15: 9 | B15: =$B$36/$B$3 -> 41379.31 | C15: =Summary!J31+Summary!J49 -> 90653.54 | D15: =C15/$B$4*$B$3 -> 90653.54 | E15: =D15/B15-1 -> 1.1907939 | F15: =D15-B15 -> 49274.23 | G15: Planned investments (marketing activites) | H15: 350000 | I15: =sum(Summary!B88:AD88) -> 281116.58 | J15: =I15/H15-1 -> -0.19680977
A16: 10 | B16: =$B$36/$B$3 -> 41379.31 | C16: =Summary!K31+Summary!K49 -> 86880.341 | D16: =C16/$B$4*$B$3 -> 86880.341 | E16: =D16/B16-1 -> 1.0996082 | F16: =D16-B16 -> 45501.031 | G16: Planned ROAS | H16: =H13/H15 -> 3.4285714 | I16: =I13/I15 -> 7.9129178 | J16: =I16/H16-1 -> 1.3079344
A17: 11 | B17: =$B$36/$B$3 -> 41379.31 | C17: =Summary!L31+Summary!L49 -> 62860.304 | D17: =C17/$B$4*$B$3 -> 62860.304 | E17: =D17/B17-1 -> 0.51912401 | F17: =D17-B17 -> 21480.994 | G17: Planned CPO | H17: =H15/H13 -> 0.29166667 | I17: =I15/I13 -> 0.12637563 | J17: =I17/H17-1 -> -0.56671212
A18: 12 | B18: =$B$36/$B$3 -> 41379.31 | C18: =Summary!M31+Summary!M49 -> 47064.565 | D18: =C18/$B$4*$B$3 -> 47064.565 | E18: =D18/B18-1 -> 0.13739367 | F18: =D18-B18 -> 5685.2552 | G18: Planned CR (DTC) | H18: 0.0125 | I18: =L18/I20 -> 0.017715636 | J18: =I18/H18-1 -> 0.41725088 | K18: DTC orders | L18: =sum(Summary!B52:AD52) -> 6320
A19: 13 | B19: =$B$36/$B$3 -> 41379.31 | C19: =Summary!N31+Summary!N49 -> 37838.12 | D19: =C19/$B$4*$B$3 -> 37838.12 | E19: =D19/B19-1 -> -0.085578767 | F19: =D19-B19 -> -3541.1903 | G19: Planned AOV | H19: 250 | I19: =I13/I14 -> 249.79813 | J19: =I19/H19-1 -> -0.00080746052
A20: 14 | B20: =$B$36/$B$3 -> 41379.31 | C20: =Summary!O31+Summary!O49 -> 45606.391 | D20: =C20/$B$4*$B$3 -> 45606.391 | E20: =D20/B20-1 -> 0.10215446 | F20: =D20-B20 -> 4227.081 | G20: Planned Website traffic (DTC) | H20: 300000 | I20: =sum(C79:C106) -> 356747 | J20: =I20/H20-1 -> 0.18915667
A21: 15 | B21: =$B$36/$B$3 -> 41379.31 | C21: =Summary!P31+Summary!P49 -> 39390.407 | D21: =C21/$B$4*$B$3 -> 39390.407 | E21: =D21/B21-1 -> -0.048065174 | F21: =D21-B21 -> -1988.9038
A22: 16 | B22: =$B$36/$B$3 -> 41379.31 | C22: =Summary!Q31+Summary!Q49 -> 48117.39 | D22: =C22/$B$4*$B$3 -> 48117.39 | E22: =D22/B22-1 -> 0.16283692 | F22: =D22-B22 -> 6738.0796 | G22: Legend: | H22: plan input data | I22: formulas
A23: 17 | B23: =$B$36/$B$3 -> 41379.31 | C23: =Summary!R31+Summary!R49 -> 42937.8 | D23: =C23/$B$4*$B$3 -> 42937.8 | E23: =D23/B23-1 -> 0.0376635 | F23: =D23-B23 -> 1558.4897
A24: 18 | B24: =$B$36/$B$3 -> 41379.31 | C24: =Summary!S31+Summary!S49 -> 31390.62 | D24: =C24/$B$4*$B$3 -> 31390.62 | E24: =D24/B24-1 -> -0.24139335 | F24: =D24-B24 -> -9988.6903
A25: 19 | B25: =$B$36/$B$3 -> 41379.31 | C25: =Summary!T31+Summary!T49 -> 33049.41 | D25: =C25/$B$4*$B$3 -> 33049.41 | E25: =D25/B25-1 -> -0.20130592 | F25: =D25-B25 -> -8329.9003
A26: 20 | B26: =$B$36/$B$3 -> 41379.31 | C26: =Summary!U31+Summary!U49 -> 36193.29 | D26: =C26/$B$4*$B$3 -> 36193.29 | E26: =D26/B26-1 -> -0.12532883 | F26: =D26-B26 -> -5186.0203
A27: 21 | B27: =$B$36/$B$3 -> 41379.31 | C27: =Summary!V31+Summary!V49 -> 34221.426 | D27: =C27/$B$4*$B$3 -> 34221.426 | E27: =D27/B27-1 -> -0.17298222 | F27: =D27-B27 -> -7157.8848
A28: 22 | B28: =$B$36/$B$3 -> 41379.31 | C28: =Summary!W31+Summary!W49 -> 49332.562 | D28: =C28/$B$4*$B$3 -> 49332.562 | E28: =D28/B28-1 -> 0.19220359 | F28: =D28-B28 -> 7953.252
A29: 23 | B29: =$B$36/$B$3 -> 41379.31 | C29: =Summary!X31+Summary!X49 -> 45030.278 | D29: =C29/$B$4*$B$3 -> 45030.278 | E29: =D29/B29-1 -> 0.088231726 | F29: =D29-B29 -> 3650.968
A30: 24 | B30: =$B$36/$B$3 -> 41379.31 | C30: =Summary!Y31+Summary!Y49 -> 52452.92 | D30: =C30/$B$4*$B$3 -> 52452.92 | E30: =D30/B30-1 -> 0.26761223 | F30: =D30-B30 -> 11073.61
A31: 25 | B31: =$B$36/$B$3 -> 41379.31 | C31: =Summary!Z31+Summary!Z49 -> 39121.979 | D31: =C31/$B$4*$B$3 -> 39121.979 | E31: =D31/B31-1 -> -0.054552169 | F31: =D31-B31 -> -2257.3311
A32: 26 | B32: =$B$36/$B$3 -> 41379.31 | C32: =Summary!AA31+Summary!AA49 -> 31960.06 | D32: =C32/$B$4*$B$3 -> 31960.06 | E32: =D32/B32-1 -> -0.22763188 | F32: =D32-B32 -> -9419.2503
A33: 27 | B33: =$B$36/$B$3 -> 41379.31 | C33: =Summary!AB31+Summary!AB49 -> 29944.22 | D33: =C33/$B$4*$B$3 -> 29944.22 | E33: =D33/B33-1 -> -0.27634802 | F33: =D33-B33 -> -11435.09
A34: 28 | B34: =$B$36/$B$3 -> 41379.31 | C34: =Summary!AC31+Summary!AC49 -> 34002.534 | D34: =C34/$B$4*$B$3 -> 34002.534 | E34: =D34/B34-1 -> -0.17827209 | F34: =D34-B34 -> -7376.7763
A35: 29 | B35: =$B$36/$B$3 -> 41379.31 | C35: =Summary!AD31+Summary!AD49 -> 26728.123 | D35: =C35/$B$4*$B$3 -> 26728.123 | E35: =D35/B35-1 -> -0.35407037 | F35: =D35-B35 -> -14651.188
A36: TOTAL | B36: =H13 -> 1200000 | C36: =sum(C7:C35) -> 2224452.4 | D36: =C36/$B$4*$B$3 -> 2224452.4 | E36: =D36/B36-1 -> 0.85371033 | F36: =D36-B36 -> 1024452.4
A38: Start date: | B38: 45293 | D38: End date: | E38: 28/02/2024
A39: Days | B39: 29 | C39: INVESTMENTS
A40: Current day | B40: =COUNT(Summary!B52:AD52) -> 29
B41: ACTUALS | D41: Linear Projection
A42: DAYS | B42: INVESTMENT PLAN | C42: Current day | D42: Linear Projection | E42: % Plan (linear projection) | F42: Linear Projection GAP
A43: 1 | B43: =$B$72/$B$39 -> 12068.966 | C43: =Summary!B88+Summary!B94 -> 20388.756 | D43: =C43/$B$4*$B$3 -> 20388.756 | E43: =D43/B43-1 -> 0.6893541 | F43: =D43-B43 -> 8319.7908
A44: 2 | B44: =$B$72/$B$39 -> 12068.966 | C44: =Summary!C88+Summary!C94 -> 20092.032 | D44: =C44/$B$4*$B$3 -> 20092.032 | E44: =D44/B44-1 -> 0.66476837 | F44: =D44-B44 -> 8023.0666
A45: 3 | B45: =$B$72/$B$39 -> 12068.966 | C45: =Summary!D88+Summary!D94 -> 19884.936 | D45: =C45/$B$4*$B$3 -> 19884.936 | E45: =D45/B45-1 -> 0.64760896 | F45: =D45-B45 -> 7815.9702
A46: 4 | B46: =$B$72/$B$39 -> 12068.966 | C46: =Summary!E88+Summary!E94 -> 16375.857 | D46: =C46/$B$4*$B$3 -> 16375.857 | E46: =D46/B46-1 -> 0.35685669 | F46: =D46-B46 -> 4306.8911
A47: 5 | B47: =$B$72/$B$39 -> 12068.966 | C47: =Summary!F88+Summary!F94 -> 13605.387 | D47: =C47/$B$4*$B$3 -> 13605.387 | E47: =D47/B47-1 -> 0.12730346 | F47: =D47-B47 -> 1536.4211
A48: 6 | B48: =$B$72/$B$39 -> 12068.966 | C48: =Summary!G88+Summary!G94 -> 13755.545 | D48: =C48/$B$4*$B$3 -> 13755.545 | E48: =D48/B48-1 -> 0.13974517 | F48: =D48-B48 -> 1686.5796
A49: 7 | B49: =$B$72/$B$39 -> 12068.966 | C49: =Summary!H88+Summary!H94 -> 14780.704 | D49: =C49/$B$4*$B$3 -> 14780.704 | E49: =D49/B49-1 -> 0.22468689 | F49: =D49-B49 -> 2711.7383
A50: 8 | B50: =$B$72/$B$39 -> 12068.966 | C50: =Summary!I88+Summary!I94 -> 15070.184 | D50: =C50/$B$4*$B$3 -> 15070.184 | E50: =D50/B50-1 -> 0.24867241 | F50: =D50-B50 -> 3001.2188
A51: 9 | B51: =$B$72/$B$39 -> 12068.966 | C51: =Summary!J88+Summary!J94 -> 16890.88 | D51: =C51/$B$4*$B$3 -> 16890.88 | E51: =D51/B51-1 -> 0.39953005 | F51: =D51-B51 -> 4821.9144
A52: 10 | B52: =$B$72/$B$39 -> 12068.966 | C52: =Summary!K88+Summary!K94 -> 17331.41 | D52: =C52/$B$4*$B$3 -> 17331.41 | E52: =D52/B52-1 -> 0.43603114 | F52: =D52-B52 -> 5262.4448
A53: 11 | B53: =$B$72/$B$39 -> 12068.966 | C53: =Summary!L88+Summary!L94 -> 13864.829 | D53: =C53/$B$4*$B$3 -> 13864.829 | E53: =D53/B53-1 -> 0.14880015 | F53: =D53-B53 -> 1795.8639
A54: 12 | B54: =$B$72/$B$39 -> 12068.966 | C54: =Summary!M88+Summary!M94 -> 12002.019 | D54: =C54/$B$4*$B$3 -> 12002.019 | E54: =D54/B54-1 -> -0.0055470106 | F54: =D54-B54 -> -66.94668
A55: 13 | B55: =$B$72/$B$39 -> 12068.966 | C55: =Summary!N88+Summary!N94 -> 11459.676 | D55: =C55/$B$4*$B$3 -> 11459.676 | E55: =D55/B55-1 -> -0.050483949 | F55: =D55-B55 -> -609.28905
A56: 14 | B56: =$B$72/$B$39 -> 12068.966 | C56: =Summary!O88+Summary!O94 -> 11206.609 | D56: =C56/$B$4*$B$3 -> 11206.609 | E56: =D56/B56-1 -> -0.071452397 | F56: =D56-B56 -> -862.35651
A57: 15 | B57: =$B$72/$B$39 -> 12068.966 | C57: =Summary!P88+Summary!P94 -> 5586.16 | D57: =C57/$B$4*$B$3 -> 5586.16 | E57: =D57/B57-1 -> -0.53714674 | F57: =D57-B57 -> -6482.8055
A58: 16 | B58: =$B$72/$B$39 -> 12068.966 | C58: =Summary!Q88+Summary!Q94 -> 5811.59 | D58: =C58/$B$4*$B$3 -> 5811.59 | E58: =D58/B58-1 -> -0.51846826 | F58: =D58-B58 -> -6257.3755
A59: 17 | B59: =$B$72/$B$39 -> 12068.966 | C59: =Summary!R88+Summary!R94 -> 5372.2 | D59: =C59/$B$4*$B$3 -> 5372.2 | E59: =D59/B59-1 -> -0.55487486 | F59: =D59-B59 -> -6696.7655
A60: 18 | B60: =$B$72/$B$39 -> 12068.966 | C60: =Summary!S88+Summary!S94 -> 4904.66 | D60: =C60/$B$4*$B$3 -> 4904.66 | E60: =D60/B60-1 -> -0.59361389 | F60: =D60-B60 -> -7164.3055
A61: 19 | B61: =$B$72/$B$39 -> 12068.966 | C61: =Summary!T88+Summary!T94 -> 4278.83 | D61: =C61/$B$4*$B$3 -> 4278.83 | E61: =D61/B61-1 -> -0.64546837 | F61: =D61-B61 -> -7790.1355
A62: 20 | B62: =$B$72/$B$39 -> 12068.966 | C62: =Summary!U88+Summary!U94 -> 4535.25 | D62: =C62/$B$4*$B$3 -> 4535.25 | E62: =D62/B62-1 -> -0.62422214 | F62: =D62-B62 -> -7533.7155
A63: 21 | B63: =$B$72/$B$39 -> 12068.966 | C63: =Summary!V88+Summary!V94 -> 4911.65 | D63: =C63/$B$4*$B$3 -> 4911.65 | E63: =D63/B63-1 -> -0.59303471 | F63: =D63-B63 -> -7157.3155
A64: 22 | B64: =$B$72/$B$39 -> 12068.966 | C64: =Summary!W88+Summary!W94 -> 4635.1089 | D64: =C64/$B$4*$B$3 -> 4635.1089 | E64: =D64/B64-1 -> -0.61594812 | F64: =D64-B64 -> -7433.8566
A65: 23 | B65: =$B$72/$B$39 -> 12068.966 | C65: =Summary!X88+Summary!X94 -> 6432.6181 | D65: =C65/$B$4*$B$3 -> 6432.6181 | E65: =D65/B65-1 -> -0.46701164 | F65: =D65-B65 -> -5636.3474
A66: 24 | B66: =$B$72/$B$39 -> 12068.966 | C66: =Summary!Y88+Summary!Y94 -> 5540.3665 | D66: =C66/$B$4*$B$3 -> 5540.3665 | E66: =D66/B66-1 -> -0.54094106 | F66: =D66-B66 -> -6528.599
A67: 25 | B67: =$B$72/$B$39 -> 12068.966 | C67: =Summary!Z88+Summary!Z94 -> 3362.7824 | D67: =C67/$B$4*$B$3 -> 3362.7824 | E67: =D67/B67-1 -> -0.72136946 | F67: =D67-B67 -> -8706.1831
A68: 26 | B68: =$B$72/$B$39 -> 12068.966 | C68: =Summary!AA88+Summary!AA94 -> 2516.83 | D68: =C68/$B$4*$B$3 -> 2516.83 | E68: =D68/B68-1 -> -0.79146266 | F68: =D68-B68 -> -9552.1355
A69: 27 | B69: =$B$72/$B$39 -> 12068.966 | C69: =Summary!AB88+Summary!AB94 -> 2754.03 | D69: =C69/$B$4*$B$3 -> 2754.03 | E69: =D69/B69-1 -> -0.77180894 | F69: =D69-B69 -> -9314.9355
A70: 28 | B70: =$B$72/$B$39 -> 12068.966 | C70: =Summary!AC88+Summary!AC94 -> 2903.5119 | D70: =C70/$B$4*$B$3 -> 2903.5119 | E70: =D70/B70-1 -> -0.7594233 | F70: =D70-B70 -> -9165.4536
A71: 29 | B71: =$B$72/$B$39 -> 12068.966 | C71: =Summary!AD88+Summary!AD94 -> 2608.01 | D71: =C71/$B$4*$B$3 -> 2608.01 | E71: =D71/B71-1 -> -0.78390774 | F71: =D71-B71 -> -9460.9555
A72: TOTAL | B72: =H15 -> 350000 | C72: =sum(C43:C71) -> 282862.42 | D72: =C72/$B$4*$B$3 -> 282862.42 | E72: =D72/B72-1 -> -0.19182165 | F72: =D72-B72 -> -67137.578
A74: Start date: | B74: 45293 | D74: End date: | E74: 28/02/2024
A75: Days | B75: 29 | C75: TRAFFIC (Sessions GA4)
A76: Current day | B76: =COUNT(C79:C106) -> 26
B77: ACTUALS | D77: Linear Projection
A78: DAYS | B78: TRAFFIC PLAN | C78: Current day | D78: Linear Projection | E78: % Plan (linear projection) | F78: Linear Projection GAP
A79: 1 | B79: =$B$108/$B$75 -> 10344.828 | C79: 7805 | D79: =C79/$B$4*$B$3 -> 7805 | E79: =D79/B79-1 -> -0.24551667 | F79: =D79-B79 -> -2539.8276
A80: 2 | B80: =$B$108/$B$75 -> 10344.828 | C80: 9042 | D80: =C80/$B$4*$B$3 -> 9042 | E80: =D80/B80-1 -> -0.12594 | F80: =D80-B80 -> -1302.8276
A81: 3 | B81: =$B$108/$B$75 -> 10344.828 | C81: 8914 | D81: =C81/$B$4*$B$3 -> 8914 | E81: =D81/B81-1 -> -0.13831333 | F81: =D81-B81 -> -1430.8276
A82: 4 | B82: =$B$108/$B$75 -> 10344.828 | C82: 8905 | D82: =C82/$B$4*$B$3 -> 8905 | E82: =D82/B82-1 -> -0.13918333 | F82: =D82-B82 -> -1439.8276
A83: 5 | B83: =$B$108/$B$75 -> 10344.828 | C83: 10176 | D83: =C83/$B$4*$B$3 -> 10176 | E83: =D83/B83-1 -> -0.01632 | F83: =D83-B83 -> -168.82759
A84: 6 | B84: =$B$108/$B$75 -> 10344.828 | C84: 10266 | D84: =C84/$B$4*$B$3 -> 10266 | E84: =D84/B84-1 -> -0.00762 | F84: =D84-B84 -> -78.827586
A85: 7 | B85: =$B$108/$B$75 -> 10344.828 | C85: 8809 | D85: =C85/$B$4*$B$3 -> 8809 | E85: =D85/B85-1 -> -0.14846333 | F85: =D85-B85 -> -1535.8276
A86: 8 | B86: =$B$108/$B$75 -> 10344.828 | C86: 10764 | D86: =C86/$B$4*$B$3 -> 10764 | E86: =D86/B86-1 -> 0.04052 | F86: =D86-B86 -> 419.17241
A87: 9 | B87: =$B$108/$B$75 -> 10344.828 | C87: 10676 | D87: =C87/$B$4*$B$3 -> 10676 | E87: =D87/B87-1 -> 0.032013333 | F87: =D87-B87 -> 331.17241
A88: 10 | B88: =$B$108/$B$75 -> 10344.828 | C88: 9889 | D88: =C88/$B$4*$B$3 -> 9889 | E88: =D88/B88-1 -> -0.044063333 | F88: =D88-B88 -> -455.82759
A89: 11 | B89: =$B$108/$B$75 -> 10344.828 | C89: 9278 | D89: =C89/$B$4*$B$3 -> 9278 | E89: =D89/B89-1 -> -0.10312667 | F89: =D89-B89 -> -1066.8276
A90: 12 | B90: =$B$108/$B$75 -> 10344.828 | C90: 8337 | D90: =C90/$B$4*$B$3 -> 8337 | E90: =D90/B90-1 -> -0.19409 | F90: =D90-B90 -> -2007.8276
... A104: 26 | B104: =$B$108/$B$75 -> 10344.828 | C104: 17906 | D104: =C104/$B$4*$B$3 -> 17906 | E104: =D104/B104-1 -> 0.73091333 | F104: =D104-B104 -> 7561.1724
A105: 27 | B105: =$B$108/$B$75 -> 10344.828 | D105: =C105/$B$4*$B$3 -> 0 | E105: =D105/B105-1 -> -1 | F105: =D105-B105 -> -10344.828
A106: 28 | B106: =$B$108/$B$75 -> 10344.828 | D106: =C106/$B$4*$B$3 -> 0 | E106: =D106/B106-1 -> -1 | F106: =D106-B106 -> -10344.828
A107: 29 | B107: =$B$108/$B$75 -> 10344.828 | D107: =C107/$B$4*$B$3 -> 0 | E107: =D107/B107-1 -> -1 | F107: =D107-B107 -> -10344.828
A108: TOTAL | B108: =H20 -> 300000 | C108: =sum(C79:C107) -> 356747 | D108: =C108/$B$4*$B$3 -> 356747 | E108: =D108/B108-1 -> 0.18915667 | F108: =D108-B108 -> 56747
A113: Date | B113: Sessions | C113: Active users
A114: 45323 | B114: 7805 | C114: 6602
A115: 45324 | B115: 9042 | C115: 7908
A116: 45325 | B116: 8914 | C116: 7406
A117: 45326 | B117: 8905 | C117: 7418
A118: 45327 | B118: 10176 | C118: 8644
A119: 45328 | B119: 10266 | C119: 8874
A120: 45329 | B120: 8809 | C120: 7535
...

Sheet Working Copy B2B - P&L
A1: JANUARY | B1: 45323 | C1: 45324 | D1: 45325 | E1: 45326 | F1: 45327 | G1: 45328 | H1: 45329 | I1: 45330 | J1: 45331 | K1: 45332 | L1: 45333 | M1: 45334 | N1: 45335 | O1: 45336 | P1: 45337 | Q1: 45338 | R1: 45339 | S1: 45340 | T1: 45341 | U1: 45342 | V1: 45343 | W1: 45344 | X1: 45345 | Y1: 45346 | Z1: 45347 | AA1: 45348 | AB1: 45349 | AC1: 45350 | AD1: 45351
A2: DAY | B2: THU | C2: FRI | D2: SAT | E2: SUN | F2: MON | G2: TUE | H2: WED | I2: THU | J2: FRI | K2: SAT | L2: SUN | M2: MON | N2: TUE | O2: WED | P2: THU | Q2: FRI | R2: SAT | S2: SUN | T2: MON | U2: TUE | V2: WED | W2: THU | X2: FRI | Y2: SAT | Z2: SUN | AA2: MON | AB2: TUE | AC2: WED | AD2: THU
A3: Best Buy 🟡
A4: Revenue | B4: =Summary!B34 -> 3992.9868 | C4: =Summary!C35 -> 4598 | D4: =Summary!D35 -> 0 | E4: =Summary!E35 -> 627 | F4: =Summary!F35 -> 4389 | G4: =Summary!G35 -> 2926 | H4: =Summary!H35 -> 2299 | I4: =Summary!I35 -> 2299 | J4: =Summary!J35 -> 1881 | ... U4: =Summary!U35 -> 16744 | V4: =Summary!V34 -> 3490.9446 | W4: =Summary!W34 -> 5712.4548 | X4: =Summary!X34 -> 6029.8134 | Y4: =Summary!Y34 -> 0 | Z4: =Summary!Z34 -> 3173.586 | AA4: =Summary!AA34 -> 8568.6822 | AB4: =Summary!AB34 -> 7299.2478 | AC4: =Summary!AC34 -> 7616.6064 | AD4: =Summary!AD34 -> 12059.627 | AE4: =sum(B4:AD4) -> 128149.95
A5: Breakdown
A6: - Tax | B6: =Summary!B36 -> 230.9868 | C6: =Summary!C36 -> 282.3172 | D6: =Summary!D36 -> 0 | E6: =Summary!E36 -> 38.4978 | F6: =Summary!F36 -> 269.4846 | G6: =Summary!G36 -> 179.6564 | H6: =Summary!H36 -> 141.1586 | I6: =Summary!I36 -> 141.1586 | ... AD6: =Summary!AD36 -> 697.6268 | AE6: =sum(B6:AD6) -> 7662.5972
A7: - Shipping | B7: =Summary!B37 | C7: =Summary!C37 | D7: =Summary!D37 | E7: =Summary!E37 | F7: =Summary!F37 | G7: =Summary!G37 | H7: =Summary!H37 | I7: =Summary!I37 | ... AD7: =Summary!AD37 | AE7: =sum(B7:AD7) -> 0
A8: Orders | B8: =Summary!B67 -> 18 | C8: =Summary!C67 -> 22 | D8: =Summary!D67 -> 0 | E8: =Summary!E67 -> 3 | F8: =Summary!F67 -> 21 | G8: =Summary!G67 -> 14 | H8: =Summary!H67 -> 11 | I8: =Summary!I67 -> 11 | ... AD8: =Summary!AD67 -> 38 | AE8: =sum(B8:AD8) -> 452
A10: Best Buy Commission (17%, pri solar $239 je 15%, pri BF $209 imajo 10%) | AE10: =sum(B10:AD10) -> 0
A11: Agency Comission
A12: Units Sold (Net) - Best Buy
A13: SKU 1 - Blue | AE13: =sum(B13:AD13) -> 0
A14: SKU 2 - Yellow | AE14: =sum(B14:AD14) -> 0
A15: SKU 3 - Blue w/ Solar | B15: =B8 -> 18 | C15: =C8 -> 22 | D15: =D8 -> 0 | E15: =E8 -> 3 | F15: =F8 -> 21 | G15: =G8 -> 14 | H15: =H8 -> 11 | I15: =I8 -> 11 | ... AD15: =AD8 -> 38 | AE15: =sum(B15:AD15) -> 452
A16: SKU 4 - Yellow w/ Solar | AE16: =sum(B16:AD16) -> 0
A17: SUM (SKU 1 - SKU 4) | B17: =SUM(B13:B16) -> 18 | C17: =SUM(C13:C16) -> 22 | D17: =SUM(D13:D16) -> 0 | E17: =SUM(E13:E16) -> 3 | F17: =SUM(F13:F16) -> 21 | G17: =SUM(G13:G16) -> 14 | H17: =SUM(H13:H16) -> 11 | I17: =SUM(I13:I16) -> 11 | ... AD17: =SUM(AD13:AD16) -> 38 | AE17: =sum(B17:AD17) -> 452
A19: Wall Mount | AE19: =sum(B19:AD19) -> 0
A20: Suet Ball Holder | AE20: =sum(B20:AD20) -> 0
A21: 3-in-1 Nutrition Set - Blue | AE21: =sum(B21:AD21) -> 0
A22: 3-in-1 Nutrition Set - Yellow | AE22: =sum(B22:AD22) -> 0
A23: Solar Roof Single - Blue | AE23: =sum(B23:AD23) -> 0
A24: Solar Roof Single - Yellow | AE24: =sum(B24:AD24) -> 0
A25: Perch Extender - Blue | AE25: =sum(B25:AD25) -> 0
A26: Perch Extender - Yellow | AE26: =sum(B26:AD26) -> 0
