Workbook
Name zsupermetrics_ru0GDtbZzDLHQOQtJJ6K08MvUDyyp7: Formulas!$G$5:$G$6
Name zsupermetrics_lx4cNai7gT6tH4j08ZRkI21Qlpjioi: Formulas!$G$5:$H$14
Name rdataslayer_d70e473bcafe40a3aa834ce157fb2ba3: Formulas!$H$9:$I$10
Name zsupermetrics_refreshAll: SupermetricsQueries!$H$5
Name zsupermetrics_8xojRjNDjo2jWHGDWjFEhflhyIq3Hq: Sales!$K$9:$K$10
Name zsupermetrics_n3GtLgiKpTmd2pYmQNMuq6TPD0qE0b: Formulas!$G$5:$G$6
Name rdataslayer_3753ddf3234e496aa261974a0222e193: Formulas!$M$3:$N$3
Name zsupermetrics_refreshAllSilent: SupermetricsQueries!$H$6
Name zsupermetrics_BioPyGBzcBsy60UCQmPcTuFReEmghI: Formulas!$G$3:$G$4
Name zsupermetrics_qWp7V908pNEYMtfv8QZvSTeDnBAHOU: Formulas!$G$6:$H$14
Name zsupermetrics_Mgms9p0QzysYvrIhnsKACeVBVxfIEO: Formulas!$F$3:$F$4
Name zsupermetrics_forceRefresh: SupermetricsQueries!$H$4
Name zsupermetrics_wbYMmT0YL9bAN0yhimW0ziPFnia9Dx: Formulas!$F$3:$F$4
Name zsupermetrics_iNpyVy90bWCI0yUaFQpxOtzWMa6sW4: Formulas!$F$3:$F$4
Name zsupermetrics_9i4W4hgd80uRpQLMeX0eRnESN8gjyv: Formulas!$H$14
Name rdataslayer_42b112e4e4be4305bb4c1be75e2dd549: Formulas!$G$3:$H$4
Name zsupermetrics_pxuhRTEmIU93xSgKclyxajD0fCZ6rF: #REF!
Name rdataslayer_4a0f150f4f2f4e4f85c890c75b7a1fa4: Formulas!$I$3:$J$4
Name rdataslayer_adf57e64065742daa5b4161161b1c3ca: Formulas!$G$5:$I$6
Name zsupermetrics_HgZqhorObHOtZHuyJjpmyYaEPoYntx: Formulas!$G$5:$G$6
Name zsupermetrics_NugLlrQxlKiqhxQae8EFpITBm1pLCj: Formulas!$G$7:$H$14
Name zsupermetrics_xwoIpANxRm908eDp5oKTwQpEI8gvD4: Formulas!$F$3
Name zsupermetrics_YsFuuYtr8vOdNXCCPiFJIO38NP4b2T: Formulas!$G$5:$H$14
Name zsupermetrics_DQl8lUbpTRu3fayaJJi7lVfOGKjNU4: Formulas!$F$4:$F$5
Name zsupermetrics_4VkB7ij7WO0JjKBEgvjB2GHjSy2Egm: Formulas!$G$5:$H$11

Sheet DataslayerQueries
A1: Query UUID | B1: Sheet name | C1: Range address | D1: Created | E1: Updated | F1: Last status | G1: Last refresh ID | H1: Results contain sampled data | I1: Execution time (sec) | J1: Object type | K1: Linked chart ID | L1: Data source | M1: Date range type | N1: Start date | O1: End date | P1: Compare to | Q1: Comparison value type | R1: Accounts/views | S1: Metrics | T1: Dimensions | U1: Pivot dimensions | V1: Filters | W1: Segment ID | X1: Segment dim | Y1: Sort | Z1: Max rows | AA1: Max pivot categories | AB1: Special settings | AC1: Other parameters | AD1: Result type | AE1: Language/country | AF1: Translate to | AG1: SQL | AH1: Database name | AI1: Range address (static) | AJ1: Report type | AK1: Highlight with colour | AL1: Refresh with user account | AM1: Returned data | AN1: Sort dimensions | AO1: Created by user account
A2: 42b112e4e4be4305bb4c1be75e2dd549 | B2: =IFERROR(__xludf.DUMMYFUNCTION("ARRAY_CONSTRAIN(split(CELL(""ADDRESS"",rdataslayer_42b112e4e4be4305bb4c1be75e2dd549),""!""),1,1)"),"Formulas") -> Formulas | C2: =IFERROR(__xludf.DUMMYFUNCTION("INDEX(split(CELL(""ADDRESS"",rdataslayer_42b112e4e4be4305bb4c1be75e2dd549),""!""),0,2)&"":""&address(row(rdataslayer_42b112e4e4be4305bb4c1be75e2dd549)+rows(rdataslayer_42b112e4e4be4305bb4c1be75e2dd549)-1,column(rdataslayer_42b112e4e4be4305bb4c1be75e2dd549"&")+COLUMNS(rdataslayer_42b112e4e4be4305bb4c1be75e2dd549)-1)"),"$G$3:$H$4") -> $G$3:$H$4 | D2: 44518.613 | E2: 44520.051 | F2: There is no data for the specified input | I2: 7 | J2: TABLE | L2: facebook | M2: yesterday | R2: [{"profile_id":"","name":"si_Bird buddy Inc_US &amp; CA_BirdBuddy","id":"act_273249767551281","account_name":"","advertiser_id":""}] | S2: [{"id":"spend","name":"Total Cost"}] | T2: [{"id":"date","name":"Date"}] | U2: [] | V2: [] | W2: [] | Y2: [] | Z2: 5 | AA2: 5 | AB2: {} | AC2: {} | AL2: User_Kumalic_Benjamin | AN2: [] | AO2: benjamin@mybirdbuddy.com
A3: 4a0f150f4f2f4e4f85c890c75b7a1fa4 | B3: =IFERROR(__xludf.DUMMYFUNCTION("ARRAY_CONSTRAIN(split(CELL(""ADDRESS"",rdataslayer_4a0f150f4f2f4e4f85c890c75b7a1fa4),""!""),1,1)"),"Formulas") -> Formulas | C3: =IFERROR(__xludf.DUMMYFUNCTION("INDEX(split(CELL(""ADDRESS"",rdataslayer_4a0f150f4f2f4e4f85c890c75b7a1fa4),""!""),0,2)&"":""&address(row(rdataslayer_4a0f150f4f2f4e4f85c890c75b7a1fa4)+rows(rdataslayer_4a0f150f4f2f4e4f85c890c75b7a1fa4)-1,column(rdataslayer_4a0f150f4f2f4e4f85c890c75b7a1fa4"&")+COLUMNS(rdataslayer_4a0f150f4f2f4e4f85c890c75b7a1fa4)-1)"),"$I$3:$J$4") -> $I$3:$J$4 | D3: 44518.615 | E3: 44520.051 | F3: There is no data for the specified input | I3: 7 | J3: TABLE | L3: facebook | M3: yesterday | R3: [{"account_name":"","advertiser_id":"","id":"act_273249767551281","profile_id":"","name":"si_Bird buddy Inc_US &amp; CA_BirdBuddy"}] | S3: [{"id":"spend","name":"Total Cost"}] | T3: [] | U3: [{"id":"date","name":"Date"}] | V3: [] | W3: [] | Y3: [] | Z3: 5 | AA3: 5 | AB3: {} | AC3: {} | AL3: User_Kumalic_Benjamin | AN3: [] | AO3: benjamin@mybirdbuddy.com
A4: adf57e64065742daa5b4161161b1c3ca | B4: =IFERROR(__xludf.DUMMYFUNCTION("ARRAY_CONSTRAIN(split(CELL(""ADDRESS"",rdataslayer_adf57e64065742daa5b4161161b1c3ca),""!""),1,1)"),"Formulas") -> Formulas | C4: =IFERROR(__xludf.DUMMYFUNCTION("INDEX(split(CELL(""ADDRESS"",rdataslayer_adf57e64065742daa5b4161161b1c3ca),""!""),0,2)&"":""&address(row(rdataslayer_adf57e64065742daa5b4161161b1c3ca)+rows(rdataslayer_adf57e64065742daa5b4161161b1c3ca)-1,column(rdataslayer_adf57e64065742daa5b4161161b1c3ca"&")+COLUMNS(rdataslayer_adf57e64065742daa5b4161161b1c3ca)-1)"),"$G$5:$I$6") -> $G$5:$I$6 | D4: 44518.618 | E4: 44520.051 | F4: There is no data for the specified input | I4: 18 | J4: TABLE | L4: facebook | M4: yesterday | R4: [{"name":"si_Bird buddy Inc_US &amp; CA_BirdBuddy","id":"act_273249767551281","profile_id":"","account_name":"","advertiser_id":""}] | S4: [{"id":"spend","name":"Total Cost"},{"id":"cpm","name":"CPM"}] | T4: [{"id":"date","name":"Date"}] | U4: [] | V4: [] | W4: [] | Y4: [] | Z4: 5 | AA4: 5 | AB4: {} | AC4: {} | AL4: User_Kumalic_Benjamin | AN4: [] | AO4: benjamin@mybirdbuddy.com
A5: d70e473bcafe40a3aa834ce157fb2ba3 | B5: =IFERROR(__xludf.DUMMYFUNCTION("ARRAY_CONSTRAIN(split(CELL(""ADDRESS"",rdataslayer_d70e473bcafe40a3aa834ce157fb2ba3),""!""),1,1)"),"Formulas") -> Formulas | C5: =IFERROR(__xludf.DUMMYFUNCTION("INDEX(split(CELL(""ADDRESS"",rdataslayer_d70e473bcafe40a3aa834ce157fb2ba3),""!""),0,2)&"":""&address(row(rdataslayer_d70e473bcafe40a3aa834ce157fb2ba3)+rows(rdataslayer_d70e473bcafe40a3aa834ce157fb2ba3)-1,column(rdataslayer_d70e473bcafe40a3aa834ce157fb2ba3"&")+COLUMNS(rdataslayer_d70e473bcafe40a3aa834ce157fb2ba3)-1)"),"$H$9:$I$10") -> $H$9:$I$10 | D5: 44518.619 | E5: 44520.051 | F5: There is no data for the specified input | I5: 7 | J5: TABLE | L5: facebook | M5: yesterday | R5: [{"advertiser_id":"","name":"si_Bird buddy Inc_US &amp; CA_BirdBuddy","id":"act_273249767551281","account_name":"","profile_id":""}] | S5: [{"id":"spend","name":"Total Cost"}] | T5: [{"id":"date","name":"Date"}] | U5: [] | V5: [] | W5: [] | Y5: [] | Z5: 100 | AA5: 100 | AB5: {} | AC5: {} | AL5: User_Kumalic_Benjamin | AN5: [] | AO5: benjamin@mybirdbuddy.com
A6: 3753ddf3234e496aa261974a0222e193 | B6: =IFERROR(__xludf.DUMMYFUNCTION("ARRAY_CONSTRAIN(split(CELL(""ADDRESS"",rdataslayer_3753ddf3234e496aa261974a0222e193),""!""),1,1)"),"Formulas") -> Formulas | C6: =IFERROR(__xludf.DUMMYFUNCTION("INDEX(split(CELL(""ADDRESS"",rdataslayer_3753ddf3234e496aa261974a0222e193),""!""),0,2)&"":""&address(row(rdataslayer_3753ddf3234e496aa261974a0222e193)+rows(rdataslayer_3753ddf3234e496aa261974a0222e193)-1,column(rdataslayer_3753ddf3234e496aa261974a0222e193"&")+COLUMNS(rdataslayer_3753ddf3234e496aa261974a0222e193)-1)"),"$M$3:$N$3") -> $M$3:$N$3 | D6: 44518.621 | E6: 44520.051 | F6: There is no data for the specified input | I6: 18 | J6: TABLE | L6: facebook | M6: yesterday | R6: [{"profile_id":"","account_name":"","advertiser_id":"","name":"si_Bird buddy Inc_US &amp; CA_BirdBuddy","id":"act_273249767551281"}] | S6: [{"id":"spend","name":"Total Cost"}] | T6: [] | U6: [] | V6: [] | W6: [] | Y6: [] | Z6: 100 | AA6: 100 | AB6: {"exclude_header_row":true} | AC6: {} | AL6: User_Kumalic_Benjamin | AN6: [] | AO6: benjamin@mybirdbuddy.com

Sheet Sales
A1: 44927 | B1: 44927 | C1: 44928 | D1: 44929 | E1: 44930 | F1: 44931 | G1: 44932 | H1: 44933 | I1: 44934 | J1: 44935 | K1: 44936 | L1: 44937 | M1: 44938 | N1: 44939 | O1: 44940 | P1: 44941 | Q1: 44942 | R1: 44943 | S1: 44944 | T1: 44945 | U1: 44946 | V1: 44947 | W1: 44948 | X1: 44949 | Y1: 44950 | Z1: 44951 | AA1: 44952 | AB1: 44953 | AC1: 44954 | AD1: 44955 | AE1: 44956 | AF1: 44957
B2: SUN | C2: MON | D2: TUE | E2: WED | F2: THU | G2: FRI | H2: SAT | I2: SUN | J2: MON | K2: TUE | L2: WED | M2: THU | N2: FRI | O2: SAT | P2: SUN | Q2: MON | R2: TUE | S2: WED | T2: THU | U2: FRI | V2: SAT | W2: SUN | X2: MON | Y2: TUE | Z2: WED | AA2: THU | AB2: FRI | AC2: SAT | AD2: SUN | AE2: MON | AF2: TUE
A3: Weekend Work | B3: Gaja | C3: Gaja | H3: Peter | I3: Peter | O3: Gaja | P3: Gaja | V3: Beno | W3: Beno | AC3: Peter | AD3: Peter
A5: Notes | C5: Mailing: Seed Gifting Test (1000) | E5: Referral Email
E6: CES | K6: Referral Email Follow-up | R6: Shopify Changes / Importing orders | Y6: Shopify Changes / Importing orders | AF6: Shopify Changes / Importing orders
A9: Shopify | B9: 34095.88 | C9: 31641.32 | D9: 21298.63 | E9: 88938.99 | F9: 77859.14 | G9: 71302.37 | H9: 67401.38 | I9: 45352.29 | J9: 42090.23 | K9: 54110.75 | L9: 37408.2 | M9: 26654.04 | N9: 35680.11 | O9: 32029.59 | P9: 41439.96 | Q9: 33693.94 | R9: 34955.95 | S9: 28882.73 | T9: 34351.04 | U9: 35450.41 | V9: 41523.18 | W9: 36775.13 | X9: 33385.99 | Y9: 38224.82 | Z9: 37011.21 | AA9: 29926.52 | AB9: 39472.04 | AC9: 39334.25 | AD9: 41568.81 | AE9: 38837.36 | AF9: 39688.03
A10: Total Revenue | B10: =SUM(B9) -> 34095.88 | C10: =SUM(C9) -> 31641.32 | D10: =SUM(D9) -> 21298.63 | E10: =SUM(E9) -> 88938.99 | F10: =SUM(F9) -> 77859.14 | G10: =SUM(G9) -> 71302.37 | H10: =SUM(H9) -> 67401.38 | I10: =SUM(I9) -> 45352.29 | ... AF10: =SUM(AF9) -> 39688.03
A11: Orders | B11: 184 | C11: 174 | D11: 136 | E11: 372 | F11: 314 | G11: 283 | H11: 262 | I11: 212 | J11: 178 | K11: 289 | L11: 171 | M11: 113 | N11: 144 | O11: 136 | P11: 176 | Q11: 146 | R11: =253-69 -> 184 | S11: 119 | T11: 138 | U11: 133 | V11: 158 | W11: 157 | X11: 127 | Y11: 152 | Z11: 141 | AA11: 112 | AB11: 145 | AC11: 156 | AD11: 164 | AE11: 135 | AF11: 140
A13: FB - US & CA | B13: 6003.49 | C13: 5666.34 | D13: 5287.53 | E13: 5405.32 | F13: 5448.5 | G13: 6253.48 | H13: 4657.96 | I13: 4892.4 | J13: 4507.56 | K13: 4379.15 | L13: 4295.76 | M13: 4171.36 | N13: 4409.89 | O13: 4930.36 | P13: 5160.51 | Q13: 4972.37 | R13: 4662.58 | S13: 4469.93 | T13: 5539.33 | U13: 6580.63 | V13: 8133.65 | W13: 9351.24 | X13: 8863.02 | Y13: 8805.28 | Z13: 8629.72 | AA13: 8138.59 | AB13: 6958.98 | AC13: 7798.06 | AD13: 7872.09 | AE13: 9682.09 | AF13: 9677.62
A14: Google - WW | B14: 2600 | C14: 2990 | D14: 2520 | E14: 3230 | F14: 3500 | G14: 2296.12 | H14: 2822.09 | I14: 2213.61 | J14: 1789.04 | K14: 2123.89 | L14: 1479.12 | M14: 1610.83 | N14: 1900 | O14: 2220 | P14: 2618.92 | Q14: 2856.36 | R14: 2308.9 | S14: 2076.88 | T14: 2047.28 | U14: 2396.9 | V14: 2607.87 | W14: 2318.01 | X14: 2109.62 | Y14: 2052.02 | Z14: 1595.22 | AA14: 1830.99 | AB14: 1987.12 | AC14: 2012.09 | AD14: 2048.27 | AE14: 1765.94 | AF14: 1573.76
A15: Bing - WW | B15: 83.03 | C15: 91.99 | D15: 89.3 | E15: 155.15 | F15: 152.58 | G15: 154.02 | H15: 126.99 | I15: 139.77 | J15: 148.1 | K15: 137.47 | L15: 129.34 | M15: 109.4 | N15: 113.26 | O15: 69.12 | P15: 84.21 | Q15: 125.1 | R15: 72.17 | S15: 71.99 | T15: 86.35 | U15: 75.36 | V15: 52.14 | W15: 80.81 | X15: 82.51 | Y15: 104.32 | Z15: 96.31 | AA15: 65.31 | AB15: 78.43 | AC15: 69.32 | AD15: 66.38 | AE15: 88.33 | AF15: 78.76
A16: TikTok - US & CA | G16: 248.33 | H16: 248.96
A17: MNTN TV
A18: Affiliate Fees - US | H18: 0 | I18: 0 | J18: 0 | K18: 15.47 | L18: 0 | M18: 0 | N18: 0 | O18: 0 | P18: 0 | Q18: 0 | R18: 0 | S18: 0 | T18: 0 | U18: =63.03+70.29 -> 133.32 | V18: 0 | W18: 0 | X18: 0 | Y18: 0 | Z18: 0 | AA18: 0 | AB18: 50.08 | AC18: 0 | AD18: 0 | AE18: 0 | AF18: 59.8
A19: Total Spend | B19: =SUM(B13:B18) -> 8686.52 | C19: =SUM(C13:C18) -> 8748.33 | D19: =SUM(D13:D18) -> 7896.83 | E19: =SUM(E13:E18) -> 8790.47 | F19: =SUM(F13:F18) -> 9101.08 | G19: =SUM(G13:G18) -> 8951.95 | H19: =SUM(H13:H18) -> 7856 | I19: =SUM(I13:I18) -> 7245.78 | ... AF19: =SUM(AF13:AF18) -> 11389.94
A21: ROAS | B21: =B10/B19 -> 3.9251484 | C21: =C10/C19 -> 3.6168412 | D21: =D10/D19 -> 2.6971114 | E21: =E10/E19 -> 10.11766 | F21: =F10/F19 -> 8.5549341 | G21: =G10/G19 -> 7.9650099 | H21: =H10/H19 -> 8.5796054 | I21: =I10/I19 -> 6.2591315 | ... AF21: =AF10/AF19 -> 3.484481
A22: CAC | B22: =B19/B11 -> 47.209348 | C22: =C19/C11 -> 50.277759 | D22: =D19/D11 -> 58.064926 | E22: =E19/E11 -> 23.630296 | F22: =F19/F11 -> 28.984331 | G22: =G19/G11 -> 31.632332 | H22: =H19/H11 -> 29.984733 | I22: =I19/I11 -> 34.178208 | ... AF22: =AF19/AF11 -> 81.356714
A23: CR | B23: 0.0175 | C23: 0.0156 | D23: 0.0142 | E23: 0.0194 | F23: 0.0141 | G23: 0.012 | H23: 0.0145 | I23: 0.0143 | J23: 0.0138 | K23: 0.0227 | L23: 0.017 | M23: 0.0106 | N23: 0.0138 | O23: 0.0127 | P23: 0.0157 | Q23: 0.0131 | R23: 0.0174 | S23: 0.0124 | T23: 0.0112 | U23: 0.0103 | V23: 0.0106 | W23: 0.0099 | X23: 0.0095 | Y23: 0.0088 | Z23: 0.009 | AA23: 0.0096 | AB23: 0.0108 | AC23: 0.0112 | AD23: 0.0121 | AE23: 0.0101 | AF23: 0.0096
A24: AOV | B24: =B10/B11 -> 185.3037 | C24: =C10/C11 -> 181.84667 | D24: =D10/D11 -> 156.60757 | E24: =E10/E11 -> 239.08331 | F24: =F10/F11 -> 247.95904 | G24: =G10/G11 -> 251.95184 | H24: =H10/H11 -> 257.25718 | I24: =I10/I11 -> 213.9259 | ... AF24: =AF10/AF11 -> 283.48593
A25: fAOV | B25: 218.0978 | C25: 213.02 | D25: 165.4201 | E25: 274.63464 | F25: 276.50143 | G25: 278.59234 | H25: 277.46098 | I25: 252.45385 | J25: 264.79034 | K25: 227.35969 | L25: 261.57974 | M25: 266.42989 | N25: 267.20383 | O25: 278.16396 | P25: 252.99895 | Q25: 256.16546 | R25: 219.09607 | S25: 268.32868 | T25: 288.91565 | U25: 287.70292 | V25: 285.63031 | W25: 266.16254 | X25: 278.8422 | Y25: 265.78616 | Z25: 287.00687 | AA25: 282.78946 | AB25: 287.54464 | AC25: 277.4263 | AD25: 278.86157 | AE25: 306.62818 | AF25: 300.16
A26: rAOV | B26: 112.23614 | C26: 112.57 | D26: 86.11 | E26: 138.92592 | F26: 131.08381 | G26: 121.52438 | H26: 164.83553 | I26: 105.26982 | J26: 102.13065 | K26: 137.46667 | L26: 130.83089 | M26: 116.31957 | N26: 170.74724 | O26: 84.807 | P26: 150.60364 | Q26: 146.37921 | R26: 101.96429 | S26: 159.45786 | T26: 102.063 | U26: 183.47778 | V26: 164.201 | W26: 120.83143 | X26: 194.90852 | Y26: 185.24259 | Z26: 118.22308 | AA26: 195.4945 | AB26: 176.448 | AC26: 146.46821 | AD26: 109.9213 | AE26: 118.95357 | AF26: 189.02
A28: Customers
A29: Returning | B29: 0.3098 | C29: 0.3103 | D29: 0.2941 | E29: 0.2634 | F29: 0.2006 | G29: 0.1696 | H29: 0.1794 | I29: 0.2642 | J29: 0.1742 | K29: 0.4464 | L29: 0.3275 | M29: 0.2035 | N29: 0.2014 | O29: 0.2206 | P29: 0.1875 | Q29: 0.2603 | R29: 0.2283 | S29: 0.2353 | T29: 0.2174 | U29: 0.203 | V29: 0.1899 | W29: 0.2229 | X29: 0.2126 | Y29: 0.1776 | Z29: 0.1844 | AA29: 0.1786 | AB29: 0.1379 | AC29: 0.1806 | AD29: 0.1411 | AE29: 0.1037 | AF29: 0.15
A30: First-time | B30: =1-B29 -> 0.6902 | C30: =1-C29 -> 0.6897 | D30: =1-D29 -> 0.7059 | E30: =1-E29 -> 0.7366 | F30: 0.7994 | G30: =1-G29 -> 0.8304 | H30: =1-H29 -> 0.8206 | I30: =1-I29 -> 0.7358 | J30: =1-J29 -> 0.8258 | K30: =1-K29 -> 0.5536 | L30: =1-L29 -> 0.6725 | M30: =1-M29 -> 0.7965 | N30: =1-N29 -> 0.7986 | ... AF30: =1-AF29 -> 0.85
A32: Post-purchase Survey
A33: Facebook / Instagram | B33: 0.2632 | C33: 0.3137 | D33: 0.1714 | E33: 0.1392 | F33: 0.101 | G33: 0.0667 | H33: 0.1519 | I33: 0.1923 | J33: 0.225 | K33: 0.2903 | L33: 0.2286 | M33: 0.3333 | N33: 0.1522 | O33: 0.1714 | P33: 0.1429 | Q33: 0.1765 | R33: 0.36 | S33: 0.1892 | T33: 0.1707 | U33: 0.1538 | V33: 0.4167 | W33: 0.4167 | X33: 0.3548 | Y33: 0.425 | Z33: 0.2857 | AA33: 0.2 | AB33: 0.3673 | AC33: 0.3158 | AD33: 0.3333 | AE33: 0.4211 | AF33: 0.5526
A34: Friends / Family | B34: 0.6842 | C34: 0.6471 | D34: 0.8286 | E34: 0.3418 | F34: 0.3434 | G34: 0.3867 | H34: 0.443 | I34: 0.4038 | J34: 0.5 | K34: 0.4516 | L34: 0.5429 | M34: 0.2667 | N34: 0.5 | O34: 0.4 | P34: 0.4694 | Q34: 0.4706 | R34: 0.44 | S34: 0.5135 | T34: 0.5366 | U34: 0.5 | V34: 0.4444 | W34: 0.4375 | X34: 0.5806 | Y34: 0.375 | Z34: 0.5238 | AA34: 0.5667 | AB34: 0.5714 | AC34: 0.4474 | AD34: 0.4706 | AE34: 0.4211 | AF34: 0.3158
A35: Google, Yahoo, Bing | B35: 0.0351 | C35: 0.0196 | D35: 0 | E35: 0 | F35: 0.0808 | G35: 0.1067 | H35: 0.1519 | I35: 0.0769 | J35: 0.075 | K35: 0.0161 | L35: 0.0857 | M35: 0.0667 | N35: 0.0435 | O35: 0.1429 | P35: 0.102 | Q35: 0.0588 | R35: 0.04 | S35: 0.0541 | T35: 0.122 | U35: 0.1538 | V35: 0.0833 | W35: 0.0417 | X35: 0 | Y35: 0.05 | Z35: 0.0476 | AA35: 0.1 | AB35: 0.0204 | AC35: 0.1053 | AD35: 0.0588 | AE35: 0.0526 | AF35: 0.0789
A36: Pinterest | B36: 0 | C36: 0 | D36: 0 | E36: 0 | F36: 0 | G36: 0 | H36: 0 | I36: 0 | J36: 0 | K36: 0 | L36: 0 | M36: 0 | N36: 0 | O36: 0 | P36: 0 | Q36: 0 | R36: 0 | S36: 0.027 | T36: 0 | U36: 0 | V36: 0 | W36: 0 | X36: 0 | Y36: 0 | Z36: 0 | AA36: 0 | AB36: 0 | AC36: 0 | AD36: 0 | AE36: 0 | AF36: 0
A37: TikTok | B37: 0 | C37: 0.0196 | D37: 0 | E37: 0.0127 | F37: 0.0202 | G37: 0 | H37: 0.0127 | I37: 0 | J37: 0 | K37: 0.0161 | L37: 0 | M37: 0 | N37: 0.0217 | O37: 0.0286 | P37: 0.0204 | Q37: 0.0294 | R37: 0 | S37: 0.027 | T37: 0.0244 | U37: 0 | V37: 0.0278 | W37: 0.0417 | X37: 0 | Y37: 0.025 | Z37: 0.0238 | AA37: 0 | AB37: 0 | AC37: 0.0526 | AD37: 0 | AE37: 0 | AF37: 0
A38: TV / Radio | B38: 0.0175 | C38: 0 | D38: 0 | E38: 0.0633 | F38: 0.0808 | G38: 0.12 | H38: 0.0759 | I38: 0.0962 | J38: 0.05 | K38: 0.0484 | L38: 0 | M38: 0.0667 | N38: 0.0435 | O38: 0.0857 | P38: 0.0816 | Q38: 0.0882 | R38: 0.08 | S38: 0 | T38: 0 | U38: 0.0385 | V38: 0.0278 | W38: 0 | X38: 0 | Y38: 0.05 | Z38: 0.0714 | AA38: 0 | AB38: 0 | AC38: 0.0789 | AD38: 0 | AE38: 0 | AF38: 0
A39: Blog / Article | B39: 0 | C39: 0 | D39: 0 | E39: 0.443 | F39: 0.3737 | G39: 0.32 | H39: 0.1646 | I39: 0.2308 | J39: 0.15 | K39: 0.1774 | L39: 0.1429 | M39: 0.2667 | N39: 0.2391 | O39: 0.1714 | P39: 0.1837 | Q39: 0.1765 | R39: 0.08 | S39: 0.1892 | T39: 0.1463 | U39: 0.1538 | V39: 0 | W39: 0.0625 | X39: 0.0645 | Y39: 0.075 | Z39: 0.0476 | AA39: 0.1333 | AB39: 0.0408 | AC39: 0 | AD39: 0.1373 | AE39: 0.1053 | AF39: 0.0526
B41: 44927 | C41: Goal | D41: % of Goal
A42: Revenue | B42: =SUM(B10:AF10) -> 1290384.3 | D42: =B42/C42 -> #DIV/0!
A43: Spend | B43: =SUM(B19:AF19) -> 268938.92 | D43: =B43/C43 -> #DIV/0!
A44: ROAS | B44: =B42/B43 -> 4.7980571 | D44: =B44/C44 -> #DIV/0!
A45: CAC | B45: =SUM(B19:AF19)/SUM(B11:AF11) -> 49.337538
A46: CAC per Unit | B46: =B43/B52 -> 71.602481 | D46: =B46/C46 -> #DIV/0!
A47: CR | B47: =AVERAGE(B23:AE23) -> 0.01313 | D47: =B47/C47 -> #DIV/0!
A48: AOV | B48: =B42/B51 -> 236.72432 | D48: =B48/C48 -> #DIV/0!
A49: fAOV | B49: =AVERAGE(B25:AF25) -> 264.89531
A50: rAOV | B50: =AVERAGE(B26:AF26) -> 138.01663
A51: Orders | B51: =SUM(B11:AF11) -> 5451
A52: Units Sold | B52: ='Detailed Report'!AG140 -> 3756 | D52: =B52/C52 -> #DIV/0!

Sheet Detailed Report
A1: JANUARY | B1: 44927 | C1: 44928 | D1: 44929 | E1: 44930 | F1: 44931 | G1: 44932 | H1: 44933 | I1: 44934 | J1: 44935 | K1: 44936 | L1: 44937 | M1: 44938 | N1: 44939 | O1: 44940 | P1: 44941 | Q1: 44942 | R1: 44943 | S1: 44944 | T1: 44945 | U1: 44946 | V1: 44947 | W1: 44948 | X1: 44949 | Y1: 44950 | Z1: 44951 | AA1: 44952 | AB1: 44953 | AC1: 44954 | AD1: 44955 | AE1: 44956 | AF1: 44957
A2: DAY | B2: SUN | C2: MON | D2: TUE | E2: WED | F2: THU | G2: FRI | H2: SAT | I2: SUN | J2: MON | K2: TUE | L2: WED | M2: THU | N2: FRI | O2: SAT | P2: SUN | Q2: MON | R2: TUE | S2: WED | T2: THU | U2: FRI | V2: SAT | W2: SUN | X2: MON | Y2: TUE | Z2: WED | AA2: THU | AB2: FRI | AC2: SAT | AD2: SUN | AE2: MON | AF2: TUE
A3: COMMENT
A4: Transactions
A5: FB (US & CA) | B5: 16 | C5: 17 | D5: 7 | E5: 13 | F5: 11 | G5: 13 | H5: 13 | I5: 6 | J5: 7 | K5: 7 | L5: 7 | M5: 9 | N5: 7 | O5: 8 | P5: 11 | Q5: 8 | R5: 11 | S5: 8 | T5: 6 | U5: 18 | V5: 28 | W5: 19 | X5: 16 | Y5: 24 | Z5: 19 | AA5: 7 | AB5: 27 | AC5: 36 | AD5: 35 | AE5: 35 | AF5: 46 | AG5: =SUM(B5:AF5) -> 495
A6: Google | B6: 50 | C6: 50 | D6: 29 | E6: 45 | F6: 95 | G6: 83 | H6: 89 | I6: 63 | J6: 44 | K6: 52 | L6: 41 | M6: 33 | N6: 53 | O6: 46 | P6: 49 | Q6: 43 | R6: 31 | S6: 33 | T6: 51 | U6: 46 | V6: 38 | W6: 48 | X6: 37 | Y6: 41 | Z6: 43 | AA6: 35 | AB6: 31 | AC6: 39 | AD6: 30 | AE6: 27 | AF6: 36 | AG6: =SUM(B6:AF6) -> 1431
A7: TikTok | B7: 0 | C7: 0 | D7: 0 | E7: 0 | F7: 0 | G7: 1 | H7: 0 | I7: 0 | J7: 0 | K7: 0 | L7: 0 | M7: 0 | N7: 0 | O7: 0 | P7: 0 | Q7: 1 | R7: 0 | S7: 0 | T7: 0 | U7: 0 | V7: 0 | W7: 0 | X7: 0 | Y7: 0 | Z7: 0 | AA7: 0 | AB7: 0 | AC7: 0 | AD7: 0 | AE7: 0 | AF7: 0 | AG7: =SUM(B7:AF7) -> 2
A8: Bing | B8: 3 | C8: 0 | D8: 10 | E8: 7 | F8: 8 | G8: 11 | H8: 6 | I8: 5 | J8: 2 | K8: 5 | L8: 3 | M8: 4 | N8: 4 | O8: 5 | P8: 5 | Q8: 8 | R8: 3 | S8: 3 | T8: 5 | U8: 1 | V8: 4 | W8: 5 | X8: 2 | Y8: 4 | Z8: 6 | AA8: 4 | AB8: 5 | AC8: 4 | AD8: 4 | AE8: 2 | AF8: 6 | AG8: =SUM(B8:AF8) -> 144
A9: MNTN TV | B9: 0 | C9: 0 | AG9: =SUM(B9:AF9) -> 0
A10: Affiliates | B10: 0 | C10: 0 | D10: 0 | E10: 0 | F10: 0 | G10: 0 | H10: 0 | I10: 0 | J10: 0 | K10: 1 | L10: 0 | M10: 0 | N10: 0 | O10: 0 | P10: 0 | Q10: 0 | R10: 0 | S10: 0 | T10: 0 | U10: 2 | V10: 0 | W10: 0 | X10: 0 | Y10: 0 | Z10: 0 | AA10: 0 | AB10: 1 | AC10: 0 | AD10: 0 | AE10: 0 | AF10: 1 | AG10: =SUM(B10:AF10) -> 5
A11: FB (Internal Paid) | AG11: =SUM(B11:AF11) -> 0
A12: FB (EU & UK) | AG12: =SUM(B12:AF12) -> 0
A13: Email | B13: 31 | C13: 8 | D13: 15 | E13: 83 | F13: 42 | G13: 16 | H13: 10 | I13: 18 | J13: 11 | K13: 132 | L13: 44 | M13: 6 | N13: 12 | O13: 6 | P13: 11 | Q13: 8 | R13: 11 | S13: 7 | T13: 7 | U13: 4 | V13: 3 | W13: 11 | X13: 6 | Y13: 9 | Z13: 5 | AA13: 7 | AB13: 10 | AC13: 6 | AD13: 7 | AE13: 5 | AF13: 7 | AG13: =SUM(B13:AF13) -> 558
A14: All | B14: =SUM(B5:B13) -> 100 | C14: =SUM(C5:C13) -> 75 | D14: =SUM(D5:D13) -> 61 | E14: =SUM(E5:E13) -> 148 | F14: =SUM(F5:F13) -> 156 | G14: =SUM(G5:G13) -> 124 | H14: =SUM(H5:H13) -> 118 | I14: =SUM(I5:I13) -> 92 | ... AF14: =SUM(AF5:AF13) -> 96 | AG14: =SUM(B14:AF14) -> 2635
A16: Revenue
A17: FB (US & CA) | B17: 6067.98 | C17: 5398.61 | D17: 2206.39 | E17: 2760.36 | F17: 2836.4 | G17: 3984.65 | H17: 3564.05 | I17: 2112.52 | J17: 2337.66 | K17: 1858.43 | L17: 2305.21 | M17: 2670.04 | N17: 1633.7 | O17: 2044.77 | P17: 3521.58 | Q17: 2299.89 | R17: 3080.7 | S17: 3473.04 | T17: 1910.67 | U17: 4899.68 | V17: 9046.52 | W17: 5874.01 | X17: 4846.67 | Y17: 6855.13 | Z17: 6236.75 | AA17: 2313.78 | AB17: 8455.86 | AC17: 11356.97 | AD17: 10562.72 | AE17: 11273.99 | AF17: 15742.81 | AG17: =SUM(B17:AF17) -> 153531.54
A18: Google | B18: 8738.77 | C18: 9578.14 | D18: 4155.18 | E18: 11063.94 | F18: 26839.74 | G18: 19585.85 | H18: 22899.5 | I18: 14018.66 | J18: 11280.43 | K18: 11897.45 | L18: 10451.33 | M18: 8033.46 | N18: 13456.98 | O18: 10495.95 | P18: 11230.7 | Q18: 11010.14 | R18: 7495.75 | S18: 8240.17 | T18: 13889.32 | U18: 12840.89 | V18: 8357.6 | W18: 11612.32 | X18: 9112.67 | Y18: 12498.52 | Z18: 11021.15 | AA18: 9435.73 | AB18: 8719.28 | AC18: 9952.69 | AD18: 7076.64 | AE18: 8401.8 | AF18: 9109.77 | AG18: =SUM(B18:AF18) -> 352500.52
A19: TikTok | B19: 0 | C19: 0 | D19: 0 | E19: 0 | F19: 0 | G19: 247.91 | H19: 0 | I19: 0 | J19: 0 | K19: 0 | L19: 0 | M19: 0 | N19: 0 | O19: 0 | P19: 0 | Q19: 20.33 | R19: 0 | S19: 0 | T19: 0 | U19: 0 | V19: 0 | W19: 0 | X19: 0 | Y19: 0 | Z19: 0 | AA19: 0 | AB19: 0 | AC19: 0 | AD19: 0 | AE19: 0 | AF19: 0 | AG19: =SUM(B19:AF19) -> 268.24
A20: Bing | B20: 798 | C20: 0 | D20: 2660 | E20: 1862 | F20: 2128 | G20: 2926 | H20: 1596 | I20: 1330 | J20: 532 | K20: 1330 | L20: 798 | M20: 1064 | N20: 1064 | O20: 1330 | P20: 1330 | Q20: 2128 | R20: 798 | S20: 798 | T20: 1330 | U20: 266 | V20: 1064 | W20: 1330 | X20: 532 | Y20: 1064 | Z20: 1596 | AA20: 1064 | AB20: 1330 | AC20: 1064 | AD20: 1064 | AE20: 532 | AF20: 1596 | AG20: =SUM(B20:AF20) -> 38304
A21: MNTN TV | AG21: =SUM(B21:AF21) -> 0
A22: Affiliates | B22: 0 | C22: 0 | D22: 0 | E22: 0 | F22: 0 | G22: 0 | H22: 0 | I22: 0 | J22: 0 | K22: 77.33 | L22: 0 | M22: 0 | N22: 0 | O22: 0 | P22: 0 | Q22: 0 | R22: 0 | S22: 0 | T22: 0 | U22: =351.43+315.14 -> 666.57 | V22: 0 | W22: 0 | X22: 0 | Y22: 0 | Z22: 0 | AA22: 0 | AB22: 250.4 | AC22: 0 | AD22: 0 | AE22: 0 | AF22: 299 | AG22: =SUM(B22:AF22) -> 1293.3
A23: FB (Internal Paid) | AG23: =SUM(B23:AF23) -> 0
A24: FB (EU & UK) | AG24: =SUM(B24:AF24) -> 0
A25: Email | B25: 4655.46 | C25: 773.28 | D25: 1690.9 | E25: 11280.65 | F25: 6426.36 | G25: 1762.8 | H25: 1705.89 | I25: 2423.02 | J25: 1813.44 | K25: 17085.19 | L25: 7193.4 | M25: 1171.2 | N25: 2294.24 | O25: 790.67 | P25: 3521.58 | Q25: 2299.89 | R25: 3080.7 | S25: 1143.75 | T25: 1157.64 | U25: 855.5 | V25: 624.78 | W25: 1660.64 | X25: 1029.11 | Y25: 1278.42 | Z25: 1074.96 | AA25: 1391.32 | AB25: 2150.26 | AC25: 1425.2 | AD25: 1489.91 | AE25: 835.47 | AF25: 1674.04 | AG25: =SUM(B25:AF25) -> 87759.67
A26: All | B26: =SUM(B17:B25) -> 20260.21 | C26: =SUM(C17:C25) -> 15750.03 | D26: =SUM(D17:D25) -> 10712.47 | E26: =SUM(E17:E25) -> 26966.95 | F26: =SUM(F17:F25) -> 38230.5 | G26: =SUM(G17:G25) -> 28507.21 | H26: =SUM(H17:H25) -> 29765.44 | I26: =SUM(I17:I25) -> 19884.2 | ... AF26: =SUM(AF17:AF25) -> 28421.62 | AG26: =SUM(B26:AF26) -> 633657.27
A28: Media Cost
A29: FB Spend (US & CA) | B29: =Sales!B13 -> 6003.49 | C29: =Sales!C13 -> 5666.34 | D29: =Sales!D13 -> 5287.53 | E29: =Sales!E13 -> 5405.32 | F29: =Sales!F13 -> 5448.5 | G29: =Sales!G13 -> 6253.48 | H29: =Sales!H13 -> 4657.96 | I29: =Sales!I13 -> 4892.4 | ... AF29: =Sales!AF13 -> 9677.62 | AG29: =SUM(B29:AF29) -> 195604.79
A30: Google Spend | B30: =Sales!B14 -> 2600 | C30: =Sales!C14 -> 2990 | D30: =Sales!D14 -> 2520 | E30: =Sales!E14 -> 3230 | F30: =Sales!F14 -> 3500 | G30: =Sales!G14 -> 2296.12 | H30: =Sales!H14 -> 2822.09 | I30: =Sales!I14 -> 2213.61 | ... AF30: =Sales!AF14 -> 1573.76 | AG30: =SUM(B30:AF30) -> 69500.85
A31: TikTok Spend | B31: 0 | C31: 0 | D31: 0 | E31: 0 | F31: 0 | G31: =Sales!G16 -> 248.33 | H31: =Sales!H16 -> 248.96 | I31: 0 | J31: 0 | K31: 0 | L31: 0 | M31: 0 | N31: 0 | O31: 0 | P31: 0 | Q31: 0 | R31: 0 | S31: 0 | T31: 0 | U31: 0 | V31: 0 | W31: 0 | X31: 0 | Y31: 0 | Z31: 0 | AA31: 0 | AB31: 0 | AC31: =Sales!AC16 | AD31: =Sales!AD16 | AE31: =Sales!AE16 | AF31: =Sales!AF16 | AG31: =SUM(B31:AF31) -> 497.29
A32: Bing Spend | B32: =Sales!B15 -> 83.03 | C32: =Sales!C15 -> 91.99 | D32: =Sales!D15 -> 89.3 | E32: =Sales!E15 -> 155.15 | F32: =Sales!F15 -> 152.58 | G32: =Sales!G15 -> 154.02 | H32: =Sales!H15 -> 126.99 | I32: =Sales!I15 -> 139.77 | ... AF32: =Sales!AF15 -> 78.76 | AG32: =SUM(B32:AF32) -> 3077.32
A33: MNTN TV | AG33: =SUM(B33:AE33) -> 0
A34: Fee 15% Purchase (Backerkit) | B34: =B21*0.15 -> 0 | C34: =C21*0.15 -> 0 | D34: =D21*0.15 -> 0 | E34: =E21*0.15 -> 0 | F34: =F21*0.15 -> 0 | G34: =G21*0.15 -> 0 | H34: =H21*0.15 -> 0 | I34: =I21*0.15 -> 0 | ... S34: =S21*0.15 -> 0 | U34: =U21*0.15 -> 0 | V34: =V21*0.15 -> 0 | W34: =W21*0.15 -> 0 | X34: =X21*0.15 -> 0 | Y34: =Y21*0.15 -> 0 | Z34: =Z21*0.15 -> 0 | AA34: =AA21*0.15 -> 0 | AB34: =AB21*0.15 -> 0 | ... AF34: =AF21*0.15 -> 0 | AG34: =SUM(B34:AE34) -> 0
A35: Google Management Fee | AG35: =SUM(B35:AE35) -> 0
A36: Affiliates Agency Payment (Grovia) | AG36: =SUM(B36:AE36) -> 0
A37: Affiliate Fee 20% | B37: =Sales!B18 | C37: =Sales!C18 | D37: =Sales!D18 | E37: =Sales!E18 | F37: =Sales!F18 | G37: =Sales!G18 | H37: =Sales!H18 -> 0 | I37: =Sales!I18 -> 0 | ... O37: =Sales!O18 -> 0 | P37: =Sales!O18 -> 0 | Q37: =Sales!Q18 -> 0 | R37: =Sales!R18 -> 0 | S37: =Sales!S18 -> 0 | U37: =Sales!U18 -> 133.32 | V37: =Sales!V18 -> 0 | W37: =Sales!W18 -> 0 | X37: =Sales!X18 -> 0 | Y37: =Sales!Y18 -> 0 | Z37: =Sales!Z18 -> 0 | AA37: =Sales!AA18 -> 0 | AB37: =Sales!AB18 -> 50.08 | ... AF37: =Sales!AF18 -> 59.8 | AG37: =SUM(B37:AF37) -> 258.67
A38: FB Spend (Internal Paid) | AG38: =SUM(B38:AE38) -> 0
A39: FB Spend (EU & UK) | AG39: =SUM(B39:AE39) -> 0
A40: Pinterest Spend | AG40: =SUM(B40:AE40) -> 0
A41: Platform Fee (6,90%) | AG41: =SUM(B41:AE41) -> 0
A42: All | B42: =SUM(B29:B41) -> 8686.52 | C42: =SUM(C29:C41) -> 8748.33 | D42: =SUM(D29:D41) -> 7896.83 | E42: =SUM(E29:E41) -> 8790.47 | F42: =SUM(F29:F41) -> 9101.08 | G42: =SUM(G29:G41) -> 8951.95 | H42: =SUM(H29:H41) -> 7856 | I42: =SUM(I29:I41) -> 7245.78 | ... AF42: =SUM(AF29:AF41) -> 11389.94 | AG42: =SUM(B42:AF42) -> 268938.92
A44: Cost
A45: Average COGS ($88.77) | B45: =B14*Formulas!$H21 -> 7982.2945 | C45: =C14*Formulas!$H21 -> 5986.7209 | D45: =D14*Formulas!$H21 -> 4869.1996 | E45: =E14*Formulas!$H21 -> 11813.796 | F45: =F14*Formulas!$H21 -> 12452.379 | G45: =G14*Formulas!$H21 -> 9898.0452 | H45: =H14*Formulas!$H21 -> 9419.1075 | I45: =I14*Formulas!$H21 -> 7343.7109 | ... AF45: =AF14*Formulas!$H21 -> 7663.0027 | AG45: =SUM(B45:AF45) -> 210333.46
A46: Average Inbound Shipping ($8.63) | B46: =B14*Formulas!$H22 -> 1843 | C46: =C14*Formulas!$H22 -> 1382.25 | D46: =D14*Formulas!$H22 -> 1124.23 | E46: =E14*Formulas!$H22 -> 2727.64 | F46: =F14*Formulas!$H22 -> 2875.08 | G46: =G14*Formulas!$H22 -> 2285.32 | H46: =H14*Formulas!$H22 -> 2174.74 | I46: =I14*Formulas!$H22 -> 1695.56 | ... AF46: =AF14*Formulas!$H22 -> 1769.28 | AG46: =SUM(B46:AF46) -> 48563.05
A47: Average Outbound Shipping ($11.59) | B47: =B14*Formulas!$H23 -> 1159 | C47: =C14*Formulas!$H23 -> 869.25 | D47: =D14*Formulas!$H23 -> 706.99 | E47: =E14*Formulas!$H23 -> 1715.32 | F47: =F14*Formulas!$H23 -> 1808.04 | G47: =G14*Formulas!$H23 -> 1437.16 | H47: =H14*Formulas!$H23 -> 1367.62 | I47: =I14*Formulas!$H23 -> 1066.28 | ... AF47: =AF14*Formulas!$H23 -> 1112.64 | AG47: =SUM(B47:AF47) -> 30539.65
A48: Average Taxes ($10.89) | B48: =B14*Formulas!$H24 -> 1089 | C48: =C14*Formulas!$H24 -> 816.75 | D48: =D14*Formulas!$H24 -> 664.29 | E48: =E14*Formulas!$H24 -> 1611.72 | F48: =F14*Formulas!$H24 -> 1698.84 | G48: =G14*Formulas!$H24 -> 1350.36 | H48: =H14*Formulas!$H24 -> 1285.02 | I48: =I14*Formulas!$H24 -> 1001.88 | ... AF48: =AF14*Formulas!$H24 -> 1045.44 | AG48: =SUM(B48:AF48) -> 28695.15
A49: China Tax (7.5%) | B49: =B14*Formulas!$H25 -> 598.67209 | C49: =C14*Formulas!$H25 -> 449.00407 | D49: =D14*Formulas!$H25 -> 365.18997 | E49: =E14*Formulas!$H25 -> 886.03469 | F49: =F14*Formulas!$H25 -> 933.92846 | G49: =G14*Formulas!$H25 -> 742.35339 | H49: =H14*Formulas!$H25 -> 706.43306 | I49: =I14*Formulas!$H25 -> 550.77832 | ... AF49: =AF14*Formulas!$H25 -> 574.7252 | AG49: =SUM(B49:AF49) -> 15775.01
A50: Duty (3.4%) | B50: =B14*Formulas!$H26 -> 271.39801 | C50: =C14*Formulas!$H26 -> 203.54851 | D50: =D14*Formulas!$H26 -> 165.55279 | E50: =E14*Formulas!$H26 -> 401.66906 | F50: =F14*Formulas!$H26 -> 423.3809 | G50: =G14*Formulas!$H26 -> 336.53354 | H50: =H14*Formulas!$H26 -> 320.24966 | I50: =I14*Formulas!$H26 -> 249.68617 | ... AF50: =AF14*Formulas!$H26 -> 260.54209 | AG50: =SUM(B50:AF50) -> 7151.3376
A51: Handling Fee ($1.50) | B51: =B14*Formulas!$H29 -> 150 | C51: =C14*Formulas!$H29 -> 112.5 | D51: =D14*Formulas!$H29 -> 91.5 | E51: =E14*Formulas!$H29 -> 222 | F51: =F14*Formulas!$H29 -> 234 | G51: =G14*Formulas!$H29 -> 186 | H51: =H14*Formulas!$H29 -> 177 | I51: =I14*Formulas!$H29 -> 138 | ... AF51: =AF14*Formulas!$H29 -> 144 | AG51: =SUM(B51:AF51) -> 3952.5
A52: Serial Capture ($0.30) | B52: =B14*Formulas!$H30 -> 30 | C52: =C14*Formulas!$H30 -> 22.5 | D52: =D14*Formulas!$H30 -> 18.3 | E52: =E14*Formulas!$H30 -> 44.4 | F52: =F14*Formulas!$H30 -> 46.8 | G52: =G14*Formulas!$H30 -> 37.2 | H52: =H14*Formulas!$H30 -> 35.4 | I52: =I14*Formulas!$H30 -> 27.6 | ... AF52: =AF14*Formulas!$H30 -> 28.8 | AG52: =SUM(B52:AF52) -> 790.5
A53: Processing Fee (2,97%) | B53: =B26*Formulas!$H35 -> 601.72824 | C53: =C26*Formulas!$H35 -> 467.77589 | D53: =D26*Formulas!$H35 -> 318.16036 | E53: =E26*Formulas!$H35 -> 800.91841 | F53: =F26*Formulas!$H35 -> 1135.4459 | G53: =G26*Formulas!$H35 -> 846.66414 | H53: =H26*Formulas!$H35 -> 884.03357 | I53: =I26*Formulas!$H35 -> 590.56074 | ... AF53: =AF26*Formulas!$H35 -> 844.12211 | AG53: =SUM(B53:AF53) -> 18819.621
A54: Transaction Fee ($0.36) | B54: =B14*Formulas!$H28 -> 36 | C54: =C14*Formulas!$H28 -> 27 | D54: =D14*Formulas!$H28 -> 21.96 | E54: =E14*Formulas!$H28 -> 53.28 | F54: =F14*Formulas!$H28 -> 56.16 | G54: =G14*Formulas!$H28 -> 44.64 | H54: =H14*Formulas!$H28 -> 42.48 | I54: =I14*Formulas!$H28 -> 33.12 | ... AF54: =AF14*Formulas!$H28 -> 34.56 | AG54: =SUM(B54:AF54) -> 948.6
A55: All | B55: =SUM(B45:B54) -> 13761.093 | C55: =SUM(C45:C54) -> 10337.299 | D55: =SUM(D45:D54) -> 8345.3728 | E55: =SUM(E45:E54) -> 20276.778 | F55: =SUM(F45:F54) -> 21664.055 | G55: =SUM(G45:G54) -> 17164.276 | H55: =SUM(H45:H54) -> 16412.084 | I55: =SUM(I45:I54) -> 12697.176 | ... AF55: =SUM(AF45:AF54) -> 13477.112 | AG55: =SUM(B55:AF55) -> 365568.88
A57: Partial Profit | B57: =B26-B42-B55 -> -2187.4028 | C57: =C26-C42-C55 -> -3335.5993 | D57: =D26-D42-D55 -> -5529.7328 | E57: =E26-E42-E55 -> -2100.298 | F57: =F26-F42-F55 -> 7465.3654 | G57: =G26-G42-G55 -> 2390.9838 | H57: =H26-H42-H55 -> 5497.3562 | I57: =I26-I42-I55 -> -58.756171 | ... AF57: =AF26-AF42-AF55 -> 3554.5679 | AG57: =SUM(B57:AF57) -> -850.52809
A58: =SUM(B57:AE57) -> -4405.096
A62: Performance Facebook US & CA | Z62: 3.11 | AA62: 1.8
A63: PROFIT | B63: =B17-(B5*Formulas!$H32)-B29 -> -2153.4997 | C63: =C17-(C5*Formulas!$H32)-C29 -> -2624.3441 | D63: =D17-(D5*Formulas!$H32)-D29 -> -4051.5105 | E63: =E17-(E5*Formulas!$H32)-E29 -> -4447.0767 | F63: =F17-(F5*Formulas!$H32)-F29 -> -4136.9679 | G63: =G17-(G5*Formulas!$H32)-G29 -> -4070.9467 | H63: =H17-(H5*Formulas!$H32)-H29 -> -2896.0267 | I63: =I17-(I5*Formulas!$H32)-I29 -> -3611.6262 | ... AF63: =AF17-(AF5*Formulas!$H32)-AF29 -> -311.53049 | AG63: =SUM(B63:AF63) -> -110692.31
A64: ROAS | B64: =B17/B29 -> 1.0107421 | C64: =C17/C29 -> 0.95275081 | D64: =D17/D29 -> 0.41728179 | E64: =E17/E29 -> 0.51067467 | F64: =F17/F29 -> 0.52058365 | G64: =G17/G29 -> 0.63718921 | H64: =H17/H29 -> 0.76515256 | I64: =I17/I29 -> 0.43179626 | ... AF64: =AF17/AF29 -> 1.6267233
A65: CPO | B65: =B29/B5 -> 375.21812 | C65: =C29/C5 -> 333.31412 | D65: =D29/D5 -> 755.36143 | E65: =E29/E5 -> 415.79385 | F65: =F29/F5 -> 495.31818 | G65: =G29/G5 -> 481.03692 | H65: =H29/H5 -> 358.30462 | I65: =I29/I5 -> 815.4 | ... AF65: =AF29/AF5 -> 210.38304
A66: MER | B66: =B17/(Formulas!$H32*B5+B29) -> 0.73806422 | C66: =C17/(Formulas!$H32*C5+C29) -> 0.67289554 | D66: =D17/(Formulas!$H32*D5+D29) -> 0.35257671 | E66: =E17/(Formulas!$H32*E5+E29) -> 0.38298776 | F66: =F17/(Formulas!$H32*F5+F29) -> 0.4067475 | G66: =G17/(Formulas!$H32*G5+G29) -> 0.49464368 | H66: =H17/(Formulas!$H32*H5+H29) -> 0.55170398 | I66: =I17/(Formulas!$H32*I5+I29) -> 0.36905417 | ... AF66: =AF17/(Formulas!$H32*AF5+AF29) -> 0.98059525
A68: Performance Google
A69: PROFIT | B69: =B18-(B6*Formulas!$H32)-B30 -> -792.44792 | C69: =C18-(C6*Formulas!$H32)-C30 -> -343.07792 | D69: =D18-(D6*Formulas!$H32)-D30 -> -2384.9264 | E69: =E18-(E6*Formulas!$H32)-E30 -> 1595.8439 | F69: =F18-(F6*Formulas!$H32)-F30 -> 10170.426 | G69: =G18-(G6*Formulas!$H32)-G30 -> 5783.9083 | H69: =H18-(H6*Formulas!$H32)-H30 -> 7739.8421 | I69: =I18-(I6*Formulas!$H32)-I30 -> 3071.7154 | ... AF69: =AF18-(AF6*Formulas!$H32)-AF30 -> 2545.5331 | AG69: =SUM(B69:AF69) -> 84628.213
A70: ROAS | B70: =B18/B30 -> 3.3610654 | C70: =C18/C30 -> 3.2033913 | D70: =D18/D30 -> 1.648881 | E70: =E18/E30 -> 3.4253684 | F70: =F18/F30 -> 7.6684971 | G70: =G18/G30 -> 8.5299767 | H70: =H18/H30 -> 8.1143762 | I70: =I18/I30 -> 6.3329403 | ... AF70: =AF18/AF30 -> 5.7885383
A71: CPO | B71: =B30/B6 -> 52 | C71: =C30/C6 -> 59.8 | D71: =D30/D6 -> 86.896552 | E71: =E30/E6 -> 71.777778 | F71: =F30/F6 -> 36.842105 | G71: =G30/G6 -> 27.664096 | H71: =H30/H6 -> 31.708876 | I71: =I30/I6 -> 35.136667 | ... AF71: =AF30/AF6 -> 43.715556
A72: MER | B72: =B18/(Formulas!$H32*B6+B30) -> 0.91685764 | C72: =C18/(Formulas!$H32*C6+C30) -> 0.96541978 | D72: =D18/(Formulas!$H32*D6+D30) -> 0.63533829 | E72: =E18/(Formulas!$H32*E6+E30) -> 1.1685496 | F72: =F18/(Formulas!$H32*F6+F30) -> 1.6101286 | G72: =G18/(Formulas!$H32*G6+G30) -> 1.4190648 | H72: =H18/(Formulas!$H32*H6+H30) -> 1.5105552 | I72: =I18/(Formulas!$H32*I6+I30) -> 1.2806003 | ... AF72: =AF18/(Formulas!$H32*AF6+AF30) -> 1.3877881
A74: Performance TikTok
A75: PROFIT | B75: =B19-(B7*Formulas!$H32)-B31 -> 0 | C75: =C19-(C7*Formulas!$H32)-C31 -> 0 | D75: =D19-(D7*Formulas!$H32)-D31 -> 0 | E75: =E19-(E7*Formulas!$H32)-E31 -> 0 | F75: =F19-(F7*Formulas!$H32)-F31 -> 0 | G75: =G19-(G7*Formulas!$H32)-G31 -> -139.04436 | H75: =H19-(H7*Formulas!$H32)-H31 -> -248.96 | I75: =I19-(I7*Formulas!$H32)-I31 -> 0 | ... AF75: =AF19-(AF7*Formulas!$H32)-AF31 -> 0 | AG75: =SUM(B75:AF75) -> -506.29872
A76: ROAS | B76: =B19/B31 -> #DIV/0! | C76: =C19/C31 -> #DIV/0! | D76: =D19/D31 -> #DIV/0! | E76: =E19/E31 -> #DIV/0! | F76: =F19/F31 -> #DIV/0! | G76: =G19/G31 -> 0.9983087 | H76: =H19/H31 -> 0 | I76: =I19/I31 -> #DIV/0! | ... AF76: =AF19/AF31 -> #DIV/0!
A77: CPO | B77: =B31/B7 -> #DIV/0! | C77: =C31/C7 -> #DIV/0! | D77: =D31/D7 -> #DIV/0! | E77: =E31/E7 -> #DIV/0! | F77: =F31/F7 -> #DIV/0! | G77: =G31/G7 -> 248.33 | H77: =H31/H7 -> #DIV/0! | I77: =I31/I7 -> #DIV/0! | ... AF77: =AF31/AF7 -> #DIV/0!
A78: MER | B78: =B19/(Formulas!$H32*B7+B31) -> #DIV/0! | C78: =C19/(Formulas!$H32*C7+C31) -> #DIV/0! | D78: =D19/(Formulas!$H32*D7+D31) -> #DIV/0! | E78: =E19/(Formulas!$H32*E7+E31) -> #DIV/0! | F78: =F19/(Formulas!$H32*F7+F31) -> #DIV/0! | G78: =G19/(Formulas!$H32*G7+G31) -> 0.64066987 | H78: =H19/(Formulas!$H32*H7+H31) -> 0 | I78: =I19/(Formulas!$H32*I7+I31) -> #DIV/0! | ... AF78: =AF19/(Formulas!$H32*AF7+AF31) -> #DIV/0!
A80: Performance Bing
A81: PROFIT | B81: =B20-(B8*Formulas!$H32)-B32 -> 299.09692 | C81: =C20-(C8*Formulas!$H32)-C32 -> -91.99 | D81: =D20-(D8*Formulas!$H32)-D32 -> 1184.4564 | E81: =E20-(E8*Formulas!$H32)-E32 -> 736.47949 | F81: =F20-(F8*Formulas!$H32)-F32 -> 866.42513 | G81: =G20-(G8*Formulas!$H32)-G32 -> 1247.1121 | H81: =H20-(H8*Formulas!$H32)-H32 -> 637.26385 | I81: =I20-(I8*Formulas!$H32)-I32 -> 497.10821 | ... AF81: =AF20-(AF8*Formulas!$H32)-AF32 -> 685.49385 | AG81: =SUM(B81:AF81) -> 15264.772
A82: ROAS | B82: =B20/B32 -> 9.610984 | C82: =C20/C32 -> 0 | D82: =D20/D32 -> 29.787234 | E82: =E20/E32 -> 12.001289 | F82: =F20/F32 -> 13.946782 | G82: =G20/G32 -> 18.997533 | H82: =H20/H32 -> 12.567919 | I82: =I20/I32 -> 9.5156328 | ... AF82: =AF20/AF32 -> 20.264093
A83: CPO | B83: =B32/B8 -> 27.676667 | C83: =C32/C8 -> #DIV/0! | D83: =D32/D8 -> 8.93 | E83: =E32/E8 -> 22.164286 | F83: =F32/F8 -> 19.0725 | G83: =G32/G8 -> 14.001818 | H83: =H32/H8 -> 21.165 | I83: =I32/I8 -> 27.954 | ... AF83: =AF32/AF8 -> 13.126667
A84: MER | B84: =B20/(Formulas!$H32*B8+B32) -> 1.5995091 | C84: =C20/(Formulas!$H32*C8+C32) -> 0 | D84: =D20/(Formulas!$H32*D8+D32) -> 1.8027255 | E84: =E20/(Formulas!$H32*E8+E32) -> 1.6543457 | F84: =F20/(Formulas!$H32*F8+F32) -> 1.6867806 | G84: =G20/(Formulas!$H32*G8+G32) -> 1.7428203 | H84: =H20/(Formulas!$H32*H8+H32) -> 1.6646916 | I84: =I20/(Formulas!$H32*I8+I32) -> 1.5968461 | ... AF84: =AF20/(Formulas!$H32*AF8+AF32) -> 1.7528712
A86: MNTN TV
A87: PROFIT | B87: =B21-(B9*Formulas!$H32)-B33 -> 0 | C87: =C21-(C9*Formulas!$H32)-C33 -> 0 | D87: =D21-(D9*Formulas!$H32)-D33 -> 0 | E87: =E21-(E9*Formulas!$H32)-E33 -> 0 | F87: =F21-(F9*Formulas!$H32)-F33 -> 0 | G87: =G21-(G9*Formulas!$H32)-G33 -> 0 | H87: =H21-(H9*Formulas!$H32)-H33 -> 0 | I87: =I21-(I9*Formulas!$H32)-I33 -> 0 | ... AF87: =AF21-(AF9*Formulas!$H32)-AF33 -> 0 | AG87: =SUM(B87:AE87) -> 0
A88: ROAS | B88: =B21/B33 -> #DIV/0! | C88: =C21/C33 -> #DIV/0! | D88: =D21/D33 -> #DIV/0! | E88: =E21/E33 -> #DIV/0! | F88: =F21/F33 -> #DIV/0! | G88: =G21/G33 -> #DIV/0! | H88: =H21/H33 -> #DIV/0! | I88: =I21/I33 -> #DIV/0! | ... AF88: =AF21/AF33 -> #DIV/0!
A89: CPO | B89: =B33/B9 -> #DIV/0! | C89: =C33/C9 -> #DIV/0! | D89: =D33/D9 -> #DIV/0! | E89: =E33/E9 -> #DIV/0! | F89: =F33/F9 -> #DIV/0! | G89: =G33/G9 -> #DIV/0! | H89: =H33/H9 -> #DIV/0! | I89: =I33/I9 -> #DIV/0! | ... AF89: =AF33/AF9 -> #DIV/0!
A90: MER | B90: =B21/(Formulas!$H32*B9+B33) -> #DIV/0! | C90: =C21/(Formulas!$H32*C9+C33) -> #DIV/0! | D90: =D21/(Formulas!$H32*D9+D33) -> #DIV/0! | E90: =E21/(Formulas!$H32*E9+E33) -> #DIV/0! | F90: =F21/(Formulas!$H32*F9+F33) -> #DIV/0! | G90: =G21/(Formulas!$H32*G9+G33) -> #DIV/0! | H90: =H21/(Formulas!$H32*H9+H33) -> #DIV/0! | I90: =I21/(Formulas!$H32*I9+I33) -> #DIV/0! | ... AF90: =AF21/(Formulas!$H32*AF9+AF33) -> #DIV/0!
A92: Affiliates (Grovia)
A93: PROFIT | AG93: =SUM(B93:AE93) -> 0
A94: ROAS
A95: CPO
A96: MER
A98: Performance Internal Paid
A99: PROFIT | AG99: =SUM(B99:AE99) -> 0
A100: ROAS
A101: CPO
A102: MER
A104: Performance EU & UK
A105: PROFIT | AG105: =SUM(B105:AE105) -> 0
A106: ROAS
A107: CPO
A108: MER
A111: Performance Email
A112: PROFIT | B112: =B25-(B13*Formulas!$H32) -> 358.10489 | C112: =C25-(C13*Formulas!$H32) -> -335.71487 | D112: =D25-(D13*Formulas!$H32) -> -388.46538 | E112: =E25-(E13*Formulas!$H32) -> -225.17175 | F112: =F25-(F13*Formulas!$H32) -> 604.13695 | G112: =G25-(G13*Formulas!$H32) -> -455.18973 | H112: =H25-(H13*Formulas!$H32) -> 319.64642 | I112: =I25-(I13*Formulas!$H32) -> -72.218451 | ... AF112: =AF25-(AF13*Formulas!$H32) -> 703.66949 | AG112: =SUM(B112:AF112) -> 10407.278
A113: ROAS
A114: CPO
A115: MER | B115: =B25/(Formulas!$H32*B13) -> 1.0833315 | C115: =C25/(Formulas!$H32*C13) -> 0.69728005 | D115: =D25/(Formulas!$H32*D13) -> 0.8131808 | E115: =E25/(Formulas!$H32*E13) -> 0.98042976 | F115: =F25/(Formulas!$H32*F13) -> 1.103764 | G115: =G25/(Formulas!$H32*G13) -> 0.79477374 | H115: =H25/(Formulas!$H32*H13) -> 1.2305846 | I115: =I25/(Formulas!$H32*I13) -> 0.9710575 | ... AF115: =AF25/(Formulas!$H32*AF13) -> 1.7251555
A117: Operations
...

Sheet Refunds
A1: Date of refund | B1: Value | C1: Date of purchase | D1: Order ID | E1: Name | F1: Email | G1: Reason | H1: Platform | I1: Refund through | J1: Country | K1: Bird Buddy | L1: Bird Buddy with Solar Roof | M1: Solar Roof | N1: Wall Mount | O1: Fence Mount | P1: Suet Ball Holder | Q1: Water Fountain | R1: Premium Subscription | S1: Seeds Subscription | T1: 12-month warranty | U1: 24-month warranty | V1: Gift Card | X1: Reason
A2: 44929 | B2: 20.39 | C2: 44923 | D2: #139028 | E2: Christen Lewis | F2: christenlewis816@gmail.com | G2: other | H2: Shopify | I2: Shopify | J2: USA | P2: 1 | X2: Cannot Afford it Anymore | Y2: 2 | Z2: =Y2/Y7 -> 1
A3: 44929 | B3: 17.8 | C3: 44159 | D3: 21480996BKS | E3: Dr. Hans-Friedrich Fuge | F3: facebook@fuge.net | G3: Delivery date | H3: Shopify | I3: Stripe | J3: Germany | N3: 1 | X3: Other | Y3: 57 | Z3: =Y3/Y4 -> 0.75
A4: 44929 | B4: 70 | C4: 44923 | D4: #139185 | E4: Edward K. Swain, Jr., DMD | F4: eksdmd@aol.com | G4: other | H4: Shopify | I4: Shopify | J4: USA | M4: 1 | X4: Delivery Date | Y4: 76 | Z4: =Y4/Y10 -> #DIV/0!
A5: 44929 | B5: 12 | C5: 44371 | D5: 24282251IGG | E5: Elisabeth Cavanagh | F5: elisabeth.cavanagh@gmail.com | G5: other | H5: Shopify | I5: Zelle | J5: USA | P5: 1 | X5: Moving | Y5: 2 | Z5: =Y5/Y9 -> #DIV/0!
A6: 44929 | B6: 17.8 | C6: 44098 | D6: 21475768BKS | E6: Kelly Gaddie | F6: krgaddie@gmail.com | G6: other | H6: Shopify | I6: Stripe | J6: USA | O6: 1 | X6: All | Y6: =SUM(#REF!) -> #REF!
A7: 44929 | B7: 249 | C7: 44672 | D7: #41690 | E7: Nicole Kate Roduit | F7: nk@nicolekate.ch | G7: other | H7: Shopify | I7: Wire | J7: Switzerland | K7: 1 | O7: 1 | X7: Refund and order another Bundle | Y7: 2 | Z7: =Y7/Y10 -> #DIV/0!
A8: 44929 | B8: 14.8 | C8: 44926 | D8: #139783 | E8: Sean Dwyer | F8: dwyer_43@hotmail.com | G8: other | H8: Shopify | I8: Shopify | J8: USA | P8: 1 | X8: Unknown | Y8: 17 | Z8: =Y8/Y10 -> #DIV/0!
A9: 44930 | B9: 24 | C9: 44891 | D9: #130036 | E9: Alisha Hurst | F9: lisha.hurst@gmail.com | G9: other | H9: Shopify | I9: Shopify | J9: USA
A10: 44930 | B10: 373.48 | C10: 44926 | D10: #139960 | E10: Bonnie March | F10: bonn76@aol.com | G10: Delivery date | H10: Shopify | I10: Shopify | J10: USA | K10: 1 | M10: 1 | N10: 1 | P10: 1 | Q10: 1
A11: 44930 | B11: 321.43 | C11: 44919 | D11: #138074 | E11: James Barnett | F11: jamesharrisonbarnett@gmail.com | G11: Delivery date | H11: Shopify | I11: Shopify | J11: USA | K11: 1 | M11: 1 | P11: 1 | X11: Refund % | Y11: =Y7/Y10 -> #DIV/0!
A12: 44930 | B12: 342.69 | C12: 44906 | D12: #135662 | E12: James King | F12: jamesmuratking@gmail.com | G12: Delivery date | H12: Shopify | I12: Shopify | J12: USA | K12: 1 | M12: 1 | P12: 1 | Q12: 1 | AA12: 109609
A13: 44930 | B13: 313 | C13: 44337 | D13: #1552KS | E13: Kathryn Witt | F13: #1552KS | G13: other | H13: Shopify | I13: Zelle | J13: USA | L13: 1 | N13: 1 | O13: 1 | P13: 1
A14: 44930 | B14: 37.4 | C14: 44929 | D14: #140415 | E14: Kristine Brown | F14: brown.kristine@comcast.net | G14: other | H14: Shopify | I14: Shopify | J14: USA | N14: 1 | X14: All Orders | Y14: =Sales!B51 -> 5451
A15: 44930 | B15: 243.32 | C15: 44906 | D15: #135605 | E15: Lisa Krych | F15: lisakrych@yahoo.com | G15: Delivery date | H15: Shopify | I15: Shopify | J15: USA | K15: 1 | P15: 1
A16: 44930 | B16: 500.7 | C16: 44153 | D16: 21475136BKS | E16: Lizzie Toyne | F16: lizzie-may@hotmail.co.uk | G16: Delivery date | H16: KS | I16: KS | J16: UK | L16: 2 | N16: 2
A17: 44930 | B17: 242.1 | C17: 44208 | D17: 21495768BKS | E17: Martin Terrier | F17: martin.terrier@gmail.com | G17: Delivery date | H17: Shopify | I17: BKS | J17: France | L17: 1
A18: 44930 | B18: 159 | C18: 44210 | D18: 21498422BKS | E18: Matthew Heywood | F18: matthew@matthewheywood.com | G18: Other | H18: KS | I18: KS | J18: UK | K18: 1 | N18: 1
A19: 44930 | B19: 231 | C19: 45234 | D19: #117507 | E19: Morven Dearden | F19: m20rvv@gmail.com | G19: Delivery date | H19: Shopify | I19: Shopify | J19: UK | K19: 1 | N19: 1 | P19: 1
A20: 44930 | B20: 238 | C20: 44209 | D20: 21496626BKS | E20: Tobias Ettlin | F20: tobiasettlin@me.com | G20: Delivery date | H20: KS | I20: KS | J20: Germany | L20: 1 | N20: 1 | P20: 1
A21: 44930 | B21: 22 | C21: 44842 | D21: #108758 | E21: Tobias Ettlin | F21: tobiasettlin@me.com | G21: Delivery date | H21: Shopify | I21: Shopify | J21: Germany | Q21: 1
A22: 44931 | B22: 24 | C22: 44930 | D22: #140587 | E22: Ingo Jahn | F22: ingo.jahn@gc-gruppe.de | G22: Other | H22: Shopify | I22: Shopify | J22: Germany | N22: 1
A23: 44932 | B23: 25.74 | C23: 44875 | D23: #120275 | E23: Brandon DuBois | F23: dubois.brandon@gmail.com | G23: Delivery date | H23: Shopify | I23: Shopify | J23: USA | N23: 1 | P23: 1
A24: 44932 | B24: 299 | C24: 44894 | D24: #133616 | E24: Chelsea Zanichelli | F24: clzanichelli2005@gmail.com | G24: Other | H24: Shopify | I24: Shopify | J24: USA | K24: 1 | M24: 1 | P24: 1
A25: 44932 | B25: 324.8 | C25: 44902 | D25: #135081 | E25: Connie Weaver | F25: csweaver917@yahoo.com | G25: Delivery date | H25: Shopify | I25: Shopify | J25: USA | K25: 1 | M25: 1 | P25: 1
A26: 44932 | B26: 299 | C26: 44917 | D26: #137472 | E26: Evan Nichols | F26: evan.j.nichols@gmail.com | G26: Other | H26: Shopify | I26: Shopify | J26: USA | K26: 1 | M26: 1 | P26: 1
A27: 44932 | B27: 267.5 | C27: 44925 | D27: #139684 | E27: Fergal Gallagher Jr | F27: fergalgallagher66@live.com | G27: Delivery date | H27: Shopify | I27: Shopify | J27: USA | K27: 1 | M27: 1 | P27: 1
A28: 44932 | B28: 319.93 | C28: 44925 | D28: #139689 | E28: Fergal Gallagher Jr | F28: fergalgallagher66@live.com | G28: Delivery date | H28: Shopify | I28: Shopify | J28: USA | K28: 1 | M28: 1 | P28: 1
A29: 44932 | B29: 18 | C29: 44165 | D29: 21482852BKS | E29: Georg Knabl | F29: georg.knabl@aquinashub.com | G29: Other | H29: KS | I29: KS | J29: Austria | O29: 1
A30: 44932 | B30: 264.82 | C30: 44900 | D30: #134600 | E30: Jaclyn Courchaine | F30: jcourchaine24@gmail.com | G30: Other | H30: Shopify | I30: Shopify | J30: USA | K30: 1 | P30: 1 | Q30: 1
A31: 44932 | B31: 669 | C31: 44686 | D31: #66451 | E31: James Walton | F31: jamesmwalton@hotmail.co.uk | G31: Delivery date | H31: Shopify | I31: Shopify | J31: UK | L31: 2 | N31: 2 | O31: 2 | P31: 2
A32: 44932 | B32: 229 | C32: 44931 | D32: #141074 | E32: Janet Huddleston | F32: twohuds@outlook.com | G32: Refund and order another Bundle | H32: Shopify | I32: Shopify | J32: USA | K32: 1 | P32: 1
A33: 44932 | B33: 107.41 | C33: 44930 | D33: #140882 | E33: Karen Ritter | F33: karen.ritter@gmail.com | G33: Other | H33: Shopify | I33: Shopify | J33: USA | M33: 1 | N33: 1 | P33: 1
A34: 44932 | B34: 69.86 | C34: 44930 | D34: #140818 | E34: Kate Dominguez | F34: kate.domi@gmail.com | G34: Other | H34: Shopify | I34: Shopify | J34: USA | N34: 1 | Q34: 1
A35: 44932 | B35: 264.6 | C35: 44876 | D35: #120820 | E35: Kim Harrison | F35: kimbritchie@gmail.com | G35: Delivery date | H35: Shopify | I35: Shopify | J35: USA | K35: 1 | N35: 1 | P35: 1 | Q35: 1
A36: 44932 | B36: 315.14 | C36: 44908 | D36: #135957 | E36: Margaret i Wergley | F36: mwergley@cox.net | G36: Delivery date | H36: Shopify | I36: Shopify | J36: USA | K36: 1 | M36: 1 | P36: 1
A37: 44932 | B37: 323 | C37: 44866 | D37: #115628 | E37: Maria Schroeder | F37: marylou@gmx.net | G37: Other | H37: Shopify | I37: Shopify | J37: USA | L37: 1 | P37: 1 | Q37: 1
A38: 44932 | B38: 299 | C38: 44932 | D38: #141265 | E38: Marie elene decarie | F38: medecarie@gmail.com | G38: Other | H38: Shopify | I38: Shopify | J38: Canada | K38: 1 | M38: 1 | P38: 1
A39: 44932 | B39: 24 | C39: 44925 | D39: #139455 | E39: Rene Geisenjohann | F39: post@renegeisenjohann.de | G39: Delivery date | H39: Shopify | I39: Shopify | J39: Germany | N39: 1
A40: 44932 | B40: 345 | C40: 44894 | D40: #133637 | E40: Rudolf Nanne | F40: ruud.nanne@gmail.com | G40: Delivery date | H40: Shopify | I40: Shopify | J40: USA | K40: 1 | M40: 1 | N40: 1 | P40: 1 | Q40: 1
A41: 44932 | B41: 269 | C41: 44923 | D41: #139088 | E41: Sarah Hamilton | F41: sarahrhamilton77@gmail.com | G41: Other | H41: Shopify | I41: Shopify | J41: USA | K41: 1 | M41: 1 | P41: 1
A42: 44932 | B42: 369.43 | C42: 44931 | D42: #141009 | E42: Shawn Donald | F42: shawn@monosyth.com | G42: Other | H42: Shopify | I42: Shopify | J42: USA | K42: 1 | M42: 1 | N42: 1 | P42: 1 | Q42: 1
A43: 44932 | B43: 243.55 | C43: 44920 | D43: #138403 | E43: Stacey Henion | F43: shenion1@aol.com | G43: Other | H43: Shopify | I43: Shopify | J43: USA | K43: 1 | P43: 1
A44: 44932 | B44: 84.8 | C44: 44926 | D44: #139988 | E44: Thomas Easterday | F44: tom@langolfco.com | G44: Other | H44: Shopify | I44: Shopify | J44: USA | M44: 1
A45: 44933 | B45: 201.8 | C45: 44764 | D45: 21475923BKS | E45: Anthony Ginger | F45: tony.ginger@live.co.uk | G45: Delivery date | H45: KS | I45: Wire | J45: UK | L45: 1 | N45: 1
A46: 44933 | B46: 247.41 | C46: 44896 | D46: #133919 | E46: Caroline Chojnacki | F46: carolchoj@gmail.com | G46: Delivery date | H46: Shopify | I46: Shopify | J46: USA | K46: 1 | P46: 1
A47: 44933 | B47: 242.1 | C47: 44153 | D47: #128/21475770BKS | E47: Darren Rees | F47: darren@djreesconsulting.com | G47: Delivery date | H47: KS | I47: KS | J47: UK | L47: 1 | N47: 1
A48: 44933 | B48: 32 | C48: 44858 | D48: #112258 | E48: David Smith | F48: dabasm@gmail.com | G48: Other | H48: Shopify | I48: Shopify | J48: USA | Q48: 1
A49: 44933 | B49: 299 | C49: 44906 | D49: #135600 | E49: Hannah Roberts | F49: hannerrose@gmail.com | G49: Other | H49: Shopify | I49: Shopify | J49: USA | K49: 1 | M49: 1 | P49: 1
A50: 44933 | B50: 229 | C50: 44920 | D50: #138163 | E50: Katie Perry | F50: kbperry1231@yahoo.com | G50: Unknown | H50: Shopify | I50: Shopify | J50: USA | K50: 1 | P50: 1
A51: 44933 | B51: 350 | C51: 44932 | D51: #141327 | E51: Martin Low | F51: loew.martin@gmail.com | G51: Other | H51: Shopify | I51: Shopify | J51: Czech | K51: 1 | M51: 1 | N51: 1 | P51: 1 | Q51: 1
A52: 44933 | B52: 313.95 | C52: 44932 | D52: #141307 | E52: Merideth Ryan | F52: meridethryan@me.com | G52: Unkown | H52: Shopify | I52: Shopify | J52: USA | K52: 1 | M52: 1 | P52: 1
A53: 44933 | B53: 366.57 | C53: 44932 | D53: #141539 | E53: Natalie White | F53: nataliew@internationallabel.com | G53: Refund and order another Bundle | H53: Shopify | I53: Shopify | J53: USA | L53: 1 | N53: 1 | P53: 1 | Q53: 1
A54: 44933 | B54: 36.81 | C54: 18/12/2022 | D54: #136653 | E54: patricia jackson | F54: pat.metcalf@sbcglobal.net | G54: Other | H54: Shopify | I54: Shopify | J54: USA | N54: 1
A55: 44933 | B55: 365.7 | C55: 45047 | D55: #141064 | E55: raymond alexander | F55: bossgoon@1791.com | G55: Delivery date | H55: Shopify | I55: Shopify | J55: USA | K55: 1 | M55: 1 | N55: 1 | P55: 1 | Q55: 1
A56: 44934 | B56: 35.86 | C56: 44931 | D56: #140991 | E56: Brian Ferguson | F56: brianferg@gmail.com | G56: Other | H56: Shopify | I56: Shopify | J56: USA | N56: 1
A57: 44934 | B57: 74.2 | C57: 44856 | D57: #111082 | E57: Bruce Conover | F57: R00A005@MSN.COM | G57: Other | H57: Shopify | I57: Shopify | J57: USA | M57: 1
A58: 44934 | B58: 343.19 | C58: 44933 | D58: #141747 | E58: David Bradley | F58: kb9koy@me.com | G58: Unknown | H58: Shopify | I58: Shopify | J58: USA | L58: 1 | N58: 1 | P58: 1
A59: 44934 | B59: 245.61 | C59: 44898 | D59: #134194 | E59: Emily Maxwell | F59: emilybmaxwell@gmail.com | G59: Other | H59: Shopify | I59: Shopify | J59: USA | K59: 1 | P59: 1
A60: 44934 | B60: 242.1 | C60: 44153 | D60: 21476439BKS | E60: Katherine Wood | F60: katherine.epsom@yahoo.com | G60: Cannot afford it anymore | H60: KS | I60: KS | J60: UK | L60: 1 | N60: 1
A61: 44934 | B61: 74.99 | C61: 44859 | D61: #112573 | E61: Lauren Delaney | F61: soren.hoeger.lerdal@gmail.com | G61: Other | H61: Shopify | I61: Shopify | J61: USA | M61: 1 | P61: 1
A62: 44934 | B62: 48.88 | C62: 44912 | D62: #128915 | E62: Mark Kudron | F62: mkudron@yahoo.com | G62: Other | H62: Shopify | I62: Shopify | J62: USA | N62: 1 | P62: 1 | Q62: 1
A63: 44934 | B63: 289 | C63: 44840 | D63: #108590 | E63: Rebecca Chambless | F63: bemore_ak@hotmail.com | G63: Other | H63: Shopify | I63: Zelle | J63: USA | K63: 1 | M63: 1 | P63: 1
A64: 44934 | B64: 339.85 | C64: 44933 | D64: #141821 | E64: Rich Ward | F64: Richdubya@aol.com | G64: Other | H64: Shopify | I64: Shopify | J64: USA | L64: 1 | N64: 1 | P64: 1
A65: 44934 | B65: 25.8 | C65: 44886 | D65: #125697 | E65: Shelley Miller | F65: shelleyanne226@gmail.com | G65: Other | H65: Shopify | I65: Shopify | J65: USA | N65: 1
A66: 44935 | B66: 461.69 | C66: 44912 | D66: #136621 | E66: Alice Bradley | F66: Ashnmitch@comcast.net | G66: Other | H66: Shopify | I66: Shopify | J66: USA | K66: 2 | P66: 2
A67: 44935 | B67: 51.18 | C67: 44878 | D67: #121748 | E67: Alice Roberts | F67: alicebr726@gmail.com | G67: Other | H67: Shopify | I67: Shopify | J67: USA | N67: 2
A68: 44935 | B68: 125.8 | C68: 44153 | D68: 21476213BKS | E68: Ann Gray | F68: billygray1@hotmail.co.uk | G68: Other | H68: KS | I68: TBA | J68: Uk | K68: 1
A69: 44935 | B69: 273.24 | C69: 44919 | D69: #137717 | E69: Carrie Follett | F69: 3cmarketingandmedia@gmail.com | G69: Other | H69: Shopify | I69: Shopify | J69: USA | K69: 1 | N69: 1 | P69: 1
A70: 44935 | B70: 76.63 | C70: 44853 | D70: 110348 | E70: Carrie Meagher | F70: carrie.a.meagher@gmail.com | G70: Other | H70: Shopify | I70: Shopify | J70: USA | M70: 1
A71: 44935 | B71: 299 | C71: 44912 | D71: #136597 | E71: Courtney King | F71: cobyrnek@gmail.com | G71: Delivery date | H71: Shopify | I71: Shopify | J71: USA | V71: 1
A72: 44935 | B72: 247.39 | C72: 44934 | D72: #142037 | E72: Dean Jones | F72: edeanjones2@gmail.com | G72: Other | H72: Shopify | I72: Shopify | J72: USA | K72: 1 | P72: 1
A73: 44935 | B73: 84.8 | C73: 44922 | D73: #138925 | E73: Deanna Davis | F73: braddeedavis@comcast.net | G73: Unknown | H73: Shopify | I73: Shopify | J73: USA | M73: 1
A74: 44935 | B74: 271.96 | C74: 44908 | D74: #136062 | E74: Emily Manning | F74: emilyarowan@gmail.com | G74: Delivery date | H74: Shopify | I74: Shopify | J74: USA | K74: 1 | N74: 1
A75: 44935 | B75: 247.9 | C75: 44906 | D75: #135626 | E75: Eunice P Qualls | F75: euniceq9902@gmail.com | G75: Unknown | H75: Shopify | I75: Shopify | J75: USA | K75: 1 | P75: 1
A76: 44935 | B76: 317.7 | C76: 44899 | D76: #134422 | E76: Glenn Bluemer | F76: bluemerglenn@gmail.com | G76: Other | H76: Shopify | I76: Shopify | J76: USA | K76: 1 | M76: 1 | P76: 1
A77: 44935 | B77: 232.3 | C77: 44219 | D77: 21496689BKS | E77: Hande Tekin | F77: hande.tekin@ymail.com | G77: Delivery date | H77: KS | I77: KS | J77: Australia | K77: 1 | N77: 1 | O77: 1
A78: 44935 | B78: 229 | C78: 44870 | D78: #117907 | E78: Holly MacLeod | F78: holly.macleod11@gmail.com | G78: Other | H78: Shopify | I78: Shopify | J78: CAnada | K78: 1 | P78: 1
A79: 44935 | B79: 62.8 | C79: 44921 | D79: #138494 | E79: Janine Bocciardi | F79: jbocciardi@gmail.com | G79: Other | H79: Shopify | I79: Shopify | J79: USA | M79: 1
A80: 44935 | B80: 541 | C80: 44389 | D80: #6767KS | E80: Jessica Bradley | F80: jesstierno1@gmail.com | G80: Delivery date | H80: Shopify | I80: Shopify | J80: USA | K80: 3 | N80: 1
A81: 44935 | B81: 201.5 | C81: 44206 | D81: 21494834BKS | E81: Josh Marshall Bryant | F81: joshmarshallbryant@gmail.com | G81: Delivery date | H81: KS | I81: Wire | J81: Uk | K81: 1 | N81: 1
A82: 44935 | B82: 167 | C82: 44402 | D82: #9310KS | E82: Karen Quevatre | F82: karenquevatre@hotmail.com | G82: Delivery date | H82: Shopify | I82: Shopify | J82: Uk | K82: 1
A83: 44935 | B83: 35.86 | C83: 44934 | D83: #141985 | E83: Kimberly Martinez | F83: kimberlymartinez2001@gmail.com | G83: Other | H83: Shopify | I83: Shopify | J83: USA | N83: 1
A84: 44935 | B84: 532.26 | C84: 44898 | D84: #134199 | E84: Leslie Miller | F84: lesliemillerdancer@gmail.com | G84: Delivery date | H84: Shopify | I84: Shopify | J84: USA | K84: 2 | M84: 1 | P84: 2
A85: 44935 | B85: 240.94 | C85: 44916 | D85: #137110 | E85: Melissa Miehling | F85: mmorin46@gmail.com | G85: Other | H85: Shopify | I85: Shopify | J85: USA | K85: 1 | P85: 1
A86: 44935 | B86: 232 | C86: 44367 | D86: #4230KS | E86: MIRIAM BOOK | F86: miriambook1@gmail.com | G86: Delivery date | H86: Shopify | I86: Shopify | J86: UK | K86: 1 | N86: 1 | P86: 1
A87: 44936 | B87: 328.15 | C87: 44894 | D87: #133626 | E87: Abigail Baker | F87: abigailbaker18@gmail.com | G87: Delivery date | H87: Shopify | I87: Shopify | J87: USA | K87: 1 | M87: 1 | P87: 1
A88: 44936 | B88: 315.82 | C88: 44663 | D88: #134310 | E88: Allison ONeill | F88: allioneill@gmail.com | G88: Delivery date | H88: Shopify | I88: Shopify | J88: USA | K88: 1 | M88: 1 | P88: 1
A89: 44936 | B89: 234 | C89: 44870 | D89: #118181 | E89: Anna-Marie Burruss | F89: amvalya1997@gmail.com | G89: Delivery date | H89: Shopify | I89: Shopify | J89: USA | K89: 1 | P89: 1
A90: 44936 | B90: 243 | C90: 44206 | D90: 21494223BKS | E90: Chris Bramley | F90: vickybramley@aol.com | G90: Delivery date | H90: KS | I90: Wire | J90: UK | L90: 1
A91: 44936 | B91: 187,86 | C91: 44199 | D91: #16626 | E91: Christofer Popoff | F91: pjcxfyp4jk@privaterelay.appleid.com | G91: Other | H91: Ks | I91: KS | J91: Sweden | K91: 1 | N91: 1 | P91: 1
A92: 44936 | B92: 233.51 | C92: 44863 | D92: #114105 | E92: Cindy Pormilli | F92: cindym109@gmail.com | G92: Delivery date | H92: Shopify | I92: Shopify chargeback | J92: USA | K92: 1 | P92: 1
A93: 44936 | B93: 272.9 | C93: 44191 | D93: 21488553BKS | E93: David Stocks | F93: davestocks@me.com | G93: Delivery date | H93: KS | I93: ? | J93: UK | L93: 1 | O93: 1 | P93: 1
A94: 44936 | B94: 253 | C94: 44918 | D94: #137618 | E94: Dorota Szelagowicz | F94: dorota100@hotmail.com | G94: Delivery date | H94: Shopify | I94: Shopify | J94: Canada | K94: 1 | N94: 1
A95: 44936 | B95: $301.00 | C95: 44848 | D95: #109492 | E95: Gabriel Urban | F95: gabriel.urban@ehl.ch | G95: Delivery date | H95: Shopify | I95: Shopify | J95: Switzerland | L95: 1 | P95: 1
A96: 44936 | B96: 125.8 | C96: 18/22/2020 | D96: 21477321BKS | E96: Glenn Browne | F96: glenn.browne@aucklandcouncil.govt.nz | G96: Delivery date | H96: KS | I96: KS | J96: NZ | K96: 1
A97: 44936 | B97: 183.2 | C97: 44193 | D97: 21489317BKS | E97: Helen Thomson | F97: helen_thomson@live.co.uk | G97: Unknown | H97: KS | I97: Wire | J97: UK | K97: 1
A98: 44936 | B98: 155.5 | C98: 44153 | D98: 21475940BKS | E98: Jacquie Campbell | F98: jacquiescampbell@me.com | G98: Unknown | H98: KS | I98: ? | J98: UK | K98: 1 | N98: 1 | P98: 1
A99: 44936 | B99: 237.4 | C99: 44162 | D99: 21482042BKS | E99: James Shaw | F99: james.shaw21@yahoo.co.uk | G99: Delivery date | H99: KS | I99: wire | J99: UK | L99: 1 | P99: 1
A100: 44936 | B100: 363.9 | C100: 44901 | D100: #134738 | E100: Jeff Gatofano | F100: jgarofano12@gmail.com | G100: Unknown | H100: Shopify | I100: Shopify | J100: USA | K100: 1 | M100: 1 | N100: 1 | P100: 1 | Q100: 1
...

Sheet Returns
A1: Date of return | B1: Value | C1: Date of purchase | D1: Order ID | E1: Name | F1: Email | G1: Reason | H1: Platform | I1: Refund through | J1: Country | K1: Bird Buddy | L1: Bird Buddy with Solar Roof | M1: Solar Roof | N1: Wall Mount | O1: Fence Mount | P1: Suet Ball Holder | Q1: Water Fountain | R1: Premium Subscription | S1: Seeds Subscription | T1: 12-month warranty | U1: 24-month warranty | W1: Reason
A2: 44930 | B2: 18 | C2: 44393 | D2: 23186212IGG | E2: Florence Tsang | F2: florencetsang@gmail.com | G2: Other | H2: IGG | I2: Zelle | J2: US | O2: 1 | W2: Delivery Date | Y2: =X2/X8 -> #DIV/0!
A3: 44930 | B3: 201.8 | C3: 44155 | D3: 21477634BKS | E3: Dan Guzzetta | F3: maria.guzzetta00@gmail.com | G3: Other | H3: KS | I3: Zelle | J3: US | L3: 1 | N3: 1 | W3: Cannot Afford it Anymore | Y3: =X3/X8 -> #DIV/0!
A4: 44927 | B4: 206 | C4: 44402 | D4: 23409340IGG | E4: William H Hodgkin | F4: whodgkin@aol.com | G4: Other | H4: IGG | I4: Wise | J4: USA | K4: 1 | W4: Faulty item
A5: 44927 | B5: 18 | C5: 44689 | D5: #67353 | E5: Devi Meyers | F5: dclmeyers@gmail.com | G5: Other | H5: Shopify | I5: Shopify | J5: USA | O5: 1
A6: 44928 | B6: 235.81 | C6: 44731 | D6: #70970 | E6: Patricia Lee | F6: patmonteiro60@gmail.com | G6: Other | H6: Shopify | I6: Shopify Chargeback | J6: USA | K6: 1
A7: 44931 | B7: 271.1 | C7: 44155 | D7: 21489242BKS | E7: Gwendolyn Koch | F7: ladyleafe@gmail.com | G7: Other | H7: KS | I7: Zelle | J7: USA | L7: 1 | P7: 1
A8: 44931 | B8: 357.22 | C8: 44680 | D8: #43213 | E8: Danielle Hawle | F8: danielle.shanaberger@gmail.com | G8: Other | H8: Shopify | I8: Shopify | J8: USA | L8: 1 | N8: 1 | O8: 1 | P8: 1 | W8: All | X8: =SUM(X2:X7) -> 0
A9: 44931 | B9: 218 | C9: 44407 | D9: #10423KS | E9: Elizabeth Smith | F9: thorndike400@gmail.com | G9: Other | H9: Shopify | I9: Shopify | J9: USA | K9: 1 | P9: 1
A10: 44931 | B10: 265 | C10: 44371 | D10: 22895189IGG | E10: Jason Odom | F10: jodom75@mac.com | G10: Other | H10: IGG | I10: Zelle | J10: USA | L10: 1
A11: 44931 | B11: 255.73 | C11: 44872 | D11: #119191 | E11: Amy Lacy | F11: amybethlacy@gmail.com | G11: Other | H11: Shopify | I11: Shopify Chargeback | J11: USA | K11: 1 | P11: 1 | W11: All Orders | X11: =Sales!B51 -> 5451
A12: 44931 | B12: 253.45 | C12: 44862 | D12: #114045 | E12: Minah Malik | F12: minahmalikk@gmail.com | G12: Other | H12: Shopify | I12: Shopify Chargeback | J12: USA | K12: 1 | P12: 1 | W12: Refund % | X12: =X8/X11 -> 0
A13: 44931 | B13: 287.16 | G13: Other | H13: Shopify | I13: Shopify | J13: USA | L13: 1
A14: 44931 | B14: 284 | C14: 44625 | D14: #19562 | E14: Megan Sechrist | F14: sechrist.signups@gmail.com | G14: Other | H14: Shopify | I14: Shopify Chargeback | J14: USA | L14: 1
A15: 44931 | B15: 351.48 | C15: 44855 | D15: #110988 | E15: Dayna Hickman | F15: daynam.hickman@gmail.com | G15: Other | H15: Shopify | I15: Shopify Chargeback | J15: USA | K15: 1 | M15: 1 | N15: 1 | P15: 1
A16: 44931 | B16: 314.66 | C16: 44855 | D16: #110816 | E16: KIM BARRETT | F16: KIMBA77@GMAIL.COM | G16: Other | H16: Shopify | I16: Shopify | J16: USA | K16: 1 | M16: 1 | P16: 1
A17: 44932 | B17: 18 | C17: 44354 | D17: #2816KS | E17: Kelly Pedersen | F17: pedersen_kelly@hotmail.com | G17: Other | H17: Shopify | I17: Shopify | J17: USA | N17: 1
A18: 44932 | B18: 330 | C18: 44639 | D18: #21245-A | E18: Jonathan Ayala | F18: jonfocus@gmail.com | G18: Other | H18: Shopify | I18: Shopify | J18: USA | L18: 1 | O18: 1
A19: 44932 | B19: 230.94 | C19: 44853 | D19: #110226 | E19: Sam Streitz | F19: samanthayancey1@gmail.com | G19: Other | H19: Shopify | I19: Shopify | J19: USA | K19: 1 | P19: 1
A20: 44932 | B20: 248.93 | C20: 44877 | D20: #121441 | E20: Laura McAllister | F20: laura.pickard84@gmail.com | G20: Other | H20: Shopify | I20: Shopify | J20: USA | K20: 1 | P20: 1
A21: 44932 | B21: 233.24 | C21: 44860 | D21: #112944 | E21: Stefani Ramsoy | F21: gracemarie23@comcast.net | G21: Other | H21: Shopify | I21: Shopify | J21: USA | K21: 1 | P21: 1
A22: 44932 | B22: 319.93 | C22: 44877 | D22: #121535 | E22: Gene Markowski | F22: kmmtoke@gmail.com | G22: Other | H22: Shopify | I22: Shopify | J22: USA | L22: 1 | P22: 1
A23: 44932 | B23: 279 | C23: 44698 | D23: #68227 | E23: Lawrence Kahsen | F23: chip@kahsen.com | G23: Other | H23: Shopify | I23: Shopify | J23: USA | L23: 1
A24: 44932 | B24: 197.6 | C24: 44170 | D24: 21483918BKS | E24: Rick Ermak | F24: rickermak@aol.com | G24: Other | H24: KS | I24: KS | J24: USA | K24: 1 | P24: 1
A25: 44932 | B25: 299 | C25: 44890 | D25: #128723 | E25: Aaron Jones | F25: aaronjn@comcast.net | G25: Other | H25: Shopify | I25: Shopify | J25: USA | K25: 1 | M25: 1 | P25: 1
A26: 44932 | B26: 185.3 | C26: 44176 | D26: 21484857BKS | E26: Patrick McGovern | F26: pmcgovern@gmail.com | G26: Other | H26: KS | I26: KS | J26: USA | K26: 1
A27: 44932 | B27: 275.55 | C27: 44302 | D27: #40548 | E27: Melinda Hooton | F27: mhooton2007@gmail.com | G27: Other | H27: Shopify | I27: Shopify | J27: USA | L27: 1
A28: 44932 | B28: 301.67 | C28: 44721 | D28: #69896 | E28: Lisa Cohen | F28: cohenfive@gmail.com | G28: Other | H28: Shopify | I28: Shopify | J28: USA | L28: 1
A29: 44932 | B29: 343.19 | C29: 44876 | D29: #120982 | E29: Christopher Leather | F29: cleather@uchicago.edu | G29: Other | H29: Shopify | I29: Shopify | J29: USA | L29: 1 | N29: 1 | P29: 1
A30: 44932 | B30: 290.16 | C30: 44680 | D30: #43222 | E30: John Stilp | F30: taylor.a.truex@gmail.com | G30: Other | H30: Shopify | I30: Shopify | J30: USA | L30: 1
A31: 44932 | B31: 307.83 | C31: 44741 | D31: #71383 | E31: Stacy Briggs | F31: sasenneff22@gmail.com | G31: Other | H31: Shopify | I31: Shopify | J31: USA | L31: 1
A32: 44932 | B32: 149.04 | C32: 44103 | D32: 21485828BKS | E32: George Heuring | F32: heuringgeo@gmail.com | G32: Other | H32: KS | I32: check | J32: USA | K32: 1
A33: 44932 | B33: 242 | C33: 44371 | D33: 22391556IGG | E33: Susan Swigor | F33: susan.swigor@gmail.com | G33: Other | H33: IGG | I33: check | J33: USA | K33: 1 | N33: 1 | O33: 1
A34: 44933 | B34: 59 | C34: 44370 | D34: #4689KS | E34: Jade Wiederholt | F34: jadewiederholt@yahoo.com | G34: Other | H34: Shopify | I34: Shopify | J34: USA | M34: 1
A35: 44934 | B35: 23.39 | C35: 44893 | D35: #132594 | E35: Meredith Diers | F35: meredith.diers@gmail.com | G35: Other | H35: Shopify | I35: Shopify | J35: USA | N35: 1
A36: 44934 | B36: 333.74 | C36: 44861 | D36: #113430 | E36: Zoha Khan | F36: zoha375@gmail.com | G36: Other | H36: Shopify | I36: Shopify | J36: USA | L36: 1 | N36: 1 | P36: 1
A37: 44934 | B37: 244.17 | C37: 44883 | D37: #123873 | E37: Randall Lotowycz | F37: randall.lotowycz@gmail.com | G37: Other | H37: Shopify | I37: Shopify | J37: USA | K37: 1
A38: 44934 | B38: 327.84 | C38: 44867 | D38: #116384 | E38: Victoria Thompson | F38: torriemthompson@me.com | G38: Other | H38: Shopify | I38: Shopify Chargeback | J38: USA | L38: 1
A39: 44934 | B39: 201.34 | C39: 44764 | D39: 21482588BKS | E39: Tom Hume | F39: twhume@gmail.com | G39: Other | H39: Shopify | I39: Shopify | J39: USA
A40: 44934 | B40: 285.78 | C40: 44860 | D40: #112795 | E40: Bianca May | F40: daya0088@gmail.com | G40: Other | H40: Shopify | I40: Waiting for chargeback | J40: USA | L40: 1 | N40: 1 | P40: 1
A41: 44934 | B41: 283.94 | C41: 44635 | D41: #20829 | E41: Andrew J McIlvaine | F41: ajmcilvaine@gmail.com | G41: Other | H41: Shopify | I41: Shopify | J41: USA | L41: 1
A42: 44934 | B42: 301.39 | C42: 44850 | D42: #109772 | E42: Sandra Bounds | F42: sandrabounds@gmail.com | G42: Other | H42: Shopify | I42: Shopify | J42: USA | K42: 1 | M42: 1 | N42: 1 | P42: 1 | R42: 1
A43: 44934 | C43: 44864 | D43: #114735 | E43: Holly Nelson | F43: hnelson5724@yahoo.com | G43: Other | H43: Shopify | I43: Waiting for chargeback | J43: USA
A44: 44934 | B44: 227.65 | C44: 44891 | D44: #130683 | E44: Sarah Feldman | F44: srfeldma@gmail.com | G44: Other | H44: Shopify | I44: Shopify | J44: USA | K44: 1
A45: 44934 | B45: 324.8 | C45: 44887 | D45: #126335 | E45: Bryan Lazarus | F45: bryanlazarus@gmail.com | G45: Other | H45: Shopify | I45: Shopify Chargeback | J45: USA | K45: 1 | M45: 1 | P45: 1
A46: 44934 | B46: 217 | C46: 44883 | D46: #14204KS | E46: Regina Haymes | F46: reginahaymes@me.com | G46: Other | H46: Shopify | I46: Shopify | J46: USA | K46: 1 | N46: 1
A47: 44934 | B47: 505 | C47: 44389 | D47: #6877KS | E47: karen stender | F47: karen_stender@yahoo.com | G47: Other | H47: Shopify | I47: Check | J47: USA | L47: 2 | N47: 1
A48: 44934 | B48: 265 | C48: 44393 | D48: 22375766IGG | E48: Randie Jaffe | F48: randie.jaffe@gmail.com | G48: Other | H48: Shopify | I48: Check | J48: USA | L48: 1
A49: 44934 | B49: 200.5 | C49: 44102 | D49: 21481943BKS | E49: Richard Forest | F49: crasher1339@aol.com | G49: Other | H49: KS | I49: Zelle | J49: USA | K49: 1 | O49: 1 | P49: 1
A50: 44934 | B50: 277.8 | C50: 44105 | D50: 21493341BKS | E50: Zachary Arnold | F50: zarnold@bangorchristian.org | G50: Other | H50: KS | I50: KS | J50: USA | L50: 1 | N50: 1 | P50: 1
A51: 44936 | B51: 212 | C51: 44371 | D51: 23944318IGG | E51: Wes farrell | F51: wesley.farrell@gmail.com | G51: Other | H51: IGG | I51: Zelle | J51: USA | L51: 1
A52: 44936 | B52: 283 | C52: 44376 | D52: #5323KS | E52: Regina Kozek | F52: ginakozek@gmail.com | G52: Other | H52: Shopify | I52: Zelle | J52: USA | L52: 1 | O52: 1
A53: 44936 | B53: 333.56 | C53: 44701 | D53: #68414 | E53: Linda Anderson | F53: tauralcanderson@gmail.com | G53: Other | H53: Shopify | I53: Zelle | J53: USA | L53: 1 | O53: 1
A54: 44937 | B54: 315.14 | C54: 44892 | D54: #131458 | E54: Andrew Tisinger | F54: ajtisinger@gmail.com | H54: Shopify | J54: USA | K54: 1 | M54: 1 | P54: 1
A55: 44938 | B55: 317.18 | C55: 44696 | D55: #68052 | E55: David Perdue | F55: d@perduemail.com | G55: Delivery date | H55: Shopify | I55: Shopify | J55: USA | L55: 1
A56: 44938 | B56: 323 | C56: 44882 | D56: #123308 | E56: Kyle Higgins | F56: kyle.higgins@gmail.com | G56: Other | H56: Shopify | I56: Shopify | J56: USA | K56: 1 | M56: 1 | N56: 1 | P56: 1
A57: 44939 | B57: 24 | C57: 44807 | D57: #106838 | E57: Martin Gagnon | F57: mgagnon@glrn.ca | G57: Faulty item | H57: Shopify | I57: Shopify | J57: Canada | O57: 1
A58: 44939 | B58: 244.46 | C58: 44886 | D58: #125709 | E58: John Donoghue | F58: jdonoghu@cisco.com | G58: Other | H58: Shopify | I58: Shopify | J58: USA | K58: 1 | P58: 1
A59: 44939 | B59: 334.28 | C59: 44678 | D59: #42886 | E59: Laurie Thielman | F59: thethielmans@gmail.com | G59: Other | H59: Shopify | I59: Shopify Chargeback | J59: USA | K59: 1 | M59: 1 | O59: 1
A60: 44939 | B60: 287.93 | C60: 44850 | D60: #109754 | E60: Doris Hoffmann | F60: dorishoffmann@sbcglobal.net | G60: Other | H60: Shopify | I60: Wise | J60: USA | K60: 1 | M60: 1 | P60: 1 | Q60: 1 | R60: 1
A61: 44939 | B61: 212.18 | C61: 44892 | D61: #131569 | E61: Lauren Mikol | F61: xgymnastswtyx@gmail.com | G61: Other | H61: Shopify | I61: Shopify | J61: USA | K61: 1 | P61: 1
A62: 44939 | B62: 206 | C62: 44463 | D62: #11780KS | E62: Rebecca Tedeschi | F62: rebteddie@comcast.net | G62: Other | H62: Shopify | I62: Zelle | J62: USA | K62: 1
A63: 44940 | B63: 252.48 | C63: 44891 | D63: #130888 | E63: Alina Korotaeva | F63: aokorotaeva@gmail.com | G63: Other | H63: Shopify | I63: Shopify | J63: USA | K63: 1 | P63: 1
A64: 44940 | B64: 248.78 | C64: 44866 | D64: #115766 | E64: Kerrie Matesich | F64: kmwmatesich@yahoo.com | G64: Other | H64: Shopify | I64: Chargeback lost | J64: USA | K64: 1
A65: 44940 | B65: 327.46 | C65: 44682 | D65: #65273 | E65: Alma Omeralovic | F65: alma.omeralovic@gmail.com | G65: Other | H65: Shopify | I65: Zelle | J65: USA | L65: 1 | N65: 1
A66: 44940 | B66: 206 | C66: 44398 | D66: #6795KS | E66: Christine Kerr | F66: ckerrnj@gmail.com | G66: Other | H66: Shopify | I66: Shopify | J66: USA | K66: 1
A67: 44940 | B67: 234 | C67: 44860 | D67: #112813 | E67: Julia Fitzer | F67: rcfitzer@gmail.com | G67: Other | H67: Shopify | I67: Shopify Chargeback | J67: USA | K67: 1 | P67: 1
A68: 44940 | B68: 206 | C68: 44394 | D68: #7519KS | E68: James Pyfer | F68: jamespyfer@gmail.com | G68: Other | H68: Shopify | I68: Shopify | J68: USA | K68: 1
A69: 44940 | B69: 229 | C69: 44890 | D69: #128666 | E69: Kathryn Richards | F69: krichards234@gmail.com | G69: Other | H69: Shopify | I69: Shopify | J69: USA | K69: 1 | P69: 1
A70: 44940 | B70: 286.88 | C70: 44859 | D70: #112475 | E70: Lori Wyatt | F70: jeralson@hotmail.com | G70: Other | H70: Shopify | I70: Shopify | J70: USA | K70: 1 | N70: 1 | P70: 1 | Q70: 1
A71: 44940 | B71: 223.63 | C71: 44680 | D71: #43204 | E71: Mary Roberts | F71: robertskt2@gmail.com | G71: Other | H71: Shopify | I71: Shopify | J71: USA | K71: 1
A72: 44940 | B72: 199 | C72: 44519 | D72: #14244KS | E72: Michael Oxton | F72: moxton@gmail.com | G72: Other | H72: Shopify | I72: Shopify | J72: USA | K72: 1
A73: 44940 | B73: 305.81 | C73: 44865 | D73: #115370 | E73: Nicole Macdonald | F73: kissmygritz@yahoo.com | G73: Other | H73: Shopify | I73: Shopify | J73: USA | K73: 1 | M73: 1 | P73: 1
A74: 44940 | B74: 242.93 | C74: 44888 | D74: #126917 | E74: Pam Ratchford | F74: pamratch@hotmail.com | G74: Other | H74: Shopify | I74: Shopify | J74: USA | K74: 1 | P74: 1
A75: 44940 | B75: 233.51 | C75: 44869 | D75: #117501 | E75: Sara Kelly | F75: sara.moke@gmail.com | G75: Other | H75: Shopify | I75: Shopify | J75: USA | K75: 1 | P75: 1
A76: 44940 | B76: 245.03 | C76: 44888 | D76: #126938 | E76: Trisha van Olhpen | F76: trisha.vanolphen@coxinc.com | G76: Other | H76: Shopify | I76: Shopify | J76: USA | K76: 1 | P76: 1
A77: 44940 | B77: 242.74 | C77: 44891 | D77: #130421 | E77: Katrina Warner | F77: swickkatrina@gmail.com | G77: Other | H77: Shopify | I77: Shopify | J77: USA | K77: 1
A78: 44940 | B78: 245.4 | C78: 44210 | D78: 21498493BKS | E78: Larry Pauley | F78: jillpauley@hotmail.com | G78: Other | H78: KS | I78: KS | J78: USA | L78: 1
A79: 44940 | B79: 297 | C79: 44610 | D79: #18516 | E79: Carissa Foster | F79: fosterCL71@gmail.com | G79: Other | H79: Shopify | I79: Shopify | J79: USA | L79: 1 | N79: 1
A80: 44940 | B80: 242.74 | C80: 44878 | D80: #121720 | E80: Harrirt Harworth | F80: hharworth@gmail.com | G80: Other | H80: Shopify | I80: Shopify | J80: USA | K80: 1
A81: 44940 | B81: 241.68 | C81: 44886 | D81: #125623 | E81: Laura Garofalo | F81: Karma411@aol.com | G81: Other | H81: Shopify | I81: Shopify | J81: USA | K81: 1 | N81: 1 | P81: 1
A82: 44940 | B82: 206 | C82: 44388 | D82: #6649KS | E82: Judith Dickinson | F82: buffalogirl@rocketmail.com | G82: Other | H82: Check | I82: Shopify | J82: USA | K82: 1 | M82: 1
A83: 44940 | B83: 32.63 | C83: 44893 | D83: #131940 | E83: Greg Dunlap | F83: gregdunlap2@gmail.com | G83: Other | H83: Shopify | I83: Shopify | J83: USA
A84: 44940 | B84: 244.7 | C84: 44103 | D84: 21484433BKS | E84: Larry Larson | F84: llarson@aol.com | G84: Other | H84: KS | I84: Zelle | J84: USA | L84: 1
A85: 44940 | B85: 206 | C85: 44432 | D85: #11256KS | E85: Karen Codespoti | F85: kfcmech@gmail.com | G85: Other | H85: Shopify | I85: Check | J85: USA | K85: 1
A86: 44940 | B86: 283 | C86: 44708 | D86: #1863KS | E86: Michelle Laird | F86: michellealaird@yahoo.com | G86: Other | H86: Shopify | I86: Zelle | J86: USA | L86: 1
A87: 44940 | B87: 487 | C87: 44371 | D87: 22767647IGG | E87: Peter Figueredo | F87: kitchensink@gmail.com | G87: Other | H87: IGG | I87: Zelle | J87: USA | L87: 2
A88: 44940 | B88: 253 | C88: 44892 | D88: #131058 | E88: Amy Ziegler | F88: Amy Ziegler | G88: Other | H88: Shopify | I88: Shopify | J88: USA | K88: 1 | N88: 1 | P88: 1
A89: 44940 | B89: 325.54 | C89: 44887 | D89: #125982 | E89: Raeann DiAngelis | F89: rgd97@msn.com | G89: Other | H89: Shopify | I89: Shopify | J89: USA | K89: 1 | M89: 1
A90: 44940 | B90: 125.5 | C90: 44054 | D90: 21478538BKS | E90: Charlene Stark | F90: jcstark1@gmail.com | G90: Other | H90: KS | I90: Zelle | J90: USA | K90: 1
A91: 44941 | B91: 307.7 | C91: 44631 | D91: #20427 | E91: Eleanor Carr | F91: ellie1@humboldt1.com | G91: Other | H91: KS | I91: Check | J91: USA | L91: 1 | N91: 1
A92: 44941 | B92: 323.21 | C92: 44671 | D92: #41528 | E92: Shel Mullen | F92: mnnice911@aol.com | G92: Other | H92: Shopify | I92: Shopify | J92: USA | L92: 1 | P92: 1
A93: 44941 | B93: 308.58 | C93: 44673 | D93: #41791 | E93: Lisa Wirth | F93: wirth.lisa.n@gmail.com | G93: Other | H93: Shopify | I93: Shopify | J93: USA | L93: 1 | O93: 1
A94: 44941 | B94: 295 | C94: 44371 | D94: 22184434IGG | E94: Joseph C Jenkins III | F94: jcjenkins3@att.net | G94: Other | H94: IGG | I94: Zelle | J94: USA | L94: 1 | O94: 1 | P94: 1
A95: 44941 | B95: 325.91 | C95: 44882 | D95: #123406 | E95: Ellie Cutright | F95: ellie.cutright@gmail.com | G95: Other | H95: Shopify | I95: Shopify | J95: USA | K95: 1 | M95: 1
A96: 44941 | B96: 343.27 | C96: 44637 | D96: #21034 | E96: Dawne Hill | F96: dawne.dey@gmail.com | G96: Other | H96: Shopify | I96: Zelle | J96: USA | L96: 1 | N96: 1 | O96: 1 | P96: 1
A97: 44942 | B97: 314.82 | C97: 44688 | D97: #66847 | E97: Denise Kraenzlein | F97: prettykitty55@hotmail.com | G97: Other | H97: Shopify | I97: Wise | J97: USA | L97: 1 | N97: 1
A98: 44942 | B98: 315.71 | C98: 44882 | D98: #123589 | E98: Matthew Allen | F98: plasticeng@mail.com | G98: Other | H98: Shopify | I98: Shopify | J98: USA | K98: 1 | M98: 1 | N98: 1 | P98: 1
A99: 44942 | B99: 296.42 | C99: 44563 | D99: #16271 | E99: Leigh Ann Culpan | F99: leighannbigley@me.com | G99: Other | H99: Shopify | I99: Shopify | J99: USA | K99: 1 | M99: 1
A100: 44942 | B100: 259.86 | C100: 44610 | D100: #18517 | E100: CATHY MERTZ | F100: cathymertz@comcast.net | G100: Other | H100: Shopify | I100: Shopify Chargeback | J100: USA | K100: 1 | P100: 1
...

Sheet Chargebacks
A1: Date of chargeback | B1: Date of payout | C1: Chargeback value | D1: Date of purchase | E1: Order ID | F1: Name | G1: Email | H1: Country | I1: Comment | J1: Status | K1: Bird Buddy | L1: Bird Buddy with Solar Roof | M1: Solar Roof | N1: Wall Mount | O1: Fence Mount | P1: Suet Ball Holder | Q1: Water Fountain | R1: Premium Subscription | S1: Seeds Subscription | T1: 12-month warranty | U1: 24-month warranty
A2: 44946 | B2: 44949 | C2: 268 | D2: 44899 | E2: #134326 | F2: Karen Nolan | G2: rooon55@aol.com | H2: US | I2: product not received | J2: Accepted | K2: 1 | N2: 1 | P2: 1
A3: 44931 | B3: 44934 | C3: 336.19 | D3: 44900 | E3: #134571 | F3: William Ferrell | G3: WFERRELL@GMAIL.COM | H3: US | I3: product not received | J3: Accepted | L3: 1
A4: 44947 | B4: 44949 | C4: 330.82 | D4: 44920 | E4: #138366 | F4: Lou Carrier | G4: lou@dhghotels.com | H4: US | I4: product not received | J4: Accepted | K4: 1 | M4: 1 | P4: 1
A5: 44940 | B5: 44942 | C5: 330.45 | D5: 44911 | E5: #136876 | F5: Rebecca Kleist | G5: abcdlkleist@gmail.com | H5: US | I5: product not received | J5: Accepted | K5: 1 | M5: 1 | P5: 1
A6: 44942 | B6: 44944 | C6: 277.63 | D6: 44909 | E6: #136116 | F6: Wes Byers | G6: byersjw1@gmail.com | H6: US | I6: product not received | J6: Accepted | K6: 1 | N6: 1 | P6: 1
A7: 44945 | B7: 44950 | C7: 228.43 | D7: 44892 | E7: #131529 | F7: Megan Meadows | G7: megfree@gmail.com | H7: US | I7: product unacceptable | J7: Accepted | K7: 1 | P7: 1
A8: 44939 | B8: 44943 | C8: 363.84 | D8: 44890 | E8: #128792 | F8: Adam Schanz | G8: adamschanz06@gmail.com | H8: US | I8: product unacceptable | J8: Accepted | K8: 1 | M8: 1 | N8: 1 | P8: 1
A9: 44945 | B9: 44949 | C9: 257.74 | D9: 44888 | E9: #127007 | F9: Megan Shilling | G9: megan.shilling@gmail.com | H9: US | I9: product not received | J9: Accepted | K9: 1 | P9: 1
A10: 44943 | B10: 44945 | C10: 255.94 | D10: 44888 | E10: #126864 | F10: Parker Parker | G10: parkerism@gmail.com | H10: US | I10: credit not processed | J10: Accepted | K10: 1 | P10: 1
A11: 44941 | B11: 44943 | C11: 380.7 | D11: 44886 | E11: #125725 | F11: Ryan Konetsky | G11: ryan@ethenllc.com | H11: US | I11: product not received | J11: Accepted | K11: 1 | M11: 1 | N11: 1 | P11: 1 | Q11: 1
A12: 44932 | B12: 44935 | C12: 357.38 | D12: 44886 | E12: #125503 | F12: Troy LeBlanc | G12: tjleblanc01@yahoo.com | H12: US | I12: product unacceptable | J12: Accepted | K12: 1 | M12: 1 | N12: 1 | P12: 1
A13: 44943 | B13: 44956 | C13: 258.32 | D13: 44884 | E13: #124198 | F13: Taylor Fox | G13: TaylorNFox92@gmail.com | H13: US | I13: general | J13: Inquiry won | K13: 1 | P13: 1
A14: 44940 | B14: 44943 | C14: 262.33 | D14: 44883 | E14: #123874 | F14: Maddy Tippie | G14: mtippie95@gmail.com | H14: US | I14: fraudulent | J14: Accepted | K14: 1 | P14: 1
A15: 44946 | B15: 44950 | C15: 358.2 | D15: 44881 | E15: #122961 | F15: Paul Davis | G15: pauledavis1980@gmail.com | H15: US | I15: product unacceptable | J15: Accepted | K15: 1 | M15: 1 | N15: 1 | P15: 1
A16: 44944 | B16: 44946 | C16: 259.46 | D16: 44880 | E16: #122811 | F16: Kathleen Papia | G16: covino.katie@gmail.com | H16: US | I16: product unacceptable | J16: Accepted | K16: 1 | P16: 1
A17: 44928 | B17: 44930 | C17: 256.44 | D17: 44880 | E17: #122548 | F17: Reese Goodman | G17: goodman.jim705@gmail.com | H17: US | I17: product not received | J17: Accepted | K17: 1 | P17: 1
A18: 44950 | B18: 44952 | C18: 331.94 | D18: 44878 | E18: #121924 | F18: Jennifer L Sturgeon | G18: jensturgeon2004@yahoo.com | H18: US | I18: product unacceptable | J18: Accepted | K18: 1 | M18: 1 | P18: 1
A19: 44945 | B19: 44950 | C19: 336.53 | D19: 44878 | E19: #121881 | F19: Mary Fike | G19: Marymichael9351@gmail.com | H19: US | I19: product unacceptable | J19: Accepted | K19: 1 | M19: 1 | P19: 1
A20: 44929 | B20: 44931 | C20: 246.92 | D20: 44875 | E20: #120189 | F20: Meg Sandu | G20: megsandu@gmail.com | H20: US | I20: product not received | J20: Accepted | K20: 1 | P20: 1
A21: 44939 | B21: 44943 | C21: 338.67 | D21: 45240 | E21: #120165 | F21: lloyd sitkoff | G21: trytone@frontier.com | H21: US | I21: credit not processed | J21: Accepted | L21: 1 | P21: 1
A22: 44943 | B22: 44945 | C22: 257.74 | D22: 44873 | E22: #119265 | F22: Katherine Patterson | G22: katie.patterson3160@gmail.com | H22: US | I22: credit not processed | J22: Accepted | K22: 1 | P22: 1
A23: 44947 | B23: 44950 | C23: 283.18 | D23: 44871 | E23: #118485 | F23: Casey Durden | G23: caseydurden@gmail.com | H23: US | I23: credit not processed | J23: Accepted | K23: 1 | N23: 1 | P23: 1
A24: 44933 | B24: 44935 | C24: 256.6 | D24: 44870 | E24: #117899 | F24: Emily Jacobsen | G24: emilyann324@yahoo.com | H24: US | I24: product unacceptable | J24: Accepted | K24: 1 | P24: 1
A25: 44934 | B25: 44935 | C25: 322.79 | D25: 44867 | E25: #116110 | F25: Nikoll Dreher | G25: urh@mybirdbuddy.com | H25: US | I25: credit not processed | J25: Accepted | L25: 1
A26: 44947 | B26: 44949 | C26: 273.19 | D26: 44866 | E26: #115884 | F26: Pyol Thompson | G26: pyolstarr@gmail.com | H26: US | I26: duplicate | J26: Accepted | K26: 1 | N26: 1 | P26: 1
A27: 44940 | B27: 44942 | C27: 247.14 | D27: 44866 | E27: #115553 | F27: Kurt Kreyling | G27: kurtkreyling@gmail.com | H27: US | I27: product not received | J27: Accepted | K27: 1 | N27: 1
A28: 44929 | B28: 44931 | C28: 375.97 | D28: 44863 | E28: #114221 | F28: Kathleen Oldford | G28: ko@bigdogmarketing.com | H28: US | I28: product unacceptable | J28: Accepted | K28: 1 | M28: 1 | N28: 1 | P28: 1 | Q28: 1
A29: 44934 | B29: 44936 | C29: 326.54 | D29: 44859 | E29: #112633 | F29: Leigh Hensley | G29: leighhensley@gmail.com | H29: US | I29: redit not processed | J29: Accepted | L29: 1 | P29: 1
A30: 44939 | B30: 44943 | C30: 247.69 | D30: 44855 | E30: #111040 | F30: Josh Schroyer | G30: s.schroyer@comcast.net | H30: US | I30: product unacceptable | J30: Accepted | K30: 1 | P30: 1
A31: 44952 | B31: 44952 | C31: 576 | D31: 44850 | E31: #109817 | F31: Mike Dias | G31: mtdias226@gmail.com | H31: US | I31: product unacceptable | J31: Accepted | K31: 2 | M31: 2 | P31: 2
A32: 44946 | B32: 44950 | C32: 299.68 | D32: 44849 | E32: #109593 | F32: Iver Holter-Andersen | G32: iver.ha@online.no | H32: US | I32: product not received | J32: Accepted | K32: 1 | N32: 1 | P32: 1
A33: 44950 | B33: 44952 | C33: 322.35 | D33: 44665 | E33: #40325 | F33: Emily Downard | G33: emilymaydownard@gmail.com | H33: US | I33: product unacceptable | J33: Accepted | L33: 1
A34: 44940 | B34: 44943 | C34: 294 | D34: 44643 | E34: #21719 | F34: Amber Kiggens-Leifheit | G34: tleifheit@charter.net | H34: US | I34: product unacceptable | J34: Accepted | L34: 1
A35: 44939 | B35: 44943 | C35: 231 | D35: 44478 | E35: #12439 | F35: Louise Farrel | G35: louise296@aol.com | H35: US | I35: product unacceptable | J35: Accepted | K35: 1

Sheet Edited Orders
A1: Date | B1: Date of purchase | C1: Order ID | D1: Name | E1: Email | F1: Old Value | G1: New Value | H1: Difference | I1: Change
A2: 44930 | B2: 44917 | C2: #137352 | D2: David Jackson | E2: jacksonds88@gmail.com | F2: 36.58 | G2: 58.51 | H2: 21.93 | I2: Added water fountain.
A3: 44930 | B3: 44930 | C3: #140792 | D3: Allison Thompson | E3: athompson3276@gmail.com | F3: 70 | G3: 70 | H3: 0 | I3: Change from blue to yellow solar roof
A4: 44932 | B4: 44923 | C4: #139069 | D4: Ramón Lith | E4: rlithmoragues@gmail.com | F4: 66 | G4: 42 | H4: 24 | I4: Refunded Wall Mount
B5: 44919 | C5: #137778 | D5: Rachel Matthews | E5: rmatthews@net-result.com | F5: 183.27 | G5: 183.27 | H5: 0 | I5: Changed blue for yellow BB
B6: 44919 | C6: #137896 | D6: Marnee Muskal | E6: marnee.muskal@gmail.com | F6: 363.27 | G6: 363.27 | H6: 0 | I6: Changed blue for yellow (BB&solar roof)
B7: 44931 | C7: #141075 | D7: David Godi | E7: godi4812@yahoo.com | F7: 271.18 | G7: 271.18 | H7: 0 | I7: Changed blue for yellow (BB&solar roof)
A8: 44935 | B8: 44874 | C8: #119755 | D8: Judy Smith | E8: jgmeshells9364@gmail.com | F8: 299 | G8: 299 | H8: 0 | I8: Removed suet ball holder
A9: 44935 | B9: 44856 | C9: #111230 | D9: Lindsay Paradis | E9: toothfairy603@yahoo.com | F9: 313 | G9: 219 | H9: 94 | I9: Removed suet ball holder, solar roof and wall mount
A10: 44935 | B10: 44885 | C10: #124827 | D10: Hollie Swofford | E10: hollieswofford@me.com | F10: 244.46 | G10: 244.46 | H10: 0 | I10: Removed suet ball holder
A11: 44935 | B11: 44886 | C11: #125625 | D11: Marisa Moore | E11: marisaraemoore@gmail.com | F11: 244.46 | G11: 244.46 | H11: 0 | I11: Removed suet ball holder
A12: 44935 | B12: 44859 | C12: #112384 | D12: Michele Brown | E12: mlbrown0516@gmail.com | F12: 239.5 | G12: 239.5 | H12: 0 | I12: Removed suet ball holder
A13: 44935 | B13: 44856 | C13: #111082 | D13: Bruce Conover | E13: R00A005@MSN.COM | F13: 306.34 | G13: 232.14 | H13: 74.2 | I13: Refunded Solar Roof
A14: 44935 | B14: 44858 | C14: #111852 | D14: Michal Owens | E14: michal.owens@gmail.com | F14: 309.23 | G14: 234.33 | H14: 74.9 | I14: Refunded Solar roof, removed suet ball holder
A15: 44936 | B15: 44889 | C15: #127201 | D15: Carianne DePasqua | E15: carianneavis@gmail.com | F15: 277.66 | G15: 251.32 | H15: 26.34 | I15: Refunded for Wall Mount, removed Suet Sall Holder
A16: 44936 | B16: 44889 | C16: #128111 | D16: Christoph Peters | E16: christoph.peters@kth-trailer.de | F16: 299.52 | G16: 248.91 | H16: 50.61 | I16: Refunded for Wall Mount and Water Fountain, removed Suet Ball Holder
A17: 44936 | B17: 44881 | C17: #122917 | D17: Alane Schettler | E17: alanes@microsoft.com | F17: 329.66 | G17: 329.66 | H17: 0 | I17: Removed Suet Ball Holder
A18: 44936 | B18: 44862 | C18: #113844 | D18: Elizabeth Gonyea | E18: elizabeth.gonyea10@gmail.com | F18: 310.68 | H18: 75.25 | I18: Removed SBH and refunded SR
A19: 44937 | B19: 44891 | C19: #130434 | D19: Jennifer Hanks | E19: jenniferhanks18@gmail.com | F19: 266.06 | G19: 242.74 | H19: 23.32 | I19: Removed and refunded Water Fountain
A20: 44938 | B20: 44937 | C20: #142654 | D20: David prystay | E20: david@rpbhotels.com | F20: 1390 | G20: 1320 | H20: 70 | I20: Removed and refunded solar roof
A21: 44938 | B21: 44933 | C21: #141742 | D21: peter schwab | E21: peteschwab@gmail.com | F21: 252.48 | G21: 409.26 | H21: 156.78 | I21: Removed bird buddy and suet ball, added gift card and solar roof
A22: 44938 | B22: 44864 | C22: #114527 | D22: Aaron Price | E22: akprice95@msn.com | F22: 297.78 | G22: 222.7 | H22: 75.08
A23: 44939 | B23: 44881 | C23: #123023 | D23: Todd Caporal | E23: toddcaporal@gmail.com | F23: 316.94 | G23: 242.74 | H23: 74.2 | I23: refunded solar roof
A24: 44939 | B24: 44867 | C24: #116593 | D24: Jessica Pope | E24: jpope7487@gmail.com | F24: 289 | G24: 289 | H24: 0 | I24: Removed Suet Ball Holder
A25: 44939 | B25: 44880 | C25: #122691 | D25: Doug English | E25: dougenglish564@gmail.com | F25: 342.62 | G25: =F25-25.6 -> 317.02 | H25: 25.6 | I25: Removed Wall Mount
A26: 44939 | B26: 44938 | C26: #142791 | D26: Grant Hurlbert | E26: ghurlb@gmail.com | F26: 359.34 | G26: 285.14 | H26: 74.2 | I26: Removed Solar roof
A27: 44940 | B27: 44878 | C27: #121720 | D27: Harrirt Harworth | E27: hharworth@gmail.com | F27: 268.18 | G27: 242.74 | H27: 25.44 | I27: Removed Wall Mount and Suet Ball Holder
A28: 44940 | B28: 44867 | C28: #116500 | D28: Isabel Vaillancourt | E28: izabel.vaillancourt@gmail.com | F28: 80 | G28: 62.2 | H28: 17.8 | I28: Refunded for fence mount in a BKS order
A29: 44940 | B29: 44156 | C29: #125906 | D29: Caitlin Rawlins | E29: caitlinrawlins@yahoo.com | F29: 270.7 | G29: =F29-H29 -> 245.02 | H29: 25.68 | I29: Removed and refunded Suet Ball Holder and Wall Mount
A30: 44940 | B30: 44860 | C30: #112758 | D30: Regina Donohue | E30: regina.donohue@gmail.com | F30: 308.15 | G30: 308.15 | H30: 0 | I30: Removed Suet Ball Holder
A31: 44940 | B31: 44891 | C31: #129985 | D31: Amy Miknis | E31: amymiknis@gmail.com | F31: 219.84 | G31: 189.84 | H31: 30 | I31: refunded shipping
A32: 44940 | B32: 44875 | C32: #120144 | D32: Susan Freitas | E32: susan82695@gmail.com | F32: 247.61 | G32: 247.61 | H32: 0 | I32: Removed Suet Ball Holder
A33: 44941 | B33: 44941 | C33: #143151 | D33: Amanda House | E33: ahouse@utexas.edu | F33: 942.86 | G33: 651.67 | H33: 291.19 | I33: Removed 1 yellow BB
A34: 44577 | B34: 44893 | C34: #132365 | D34: Margaret McCown | E34: margaret.mccown@gmail.com | F34: 268.18 | G34: 268.18 | H34: 0 | I34: Removed Suet Ball Holder
A35: 44577 | B35: 44773 | C35: #106109 | D35: Shyronn Smardon | E35: shyronn@icloud.com | F35: 18 | G35: 18 | H35: 0 | I35: Changed blue for yellow (water fountain)
A36: 44578 | B36: 44935 | C36: #142075 | D36: Sam Page | E36: svpsamo@gmail.com | F36: 345 | G36: 345 | H36: 0 | I36: Changed blue to yellow
A37: 44578 | B37: 44677 | C37: #42736 | D37: ryan mcdougall | E37: dig4602@gmail.com | F37: 315 | G37: 297 | H37: 18 | I37: Refunded FM
A38: 44578 | B38: 44937 | C38: #142669 | D38: Judith Benz | E38: judith.benz@gmail.com | F38: 212.93 | G38: 250.38 | H38: 37.45 | I38: Added solar roof with 50%discount
A39: 44944 | B39: 44942 | C39: #143427 | D39: Youri KIVITS | E39: youri_kivits@hotmail.nl | F39: 430 | G39: 360 | H39: 70 | I39: Removed and refunded Solar Roof
A40: 44944 | B40: 44654 | C40: #39370 | D40: Kai Hartmann | E40: kai@familiehartmann.org | F40: 309 | G40: 291 | H40: 18 | I40: Removed and refunded Wall Mount
A41: 44944 | B41: 44869 | C41: #117720 | D41: Lauren Kos | E41: laurenkos@outlook.com | F41: 308.51 | G41: 308.51 | H41: 0 | I41: Removed Suet ball Holder
... A50: 44945 | B50: 44877 | C50: #121362 | D50: TAYLOR SAVAGE | E50: tsavage@exploreusa.com | F50: 373.47 | G50: 323.67 | H50: 49.8 | I50: Removed and refunded Wall Mount, Water fountain, Suet Ball Holder
A51: 44945 | B51: 44882 | C51: #123577 | D51: 44882 | E51: kuentzelalaska@gmail.com | F51: 293 | G51: 143 | H51: 150 | I51: Refunded for compensation.
A52: 44945 | B52: 44934 | C52: #141983 | D52: Janina Storm | E52: stormi1@gmx.net | F52: 62 | G52: 38 | H52: 24 | I52: Removed and refunded 1 Wall Mount.
A53: 44945 | B53: 44860 | C53: #113099 | D53: Lauren Marusich | E53: marusichlauren@gmail.com | F53: 355.94 | G53: 332.56 | H53: 23.38 | I53: Removed and refunded Water Fountain
A54: 44945 | B54: 44602 | C54: #18258 | D54: Rose Mickleson | E54: rosemickleson@live.com | F54: 309 | G54: 291 | H54: 18 | I54: Removed and refunded Fence Mount
A55: 44945 | B55: 44712 | C55: #69114 | D55: Lilien Sugár | E55: sugar.lilien@gmail.com | F55: 469 | G55: 433 | H55: 36 | I55: Removed and refunded Fence Mounts
A56: 44946 | B56: 44459 | C56: #11731KS | D56: Francesco Serianni | E56: seriannif@gmail.com | F56: 279 | G56: 261 | H56: 18 | I56: Removed and refunded Fence Mounts
A57: 44946 | B57: 44876 | C57: #120908 | D57: Alexander Berz | E57: alexanderjberz@gmail.com | F57: 266.38 | G57: 240.94 | H57: 25.44 | I57: removed and refunded Wall Mount
A58: 44948 | B58: 44947 | C58: #144198 | D58: Michele White | E58: mwhite@pvm.org | F58: 584.06 | G58: 584.06 | H58: 0 | I58: changed the solar roof color from blue to yellow
A59: 44949 | B59: 44948 | C59: #144394 | D59: Liz Zipoff | E59: lizzipoff@gmail.com | F59: 394.83 | G59: 319.93 | H59: 74.9 | I59: Removed and refunded Solar Roof
A60: 44949 | B60: 44918 | C60: #137580 | D60: Norbert Hausherr | E60: norbert@hausherr.at | F60: 146 | G60: 76 | H60: 70 | I60: Removed and refunded Solar Roof
A61: 44951 | B61: 44890 | C61: #129696 | D61: Nicole Hawkins | E61: alanicole@swbell.net | F61: 289.05 | G61: 247.91 | H61: 41.14 | I61: Removed and refunded Suet ball Holder and Wall Mount
A62: 44951 | B62: 44888 | C62: #144490 | D62: Barbara Spencer | E62: bspencer6@gmail.com | F62: 425.68 | G62: 349.37 | H62: 76.31 | I62: Removed and refunded Solar Roof
A63: 44951 | B63: 44925 | C63: #139404 | D63: Suann Shoemaker | E63: sshoemail@aol.com | F63: 70.13 | G63: 44.63 | H63: 25.5 | I63: Removed and refunded Wall Mount
... A68: 44957 | B68: 44956 | C68: #145574 | D68: Dolly Chugh | E68: dchugh@stern.nyu.edu | F68: 451.83 | G68: 375.62 | H68: 76.21 | I68: Removed and refunded Solar Roof

Sheet Formulas
A1: Advertising | G1: Business Metrics
C3: FB - US and CA | G3: COGS | H3: Source | J3: 3PL Costs
C4: EUR | D4: USD | G4: Bird Buddy | H4: 70.53 | J4: Handling Fee | K4: 1.5
A5: 44896 | C5: Don't | D5: =IFERROR(__xludf.DUMMYFUNCTION("GOOGLEFINANCE(""CURRENCY:EURUSD"")*C5"),"#VALUE!") -> #VALUE! | G5: Bird Buddy with Solar Roof | H5: 80.08 | J5: Serial Capture | K5: 0.3
A6: 44897 | C6: Don't | D6: =IFERROR(__xludf.DUMMYFUNCTION("GOOGLEFINANCE(""CURRENCY:EURUSD"")*C6"),"#VALUE!") -> #VALUE! | G6: Solar Roof Single | H6: 9.98 | J6: Storage | K6: 0.31
A7: 44898 | C7: Don't | D7: =IFERROR(__xludf.DUMMYFUNCTION("GOOGLEFINANCE(""CURRENCY:EURUSD"")*C7"),"#VALUE!") -> #VALUE! | G7: Wall Mount | H7: 4.93 | J7: Other
A8: 44899 | C8: Don't | D8: =IFERROR(__xludf.DUMMYFUNCTION("GOOGLEFINANCE(""CURRENCY:EURUSD"")*C8"),"#VALUE!") -> #VALUE! | G8: Fence Mount | H8: 6.37 | J8: Source
A9: 44900 | C9: Don't | D9: =IFERROR(__xludf.DUMMYFUNCTION("GOOGLEFINANCE(""CURRENCY:EURUSD"")*C9"),"#VALUE!") -> #VALUE! | G9: Suet Ball Holder | H9: 1.07
A10: 44901 | C10: Don't | D10: =IFERROR(__xludf.DUMMYFUNCTION("GOOGLEFINANCE(""CURRENCY:EURUSD"")*C10"),"#VALUE!") -> #VALUE! | G10: 3-in-1 Nutrition Set | H10: 6.08
A11: 44902 | C11: Don't | D11: =IFERROR(__xludf.DUMMYFUNCTION("GOOGLEFINANCE(""CURRENCY:EURUSD"")*C11"),"#VALUE!") -> #VALUE!
A12: 44903 | C12: Don't | D12: =IFERROR(__xludf.DUMMYFUNCTION("GOOGLEFINANCE(""CURRENCY:EURUSD"")*C12"),"#VALUE!") -> #VALUE! | G12: Bird Buddy Shipping | H12: Source | J12: Add-ons Shipping
A13: 44904 | C13: Don't | D13: =IFERROR(__xludf.DUMMYFUNCTION("GOOGLEFINANCE(""CURRENCY:EURUSD"")*C13"),"#VALUE!") -> #VALUE! | G13: Inbound (NA) | H13: 18.43 | J13: Inbound (NA) | K13: 1.22
A14: 44905 | C14: Don't | D14: =IFERROR(__xludf.DUMMYFUNCTION("GOOGLEFINANCE(""CURRENCY:EURUSD"")*C14"),"#VALUE!") -> #VALUE! | G14: Inbound (Europe) | H14: 4.98 | J14: Inbound (Europe)
A15: 44906 | C15: Don't | D15: =IFERROR(__xludf.DUMMYFUNCTION("GOOGLEFINANCE(""CURRENCY:EURUSD"")*C15"),"#VALUE!") -> #VALUE! | G15: Inbound (ROW) | H15: 10 | J15: Inbound (ROW)
A16: 44907 | C16: Don't | D16: =IFERROR(__xludf.DUMMYFUNCTION("GOOGLEFINANCE(""CURRENCY:EURUSD"")*C16"),"#VALUE!") -> #VALUE! | G16: Outbound (NA) | H16: 11.59 | J16: Outbound (NA)
A17: 44908 | C17: Don't | D17: =IFERROR(__xludf.DUMMYFUNCTION("GOOGLEFINANCE(""CURRENCY:EURUSD"")*C17"),"#VALUE!") -> #VALUE! | G17: Outbound (Europe) | H17: 15 | J17: Outbound (Europe)
A18: 44909 | C18: Don't | D18: =IFERROR(__xludf.DUMMYFUNCTION("GOOGLEFINANCE(""CURRENCY:EURUSD"")*C18"),"#VALUE!") -> #VALUE! | G18: Outbound (ROW) | H18: 20 | J18: Outbound (ROW)
A19: 44910 | C19: Don't | D19: =IFERROR(__xludf.DUMMYFUNCTION("GOOGLEFINANCE(""CURRENCY:EURUSD"")*C19"),"#VALUE!") -> #VALUE!
A20: 44911 | C20: Don't | D20: =IFERROR(__xludf.DUMMYFUNCTION("GOOGLEFINANCE(""CURRENCY:EURUSD"")*C20"),"#VALUE!") -> #VALUE! | G20: Marketing Averages (per unit) | J20: VAT Averages
A21: 44912 | C21: Don't | D21: =IFERROR(__xludf.DUMMYFUNCTION("GOOGLEFINANCE(""CURRENCY:EURUSD"")*C21"),"#VALUE!") -> #VALUE! | G21: COGS | H21: =(H4*1)+(H6*K26)+(H7*K27)+(H8*K28)+(H9*K29)+(H10*K30) -> 79.822945 | J21: Europe | K21: 0.22
A22: 44913 | C22: Don't | D22: =IFERROR(__xludf.DUMMYFUNCTION("GOOGLEFINANCE(""CURRENCY:EURUSD"")*C22"),"#VALUE!") -> #VALUE! | G22: Inbound Shipping | H22: =H13 -> 18.43 | J22: ROW | K22: 0.13
A23: 44914 | C23: Don't | D23: =IFERROR(__xludf.DUMMYFUNCTION("GOOGLEFINANCE(""CURRENCY:EURUSD"")*C23"),"#VALUE!") -> #VALUE! | G23: Outbound Shipping | H23: =H16 -> 11.59 | J23: NA
A24: 44915 | C24: Don't | D24: =IFERROR(__xludf.DUMMYFUNCTION("GOOGLEFINANCE(""CURRENCY:EURUSD"")*C24"),"#VALUE!") -> #VALUE! | G24: Taxes and VAT | H24: 10.89
A25: 44916 | C25: Don't | D25: =IFERROR(__xludf.DUMMYFUNCTION("GOOGLEFINANCE(""CURRENCY:EURUSD"")*C25"),"#VALUE!") -> #VALUE! | G25: China Tax (7.5%) | H25: =H21*0.075 -> 5.9867209 | J25: Attachment Rates
A26: 44917 | C26: Don't | D26: =IFERROR(__xludf.DUMMYFUNCTION("GOOGLEFINANCE(""CURRENCY:EURUSD"")*C26"),"#VALUE!") -> #VALUE! | G26: Duty (3.4%) | H26: =H21*0.034 -> 2.7139801 | J26: Solar Roof | K26: ='Detailed Report'!AG169/'Detailed Report'!AG163 -> 0.33656958
A27: 44918 | C27: Don't | D27: =IFERROR(__xludf.DUMMYFUNCTION("GOOGLEFINANCE(""CURRENCY:EURUSD"")*C27"),"#VALUE!") -> #VALUE! | G27: Processing Fee (2,97%) | H27: =Sales!B48*0.0297 -> 7.0307124 | J27: Wall Mount | K27: ='Detailed Report'!AG165/'Detailed Report'!AG163 -> 0.52191821
A28: 44919 | C28: Don't | D28: =IFERROR(__xludf.DUMMYFUNCTION("GOOGLEFINANCE(""CURRENCY:EURUSD"")*C28"),"#VALUE!") -> #VALUE! | G28: Transaction Fee ($0.36) | H28: =0.36 -> 0.36 | J28: Fence Mount | K28: ='Detailed Report'!AG166/'Detailed Report'!AG163 -> 0.0017652251
A29: 44920 | C29: Don't | D29: =IFERROR(__xludf.DUMMYFUNCTION("GOOGLEFINANCE(""CURRENCY:EURUSD"")*C29"),"#VALUE!") -> #VALUE! | G29: 3PL - Handling Fee | H29: =K4 -> 1.5 | J29: Suet Ball Holder | K29: ='Detailed Report'!AG167/'Detailed Report'!AG163 -> 1.0508973
A30: 44921 | C30: Don't | D30: =IFERROR(__xludf.DUMMYFUNCTION("GOOGLEFINANCE(""CURRENCY:EURUSD"")*C30"),"#VALUE!") -> #VALUE! | G30: 3PL - Serial Capture | H30: =K5 -> 0.3 | J30: Water Fountain | K30: ='Detailed Report'!AG168/'Detailed Report'!AG163 -> 0.36599
A31: 44922 | C31: Don't | D31: =IFERROR(__xludf.DUMMYFUNCTION("GOOGLEFINANCE(""CURRENCY:EURUSD"")*C31"),"#VALUE!") -> #VALUE! | G31: 3PL - Storage Cost | H31: =K6 -> 0.31
A32: 44923 | C32: Don't | D32: =IFERROR(__xludf.DUMMYFUNCTION("GOOGLEFINANCE(""CURRENCY:EURUSD"")*C32"),"#VALUE!") -> #VALUE! | G32: All | H32: =SUM(H21:H30) -> 138.62436
A33: 44924 | C33: Don't | D33: =IFERROR(__xludf.DUMMYFUNCTION("GOOGLEFINANCE(""CURRENCY:EURUSD"")*C33"),"#VALUE!") -> #VALUE!
A34: 44925 | C34: Don't | D34: =IFERROR(__xludf.DUMMYFUNCTION("GOOGLEFINANCE(""CURRENCY:EURUSD"")*C34"),"#VALUE!") -> #VALUE! | G34: Fees | J34: 30 Day Returns
A35: 44926 | C35: Don't | D35: =IFERROR(__xludf.DUMMYFUNCTION("GOOGLEFINANCE(""CURRENCY:EURUSD"")*C35"),"#VALUE!") -> #VALUE! | G35: Processing Fee | H35: 0.0297 | J35: US Shipping | K35: 10
G36: Duty | H36: 0.034 | J36: ROW Shipping | K36: 20
G37: China Tax | H37: 0.075 | J37: Money Return % | K37: 0.8
G38: HMF | H38: 0.00125 | J38: EU Shipping | K38: 20
G39: MPF | H39: 0.003464
G40: Solar Roof China Tax | H40: 0.25
G41: Solar Roof Duty | H41: 0.025

Sheet pivot_do_not_delete_1
I1: HARDWARE QTY
I2: {=IF(A2:A5725="","",BYROW(G2:H5725,LAMBDA(x,SUM(x))))}
I6: 0
I7: 1
I8: 2
I9: 1
I10: 1
I11: 1
I12: 1
I13: 2
I14: 1
I15: 1
I16: 0
I17: 1
... I360: 1

Sheet dtc_return_for_refund_do_not_de
X1: =COLUMN() -> 24 | Y1: {={"Hardware Qty"; IF(A2:A362="","", BYROW(G2:X362, LAMBDA(r, SUM(N(r)))) ) }} -> Hardware Qty | Z1: {={"Order ID"; B2:B362 }} -> Order ID
Z3: #139064
Z4: #141528
Z5: #142811
Y6: 0 | Z6: 21475768BKS
Y7: 1 | Z7: #128/21475770BKS
Y8: 2 | Z8: 21475136BKS
Y9: 1 | Z9: 21475774BKS
Y10: 1 | Z10: 21475940BKS
Y11: 1 | Z11: 21476065BKS
Y12: 1 | Z12: 21476197BKS
Y13: 2 | Z13: 21476213BKS
Y14: 1 | Z14: 21476439BKS
Y15: 1 | Z15: 21476906BKS
Y16: 0 | Z16: 21479142BKS
Y17: 1 | Z17: 21479197BKS
... Y63: 0 | Z63: #11731KS
Y64: 0
Y65: 0 | Z65: #12301KS
Y66: 2 | Z66: #11301KS
Y67: 1 | Z67: #13407KS
Y68: 0 | Z68: #1173 (old webstore)
Y69: 1 | Z69: #15444KS
Y70: 1 | Z70: #16319KS
Y71: 0 | Z71: #143224
Y72: 0 | Z72: #143259
Y73: 1 | Z73: #143712
Y74: 0 | Z74: #18258
Y75: 1 | Z75: #19840
Y76: 1 | Z76: #21886
... Y92: 1 | Z92: 21475923BKS
Y93: 1
Y94: 1 | Z94: #106384
Y95: 0 | Z95: #106510
Y96: 0 | Z96: #106665
Y97: 0 | Z97: #108044
Y98: 1 | Z98: #108590
Y99: 0 | Z99: #108758
Y100: 1 | Z100: #135208
Y101: 1 | Z101: #109153
Y102: 1 | Z102: #109432
Y103: 1 | Z103: #109492
Y104: 0 | Z104: #109706
Y105: 1 | Z105: #110103
Y106: 0 | Z106: #110178
Y107: 0 | Z107: 110348
Y108: 0 | Z108: #111082
Y109: 0 | Z109: #111230
Y110: 1 | Z110: #111945
Y111: 0 | Z111: #112258
Y112: 1 | Z112: #112402
Y113: 0 | Z113: #112573
Y114: 1 | Z114: #112893
Y115: 0 | Z115: #113099
Y116: 1 | Z116: #114029
Y117: 1 | Z117: #114105
Y118: 1 | Z118: #115128
Y119: 1 | Z119: #115628
... Y360: 1 | Z360: #139412

Sheet SupermetricsQueries
A1: Supermetrics Queries
A3: All the queries created by Supermetrics are stored here, each in its own row.
H4: 16406162
A5: On this sheet you can:
A6: 1. Modify the parameters of a query. Any changes will be visible when you run a refresh.
A8: 2. Remove a query by deleting its row | H8: Europe/Paris
A10: 3. Add new queries: type a range address and query parameters, leave the query ID empty. The query will be added when you run a refresh. (Of course, it's much easier to use the sidebar to add new queries.)
A13: Queries are stored with the authentication of the original user that created the query. If you want to transfer a query to the currently active Google Sheets user, delete its query ID from column A and run a refresh. For complete instructions on transferring queries, see https://support.supermetrics.com/support/solutions/articles/19000050074-how-can-i-transfer-queries-from-one-user-to-another-
A16: Don't delete or rename this sheet. If you delete or rename it, your existing queries can no longer be refreshed. Hiding the sheet is OK. Also, don't delete any rows above row 21.
A19: Query ID | D19: Sheet name | E19: Range address | G19: Created | H19: Updated | I19: Last status | J19: Last refresh ID | K19: Results contain sampled data | L19: Execution time (sec) | M19: Object type | N19: Linked chart ID | O19: Data source | Q19: Date range type | R19: Start date | S19: End date | T19: Compare to | U19: Comparison value type | W19: Accounts/views | X19: Metrics | Y19: Dimensions | Z19: Pivot dimensions | AA19: Filters | AB19: Segment ID | AC19: Sort | AD19: Max rows | AE19: Max pivot categories | AF19: Special settings | AG19: Other parameters | AJ19: Result type | AK19: Language/country | AL19: Translate to | AN19: SQL | AO19: Database name | AP19: Range address (static) | AQ19: Report type | AT19: Highlight with colour | AU19: Refresh with user account | AV19: Returned data
A20: paramsID | C20: ssID | D20: sheetName | E20: rangeAddress | G20: created | H20: updated | I20: lastStatus | J20: lastqueryID | K20: sampled | L20: runtime_sec | M20: objType | N20: linkedChartID | O20: dataSource | Q20: dateRangeType | R20: startDateString | S20: endDateString | T20: comp | U20: cvt | W20: profiles | X20: metrics | Y20: dimensions | Z20: sd | AA20: filterArr | AB20: segment | AC20: sort | AD20: maxResults | AE20: maxCategories | AF20: specialSettings | AG20: otherParams | AJ20: sds_result_type | AK20: sds_lang | AL20: sds_tolang | AN20: sql | AO20: db_name | AP20: rangeAddressStatic | AQ20: rt | AR20: scopeMZ | AS20: sortMZ | AT20: condform | AU20: authUser | AV20: metaDataToUser
A21: pxuhRTEmIU93xSgKclyxajD0fCZ6rF | D21: =IFERROR(__xludf.DUMMYFUNCTION("ARRAY_CONSTRAIN(split(CELL(""ADDRESS"",zsupermetrics_pxuhRTEmIU93xSgKclyxajD0fCZ6rF),""!""),1,1)"),"#REF!") -> #REF! | E21: =CELL("ADDRESS",zsupermetrics_pxuhRTEmIU93xSgKclyxajD0fCZ6rF)&":"&address(row(zsupermetrics_pxuhRTEmIU93xSgKclyxajD0fCZ6rF)+rows(zsupermetrics_pxuhRTEmIU93xSgKclyxajD0fCZ6rF)-1,column(zsupermetrics_pxuhRTEmIU93xSgKclyxajD0fCZ6rF)+COLUMNS(zsupermetrics_pxuhRTEmIU93xSgKclyxajD0fCZ6rF)-1) -> #REF! | G21: 44557.697 | H21: 44557.839 | I21: Created successfully | K21: FALSE | L21: 4 | M21: TABLE | O21: SHP | Q21: thismonth | W21: ["gid://shopify/Shop/55807180983`Bird Buddy"] | X21: ["gross_sales","returns","shipping","tax","total_sales","sm_order_count"] | Y21: [] | Z21: ["date"] | AA21: [] | AB21: [] | AD21: 10000 | AE21: 50 | AF21: ["METRICS_IN_ROWS","MULTILEVEL_COL_HEADERS"] | AG21: {} | AP21: Shopify 1'!A1:AB7 | AU21: gid://shopify/Shop/55807180983
