Workbook
Name rdataslayer_d70e473bcafe40a3aa834ce157fb2ba3: 'Business Metrics Canada'!$C$16:$D$17
Name zsupermetrics_xwoIpANxRm908eDp5oKTwQpEI8gvD4: 'Business Metrics US'!$A$5
Name zsupermetrics_ru0GDtbZzDLHQOQtJJ6K08MvUDyyp7: 'OLD Formulas'!$B$5:$B$6
Name zsupermetrics_iNpyVy90bWCI0yUaFQpxOtzWMa6sW4: 'Business Metrics US'!$A$5:$A$12
Name zsupermetrics_DQl8lUbpTRu3fayaJJi7lVfOGKjNU4: 'ECOMMERCE Formulas'!$A$3:$A$4
Name zsupermetrics_NugLlrQxlKiqhxQae8EFpITBm1pLCj: 'Business Metrics Canada'!$B$15:$C$23
Name rdataslayer_4a0f150f4f2f4e4f85c890c75b7a1fa4: 'Business Metrics Canada'!$D$5:$E$12
Name zsupermetrics_BioPyGBzcBsy60UCQmPcTuFReEmghI: 'ECOMMERCE Formulas'!$B$2:$B$3
Name zsupermetrics_refreshAll: SupermetricsQueries!$H$5
Name zsupermetrics_DQl8lUbpTRu3fayaJJi7lVfOGKjNU4: 'Business Metrics Canada'!$A$2:$A$13
Name zsupermetrics_n3GtLgiKpTmd2pYmQNMuq6TPD0qE0b: 'OLD Formulas'!$B$5:$B$6
Name zsupermetrics_9i4W4hgd80uRpQLMeX0eRnESN8gjyv: 'Business Metrics US'!$C$23
Name zsupermetrics_qWp7V908pNEYMtfv8QZvSTeDnBAHOU: 'Business Metrics Canada'!$B$14:$C$23
Name zsupermetrics_refreshAllSilent: SupermetricsQueries!$H$6
Name zsupermetrics_Mgms9p0QzysYvrIhnsKACeVBVxfIEO: 'OLD Formulas'!$A$3:$A$4
Name rdataslayer_4a0f150f4f2f4e4f85c890c75b7a1fa4: 'Business Metrics US'!$D$5:$E$12
Name zsupermetrics_lx4cNai7gT6tH4j08ZRkI21Qlpjioi: 'Business Metrics Canada'!$B$13:$C$23
Name zsupermetrics_Mgms9p0QzysYvrIhnsKACeVBVxfIEO: 'ECOMMERCE Formulas'!$A$2:$A$3
Name zsupermetrics_forceRefresh: SupermetricsQueries!$H$4
Name zsupermetrics_wbYMmT0YL9bAN0yhimW0ziPFnia9Dx: 'OLD Formulas'!$A$3:$A$4
Name zsupermetrics_iNpyVy90bWCI0yUaFQpxOtzWMa6sW4: 'OLD Formulas'!$A$3:$A$4
Name zsupermetrics_xwoIpANxRm908eDp5oKTwQpEI8gvD4: 'Business Metrics Canada'!$A$5
Name zsupermetrics_xwoIpANxRm908eDp5oKTwQpEI8gvD4: #REF!
Name rdataslayer_3753ddf3234e496aa261974a0222e193: 'Business Metrics US'!$H$5:$I$5
Name zsupermetrics_4VkB7ij7WO0JjKBEgvjB2GHjSy2Egm: 'Business Metrics Canada'!$B$13:$C$17
Name zsupermetrics_n3GtLgiKpTmd2pYmQNMuq6TPD0qE0b: 'ECOMMERCE Formulas'!$B$4:$B$5
Name rdataslayer_42b112e4e4be4305bb4c1be75e2dd549: 'ECOMMERCE Formulas'!$B$2:$C$3
Name zsupermetrics_wbYMmT0YL9bAN0yhimW0ziPFnia9Dx: 'Business Metrics Canada'!$A$5:$A$12
Name zsupermetrics_9i4W4hgd80uRpQLMeX0eRnESN8gjyv: 'OLD Formulas'!$C$14
Name zsupermetrics_YsFuuYtr8vOdNXCCPiFJIO38NP4b2T: 'Business Metrics US'!$B$13:$C$23
Name zsupermetrics_5bmwtOpHUbSYmDMeuCPkrxaojTprPP: #REF!
Name rdataslayer_adf57e64065742daa5b4161161b1c3ca: 'Business Metrics Canada'!$B$13:$D$14
Name zsupermetrics_9i4W4hgd80uRpQLMeX0eRnESN8gjyv: 'Business Metrics Canada'!$C$23
Name rdataslayer_3753ddf3234e496aa261974a0222e193: 'ECOMMERCE Formulas'!$H$2:$I$2
Name zsupermetrics_4VkB7ij7WO0JjKBEgvjB2GHjSy2Egm: 'Business Metrics US'!$B$13:$C$17
Name zsupermetrics_SGBxROnInO9rFyh3H7j2Lldx0Bdc5v: #REF!
Name zsupermetrics_pxuhRTEmIU93xSgKclyxajD0fCZ6rF: #REF!
Name zsupermetrics_ru0GDtbZzDLHQOQtJJ6K08MvUDyyp7: 'ECOMMERCE Formulas'!$B$4:$B$5
Name zsupermetrics_qWp7V908pNEYMtfv8QZvSTeDnBAHOU: 'ECOMMERCE Formulas'!$B$5:$C$13
Name zsupermetrics_wbYMmT0YL9bAN0yhimW0ziPFnia9Dx: 'Business Metrics US'!$A$5:$A$12
Name rdataslayer_4a0f150f4f2f4e4f85c890c75b7a1fa4: 'OLD Formulas'!$D$3:$E$4
Name zsupermetrics_iNpyVy90bWCI0yUaFQpxOtzWMa6sW4: 'Business Metrics Canada'!$A$5:$A$12
Name zsupermetrics_HgZqhorObHOtZHuyJjpmyYaEPoYntx: 'OLD Formulas'!$B$5:$B$6
Name zsupermetrics_YsFuuYtr8vOdNXCCPiFJIO38NP4b2T: 'OLD Formulas'!$B$5:$C$14
Name zsupermetrics_DQl8lUbpTRu3fayaJJi7lVfOGKjNU4: 'OLD Formulas'!$A$4:$A$5
Name zsupermetrics_YVuzfmsfdurz7Ldl84Rfns8oka6LsS: #REF!
Name zsupermetrics_4VkB7ij7WO0JjKBEgvjB2GHjSy2Egm: 'OLD Formulas'!$B$5:$C$11
Name zsupermetrics_9i4W4hgd80uRpQLMeX0eRnESN8gjyv: 'ECOMMERCE Formulas'!$C$13
Name zsupermetrics_Mgms9p0QzysYvrIhnsKACeVBVxfIEO: 'Business Metrics US'!$A$5:$A$12
Name zsupermetrics_lx4cNai7gT6tH4j08ZRkI21Qlpjioi: 'OLD Formulas'!$B$5:$C$14
Name zsupermetrics_BioPyGBzcBsy60UCQmPcTuFReEmghI: 'Business Metrics US'!$B$5:$B$12
Name zsupermetrics_qWp7V908pNEYMtfv8QZvSTeDnBAHOU: 'Business Metrics US'!$B$14:$C$23
Name rdataslayer_adf57e64065742daa5b4161161b1c3ca: 'Business Metrics US'!$B$13:$D$14
Name rdataslayer_d70e473bcafe40a3aa834ce157fb2ba3: 'OLD Formulas'!$C$9:$D$10
Name zsupermetrics_NugLlrQxlKiqhxQae8EFpITBm1pLCj: 'ECOMMERCE Formulas'!$B$6:$C$13
Name zsupermetrics_8xojRjNDjo2jWHGDWjFEhflhyIq3Hq: 'OLD Sales'!$K$8:$K$14
Name rdataslayer_42b112e4e4be4305bb4c1be75e2dd549: 'Business Metrics Canada'!$B$5:$C$12
Name rdataslayer_d70e473bcafe40a3aa834ce157fb2ba3: 'Business Metrics US'!$C$16:$D$17
Name rdataslayer_3753ddf3234e496aa261974a0222e193: 'OLD Formulas'!$H$3:$I$3
Name zsupermetrics_BioPyGBzcBsy60UCQmPcTuFReEmghI: 'Business Metrics Canada'!$B$5:$B$12

Sheet DataslayerQueries
A1: Query UUID | B1: Sheet name | C1: Range address | D1: Created | E1: Updated | F1: Last status | G1: Last refresh ID | H1: Results contain sampled data | I1: Execution time (sec) | J1: Object type | K1: Linked chart ID | L1: Data source | M1: Date range type | N1: Start date | O1: End date | P1: Compare to | Q1: Comparison value type | R1: Accounts/views | S1: Metrics | T1: Dimensions | U1: Pivot dimensions | V1: Filters | W1: Segment ID | X1: Segment dim | Y1: Sort | Z1: Max rows | AA1: Max pivot categories | AB1: Special settings | AC1: Other parameters | AD1: Result type | AE1: Language/country | AF1: Translate to | AG1: SQL | AH1: Database name | AI1: Range address (static) | AJ1: Report type | AK1: Highlight with colour | AL1: Refresh with user account | AM1: Returned data | AN1: Sort dimensions | AO1: Created by user account
A2: 42b112e4e4be4305bb4c1be75e2dd549 | B2: =IFERROR(__xludf.DUMMYFUNCTION("ARRAY_CONSTRAIN(split(CELL(""ADDRESS"",rdataslayer_42b112e4e4be4305bb4c1be75e2dd549),""!""),1,1)"),"[OLD] Formulas'") -> [OLD] Formulas' | C2: =IFERROR(__xludf.DUMMYFUNCTION("INDEX(split(CELL(""ADDRESS"",rdataslayer_42b112e4e4be4305bb4c1be75e2dd549),""!""),0,2)&"":""&address(row(rdataslayer_42b112e4e4be4305bb4c1be75e2dd549)+rows(rdataslayer_42b112e4e4be4305bb4c1be75e2dd549)-1,column(rdataslayer_42b112e4e4be4305bb4c1be75e2dd549"&")+COLUMNS(rdataslayer_42b112e4e4be4305bb4c1be75e2dd549)-1)"),"$B$3:$C$4") -> $B$3:$C$4 | D2: 44518.613 | E2: 44520.051 | F2: There is no data for the specified input | I2: 7 | J2: TABLE | L2: facebook | M2: yesterday | R2: [{"profile_id":"","name":"si_Bird buddy Inc_US &amp; CA_BirdBuddy","id":"act_273249767551281","account_name":"","advertiser_id":""}] | S2: [{"id":"spend","name":"Total Cost"}] | T2: [{"id":"date","name":"Date"}] | U2: [] | V2: [] | W2: [] | Y2: [] | Z2: 5 | AA2: 5 | AB2: {} | AC2: {} | AL2: User_Kumalic_Benjamin | AN2: [] | AO2: benjamin@mybirdbuddy.com
A3: 4a0f150f4f2f4e4f85c890c75b7a1fa4 | B3: =IFERROR(__xludf.DUMMYFUNCTION("ARRAY_CONSTRAIN(split(CELL(""ADDRESS"",rdataslayer_4a0f150f4f2f4e4f85c890c75b7a1fa4),""!""),1,1)"),"[OLD] Formulas'") -> [OLD] Formulas' | C3: =IFERROR(__xludf.DUMMYFUNCTION("INDEX(split(CELL(""ADDRESS"",rdataslayer_4a0f150f4f2f4e4f85c890c75b7a1fa4),""!""),0,2)&"":""&address(row(rdataslayer_4a0f150f4f2f4e4f85c890c75b7a1fa4)+rows(rdataslayer_4a0f150f4f2f4e4f85c890c75b7a1fa4)-1,column(rdataslayer_4a0f150f4f2f4e4f85c890c75b7a1fa4"&")+COLUMNS(rdataslayer_4a0f150f4f2f4e4f85c890c75b7a1fa4)-1)"),"$D$3:$E$4") -> $D$3:$E$4 | D3: 44518.615 | E3: 44520.051 | F3: There is no data for the specified input | I3: 7 | J3: TABLE | L3: facebook | M3: yesterday | R3: [{"account_name":"","advertiser_id":"","id":"act_273249767551281","profile_id":"","name":"si_Bird buddy Inc_US &amp; CA_BirdBuddy"}] | S3: [{"id":"spend","name":"Total Cost"}] | T3: [] | U3: [{"id":"date","name":"Date"}] | V3: [] | W3: [] | Y3: [] | Z3: 5 | AA3: 5 | AB3: {} | AC3: {} | AL3: User_Kumalic_Benjamin | AN3: [] | AO3: benjamin@mybirdbuddy.com
A4: adf57e64065742daa5b4161161b1c3ca | B4: =IFERROR(__xludf.DUMMYFUNCTION("ARRAY_CONSTRAIN(split(CELL(""ADDRESS"",rdataslayer_adf57e64065742daa5b4161161b1c3ca),""!""),1,1)"),"[OLD] Formulas'") -> [OLD] Formulas' | C4: =IFERROR(__xludf.DUMMYFUNCTION("INDEX(split(CELL(""ADDRESS"",rdataslayer_adf57e64065742daa5b4161161b1c3ca),""!""),0,2)&"":""&address(row(rdataslayer_adf57e64065742daa5b4161161b1c3ca)+rows(rdataslayer_adf57e64065742daa5b4161161b1c3ca)-1,column(rdataslayer_adf57e64065742daa5b4161161b1c3ca"&")+COLUMNS(rdataslayer_adf57e64065742daa5b4161161b1c3ca)-1)"),"$B$5:$D$6") -> $B$5:$D$6 | D4: 44518.618 | E4: 44520.051 | F4: There is no data for the specified input | I4: 18 | J4: TABLE | L4: facebook | M4: yesterday | R4: [{"name":"si_Bird buddy Inc_US &amp; CA_BirdBuddy","id":"act_273249767551281","profile_id":"","account_name":"","advertiser_id":""}] | S4: [{"id":"spend","name":"Total Cost"},{"id":"cpm","name":"CPM"}] | T4: [{"id":"date","name":"Date"}] | U4: [] | V4: [] | W4: [] | Y4: [] | Z4: 5 | AA4: 5 | AB4: {} | AC4: {} | AL4: User_Kumalic_Benjamin | AN4: [] | AO4: benjamin@mybirdbuddy.com
A5: d70e473bcafe40a3aa834ce157fb2ba3 | B5: =IFERROR(__xludf.DUMMYFUNCTION("ARRAY_CONSTRAIN(split(CELL(""ADDRESS"",rdataslayer_d70e473bcafe40a3aa834ce157fb2ba3),""!""),1,1)"),"[OLD] Formulas'") -> [OLD] Formulas' | C5: =IFERROR(__xludf.DUMMYFUNCTION("INDEX(split(CELL(""ADDRESS"",rdataslayer_d70e473bcafe40a3aa834ce157fb2ba3),""!""),0,2)&"":""&address(row(rdataslayer_d70e473bcafe40a3aa834ce157fb2ba3)+rows(rdataslayer_d70e473bcafe40a3aa834ce157fb2ba3)-1,column(rdataslayer_d70e473bcafe40a3aa834ce157fb2ba3"&")+COLUMNS(rdataslayer_d70e473bcafe40a3aa834ce157fb2ba3)-1)"),"$C$9:$D$10") -> $C$9:$D$10 | D5: 44518.619 | E5: 44520.051 | F5: There is no data for the specified input | I5: 7 | J5: TABLE | L5: facebook | M5: yesterday | R5: [{"advertiser_id":"","name":"si_Bird buddy Inc_US &amp; CA_BirdBuddy","id":"act_273249767551281","account_name":"","profile_id":""}] | S5: [{"id":"spend","name":"Total Cost"}] | T5: [{"id":"date","name":"Date"}] | U5: [] | V5: [] | W5: [] | Y5: [] | Z5: 100 | AA5: 100 | AB5: {} | AC5: {} | AL5: User_Kumalic_Benjamin | AN5: [] | AO5: benjamin@mybirdbuddy.com
A6: 3753ddf3234e496aa261974a0222e193 | B6: =IFERROR(__xludf.DUMMYFUNCTION("ARRAY_CONSTRAIN(split(CELL(""ADDRESS"",rdataslayer_3753ddf3234e496aa261974a0222e193),""!""),1,1)"),"[OLD] Formulas'") -> [OLD] Formulas' | C6: =IFERROR(__xludf.DUMMYFUNCTION("INDEX(split(CELL(""ADDRESS"",rdataslayer_3753ddf3234e496aa261974a0222e193),""!""),0,2)&"":""&address(row(rdataslayer_3753ddf3234e496aa261974a0222e193)+rows(rdataslayer_3753ddf3234e496aa261974a0222e193)-1,column(rdataslayer_3753ddf3234e496aa261974a0222e193"&")+COLUMNS(rdataslayer_3753ddf3234e496aa261974a0222e193)-1)"),"$H$3:$I$3") -> $H$3:$I$3 | D6: 44518.621 | E6: 44520.051 | F6: There is no data for the specified input | I6: 18 | J6: TABLE | L6: facebook | M6: yesterday | R6: [{"profile_id":"","account_name":"","advertiser_id":"","name":"si_Bird buddy Inc_US &amp; CA_BirdBuddy","id":"act_273249767551281"}] | S6: [{"id":"spend","name":"Total Cost"}] | T6: [] | U6: [] | V6: [] | W6: [] | Y6: [] | Z6: 100 | AA6: 100 | AB6: {"exclude_header_row":true} | AC6: {} | AL6: User_Kumalic_Benjamin | AN6: [] | AO6: benjamin@mybirdbuddy.com

Sheet Summary
A1: 45108 | B1: 45108 | C1: 45109 | D1: 45110 | E1: 45111 | F1: 45112 | G1: 45113 | H1: 45114 | I1: 45115 | J1: 45116 | K1: 45117 | L1: 45118 | M1: 45119 | N1: 45120 | O1: 45121 | P1: 45122 | Q1: 45123 | R1: 45124 | S1: 45125 | T1: 45126 | U1: 45127 | V1: 45128 | W1: 45129 | X1: 45130 | Y1: 45131 | Z1: 45132 | AA1: 45133 | AB1: 45134 | AC1: 45135 | AD1: 45136 | AE1: 45137 | AF1: 45138
B2: SAT | C2: SUN | D2: MON | E2: TUE | F2: WED | G2: THU | H2: FRI | I2: SAT | J2: SUN | K2: MON | L2: TUE | M2: WED | N2: THU | O2: FRI | P2: SAT | Q2: SUN | R2: MON | S2: TUE | T2: WED | U2: THU | V2: FRI | W2: SAT | X2: SUN | Y2: MON | Z2: TUE | AA2: WED | AB2: THU | AC2: FRI | AD2: SAT | AE2: SUN | AF2: MON
A3: Weekend Work | B3: Peter | C3: Peter | I3: Peter | J3: Peter | P3: Peco | Q3: Peco | W3: Peco | X3: Peco | AD3: Peter | AE3: Peter
B4: Summer Sale | Z4: Friendship Day
G5: Check comments in this cell | H5: Check comments in this cell | K5: Switch to BB yellow AND blue 10% off | N5: Communication changed from next day shipping to now shipping | R5: Website caching problem / Site down for 8 hours | V5: SBF (Blue) - out of stock | Y5: One page checkout live from 3pm | Z5: Friendship Day starts at 18:00 CET | AC5: SBF (Blue) Back in stock
N6: In-Stock Sale Email | O6: In-Stock Sale Push Notification | R6: In-Stock Sale Follow-up Email | AA6: Switching FB strategy to separate MOF & BOF
A8: DTC Revenue | B8: =sum(B9:B12) -> 45643.43 | C8: =sum(C9:C12) -> 45073.44 | D8: =sum(D9:D12) -> 38928.55 | E8: =sum(E9:E12) -> 42623.92 | F8: =sum(F9:F12) -> 41052.98 | G8: =sum(G9:G12) -> 44139.05 | H8: =sum(H9:H12) -> 46442.05 | I8: =sum(I9:I12) -> 54824.78 | ... AF8: =sum(AF9:AF12) -> 36477.99
A9: - Hardware | B9: 36339.3 | C9: 35421 | D9: 31591.8 | E9: 34100.4 | F9: 33472.26 | G9: 35821.56 | H9: 38210.4 | I9: 43742.46 | J9: 41422.2 | K9: 39284.96 | L9: 40703.3 | M9: 41234.16 | N9: 63104.9 | O9: 56976.1 | P9: 47668.1 | Q9: 49046.66 | R9: 26941 | S9: 48103.1 | T9: 35159.9 | U9: 39792.4 | V9: 36372.6 | W9: 36633.8 | X9: 30906.36 | Y9: 26358.4 | Z9: 27558.89 | AA9: 25640.36 | AB9: 28999.96 | AC9: 26447.16 | AD9: 25269.66 | AE9: 25398.43 | AF9: 29808.2
A10: - Add-ons | B10: 3989.9 | C10: 4273 | D10: 2907 | E10: 3694 | F10: 2903.84 | G10: 3373.34 | H10: 3094 | I10: 4878.34 | J10: 4884.2 | K10: 4714.34 | L10: 3192 | M10: 3191.34 | N10: 6532 | O10: 5318.7 | P10: 5447.5 | Q10: 4774.34 | R10: 2782.5 | S10: 4742 | T10: 3127.5 | U10: 4219 | V10: 3698 | W10: 3777.5 | X10: 4035.84 | Y10: 2513 | Z10: 2883.51 | AA10: 2296.84 | AB10: 2151.84 | AC10: 2146.84 | AD10: 2833.34 | AE10: 2899.17 | AF10: 2702.4
A11: - Taxes | B11: 2609.23 | C11: 2794.44 | D11: 2179.75 | E11: 2264.52 | F11: 2326.88 | G11: 2594.15 | H11: 2622.65 | I11: 3158.98 | J11: 2956.54 | K11: 2753.74 | L11: 2970.74 | M11: 2809.39 | N11: 4513.51 | O11: 4143.08 | P11: 3461.03 | Q11: 3387.67 | R11: 1939.38 | S11: 3498.68 | T11: 2561.62 | U11: 2827.76 | V11: 2666.73 | W11: 2596.99 | X11: 2267.02 | Y11: 1868.93 | Z11: 1873.95 | AA11: 1777.49 | AB11: 1878.56 | AC11: 1670.07 | AD11: 1808.81 | AE11: 1886.17 | AF11: 1967.39
A12: - Shipping | B12: 2705 | C12: 2585 | D12: 2250 | E12: 2565 | F12: 2350 | G12: 2350 | H12: 2515 | I12: 3045 | J12: 2980 | K12: 2970 | L12: 2580 | M12: 2695 | N12: 4355 | O12: 3935 | P12: 3460 | Q12: 3550 | R12: 1955 | S12: 3210 | T12: 2460 | U12: 2680 | V12: 2580 | W12: 2460 | X12: 2305 | Y12: 1840 | Z12: 1875 | AA12: 1745 | AB12: 1820 | AC12: 1945 | AD12: 1750 | AE12: 1850 | AF12: 2000
A13: Total Revenue | B13: =SUM(B8) -> 45643.43 | C13: =SUM(C8) -> 45073.44 | D13: =SUM(D8) -> 38928.55 | E13: =SUM(E8) -> 42623.92 | F13: =SUM(F8) -> 41052.98 | G13: =SUM(G8) -> 44139.05 | H13: =SUM(H8) -> 46442.05 | I13: =SUM(I8) -> 54824.78 | ... AF13: =SUM(AF8) -> 36477.99
A15: DTC Orders | B15: 196 | C15: 181 | D15: 159 | E15: 187 | F15: 174 | G15: 186 | H15: 197 | I15: 239 | J15: 221 | K15: 219 | L15: 210 | M15: 200 | N15: 333 | O15: 294 | P15: 255 | Q15: 256 | R15: 153 | S15: 240 | T15: 177 | U15: 200 | V15: 192 | W15: 191 | X15: 173 | Y15: 130 | Z15: 135 | AA15: 119 | AB15: 130 | AC15: 133 | AD15: 131 | AE15: 132 | AF15: 141
A16: - Hardware (units sold) | B16: 151 | C16: 149 | D16: 134 | E16: 146 | F16: 147 | G16: 154 | H16: 170 | I16: 189 | J16: 178 | K16: 174 | L16: 181 | M16: 182 | N16: 287 | O16: 263 | P16: 217 | Q16: 222 | R16: 122 | S16: 213 | T16: 154 | U16: 171 | V16: 154 | W16: 146 | X16: 125 | Y16: 104 | Z16: 112 | AA16: 106 | AB16: 119 | AC16: 112 | AD16: 103 | AE16: 106 | AF16: 122
A17: - Add-ons (units sold) | B17: 134 | C17: 150 | D17: 94 | E17: 122 | F17: 104 | G17: 109 | H17: 101 | I17: 167 | J17: 160 | K17: 154 | L17: 118 | M17: 114 | N17: 221 | O17: 183 | P17: 197 | Q17: 176 | R17: 93 | S17: 170 | T17: 120 | U17: 145 | V17: 132 | W17: 135 | X17: 138 | Y17: 92 | Z17: 95 | AA17: 83 | AB17: 80 | AC17: 75 | AD17: 90 | AE17: 99 | AF17: 98
A18: Total Orders | B18: =SUM(B15) -> 196 | C18: =SUM(C15) -> 181 | D18: =SUM(D15) -> 159 | E18: =SUM(E15) -> 187 | F18: =SUM(F15) -> 174 | G18: =SUM(G15) -> 186 | H18: =SUM(H15) -> 197 | I18: =SUM(I15) -> 239 | ... AF18: =SUM(AF15) -> 141
A20: Meta Spend EUR | B20: 6812.23 | C20: 8920.58 | D20: 10641.93 | E20: =12542.67 -> 12542.67 | F20: =12229.74 -> 12229.74 | G20: =12058.01 -> 12058.01 | H20: =12244.54 -> 12244.54 | I20: =12582.44 -> 12582.44 | J20: =15187 -> 15187 | K20: =14931.46 -> 14931.46 | L20: =13178.9 -> 13178.9 | M20: 8654.11 | N20: 8564.89 | O20: 11789.45 | P20: 15747.93 | Q20: 18280.91 | R20: 13347.97 | S20: 13146.6 | T20: 14341.92 | U20: 14801 | V20: 14841.48 | W20: 15111.05 | X20: 15762.12 | Y20: 10132.76 | Z20: 8367.72 | AA20: 8856.5 | AB20: 6682.97 | AC20: 6077.66 | AD20: 6139.65 | AE20: 7096.91 | AF20: 7025.38
A21: Currency rate
A22: Meta Spend | B22: =IFERROR(__xludf.DUMMYFUNCTION("GOOGLEFINANCE(""CURRENCY:EURUSD"")*B20"),7810.5282453499985) -> 7810.5282 | C22: =IFERROR(__xludf.DUMMYFUNCTION("GOOGLEFINANCE(""CURRENCY:EURUSD"")*C20"),10227.8463961) -> 10227.846 | D22: =IFERROR(__xludf.DUMMYFUNCTION("GOOGLEFINANCE(""CURRENCY:EURUSD"")*D20"),12201.45163185) -> 12201.452 | E22: =IFERROR(__xludf.DUMMYFUNCTION("GOOGLEFINANCE(""CURRENCY:EURUSD"")*E20"),14380.73557515) -> 14380.736 | F22: =IFERROR(__xludf.DUMMYFUNCTION("GOOGLEFINANCE(""CURRENCY:EURUSD"")*F20"),14021.947248299999) -> 14021.947 | G22: =IFERROR(__xludf.DUMMYFUNCTION("GOOGLEFINANCE(""CURRENCY:EURUSD"")*G20"),13825.05107545) -> 13825.051 | H22: =IFERROR(__xludf.DUMMYFUNCTION("GOOGLEFINANCE(""CURRENCY:EURUSD"")*H20"),14038.9161143) -> 14038.916 | I22: =IFERROR(__xludf.DUMMYFUNCTION("GOOGLEFINANCE(""CURRENCY:EURUSD"")*I20"),14426.3336698) -> 14426.334 | J22: =IFERROR(__xludf.DUMMYFUNCTION("GOOGLEFINANCE(""CURRENCY:EURUSD"")*J20"),17412.578915) -> 17412.579 | K22: =IFERROR(__xludf.DUMMYFUNCTION("GOOGLEFINANCE(""CURRENCY:EURUSD"")*K20"),17119.590805699998) -> 17119.591 | L22: =IFERROR(__xludf.DUMMYFUNCTION("GOOGLEFINANCE(""CURRENCY:EURUSD"")*L20"),15110.201900499998) -> 15110.202 | M22: =IFERROR(__xludf.DUMMYFUNCTION("GOOGLEFINANCE(""CURRENCY:EURUSD"")*M20"),9922.32654995) -> 9922.3265 | N22: =IFERROR(__xludf.DUMMYFUNCTION("GOOGLEFINANCE(""CURRENCY:EURUSD"")*N20"),9820.03180505) -> 9820.0318 | O22: =IFERROR(__xludf.DUMMYFUNCTION("GOOGLEFINANCE(""CURRENCY:EURUSD"")*O20"),13517.13495025) -> 13517.135 | P22: =IFERROR(__xludf.DUMMYFUNCTION("GOOGLEFINANCE(""CURRENCY:EURUSD"")*P20"),18055.71040185) -> 18055.71 | Q22: =IFERROR(__xludf.DUMMYFUNCTION("GOOGLEFINANCE(""CURRENCY:EURUSD"")*Q20"),20959.885955949998) -> 20959.886 | R22: =IFERROR(__xludf.DUMMYFUNCTION("GOOGLEFINANCE(""CURRENCY:EURUSD"")*R20"),15304.048263649998) -> 15304.048 | S22: =IFERROR(__xludf.DUMMYFUNCTION("GOOGLEFINANCE(""CURRENCY:EURUSD"")*S20"),15073.168496999999) -> 15073.168 | T22: =IFERROR(__xludf.DUMMYFUNCTION("GOOGLEFINANCE(""CURRENCY:EURUSD"")*T20"),16443.6566664) -> 16443.657 | U22: =IFERROR(__xludf.DUMMYFUNCTION("GOOGLEFINANCE(""CURRENCY:EURUSD"")*U20"),16970.012544999998) -> 16970.013 | V22: =IFERROR(__xludf.DUMMYFUNCTION("GOOGLEFINANCE(""CURRENCY:EURUSD"")*V20"),17016.4246866) -> 17016.425 | W22: =IFERROR(__xludf.DUMMYFUNCTION("GOOGLEFINANCE(""CURRENCY:EURUSD"")*W20"),17325.49882225) -> 17325.499 | X22: =IFERROR(__xludf.DUMMYFUNCTION("GOOGLEFINANCE(""CURRENCY:EURUSD"")*X20"),18071.9798754) -> 18071.98 | Y22: =IFERROR(__xludf.DUMMYFUNCTION("GOOGLEFINANCE(""CURRENCY:EURUSD"")*Y20"),11617.6653142) -> 11617.665 | Z22: =IFERROR(__xludf.DUMMYFUNCTION("GOOGLEFINANCE(""CURRENCY:EURUSD"")*Z20"),9593.967527399998) -> 9593.9675 | AA22: =IFERROR(__xludf.DUMMYFUNCTION("GOOGLEFINANCE(""CURRENCY:EURUSD"")*AA20"),10154.375792499999) -> 10154.376 | AB22: =IFERROR(__xludf.DUMMYFUNCTION("GOOGLEFINANCE(""CURRENCY:EURUSD"")*AB20"),7662.32583865) -> 7662.3258 | AC22: =IFERROR(__xludf.DUMMYFUNCTION("GOOGLEFINANCE(""CURRENCY:EURUSD"")*AC20"),6968.310684699999) -> 6968.3107 | AD22: =IFERROR(__xludf.DUMMYFUNCTION("GOOGLEFINANCE(""CURRENCY:EURUSD"")*AD20"),7039.385009249999) -> 7039.385 | AE22: =IFERROR(__xludf.DUMMYFUNCTION("GOOGLEFINANCE(""CURRENCY:EURUSD"")*AE20"),8136.92667595) -> 8136.9267 | AF22: =IFERROR(__xludf.DUMMYFUNCTION("GOOGLEFINANCE(""CURRENCY:EURUSD"")*AF20"),8054.9143121) -> 8054.9143
A23: Google Spend | B23: 3497.11 | C23: 3319.47 | D23: 3105.73 | E23: 3164.17 | F23: 2743.6 | G23: 3026.1 | H23: 3130.09 | I23: 3395.52 | J23: 3789.66 | K23: 3114.09 | L23: 3480.59 | M23: 3371.41 | N23: 3892.08 | O23: 4289.26 | P23: 5070.66 | Q23: 5352.91 | R23: 4266.18 | S23: 5866.88 | T23: 3965.4 | U23: 3445.26 | V23: 4409.06 | W23: 6178.13 | X23: 7918.68 | Y23: 7299.64 | Z23: 6903.82 | AA23: 5757.83 | AB23: 6501.5 | AC23: 6675.18 | AD23: 5629.81 | AE23: 3929.84 | AF23: 2235.27
A24: Bing Spend | B24: 244.51 | C24: 259.8 | D24: 259.73 | E24: 251.56 | F24: 260.93 | G24: 252.96 | H24: 250.94 | I24: 249.85 | J24: 248.72 | K24: 245.95 | L24: 250.54 | M24: 247.66 | N24: 82.36 | O24: 0 | P24: 0 | Q24: 0 | R24: 0 | S24: 0 | T24: 130.29 | U24: 247.33 | V24: 241.87 | W24: 267.6 | X24: 247.2 | Y24: 239.41 | Z24: 253.25 | AA24: 281.69 | AB24: 262.48 | AC24: 301.09 | AD24: 283.72 | AE24: 289.28 | AF24: 296.9
A25: TikTok Spend | B25: 0 | C25: 0 | D25: 0 | E25: 0 | F25: 0 | G25: 0 | H25: 0 | I25: 0 | J25: 0 | K25: 0 | L25: 0 | M25: 0 | N25: 0 | O25: 0 | P25: 0 | Q25: 0 | R25: 0 | S25: 0 | T25: 0 | U25: 0 | V25: 0 | W25: 0 | X25: 0 | Y25: 0 | Z25: 0 | AA25: 0 | AB25: 0 | AC25: 0 | AD25: 0 | AE25: 0 | AF25: 0
A26: Nextdoor Spend | B26: 0 | C26: 0 | D26: 0 | E26: 0 | F26: 0 | G26: 0 | H26: 0 | I26: 0 | J26: 0 | K26: 0 | L26: 0 | M26: 0 | N26: 0 | O26: 0 | P26: 0 | Q26: 0 | R26: 0 | S26: 0 | T26: 0 | U26: 0 | V26: 0 | W26: 0 | X26: 0 | Y26: 0 | Z26: 0 | AA26: 0 | AB26: 0 | AC26: 0 | AD26: 0 | AE26: 0 | AF26: 0
A27: Affiliate Fees | B27: 0 | C27: 0 | D27: 0 | E27: 0 | F27: 0 | G27: 0 | H27: 0 | I27: 0 | J27: 0 | K27: 0 | L27: 0 | M27: 0 | N27: 0 | O27: 0 | P27: 0 | Q27: 0 | R27: 0 | S27: 156.16 | T27: 131.12 | U27: 215.27 | V27: 264.81 | W27: 122.94 | X27: 187.67 | Y27: 229.7 | Z27: 157.02 | AA27: 108.61 | AB27: 196.05 | AC27: 49.05 | AD27: 0 | AE27: 136.42 | AF27: 0
A28: Total DTC Spend | B28: =B22+B23+B24+B25+B26+B27 -> 11552.148 | C28: =C22+C23+C24+C25+C26+C27 -> 13807.116 | D28: =D22+D23+D24+D25+D26+D27 -> 15566.912 | E28: =E22+E23+E24+E25+E26+E27 -> 17796.466 | F28: =F22+F23+F24+F25+F26+F27 -> 17026.477 | G28: =G22+G23+G24+G25+G26+G27 -> 17104.111 | H28: =H22+H23+H24+H25+H26+H27 -> 17419.946 | I28: =I22+I23+I24+I25+I26+I27 -> 18071.704 | ... AF28: =AF22+AF23+AF24+AF25+AF26+AF27 -> 10587.084
A29: Total Spend | B29: =SUM(B22:B27) -> 11552.148 | C29: =SUM(C22:C27) -> 13807.116 | D29: =SUM(D22:D27) -> 15566.912 | E29: =SUM(E22:E27) -> 17796.466 | F29: =SUM(F22:F27) -> 17026.477 | G29: =SUM(G22:G27) -> 17104.111 | H29: =SUM(H22:H27) -> 17419.946 | I29: =SUM(I22:I27) -> 18071.704 | ... AF29: =SUM(AF22:AF27) -> 10587.084
A31: Blended ROAS | B31: =B13/B29 -> 3.9510772 | C31: =C13/C29 -> 3.2645079 | D31: =D13/D29 -> 2.500724 | E31: =E13/E29 -> 2.3950778 | F31: =F13/F29 -> 2.4111259 | G31: =G13/G29 -> 2.5806106 | H31: =H13/H29 -> 2.6660272 | I31: =I13/I29 -> 3.0337361 | ... AF31: =AF13/AF29 -> 3.445518
A32: wROAS | B32: =B8/B28 -> 3.9510772 | C32: =C8/C28 -> 3.2645079 | D32: =D8/D28 -> 2.500724 | E32: =E8/E28 -> 2.3950778 | F32: =F8/F28 -> 2.4111259 | G32: =G8/G28 -> 2.5806106 | H32: =H8/H28 -> 2.6660272 | I32: =I8/I28 -> 3.0337361 | ... AF32: =AF8/AF28 -> 3.445518
A34: Blended Spend per Unit | B34: =B29/'DTC - P&L'!B57 -> 76.504293 | C34: =C29/'DTC - P&L'!C57 -> 92.665211 | D34: =D29/'DTC - P&L'!D57 -> 116.17098 | E34: =E29/'DTC - P&L'!E57 -> 121.8936 | F34: =F29/'DTC - P&L'!F57 -> 115.82638 | G34: =G29/'DTC - P&L'!G57 -> 111.06566 | H34: =H29/'DTC - P&L'!H57 -> 102.47027 | I34: =I29/'DTC - P&L'!I57 -> 95.61748 | ... AF34: =AF29/'DTC - P&L'!AF57 -> 86.77938
A35: Web Spend per Unit | B35: =B28/'DTC - P&L'!B57 -> 76.504293 | C35: =C28/'DTC - P&L'!C57 -> 92.665211 | D35: =D28/'DTC - P&L'!D57 -> 116.17098 | E35: =E28/'DTC - P&L'!E57 -> 121.8936 | F35: =F28/'DTC - P&L'!F57 -> 115.82638 | G35: =G28/'DTC - P&L'!G57 -> 111.06566 | H35: =H28/'DTC - P&L'!H57 -> 102.47027 | I35: =I28/'DTC - P&L'!I57 -> 95.61748 | ... AF35: =AF28/'DTC - P&L'!AF57 -> 86.77938
A37: Web CR | B37: 0.0202 | C37: 0.0166 | D37: 0.0147 | E37: 0.0172 | F37: 0.0173 | G37: 0.0182 | H37: 0.018 | I37: 0.0213 | J37: 0.0175 | K37: 0.0189 | L37: 0.0184 | M37: 0.0227 | N37: 0.0302 | O37: 0.0177 | P37: 0.0204 | Q37: 0.0194 | R37: 0.0147 | S37: 0.0229 | T37: 0.0182 | U37: 0.0219 | V37: 0.0189 | W37: 0.0176 | X37: 0.0159 | Y37: 0.015 | Z37: 0.0165 | AA37: 0.0153 | AB37: 0.0168 | AC37: 0.0173 | AD37: 0.0182 | AE37: 0.0179 | AF37: 0.0221
A38: Web AOV | B38: =B8/B15 -> 232.87464 | C38: =C8/C15 -> 249.02453 | D38: =D8/D15 -> 244.83365 | E38: =E8/E15 -> 227.9354 | F38: =F8/F15 -> 235.93667 | G38: =G8/G15 -> 237.30672 | H38: =H8/H15 -> 235.74645 | I38: =I8/I15 -> 229.39238 | ... AF38: =AF8/AF15 -> 258.70915
A39: fAOV | B39: 232.87 | C39: 250.12 | D39: 245.84 | E39: 228.12 | F39: 233.8 | G39: 237.07 | H39: 235.75 | I39: 229.1 | J39: 236.39 | K39: 226.93 | L39: 236.28 | M39: 249.32 | N39: 236.82 | O39: 239.27 | P39: 237.04 | Q39: 239.26 | R39: 224.56 | S39: 249.17 | T39: 251.88 | U39: 247.08 | V39: 238.35 | W39: 239.44 | X39: 231.27 | Y39: 262.63 | Z39: 252.93 | AA39: 267.26 | AB39: 270.84 | AC39: 244.41 | AD39: 249.79 | AE39: 247.92 | AF39: 264.04
A40: rAOV | B40: 0 | C40: 150.77 | D40: 86.4 | E40: 210.85 | F40: 320.38 | G40: 251.65 | H40: 0 | I40: 246.79 | J40: 0 | K40: 235.68 | L40: 64.09 | M40: 282.07 | N40: 177.61 | O40: 267.23 | P40: 156.3 | Q40: 177.77 | R40: 76.55 | S40: 218.32 | T40: 69.85 | U40: 298.57 | V40: 164.13 | W40: 151.25 | X40: 160.39 | Y40: 89.17 | Z40: 275.82 | AA40: 152.47 | AB40: 151.33 | AC40: 145.32 | AD40: 73.05 | AE40: 109.48 | AF40: 113.61
A42: Customers
A43: Returning | B43: 1 | C43: 0.011 | D43: 0.006 | E43: 0.011 | F43: 0.012 | G43: 0.016 | H43: 0 | I43: 0.017 | J43: 0 | K43: 0.014 | L43: 0.005 | M43: 0.01 | N43: 0.018 | O43: 0.004 | P43: 0.028 | Q43: 0.032 | R43: 0.034 | S43: 0.034 | T43: 0.034 | U43: 0.01 | V43: 0.032 | W43: 0.016 | X43: 0.041 | Y43: 0.071 | Z43: 0.015 | AA43: 0.025 | AB43: 0.023 | AC43: 0.015 | AD43: 0.047 | AE43: 0.038 | AF43: 0.036
A44: First-time | B44: =1-B43 -> 0 | C44: =1-C43 -> 0.989 | D44: =1-D43 -> 0.994 | E44: =1-E43 -> 0.989 | F44: =1-F43 -> 0.988 | G44: =1-G43 -> 0.984 | H44: =1-H43 -> 1 | I44: =1-I43 -> 0.983 | ... AF44: =1-AF43 -> 0.964
B46: 45108 | C46: Goal | D46: % of Goal
A47: Revenue | B47: =SUM(B13:AF13) -> 1411507.8 | C47: 1200000 | D47: =B47/C47 -> 1.1762565
A48: Spend | B48: =SUM(B29:AF29) -> 555410.3 | C48: =C47/C49 -> 300000 | D48: =B48/C48 -> 1.8513677
A49: ROAS | B49: =B47/B48 -> 2.5413784 | C49: 4 | D49: =B49/C49 -> 0.6353446
A50: Spend per Unit | B50: =SUM(B29:AF29)/SUM('DTC - P&L'!B57:AF57) -> 113.04912
A51: CR | B51: =IFERROR(__xludf.DUMMYFUNCTION("AVERAGE.WEIGHTED(B37:AF37,B15:AF15)"),0.01917450713800136) -> 0.019174507
A52: AOV | B52: =AVERAGE(B38:AF38) -> 241.08744
A53: fAOV | B53: =IFERROR(__xludf.DUMMYFUNCTION("AVERAGE.WEIGHTED(B39:AF39,B15:AF15)"),241.52070870156356) -> 241.52071
A54: rAOV | B54: =IFERROR(__xludf.DUMMYFUNCTION("AVERAGE.weighted(B40:AF40,B15:AF15)"),162.62774133242692) -> 162.62774
A55: Orders | B55: =SUM(B18:AF18) -> 5884
A56: Units Sold | B56: ='DTC - P&L'!AG57 -> 4913 | C56: 4000 | D56: =B56/C56 -> 1.22825
A57: CAC per Unit | B57: =(SUM(B29:AF29)/B56) -> 113.04912
A58: First-time customers | B58: =IFERROR(__xludf.DUMMYFUNCTION("AVERAGE.WEIGHTED(B44:AF44,B15:AF15)"),0.9469945615227736) -> 0.94699456
A59: Returning customers | B59: =IFERROR(__xludf.DUMMYFUNCTION("AVERAGE.WEIGHTED(B43:AF43,B15:AF15)"),0.053005438477226385) -> 0.053005438

Sheet DTC - P&L
A1: JULY | B1: 45108 | C1: 45109 | D1: 45110 | E1: 45111 | F1: 45112 | G1: 45113 | H1: 45114 | I1: 45115 | J1: 45116 | K1: 45117 | L1: 45118 | M1: 45119 | N1: 45120 | O1: 45121 | P1: 45122 | Q1: 45123 | R1: 45124 | S1: 45125 | T1: 45126 | U1: 45127 | V1: 45128 | W1: 45129 | X1: 45130 | Y1: 45131 | Z1: 45132 | AA1: 45133 | AB1: 45134 | AC1: 45135 | AD1: 45136 | AE1: 45137 | AF1: 45138
A2: DAY | B2: SAT | C2: SUN | D2: MON | E2: TUE | F2: WED | G2: THU | H2: FRI | I2: SAT | J2: SUN | K2: MON | L2: TUE | M2: WED | N2: THU | O2: FRI | P2: SAT | Q2: SUN | R2: MON | S2: TUE | T2: WED | U2: THU | V2: FRI | W2: SAT | X2: SUN | Y2: MON | Z2: TUE | AA2: WED | AB2: THU | AC2: FRI | AD2: SAT | AE2: SUN | AF2: MON
A3: COMMENT
A4: Orders
A5: Meta | B5: 52 | C5: 93 | D5: 64 | E5: 95 | F5: 81 | G5: 102 | H5: 101 | I5: 140 | J5: 113 | K5: 120 | L5: 107 | M5: 80 | N5: 140 | O5: 146 | P5: 114 | Q5: 118 | R5: 66 | S5: 96 | T5: 91 | U5: 104 | V5: 90 | W5: 89 | X5: 93 | Y5: 60 | Z5: 51 | AA5: 37 | AB5: 50 | AC5: 43 | AD5: 39 | AE5: 30 | AF5: 41 | AG5: =SUM(B5:AF5) -> 2646
A6: Google | B6: 78 | C6: 85 | D6: 66 | E6: 73 | F6: 67 | G6: 80 | H6: 86 | I6: 102 | J6: 95 | K6: 111 | L6: 91 | M6: 117 | N6: 94 | O6: 98 | P6: 84 | Q6: 86 | R6: 88 | S6: 130 | T6: 98 | U6: 150 | V6: 153 | W6: 140 | X6: 174 | Y6: 113 | Z6: 116 | AA6: 115 | AB6: 119 | AC6: 139 | AD6: 101 | AE6: 115 | AF6: 72 | AG6: =SUM(B6:AF6) -> 3236
A7: TikTok | B7: 0 | C7: 0 | D7: 0 | E7: 0 | F7: 0 | G7: 0 | H7: 0 | I7: 0 | J7: 0 | K7: 0 | L7: 0 | M7: 0 | N7: 0 | O7: 0 | P7: 0 | Q7: 0 | R7: 0 | S7: 0 | T7: 0 | U7: 0 | V7: 0 | W7: 0 | X7: 0 | Y7: 0 | Z7: 0 | AA7: 0 | AB7: 0 | AC7: 0 | AD7: 0 | AE7: 0 | AF7: 0 | AG7: 0
A8: Bing | B8: 0 | C8: 0 | D8: 0 | E8: 0 | F8: 0 | G8: 0 | H8: 0 | I8: 0 | J8: 0 | K8: 0 | L8: 0 | M8: 0 | N8: 0 | O8: 0 | P8: 0 | Q8: 0 | R8: 0 | S8: 0 | T8: 0 | U8: 0 | V8: 0 | W8: 0 | X8: 0 | Y8: 0 | Z8: 0 | AA8: 0 | AB8: 0 | AC8: 0 | AD8: 0 | AE8: 0 | AF8: 0 | AG8: =SUM(B8:AF8) -> 0
A9: Nextdoor | B9: 0 | C9: 0 | D9: 0 | E9: 0 | F9: 0 | G9: 0 | H9: 0 | I9: 0 | J9: 0 | K9: 0 | L9: 0 | M9: 0 | N9: 0 | O9: 0 | P9: 0 | Q9: 0 | R9: 0 | S9: 0 | T9: 0 | U9: 0 | V9: 0 | W9: 0 | X9: 0 | Y9: 0 | Z9: 0 | AA9: 0 | AB9: 0 | AC9: 0 | AD9: 0 | AE9: 0 | AF9: 0 | AG9: =SUM(B9:AF9) -> 0
A10: Affiliates (Refersion) | B10: 0 | C10: 0 | D10: 0 | E10: 0 | F10: 0 | G10: 0 | H10: 0 | I10: 0 | J10: 0 | K10: 0 | L10: 0 | M10: 0 | N10: 0 | O10: 0 | P10: 0 | Q10: 0 | R10: 0 | S10: 4 | T10: 3 | U10: 3 | V10: 4 | W10: 2 | X10: 3 | Y10: 5 | Z10: 3 | AA10: 2 | AB10: 3 | AC10: 1 | AD10: 0 | AE10: 4 | AF10: 0 | AG10: 37
A11: Email | B11: 4 | C11: 6 | D11: 3 | E11: 2 | F11: 1 | G11: 1 | H11: 0 | I11: 1 | J11: 2 | K11: 3 | L11: 1 | M11: 2 | N11: 94 | O11: 76 | P11: 25 | Q11: 17 | R11: 29 | S11: 38 | T11: 2 | U11: 4 | V11: 3 | W11: 2 | X11: 6 | Y11: 2 | Z11: 1 | AA11: 0 | AB11: 4 | AC11: 4 | AD11: 1 | AE11: 4 | AF11: 4 | AG11: =SUM(B11:AF11) -> 342
A12: All | B12: =SUM(B5:B11) -> 134 | C12: =SUM(C5:C11) -> 184 | D12: =SUM(D5:D11) -> 133 | E12: =SUM(E5:E11) -> 170 | F12: =SUM(F5:F11) -> 149 | G12: =SUM(G5:G11) -> 183 | H12: =SUM(H5:H11) -> 187 | I12: =SUM(I5:I11) -> 243 | ... AF12: =SUM(AF5:AF11) -> 117 | AG12: =SUM(B12:AF12) -> 6261
A14: Revenue | B14: 12675.01 | C14: 24381.02 | D14: 15128.23 | E14: 21258.9 | F14: 19092.71 | G14: 22290.99 | H14: 22384.22 | I14: 31413.49 | J14: 26123.96 | K14: 27325.69 | L14: 23733.94 | M14: 18438.07 | N14: 33573.93 | O14: 33415.06 | P14: 24031.07 | Q14: 25557.35 | R14: 13441.3 | S14: 21801.24 | T14: 20575.78 | U14: 25635.85 | V14: 19910.12 | W14: 21315.94 | X14: 20426.44 | Y14: 13358.97 | Z14: 12504.83 | AA14: 8226.96 | AB14: 12250.88 | AC14: 9252.93 | AD14: 9205.01 | AE14: 6970.93 | AF14: 10140.6
A15: Meta | B15: =IFERROR(__xludf.DUMMYFUNCTION("GOOGLEFINANCE(""CURRENCY:EURUSD"")*B14"),14532.46934045) -> 14532.469 | C15: =IFERROR(__xludf.DUMMYFUNCTION("GOOGLEFINANCE(""CURRENCY:EURUSD"")*C14"),27953.9365759) -> 27953.937 | D15: =IFERROR(__xludf.DUMMYFUNCTION("GOOGLEFINANCE(""CURRENCY:EURUSD"")*D14"),17345.19646535) -> 17345.196 | E15: =IFERROR(__xludf.DUMMYFUNCTION("GOOGLEFINANCE(""CURRENCY:EURUSD"")*E14"),24374.2855005) -> 24374.286 | F15: =IFERROR(__xludf.DUMMYFUNCTION("GOOGLEFINANCE(""CURRENCY:EURUSD"")*F14"),21890.65118695) -> 21890.651 | G15: =IFERROR(__xludf.DUMMYFUNCTION("GOOGLEFINANCE(""CURRENCY:EURUSD"")*G14"),25557.62312955) -> 25557.623 | H15: =IFERROR(__xludf.DUMMYFUNCTION("GOOGLEFINANCE(""CURRENCY:EURUSD"")*H14"),25664.5155199) -> 25664.516 | I15: =IFERROR(__xludf.DUMMYFUNCTION("GOOGLEFINANCE(""CURRENCY:EURUSD"")*I14"),36016.979892049996) -> 36016.98 | J15: =IFERROR(__xludf.DUMMYFUNCTION("GOOGLEFINANCE(""CURRENCY:EURUSD"")*J14"),29952.295718199995) -> 29952.296 | K15: =IFERROR(__xludf.DUMMYFUNCTION("GOOGLEFINANCE(""CURRENCY:EURUSD"")*K14"),31330.133241049996) -> 31330.133 | L15: =IFERROR(__xludf.DUMMYFUNCTION("GOOGLEFINANCE(""CURRENCY:EURUSD"")*L14"),27212.030237299998) -> 27212.03 | M15: =IFERROR(__xludf.DUMMYFUNCTION("GOOGLEFINANCE(""CURRENCY:EURUSD"")*M14"),21140.07696815) -> 21140.077 | N15: =IFERROR(__xludf.DUMMYFUNCTION("GOOGLEFINANCE(""CURRENCY:EURUSD"")*N14"),38494.02157185) -> 38494.022 | O15: =IFERROR(__xludf.DUMMYFUNCTION("GOOGLEFINANCE(""CURRENCY:EURUSD"")*O14"),38311.8699677) -> 38311.87 | P15: =IFERROR(__xludf.DUMMYFUNCTION("GOOGLEFINANCE(""CURRENCY:EURUSD"")*P14"),27552.703153149996) -> 27552.703 | Q15: =IFERROR(__xludf.DUMMYFUNCTION("GOOGLEFINANCE(""CURRENCY:EURUSD"")*Q14"),29302.651855749995) -> 29302.652 | R15: =IFERROR(__xludf.DUMMYFUNCTION("GOOGLEFINANCE(""CURRENCY:EURUSD"")*R14"),15411.055308499997) -> 15411.055 | S15: =IFERROR(__xludf.DUMMYFUNCTION("GOOGLEFINANCE(""CURRENCY:EURUSD"")*S14"),24996.1027158) -> 24996.103 | T15: =IFERROR(__xludf.DUMMYFUNCTION("GOOGLEFINANCE(""CURRENCY:EURUSD"")*T14"),23591.0576801) -> 23591.058 | U15: =IFERROR(__xludf.DUMMYFUNCTION("GOOGLEFINANCE(""CURRENCY:EURUSD"")*U14"),29392.655638249995) -> 29392.656 | V15: =IFERROR(__xludf.DUMMYFUNCTION("GOOGLEFINANCE(""CURRENCY:EURUSD"")*V14"),22827.848535399997) -> 22827.849 | W15: =IFERROR(__xludf.DUMMYFUNCTION("GOOGLEFINANCE(""CURRENCY:EURUSD"")*W14"),24439.684427299995) -> 24439.684 | X15: =IFERROR(__xludf.DUMMYFUNCTION("GOOGLEFINANCE(""CURRENCY:EURUSD"")*X14"),23419.8326498) -> 23419.833 | Y15: =IFERROR(__xludf.DUMMYFUNCTION("GOOGLEFINANCE(""CURRENCY:EURUSD"")*Y14"),15316.660258649998) -> 15316.66 | Z15: =IFERROR(__xludf.DUMMYFUNCTION("GOOGLEFINANCE(""CURRENCY:EURUSD"")*Z14"),14337.35031235) -> 14337.35 | AA15: =IFERROR(__xludf.DUMMYFUNCTION("GOOGLEFINANCE(""CURRENCY:EURUSD"")*AA14"),9432.579853199999) -> 9432.5799 | AB15: =IFERROR(__xludf.DUMMYFUNCTION("GOOGLEFINANCE(""CURRENCY:EURUSD"")*AB14"),14046.185209599998) -> 14046.185 | AC15: =IFERROR(__xludf.DUMMYFUNCTION("GOOGLEFINANCE(""CURRENCY:EURUSD"")*AC14"),10608.90062685) -> 10608.901 | AD15: =IFERROR(__xludf.DUMMYFUNCTION("GOOGLEFINANCE(""CURRENCY:EURUSD"")*AD14"),10553.95819045) -> 10553.958 | AE15: =IFERROR(__xludf.DUMMYFUNCTION("GOOGLEFINANCE(""CURRENCY:EURUSD"")*AE14"),7992.48493685) -> 7992.4849 | AF15: =IFERROR(__xludf.DUMMYFUNCTION("GOOGLEFINANCE(""CURRENCY:EURUSD"")*AF14"),11626.654226999999) -> 11626.654 | AG15: =SUM(B15:AF15) -> 694624.45
A16: Google | B16: 17677.42 | C16: 19491.64 | D16: 16155.61 | E16: 16190.97 | F16: 14253.45 | G16: 18950.64 | H16: 17552.74 | I16: 21202.65 | J16: 22383.36 | K16: 24365.38 | L16: 21103.84 | M16: 27826.14 | N16: 21588.42 | O16: 22876.85 | P16: 18232.01 | Q16: 19035.3 | R16: 19745.03 | S16: 29990.59 | T16: 25696.34 | U16: 35243.03 | V16: 35780.89 | W16: 30440.01 | X16: 41113.74 | Y16: 29308.52 | Z16: 31396.99 | AA16: 28641.3 | AB16: 29733.18 | AC16: 34539.75 | AD16: 24300.69 | AE16: 28836.64 | AF16: 16758.04 | AG16: =SUM(B16:AF16) -> 760411.16
A17: TikTok | B17: 0 | C17: 0 | D17: 0 | E17: 0 | F17: 0 | G17: 0 | H17: 0 | I17: 0 | J17: 0 | K17: 0 | L17: 0 | M17: 0 | N17: 0 | O17: 0 | P17: 0 | Q17: 0 | R17: 0 | S17: 0 | T17: 0 | U17: 0 | V17: 0 | W17: 0 | X17: 0 | Y17: 0 | Z17: 0 | AA17: 0 | AB17: 0 | AC17: 0 | AD17: 0 | AE17: 0 | AF17: 0 | AG17: 0
A18: Bing | B18: 0 | C18: 0 | D18: 0 | E18: 0 | F18: 0 | G18: 0 | H18: 0 | I18: 0 | J18: 0 | K18: 0 | L18: 0 | M18: 0 | N18: 0 | O18: 0 | P18: 0 | Q18: 0 | R18: 0 | S18: 0 | T18: 0 | U18: 0 | V18: 0 | W18: 0 | X18: 0 | Y18: 0 | Z18: 0 | AA18: 0 | AB18: 0 | AC18: 0 | AD18: 0 | AE18: 0 | AF18: 0 | AG18: =SUM(B18:AF18) -> 0
A19: Nextdoor | B19: 0 | C19: 0 | D19: 0 | E19: 0 | F19: 0 | G19: 0 | H19: 0 | I19: 0 | J19: 0 | K19: 0 | L19: 0 | M19: 0 | N19: 0 | O19: 0 | P19: 0 | Q19: 0 | R19: 0 | S19: 0 | T19: 0 | U19: 0 | V19: 0 | W19: 0 | X19: 0 | Y19: 0 | Z19: 0 | AA19: 0 | AB19: 0 | AC19: 0 | AD19: 0 | AE19: 0 | AF19: 0 | AG19: =SUM(B19:AF19) -> 0
A20: Affiliates (Refersion) | B20: 0 | C20: 0 | D20: 0 | E20: 0 | F20: 0 | G20: 0 | H20: 0 | I20: 0 | J20: 0 | K20: 0 | L20: 0 | M20: 0 | N20: 0 | O20: 0 | P20: 0 | Q20: 0 | R20: 0 | S20: 780.81 | T20: 541.79 | U20: 925.45 | V20: 1184.57 | W20: 531.95 | X20: 938.33 | Y20: 1148.46 | Z20: 785.1 | AA20: 543.06 | AB20: 908.25 | AC20: 245.27 | AD20: 0 | AE20: 682.12 | AF20: 0 | AG20: 9215.16
A21: Email | B21: 815.46 | C21: 1741.69 | D21: 729.81 | E21: 509.74 | F21: 204.7 | G21: 266.63 | H21: 0 | I21: 30.74 | J21: 425.14 | K21: 543.68 | L21: 63 | M21: 348.11 | N21: 21081.09 | O21: 19052.55 | P21: 6531.28 | Q21: 3775.83 | R21: 6515.75 | S21: 7669.01 | T21: 238.68 | U21: 825.72 | V21: 465.42 | W21: 309.71 | X21: 1222.39 | Y21: 351.79 | Z21: 24.84 | AA21: 0 | AB21: 1047.31 | AC21: 576.18 | AD21: 124.94 | AE21: 646.42 | AF21: 1000.93 | AG21: =SUM(B21:AF21) -> 77138.54
A22: All | B22: =SUM(B15:B21) -> 33025.349 | C22: =SUM(C15:C21) -> 49187.267 | D22: =SUM(D15:D21) -> 34230.616 | E22: =SUM(E15:E21) -> 41074.995 | F22: =SUM(F15:F21) -> 36348.801 | G22: =SUM(G15:G21) -> 44774.893 | H22: =SUM(H15:H21) -> 43217.256 | I22: =SUM(I15:I21) -> 57250.37 | ... AF22: =SUM(AF15:AF21) -> 29385.624 | AG22: =SUM(B22:AF22) -> 1541389.3
A24: Media Cost
A25: Meta | B25: =Summary!B22 -> 7810.5282 | C25: =Summary!C22 -> 10227.846 | D25: =Summary!D22 -> 12201.452 | E25: =Summary!E22 -> 14380.736 | F25: =Summary!F22 -> 14021.947 | G25: =Summary!G22 -> 13825.051 | H25: =Summary!H22 -> 14038.916 | I25: =Summary!I22 -> 14426.334 | ... AF25: =Summary!AF22 -> 8054.9143 | AG25: =SUM(B25:AF25) -> 408282.93
A26: Google | B26: =Summary!B23 -> 3497.11 | C26: =Summary!C23 -> 3319.47 | D26: =Summary!D23 -> 3105.73 | E26: =Summary!E23 -> 3164.17 | F26: =Summary!F23 -> 2743.6 | G26: =Summary!G23 -> 3026.1 | H26: =Summary!H23 -> 3130.09 | I26: =Summary!I23 -> 3395.52 | ... AF26: =Summary!AF23 -> 2235.27 | AG26: =SUM(B26:AF26) -> 138724.93
A27: TikTok | B27: =Summary!B25 -> 0 | C27: =Summary!C25 -> 0 | D27: =Summary!D25 -> 0 | E27: =Summary!E25 -> 0 | F27: =Summary!F25 -> 0 | G27: =Summary!G25 -> 0 | H27: =Summary!H25 -> 0 | I27: =Summary!I25 -> 0 | ... AF27: =Summary!AF25 -> 0 | AG27: =SUM(B27:AF27) -> 0
A28: Bing | B28: =Summary!B24 -> 244.51 | C28: =Summary!C24 -> 259.8 | D28: =Summary!D24 -> 259.73 | E28: =Summary!E24 -> 251.56 | F28: =Summary!F24 -> 260.93 | G28: =Summary!G24 -> 252.96 | H28: =Summary!H24 -> 250.94 | I28: =Summary!I24 -> 249.85 | ... AF28: =Summary!AF24 -> 296.9 | AG28: =SUM(B28:AF28) -> 6447.62
A29: Nextdoor | B29: =Summary!B26 -> 0 | C29: =Summary!C26 -> 0 | D29: =Summary!D26 -> 0 | E29: =Summary!E26 -> 0 | F29: =Summary!F26 -> 0 | G29: =Summary!G26 -> 0 | H29: =Summary!H26 -> 0 | I29: =Summary!I26 -> 0 | ... AF29: =Summary!AF26 -> 0 | AG29: =SUM(B29:AF29) -> 0
A30: Affiliate Fee (20%) | B30: =Summary!B27 -> 0 | C30: =Summary!C27 -> 0 | D30: =Summary!D27 -> 0 | E30: =Summary!E27 -> 0 | F30: =Summary!F27 -> 0 | G30: =Summary!G27 -> 0 | H30: =Summary!H27 -> 0 | I30: =Summary!I27 -> 0 | ... AF30: =Summary!AF27 -> 0 | AG30: =SUM(B30:AF30) -> 1954.82
A31: All | B31: =SUM(B25:B30) -> 11552.148 | C31: =SUM(C25:C30) -> 13807.116 | D31: =SUM(D25:D30) -> 15566.912 | E31: =SUM(E25:E30) -> 17796.466 | F31: =SUM(F25:F30) -> 17026.477 | G31: =SUM(G25:G30) -> 17104.111 | H31: =SUM(H25:H30) -> 17419.946 | I31: =SUM(I25:I30) -> 18071.704 | ... AF31: =SUM(AF25:AF30) -> 10587.084 | AG31: =SUM(B31:AF31) -> 555410.3
A36: Revenue
A37: Revenue Woocommerce (Platform) | B37: =Summary!B8 -> 45643.43 | C37: =Summary!C8 -> 45073.44 | D37: =Summary!D8 -> 38928.55 | E37: =Summary!E8 -> 42623.92 | F37: =Summary!F8 -> 41052.98 | G37: =Summary!G8 -> 44139.05 | H37: =Summary!H8 -> 46442.05 | I37: =Summary!I8 -> 54824.78 | ... AF37: =Summary!AF8 -> 36477.99 | AG37: =sum(B37:AF37) -> 1411507.8
A38: SUM | B38: =SUM(B37) -> 45643.43 | C38: =SUM(C37) -> 45073.44 | D38: =SUM(D37) -> 38928.55 | E38: =SUM(E37) -> 42623.92 | F38: =SUM(F37) -> 41052.98 | G38: =SUM(G37) -> 44139.05 | H38: =SUM(H37) -> 46442.05 | I38: =SUM(I37) -> 54824.78 | ... AF38: =SUM(AF37) -> 36477.99 | AG38: =sum(B38:AF38) -> 1411507.8
A40: Orders
A41: Orders Woocommerce (Platform) | B41: =Summary!B15 -> 196 | C41: =Summary!C15 -> 181 | D41: =Summary!D15 -> 159 | E41: =Summary!E15 -> 187 | F41: =Summary!F15 -> 174 | G41: =Summary!G15 -> 186 | H41: =Summary!H15 -> 197 | I41: =Summary!I15 -> 239 | ... AF41: =Summary!AF15 -> 141 | AG41: =sum(B41:AF41) -> 5884
A42: SUM | B42: =SUM(B41) -> 196 | C42: =SUM(C41) -> 181 | D42: =SUM(D41) -> 159 | E42: =SUM(E41) -> 187 | F42: =SUM(F41) -> 174 | G42: =SUM(G41) -> 186 | H42: =SUM(H41) -> 197 | I42: =SUM(I41) -> 239 | ... AF42: =SUM(AF41) -> 141 | AG42: =sum(B42:AF42) -> 5884
A44: Breakdown
A45: - Hardware | B45: =Summary!B9 -> 36339.3 | C45: =Summary!C9 -> 35421 | D45: =Summary!D9 -> 31591.8 | E45: =Summary!E9 -> 34100.4 | F45: =Summary!F9 -> 33472.26 | G45: =Summary!G9 -> 35821.56 | H45: =Summary!H9 -> 38210.4 | I45: =Summary!I9 -> 43742.46 | ... AF45: =Summary!AF9 -> 29808.2 | AG45: =SUM(B45:AF45) -> 1137529.8
A46: - Add-ons | B46: =Summary!B10 -> 3989.9 | C46: =Summary!C10 -> 4273 | D46: =Summary!D10 -> 2907 | E46: =Summary!E10 -> 3694 | F46: =Summary!F10 -> 2903.84 | G46: =Summary!G10 -> 3373.34 | H46: =Summary!H10 -> 3094 | I46: =Summary!I10 -> 4878.34 | ... AF46: =Summary!AF10 -> 2702.4 | AG46: =SUM(B46:AF46) -> 113977.12
A47: - Merch
A48: - Taxes | B48: =Summary!B11 -> 2609.23 | C48: =Summary!C11 -> 2794.44 | D48: =Summary!D11 -> 2179.75 | E48: =Summary!E11 -> 2264.52 | F48: =Summary!F11 -> 2326.88 | G48: =Summary!G11 -> 2594.15 | H48: =Summary!H11 -> 2622.65 | I48: =Summary!I11 -> 3158.98 | ... AF48: =Summary!AF11 -> 1967.39 | AG48: =SUM(B48:AF48) -> 80635.85
A49: - Shipping | B49: =Summary!B12 -> 2705 | C49: =Summary!C12 -> 2585 | D49: =Summary!D12 -> 2250 | E49: =Summary!E12 -> 2565 | F49: =Summary!F12 -> 2350 | G49: =Summary!G12 -> 2350 | H49: =Summary!H12 -> 2515 | I49: =Summary!I12 -> 3045 | ... AF49: =Summary!AF12 -> 2000 | AG49: =SUM(B49:AF49) -> 79365
A50: SUM | B50: =SUM(B45:B49) -> 45643.43 | C50: =SUM(C45:C49) -> 45073.44 | D50: =SUM(D45:D49) -> 38928.55 | E50: =SUM(E45:E49) -> 42623.92 | F50: =SUM(F45:F49) -> 41052.98 | G50: =SUM(G45:G49) -> 44139.05 | H50: =SUM(H45:H49) -> 46442.05 | I50: =SUM(I45:I49) -> 54824.78 | ... AF50: =SUM(AF45:AF49) -> 36477.99 | AG50: =SUM(B50:AF50) -> 1411507.8
A52: Units Sold (Gross)
A53: SKU 1 - Blue | B53: 16 | C53: 29 | D53: 13 | E53: 10 | F53: 15 | G53: 24 | H53: 16 | I53: 21 | J53: 13 | K53: 25 | L53: 40 | M53: 49 | N53: 49 | O53: 59 | P53: 50 | Q53: 66 | R53: 21 | S53: 42 | T53: 32 | U53: 38 | V53: 24 | W53: 0 | X53: 0 | Y53: 0 | Z53: 0 | AA53: 0 | AB53: 0 | AC53: 11 | AD53: 3 | AE53: 17 | AF53: 9 | AG53: =sum(B53:AF53) -> 692
A54: SKU 2 - Yellow | B54: 30 | C54: 28 | D54: 32 | E54: 30 | F54: 36 | G54: 24 | H54: 48 | I54: 34 | J54: 39 | K54: 39 | L54: 16 | M54: 9 | N54: 13 | O54: 13 | P54: 14 | Q54: 7 | R54: 11 | S54: 16 | T54: 12 | U54: 9 | V54: 24 | W54: 30 | X54: 29 | Y54: 20 | Z54: 26 | AA54: 26 | AB54: 35 | AC54: 25 | AD54: 14 | AE54: 13 | AF54: 19 | AG54: =sum(B54:AF54) -> 721
A55: SKU 3 - Blue w/ Solar | B55: 57 | C55: 51 | D55: 44 | E55: 46 | F55: 41 | G55: 42 | H55: 50 | I55: 58 | J55: 54 | K55: 70 | L55: 104 | M55: 96 | N55: 173 | O55: 136 | P55: 120 | Q55: 125 | R55: 64 | S55: 117 | T55: 89 | U55: 94 | V55: 84 | W55: 92 | X55: 76 | Y55: 65 | Z55: 67 | AA55: 63 | AB55: 69 | AC55: 66 | AD55: 67 | AE55: 59 | AF55: 72 | AG55: =sum(B55:AF55) -> 2411
A56: SKU 4 - Yellow w/ Solar | B56: 48 | C56: 41 | D56: 45 | E56: 60 | F56: 55 | G56: 64 | H56: 56 | I56: 76 | J56: 72 | K56: 40 | L56: 21 | M56: 28 | N56: 52 | O56: 55 | P56: 33 | Q56: 24 | R56: 26 | S56: 38 | T56: 21 | U56: 30 | V56: 22 | W56: 24 | X56: 20 | Y56: 19 | Z56: 19 | AA56: 17 | AB56: 15 | AC56: 10 | AD56: 19 | AE56: 17 | AF56: 22 | AG56: =sum(B56:AF56) -> 1089
A57: SUM (SKU 1 - SKU 4) | B57: =SUM(B53:B56) -> 151 | C57: =SUM(C53:C56) -> 149 | D57: =SUM(D53:D56) -> 134 | E57: =SUM(E53:E56) -> 146 | F57: =SUM(F53:F56) -> 147 | G57: =SUM(G53:G56) -> 154 | H57: =SUM(H53:H56) -> 170 | I57: =SUM(I53:I56) -> 189 | ... AF57: =SUM(AF53:AF56) -> 122 | AG57: =sum(B57:AF57) -> 4913
A59: Wall Mount | B59: 53 | C59: 52 | D59: 32 | E59: 37 | F59: 44 | G59: 43 | H59: 48 | I59: 71 | J59: 72 | K59: 62 | L59: 56 | M59: 46 | N59: 84 | O59: 69 | P59: 86 | Q59: 82 | R59: 34 | S59: 79 | T59: 47 | U59: 59 | V59: 50 | W59: 62 | X59: 56 | Y59: 37 | Z59: 42 | AA59: 27 | AB59: 41 | AC59: 32 | AD59: 41 | AE59: 37 | AF59: 48 | AG59: =sum(B59:AF59) -> 1629
A60: Suet Ball Holder | B60: 26 | C60: 37 | D60: 22 | E60: 28 | F60: 24 | G60: 19 | H60: 16 | I60: 33 | J60: 25 | K60: 29 | L60: 24 | M60: 26 | N60: 47 | O60: 40 | P60: 40 | Q60: 39 | R60: 24 | S60: 36 | T60: 33 | U60: 32 | V60: 27 | W60: 27 | X60: 26 | Y60: 24 | Z60: 19 | AA60: 21 | AB60: 14 | AC60: 15 | AD60: 18 | AE60: 23 | AF60: 19 | AG60: =sum(B60:AF60) -> 833
A61: 3-in-1 Nutrition Set - Blue | B61: 26 | C61: 31 | D61: 13 | E61: 24 | F61: 15 | G61: 14 | H61: 11 | I61: 22 | J61: 27 | K61: 23 | L61: 21 | M61: 23 | N61: 41 | O61: 41 | P61: 38 | Q61: 30 | R61: 13 | S61: 28 | T61: 23 | U61: 23 | V61: 30 | W61: 17 | X61: 28 | Y61: 13 | Z61: 15 | AA61: 15 | AB61: 11 | AC61: 13 | AD61: 8 | AE61: 19 | AF61: 12 | AG61: =sum(B61:AF61) -> 668
A62: 3-in-1 Nutrition Set - Yellow | B62: 10 | C62: 12 | D62: 9 | E62: 10 | F62: 8 | G62: 14 | H62: 8 | I62: 17 | J62: 11 | K62: 13 | L62: 5 | M62: 5 | N62: 14 | O62: 8 | P62: 11 | Q62: 8 | R62: 5 | S62: 7 | T62: 7 | U62: 10 | V62: 9 | W62: 12 | X62: 8 | Y62: 7 | Z62: 2 | AA62: 9 | AB62: 4 | AC62: 4 | AD62: 3 | AE62: 4 | AF62: 7 | AG62: =sum(B62:AF62) -> 261
A63: Solar Roof Single - Blue | B63: 12 | C63: 12 | D63: 14 | E63: 19 | F63: 9 | G63: 17 | H63: 12 | I63: 16 | J63: 21 | K63: 21 | L63: 8 | M63: 9 | N63: 32 | O63: 20 | P63: 14 | Q63: 11 | R63: 14 | S63: 15 | T63: 8 | U63: 16 | V63: 11 | W63: 13 | X63: 15 | Y63: 8 | Z63: 13 | AA63: 8 | AB63: 8 | AC63: 8 | AD63: 17 | AE63: 11 | AF63: 9 | AG63: =sum(B63:AF63) -> 421
A64: Solar Roof Single - Yellow | B64: 7 | C64: 6 | D64: 4 | E64: 4 | F64: 4 | G64: 2 | H64: 6 | I64: 8 | J64: 4 | K64: 6 | L64: 4 | M64: 5 | N64: 3 | O64: 5 | P64: 8 | Q64: 6 | R64: 3 | S64: 5 | T64: 2 | U64: 5 | V64: 5 | W64: 4 | X64: 5 | Y64: 3 | Z64: 4 | AA64: 3 | AB64: 2 | AC64: 3 | AD64: 3 | AE64: 5 | AF64: 3 | AG64: =sum(B64:AF64) -> 137
A65: Perch Extender - Blue | B65: 0 | C65: 0 | D65: 0 | E65: 0 | F65: 0 | G65: 0 | H65: 0 | I65: 0 | J65: 0 | K65: 0 | L65: 0 | M65: 0 | N65: 0 | O65: 0 | P65: 0 | Q65: 0 | R65: 0 | S65: 0 | T65: 0 | U65: 0 | V65: 0 | W65: 0 | X65: 0 | Y65: 0 | Z65: 0 | AA65: 0 | AB65: 0 | AC65: 0 | AD65: 0 | AE65: 0 | AF65: 0 | AG65: =sum(B65:AF65) -> 0
A66: Perch Extender - Yellow | B66: 0 | C66: 0 | D66: 0 | E66: 0 | F66: 0 | G66: 0 | H66: 0 | I66: 0 | J66: 0 | K66: 0 | L66: 0 | M66: 0 | N66: 0 | O66: 0 | P66: 0 | Q66: 0 | R66: 0 | S66: 0 | T66: 0 | U66: 0 | V66: 0 | W66: 0 | X66: 0 | Y66: 0 | Z66: 0 | AA66: 0 | AB66: 0 | AC66: 0 | AD66: 0 | AE66: 0 | AF66: 0 | AG66: =sum(B66:AF66) -> 0
A67: SUM (Add-ons) | B67: =SUM(B59:B66) -> 134 | C67: =SUM(C59:C66) -> 150 | D67: =SUM(D59:D66) -> 94 | E67: =SUM(E59:E66) -> 122 | F67: =SUM(F59:F66) -> 104 | G67: =SUM(G59:G66) -> 109 | H67: =SUM(H59:H66) -> 101 | I67: =SUM(I59:I66) -> 167 | ... AF67: =SUM(AF59:AF66) -> 98 | AG67: =sum(B67:AF67) -> 3949
A69: Merch Units Sold (Gross)
A70: Merch Units
A72: First-time Customers
A73: SKU 1 - Blue | B73: =B53-B90 -> 16 | C73: =C53-C90 -> 29 | D73: =D53-D90 -> 13 | E73: =E53-E90 -> 10 | F73: =F53-F90 -> 15 | G73: =G53-G90 -> 23 | H73: =H53-H90 -> 16 | I73: =I53-I90 -> 21 | ... AF73: =AF53-AF90 -> 9 | AG73: =sum(B73:AF73) -> 687
A74: SKU 2 - Yellow | B74: =B54-B91 -> 30 | C74: =C54-C91 -> 27 | D74: =D54-D91 -> 32 | E74: =E54-E91 -> 30 | F74: =F54-F91 -> 36 | G74: =G54-G91 -> 23 | H74: =H54-H91 -> 48 | I74: =I54-I91 -> 34 | ... AF74: =AF54-AF91 -> 17 | AG74: =sum(B74:AF74) -> 708
A75: SKU 3 - Blue w/ Solar | B75: =B55-B92 -> 57 | C75: =C55-C92 -> 51 | D75: =D55-D92 -> 44 | E75: =E55-E92 -> 46 | F75: =F55-F92 -> 40 | G75: =G55-G92 -> 42 | H75: =H55-H92 -> 50 | I75: =I55-I92 -> 56 | ... AF75: =AF55-AF92 -> 72 | AG75: =sum(B75:AF75) -> 2390
A76: SKU 4 - Yellow w/ Solar | B76: =B56-B93 -> 48 | C76: =C56-C93 -> 41 | D76: =D56-D93 -> 45 | E76: =E56-E93 -> 59 | F76: =F56-F93 -> 54 | G76: =G56-G93 -> 63 | H76: =H56-H93 -> 56 | I76: =I56-I93 -> 75 | ... AF76: =AF56-AF93 -> 22 | AG76: =sum(B76:AF76) -> 1073
A77: SUM (SKU 1 - SKU 4) | B77: =SUM(B73:B76) -> 151 | C77: =SUM(C73:C76) -> 148 | D77: =SUM(D73:D76) -> 134 | E77: =SUM(E73:E76) -> 145 | F77: =SUM(F73:F76) -> 145 | G77: =SUM(G73:G76) -> 151 | H77: =SUM(H73:H76) -> 170 | I77: =SUM(I73:I76) -> 186 | ... AF77: =SUM(AF73:AF76) -> 120 | AG77: =sum(B77:AF77) -> 4858
A79: Wall Mount | B79: =B59-B96 -> 53 | C79: =C59-C96 -> 52 | D79: =D59-D96 -> 32 | E79: =E59-E96 -> 36 | F79: =F59-F96 -> 43 | G79: =G59-G96 -> 42 | H79: =H59-H96 -> 48 | I79: =I59-I96 -> 70 | ... AF79: =AF59-AF96 -> 44 | AG79: =sum(B79:AF79) -> 1592
A80: Suet Ball Holder | B80: =B60-B97 -> 26 | C80: =C60-C97 -> 37 | D80: =D60-D97 -> 22 | E80: =E60-E97 -> 27 | F80: =F60-F97 -> 23 | G80: =G60-G97 -> 19 | H80: =H60-H97 -> 16 | I80: =I60-I97 -> 33 | ... AF80: =AF60-AF97 -> 19 | AG80: =sum(B80:AF80) -> 811
A81: 3-in-1 Nutrition Set - Blue | B81: =B61-B98 -> 26 | C81: =C61-C98 -> 31 | D81: =D61-D98 -> 13 | E81: =E61-E98 -> 24 | F81: =F61-F98 -> 14 | G81: =G61-G98 -> 14 | H81: =H61-H98 -> 11 | I81: =I61-I98 -> 22 | ... AF81: =AF61-AF98 -> 12 | AG81: =sum(B81:AF81) -> 657
A82: 3-in-1 Nutrition Set - Yellow | B82: =B62-B99 -> 10 | C82: =C62-C99 -> 12 | D82: =D62-D99 -> 9 | E82: =E62-E99 -> 9 | F82: =F62-F99 -> 8 | G82: =G62-G99 -> 13 | H82: =H62-H99 -> 8 | I82: =I62-I99 -> 17 | ... AF82: =AF62-AF99 -> 7 | AG82: =sum(B82:AF82) -> 249
A83: Solar Roof Single - Blue | B83: =B63-B100 -> 12 | C83: =C63-C100 -> 11 | D83: =D63-D100 -> 13 | E83: =E63-E100 -> 18 | F83: =F63-F100 -> 9 | G83: =G63-G100 -> 17 | H83: =H63-H100 -> 12 | I83: =I63-I100 -> 15 | ... AF83: =AF63-AF100 -> 9 | AG83: =sum(B83:AF83) -> 404
A84: Solar Roof Single - Yellow | B84: =B64-B101 -> 7 | C84: =C64-C101 -> 6 | D84: =D64-D101 -> 4 | E84: =E64-E101 -> 4 | F84: =F64-F101 -> 4 | G84: =G64-G101 -> 2 | H84: =H64-H101 -> 6 | I84: =I64-I101 -> 8 | ... AF84: =AF64-AF101 -> 3 | AG84: =sum(B84:AF84) -> 134
A85: Perch Extender - Blue | B85: =B65-B102 -> 0 | C85: =C65-C102 -> 0 | D85: =D65-D102 -> 0 | E85: =E65-E102 -> 0 | F85: =F65-F102 -> 0 | G85: =G65-G102 -> 0 | H85: =H65-H102 -> 0 | I85: =I65-I102 -> 0 | ... AF85: =AF65-AF102 -> 0 | AG85: =sum(B85:AF85) -> 0
A86: Perch Extender - Yellow | B86: =B66-B103 -> 0 | C86: =C66-C103 -> 0 | D86: =D66-D103 -> 0 | E86: =E66-E103 -> 0 | F86: =F66-F103 -> 0 | G86: =G66-G103 -> 0 | H86: =H66-H103 -> 0 | I86: =I66-I103 -> 0 | ... AF86: =AF66-AF103 -> 0 | AG86: =sum(B86:AF86) -> 0
A87: SUM (Add-ons) | B87: =SUM(B79:B86) -> 134 | C87: =SUM(C79:C86) -> 149 | D87: =SUM(D79:D86) -> 93 | E87: =SUM(E79:E86) -> 118 | F87: =SUM(F79:F86) -> 101 | G87: =SUM(G79:G86) -> 107 | H87: =SUM(H79:H86) -> 101 | I87: =SUM(I79:I86) -> 165 | ... AF87: =SUM(AF79:AF86) -> 94 | AG87: =sum(B87:AF87) -> 3847
A89: Returning Customers
A90: SKU 1 - Blue | B90: 0 | C90: 0 | D90: 0 | E90: 0 | F90: 0 | G90: 1 | H90: 0 | I90: 0 | J90: 0 | K90: 0 | L90: 0 | M90: 0 | N90: 1 | O90: 0 | P90: 1 | Q90: 0 | R90: 1 | S90: 1 | T90: 0 | U90: 0 | V90: 0 | W90: 0 | X90: 0 | Y90: 0 | Z90: 0 | AA90: 0 | AB90: 0 | AC90: 0 | AD90: 0 | AE90: 0 | AF90: 0 | AG90: =sum(B90:AF90) -> 5
A91: SKU 2 - Yellow | B91: 0 | C91: 1 | D91: 0 | E91: 0 | F91: 0 | G91: 1 | H91: 0 | I91: 0 | J91: 0 | K91: 2 | L91: 0 | M91: 0 | N91: 1 | O91: 0 | P91: 0 | Q91: 0 | R91: 0 | S91: 0 | T91: 0 | U91: 0 | V91: 1 | W91: 0 | X91: 1 | Y91: 0 | Z91: 1 | AA91: 0 | AB91: 0 | AC91: 2 | AD91: 1 | AE91: 0 | AF91: 2 | AG91: =sum(B91:AF91) -> 13
A92: SKU 3 - Blue w/ Solar | B92: 0 | C92: 0 | D92: 0 | E92: 0 | F92: 1 | G92: 0 | H92: 0 | I92: 2 | J92: 0 | K92: 1 | L92: 0 | M92: 1 | N92: 1 | O92: 0 | P92: 2 | Q92: 4 | R92: 0 | S92: 1 | T92: 0 | U92: 2 | V92: 1 | W92: 0 | X92: 1 | Y92: 1 | Z92: 0 | AA92: 1 | AB92: 1 | AC92: 0 | AD92: 0 | AE92: 1 | AF92: 0 | AG92: =sum(B92:AF92) -> 21
A93: SKU 4 - Yellow w/ Solar | B93: 0 | C93: 0 | D93: 0 | E93: 1 | F93: 1 | G93: 1 | H93: 0 | I93: 1 | J93: 0 | K93: 0 | L93: 0 | M93: 1 | N93: 1 | O93: 1 | P93: 1 | Q93: 0 | R93: 0 | S93: 4 | T93: 0 | U93: 0 | V93: 1 | W93: 1 | X93: 1 | Y93: 0 | Z93: 1 | AA93: 0 | AB93: 0 | AC93: 0 | AD93: 0 | AE93: 0 | AF93: 0 | AG93: =sum(B93:AF93) -> 16
A94: SUM (SKU 1 - SKU 4) | B94: =SUM(B90:B93) -> 0 | C94: =SUM(C90:C93) -> 1 | D94: =SUM(D90:D93) -> 0 | E94: =SUM(E90:E93) -> 1 | F94: =SUM(F90:F93) -> 2 | G94: =SUM(G90:G93) -> 3 | H94: =SUM(H90:H93) -> 0 | I94: =SUM(I90:I93) -> 3 | ... AF94: =SUM(AF90:AF93) -> 2 | AG94: =sum(B94:AF94) -> 55
A96: Wall Mount | B96: 0 | C96: 0 | D96: 0 | E96: 1 | F96: 1 | G96: 1 | H96: 0 | I96: 1 | J96: 0 | K96: 0 | L96: 0 | M96: 1 | N96: 0 | O96: 0 | P96: 2 | Q96: 4 | R96: 3 | S96: 1 | T96: 3 | U96: 0 | V96: 2 | W96: 1 | X96: 3 | Y96: 5 | Z96: 1 | AA96: 0 | AB96: 2 | AC96: 0 | AD96: 0 | AE96: 1 | AF96: 4 | AG96: =sum(B96:AF96) -> 37
A97: Suet Ball Holder | B97: 0 | C97: 0 | D97: 0 | E97: 1 | F97: 1 | G97: 0 | H97: 0 | I97: 0 | J97: 0 | K97: 0 | L97: 0 | M97: 0 | N97: 3 | O97: 0 | P97: 1 | Q97: 3 | R97: 0 | S97: 3 | T97: 4 | U97: 0 | V97: 0 | W97: 0 | X97: 0 | Y97: 4 | Z97: 0 | AA97: 0 | AB97: 0 | AC97: 0 | AD97: 0 | AE97: 2 | AF97: 0 | AG97: =sum(B97:AF97) -> 22
A98: 3-in-1 Nutrition Set - Blue | B98: 0 | C98: 0 | D98: 0 | E98: 0 | F98: 1 | G98: 0 | H98: 0 | I98: 0 | J98: 0 | K98: 0 | L98: 0 | M98: 0 | N98: 1 | O98: 0 | P98: 1 | Q98: 2 | R98: 0 | S98: 0 | T98: 2 | U98: 0 | V98: 1 | W98: 0 | X98: 0 | Y98: 1 | Z98: 0 | AA98: 0 | AB98: 0 | AC98: 1 | AD98: 1 | AE98: 0 | AF98: 0 | AG98: =sum(B98:AF98) -> 11
A99: 3-in-1 Nutrition Set - Yellow | B99: 0 | C99: 0 | D99: 0 | E99: 1 | F99: 0 | G99: 1 | H99: 0 | I99: 0 | J99: 0 | K99: 0 | L99: 0 | M99: 0 | N99: 1 | O99: 0 | P99: 1 | Q99: 2 | R99: 0 | S99: 1 | T99: 3 | U99: 0 | V99: 0 | W99: 1 | X99: 0 | Y99: 1 | Z99: 0 | AA99: 0 | AB99: 0 | AC99: 0 | AD99: 0 | AE99: 0 | AF99: 0 | AG99: =sum(B99:AF99) -> 12
A100: Solar Roof Single - Blue | B100: 0 | C100: 1 | D100: 1 | E100: 1 | F100: 0 | G100: 0 | H100: 0 | I100: 1 | J100: 0 | K100: 0 | L100: 1 | M100: 0 | N100: 0 | O100: 0 | P100: 0 | Q100: 0 | R100: 1 | S100: 0 | T100: 1 | U100: 0 | V100: 1 | W100: 1 | X100: 3 | Y100: 2 | Z100: 0 | AA100: 2 | AB100: 0 | AC100: 0 | AD100: 0 | AE100: 1 | AF100: 0 | AG100: =sum(B100:AF100) -> 17
A101: Solar Roof Single - Yellow | B101: 0 | C101: 0 | D101: 0 | E101: 0 | F101: 0 | G101: 0 | H101: 0 | I101: 0 | J101: 0 | K101: 0 | L101: 0 | M101: 0 | N101: 0 | O101: 0 | P101: 1 | Q101: 0 | R101: 0 | S101: 0 | T101: 0 | U101: 0 | V101: 0 | W101: 0 | X101: 0 | Y101: 0 | Z101: 0 | AA101: 0 | AB101: 1 | AC101: 0 | AD101: 0 | AE101: 1 | AF101: 0 | AG101: =sum(B101:AF101) -> 3
A102: Perch Extender - Blue | B102: 0 | C102: 0 | D102: 0 | E102: 0 | F102: 0 | G102: 0 | H102: 0 | I102: 0 | J102: 0 | K102: 0 | L102: 0 | M102: 0 | N102: 0 | O102: 0 | P102: 0 | Q102: 0 | R102: 0 | S102: 0 | T102: 0 | U102: 0 | V102: 0 | W102: 0 | X102: 0 | Y102: 0 | Z102: 0 | AA102: 0 | AB102: 0 | AC102: 0 | AD102: 0 | AE102: 0 | AF102: 0 | AG102: =sum(B102:AF102) -> 0
A103: Perch Extender - Yellow | B103: 0 | C103: 0 | D103: 0 | E103: 0 | F103: 0 | G103: 0 | H103: 0 | I103: 0 | J103: 0 | K103: 0 | L103: 0 | M103: 0 | N103: 0 | O103: 0 | P103: 0 | Q103: 0 | R103: 0 | S103: 0 | T103: 0 | U103: 0 | V103: 0 | W103: 0 | X103: 0 | Y103: 0 | Z103: 0 | AA103: 0 | AB103: 0 | AC103: 0 | AD103: 0 | AE103: 0 | AF103: 0 | AG103: =sum(B103:AF103) -> 0
A104: SUM (Add-ons) | B104: =SUM(B96:B103) -> 0 | C104: =SUM(C96:C103) -> 1 | D104: =SUM(D96:D103) -> 1 | E104: =SUM(E96:E103) -> 4 | F104: =SUM(F96:F103) -> 3 | G104: =SUM(G96:G103) -> 2 | H104: =SUM(H96:H103) -> 0 | I104: =SUM(I96:I103) -> 2 | ... AF104: =SUM(AF96:AF103) -> 4 | AG104: =sum(B104:AF104) -> 102
A106: Units Sold (Net)
A107: SKU 1 - Blue | B107: =B53-(B200+B205+B246+B296+B305) -> 16 | C107: =C53-(C200+C205+C246+C296+C305) -> 29 | D107: =D53-(D200+D205+D246+D296+D305) -> 12 | E107: =E53-(E200+E205+E246+E296+E305) -> 9 | F107: =F53-(F200+F205+F246+F296+F305) -> 12 | G107: =G53-(G200+G205+G246+G296+G305) -> 24 | H107: =H53-(H200+H205+H246+H296+H305) -> 15 | I107: =I53-(I200+I205+I246+I296+I305) -> 21 | ... AF107: =AF53-(AF200+AF205+AF246+AF296+AF305) -> -1 | AG107: =sum(B107:AF107) -> 550
A108: SKU 2 - Yellow | B108: =B54-(B201+B206+B247+B297+B306) -> 30 | C108: =C54-(C201+C206+C247+C297+C306) -> 28 | D108: =D54-(D201+D206+D247+D297+D306) -> 32 | E108: =E54-(E201+E206+E247+E297+E306) -> 30 | F108: =F54-(F201+F206+F247+F297+F306) -> 36 | G108: =G54-(G201+G206+G247+G297+G306) -> 24 | H108: =H54-(H201+H206+H247+H297+H306) -> 48 | I108: =I54-(I201+I206+I247+I297+I306) -> 34 | ... AF108: =AF54-(AF201+AF206+AF247+AF297+AF306) -> 18 | AG108: =sum(B108:AF108) -> 675
A109: SKU 3 - Blue w/ Solar | B109: =B55-(B202+B207+B248+B298+B307) -> 57 | C109: =C55-(C202+C207+C248+C298+C307) -> 51 | D109: =D55-(D202+D207+D248+D298+D307) -> 44 | E109: =E55-(E202+E207+E248+E298+E307) -> 46 | F109: =F55-(F202+F207+F248+F298+F307) -> 38 | G109: =G55-(G202+G207+G248+G298+G307) -> 40 | H109: =H55-(H202+H207+H248+H298+H307) -> 50 | I109: =I55-(I202+I207+I248+I298+I307) -> 58 | ... AF109: =AF55-(AF202+AF207+AF248+AF298+AF307) -> 64 | AG109: =sum(B109:AF109) -> 2280
A110: SKU 4 - Yellow w/ Solar | B110: =B56-(B203+B208+B249+B299+B308) -> 48 | C110: =C56-(C203+C208+C249+C299+C308) -> 41 | D110: =D56-(D203+D208+D249+D299+D308) -> 45 | E110: =E56-(E203+E208+E249+E299+E308) -> 60 | F110: =F56-(F203+F208+F249+F299+F308) -> 55 | G110: =G56-(G203+G208+G249+G299+G308) -> 64 | H110: =H56-(H203+H208+H249+H299+H308) -> 56 | I110: =I56-(I203+I208+I249+I299+I308) -> 76 | ... AF110: =AF56-(AF203+AF208+AF249+AF299+AF308) -> 22 | AG110: =sum(B110:AF110) -> 1065
A111: SUM (SKU 1 - SKU 4) | B111: =SUM(B107:B110) -> 151 | C111: =SUM(C107:C110) -> 149 | D111: =SUM(D107:D110) -> 133 | E111: =SUM(E107:E110) -> 145 | F111: =SUM(F107:F110) -> 141 | G111: =SUM(G107:G110) -> 152 | H111: =SUM(H107:H110) -> 169 | I111: =SUM(I107:I110) -> 189 | ... AF111: =SUM(AF107:AF110) -> 103 | AG111: =sum(B111:AF111) -> 4570
A113: Wall Mount | B113: =B59-(B213+B224+B259+B317+B328) -> 53 | C113: =C59-(C213+C224+C259+C317+C328) -> 52 | D113: =D59-(D213+D224+D259+D317+D328) -> 32 | E113: =E59-(E213+E224+E259+E317+E328) -> 37 | F113: =F59-(F213+F224+F259+F317+F328) -> 41 | G113: =G59-(G213+G224+G259+G317+G328) -> 42 | H113: =H59-(H213+H224+H259+H317+H328) -> 48 | I113: =I59-(I213+I224+I259+I317+I328) -> 71 | ... AF113: =AF59-(AF213+AF224+AF259+AF317+AF328) -> 31 | AG113: =sum(B113:AF113) -> 1478
A114: Suet Ball Holder | B114: =B60-(B214+B225+B260+B318+B329) -> 26 | C114: =C60-(C214+C225+C260+C318+C329) -> 37 | D114: =D60-(D214+D225+D260+D318+D329) -> 22 | E114: =E60-(E214+E225+E260+E318+E329) -> 28 | F114: =F60-(F214+F225+F260+F318+F329) -> 23 | G114: =G60-(G214+G225+G260+G318+G329) -> 19 | H114: =H60-(H214+H225+H260+H318+H329) -> 16 | I114: =I60-(I214+I225+I260+I318+I329) -> 33 | ... AF114: =AF60-(AF214+AF225+AF260+AF318+AF329) -> 14 | AG114: =sum(B114:AF114) -> 704
A115: 3-in-1 Nutrition Set - Blue | B115: =B61-(B215+B226+B261+B319+B330) -> 26 | C115: =C61-(C215+C226+C261+C319+C330) -> 31 | D115: =D61-(D215+D226+D261+D319+D330) -> 13 | E115: =E61-(E215+E226+E261+E319+E330) -> 24 | F115: =F61-(F215+F226+F261+F319+F330) -> 14 | G115: =G61-(G215+G226+G261+G319+G330) -> 14 | H115: =H61-(H215+H226+H261+H319+H330) -> 11 | I115: =I61-(I215+I226+I261+I319+I330) -> 22 | ... AF115: =AF61-(AF215+AF226+AF261+AF319+AF330) -> 8 | AG115: =sum(B115:AF115) -> 615
A116: 3-in-1 Nutrition Set - Yellow | B116: =B62-(B216+B227+B262+B320+B331) -> 10 | C116: =C62-(C216+C227+C262+C320+C331) -> 12 | D116: =D62-(D216+D227+D262+D320+D331) -> 9 | E116: =E62-(E216+E227+E262+E320+E331) -> 10 | F116: =F62-(F216+F227+F262+F320+F331) -> 8 | G116: =G62-(G216+G227+G262+G320+G331) -> 14 | H116: =H62-(H216+H227+H262+H320+H331) -> 8 | I116: =I62-(I216+I227+I262+I320+I331) -> 17 | ... AF116: =AF62-(AF216+AF227+AF262+AF320+AF331) -> 7 | AG116: =sum(B116:AF116) -> 261
A117: Solar Roof Single - Blue | B117: =B63-(B217+B228+B263+B321+B332) -> 12 | C117: =C63-(C217+C228+C263+C321+C332) -> 12 | D117: =D63-(D217+D228+D263+D321+D332) -> 14 | E117: =E63-(E217+E228+E263+E321+E332) -> 19 | F117: =F63-(F217+F228+F263+F321+F332) -> 7 | G117: =G63-(G217+G228+G263+G321+G332) -> 16 | H117: =H63-(H217+H228+H263+H321+H332) -> 12 | I117: =I63-(I217+I228+I263+I321+I332) -> 16 | ... AF117: =AF63-(AF217+AF228+AF263+AF321+AF332) -> 5 | AG117: =sum(B117:AF117) -> 369
...

Sheet DATA - P&L
B1: Business Metrics
A2: Source | B2: COGS | E2: Attachment Rates | H2: Marketing Averages (per first-time order) | K2: Fees | N2: VAT Averages | Q2: 30 Day Returns | T2: Digital Market Places & B2B
B3: Bird Buddy | C3: 86.9 | D3: 86.9 | E3: Solar Roof | F3: =(('DTC - P&L'!AG83+'DTC - P&L'!AG84)/'DTC - P&L'!AG77) -> 0.11074516 | H3: COGS | I3: =(C3*F9)+(C4*F8)+(C5*F3)+(C6*F4)+(C7*F5)+(C8*F6)+(C9*F7)+(C10*F10) -> 99.26282 | J3: =(D3*F9)+(D4*F8)+(D5*F3)+(D6*F4)+(D7*F5)+(D8*F6)+(D9*F7) -> 99.26282 | K3: Stripe Processing Fee | L3: 0.029 | N3: Europe | O3: 0.22 | Q3: US Shipping | R3: 15 | T3: Average % tax | U3: 0.0614 | V3: Source
B4: Bird Buddy with Solar Roof | C4: 97.61 | D4: 97.61 | E4: Wall Mount | F4: =('DTC - P&L'!AG79/'DTC - P&L'!AG77) -> 0.32770688 | H4: Inbound Shipping | I4: =C38+('DTC - P&L'!AG87/'DTC - P&L'!AG77)*D38 -> 13.076362 | K4: Duty | L4: 0.034 | N4: ROW | O4: 0.13 | Q4: EU Shipping | R4: 40
B5: Solar Roof Single | C5: 13.44 | D5: 13.44 | E5: Fence Mount | F5: 0 | H5: Outbound Shipping | I5: =C34+('DTC - P&L'!AG87/'DTC - P&L'!AG77)*D34 -> 16.814081 | K5: China Tax | L5: 0.075 | N5: NA | Q5: ROW Shipping | R5: 20
B6: Wall Mount | C6: 5.49 | D6: 5.49 | E6: Suet Ball Holder | F6: =('DTC - P&L'!AG80)/'DTC - P&L'!AG77 -> 0.16694113 | H6: Taxes and VAT | I6: 16.81 | K6: HMF | L6: 0.00125 | Q6: Money Return | R6: 1
B7: Fence Mount | C7: 6.37 | E7: 3-in-1 | F7: =('DTC - P&L'!AG81+'DTC - P&L'!AG82)/'DTC - P&L'!AG77 -> 0.1864965 | H7: China Tax (7.5%) | I7: 0 | K7: MPF | L7: 0.003464
B8: Suet Ball Holder | C8: 1.19 | D8: 1.19 | E8: Bird Buddy w/ Solar | F8: =('DTC - P&L'!AG75+'DTC - P&L'!AG76)/'DTC - P&L'!AG77 -> 0.71284479 | H8: Duty (3.4%) | I8: 0 | K8: Solar Roof China Tax | L8: 0.075
B9: 3-in-1 Nutrition Set | C9: 6.66 | D9: 6.66 | E9: Bird Buddy | F9: =1-F8 -> 0.28715521 | H9: Processing Fee (2,90%) | I9: =Summary!B52*L3 -> 6.9915358 | K9: Solar Roof Duty | L9: 0.025
B10: Perch Extender | C10: 6 | E10: Perch Extender | F10: =('DTC - P&L'!AG85+'DTC - P&L'!AG86)/'DTC - P&L'!AG77 -> 0 | H10: Transaction Fee ($0.30) | I10: =0.3 -> 0.3 | K10: Chargeback Fee (Stripe) | L10: 15
B11: Avg. Merch Cost | C11: 3.94 | E11: OTHER 2 | H11: OTHER 1
B12: Avg. Merch Cost without Calendar | C12: 14.79 | E12: OTHER 3 | H12: OTHER 2 | K12: Stripe | L12: 0.95
B13: SBF Housing | E13: OTHER 4 | H13: OTHER 3 | K13: Affirm | L13: 0.05
B14: SBF Camera | E14: OTHER 5 | H14: OTHER 4 | K14: Affirm processing fee | L14: 0.0579
H15: All | I15: =SUM(I3:I14) -> 153.2548 | K15: Affirm transaction fee | L15: 0.3
B22: Outbound shipping | C22: Bird buddy | D22: Add-ons | E22: Merch
A23: *w/o CA weight | B23: Outbound (NA) | C23: 11.94 | D23: 6.155 | E23: 5.4 | H23: App Advertising
B24: Outbound (Europe) | C24: 11.94 | D24: 6.16 | H24: Meta Share to Apple Store | I24: 0.8
B25: Outbound (ROW) | C25: 11.94 | D25: 6.16 | H25: Meta Share to Google Store | I25: 0.2
A26: Source | B26: 3PL Costs | C26: 0 | D26: 0
B27: Handling Fee
B28: Serial Capture | C28: 0.1 | D28: 0
B29: Storage | C29: 0.31 | D29: 0.31
B30: Supplies cost | C30: 0 | D30: 0
B31: Pick charge | C31: 0.35 | D31: 0.35
B32: Pollybag cost | C32: 0 | D32: 0
B33: Carton cost | C33: 1.65 | D33: 0.71
B34: Total outbound (NA) | C34: =C26+C23-C27 -> 11.94 | D34: =D26+D23-D27 -> 6.155
B35: Total outbound (Europe) | C35: 15.06 | D35: =D27+D24-D28 -> 6.16
B36: Total outbound (ROW) | C36: 20
A37: Source | B37: Inbound shipping | C37: Bird buddy | D37: Add-ons
B38: Inbound (NA) | C38: 11.94 | D38: 1.435
B39: Inbound (Europe) | C39: 11.94 | D39: 1.44
B40: Inbound (ROW) | C40: 11.94 | D40: 1.44
B42: AMAZON Logistics | C42: Bird buddy | D42: Add-ons
A43: https://docs.google.com/spreadsheets/d/1Dn0q7h1bHxXdG0N9KpcqzFo0tWUWYXOrRX7yxv3G1E0/edit#gid=1264242332 | B43: Inbound | C43: 11.94 | D43: 1.435
A44: =sum(C43:C44) -> 12.18 | B44: Storage Fee | C44: 0.24 | D44: 0.24
A45: =C46 -> 12.94 | B45: AMAZON Fees | C45: Bird buddy
A46: =sum(F43:F45) -> 0 | B46: FBA fee for units | C46: 12.94
B47: FBA fee for addons | C47: 5.7
A48: =C38 -> 11.94 | B48: Sales Fee | C48: 0.15
B49: AMAZON Shipping | C49: Bird buddy
A50: =sum(A43:A48) -> 37.06 | B50: BB units Shipping | C50: 11
B51: Addons Shipping | C51: 6.155
B53: COGS adjustment for DTC
B54: Returns for refunds | C54: 0.25
B55: Returns for replacements | C55: 0.1
B57: COGS adjustment for Amazon
B58: Returns for refunds | C58: 0.5644
B59: Returns for replacements | C59: 0.4603
B61: Amazon Removal Fee
B62: Units | C62: 5.56
B63: Add-ons | C63: 2.2

Sheet OLD Sales
A1: 45108 | B1: 45108 | C1: 45109 | D1: 45110 | E1: 45111 | F1: 45112 | G1: 45113 | H1: 45114 | I1: 45115 | J1: 45116 | K1: 45117 | L1: 45118 | M1: 45119 | N1: 45120 | O1: 45121 | P1: 45122 | Q1: 45123 | R1: 45124 | S1: 45125 | T1: 45126 | U1: 45127 | V1: 45128 | W1: 45129 | X1: 45130 | Y1: 45131 | Z1: 45132 | AA1: 45133 | AB1: 45134 | AC1: 45135 | AD1: 45136 | AE1: 45137 | AF1: 45138
B2: SAT | C2: SUN | D2: MON | E2: TUE | F2: WED | G2: THU | H2: FRI | I2: SAT | J2: SUN | K2: MON | L2: TUE | M2: WED | N2: THU | O2: FRI | P2: SAT | Q2: SUN | R2: MON | S2: TUE | T2: WED | U2: THU | V2: FRI | W2: SAT | X2: SUN | Y2: MON | Z2: TUE | AA2: WED | AB2: THU | AC2: FRI | AD2: SAT | AE2: SUN | AF2: MON
A3: Weekend Work | B3: Peter | C3: Peter | I3: Peter | J3: Peter | P3: Peco | Q3: Peco | W3: Peco | X3: Peco | AD3: Peter | AE3: Peter
B4: Summer Sale | Z4: Friendship Day
G5: Check comments in this cell | H5: Check comments in this cell | K5: Switch to BB yellow AND blue 10% off | N5: Communication changed from next day shipping to now shipping | R5: Website caching problem / Site down for 8 hours | V5: SBF (Blue) - out of stock | Y5: One page checkout live from 3pm | Z5: Friendship Day starts at 18:00 CET | AC5: SBF (Blue) Back in stock
N6: In-Stock Sale Email | O6: In-Stock Sale Push Notification | R6: In-Stock Sale Follow-up Email | AA6: Switching FB strategy to separate MOF & BOF
A8: WordPress | B8: 49127.2 | C8: 44359.94 | D8: 41176.95 | E8: 43682.34 | F8: 40447.23 | G8: 43380.21 | H8: 47720.49 | I8: 53389.16 | J8: 55427.36 | K8: 45887.67 | L8: 51043.74 | M8: 51340.77 | N8: 80153.53 | O8: 68572.56 | P8: 60624.25 | Q8: 59856.53 | R8: 32044.25 | S8: 60316.3 | T8: 43139.27 | U8: 47288.79 | V8: 48826.1 | W8: 41957.56 | X8: 40174.12 | Y8: 31487.95 | Z8: 36143.33 | AA8: 30366.88 | AB8: 34701.54 | AC8: 30849.69 | AD8: 32381.7 | AE8: 31165.57 | AF8: 34474.77
A9: - Hardware | B9: 38838.3 | C9: 35153 | D9: 33448.8 | E9: 34820.96 | F9: 33275.8 | G9: 35142.66 | H9: 39129.4 | I9: 42610.16 | J9: 43820 | K9: 36440.66 | L9: 41884.4 | M9: 42312.66 | N9: 64361.4 | O9: 55693.9 | P9: 47887.4 | Q9: 48508.86 | R9: 25786.1 | S9: 48734.4 | T9: 35136.7 | U9: 37751.3 | V9: 39691.9 | W9: 33371.7 | X9: 31170.36 | Y9: 25637.3 | Z9: 29158.29 | AA9: 24819.62 | AB9: 29034.5 | AC9: 25107.36 | AD9: 25791.26 | AE9: 24811.43 | AF9: 28199.2
A10: - Add-ons | B10: 4520.9 | C10: 3973 | D10: 3041 | E10: 3854.34 | F10: 2602.5 | G10: 3407.34 | H10: 3307 | I10: 4744.34 | J10: 5288.2 | K10: 4194.34 | L10: 3421 | M10: 3348.34 | N10: 6765 | O10: 4947.7 | P10: 5754.5 | Q10: 4532.34 | R10: 2548.5 | S10: 4762 | T10: 3096.5 | U10: 4190 | V10: 3601 | W10: 3856.5 | X10: 4290.84 | Y10: 2311 | Z10: 3009.51 | AA10: 2200.18 | AB10: 1970.5 | AC10: 2210.84 | AD10: 2940.34 | AE10: 2794.17 | AF10: 2493.4
A11: - Merch | B11: 0 | C11: 0 | D11: 0 | E11: 0 | F11: 0 | G11: 0 | H11: 0 | I11: 0 | J11: 0 | K11: 0 | L11: 0 | M11: 0 | N11: 0 | O11: 0 | P11: 0 | Q11: 0 | R11: 0 | S11: 0 | T11: 0 | U11: 0 | V11: 0 | W11: 0 | X11: 0 | Y11: 0 | Z11: 0 | AA11: 0 | AB11: 0 | AC11: 0 | AD11: 0 | AE11: 0 | AF11: 0
A12: - Taxes | B12: 2823 | C12: 2733.94 | D12: 2277.15 | E12: 2382.04 | F12: 2343.93 | G12: 2470.21 | H12: 2749.09 | I12: 2999.66 | J12: 3139.16 | K12: 2572.67 | L12: 3033.34 | M12: 2959.77 | N12: 4577.13 | O12: 4045.96 | P12: 3397.35 | Q12: 3395.33 | R12: 1884.65 | S12: 3534.9 | T12: 2551.07 | U12: 2717.49 | V12: 2883.2 | W12: 2349.36 | X12: 2317.92 | Y12: 1784.65 | Z12: 2015.53 | AA12: 1682.08 | AB12: 1861.54 | AC12: 1651.49 | AD12: 1830.1 | AE12: 1799.97 | AF12: 1872.17
A13: - Shipping | B13: 2945 | C13: 2500 | D13: 2410 | E13: 2625 | F13: 2225 | G13: 2360 | H13: 2535 | I13: 3035 | J13: 3180 | K13: 2680 | L13: 2705 | M13: 2720 | N13: 4450 | O13: 3885 | P13: 3585 | Q13: 3420 | R13: 1825 | S13: 3285 | T13: 2355 | U13: 2630 | V13: 2650 | W13: 2380 | X13: 2395 | Y13: 1755 | Z13: 1960 | AA13: 1665 | AB13: 1835 | AC13: 1880 | AD13: 1820 | AE13: 1760 | AF13: 1910
A14: Total Revenue | B14: =SUM(B9:B13) -> 49127.2 | C14: =SUM(C9:C13) -> 44359.94 | D14: =SUM(D9:D13) -> 41176.95 | E14: =SUM(E9:E13) -> 43682.34 | F14: =SUM(F9:F13) -> 40447.23 | G14: =SUM(G9:G13) -> 43380.21 | H14: =SUM(H9:H13) -> 47720.49 | I14: =SUM(I9:I13) -> 53389.16 | ... AF14: =SUM(AF9:AF13) -> 34474.77
A15: Orders | B15: 173 | C15: 181 | D15: 159 | E15: 184 | F15: 171 | G15: 187 | H15: 193 | I15: 236 | J15: 216 | K15: 214 | L15: 204 | M15: 198 | N15: 326 | O15: 288 | P15: 252 | Q15: 249 | R15: 147 | S15: 234 | T15: 172 | U15: 198 | V15: 188 | W15: 187 | X15: 171 | Y15: 126 | Z15: 129 | AA15: 114 | AB15: 128 | AC15: 130 | AD15: 126 | AE15: 128 | AF15: 131
A16: - Hardware (units sold) | B16: 161 | C16: 142 | D16: 139 | E16: 147 | F16: 144 | G16: 153 | H16: 167 | I16: 179 | J16: 186 | K16: 162 | L16: 186 | M16: 182 | N16: 289 | O16: 248 | P16: 213 | Q16: 216 | R16: 112 | S16: 206 | T16: 151 | U16: 159 | V16: 164 | W16: 130 | X16: 124 | Y16: 98 | Z16: 118 | AA16: 98 | AB16: 114 | AC16: 103 | AD16: 103 | AE16: 96 | AF16: 113
A17: - Add-ons (units sold) | B17: 146 | C17: 132 | D17: 97 | E17: 127 | F17: 89 | G17: 108 | H17: 106 | I17: 159 | J17: 163 | K17: 134 | L17: 116 | M17: 112 | N17: 217 | O17: 172 | P17: 201 | Q17: 165 | R17: 88 | S17: 159 | T17: 105 | U17: 138 | V17: 128 | W17: 133 | X17: 139 | Y17: 87 | Z17: 96 | AA17: 80 | AB17: 74 | AC17: 73 | AD17: 93 | AE17: 91 | AF17: 85
A18: - Merch (units sold) | B18: 0 | C18: 0 | D18: 0 | E18: 0 | F18: 0 | G18: 0 | H18: 0 | I18: 0 | J18: 0 | K18: 0 | L18: 0 | M18: 0 | N18: 0 | O18: 0 | P18: 0 | Q18: 0 | R18: 0 | S18: 0 | T18: 0 | U18: 0 | V18: 0 | W18: 0 | X18: 0 | Y18: 0 | Z18: 0 | AA18: 0 | AB18: 0 | AC18: 0 | AD18: 0 | AE18: 0 | AF18: 0
A19: =sum(14:14) -> 1411507.8
A20: FB - US & CA | B20: 7590.32 | C20: 9939.48 | D20: 11857.85 | E20: 13975.77 | F20: 13627.08 | G20: 13435.73 | H20: 13643.57 | I20: 14020.82 | J20: 16923.12 | K20: 16638.37 | L20: 14685.47 | M20: 9643.71 | N20: 9544.29 | O20: 13137.58 | P20: 17548.71 | Q20: 20371.34 | R20: 14875.41 | S20: 14651 | T20: 15983.11 | U20: 16495.31 | V20: 16540.43 | W20: 16840.85 | X20: 17566.45 | Y20: 11293.8 | Z20: 9326.51 | AA20: 9853.2 | AB20: 7316.48 | AC20: 6685.51 | AD20: 6692.13 | AE20: 7810.96 | AF20: 7705.29
A21: Google - WW | B21: 3493.03 | C21: 3318.69 | D21: 3105.04 | E21: 3164.26 | F21: 2740.55 | G21: 3020.34 | H21: 3129.51 | I21: 3393.25 | J21: 3789.9 | K21: 3108.44 | L21: 3475.99 | M21: 3368.31 | N21: 3891.75 | O21: 4289.75 | P21: 4978.18 | Q21: 5350.38 | R21: 4262.94 | S21: 5867.41 | T21: 3955.4 | U21: 3443.43 | V21: 4404.04 | W21: 6179.63 | X21: 7876.81 | Y21: 6931.42 | Z21: 6903.19 | AA21: 5631.54 | AB21: 6483.21 | AC21: 6665.27 | AD21: 5627.76 | AE21: 3929.84 | AF21: 2235.27
A22: Bing - WW | B22: 244.51 | C22: 259.8 | D22: 259.73 | E22: 251.56 | F22: 260.93 | G22: 252.96 | H22: 250.94 | I22: 249.85 | J22: 248.72 | K22: 245.95 | L22: 250.54 | M22: 247.66 | N22: 82.36 | O22: 0 | P22: 0 | Q22: 0 | R22: 0 | S22: 0 | T22: 130.29 | U22: 247.33 | V22: 241.87 | W22: 267.6 | X22: 243.5 | Y22: 239.41 | Z22: 253.25 | AA22: 274.45 | AB22: 262.48 | AC22: 301.09 | AD22: 283.72 | AE22: 289.28 | AF22: 296.9
A23: TikTok - US & CA | B23: 0 | C23: 0 | D23: 0 | E23: 0 | F23: 0 | G23: 0 | H23: 0 | I23: 0 | J23: 0 | K23: 0 | L23: 0 | M23: 0 | N23: 0 | O23: 0 | P23: 0 | Q23: 0 | R23: 0 | S23: 0 | T23: 0 | U23: 0 | V23: 0 | W23: 0 | X23: 0 | Y23: 0 | Z23: 0 | AA23: 0 | AB23: 0 | AC23: 0 | AD23: 0 | AE23: 0
A24: MNTN TV
A25: Affiliate Fees - US | B25: 0 | C25: 0 | D25: 0 | E25: 0 | F25: 0 | G25: 0 | H25: 0 | I25: 0 | J25: 0 | K25: 0 | L25: 0 | M25: 0 | N25: 0 | O25: 0 | P25: 0 | Q25: 0 | R25: 0 | S25: 156.16 | T25: 131.12 | U25: 215.27 | V25: 264.81 | W25: 122.94 | X25: 187.67 | Y25: 229.7 | Z25: 157.02 | AA25: 108.61 | AB25: 196.05 | AC25: 49.05 | AD25: 0 | AE25: 136.42 | AF25: 0
A26: Total Spend | B26: =SUM(B20:B25) -> 11327.86 | C26: =SUM(C20:C25) -> 13517.97 | D26: =SUM(D20:D25) -> 15222.62 | E26: =SUM(E20:E25) -> 17391.59 | F26: =SUM(F20:F25) -> 16628.56 | G26: =SUM(G20:G25) -> 16709.03 | H26: =SUM(H20:H25) -> 17024.02 | I26: =SUM(I20:I25) -> 17663.92 | ... AF26: =SUM(AF20:AF25) -> 10237.46
A27: =sum(26:26) -> 542625.68
A28: ROAS | B28: =B14/B26 -> 4.3368474 | C28: =C14/C26 -> 3.2815534 | D28: =D14/D26 -> 2.7049844 | E28: =E14/E26 -> 2.5116933 | F28: =F14/F26 -> 2.4323952 | G28: =G14/G26 -> 2.5962135 | H28: =H14/H26 -> 2.803127 | I28: =I14/I26 -> 3.0224978 | ... AF28: =AF14/AF26 -> 3.3675121
A29: CAC | B29: =B26/B15 -> 65.47896 | C29: =C26/C15 -> 74.684917 | D29: =D26/D15 -> 95.739748 | E29: =E26/E15 -> 94.519511 | F29: =F26/F15 -> 97.243041 | G29: =G26/G15 -> 89.353102 | H29: =H26/H15 -> 88.207358 | I29: =I26/I15 -> 74.847119 | ... AF29: =AF26/AF15 -> 78.14855
A30: CR | B30: 0.0145 | C30: 0.0134 | D30: 0.0122 | E30: 0.0141 | F30: 0.0138 | G30: 0.0142 | H30: 0.0145 | I30: 0.018 | J30: 0.0145 | K30: 0.0152 | L30: 0.0167 | M30: 0.0175 | N30: 0.0229 | O30: 0.0149 | P30: 0.0227 | Q30: 0.0159 | R30: 0.0124 | S30: 0.0213 | T30: 0.0175 | U30: 0.022 | V30: 0.0153 | W30: 0.0155 | X30: 0.0139 | Y30: 0.0125 | Z30: 0.0138 | AA30: 0.0115 | AB30: 0.0139 | AC30: 0.0154 | AD30: 0.0159 | AE30: 0.0143 | AF30: 0.017
A31: AOV | B31: =B14/B15 -> 283.97225 | C31: =C14/C15 -> 245.08254 | D31: =D14/D15 -> 258.97453 | E31: =E14/E15 -> 237.40402 | F31: =F14/F15 -> 236.53351 | G31: =G14/G15 -> 231.97973 | H31: =H14/H15 -> 247.25642 | I31: =I14/I15 -> 226.22525 | ... AF31: =AF14/AF15 -> 263.16618
A32: fAOV | B32: 230 | C32: 250 | D32: 246.65 | E32: 202.04 | F32: 207.45 | G32: 209.04 | H32: 238 | I32: 232 | J32: 209.7 | K32: 204.43 | L32: 210.2 | M32: 219.24 | N32: 210.16 | O32: 211.85 | P32: 211.62 | Q32: 212.28 | R32: 199.44 | S32: 218.72 | T32: 223.74 | U32: 219.67 | V32: 211.86 | W32: 209.25 | X32: 204.42 | Y32: 235.35 | Z32: 223.39 | AA32: 239.8 | AB32: 244.19 | AC32: 247 | AD32: 251 | AE32: 220.65 | AF32: 238.88
A33: rAOV | B33: 218 | C33: 242 | D33: 182.5 | E33: 208.07 | F33: 226.03 | G33: 236.7 | H33: 222 | I33: 199 | J33: 124.55 | K33: 111.81 | L33: 116.24 | M33: 203.05 | N33: 159.26 | O33: 203.1 | P33: 138.28 | Q33: 146.12 | R33: 82.14 | S33: 226.82 | T33: 50.38 | U33: 221.05 | V33: 116.11 | W33: 163.28 | X33: 142.14 | Y33: 83.5 | Z33: 246 | AA33: 65 | AB33: 45.5 | AC33: 155 | AD33: 37 | AE33: 116.29 | AF33: 98.33
A35: Customers
A36: Returning | B36: 0.006 | C36: 0.0226 | D36: 0.0127 | E36: 0.0163 | F36: 0.0234 | G36: 0.0321 | H36: 0.0105 | I36: 0.0044 | J36: 0.0093 | K36: 0.0421 | L36: 0.0245 | M36: 0.0101 | N36: 0.0245 | O36: 0.0347 | P36: 0.0476 | Q36: 0.0522 | R36: 0.0544 | S36: 0.0427 | T36: 0.0465 | U36: 0.0303 | V36: 0.0532 | W36: 0.0214 | X36: 0.0409 | Y36: 0.0952 | Z36: 0.0155 | AA36: 0.0175 | AB36: 0.0156 | AC36: 0.0079 | AD36: 0.0084 | AE36: 0.0547 | AF36: 0.0458
A37: First-time | B37: =1-B36 -> 0.994 | C37: =1-C36 -> 0.9774 | D37: =1-D36 -> 0.9873 | E37: =1-E36 -> 0.9837 | F37: =1-F36 -> 0.9766 | G37: =1-G36 -> 0.9679 | H37: =1-H36 -> 0.9895 | I37: =1-I36 -> 0.9956 | ... AF37: =1-AF36 -> 0.9542
A40: Post-purchase Survey
A41: Facebook / Instagram | B41: / | C41: / | D41: / | E41: / | F41: / | G41: / | H41: / | I41: / | J41: / | K41: / | L41: / | M41: / | N41: 0.4214 | O41: 0 | P41: 0 | Q41: 0 | R41: 0 | S41: 0 | T41: 0 | U41: ='OLD Formulas'!N16 -> 0.32 | V41: ='OLD Formulas'!O16 -> 0.39285714 | W41: ='OLD Formulas'!P16 -> 0.42741935 | X41: ='OLD Formulas'!Q16 -> 0.42741935 | Y41: ='OLD Formulas'!R16 -> 0.4109589 | Z41: ='OLD Formulas'!S16 -> 0.29032258 | AA41: ='OLD Formulas'!T16 -> 0.37142857 | AB41: ='OLD Formulas'!U16 -> 0.31506849 | ... AF41: ='OLD Formulas'!Y16 -> 0.31111111
A42: Friends / Family | B42: / | C42: / | D42: / | E42: / | F42: / | G42: / | H42: / | I42: / | J42: / | K42: / | L42: / | M42: / | N42: 0.5157 | O42: 0 | P42: 0 | Q42: 0 | R42: 0 | S42: 0 | T42: 0 | U42: ='OLD Formulas'!N17 -> 0.56 | V42: ='OLD Formulas'!O17 -> 0.51785714 | W42: ='OLD Formulas'!P17 -> 0.48387097 | X42: ='OLD Formulas'!Q17 -> 0.4516129 | Y42: ='OLD Formulas'!R17 -> 0.42465753 | Z42: ='OLD Formulas'!S17 -> 0.59139785 | AA42: ='OLD Formulas'!T17 -> 0.48571429 | AB42: ='OLD Formulas'!U17 -> 0.53424658 | ... AF42: ='OLD Formulas'!Y17 -> 0.58888889
A43: TikTok | B43: / | C43: / | D43: / | E43: / | F43: / | G43: / | H43: / | I43: / | J43: / | K43: / | L43: / | M43: / | N43: 0.0126 | O43: 0 | P43: 0 | Q43: 0 | R43: 0 | S43: 0 | T43: 0 | U43: ='OLD Formulas'!N18 -> 0 | V43: ='OLD Formulas'!O18 -> 0 | W43: ='OLD Formulas'!P18 -> 0.0080645161 | X43: ='OLD Formulas'!Q18 -> 0.0080645161 | Y43: ='OLD Formulas'!R18 -> 0.02739726 | Z43: ='OLD Formulas'!S18 -> 0.032258065 | AA43: ='OLD Formulas'!T18 -> 0.042857143 | AB43: ='OLD Formulas'!U18 -> 0.04109589 | ... AF43: ='OLD Formulas'!Y18 -> 0.033333333
A44: TV / Radio | B44: / | C44: / | D44: / | E44: / | F44: / | G44: / | H44: / | I44: / | J44: / | K44: / | L44: / | M44: / | N44: 0 | O44: 0 | P44: 0 | Q44: 0 | R44: 0 | S44: 0 | T44: 0 | U44: ='OLD Formulas'!N19 -> 0.026666667 | V44: ='OLD Formulas'!O19 -> 0 | W44: ='OLD Formulas'!P19 -> 0.0080645161 | X44: ='OLD Formulas'!Q19 -> 0.016129032 | Y44: ='OLD Formulas'!R19 -> 0 | Z44: ='OLD Formulas'!S19 -> 0 | AA44: ='OLD Formulas'!T19 -> 0.014285714 | AB44: ='OLD Formulas'!U19 -> 0.01369863 | ... AF44: ='OLD Formulas'!Y19 -> 0.011111111
A45: Blog / Article | B45: / | C45: / | D45: / | E45: / | F45: / | G45: / | H45: / | I45: / | J45: / | K45: / | L45: / | M45: / | N45: 0.0503 | O45: 0 | P45: 0 | Q45: 0 | R45: 0 | S45: 0 | T45: 0 | U45: ='OLD Formulas'!N20 -> 0.093333333 | V45: ='OLD Formulas'!O20 -> 0.053571429 | W45: ='OLD Formulas'!P20 -> 0.016129032 | X45: ='OLD Formulas'!Q20 -> 0.024193548 | Y45: ='OLD Formulas'!R20 -> 0.01369863 | Z45: ='OLD Formulas'!S20 -> 0.032258065 | AA45: ='OLD Formulas'!T20 -> 0.057142857 | AB45: ='OLD Formulas'!U20 -> 0.02739726 | ... AF45: ='OLD Formulas'!Y20 -> 0.033333333
A46: Reddit | B46: / | C46: / | D46: / | E46: / | F46: / | G46: / | H46: / | I46: / | J46: / | K46: / | L46: / | M46: / | N46: / | O46: / | P46: / | Q46: / | R46: / | S46: / | T46: / | U46: / | V46: ='OLD Formulas'!O21 -> 0 | W46: ='OLD Formulas'!P21 -> 0.016129032 | X46: ='OLD Formulas'!Q21 -> 0.0080645161 | Y46: ='OLD Formulas'!R21 -> 0.01369863 | Z46: ='OLD Formulas'!S21 -> 0.010752688 | AA46: ='OLD Formulas'!T21 -> 0 | AB46: ='OLD Formulas'!U21 -> 0.01369863 | AC46: ='OLD Formulas'!V21 -> 0 | ... AF46: ='OLD Formulas'!Y21 -> 0
A47: Google, Youtube | B47: / | C47: / | D47: / | E47: / | F47: / | G47: / | H47: / | I47: / | J47: / | K47: / | L47: / | M47: / | N47: / | O47: / | P47: / | Q47: / | R47: / | S47: / | T47: / | U47: / | V47: ='OLD Formulas'!O22 -> 0.035714286 | W47: ='OLD Formulas'!P22 -> 0.032258065 | X47: ='OLD Formulas'!Q22 -> 0.064516129 | Y47: ='OLD Formulas'!R22 -> 0.10958904 | Z47: ='OLD Formulas'!S22 -> 0.032258065 | AA47: ='OLD Formulas'!T22 -> 0.028571429 | AB47: ='OLD Formulas'!U22 -> 0.054794521 | AC47: ='OLD Formulas'!V22 -> 0.075268817 | ... AF47: ='OLD Formulas'!Y22 -> 0.022222222
A48: Yahoo, Bing | B48: / | C48: / | D48: / | E48: / | F48: / | G48: / | H48: / | I48: / | J48: / | K48: / | L48: / | M48: / | N48: / | O48: / | P48: / | Q48: / | R48: / | S48: / | T48: / | U48: / | V48: ='OLD Formulas'!O23 -> 0 | W48: ='OLD Formulas'!P23 -> 0.0080645161 | X48: ='OLD Formulas'!Q23 -> 0 | Y48: ='OLD Formulas'!R23 -> 0 | Z48: ='OLD Formulas'!S23 -> 0.010752688 | AA48: ='OLD Formulas'!T23 -> 0 | AB48: ='OLD Formulas'!U23 -> 0 | AC48: ='OLD Formulas'!V23 -> 0 | ... AF48: ='OLD Formulas'!Y23 -> 0
B50: 45108 | C50: Goal | D50: % of Goal
A51: Revenue | B51: =SUM(B14:AF14) -> 1411507.8 | C51: 2000000 | D51: =B51/C51 -> 0.70575387
A52: Spend | B52: =SUM(B26:AF26) -> 542625.68 | C52: 666000 | D52: =B52/C52 -> 0.81475327
A53: ROAS | B53: =B51/B52 -> 2.601255 | C53: 3 | D53: =B53/C53 -> 0.86708499
A54: CAC | B54: =SUM(B26:AF26)/SUM(B15:AF15) -> 94.534091
A55: CR | B55: =AVERAGE(B30:AF30) -> 0.015716129
A56: AOV | B56: =B51/B59 -> 245.90727
A57: fAOV | B57: =AVERAGE(B32:AF32) -> 222.32323
A58: rAOV | B58: =AVERAGE(B33:AF33) -> 154.3629
A59: Orders | B59: =SUM(B15:AF15) -> 5740
A60: Units Sold | B60: ='OLD Detailed Report'!AG141 -> 4752 | C60: 7500 | D60: =B60/C60 -> 0.6336
A61: CAC per Unit | B61: =B52/B60 -> 114.18891
A62: First-time customers | B62: =AVERAGE(B37:AF37) -> 0.97022581
A63: Returning customers | B63: =AVERAGE(B36:AF36) -> 0.029774194

Sheet OLD Detailed Report
A1: JULY | B1: 45108 | C1: 45109 | D1: 45110 | E1: 45111 | F1: 45112 | G1: 45113 | H1: 45114 | I1: 45115 | J1: 45116 | K1: 45117 | L1: 45118 | M1: 45119 | N1: 45120 | O1: 45121 | P1: 45122 | Q1: 45123 | R1: 45124 | S1: 45125 | T1: 45126 | U1: 45127 | V1: 45128 | W1: 45129 | X1: 45130 | Y1: 45131 | Z1: 45132 | AA1: 45133 | AB1: 45134 | AC1: 45135 | AD1: 45136 | AE1: 45137 | AF1: 45138
A2: DAY | B2: SAT | C2: SUN | D2: MON | E2: TUE | F2: WED | G2: THU | H2: FRI | I2: SAT | J2: SUN | K2: MON | L2: TUE | M2: WED | N2: THU | O2: FRI | P2: SAT | Q2: SUN | R2: MON | S2: TUE | T2: WED | U2: THU | V2: FRI | W2: SAT | X2: SUN | Y2: MON | Z2: TUE | AA2: WED | AB2: THU | AC2: FRI | AD2: SAT | AE2: SUN | AF2: MON
A3: COMMENT
A4: Transactions
A5: FB (US & CA) | B5: 29 | C5: 56 | D5: 31 | E5: 59 | F5: 47 | G5: 60 | H5: 64 | I5: 89 | J5: 75 | K5: 62 | L5: 51 | M5: 42 | N5: 53 | O5: 73 | P5: 68 | Q5: 67 | R5: 28 | S5: 48 | T5: 53 | U5: 64 | V5: 60 | W5: 65 | X5: 65 | Y5: 30 | Z5: 31 | AA5: 12 | AB5: 27 | AC5: 21 | AD5: 21 | AE5: 18 | AF5: 24 | AG5: =SUM(B5:AF5) -> 1493
A6: Google | B6: 55 | C6: 62 | D6: 52 | E6: 62 | F6: 59 | G6: 59 | H6: 62 | I6: 79 | J6: 67 | K6: 80 | L6: 78 | M6: 77 | N6: 84 | O6: 63 | P6: 69 | Q6: 65 | R6: 42 | S6: 63 | T6: 66 | U6: 66 | V6: 58 | W6: 57 | X6: 65 | Y6: 45 | Z6: 40 | AA6: 49 | AB6: 46 | AC6: 53 | AD6: 39 | AE6: 51 | AF6: 36 | AG6: =SUM(B6:AF6) -> 1849
A7: TikTok | B7: 0 | C7: 0 | D7: 0 | E7: 0 | F7: 0 | G7: 0 | H7: 0 | I7: 0 | J7: 0 | K7: 0 | L7: 0 | M7: 0 | N7: 0 | O7: 0 | P7: 0 | Q7: 0 | R7: 0 | S7: 0 | T7: 0 | U7: 0 | V7: 0 | W7: 0 | X7: 0 | Y7: 0 | Z7: 0 | AA7: 0 | AB7: 0 | AC7: 0 | AD7: 0 | AE7: 0 | AF7: 0 | AG7: =SUM(B7:AF7) -> 0
A8: Bing | B8: 2 | C8: 2 | D8: 1 | E8: 4 | F8: 3 | G8: 2 | H8: 1 | I8: 2 | J8: 6 | K8: 5 | L8: 4 | M8: 3 | N8: 1 | O8: 3 | P8: 1 | Q8: 3 | R8: 1 | S8: 1 | T8: 0 | U8: 4 | V8: 6 | W8: 7 | X8: 4 | Y8: 1 | Z8: 1 | AA8: 1 | AB8: 1 | AC8: 1 | AD8: 0 | AE8: 1 | AF8: 1 | AG8: =SUM(B8:AF8) -> 73
A9: MNTN TV | AG9: =SUM(B9:AF9) -> 0
A10: Affiliates (Refersion) | B10: 0 | C10: 0 | D10: 0 | E10: 0 | F10: 0 | G10: 0 | H10: 0 | I10: 0 | J10: 0 | K10: 0 | L10: 0 | M10: 0 | N10: 0 | O10: 0 | P10: 0 | Q10: 0 | R10: 0 | S10: 4 | T10: 3 | U10: 3 | V10: 4 | W10: 2 | X10: 3 | Y10: 5 | Z10: 3 | AA10: 2 | AB10: 3 | AC10: 1 | AD10: 0 | AE10: 4 | AF10: 0 | AG10: =SUM(B10:AF10) -> 37
A11: FB (Internal Paid) | AG11: =SUM(B11:AF11) -> 0
A12: FB (EU & UK) | AG12: =SUM(B12:AF12) -> 0
A13: Email | B13: 4 | C13: 6 | D13: 3 | E13: 2 | F13: 1 | G13: 1 | H13: 0 | I13: 1 | J13: 2 | K13: 3 | L13: 1 | M13: 2 | N13: 94 | O13: 76 | P13: 25 | Q13: 17 | R13: 29 | S13: 38 | T13: 2 | U13: 4 | V13: 3 | W13: 2 | X13: 6 | Y13: 2 | Z13: 1 | AA13: 0 | AB13: 4 | AD13: 1 | AE13: 4 | AF13: 4 | AG13: =SUM(B13:AF13) -> 338
A14: All | B14: =SUM(B5:B13) -> 90 | C14: =SUM(C5:C13) -> 126 | D14: =SUM(D5:D13) -> 87 | E14: =SUM(E5:E13) -> 127 | F14: =SUM(F5:F13) -> 110 | G14: =SUM(G5:G13) -> 122 | H14: =SUM(H5:H13) -> 127 | I14: =SUM(I5:I13) -> 171 | ... AF14: =SUM(AF5:AF13) -> 65 | AG14: =SUM(B14:AF14) -> 3790
AG15: =SUM(B15:AF15) -> 0
A16: Revenue | AG16: =SUM(B16:AF16) -> 0
A17: FB (US & CA) | B17: 8613.9 | C17: 15724.4 | D17: 8025.24 | E17: 16088.3 | F17: 12903.82 | G17: 14883.81 | H17: 16270.4 | I17: 25945.45 | J17: 19825.93 | K17: 17028.9 | L17: 13397.83 | M17: 10977.79 | N17: 14178.65 | O17: 19579.31 | P17: 17923.96 | Q17: 17121.73 | R17: 7919.38 | S17: 14118.96 | T17: 12662.5 | U17: 18657.19 | V17: 15148.98 | W17: 18426.12 | X17: 16067.5 | Y17: 7934.14 | Z17: 9221.02 | AA17: 4261.21 | AB17: 7567.93 | AC17: 5416.74 | AD17: 5924.43 | AE17: 4314.2 | AF17: 7496.05 | AG17: =SUM(B17:AF17) -> 403625.77
A18: Google | B18: 12359.29 | C18: 15714.44 | D18: 12992.16 | E18: 14130.15 | F18: 12779.82 | G18: 13797.36 | H18: 13621.06 | I18: 16193.95 | J18: 15558.05 | K18: 17274.51 | L18: 18071.04 | M18: 18496.68 | N18: 19977.39 | O18: 14636.37 | P18: 14578.95 | Q18: 14867.89 | R18: 9667.93 | S18: 14155.55 | T18: 17455.8 | U18: 14739.52 | V18: 13885.52 | W18: 12885.06 | X18: 15358.08 | Y18: 11022.06 | Z18: 11322.51 | AA18: 12117.25 | AB18: 12457.81 | AC18: 13306.27 | AD18: 8931.61 | AE18: 13855.82 | AF18: 9278.69 | AG18: =SUM(B18:AF18) -> 435488.59
A19: TikTok | M19: 0 | N19: 0 | O19: 0 | P19: 0 | Q19: 0 | R19: 0 | S19: 0 | T19: 0 | U19: 0 | V19: 0 | W19: 0 | X19: 0 | Y19: 0 | Z19: 0 | AA19: 0 | AB19: 0 | AC19: 0 | AD19: 0 | AE19: 0 | AF19: 0 | AG19: =SUM(B19:AF19) -> 0
A20: Bing | B20: 381.38 | C20: 380.76 | D20: 86.4 | E20: 774.99 | F20: 441.39 | G20: 632.04 | H20: 249.31 | I20: 304.66 | J20: 2048.44 | K20: 1113.52 | L20: 713.3 | M20: 771.48 | N20: 292.98 | O20: 551.04 | P20: 292.66 | Q20: 845.41 | R20: 25.44 | S20: 85.41 | T20: 0 | U20: 638.28 | V20: 1353.82 | W20: 1682.28 | X20: 430.18 | Y20: 299.38 | Z20: 342 | AA20: 68.21 | AB20: 297.14 | AC20: 602.4 | AD20: 0 | AE20: 295.14 | AF20: 297.48 | AG20: =SUM(B20:AF20) -> 16296.92
A21: MNTN TV | AG21: =SUM(B21:AF21) -> 0
A22: Affiliates (Refersion) | B22: 0 | C22: 0 | D22: 0 | E22: 0 | F22: 0 | G22: 0 | H22: 0 | I22: 0 | J22: 0 | K22: 0 | L22: 0 | M22: 0 | N22: 0 | O22: 0 | P22: 0 | Q22: 0 | R22: 0 | S22: 780.81 | T22: 541.79 | U22: 925.45 | V22: 1184.57 | W22: 531.95 | X22: 938.33 | Y22: 1148.46 | Z22: 785.1 | AA22: 543.06 | AB22: 908.25 | AC22: 245.27 | AD22: 0 | AE22: 682.12 | AF22: 0 | AG22: =SUM(B22:AF22) -> 9215.16
A23: FB (Internal Paid) | AG23: =SUM(B23:AF23) -> 0
A24: FB (EU & UK) | AG24: =SUM(B24:AF24) -> 0
A25: Email | B25: 815.46 | C25: 1741.69 | D25: 759.15 | E25: 509.74 | F25: 204.7 | G25: 266.63 | H25: 0 | I25: 30.74 | J25: 425.14 | K25: 543.68 | L25: 63 | M25: 348.11 | N25: 21081.09 | O25: 19052.55 | P25: 6531.28 | Q25: 3775.83 | R25: 6537.36 | S25: 7669.01 | T25: 238.68 | U25: 825.72 | V25: 465.42 | W25: 309.71 | X25: 1222.39 | Y25: 351.79 | Z25: 24.84 | AA25: 0 | AB25: 1047.31 | AC25: 576.18 | AD25: 124.94 | AE25: 646.42 | AF25: 1000.93 | AG25: =SUM(B25:AF25) -> 77189.49
A26: All | B26: =SUM(B17:B25) -> 22170.03 | C26: =SUM(C17:C25) -> 33561.29 | D26: =SUM(D17:D25) -> 21862.95 | E26: =SUM(E17:E25) -> 31503.18 | F26: =SUM(F17:F25) -> 26329.73 | G26: =SUM(G17:G25) -> 29579.84 | H26: =SUM(H17:H25) -> 30140.77 | I26: =SUM(I17:I25) -> 42474.8 | ... AF26: =SUM(AF17:AF25) -> 18073.15 | AG26: =SUM(B26:AF26) -> 941815.93
AG27: =SUM(B27:AF27) -> 0
A28: Media Cost | AG28: =SUM(B28:AF28) -> 0
A29: FB Spend (US & CA) | B29: ='OLD Sales'!B20 -> 7590.32 | C29: ='OLD Sales'!C20 -> 9939.48 | D29: ='OLD Sales'!D20 -> 11857.85 | E29: ='OLD Sales'!E20 -> 13975.77 | F29: ='OLD Sales'!F20 -> 13627.08 | G29: ='OLD Sales'!G20 -> 13435.73 | H29: ='OLD Sales'!H20 -> 13643.57 | I29: ='OLD Sales'!I20 -> 14020.82 | ... AF29: ='OLD Sales'!AF20 -> 7705.29 | AG29: =SUM(B29:AF29) -> 396219.65
A30: Google Spend | B30: ='OLD Sales'!B21 -> 3493.03 | C30: ='OLD Sales'!C21 -> 3318.69 | D30: ='OLD Sales'!D21 -> 3105.04 | E30: ='OLD Sales'!E21 -> 3164.26 | F30: ='OLD Sales'!F21 -> 2740.55 | G30: ='OLD Sales'!G21 -> 3020.34 | H30: ='OLD Sales'!H21 -> 3129.51 | I30: ='OLD Sales'!I21 -> 3393.25 | ... AF30: ='OLD Sales'!AF21 -> 2235.27 | AG30: =SUM(B30:AF30) -> 138014.53
A31: TikTok Spend | B31: ='OLD Sales'!B23 -> 0 | C31: ='OLD Sales'!C23 -> 0 | D31: ='OLD Sales'!D23 -> 0 | E31: ='OLD Sales'!E23 -> 0 | F31: ='OLD Sales'!F23 -> 0 | G31: ='OLD Sales'!G23 -> 0 | H31: ='OLD Sales'!H23 -> 0 | I31: ='OLD Sales'!I23 -> 0 | ... AE31: ='OLD Sales'!AE23 -> 0 | AG31: =SUM(B31:AF31) -> 0
A32: Bing Spend | B32: ='OLD Sales'!B22 -> 244.51 | C32: ='OLD Sales'!C22 -> 259.8 | D32: ='OLD Sales'!D22 -> 259.73 | E32: ='OLD Sales'!E22 -> 251.56 | F32: ='OLD Sales'!F22 -> 260.93 | G32: ='OLD Sales'!G22 -> 252.96 | H32: ='OLD Sales'!H22 -> 250.94 | I32: ='OLD Sales'!I22 -> 249.85 | ... AF32: ='OLD Sales'!AF22 -> 296.9 | AG32: =SUM(B32:AF32) -> 6436.68
A33: MNTN TV | B33: ='OLD Sales'!B24 | C33: ='OLD Sales'!C24 | D33: ='OLD Sales'!D24 | E33: ='OLD Sales'!E24 | F33: ='OLD Sales'!F24 | G33: ='OLD Sales'!G24 | H33: ='OLD Sales'!H24 | I33: ='OLD Sales'!I24 | ... AE33: ='OLD Sales'!AE24 | AG33: =SUM(B33:AF33) -> 0
A34: Fee 15% Purchase (Backerkit) | B34: =B21*0.15 -> 0 | C34: =C21*0.15 -> 0 | D34: =D21*0.15 -> 0 | E34: =E21*0.15 -> 0 | F34: =F21*0.15 -> 0 | G34: =G21*0.15 -> 0 | H34: =H21*0.15 -> 0 | I34: =I21*0.15 -> 0 | ... S34: =S21*0.15 -> 0 | U34: =U21*0.15 -> 0 | V34: =V21*0.15 -> 0 | W34: =W21*0.15 -> 0 | X34: =X21*0.15 -> 0 | Y34: =Y21*0.15 -> 0 | Z34: =Z21*0.15 -> 0 | AA34: =AA21*0.15 -> 0 | AB34: =AB21*0.15 -> 0 | AC34: =AC21*0.15 -> 0 | AG34: =SUM(B34:AF34) -> 0
A35: Google Management Fee | AG35: =SUM(B35:AF35) -> 0
A36: Affiliates Agency Payment (Grovia) | AG36: =SUM(B36:AF36) -> 0
A37: Affiliate Fee 20% (Grovia) | B37: ='OLD Sales'!B25 -> 0 | C37: ='OLD Sales'!C25 -> 0 | D37: ='OLD Sales'!D25 -> 0 | E37: ='OLD Sales'!E25 -> 0 | F37: ='OLD Sales'!F25 -> 0 | G37: ='OLD Sales'!G25 -> 0 | H37: ='OLD Sales'!H25 -> 0 | I37: ='OLD Sales'!I25 -> 0 | ... AF37: ='OLD Sales'!AF25 -> 0 | AG37: =SUM(B37:AF37) -> 1954.82
A38: FB Spend (Internal Paid) | AG38: =SUM(B38:AF38) -> 0
A39: FB Spend (EU & UK) | AG39: =SUM(B39:AF39) -> 0
A40: Pinterest Spend | AG40: =SUM(B40:AF40) -> 0
A41: Platform Fee (6,90%) | AG41: =SUM(B41:AF41) -> 0
A42: All | B42: =SUM(B29:B41) -> 11327.86 | C42: =SUM(C29:C41) -> 13517.97 | D42: =SUM(D29:D41) -> 15222.62 | E42: =SUM(E29:E41) -> 17391.59 | F42: =SUM(F29:F41) -> 16628.56 | G42: =SUM(G29:G41) -> 16709.03 | H42: =SUM(H29:H41) -> 17024.02 | I42: =SUM(I29:I41) -> 17663.92 | ... AF42: =SUM(AF29:AF41) -> 10237.46 | AG42: =SUM(B42:AF42) -> 542625.68
AG43: =SUM(B43:AF43) -> 0
A44: Cost | AG44: =SUM(B44:AF44) -> 0
A45: Average COGS ($88.77) | B45: =B14*'OLD Formulas'!$C21 -> 8322.3044 | C45: =C14*'OLD Formulas'!$C21 -> 11651.226 | D45: =D14*'OLD Formulas'!$C21 -> 8044.8943 | E45: =E14*'OLD Formulas'!$C21 -> 11743.696 | F45: =F14*'OLD Formulas'!$C21 -> 10171.705 | G45: =G14*'OLD Formulas'!$C21 -> 11281.346 | H45: =H14*'OLD Formulas'!$C21 -> 11743.696 | I45: =I14*'OLD Formulas'!$C21 -> 15812.378 | ... AF45: =AF14*'OLD Formulas'!$C21 -> 6010.5532 | AG45: =SUM(B45:AF45) -> 350461.49
A46: Average Inbound Shipping ($8.63) | B46: =B14*'OLD Formulas'!$C22 -> 1175.337 | C46: =C14*'OLD Formulas'!$C22 -> 1645.4718 | D46: =D14*'OLD Formulas'!$C22 -> 1136.1591 | E46: =E14*'OLD Formulas'!$C22 -> 1658.5311 | F46: =F14*'OLD Formulas'!$C22 -> 1436.523 | G46: =G14*'OLD Formulas'!$C22 -> 1593.2346 | H46: =H14*'OLD Formulas'!$C22 -> 1658.5311 | I46: =I14*'OLD Formulas'!$C22 -> 2233.1403 | ... AF46: =AF14*'OLD Formulas'!$C22 -> 848.8545 | AG46: =SUM(B46:AF46) -> 49494.747
A47: Average Outbound Shipping ($11.59) | B47: =B14*'OLD Formulas'!$C23 -> 1355.4 | C47: =C14*'OLD Formulas'!$C23 -> 1897.56 | D47: =D14*'OLD Formulas'!$C23 -> 1310.22 | E47: =E14*'OLD Formulas'!$C23 -> 1912.62 | F47: =F14*'OLD Formulas'!$C23 -> 1656.6 | G47: =G14*'OLD Formulas'!$C23 -> 1837.32 | H47: =H14*'OLD Formulas'!$C23 -> 1912.62 | I47: =I14*'OLD Formulas'!$C23 -> 2575.26 | ... AF47: =AF14*'OLD Formulas'!$C23 -> 978.9 | AG47: =SUM(B47:AF47) -> 57077.4
A48: Average Taxes ($10.89) | B48: =B14*'OLD Formulas'!$C24 -> 980.1 | C48: =C14*'OLD Formulas'!$C24 -> 1372.14 | D48: =D14*'OLD Formulas'!$C24 -> 947.43 | E48: =E14*'OLD Formulas'!$C24 -> 1383.03 | F48: =F14*'OLD Formulas'!$C24 -> 1197.9 | G48: =G14*'OLD Formulas'!$C24 -> 1328.58 | H48: =H14*'OLD Formulas'!$C24 -> 1383.03 | I48: =I14*'OLD Formulas'!$C24 -> 1862.19 | ... AF48: =AF14*'OLD Formulas'!$C24 -> 707.85 | AG48: =SUM(B48:AF48) -> 41273.1
A49: China Tax (7.5%) | B49: =B14*'OLD Formulas'!$C25 -> 624.17283 | C49: =C14*'OLD Formulas'!$C25 -> 873.84197 | D49: =D14*'OLD Formulas'!$C25 -> 603.36707 | E49: =E14*'OLD Formulas'!$C25 -> 880.77722 | F49: =F14*'OLD Formulas'!$C25 -> 762.87791 | G49: =G14*'OLD Formulas'!$C25 -> 846.10095 | H49: =H14*'OLD Formulas'!$C25 -> 880.77722 | I49: =I14*'OLD Formulas'!$C25 -> 1185.9284 | ... AF49: =AF14*'OLD Formulas'!$C25 -> 450.79149 | AG49: =SUM(B49:AF49) -> 26284.612
A50: Duty (3.4%) | B50: =B14*'OLD Formulas'!$C26 -> 11.801808 | C50: =C14*'OLD Formulas'!$C26 -> 16.52253 | D50: =D14*'OLD Formulas'!$C26 -> 11.408414 | E50: =E14*'OLD Formulas'!$C26 -> 16.653662 | F50: =F14*'OLD Formulas'!$C26 -> 14.424431 | G50: =G14*'OLD Formulas'!$C26 -> 15.998006 | H50: =H14*'OLD Formulas'!$C26 -> 16.653662 | I50: =I14*'OLD Formulas'!$C26 -> 22.423434 | ... AF50: =AF14*'OLD Formulas'!$C26 -> 8.5235276 | AG50: =SUM(B50:AF50) -> 496.98723
A51: Handling Fee ($1.50) | B51: =B14*'OLD Formulas'!$C29 -> 0 | C51: =C14*'OLD Formulas'!$C29 -> 0 | D51: =D14*'OLD Formulas'!$C29 -> 0 | E51: =E14*'OLD Formulas'!$C29 -> 0 | F51: =F14*'OLD Formulas'!$C29 -> 0 | G51: =G14*'OLD Formulas'!$C29 -> 0 | H51: =H14*'OLD Formulas'!$C29 -> 0 | I51: =I14*'OLD Formulas'!$C29 -> 0 | ... AF51: =AF14*'OLD Formulas'!$C29 -> 0 | AG51: =SUM(B51:AF51) -> 0
A52: Serial Capture ($0.30) | B52: =B14*'OLD Formulas'!$C30 -> 27 | C52: =C14*'OLD Formulas'!$C30 -> 37.8 | D52: =D14*'OLD Formulas'!$C30 -> 26.1 | E52: =E14*'OLD Formulas'!$C30 -> 38.1 | F52: =F14*'OLD Formulas'!$C30 -> 33 | G52: =G14*'OLD Formulas'!$C30 -> 36.6 | H52: =H14*'OLD Formulas'!$C30 -> 38.1 | I52: =I14*'OLD Formulas'!$C30 -> 51.3 | ... AF52: =AF14*'OLD Formulas'!$C30 -> 19.5 | AG52: =SUM(B52:AF52) -> 1137
A53: Processing Fee (2,97%) | B53: =B26*'OLD Formulas'!$C35 -> 642.93087 | C53: =C26*'OLD Formulas'!$C35 -> 973.27741 | D53: =D26*'OLD Formulas'!$C35 -> 634.02555 | E53: =E26*'OLD Formulas'!$C35 -> 913.59222 | F53: =F26*'OLD Formulas'!$C35 -> 763.56217 | G53: =G26*'OLD Formulas'!$C35 -> 857.81536 | H53: =H26*'OLD Formulas'!$C35 -> 874.08233 | I53: =I26*'OLD Formulas'!$C35 -> 1231.7692 | ... AF53: =AF26*'OLD Formulas'!$C35 -> 524.12135 | AG53: =SUM(B53:AF53) -> 27312.662
A54: Transaction Fee ($0.36) | B54: =B14*'OLD Formulas'!$C28 -> 27 | C54: =C14*'OLD Formulas'!$C28 -> 37.8 | D54: =D14*'OLD Formulas'!$C28 -> 26.1 | E54: =E14*'OLD Formulas'!$C28 -> 38.1 | F54: =F14*'OLD Formulas'!$C28 -> 33 | G54: =G14*'OLD Formulas'!$C28 -> 36.6 | H54: =H14*'OLD Formulas'!$C28 -> 38.1 | I54: =I14*'OLD Formulas'!$C28 -> 51.3 | ... AF54: =AF14*'OLD Formulas'!$C28 -> 19.5 | AG54: =SUM(B54:AF54) -> 1137
A55: All | B55: =SUM(B45:B54) -> 13166.047 | C55: =SUM(C45:C54) -> 18505.64 | D55: =SUM(D45:D54) -> 12739.704 | E55: =SUM(E45:E54) -> 18585.1 | F55: =SUM(F45:F54) -> 16069.593 | G55: =SUM(G45:G54) -> 17833.595 | H55: =SUM(H45:H54) -> 18545.591 | I55: =SUM(I45:I54) -> 25025.69 | ... AF55: =SUM(AF45:AF54) -> 9568.5941 | AG55: =SUM(B55:AF55) -> 554674.99
AG56: =SUM(B56:AF56) -> 0
A57: Partial Profit | B57: =B26-B42-B55 -> -2323.877 | C57: =C26-C42-C55 -> 1537.6801 | D57: =D26-D42-D55 -> -6099.3744 | E57: =E26-E42-E55 -> -4473.5105 | F57: =F26-F42-F55 -> -6368.4229 | G57: =G26-G42-G55 -> -4962.7849 | H57: =H26-H42-H55 -> -5428.8406 | I57: =I26-I42-I55 -> -214.80977 | ... AF57: =AF26-AF42-AF55 -> -1732.9041 | AG57: =SUM(B57:AF57) -> -155484.74
A58: =SUM(B57:AC57) -> -143406.69
A62: Performance Facebook US & CA | Z62: 3.11 | AA62: 1.8
A63: PROFIT | B63: =B17-(B5*'OLD Formulas'!$C32)-B29 -> -3227.4443 | C63: =C17-(C5*'OLD Formulas'!$C32)-C29 -> -2423.9545 | D63: =D17-(D5*'OLD Formulas'!$C32)-D29 -> -8376.8084 | E63: =E17-(E5*'OLD Formulas'!$C32)-E29 -> -6536.1057 | F63: =F17-(F5*'OLD Formulas'!$C32)-F29 -> -7612.8511 | G63: =G17-(G5*'OLD Formulas'!$C32)-G29 -> -7347.1427 | H63: =H17-(H5*'OLD Formulas'!$C32)-H29 -> -6754.7409 | I63: =I17-(I5*'OLD Formulas'!$C32)-I29 -> -1121.617 | ... AF63: =AF17-(AF5*'OLD Formulas'!$C32)-AF29 -> -3727.3291 | AG63: =SUM(B63:AF63) -> -211448.34
A64: ROAS | B64: =B17/B29 -> 1.1348533 | C64: =C17/C29 -> 1.5820144 | D64: =D17/D29 -> 0.67678711 | E64: =E17/E29 -> 1.1511566 | F64: =F17/F29 -> 0.9469248 | G64: =G17/G29 -> 1.1077783 | H64: =H17/H29 -> 1.1925325 | I64: =I17/I29 -> 1.8504945 | ... AF64: =AF17/AF29 -> 0.97284463
A65: CPO | B65: =B29/B5 -> 261.73517 | C65: =C29/C5 -> 177.49071 | D65: =D29/D5 -> 382.51129 | E65: =E29/E5 -> 236.87746 | F65: =F29/F5 -> 289.93787 | G65: =G29/G5 -> 223.92883 | H65: =H29/H5 -> 213.18078 | I65: =I29/I5 -> 157.5373 | ... AF65: =AF29/AF5 -> 321.05375
A66: MER | B66: =B17/('OLD Formulas'!$C32*B5+B29) -> 0.72744274 | C66: =C17/('OLD Formulas'!$C32*C5+C29) -> 0.86643668 | D66: =D17/('OLD Formulas'!$C32*D5+D29) -> 0.48928279 | E66: =E17/('OLD Formulas'!$C32*E5+E29) -> 0.71110376 | F66: =F17/('OLD Formulas'!$C32*F5+F29) -> 0.62894316 | G66: =G17/('OLD Formulas'!$C32*G5+G29) -> 0.66950842 | H66: =H17/('OLD Formulas'!$C32*H5+H29) -> 0.70663628 | I66: =I17/('OLD Formulas'!$C32*I5+I29) -> 0.95856156 | ... AF66: =AF17/('OLD Formulas'!$C32*AF5+AF29) -> 0.667896
A68: Performance Google
A69: PROFIT | B69: =B18-(B6*'OLD Formulas'!$C32)-B30 -> 803.97251 | C69: =C18-(C6*'OLD Formulas'!$C32)-C30 -> 3307.3532 | D69: =D18-(D6*'OLD Formulas'!$C32)-D30 -> 2264.5936 | E69: =E18-(E6*'OLD Formulas'!$C32)-E30 -> 1877.4932 | F69: =F18-(F6*'OLD Formulas'!$C32)-F30 -> 1390.6343 | G69: =G18-(G6*'OLD Formulas'!$C32)-G30 -> 2128.3843 | H69: =H18-(H6*'OLD Formulas'!$C32)-H30 -> 1403.1532 | I69: =I18-(I6*'OLD Formulas'!$C32)-I30 -> 1220.3234 | ... AF69: =AF18-(AF6*'OLD Formulas'!$C32)-AF30 -> 1766.2864 | AG69: =SUM(B69:AF69) -> 26434.613
A70: ROAS | B70: =B18/B30 -> 3.5382719 | C70: =C18/C30 -> 4.7351334 | D70: =D18/D30 -> 4.1842166 | E70: =E18/E30 -> 4.4655464 | F70: =F18/F30 -> 4.6632318 | G70: =G18/G30 -> 4.568148 | H70: =H18/H30 -> 4.3524577 | I70: =I18/I30 -> 4.7724011 | ... AF70: =AF18/AF30 -> 4.1510377
A71: CPO | B71: =B30/B6 -> 63.509636 | C71: =C30/C6 -> 53.527258 | D71: =D30/D6 -> 59.712308 | E71: =E30/E6 -> 51.036452 | F71: =F30/F6 -> 46.45 | G71: =G30/G6 -> 51.192203 | H71: =H30/H6 -> 50.475968 | I71: =I30/I6 -> 42.952532 | ... AF71: =AF30/AF6 -> 62.090833
A72: MER | B72: =B18/('OLD Formulas'!$C32*B6+B30) -> 1.069576 | C72: =C18/('OLD Formulas'!$C32*C6+C30) -> 1.2665697 | D72: =D18/('OLD Formulas'!$C32*D6+D30) -> 1.2111004 | E72: =E18/('OLD Formulas'!$C32*E6+E30) -> 1.1532315 | F72: =F18/('OLD Formulas'!$C32*F6+F30) -> 1.1221013 | G72: =G18/('OLD Formulas'!$C32*G6+G30) -> 1.1823968 | H72: =H18/('OLD Formulas'!$C32*H6+H30) -> 1.114844 | I72: =I18/('OLD Formulas'!$C32*I6+I30) -> 1.0814982 | ... AF72: =AF18/('OLD Formulas'!$C32*AF6+AF30) -> 1.235116
A74: Performance TikTok
A75: PROFIT | B75: =B19-(B7*'OLD Formulas'!$C32)-B31 -> 0 | C75: =C19-(C7*'OLD Formulas'!$C32)-C31 -> 0 | D75: =D19-(D7*'OLD Formulas'!$C32)-D31 -> 0 | E75: =E19-(E7*'OLD Formulas'!$C32)-E31 -> 0 | F75: =F19-(F7*'OLD Formulas'!$C32)-F31 -> 0 | G75: =G19-(G7*'OLD Formulas'!$C32)-G31 -> 0 | H75: =H19-(H7*'OLD Formulas'!$C32)-H31 -> 0 | I75: =I19-(I7*'OLD Formulas'!$C32)-I31 -> 0 | ... AF75: =AF19-(AF7*'OLD Formulas'!$C32)-AF31 -> 0 | AG75: =SUM(B75:AF75) -> 0
A76: ROAS | B76: =B19/B31 -> #DIV/0! | C76: =C19/C31 -> #DIV/0! | D76: =D19/D31 -> #DIV/0! | E76: =E19/E31 -> #DIV/0! | F76: =F19/F31 -> #DIV/0! | G76: =G19/G31 -> #DIV/0! | H76: =H19/H31 -> #DIV/0! | I76: =I19/I31 -> #DIV/0! | ... AF76: =AF19/AF31 -> #DIV/0!
A77: CPO | B77: =B31/B7 -> #DIV/0! | C77: =C31/C7 -> #DIV/0! | D77: =D31/D7 -> #DIV/0! | E77: =E31/E7 -> #DIV/0! | F77: =F31/F7 -> #DIV/0! | G77: =G31/G7 -> #DIV/0! | H77: =H31/H7 -> #DIV/0! | I77: =I31/I7 -> #DIV/0! | ... AF77: =AF31/AF7 -> #DIV/0!
A78: MER | B78: =B19/('OLD Formulas'!$C32*B7+B31) -> #DIV/0! | C78: =C19/('OLD Formulas'!$C32*C7+C31) -> #DIV/0! | D78: =D19/('OLD Formulas'!$C32*D7+D31) -> #DIV/0! | E78: =E19/('OLD Formulas'!$C32*E7+E31) -> #DIV/0! | F78: =F19/('OLD Formulas'!$C32*F7+F31) -> #DIV/0! | G78: =G19/('OLD Formulas'!$C32*G7+G31) -> #DIV/0! | H78: =H19/('OLD Formulas'!$C32*H7+H31) -> #DIV/0! | I78: =I19/('OLD Formulas'!$C32*I7+I31) -> #DIV/0! | ... AF78: =AF19/('OLD Formulas'!$C32*AF7+AF31) -> #DIV/0!
A80: Performance Bing
A81: PROFIT | B81: =B20-(B8*'OLD Formulas'!$C32)-B32 -> -156.30409 | C81: =C20-(C8*'OLD Formulas'!$C32)-C32 -> -172.21409 | D81: =D20-(D8*'OLD Formulas'!$C32)-D32 -> -319.91705 | E81: =E20-(E8*'OLD Formulas'!$C32)-E32 -> -62.918181 | F81: =F20-(F8*'OLD Formulas'!$C32)-F32 -> -259.30114 | G81: =G20-(G8*'OLD Formulas'!$C32)-G32 -> 85.90591 | H81: =H20-(H8*'OLD Formulas'!$C32)-H32 -> -148.21705 | I81: =I20-(I8*'OLD Formulas'!$C32)-I32 -> -238.36409 | ... AF81: =AF20-(AF8*'OLD Formulas'!$C32)-AF32 -> -146.00705 | AG81: =SUM(B81:AF81) -> -840.6143
A82: ROAS | B82: =B20/B32 -> 1.5597726 | C82: =C20/C32 -> 1.4655889 | D82: =D20/D32 -> 0.33265314 | E82: =E20/E32 -> 3.0807362 | F82: =F20/F32 -> 1.6916031 | G82: =G20/G32 -> 2.4985769 | H82: =H20/H32 -> 0.99350442 | I82: =I20/I32 -> 1.2193716 | ... AF82: =AF20/AF32 -> 1.0019535
A83: CPO | B83: =B32/B8 -> 122.255 | C83: =C32/C8 -> 129.9 | D83: =D32/D8 -> 259.73 | E83: =E32/E8 -> 62.89 | F83: =F32/F8 -> 86.976667 | G83: =G32/G8 -> 126.48 | H83: =H32/H8 -> 250.94 | I83: =I32/I8 -> 124.925 | ... AF83: =AF32/AF8 -> 296.9
A84: MER | B84: =B20/('OLD Formulas'!$C32*B8+B32) -> 0.70930125 | C84: =C20/('OLD Formulas'!$C32*C8+C32) -> 0.68856752 | D84: =D20/('OLD Formulas'!$C32*D8+D32) -> 0.21264183 | E84: =E20/('OLD Formulas'!$C32*E8+E32) -> 0.92491041 | F84: =F20/('OLD Formulas'!$C32*F8+F32) -> 0.62993518 | G84: =G20/('OLD Formulas'!$C32*G8+G32) -> 1.1572982 | H84: =H20/('OLD Formulas'!$C32*H8+H32) -> 0.6271523 | I84: =I20/('OLD Formulas'!$C32*I8+I32) -> 0.56104325 | ... AF84: =AF20/('OLD Formulas'!$C32*AF8+AF32) -> 0.67077495
A86: MNTN TV
A87: PROFIT | B87: =B21-(B9*'OLD Formulas'!$C32)-B33 -> 0 | C87: =C21-(C9*'OLD Formulas'!$C32)-C33 -> 0 | D87: =D21-(D9*'OLD Formulas'!$C32)-D33 -> 0 | E87: =E21-(E9*'OLD Formulas'!$C32)-E33 -> 0 | F87: =F21-(F9*'OLD Formulas'!$C32)-F33 -> 0 | G87: =G21-(G9*'OLD Formulas'!$C32)-G33 -> 0 | H87: =H21-(H9*'OLD Formulas'!$C32)-H33 -> 0 | I87: =I21-(I9*'OLD Formulas'!$C32)-I33 -> 0 | ... AF87: =AF21-(AF9*'OLD Formulas'!$C32)-AF33 -> 0 | AG87: =SUM(B87:AF87) -> 0
A88: ROAS | B88: =B21/B33 -> #DIV/0! | C88: =C21/C33 -> #DIV/0! | D88: =D21/D33 -> #DIV/0! | E88: =E21/E33 -> #DIV/0! | F88: =F21/F33 -> #DIV/0! | G88: =G21/G33 -> #DIV/0! | H88: =H21/H33 -> #DIV/0! | I88: =I21/I33 -> #DIV/0! | ... AF88: =AF21/AF33 -> #DIV/0!
A89: CPO | B89: =B33/B9 -> #DIV/0! | C89: =C33/C9 -> #DIV/0! | D89: =D33/D9 -> #DIV/0! | E89: =E33/E9 -> #DIV/0! | F89: =F33/F9 -> #DIV/0! | G89: =G33/G9 -> #DIV/0! | H89: =H33/H9 -> #DIV/0! | I89: =I33/I9 -> #DIV/0! | ... AF89: =AF33/AF9 -> #DIV/0!
A90: MER | B90: =B21/('OLD Formulas'!$C32*B9+B33) -> #DIV/0! | C90: =C21/('OLD Formulas'!$C32*C9+C33) -> #DIV/0! | D90: =D21/('OLD Formulas'!$C32*D9+D33) -> #DIV/0! | E90: =E21/('OLD Formulas'!$C32*E9+E33) -> #DIV/0! | F90: =F21/('OLD Formulas'!$C32*F9+F33) -> #DIV/0! | G90: =G21/('OLD Formulas'!$C32*G9+G33) -> #DIV/0! | H90: =H21/('OLD Formulas'!$C32*H9+H33) -> #DIV/0! | I90: =I21/('OLD Formulas'!$C32*I9+I33) -> #DIV/0! | ... AF90: =AF21/('OLD Formulas'!$C32*AF9+AF33) -> #DIV/0!
A92: Affiliates (Grovia)
A93: PROFIT | AG93: =SUM(B93:AF93) -> 0
A94: ROAS
A95: CPO
A96: MER
A98: Performance Internal Paid
A99: PROFIT | AG99: =SUM(B99:AF99) -> 0
A100: ROAS
A101: CPO
A102: MER
A104: Performance EU & UK
A105: PROFIT | AG105: =SUM(B105:AF105) -> 0
A106: ROAS
A107: CPO
A108: MER
A111: Performance Email
A112: PROFIT | B112: =B25-(B13*'OLD Formulas'!$C32) -> 229.11182 | C112: =C25-(C13*'OLD Formulas'!$C32) -> 862.16773 | D112: =D25-(D13*'OLD Formulas'!$C32) -> 319.38886 | E112: =E25-(E13*'OLD Formulas'!$C32) -> 216.56591 | F112: =F25-(F13*'OLD Formulas'!$C32) -> 58.112955 | G112: =G25-(G13*'OLD Formulas'!$C32) -> 120.04295 | H112: =H25-(H13*'OLD Formulas'!$C32) -> 0 | I112: =I25-(I13*'OLD Formulas'!$C32) -> -115.84705 | ... AF112: =AF25-(AF13*'OLD Formulas'!$C32) -> 414.58182 | AG112: =SUM(B112:AF112) -> 27643.069
...

Sheet OLD Formulas
B1: Business Metrics
E2: Source
B3: COGS | C3: Source | E3: 3PL Costs | F3: Bird Buddy | G3: Addons | J3: Shipping Costs
B4: Bird Buddy | C4: 81.22 | E4: Handling Fee | J4: US | K4: 10 | M4: Post-purchase Survey | N4: 45127 | O4: 45128 | P4: 45129 | Q4: 45130 | R4: 45131 | S4: 45132 | T4: 45133 | U4: 45134 | V4: 45135 | W4: 45136 | X4: 45137 | Y4: 45138
B5: Bird Buddy with Solar Roof | C5: 91.14 | E5: Serial Capture | F5: 0.3 | G5: 0 | J5: EU | K5: 35 | M5: Facebook / Instagram | N5: 24 | O5: 44 | P5: 53 | Q5: 53 | R5: 30 | S5: 27 | T5: 26 | U5: 23 | V5: =22+7 -> 29 | W5: =26+6 -> 32 | X5: =22+5 -> 27 | Y5: 28
B6: Solar Roof Single | C6: 10.5 | E6: Storage | F6: 0.31 | G6: 0.31 | M6: Friends / Family | N6: 42 | O6: 58 | P6: 60 | Q6: 56 | R6: 31 | S6: 55 | T6: 34 | U6: 39 | V6: 53 | W6: 51 | X6: 41 | Y6: 53
B7: Wall Mount | C7: 4.93 | E7: Supplies cost | F7: 1.01 | G7: 0.6 | M7: TikTok | N7: 0 | O7: 0 | P7: 1 | Q7: 1 | R7: 2 | S7: 3 | T7: 3 | U7: 3 | V7: 1 | W7: 0 | X7: 0 | Y7: 3
B8: Fence Mount | C8: 6.37 | E8: Pick charge | F8: 0.3 | G8: 0.3 | M8: TV / Radio | N8: 2 | O8: 0 | P8: 1 | Q8: 2 | R8: 0 | S8: 0 | T8: 1 | U8: 1 | V8: 0 | W8: 0 | X8: 0 | Y8: 1
B9: Suet Ball Holder | C9: 1.07 | E9: Pollybag cost | F9: 0 | G9: 1.1 | M9: Blog / Article | N9: 7 | O9: 6 | P9: 2 | Q9: 3 | R9: 1 | S9: 3 | T9: 4 | U9: 2 | V9: 3 | W9: 3 | X9: 3 | Y9: 3
B10: 3-in-1 Nutrition Set | C10: 5.98 | E10: Carton cost | F10: 1.2 | G10: 0 | M10: Reddit | N10: 0 | O10: 0 | P10: 2 | Q10: 1 | R10: 1 | S10: 1 | T10: 0 | U10: 1 | V10: 0 | W10: 0 | X10: 0 | Y10: 0
M11: Google, Youtube | N11: 0 | O11: 4 | P11: 4 | Q11: 8 | R11: 8 | S11: 3 | T11: 2 | U11: 4 | V11: 7 | W11: 7 | X11: 12 | Y11: 2
B12: Bird Buddy Shipping | C12: Source | E12: Add-ons Shipping | M12: Yahoo, Bing | N12: 0 | O12: 0 | P12: 1 | Q12: 0 | R12: 0 | S12: 1 | T12: 0 | U12: 0 | V12: 0 | W12: 0 | X12: 1 | Y12: 0
B13: Inbound (NA) | C13: 11.94 | E13: Inbound (NA) | F13: 1.435 | M13: Total submissions: | N13: =SUM(N5:N12) -> 75 | O13: =SUM(O5:O12) -> 112 | P13: =SUM(P5:P12) -> 124 | Q13: =SUM(Q5:Q12) -> 124 | R13: =SUM(R5:R12) -> 73 | S13: =SUM(S5:S12) -> 93 | T13: =SUM(T5:T12) -> 70 | U13: =SUM(U5:U12) -> 73 | ... Y13: =SUM(Y5:Y12) -> 90
B14: Inbound (Europe) | C14: 11.94 | E14: Inbound (Europe) | F14: 1.44
B15: Inbound (ROW) | C15: 11.94 | E15: Inbound (ROW) | F15: 1.44 | M15: Percentage | N15: 45127 | O15: 45128 | P15: 45129 | Q15: 45130 | R15: 45131 | S15: 45132 | T15: 45133 | U15: 45134 | V15: 45135 | W15: 45136 | X15: 45137 | Y15: 45138
A16: *w/o CA weight | B16: Outbound (NA) | C16: 15.06 | D16: *w/o CA weight | E16: Outbound (NA) | F16: 8.47 | M16: Facebook / Instagram | N16: =N5/$N$13 -> 0.32 | O16: =O5/$O$13 -> 0.39285714 | P16: =P5/$P$13 -> 0.42741935 | Q16: =Q5/$Q$13 -> 0.42741935 | R16: =R5/$R$13 -> 0.4109589 | S16: =S5/$S$13 -> 0.29032258 | T16: =T5/$T$13 -> 0.37142857 | U16: =U5/$U$13 -> 0.31506849 | V16: =V5/$V$13 -> 0.31182796 | W16: =W5/$W$13 -> 0.34408602 | X16: =X5/$X$13 -> 0.32142857 | Y16: =Y5/$Y$13 -> 0.31111111
B17: Outbound (Europe) | C17: 15.06 | E17: Outbound (Europe) | M17: Friends / Family | N17: =N6/$N$13 -> 0.56 | O17: =O6/$O$13 -> 0.51785714 | P17: =P6/$P$13 -> 0.48387097 | Q17: =Q6/$Q$13 -> 0.4516129 | R17: =R6/$R$13 -> 0.42465753 | S17: =S6/$S$13 -> 0.59139785 | T17: =T6/$T$13 -> 0.48571429 | U17: =U6/$U$13 -> 0.53424658 | V17: =V6/$V$13 -> 0.56989247 | W17: =W6/$W$13 -> 0.5483871 | X17: =X6/$X$13 -> 0.48809524 | Y17: =Y6/$Y$13 -> 0.58888889
B18: Outbound (ROW) | C18: 20 | E18: Outbound (ROW) | M18: TikTok | N18: =N7/$N$13 -> 0 | O18: =O7/$O$13 -> 0 | P18: =P7/$P$13 -> 0.0080645161 | Q18: =Q7/$Q$13 -> 0.0080645161 | R18: =R7/$R$13 -> 0.02739726 | S18: =S7/$S$13 -> 0.032258065 | T18: =T7/$T$13 -> 0.042857143 | U18: =U7/$U$13 -> 0.04109589 | V18: =V7/$V$13 -> 0.010752688 | W18: =W7/$W$13 -> 0 | X18: =X7/$X$13 -> 0 | Y18: =Y7/$Y$13 -> 0.033333333
M19: TV / Radio | N19: =N8/$N$13 -> 0.026666667 | O19: =O8/$O$13 -> 0 | P19: =P8/$P$13 -> 0.0080645161 | Q19: =Q8/$Q$13 -> 0.016129032 | R19: =R8/$R$13 -> 0 | S19: =S8/$S$13 -> 0 | T19: =T8/$T$13 -> 0.014285714 | U19: =U8/$U$13 -> 0.01369863 | V19: =V8/$V$13 -> 0 | W19: =W8/$W$13 -> 0 | X19: =X8/$X$13 -> 0 | Y19: =Y8/$Y$13 -> 0.011111111
B20: Marketing Averages (per order) | E20: VAT Averages | M20: Blog / Article | N20: =N9/$N$13 -> 0.093333333 | O20: =O9/$O$13 -> 0.053571429 | P20: =P9/$P$13 -> 0.016129032 | Q20: =Q9/$Q$13 -> 0.024193548 | R20: =R9/$R$13 -> 0.01369863 | S20: =S9/$S$13 -> 0.032258065 | T20: =T9/$T$13 -> 0.057142857 | U20: =U9/$U$13 -> 0.02739726 | V20: =V9/$V$13 -> 0.032258065 | W20: =W9/$W$13 -> 0.032258065 | X20: =X9/$X$13 -> 0.035714286 | Y20: =Y9/$Y$13 -> 0.033333333
B21: COGS | C21: =(C4*(1-F31)+(C5*F31)+(C6*F26)+(C7*F27)+(C8*F28)+(C9*F29)+(C10*F30)) -> 92.470049 | E21: Europe | F21: 0.22 | M21: Reddit | N21: =N10/$N$13 -> 0 | O21: =O10/$O$13 -> 0 | P21: =P10/$P$13 -> 0.016129032 | Q21: =Q10/$Q$13 -> 0.0080645161 | R21: =R10/$R$13 -> 0.01369863 | S21: =S10/$S$13 -> 0.010752688 | T21: =T10/$T$13 -> 0 | U21: =U10/$U$13 -> 0.01369863 | V21: =V10/$V$13 -> 0 | W21: =W10/$W$13 -> 0 | X21: =X10/$X$13 -> 0 | Y21: =Y10/$Y$13 -> 0
B22: Inbound Shipping | C22: =C13+(F13*0.78) -> 13.0593 | E22: ROW | F22: 0.13 | M22: Google, Youtube | N22: =N11/$N$13 -> 0 | O22: =O11/$O$13 -> 0.035714286 | P22: =P11/$P$13 -> 0.032258065 | Q22: =Q11/$Q$13 -> 0.064516129 | R22: =R11/$R$13 -> 0.10958904 | S22: =S11/$S$13 -> 0.032258065 | T22: =T11/$T$13 -> 0.028571429 | U22: =U11/$U$13 -> 0.054794521 | V22: =V11/$V$13 -> 0.075268817 | W22: =W11/$W$13 -> 0.075268817 | X22: =X11/$X$13 -> 0.14285714 | Y22: =Y11/$Y$13 -> 0.022222222
B23: Outbound Shipping | C23: =C16 -> 15.06 | E23: NA | M23: Yahoo, Bing | N23: =N12/$N$13 -> 0 | O23: =O12/$O$13 -> 0 | P23: =P12/$P$13 -> 0.0080645161 | Q23: =Q12/$Q$13 -> 0 | R23: =R12/$R$13 -> 0 | S23: =S12/$S$13 -> 0.010752688 | T23: =T12/$T$13 -> 0 | U23: =U12/$U$13 -> 0 | V23: =V12/$V$13 -> 0 | W23: =W12/$W$13 -> 0 | X23: =X12/$X$13 -> 0.011904762 | Y23: =Y12/$Y$13 -> 0
B24: Taxes and VAT | C24: 10.89
B25: China Tax (7.5%) | C25: =C21*0.075 -> 6.9352537 | E25: Attachment Rates
B26: Duty (3.4%) | C26: =(C6*F26)*0.025+(C7*F27)*0.034+(C9*F29)*0.034+(C10*F30)*0.034 -> 0.13113119 | E26: Solar Roof | F26: =('OLD Detailed Report'!AG170)/'OLD Detailed Report'!AG164 -> 0.11461758
B27: Processing Fee (2,90%) | C27: ='OLD Sales'!B56*0.029 -> 7.1313109 | E27: Wall Mount | F27: =('OLD Detailed Report'!AG166)/'OLD Detailed Report'!AG164 -> 0.33596318
B28: Transaction Fee ($0.30) | C28: =0.3 -> 0.3 | E28: Fence Mount | F28: =('OLD Detailed Report'!AG167)/'OLD Detailed Report'!AG164 -> 0
B29: 3PL - Handling Fee | E29: Suet Ball Holder | F29: =('OLD Detailed Report'!AG168)/'OLD Detailed Report'!AG164 -> 0.17006355
B30: 3PL - Serial Capture | C30: =F5 -> 0.3 | E30: 3-in-1 | F30: =('OLD Detailed Report'!AG169)/'OLD Detailed Report'!AG164 -> 0.18956827
B31: 3PL - Storage Cost | C31: =F6 -> 0.31 | E31: Bird Buddy w/ Solar | F31: ='OLD Detailed Report'!AG140/'OLD Detailed Report'!AG141 -> 0.7131734
B32: All | C32: =SUM(C21:C31) -> 146.58705 | E32: Bird Buddy | F32: =1-F31 -> 0.2868266
B34: Fees | E34: 30 Day Returns
B35: Processing Fee | C35: 0.029 | E35: US Shipping | F35: 10
B36: Duty | C36: 0.034 | E36: EU Shipping | F36: 20
B37: China Tax | C37: 0.075 | E37: ROW Shipping | F37: 20
B38: HMF | C38: 0.00125 | E38: Money Return | F38: 1
B39: MPF | C39: 0.003464
B40: Solar Roof China Tax | C40: 0.075
B41: Solar Roof Duty | C41: 0.025

Sheet SupermetricsQueries
A1: Supermetrics Queries
A3: All the queries created by Supermetrics are stored here, each in its own row.
H4: 17853918
A5: On this sheet you can:
A6: 1. Modify the parameters of a query. Any changes will be visible when you run a refresh.
A8: 2. Remove a query by deleting its row | H8: Europe/Paris
A10: 3. Add new queries: type a range address and query parameters, leave the query ID empty. The query will be added when you run a refresh. (Of course, it's much easier to use the sidebar to add new queries.)
A13: Queries are stored with the authentication of the original user that created the query. If you want to transfer a query to the currently active Google Sheets user, delete its query ID from column A and run a refresh. For complete instructions on transferring queries, see https://support.supermetrics.com/support/solutions/articles/19000050074-how-can-i-transfer-queries-from-one-user-to-another-
A16: Don't delete or rename this sheet. If you delete or rename it, your existing queries can no longer be refreshed. Hiding the sheet is OK. Also, don't delete any rows above row 21.
A19: Query ID | D19: Sheet name | E19: Range address | G19: Created | H19: Updated | I19: Last status | J19: Last refresh ID | K19: Results contain sampled data | L19: Execution time (sec) | M19: Object type | N19: Linked chart ID | O19: Data source | Q19: Date range type | R19: Start date | S19: End date | T19: Compare to | U19: Comparison value type | W19: Accounts/views | X19: Metrics | Y19: Dimensions | Z19: Pivot dimensions | AA19: Filters | AB19: Segment ID | AC19: Sort | AD19: Max rows | AE19: Max pivot categories | AF19: Special settings | AG19: Other parameters | AJ19: Result type | AK19: Language/country | AL19: Translate to | AN19: SQL | AO19: Database name | AP19: Range address (static) | AQ19: Report type | AT19: Highlight with colour | AU19: Refresh with user account | AV19: Returned data | AW19: Refresh button number
A20: paramsID | C20: ssID | D20: sheetName | E20: rangeAddress | G20: created | H20: updated | I20: lastStatus | J20: lastqueryID | K20: sampled | L20: runtime_sec | M20: objType | N20: linkedChartID | O20: dataSource | Q20: dateRangeType | R20: startDateString | S20: endDateString | T20: comp | U20: cvt | W20: profiles | X20: metrics | Y20: dimensions | Z20: sd | AA20: filterArr | AB20: segment | AC20: sort | AD20: maxResults | AE20: maxCategories | AF20: specialSettings | AG20: otherParams | AJ20: sds_result_type | AK20: sds_lang | AL20: sds_tolang | AN20: sql | AO20: db_name | AP20: rangeAddressStatic | AQ20: rt | AR20: scopeMZ | AS20: sortMZ | AT20: condform | AU20: authUser | AV20: metaDataToUser | AW20: refreshButtonNumber

Sheet Business Metrics US
A1: United States
A2: Product | B2: Bird Buddy | C2: Bird Buddy with Solar Roof | D2: Solar Roof | E2: Wall Mount | F2: Suet Ball Holder | G2: 3-in-1 Nutrition Set | H2: Hummingbird Feeder | I2: Perch Extender | J2: Pole System
A3: Category | B3: Bird Feeder | C3: Bird Feeder | D3: Add-on | E3: Add-on | F3: Add-on | G3: Add-on
A5: COGS
A6: Source
A7: Owner | B7: Nick Koukourakis | C7: Nick Koukourakis | D7: Nick Koukourakis | E7: Nick Koukourakis | F7: Nick Koukourakis | G7: Nick Koukourakis
A8: Controller #1 | B8: Diana Spiewak | C8: Diana Spiewak | D8: Diana Spiewak | E8: Diana Spiewak | F8: Diana Spiewak | G8: Diana Spiewak
A9: Controller #2 | B9: Eric Malkowski | C9: Eric Malkowski | D9: Eric Malkowski | E9: Eric Malkowski | F9: Eric Malkowski | G9: Eric Malkowski
A10: Batch | B10: 150000 | C10: 150000
A11: Batch Timeline | B11: April - November | C11: April - November
A13: Chip | B13: 6.1433 | C13: 6.1433 | D13: 0 | E13: 0 | F13: 0 | G13: 0
A14: Other Component | B14: 38.23 | C14: 45.3 | D14: 6.87 | E14: 3.79 | F14: 0.82 | G14: 3.8336
A15: BOM Margin | B15: =(B13+B14)*B23 -> 15.530655 | C15: =(C13+C14)*C23 -> 18.005155 | D15: =(D13+D14)*D23 -> 2.4045 | E15: =(E13+E14)*E23 -> 1.137 | F15: =(F13+F14)*F23 -> 0.246 | G15: =(G13+G14)*G23 -> 1.15008
A16: Packaging and Accessories | B16: 8.1762 | C16: 8.1762 | D16: 0.544 | E16: 0 | F16: 0 | G16: 0.8422
A17: Package Margin | B17: =B16*B24 -> 2.45286 | C17: =C16*C24 -> 2.45286 | D17: =D16*D24 -> 0.1632 | E17: =E16*E24 -> 0 | F17: =F16*F24 -> 0 | G17: =G16*G24 -> 0.25266
A18: Total Product Cost | B18: =SUM(B13:B17) -> 70.533015 | C18: =SUM(C13:C17) -> 80.077515 | D18: =SUM(D13:D17) -> 9.9817 | E18: =SUM(E13:E17) -> 4.927 | F18: =SUM(F13:F17) -> 1.066 | G18: =SUM(G13:G17) -> 6.07854
A20: Finance fee | B20: 10 | C20: 10 | D20: 0 | E20: 0 | F20: 0 | G20: 0
A21: PPV cost component | B21: 1.88 | C21: 1.88 | D21: 0 | E21: 0 | F21: 0 | G21: 0
A23: BOM Margin (%) | B23: 0.35 | C23: 0.35 | D23: 0.35 | E23: 0.3 | F23: 0.3 | G23: 0.3
A24: Package Margin (%) | B24: 0.3 | C24: 0.3 | D24: 0.3 | E24: 0.3 | F24: 0.3 | G24: 0.3
A26: Duty Rate | B26: =sum(B13:B17)*B32 -> 0 | C26: =sum(C13:C17)*C32 -> 0 | D26: =sum(D13:D17)*D32 -> 0.2495425 | E26: =sum(E13:E17)*E32 -> 0.167518 | F26: =sum(F13:F17)*F32 -> 0.036244 | G26: =sum(G13:G17)*G32 -> 0.20667036
A27: Tarrif Rate | B27: =sum(B13:B17)*B33 -> 5.2899761 | C27: =sum(C13:C17)*C33 -> 6.0058136 | D27: =sum(D13:D17)*D33 -> 2.495425 | E27: =sum(E13:E17)*E33 -> 0.369525 | F27: =sum(F13:F17)*F33 -> 0.07995 | G27: =sum(G13:G17)*G33 -> 0.4558905
A28: HMF | B28: =SUM($B$13:$B$17)*B34 -> 0.088166269 | C28: =SUM($B$13:$B$17)*C34 -> 0.088166269 | D28: =SUM($B$13:$B$17)*D34 -> 0.088166269 | E28: =SUM($B$13:$B$17)*E34 -> 0.088166269 | F28: =SUM($B$13:$B$17)*F34 -> 0.088166269 | G28: =SUM($B$13:$B$17)*G34 -> 0.088166269
A29: MPF | B29: =SUM($B$13:$B$17)*B35 -> 0.24432636 | C29: =SUM($B$13:$B$17)*C35 -> 0.24432636 | D29: =SUM($B$13:$B$17)*D35 -> 0.24432636 | E29: =SUM($B$13:$B$17)*E35 -> 0.24432636 | F29: =SUM($B$13:$B$17)*F35 -> 0.24432636 | G29: =SUM($B$13:$B$17)*G35 -> 0.24432636
A30: Total Port Cost | B30: =SUM(B26:B29) -> 5.6224688 | C30: =SUM(C26:C29) -> 6.3383063 | D30: =SUM(D26:D29) -> 3.0774601 | E30: =SUM(E26:E29) -> 0.86953563 | F30: =SUM(F26:F29) -> 0.44868663 | G30: =SUM(G26:G29) -> 0.99505349
A32: Duty Rate (%) | B32: 0 | C32: 0 | D32: 0.025 | E32: 0.034 | F32: 0.034 | G32: 0.034
A33: Tarrif Rate (%) | B33: 0.075 | C33: 0.075 | D33: 0.25 | E33: 0.075 | F33: 0.075 | G33: 0.075
A34: HMF (%) | B34: 0.00125 | C34: 0.00125 | D34: 0.00125 | E34: 0.00125 | F34: 0.00125 | G34: 0.00125
A35: MPF (%) | B35: 0.003464 | C35: 0.003464 | D35: 0.003464 | E35: 0.003464 | F35: 0.003464 | G35: 0.003464
A37: Total Cost | B37: =B18+B20+B21+B30 -> 88.035484 | C37: =C18+C20+C21+C30 -> 98.295821 | D37: =D18+D20+D21+D30 -> 13.05916 | E37: =E18+E20+E21+E30 -> 5.7965356 | F37: =F18+F20+F21+F30 -> 1.5146866 | G37: =G18+G20+G21+G30 -> 7.0735935
A41: Inbound Shipping
A42: Source
A43: Owner | B43: Judy Stanis | C43: Judy Stanis | D43: Judy Stanis | E43: Judy Stanis | F43: Judy Stanis | G43: Judy Stanis
A44: Controller #1 | B44: Diana Spiewak | C44: Diana Spiewak | D44: Diana Spiewak | E44: Diana Spiewak | F44: Diana Spiewak | G44: Diana Spiewak
A45: Controller #2 | B45: Eric Malkowski | C45: Eric Malkowski | D45: Eric Malkowski | E45: Eric Malkowski | F45: Eric Malkowski | G45: Eric Malkowski
A46: Batch
A47: Batch Timeline
A49: Air Freight | B49: 22.88 | C49: 22.88 | D49: 3.06 | E49: 4.88 | F49: 0.75 | G49: 2.55
A50: Fast Ocean | B50: 10.56 | C50: 10.56 | D50: 1.31 | E50: 2.09 | F50: 0.32 | G50: 0.97
A51: Ocean | B51: 2.65 | C51: 2.65 | D51: 0.39 | E51: 0.58 | F51: 0.1 | G51: 0.35
A52: Total Inbound Cost | B52: =(B49*B54)+(B50*B55)+(B56*B51) -> 11.442 | C52: =(C49*C54)+(C50*C55)+(C56*C51) -> 11.442 | D52: =(D49*D54)+(D50*D55)+(D56*D51) -> 1.476 | E52: =(E49*E54)+(E50*E55)+(E56*E51) -> 2.346 | F52: =(F49*F54)+(F50*F55)+(F56*F51) -> 0.362 | G52: =(G49*G54)+(G50*G55)+(G56*G51) -> 1.162
A54: Air Freight (%) | B54: 0.2 | C54: 0.2 | D54: 0.2 | E54: 0.2 | F54: 0.2 | G54: 0.2
A55: Fast Ocean (%) | B55: 0.6 | C55: 0.6 | D55: 0.6 | E55: 0.6 | F55: 0.6 | G55: 0.6
A56: Ocean (%) | B56: 0.2 | C56: 0.2 | D56: 0.2 | E56: 0.2 | F56: 0.2 | G56: 0.2
B57: =SUM(B54:B56) -> 1 | C57: =SUM(C54:C56) -> 1 | D57: =SUM(D54:D56) -> 1 | E57: =SUM(E54:E56) -> 1 | F57: =SUM(F54:F56) -> 1 | G57: =SUM(G54:G56) -> 1
A59: Total Cost | B59: =B37+B52 -> 99.477484 | C59: =C37+C52 -> 109.73782 | D59: =D37+D52 -> 14.53516 | E59: =E37+E52 -> 8.1425356 | F59: =F37+F52 -> 1.8766866 | G59: =G37+G52 -> 8.2355935
A63: Outbound Shipping
A64: Source
A65: Owner | B65: Remzo Hotić | C65: Remzo Hotić | D65: Remzo Hotić | E65: Remzo Hotić | F65: Remzo Hotić | G65: Remzo Hotić
A66: Controller #1 | B66: Diana Spiewak | C66: Diana Spiewak | D66: Diana Spiewak | E66: Diana Spiewak | F66: Diana Spiewak | G66: Diana Spiewak
A67: Controller #2 | B67: Eric Malkowski | C67: Eric Malkowski | D67: Eric Malkowski | E67: Eric Malkowski | F67: Eric Malkowski | G67: Eric Malkowski
A68: Batch
A69: Batch Timeline
A71: Outbound Shipping | B71: 11.94 | C71: 11.94 | D71: 6.28 | E71: 6.28 | F71: 5.78 | G71: 6.28
A72: Customs and Duty
A73: Supplies Cost | B73: 1.01 | C73: 1.01 | D73: 0.6 | E73: 0.6 | F73: 0.6 | G73: 0.6
A74: Pick Charge | B74: 0.3 | C74: 0.3 | D74: 0.3 | E74: 0.3 | F74: 0.3 | G74: 0.3
A75: Pallet Cost | B75: =25/80 -> 0.3125 | C75: =25/80 -> 0.3125 | D75: =25/720 -> 0.034722222 | E75: =25/450 -> 0.055555556 | F75: =25/2940 -> 0.0085034014 | G75: =25/640 -> 0.0390625
A76: PollyBag Cost | B76: 0 | C76: 0 | D76: 1.2 | E76: 1.2 | F76: 1.2 | G76: 1.2
A77: Carton Cost | B77: 1.3 | C77: 1.3 | D77: 0 | E77: 0 | F77: 0 | G77: 0
A78: VAS
A79: Serial Capture | B79: 0.3 | C79: 0.3 | D79: 0 | E79: 0 | F79: 0 | G79: 0
A80: Storage Cost | B80: 0.31 | C80: 0.31 | D80: 0.31 | E80: 0.31 | F80: 0.31 | G80: 0.31
A81: Total Outbound Cost | B81: =SUM(B71:B80) -> 15.4725 | C81: =SUM(C71:C80) -> 15.4725 | D81: =SUM(D71:D80) -> 8.7247222 | E81: =SUM(E71:E80) -> 8.7455556 | F81: =SUM(F71:F80) -> 8.1985034 | G81: =SUM(G71:G80) -> 8.7290625
A83: Total Cost | B83: =B59+B81 -> 114.94998 | C83: =C59+C81 -> 125.21032 | D83: =D59+D81 -> 23.259882 | E83: =E59+E81 -> 16.888091 | F83: =F59+F81 -> 10.07519 | G83: =G59+G81 -> 16.964656
B86: 80 units per pallet | D86: 720 per pallet | E86: 450 per pallet | F86: 2940 per pallet | G86: 640 per pallet

Sheet Business Metrics Canada
A1: Canada
A2: Product | B2: Bird Buddy | C2: Bird Buddy with Solar Roof | D2: Solar Roof | E2: Wall Mount | F2: Suet Ball Holder | G2: 3-in-1 Nutrition Set | H2: Hummingbird Feeder | I2: Perch Extender | J2: Pole System
A3: Category | B3: Bird Feeder | C3: Bird Feeder | D3: Add-on | E3: Add-on | F3: Add-on | G3: Add-on
A5: COGS
A6: Source
A7: Owner | B7: Nick Koukourakis | C7: Nick Koukourakis | D7: Nick Koukourakis | E7: Nick Koukourakis | F7: Nick Koukourakis | G7: Nick Koukourakis
A8: Controller #1 | B8: Diana Spiewak | C8: Diana Spiewak | D8: Diana Spiewak | E8: Diana Spiewak | F8: Diana Spiewak | G8: Diana Spiewak
A9: Controller #2 | B9: Eric Malkowski | C9: Eric Malkowski | D9: Eric Malkowski | E9: Eric Malkowski | F9: Eric Malkowski | G9: Eric Malkowski
A10: Batch | B10: 150000 | C10: 150000
A11: Batch Timeline | B11: April - November | C11: April - November
A13: Chip | B13: 6.1433 | C13: 6.1433 | D13: 0 | E13: 0 | F13: 0 | G13: 0
A14: Other Component | B14: 38.23 | C14: 45.3 | D14: 6.87 | E14: 3.79 | F14: 0.82 | G14: 3.8336
A15: BOM Margin | B15: =(B13+B14)*B23 -> 15.530655 | C15: =(C13+C14)*C23 -> 18.005155 | D15: =(D13+D14)*D23 -> 2.4045 | E15: =(E13+E14)*E23 -> 1.137 | F15: =(F13+F14)*F23 -> 0.246 | G15: =(G13+G14)*G23 -> 1.15008
A16: Packaging and Accessories | B16: 8.1762 | C16: 8.1762 | D16: 0.544 | E16: 0 | F16: 0 | G16: 0.8422
A17: Package Margin | B17: =B16*B24 -> 2.45286 | C17: =C16*C24 -> 2.45286 | D17: =D16*D24 -> 0.1632 | E17: =E16*E24 -> 0 | F17: =F16*F24 -> 0 | G17: =G16*G24 -> 0.25266
A18: Total Product Cost | B18: =SUM(B13:B17) -> 70.533015 | C18: =SUM(C13:C17) -> 80.077515 | D18: =SUM(D13:D17) -> 9.9817 | E18: =SUM(E13:E17) -> 4.927 | F18: =SUM(F13:F17) -> 1.066 | G18: =SUM(G13:G17) -> 6.07854
A20: Finance fee | B20: 10 | C20: 10 | D20: 0 | E20: 0 | F20: 0 | G20: 0
A21: PPV cost component | B21: 1.88 | C21: 1.88 | D21: 0 | E21: 0 | F21: 0 | G21: 0
A23: BOM Margin (%) | B23: 0.35 | C23: 0.35 | D23: 0.35 | E23: 0.3 | F23: 0.3 | G23: 0.3
A24: Package Margin (%) | B24: 0.3 | C24: 0.3 | D24: 0.3 | E24: 0.3 | F24: 0.3 | G24: 0.3
A26: Duty Rate | B26: =sum(B13:B17)*B32 -> 0 | C26: =sum(C13:C17)*C32 -> 0 | D26: =sum(D13:D17)*D32 -> 0.2495425 | E26: =sum(E13:E17)*E32 -> 0.167518 | F26: =sum(F13:F17)*F32 -> 0.036244 | G26: =sum(G13:G17)*G32 -> 0.20667036
A27: Tarrif Rate | B27: =sum(B13:B17)*B33 -> 5.2899761 | C27: =sum(C13:C17)*C33 -> 6.0058136 | D27: =sum(D13:D17)*D33 -> 2.495425 | E27: =sum(E13:E17)*E33 -> 0.369525 | F27: =sum(F13:F17)*F33 -> 0.07995 | G27: =sum(G13:G17)*G33 -> 0.4558905
A28: HMF | B28: =SUM($B$13:$B$17)*B34 -> 0.088166269 | C28: =SUM($B$13:$B$17)*C34 -> 0.088166269 | D28: =SUM($B$13:$B$17)*D34 -> 0.088166269 | E28: =SUM($B$13:$B$17)*E34 -> 0.088166269 | F28: =SUM($B$13:$B$17)*F34 -> 0.088166269 | G28: =SUM($B$13:$B$17)*G34 -> 0.088166269
A29: MPF | B29: =SUM($B$13:$B$17)*B35 -> 0.24432636 | C29: =SUM($B$13:$B$17)*C35 -> 0.24432636 | D29: =SUM($B$13:$B$17)*D35 -> 0.24432636 | E29: =SUM($B$13:$B$17)*E35 -> 0.24432636 | F29: =SUM($B$13:$B$17)*F35 -> 0.24432636 | G29: =SUM($B$13:$B$17)*G35 -> 0.24432636
A30: Total Port Cost | B30: =SUM(B26:B29) -> 5.6224688 | C30: =SUM(C26:C29) -> 6.3383063 | D30: =SUM(D26:D29) -> 3.0774601 | E30: =SUM(E26:E29) -> 0.86953563 | F30: =SUM(F26:F29) -> 0.44868663 | G30: =SUM(G26:G29) -> 0.99505349
A32: Duty Rate (%) | B32: 0 | C32: 0 | D32: 0.025 | E32: 0.034 | F32: 0.034 | G32: 0.034
A33: Tarrif Rate (%) | B33: 0.075 | C33: 0.075 | D33: 0.25 | E33: 0.075 | F33: 0.075 | G33: 0.075
A34: HMF (%) | B34: 0.00125 | C34: 0.00125 | D34: 0.00125 | E34: 0.00125 | F34: 0.00125 | G34: 0.00125
A35: MPF (%) | B35: 0.003464 | C35: 0.003464 | D35: 0.003464 | E35: 0.003464 | F35: 0.003464 | G35: 0.003464
A37: Total Cost | B37: =B18+B20+B21+B30 -> 88.035484 | C37: =C18+C20+C21+C30 -> 98.295821 | D37: =D18+D20+D21+D30 -> 13.05916 | E37: =E18+E20+E21+E30 -> 5.7965356 | F37: =F18+F20+F21+F30 -> 1.5146866 | G37: =G18+G20+G21+G30 -> 7.0735935
A41: Inbound Shipping
A42: Source
A43: Owner | B43: Judy Stanis | C43: Judy Stanis | D43: Judy Stanis | E43: Judy Stanis | F43: Judy Stanis | G43: Judy Stanis
A44: Controller #1 | B44: Diana Spiewak | C44: Diana Spiewak | D44: Diana Spiewak | E44: Diana Spiewak | F44: Diana Spiewak | G44: Diana Spiewak
A45: Controller #2 | B45: Eric Malkowski | C45: Eric Malkowski | D45: Eric Malkowski | E45: Eric Malkowski | F45: Eric Malkowski | G45: Eric Malkowski
A46: Batch
A47: Batch Timeline
A49: Air Freight | B49: 22.88 | C49: 22.88 | D49: 3.06 | E49: 4.88 | F49: 0.75 | G49: 2.55
A50: Fast Ocean | B50: 10.56 | C50: 10.56 | D50: 1.31 | E50: 2.09 | F50: 0.32 | G50: 0.97
A51: Ocean | B51: 2.65 | C51: 2.65 | D51: 0.39 | E51: 0.58 | F51: 0.1 | G51: 0.35
A52: Total Inbound Cost | B52: =(B49*B54)+(B50*B55)+(B56*B51) -> 11.442 | C52: =(C49*C54)+(C50*C55)+(C56*C51) -> 11.442 | D52: =(D49*D54)+(D50*D55)+(D56*D51) -> 1.476 | E52: =(E49*E54)+(E50*E55)+(E56*E51) -> 2.346 | F52: =(F49*F54)+(F50*F55)+(F56*F51) -> 0.362 | G52: =(G49*G54)+(G50*G55)+(G56*G51) -> 1.162
A54: Air Freight (%) | B54: 0.2 | C54: 0.2 | D54: 0.2 | E54: 0.2 | F54: 0.2 | G54: 0.2
A55: Fast Ocean (%) | B55: 0.6 | C55: 0.6 | D55: 0.6 | E55: 0.6 | F55: 0.6 | G55: 0.6
A56: Ocean (%) | B56: 0.2 | C56: 0.2 | D56: 0.2 | E56: 0.2 | F56: 0.2 | G56: 0.2
B57: =SUM(B54:B56) -> 1 | C57: =SUM(C54:C56) -> 1 | D57: =SUM(D54:D56) -> 1 | E57: =SUM(E54:E56) -> 1 | F57: =SUM(F54:F56) -> 1 | G57: =SUM(G54:G56) -> 1
A59: Total Cost | B59: =B37+B52 -> 99.477484 | C59: =C37+C52 -> 109.73782 | D59: =D37+D52 -> 14.53516 | E59: =E37+E52 -> 8.1425356 | F59: =F37+F52 -> 1.8766866 | G59: =G37+G52 -> 8.2355935
A63: Outbound Shipping
A64: Source
A65: Owner | B65: Remzo Hotić | C65: Remzo Hotić | D65: Remzo Hotić | E65: Remzo Hotić | F65: Remzo Hotić | G65: Remzo Hotić
A66: Controller #1 | B66: Diana Spiewak | C66: Diana Spiewak | D66: Diana Spiewak | E66: Diana Spiewak | F66: Diana Spiewak | G66: Diana Spiewak
A67: Controller #2 | B67: Eric Malkowski | C67: Eric Malkowski | D67: Eric Malkowski | E67: Eric Malkowski | F67: Eric Malkowski | G67: Eric Malkowski
A68: Batch
A69: Batch Timeline
A71: Outbound Shipping | B71: 44 | C71: 44 | D71: 22 | E71: 22 | F71: 22 | G71: 22
A72: Customs and Duty
A73: Supplies Cost | B73: 1.01 | C73: 1.01 | D73: 0.6 | E73: 0.6 | F73: 0.6 | G73: 0.6
A74: Pick Charge | B74: 0.35 | C74: 0.35 | D74: 0.35 | E74: 0.35 | F74: 0.35 | G74: 0.35
A75: Pallet Cost | B75: 0.31 | C75: 0.31 | D75: 0.03 | E75: 0.06 | F75: 0.01 | G75: 0.04
A76: PollyBag Cost | B76: 0 | C76: 0 | D76: 1.2 | E76: 1.2 | F76: 1.2 | G76: 1.2
A77: Carton Cost | B77: 1.3 | C77: 1.3 | D77: 0 | E77: 0 | F77: 0 | G77: 0
A78: VAS
A79: Serial Capture | B79: 0.3 | C79: 0.3 | D79: 0 | E79: 0 | F79: 0 | G79: 0
A80: Storage Cost | B80: 0.31 | C80: 0.31 | D80: 0.31 | E80: 0.31 | F80: 0.31 | G80: 0.31
A81: Total Outbound Cost | B81: =SUM(B71:B80) -> 47.58 | C81: =SUM(C71:C80) -> 47.58 | D81: =SUM(D71:D80) -> 24.49 | E81: =SUM(E71:E80) -> 24.52 | F81: =SUM(F71:F80) -> 24.47 | G81: =SUM(G71:G80) -> 24.5
A83: Total Cost | B83: =B59+B81 -> 147.05748 | C83: =C59+C81 -> 157.31782 | D83: =D59+D81 -> 39.02516 | E83: =E59+E81 -> 32.662536 | F83: =F59+F81 -> 26.346687 | G83: =G59+G81 -> 32.735593
C87: Price | D87: 70 | E87: 24 | F87: 14 | G87: 29
C88: Shipping | D88: 10 | E88: 10 | F88: 10 | G88: 10
D89: =(D87-D83)+D88 -> 40.97484 | E89: =(E87-E83)+E88 -> 1.3374644 | F89: =(F87-F83)+F88 -> -2.3466866 | G89: =(G87-G83)+G88 -> 6.2644065
C91: Tax | D91: =D87*0.13 -> 9.1 | E91: =E87*0.13 -> 3.12 | F91: =F87*0.13 -> 1.82 | G91: =G87*0.13 -> 3.77
C93: Total | D93: =D89-D91 -> 31.87484 | E93: =E89-E91 -> -1.7825356 | F93: =F89-F91 -> -4.1666866 | G93: =G89-G91 -> 2.4944065

Sheet Forecast projection
A2: Start date: | B2: 44933 | D2: End date: | E2: 31/07/2023 | G2: 2023 benchmark per month | I2: 2023 benchmark per day
A3: Days | B3: 31 | C3: REVENUE | G3: AVG revenue per month | H3: 1442794 | I3: AVG revenue per day | J3: 58775
A4: Current day | B4: =count('OLD Sales'!B15:AF15) -> 31 | G4: AVG orders per month | H4: 6922 | I4: AVG orders per day | J4: 230
B5: ACTUALS | D5: Linear Projection | G5: AVG investments per month | H5: 509669 | I5: AVG investments per day | J5: 16862
A6: DAYS | B6: REVENUE PLAN | C6: Current day | D6: Linear Projection | E6: % Plan (linear projection) | F6: Linear Projection GAP | G6: Avg users per month | H6: 606911 | I6: Avg users per day (cca.) | J6: 20230
A7: 1 | B7: =$B$38/$B$3 -> 64516.129 | C7: ='OLD Sales'!B14 -> 49127.2 | D7: =C7/$B$4*$B$3 -> 49127.2 | E7: =D7/B7-1 -> -0.2385284 | F7: =D7-B7 -> -15388.929 | G7: AVG ROAS per month | H7: 3.63
A8: 2 | B8: =$B$38/$B$3 -> 64516.129 | C8: ='OLD Sales'!C14 -> 44359.94 | D8: =C8/$B$4*$B$3 -> 44359.94 | E8: =D8/B8-1 -> -0.31242093 | F8: =D8-B8 -> -20156.189 | G8: AVG CPO per month | H8: 0.3
A9: 3 | B9: =$B$38/$B$3 -> 64516.129 | C9: ='OLD Sales'!D14 -> 41176.95 | D9: =C9/$B$4*$B$3 -> 41176.95 | E9: =D9/B9-1 -> -0.36175727 | F9: =D9-B9 -> -23339.179 | G9: AVG CR per month | H9: 0,91%
A10: 4 | B10: =$B$38/$B$3 -> 64516.129 | C10: ='OLD Sales'!E14 -> 43682.34 | D10: =C10/$B$4*$B$3 -> 43682.34 | E10: =D10/B10-1 -> -0.32292373 | F10: =D10-B10 -> -20833.789 | G10: AVG AOV per month | H10: 256.11
A11: 5 | B11: =$B$38/$B$3 -> 64516.129 | C11: ='OLD Sales'!F14 -> 40447.23 | D11: =C11/$B$4*$B$3 -> 40447.23 | E11: =D11/B11-1 -> -0.37306794 | F11: =D11-B11 -> -24068.899
A12: 6 | B12: =$B$38/$B$3 -> 64516.129 | C12: ='OLD Sales'!G14 -> 43380.21 | D12: =C12/$B$4*$B$3 -> 43380.21 | E12: =D12/B12-1 -> -0.32760674 | F12: =D12-B12 -> -21135.919 | G12: How can we achieve the plan? (KPI-s perspective) - MTD | H12: Planned MTD | I12: Actuals MTD | J12: Realization %
A13: 7 | B13: =$B$38/$B$3 -> 64516.129 | C13: ='OLD Sales'!H14 -> 47720.49 | D13: =C13/$B$4*$B$3 -> 47720.49 | E13: =D13/B13-1 -> -0.2603324 | F13: =D13-B13 -> -16795.639 | G13: Planned revenue | H13: 2000000 | I13: =C38 -> 1411507.8 | J13: =I13/H13-1 -> -0.29424613
A14: 8 | B14: =$B$38/$B$3 -> 64516.129 | C14: ='OLD Sales'!I14 -> 53389.16 | D14: =C14/$B$4*$B$3 -> 53389.16 | E14: =D14/B14-1 -> -0.17246802 | F14: =D14-B14 -> -11126.969 | G14: Planned orders | H14: 7800 | I14: =sum('OLD Sales'!B15:AF15) -> 5740 | J14: =I14/H14-1 -> -0.26410256
A15: 9 | B15: =$B$38/$B$3 -> 64516.129 | C15: ='OLD Sales'!J14 -> 55427.36 | D15: =C15/$B$4*$B$3 -> 55427.36 | E15: =D15/B15-1 -> -0.14087592 | F15: =D15-B15 -> -9088.769 | G15: Planned investments (marketing activites) | H15: 700000 | I15: =sum('OLD Sales'!B26:AF26) -> 542625.68 | J15: =I15/H15-1 -> -0.22482046
A16: 10 | B16: =$B$38/$B$3 -> 64516.129 | C16: ='OLD Sales'!K14 -> 45887.67 | D16: =C16/$B$4*$B$3 -> 45887.67 | E16: =D16/B16-1 -> -0.28874111 | F16: =D16-B16 -> -18628.459 | G16: Planned ROAS | H16: =H13/H15 -> 2.8571429 | I16: =I13/I15 -> 2.601255 | J16: =I16/H16-1 -> -0.089560759
A17: 11 | B17: =$B$38/$B$3 -> 64516.129 | C17: ='OLD Sales'!L14 -> 51043.74 | D17: =C17/$B$4*$B$3 -> 51043.74 | E17: =D17/B17-1 -> -0.20882203 | F17: =D17-B17 -> -13472.389 | G17: Planned CPO | H17: =H15/H13 -> 0.35 | I17: =I15/I13 -> 0.38442983 | J17: =I17/H17-1 -> 0.098370934
A18: 12 | B18: =$B$38/$B$3 -> 64516.129 | C18: ='OLD Sales'!M14 -> 51340.77 | D18: =C18/$B$4*$B$3 -> 51340.77 | E18: =D18/B18-1 -> -0.20421807 | F18: =D18-B18 -> -13175.359 | G18: Planned CR | H18: 0.0125 | I18: =I14/I20 -> 0.016463219 | J18: =I18/H18-1 -> 0.3170575
A19: 13 | B19: =$B$38/$B$3 -> 64516.129 | C19: ='OLD Sales'!N14 -> 80153.53 | D19: =C19/$B$4*$B$3 -> 80153.53 | E19: =D19/B19-1 -> 0.24237971 | F19: =D19-B19 -> 15637.401 | G19: Planned AOV | H19: =H13/H14 -> 256.41026 | I19: =I13/I14 -> 245.90727 | J19: =I19/H19-1 -> -0.040961633
A20: 14 | B20: =$B$38/$B$3 -> 64516.129 | C20: ='OLD Sales'!O14 -> 68572.56 | D20: =C20/$B$4*$B$3 -> 68572.56 | E20: =D20/B20-1 -> 0.06287468 | F20: =D20-B20 -> 4056.431 | G20: Planned Website traffic | H20: =H14/H18 -> 624000 | I20: =sum(C83:C113) -> 348656 | J20: =I20/H20-1 -> -0.44125641
A21: 15 | B21: =$B$38/$B$3 -> 64516.129 | C21: ='OLD Sales'!P14 -> 60624.25 | D21: =C21/$B$4*$B$3 -> 60624.25 | E21: =D21/B21-1 -> -0.060324125 | F21: =D21-B21 -> -3891.879
A22: 16 | B22: =$B$38/$B$3 -> 64516.129 | C22: ='OLD Sales'!Q14 -> 59856.53 | D22: =C22/$B$4*$B$3 -> 59856.53 | E22: =D22/B22-1 -> -0.072223785 | F22: =D22-B22 -> -4659.599 | G22: Legend: | H22: plan input data | I22: formulas
A23: 17 | B23: =$B$38/$B$3 -> 64516.129 | C23: ='OLD Sales'!R14 -> 32044.25 | D23: =C23/$B$4*$B$3 -> 32044.25 | E23: =D23/B23-1 -> -0.50331412 | F23: =D23-B23 -> -32471.879
A24: 18 | B24: =$B$38/$B$3 -> 64516.129 | C24: ='OLD Sales'!S14 -> 60316.3 | D24: =C24/$B$4*$B$3 -> 60316.3 | E24: =D24/B24-1 -> -0.06509735 | F24: =D24-B24 -> -4199.829
A25: 19 | B25: =$B$38/$B$3 -> 64516.129 | C25: ='OLD Sales'!T14 -> 43139.27 | D25: =C25/$B$4*$B$3 -> 43139.27 | E25: =D25/B25-1 -> -0.33134132 | F25: =D25-B25 -> -21376.859
A26: 20 | B26: =$B$38/$B$3 -> 64516.129 | C26: ='OLD Sales'!U14 -> 47288.79 | D26: =C26/$B$4*$B$3 -> 47288.79 | E26: =D26/B26-1 -> -0.26702375 | F26: =D26-B26 -> -17227.339
A27: 21 | B27: =$B$38/$B$3 -> 64516.129 | C27: ='OLD Sales'!V14 -> 48826.1 | D27: =C27/$B$4*$B$3 -> 48826.1 | E27: =D27/B27-1 -> -0.24319545 | F27: =D27-B27 -> -15690.029
A28: 22 | B28: =$B$38/$B$3 -> 64516.129 | C28: ='OLD Sales'!W14 -> 41957.56 | D28: =C28/$B$4*$B$3 -> 41957.56 | E28: =D28/B28-1 -> -0.34965782 | F28: =D28-B28 -> -22558.569
A29: 23 | B29: =$B$38/$B$3 -> 64516.129 | C29: ='OLD Sales'!X14 -> 40174.12 | D29: =C29/$B$4*$B$3 -> 40174.12 | E29: =D29/B29-1 -> -0.37730114 | F29: =D29-B29 -> -24342.009
A30: 24 | B30: =$B$38/$B$3 -> 64516.129 | C30: ='OLD Sales'!Y14 -> 31487.95 | D30: =C30/$B$4*$B$3 -> 31487.95 | E30: =D30/B30-1 -> -0.51193678 | F30: =D30-B30 -> -33028.179
A31: 25 | B31: =$B$38/$B$3 -> 64516.129 | C31: ='OLD Sales'!Z14 -> 36143.33 | D31: =C31/$B$4*$B$3 -> 36143.33 | E31: =D31/B31-1 -> -0.43977838 | F31: =D31-B31 -> -28372.799
A32: 26 | B32: =$B$38/$B$3 -> 64516.129 | C32: ='OLD Sales'!AA14 -> 30366.88 | D32: =C32/$B$4*$B$3 -> 30366.88 | E32: =D32/B32-1 -> -0.52931336 | F32: =D32-B32 -> -34149.249
A33: 27 | B33: =$B$38/$B$3 -> 64516.129 | C33: ='OLD Sales'!AB14 -> 34701.54 | D33: =C33/$B$4*$B$3 -> 34701.54 | E33: =D33/B33-1 -> -0.46212613 | F33: =D33-B33 -> -29814.589
A34: 28 | B34: =$B$38/$B$3 -> 64516.129 | C34: ='OLD Sales'!AC14 -> 30849.69 | D34: =C34/$B$4*$B$3 -> 30849.69 | E34: =D34/B34-1 -> -0.5218298 | F34: =D34-B34 -> -33666.439
A35: 29 | B35: =$B$38/$B$3 -> 64516.129 | C35: ='OLD Sales'!AD14 -> 32381.7 | D35: =C35/$B$4*$B$3 -> 32381.7 | E35: =D35/B35-1 -> -0.49808365 | F35: =D35-B35 -> -32134.429
A36: 30 | B36: =$B$38/$B$3 -> 64516.129 | C36: ='OLD Sales'!AE14 -> 31165.57 | D36: =C36/$B$4*$B$3 -> 31165.57 | E36: =D36/B36-1 -> -0.51693367 | F36: =D36-B36 -> -33350.559
A37: 31 | B37: =$B$38/$B$3 -> 64516.129 | C37: ='OLD Sales'!AF14 -> 34474.77 | D37: =C37/$B$4*$B$3 -> 34474.77 | E37: =D37/B37-1 -> -0.46564107 | F37: =D37-B37 -> -30041.359
A38: TOTAL | B38: =H13 -> 2000000 | C38: =sum(C7:C37) -> 1411507.8 | D38: =C38/$B$4*$B$3 -> 1411507.8 | E38: =D38/B38-1 -> -0.29424613 | F38: =D38-B38 -> -588492.25
A40: Start date: | B40: 44933 | D40: End date: | E40: 31/07/2023
A41: Days | B41: 31 | C41: INVESTMENTS
A42: Current day | B42: =COUNT('OLD Sales'!B15:AF15) -> 31
B43: ACTUALS | D43: Linear Projection
A44: DAYS | B44: INVESTMENT PLAN | C44: Current day | D44: Linear Projection | E44: % Plan (linear projection) | F44: Linear Projection GAP
A45: 1 | B45: =$B$76/$B$41 -> 22580.645 | C45: ='OLD Sales'!B26 -> 11327.86 | D45: =C45/$B$4*$B$3 -> 11327.86 | E45: =D45/B45-1 -> -0.49833763 | F45: =D45-B45 -> -11252.785
A46: 2 | B46: =$B$76/$B$41 -> 22580.645 | C46: ='OLD Sales'!C26 -> 13517.97 | D46: =C46/$B$4*$B$3 -> 13517.97 | E46: =D46/B46-1 -> -0.40134704 | F46: =D46-B46 -> -9062.6752
A47: 3 | B47: =$B$76/$B$41 -> 22580.645 | C47: ='OLD Sales'!D26 -> 15222.62 | D47: =C47/$B$4*$B$3 -> 15222.62 | E47: =D47/B47-1 -> -0.3258554 | F47: =D47-B47 -> -7358.0252
A48: 4 | B48: =$B$76/$B$41 -> 22580.645 | C48: ='OLD Sales'!E26 -> 17391.59 | D48: =C48/$B$4*$B$3 -> 17391.59 | E48: =D48/B48-1 -> -0.22980101 | F48: =D48-B48 -> -5189.0552
A49: 5 | B49: =$B$76/$B$41 -> 22580.645 | C49: ='OLD Sales'!F26 -> 16628.56 | D49: =C49/$B$4*$B$3 -> 16628.56 | E49: =D49/B49-1 -> -0.26359234 | F49: =D49-B49 -> -5952.0852
A50: 6 | B50: =$B$76/$B$41 -> 22580.645 | C50: ='OLD Sales'!G26 -> 16709.03 | D50: =C50/$B$4*$B$3 -> 16709.03 | E50: =D50/B50-1 -> -0.26002867 | F50: =D50-B50 -> -5871.6152
A51: 7 | B51: =$B$76/$B$41 -> 22580.645 | C51: ='OLD Sales'!H26 -> 17024.02 | D51: =C51/$B$4*$B$3 -> 17024.02 | E51: =D51/B51-1 -> -0.24607911 | F51: =D51-B51 -> -5556.6252
A52: 8 | B52: =$B$76/$B$41 -> 22580.645 | C52: ='OLD Sales'!I26 -> 17663.92 | D52: =C52/$B$4*$B$3 -> 17663.92 | E52: =D52/B52-1 -> -0.21774069 | F52: =D52-B52 -> -4916.7252
A53: 9 | B53: =$B$76/$B$41 -> 22580.645 | C53: ='OLD Sales'!J26 -> 20961.74 | D53: =C53/$B$4*$B$3 -> 20961.74 | E53: =D53/B53-1 -> -0.071694371 | F53: =D53-B53 -> -1618.9052
A54: 10 | B54: =$B$76/$B$41 -> 22580.645 | C54: ='OLD Sales'!K26 -> 19992.76 | D54: =C54/$B$4*$B$3 -> 19992.76 | E54: =D54/B54-1 -> -0.11460634 | F54: =D54-B54 -> -2587.8852
A55: 11 | B55: =$B$76/$B$41 -> 22580.645 | C55: ='OLD Sales'!L26 -> 18412 | D55: =C55/$B$4*$B$3 -> 18412 | E55: =D55/B55-1 -> -0.18461143 | F55: =D55-B55 -> -4168.6452
A56: 12 | B56: =$B$76/$B$41 -> 22580.645 | C56: ='OLD Sales'!M26 -> 13259.68 | D56: =C56/$B$4*$B$3 -> 13259.68 | E56: =D56/B56-1 -> -0.4127856 | F56: =D56-B56 -> -9320.9652
A57: 13 | B57: =$B$76/$B$41 -> 22580.645 | C57: ='OLD Sales'!N26 -> 13518.4 | D57: =C57/$B$4*$B$3 -> 13518.4 | E57: =D57/B57-1 -> -0.401328 | F57: =D57-B57 -> -9062.2452
A58: 14 | B58: =$B$76/$B$41 -> 22580.645 | C58: ='OLD Sales'!O26 -> 17427.33 | D58: =C58/$B$4*$B$3 -> 17427.33 | E58: =D58/B58-1 -> -0.22821824 | F58: =D58-B58 -> -5153.3152
A59: 15 | B59: =$B$76/$B$41 -> 22580.645 | C59: ='OLD Sales'!P26 -> 22526.89 | D59: =C59/$B$4*$B$3 -> 22526.89 | E59: =D59/B59-1 -> -0.0023805857 | F59: =D59-B59 -> -53.755161
A60: 16 | B60: =$B$76/$B$41 -> 22580.645 | C60: ='OLD Sales'!Q26 -> 25721.72 | D60: =C60/$B$4*$B$3 -> 25721.72 | E60: =D60/B60-1 -> 0.13910474 | F60: =D60-B60 -> 3141.0748
A61: 17 | B61: =$B$76/$B$41 -> 22580.645 | C61: ='OLD Sales'!R26 -> 19138.35 | D61: =C61/$B$4*$B$3 -> 19138.35 | E61: =D61/B61-1 -> -0.1524445 | F61: =D61-B61 -> -3442.2952
A62: 18 | B62: =$B$76/$B$41 -> 22580.645 | C62: ='OLD Sales'!S26 -> 20674.57 | D62: =C62/$B$4*$B$3 -> 20674.57 | E62: =D62/B62-1 -> -0.0844119 | F62: =D62-B62 -> -1906.0752
A63: 19 | B63: =$B$76/$B$41 -> 22580.645 | C63: ='OLD Sales'!T26 -> 20199.92 | D63: =C63/$B$4*$B$3 -> 20199.92 | E63: =D63/B63-1 -> -0.10543211 | F63: =D63-B63 -> -2380.7252
A64: 20 | B64: =$B$76/$B$41 -> 22580.645 | C64: ='OLD Sales'!U26 -> 20401.34 | D64: =C64/$B$4*$B$3 -> 20401.34 | E64: =D64/B64-1 -> -0.096512086 | F64: =D64-B64 -> -2179.3052
A65: 21 | B65: =$B$76/$B$41 -> 22580.645 | C65: ='OLD Sales'!V26 -> 21451.15 | D65: =C65/$B$4*$B$3 -> 21451.15 | E65: =D65/B65-1 -> -0.0500205 | F65: =D65-B65 -> -1129.4952
A66: 22 | B66: =$B$76/$B$41 -> 22580.645 | C66: ='OLD Sales'!W26 -> 23411.02 | D66: =C66/$B$4*$B$3 -> 23411.02 | E66: =D66/B66-1 -> 0.036773743 | F66: =D66-B66 -> 830.37484
A67: 23 | B67: =$B$76/$B$41 -> 22580.645 | C67: ='OLD Sales'!X26 -> 25874.43 | D67: =C67/$B$4*$B$3 -> 25874.43 | E67: =D67/B67-1 -> 0.14586761 | F67: =D67-B67 -> 3293.7848
A68: 24 | B68: =$B$76/$B$41 -> 22580.645 | C68: ='OLD Sales'!Y26 -> 18694.33 | D68: =C68/$B$4*$B$3 -> 18694.33 | E68: =D68/B68-1 -> -0.17210824 | F68: =D68-B68 -> -3886.3152
A69: 25 | B69: =$B$76/$B$41 -> 22580.645 | C69: ='OLD Sales'!Z26 -> 16639.97 | D69: =C69/$B$4*$B$3 -> 16639.97 | E69: =D69/B69-1 -> -0.26308704 | F69: =D69-B69 -> -5940.6752
A70: 26 | B70: =$B$76/$B$41 -> 22580.645 | C70: ='OLD Sales'!AA26 -> 15867.8 | D70: =C70/$B$4*$B$3 -> 15867.8 | E70: =D70/B70-1 -> -0.29728314 | F70: =D70-B70 -> -6712.8452
A71: 27 | B71: =$B$76/$B$41 -> 22580.645 | C71: ='OLD Sales'!AB26 -> 14258.22 | D71: =C71/$B$4*$B$3 -> 14258.22 | E71: =D71/B71-1 -> -0.36856454 | F71: =D71-B71 -> -8322.4252
A72: 28 | B72: =$B$76/$B$41 -> 22580.645 | C72: ='OLD Sales'!AC26 -> 13700.92 | D72: =C72/$B$4*$B$3 -> 13700.92 | E72: =D72/B72-1 -> -0.39324497 | F72: =D72-B72 -> -8879.7252
A73: 29 | B73: =$B$76/$B$41 -> 22580.645 | C73: ='OLD Sales'!AD26 -> 12603.61 | D73: =C73/$B$4*$B$3 -> 12603.61 | E73: =D73/B73-1 -> -0.44184013 | F73: =D73-B73 -> -9977.0352
A74: 30 | B74: =$B$76/$B$41 -> 22580.645 | C74: ='OLD Sales'!AE26 -> 12166.5 | D74: =C74/$B$4*$B$3 -> 12166.5 | E74: =D74/B74-1 -> -0.46119786 | F74: =D74-B74 -> -10414.145
A75: 31 | B75: =$B$76/$B$41 -> 22580.645 | C75: ='OLD Sales'!AF26 -> 10237.46 | D75: =C75/$B$4*$B$3 -> 10237.46 | E75: =D75/B75-1 -> -0.54662677 | F75: =D75-B75 -> -12343.185
A76: TOTAL | B76: =H15 -> 700000 | C76: =sum(C45:C75) -> 542625.68 | D76: =C76/$B$4*$B$3 -> 542625.68 | E76: =D76/B76-1 -> -0.22482046 | F76: =D76-B76 -> -157374.32
A78: Start date: | B78: 44933 | D78: End date: | E78: 31/07/2023
A79: Days | B79: 31 | C79: TRAFFIC (Sessions GA4)
A80: Current day | B80: =COUNT(C83:C113) -> 31
B81: ACTUALS | D81: Linear Projection
A82: DAYS | B82: TRAFFIC PLAN | C82: Current day | D82: Linear Projection | E82: % Plan (linear projection) | F82: Linear Projection GAP
A83: 1 | B83: =$B$114/$B$79 -> 20129.032 | C83: 10846 | D83: =C83/$B$4*$B$3 -> 10846 | E83: =D83/B83-1 -> -0.46117628 | F83: =D83-B83 -> -9283.0323
A84: 2 | B84: =$B$114/$B$79 -> 20129.032 | C84: 12273 | D84: =C84/$B$4*$B$3 -> 12273 | E84: =D84/B84-1 -> -0.39028365 | F84: =D84-B84 -> -7856.0323
A85: 3 | B85: =$B$114/$B$79 -> 20129.032 | C85: 12077 | D85: =C85/$B$4*$B$3 -> 12077 | E85: =D85/B85-1 -> -0.40002083 | F85: =D85-B85 -> -8052.0323
A86: 4 | B86: =$B$114/$B$79 -> 20129.032 | C86: 12183 | D86: =C86/$B$4*$B$3 -> 12183 | E86: =D86/B86-1 -> -0.39475481 | F86: =D86-B86 -> -7946.0323
A87: 5 | B87: =$B$114/$B$79 -> 20129.032 | C87: 10976 | D87: =C87/$B$4*$B$3 -> 10976 | E87: =D87/B87-1 -> -0.45471795 | F87: =D87-B87 -> -9153.0323
A88: 6 | B88: =$B$114/$B$79 -> 20129.032 | C88: 11393 | D88: =C88/$B$4*$B$3 -> 11393 | E88: =D88/B88-1 -> -0.4340016 | F88: =D88-B88 -> -8736.0323
A89: 7 | B89: =$B$114/$B$79 -> 20129.032 | C89: 12209 | D89: =C89/$B$4*$B$3 -> 12209 | E89: =D89/B89-1 -> -0.39346314 | F89: =D89-B89 -> -7920.0323
A90: 8 | B90: =$B$114/$B$79 -> 20129.032 | C90: 12363 | D90: =C90/$B$4*$B$3 -> 12363 | E90: =D90/B90-1 -> -0.3858125 | F90: =D90-B90 -> -7766.0323
A91: 9 | B91: =$B$114/$B$79 -> 20129.032 | C91: 13589 | D91: =C91/$B$4*$B$3 -> 13589 | E91: =D91/B91-1 -> -0.32490545 | F91: =D91-B91 -> -6540.0323
A92: 10 | B92: =$B$114/$B$79 -> 20129.032 | C92: 13094 | D92: =C92/$B$4*$B$3 -> 13094 | E92: =D92/B92-1 -> -0.34949679 | F92: =D92-B92 -> -7035.0323
A93: 11 | B93: =$B$114/$B$79 -> 20129.032 | C93: 12622 | D93: =C93/$B$4*$B$3 -> 12622 | E93: =D93/B93-1 -> -0.37294551 | F93: =D93-B93 -> -7507.0323
A94: 12 | B94: =$B$114/$B$79 -> 20129.032 | C94: 9925 | D94: =C94/$B$4*$B$3 -> 9925 | E94: =D94/B94-1 -> -0.50693109 | F94: =D94-B94 -> -10204.032
... A113: 31 | B113: =$B$114/$B$79 -> 20129.032 | C113: 7420 | D113: =C113/$B$4*$B$3 -> 7420 | E113: =D113/B113-1 -> -0.63137821 | F113: =D113-B113 -> -12709.032
A114: TOTAL | B114: =H20 -> 624000 | C114: =sum(C83:C113) -> 348656 | D114: =C114/$B$4*$B$3 -> 348656 | E114: =D114/B114-1 -> -0.44125641 | F114: =D114-B114 -> -275344

Sheet ECOMMERCE Formulas
B1: Business Metrics
A2: Source | B2: COGS | E2: Attachment Rates | H2: Marketing Averages (per order) | K2: Fees | N2: VAT Averages | Q2: 30 Day Returns | T2: Post-purchase Survey | U2: 45108 | V2: 45109 | W2: 45110 | X2: 45111 | Y2: 45112 | Z2: 45113 | AA2: 45114 | AB2: 45115 | AC2: 45116 | AD2: 45117 | AE2: 45118 | AF2: 45119 | AG2: 45120 | AH2: 45121 | AI2: 45122 | AJ2: 45123 | AK2: 45124 | AL2: 45125 | AM2: 45126 | AN2: 45127 | AO2: 45128 | AP2: 45129 | AQ2: 45130 | AR2: 45131 | AS2: 45132 | AT2: 45133 | AU2: 45134 | AV2: 45135 | AW2: 45136 | AX2: 45137 | AY2: 45138
B3: Bird Buddy | C3: 81.22 | D3: 86.9 | E3: Solar Roof | F3: =('OLD Detailed Report'!AG170)/'OLD Detailed Report'!AG164 -> 0.11461758 | H3: COGS | I3: =(C3*F9)+(C4*F8)+(C5*F3)+(C6*F4)+(C7*F5)+(C8*F6)+(C9*F7) -> 92.470049 | J3: =(D3*F9)+(D4*F8)+(D5*F3)+(D6*F4)+(D7*F5)+(D8*F6)+(D9*F7) -> 99.387885 | K3: Processing Fee | L3: 0.029 | N3: Europe | O3: 0.22 | Q3: US Shipping | R3: 10 | T3: Facebook / Instagram | AN3: 24 | AO3: 44 | AP3: 53 | AQ3: 53
B4: Bird Buddy with Solar Roof | C4: 91.14 | D4: 97.61 | E4: Wall Mount | F4: =('OLD Detailed Report'!AG166)/'OLD Detailed Report'!AG164 -> 0.33596318 | H4: Inbound Shipping | I4: =C32+(D32*0.78) -> 13.0593 | K4: Duty | L4: 0.034 | N4: ROW | O4: 0.13 | Q4: EU Shipping | R4: 20 | T4: Friends / Family | AN4: 42 | AO4: 58 | AP4: 60 | AQ4: 56
B5: Solar Roof Single | C5: 10.5 | D5: 13.44 | E5: Fence Mount | F5: =('OLD Detailed Report'!AG167)/'OLD Detailed Report'!AG164 -> 0 | H5: Outbound Shipping | I5: =C28 -> 15.06 | K5: China Tax | L5: 0.075 | N5: NA | Q5: ROW Shipping | R5: 20 | T5: TikTok | AN5: 0 | AO5: 0 | AP5: 1 | AQ5: 1
B6: Wall Mount | C6: 4.93 | D6: 5.49 | E6: Suet Ball Holder | F6: =('OLD Detailed Report'!AG168)/'OLD Detailed Report'!AG164 -> 0.17006355 | H6: Taxes and VAT | I6: 16.81 | K6: HMF | L6: 0.00125 | Q6: Money Return | R6: 1 | T6: TV / Radio | AN6: 2 | AO6: 0 | AP6: 1 | AQ6: 2
B7: Fence Mount | C7: 6.37 | E7: 3-in-1 | F7: =('OLD Detailed Report'!AG169)/'OLD Detailed Report'!AG164 -> 0.18956827 | H7: China Tax (7.5%) | I7: =I3*0.075 -> 6.9352537 | K7: MPF | L7: 0.003464 | N7: US+CA | O7: 0.943 | T7: Blog / Article | AN7: 7 | AO7: 6 | AP7: 2 | AQ7: 3
B8: Suet Ball Holder | C8: 1.07 | D8: 1.19 | E8: Bird Buddy w/ Solar | F8: ='OLD Detailed Report'!AG140/'OLD Detailed Report'!AG141 -> 0.7131734 | H8: Duty (3.4%) | I8: =(C5*F3)*0.025+(C6*F4)*0.034+(C7*F5)*0.034+(C8*F6)*0.034+(C9*F7)*0.034 -> 0.13113119 | K8: Solar Roof China Tax | L8: 0.075 | M8: *from july.23 | N8: EUROPE | O8: =1-O7 -> 0.057 | T8: Reddit | AN8: 0 | AO8: 0 | AP8: 2 | AQ8: 1
B9: 3-in-1 Nutrition Set | C9: 5.98 | D9: 6.66 | E9: Bird Buddy | F9: =1-F8 -> 0.2868266 | H9: Processing Fee (2,90%) | I9: ='OLD Sales'!B56*0.029 -> 7.1313109 | K9: Solar Roof Duty | L9: 0.025 | T9: Google, Youtube | AN9: 0 | AO9: 4 | AP9: 4 | AQ9: 8
B10: OTHER 1 | E10: OTHER 1 | H10: Transaction Fee ($0.30) | I10: =0.3 -> 0.3 | K10: Chargeback Fee (Stripe) | L10: 15 | T10: Yahoo, Bing | AN10: 0 | AO10: 0 | AP10: 1 | AQ10: 0
B11: OTHER 2 | E11: OTHER 2 | H11: OTHER 1 | N11: jan.23-jun.23 AOV | O11: 252.085 | P11: =(O12*O7)+(O13*O8) -> 16.806398 | T11: Total submissions: | U11: =SUM(U3:U10) -> 0 | V11: =SUM(V3:V10) -> 0 | W11: =SUM(W3:W10) -> 0 | X11: =SUM(X3:X10) -> 0 | Y11: =SUM(Y3:Y10) -> 0 | Z11: =SUM(Z3:Z10) -> 0 | AA11: =SUM(AA3:AA10) -> 0 | AB11: =SUM(AB3:AB10) -> 0 | ... AY11: =SUM(AY3:AY10) -> 0
B12: OTHER 3 | E12: OTHER 3 | H12: OTHER 2 | K12: Stripe | L12: 0.95 | N12: NA (cca 6 %) | O12: 14.469966 | T12: Percentage | U12: 45108 | V12: 45109 | W12: 45110 | X12: 45111 | Y12: 45112 | Z12: 45113 | AA12: 45114 | AB12: 45115 | AC12: 45116 | AD12: 45117 | AE12: 45118 | AF12: 45119 | AG12: 45120 | AH12: 45121 | AI12: 45122 | AJ12: 45123 | AK12: 45124 | AL12: 45125 | AM12: 45126 | AN12: 45127 | AO12: 45128 | AP12: 45129 | AQ12: 45130 | AR12: 45131 | AS12: 45132 | AT12: 45133 | AU12: 45134 | AV12: 45135 | AW12: 45136 | AX12: 45137 | AY12: 45138
B13: OTHER 4 | E13: OTHER 4 | H13: OTHER 3 | K13: Affirm | L13: 0.05 | N13: Europe (22 %) | O13: 55.46 | T13: Facebook / Instagram | U13: =iferror(U3/U$11,"") | V13: =iferror(V3/V$11,"") | W13: =iferror(W3/W$11,"") | X13: =iferror(X3/X$11,"") | Y13: =iferror(Y3/Y$11,"") | Z13: =iferror(Z3/Z$11,"") | AA13: =iferror(AA3/AA$11,"") | AB13: =iferror(AB3/AB$11,"") | ... AY13: =iferror(AY3/AY$11,"")
B14: OTHER 5 | E14: OTHER 5 | H14: OTHER 4 | K14: Affirm processing fee | L14: 0 | T14: Friends / Family | U14: =iferror(U4/U$11,"") | V14: =iferror(V4/V$11,"") | W14: =iferror(W4/W$11,"") | X14: =iferror(X4/X$11,"") | Y14: =iferror(Y4/Y$11,"") | Z14: =iferror(Z4/Z$11,"") | AA14: =iferror(AA4/AA$11,"") | AB14: =iferror(AB4/AB$11,"") | ... AY14: =iferror(AY4/AY$11,"")
H15: All | I15: =SUM(I3:I13) -> 151.89705 | K15: Affirm transaction fee | L15: 0 | T15: TikTok | U15: =iferror(U5/U$11,"") | V15: =iferror(V5/V$11,"") | W15: =iferror(W5/W$11,"") | X15: =iferror(X5/X$11,"") | Y15: =iferror(Y5/Y$11,"") | Z15: =iferror(Z5/Z$11,"") | AA15: =iferror(AA5/AA$11,"") | AB15: =iferror(AB5/AB$11,"") | ... AY15: =iferror(AY5/AY$11,"")
B16: Outbound shipping | C16: Bird buddy | D16: Add-ons | T16: TV / Radio | U16: =iferror(U6/U$11,"") | V16: =iferror(V6/V$11,"") | W16: =iferror(W6/W$11,"") | X16: =iferror(X6/X$11,"") | Y16: =iferror(Y6/Y$11,"") | Z16: =iferror(Z6/Z$11,"") | AA16: =iferror(AA6/AA$11,"") | AB16: =iferror(AB6/AB$11,"") | ... AY16: =iferror(AY6/AY$11,"")
A17: *w/o CA weight | B17: Outbound (NA) | C17: 11.94 | D17: 6.155 | T17: Blog / Article | U17: =iferror(U7/U$11,"") | V17: =iferror(V7/V$11,"") | W17: =iferror(W7/W$11,"") | X17: =iferror(X7/X$11,"") | Y17: =iferror(Y7/Y$11,"") | Z17: =iferror(Z7/Z$11,"") | AA17: =iferror(AA7/AA$11,"") | AB17: =iferror(AB7/AB$11,"") | ... AY17: =iferror(AY7/AY$11,"")
B18: Outbound (Europe) | C18: 11.94 | D18: 6.16 | T18: Reddit | U18: =iferror(U8/U$11,"") | V18: =iferror(V8/V$11,"") | W18: =iferror(W8/W$11,"") | X18: =iferror(X8/X$11,"") | Y18: =iferror(Y8/Y$11,"") | Z18: =iferror(Z8/Z$11,"") | AA18: =iferror(AA8/AA$11,"") | AB18: =iferror(AB8/AB$11,"") | ... AY18: =iferror(AY8/AY$11,"")
B19: Outbound (ROW) | C19: 11.94 | D19: 6.16 | T19: Google, Youtube | U19: =iferror(U9/U$11,"") | V19: =iferror(V9/V$11,"") | W19: =iferror(W9/W$11,"") | X19: =iferror(X9/X$11,"") | Y19: =iferror(Y9/Y$11,"") | Z19: =iferror(Z9/Z$11,"") | AA19: =iferror(AA9/AA$11,"") | AB19: =iferror(AB9/AB$11,"") | ... AY19: =iferror(AY9/AY$11,"")
A20: Source | B20: 3PL Costs | C20: =sum(C21:C27) -> 3.12 | D20: =sum(D21:D27) -> 2.31 | T20: Yahoo, Bing | U20: =iferror(U10/U$11,"") | V20: =iferror(V10/V$11,"") | W20: =iferror(W10/W$11,"") | X20: =iferror(X10/X$11,"") | Y20: =iferror(Y10/Y$11,"") | Z20: =iferror(Z10/Z$11,"") | AA20: =iferror(AA10/AA$11,"") | AB20: =iferror(AB10/AB$11,"") | ... AY20: =iferror(AY10/AY$11,"")
B21: Handling Fee
B22: Serial Capture | C22: 0.3 | D22: 0
B23: Storage | C23: 0.31 | D23: 0.31
B24: Supplies cost | C24: 1.01 | D24: 0.6
B25: Pick charge | C25: 0.3 | D25: 0.3
B26: Pollybag cost | C26: 0 | D26: 1.1
B27: Carton cost | C27: 1.2 | D27: 0
B28: Total outbound (NA) | C28: =C20+C17-C21 -> 15.06 | D28: =D20+D17-D21 -> 8.465
B29: Total outbound (Europe) | C29: 15.06
B30: Total outbound (ROW) | C30: 20
A31: Source | B31: Inbound shipping | C31: Bird buddy | D31: Add-ons
B32: Inbound (NA) | C32: 11.94 | D32: 1.435
B33: Inbound (Europe) | C33: 11.94 | D33: 1.44
B34: Inbound (ROW) | C34: 11.94 | D34: 1.44
B36: AMAZON Logistics | C36: Bird buddy | E36: KCTC (additionally for first 3.000 items) | G36: *KCTC = China -> LA with Air fraight
A37: =AVERAGE(D3:D4) -> 92.255 | B37: Inbound | C37: 2.27 | E37: Logistics | F37: 0.63
A38: =sum(C37:C38) -> 2.51 | B38: Storage Fee | C38: 0.24 | E38: Storage Fee | F38: 0.11
A39: =C40 -> 11.94 | B39: AMAZON Fees | C39: Bird buddy | E39: Label Handling | F39: 1.01
A40: =sum(F37:F39) -> 1.75 | B40: FBA fees | C40: 11.94
A41: =C32 -> 11.94 | B41: Sales Fee | C41: 0.1 | D41: *for first milion is 10 % than 15 %
A43: =sum(A37:A41) -> 120.395

Sheet ECOMMERCE Detailed Report
A1: JULY | B1: 45108 | C1: 45109 | D1: 45110 | E1: 45111 | F1: 45112 | G1: 45113 | H1: 45114 | I1: 45115 | J1: 45116 | K1: 45117 | L1: 45118 | M1: 45119 | N1: 45120 | O1: 45121 | P1: 45122 | Q1: 45123 | R1: 45124 | S1: 45125 | T1: 45126 | U1: 45127 | V1: 45128 | W1: 45129 | X1: 45130 | Y1: 45131 | Z1: 45132 | AA1: 45133 | AB1: 45134 | AC1: 45135 | AD1: 45136 | AE1: 45137 | AF1: 45138
A2: DAY | B2: SAT | C2: SUN | D2: MON | E2: TUE | F2: WED | G2: THU | H2: FRI | I2: SAT | J2: SUN | K2: MON | L2: TUE | M2: WED | N2: THU | O2: FRI | P2: SAT | Q2: SUN | R2: MON | S2: TUE | T2: WED | U2: THU | V2: FRI | W2: SAT | X2: SUN | Y2: MON | Z2: TUE | AA2: WED | AB2: THU | AC2: FRI | AD2: SAT | AE2: SUN | AF2: MON
A3: COMMENT
A4: Orders
A5: FB (US & CA) | B5: 29 | C5: 56 | D5: 31 | E5: 59 | F5: 47 | G5: 60 | H5: 64 | I5: 89 | J5: 75 | K5: 62 | L5: 51 | M5: 42 | N5: 53 | O5: 73 | P5: 68 | Q5: 67 | R5: 28 | S5: 48 | T5: 53 | U5: 64 | V5: 60 | W5: 65 | X5: 65 | Y5: 30 | Z5: 31 | AA5: 12 | AB5: 27 | AC5: 21 | AD5: 21 | AG5: =SUM(B5:AF5) -> 1451
A6: Google | B6: 55 | C6: 62 | D6: 52 | E6: 62 | F6: 59 | G6: 59 | H6: 62 | I6: 79 | J6: 67 | K6: 80 | L6: 78 | M6: 77 | N6: 84 | O6: 63 | P6: 69 | Q6: 65 | R6: 42 | S6: 63 | T6: 66 | U6: 66 | V6: 58 | W6: 57 | X6: 65 | Y6: 45 | Z6: 40 | AA6: 49 | AB6: 46 | AC6: 53 | AD6: 39 | AE6: 51 | AF6: 36 | AG6: =SUM(B6:AF6) -> 1849
A7: TikTok | B7: 0 | C7: 0 | D7: 0 | E7: 0 | F7: 0 | G7: 0 | H7: 0 | I7: 0 | J7: 0 | K7: 0 | L7: 0 | M7: 0 | N7: 0 | O7: 0 | P7: 0 | Q7: 0 | R7: 0 | S7: 0 | T7: 0 | U7: 0 | V7: 0 | W7: 0 | X7: 0 | Y7: 0 | Z7: 0 | AA7: 0 | AB7: 0 | AC7: 0 | AD7: 0 | AE7: 0 | AF7: 0 | AG7: =SUM(B7:AF7) -> 0
A8: Bing | B8: 2 | C8: 2 | D8: 1 | E8: 4 | F8: 3 | G8: 2 | H8: 1 | I8: 2 | J8: 6 | K8: 5 | L8: 4 | M8: 3 | N8: 1 | O8: 3 | P8: 1 | Q8: 3 | R8: 1 | S8: 1 | T8: 0 | U8: 4 | V8: 6 | W8: 7 | X8: 4 | Y8: 1 | Z8: 1 | AA8: 1 | AB8: 1 | AC8: 1 | AD8: 0 | AE8: 1 | AF8: 1 | AG8: =SUM(B8:AF8) -> 73
A9: MNTN TV | AG9: =SUM(B9:AF9) -> 0
A10: Affiliates (Refersion) | B10: 0 | C10: 0 | D10: 0 | E10: 0 | F10: 0 | G10: 0 | H10: 0 | I10: 0 | J10: 0 | K10: 0 | L10: 0 | M10: 0 | N10: 0 | O10: 0 | P10: 0 | Q10: 0 | R10: 0 | S10: 4 | T10: 3 | U10: 3 | V10: 4 | W10: 2 | X10: 3 | Y10: 5 | Z10: 3 | AA10: 2 | AB10: 3 | AC10: 1 | AD10: 0 | AE10: 4 | AF10: 0 | AG10: =SUM(B10:AF10) -> 37
A11: FB (Internal Paid) | AG11: =SUM(B11:AF11) -> 0
A12: FB (EU & UK) | AG12: =SUM(B12:AF12) -> 0
A13: Email | B13: 4 | C13: 6 | D13: 3 | E13: 2 | F13: 1 | G13: 1 | H13: 0 | I13: 1 | J13: 2 | K13: 3 | L13: 1 | M13: 2 | N13: 94 | O13: 76 | P13: 25 | Q13: 17 | R13: 29 | S13: 38 | T13: 2 | U13: 4 | V13: 3 | W13: 2 | X13: 6 | Y13: 2 | Z13: 1 | AA13: 0 | AB13: 4 | AD13: 1 | AE13: 4 | AF13: 4 | AG13: =SUM(B13:AF13) -> 338
A14: Amazon (market place)
A15: All | B15: =SUM(B5:B14) -> 90 | C15: =SUM(C5:C14) -> 126 | D15: =SUM(D5:D14) -> 87 | E15: =SUM(E5:E14) -> 127 | F15: =SUM(F5:F14) -> 110 | G15: =SUM(G5:G14) -> 122 | H15: =SUM(H5:H14) -> 127 | I15: =SUM(I5:I14) -> 171 | ... AF15: =SUM(AF5:AF14) -> 41 | AG15: =SUM(B15:AF15) -> 3748
A17: Revenue
A18: FB (US & CA) | B18: 8613.9 | C18: 15724.4 | D18: 8025.24 | E18: 16088.3 | F18: 12903.82 | G18: 14883.81 | H18: 16270.4 | I18: 25945.45 | J18: 19825.93 | K18: 17028.9 | L18: 13397.83 | M18: 10977.79 | N18: 14178.65 | O18: 19579.31 | P18: 17923.96 | Q18: 17121.73 | R18: 7919.38 | S18: 14118.96 | T18: 12662.5 | U18: 18657.19 | V18: 15148.98 | W18: 18426.12 | X18: 16067.5 | Y18: 7934.14 | Z18: 9221.02 | AA18: 4261.21 | AB18: 7567.93 | AC18: 5416.74 | AD18: 5924.43 | AG18: =SUM(B18:AF18) -> 391815.52
A19: Google | B19: 12359.29 | C19: 15714.44 | D19: 12992.16 | E19: 14130.15 | F19: 12779.82 | G19: 13797.36 | H19: 13621.06 | I19: 16193.95 | J19: 15558.05 | K19: 17274.51 | L19: 18071.04 | M19: 18496.68 | N19: 19977.39 | O19: 14636.37 | P19: 14578.95 | Q19: 14867.89 | R19: 9667.93 | S19: 14155.55 | T19: 17455.8 | U19: 14739.52 | V19: 13885.52 | W19: 12885.06 | X19: 15358.08 | Y19: 11022.06 | Z19: 11322.51 | AA19: 12117.25 | AB19: 12457.81 | AC19: 13306.27 | AD19: 8931.61 | AE19: 13855.82 | AF19: 9278.69 | AG19: =SUM(B19:AF19) -> 435488.59
A20: TikTok | M20: 0 | N20: 0 | O20: 0 | P20: 0 | Q20: 0 | R20: 0 | S20: 0 | T20: 0 | U20: 0 | V20: 0 | W20: 0 | X20: 0 | Y20: 0 | Z20: 0 | AA20: 0 | AB20: 0 | AC20: 0 | AD20: 0 | AE20: 0 | AF20: 0 | AG20: =SUM(B20:AF20) -> 0
A21: Bing | B21: 381.38 | C21: 380.76 | D21: 86.4 | E21: 774.99 | F21: 441.39 | G21: 632.04 | H21: 249.31 | I21: 304.66 | J21: 2048.44 | K21: 1113.52 | L21: 713.3 | M21: 771.48 | N21: 292.98 | O21: 551.04 | P21: 292.66 | Q21: 845.41 | R21: 25.44 | S21: 85.41 | T21: 0 | U21: 638.28 | V21: 1353.82 | W21: 1682.28 | X21: 430.18 | Y21: 299.38 | Z21: 342 | AA21: 68.21 | AB21: 297.14 | AC21: 602.4 | AD21: 0 | AE21: 295.14 | AF21: 297.48 | AG21: =SUM(B21:AF21) -> 16296.92
A22: MNTN TV | AG22: =SUM(B22:AF22) -> 0
A23: Affiliates (Refersion) | B23: 0 | C23: 0 | D23: 0 | E23: 0 | F23: 0 | G23: 0 | H23: 0 | I23: 0 | J23: 0 | K23: 0 | L23: 0 | M23: 0 | N23: 0 | O23: 0 | P23: 0 | Q23: 0 | R23: 0 | S23: 780.81 | T23: 541.79 | U23: 925.45 | V23: 1184.57 | W23: 531.95 | X23: 938.33 | Y23: 1148.46 | Z23: 785.1 | AA23: 543.06 | AB23: 908.25 | AC23: 245.27 | AD23: 0 | AE23: 682.12 | AF23: 0 | AG23: =SUM(B23:AF23) -> 9215.16
A24: FB (Internal Paid) | AG24: =SUM(B24:AF24) -> 0
A25: FB (EU & UK) | AG25: =SUM(B25:AF25) -> 0
A26: Email | B26: 815.46 | C26: 1741.69 | D26: 759.15 | E26: 509.74 | F26: 204.7 | G26: 266.63 | H26: 0 | I26: 30.74 | J26: 425.14 | K26: 543.68 | L26: 63 | M26: 348.11 | N26: 21081.09 | O26: 19052.55 | P26: 6531.28 | Q26: 3775.83 | R26: 6537.36 | S26: 7669.01 | T26: 238.68 | U26: 825.72 | V26: 465.42 | W26: 309.71 | X26: 1222.39 | Y26: 351.79 | Z26: 24.84 | AA26: 0 | AB26: 1047.31 | AC26: 576.18 | AD26: 124.94 | AE26: 646.42 | AF26: 1000.93 | AG26: =SUM(B26:AF26) -> 77189.49
A27: Amazon (market place)
A28: All | B28: =SUM(B18:B27) -> 22170.03 | C28: =SUM(C18:C27) -> 33561.29 | D28: =SUM(D18:D27) -> 21862.95 | E28: =SUM(E18:E27) -> 31503.18 | F28: =SUM(F18:F27) -> 26329.73 | G28: =SUM(G18:G27) -> 29579.84 | H28: =SUM(H18:H27) -> 30140.77 | I28: =SUM(I18:I27) -> 42474.8 | ... AF28: =SUM(AF18:AF27) -> 10577.1 | AG28: =SUM(B28:AF28) -> 930005.68
A30: Media Cost
A31: FB Spend (US & CA) | B31: ='OLD Sales'!B20 -> 7590.32 | C31: ='OLD Sales'!C20 -> 9939.48 | D31: ='OLD Sales'!D20 -> 11857.85 | E31: ='OLD Sales'!E20 -> 13975.77 | F31: ='OLD Sales'!F20 -> 13627.08 | G31: ='OLD Sales'!G20 -> 13435.73 | H31: ='OLD Sales'!H20 -> 13643.57 | I31: ='OLD Sales'!I20 -> 14020.82 | ... AF31: ='OLD Sales'!AF20 -> 7705.29 | AG31: =SUM(B31:AF31) -> 396219.65
A32: Google Spend | B32: ='OLD Sales'!B21 -> 3493.03 | C32: ='OLD Sales'!C21 -> 3318.69 | D32: ='OLD Sales'!D21 -> 3105.04 | E32: ='OLD Sales'!E21 -> 3164.26 | F32: ='OLD Sales'!F21 -> 2740.55 | G32: ='OLD Sales'!G21 -> 3020.34 | H32: ='OLD Sales'!H21 -> 3129.51 | I32: ='OLD Sales'!I21 -> 3393.25 | ... AF32: ='OLD Sales'!AF21 -> 2235.27 | AG32: =SUM(B32:AF32) -> 138014.53
A33: TikTok Spend | B33: ='OLD Sales'!B23 -> 0 | C33: ='OLD Sales'!C23 -> 0 | D33: ='OLD Sales'!D23 -> 0 | E33: ='OLD Sales'!E23 -> 0 | F33: ='OLD Sales'!F23 -> 0 | G33: ='OLD Sales'!G23 -> 0 | H33: ='OLD Sales'!H23 -> 0 | I33: ='OLD Sales'!I23 -> 0 | ... AF33: ='OLD Sales'!AF23 | AG33: =SUM(B33:AF33) -> 0
A34: Bing Spend | B34: ='OLD Sales'!B22 -> 244.51 | C34: ='OLD Sales'!C22 -> 259.8 | D34: ='OLD Sales'!D22 -> 259.73 | E34: ='OLD Sales'!E22 -> 251.56 | F34: ='OLD Sales'!F22 -> 260.93 | G34: ='OLD Sales'!G22 -> 252.96 | H34: ='OLD Sales'!H22 -> 250.94 | I34: ='OLD Sales'!I22 -> 249.85 | ... AF34: ='OLD Sales'!AF22 -> 296.9 | AG34: =SUM(B34:AF34) -> 6436.68
A35: MNTN TV | B35: ='OLD Sales'!B24 | C35: ='OLD Sales'!C24 | D35: ='OLD Sales'!D24 | E35: ='OLD Sales'!E24 | F35: ='OLD Sales'!F24 | G35: ='OLD Sales'!G24 | H35: ='OLD Sales'!H24 | I35: ='OLD Sales'!I24 | ... AE35: ='OLD Sales'!AE24 | AG35: =SUM(B35:AF35) -> 0
A36: Fee 15% Purchase (Backerkit) | B36: =B22*0.15 -> 0 | C36: =C22*0.15 -> 0 | D36: =D22*0.15 -> 0 | E36: =E22*0.15 -> 0 | F36: =F22*0.15 -> 0 | G36: =G22*0.15 -> 0 | H36: =H22*0.15 -> 0 | I36: =I22*0.15 -> 0 | ... S36: =S22*0.15 -> 0 | U36: =U22*0.15 -> 0 | V36: =V22*0.15 -> 0 | W36: =W22*0.15 -> 0 | X36: =X22*0.15 -> 0 | Y36: =Y22*0.15 -> 0 | Z36: =Z22*0.15 -> 0 | AA36: =AA22*0.15 -> 0 | AB36: =AB22*0.15 -> 0 | AC36: =AC22*0.15 -> 0 | AG36: =SUM(B36:AF36) -> 0
A37: Google Management Fee | AG37: =SUM(B37:AF37) -> 0
A38: Affiliates Agency Payment (Grovia) | AG38: =SUM(B38:AF38) -> 0
A39: Affiliate Fee 20% (Grovia) | B39: ='OLD Sales'!B25 -> 0 | C39: ='OLD Sales'!C25 -> 0 | D39: ='OLD Sales'!D25 -> 0 | E39: ='OLD Sales'!E25 -> 0 | F39: ='OLD Sales'!F25 -> 0 | G39: ='OLD Sales'!G25 -> 0 | H39: ='OLD Sales'!H25 -> 0 | I39: ='OLD Sales'!I25 -> 0 | ... AF39: ='OLD Sales'!AF25 -> 0 | AG39: =SUM(B39:AF39) -> 1954.82
A40: FB Spend (Internal Paid) | AG40: =SUM(B40:AF40) -> 0
A41: FB Spend (EU & UK) | AG41: =SUM(B41:AF41) -> 0
A42: Pinterest Spend | AG42: =SUM(B42:AF42) -> 0
A43: Amazon (market place) Spend
A44: Amazon (market place) Sales Fee (10-15 %) | B44: =B27*'ECOMMERCE Formulas'!$C$41 -> 0 | C44: =C27*'ECOMMERCE Formulas'!$C$41 -> 0 | D44: =D27*'ECOMMERCE Formulas'!$C$41 -> 0 | E44: =E27*'ECOMMERCE Formulas'!$C$41 -> 0 | F44: =F27*'ECOMMERCE Formulas'!$C$41 -> 0 | G44: =G27*'ECOMMERCE Formulas'!$C$41 -> 0 | H44: =H27*'ECOMMERCE Formulas'!$C$41 -> 0 | I44: =I27*'ECOMMERCE Formulas'!$C$41 -> 0 | ... AF44: =AF27*'ECOMMERCE Formulas'!$C$41 -> 0
A45: Platform Fee (6,90%) | AG45: =SUM(B45:AF45) -> 0
A46: All | B46: =SUM(B31:B45) -> 11327.86 | C46: =SUM(C31:C45) -> 13517.97 | D46: =SUM(D31:D45) -> 15222.62 | E46: =SUM(E31:E45) -> 17391.59 | F46: =SUM(F31:F45) -> 16628.56 | G46: =SUM(G31:G45) -> 16709.03 | H46: =SUM(H31:H45) -> 17024.02 | I46: =SUM(I31:I45) -> 17663.92 | ... AF46: =SUM(AF31:AF45) -> 10237.46 | AG46: =SUM(B46:AF46) -> 542625.68
A48: Cost
A49: Average COGS ($92.18) | B49: =B15*'ECOMMERCE Formulas'!$J$3 -> 8944.9097 | C49: =C15*'ECOMMERCE Formulas'!$J$3 -> 12522.874 | D49: =D15*'ECOMMERCE Formulas'!$J$3 -> 8646.746 | E49: =E15*'ECOMMERCE Formulas'!$J$3 -> 12622.261 | F49: =F15*'ECOMMERCE Formulas'!$J$3 -> 10932.667 | G49: =G15*'ECOMMERCE Formulas'!$J$3 -> 12125.322 | H49: =H15*'ECOMMERCE Formulas'!$J$3 -> 12622.261 | I49: =I15*'ECOMMERCE Formulas'!$J$3 -> 16995.328 | ... AF49: =AF15*'ECOMMERCE Formulas'!$J$3 -> 4074.9033 | AG49: =SUM(B49:AF49) -> 372505.79
A50: Average Inbound Shipping ($13.06) | B50: =B15*'ECOMMERCE Formulas'!$I$4 -> 1175.337 | C50: =C15*'ECOMMERCE Formulas'!$I$4 -> 1645.4718 | D50: =D15*'ECOMMERCE Formulas'!$I$4 -> 1136.1591 | E50: =E15*'ECOMMERCE Formulas'!$I$4 -> 1658.5311 | F50: =F15*'ECOMMERCE Formulas'!$I$4 -> 1436.523 | G50: =G15*'ECOMMERCE Formulas'!$I$4 -> 1593.2346 | H50: =H15*'ECOMMERCE Formulas'!$I$4 -> 1658.5311 | I50: =I15*'ECOMMERCE Formulas'!$I$4 -> 2233.1403 | ... AF50: =AF15*'ECOMMERCE Formulas'!$I$4 -> 535.4313 | AG50: =SUM(B50:AF50) -> 48946.256
A51: Average Outbound Shipping ($15.06) | B51: =B15*'ECOMMERCE Formulas'!$I$5 -> 1355.4 | C51: =C15*'ECOMMERCE Formulas'!$I$5 -> 1897.56 | D51: =D15*'ECOMMERCE Formulas'!$I$5 -> 1310.22 | E51: =E15*'ECOMMERCE Formulas'!$I$5 -> 1912.62 | F51: =F15*'ECOMMERCE Formulas'!$I$5 -> 1656.6 | G51: =G15*'ECOMMERCE Formulas'!$I$5 -> 1837.32 | H51: =H15*'ECOMMERCE Formulas'!$I$5 -> 1912.62 | I51: =I15*'ECOMMERCE Formulas'!$I$5 -> 2575.26 | ... AF51: =AF15*'ECOMMERCE Formulas'!$I$5 -> 617.46 | AG51: =SUM(B51:AF51) -> 56444.88
A52: Average Taxes ($16.81) | B52: =B15*'ECOMMERCE Formulas'!$I$6 -> 1512.9 | C52: =C15*'ECOMMERCE Formulas'!$I$6 -> 2118.06 | D52: =D15*'ECOMMERCE Formulas'!$I$6 -> 1462.47 | E52: =E15*'ECOMMERCE Formulas'!$I$6 -> 2134.87 | F52: =F15*'ECOMMERCE Formulas'!$I$6 -> 1849.1 | G52: =G15*'ECOMMERCE Formulas'!$I$6 -> 2050.82 | H52: =H15*'ECOMMERCE Formulas'!$I$6 -> 2134.87 | I52: =I15*'ECOMMERCE Formulas'!$I$6 -> 2874.51 | ... AF52: =AF15*'ECOMMERCE Formulas'!$I$6 -> 689.21 | AG52: =SUM(B52:AF52) -> 63003.88
A53: Processing Fee (2,90%) | B53: =B28*'ECOMMERCE Formulas'!$L$3 -> 642.93087 | C53: =C28*'ECOMMERCE Formulas'!$L$3 -> 973.27741 | D53: =D28*'ECOMMERCE Formulas'!$L$3 -> 634.02555 | E53: =E28*'ECOMMERCE Formulas'!$L$3 -> 913.59222 | F53: =F28*'ECOMMERCE Formulas'!$L$3 -> 763.56217 | G53: =G28*'ECOMMERCE Formulas'!$L$3 -> 857.81536 | H53: =H28*'ECOMMERCE Formulas'!$L$3 -> 874.08233 | I53: =I28*'ECOMMERCE Formulas'!$L$3 -> 1231.7692 | ... AF53: =AF28*'ECOMMERCE Formulas'!$L$3 -> 306.7359 | AG53: =SUM(B53:AF53) -> 26970.165
A54: Transaction Fee ($0.30) | B54: =B15*'ECOMMERCE Formulas'!$I$10 -> 27 | C54: =C15*'ECOMMERCE Formulas'!$I$10 -> 37.8 | D54: =D15*'ECOMMERCE Formulas'!$I$10 -> 26.1 | E54: =E15*'ECOMMERCE Formulas'!$I$10 -> 38.1 | F54: =F15*'ECOMMERCE Formulas'!$I$10 -> 33 | G54: =G15*'ECOMMERCE Formulas'!$I$10 -> 36.6 | H54: =H15*'ECOMMERCE Formulas'!$I$10 -> 38.1 | I54: =I15*'ECOMMERCE Formulas'!$I$10 -> 51.3 | ... AF54: =AF15*'ECOMMERCE Formulas'!$I$10 -> 12.3 | AG54: =SUM(B54:AF54) -> 1124.4
A55: All | B55: =SUM(B49:B54) -> 13658.478 | C55: =SUM(C49:C54) -> 19195.043 | D55: =SUM(D49:D54) -> 13215.721 | E55: =SUM(E49:E54) -> 19279.975 | F55: =SUM(F49:F54) -> 16671.453 | G55: =SUM(G49:G54) -> 18501.112 | H55: =SUM(H49:H54) -> 19240.465 | I55: =SUM(I49:I54) -> 25961.308 | ... AF55: =SUM(AF49:AF54) -> 6236.0405 | AG55: =SUM(B55:AF55) -> 568995.38
AG56: =SUM(B56:AF56) -> 0
A57: Partial Profit | B57: =B28-B46-B55 -> -2816.3076 | C57: =C28-C46-C55 -> 848.27722 | D57: =D28-D46-D55 -> -6575.3907 | E57: =E28-E46-E55 -> -5168.3848 | F57: =F28-F46-F55 -> -6970.2826 | G57: =G28-G46-G55 -> -5630.302 | H57: =H28-H46-H55 -> -6123.7149 | I57: =I28-I46-I55 -> -1150.4279 | ... AF57: =AF28-AF46-AF55 -> -5896.4005 | AG57: =SUM(B57:AF57) -> -181615.38
A58: =SUM(B57:AC57) -> -163027.31
A62: Performance Facebook US & CA | Z62: 3.11 | AA62: 1.8
A63: PROFIT | B63: =B18-(B5*'ECOMMERCE Formulas'!$I$15)-B31 -> -3381.4343 | C63: =C18-(C5*'ECOMMERCE Formulas'!$I$15)-C31 -> -2721.3145 | D63: =D18-(D5*'ECOMMERCE Formulas'!$I$15)-D31 -> -8541.4184 | E63: =E18-(E5*'ECOMMERCE Formulas'!$I$15)-E31 -> -6849.3957 | F63: =F18-(F5*'ECOMMERCE Formulas'!$I$15)-F31 -> -7862.4211 | G63: =G18-(G5*'ECOMMERCE Formulas'!$I$15)-G31 -> -7665.7427 | H63: =H18-(H5*'ECOMMERCE Formulas'!$I$15)-H31 -> -7094.5809 | I63: =I18-(I5*'ECOMMERCE Formulas'!$I$15)-I31 -> -1594.207 | ... AF63: =AF18-(AF5*'ECOMMERCE Formulas'!$I$15)-AF31 -> -7705.29 | AG63: =SUM(B63:AF63) -> -224806.74
A64: ROAS | B64: =B18/B31 -> 1.1348533 | C64: =C18/C31 -> 1.5820144 | D64: =D18/D31 -> 0.67678711 | E64: =E18/E31 -> 1.1511566 | F64: =F18/F31 -> 0.9469248 | G64: =G18/G31 -> 1.1077783 | H64: =H18/H31 -> 1.1925325 | I64: =I18/I31 -> 1.8504945 | ... AF64: =AF18/AF31 -> 0
A65: CPO | B65: =B31/B5 -> 261.73517 | C65: =C31/C5 -> 177.49071 | D65: =D31/D5 -> 382.51129 | E65: =E31/E5 -> 236.87746 | F65: =F31/F5 -> 289.93787 | G65: =G31/G5 -> 223.92883 | H65: =H31/H5 -> 213.18078 | I65: =I31/I5 -> 157.5373 | ... AF65: =AF31/AF5 -> #DIV/0!
A66: MER | B66: =B18/('ECOMMERCE Formulas'!$I$15*B5+B31) -> 0.7181042 | C66: =C18/('ECOMMERCE Formulas'!$I$15*C5+C31) -> 0.85246901 | D66: =D18/('ECOMMERCE Formulas'!$I$15*D5+D31) -> 0.48442117 | E66: =E18/('ECOMMERCE Formulas'!$I$15*E5+E31) -> 0.70139129 | F66: =F18/('ECOMMERCE Formulas'!$I$15*F5+F31) -> 0.62138448 | G66: =G18/('ECOMMERCE Formulas'!$I$15*G5+G31) -> 0.66004901 | H66: =H18/('ECOMMERCE Formulas'!$I$15*H5+H31) -> 0.69635837 | I66: =I18/('ECOMMERCE Formulas'!$I$15*I5+I31) -> 0.94211231 | ... AF66: =AF18/('ECOMMERCE Formulas'!$I$15*AF5+AF31) -> 0
A68: Performance Google
A69: PROFIT | B69: =B19-(B6*'ECOMMERCE Formulas'!$I$15)-B32 -> 511.92251 | C69: =C19-(C6*'ECOMMERCE Formulas'!$I$15)-C32 -> 2978.1332 | D69: =D19-(D6*'ECOMMERCE Formulas'!$I$15)-D32 -> 1988.4736 | E69: =E19-(E6*'ECOMMERCE Formulas'!$I$15)-E32 -> 1548.2732 | F69: =F19-(F6*'ECOMMERCE Formulas'!$I$15)-F32 -> 1077.3443 | G69: =G19-(G6*'ECOMMERCE Formulas'!$I$15)-G32 -> 1815.0943 | H69: =H19-(H6*'ECOMMERCE Formulas'!$I$15)-H32 -> 1073.9332 | I69: =I19-(I6*'ECOMMERCE Formulas'!$I$15)-I32 -> 800.83343 | ... AF69: =AF19-(AF6*'ECOMMERCE Formulas'!$I$15)-AF32 -> 1575.1264 | AG69: =SUM(B69:AF69) -> 16616.423
A70: ROAS | B70: =B19/B32 -> 3.5382719 | C70: =C19/C32 -> 4.7351334 | D70: =D19/D32 -> 4.1842166 | E70: =E19/E32 -> 4.4655464 | F70: =F19/F32 -> 4.6632318 | G70: =G19/G32 -> 4.568148 | H70: =H19/H32 -> 4.3524577 | I70: =I19/I32 -> 4.7724011 | ... AF70: =AF19/AF32 -> 4.1510377
A71: CPO | B71: =B32/B6 -> 63.509636 | C71: =C32/C6 -> 53.527258 | D71: =D32/D6 -> 59.712308 | E71: =E32/E6 -> 51.036452 | F71: =F32/F6 -> 46.45 | G71: =G32/G6 -> 51.192203 | H71: =H32/H6 -> 50.475968 | I71: =I32/I6 -> 42.952532 | ... AF71: =AF32/AF6 -> 62.090833
A72: MER | B72: =B19/('ECOMMERCE Formulas'!$I$15*B6+B32) -> 1.0432098 | C72: =C19/('ECOMMERCE Formulas'!$I$15*C6+C32) -> 1.2338302 | D72: =D19/('ECOMMERCE Formulas'!$I$15*D6+D32) -> 1.1807098 | E72: =E19/('ECOMMERCE Formulas'!$I$15*E6+E32) -> 1.1230558 | F72: =F19/('ECOMMERCE Formulas'!$I$15*F6+F32) -> 1.0920612 | G72: =G19/('ECOMMERCE Formulas'!$I$15*G6+G32) -> 1.1514817 | H72: =H19/('ECOMMERCE Formulas'!$I$15*H6+H32) -> 1.085592 | I72: =I19/('ECOMMERCE Formulas'!$I$15*I6+I32) -> 1.0520254 | ... AF72: =AF19/('ECOMMERCE Formulas'!$I$15*AF6+AF32) -> 1.2044672
A74: Performance TikTok
A75: PROFIT | B75: =B20-(B7*'ECOMMERCE Formulas'!$I$15)-B33 -> 0 | C75: =C20-(C7*'ECOMMERCE Formulas'!$I$15)-C33 -> 0 | D75: =D20-(D7*'ECOMMERCE Formulas'!$I$15)-D33 -> 0 | E75: =E20-(E7*'ECOMMERCE Formulas'!$I$15)-E33 -> 0 | F75: =F20-(F7*'ECOMMERCE Formulas'!$I$15)-F33 -> 0 | G75: =G20-(G7*'ECOMMERCE Formulas'!$I$15)-G33 -> 0 | H75: =H20-(H7*'ECOMMERCE Formulas'!$I$15)-H33 -> 0 | I75: =I20-(I7*'ECOMMERCE Formulas'!$I$15)-I33 -> 0 | ... AF75: =AF20-(AF7*'ECOMMERCE Formulas'!$I$15)-AF33 -> 0 | AG75: =SUM(B75:AF75) -> 0
A76: ROAS | B76: =B20/B33 -> #DIV/0! | C76: =C20/C33 -> #DIV/0! | D76: =D20/D33 -> #DIV/0! | E76: =E20/E33 -> #DIV/0! | F76: =F20/F33 -> #DIV/0! | G76: =G20/G33 -> #DIV/0! | H76: =H20/H33 -> #DIV/0! | I76: =I20/I33 -> #DIV/0! | ... AF76: =AF20/AF33 -> #DIV/0!
A77: CPO | B77: =B33/B7 -> #DIV/0! | C77: =C33/C7 -> #DIV/0! | D77: =D33/D7 -> #DIV/0! | E77: =E33/E7 -> #DIV/0! | F77: =F33/F7 -> #DIV/0! | G77: =G33/G7 -> #DIV/0! | H77: =H33/H7 -> #DIV/0! | I77: =I33/I7 -> #DIV/0! | ... AF77: =AF33/AF7 -> #DIV/0!
A78: MER | B78: =B20/('ECOMMERCE Formulas'!$I$15*B7+B33) -> #DIV/0! | C78: =C20/('ECOMMERCE Formulas'!$I$15*C7+C33) -> #DIV/0! | D78: =D20/('ECOMMERCE Formulas'!$I$15*D7+D33) -> #DIV/0! | E78: =E20/('ECOMMERCE Formulas'!$I$15*E7+E33) -> #DIV/0! | F78: =F20/('ECOMMERCE Formulas'!$I$15*F7+F33) -> #DIV/0! | G78: =G20/('ECOMMERCE Formulas'!$I$15*G7+G33) -> #DIV/0! | H78: =H20/('ECOMMERCE Formulas'!$I$15*H7+H33) -> #DIV/0! | I78: =I20/('ECOMMERCE Formulas'!$I$15*I7+I33) -> #DIV/0! | ... AF78: =AF20/('ECOMMERCE Formulas'!$I$15*AF7+AF33) -> #DIV/0!
A80: Performance Bing
A81: PROFIT | B81: =B21-(B8*'ECOMMERCE Formulas'!$I$15)-B34 -> -166.92409 | C81: =C21-(C8*'ECOMMERCE Formulas'!$I$15)-C34 -> -182.83409 | D81: =D21-(D8*'ECOMMERCE Formulas'!$I$15)-D34 -> -325.22705 | E81: =E21-(E8*'ECOMMERCE Formulas'!$I$15)-E34 -> -84.158181 | F81: =F21-(F8*'ECOMMERCE Formulas'!$I$15)-F34 -> -275.23114 | G81: =G21-(G8*'ECOMMERCE Formulas'!$I$15)-G34 -> 75.28591 | H81: =H21-(H8*'ECOMMERCE Formulas'!$I$15)-H34 -> -153.52705 | I81: =I21-(I8*'ECOMMERCE Formulas'!$I$15)-I34 -> -248.98409 | ... AF81: =AF21-(AF8*'ECOMMERCE Formulas'!$I$15)-AF34 -> -151.31705 | AG81: =SUM(B81:AF81) -> -1228.2443
A82: ROAS | B82: =B21/B34 -> 1.5597726 | C82: =C21/C34 -> 1.4655889 | D82: =D21/D34 -> 0.33265314 | E82: =E21/E34 -> 3.0807362 | F82: =F21/F34 -> 1.6916031 | G82: =G21/G34 -> 2.4985769 | H82: =H21/H34 -> 0.99350442 | I82: =I21/I34 -> 1.2193716 | ... AF82: =AF21/AF34 -> 1.0019535
A83: CPO | B83: =B34/B8 -> 122.255 | C83: =C34/C8 -> 129.9 | D83: =D34/D8 -> 259.73 | E83: =E34/E8 -> 62.89 | F83: =F34/F8 -> 86.976667 | G83: =G34/G8 -> 126.48 | H83: =H34/H8 -> 250.94 | I83: =I34/I8 -> 124.925 | ... AF83: =AF34/AF8 -> 296.9
A84: MER | B84: =B21/('ECOMMERCE Formulas'!$I$15*B8+B34) -> 0.69556293 | C84: =C21/('ECOMMERCE Formulas'!$I$15*C8+C34) -> 0.67559261 | D84: =D21/('ECOMMERCE Formulas'!$I$15*D8+D34) -> 0.20989874 | E84: =E21/('ECOMMERCE Formulas'!$I$15*E8+E34) -> 0.90204463 | F84: =F21/('ECOMMERCE Formulas'!$I$15*F8+F34) -> 0.61593215 | G84: =G21/('ECOMMERCE Formulas'!$I$15*G8+G34) -> 1.1352229 | H84: =H21/('ECOMMERCE Formulas'!$I$15*H8+H34) -> 0.61888548 | I84: =I21/('ECOMMERCE Formulas'!$I$15*I8+I34) -> 0.55028132 | ... AD84: =AD21/('ECOMMERCE Formulas'!$I$15*AD8+AD34) -> 0 | AE84: =AE35/AE9 -> #DIV/0! | AF84: =AF21/('ECOMMERCE Formulas'!$I$15*AF8+AF34) -> 0.66283859
A86: MNTN TV
A87: PROFIT | B87: =B22-(B9*'OLD Formulas'!$C32)-B35 -> 0 | C87: =C22-(C9*'OLD Formulas'!$C32)-C35 -> 0 | D87: =D22-(D9*'OLD Formulas'!$C32)-D35 -> 0 | E87: =E22-(E9*'OLD Formulas'!$C32)-E35 -> 0 | F87: =F22-(F9*'OLD Formulas'!$C32)-F35 -> 0 | G87: =G22-(G9*'OLD Formulas'!$C32)-G35 -> 0 | H87: =H22-(H9*'OLD Formulas'!$C32)-H35 -> 0 | I87: =I22-(I9*'OLD Formulas'!$C32)-I35 -> 0 | ... AE87: =AE22-(AE9*'OLD Formulas'!$C32)-AE35 -> 0 | AG87: =SUM(B87:AF87) -> 0
A88: ROAS | B88: =B22/B35 -> #DIV/0! | C88: =C22/C35 -> #DIV/0! | D88: =D22/D35 -> #DIV/0! | E88: =E22/E35 -> #DIV/0! | F88: =F22/F35 -> #DIV/0! | G88: =G22/G35 -> #DIV/0! | H88: =H22/H35 -> #DIV/0! | I88: =I22/I35 -> #DIV/0! | ... AF88: =AF22/AF35 -> #DIV/0!
A89: CPO | B89: =B35/B9 -> #DIV/0! | C89: =C35/C9 -> #DIV/0! | D89: =D35/D9 -> #DIV/0! | E89: =E35/E9 -> #DIV/0! | F89: =F35/F9 -> #DIV/0! | G89: =G35/G9 -> #DIV/0! | H89: =H35/H9 -> #DIV/0! | I89: =I35/I9 -> #DIV/0! | ... AF89: =AF35/AF9 -> #DIV/0!
A90: MER | B90: =B22/('OLD Formulas'!$C32*B9+B35) -> #DIV/0! | C90: =C22/('OLD Formulas'!$C32*C9+C35) -> #DIV/0! | D90: =D22/('OLD Formulas'!$C32*D9+D35) -> #DIV/0! | E90: =E22/('OLD Formulas'!$C32*E9+E35) -> #DIV/0! | F90: =F22/('OLD Formulas'!$C32*F9+F35) -> #DIV/0! | G90: =G22/('OLD Formulas'!$C32*G9+G35) -> #DIV/0! | H90: =H22/('OLD Formulas'!$C32*H9+H35) -> #DIV/0! | I90: =I22/('OLD Formulas'!$C32*I9+I35) -> #DIV/0! | ... AF90: =AF22/('OLD Formulas'!$C32*AF9+AF35) -> #DIV/0!
A92: Affiliates (Grovia)
A93: PROFIT | AG93: =SUM(B93:AF93) -> 0
A94: ROAS
A95: CPO
A96: MER
A98: Performance Internal Paid
A99: PROFIT | AG99: =SUM(B99:AF99) -> 0
A100: ROAS
A101: CPO
A102: MER
A104: Performance EU & UK
A105: PROFIT | AG105: =SUM(B105:AF105) -> 0
A106: ROAS
A107: CPO
A108: MER
A111: Performance Email
A112: PROFIT | B112: =B26-(B13*'ECOMMERCE Formulas'!$I$15) -> 207.87182 | C112: =C26-(C13*'ECOMMERCE Formulas'!$I$15) -> 830.30773 | D112: =D26-(D13*'ECOMMERCE Formulas'!$I$15) -> 303.45886 | E112: =E26-(E13*'ECOMMERCE Formulas'!$I$15) -> 205.94591 | F112: =F26-(F13*'ECOMMERCE Formulas'!$I$15) -> 52.802955 | G112: =G26-(G13*'ECOMMERCE Formulas'!$I$15) -> 114.73295 | H112: =H26-(H13*'ECOMMERCE Formulas'!$I$15) -> 0 | I112: =I26-(I13*'ECOMMERCE Formulas'!$I$15) -> -121.15705 | ... AF112: =AF26-(AF13*'ECOMMERCE Formulas'!$I$15) -> 393.34182 | AG112: =SUM(B112:AF112) -> 25848.289
A113: ROAS
A114: CPO
A115: MER | B115: =B26/('ECOMMERCE Formulas'!$I$15*B13) -> 1.3421262 | C115: =C26/('ECOMMERCE Formulas'!$I$15*C13) -> 1.9110422 | D115: =D26/('ECOMMERCE Formulas'!$I$15*D13) -> 1.665931 | E115: =E26/('ECOMMERCE Formulas'!$I$15*E13) -> 1.6779128 | F115: =F26/('ECOMMERCE Formulas'!$I$15*F13) -> 1.3476233 | G115: =G26/('ECOMMERCE Formulas'!$I$15*G13) -> 1.7553337 | H115: =H26/('ECOMMERCE Formulas'!$I$15*H13) -> #DIV/0! | I115: =I26/('ECOMMERCE Formulas'!$I$15*I13) -> 0.20237392 | ... AF115: =AF26/('ECOMMERCE Formulas'!$I$15*AF13) -> 1.6473823
...

Sheet MTD & YTD CS realization
A1: FINANCE REPORT July 2023 | B1: MTD History | D1: MTD Actuals | F1: MTD Plan | H1: Actuals VS Plan | J1: GROWTH
B2: Jul.22 | D2: Jul.23 | F2: Jul.23 | H2: Jul.23 | J2: Growth YOY (%) | K2: Planned Growth (%)
A3: Contribution statment | B3: MTD EUR | C3: MTD EUR % TR | D3: MTD EUR | E3: MTD EUR % TR | F3: MTD EUR | G3: MTD EUR % TR | H3: Plan realization (%) | I3: Plan realization diff.
A4: TOTAL REVENUES (Order value) | B4: 135385.92 | C4: =IFERROR(B4/$B$4,"") -> 1 | D4: ='OLD Sales'!$B$51 -> 1411507.8 | E4: =IFERROR(D4/$D$4,"") -> 1 | F4: ='Forecast projection'!H13 -> 2000000 | G4: =IFERROR(F4/$F$4,"") -> 1 | H4: =IFERROR(D4/F4,"") -> 0.70575387 | I4: =D4-F4 -> -588492.25 | J4: =IFERROR(D4/B4-1,"") -> 9.425809 | K4: =IFERROR(F4/B4-1,"") -> 13.772585
A5: TOTAL REVENUES (Net order value) | B5: =B4-B14 -> 37446.04 | C5: =IFERROR(B5/$B$4,"") -> 0.2765874 | D5: =D4-D14 -> 1345221.1 | E5: =IFERROR(D5/$D$4,"") -> 0.95303841 | F5: =F4-F14 -> 1945000 | G5: =IFERROR(F5/$F$4,"") -> 0.9725 | H5: =IFERROR(D5/F5,"") -> 0.69163038 | I5: =D5-F5 -> -599778.9 | J5: =IFERROR(D5/B5-1,"") -> 34.924255 | K5: =IFERROR(F5/B5-1,"") -> 50.941407
A6: GROSS MARGIN (Net order value) | B6: =B5-B12 -> 28999.8 | C6: =IFERROR(B6/$B$5,"") -> 0.77444237 | D6: =D5-D12 -> 876798.99 | E6: =IFERROR(D6/$D$5,"") -> 0.65178801 | F6: =F5-F12 -> 1245000 | G6: =IFERROR(F6/$F$4,"") -> 0.6225 | H6: =IFERROR(D6/F6,"") -> 0.70425621 | I6: =D6-F6 -> -368201.01 | J6: =IFERROR(D6/B6-1,"") -> 29.234656 | K6: =IFERROR(F6/B6-1,"") -> 41.931331
A7: MEDIA GROSS PROFIT (Net order value) | B7: =B5-B12-B9 -> -12757.12 | C7: =IFERROR(B7/$B$5,"") -> -0.34068008 | D7: =D5-D12-D9 -> 334173.31 | E7: =IFERROR(D7/$D$5,"") -> 0.24841515 | F7: =F5-F12-F9 -> 545000 | G7: =IFERROR(F7/$F$5,"") -> 0.28020566 | H7: =IFERROR(D7/F7,"") -> 0.61316203 | I7: =D7-F7 -> -210826.69 | J7: =IFERROR(D7/B7-1,"") -> -27.195043 | K7: =IFERROR(F7/B7-1,"") -> -43.721241
A8: TOTAL COSTS | B8: =161681.9-B14 -> 63742.02 | C8: =IFERROR(B8/$B$4,"") -> 0.4708172 | D8: =sum(D9:D13) -> 1274147.7 | E8: =IFERROR(D8/$D$4,"") -> 0.90268558 | F8: =sum(F9:F13) -> 1750000 | G8: =IFERROR(F8/$F$4,"") -> 0.875 | H8: =IFERROR(D8/F8,"") -> 0.72808439 | I8: =D8-F8 -> -475852.31 | J8: =IFERROR(D8/B8-1,"") -> 18.989133 | K8: =IFERROR(F8/B8-1,"") -> 26.454417
A9: Media mix costs | B9: 41756.92 | C9: =IFERROR(B9/$B$4,"") -> 0.30842882 | D9: =sum('ECOMMERCE Detailed Report'!AG489:AG490) -> 542625.68 | E9: =IFERROR(D9/$D$4,"") -> 0.38442983 | F9: ='Forecast projection'!H15 -> 700000 | G9: =IFERROR(F9/$F$4,"") -> 0.35 | H9: =IFERROR(D9/F9,"") -> 0.77517954 | I9: =D9-F9 -> -157374.32 | J9: =IFERROR(D9/B9-1,"") -> 11.994868 | K9: =IFERROR(F9/B9-1,"") -> 15.763689
A10: Shipping costs (inbound & outbound) | B10: 5295.1 | C10: =IFERROR(B10/$B$4,"") -> 0.039111157 | D10: =sum('ECOMMERCE Detailed Report'!AG514:AG517) -> 133721.76 | E10: =IFERROR(D10/$D$4,"") -> 0.09473682 | F10: 180000 | G10: =IFERROR(F10/$F$4,"") -> 0.09 | H10: =IFERROR(D10/F10,"") -> 0.74289864 | I10: =D10-F10 -> -46278.245 | J10: =IFERROR(D10/B10-1,"") -> 24.253868 | K10: =IFERROR(F10/B10-1,"") -> 32.993692
A11: Fee costs (processing & transaction fees) | B11: 4060.06 | C11: =IFERROR(B11/$B$4,"") -> 0.029988791 | D11: =sum('ECOMMERCE Detailed Report'!AG512:AG513) -> 39425.59 | E11: =IFERROR(D11/$D$4,"") -> 0.027931543 | F11: 50000 | G11: =IFERROR(F11/$F$4,"") -> 0.025 | H11: =IFERROR(D11/F11,"") -> 0.7885118 | I11: =D11-F11 -> -10574.41 | J11: =IFERROR(D11/B11-1,"") -> 8.710593 | K11: =IFERROR(F11/B11-1,"") -> 11.315089
A12: COGS | B12: 8446.24 | C12: =IFERROR(B12/$B$5,"") -> 0.22555763 | D12: =sum('ECOMMERCE Detailed Report'!AG491:AG511) -> 468422.11 | E12: =IFERROR(D12/$D$5,"") -> 0.34821199 | F12: 700000 | G12: =IFERROR(F12/$F$4,"") -> 0.35 | H12: =IFERROR(D12/F12,"") -> 0.66917445 | I12: =D12-F12 -> -231577.89 | J12: =IFERROR(D12/B12-1,"") -> 54.459247 | K12: =IFERROR(F12/B12-1,"") -> 81.877115
A13: Taxes | B13: 4183.7 | C13: =IFERROR(B13/$B$4,"") -> 0.030902032 | D13: =sum('ECOMMERCE Detailed Report'!AG518:AG520) -> 89952.549 | E13: =IFERROR(D13/$D$4,"") -> 0.063727988 | F13: 120000 | G13: =IFERROR(F13/$F$4,"") -> 0.06 | H13: =IFERROR(D13/F13,"") -> 0.74960458 | I13: =D13-F13 -> -30047.451 | J13: =IFERROR(D13/B13-1,"") -> 20.500717 | K13: =IFERROR(F13/B13-1,"") -> 27.682745
A14: TOTAL REFUNDS (complaints) | B14: 97939.88 | C14: =IFERROR(B14/$B$4,"") -> 0.7234126 | D14: =sum(D15:D18) -> 66286.652 | E14: =IFERROR(D14/$D$4,"") -> 0.046961593 | F14: =sum(F15:F18) -> 55000 | G14: =IFERROR(F14/$F$4,"") -> 0.0275 | H14: =IFERROR(D14/F14,"") -> 1.2052119 | I14: =D14-F14 -> 11286.652 | J14: =IFERROR(D14/B14-1,"") -> -0.32319039 | K14: =IFERROR(F14/B14-1,"") -> -0.438431
A15: Cancellations | C15: =IFERROR(B15/$B$4,"") -> 0 | D15: ='ECOMMERCE Detailed Report'!AG522 -> 4396.92 | E15: =IFERROR(D15/$D$4,"") -> 0.003115052 | F15: 30000 | G15: =IFERROR(F15/$F$4,"") -> 0.015 | H15: =IFERROR(D15/F15,"") -> 0.146564 | I15: =D15-F15 -> -25603.08 | J15: =IFERROR(D15/B15-1,"") | K15: =IFERROR(F15/B15-1,"")
A16: Refunds + Shipping | C16: =IFERROR(B16/$B$4,"") -> 0 | D16: =sum('ECOMMERCE Detailed Report'!AG523:AG524) -> 61889.732 | E16: =IFERROR(D16/$D$4,"") -> 0.043846541 | F16: 15000 | G16: =IFERROR(F16/$F$4,"") -> 0.0075 | H16: =IFERROR(D16/F16,"") -> 4.1259821 | I16: =D16-F16 -> 46889.732 | J16: =IFERROR(D16/B16-1,"") | K16: =IFERROR(F16/B16-1,"")
A17: Chargebacks | C17: =IFERROR(B17/$B$4,"") -> 0 | D17: ='ECOMMERCE Detailed Report'!AG525 -> 0 | E17: =IFERROR(D17/$D$4,"") -> 0 | F17: 5000 | G17: =IFERROR(F17/$F$4,"") -> 0.0025 | H17: =IFERROR(D17/F17,"") -> 0 | I17: =D17-F17 -> -5000 | J17: =IFERROR(D17/B17-1,"") | K17: =IFERROR(F17/B17-1,"")
A18: Returns & Replacements | C18: =IFERROR(B18/$B$4,"") -> 0 | D18: ='ECOMMERCE Detailed Report'!AG579 -> 0 | E18: =IFERROR(D18/$D$4,"") -> 0 | F18: 5000 | G18: =IFERROR(F18/$F$4,"") -> 0.0025 | H18: =IFERROR(D18/F18,"") -> 0 | I18: =D18-F18 -> -5000 | J18: =IFERROR(D18/B18-1,"") | K18: =IFERROR(F18/B18-1,"")
A19: Sales profit | B19: =B4-B8-B14 -> -26295.98 | C19: =IFERROR(B19/$B$4,"") -> -0.1942298 | D19: =D4-D8-D14 -> 71073.411 | E19: =IFERROR(D19/$D$4,"") -> 0.050352831 | F19: =F4-F8-F14 -> 195000 | G19: =IFERROR(F19/$F$4,"") -> 0.0975 | H19: =IFERROR(D19/F19,"") -> 0.36447903 | I19: =D19-F19 -> -123926.59 | J19: =IFERROR(D19/B19-1,"") -> -3.7028242 | K19: =IFERROR(F19/B19-1,"") -> -8.4155822
A20: Sessions | B20: 54892 | D20: ='Forecast projection'!C114 -> 348656 | F20: ='Forecast projection'!H20 -> 624000 | H20: =IFERROR(D20/F20,"") -> 0.55874359 | I20: =D20-F20 -> -275344 | J20: =IFERROR(D20/B20-1,"") -> 5.3516724 | K20: =IFERROR(F20/B20-1,"") -> 10.367777
A21: Orders | B21: 418 | D21: ='OLD Sales'!B59 -> 5740 | F21: ='Forecast projection'!H14 -> 7800 | H21: =IFERROR(D21/F21,"") -> 0.73589744 | I21: =D21-F21 -> -2060 | J21: =IFERROR(D21/B21-1,"") -> 12.732057 | K21: =IFERROR(F21/B21-1,"") -> 17.660287
A22: Units sold | B22: 216 | D22: ='OLD Sales'!B60 -> 4752 | F22: 5000 | H22: =IFERROR(D22/F22,"") -> 0.9504 | I22: =D22-F22 -> -248 | J22: =IFERROR(D22/B22-1,"") -> 21 | K22: =IFERROR(F22/B22-1,"") -> 22.148148
A23: CR | B23: =B21/B20 -> 0.007614953 | D23: =D21/D20 -> 0.016463219 | F23: =F21/F20 -> 0.0125 | H23: =IFERROR(D23/F23,"") -> 1.3170575 | I23: =D23-F23 -> 0.0039632188 | J23: =IFERROR(D23/B23-1,"") -> 1.1619593 | K23: =IFERROR(F23/B23-1,"") -> 0.64150718
A24: CAC per order | B24: =B9/B21 -> 99.896938 | D24: =D9/D21 -> 94.534091 | F24: =F9/F21 -> 89.74359 | H24: =IFERROR(D24/F24,"") -> 1.0533799 | I24: =D24-F24 -> 4.7905008 | J24: =IFERROR(D24/B24-1,"") -> -0.0536838 | K24: =IFERROR(F24/B24-1,"") -> -0.10163823
A25: CAC per unit | B25: =B9/B22 -> 193.31907 | D25: =D9/D22 -> 114.18891 | F25: =F9/F22 -> 140 | H25: =IFERROR(D25/F25,"") -> 0.81563504 | I25: =D25-F25 -> -25.811094 | J25: =IFERROR(D25/B25-1,"") -> -0.40932416 | K25: =IFERROR(F25/B25-1,"") -> -0.27580866
A26: AOV | B26: =B4/B21 -> 323.88976 | D26: =D4/D21 -> 245.90727 | F26: =F4/F21 -> 256.41026 | H26: =IFERROR(D26/F26,"") -> 0.95903837 | I26: =D26-F26 -> -10.502983 | J26: =IFERROR(D26/B26-1,"") -> -0.24076861 | K26: =IFERROR(F26/B26-1,"") -> -0.20834096
A27: Revenue Per Session | B27: =B4/B20 -> 2.4664053 | D27: =D4/D20 -> 4.0484252 | F27: =F4/F20 -> 3.2051282 | H27: =IFERROR(D27/F27,"") -> 1.2631087 | I27: =D27-F27 -> 0.84329703 | J27: =IFERROR(D27/B27-1,"") -> 0.6414274 | K27: =IFERROR(F27/B27-1,"") -> 0.29951399
A28: Cost Per Session (media mix costs) | B28: =B9/B20 -> 0.76071049 | D28: =D9/D20 -> 1.5563354 | F28: =F9/F20 -> 1.1217949 | H28: =IFERROR(D28/F28,"") -> 1.3873619 | I28: =D28-F28 -> 0.43454054 | J28: =IFERROR(D28/B28-1,"") -> 1.0458971 | K28: =IFERROR(F28/B28-1,"") -> 0.47466729

Sheet Ziga - TEST by prod.
A1: CPO NONVV % = Marketing costs / Order no vat value * 100
A2: ROI NONVV = (Net order no VAT value - Purchase value of sold products (NONVV)) / Marketing costs
A3: COGS NONVV % = Purchase Value of Sold Products (NONVV) / Net order no VAT value
A4: MGP NONVV = Net Order no VAT value - Purchase Value of Sold Products (NONVV) - Marketing costs
A5: MGP Company by IL NONVV %T = measure gives us information how much each item level represents in total MGP inside the company. Media gross profit (MGP) calculated based on Net Order no VAT Value. Calculated as: if Media Gross Profit (NONVV) < 0 then “loss” else Media Gross Profit (NONVV) / Media Gross Profit (NONVV) on All Product Hierarchy level
A6: Revenue Company by IL NONVV % = measure gives us information how much each item level represents in total revenue (NONVV) inside the company. Calculated as: Net Order no VAT Value / Net Order no VAT Value on All Product Hierarchy level
A7: Cost company by IL % =The measure gives us information how much each item level represents in total costs inside the company. Calculated as: if Marketing Costs < 0 then “return” else Cost Value / Cost Value on All Product Hierarchy level
A8: Net Order no VAT Value – Order value subtracted with estimated complaints and without VAT. IL = item level
A10: Sales KPI-s by product | C10: W01-23 | D10: W02-23 | E10: W03-23 | F10: W04-23 | G10: jan.23 | H10: W05-23 | I10: W06-23 | J10: W07-23 | K10: W08-23 | L10: feb.23 | M10: W09-23 | N10: W010-23 | O10: W11-23 | P10: W12-23 | Q10: mar.23 | R10: W013-23 | S10: W14-23 | T10: W15-23 | U10: W16-23 | V10: apr.23 | W10: W17-23 | X10: W18-23 | Y10: W19-23 | Z10: W20-23 | AA10: may.23 | AB10: W21-23 | AC10: W22-23 | AD10: W23-23 | AE10: W24-23 | AF10: jun.23 | AG10: W25-23 | AH10: W26-23 | AI10: W27-23 | AJ10: W28-23 | AK10: jul.23 | AL10: W29-23 | AM10: W30-23 | AN10: W31-23 | AO10: W32-23
A11: SKU1 - Bird Buddy | B11: CPO NONVV %
B12: ROI NONVV
B13: COGS NONVV % | G13: 0.309895 | L13: 0.3119217 | Q13: 0.29415804 | V13: 0.30865335 | AA13: 0.31000242 | AF13: 0.27982409 | AG13: 0.2785 | AH13: 0.2856 | AI13: 0.3275 | AJ13: 0.18
B14: Revenue Company by IL NONVV % | G14: 0.25098081 | L14: 0.1654453 | Q14: 0.16328349 | V14: 0.23704979 | AA14: 0.27294309 | AF14: 0.25235275 | AG14: 0.2384 | AH14: 0.2648 | AI14: 0.2539 | AJ14: 0.2468
B15: Cost Company by IL %
B16: MGP Company by IL NONVV %
B17: MGP NONVV
B18: Net Order no VAT Value | G18: 321134.03 | L18: 230184.5 | Q18: 286763.81 | V18: 504547.38 | AA18: 682315.55 | AF18: 314811.96 | AG18: 67360.26 | AH18: 95833.95 | AI18: 99499.82 | AJ18: 52117.93
B19: Cost no VAT Value | G19: ? | L19: ? | Q19: ? | V19: ? | AA19: ? | AF19: ?
A20: SKU3 - Bird Buddy w Solar Roof | B20: CPO NONVV %
B21: ROI NONVV
B22: COGS NONVV % | G22: 0.28119759 | L22: 0.30040943 | Q22: 0.29855249 | V22: 0.29444208 | AA22: 0.30231202 | AF22: 0.2823923 | AG22: 0.2712 | AH22: 0.2781 | AI22: 0.3018 | AJ22: 0.2709
B23: Revenue Company by IL NONVV % | G23: 0.46094251 | L23: 0.60506353 | Q23: 0.64054512 | V23: 0.59558108 | AA23: 0.57082433 | AF23: 0.57738002 | AG23: 0.6018 | AH23: 0.5506 | AI23: 0.56 | AJ23: 0.6229
B24: Cost Company by IL %
B25: MGP Company by IL NONVV %
B26: MGP NONVV
B27: Net Order no VAT Value | G27: 589783.44 | L27: 841826.57 | Q27: 1124946.3 | V27: 1267661.4 | AA27: 1426972.6 | AF27: 720285.94 | AG27: 170067.38 | AH27: 199232.97 | AI27: 219454.83 | AJ27: 131530.76
B28: Cost no VAT Value | G28: ? | L28: ? | Q28: ? | V28: ? | AA28: ? | AF28: ?
A29: SKU6 - Solar Roof Single | B29: CPO NONVV %
B30: ROI NONVV
B31: COGS NONVV % | G31: 0.13876091 | L31: 0.13102871 | Q31: 0.13358532 | V31: 0.14259104 | AA31: 0.13550836 | AF31: 0.14426752 | AG31: 0.1701 | AH31: 0.1362 | AI31: 0.1424 | AJ31: 0.129
B32: Revenue Company by IL NONVV % | G32: 0.09100483 | L32: 0.028576756 | Q32: 0.022503259 | V32: 0.029167522 | AA32: 0.019856888 | AF32: 0.02922331 | AG32: 0.0295 | AH32: 0.0306 | AI32: 0.0256 | AJ32: 0.0333
B33: Cost Company by IL %
B34: MGP Company by IL NONVV %
B35: MGP NONVV
B36: Net Order no VAT Value | G36: 116442.16 | L36: 39758.92 | Q36: 39520.96 | V36: 62081.46 | AA36: 49639.15 | AF36: 36456.3 | AG36: 8333.11 | AH36: 11062.28 | AI36: 10023 | AJ36: 7037.91
B37: Cost no VAT Value | G37: ? | L37: ? | Q37: ? | V37: ? | AA37: ? | AF37: ?
A38: Sales KPI-s by product (US)
A39: SKU1 - Bird Buddy Blue | B39: CPO NONVV %
B40: ROI NONVV
B41: COGS NONVV %
B42: Revenue Company by IL NONVV %
B43: Cost Company by IL %
B44: MGP Company by IL NONVV %
B45: MGP NONVV
B46: Net Order no VAT Value
B47: Cost no VAT Value
A48: SKU2 - Bird Buddy Yellow | B48: CPO NONVV %
B49: ROI NONVV
B50: COGS NONVV %
B51: Revenue Company by IL NONVV %
B52: Cost Company by IL %
B53: MGP Company by IL NONVV %
B54: MGP NONVV
B55: Net Order no VAT Value
B56: Cost no VAT Value
A57: SKU3 - Bird Buddy Blue w Solar Roof | B57: CPO NONVV %
B58: ROI NONVV
B59: COGS NONVV %
B60: Revenue Company by IL NONVV %
B61: Cost Company by IL %
B62: MGP Company by IL NONVV %
B63: MGP NONVV
B64: Net Order no VAT Value
B65: Cost no VAT Value
A66: SKU4 - Bird Buddy Yellow w Solar Roof | B66: CPO NONVV %
B67: ROI NONVV
B68: COGS NONVV %
B69: Revenue Company by IL NONVV %
B70: Cost Company by IL %
B71: MGP Company by IL NONVV %
B72: MGP NONVV
B73: Net Order no VAT Value
B74: Cost no VAT Value
A75: SKU5 - Fence Mount | B75: CPO NONVV %
B76: ROI NONVV
B77: COGS NONVV %
B78: Revenue Company by IL NONVV %
B79: Cost Company by IL %
B80: MGP Company by IL NONVV %
B81: MGP NONVV
B82: Net Order no VAT Value
B83: Cost no VAT Value
A84: SKU6 - Solar Roof Blue | B84: CPO NONVV %
B85: ROI NONVV
B86: COGS NONVV %
B87: Revenue Company by IL NONVV %
B88: Cost Company by IL %
B89: MGP Company by IL NONVV %
B90: MGP NONVV
B91: Net Order no VAT Value
B92: Cost no VAT Value
A93: SKU7 - Solar Roof Yellow | B93: CPO NONVV %
B94: ROI NONVV
B95: COGS NONVV %
B96: Revenue Company by IL NONVV %
B97: Cost Company by IL %
B98: MGP Company by IL NONVV %
B99: MGP NONVV
B100: Net Order no VAT Value
B101: Cost no VAT Value
...
