Workbook
Name rdataslayer_d70e473bcafe40a3aa834ce157fb2ba3: 'Business Metrics Canada'!$C$16:$D$17
Name zsupermetrics_xwoIpANxRm908eDp5oKTwQpEI8gvD4: 'Business Metrics US'!$A$5
Name zsupermetrics_ru0GDtbZzDLHQOQtJJ6K08MvUDyyp7: #REF!
Name zsupermetrics_iNpyVy90bWCI0yUaFQpxOtzWMa6sW4: 'Business Metrics US'!$A$5:$A$12
Name zsupermetrics_DQl8lUbpTRu3fayaJJi7lVfOGKjNU4: 'OLD Formulas'!$A$3:$A$4
Name zsupermetrics_NugLlrQxlKiqhxQae8EFpITBm1pLCj: 'Business Metrics Canada'!$B$15:$C$23
Name rdataslayer_4a0f150f4f2f4e4f85c890c75b7a1fa4: 'Business Metrics Canada'!$D$5:$E$12
Name zsupermetrics_BioPyGBzcBsy60UCQmPcTuFReEmghI: 'OLD Formulas'!$B$2:$B$3
Name zsupermetrics_refreshAll: SupermetricsQueries!$H$5
Name zsupermetrics_DQl8lUbpTRu3fayaJJi7lVfOGKjNU4: 'Business Metrics Canada'!$A$2:$A$13
Name zsupermetrics_n3GtLgiKpTmd2pYmQNMuq6TPD0qE0b: #REF!
Name zsupermetrics_9i4W4hgd80uRpQLMeX0eRnESN8gjyv: 'Business Metrics US'!$C$23
Name zsupermetrics_qWp7V908pNEYMtfv8QZvSTeDnBAHOU: 'Business Metrics Canada'!$B$14:$C$23
Name zsupermetrics_refreshAllSilent: SupermetricsQueries!$H$6
Name zsupermetrics_Mgms9p0QzysYvrIhnsKACeVBVxfIEO: #REF!
Name rdataslayer_4a0f150f4f2f4e4f85c890c75b7a1fa4: 'Business Metrics US'!$D$5:$E$12
Name zsupermetrics_lx4cNai7gT6tH4j08ZRkI21Qlpjioi: 'Business Metrics Canada'!$B$13:$C$23
Name zsupermetrics_Mgms9p0QzysYvrIhnsKACeVBVxfIEO: 'OLD Formulas'!$A$2:$A$3
Name zsupermetrics_forceRefresh: SupermetricsQueries!$H$4
Name zsupermetrics_wbYMmT0YL9bAN0yhimW0ziPFnia9Dx: #REF!
Name zsupermetrics_iNpyVy90bWCI0yUaFQpxOtzWMa6sW4: #REF!
Name zsupermetrics_xwoIpANxRm908eDp5oKTwQpEI8gvD4: 'Business Metrics Canada'!$A$5
Name zsupermetrics_xwoIpANxRm908eDp5oKTwQpEI8gvD4: #REF!
Name rdataslayer_3753ddf3234e496aa261974a0222e193: 'Business Metrics US'!$H$5:$I$5
Name zsupermetrics_4VkB7ij7WO0JjKBEgvjB2GHjSy2Egm: 'Business Metrics Canada'!$B$13:$C$17
Name zsupermetrics_n3GtLgiKpTmd2pYmQNMuq6TPD0qE0b: 'OLD Formulas'!$B$4:$B$5
Name rdataslayer_42b112e4e4be4305bb4c1be75e2dd549: 'OLD Formulas'!$B$2:$C$3
Name zsupermetrics_wbYMmT0YL9bAN0yhimW0ziPFnia9Dx: 'Business Metrics Canada'!$A$5:$A$12
Name zsupermetrics_9i4W4hgd80uRpQLMeX0eRnESN8gjyv: #REF!
Name zsupermetrics_YsFuuYtr8vOdNXCCPiFJIO38NP4b2T: 'Business Metrics US'!$B$13:$C$23
Name zsupermetrics_5bmwtOpHUbSYmDMeuCPkrxaojTprPP: #REF!
Name rdataslayer_adf57e64065742daa5b4161161b1c3ca: 'Business Metrics Canada'!$B$13:$D$14
Name zsupermetrics_9i4W4hgd80uRpQLMeX0eRnESN8gjyv: 'Business Metrics Canada'!$C$23
Name rdataslayer_3753ddf3234e496aa261974a0222e193: 'OLD Formulas'!$H$2:$I$2
Name zsupermetrics_4VkB7ij7WO0JjKBEgvjB2GHjSy2Egm: 'Business Metrics US'!$B$13:$C$17
Name zsupermetrics_SGBxROnInO9rFyh3H7j2Lldx0Bdc5v: #REF!
Name zsupermetrics_pxuhRTEmIU93xSgKclyxajD0fCZ6rF: #REF!
Name zsupermetrics_ru0GDtbZzDLHQOQtJJ6K08MvUDyyp7: 'OLD Formulas'!$B$4:$B$5
Name zsupermetrics_qWp7V908pNEYMtfv8QZvSTeDnBAHOU: 'OLD Formulas'!$B$5:$C$13
Name zsupermetrics_wbYMmT0YL9bAN0yhimW0ziPFnia9Dx: 'Business Metrics US'!$A$5:$A$12
Name rdataslayer_4a0f150f4f2f4e4f85c890c75b7a1fa4: #REF!
Name zsupermetrics_iNpyVy90bWCI0yUaFQpxOtzWMa6sW4: 'Business Metrics Canada'!$A$5:$A$12
Name zsupermetrics_HgZqhorObHOtZHuyJjpmyYaEPoYntx: #REF!
Name zsupermetrics_YsFuuYtr8vOdNXCCPiFJIO38NP4b2T: #REF!
Name zsupermetrics_DQl8lUbpTRu3fayaJJi7lVfOGKjNU4: #REF!
Name zsupermetrics_YVuzfmsfdurz7Ldl84Rfns8oka6LsS: #REF!
Name zsupermetrics_4VkB7ij7WO0JjKBEgvjB2GHjSy2Egm: #REF!
Name zsupermetrics_9i4W4hgd80uRpQLMeX0eRnESN8gjyv: 'OLD Formulas'!$C$13
Name zsupermetrics_Mgms9p0QzysYvrIhnsKACeVBVxfIEO: 'Business Metrics US'!$A$5:$A$12
Name zsupermetrics_lx4cNai7gT6tH4j08ZRkI21Qlpjioi: #REF!
Name zsupermetrics_BioPyGBzcBsy60UCQmPcTuFReEmghI: 'Business Metrics US'!$B$5:$B$12
Name zsupermetrics_qWp7V908pNEYMtfv8QZvSTeDnBAHOU: 'Business Metrics US'!$B$14:$C$23
Name rdataslayer_adf57e64065742daa5b4161161b1c3ca: 'Business Metrics US'!$B$13:$D$14
Name rdataslayer_d70e473bcafe40a3aa834ce157fb2ba3: #REF!
Name zsupermetrics_NugLlrQxlKiqhxQae8EFpITBm1pLCj: 'OLD Formulas'!$B$6:$C$13
Name zsupermetrics_8xojRjNDjo2jWHGDWjFEhflhyIq3Hq: 'OLD Sales'!$K$8:$K$23
Name rdataslayer_42b112e4e4be4305bb4c1be75e2dd549: 'Business Metrics Canada'!$B$5:$C$12
Name rdataslayer_d70e473bcafe40a3aa834ce157fb2ba3: 'Business Metrics US'!$C$16:$D$17
Name rdataslayer_3753ddf3234e496aa261974a0222e193: #REF!
Name zsupermetrics_BioPyGBzcBsy60UCQmPcTuFReEmghI: 'Business Metrics Canada'!$B$5:$B$12

Sheet DataslayerQueries
A1: Query UUID | B1: Sheet name | C1: Range address | D1: Created | E1: Updated | F1: Last status | G1: Last refresh ID | H1: Results contain sampled data | I1: Execution time (sec) | J1: Object type | K1: Linked chart ID | L1: Data source | M1: Date range type | N1: Start date | O1: End date | P1: Compare to | Q1: Comparison value type | R1: Accounts/views | S1: Metrics | T1: Dimensions | U1: Pivot dimensions | V1: Filters | W1: Segment ID | X1: Segment dim | Y1: Sort | Z1: Max rows | AA1: Max pivot categories | AB1: Special settings | AC1: Other parameters | AD1: Result type | AE1: Language/country | AF1: Translate to | AG1: SQL | AH1: Database name | AI1: Range address (static) | AJ1: Report type | AK1: Highlight with colour | AL1: Refresh with user account | AM1: Returned data | AN1: Sort dimensions | AO1: Created by user account
A2: 42b112e4e4be4305bb4c1be75e2dd549 | B2: =IFERROR(__xludf.DUMMYFUNCTION("ARRAY_CONSTRAIN(split(CELL(""ADDRESS"",rdataslayer_42b112e4e4be4305bb4c1be75e2dd549),""!""),1,1)"),"#REF!") -> #REF! | C2: =IFERROR(__xludf.DUMMYFUNCTION("INDEX(split(CELL(""ADDRESS"",rdataslayer_42b112e4e4be4305bb4c1be75e2dd549),""!""),0,2)&"":""&address(row(rdataslayer_42b112e4e4be4305bb4c1be75e2dd549)+rows(rdataslayer_42b112e4e4be4305bb4c1be75e2dd549)-1,column(rdataslayer_42b112e4e4be4305bb4c1be75e2dd549"&")+COLUMNS(rdataslayer_42b112e4e4be4305bb4c1be75e2dd549)-1)"),"#REF!") -> #REF! | D2: 44518.613 | E2: 44520.051 | F2: There is no data for the specified input | I2: 7 | J2: TABLE | L2: facebook | M2: yesterday | R2: [{"profile_id":"","name":"si_Bird buddy Inc_US &amp; CA_BirdBuddy","id":"act_273249767551281","account_name":"","advertiser_id":""}] | S2: [{"id":"spend","name":"Total Cost"}] | T2: [{"id":"date","name":"Date"}] | U2: [] | V2: [] | W2: [] | Y2: [] | Z2: 5 | AA2: 5 | AB2: {} | AC2: {} | AL2: User_Kumalic_Benjamin | AN2: [] | AO2: benjamin@mybirdbuddy.com
A3: 4a0f150f4f2f4e4f85c890c75b7a1fa4 | B3: =IFERROR(__xludf.DUMMYFUNCTION("ARRAY_CONSTRAIN(split(CELL(""ADDRESS"",rdataslayer_4a0f150f4f2f4e4f85c890c75b7a1fa4),""!""),1,1)"),"#REF!") -> #REF! | C3: =IFERROR(__xludf.DUMMYFUNCTION("INDEX(split(CELL(""ADDRESS"",rdataslayer_4a0f150f4f2f4e4f85c890c75b7a1fa4),""!""),0,2)&"":""&address(row(rdataslayer_4a0f150f4f2f4e4f85c890c75b7a1fa4)+rows(rdataslayer_4a0f150f4f2f4e4f85c890c75b7a1fa4)-1,column(rdataslayer_4a0f150f4f2f4e4f85c890c75b7a1fa4"&")+COLUMNS(rdataslayer_4a0f150f4f2f4e4f85c890c75b7a1fa4)-1)"),"#REF!") -> #REF! | D3: 44518.615 | E3: 44520.051 | F3: There is no data for the specified input | I3: 7 | J3: TABLE | L3: facebook | M3: yesterday | R3: [{"account_name":"","advertiser_id":"","id":"act_273249767551281","profile_id":"","name":"si_Bird buddy Inc_US &amp; CA_BirdBuddy"}] | S3: [{"id":"spend","name":"Total Cost"}] | T3: [] | U3: [{"id":"date","name":"Date"}] | V3: [] | W3: [] | Y3: [] | Z3: 5 | AA3: 5 | AB3: {} | AC3: {} | AL3: User_Kumalic_Benjamin | AN3: [] | AO3: benjamin@mybirdbuddy.com
A4: adf57e64065742daa5b4161161b1c3ca | B4: =IFERROR(__xludf.DUMMYFUNCTION("ARRAY_CONSTRAIN(split(CELL(""ADDRESS"",rdataslayer_adf57e64065742daa5b4161161b1c3ca),""!""),1,1)"),"#REF!") -> #REF! | C4: =IFERROR(__xludf.DUMMYFUNCTION("INDEX(split(CELL(""ADDRESS"",rdataslayer_adf57e64065742daa5b4161161b1c3ca),""!""),0,2)&"":""&address(row(rdataslayer_adf57e64065742daa5b4161161b1c3ca)+rows(rdataslayer_adf57e64065742daa5b4161161b1c3ca)-1,column(rdataslayer_adf57e64065742daa5b4161161b1c3ca"&")+COLUMNS(rdataslayer_adf57e64065742daa5b4161161b1c3ca)-1)"),"#REF!") -> #REF! | D4: 44518.618 | E4: 44520.051 | F4: There is no data for the specified input | I4: 18 | J4: TABLE | L4: facebook | M4: yesterday | R4: [{"name":"si_Bird buddy Inc_US &amp; CA_BirdBuddy","id":"act_273249767551281","profile_id":"","account_name":"","advertiser_id":""}] | S4: [{"id":"spend","name":"Total Cost"},{"id":"cpm","name":"CPM"}] | T4: [{"id":"date","name":"Date"}] | U4: [] | V4: [] | W4: [] | Y4: [] | Z4: 5 | AA4: 5 | AB4: {} | AC4: {} | AL4: User_Kumalic_Benjamin | AN4: [] | AO4: benjamin@mybirdbuddy.com
A5: d70e473bcafe40a3aa834ce157fb2ba3 | B5: =IFERROR(__xludf.DUMMYFUNCTION("ARRAY_CONSTRAIN(split(CELL(""ADDRESS"",rdataslayer_d70e473bcafe40a3aa834ce157fb2ba3),""!""),1,1)"),"#REF!") -> #REF! | C5: =IFERROR(__xludf.DUMMYFUNCTION("INDEX(split(CELL(""ADDRESS"",rdataslayer_d70e473bcafe40a3aa834ce157fb2ba3),""!""),0,2)&"":""&address(row(rdataslayer_d70e473bcafe40a3aa834ce157fb2ba3)+rows(rdataslayer_d70e473bcafe40a3aa834ce157fb2ba3)-1,column(rdataslayer_d70e473bcafe40a3aa834ce157fb2ba3"&")+COLUMNS(rdataslayer_d70e473bcafe40a3aa834ce157fb2ba3)-1)"),"#REF!") -> #REF! | D5: 44518.619 | E5: 44520.051 | F5: There is no data for the specified input | I5: 7 | J5: TABLE | L5: facebook | M5: yesterday | R5: [{"advertiser_id":"","name":"si_Bird buddy Inc_US &amp; CA_BirdBuddy","id":"act_273249767551281","account_name":"","profile_id":""}] | S5: [{"id":"spend","name":"Total Cost"}] | T5: [{"id":"date","name":"Date"}] | U5: [] | V5: [] | W5: [] | Y5: [] | Z5: 100 | AA5: 100 | AB5: {} | AC5: {} | AL5: User_Kumalic_Benjamin | AN5: [] | AO5: benjamin@mybirdbuddy.com
A6: 3753ddf3234e496aa261974a0222e193 | B6: =IFERROR(__xludf.DUMMYFUNCTION("ARRAY_CONSTRAIN(split(CELL(""ADDRESS"",rdataslayer_3753ddf3234e496aa261974a0222e193),""!""),1,1)"),"#REF!") -> #REF! | C6: =IFERROR(__xludf.DUMMYFUNCTION("INDEX(split(CELL(""ADDRESS"",rdataslayer_3753ddf3234e496aa261974a0222e193),""!""),0,2)&"":""&address(row(rdataslayer_3753ddf3234e496aa261974a0222e193)+rows(rdataslayer_3753ddf3234e496aa261974a0222e193)-1,column(rdataslayer_3753ddf3234e496aa261974a0222e193"&")+COLUMNS(rdataslayer_3753ddf3234e496aa261974a0222e193)-1)"),"#REF!") -> #REF! | D6: 44518.621 | E6: 44520.051 | F6: There is no data for the specified input | I6: 18 | J6: TABLE | L6: facebook | M6: yesterday | R6: [{"profile_id":"","account_name":"","advertiser_id":"","name":"si_Bird buddy Inc_US &amp; CA_BirdBuddy","id":"act_273249767551281"}] | S6: [{"id":"spend","name":"Total Cost"}] | T6: [] | U6: [] | V6: [] | W6: [] | Y6: [] | Z6: 100 | AA6: 100 | AB6: {"exclude_header_row":true} | AC6: {} | AL6: User_Kumalic_Benjamin | AN6: [] | AO6: benjamin@mybirdbuddy.com

Sheet Summary
A1: 45170 | B1: 45170 | C1: 45171 | D1: 45172 | E1: 45173 | F1: 45174 | G1: 45175 | H1: 45176 | I1: 45177 | J1: 45178 | K1: 45179 | L1: 45180 | M1: 45181 | N1: 45182 | O1: 45183 | P1: 45184 | Q1: 45185 | R1: 45186 | S1: 45187 | T1: 45188 | U1: 45189 | V1: 45190 | W1: 45191 | X1: 45192 | Y1: 45193 | Z1: 45194 | AA1: 45195 | AB1: 45196 | AC1: 45197 | AD1: 45198 | AE1: 45199
B2: FRI | C2: SAT | D2: SUN | E2: MON | F2: TUE | G2: WED | H2: THU | I2: FRI | J2: SAT | K2: SUN | L2: MON | M2: TUE | N2: WED | O2: THU | P2: FRI | Q2: SAT | R2: SUN | S2: MON | T2: TUE | U2: WED | V2: THU | W2: FRI | X2: SAT | Y2: SUN | Z2: MON | AA2: TUE | AB2: WED | AC2: THU | AD2: FRI | AE2: SAT
A3: Weekend Work | C3: Peco | D3: Peco | J3: Peco | K3: Peco | Q3: Peter | R3: Peter | X3: Peter | Y3: Peter | AE3: Peco
A4: Notes | S4: PRO Subscription Launch | X4: SKU3 ABC Test - Testing availability
B5: Labor Day | N5: 10% off Sitewide | S5: Keynote
G6: IGG Launch | S6: Perch Extender Launch | AB6: Existing users email sent at 15:35
A8: DTC Revenue | B8: =sum(B9:B14) -> 16813.33 | C8: =sum(C9:C14) -> 24584.7 | D8: =sum(D9:D14) -> 29900.76 | E8: =sum(E9:E14) -> 36334.28 | F8: =sum(F9:F14) -> 33865.73 | G8: =sum(G9:G14) -> 26222.32 | H8: =sum(H9:H14) -> 19010.62 | I8: =sum(I9:I14) -> 14263.81 | ... AE8: =sum(AE9:AE14) -> 24655.64
A9: - Hardware | B9: 13722.1 | C9: 19550.7 | D9: 23435.2 | E9: 29484.65 | F9: 27664 | G9: 20990.5 | H9: 15207.5 | I9: 11768 | J9: 14587.8 | K9: 18895.35 | L9: 16210 | M9: 14428.3 | N9: 14116.6 | O9: 16589.5 | P9: 17022.8 | Q9: 15507.9 | R9: 16466.4 | S9: 19896.36 | T9: 17790.86 | U9: 15609.46 | V9: 15125.66 | W9: 14080.46 | X9: 14631.43 | Y9: 17414.66 | Z9: 17603 | AA9: 12051.38 | AB9: 21870.44 | AC9: 15951.41 | AD9: 17981.86 | AE9: 19255.96
A10: - Add-ons | B10: 1072.8 | C10: 1944.6 | D10: 2730.2 | E10: 2310.6 | F10: 2146.4 | G10: 2010 | H10: 1468.7 | I10: 941 | J10: 1121.5 | K10: 1949.4 | L10: 2023.5 | M10: 1254 | N10: 1044 | O10: 1530.2 | P10: 1517.4 | Q10: 1717.1 | R10: 1458 | S10: 22114.94 | T10: 11299.34 | U10: 5629.34 | V10: 4905.34 | W10: 3952.34 | X10: 4079.17 | Y10: 4446.34 | Z10: 3484 | AA10: 2812.7 | AB10: 3183.5 | AC10: 3209.84 | AD10: 3033.54 | AE10: 2396.19
A11: - Merch
A12: - Seeds
A13: - Taxes | B13: 868.43 | C13: 1259.4 | D13: 1585.36 | E13: 1889.03 | F13: 1815.33 | G13: 1391.82 | H13: 1024.42 | I13: 584.81 | J13: 1032.12 | K13: 1238.66 | L13: 1152.7 | M13: 933.13 | N13: 850.02 | O13: 1041.8 | P13: 1073.31 | Q13: 1026.42 | R13: 1169.32 | S13: 2713 | T13: 1702.35 | U13: 1234.72 | V13: 1184.78 | W13: 1095.42 | X13: 1040.12 | Y13: 1309.75 | Z13: 1109.86 | AA13: 881.17 | AB13: 1570.77 | AC13: 1125.82 | AD13: 1271.39 | AE13: 1353.49
A14: - Shipping | B14: 1150 | C14: 1830 | D14: 2150 | E14: 2650 | F14: 2240 | G14: 1830 | H14: 1310 | I14: 970 | J14: 965 | K14: 1485 | L14: 1360 | M14: 990 | N14: 1100 | O14: 1425 | P14: 1470 | Q14: 1265 | R14: 1215 | S14: 7925 | T14: 4445 | U14: 2485 | V14: 2110 | W14: 1895 | X14: 1900 | Y14: 2120 | Z14: 2150 | AA14: 1440 | AB14: 1785 | AC14: 1740 | AD14: 1520 | AE14: 1650
A15: Amazon Revenue | B15: =B16+B17+B18+B19+B20 -> 3281.76 | C15: =C16+C17+C18+C19+C20 -> 3000.84 | D15: =D16+D17+D18+D19+D20 -> 4785.04 | E15: =E16+E17+E18+E19+E20 -> 6287.08 | F15: =F16+F17+F18+F19+F20 -> 5999.8 | G15: =G16+G17+G18+G19+G20 -> 5360.55 | H15: =H16+H17+H18+H19+H20 -> 3848.96 | I15: =I16+I17+I18+I19+I20 -> 2985.94 | ... AE15: =AE16+AE17+AE18+AE19+AE20 -> 7779.39
A16: - Hardware | B16: 3069 | C16: 2790 | D16: 4464 | E16: 5859 | F16: 5580 | G16: 5022 | H16: 3627 | I16: 2790 | J16: 7254 | K16: 6138 | L16: 6138 | M16: 7533 | N16: 7533 | O16: 8649 | P16: 4185 | Q16: 5859 | R16: 5022 | S16: 6975 | T16: 13671 | U16: 8928 | V16: 8649 | W16: 11160 | X16: 5580 | Y16: 10881 | Z16: 8928 | AA16: 10044 | AB16: 9207 | AC16: 11439 | AD16: 10323 | AE16: 7254
A17: - Add-ons | B17: 0 | C17: 0 | D17: 0 | E17: 0 | F17: 0 | G17: 0 | H17: 0 | I17: 0 | J17: 0 | K17: 0 | L17: 0 | M17: 0 | N17: 0 | O17: 0 | P17: 0 | Q17: 0 | R17: 0 | S17: 0 | T17: 0 | U17: 0 | V17: 0 | W17: 0 | X17: 0 | Y17: 0 | Z17: 0 | AA17: 0 | AB17: 0 | AC17: 0 | AD17: 0 | AE17: 0
A18: - Tax | B18: 205.77 | C18: 210.38 | D18: 302.63 | E18: 423.13 | F18: 410.82 | G18: 328.65 | H18: 221.96 | I18: 195.94 | J18: 524.61 | K18: 451.31 | L18: 392.02 | M18: 499.26 | N18: 554.7 | O18: 583.53 | P18: 320.37 | Q18: 382.52 | R18: 342.06 | S18: 506.38 | T18: 989.01 | U18: 581.41 | V18: 602.81 | W18: 795.33 | X18: 424.74 | Y18: 795.77 | Z18: 629.32 | AA18: 699.27 | AB18: 608.52 | AC18: 823.17 | AD18: 705.3 | AE18: 520.9
A19: - Shipping | B19: 6.99 | C19: 0.29 | D19: 13.75 | E19: 0.29 | F19: 0 | G19: 0.58 | H19: 0 | I19: 0 | J19: 0.29 | K19: 0 | L19: 6.99 | M19: 6.15 | N19: 11.79 | O19: 7.28 | P19: 0 | Q19: 0 | R19: 0 | S19: 0 | T19: 0.58 | U19: 6.99 | V19: 0 | W19: 0.29 | X19: 4.48 | Y19: 0.29 | Z19: 0 | AA19: 0 | AB19: 1.45 | AC19: 7.28 | AD19: 0.58 | AE19: 0
A20: - Gift Wrap | B20: 0 | C20: 0.17 | D20: 4.66 | E20: 4.66 | F20: 8.98 | G20: 9.32 | H20: 0 | I20: 0 | J20: 0.17 | K20: 4.49 | L20: 4.49 | M20: 13.98 | N20: 13.47 | O20: 9.15 | P20: 8.98 | Q20: 0 | R20: 8.98 | S20: 0 | T20: 4.83 | U20: 4.49 | V20: 0 | W20: 4.66 | X20: 4.49 | Y20: 9.15 | Z20: 0 | AA20: 0 | AB20: 5.34 | AC20: 9.15 | AD20: 9.32 | AE20: 4.49
A21: Digital Marketplaces Revenue | B21: =SUM(B26,B22) -> 0 | C21: =SUM(C26,C22) -> 0 | D21: =SUM(D26,D22) -> 0 | E21: =SUM(E26,E22) -> 0 | F21: =SUM(F26,F22) -> 0 | G21: =SUM(G26,G22) -> 0 | H21: =SUM(H26,H22) -> 0 | I21: =SUM(I26,I22) -> 0 | ... AE21: =SUM(AE26,AE22) -> 1039
A22: Rachio | B22: =SUM(B23:B25) -> 0 | C22: =SUM(C23:C25) -> 0 | D22: =SUM(D23:D25) -> 0 | E22: =SUM(E23:E25) -> 0 | F22: =SUM(F23:F25) -> 0 | G22: =SUM(G23:G25) -> 0 | H22: =SUM(H23:H25) -> 0 | I22: =SUM(I23:I25) -> 0 | ... AB22: =SUM(AB23:AB25) -> 0 | AC22: 8188.24 | AD22: 5806.09 | AE22: 1039
A23: - Hardware
A24: - Tax
A25: - Shipping | B25: 0 | C25: 0 | D25: 0 | E25: 0 | F25: 0 | G25: 0 | H25: 0 | I25: 0 | J25: 0 | K25: 0 | L25: 0 | M25: 0 | N25: 0 | O25: 0 | P25: 0 | Q25: 0 | R25: 0 | S25: 0 | T25: 0 | U25: 0 | V25: 0 | W25: 0 | X25: 0 | Y25: 0 | Z25: 0 | AA25: 0 | AB25: 0 | AC25: 0 | AD25: 0 | AE25: 0
A26: Weatherflow | B26: =SUM(B27:B29) -> 0 | C26: =SUM(C27:C29) -> 0 | D26: =SUM(D27:D29) -> 0 | E26: =SUM(E27:E29) -> 0 | F26: =SUM(F27:F29) -> 0 | G26: =SUM(G27:G29) -> 0 | H26: =SUM(H27:H29) -> 0 | I26: =SUM(I27:I29) -> 0 | ... AE26: =SUM(AE27:AE29) -> 0
A27: - Hardware | B27: 0 | C27: 0 | D27: 0 | E27: 0 | F27: 0 | G27: 0 | H27: 0 | I27: 0 | J27: 0 | K27: 0 | L27: 0 | M27: 0 | N27: 0 | O27: 0 | P27: 0 | Q27: 0 | R27: 0 | S27: 0 | T27: 0 | U27: 0 | V27: 0 | W27: 0 | X27: 0 | Y27: 0 | Z27: 0 | AA27: 0 | AB27: 0 | AC27: 0 | AD27: 0 | AE27: 0
A28: - Tax
A29: - Shipping
A30: IndieGoGo | B30: 0 | C30: 0 | D30: 0 | E30: 0 | F30: 0 | G30: 1402 | H30: 1770 | I30: 4010 | J30: 4732 | K30: 3202 | L30: 5231 | M30: 5261 | N30: 2388 | O30: 2038 | P30: 2542 | Q30: 5190 | R30: 1034 | S30: 1367 | T30: 2658 | U30: 1459 | V30: 418 | W30: 0 | X30: 298 | Y30: 298 | Z30: 0 | AA30: 298 | AB30: 992 | AC30: 0 | AD30: 324 | AE30: 1034
A31: - Hardware | B31: 0 | C31: 0 | D31: 0 | E31: 0 | F31: 0 | G31: 770 | H31: 1267 | I31: 3815 | J31: 3721 | K31: 2718 | L31: 4687 | M31: 4529 | N31: 2268 | O31: 1933 | P31: 2039 | Q31: 4965 | R31: 974 | S31: 1317 | T31: 1856 | U31: 1389 | V31: 403 | W31: 0 | X31: 283 | Y31: 283 | Z31: 0 | AA31: 283 | AB31: 967 | AC31: 0 | AD31: 309 | AE31: 974
A32: - Add-ons | B32: 0 | C32: 0 | D32: 0 | E32: 0 | F32: 0 | G32: 567 | H32: 408 | I32: 0 | J32: 786 | K32: 299 | L32: 299 | M32: 487 | N32: 0 | O32: 0 | P32: 378 | Q32: 0 | R32: 0 | S32: 0 | T32: 677 | U32: 0 | V32: 0 | W32: 0 | X32: 0 | Y32: 0 | Z32: 0 | AA32: 0 | AB32: 0 | AC32: 0 | AD32: 0 | AE32: 0
A33: - Taxes | B33: 0 | C33: 0 | D33: 0 | E33: 0 | F33: 0 | G33: 0 | H33: 0 | I33: 0 | J33: 0 | K33: 0 | L33: 0 | M33: 0 | N33: 0 | O33: 0 | P33: 0 | Q33: 0 | R33: 0 | S33: 0 | T33: 0 | U33: 0 | V33: 0 | W33: 0 | X33: 0 | Y33: 0 | Z33: 0 | AA33: 0 | AB33: 0 | AC33: 0 | AD33: 0 | AE33: 0
A34: - Shipping | B34: 0 | C34: 0 | D34: 0 | E34: 0 | F34: 0 | G34: 65 | H34: 95 | I34: 195 | J34: 225 | K34: 185 | L34: 245 | M34: 245 | N34: 120 | O34: 105 | P34: 125 | Q34: 225 | R34: 60 | S34: 50 | T34: 125 | U34: 70 | V34: 15 | W34: 0 | X34: 15 | Y34: 15 | Z34: 0 | AA34: 15 | AB34: 25 | AC34: 0 | AD34: 15 | AE34: 60
A35: Total Revenue | B35: =SUM(B8+B15+B21+B30) -> 20095.09 | C35: =SUM(C8+C15+C21+C30) -> 27585.54 | D35: =SUM(D8+D15+D21+D30) -> 34685.8 | E35: =SUM(E8+E15+E21+E30) -> 42621.36 | F35: =SUM(F8+F15+F21+F30) -> 39865.53 | G35: =SUM(G8+G15+G21+G30) -> 32984.87 | H35: =SUM(H8+H15+H21+H30) -> 24629.58 | I35: =SUM(I8+I15+I21+I30) -> 21259.75 | ... AE35: =SUM(AE8+AE15+AE21+AE30) -> 34508.03
A37: App Revenue
A38: - Google Store | B38: ='App - P&L'!B90 -> 0 | C38: ='App - P&L'!C90 -> 0 | D38: ='App - P&L'!D90 -> 0 | E38: ='App - P&L'!E90 -> 0 | F38: ='App - P&L'!F90 -> 0 | G38: ='App - P&L'!G90 -> 2.3605 | H38: ='App - P&L'!H90 -> 2.352 | I38: ='App - P&L'!I90 -> 0 | ... AE38: ='App - P&L'!AE90 -> 2312.095
A39: - Apple Store | B39: ='App - P&L'!B91 -> 0 | C39: ='App - P&L'!C91 -> 0 | D39: ='App - P&L'!D91 -> 0 | E39: ='App - P&L'!E91 -> 0 | F39: ='App - P&L'!F91 -> 0 | G39: ='App - P&L'!G91 -> 0 | H39: ='App - P&L'!H91 -> 0 | I39: ='App - P&L'!I91 -> 0 | ... AE39: ='App - P&L'!AE91 -> 3232.2861
A40: - Comission | B40: ='App - P&L'!B67 -> 0 | C40: ='App - P&L'!C67 -> 0 | D40: ='App - P&L'!D67 -> 0 | E40: ='App - P&L'!E67 -> 0 | F40: ='App - P&L'!F67 -> 0 | G40: ='App - P&L'!G67 -> 0.5295 | H40: ='App - P&L'!H67 -> 0.528 | I40: ='App - P&L'!I67 -> 0 | ... AE40: ='App - P&L'!AE67 -> 1871.4476
A41: - Tax | B41: ='App - P&L'!B68 -> 0 | C41: ='App - P&L'!C68 -> 0 | D41: ='App - P&L'!D68 -> 0 | E41: ='App - P&L'!E68 -> 0 | F41: ='App - P&L'!F68 -> 0 | G41: ='App - P&L'!G68 -> 0.64 | H41: ='App - P&L'!H68 -> 0.64 | I41: ='App - P&L'!I68 -> 0 | ... AE41: ='App - P&L'!AE68 -> 253.18
A42: Total Revenue | B42: =sum(B38:B41) -> 0 | C42: =sum(C38:C41) -> 0 | D42: =sum(D38:D41) -> 0 | E42: =sum(E38:E41) -> 0 | F42: =sum(F38:F41) -> 0 | G42: =sum(G38:G41) -> 3.53 | H42: =sum(H38:H41) -> 3.52 | I42: =sum(I38:I41) -> 0 | ... AE42: =sum(AE38:AE41) -> 7669.0088
A44: DTC Orders | B44: 80 | C44: 113 | D44: 139 | E44: 168 | F44: 153 | G44: 125 | H44: 81 | I44: 53 | J44: 64 | K44: 93 | L44: 86 | M44: 69 | N44: 66 | O44: 79 | P44: 93 | Q44: 86 | R44: 83 | S44: 594 | T44: 310 | U44: 175 | V44: 139 | W44: 122 | X44: 125 | Y44: 135 | Z44: 123 | AA44: 100 | AB44: 120 | AC44: 109 | AD44: 103 | AE44: 103
A45: - Hardware (units sold) | B45: 65 | C45: 98 | D45: 117 | E45: 151 | F45: 140 | G45: 107 | H45: 70 | I45: 49 | J45: 59 | K45: 76 | L45: 68 | M45: 61 | N45: 63 | O45: 76 | P45: 76 | Q45: 69 | R45: 75 | S45: 86 | T45: 74 | U45: 65 | V45: 62 | W45: 59 | X45: 58 | Y45: 70 | Z45: 72 | AA45: 51 | AB45: 94 | AC45: 69 | AD45: 73 | AE45: 78
A46: - Add-ons (units sold) | B46: 45 | C46: 90 | D46: 124 | E46: 107 | F46: 97 | G46: 82 | H46: 64 | I46: 37 | J46: 42 | K46: 74 | L46: 74 | M46: 49 | N46: 45 | O46: 67 | P46: 57 | Q46: 71 | R46: 54 | S46: 730 | T46: 388 | U46: 189 | V46: 157 | W46: 130 | X46: 137 | Y46: 155 | Z46: 126 | AA46: 100 | AB46: 117 | AC46: 120 | AD46: 99 | AE46: 92
A47: Amazon Orders | B47: 14 | C47: 8 | D47: 20 | E47: 24 | F47: 16 | G47: 21 | H47: 12 | I47: 11 | J47: 29 | K47: 18 | L47: 22 | M47: 28 | N47: 26 | O47: 28 | P47: 15 | Q47: 21 | R47: 25 | S47: 27 | T47: 40 | U47: 36 | V47: 35 | W47: 31 | X47: 25 | Y47: 34 | Z47: 32 | AA47: 38 | AB47: 32 | AC47: 41 | AD47: 33 | AE47: 30
A48: - Hardware (units sold) | B48: 14 | C48: 8 | D48: 20 | E48: 24 | F48: 16 | G48: 21 | H48: 12 | I48: 11 | J48: 29 | K48: 19 | L48: 22 | M48: 28 | N48: 26 | O48: 28 | P48: 15 | Q48: 23 | R48: 26 | S48: 27 | T48: 40 | U48: 36 | V48: 36 | W48: 33 | X48: 26 | Y48: 34 | Z48: 32 | AA48: 38 | AB48: 33 | AC48: 41 | AD48: 33 | AE48: 30
A49: - Add-ons (units sold) | B49: 0 | C49: 0 | D49: 0 | E49: 0 | F49: 0 | G49: 0 | H49: 0 | I49: 0 | J49: 0 | K49: 0 | L49: 0 | M49: 0 | N49: 0 | O49: 0 | P49: 0 | Q49: 0 | R49: 0 | S49: 0 | T49: 0 | U49: 0 | V49: 0 | W49: 0 | X49: 0 | Y49: 0 | Z49: 0 | AA49: 0 | AB49: 0 | AC49: 0 | AD49: 0 | AE49: 0
A50: Digital Marketplaces Orders | B50: =SUM(B51:B52) -> 0 | C50: =SUM(C51:C52) -> 0 | D50: =SUM(D51:D52) -> 0 | E50: =SUM(E51:E52) -> 0 | F50: =SUM(F51:F52) -> 0 | G50: =SUM(G51:G52) -> 0 | H50: =SUM(H51:H52) -> 0 | I50: =SUM(I51:I52) -> 0 | ... AE50: =SUM(AE51:AE52) -> 5
A51: Rachio Orders | AC51: 38 | AD51: 26 | AE51: 5
A52: Weatherflow Orders
A53: IndieGoGo Orders | B53: 0 | C53: 0 | D53: 0 | E53: 0 | F53: 0 | G53: 4 | H53: 6 | I53: 11 | J53: 13 | K53: 12 | L53: 14 | M53: 14 | N53: 8 | O53: 7 | P53: 8 | Q53: 13 | R53: 4 | S53: 2 | T53: 7 | U53: 4 | V53: 1 | W53: 0 | X53: 1 | Y53: 1 | Z53: 0 | AA53: 1 | AB53: 1 | AC53: 0 | AD53: 1 | AE53: 4
A54: - Hardware (units sold) | B54: 0 | C54: 0 | D54: 0 | E54: 0 | F54: 0 | G54: 3 | H54: 5 | I54: 11 | J54: 11 | K54: 11 | L54: 13 | M54: 13 | N54: 8 | O54: 7 | P54: 7 | Q54: 13 | R54: 4 | S54: 2 | T54: 5 | U54: 4 | V54: 1 | W54: 0 | X54: 1 | Y54: 1 | Z54: 0 | AA54: 1 | AB54: 1 | AC54: 0 | AD54: 1 | AE54: 4
A55: - Add-ons (units sold) | B55: 0 | C55: 0 | D55: 0 | E55: 0 | F55: 0 | G55: 4 | H55: 5 | I55: 7 | J55: 12 | K55: 7 | L55: 14 | M55: 14 | N55: 5 | O55: 4 | P55: 6 | Q55: 14 | R55: 2 | S55: 3 | T55: 9 | U55: 3 | V55: 0 | W55: 0 | X55: 1 | Y55: 1 | Z55: 0 | AA55: 1 | AB55: 2 | AC55: 0 | AD55: 1 | AE55: 2
A56: Total Orders | B56: =SUM(B44+B47+B51+B52+B53) -> 94 | C56: =SUM(C44+C47+C51+C52+C53) -> 121 | D56: =SUM(D44+D47+D51+D52+D53) -> 159 | E56: =SUM(E44+E47+E51+E52+E53) -> 192 | F56: =SUM(F44+F47+F51+F52+F53) -> 169 | G56: =SUM(G44+G47+G51+G52+G53) -> 150 | H56: =SUM(H44+H47+H51+H52+H53) -> 99 | I56: =SUM(I44+I47+I51+I52+I53) -> 75 | ... AE56: =SUM(AE44+AE47+AE51+AE52+AE53) -> 142
A58: App Orders
A59: - Google Store | B59: ='App - P&L'!B17 -> 0 | C59: ='App - P&L'!C17 -> 0 | D59: ='App - P&L'!D17 -> 0 | E59: ='App - P&L'!E17 -> 0 | F59: ='App - P&L'!F17 -> 0 | G59: ='App - P&L'!G17 -> 1 | H59: ='App - P&L'!H17 -> 1 | I59: ='App - P&L'!I17 -> 0 | ... AE59: ='App - P&L'!AE17 -> 182
A60: - Apple Store | B60: ='App - P&L'!B14 -> 0 | C60: ='App - P&L'!C14 -> 0 | D60: ='App - P&L'!D14 -> 0 | E60: ='App - P&L'!E14 -> 0 | F60: ='App - P&L'!F14 -> 0 | G60: ='App - P&L'!G14 -> 0 | H60: ='App - P&L'!H14 -> 0 | I60: ='App - P&L'!I14 -> 0 | ... AE60: ='App - P&L'!AE14 -> 319
A61: Total Orders | B61: =sum(B59:B60) -> 0 | C61: =sum(C59:C60) -> 0 | D61: =sum(D59:D60) -> 0 | E61: =sum(E59:E60) -> 0 | F61: =sum(F59:F60) -> 0 | G61: =sum(G59:G60) -> 1 | H61: =sum(H59:H60) -> 1 | I61: =sum(I59:I60) -> 0 | ... AE61: =sum(AE59:AE60) -> 501
A62: Meta Spend EUR | B62: =4579.54-B64 -> 4579.54 | C62: =4206.6-C64 -> 4206.6 | D62: =5841.39 -> 5841.39 | E62: =6637.02 -> 6637.02 | F62: =8917.07 -> 8917.07 | G62: =9622.4-G64 -> 9305.35 | H62: =4366.84-H64 -> 3878.58 | I62: =2512.86-I64 -> 1849.15 | J62: =4162.07-J64 -> 3328.79 | K62: =7434.2-K64 -> 6175.55 | L62: =7472.41-L64 -> 5965.32 | M62: =6734.36-M64 -> 4870.06 | N62: =5246.37-N64 -> 2985.67 | O62: =4382.77-O64 -> 2319.94 | P62: =4769.72-P64 -> 3108.49 | Q62: =4973.47-Q64 -> 3542.98 | R62: =5217.97-R64 -> 3731.08 | S62: =4950.45-S64 -> 3485.96 | T62: =5284.71-T64 -> 4389.74 | U62: =4358.12-U64 -> 4272.82 | V62: =4499.65 -> 4499.65 | W62: =4723.28 -> 4723.28 | X62: =6086.67 -> 6086.67 | Y62: =7837.51 -> 7837.51 | Z62: =6945.36 -> 6945.36 | AA62: =6434.22 -> 6434.22 | AB62: =4494.81 -> 4494.81 | AC62: =3484.5 -> 3484.5 | AD62: =4594.62 -> 4594.62 | AE62: =5445.74-AE64 -> 5017.49
A63: Currency rate | B63: 1.0788 | C63: 1.0788 | D63: 1.0773 | E63: 1.0795 | F63: 1.0726 | G63: 1.0727 | H63: 1.07 | I63: 1.0707 | J63: 1.0707 | K63: 1.0711 | L63: 1.075 | M63: 1.0756 | N63: 1.0733 | O63: 1.0643 | P63: 1.067 | Q63: 1.067 | R63: 1.0664 | S63: 1.0692 | T63: 1.0683 | U63: 1.0655 | V63: 1.0663 | X63: 1.0664 | Y63: 1.065 | Z63: 1.0594 | AA63: 1.0571 | AB63: 1.0505 | AC63: 1.0567 | AD63: 1.0587 | AE63: 1.058
A64: IndieGoGo Spend EUR | B64: 0 | C64: 0 | D64: 0 | E64: 0 | F64: 0 | G64: 317.05 | H64: 488.26 | I64: 663.71 | J64: 833.28 | K64: 1258.65 | L64: 1507.09 | M64: 1864.3 | N64: 2260.7 | O64: 2062.83 | P64: 1661.23 | Q64: 1430.49 | R64: 1486.89 | S64: 1464.49 | T64: 894.97 | U64: 85.3 | V64: 0 | W64: 0 | X64: 0 | Y64: 0 | Z64: 0 | AA64: 0 | AB64: 0 | AC64: 0 | AD64: 0 | AE64: 428.25
A65: Meta Spend | B65: =B62*B63 -> 4940.4078 | C65: =C62*C63 -> 4538.0801 | D65: =D62*D63 -> 6292.9294 | E65: =E62*E63 -> 7164.6631 | F65: =F62*F63 -> 9564.4493 | G65: =G62*G63 -> 9981.8489 | H65: =H62*H63 -> 4150.0806 | I65: =I62*I63 -> 1979.8849 | ... AE65: =AE62*AE63 -> 5308.5044
A66: Google Spend | B66: 1210.79 | C66: 1399.9 | D66: 1709.65 | E66: 1315.99 | F66: 1354.7 | G66: 1334.04 | H66: 1388.13 | I66: 1350.77 | J66: 1438.08 | K66: 1962.58 | L66: 1887.85 | M66: 1863.85 | N66: 2181.78 | O66: 1644.15 | P66: 2151.14 | Q66: 2408.3 | R66: 2607.01 | S66: 2871.65 | T66: 2751.55 | U66: 2287.74 | V66: 2055.93 | W66: 1949 | X66: 2011.34 | Y66: 2162.32 | Z66: 1938.83 | AA66: 1647.2 | AB66: 1733.42 | AC66: 2080.01 | AD66: 1795.19 | AE66: 2141.16
A67: Bing Spend | B67: 183.94 | C67: 172.98 | D67: 228.88 | E67: 223.48 | F67: 230.68 | G67: 227.63 | H67: 224.23 | I67: 191.43 | J67: 355.52 | K67: 218.82 | L67: 224.19 | M67: 217.46 | N67: 212.7 | O67: 216.39 | P67: 191.06 | Q67: 221.71 | R67: 486.58 | S67: 238.96 | T67: 212.46 | U67: 207.49 | V67: 199.05 | W67: 212.03 | X67: 212.05 | Y67: 197.44 | Z67: 62.73 | AA67: 20.31 | AB67: 0 | AC67: 4.23 | AD67: 161.76 | AE67: 464.33
A68: TikTok Spend | B68: 0 | C68: 0 | D68: 0 | E68: 0 | F68: 0 | G68: 0 | H68: 0 | I68: 0 | J68: 0 | K68: 0 | L68: 0 | M68: 0 | N68: 30 | O68: 30 | P68: 30 | Q68: 30 | R68: 30 | S68: 16.29 | T68: 0 | U68: 0 | V68: 0 | W68: 0 | X68: 0 | Y68: 0 | Z68: 20 | AA68: 20 | AB68: 11.23 | AC68: 0 | AD68: 0 | AE68: 0
A69: Amazon Spend | B69: 1276.67 | C69: 1876.55 | D69: 2182.61 | E69: 1886.24 | F69: 1401.31 | G69: 1491.07 | H69: 1448.93 | I69: 1479.75 | J69: 1888.27 | K69: 2296.89 | L69: 1797.51 | M69: 1678.5 | N69: 1662.46 | O69: 1696.47 | P69: 1674.55 | Q69: 2303.3 | R69: 2443.56 | S69: 2161.34 | T69: 2309.42 | U69: 2091.87 | V69: 1920.72 | W69: 1492.52 | X69: 1881.18 | Y69: 2255.79 | Z69: 1672.88 | AA69: 1771.38 | AB69: 2743.88 | AC69: 3792.92 | AD69: 2832.22 | AE69: 3932.81
A70: Nextdoor Spend | B70: 0 | C70: 0 | D70: 0 | E70: 0 | F70: 0 | G70: 0 | H70: 0 | I70: 0 | J70: 0 | K70: 0 | L70: 190.92 | M70: 184.37 | N70: 347.34 | O70: 400.58 | P70: 527.61 | Q70: 503.39 | R70: 504.5 | S70: 501.28 | T70: 501.22 | U70: 335.16 | V70: 468.16 | W70: 377.74 | X70: 403.1 | Y70: 403 | Z70: 403.6 | AA70: 402.86 | AB70: 402.38 | AC70: 388.24 | AD70: 0.02 | AE70: 0
A71: IndieGoGo Spend | B71: =IFERROR(__xludf.DUMMYFUNCTION("GOOGLEFINANCE(""CURRENCY:EURUSD"")*B64"),0.0) -> 0 | C71: =IFERROR(__xludf.DUMMYFUNCTION("GOOGLEFINANCE(""CURRENCY:EURUSD"")*C64"),0.0) -> 0 | D71: =IFERROR(__xludf.DUMMYFUNCTION("GOOGLEFINANCE(""CURRENCY:EURUSD"")*D64"),0.0) -> 0 | E71: =IFERROR(__xludf.DUMMYFUNCTION("GOOGLEFINANCE(""CURRENCY:EURUSD"")*E64"),0.0) -> 0 | F71: =IFERROR(__xludf.DUMMYFUNCTION("GOOGLEFINANCE(""CURRENCY:EURUSD"")*F64"),0.0) -> 0 | G71: =IFERROR(__xludf.DUMMYFUNCTION("GOOGLEFINANCE(""CURRENCY:EURUSD"")*G64"),363.51209224999997) -> 363.51209 | H71: =IFERROR(__xludf.DUMMYFUNCTION("GOOGLEFINANCE(""CURRENCY:EURUSD"")*H64"),559.8120617) -> 559.81206 | I71: =IFERROR(__xludf.DUMMYFUNCTION("GOOGLEFINANCE(""CURRENCY:EURUSD"")*I64"),760.97338195) -> 760.97338 | J71: =IFERROR(__xludf.DUMMYFUNCTION("GOOGLEFINANCE(""CURRENCY:EURUSD"")*J64"),955.3930175999999) -> 955.39302 | K71: =IFERROR(__xludf.DUMMYFUNCTION("GOOGLEFINANCE(""CURRENCY:EURUSD"")*K64"),1443.09886425) -> 1443.0989 | L71: =IFERROR(__xludf.DUMMYFUNCTION("GOOGLEFINANCE(""CURRENCY:EURUSD"")*L64"),1727.9465040499997) -> 1727.9465 | M71: =IFERROR(__xludf.DUMMYFUNCTION("GOOGLEFINANCE(""CURRENCY:EURUSD"")*M64"),2137.5038434999997) -> 2137.5038 | N71: =IFERROR(__xludf.DUMMYFUNCTION("GOOGLEFINANCE(""CURRENCY:EURUSD"")*N64"),2591.9942814999995) -> 2591.9943 | O71: =IFERROR(__xludf.DUMMYFUNCTION("GOOGLEFINANCE(""CURRENCY:EURUSD"")*O64"),2365.12742235) -> 2365.1274 | P71: =IFERROR(__xludf.DUMMYFUNCTION("GOOGLEFINANCE(""CURRENCY:EURUSD"")*P64"),1904.6749503499998) -> 1904.675 | Q71: =IFERROR(__xludf.DUMMYFUNCTION("GOOGLEFINANCE(""CURRENCY:EURUSD"")*Q64"),1640.12115705) -> 1640.1212 | R71: =IFERROR(__xludf.DUMMYFUNCTION("GOOGLEFINANCE(""CURRENCY:EURUSD"")*R64"),1704.78629505) -> 1704.7863 | S71: =IFERROR(__xludf.DUMMYFUNCTION("GOOGLEFINANCE(""CURRENCY:EURUSD"")*S64"),1679.10368705) -> 1679.1037 | T71: =IFERROR(__xludf.DUMMYFUNCTION("GOOGLEFINANCE(""CURRENCY:EURUSD"")*T64"),1026.12337865) -> 1026.1234 | U71: =IFERROR(__xludf.DUMMYFUNCTION("GOOGLEFINANCE(""CURRENCY:EURUSD"")*U64"),97.8002885) -> 97.800288 | V71: =IFERROR(__xludf.DUMMYFUNCTION("GOOGLEFINANCE(""CURRENCY:EURUSD"")*V64"),0.0) -> 0 | W71: =IFERROR(__xludf.DUMMYFUNCTION("GOOGLEFINANCE(""CURRENCY:EURUSD"")*W64"),0.0) -> 0 | X71: =IFERROR(__xludf.DUMMYFUNCTION("GOOGLEFINANCE(""CURRENCY:EURUSD"")*X64"),0.0) -> 0 | Y71: =IFERROR(__xludf.DUMMYFUNCTION("GOOGLEFINANCE(""CURRENCY:EURUSD"")*Y64"),0.0) -> 0 | Z71: =IFERROR(__xludf.DUMMYFUNCTION("GOOGLEFINANCE(""CURRENCY:EURUSD"")*Z64"),0.0) -> 0 | AA71: =IFERROR(__xludf.DUMMYFUNCTION("GOOGLEFINANCE(""CURRENCY:EURUSD"")*AA64"),0.0) -> 0 | AB71: =IFERROR(__xludf.DUMMYFUNCTION("GOOGLEFINANCE(""CURRENCY:EURUSD"")*AB64"),0.0) -> 0 | AC71: =IFERROR(__xludf.DUMMYFUNCTION("GOOGLEFINANCE(""CURRENCY:EURUSD"")*AC64"),0.0) -> 0 | AD71: =IFERROR(__xludf.DUMMYFUNCTION("GOOGLEFINANCE(""CURRENCY:EURUSD"")*AD64"),0.0) -> 0 | AE71: =IFERROR(__xludf.DUMMYFUNCTION("GOOGLEFINANCE(""CURRENCY:EURUSD"")*AE64"),491.00789625) -> 491.0079
A72: Affiliate Fees | B72: 0 | C72: 0 | D72: 0 | E72: 47.81 | F72: 113.06 | G72: 62.55 | H72: 0 | I72: 0 | J72: 0 | K72: 149.78 | L72: 0 | M72: 0 | N72: 0 | O72: 139.61 | P72: 53.32 | Q72: 59.92 | R72: 53.62 | S72: 15.48 | T72: 59.05 | U72: 57.04 | V72: 0 | W72: 57.16 | X72: 0 | Y72: 26.91 | Z72: 0 | AA72: 0 | AB72: 0 | AC72: 0 | AD72: 0 | AE72: 0
A73: Rachio Fees | B73: =B22*0.2 -> 0 | C73: =C22*0.2 -> 0 | D73: =D22*0.2 -> 0 | E73: =E22*0.2 -> 0 | F73: =F22*0.2 -> 0 | G73: =G22*0.2 -> 0 | H73: =H22*0.2 -> 0 | I73: =I22*0.2 -> 0 | ... AE73: =AE22*0.2 -> 207.8
A74: Weatherflow Fees | B74: =B26*0.15 -> 0 | C74: =C26*0.15 -> 0 | D74: =D26*0.15 -> 0 | E74: =E26*0.15 -> 0 | F74: =F26*0.15 -> 0 | G74: =G26*0.15 -> 0 | H74: =H26*0.15 -> 0 | I74: =I26*0.15 -> 0 | ... AE74: =AE26*0.15 -> 0
A75: Total DTC Spend | B75: =B65+B66+B67+B68+B70+B72 -> 6335.1378 | C75: =C65+C66+C67+C68+C70+C72 -> 6110.9601 | D75: =D65+D66+D67+D68+D70+D72 -> 8231.4594 | E75: =E65+E66+E67+E68+E70+E72 -> 8751.9431 | F75: =F65+F66+F67+F68+F70+F72 -> 11262.889 | G75: =G65+G66+G67+G68+G70+G72 -> 11606.069 | H75: =H65+H66+H67+H68+H70+H72 -> 5762.4406 | I75: =I65+I66+I67+I68+I70+I72 -> 3522.0849 | ... AE75: =AE65+AE66+AE67+AE68+AE70+AE72 -> 7913.9944
A76: Total Spend | B76: =SUM(B65:B74) -> 7611.8078 | C76: =SUM(C65:C74) -> 7987.5101 | D76: =SUM(D65:D74) -> 10414.069 | E76: =SUM(E65:E74) -> 10638.183 | F76: =SUM(F65:F74) -> 12664.199 | G76: =SUM(G65:G74) -> 13460.651 | H76: =SUM(H65:H74) -> 7771.1827 | I76: =SUM(I65:I74) -> 5762.8083 | ... AE76: =SUM(AE65:AE74) -> 12545.612
A78: App Spend | B78: 0.66 | C78: 0.36 | D78: 0 | E78: 0.39 | F78: 0.9 | G78: 0.53 | U78: 6.12 | V78: 22.03 | W78: 27.26 | X78: 27.95 | Y78: 28.67 | Z78: 28.71 | AA78: 47.41 | AB78: 47.47 | AC78: 47.8 | AD78: 47.8 | AE78: 47.79
A79: Meta Spend | B79: =IFERROR(__xludf.DUMMYFUNCTION("GOOGLEFINANCE(""CURRENCY:EURUSD"")*B78"),0.7567197) -> 0.7567197 | C79: =IFERROR(__xludf.DUMMYFUNCTION("GOOGLEFINANCE(""CURRENCY:EURUSD"")*C78"),0.41275619999999996) -> 0.4127562 | D79: =IFERROR(__xludf.DUMMYFUNCTION("GOOGLEFINANCE(""CURRENCY:EURUSD"")*D78"),0.0) -> 0 | E79: =IFERROR(__xludf.DUMMYFUNCTION("GOOGLEFINANCE(""CURRENCY:EURUSD"")*E78"),0.44715255) -> 0.44715255 | F79: =IFERROR(__xludf.DUMMYFUNCTION("GOOGLEFINANCE(""CURRENCY:EURUSD"")*F78"),1.0318905) -> 1.0318905 | G79: =IFERROR(__xludf.DUMMYFUNCTION("GOOGLEFINANCE(""CURRENCY:EURUSD"")*G78"),0.60766885) -> 0.60766885 | H79: =IFERROR(__xludf.DUMMYFUNCTION("GOOGLEFINANCE(""CURRENCY:EURUSD"")*H78"),0.0) -> 0 | I79: =IFERROR(__xludf.DUMMYFUNCTION("GOOGLEFINANCE(""CURRENCY:EURUSD"")*I78"),0.0) -> 0 | J79: =IFERROR(__xludf.DUMMYFUNCTION("GOOGLEFINANCE(""CURRENCY:EURUSD"")*J78"),0.0) -> 0 | K79: =IFERROR(__xludf.DUMMYFUNCTION("GOOGLEFINANCE(""CURRENCY:EURUSD"")*K78"),0.0) -> 0 | L79: =IFERROR(__xludf.DUMMYFUNCTION("GOOGLEFINANCE(""CURRENCY:EURUSD"")*L78"),0.0) -> 0 | M79: =IFERROR(__xludf.DUMMYFUNCTION("GOOGLEFINANCE(""CURRENCY:EURUSD"")*M78"),0.0) -> 0 | N79: =IFERROR(__xludf.DUMMYFUNCTION("GOOGLEFINANCE(""CURRENCY:EURUSD"")*N78"),0.0) -> 0 | O79: =IFERROR(__xludf.DUMMYFUNCTION("GOOGLEFINANCE(""CURRENCY:EURUSD"")*O78"),0.0) -> 0 | P79: =IFERROR(__xludf.DUMMYFUNCTION("GOOGLEFINANCE(""CURRENCY:EURUSD"")*P78"),0.0) -> 0 | Q79: =IFERROR(__xludf.DUMMYFUNCTION("GOOGLEFINANCE(""CURRENCY:EURUSD"")*Q78"),0.0) -> 0 | R79: =IFERROR(__xludf.DUMMYFUNCTION("GOOGLEFINANCE(""CURRENCY:EURUSD"")*R78"),0.0) -> 0 | S79: =IFERROR(__xludf.DUMMYFUNCTION("GOOGLEFINANCE(""CURRENCY:EURUSD"")*S78"),0.0) -> 0 | T79: =IFERROR(__xludf.DUMMYFUNCTION("GOOGLEFINANCE(""CURRENCY:EURUSD"")*T78"),0.0) -> 0 | U79: =IFERROR(__xludf.DUMMYFUNCTION("GOOGLEFINANCE(""CURRENCY:EURUSD"")*U78"),7.0168554) -> 7.0168554 | V79: =IFERROR(__xludf.DUMMYFUNCTION("GOOGLEFINANCE(""CURRENCY:EURUSD"")*V78"),25.25838635) -> 25.258386 | W79: =IFERROR(__xludf.DUMMYFUNCTION("GOOGLEFINANCE(""CURRENCY:EURUSD"")*W78"),31.2548167) -> 31.254817 | X79: =IFERROR(__xludf.DUMMYFUNCTION("GOOGLEFINANCE(""CURRENCY:EURUSD"")*X78"),32.04593275) -> 32.045933 | Y79: =IFERROR(__xludf.DUMMYFUNCTION("GOOGLEFINANCE(""CURRENCY:EURUSD"")*Y78"),32.87144515) -> 32.871445 | Z79: =IFERROR(__xludf.DUMMYFUNCTION("GOOGLEFINANCE(""CURRENCY:EURUSD"")*Z78"),32.91730695) -> 32.917307 | AA79: =IFERROR(__xludf.DUMMYFUNCTION("GOOGLEFINANCE(""CURRENCY:EURUSD"")*AA78"),54.357698449999994) -> 54.357698 | AB79: =IFERROR(__xludf.DUMMYFUNCTION("GOOGLEFINANCE(""CURRENCY:EURUSD"")*AB78"),54.42649115) -> 54.426491 | AC79: =IFERROR(__xludf.DUMMYFUNCTION("GOOGLEFINANCE(""CURRENCY:EURUSD"")*AC78"),54.80485099999999) -> 54.804851 | AD79: =IFERROR(__xludf.DUMMYFUNCTION("GOOGLEFINANCE(""CURRENCY:EURUSD"")*AD78"),54.80485099999999) -> 54.804851 | AE79: =IFERROR(__xludf.DUMMYFUNCTION("GOOGLEFINANCE(""CURRENCY:EURUSD"")*AE78"),54.793385549999996) -> 54.793386
A80: Apple Spend | B80: 0 | C80: 0 | D80: 0 | E80: 0 | F80: 0 | G80: 0 | H80: 0 | I80: 0 | J80: 0 | K80: 0 | L80: 0 | M80: 0 | N80: 0 | O80: 5.72 | P80: 7.5 | Q80: 5.65 | R80: 7.21 | S80: 5.84 | T80: 0 | U80: 0 | V80: 0 | W80: 0 | X80: 0 | Y80: 0 | Z80: 40.34 | AA80: 38.09 | AB80: 51.01 | AC80: 46.29 | AD80: 43.94 | AE80: 35.18
A81: Google Spend | B81: 0 | C81: 0 | D81: 0 | E81: 0 | F81: 0 | G81: 0 | H81: 0 | I81: 0 | J81: 0 | K81: 0 | L81: 0 | M81: 0 | N81: 0 | O81: 0 | P81: 0 | Q81: 0 | R81: 0 | S81: 0 | T81: 0 | U81: 0 | V81: 0 | W81: 0 | X81: 0 | Y81: 0 | Z81: 0 | AA81: 0 | AB81: 0 | AC81: 0 | AD81: 0 | AE81: 0
A82: Total APP Spend | B82: =SUM(B79:B80) -> 0.7567197 | C82: =SUM(C79:C80) -> 0.4127562 | D82: =SUM(D79:D80) -> 0 | E82: =SUM(E79:E80) -> 0.44715255 | F82: =SUM(F79:F80) -> 1.0318905 | G82: =SUM(G79:G80) -> 0.60766885 | H82: =SUM(H79:H80) -> 0 | I82: =SUM(I79:I80) -> 0 | ... AE82: =SUM(AE79:AE80) -> 89.973386
A84: Blended ROAS | B84: =B35/B76 -> 2.6399892 | C84: =C35/C76 -> 3.4535844 | D84: =D35/D76 -> 3.3306672 | E84: =E35/E76 -> 4.0064511 | F84: =F35/F76 -> 3.1478919 | G84: =G35/G76 -> 2.4504662 | H84: =H35/H76 -> 3.1693477 | I84: =I35/I76 -> 3.6891302 | ... AE84: =AE35/AE76 -> 2.7506055
A85: wROAS | B85: =B8/B75 -> 2.6539802 | C85: =C8/C75 -> 4.0230503 | D85: =D8/D75 -> 3.632498 | E85: =E8/E75 -> 4.1515672 | F85: =F8/F75 -> 3.0068421 | G85: =G8/G75 -> 2.2593628 | H85: =H8/H75 -> 3.299057 | I85: =I8/I75 -> 4.04982 | ... AE85: =AE8/AE75 -> 3.1154482
A86: aROAS | B86: =B15/B69 -> 2.5705625 | C86: =C15/C69 -> 1.5991261 | D86: =D15/D69 -> 2.1923477 | E86: =E15/E69 -> 3.3331283 | F86: =F15/F69 -> 4.2815651 | G86: =G15/G69 -> 3.5951028 | H86: =H15/H69 -> 2.6564154 | I86: =I15/I69 -> 2.0178679 | ... AE86: =AE15/AE69 -> 1.9780742
A87: appROAS | B87: =B42/B82 -> 0 | C87: =C42/C82 -> 0 | D87: =D42/D82 -> #DIV/0! | E87: =E42/E82 -> 0 | F87: =F42/F82 -> 0 | G87: =G42/G82 -> 5.809085 | H87: =H42/H82 -> #DIV/0! | I87: =I42/I82 -> #DIV/0! | ... AE87: =AE42/AE82 -> 85.236414
A89: Blended Spend per Unit | B89: =B76/sum('DTC - P&L'!B57,'AMAZON - P&L'!B32,'Digital Marketplaces'!B17) -> 100.15537 | C89: =C76/sum('DTC - P&L'!C57,'AMAZON - P&L'!C32,'Digital Marketplaces'!C17) -> 73.958427 | D89: =D76/sum('DTC - P&L'!D57,'AMAZON - P&L'!D32,'Digital Marketplaces'!D17) -> 77.716936 | E89: =E76/sum('DTC - P&L'!E57,'AMAZON - P&L'!E32,'Digital Marketplaces'!E17) -> 61.492388 | F89: =F76/sum('DTC - P&L'!F57,'AMAZON - P&L'!F32,'Digital Marketplaces'!F17) -> 78.659623 | G89: =G76/sum('DTC - P&L'!G57,'AMAZON - P&L'!G32,'Digital Marketplaces'!G17) -> 107.68521 | H89: =H76/sum('DTC - P&L'!H57,'AMAZON - P&L'!H32,'Digital Marketplaces'!H17) -> 93.628707 | I89: =I76/sum('DTC - P&L'!I57,'AMAZON - P&L'!I32,'Digital Marketplaces'!I17) -> 97.674717 | ... AE89: =AE76/sum('DTC - P&L'!AE57,'AMAZON - P&L'!AE32,'Digital Marketplaces'!AE17) -> 109.09228
A90: wSPU | B90: =B75/'DTC - P&L'!B57 -> 97.463658 | C90: =C75/'DTC - P&L'!C57 -> 62.356736 | D90: =D75/'DTC - P&L'!D57 -> 70.354354 | E90: =E75/'DTC - P&L'!E57 -> 57.959888 | F90: =F75/'DTC - P&L'!F57 -> 80.449209 | G90: =G75/'DTC - P&L'!G57 -> 108.46793 | H90: =H75/'DTC - P&L'!H57 -> 82.32058 | I90: =I75/'DTC - P&L'!I57 -> 71.879284 | ... AE90: =AE75/'DTC - P&L'!AE57 -> 101.46147
A91: aSPU | B91: =B69/'AMAZON - P&L'!B32 -> 116.06091 | C91: =C69/'AMAZON - P&L'!C32 -> 187.655 | D91: =D69/'AMAZON - P&L'!D32 -> 128.38882 | E91: =E69/'AMAZON - P&L'!E32 -> 85.738182 | F91: =F69/'AMAZON - P&L'!F32 -> 66.729048 | G91: =G69/'AMAZON - P&L'!G32 -> 82.837222 | H91: =H69/'AMAZON - P&L'!H32 -> 111.45615 | I91: =I69/'AMAZON - P&L'!I32 -> 147.975 | ... AE91: =AE69/'AMAZON - P&L'!AE32 -> 122.90031
A92: appCAC | B92: =B82/B61 -> #DIV/0! | C92: =C82/C61 -> #DIV/0! | D92: =D82/D61 -> #DIV/0! | E92: =E82/E61 -> #DIV/0! | F92: =F82/F61 -> #DIV/0! | G92: =G82/G61 -> 0.60766885 | H92: =H82/H61 -> 0 | I92: =I82/I61 -> #DIV/0! | ... AE92: =AE82/AE61 -> 0.1795876
A94: Web CR | B94: 0.0114 | C94: 0.0097 | D94: 0.0157 | E94: 0.0198 | F94: 0.0182 | G94: 0.0167 | H94: 0.0153 | I94: 0.0146 | J94: 0.0133 | K94: 0.0132 | L94: 0.0109 | M94: 0.0093 | N94: 0.01 | O94: 0.0132 | P94: 0.0168 | Q94: 0.0146 | R94: 0.0127 | S94: 0.0496 | T94: 0.0211 | U94: 0.0166 | V94: 0.015 | W94: 0.0169 | X94: 0.0177 | Y94: 0.0164 | Z94: 0.0161 | AA94: 0.014 | AB94: 0.0187 | AC94: 0.0166 | AD94: 0.0157 | AE94: 0.0169
A95: Web AOV | B95: =B8/B44 -> 210.16663 | C95: =C8/C44 -> 217.56372 | D95: =D8/D44 -> 215.11338 | E95: =E8/E44 -> 216.27548 | F95: =F8/F44 -> 221.34464 | G95: =G8/G44 -> 209.77856 | H95: =H8/H44 -> 234.69901 | I95: =I8/I44 -> 269.12849 | ... AE95: =AE8/AE44 -> 239.37515
A96: fAOV | B96: 215.53 | C96: 221.15 | D96: 224.7 | E96: 223.56 | F96: 222.26 | G96: 212.86 | H96: 239.25 | I96: 269.13 | J96: 284.02 | K96: 256.73 | L96: 246.8 | M96: 259.84 | N96: 263.24 | O96: 263.01 | P96: 236.28 | Q96: 230.73 | R96: 242.64 | S96: 89.75 | T96: 113.72 | U96: 151.24 | V96: 171.56 | W96: 176.02 | X96: 182.73 | Y96: 187.71 | Z96: 207.99 | AA96: 179.9 | AB96: 224.79 | AC96: 204.07 | AD96: 243.02 | AE96: 244.55
A97: rAOV | B97: 129.7 | C97: 140.04 | D97: 113.62 | E97: 87.51 | F97: 198.86 | G97: 135.89 | H97: 54.97 | I97: 0 | J97: 48.73 | K97: 195.16 | L97: 127.08 | M97: 213.58 | N97: 0 | O97: 71.7 | P97: 147.25 | Q97: 122.02 | R97: 327.3 | S97: 71.86 | T97: 112.97 | U97: 56.92 | V97: 84.77 | W97: 63.23 | X97: 63.73 | Y97: 179.42 | Z97: 112.89 | AA97: 106.76 | AB97: 304.52 | AC97: 173.2 | AD97: 107.01 | AE97: 168.42
A99: Customers
A100: Returning | B100: 0.063 | C100: 0.045 | D100: 0.081 | E100: 0.054 | F100: 0.04 | G100: 0.041 | H100: 0.025 | I100: 0 | J100: 0.031 | K100: 0.054 | L100: 0.048 | M100: 0.088 | N100: 0.015 | O100: 0.013 | P100: 0.108 | Q100: 0.035 | R100: 0.024 | S100: 0.062 | T100: 0.065 | U100: 0.091 | V100: 0.044 | W100: 0.033 | X100: 0.08 | Y100: 0.044 | Z100: 0.108 | AA100: 0.103 | AB100: 0.153 | AC100: 0.067 | AD100: 0.087 | AE100: 0.068
A101: First-time | B101: =1-B100 -> 0.937 | C101: =1-C100 -> 0.955 | D101: =1-D100 -> 0.919 | E101: =1-E100 -> 0.946 | F101: =1-F100 -> 0.96 | G101: =1-G100 -> 0.959 | H101: =1-H100 -> 0.975 | I101: =1-I100 -> 1 | ... AE101: =1-AE100 -> 0.932
B103: 45170 | C103: Goal | D103: % of Goal
A104: Revenue | B104: =SUM(B35:AE35)+SUM(B42:AE42) -> 1073520.8 | C104: 1200000 | D104: =B104/C104 -> 0.89460069
A105: Spend | B105: =SUM(B76:AE76)+SUM(B82:AE82) -> 310269.72 | C105: =C104/C106 -> 300000 | D105: =B105/C105 -> 1.0342324
A106: ROAS | B106: =B104/B105 -> 3.45996 | C106: 4 | D106: =B106/C106 -> 0.86499001
A107: Spend per Unit | B107: =SUM(B76:AE76)/SUM('DTC - P&L'!B57:AE57,'AMAZON - P&L'!B32:AE32,'Digital Marketplaces'!B17:AE17) -> 97.371859
A108: CR | B108: =IFERROR(__xludf.DUMMYFUNCTION("AVERAGE.WEIGHTED(B94:AE94,B44:AE44)"),0.02106145538698894) -> 0.021061455
A109: AOV | B109: =AVERAGE(B95:AE95) -> 212.11475
A110: fAOV | B110: =IFERROR(__xludf.DUMMYFUNCTION("AVERAGE.WEIGHTED(B96:AE96,B44:AE44)"),189.8021702237079) -> 189.80217
...

Sheet DTC - P&L
A1: SEPTEMBER | B1: 45170 | C1: 45171 | D1: 45172 | E1: 45173 | F1: 45174 | G1: 45175 | H1: 45176 | I1: 45177 | J1: 45178 | K1: 45179 | L1: 45180 | M1: 45181 | N1: 45182 | O1: 45183 | P1: 45184 | Q1: 45185 | R1: 45186 | S1: 45187 | T1: 45188 | U1: 45189 | V1: 45190 | W1: 45191 | X1: 45192 | Y1: 45193 | Z1: 45194 | AA1: 45195 | AB1: 45196 | AC1: 45197 | AD1: 45198 | AE1: 45199
A2: DAY | B2: FRI | C2: SAT | D2: SUN | E2: MON | F2: TUE | G2: WED | H2: THU | I2: FRI | J2: SAT | K2: SUN | L2: MON | M2: TUE | N2: WED | O2: THU | P2: FRI | Q2: SAT | R2: SUN | S2: MON | T2: TUE | U2: WED | V2: THU | W2: FRI | X2: SAT | Y2: SUN | Z2: MON | AA2: TUE | AB2: WED | AC2: THU | AD2: FRI | AE2: SAT
A3: COMMENT
A4: Orders
A5: Meta | B5: 30 | C5: 37 | D5: 55 | E5: 64 | F5: 74 | G5: 60 | H5: 30 | I5: 25 | J5: 37 | K5: 46 | L5: 65 | M5: 47 | N5: 34 | O5: 38 | P5: 56 | Q5: 49 | R5: 34 | S5: 151 | T5: 103 | U5: 73 | V5: 46 | W5: 34 | X5: 38 | Y5: 43 | Z5: 33 | AA5: 27 | AB5: 28 | AC5: 29 | AD5: 31 | AE5: 36 | AF5: =SUM(B5:AE5) -> 1453
A6: Google | B6: 33 | C6: 43 | D6: 59 | E6: 58 | F6: 53 | G6: 46 | H6: 22 | I6: 22 | J6: 38 | K6: 40 | L6: 26 | M6: 34 | N6: 24 | O6: 28 | P6: 35 | Q6: 33 | R6: 38 | S6: 88 | T6: 73 | U6: 43 | V6: 41 | W6: 42 | X6: 47 | Y6: 38 | Z6: 33 | AA6: 33 | AB6: 32 | AC6: 33 | AD6: 32 | AE6: 45 | AF6: =SUM(B6:AE6) -> 1212
A7: TikTok | B7: 0 | C7: 0 | D7: 0 | E7: 0 | F7: 0 | G7: 0 | H7: 0 | I7: 0 | J7: 0 | K7: 0 | L7: 0 | M7: 0 | N7: 0 | O7: 0 | P7: 0 | Q7: 0 | R7: 0 | S7: 0 | T7: 0 | U7: 0 | V7: 0 | W7: 0 | X7: 0 | Y7: 0 | Z7: 0 | AA7: 0 | AB7: 0 | AC7: 0 | AD7: 0 | AE7: 0 | AF7: 0
A8: Bing | B8: 0 | C8: 2 | D8: 0 | E8: 0 | F8: 0 | G8: 0 | H8: 0 | I8: 0 | J8: 0 | K8: 0 | L8: 0 | M8: 0 | N8: 0 | O8: 0 | P8: 0 | Q8: 0 | R8: 0 | S8: 0 | T8: 0 | U8: 0 | V8: 0 | W8: 0 | X8: 0 | Y8: 22 | Z8: 6 | AA8: 2 | AB8: 0 | AC8: 4 | AD8: 4 | AE8: 6 | AF8: =SUM(B8:AE8) -> 46
A9: Nextdoor | B9: 0 | C9: 0 | D9: 0 | E9: 0 | F9: 0 | G9: 0 | H9: 0 | I9: 0 | J9: 0 | K9: 0 | L9: 0 | M9: 0 | N9: 0 | O9: 0 | P9: 0 | Q9: 0 | R9: 0 | S9: 0 | T9: 0 | U9: 0 | V9: 0 | W9: 0 | X9: 0 | Y9: 0 | Z9: 0 | AA9: 0 | AB9: 0 | AC9: 0 | AD9: 0 | AE9: 0 | AF9: 0
A10: Affiliates (Refersion) | B10: 0 | C10: 0 | D10: 0 | E10: 1 | F10: 2 | G10: 1 | H10: 0 | I10: 0 | J10: 0 | K10: 2 | L10: 0 | M10: 0 | N10: 0 | O10: 2 | P10: 1 | Q10: 2 | R10: 1 | S10: 1 | T10: 1 | U10: 1 | V10: 0 | W10: 1 | X10: 0 | Y10: 1 | Z10: 0 | AA10: 0 | AB10: 0 | AC10: 0 | AD10: 0 | AE10: 0 | AF10: 17
A11: Email | B11: 1 | C11: 1 | D11: 1 | E11: 2 | F11: 2 | G11: 1 | H11: 0 | I11: 2 | J11: 0 | K11: 1 | L11: 2 | M11: 0 | N11: 0 | O11: 1 | P11: 1 | Q11: 0 | R11: 1 | S11: 289 | T11: 87 | U11: 26 | V11: 25 | W11: 21 | X11: 19 | Y11: 13 | Z11: 8 | AA11: 7 | AB11: 30 | AC11: 17 | AD11: 10 | AE11: 4 | AF11: =SUM(B11:AE11) -> 572
A12: All | B12: =SUM(B5:B11) -> 64 | C12: =SUM(C5:C11) -> 83 | D12: =SUM(D5:D11) -> 115 | E12: =SUM(E5:E11) -> 125 | F12: =SUM(F5:F11) -> 131 | G12: =SUM(G5:G11) -> 108 | H12: =SUM(H5:H11) -> 52 | I12: =SUM(I5:I11) -> 49 | ... AE12: =SUM(AE5:AE11) -> 91 | AF12: =SUM(B12:AE12) -> 3300
A14: Revenue | B14: 6093.17 | C14: 7548.12 | D14: 12070.55 | E14: 14020.42 | F14: 15836.42 | G14: 10672.44 | H14: 6908.16 | I14: 6192.65 | J14: 8844.93 | K14: 12091.33 | L14: 16674.1 | M14: 13103.66 | N14: 9013.67 | O14: 8206.73 | P14: 13576.03 | Q14: 11601.77 | R14: 8073.45 | S14: 15805.2 | T14: 12819.7 | U14: 11558.54 | V14: 7521.11 | W14: 6317.87 | X14: 8096.65 | Y14: 9209.38 | Z14: 7333.24 | AA14: 5704 | AB14: 5914.6 | AC14: 6436.66 | AD14: 7919.38 | AE14: 9068.7
A15: Meta | B15: =B14*Summary!B63 -> 6573.3118 | C15: =C14*Summary!C63 -> 8142.9119 | D15: =D14*Summary!D63 -> 13003.604 | E15: =E14*Summary!E63 -> 15135.043 | F15: =F14*Summary!F63 -> 16986.144 | G15: =G14*Summary!G63 -> 11448.326 | H15: =H14*Summary!H63 -> 7391.7312 | I15: =I14*Summary!I63 -> 6630.4704 | ... AE15: =AE14*Summary!AE63 -> 9594.6846 | AF15: =SUM(B15:AE15) -> 307799.04
A16: Google | B16: 5686.76 | C16: 7591.09 | D16: 10836.18 | E16: 10459.89 | F16: 11145.3 | G16: 8833.63 | H16: 4455.65 | I16: 4929.52 | J16: 8377.98 | K16: 8034.35 | L16: 4735.4 | M16: 8170.46 | N16: 4528.93 | O16: 5890.99 | P16: 5996.7 | Q16: 6054.73 | R16: 7230.17 | S16: 11758.69 | T16: 11983.88 | U16: 7147.16 | V16: 7394.44 | W16: 6893.83 | X16: 9346.26 | Y16: 8085.14 | Z16: 6676.5 | AA16: 6657.14 | AB16: 6547.23 | AC16: 6488.04 | AD16: 6111.93 | AE16: 11198.87 | AF16: =SUM(B16:AE16) -> 229246.84
A17: TikTok | B17: 0 | C17: 0 | D17: 0 | E17: 0 | F17: 0 | G17: 0 | H17: 0 | I17: 0 | J17: 0 | K17: 0 | L17: 0 | M17: 0 | N17: 0 | O17: 0 | P17: 0 | Q17: 0 | R17: 0 | S17: 0 | T17: 0 | U17: 0 | V17: 0 | W17: 0 | X17: 0 | Y17: 0 | Z17: 0 | AA17: 0 | AB17: 0 | AC17: 0 | AD17: 0 | AE17: 0 | AF17: =SUM(B17:AE17) -> 0
A18: Bing | B18: 0 | C18: 251 | D18: 0 | E18: 0 | F18: 0 | G18: 0 | H18: 0 | I18: 0 | J18: 0 | K18: 0 | L18: 0 | M18: 0 | N18: 0 | O18: 0 | P18: 0 | Q18: 0 | R18: 0 | S18: 0 | T18: 0 | U18: 0 | V18: 0 | W18: 0 | X18: 0 | Y18: 2761 | Z18: 753 | AA18: 251 | AB18: 0 | AC18: 502 | AD18: 502 | AE18: 753 | AF18: =SUM(B18:AE18) -> 5773
A19: Nextdoor | B19: 0 | C19: 0 | D19: 0 | E19: 0 | F19: 0 | G19: 0 | H19: 0 | I19: 0 | J19: 0 | K19: 0 | L19: 0 | M19: 0 | N19: 0 | O19: 0 | P19: 0 | Q19: 0 | R19: 0 | S19: 0 | T19: 0 | U19: 0 | V19: 0 | W19: 0 | X19: 0 | Y19: 0 | Z19: 0 | AA19: 0 | AB19: 0 | AC19: 0 | AD19: 0 | AE19: 0 | AF19: =SUM(B19:AE19) -> 0
A20: Affiliates (Refersion) | B20: 0 | C20: 0 | D20: 0 | E20: 191.22 | F20: 500.33 | G20: 250.2 | H20: 0 | I20: 0 | J20: 0 | K20: 656.14 | L20: 0 | M20: 0 | N20: 0 | O20: 558.43 | P20: 266.62 | Q20: 299.58 | R20: 268.11 | S20: 77.38 | T20: 295.24 | U20: 285.19 | V20: 0 | W20: 285.82 | X20: 0 | Y20: 134.53 | Z20: 0 | AA20: 0 | AB20: 0 | AC20: 0 | AD20: 0 | AE20: 0 | AF20: 4068.79
A21: Email | B21: 31.54 | C21: 194.2 | D21: 325.4 | E21: 299.73 | F21: 758.64 | G21: 30.22 | H21: 0 | I21: 284.54 | J21: 0 | K21: 277.14 | L21: 272.9 | M21: 0 | N21: 0 | O21: 360.23 | P21: 62.95 | Q21: 0 | R21: 276.01 | S21: 17465.79 | T21: 4691.16 | U21: 1885.65 | V21: 2249.89 | W21: 2177.45 | X21: 912.06 | Y21: 712.15 | Z21: 731.4 | AA21: 720.45 | AB21: 8391.12 | AC21: 3445.83 | AD21: 2534.36 | AE21: 1006.28 | AF21: =SUM(B21:AE21) -> 50097.09
A22: All | B22: =SUM(B15:B21) -> 12291.612 | C22: =SUM(C15:C21) -> 16179.202 | D22: =SUM(D15:D21) -> 24165.184 | E22: =SUM(E15:E21) -> 26085.883 | F22: =SUM(F15:F21) -> 29390.414 | G22: =SUM(G15:G21) -> 20562.376 | H22: =SUM(H15:H21) -> 11847.381 | I22: =SUM(I15:I21) -> 11844.53 | ... AE22: =SUM(AE15:AE21) -> 22552.835 | AF22: =SUM(B22:AE22) -> 596984.76
A24: Media Cost
A25: Meta | B25: =Summary!B65 -> 4940.4078 | C25: =Summary!C65 -> 4538.0801 | D25: =Summary!D65 -> 6292.9294 | E25: =Summary!E65 -> 7164.6631 | F25: =Summary!F65 -> 9564.4493 | G25: =Summary!G65 -> 9981.8489 | H25: =Summary!H65 -> 4150.0806 | I25: =Summary!I65 -> 1979.8849 | ... AE25: =Summary!AE65 -> 5308.5044 | AF25: =SUM(B25:AE25) -> 152533.05
A26: Google | B26: =Summary!B66 -> 1210.79 | C26: =Summary!C66 -> 1399.9 | D26: =Summary!D66 -> 1709.65 | E26: =Summary!E66 -> 1315.99 | F26: =Summary!F66 -> 1354.7 | G26: =Summary!G66 -> 1334.04 | H26: =Summary!H66 -> 1388.13 | I26: =Summary!I66 -> 1350.77 | ... AE26: =Summary!AE66 -> 2141.16 | AF26: =SUM(B26:AE26) -> 56634.05
A27: TikTok | B27: =Summary!B68 -> 0 | C27: =Summary!C68 -> 0 | D27: =Summary!D68 -> 0 | E27: =Summary!E68 -> 0 | F27: =Summary!F68 -> 0 | G27: =Summary!G68 -> 0 | H27: =Summary!H68 -> 0 | I27: =Summary!I68 -> 0 | ... AE27: =Summary!AE68 -> 0 | AF27: =SUM(B27:AE27) -> 217.52
A28: Bing | B28: =Summary!B67 -> 183.94 | C28: =Summary!C67 -> 172.98 | D28: =Summary!D67 -> 228.88 | E28: =Summary!E67 -> 223.48 | F28: =Summary!F67 -> 230.68 | G28: =Summary!G67 -> 227.63 | H28: =Summary!H67 -> 224.23 | I28: =Summary!I67 -> 191.43 | ... AE28: =Summary!AE67 -> 464.33 | AF28: =SUM(B28:AE28) -> 6220.52
A29: Nextdoor | B29: =Summary!B70 -> 0 | C29: =Summary!C70 -> 0 | D29: =Summary!D70 -> 0 | E29: =Summary!E70 -> 0 | F29: =Summary!F70 -> 0 | G29: =Summary!G70 -> 0 | H29: =Summary!H70 -> 0 | I29: =Summary!I70 -> 0 | ... AE29: =Summary!AE70 -> 0 | AF29: =SUM(B29:AE29) -> 7245.47
A30: Affiliate Fee (20%) | B30: =Summary!B72 -> 0 | C30: =Summary!C72 -> 0 | D30: =Summary!D72 -> 0 | E30: =Summary!E72 -> 47.81 | F30: =Summary!F72 -> 113.06 | G30: =Summary!G72 -> 62.55 | H30: =Summary!H72 -> 0 | I30: =Summary!I72 -> 0 | ... AE30: =Summary!AE72 -> 0 | AF30: =SUM(B30:AE30) -> 895.31
A31: All | B31: =SUM(B25:B30) -> 6335.1378 | C31: =SUM(C25:C30) -> 6110.9601 | D31: =SUM(D25:D30) -> 8231.4594 | E31: =SUM(E25:E30) -> 8751.9431 | F31: =SUM(F25:F30) -> 11262.889 | G31: =SUM(G25:G30) -> 11606.069 | H31: =SUM(H25:H30) -> 5762.4406 | I31: =SUM(I25:I30) -> 3522.0849 | ... AE31: =SUM(AE25:AE30) -> 7913.9944 | AF31: =SUM(B31:AE31) -> 223745.92
A36: Revenue
A37: Revenue Woocommerce (Platform) | B37: =Summary!B8 -> 16813.33 | C37: =Summary!C8 -> 24584.7 | D37: =Summary!D8 -> 29900.76 | E37: =Summary!E8 -> 36334.28 | F37: =Summary!F8 -> 33865.73 | G37: =Summary!G8 -> 26222.32 | H37: =Summary!H8 -> 19010.62 | I37: =Summary!I8 -> 14263.81 | ... AE37: =Summary!AE8 -> 24655.64 | AF37: =sum(B37:AE37) -> 723794.94
A38: SUM | B38: =SUM(B37) -> 16813.33 | C38: =SUM(C37) -> 24584.7 | D38: =SUM(D37) -> 29900.76 | E38: =SUM(E37) -> 36334.28 | F38: =SUM(F37) -> 33865.73 | G38: =SUM(G37) -> 26222.32 | H38: =SUM(H37) -> 19010.62 | I38: =SUM(I37) -> 14263.81 | ... AE38: =SUM(AE37) -> 24655.64 | AF38: =sum(B38:AE38) -> 723794.94
A40: Orders
A41: Orders Woocommerce (Platform) | B41: =Summary!B44 -> 80 | C41: =Summary!C44 -> 113 | D41: =Summary!D44 -> 139 | E41: =Summary!E44 -> 168 | F41: =Summary!F44 -> 153 | G41: =Summary!G44 -> 125 | H41: =Summary!H44 -> 81 | I41: =Summary!I44 -> 53 | ... AE41: =Summary!AE44 -> 103 | AF41: =sum(B41:AE41) -> 3889
A42: SUM | B42: =SUM(B41) -> 80 | C42: =SUM(C41) -> 113 | D42: =SUM(D41) -> 139 | E42: =SUM(E41) -> 168 | F42: =SUM(F41) -> 153 | G42: =SUM(G41) -> 125 | H42: =SUM(H41) -> 81 | I42: =SUM(I41) -> 53 | ... AE42: =SUM(AE41) -> 103 | AF42: =sum(B42:AE42) -> 3889
A44: Breakdown
A45: - Hardware | B45: =Summary!B9 -> 13722.1 | C45: =Summary!C9 -> 19550.7 | D45: =Summary!D9 -> 23435.2 | E45: =Summary!E9 -> 29484.65 | F45: =Summary!F9 -> 27664 | G45: =Summary!G9 -> 20990.5 | H45: =Summary!H9 -> 15207.5 | I45: =Summary!I9 -> 11768 | ... AE45: =Summary!AE9 -> 19255.96 | AF45: =SUM(B45:AE45) -> 524910.24
A46: - Add-ons | B46: =Summary!B10 -> 1072.8 | C46: =Summary!C10 -> 1944.6 | D46: =Summary!D10 -> 2730.2 | E46: =Summary!E10 -> 2310.6 | F46: =Summary!F10 -> 2146.4 | G46: =Summary!G10 -> 2010 | H46: =Summary!H10 -> 1468.7 | I46: =Summary!I10 -> 941 | ... AE46: =Summary!AE10 -> 2396.19 | AF46: =SUM(B46:AE46) -> 102785.98
A47: - Merch | B47: =Summary!B11 | C47: =Summary!C11 | D47: =Summary!D11 | E47: =Summary!E11 | F47: =Summary!F11 | G47: =Summary!G11 | H47: =Summary!H11 | I47: =Summary!I11 | ... AE47: =Summary!AE11
A48: - Taxes | B48: =Summary!B13 -> 868.43 | C48: =Summary!C13 -> 1259.4 | D48: =Summary!D13 -> 1585.36 | E48: =Summary!E13 -> 1889.03 | F48: =Summary!F13 -> 1815.33 | G48: =Summary!G13 -> 1391.82 | H48: =Summary!H13 -> 1024.42 | I48: =Summary!I13 -> 584.81 | ... AE48: =Summary!AE13 -> 1353.49 | AF48: =SUM(B48:AE48) -> 37528.72
A49: - Shipping | B49: =Summary!B14 -> 1150 | C49: =Summary!C14 -> 1830 | D49: =Summary!D14 -> 2150 | E49: =Summary!E14 -> 2650 | F49: =Summary!F14 -> 2240 | G49: =Summary!G14 -> 1830 | H49: =Summary!H14 -> 1310 | I49: =Summary!I14 -> 970 | ... AE49: =Summary!AE14 -> 1650 | AF49: =SUM(B49:AE49) -> 58570
A50: SUM | B50: =SUM(B45:B49) -> 16813.33 | C50: =SUM(C45:C49) -> 24584.7 | D50: =SUM(D45:D49) -> 29900.76 | E50: =SUM(E45:E49) -> 36334.28 | F50: =SUM(F45:F49) -> 33865.73 | G50: =SUM(G45:G49) -> 26222.32 | H50: =SUM(H45:H49) -> 19010.62 | I50: =SUM(I45:I49) -> 14263.81 | ... AE50: =SUM(AE45:AE49) -> 24655.64 | AF50: =SUM(B50:AE50) -> 723794.94
A52: Units Sold (Gross)
A53: SKU 1 - Blue | B53: 14 | C53: 25 | D53: 28 | E53: 43 | F53: 35 | G53: 25 | H53: 21 | I53: 12 | J53: 13 | K53: 15 | L53: 17 | M53: 19 | N53: 18 | O53: 21 | P53: 16 | Q53: 18 | R53: 20 | S53: 27 | T53: 18 | U53: 16 | V53: 19 | W53: 16 | X53: 10 | Y53: 11 | Z53: 9 | AA53: 10 | AB53: 20 | AC53: 20 | AD53: 13 | AE53: 15 | AF53: =sum(B53:AE53) -> 564
A54: SKU 2 - Yellow | B54: 3 | C54: 2 | D54: 4 | E54: 11 | F54: 9 | G54: 11 | H54: 1 | I54: 1 | J54: 3 | K54: 4 | L54: 5 | M54: 6 | N54: 3 | O54: 8 | P54: 5 | Q54: 1 | R54: 3 | S54: 6 | T54: 6 | U54: 6 | V54: 2 | W54: 2 | X54: 1 | Y54: 9 | Z54: 8 | AA54: 5 | AB54: 6 | AC54: 5 | AD54: 4 | AE54: 4 | AF54: =sum(B54:AE54) -> 144
A55: SKU 3 - Blue w/ Solar | B55: 45 | C55: 60 | D55: 69 | E55: 80 | F55: 84 | G55: 58 | H55: 46 | I55: 31 | J55: 39 | K55: 45 | L55: 38 | M55: 30 | N55: 34 | O55: 37 | P55: 42 | Q55: 45 | R55: 45 | S55: 43 | T55: 33 | U55: 38 | V55: 34 | W55: 25 | X55: 31 | Y55: 32 | Z55: 31 | AA55: 17 | AB55: 37 | AC55: 25 | AD55: 34 | AE55: 44 | AF55: =sum(B55:AE55) -> 1252
A56: SKU 4 - Yellow w/ Solar | B56: 3 | C56: 11 | D56: 16 | E56: 17 | F56: 12 | G56: 13 | H56: 2 | I56: 5 | J56: 4 | K56: 12 | L56: 8 | M56: 6 | N56: 8 | O56: 10 | P56: 13 | Q56: 5 | R56: 7 | S56: 10 | T56: 17 | U56: 5 | V56: 7 | W56: 16 | X56: 16 | Y56: 18 | Z56: 24 | AA56: 19 | AB56: 31 | AC56: 19 | AD56: 22 | AE56: 15 | AF56: =sum(B56:AE56) -> 371
A57: SUM (SKU 1 - SKU 4) | B57: =SUM(B53:B56) -> 65 | C57: =SUM(C53:C56) -> 98 | D57: =SUM(D53:D56) -> 117 | E57: =SUM(E53:E56) -> 151 | F57: =SUM(F53:F56) -> 140 | G57: =SUM(G53:G56) -> 107 | H57: =SUM(H53:H56) -> 70 | I57: =SUM(I53:I56) -> 49 | ... AE57: =SUM(AE53:AE56) -> 78 | AF57: =sum(B57:AE57) -> 2331
A59: Wall Mount | B59: 20 | C59: 34 | D59: 48 | E59: 41 | F59: 36 | G59: 30 | H59: 24 | I59: 13 | J59: 18 | K59: 27 | L59: 30 | M59: 19 | N59: 17 | O59: 25 | P59: 23 | Q59: 30 | R59: 24 | S59: 38 | T59: 37 | U59: 23 | V59: 20 | W59: 20 | X59: 21 | Y59: 32 | Z59: 27 | AA59: 18 | AB59: 31 | AC59: 29 | AD59: 20 | AE59: 19 | AF59: =sum(B59:AE59) -> 794
A60: Suet Ball Holder | B60: 10 | C60: 22 | D60: 29 | E60: 26 | F60: 24 | G60: 18 | H60: 17 | I60: 10 | J60: 9 | K60: 22 | L60: 17 | M60: 12 | N60: 13 | O60: 21 | P60: 12 | Q60: 19 | R60: 13 | S60: 28 | T60: 34 | U60: 16 | V60: 14 | W60: 14 | X60: 16 | Y60: 22 | Z60: 23 | AA60: 19 | AB60: 21 | AC60: 23 | AD60: 13 | AE60: 21 | AF60: =sum(B60:AE60) -> 558
A61: 3-in-1 Nutrition Set - Blue | B61: 7 | C61: 19 | D61: 28 | E61: 24 | F61: 22 | G61: 15 | H61: 16 | I61: 10 | J61: 10 | K61: 13 | L61: 13 | M61: 14 | N61: 10 | O61: 6 | P61: 6 | Q61: 13 | R61: 5 | S61: 83 | T61: 36 | U61: 19 | V61: 22 | W61: 6 | X61: 13 | Y61: 11 | Z61: 9 | AA61: 8 | AB61: 5 | AC61: 9 | AD61: 8 | AE61: 7 | AF61: =sum(B61:AE61) -> 467
A62: 3-in-1 Nutrition Set - Yellow | B62: 2 | C62: 7 | D62: 7 | E62: 7 | F62: 5 | G62: 5 | H62: 1 | I62: 1 | J62: 0 | K62: 5 | L62: 5 | M62: 1 | N62: 2 | O62: 10 | P62: 8 | Q62: 2 | R62: 3 | S62: 37 | T62: 23 | U62: 2 | V62: 11 | W62: 10 | X62: 6 | Y62: 11 | Z62: 9 | AA62: 6 | AB62: 7 | AC62: 5 | AD62: 11 | AE62: 5 | AF62: =sum(B62:AE62) -> 214
A63: Solar Roof Single - Blue | B63: 3 | C63: 5 | D63: 8 | E63: 6 | F63: 7 | G63: 11 | H63: 5 | I63: 3 | J63: 2 | K63: 6 | L63: 6 | M63: 3 | N63: 3 | O63: 4 | P63: 6 | Q63: 4 | R63: 7 | S63: 5 | T63: 6 | U63: 5 | V63: 7 | W63: 7 | X63: 7 | Y63: 5 | Z63: 4 | AA63: 6 | AB63: 4 | AC63: 3 | AD63: 8 | AE63: 2 | AF63: =sum(B63:AE63) -> 158
A64: Solar Roof Single - Yellow | B64: 3 | C64: 3 | D64: 4 | E64: 3 | F64: 3 | G64: 3 | H64: 1 | I64: 0 | J64: 3 | K64: 1 | L64: 3 | M64: 0 | N64: 0 | O64: 1 | P64: 2 | Q64: 3 | R64: 2 | S64: 7 | T64: 0 | U64: 4 | V64: 4 | W64: 3 | X64: 1 | Y64: 1 | Z64: 0 | AA64: 3 | AB64: 1 | AC64: 1 | AD64: 0 | AE64: 0 | AF64: =sum(B64:AE64) -> 60
A65: Perch Extender - Blue | B65: 0 | C65: 0 | D65: 0 | E65: 0 | F65: 0 | G65: 0 | H65: 0 | I65: 0 | J65: 0 | K65: 0 | L65: 0 | M65: 0 | N65: 0 | O65: 0 | P65: 0 | Q65: 0 | R65: 0 | S65: 430 | T65: 194 | U65: 98 | V65: 62 | W65: 55 | X65: 63 | Y65: 54 | Z65: 39 | AA65: 26 | AB65: 34 | AC65: 36 | AD65: 31 | AE65: 26 | AF65: =sum(B65:AE65) -> 1148
A66: Perch Extender - Yellow | B66: 0 | C66: 0 | D66: 0 | E66: 0 | F66: 0 | G66: 0 | H66: 0 | I66: 0 | J66: 0 | K66: 0 | L66: 0 | M66: 0 | N66: 0 | O66: 0 | P66: 0 | Q66: 0 | R66: 0 | S66: 102 | T66: 58 | U66: 22 | V66: 17 | W66: 15 | X66: 10 | Y66: 19 | Z66: 15 | AA66: 14 | AB66: 14 | AC66: 14 | AD66: 8 | AE66: 12 | AF66: =sum(B66:AE66) -> 320
A67: SUM (Add-ons) | B67: =SUM(B59:B66) -> 45 | C67: =SUM(C59:C66) -> 90 | D67: =SUM(D59:D66) -> 124 | E67: =SUM(E59:E66) -> 107 | F67: =SUM(F59:F66) -> 97 | G67: =SUM(G59:G66) -> 82 | H67: =SUM(H59:H66) -> 64 | I67: =SUM(I59:I66) -> 37 | ... AE67: =SUM(AE59:AE66) -> 92 | AF67: =sum(B67:AE67) -> 3719
A69: Merch Units Sold (Gross)
A70: Merch Units
A72: First-time Customers
A73: SKU 1 - Blue | B73: =B53-B90 -> 13 | C73: =C53-C90 -> 25 | D73: =D53-D90 -> 25 | E73: =E53-E90 -> 43 | F73: =F53-F90 -> 34 | G73: =G53-G90 -> 25 | H73: =H53-H90 -> 21 | I73: =I53-I90 -> 12 | ... AE73: =AE53-AE90 -> 15 | AF73: =sum(B73:AE73) -> 545
A74: SKU 2 - Yellow | B74: =B54-B91 -> 3 | C74: =C54-C91 -> 2 | D74: =D54-D91 -> 4 | E74: =E54-E91 -> 11 | F74: =F54-F91 -> 9 | G74: =G54-G91 -> 11 | H74: =H54-H91 -> 1 | I74: =I54-I91 -> 1 | ... AE74: =AE54-AE91 -> 4 | AF74: =sum(B74:AE74) -> 140
A75: SKU 3 - Blue w/ Solar | B75: =B55-B92 -> 44 | C75: =C55-C92 -> 58 | D75: =D55-D92 -> 68 | E75: =E55-E92 -> 79 | F75: =F55-F92 -> 82 | G75: =G55-G92 -> 58 | H75: =H55-H92 -> 46 | I75: =I55-I92 -> 31 | ... AE75: =AE55-AE92 -> 41 | AF75: =sum(B75:AE75) -> 1214
A76: SKU 4 - Yellow w/ Solar | B76: =B56-B93 -> 3 | C76: =C56-C93 -> 11 | D76: =D56-D93 -> 15 | E76: =E56-E93 -> 16 | F76: =F56-F93 -> 11 | G76: =G56-G93 -> 11 | H76: =H56-H93 -> 2 | I76: =I56-I93 -> 5 | ... AE76: =AE56-AE93 -> 14 | AF76: =sum(B76:AE76) -> 352
A77: SUM (SKU 1 - SKU 4) | B77: =SUM(B73:B76) -> 63 | C77: =SUM(C73:C76) -> 96 | D77: =SUM(D73:D76) -> 112 | E77: =SUM(E73:E76) -> 149 | F77: =SUM(F73:F76) -> 136 | G77: =SUM(G73:G76) -> 105 | H77: =SUM(H73:H76) -> 70 | I77: =SUM(I73:I76) -> 49 | ... AE77: =SUM(AE73:AE76) -> 74 | AF77: =sum(B77:AE77) -> 2251
A79: Wall Mount | B79: =B59-B96 -> 20 | C79: =C59-C96 -> 32 | D79: =D59-D96 -> 45 | E79: =E59-E96 -> 37 | F79: =F59-F96 -> 34 | G79: =G59-G96 -> 30 | H79: =H59-H96 -> 24 | I79: =I59-I96 -> 13 | ... AE79: =AE59-AE96 -> 19 | AF79: =sum(B79:AE79) -> 755
A80: Suet Ball Holder | B80: =B60-B97 -> 10 | C80: =C60-C97 -> 21 | D80: =D60-D97 -> 24 | E80: =E60-E97 -> 24 | F80: =F60-F97 -> 23 | G80: =G60-G97 -> 18 | H80: =H60-H97 -> 16 | I80: =I60-I97 -> 10 | ... AE80: =AE60-AE97 -> 20 | AF80: =sum(B80:AE80) -> 519
A81: 3-in-1 Nutrition Set - Blue | B81: =B61-B98 -> 6 | C81: =C61-C98 -> 16 | D81: =D61-D98 -> 28 | E81: =E61-E98 -> 23 | F81: =F61-F98 -> 18 | G81: =G61-G98 -> 14 | H81: =H61-H98 -> 16 | I81: =I61-I98 -> 10 | ... AE81: =AE61-AE98 -> 7 | AF81: =sum(B81:AE81) -> 431
A82: 3-in-1 Nutrition Set - Yellow | B82: =B62-B99 -> 2 | C82: =C62-C99 -> 6 | D82: =D62-D99 -> 4 | E82: =E62-E99 -> 6 | F82: =F62-F99 -> 4 | G82: =G62-G99 -> 4 | H82: =H62-H99 -> 1 | I82: =I62-I99 -> 1 | ... AE82: =AE62-AE99 -> 5 | AF82: =sum(B82:AE82) -> 195
A83: Solar Roof Single - Blue | B83: =B63-B100 -> 3 | C83: =C63-C100 -> 5 | D83: =D63-D100 -> 8 | E83: =E63-E100 -> 6 | F83: =F63-F100 -> 6 | G83: =G63-G100 -> 10 | H83: =H63-H100 -> 4 | I83: =I63-I100 -> 3 | ... AE83: =AE63-AE100 -> 2 | AF83: =sum(B83:AE83) -> 133
A84: Solar Roof Single - Yellow | B84: =B64-B101 -> 1 | C84: =C64-C101 -> 3 | D84: =D64-D101 -> 3 | E84: =E64-E101 -> 2 | F84: =F64-F101 -> 3 | G84: =G64-G101 -> 2 | H84: =H64-H101 -> 1 | I84: =I64-I101 -> 0 | ... AE84: =AE64-AE101 -> 0 | AF84: =sum(B84:AE84) -> 45
A85: Perch Extender - Blue | B85: =B65-B102 -> 0 | C85: =C65-C102 -> 0 | D85: =D65-D102 -> 0 | E85: =E65-E102 -> 0 | F85: =F65-F102 -> 0 | G85: =G65-G102 -> 0 | H85: =H65-H102 -> 0 | I85: =I65-I102 -> 0 | ... AE85: =AE65-AE102 -> 25 | AF85: =sum(B85:AE85) -> 1063
A86: Perch Extender - Yellow | B86: =B66-B103 -> 0 | C86: =C66-C103 -> 0 | D86: =D66-D103 -> 0 | E86: =E66-E103 -> 0 | F86: =F66-F103 -> 0 | G86: =G66-G103 -> 0 | H86: =H66-H103 -> 0 | I86: =I66-I103 -> 0 | ... AE86: =AE66-AE103 -> 9 | AF86: =sum(B86:AE86) -> 282
A87: SUM (Add-ons) | B87: =SUM(B79:B86) -> 42 | C87: =SUM(C79:C86) -> 83 | D87: =SUM(D79:D86) -> 112 | E87: =SUM(E79:E86) -> 98 | F87: =SUM(F79:F86) -> 88 | G87: =SUM(G79:G86) -> 78 | H87: =SUM(H79:H86) -> 62 | I87: =SUM(I79:I86) -> 37 | ... AE87: =SUM(AE79:AE86) -> 87 | AF87: =sum(B87:AE87) -> 3423
A89: Returning Customers
A90: SKU 1 - Blue | B90: 1 | C90: 0 | D90: 3 | E90: 0 | F90: 1 | G90: 0 | H90: 0 | I90: 0 | J90: 0 | K90: 0 | L90: 0 | M90: 0 | N90: 1 | O90: 0 | P90: 1 | Q90: 0 | R90: 0 | S90: 1 | T90: 0 | U90: 0 | V90: 1 | W90: 0 | X90: 0 | Y90: 0 | Z90: 0 | AA90: 2 | AB90: 6 | AC90: 1 | AD90: 1 | AE90: 0 | AF90: =sum(B90:AE90) -> 19
A91: SKU 2 - Yellow | B91: 0 | C91: 0 | D91: 0 | E91: 0 | F91: 0 | G91: 0 | H91: 0 | I91: 0 | J91: 0 | K91: 0 | L91: 0 | M91: 1 | N91: 0 | O91: 0 | P91: 1 | Q91: 0 | R91: 0 | S91: 0 | T91: 1 | U91: 0 | V91: 0 | W91: 0 | X91: 0 | Y91: 0 | Z91: 1 | AA91: 0 | AB91: 0 | AC91: 0 | AD91: 0 | AE91: 0 | AF91: =sum(B91:AE91) -> 4
A92: SKU 3 - Blue w/ Solar | B92: 1 | C92: 2 | D92: 1 | E92: 1 | F92: 2 | G92: 0 | H92: 0 | I92: 0 | J92: 0 | K92: 2 | L92: 1 | M92: 3 | N92: 0 | O92: 0 | P92: 0 | Q92: 1 | R92: 2 | S92: 0 | T92: 3 | U92: 0 | V92: 0 | W92: 0 | X92: 0 | Y92: 2 | Z92: 0 | AA92: 2 | AB92: 9 | AC92: 2 | AD92: 1 | AE92: 3 | AF92: =sum(B92:AE92) -> 38
A93: SKU 4 - Yellow w/ Solar | B93: 0 | C93: 0 | D93: 1 | E93: 1 | F93: 1 | G93: 2 | H93: 0 | I93: 0 | J93: 0 | K93: 1 | L93: 0 | M93: 1 | N93: 0 | O93: 0 | P93: 2 | Q93: 0 | R93: 0 | S93: 0 | T93: 1 | U93: 0 | V93: 0 | W93: 0 | X93: 0 | Y93: 0 | Z93: 2 | AA93: 0 | AB93: 5 | AC93: 1 | AD93: 0 | AE93: 1 | AF93: =sum(B93:AE93) -> 19
A94: SUM (SKU 1 - SKU 4) | B94: =SUM(B90:B93) -> 2 | C94: =SUM(C90:C93) -> 2 | D94: =SUM(D90:D93) -> 5 | E94: =SUM(E90:E93) -> 2 | F94: =SUM(F90:F93) -> 4 | G94: =SUM(G90:G93) -> 2 | H94: =SUM(H90:H93) -> 0 | I94: =SUM(I90:I93) -> 0 | ... AE94: =SUM(AE90:AE93) -> 4 | AF94: =sum(B94:AE94) -> 80
A96: Wall Mount | B96: 0 | C96: 2 | D96: 3 | E96: 4 | F96: 2 | G96: 0 | H96: 0 | I96: 0 | J96: 1 | K96: 1 | L96: 2 | M96: 3 | N96: 0 | O96: 0 | P96: 4 | Q96: 0 | R96: 1 | S96: 0 | T96: 0 | U96: 0 | V96: 0 | W96: 0 | X96: 2 | Y96: 2 | Z96: 3 | AA96: 2 | AB96: 6 | AC96: 1 | AD96: 0 | AE96: 0 | AF96: =sum(B96:AE96) -> 39
A97: Suet Ball Holder | B97: 0 | C97: 1 | D97: 5 | E97: 2 | F97: 1 | G97: 0 | H97: 1 | I97: 0 | J97: 1 | K97: 1 | L97: 1 | M97: 1 | N97: 0 | O97: 0 | P97: 3 | Q97: 1 | R97: 2 | S97: 2 | T97: 1 | U97: 2 | V97: 0 | W97: 0 | X97: 0 | Y97: 1 | Z97: 3 | AA97: 2 | AB97: 4 | AC97: 2 | AD97: 1 | AE97: 1 | AF97: =sum(B97:AE97) -> 39
A98: 3-in-1 Nutrition Set - Blue | B98: 1 | C98: 3 | D98: 0 | E98: 1 | F98: 4 | G98: 1 | H98: 0 | I98: 0 | J98: 1 | K98: 1 | L98: 1 | M98: 2 | N98: 0 | O98: 0 | P98: 0 | Q98: 2 | R98: 1 | S98: 3 | T98: 5 | U98: 2 | V98: 1 | W98: 0 | X98: 0 | Y98: 1 | Z98: 2 | AA98: 3 | AB98: 1 | AC98: 0 | AD98: 0 | AE98: 0 | AF98: =sum(B98:AE98) -> 36
A99: 3-in-1 Nutrition Set - Yellow | B99: 0 | C99: 1 | D99: 3 | E99: 1 | F99: 1 | G99: 1 | H99: 0 | I99: 0 | J99: 0 | K99: 0 | L99: 0 | M99: 0 | N99: 0 | O99: 0 | P99: 3 | Q99: 0 | R99: 0 | S99: 3 | T99: 0 | U99: 0 | V99: 0 | W99: 0 | X99: 1 | Y99: 2 | Z99: 0 | AA99: 0 | AB99: 2 | AC99: 0 | AD99: 1 | AE99: 0 | AF99: =sum(B99:AE99) -> 19
A100: Solar Roof Single - Blue | B100: 0 | C100: 0 | D100: 0 | E100: 0 | F100: 1 | G100: 1 | H100: 1 | I100: 0 | J100: 0 | K100: 0 | L100: 0 | M100: 0 | N100: 0 | O100: 0 | P100: 1 | Q100: 0 | R100: 0 | S100: 2 | T100: 0 | U100: 2 | V100: 9 | W100: 1 | X100: 2 | Y100: 0 | Z100: 0 | AA100: 3 | AB100: 0 | AC100: 0 | AD100: 2 | AE100: 0 | AF100: =sum(B100:AE100) -> 25
A101: Solar Roof Single - Yellow | B101: 2 | C101: 0 | D101: 1 | E101: 1 | F101: 0 | G101: 1 | H101: 0 | I101: 0 | J101: 1 | K101: 0 | L101: 1 | M101: 0 | N101: 0 | O101: 1 | P101: 2 | Q101: 0 | R101: 0 | S101: 1 | T101: 0 | U101: 1 | V101: 1 | W101: 1 | X101: 0 | Y101: 0 | Z101: 0 | AA101: 0 | AB101: 0 | AC101: 1 | AD101: 0 | AE101: 0 | AF101: =sum(B101:AE101) -> 15
A102: Perch Extender - Blue | B102: 0 | C102: 0 | D102: 0 | E102: 0 | F102: 0 | G102: 0 | H102: 0 | I102: 0 | J102: 0 | K102: 0 | L102: 0 | M102: 0 | N102: 0 | O102: 0 | P102: 0 | Q102: 0 | R102: 0 | S102: 32 | T102: 11 | U102: 9 | V102: 3 | W102: 2 | X102: 6 | Y102: 2 | Z102: 6 | AA102: 3 | AB102: 4 | AC102: 2 | AD102: 4 | AE102: 1 | AF102: =sum(B102:AE102) -> 85
A103: Perch Extender - Yellow | B103: 0 | C103: 0 | D103: 0 | E103: 0 | F103: 0 | G103: 0 | H103: 0 | I103: 0 | J103: 0 | K103: 0 | L103: 0 | M103: 0 | N103: 0 | O103: 0 | P103: 0 | Q103: 0 | R103: 0 | S103: 11 | T103: 4 | U103: 4 | V103: 1 | W103: 0 | X103: 1 | Y103: 4 | Z103: 3 | AA103: 1 | AB103: 3 | AC103: 1 | AD103: 2 | AE103: 3 | AF103: =sum(B103:AE103) -> 38
A104: SUM (Add-ons) | B104: =SUM(B96:B103) -> 3 | C104: =SUM(C96:C103) -> 7 | D104: =SUM(D96:D103) -> 12 | E104: =SUM(E96:E103) -> 9 | F104: =SUM(F96:F103) -> 9 | G104: =SUM(G96:G103) -> 4 | H104: =SUM(H96:H103) -> 2 | I104: =SUM(I96:I103) -> 0 | ... AE104: =SUM(AE96:AE103) -> 5 | AF104: =sum(B104:AE104) -> 296
A106: Units Sold (Net)
A107: SKU 1 - Blue | B107: =B53-(B200+B205+B246+B296+B305) -> 12 | C107: =C53-(C200+C205+C246+C296+C305) -> 25 | D107: =D53-(D200+D205+D246+D296+D305) -> 27 | E107: =E53-(E200+E205+E246+E296+E305) -> 43 | F107: =F53-(F200+F205+F246+F296+F305) -> 33 | G107: =G53-(G200+G205+G246+G296+G305) -> 23 | H107: =H53-(H200+H205+H246+H296+H305) -> 19 | I107: =I53-(I200+I205+I246+I296+I305) -> 12 | ... AE107: =AE53-(AE200+AE205+AE246+AE296+AE305) -> 13 | AF107: =sum(B107:AE107) -> 483
A108: SKU 2 - Yellow | B108: =B54-(B201+B206+B247+B297+B306) -> -2 | C108: =C54-(C201+C206+C247+C297+C306) -> 2 | D108: =D54-(D201+D206+D247+D297+D306) -> 4 | E108: =E54-(E201+E206+E247+E297+E306) -> 11 | F108: =F54-(F201+F206+F247+F297+F306) -> 9 | G108: =G54-(G201+G206+G247+G297+G306) -> 9 | H108: =H54-(H201+H206+H247+H297+H306) -> 0 | I108: =I54-(I201+I206+I247+I297+I306) -> 1 | ... AE108: =AE54-(AE201+AE206+AE247+AE297+AE306) -> 4 | AF108: =sum(B108:AE108) -> 112
A109: SKU 3 - Blue w/ Solar | B109: =B55-(B202+B207+B248+B298+B307) -> 38 | C109: =C55-(C202+C207+C248+C298+C307) -> 60 | D109: =D55-(D202+D207+D248+D298+D307) -> 66 | E109: =E55-(E202+E207+E248+E298+E307) -> 80 | F109: =F55-(F202+F207+F248+F298+F307) -> 80 | G109: =G55-(G202+G207+G248+G298+G307) -> 48 | H109: =H55-(H202+H207+H248+H298+H307) -> 42 | I109: =I55-(I202+I207+I248+I298+I307) -> 31 | ... AE109: =AE55-(AE202+AE207+AE248+AE298+AE307) -> 43 | AF109: =sum(B109:AE109) -> 1139
A110: SKU 4 - Yellow w/ Solar | B110: =B56-(B203+B208+B249+B299+B308) -> 2 | C110: =C56-(C203+C208+C249+C299+C308) -> 8 | D110: =D56-(D203+D208+D249+D299+D308) -> 16 | E110: =E56-(E203+E208+E249+E299+E308) -> 16 | F110: =F56-(F203+F208+F249+F299+F308) -> 12 | G110: =G56-(G203+G208+G249+G299+G308) -> 12 | H110: =H56-(H203+H208+H249+H299+H308) -> 2 | I110: =I56-(I203+I208+I249+I299+I308) -> 5 | ... AE110: =AE56-(AE203+AE208+AE249+AE299+AE308) -> 15 | AF110: =sum(B110:AE110) -> 338
A111: SUM (SKU 1 - SKU 4) | B111: =SUM(B107:B110) -> 50 | C111: =SUM(C107:C110) -> 95 | D111: =SUM(D107:D110) -> 113 | E111: =SUM(E107:E110) -> 150 | F111: =SUM(F107:F110) -> 134 | G111: =SUM(G107:G110) -> 92 | H111: =SUM(H107:H110) -> 63 | I111: =SUM(I107:I110) -> 49 | ... AE111: =SUM(AE107:AE110) -> 75 | AF111: =sum(B111:AE111) -> 2072
A113: Wall Mount | B113: =B59-(B213+B224+B259+B317+B328) -> 19 | C113: =C59-(C213+C224+C259+C317+C328) -> 33 | D113: =D59-(D213+D224+D259+D317+D328) -> 47 | E113: =E59-(E213+E224+E259+E317+E328) -> 41 | F113: =F59-(F213+F224+F259+F317+F328) -> 34 | G113: =G59-(G213+G224+G259+G317+G328) -> 27 | H113: =H59-(H213+H224+H259+H317+H328) -> 24 | I113: =I59-(I213+I224+I259+I317+I328) -> 12 | ... AE113: =AE59-(AE213+AE224+AE259+AE317+AE328) -> 16 | AF113: =sum(B113:AE113) -> 711
A114: Suet Ball Holder | B114: =B60-(B214+B225+B260+B318+B329) -> 10 | C114: =C60-(C214+C225+C260+C318+C329) -> 22 | D114: =D60-(D214+D225+D260+D318+D329) -> 29 | E114: =E60-(E214+E225+E260+E318+E329) -> 26 | F114: =F60-(F214+F225+F260+F318+F329) -> 24 | G114: =G60-(G214+G225+G260+G318+G329) -> 18 | H114: =H60-(H214+H225+H260+H318+H329) -> 17 | I114: =I60-(I214+I225+I260+I318+I329) -> 9 | ... AE114: =AE60-(AE214+AE225+AE260+AE318+AE329) -> 19 | AF114: =sum(B114:AE114) -> 508
A115: 3-in-1 Nutrition Set - Blue | B115: =B61-(B215+B226+B261+B319+B330) -> 7 | C115: =C61-(C215+C226+C261+C319+C330) -> 19 | D115: =D61-(D215+D226+D261+D319+D330) -> 28 | E115: =E61-(E215+E226+E261+E319+E330) -> 24 | F115: =F61-(F215+F226+F261+F319+F330) -> 22 | G115: =G61-(G215+G226+G261+G319+G330) -> 14 | H115: =H61-(H215+H226+H261+H319+H330) -> 16 | I115: =I61-(I215+I226+I261+I319+I330) -> 10 | ... L115: =L61-(L215+L226+L261+L319+L330) -> 13 | M115: =M61-(M215+M226+M263+M319+M330) -> 10 | N115: =N61-(N215+N226+N261+N319+N330) -> 6 | O115: =O61-(O215+O226+O261+O319+O330) -> 5 | P115: =P61-(P215+P226+P261+P319+P330) -> 6 | Q115: =Q61-(Q215+Q226+Q261+Q319+Q330) -> 12 | R115: =R61-(R215+R226+R261+R319+R330) -> 5 | S115: =S61-(S215+S226+S261+S319+S330) -> 82 | T115: =T61-(T215+T226+T261+T319+T330) -> 36 | U115: =U61-(U215+U226+U261+U319+U330) -> 17 | ... AE115: =AE61-(AE215+AE226+AE261+AE319+AE330) -> 7 | AF115: =sum(B115:AE115) -> 443
A116: 3-in-1 Nutrition Set - Yellow | B116: =B62-(B216+B227+B262+B320+B331) -> 2 | C116: =C62-(C216+C227+C262+C320+C331) -> 6 | D116: =D62-(D216+D227+D262+D320+D331) -> 7 | E116: =E62-(E216+E227+E262+E320+E331) -> 6 | F116: =F62-(F216+F227+F262+F320+F331) -> 5 | G116: =G62-(G216+G227+G262+G320+G331) -> 4 | H116: =H62-(H216+H227+H262+H320+H331) -> 1 | I116: =I62-(I216+I227+I262+I320+I331) -> 1 | ... L116: =L62-(L216+L227+L262+L320+L331) -> 5 | M116: =M62-(M216+M227+M264+M320+M331) -> -1 | N116: =N62-(N216+N227+N262+N320+N331) -> 1 | O116: =O62-(O216+O227+O262+O320+O331) -> 9 | P116: =P62-(P216+P227+P262+P320+P331) -> 7 | Q116: =Q62-(Q216+Q227+Q262+Q320+Q331) -> 2 | R116: =R62-(R216+R227+R262+R320+R331) -> 3 | S116: =S62-(S216+S227+S262+S320+S331) -> 37 | T116: =T62-(T216+T227+T262+T320+T331) -> 23 | U116: =U62-(U216+U227+U262+U320+U331) -> 2 | ... AE116: =AE62-(AE216+AE227+AE262+AE320+AE331) -> 5 | AF116: =sum(B116:AE116) -> 205
A117: Solar Roof Single - Blue | B117: =B63-(B217+B228+B263+B321+B332) -> 3 | C117: =C63-(C217+C228+C263+C321+C332) -> 5 | D117: =D63-(D217+D228+D263+D321+D332) -> 8 | E117: =E63-(E217+E228+E263+E321+E332) -> 6 | F117: =F63-(F217+F228+F263+F321+F332) -> 7 | G117: =G63-(G217+G228+G263+G321+G332) -> 11 | H117: =H63-(H217+H228+H263+H321+H332) -> 5 | I117: =I63-(I217+I228+I263+I321+I332) -> 3 | ... AE117: =AE63-(AE217+AE228+AE263+AE321+AE332) -> 1 | AF117: =sum(B117:AE117) -> 121
...

Sheet AMAZON - P&L
A1: JANUARY | B1: 45170 | C1: 45171 | D1: 45172 | E1: 45173 | F1: 45174 | G1: 45175 | H1: 45176 | I1: 45177 | J1: 45178 | K1: 45179 | L1: 45180 | M1: 45181 | N1: 45182 | O1: 45183 | P1: 45184 | Q1: 45185 | R1: 45186 | S1: 45187 | T1: 45188 | U1: 45189 | V1: 45190 | W1: 45191 | X1: 45192 | Y1: 45193 | Z1: 45194 | AA1: 45195 | AB1: 45196 | AC1: 45197 | AD1: 45198 | AE1: 45199
A2: DAY | B2: FRI | C2: SAT | D2: SUN | E2: MON | F2: TUE | G2: WED | H2: THU | I2: FRI | J2: SAT | K2: SUN | L2: MON | M2: TUE | N2: WED | O2: THU | P2: FRI | Q2: SAT | R2: SUN | S2: MON | T2: TUE | U2: WED | V2: THU | W2: FRI | X2: SAT | Y2: SUN | Z2: MON | AA2: TUE | AB2: WED | AC2: THU | AD2: FRI | AE2: SAT
A3: COMMENT
A4: Orders
A5: Amazon (market place) | B5: =Summary!B47 -> 14 | C5: =Summary!C47 -> 8 | D5: =Summary!D47 -> 20 | E5: =Summary!E47 -> 24 | F5: =Summary!F47 -> 16 | G5: =Summary!G47 -> 21 | H5: =Summary!H47 -> 12 | I5: =Summary!I47 -> 11 | ... AE5: =Summary!AE47 -> 30
A6: All | B6: =SUM(B5) -> 14 | C6: =SUM(C5) -> 8 | D6: =SUM(D5) -> 20 | E6: =SUM(E5) -> 24 | F6: =SUM(F5) -> 16 | G6: =SUM(G5) -> 21 | H6: =SUM(H5) -> 12 | I6: =SUM(I5) -> 11 | ... AE6: =SUM(AE5) -> 30 | AF6: =SUM(B6:AE6) -> 772
A8: Revenue
A9: Amazon (market place) | B9: =Summary!B15 -> 3281.76 | C9: =Summary!C15 -> 3000.84 | D9: =Summary!D15 -> 4785.04 | E9: =Summary!E15 -> 6287.08 | F9: =Summary!F15 -> 5999.8 | G9: =Summary!G15 -> 5360.55 | H9: =Summary!H15 -> 3848.96 | I9: =Summary!I15 -> 2985.94 | ... AE9: =Summary!AE15 -> 7779.39
A10: All | B10: =SUM(B9) -> 3281.76 | C10: =SUM(C9) -> 3000.84 | D10: =SUM(D9) -> 4785.04 | E10: =SUM(E9) -> 6287.08 | F10: =SUM(F9) -> 5999.8 | G10: =SUM(G9) -> 5360.55 | H10: =SUM(H9) -> 3848.96 | I10: =SUM(I9) -> 2985.94 | ... AE10: =SUM(AE9) -> 7779.39 | AF10: =SUM(B10:AE10) -> 229806.35
A12: Media Cost
A13: Amazon Spend | B13: =Summary!B69 -> 1276.67 | C13: =Summary!C69 -> 1876.55 | D13: =Summary!D69 -> 2182.61 | E13: =Summary!E69 -> 1886.24 | F13: =Summary!F69 -> 1401.31 | G13: =Summary!G69 -> 1491.07 | H13: =Summary!H69 -> 1448.93 | I13: =Summary!I69 -> 1479.75 | ... AE13: =Summary!AE69 -> 3932.81 | AF13: =sum(B13:AE13) -> 61343.57
A14: Amazon Platform Fee (15 %) | B14: =B9*'DATA - P&L'!$C$48 -> 492.264 | C14: =C9*'DATA - P&L'!$C$48 -> 450.126 | D14: =D9*'DATA - P&L'!$C$48 -> 717.756 | E14: =E9*'DATA - P&L'!$C$48 -> 943.062 | F14: =F9*'DATA - P&L'!$C$48 -> 899.97 | G14: =G9*'DATA - P&L'!$C$48 -> 804.0825 | H14: =H9*'DATA - P&L'!$C$48 -> 577.344 | I14: =I9*'DATA - P&L'!$C$48 -> 447.891 | ... AE14: =AE9*'DATA - P&L'!$C$48 -> 1166.9085
A15: All | B15: =SUM(B13:B14) -> 1768.934 | C15: =SUM(C13:C14) -> 2326.676 | D15: =SUM(D13:D14) -> 2900.366 | E15: =SUM(E13:E14) -> 2829.302 | F15: =SUM(F13:F14) -> 2301.28 | G15: =SUM(G13:G14) -> 2295.1525 | H15: =SUM(H13:H14) -> 2026.274 | I15: =SUM(I13:I14) -> 1927.641 | ... AE15: =SUM(AE13:AE14) -> 5099.7185 | AF15: =SUM(B15:AE15) -> 95814.523
A19: Amazon Orders
A20: Hardware | B20: =Summary!B16 -> 3069 | C20: =Summary!C16 -> 2790 | D20: =Summary!D16 -> 4464 | E20: =Summary!E16 -> 5859 | F20: =Summary!F16 -> 5580 | G20: =Summary!G16 -> 5022 | H20: =Summary!H16 -> 3627 | I20: =Summary!I16 -> 2790 | ... AE20: =Summary!AE16 -> 7254 | AF20: =SUM(B20:AE20) -> 214551
A21: Addons | B21: =Summary!B17 -> 0 | C21: =Summary!C17 -> 0 | D21: =Summary!D17 -> 0 | E21: =Summary!E17 -> 0 | F21: =Summary!F17 -> 0 | G21: =Summary!G17 -> 0 | H21: =Summary!H17 -> 0 | I21: =Summary!I17 -> 0 | ... AE21: =Summary!AE17 -> 0 | AF21: =SUM(B21:AE21) -> 0
A22: Tax | B22: =Summary!B18 -> 205.77 | C22: =Summary!C18 -> 210.38 | D22: =Summary!D18 -> 302.63 | E22: =Summary!E18 -> 423.13 | F22: =Summary!F18 -> 410.82 | G22: =Summary!G18 -> 328.65 | H22: =Summary!H18 -> 221.96 | I22: =Summary!I18 -> 195.94 | ... AE22: =Summary!AE18 -> 520.9 | AF22: =SUM(B22:AE22) -> 15031.59
A23: Shipping | B23: =Summary!B19 -> 6.99 | C23: =Summary!C19 -> 0.29 | D23: =Summary!D19 -> 13.75 | E23: =Summary!E19 -> 0.29 | F23: =Summary!F19 -> 0 | G23: =Summary!G19 -> 0.58 | H23: =Summary!H19 -> 0 | I23: =Summary!I19 -> 0 | ... AE23: =Summary!AE19 -> 0 | AF23: =SUM(B23:AE23) -> 76.34
A24: Gift Wrap Price | B24: =Summary!B20 -> 0 | C24: =Summary!C20 -> 0.17 | D24: =Summary!D20 -> 4.66 | E24: =Summary!E20 -> 4.66 | F24: =Summary!F20 -> 8.98 | G24: =Summary!G20 -> 9.32 | H24: =Summary!H20 -> 0 | I24: =Summary!I20 -> 0 | ... AE24: =Summary!AE20 -> 4.49 | AF24: =SUM(B24:AE24) -> 147.42
A25: All Amazon | B25: =SUM(B20:B24) -> 3281.76 | C25: =SUM(C20:C24) -> 3000.84 | D25: =SUM(D20:D24) -> 4785.04 | E25: =SUM(E20:E24) -> 6287.08 | F25: =SUM(F20:F24) -> 5999.8 | G25: =SUM(G20:G24) -> 5360.55 | H25: =SUM(H20:H24) -> 3848.96 | I25: =SUM(I20:I24) -> 2985.94 | ... AE25: =SUM(AE20:AE24) -> 7779.39 | AF25: =SUM(B25:AE25) -> 229806.35
A27: Units Sold (Gross)
A28: SKU 1 - Blue | AF28: =sum(B28:AE28) -> 0
A29: SKU 2 - Yellow | AF29: =sum(B29:AE29) -> 0
A30: SKU 3 - Blue w/ Solar | B30: 11 | C30: 10 | D30: 17 | E30: 22 | F30: 21 | G30: 18 | H30: 13 | I30: 10 | J30: 26 | K30: 22 | L30: 22 | M30: 27 | N30: 27 | O30: 31 | P30: 15 | Q30: 21 | R30: 18 | S30: 25 | T30: 49 | U30: 32 | V30: 31 | W30: 41 | X30: 21 | Y30: 39 | Z30: 32 | AA30: 36 | AB30: 34 | AC30: 41 | AD30: 37 | AE30: 32 | AF30: =sum(B30:AE30) -> 781
A31: SKU 4 - Yellow w/ Solar | AF31: =sum(B31:AE31) -> 0
A32: SUM (SKU 1 - SKU 4) | B32: =sum(B28:B31) -> 11 | C32: =sum(C28:C31) -> 10 | D32: =sum(D28:D31) -> 17 | E32: =sum(E28:E31) -> 22 | F32: =sum(F28:F31) -> 21 | G32: =sum(G28:G31) -> 18 | H32: =sum(H28:H31) -> 13 | I32: =sum(I28:I31) -> 10 | ... AE32: =sum(AE28:AE31) -> 32 | AF32: =sum(B32:AE32) -> 781
A34: Wall Mount | AF34: =sum(B34:AE34) -> 0
A35: Suet Ball Holder | AF35: =sum(B35:AE35) -> 0
A36: 3-in-1 Nutrition Set - Blue | AF36: =sum(B36:AE36) -> 0
A37: 3-in-1 Nutrition Set - Yellow | AF37: =sum(B37:AE37) -> 0
A38: Solar Roof Single - Blue | AF38: =sum(B38:AE38) -> 0
A39: Solar Roof Single - Yellow | AF39: =sum(B39:AE39) -> 0
A40: Perch Extender - Blue | AF40: =sum(B40:AE40) -> 0
A41: Perch Extender - Yellow | AF41: =sum(B41:AE41) -> 0
A42: SUM (Add-ons) | B42: =SUM(B34:B41) -> 0 | C42: =SUM(C34:C41) -> 0 | D42: =SUM(D34:D41) -> 0 | E42: =SUM(E34:E41) -> 0 | F42: =SUM(F34:F41) -> 0 | G42: =SUM(G34:G41) -> 0 | H42: =SUM(H34:H41) -> 0 | I42: =SUM(I34:I41) -> 0 | ... AE42: =SUM(AE34:AE41) -> 0 | AF42: =sum(B42:AE42) -> 0
A45: Units Sold by country (Gross) - Only selling in US
A46: Bird Buddy - Blue - AMAZON.US | AF46: =sum(B46:AE46) -> 0
A47: Bird Buddy - Yellow - AMAZON.US
A48: Bird Buddy with Solar Roof Blue - AMAZON.US | AB48: =AB31 | AC48: =AC31 | AD48: =AD31 | AE48: =AE31 | AF48: =sum(B48:AE48) -> 0
A49: Bird Buddy with Solar Roof Yellow - AMAZON.US
A50: Bird Buddy - AMAZON.EU | AF50: =sum(B50:AE50) -> 0
A51: Bird Buddy with Solar Roof - AMAZON.EU | AF51: =sum(B51:AE51) -> 0
A52: Bird Buddy - AMAZON (OTHER1) | AF52: =sum(B52:AE52) -> 0
A53: Bird Buddy with Solar Roof - AMAZON (OTHER1) | AF53: =sum(B53:AE53) -> 0
A54: All Bird Buddy | B54: =B46+B50+B52 -> 0 | C54: =SUM(C46:C53) -> 0 | D54: =SUM(D46:D53) -> 0 | E54: =SUM(E46:E53) -> 0 | F54: =SUM(F46:F53) -> 0 | G54: =SUM(G46:G53) -> 0 | H54: =SUM(H46:H53) -> 0 | I54: =SUM(I46:I53) -> 0 | J54: =SUM(J46:J53) -> 0 | ... AE54: =SUM(AE46:AE53) -> 0 | AF54: =sum(B54:AE54) -> 0
A55: All Bird Buddy with Solar Roof | B55: =B48+B51+B53 -> 0 | C55: =C48+C51+C53 -> 0 | D55: =D48+D51+D53 -> 0 | E55: =E48+E51+E53 -> 0 | F55: =F48+F51+F53 -> 0 | G55: =G48+G51+G53 -> 0 | H55: =H48+H51+H53 -> 0 | I55: =I48+I51+I53 -> 0 | ... AE55: =AE48+AE51+AE53 -> 0 | AF55: =sum(B55:AE55) -> 0
A57: Wall Mount - AMAZON.US | AF57: =sum(B57:AE57) -> 0
A58: Fence Mount - AMAZON.US | AF58: =sum(B58:AE58) -> 0
A59: Suet Ball Holder - AMAZON.US | AF59: =sum(B59:AE59) -> 0
A60: 3-in-1 Nutrition Set - AMAZON.US | AF60: =sum(B60:AE60) -> 0
A61: Solar Roof Single - AMAZON.US | AF61: =sum(B61:AE61) -> 0
A62: All AMAZON.US | B62: =SUM(B57:B61) -> 0 | C62: =SUM(C57:C61) -> 0 | D62: =SUM(D57:D61) -> 0 | E62: =SUM(E57:E61) -> 0 | F62: =SUM(F57:F61) -> 0 | G62: =SUM(G57:G61) -> 0 | H62: =SUM(H57:H61) -> 0 | I62: =SUM(I57:I61) -> 0 | ... AE62: =SUM(AE57:AE61) -> 0 | AF62: =sum(B62:AE62) -> 0
A64: Wall Mount - AMAZON.EU | AF64: =sum(B64:AE64) -> 0
A65: Fence Mount - AMAZON.EU | AF65: =sum(B65:AE65) -> 0
A66: Suet Ball Holder - AMAZON.EU | AF66: =sum(B66:AE66) -> 0
A67: 3-in-1 Nutrition Set - AMAZON.EU | AF67: =sum(B67:AE67) -> 0
A68: Solar Roof Single - AMAZON.EU | AF68: =sum(B68:AE68) -> 0
A69: All AMAZON.EU | B69: =SUM(B64:B68) -> 0 | C69: =SUM(C64:C68) -> 0 | D69: =SUM(D64:D68) -> 0 | E69: =SUM(E64:E68) -> 0 | F69: =SUM(F64:F68) -> 0 | G69: =SUM(G64:G68) -> 0 | H69: =SUM(H64:H68) -> 0 | I69: =SUM(I64:I68) -> 0 | ... AE69: =SUM(AE64:AE68) -> 0 | AF69: =sum(B69:AE69) -> 0
A71: Wall Mount - AMAZON (OTHER1) | AF71: =sum(B71:AE71) -> 0
A72: Fence Mount - AMAZON (OTHER1) | AF72: =sum(B72:AE72) -> 0
A73: Suet Ball Holder - AMAZON (OTHER1) | AF73: =sum(B73:AE73) -> 0
A74: 3-in-1 Nutrition Set - AMAZON (OTHER1) | AF74: =sum(B74:AE74) -> 0
A75: Solar Roof Single - AMAZON (OTHER1) | AF75: =sum(B75:AE75) -> 0
A76: All AMAZON (OTHER1) | B76: =SUM(B71:B75) -> 0 | C76: =SUM(C71:C74) -> 0 | D76: =SUM(D71:D75) -> 0 | E76: =SUM(E71:E75) -> 0 | F76: =SUM(F71:F75) -> 0 | G76: =SUM(G71:G74) -> 0 | H76: =SUM(H71:H74) -> 0 | I76: =SUM(I71:I74) -> 0 | J76: =SUM(J71:J74) -> 0 | K76: =SUM(K71:K74) -> 0 | L76: =SUM(L71:L74) -> 0 | M76: =SUM(M71:M74) -> 0 | N76: =SUM(N71:N74) -> 0 | ... V76: =SUM(V71:V74) -> 0 | W76: =SUM(W71:W75) -> 0 | X76: =SUM(X71:X74) -> 0 | Y76: =SUM(Y71:Y74) -> 0 | Z76: =SUM(Z71:Z74) -> 0 | AA76: =SUM(AA71:AA74) -> 0 | AB76: =SUM(AB71:AB74) -> 0 | AC76: =SUM(AC71:AC74) -> 0 | AD76: =SUM(AD71:AD74) -> 0 | AE76: =SUM(AE71:AE74) -> 0 | AF76: =sum(B76:AE76) -> 0
A78: Revenue by country (Gross) - Only selling in US
A79: Bird Buddy - AMAZON.US | AF79: =SUM(B79:AE79) -> 0
A80: Bird Buddy with Solar Roof - AMAZON.US | AF80: =SUM(B80:AE80) -> 0
A81: Bird Buddy - AMAZON.EU | AF81: =SUM(B81:AE81) -> 0
A82: Bird Buddy with Solar Roof - AMAZON.EU | AF82: =SUM(B82:AE82) -> 0
A83: Bird Buddy - AMAZON (OTHER1) | AF83: =SUM(B83:AE83) -> 0
A84: Bird Buddy with Solar Roof - AMAZON (OTHER1) | AF84: =SUM(B84:AE84) -> 0
A85: All Bird Buddy | B85: =B79+B81+B83 -> 0 | C85: =C79+C81+C83 -> 0 | D85: =D79+D81+D83 -> 0 | E85: =E79+E81+E83 -> 0 | F85: =F79+F81+F83 -> 0 | G85: =G79+G81+G83 -> 0 | H85: =H79+H81+H83 -> 0 | I85: =I79+I81+I83 -> 0 | ... AE85: =AE79+AE81+AE83 -> 0 | AF85: =SUM(B85:AE85) -> 0
A86: All Bird Buddy with Solar Roof | B86: =B80+B82+B84 -> 0 | C86: =C80+C82+C84 -> 0 | D86: =D80+D82+D84 -> 0 | E86: =E80+E82+E84 -> 0 | F86: =F80+F82+F84 -> 0 | G86: =G80+G82+G84 -> 0 | H86: =H80+H82+H84 -> 0 | I86: =I80+I82+I84 -> 0 | ... AE86: =AE80+AE82+AE84 -> 0 | AF86: =SUM(B86:AE86) -> 0
A88: Wall Mount - AMAZON.US | AF88: =SUM(B88:AE88) -> 0
A89: Fence Mount - AMAZON.US | AF89: =SUM(B89:AE89) -> 0
A90: Suet Ball Holder - AMAZON.US | AF90: =SUM(B90:AE90) -> 0
A91: 3-in-1 Nutrition Set - AMAZON.US | AF91: =SUM(B91:AE91) -> 0
A92: Solar Roof Single - AMAZON.US | AF92: =SUM(B92:AE92) -> 0
A93: All AMAZON.US | B93: =SUM(B88:B92) -> 0 | C93: =SUM(C88:C92) -> 0 | D93: =SUM(D88:D92) -> 0 | E93: =SUM(E88:E92) -> 0 | F93: =SUM(F88:F92) -> 0 | G93: =SUM(G88:G92) -> 0 | H93: =SUM(H88:H92) -> 0 | I93: =SUM(I88:I92) -> 0 | ... AE93: =SUM(AE88:AE92) -> 0 | AF93: =SUM(B93:AE93) -> 0
A95: Wall Mount - AMAZON.EU | AF95: =SUM(B95:AE95) -> 0
A96: Fence Mount - AMAZON.EU | AF96: =SUM(B96:AE96) -> 0
A97: Suet Ball Holder - AMAZON.EU | AF97: =SUM(B97:AE97) -> 0
A98: 3-in-1 Nutrition Set - AMAZON.EU | AF98: =SUM(B98:AE98) -> 0
A99: Solar Roof Single - AMAZON.EU | AF99: =SUM(B99:AE99) -> 0
A100: All AMAZON.EU | B100: =SUM(B95:B99) -> 0 | C100: =SUM(C95:C99) -> 0 | D100: =SUM(D95:D99) -> 0 | E100: =SUM(E95:E99) -> 0 | F100: =SUM(F95:F99) -> 0 | G100: =SUM(G95:G99) -> 0 | H100: =SUM(H95:H99) -> 0 | I100: =SUM(I95:I99) -> 0 | ... AE100: =SUM(AE95:AE99) -> 0 | AF100: =SUM(B100:AE100) -> 0
A102: Wall Mount - AMAZON (OTHER1) | AF102: =SUM(B102:AE102) -> 0
A103: Fence Mount - AMAZON (OTHER1) | AF103: =SUM(B103:AE103) -> 0
A104: Suet Ball Holder - AMAZON (OTHER1) | AF104: =SUM(B104:AE104) -> 0
A105: 3-in-1 Nutrition Set - AMAZON (OTHER1) | AF105: =SUM(B105:AE105) -> 0
A106: Solar Roof Single - AMAZON (OTHER1) | AF106: =SUM(B106:AE106) -> 0
A107: All AMAZON (OTHER1) | B107: =SUM(B102:B106) -> 0 | C107: =SUM(C102:C106) -> 0 | D107: =SUM(D102:D106) -> 0 | E107: =SUM(E102:E106) -> 0 | F107: =SUM(F102:F106) -> 0 | G107: =SUM(G102:G106) -> 0 | H107: =SUM(H102:H106) -> 0 | I107: =SUM(I102:I106) -> 0 | ... AE107: =SUM(AE102:AE106) -> 0 | AF107: =SUM(B107:AE107) -> 0
A110: Units Cancelled (Gross)
A111: SKU 1 - Blue | B111: 0 | C111: 0 | D111: 0 | E111: 0 | F111: 0 | G111: 0 | H111: 0 | I111: 0 | J111: 0 | K111: 0 | L111: 0 | M111: 0 | N111: 0 | O111: 0 | P111: 0 | Q111: 0 | R111: 0 | S111: 0 | T111: 0 | U111: 0 | V111: 0 | W111: 0 | X111: 0 | Y111: 0 | Z111: 0 | AA111: 0 | AB111: 0 | AC111: 0 | AD111: 0 | AE111: 0 | AF111: =SUM(B111:AE111) -> 0
A112: SKU 2 - Yellow | B112: 0 | C112: 0 | D112: 0 | E112: 0 | F112: 0 | G112: 0 | H112: 0 | I112: 0 | J112: 0 | K112: 0 | L112: 0 | M112: 0 | N112: 0 | O112: 0 | P112: 0 | Q112: 0 | R112: 0 | S112: 0 | T112: 0 | U112: 0 | V112: 0 | W112: 0 | X112: 0 | Y112: 0 | Z112: 0 | AA112: 0 | AB112: 0 | AC112: 0 | AD112: 0 | AE112: 0 | AF112: =SUM(B112:AE112) -> 0
A113: SKU 3 - Blue w/ Solar | B113: 0 | C113: 2 | D113: 3 | E113: 1 | F113: 0 | G113: 2 | H113: 0 | I113: 0 | J113: 3 | K113: 0 | L113: 0 | M113: 3 | N113: 0 | O113: 1 | P113: 0 | Q113: 0 | R113: 0 | S113: 0 | T113: 2 | U113: 0 | V113: 0 | W113: 1 | X113: 0 | Y113: 1 | Z113: 0 | AA113: 0 | AB113: 5 | AC113: 1 | AD113: 1 | AE113: 1 | AF113: =SUM(B113:AE113) -> 27
A114: SKU 4 - Yellow w/ Solar | B114: 0 | C114: 0 | D114: 0 | E114: 0 | F114: 0 | G114: 0 | H114: 0 | I114: 0 | J114: 0 | K114: 0 | L114: 0 | M114: 0 | N114: 0 | O114: 0 | P114: 0 | Q114: 0 | R114: 0 | S114: 0 | T114: 0 | U114: 0 | V114: 0 | W114: 0 | X114: 0 | Y114: 0 | Z114: 0 | AA114: 0 | AB114: 0 | AC114: 0 | AD114: 0 | AE114: 0 | AF114: =SUM(B114:AE114) -> 0
A115: SUM (SKU 1 + SKU 2) | B115: =B111+B112 -> 0 | C115: =C111+C112 -> 0 | D115: =D111+D112 -> 0 | E115: =E111+E112 -> 0 | F115: =F111+F112 -> 0 | G115: =G111+G112 -> 0 | H115: =H111+H112 -> 0 | I115: =I111+I112 -> 0 | ... AE115: =AE111+AE112 -> 0 | AF115: =SUM(B115:AE115) -> 0
A116: SUM (SKU 3 + SKU 4) | B116: =B113+B114 -> 0 | C116: =C113+C114 -> 2 | D116: =D113+D114 -> 3 | E116: =E113+E114 -> 1 | F116: =F113+F114 -> 0 | G116: =G113+G114 -> 2 | H116: =H113+H114 -> 0 | I116: =I113+I114 -> 0 | ... AE116: =AE113+AE114 -> 1 | AF116: =SUM(B116:AE116) -> 27
A118: Wall Mount | B118: 0 | C118: 0 | D118: 0 | E118: 0 | F118: 0 | G118: 0 | H118: 0 | I118: 0 | J118: 0 | K118: 0 | L118: 0 | M118: 0 | N118: 0 | O118: 0 | P118: 0 | Q118: 0 | R118: 0 | S118: 0 | T118: 0 | U118: 0 | V118: 0 | W118: 0 | X118: 0 | Y118: 0 | Z118: 0 | AA118: 0 | AB118: 0 | AC118: 0 | AD118: 0 | AE118: 0 | AF118: =SUM(B118:AE118) -> 0
A119: Suet Ball Holder | AF119: =SUM(B119:AE119) -> 0
...

Sheet App - P&L
A1: SEPTEMBER | B1: 45170 | C1: 45171 | D1: 45172 | E1: 45173 | F1: 45174 | G1: 45175 | H1: 45176 | I1: 45177 | J1: 45178 | K1: 45179 | L1: 45180 | M1: 45181 | N1: 45182 | O1: 45183 | P1: 45184 | Q1: 45185 | R1: 45186 | S1: 45187 | T1: 45188 | U1: 45189 | V1: 45190 | W1: 45191 | X1: 45192 | Y1: 45193 | Z1: 45194 | AA1: 45195 | AB1: 45196 | AC1: 45197 | AD1: 45198 | AE1: 45199
A2: DAY | B2: FRI | C2: SAT | D2: SUN | E2: MON | F2: TUE | G2: WED | H2: THU | I2: FRI | J2: SAT | K2: SUN | L2: MON | M2: TUE | N2: WED | O2: THU | P2: FRI | Q2: SAT | R2: SUN | S2: MON | T2: TUE | U2: WED | V2: THU | W2: FRI | X2: SAT | Y2: SUN | Z2: MON | AA2: TUE | AB2: WED | AC2: THU | AD2: FRI | AE2: SAT
A4: Gross Revenue
A5: Apple Store Sales | B5: 0 | C5: 0 | D5: 0 | E5: 0 | F5: 0 | G5: 0 | H5: 0 | I5: 0 | J5: 0 | K5: 0 | L5: 0 | M5: 0 | N5: 0 | O5: 0 | P5: 0 | Q5: 0 | R5: 0 | S5: 5748.6935 | T5: 6580.5519 | U5: 4058.2307 | V5: 3177.1625 | W5: 2122.4201 | X5: 2216.3139 | Y5: 2009.1927 | Z5: 1405.2564 | AA5: 1441.6047 | AB5: 965.97582 | AC5: 1057.4882 | AD5: 5026.6341 | AE5: 4807.3088 | AF5: =sum(B5:AE5) -> 40616.833
A6: - Yearly Subscription | B6: 0 | C6: 0 | D6: 0 | E6: 0 | F6: 0 | G6: 0 | H6: 0 | I6: 0 | J6: 0 | K6: 0 | L6: 0 | M6: 0 | N6: 0 | O6: 0 | P6: 0 | Q6: 0 | R6: 0 | S6: 5748.6935 | T6: 6580.5519 | U6: 4058.2307 | V6: 3177.1625 | W6: 2122.4201 | X6: 2216.3139 | Y6: 2009.1927 | Z6: 1361.2228 | AA6: 1348.0112 | AB6: 934.39645 | AC6: 1026.3088 | AD6: 5005.441 | AE6: 4783.1257 | AF6: =sum(B6:AE6) -> 40371.071
A7: - Monthly Subscription | B7: 0 | C7: 0 | D7: 0 | E7: 0 | F7: 0 | G7: 0 | H7: 0 | I7: 0 | J7: 0 | K7: 0 | L7: 0 | M7: 0 | N7: 0 | O7: 0 | P7: 0 | Q7: 0 | R7: 0 | S7: 0 | T7: 0 | U7: 0 | V7: 0 | W7: 0 | X7: 0 | Y7: 0 | Z7: 44.033621 | AA7: 93.59341 | AB7: 31.579364 | AC7: 31.179341 | AD7: 21.19312 | AE7: 24.18312 | AF7: =sum(B7:AE7) -> 245.76198
A8: Google Store Sales | B8: 0 | C8: 0 | D8: 0 | E8: 0 | F8: 0 | G8: 3.53 | H8: 3.52 | I8: 0 | J8: 0 | K8: 0 | L8: 0 | M8: 0 | N8: 0 | O8: 0 | P8: 35.16 | Q8: 15.99 | R8: 35.15 | S8: 2612.31 | T8: 1993.73 | U8: 1418.95 | V8: 1165.15 | W8: 829.06 | X8: 745.44 | Y8: 626.12 | Z8: 497.57 | AA8: 589.46 | AB8: 457.86 | AC8: 360.17 | AD8: 2072.5 | AE8: 2861.7 | AF8: =sum(B8:AE8) -> 16323.37
A9: - Yearly Subscription | B9: 0 | C9: 0 | D9: 0 | E9: 0 | F9: 0 | G9: 0 | H9: 0 | I9: 0 | J9: 0 | K9: 0 | L9: 0 | M9: 0 | N9: 0 | O9: 0 | P9: 31.97 | Q9: 15.99 | R9: 31.96 | S9: 2602.74 | T9: 1993.73 | U9: 1412.75 | V9: 1165.15 | W9: 829.06 | X9: 745.44 | Y9: 626.12 | Z9: 491.4 | AA9: 570.4 | AB9: 448.25 | AC9: 353.64 | AD9: 2066.35 | AE9: 2852.07 | AF9: =sum(B9:AE9) -> 16237.02
A10: - Monthly Subscription | B10: 0 | C10: 0 | D10: 0 | E10: 0 | F10: 0 | G10: 3.53 | H10: 3.52 | I10: 0 | J10: 0 | K10: 0 | L10: 0 | M10: 0 | N10: 0 | O10: 0 | P10: 3.19 | Q10: 0 | R10: 3.19 | S10: 9.57 | T10: 0 | U10: 6.2 | V10: 0 | W10: 0 | X10: 0 | Y10: 0 | Z10: 6.17 | AA10: 19.06 | AB10: 9.61 | AC10: 6.53 | AD10: 6.15 | AE10: 9.63 | AF10: =sum(B10:AE10) -> 86.35
A11: SUM | B11: =sum(B5+B8) -> 0 | C11: =sum(C5+C8) -> 0 | D11: =sum(D5+D8) -> 0 | E11: =sum(E5+E8) -> 0 | F11: =sum(F5+F8) -> 0 | G11: =sum(G5+G8) -> 3.53 | H11: =sum(H5+H8) -> 3.52 | I11: =sum(I5+I8) -> 0 | ... AE11: =sum(AE5+AE8) -> 7669.0088 | AF11: =sum(B11:AE11) -> 56940.203
A13: Gross Orders
A14: Apple Store Orders | B14: =sum(B15:B16) -> 0 | C14: =sum(C15:C16) -> 0 | D14: =sum(D15:D16) -> 0 | E14: =sum(E15:E16) -> 0 | F14: =sum(F15:F16) -> 0 | G14: =sum(G15:G16) -> 0 | H14: =sum(H15:H16) -> 0 | I14: =sum(I15:I16) -> 0 | ... AE14: =sum(AE15:AE16) -> 319 | AF14: =sum(B14:AE14) -> 2719
A15: - Yearly Subscription | B15: 0 | C15: 0 | D15: 0 | E15: 0 | F15: 0 | G15: 0 | H15: 0 | I15: 0 | J15: 0 | K15: 0 | L15: 0 | M15: 0 | N15: 0 | O15: 0 | P15: 0 | Q15: 0 | R15: 0 | S15: 372 | T15: 431 | U15: 265 | V15: 207 | W15: 141 | X15: 145 | Y15: 132 | Z15: 89 | AA15: 86 | AB15: 62 | AC15: 67 | AD15: 331 | AE15: 311 | AF15: =sum(B15:AE15) -> 2639
A16: - Monthly Subscription | B16: 0 | C16: 0 | D16: 0 | E16: 0 | F16: 0 | G16: 0 | H16: 0 | I16: 0 | J16: 0 | K16: 0 | L16: 0 | M16: 0 | N16: 0 | O16: 0 | P16: 0 | Q16: 0 | R16: 0 | S16: 0 | T16: 0 | U16: 0 | V16: 0 | W16: 0 | X16: 0 | Y16: 0 | Z16: 14 | AA16: 31 | AB16: 10 | AC16: 10 | AD16: 7 | AE16: 8 | AF16: =sum(B16:AE16) -> 80
A17: Google Store Orders | B17: =sum(B18:B19) -> 0 | C17: =sum(C18:C19) -> 0 | D17: =sum(D18:D19) -> 0 | E17: =sum(E18:E19) -> 0 | F17: =sum(F18:F19) -> 0 | G17: =sum(G18:G19) -> 1 | H17: =sum(H18:H19) -> 1 | I17: =sum(I18:I19) -> 0 | ... AE17: =sum(AE18:AE19) -> 182 | AF17: =sum(B17:AE17) -> 1069
A18: - Yearly Subscription | B18: 0 | C18: 0 | D18: 0 | E18: 0 | F18: 0 | G18: 0 | H18: 0 | I18: 0 | J18: 0 | K18: 0 | L18: 0 | M18: 0 | N18: 0 | O18: 0 | P18: 1 | Q18: 1 | R18: 1 | S18: 145 | T18: 157 | U18: 98 | V18: 74 | W18: 56 | X18: 46 | Y18: 39 | Z18: 31 | AA18: 35 | AB18: 28 | AC18: 22 | AD18: 129 | AE18: 179 | AF18: =sum(B18:AE18) -> 1042
A19: - Monthly Subscription | B19: 0 | C19: 0 | D19: 0 | E19: 0 | F19: 0 | G19: 1 | H19: 1 | I19: 0 | J19: 0 | K19: 0 | L19: 0 | M19: 0 | N19: 0 | O19: 0 | P19: 1 | Q19: 0 | R19: 1 | S19: 3 | T19: 0 | U19: 2 | V19: 0 | W19: 0 | X19: 0 | Y19: 0 | Z19: 2 | AA19: 6 | AB19: 3 | AC19: 2 | AD19: 2 | AE19: 3 | AF19: =sum(B19:AE19) -> 27
A20: SUM | B20: =sum(B14+B17) -> 0 | C20: =sum(C14+C17) -> 0 | D20: =sum(D14+D17) -> 0 | E20: =sum(E14+E17) -> 0 | F20: =sum(F14+F17) -> 0 | G20: =sum(G14+G17) -> 1 | H20: =sum(H14+H17) -> 1 | I20: =sum(I14+I17) -> 0 | ... AE20: =sum(AE14+AE17) -> 501 | AF20: =sum(B20:AE20) -> 3788
A21: - Yearly Subscription | B21: =B15+B18 -> 0 | C21: =C15+C18 -> 0 | D21: =D15+D18 -> 0 | E21: =E15+E18 -> 0 | F21: =F15+F18 -> 0 | G21: =G15+G18 -> 0 | H21: =H15+H18 -> 0 | I21: =I15+I18 -> 0 | ... AE21: =AE15+AE18 -> 490 | AF21: =sum(B21:AE21) -> 3681
A22: - Monthly Subscription | B22: =B16+B19 -> 0 | C22: =C16+C19 -> 0 | D22: =D16+D19 -> 0 | E22: =E16+E19 -> 0 | F22: =F16+F19 -> 0 | G22: =G16+G19 -> 1 | H22: =H16+H19 -> 1 | I22: =I16+I19 -> 0 | ... AE22: =AE16+AE19 -> 11 | AF22: =sum(B22:AE22) -> 107
A24: Refunded Revenue
A25: Apple Store Sales | B25: =sum(B26:B27) -> 0 | C25: =sum(C26:C27) -> 0 | D25: =sum(D26:D27) -> 0 | E25: =sum(E26:E27) -> 0 | F25: =sum(F26:F27) -> 0 | G25: =sum(G26:G27) -> 0 | H25: =sum(H26:H27) -> 0 | I25: =sum(I26:I27) -> 0 | ... AE25: =sum(AE26:AE27) -> 14.99 | AF25: =sum(B25:AE25) -> 88.17
A26: - Yearly Subscription | B26: 0 | C26: 0 | D26: 0 | E26: 0 | F26: 0 | G26: 0 | H26: 0 | I26: 0 | J26: 0 | K26: 0 | L26: 0 | M26: 0 | N26: 0 | O26: 0 | P26: 0 | Q26: 0 | R26: 0 | S26: 0 | T26: 14.99 | U26: 0 | V26: 0 | W26: 29.72 | X26: 0 | Y26: 0 | Z26: 0 | AA26: 0 | AB26: 28.47 | AC26: 0 | AD26: 0 | AE26: 14.99 | AF26: =sum(B26:AE26) -> 88.17
A27: - Monthly Subscription | B27: 0 | C27: 0 | D27: 0 | E27: 0 | F27: 0 | G27: 0 | H27: 0 | I27: 0 | J27: 0 | K27: 0 | L27: 0 | M27: 0 | N27: 0 | O27: 0 | P27: 0 | Q27: 0 | R27: 0 | S27: 0 | T27: 0 | U27: 0 | V27: 0 | W27: 0 | X27: 0 | Y27: 0 | Z27: 0 | AA27: 0 | AB27: 0 | AC27: 0 | AD27: 0 | AE27: 0 | AF27: =sum(B27:AE27) -> 0
A28: Google Store Sales | B28: =sum(B29:B30) -> 0 | C28: =sum(C29:C30) -> 0 | D28: =sum(D29:D30) -> 0 | E28: =sum(E29:E30) -> 0 | F28: =sum(F29:F30) -> 0 | G28: =sum(G29:G30) -> 0 | H28: =sum(H29:H30) -> 0 | I28: =sum(I29:I30) -> 0 | ... AE28: =sum(AE29:AE30) -> 0 | AF28: =sum(B28:AE28) -> 359.76
A29: - Yearly Subscription | B29: 0 | C29: 0 | D29: 0 | E29: 0 | F29: 0 | G29: 0 | H29: 0 | I29: 0 | J29: 0 | K29: 0 | L29: 0 | M29: 0 | N29: 0 | O29: 0 | P29: 0 | Q29: 14.99 | R29: 0 | S29: 0 | T29: =21*14.99 -> 314.79 | U29: 0 | V29: 14.99 | W29: 14.99 | X29: 0 | Y29: 0 | Z29: 0 | AA29: 0 | AB29: 0 | AC29: 0 | AD29: 0 | AE29: 0 | AF29: =sum(B29:AE29) -> 359.76
A30: - Monthly Subscription | B30: 0 | C30: 0 | D30: 0 | E30: 0 | F30: 0 | G30: 0 | H30: 0 | I30: 0 | J30: 0 | K30: 0 | L30: 0 | M30: 0 | N30: 0 | O30: 0 | P30: 0 | Q30: 0 | R30: 0 | S30: 0 | T30: 0 | U30: 0 | V30: 0 | W30: 0 | X30: 0 | Y30: 0 | Z30: 0 | AA30: 0 | AB30: 0 | AC30: 0 | AD30: 0 | AE30: 0 | AF30: =sum(B30:AE30) -> 0
A31: SUM | B31: =B25+B28 -> 0 | C31: =C25+C28 -> 0 | D31: =D25+D28 -> 0 | E31: =E25+E28 -> 0 | F31: =F25+F28 -> 0 | G31: =G25+G28 -> 0 | H31: =H25+H28 -> 0 | I31: =I25+I28 -> 0 | ... AE31: =AE25+AE28 -> 14.99 | AF31: =sum(B31:AE31) -> 447.93
A33: Refunded Orders
A34: Apple Store orders | B34: =sum(B35:B36) -> 0 | C34: =sum(C35:C36) -> 0 | D34: =sum(D35:D36) -> 0 | E34: =sum(E35:E36) -> 0 | F34: =sum(F35:F36) -> 0 | G34: =sum(G35:G36) -> 0 | H34: =sum(H35:H36) -> 0 | I34: =sum(I35:I36) -> 0 | ... AE34: =sum(AE35:AE36) -> 1 | AF34: =sum(B34:AE34) -> 5
A35: - Yearly Subscription | B35: 0 | C35: 0 | D35: 0 | E35: 0 | F35: 0 | G35: 0 | H35: 0 | I35: 0 | J35: 0 | K35: 0 | L35: 0 | M35: 0 | N35: 0 | O35: 0 | P35: 0 | Q35: 0 | R35: 0 | S35: 0 | T35: 1 | U35: 0 | V35: 0 | W35: 2 | X35: 0 | Y35: 0 | Z35: 0 | AA35: 0 | AB35: 1 | AC35: 0 | AD35: 0 | AE35: 1
A36: - Monthly Subscription | B36: 0 | C36: 0 | D36: 0 | E36: 0 | F36: 0 | G36: 0 | H36: 0 | I36: 0 | J36: 0 | K36: 0 | L36: 0 | M36: 0 | N36: 0 | O36: 0 | P36: 0 | Q36: 0 | R36: 0 | S36: 0 | T36: 0 | U36: 0 | V36: 0 | W36: 0 | X36: 0 | Y36: 0 | Z36: 0 | AA36: 0 | AB36: 0 | AC36: 0 | AD36: 0 | AE36: 0
A37: Google Store orders | B37: =sum(B38:B39) -> 0 | C37: =sum(C38:C39) -> 0 | D37: =sum(D38:D39) -> 0 | E37: =sum(E38:E39) -> 0 | F37: =sum(F38:F39) -> 0 | G37: =sum(G38:G39) -> 0 | H37: =sum(H38:H39) -> 0 | I37: =sum(I38:I39) -> 0 | ... AE37: =sum(AE38:AE39) -> 0 | AF37: =sum(B37:AE37) -> 24
A38: - Yearly Subscription | B38: 0 | C38: 0 | D38: 0 | E38: 0 | F38: 0 | G38: 0 | H38: 0 | I38: 0 | J38: 0 | K38: 0 | L38: 0 | M38: 0 | N38: 0 | O38: 0 | P38: 0 | Q38: 1 | R38: 0 | S38: 0 | T38: 21 | U38: 0 | V38: 1 | W38: 1 | X38: 0 | Y38: 0 | Z38: 0 | AA38: 0 | AB38: 0 | AC38: 0 | AD38: 0 | AE38: 0
A39: - Monthly Subscription | B39: 0 | C39: 0 | D39: 0 | E39: 0 | F39: 0 | G39: 0 | H39: 0 | I39: 0 | J39: 0 | K39: 0 | L39: 0 | M39: 0 | N39: 0 | O39: 0 | P39: 0 | Q39: 0 | R39: 0 | S39: 0 | T39: 0 | U39: 0 | V39: 0 | W39: 0 | X39: 0 | Y39: 0 | Z39: 0 | AA39: 0 | AB39: 0 | AC39: 0 | AD39: 0 | AE39: 0
A40: SUM | B40: =B34+B37 -> 0 | C40: =C34+C37 -> 0 | D40: =D34+D37 -> 0 | E40: =E34+E37 -> 0 | F40: =F34+F37 -> 0 | G40: =G34+G37 -> 0 | H40: =H34+H37 -> 0 | I40: =I34+I37 -> 0 | ... AE40: =AE34+AE37 -> 1 | AF40: =sum(B40:AE40) -> 29
A42: Net Revenue
A43: Apple Store | B43: =B5-B25 -> 0 | C43: =C5-C25 -> 0 | D43: =D5-D25 -> 0 | E43: =E5-E25 -> 0 | F43: =F5-F25 -> 0 | G43: =G5-G25 -> 0 | H43: =H5-H25 -> 0 | I43: =I5-I25 -> 0 | ... AE43: =AE5-AE25 -> 4792.3188 | AF43: =sum(B43:AE43) -> 40528.663
A44: - Yearly Subscription | B44: =B6-B26 -> 0 | C44: =C6-C26 -> 0 | D44: =D6-D26 -> 0 | E44: =E6-E26 -> 0 | F44: =F6-F26 -> 0 | G44: =G6-G26 -> 0 | H44: =H6-H26 -> 0 | I44: =I6-I26 -> 0 | ... AE44: =AE6-AE26 -> 4768.1357 | AF44: =sum(B44:AE44) -> 40282.901
A45: - Monthly Subscription | B45: =B7-B27 -> 0 | C45: =C7-C27 -> 0 | D45: =D7-D27 -> 0 | E45: =E7-E27 -> 0 | F45: =F7-F27 -> 0 | G45: =G7-G27 -> 0 | H45: =H7-H27 -> 0 | I45: =I7-I27 -> 0 | ... AE45: =AE7-AE27 -> 24.18312 | AF45: =sum(B45:AE45) -> 245.76198
A46: Google Store | B46: =B8-B28 -> 0 | C46: =C8-C28 -> 0 | D46: =D8-D28 -> 0 | E46: =E8-E28 -> 0 | F46: =F8-F28 -> 0 | G46: =G8-G28 -> 3.53 | H46: =H8-H28 -> 3.52 | I46: =I8-I28 -> 0 | ... AE46: =AE8-AE28 -> 2861.7 | AF46: =sum(B46:AE46) -> 15963.61
A47: - Yearly Subscription | B47: =B9-B29 -> 0 | C47: =C9-C29 -> 0 | D47: =D9-D29 -> 0 | E47: =E9-E29 -> 0 | F47: =F9-F29 -> 0 | G47: =G9-G29 -> 0 | H47: =H9-H29 -> 0 | I47: =I9-I29 -> 0 | ... AE47: =AE9-AE29 -> 2852.07 | AF47: =sum(B47:AE47) -> 15877.26
A48: - Monthly Subscription | B48: =B10-B30 -> 0 | C48: =C10-C30 -> 0 | D48: =D10-D30 -> 0 | E48: =E10-E30 -> 0 | F48: =F10-F30 -> 0 | G48: =G10-G30 -> 3.53 | H48: =H10-H30 -> 3.52 | I48: =I10-I30 -> 0 | ... AE48: =AE10-AE30 -> 9.63 | AF48: =sum(B48:AE48) -> 86.35
A49: SUM | B49: =B43+B46 -> 0 | C49: =C43+C46 -> 0 | D49: =D43+D46 -> 0 | E49: =E43+E46 -> 0 | F49: =F43+F46 -> 0 | G49: =G43+G46 -> 3.53 | H49: =H43+H46 -> 3.52 | I49: =I43+I46 -> 0 | ... AE49: =AE43+AE46 -> 7654.0188 | AF49: =sum(B49:AE49) -> 56492.273
A51: Net Orders
A52: Apple Store | B52: =B14-B34 -> 0 | C52: =C14-C34 -> 0 | D52: =D14-D34 -> 0 | E52: =E14-E34 -> 0 | F52: =F14-F34 -> 0 | G52: =G14-G34 -> 0 | H52: =H14-H34 -> 0 | I52: =I14-I34 -> 0 | ... AE52: =AE14-AE34 -> 318 | AF52: =sum(B52:AE52) -> 2714
A53: - Yearly Subscription | B53: =B15-B35 -> 0 | C53: =C15-C35 -> 0 | D53: =D15-D35 -> 0 | E53: =E15-E35 -> 0 | F53: =F15-F35 -> 0 | G53: =G15-G35 -> 0 | H53: =H15-H35 -> 0 | I53: =I15-I35 -> 0 | ... AE53: =AE15-AE35 -> 310 | AF53: =sum(B53:AE53) -> 2634
A54: - Monthly Subscription | B54: =B16-B36 -> 0 | C54: =C16-C36 -> 0 | D54: =D16-D36 -> 0 | E54: =E16-E36 -> 0 | F54: =F16-F36 -> 0 | G54: =G16-G36 -> 0 | H54: =H16-H36 -> 0 | I54: =I16-I36 -> 0 | ... AE54: =AE16-AE36 -> 8 | AF54: =sum(B54:AE54) -> 80
A55: Google Store | B55: =B17-B37 -> 0 | C55: =C17-C37 -> 0 | D55: =D17-D37 -> 0 | E55: =E17-E37 -> 0 | F55: =F17-F37 -> 0 | G55: =G17-G37 -> 1 | H55: =H17-H37 -> 1 | I55: =I17-I37 -> 0 | ... AE55: =AE17-AE37 -> 182 | AF55: =sum(B55:AE55) -> 1045
A56: - Yearly Subscription | B56: =B18-B38 -> 0 | C56: =C18-C38 -> 0 | D56: =D18-D38 -> 0 | E56: =E18-E38 -> 0 | F56: =F18-F38 -> 0 | G56: =G18-G38 -> 0 | H56: =H18-H38 -> 0 | I56: =I18-I38 -> 0 | ... AE56: =AE18-AE38 -> 179 | AF56: =sum(B56:AE56) -> 1018
A57: - Monthly Subscription | B57: =B19-B39 -> 0 | C57: =C19-C39 -> 0 | D57: =D19-D39 -> 0 | E57: =E19-E39 -> 0 | F57: =F19-F39 -> 0 | G57: =G19-G39 -> 1 | H57: =H19-H39 -> 1 | I57: =I19-I39 -> 0 | ... AE57: =AE19-AE39 -> 3 | AF57: =sum(B57:AE57) -> 27
A58: SUM | B58: =B52+B55 -> 0 | C58: =C52+C55 -> 0 | D58: =D52+D55 -> 0 | E58: =E52+E55 -> 0 | F58: =F52+F55 -> 0 | G58: =G52+G55 -> 1 | H58: =H52+H55 -> 1 | I58: =I52+I55 -> 0 | ... AE58: =AE52+AE55 -> 500 | AF58: =sum(B58:AE58) -> 3759
A62: Commision Fees & Taxes
A63: Estimated Apple Store Commision Fee (30%) --> check again after 1. mil. | B63: =B5*0.3 -> 0 | C63: =C5*0.3 -> 0 | D63: =D5*0.3 -> 0 | E63: =E5*0.3 -> 0 | F63: =F5*0.3 -> 0 | G63: =G5*0.3 -> 0 | H63: =H5*0.3 -> 0 | I63: =I5*0.3 -> 0 | ... AE63: =AE5*0.3 -> 1442.1926 | AF63: =SUM(B63:AE63) -> 12185.05
A64: Estimated Apple Store Taxes | B64: 0 | C64: 0 | D64: 0 | E64: 0 | F64: 0 | G64: 0 | H64: 0 | I64: 0 | J64: 0 | K64: 0 | L64: 0 | M64: 0 | N64: 0 | O64: 0 | P64: 0 | Q64: 12.12 | R64: 0 | S64: 152.44 | T64: 127.28 | U64: 80.86 | V64: 50.36 | W64: 31.12 | X64: 35.52 | Y64: 26.45 | Z64: 32.8 | AA64: 29.38 | AB64: 17.18 | AC64: 23.21 | AD64: 42.67 | AE64: 132.83 | AF64: =SUM(B64:AE64) -> 794.22
A65: Estimated Google Store Commision Fee (15%) --> check again after 1. mil. | B65: =B8*0.15 -> 0 | C65: =C8*0.15 -> 0 | D65: =D8*0.15 -> 0 | E65: =E8*0.15 -> 0 | F65: =F8*0.15 -> 0 | G65: =G8*0.15 -> 0.5295 | H65: =H8*0.15 -> 0.528 | I65: =I8*0.15 -> 0 | ... AE65: =AE8*0.15 -> 429.255 | AF65: =SUM(B65:AE65) -> 2448.5055
A66: Estimated Google Store Taxes | B66: 0 | C66: 0 | D66: 0 | E66: 0 | F66: 0 | G66: 0.64 | H66: 0.64 | I66: 0 | J66: 0 | K66: 0 | L66: 0 | M66: 0 | N66: 0 | O66: 0 | P66: 0.57 | Q66: 3.27 | R66: 0.58 | S66: 131.5 | T66: 95.03 | U66: 45.24 | V66: 60.6 | W66: 33.15 | X66: 52.05 | Y66: 39.21 | Z66: 27.35 | AA66: 28.43 | AB66: 16.38 | AC66: 14.35 | AD66: 61.11 | AE66: 120.35 | AF66: =SUM(B66:AE66) -> 730.45
A67: Estimated SUM Store Commision Fees | B67: =B63+B65 -> 0 | C67: =C63+C65 -> 0 | D67: =D63+D65 -> 0 | E67: =E63+E65 -> 0 | F67: =F63+F65 -> 0 | G67: =G63+G65 -> 0.5295 | H67: =H63+H65 -> 0.528 | I67: =I63+I65 -> 0 | ... AE67: =AE63+AE65 -> 1871.4476 | AF67: =SUM(B67:AE67) -> 14633.555
A68: Estimated SUM Store Taxes | B68: =B64+B66 -> 0 | C68: =C64+C66 -> 0 | D68: =D64+D66 -> 0 | E68: =E64+E66 -> 0 | F68: =F64+F66 -> 0 | G68: =G64+G66 -> 0.64 | H68: =H64+H66 -> 0.64 | I68: =I64+I66 -> 0 | ... AE68: =AE64+AE66 -> 253.18 | AF68: =SUM(B68:AE68) -> 1524.67
A70: Advertising
A71: Meta Spend | B71: =Summary!B79 -> 0.7567197 | C71: =Summary!C79 -> 0.4127562 | D71: =Summary!D79 -> 0 | E71: =Summary!E79 -> 0.44715255 | F71: =Summary!F79 -> 1.0318905 | G71: =Summary!G79 -> 0.60766885 | H71: =Summary!H79 -> 0 | I71: =Summary!I79 -> 0 | ... AE71: =Summary!AE79 -> 54.793386 | AF71: =SUM(B71:AE71) -> 437.80821
A72: Apple Spend | B72: =Summary!B80 -> 0 | C72: =Summary!C80 -> 0 | D72: =Summary!D80 -> 0 | E72: =Summary!E80 -> 0 | F72: =Summary!F80 -> 0 | G72: =Summary!G80 -> 0 | H72: =Summary!H80 -> 0 | I72: =Summary!I80 -> 0 | ... AE72: =Summary!AE80 -> 35.18 | AF72: =SUM(B72:AE72) -> 286.77
A73: Google Spend | B73: =Summary!B81 -> 0 | C73: =Summary!C81 -> 0 | D73: =Summary!D81 -> 0 | E73: =Summary!E81 -> 0 | F73: =Summary!F81 -> 0 | G73: =Summary!G81 -> 0 | H73: =Summary!H81 -> 0 | I73: =Summary!I81 -> 0 | ... AE73: =Summary!AE81 -> 0 | AF73: =SUM(B73:AE73) -> 0
A74: SUM | B74: =SUM(B71:B73) -> 0.7567197 | C74: =SUM(C71:C73) -> 0.4127562 | D74: =SUM(D71:D73) -> 0 | E74: =SUM(E71:E73) -> 0.44715255 | F74: =SUM(F71:F73) -> 1.0318905 | G74: =SUM(G71:G73) -> 0.60766885 | H74: =SUM(H71:H73) -> 0 | I74: =SUM(I71:I73) -> 0 | ... AE74: =SUM(AE71:AE73) -> 89.973386
A76: Estimated Subscription Profit
A77: - Estimated Apple Store profit | B77: =B43-B63-B64-B72-(B71*'DATA - P&L'!$I$18) -> 0 | C77: =C43-C63-C64-C72-(C71*'DATA - P&L'!$I$18) -> 0 | D77: =D43-D63-D64-D72-(D71*'DATA - P&L'!$I$18) -> 0 | E77: =E43-E63-E64-E72-(E71*'DATA - P&L'!$I$18) -> 0 | F77: =F43-F63-F64-F72-(F71*'DATA - P&L'!$I$18) -> 0 | G77: =G43-G63-G64-G72-(G71*'DATA - P&L'!$I$18) -> 0 | H77: =H43-H63-H64-H72-(H71*'DATA - P&L'!$I$18) -> 0 | I77: =I43-I63-I64-I72-(I71*'DATA - P&L'!$I$18) -> 0 | ... AE77: =AE43-AE63-AE64-AE72-(AE71*'DATA - P&L'!$I$18) -> 3182.1161 | AF77: =sum(B77:AE77) -> 27262.623
A78: - Estimated Google Store profit | B78: =B46-B65-B66-B73-(B71*'DATA - P&L'!$I$19) -> 0 | C78: =C46-C65-C66-C73-(C71*'DATA - P&L'!$I$19) -> 0 | D78: =D46-D65-D66-D73-(D71*'DATA - P&L'!$I$19) -> 0 | E78: =E46-E65-E66-E73-(E71*'DATA - P&L'!$I$19) -> 0 | F78: =F46-F65-F66-F73-(F71*'DATA - P&L'!$I$19) -> 0 | G78: =G46-G65-G66-G73-(G71*'DATA - P&L'!$I$19) -> 2.3605 | H78: =H46-H65-H66-H73-(H71*'DATA - P&L'!$I$19) -> 2.352 | I78: =I46-I65-I66-I73-(I71*'DATA - P&L'!$I$19) -> 0 | ... AE78: =AE46-AE65-AE66-AE73-(AE71*'DATA - P&L'!$I$19) -> 2312.095 | AF78: =sum(B78:AE78) -> 12784.655
A79: Estimated SUM Profit | B79: =sum(B77:B78) -> 0 | C79: =sum(C77:C78) -> 0 | D79: =sum(D77:D78) -> 0 | E79: =sum(E77:E78) -> 0 | F79: =sum(F77:F78) -> 0 | G79: =sum(G77:G78) -> 2.3605 | H79: =sum(H77:H78) -> 2.352 | I79: =sum(I77:I78) -> 0 | ... AE79: =sum(AE77:AE78) -> 5494.2111 | AF79: =sum(B79:AE79) -> 40047.278
A82: Gross Revenue
A83: =SUM(B11:AE11) -> 56940.203
A84: Gross Sales Profit
A85: =SUM(B79:AE79) -> 40047.278
A86: Gross Sales Margin
A87: =A85/A83 -> 0.70332165
A89: For summary
A90: Google | B90: =B8-B65-B66 -> 0 | C90: =C8-C65-C66 -> 0 | D90: =D8-D65-D66 -> 0 | E90: =E8-E65-E66 -> 0 | F90: =F8-F65-F66 -> 0 | G90: =G8-G65-G66 -> 2.3605 | H90: =H8-H65-H66 -> 2.352 | I90: =I8-I65-I66 -> 0 | ... AE90: =AE8-AE65-AE66 -> 2312.095
A91: Apple | B91: =B5-B63-B64 -> 0 | C91: =C5-C63-C64 -> 0 | D91: =D5-D63-D64 -> 0 | E91: =E5-E63-E64 -> 0 | F91: =F5-F63-F64 -> 0 | G91: =G5-G63-G64 -> 0 | H91: =H5-H63-H64 -> 0 | I91: =I5-I63-I64 -> 0 | ... AE91: =AE5-AE63-AE64 -> 3232.2861

Sheet Digital Marketplaces
A1: SEPTEMBER | B1: 45170 | C1: 45171 | D1: 45172 | E1: 45173 | F1: 45174 | G1: 45175 | H1: 45176 | I1: 45177 | J1: 45178 | K1: 45179 | L1: 45180 | M1: 45181 | N1: 45182 | O1: 45183 | P1: 45184 | Q1: 45185 | R1: 45186 | S1: 45187 | T1: 45188 | U1: 45189 | V1: 45190 | W1: 45191 | X1: 45192 | Y1: 45193 | Z1: 45194 | AA1: 45195 | AB1: 45196 | AC1: 45197 | AD1: 45198 | AE1: 45199
A2: DAY | B2: MON | C2: TUE | D2: WED | E2: THU | F2: FRI | G2: SAT | H2: SUN | I2: MON | J2: TUE | K2: WED | L2: THU | M2: FRI | N2: SAT | O2: SUN | P2: MON | Q2: TUE | R2: WED | S2: THU | T2: FRI | U2: SAT | V2: SUN | W2: MON | X2: TUE | Y2: WED | Z2: THU | AA2: FRI | AB2: SAT | AC2: SUN | AD2: MON | AE2: TUE
A3: Rachio (Shopify)
A4: Revenue | B4: =Summary!B22 -> 0 | C4: =Summary!C22 -> 0 | D4: =Summary!D22 -> 0 | E4: =Summary!E22 -> 0 | F4: =Summary!F22 -> 0 | G4: =Summary!G22 -> 0 | H4: =Summary!H22 -> 0 | I4: =Summary!I22 -> 0 | ... AE4: =Summary!AE22 -> 1039 | AF4: =sum(B4:AE4) -> 15033.33
A5: Breakdown
A6: - Tax | B6: =Summary!B24 | C6: =Summary!C24 | D6: =Summary!D24 | E6: =Summary!E24 | F6: =Summary!F24 | G6: =Summary!G24 | H6: =Summary!H24 | I6: =Summary!I24 | ... AE6: =Summary!AE24 | AF6: =sum(B6:AE6) -> 0
A7: - Shipping | B7: =Summary!B25 -> 0 | C7: =Summary!C25 -> 0 | D7: =Summary!D25 -> 0 | E7: =Summary!E25 -> 0 | F7: =Summary!F25 -> 0 | G7: =Summary!G25 -> 0 | H7: =Summary!H25 -> 0 | I7: =Summary!I25 -> 0 | ... AE7: =Summary!AE25 -> 0 | AF7: =sum(B7:AE7) -> 0
A8: Orders | B8: =Summary!B51 | C8: =Summary!C51 | D8: =Summary!D51 | E8: =Summary!E51 | F8: =Summary!F51 | G8: =Summary!G51 | H8: =Summary!H51 | I8: =Summary!I51 | ... AE8: =Summary!AE51 -> 5 | AF8: =sum(B8:AE8) -> 69
A10: Rachio Fees (20%) | B10: =Summary!B73 -> 0 | C10: =Summary!C73 -> 0 | D10: =Summary!D73 -> 0 | E10: =Summary!E73 -> 0 | F10: =Summary!F73 -> 0 | G10: =Summary!G73 -> 0 | H10: =Summary!H73 -> 0 | I10: =Summary!I73 -> 0 | ... AE10: =Summary!AE73 -> 207.8 | AF10: =sum(B10:AE10) -> 3006.666
A12: Units Sold (Gross) - Rachio
A13: SKU 1 - Blue | AC13: 7 | AD13: 9 | AE13: 0 | AF13: =sum(B13:AE13) -> 16
A14: SKU 2 - Yellow | AC14: 4 | AD14: 3 | AE14: 1 | AF14: =sum(B14:AE14) -> 8
A15: SKU 3 - Blue w/ Solar | AC15: 19 | AD15: 12 | AE15: 3 | AF15: =sum(B15:AE15) -> 34
A16: SKU 4 - Yellow w/ Solar | AC16: 5 | AD16: 3 | AE16: 1 | AF16: =sum(B16:AE16) -> 9
A17: SUM (SKU 1 - SKU 4) | B17: =SUM(B13:B16) -> 0 | C17: =SUM(C13:C16) -> 0 | D17: =SUM(D13:D16) -> 0 | E17: =SUM(E13:E16) -> 0 | F17: =SUM(F13:F16) -> 0 | G17: =SUM(G13:G16) -> 0 | H17: =SUM(H13:H16) -> 0 | I17: =SUM(I13:I16) -> 0 | ... AE17: =SUM(AE13:AE16) -> 5 | AF17: =sum(B17:AE17) -> 67
A19: Wall Mount | AC19: 0 | AD19: 0 | AE19: 0 | AF19: =sum(B19:AE19) -> 0
A20: Suet Ball Holder | AC20: 0 | AD20: 0 | AE20: 0 | AF20: =sum(B20:AE20) -> 0
A21: 3-in-1 Nutrition Set - Blue | AC21: 0 | AD21: 0 | AE21: 0 | AF21: =sum(B21:AE21) -> 0
A22: 3-in-1 Nutrition Set - Yellow | AC22: 0 | AD22: 0 | AE22: 0 | AF22: =sum(B22:AE22) -> 0
A23: Solar Roof Single - Blue | AC23: 0 | AD23: 0 | AE23: 0 | AF23: =sum(B23:AE23) -> 0
A24: Solar Roof Single - Yellow | AC24: 0 | AD24: 0 | AE24: 0 | AF24: =sum(B24:AE24) -> 0
A25: Perch Extender - Blue | AC25: 0 | AD25: 0 | AE25: 0 | AF25: =sum(B25:AE25) -> 0
A26: Perch Extender - Yellow | AC26: 0 | AD26: 0 | AE26: 0 | AF26: =sum(B26:AE26) -> 0
A27: SUM (Add-ons) | B27: =SUM(B19:B26) -> 0 | C27: =SUM(C19:C26) -> 0 | D27: =SUM(D19:D26) -> 0 | E27: =SUM(E19:E26) -> 0 | F27: =SUM(F19:F26) -> 0 | G27: =SUM(G19:G26) -> 0 | H27: =SUM(H19:H26) -> 0 | I27: =SUM(I19:I26) -> 0 | ... AE27: =SUM(AE19:AE26) -> 0 | AF27: =sum(B27:AE27) -> 0
A29: Units and Revenue Cancelled & Refunds - Rachio
A31: Units Cancelled (Gross) - Rachio
A32: SKU 1 - Blue | AF32: =SUM(B32:AE32) -> 0
A33: SKU 2 - Yellow | AF33: =SUM(B33:AE33) -> 0
A34: SKU 3 - Blue w/ Solar | AF34: =SUM(B34:AE34) -> 0
A35: SKU 4 - Yellow w/ Solar | AF35: =SUM(B35:AE35) -> 0
A36: SUM (SKU 1 + SKU 2) | B36: =SUM(B32:B33) -> 0 | C36: =SUM(C32:C33) -> 0 | D36: =SUM(D32:D33) -> 0 | E36: =SUM(E32:E33) -> 0 | F36: =SUM(F32:F33) -> 0 | G36: =SUM(G32:G33) -> 0 | H36: =SUM(H32:H33) -> 0 | I36: =SUM(I32:I33) -> 0 | ... AE36: =SUM(AE32:AE33) -> 0 | AF36: =SUM(B36:AE36) -> 0
A37: SUM (SKU 3 + SKU 4) | B37: =SUM(B34:B35) -> 0 | C37: =SUM(C34:C35) -> 0 | D37: =SUM(D34:D35) -> 0 | E37: =SUM(E34:E35) -> 0 | F37: =SUM(F34:F35) -> 0 | G37: =SUM(G34:G35) -> 0 | H37: =SUM(H34:H35) -> 0 | I37: =SUM(I34:I35) -> 0 | ... AE37: =SUM(AE34:AE35) -> 0 | AF37: =SUM(B37:AE37) -> 0
A39: Wall Mount | AF39: =SUM(B39:AE39) -> 0
A40: Suet Ball Holder | AF40: =SUM(B40:AE40) -> 0
A41: 3-in-1 Nutrition Set - Blue | AF41: =SUM(B41:AE41) -> 0
A42: 3-in-1 Nutrition Set - Yellow | AF42: =SUM(B42:AE42) -> 0
A43: Solar Roof Single - Blue | AF43: =SUM(B43:AE43) -> 0
A44: Solar Roof Single - Yellow | AF44: =SUM(B44:AE44) -> 0
A45: Perch Extender - Blue | AF45: =SUM(B45:AE45) -> 0
A46: Perch Extender - Yellow | AF46: =SUM(B46:AE46) -> 0
A47: SUM (Add-ons) | B47: =SUM(B39:B46) -> 0 | C47: =SUM(C39:C46) -> 0 | D47: =SUM(D39:D46) -> 0 | E47: =SUM(E39:E46) -> 0 | F47: =SUM(F39:F46) -> 0 | G47: =SUM(G39:G46) -> 0 | H47: =SUM(H39:H46) -> 0 | I47: =SUM(I39:I46) -> 0 | ... AE47: =SUM(AE39:AE46) -> 0 | AF47: =SUM(B47:AE47) -> 0
A49: Revenue Cancelled (Gross) - Rachio
A50: Hardware | AF50: =SUM(B50:AE50) -> 0
A51: Shipping | AF51: =SUM(B51:AE51) -> 0
A52: Taxes | AF52: =SUM(B52:AE52) -> 0
A53: All NA | B53: =SUM(B50:B52) -> 0 | C53: =SUM(C50:C52) -> 0 | D53: =SUM(D50:D52) -> 0 | E53: =SUM(E50:E52) -> 0 | F53: =SUM(F50:F52) -> 0 | G53: =SUM(G50:G52) -> 0 | H53: =SUM(H50:H52) -> 0 | I53: =SUM(I50:I52) -> 0 | ... AE53: =SUM(AE50:AE52) -> 0 | AF53: =SUM(B53:AE53) -> 0
A55: Hardware - Europe | AF55: =SUM(B55:AE55) -> 0
A56: Shipping - Europe | AF56: =SUM(B56:AE56) -> 0
A57: All EU | B57: =sum(B55:B56) -> 0 | C57: =sum(C55:C56) -> 0 | D57: =sum(D55:D56) -> 0 | E57: =sum(E55:E56) -> 0 | F57: =sum(F55:F56) -> 0 | G57: =sum(G55:G56) -> 0 | H57: =sum(H55:H56) -> 0 | I57: =sum(I55:I56) -> 0 | ... AE57: =sum(AE55:AE56) -> 0 | AF57: =SUM(B57:AE57) -> 0
A59: Units Refund (Gross) - Rachio
A60: SKU 1 - Blue | AF60: =SUM(B60:AE60) -> 0
A61: SKU 2 - Yellow | AF61: =SUM(B61:AE61) -> 0
A62: SKU 3 - Blue w/ Solar | AF62: =SUM(B62:AE62) -> 0
A63: SKU 4 - Yellow w/ Solar | AF63: =SUM(B63:AE63) -> 0
A64: SUM (SKU 1 + SKU 2) | B64: =SUM(B60:B61) -> 0 | C64: =SUM(C60:C61) -> 0 | D64: =SUM(D60:D61) -> 0 | E64: =SUM(E60:E61) -> 0 | F64: =SUM(F60:F61) -> 0 | G64: =SUM(G60:G61) -> 0 | H64: =SUM(H60:H61) -> 0 | I64: =SUM(I60:I61) -> 0 | ... AE64: =SUM(AE60:AE61) -> 0 | AF64: =SUM(B64:AE64) -> 0
A65: SUM (SKU 3 + SKU 4) | B65: =SUM(B62:B63) -> 0 | C65: =SUM(C62:C63) -> 0 | D65: =SUM(D62:D63) -> 0 | E65: =SUM(E62:E63) -> 0 | F65: =SUM(F62:F63) -> 0 | G65: =SUM(G62:G63) -> 0 | H65: =SUM(H62:H63) -> 0 | I65: =SUM(I62:I63) -> 0 | ... AE65: =SUM(AE62:AE63) -> 0 | AF65: =SUM(B65:AE65) -> 0
A67: Wall Mount | AF67: =SUM(B67:AE67) -> 0
A68: Suet Ball Holder | AF68: =SUM(B68:AE68) -> 0
A69: 3-in-1 Nutrition Set - Blue | AF69: =SUM(B69:AE69) -> 0
A70: 3-in-1 Nutrition Set - Yellow | AF70: =SUM(B70:AE70) -> 0
A71: Solar Roof Single - Blue | AF71: =SUM(B71:AE71) -> 0
A72: Solar Roof Single - Yellow | AF72: =SUM(B72:AE72) -> 0
A73: Perch Extender - Blue | AF73: =SUM(B73:AE73) -> 0
A74: Perch Extender - Yellow | AF74: =SUM(B74:AE74) -> 0
A75: SUM (Add-ons) | B75: =SUM(B67:B74) -> 0 | C75: =SUM(C67:C74) -> 0 | D75: =SUM(D67:D74) -> 0 | E75: =SUM(E67:E74) -> 0 | F75: =SUM(F67:F74) -> 0 | G75: =SUM(G67:G74) -> 0 | H75: =SUM(H67:H74) -> 0 | I75: =SUM(I67:I74) -> 0 | ... AE75: =SUM(AE67:AE74) -> 0 | AF75: =SUM(B75:AE75) -> 0
A77: Orders Return for Refund
A79: Revenue Refunded (Gross) - Rachio
A80: Hardware | B80: 0 | C80: 0 | D80: 0 | E80: 0 | F80: 0 | G80: 0 | H80: 0 | I80: 0 | J80: 0 | K80: 0 | L80: 0 | M80: 0 | N80: 0 | O80: 0 | P80: 0 | Q80: 0 | R80: 0 | S80: 0 | T80: 0 | U80: 0 | V80: 0 | W80: 0 | X80: 0 | Y80: 0 | Z80: 0 | AA80: 0 | AB80: 0 | AC80: 0 | AD80: 0 | AE80: 0 | AF80: =SUM(B80:AE80) -> 0
A81: Shipping | AF81: =SUM(B81:AE81) -> 0
A82: Taxes | AF82: =SUM(B82:AE82) -> 0
A83: All NA | B83: =sum(B80:B82) -> 0 | C83: =sum(C80:C82) -> 0 | D83: =sum(D80:D82) -> 0 | E83: =sum(E80:E82) -> 0 | F83: =sum(F80:F82) -> 0 | G83: =sum(G80:G82) -> 0 | H83: =sum(H80:H82) -> 0 | I83: =sum(I80:I82) -> 0 | ... AE83: =sum(AE80:AE82) -> 0 | AF83: =SUM(B83:AE83) -> 0
A85: Hardware - Europe | AF85: =SUM(B85:AE85) -> 0
A86: Shipping - Europe | AF86: =SUM(B86:AE86) -> 0
A87: All EU | B87: =sum(B85:B86) -> 0 | C87: =sum(C85:C86) -> 0 | D87: =sum(D85:D86) -> 0 | E87: =sum(E85:E86) -> 0 | F87: =sum(F85:F86) -> 0 | G87: =sum(G85:G86) -> 0 | H87: =sum(H85:H86) -> 0 | I87: =sum(I85:I86) -> 0 | ... AE87: =sum(AE85:AE86) -> 0 | AF87: =SUM(B87:AE87) -> 0
A89: RETURN (Replacement Units & Claims) - Rachio
A90: SKU 1 - Blue | B90: 0 | C90: 0 | D90: 0 | E90: 0 | F90: 0 | G90: 0 | H90: 0 | I90: 0 | J90: 0 | K90: 0 | L90: 0 | M90: 0 | N90: 0 | O90: 0 | P90: 0 | Q90: 0 | R90: 0 | S90: 0 | T90: 0 | U90: 0 | V90: 0 | W90: 0 | X90: 0 | Y90: 0 | Z90: 0 | AA90: 0 | AB90: 0 | AC90: 0 | AD90: 0 | AE90: 0 | AF90: =SUM(B90:AE90) -> 0
A91: SKU 2 - Yellow | B91: 0 | C91: 0 | D91: 0 | E91: 0 | F91: 0 | G91: 0 | H91: 0 | I91: 0 | J91: 0 | K91: 0 | L91: 0 | M91: 0 | N91: 0 | O91: 0 | P91: 0 | Q91: 0 | R91: 0 | S91: 0 | T91: 0 | U91: 0 | V91: 0 | W91: 0 | X91: 0 | Y91: 0 | Z91: 0 | AA91: 0 | AB91: 0 | AC91: 0 | AD91: 0 | AE91: 0 | AF91: =SUM(B91:AE91) -> 0
A92: SKU 3 - Blue w/ Solar | B92: 0 | C92: 0 | D92: 0 | E92: 0 | F92: 0 | G92: 0 | H92: 0 | I92: 0 | J92: 0 | K92: 0 | L92: 0 | M92: 0 | N92: 0 | O92: 0 | P92: 0 | Q92: 0 | R92: 0 | S92: 0 | T92: 0 | U92: 0 | V92: 0 | W92: 0 | X92: 0 | Y92: 0 | Z92: 0 | AA92: 0 | AB92: 0 | AC92: 0 | AD92: 0 | AE92: 0 | AF92: =SUM(B92:AE92) -> 0
A93: SKU 4 - Yellow w/ Solar | B93: 0 | C93: 0 | D93: 0 | E93: 0 | F93: 0 | G93: 0 | H93: 0 | I93: 0 | J93: 0 | K93: 0 | L93: 0 | M93: 0 | N93: 0 | O93: 0 | P93: 0 | Q93: 0 | R93: 0 | S93: 0 | T93: 0 | U93: 0 | V93: 0 | W93: 0 | X93: 0 | Y93: 0 | Z93: 0 | AA93: 0 | AB93: 0 | AC93: 0 | AD93: 0 | AE93: 0 | AF93: =SUM(B93:AE93) -> 0
A94: SUM (SKU 1 + SKU 2) | B94: =B90+B91 -> 0 | C94: =C90+C91 -> 0 | D94: =D90+D91 -> 0 | E94: =E90+E91 -> 0 | F94: =F90+F91 -> 0 | G94: =G90+G91 -> 0 | H94: =H90+H91 -> 0 | I94: =I90+I91 -> 0 | ... AE94: =AE90+AE91 -> 0 | AF94: =SUM(B94:AE94) -> 0
A95: SUM (SKU 3 + SKU 4) | B95: =B92+B93 -> 0 | C95: =C92+C93 -> 0 | D95: =D92+D93 -> 0 | E95: =E92+E93 -> 0 | F95: =F92+F93 -> 0 | G95: =G92+G93 -> 0 | H95: =H92+H93 -> 0 | I95: =I92+I93 -> 0 | ... AE95: =AE92+AE93 -> 0 | AF95: =SUM(B95:AE95) -> 0
AF96: =SUM(B96:AE96) -> 0
A97: Wall Mount | B97: 0 | C97: 0 | D97: 0 | E97: 0 | F97: 0 | G97: 0 | H97: 0 | I97: 0 | J97: 0 | K97: 0 | L97: 0 | M97: 0 | N97: 0 | O97: 0 | P97: 0 | Q97: 0 | R97: 0 | S97: 0 | T97: 0 | U97: 0 | V97: 0 | W97: 0 | X97: 0 | Y97: 0 | Z97: 0 | AA97: 0 | AB97: 0 | AC97: 0 | AD97: 0 | AE97: 0 | AF97: =SUM(B97:AE97) -> 0
A98: Suet Ball Holder | B98: 0 | C98: 0 | D98: 0 | E98: 0 | F98: 0 | G98: 0 | H98: 0 | I98: 0 | J98: 0 | K98: 0 | L98: 0 | M98: 0 | N98: 0 | O98: 0 | P98: 0 | Q98: 0 | R98: 0 | S98: 0 | T98: 0 | U98: 0 | V98: 0 | W98: 0 | X98: 0 | Y98: 0 | Z98: 0 | AA98: 0 | AB98: 0 | AC98: 0 | AD98: 0 | AE98: 0 | AF98: =SUM(B98:AE98) -> 0
A99: 3-in-1 Nutrition Set - Blue | B99: 0 | C99: 0 | D99: 0 | E99: 0 | F99: 0 | G99: 0 | H99: 0 | I99: 0 | J99: 0 | K99: 0 | L99: 0 | M99: 0 | N99: 0 | O99: 0 | P99: 0 | Q99: 0 | R99: 0 | S99: 0 | T99: 0 | U99: 0 | V99: 0 | W99: 0 | X99: 0 | Y99: 0 | Z99: 0 | AA99: 0 | AB99: 0 | AC99: 0 | AD99: 0 | AE99: 0 | AF99: =SUM(B99:AE99) -> 0
A100: 3-in-1 Nutrition Set - Yellow | B100: 0 | C100: 0 | D100: 0 | E100: 0 | F100: 0 | G100: 0 | H100: 0 | I100: 0 | J100: 0 | K100: 0 | L100: 0 | M100: 0 | N100: 0 | O100: 0 | P100: 0 | Q100: 0 | R100: 0 | S100: 0 | T100: 0 | U100: 0 | V100: 0 | W100: 0 | X100: 0 | Y100: 0 | Z100: 0 | AA100: 0 | AB100: 0 | AC100: 0 | AD100: 0 | AE100: 0 | AF100: =SUM(B100:AE100) -> 0
A101: Solar Roof Single - Blue | B101: 0 | C101: 0 | D101: 0 | E101: 0 | F101: 0 | G101: 0 | H101: 0 | I101: 0 | J101: 0 | K101: 0 | L101: 0 | M101: 0 | N101: 0 | O101: 0 | P101: 0 | Q101: 0 | R101: 0 | S101: 0 | T101: 0 | U101: 0 | V101: 0 | W101: 0 | X101: 0 | Y101: 0 | Z101: 0 | AA101: 0 | AB101: 0 | AC101: 0 | AD101: 0 | AE101: 0 | AF101: =SUM(B101:AE101) -> 0
A102: Solar Roof Single - Yellow | B102: 0 | C102: 0 | D102: 0 | E102: 0 | F102: 0 | G102: 0 | H102: 0 | I102: 0 | J102: 0 | K102: 0 | L102: 0 | M102: 0 | N102: 0 | O102: 0 | P102: 0 | Q102: 0 | R102: 0 | S102: 0 | T102: 0 | U102: 0 | V102: 0 | W102: 0 | X102: 0 | Y102: 0 | Z102: 0 | AA102: 0 | AB102: 0 | AC102: 0 | AD102: 0 | AE102: 0 | AF102: =SUM(B102:AE102) -> 0
A103: Perch Extender - Blue | B103: 0 | C103: 0 | D103: 0 | E103: 0 | F103: 0 | G103: 0 | H103: 0 | I103: 0 | J103: 0 | K103: 0 | L103: 0 | M103: 0 | N103: 0 | O103: 0 | P103: 0 | Q103: 0 | R103: 0 | S103: 0 | T103: 0 | U103: 0 | V103: 0 | W103: 0 | X103: 0 | Y103: 0 | Z103: 0 | AA103: 0 | AB103: 0 | AC103: 0 | AD103: 0 | AE103: 0 | AF103: =SUM(B103:AE103) -> 0
A104: Perch Extender - Yellow | B104: 0 | C104: 0 | D104: 0 | E104: 0 | F104: 0 | G104: 0 | H104: 0 | I104: 0 | J104: 0 | K104: 0 | L104: 0 | M104: 0 | N104: 0 | O104: 0 | P104: 0 | Q104: 0 | R104: 0 | S104: 0 | T104: 0 | U104: 0 | V104: 0 | W104: 0 | X104: 0 | Y104: 0 | Z104: 0 | AA104: 0 | AB104: 0 | AC104: 0 | AD104: 0 | AE104: 0 | AF104: =SUM(B104:AE104) -> 0
A105: SUM (Add-ons) | B105: =SUM(B97:B104) -> 0 | C105: =SUM(C97:C101) -> 0 | D105: =SUM(D97:D101) -> 0 | E105: =SUM(E97:E101) -> 0 | F105: =SUM(F97:F101) -> 0 | G105: =SUM(G97:G101) -> 0 | H105: =SUM(H97:H101) -> 0 | I105: =SUM(I97:I101) -> 0 | J105: =SUM(J97:J101) -> 0 | ... AE105: =SUM(AE97:AE101) -> 0 | AF105: =SUM(B105:AE105) -> 0
AF106: =SUM(B106:AE106) -> 0
A107: Parts | AF107: =SUM(B107:AE107) -> 0
A108: Housing - Blue | B108: 0 | C108: 0 | D108: 0 | E108: 0 | F108: 0 | G108: 0 | H108: 0 | I108: 0 | J108: 0 | K108: 0 | L108: 0 | M108: 0 | N108: 0 | O108: 0 | P108: 0 | Q108: 0 | R108: 0 | S108: 0 | T108: 0 | U108: 0 | V108: 0 | W108: 0 | X108: 0 | Y108: 0 | Z108: 0 | AA108: 0 | AB108: 0 | AC108: 0 | AD108: 0 | AE108: 0 | AF108: =SUM(B108:AE108) -> 0
A109: Housing - Yellow | B109: 0 | C109: 0 | D109: 0 | E109: 0 | F109: 0 | G109: 0 | H109: 0 | I109: 0 | J109: 0 | K109: 0 | L109: 0 | M109: 0 | N109: 0 | O109: 0 | P109: 0 | Q109: 0 | R109: 0 | S109: 0 | T109: 0 | U109: 0 | V109: 0 | W109: 0 | X109: 0 | Y109: 0 | Z109: 0 | AA109: 0 | AB109: 0 | AC109: 0 | AD109: 0 | AE109: 0 | AF109: =SUM(B109:AE109) -> 0
A110: Camera Module | B110: 0 | C110: 0 | D110: 0 | E110: 0 | F110: 0 | G110: 0 | H110: 0 | I110: 0 | J110: 0 | K110: 0 | L110: 0 | M110: 0 | N110: 0 | O110: 0 | P110: 0 | Q110: 0 | R110: 0 | S110: 0 | T110: 0 | U110: 0 | V110: 0 | W110: 0 | X110: 0 | Y110: 0 | Z110: 0 | AA110: 0 | AB110: 0 | AC110: 0 | AD110: 0 | AE110: 0 | AF110: =SUM(B110:AE110) -> 0
AF111: =SUM(B111:AE111) -> 0
A112: Orders Replaced NA | B112: 0 | C112: 0 | D112: 0 | E112: 0 | F112: 0 | G112: 0 | H112: 0 | I112: 0 | J112: 0 | K112: 0 | L112: 0 | M112: 0 | N112: 0 | O112: 0 | P112: 0 | Q112: 0 | R112: 0 | S112: 0 | T112: 0 | U112: 0 | V112: 0 | W112: 0 | X112: 0 | Y112: 0 | Z112: 0 | AA112: 0 | AB112: 0 | AC112: 0 | AD112: 0 | AE112: 0 | AF112: =SUM(B112:AE112) -> 0
A115: Weatherflow (Shopify)
A116: Revenue | AF116: =SUM(B116:AE116) -> 0
...

Sheet DATA - P&L
B1: Business Metrics
A2: Source | B2: COGS | E2: Attachment Rates | H2: Marketing Averages (per first-time order) | K2: Fees | N2: VAT Averages | Q2: 30 Day Returns | T2: Digital Market Places & B2B
B3: Bird Buddy | C3: 86.9 | D3: 86.9 | E3: Solar Roof | F3: =(('DTC - P&L'!AF83+'DTC - P&L'!AF84)/'DTC - P&L'!AF77) -> 0.079075966 | H3: COGS | I3: =(C3*F9)+(C4*F8)+(C5*F3)+(C6*F4)+(C7*F5)+(C8*F6)+(C9*F7)+(C10*F10) -> 102.96659 | J3: =(D3*F9)+(D4*F8)+(D5*F3)+(D6*F4)+(D7*F5)+(D8*F6)+(D9*F7) -> 99.381519 | K3: Stripe Processing Fee | L3: 0.029 | N3: Europe | O3: 0.22 | Q3: US Shipping | R3: 15 | T3: Average % tax | U3: 0.0614 | V3: Source
B4: Bird Buddy with Solar Roof | C4: 97.61 | D4: 97.61 | E4: Wall Mount | F4: =('DTC - P&L'!AF79/'DTC - P&L'!AF77) -> 0.33540649 | H4: Inbound Shipping | I4: =C38+('DTC - P&L'!AF87/'DTC - P&L'!AF77)*D38 -> 14.122143 | K4: Duty | L4: 0.034 | N4: ROW | O4: 0.13 | Q4: EU Shipping | R4: 40
B5: Solar Roof Single | C5: 13.44 | D5: 13.44 | E5: Fence Mount | F5: 0 | H5: Outbound Shipping | I5: =C34+('DTC - P&L'!AF87/'DTC - P&L'!AF77)*D34 -> 21.299647 | K5: China Tax | L5: 0.075 | N5: NA | Q5: ROW Shipping | R5: 20
B6: Wall Mount | C6: 5.49 | D6: 5.49 | E6: Suet Ball Holder | F6: =('DTC - P&L'!AF80)/'DTC - P&L'!AF77 -> 0.23056419 | H6: Taxes and VAT | I6: 16.81 | K6: HMF | L6: 0.00125 | Q6: Money Return | R6: 1
B7: Fence Mount | C7: 6.37 | E7: 3-in-1 | F7: =('DTC - P&L'!AF81+'DTC - P&L'!AF82)/'DTC - P&L'!AF77 -> 0.27809862 | H7: China Tax (7.5%) | I7: 0 | K7: MPF | L7: 0.003464
B8: Suet Ball Holder | C8: 1.19 | D8: 1.19 | E8: Bird Buddy w/ Solar | F8: =('DTC - P&L'!AF75+'DTC - P&L'!AF76)/'DTC - P&L'!AF77 -> 0.6956908 | H8: Duty (3.4%) | I8: 0 | K8: Solar Roof China Tax | L8: 0.075
B9: 3-in-1 Nutrition Set | C9: 6.66 | D9: 6.66 | E9: Bird Buddy | F9: =1-F8 -> 0.3043092 | H9: Processing Fee (2,90%) | I9: =Summary!B109*L3 -> 6.1513277 | K9: Solar Roof Duty | L9: 0.025
B10: Perch Extender | C10: 6 | E10: Perch Extender | F10: =('DTC - P&L'!AF85+'DTC - P&L'!AF86)/'DTC - P&L'!AF77 -> 0.59751222 | H10: Transaction Fee ($0.30) | I10: =0.3 -> 0.3 | K10: Chargeback Fee (Stripe) | L10: 15
B11: Avg. Merch Cost | C11: 3.94 | E11: OTHER 2 | H11: OTHER 1
B12: Avg. Merch Cost without Calendar | C12: 14.79 | E12: OTHER 3 | H12: OTHER 2 | K12: Stripe | L12: 0.95
B13: SBF Housing | E13: OTHER 4 | H13: OTHER 3 | K13: Affirm | L13: 0.05
B14: SBF Camera | E14: OTHER 5 | H14: OTHER 4 | K14: Affirm processing fee | L14: 0.0579
H15: All | I15: =SUM(I3:I14) -> 161.64971 | K15: Affirm transaction fee | L15: 0.3
B22: Outbound shipping | C22: Bird buddy | D22: Add-ons | E22: Merch
A23: *w/o CA weight | B23: Outbound (NA) | C23: 11.94 | D23: 6.155 | E23: 5.4 | H23: App Advertising
B24: Outbound (Europe) | C24: 11.94 | D24: 6.16 | H24: Meta Share to Apple Store | I24: 0.8
B25: Outbound (ROW) | C25: 11.94 | D25: 6.16 | H25: Meta Share to Google Store | I25: 0.2
A26: Source | B26: 3PL Costs | C26: 0 | D26: 0
B27: Handling Fee
B28: Serial Capture | C28: 0.1 | D28: 0
B29: Storage | C29: 0.31 | D29: 0.31
B30: Supplies cost | C30: 0 | D30: 0
B31: Pick charge | C31: 0.35 | D31: 0.35
B32: Pollybag cost | C32: 0 | D32: 0
B33: Carton cost | C33: 1.65 | D33: 0.71
B34: Total outbound (NA) | C34: =C26+C23-C27 -> 11.94 | D34: =D26+D23-D27 -> 6.155
B35: Total outbound (Europe) | C35: 15.06 | D35: =D27+D24-D28 -> 6.16
B36: Total outbound (ROW) | C36: 20
A37: Source | B37: Inbound shipping | C37: Bird buddy | D37: Add-ons
B38: Inbound (NA) | C38: 11.94 | D38: 1.435
B39: Inbound (Europe) | C39: 11.94 | D39: 1.44
B40: Inbound (ROW) | C40: 11.94 | D40: 1.44
B42: AMAZON Logistics | C42: Bird buddy | D42: Add-ons
A43: https://docs.google.com/spreadsheets/d/1Dn0q7h1bHxXdG0N9KpcqzFo0tWUWYXOrRX7yxv3G1E0/edit#gid=1264242332 | B43: Inbound | C43: 11.94 | D43: 1.435
A44: =sum(C43:C44) -> 12.18 | B44: Storage Fee | C44: 0.24 | D44: 0.24
A45: =C46 -> 12.94 | B45: AMAZON Fees | C45: Bird buddy
A46: =sum(F43:F45) -> 0 | B46: FBA fee for units | C46: 12.94
B47: FBA fee for addons | C47: 5.7
A48: =C38 -> 11.94 | B48: Sales Fee | C48: 0.15
B49: AMAZON Shipping | C49: Bird buddy
A50: =sum(A43:A48) -> 37.06 | B50: BB units Shipping | C50: 11
B51: Addons Shipping | C51: 6.155
B53: COGS adjustment for DTC
B54: Returns for refunds | C54: 0.25
B55: Returns for replacements | C55: 0.1
B57: COGS adjustment for Amazon
B58: Returns for refunds | C58: 0.5644
B59: Returns for replacements | C59: 0.4603
B61: Amazon Removal Fee
B62: Units | C62: 5.56
B63: Add-ons | C63: 2.2
A66: https://docs.google.com/document/d/1m1D0mcq6_cpIUs4Z2pSMjDX9L4kRSfAwaLu0UKQppIM/edit?usp=sharing | B66: Explanation for Returns, Cancellations, Replacements calculation
A68: https://docs.google.com/spreadsheets/d/1JFD6SusYZSq5MvMm0PnCaYPmLBVKBKvK09yjZIlSFN4/edit#gid=0 | B68: Amazon Modelling for cancelled orders
B69: Full Price Template for cancelled orders
B70: item-tax | C70: 17.58
B71: shipping-price | C71: 0.29
B72: shipping-tax | C72: 0 | I72: 17.58 | J72: 0.29 | K72: 0 | L72: 0.17 | M72: 0.01
B73: gift-wrap-price | C73: 0.17
B74: gift-wrap-tax | C74: 0.01
B75: item-promotion-discount | C75: 2.44
B76: ship-promotion-discount | C76: 0.21
B79: B2B
B80: Agency Fee | C80: 0.05 | D80: NET NET
B81: Agency transportation best buy | C81: *Dejan sporoči

Sheet OLD Sales
A1: 45170 | B1: 45170 | C1: 45171 | D1: 45172 | E1: 45173 | F1: 45174 | G1: 45175 | H1: 45176 | I1: 45177 | J1: 45178 | K1: 45179 | L1: 45180 | M1: 45181 | N1: 45182 | O1: 45183 | P1: 45184 | Q1: 45185 | R1: 45186 | S1: 45187 | T1: 45188 | U1: 45189 | V1: 45190 | W1: 45191 | X1: 45192 | Y1: 45193 | Z1: 45194 | AA1: 45195 | AB1: 45196 | AC1: 45197 | AD1: 45198 | AE1: 45199
B2: FRI | C2: SAT | D2: SUN | E2: MON | F2: TUE | G2: WED | H2: THU | I2: FRI | J2: SAT | K2: SUN | L2: MON | M2: TUE | N2: WED | O2: THU | P2: FRI | Q2: SAT | R2: SUN | S2: MON | T2: TUE | U2: WED | V2: THU | W2: FRI | X2: SAT | Y2: SUN | Z2: MON | AA2: TUE | AB2: WED | AC2: THU | AD2: FRI | AE2: SAT
A3: Weekend Work | C3: Peco | D3: Peco | J3: Peco | K3: Peco | Q3: Peter | R3: Peter | X3: Peter | Y3: Peter | AE3: Peco
S4: PRO Subscription Launch | X4: SKU3 ABC Test - Testing availability
B5: Labor Day | N5: 10% off Sitewide | S5: Keynote
G6: IGG Launch | S6: Perch Extender Launch | AB6: Existing users email sent at 15:35
A8: DTC Revenue | B8: 17265.68 | C8: 23737.33 | D8: 31027.91 | E8: 38624.27 | F8: 32334.23 | G8: 25523.42 | H8: 16513.05 | I8: 16047.62 | J8: 16896.24 | K8: 25310.44 | L8: 19069.47 | M8: 17658.35 | N8: 16855.53 | O8: 21866.4 | P8: 19818.81 | Q8: 20289.02 | R8: 20492.89 | S8: 54783.26 | T8: 32668.33 | U8: 24173.38 | V8: 23765.13 | W8: 20293.99 | X8: 23532.56 | Y8: 25409.48 | Z8: 24613.92 | AA8: 16571.82 | AB8: 28234.49 | AC8: 22796.27 | AD8: 23841.8 | AE8: 21795.85
A9: - Hardware | B9: 14026.9 | C9: 18793.1 | D9: 24511.2 | E9: 31197.45 | F9: 26437.6 | G9: 20504.1 | H9: 13104.1 | I9: 13302 | J9: 13850.8 | K9: 19907.55 | L9: 15207.8 | M9: 14622.3 | N9: 13822 | O9: 17737 | P9: 15812.3 | Q9: 15992.1 | R9: 16698.6 | S9: 20269.56 | T9: 16381.86 | U9: 15554.46 | V9: 15454.66 | W9: 13552.46 | X9: 16245.43 | Y9: 17145.66 | Z9: 17990.3 | AA9: 11982.08 | AB9: 21447.09 | AC9: 16473.96 | AD9: 18216.46 | AE9: 16990.16
A10: - Add-ons | B10: 1138.6 | C10: 1939.8 | D10: 2670.2 | E10: 2579.4 | F10: 2048.8 | G10: 1858 | H10: 1400.5 | I10: 989 | J10: 1135.5 | K10: 2415.4 | L10: 1591.5 | M10: 1134 | N10: 1119.5 | O10: 1517.6 | P10: 1613.7 | Q10: 1853 | R10: 1399.5 | S10: 23372.34 | T10: 10539.34 | U10: 5133.34 | V10: 4937.34 | W10: 3861.34 | X10: 4131.17 | Y10: 4750.34 | Z10: 3417.8 | AA10: 2401.9 | AB10: 3390.5 | AC10: 3394.84 | AD10: 2819.54 | AE10: 2141.19
A11: - Merch | B11: 0 | C11: 0 | D11: 0 | E11: 0 | F11: 0 | G11: 0 | H11: 0 | I11: 0 | J11: 0 | K11: 0 | L11: 0 | M11: 0 | N11: 0 | O11: 0 | P11: 0 | Q11: 0 | R11: 0 | S11: 0 | T11: 0 | U11: 0 | V11: 0 | W11: 0 | X11: 0 | Y11: 0 | Z11: 0 | AA11: 0 | AB11: 0 | AC11: 0 | AD11: 0 | AE11: 0
A12: - Taxes | B12: 885.18 | C12: 1219.43 | D12: 1651.51 | E12: 2027.42 | F12: 1707.83 | G12: 1391.32 | H12: 843.45 | I12: 726.62 | J12: 964.94 | K12: 1342.49 | L12: 1050.17 | M12: 902.05 | N12: 854.03 | O12: 1081.8 | P12: 1017.81 | Q12: 1118.92 | R12: 1169.79 | S12: 2776.36 | T12: 1602.13 | U12: 1190.58 | V12: 1198.13 | W12: 1070.19 | X12: 1150.96 | Y12: 1318.48 | Z12: 1125.82 | AA12: 802.84 | AB12: 1606.9 | AC12: 1117.47 | AD12: 1335.8 | AE12: 1164.5
A13: - Shipping | B13: 1215 | C13: 1785 | D13: 2195 | E13: 2820 | F13: 2140 | G13: 1770 | H13: 1165 | I13: 1030 | J13: 945 | K13: 1645 | L13: 1220 | M13: 1000 | N13: 1060 | O13: 1530 | P13: 1375 | Q13: 1325 | R13: 1225 | S13: 8365 | T13: 4145 | U13: 2295 | V13: 2175 | W13: 1810 | X13: 2005 | Y13: 2195 | Z13: 2080 | AA13: 1385 | AB13: 1790 | AC13: 1810 | AD13: 1470 | AE13: 1500
A14: IndieGoGo Revenue | B14: 0 | C14: 0 | D14: 0 | E14: 0 | F14: 0 | G14: 1337 | H14: 1675 | I14: 3815 | J14: 4507 | K14: 3017 | L14: 4996 | M14: 4733 | N14: 2268 | O14: 1933 | P14: 3188 | Q14: 4965 | R14: 974 | S14: 1317 | T14: 2533 | U14: 1389 | V14: 403 | W14: 0 | X14: 283 | Y14: 283 | Z14: 0 | AA14: 283 | AB14: 967 | AC14: 0 | AD14: 309 | AE14: 974
A15: Amazon Revenue | B15: 3069 | C15: 2511 | D15: 4185 | E15: 5580 | F15: 5580 | G15: 4464 | H15: 3627 | I15: 2790 | J15: 6975 | K15: 6138 | L15: 6138 | M15: 6696 | N15: 7533 | O15: 8370 | P15: 4185 | Q15: 5859 | R15: 7254 | S15: 6975 | T15: 13113 | U15: 8928 | V15: 8649 | W15: 10881 | X15: 5580 | Y15: 10602 | Z15: 8928 | AA15: 10881 | AB15: 7812 | AC15: 11160 | AD15: 9765 | AE15: 7254
A16: - Hardware | B16: 3069 | C16: 2511 | D16: 4185 | E16: 5580 | F16: 5580 | G16: 4464 | H16: 3627 | I16: 2790 | J16: 6975 | K16: 6138 | L16: 6138 | M16: 6696 | N16: 7533 | O16: 8370 | P16: 4185 | Q16: 5859 | R16: 5022 | S16: 6975 | T16: 13113 | U16: 8928 | V16: 8649 | W16: 10881 | X16: 5580 | Y16: 10602 | Z16: 8928 | AA16: 10044 | AB16: 7812 | AC16: 11160 | AD16: 9765 | AE16: 7254
A17: - Add-ons | B17: 0 | C17: 0 | D17: 0 | E17: 0 | F17: 0 | G17: 0 | H17: 0 | I17: 0 | J17: 0 | K17: 0 | L17: 0 | M17: 0 | N17: 0 | O17: 0 | P17: 0 | Q17: 0 | R17: 0 | S17: 0 | T17: 0 | U17: 0 | V17: 0 | W17: 0 | X17: 0 | Y17: 0 | Z17: 0 | AA17: 0 | AB17: 0 | AC17: 0 | AD17: 0 | AE17: 0
A18: - Tax | B18: 205.77 | C18: 192.79 | D18: 285.04 | E18: 405.54 | F18: 410.82 | G18: 293.47 | H18: 221.96 | I18: 195.94 | J18: 507.02 | K18: 451.31 | L18: 392.02 | M18: 446.49 | N18: 554.7 | O18: 565.94 | P18: 320.37 | Q18: 382.52 | R18: 342.06 | S18: 506.38 | T18: 953.83 | U18: 581.41 | V18: 602.81 | W18: 777.74 | X18: 424.74 | Y18: 778.18 | Z18: 629.32 | AA18: 699.27 | AB18: 520.57 | AC18: 805.58 | AD18: 670.12 | AE18: 520.9
A19: - Shipping | B19: 6.99 | C19: 0 | D19: 13.46 | E19: 0 | F19: 0 | G19: 0 | H19: 0 | I19: 0 | J19: 0 | K19: 0 | L19: 6.99 | M19: 5.28 | N19: 11.79 | O19: 6.99 | P19: 0 | Q19: 0 | R19: 0 | S19: 0 | T19: 0 | U19: 6.99 | V19: 0 | W19: 0 | X19: 4.48 | Y19: 0 | Z19: 0 | AA19: 0 | AB19: 0 | AC19: 6.99 | AD19: 0 | AE19: 0
A20: - Gift Wrap | B20: 0 | C20: 0 | D20: 4.49 | E20: 4.49 | F20: 8.98 | G20: 8.98 | H20: 0 | I20: 0 | J20: 0 | K20: 4.49 | L20: 4.49 | M20: 13.47 | N20: 13.47 | O20: 8.98 | P20: 8.98 | Q20: 0 | R20: 8.98 | S20: 0 | T20: 4.49 | U20: 4.49 | V20: 0 | W20: 4.49 | X20: 4.49 | Y20: 8.98 | Z20: 0 | AA20: 0 | AB20: 4.49 | AC20: 8.98 | AD20: 8.98 | AE20: 4.49
A21: Rachio Revenue | AC21: 8188.24 | AD21: 5806.09 | AE21: 1039
A22: Net PRO Subscription Revenue | B22: 0 | C22: 0 | D22: 0 | E22: 0 | F22: 0 | G22: 0 | H22: 0 | I22: 0 | J22: 0 | K22: 0 | L22: 0 | M22: 0 | N22: 0 | O22: 0 | P22: 0 | Q22: 0 | R22: 0 | S22: 7726 | T22: 9063 | U22: 5576 | V22: 4328 | W22: 2975 | X22: 2918 | Y22: 2611 | Z22: 1872 | AA22: 1985 | AB22: 1409 | AC22: 1402 | AD22: 7004 | AE22: 7498
A23: Total Revenue | B23: =SUM(B8+B14+B15+B21+B22) -> 20334.68 | C23: =SUM(C8+C14+C15+C21+C22) -> 26248.33 | D23: =SUM(D8+D14+D15+D21+D22) -> 35212.91 | E23: =SUM(E8+E14+E15+E21+E22) -> 44204.27 | F23: =SUM(F8+F14+F15+F21+F22) -> 37914.23 | G23: =SUM(G8+G14+G15+G21+G22) -> 31324.42 | H23: =SUM(H8+H14+H15+H21+H22) -> 21815.05 | I23: =SUM(I8+I14+I15+I21+I22) -> 22652.62 | ... AE23: =SUM(AE8+AE14+AE15+AE21+AE22) -> 38560.85
A25: DTC Orders | B25: 79 | C25: 110 | D25: 135 | E25: 165 | F25: 149 | G25: 121 | H25: 79 | I25: 52 | J25: 63 | K25: 93 | L25: 84 | M25: 69 | N25: 64 | O25: 79 | P25: 91 | Q25: 86 | R25: 82 | S25: 587 | T25: 307 | U25: 173 | V25: 135 | W25: 119 | X25: 123 | Y25: 132 | Z25: 119 | AA25: 98 | AB25: 114 | AC25: 103 | AD25: 100 | AE25: 102
A26: - Hardware (units sold) | B26: 68 | C26: 93 | D26: 119 | E26: 158 | F26: 126 | G26: 102 | H26: 57 | I26: 54 | J26: 52 | K26: 80 | L26: 61 | M26: 62 | N26: 61 | O26: 75 | P26: 71 | Q26: 71 | R26: 76 | S26: 84 | T26: 68 | U26: 65 | V26: 62 | W26: 56 | X26: 62 | Y26: 69 | Z26: 72 | AA26: 51 | AB26: 88 | AC26: 70 | AD26: 72 | AE26: 68
A27: - Add-ons (units sold) | B27: 50 | C27: 83 | D27: 117 | E27: 119 | F27: 89 | G27: 75 | H27: 59 | I27: 39 | J27: 43 | K27: 88 | L27: 58 | M27: 43 | N27: 47 | O27: 55 | P27: 57 | Q27: 73 | R27: 51 | S27: 739 | T27: 352 | U27: 164 | V27: 153 | W27: 123 | X27: 138 | Y27: 162 | Z27: 120 | AA27: 87 | AB27: 124 | AC27: 115 | AD27: 96 | AE27: 81
A28: - Merch (units sold) | B28: 0 | C28: 0 | D28: 0 | E28: 0 | F28: 0 | G28: 0 | H28: 0 | I28: 0 | J28: 0 | K28: 0 | L28: 0 | M28: 0 | N28: 0 | O28: 0 | P28: 0 | Q28: 0 | R28: 0 | S28: 0 | T28: 0 | U28: 0 | V28: 0 | W28: 0 | X28: 0 | Y28: 0 | Z28: 0 | AA28: 0 | AB28: 0 | AC28: 0 | AD28: 0 | AE28: 0
A29: IndieGoGo Orders | B29: 0 | C29: 0 | D29: 0 | E29: 0 | F29: 0 | G29: 4 | H29: 6 | I29: 11 | J29: 13 | K29: 12 | L29: 15 | M29: 13 | N29: 8 | O29: 7 | P29: 8 | Q29: 13 | R29: 4 | S29: 2 | T29: 7 | U29: 4 | V29: 1 | W29: 0 | X29: 1 | Y29: 1 | Z29: 0 | AA29: 1 | AB29: 1 | AC29: 0 | AD29: 1 | AE29: 4
A30: Amazon Orders | B30: 14 | C30: 7 | D30: 19 | E30: 23 | F30: 16 | G30: 20 | H30: 12 | I30: 12 | J30: 28 | K30: 19 | L30: 22 | M30: 25 | N30: 26 | O30: 27 | P30: 15 | Q30: 21 | R30: 26 | S30: 28 | T30: 38 | U30: 36 | V30: 36 | W30: 30 | X30: 25 | Y30: 33 | Z30: 32 | AA30: 39 | AB30: 28 | AC30: 40 | AD30: 31 | AE30: 30
A31: Rachio Orders | AC31: 38 | AD31: 26 | AE31: 5
A32: Net PRO Subscription Orders | S32: 520 | T32: 574 | U32: 358 | V32: 280 | W32: 191 | X32: 190 | Y32: 171 | Z32: 133 | AA32: =2574-2419 -> 155 | AB32: =2679-2574 -> 105 | AC32: =2782-2679 -> 103 | AD32: 468 | AE32: 498
A33: Total Orders | B33: =SUM(B25:B32) -> 211 | C33: =SUM(C25:C30) -> 293 | D33: =SUM(D25:D30) -> 390 | E33: =SUM(E25:E30) -> 465 | F33: =SUM(F25:F30) -> 380 | G33: =SUM(G25:G30) -> 322 | H33: =SUM(H25:H30) -> 213 | I33: =SUM(I25:I30) -> 168 | J33: =SUM(J25:J30) -> 199 | ... Y33: =SUM(Y25:Y30) -> 397 | Z33: =SUM(Z25:Z32) -> 476 | AA33: =SUM(AA25:AA30) -> 276 | AB33: =SUM(AB25:AB30) -> 355 | AC33: =SUM(AC25:AC30) -> 328 | AD33: =SUM(AD25:AD30) -> 300 | AE33: =SUM(AE25:AE30) -> 285
A35: FB - US & CA | B35: =5148.04+212.45 -> 5360.49 | C35: =4523.38+213.8 -> 4737.18 | D35: =6281.28+214.38 -> 6495.66 | E35: =7130.14+314.25 -> 7444.39 | F35: =9523.05+425.64 -> 9948.69 | G35: =10243.07+411.17 -> 10654.24 | H35: =4678.28+192.12 -> 4870.4 | I35: 2686.43 | J35: 4453.73 | K35: 7934.61 | L35: 7938.61 | M35: 7224.58 | N35: 6434.49 | O35: 4665.45 | P35: 5085.26 | Q35: 5306.87 | R35: 5557.57 | S35: 5291.59 | T35: 5637.88 | U35: 4633.57 | V35: 4778.31 | W35: 5026.69 | X35: 6492.73 | Y35: 8338.56 | Z35: 7339.68 | AA35: 6794.39 | AB35: 4723.67 | AC35: 3688.31 | AD35: 4859.14 | AE35: 5765.64
A36: Google - WW | B36: 1211.12 | C36: 1401.64 | D36: 1710.2 | E36: 1317 | F36: 1357.2 | G36: 1340.41 | H36: 1379.91 | I36: 1350.77 | J36: 1446.61 | K36: 1925.14 | L36: 1897.8 | M36: 1863.85 | N36: 2181.78 | O36: 1588.03 | P36: 2151.14 | Q36: 2408.3 | R36: 2606.98 | S36: 2845.1 | T36: 2751.55 | U36: 2266 | V36: 2050.31 | W36: 1949 | X36: 2011.34 | Y36: 2159.48 | Z36: 1935.34 | AA36: 1646.91 | AB36: 1733.42 | AC36: 2080.01 | AD36: 1795.19 | AE36: 2141.16
A37: Bing - WW | B37: 183.94 | C37: 172.98 | D37: 228.88 | E37: 223.48 | F37: 230.68 | G37: 226.06 | H37: 224.23 | I37: 191.43 | J37: 355.52 | K37: 218.82 | L37: 224.14 | M37: 217.46 | N37: 212.7 | O37: 216.39 | P37: 191.06 | Q37: 221.71 | R37: 486.58 | S37: 238.96 | T37: 212.46 | U37: 207.49 | V37: 199.05 | W37: 212.03 | X37: 212.05 | Y37: 197.44 | Z37: 62.73 | AA37: 20.31 | AB37: 0 | AC37: 0 | AD37: 161.76 | AE37: 464.33
A38: TikTok - US & CA | B38: 0 | C38: 0 | D38: 0 | E38: 0 | F38: 0 | G38: 0 | H38: 0 | I38: 0 | J38: 0 | K38: 0 | L38: 0 | M38: 0 | N38: 0 | O38: 0 | P38: 0 | Q38: 0 | R38: 0 | S38: 0 | T38: 0 | U38: 0 | V38: 0 | W38: 0 | X38: 0 | Y38: 0 | Z38: 0 | AA38: 0 | AB38: 0 | AC38: 0 | AD38: 0 | AE38: 0
A39: Amazon Spend | B39: 1276.67 | C39: 1876.55 | D39: 2182.61 | E39: 1886.24 | F39: 1401.31 | G39: 1491.07 | H39: 1448.93 | I39: 1479.75 | J39: 1888.27 | K39: 2296.89 | L39: 1797.51 | M39: 1678.5 | N39: 1662.46 | O39: 1696.47 | P39: 1674.55 | Q39: 2303.3 | R39: 2443.56 | S39: 2161.34 | T39: 2309.42 | U39: 2091.87 | V39: 1920.72 | W39: 1492.52 | X39: 1881.18 | Y39: 2255.79 | Z39: 1672.88 | AA39: 1771.38 | AB39: 2743.88 | AC39: 3792.92 | AD39: 2832.22 | AE39: 3932.81
A40: Nextdoor Spend | B40: 0 | C40: 0 | D40: 0 | E40: 0 | F40: 0 | G40: 0 | H40: 0 | I40: 0 | J40: 0 | K40: 0 | L40: 190.92 | M40: 184.37 | N40: 347.34 | O40: 400.58 | P40: 527.61 | Q40: 503.39 | R40: 504.5 | S40: 501.28 | T40: 501.22 | U40: 335.16 | V40: 468.16 | W40: 377.74 | X40: 403.1 | Y40: 403 | Z40: 403.6 | AA40: 402.86 | AB40: 402.38 | AC40: 388.24 | AD40: 0.02
A41: IndieGoGo Spend | B41: 0 | C41: 0 | D41: 0 | E41: 0 | F41: 0 | G41: 337.21 | H41: 523.13 | I41: 709.35 | J41: 891.68 | K41: 1344.44 | L41: 1615.86 | M41: 1999.78 | N41: 2425.6 | O41: 2195.19 | P41: 1864.98 | Q41: 1526.04 | R41: 1583.49 | S41: 1406.57 | T41: 955.18 | U41: 90.8 | V41: 0 | W41: 0 | X41: 0 | Y41: 0 | Z41: 0 | AA41: 0 | AB41: 0 | AC41: 0 | AD41: 0 | AE41: 453.31
A42: Affiliate Fees - US | B42: 0 | C42: 0 | D42: 0 | E42: 47.81 | F42: 113.06 | G42: 62.55 | H42: 0 | I42: 0 | J42: 0 | K42: 149.78 | L42: 0 | M42: 0 | N42: 0 | O42: 139.61 | P42: 53.32 | Q42: 59.92 | R42: 53.62 | S42: 15.48 | T42: 59.05 | U42: 57.04 | V42: 0 | W42: 57.16 | X42: 0 | Y42: 26.91 | Z42: 0 | AA42: 0 | AB42: 0 | AC42: 0 | AD42: 0 | AE42: 0
A43: Total Web Spend | B43: =B35+B36+B37+B38+B40+B42 -> 6755.55 | C43: =C35+C36+C37+C38+C40+C42 -> 6311.8 | D43: =D35+D36+D37+D38+D40+D42 -> 8434.74 | E43: =E35+E36+E37+E38+E40+E42 -> 9032.68 | F43: =F35+F36+F37+F38+F40+F42 -> 11649.63 | G43: =G35+G36+G37+G38+G40+G42 -> 12283.26 | H43: =H35+H36+H37+H38+H40+H42 -> 6474.54 | I43: =I35+I36+I37+I38+I40+I42 -> 4228.63 | ... AE43: =AE35+AE36+AE37+AE38+AE40+AE42 -> 8371.13
A44: Total Spend | B44: =SUM(B35:B42) -> 8032.22 | C44: =SUM(C35:C42) -> 8188.35 | D44: =SUM(D35:D42) -> 10617.35 | E44: =SUM(E35:E42) -> 10918.92 | F44: =SUM(F35:F42) -> 13050.94 | G44: =SUM(G35:G42) -> 14111.54 | H44: =SUM(H35:H42) -> 8446.6 | I44: =SUM(I35:I42) -> 6417.73 | ... K44: =SUM(K35:K42) -> 13869.68 | L44: =SUM(L35:L42)+190.92 -> 13855.76 | M44: =SUM(M35:M42)+184.37 -> 13352.91 | N44: =SUM(N35:N42)+317.91 -> 13582.28 | O44: =SUM(O35:O42) -> 10901.72 | P44: =SUM(P35:P42) -> 11547.92 | Q44: =SUM(Q35:Q42) -> 12329.53 | R44: =SUM(R35:R42) -> 13236.3 | S44: =SUM(S35:S42) -> 12460.32 | T44: =SUM(T35:T42) -> 12426.76 | U44: =SUM(U35:U42) -> 9681.93 | V44: =SUM(V35:V42) -> 9416.55 | ... AE44: =SUM(AE35:AE42) -> 12757.25
A46: Blended ROAS | B46: =B23/B44 -> 2.5316388 | C46: =C23/C44 -> 3.2055701 | D46: =D23/D44 -> 3.3165441 | E46: =E23/E44 -> 4.0484105 | F46: =F23/F44 -> 2.9050957 | G46: =G23/G44 -> 2.2197733 | H46: =H23/H44 -> 2.5827019 | I46: =I23/I44 -> 3.5296935 | ... AE46: =AE23/AE44 -> 3.0226616
A47: wROAS | B47: =B8/B43 -> 2.5557771 | C47: =C8/C43 -> 3.7607861 | D47: =D8/D43 -> 3.6785852 | E47: =E8/E43 -> 4.2760587 | F47: =F8/F43 -> 2.7755585 | G47: =G8/G43 -> 2.0779028 | H47: =H8/H43 -> 2.5504592 | I47: =I8/I43 -> 3.7949927 | ... AE47: =AE8/AE43 -> 2.6036927
A48: aROAS | B48: =B15/B39 -> 2.4039102 | C48: =C15/C39 -> 1.3380938 | D48: =D15/D39 -> 1.9174291 | E48: =E15/E39 -> 2.9582662 | F48: =F15/F39 -> 3.9819883 | G48: =G15/G39 -> 2.9938232 | H48: =H15/H39 -> 2.5032265 | I48: =I15/I39 -> 1.8854536 | ... AE48: =AE15/AE39 -> 1.8444827
A49: igROAS | G49: =G14/G41 -> 3.9648883 | H49: =H14/H41 -> 3.201881 | I49: =I14/I41 -> 5.3781631 | J49: =J14/J41 -> 5.0545039 | K49: =K14/K41 -> 2.244057 | L49: =L14/L41 -> 3.091852 | M49: =M14/M41 -> 2.3667603 | N49: =N14/N41 -> 0.93502639 | ... AE49: =AE14/AE41 -> 2.14864
A51: Blended CAC | B51: =B44/B33 -> 38.067393 | C51: =C44/C33 -> 27.946587 | D51: =D44/D33 -> 27.223974 | E51: =E44/E33 -> 23.481548 | F51: =F44/F33 -> 34.344579 | G51: =G44/G33 -> 43.824658 | H51: =H44/H33 -> 39.655399 | I51: =I44/I33 -> 38.200774 | ... AE51: =AE44/AE33 -> 44.762281
A52: wCAC | B52: =B43/B25 -> 85.513291 | C52: =C43/C25 -> 57.38 | D52: =D43/D25 -> 62.479556 | E52: =E43/E25 -> 54.743515 | F52: =F43/F25 -> 78.185436 | G52: =G43/G25 -> 101.51455 | H52: =H43/H25 -> 81.956203 | I52: =I43/I25 -> 81.319808 | ... AE52: =AE43/AE25 -> 82.069902
A53: aCAC | B53: =B39/B30 -> 91.190714 | C53: =C39/C30 -> 268.07857 | D53: =D39/D30 -> 114.87421 | E53: =E39/E30 -> 82.010435 | F53: =F39/F30 -> 87.581875 | G53: =G39/G30 -> 74.5535 | H53: =H39/H30 -> 120.74417 | I53: =I39/I30 -> 123.3125 | ... AE53: =AE39/AE30 -> 131.09367
A54: igCAC | G54: =G41/G29 -> 84.3025 | H54: =H41/H29 -> 87.188333 | I54: =I41/I29 -> 64.486364 | J54: =J41/J29 -> 68.590769 | K54: =K41/K29 -> 112.03667 | L54: =L41/L29 -> 107.724 | M54: =M41/M29 -> 153.82923 | N54: =N41/N29 -> 303.2 | ... AE54: =AE41/AE29 -> 113.3275
A56: Web CR | B56: 0.0098 | C56: 0.0073 | D56: 0.0125 | E56: 0.0167 | F56: 0.0166 | G56: 0.0131 | H56: 0.0117 | I56: 0.0122 | J56: 0.0109 | K56: 0.0112 | L56: 0.0094 | M56: 0.0083 | N56: 0.0116 | O56: 0.0175 | P56: 0.0169 | Q56: 0.0127 | R56: 0.0137 | S56: 0.0528 | T56: 0.0163 | U56: 0.013 | V56: 0.0112 | W56: 0.013 | X56: 0.0142 | Y56: 0.0123 | Z56: 0.0158 | AA56: 0.012 | AB56: 0.0183 | AC56: 0.0122 | AD56: 0.0125 | AE56: 0.0129
A57: Web AOV | B57: =B8/B25 -> 218.55291 | C57: =C8/C25 -> 215.79391 | D57: =D8/D25 -> 229.83637 | E57: =E8/E25 -> 234.08648 | F57: =F8/F25 -> 217.00825 | G57: =G8/G25 -> 210.93736 | H57: =H8/H25 -> 209.02595 | I57: =I8/I25 -> 308.60808 | ... AE57: =AE8/AE25 -> 213.6848
A58: fAOV | B58: 189.6 | C58: 194.16 | D58: 198.48 | E58: 196.24 | F58: 195.17 | G58: 185.41 | H58: 207.92 | I58: 244.25 | J58: 251.37 | K58: 227.1 | L58: 215.46 | M58: 231.35 | N58: 230.3 | O58: 231.34 | P58: 207.68 | Q58: 209.88 | R58: 214.07 | S58: 72.46 | T58: 95.3 | U58: 130.22 | V58: 145.66 | W58: 148.39 | X58: 158.58 | Y58: 163.4 | Z58: 182.68 | AA58: 153.45 | AB58: 191.57 | AC58: 179.23 | AD58: 213.57 | AE58: 220.43
A59: rAOV | B59: 109.88 | C59: 124 | D59: 93.26 | E59: 80.73 | F59: 149.37 | G59: 162.04 | H59: 89.83 | I59: 53 | J59: 41.5 | K59: 181.17 | L59: 138.8 | M59: 191.19 | N59: 0 | O59: 179.17 | P59: 123.39 | Q59: 45 | R59: 278.55 | S59: 51.8 | T59: 68 | U59: 42.57 | V59: 68.4 | W59: 95.69 | X59: 46.33 | Y59: 108.67 | Z59: 107.48 | AA59: 116.05 | AB59: 261.56 | AC59: 117.37 | AD59: 109.41 | AE59: 110.32
A61: Customers
A62: Returning | B62: 0.0633 | C62: 0.0727 | D62: 0.1037 | E62: 0.0667 | F62: 0.047 | G62: 0.0744 | H62: 0.038 | I62: 0.0192 | J62: 0.0192 | K62: 0.0645 | L62: 0.0595 | M62: 0.1014 | N62: 0 | O62: 0.038 | P62: 0.1099 | Q62: 0.0581 | R62: 0.0244 | S62: 0.1482 | T62: 0.1042 | U62: 0.1214 | V62: 0.0741 | W62: 0.1092 | X62: 0.0976 | Y62: 0.0682 | Z62: 0.1765 | AA62: 0.1327 | AB62: 0.1667 | AC62: 0.1262 | AD62: 0.09 | AE62: 0.098
A63: First-time | B63: =1-B62 -> 0.9367 | C63: =1-C62 -> 0.9273 | D63: =1-D62 -> 0.8963 | E63: =1-E62 -> 0.9333 | F63: =1-F62 -> 0.953 | G63: =1-G62 -> 0.9256 | H63: =1-H62 -> 0.962 | I63: =1-I62 -> 0.9808 | ... AE63: =1-AE62 -> 0.902
A65: Post-purchase Survey
A66: Facebook / Instagram | B66: ='OLD Formulas'!U13 -> 0.27272727 | C66: ='OLD Formulas'!V13 -> 0.29577465 | D66: ='OLD Formulas'!W13 -> 0.35714286 | E66: ='OLD Formulas'!X13 -> 0.31313131 | F66: ='OLD Formulas'!Y13 -> 0.2025 | G66: ='OLD Formulas'!Z13 -> 0.38095238 | H66: ='OLD Formulas'!AA13 -> 0.35294118 | I66: ='OLD Formulas'!AB13 -> 0.40540541 | ... AE66: ='OLD Formulas'!AX13 -> 0.43055556
A67: Friends / Family | B67: ='OLD Formulas'!U14 -> 0.56363636 | C67: ='OLD Formulas'!V14 -> 0.50704225 | D67: ='OLD Formulas'!W14 -> 0.56122449 | E67: ='OLD Formulas'!X14 -> 0.35353535 | F67: ='OLD Formulas'!Y14 -> 0.4425 | G67: ='OLD Formulas'!Z14 -> 0.53571429 | H67: ='OLD Formulas'!AA14 -> 0.50980392 | I67: ='OLD Formulas'!AB14 -> 0.51351351 | ... AE67: ='OLD Formulas'!AX14 -> 0.43055556
A68: TikTok | B68: ='OLD Formulas'!U15 -> 0.018181818 | C68: ='OLD Formulas'!V15 -> 0.014084507 | D68: ='OLD Formulas'!W15 -> 0 | E68: ='OLD Formulas'!X15 -> 0.065656566 | F68: ='OLD Formulas'!Y15 -> 0.0675 | G68: ='OLD Formulas'!Z15 -> 0 | H68: ='OLD Formulas'!AA15 -> 0.039215686 | I68: ='OLD Formulas'!AB15 -> 0 | ... AE68: ='OLD Formulas'!AX15 -> 0
A69: TV / Radio | B69: ='OLD Formulas'!U16 -> 0.018181818 | C69: ='OLD Formulas'!V16 -> 0 | D69: ='OLD Formulas'!W16 -> 0.020408163 | E69: ='OLD Formulas'!X16 -> 0 | F69: ='OLD Formulas'!Y16 -> 0.2025 | G69: ='OLD Formulas'!Z16 -> 0.011904762 | H69: ='OLD Formulas'!AA16 -> 0.019607843 | I69: ='OLD Formulas'!AB16 -> 0 | ... AE69: ='OLD Formulas'!AX16 -> 0.013888889
A70: Blog / Article | B70: ='OLD Formulas'!U17 -> 0.018181818 | C70: ='OLD Formulas'!V17 -> 0.056338028 | D70: ='OLD Formulas'!W17 -> 0.040816327 | E70: ='OLD Formulas'!X17 -> 0.18686869 | F70: ='OLD Formulas'!Y17 -> 0.07 | G70: ='OLD Formulas'!Z17 -> 0.035714286 | H70: ='OLD Formulas'!AA17 -> 0.019607843 | I70: ='OLD Formulas'!AB17 -> 0.027027027 | ... AE70: ='OLD Formulas'!AX17 -> 0.041666667
A71: Reddit | B71: ='OLD Formulas'!U18 -> 0 | C71: ='OLD Formulas'!V18 -> 0 | D71: ='OLD Formulas'!W18 -> 0 | E71: ='OLD Formulas'!X18 -> 0 | F71: ='OLD Formulas'!Y18 -> 0.0025 | G71: ='OLD Formulas'!Z18 -> 0.023809524 | H71: ='OLD Formulas'!AA18 -> 0.019607843 | I71: ='OLD Formulas'!AB18 -> 0.027027027 | ... AE71: ='OLD Formulas'!AX18 -> 0
A72: Google, Youtube | B72: ='OLD Formulas'!U19 -> 0.090909091 | C72: ='OLD Formulas'!V19 -> 0.12676056 | D72: ='OLD Formulas'!W19 -> 0.020408163 | E72: ='OLD Formulas'!X19 -> 0.080808081 | F72: ='OLD Formulas'!Y19 -> 0.01 | G72: ='OLD Formulas'!Z19 -> 0.011904762 | H72: ='OLD Formulas'!AA19 -> 0.039215686 | I72: ='OLD Formulas'!AB19 -> 0.027027027 | ... AE72: ='OLD Formulas'!AX19 -> 0.055555556
A73: Yahoo, Bing | B73: ='OLD Formulas'!U20 -> 0.018181818 | C73: ='OLD Formulas'!V20 -> 0 | D73: ='OLD Formulas'!W20 -> 0 | E73: ='OLD Formulas'!X20 -> 0 | F73: ='OLD Formulas'!Y20 -> 0.0025 | G73: ='OLD Formulas'!Z20 -> 0 | H73: ='OLD Formulas'!AA20 -> 0 | I73: ='OLD Formulas'!AB20 -> 0 | ... AE73: ='OLD Formulas'!AX20 -> 0.027777778
B75: 45170 | C75: Goal | D75: % of Goal
A76: Revenue | B76: =SUM(B23:AE23) -> 1050842.3 | C76: 1450000 | D76: =B76/C76 -> 0.72471881
A77: Spend | B77: =SUM(B44:AE44) -> 332986.33 | C77: 500000 | D77: =B77/C77 -> 0.66597266
A78: ROAS | B78: =B76/B77 -> 3.155812 | C78: 3 | D78: =B78/C78 -> 1.0519373
A79: CAC | B79: =SUM(B44:AE44)/SUM(B33:AE33) -> 31.079553
A80: CR | B80: =AVERAGE(B56:AE56) -> 0.014286667
A81: AOV | B81: =B76/B84 -> 98.081227
A82: fAOV | B82: =AVERAGE(B58:AE58) -> 189.49067
A83: rAOV | B83: =AVERAGE(B59:AE59) -> 111.48433
A84: Orders | B84: =SUM(B33:AE33) -> 10714
A85: Units Sold | B85: ='OLD Detailed Report'!AF149 +'OLD AMAZON Detailed Report'!AF43 -> 2958 | C85: 3500 | D85: =B85/C85 -> 0.84514286
A86: CAC per Unit | B86: =B77/B85 -> 112.57144
A87: First-time customers | B87: =AVERAGE(B63:AE63) -> 0.91756667
A88: Returning customers | B88: =AVERAGE(B62:AE62) -> 0.082433333

Sheet OLD Detailed Report
A1: SEPTEMBER | B1: 45170 | C1: 45171 | D1: 45172 | E1: 45173 | F1: 45174 | G1: 45175 | H1: 45176 | I1: 45177 | J1: 45178 | K1: 45179 | L1: 45180 | M1: 45181 | N1: 45182 | O1: 45183 | P1: 45184 | Q1: 45185 | R1: 45186 | S1: 45187 | T1: 45188 | U1: 45189 | V1: 45190 | W1: 45191 | X1: 45192 | Y1: 45193 | Z1: 45194 | AA1: 45195 | AB1: 45196 | AC1: 45197 | AD1: 45198 | AE1: 45199
A2: DAY | B2: FRI | C2: SAT | D2: SUN | E2: MON | F2: TUE | G2: WED | H2: THU | I2: FRI | J2: SAT | K2: SUN | L2: MON | M2: TUE | N2: WED | O2: THU | P2: FRI | Q2: SAT | R2: SUN | S2: MON | T2: TUE | U2: WED | V2: THU | W2: FRI | X2: SAT | Y2: SUN | Z2: MON | AA2: TUE | AB2: WED | AC2: THU | AD2: FRI | AE2: SAT
A3: COMMENT
A4: Orders
A5: FB (US & CA) | B5: 15 | C5: 22 | D5: 30 | E5: 40 | F5: 43 | G5: 38 | H5: 15 | I5: 6 | J5: 18 | K5: 22 | L5: 32 | M5: 19 | N5: 16 | O5: 18 | P5: 21 | Q5: 22 | R5: 15 | S5: 28 | T5: 21 | U5: 28 | V5: 14 | W5: 14 | X5: 13 | Y5: 21 | Z5: 15 | AA5: 14 | AB5: 11 | AC5: 13 | AD5: 16 | AE5: 16 | AF5: =SUM(B5:AE5) -> 616
A6: Google | B6: 28 | C6: 29 | D6: 44 | E6: 35 | F6: 51 | G6: 40 | H6: 17 | I6: 12 | J6: 15 | K6: 19 | L6: 19 | M6: 19 | N6: 18 | O6: 17 | P6: 31 | Q6: 24 | R6: 24 | S6: 54 | T6: 40 | U6: 27 | V6: 25 | W6: 21 | X6: 30 | Y6: 25 | Z6: 24 | AA6: 16 | AB6: 17 | AC6: 18 | AD6: 20 | AE6: 27 | AF6: =SUM(B6:AE6) -> 786
A7: TikTok | B7: 0 | C7: 0 | D7: 0 | E7: 0 | F7: 0 | G7: 0 | H7: 0 | I7: 0 | J7: 0 | K7: 0 | L7: 0 | M7: 0 | N7: 0 | O7: 0 | P7: 0 | Q7: 0 | R7: 0 | S7: 0 | T7: 0 | U7: 0 | V7: 0 | W7: 0 | X7: 0 | Y7: 0 | Z7: 0 | AA7: 0 | AB7: 0 | AC7: 0 | AD7: 0 | AE7: 0 | AF7: =SUM(B7:AE7) -> 0
A8: Bing | B8: 3 | C8: 0 | D8: 2 | E8: 2 | F8: 5 | G8: 1 | H8: 2 | I8: 2 | J8: 1 | K8: 2 | L8: 1 | M8: 0 | N8: 0 | O8: 1 | P8: 3 | Q8: 2 | R8: 0 | S8: 0 | T8: 0 | U8: 2 | V8: 0 | W8: 1 | X8: 1 | Y8: 3 | Z8: 0 | AA8: 0 | AB8: 0 | AC8: 0 | AD8: 1 | AE8: 2 | AF8: =SUM(B8:AE8) -> 37
A9: MNTN TV | AF9: =SUM(B9:AE9) -> 0
A10: Affiliates (Refersion) | B10: 0 | C10: 0 | D10: 0 | E10: 1 | F10: 2 | G10: 1 | H10: 0 | I10: 0 | J10: 0 | K10: 2 | L10: 0 | M10: 0 | N10: 0 | O10: 2 | P10: 1 | Q10: 2 | R10: 1 | S10: 1 | T10: 1 | U10: 1 | V10: 0 | W10: 1 | X10: 0 | Y10: 1 | Z10: 0 | AA10: 0 | AB10: 0 | AC10: 0 | AD10: 0 | AE10: 0 | AF10: =SUM(B10:AE10) -> 17
A11: FB (Internal Paid) | AF11: =SUM(B11:AE11) -> 0
A12: FB (EU & UK) | AF12: =SUM(B12:AE12) -> 0
A13: Email | B13: 1 | C13: 1 | D13: 1 | E13: 2 | F13: 2 | G13: 1 | H13: 0 | I13: 2 | J13: 0 | K13: 1 | L13: 2 | M13: 0 | N13: 0 | O13: 0 | P13: 0 | Q13: 0 | R13: 0 | S13: 100 | T13: 87 | U13: 26 | V13: 25 | W13: 21 | X13: 19 | Y13: 13 | Z13: 8 | AA13: 7 | AB13: 30 | AC13: 17 | AD13: 10 | AE13: 4 | AF13: =SUM(B13:AE13) -> 380
A14: Amazon (market place)
A15: All | B15: =SUM(B5:B14) -> 47 | C15: =SUM(C5:C14) -> 52 | D15: =SUM(D5:D14) -> 77 | E15: =SUM(E5:E14) -> 80 | F15: =SUM(F5:F14) -> 103 | G15: =SUM(G5:G14) -> 81 | H15: =SUM(H5:H14) -> 34 | I15: =SUM(I5:I14) -> 22 | ... AE15: =SUM(AE5:AE14) -> 49 | AF15: =SUM(B15:AE15) -> 1836
A17: Revenue
A18: FB (US & CA) | B18: 3497.37 | C18: 5265.83 | D18: 7524.14 | E18: 10296.92 | F18: 10673.07 | G18: 7133.14 | H18: 3830.67 | I18: 1036.41 | J18: 4423.39 | K18: 5932.72 | L18: 8645.01 | M18: 5165.91 | N18: 4538.72 | O18: 4438.45 | P18: 6109.43 | Q18: 5515.95 | R18: 3565.7 | S18: 6694.41 | T18: 4099.74 | U18: 6126.12 | V18: 3225.27 | W18: 3809.63 | X18: 3668.48 | Y18: 6060.96 | Z18: 4447.05 | AA18: 3047.71 | AB18: 2761.56 | AC18: 3511.88 | AD18: 4578.1 | AE18: 4503.75 | AF18: =SUM(B18:AE18) -> 154127.49
A19: Google | B19: 6181.08 | C19: 6015.66 | D19: 8762.93 | E19: 7217.28 | F19: 11706.1 | G19: 8056.21 | H19: 4202.22 | I19: 2822.74 | J19: 5155.38 | K19: 5280.71 | L19: 4378.12 | M19: 5210.25 | N19: 4370.41 | O19: 4145.34 | P19: 6701.52 | Q19: 5228.11 | R19: 5375.63 | S19: 8642.5 | T19: 6544.65 | U19: 5677.68 | V19: 6028.01 | W19: 4044.3 | X19: 6569.26 | Y19: 6028.13 | Z19: 5778.78 | AA19: 3674.95 | AB19: 3877.96 | AC19: 4371.97 | AD19: 4640.51 | AE19: 7634.69 | AF19: =SUM(B19:AE19) -> 174323.08
A20: TikTok | B20: 0 | C20: 0 | D20: 0 | E20: 0 | F20: 0 | G20: 0 | H20: 0 | I20: 0 | J20: 0 | K20: 0 | L20: 0 | M20: 0 | N20: 0 | O20: 0 | P20: 0 | Q20: 0 | R20: 0 | S20: 0 | T20: 0 | U20: 0 | V20: 0 | W20: 0 | X20: 0 | Y20: 0 | Z20: 0 | AA20: 0 | AB20: 0 | AC20: 0 | AD20: 0 | AE20: 0 | AF20: =SUM(B20:AE20) -> 0
A21: Bing | B21: 281.14 | C21: 0 | D21: 507.32 | E21: 282.49 | F21: 844.05 | G21: 183.17 | H21: 310.1 | I21: 586.53 | J21: 392.99 | K21: 334.74 | L21: 111.78 | M21: 0 | N21: 0 | O21: 204.71 | P21: 581.01 | Q21: 597.07 | R21: 0 | S21: 0 | T21: 0 | U21: 135.28 | V21: 0 | W21: 303.49 | X21: 328 | Y21: 2259 | Z21: 753 | AA21: 251 | AB21: 0 | AC21: 0 | AD21: 298.53 | AE21: 337.37 | AF21: =SUM(B21:AE21) -> 9882.77
A22: MNTN TV | AF22: =SUM(B22:AE22) -> 0
A23: Affiliates (Refersion) | B23: 0 | C23: 0 | D23: 0 | E23: 191.22 | F23: 500.33 | G23: 250.2 | H23: 0 | I23: 0 | J23: 0 | K23: 656.14 | L23: 0 | M23: 0 | N23: 0 | O23: 558.43 | P23: 266.62 | Q23: 299.58 | R23: 268.11 | S23: 77.38 | T23: 295.24 | U23: 285.19 | V23: 0 | W23: 285.82 | X23: 0 | Y23: 134.53 | Z23: 0 | AA23: 0 | AB23: 0 | AC23: 0 | AD23: 0 | AE23: 0 | AF23: =SUM(B23:AE23) -> 4068.79
A24: FB (Internal Paid) | AF24: =SUM(B24:AE24) -> 0
A25: FB (EU & UK) | AF25: =SUM(B25:AE25) -> 0
A26: Email | B26: 31.54 | C26: 194.2 | D26: 325.4 | E26: 299.73 | F26: 758.64 | G26: 30.22 | H26: 0 | I26: 284.54 | J26: 0 | K26: 227.14 | L26: 272.9 | M26: 0 | N26: 0 | O26: 0 | P26: 0 | Q26: 0 | R26: 0 | S26: 6715.03 | T26: 4691.16 | U26: 1885.65 | V26: 2249.89 | W26: 2177.45 | X26: 912.06 | Y26: 712.15 | Z26: 731.4 | AA26: 720.45 | AB26: 8391.12 | AC26: 3445.83 | AD26: 2534.36 | AE26: 1006.28 | AF26: =SUM(B26:AE26) -> 38597.14
A27: Amazon (market place)
A28: All | B28: =SUM(B18:B27) -> 9991.13 | C28: =SUM(C18:C27) -> 11475.69 | D28: =SUM(D18:D27) -> 17119.79 | E28: =SUM(E18:E27) -> 18287.64 | F28: =SUM(F18:F27) -> 24482.19 | G28: =SUM(G18:G27) -> 15652.94 | H28: =SUM(H18:H27) -> 8342.99 | I28: =SUM(I18:I27) -> 4730.22 | ... AE28: =SUM(AE18:AE27) -> 13482.09 | AF28: =SUM(B28:AE28) -> 380999.27
A30: Media Cost
A31: FB Spend (US & CA) | B31: ='OLD Sales'!B35 -> 5360.49 | C31: ='OLD Sales'!C35 -> 4737.18 | D31: ='OLD Sales'!D35 -> 6495.66 | E31: ='OLD Sales'!E35 -> 7444.39 | F31: ='OLD Sales'!F35 -> 9948.69 | G31: ='OLD Sales'!G35 -> 10654.24 | H31: ='OLD Sales'!H35 -> 4870.4 | I31: ='OLD Sales'!I35 -> 2686.43 | ... AE31: ='OLD Sales'!AE35 -> 5765.64 | AF31: =SUM(B31:AE31) -> 180168.81
A32: Google Spend | B32: ='OLD Sales'!B36 -> 1211.12 | C32: ='OLD Sales'!C36 -> 1401.64 | D32: ='OLD Sales'!D36 -> 1710.2 | E32: ='OLD Sales'!E36 -> 1317 | F32: ='OLD Sales'!F36 -> 1357.2 | G32: ='OLD Sales'!G36 -> 1340.41 | H32: ='OLD Sales'!H36 -> 1379.91 | I32: ='OLD Sales'!I36 -> 1350.77 | ... AE32: ='OLD Sales'!AE36 -> 2141.16 | AF32: =SUM(B32:AE32) -> 56502.69
A33: TikTok Spend | B33: ='OLD Sales'!B38 -> 0 | C33: ='OLD Sales'!C38 -> 0 | D33: ='OLD Sales'!D38 -> 0 | E33: ='OLD Sales'!E38 -> 0 | F33: ='OLD Sales'!F38 -> 0 | G33: ='OLD Sales'!G38 -> 0 | H33: ='OLD Sales'!H38 -> 0 | I33: ='OLD Sales'!I38 -> 0 | ... O33: ='OLD Sales'!O38 -> 0 | P33: ='OLD Sales'!P39 -> 1674.55 | Q33: ='OLD Sales'!Q38 -> 0 | R33: ='OLD Sales'!R38 -> 0 | S33: ='OLD Sales'!S38 -> 0 | T33: ='OLD Sales'!T38 -> 0 | U33: ='OLD Sales'!U38 -> 0 | V33: ='OLD Sales'!V38 -> 0 | W33: ='OLD Sales'!W38 -> 0 | X33: ='OLD Sales'!X38 -> 0 | ... AE33: ='OLD Sales'!AE38 -> 0 | AF33: =SUM(B33:AE33) -> 1674.55
A34: Bing Spend | B34: ='OLD Sales'!B37 -> 183.94 | C34: ='OLD Sales'!C37 -> 172.98 | D34: ='OLD Sales'!D37 -> 228.88 | E34: ='OLD Sales'!E37 -> 223.48 | F34: ='OLD Sales'!F37 -> 230.68 | G34: ='OLD Sales'!G37 -> 226.06 | H34: ='OLD Sales'!H37 -> 224.23 | I34: ='OLD Sales'!I37 -> 191.43 | ... AE34: ='OLD Sales'!AE37 -> 464.33 | AF34: =SUM(B34:AE34) -> 6214.67
A35: MNTN TV | B35: ='OLD Sales'!B39 -> 1276.67 | C35: ='OLD Sales'!C39 -> 1876.55 | D35: ='OLD Sales'!D39 -> 2182.61 | E35: ='OLD Sales'!E39 -> 1886.24 | F35: ='OLD Sales'!F39 -> 1401.31 | G35: ='OLD Sales'!G39 -> 1491.07 | H35: ='OLD Sales'!H39 -> 1448.93 | I35: ='OLD Sales'!I39 -> 1479.75 | ... O35: ='OLD Sales'!O39 -> 1696.47 | Q35: ='OLD Sales'!Q39 -> 2303.3 | R35: ='OLD Sales'!R39 -> 2443.56 | S35: ='OLD Sales'!S39 -> 2161.34 | T35: ='OLD Sales'!T39 -> 2309.42 | U35: ='OLD Sales'!U39 -> 2091.87 | V35: ='OLD Sales'!V39 -> 1920.72 | W35: ='OLD Sales'!W39 -> 1492.52 | X35: ='OLD Sales'!X39 -> 1881.18 | ... AE35: ='OLD Sales'!AE39 -> 3932.81 | AF35: =SUM(B35:AE35) -> 59669.02
A36: Fee 15% Purchase (Backerkit) | B36: =B22*0.15 -> 0 | C36: =C22*0.15 -> 0 | D36: =D22*0.15 -> 0 | E36: =E22*0.15 -> 0 | F36: =F22*0.15 -> 0 | G36: =G22*0.15 -> 0 | H36: =H22*0.15 -> 0 | I36: =I22*0.15 -> 0 | ... S36: =S22*0.15 -> 0 | U36: =U22*0.15 -> 0 | V36: =V22*0.15 -> 0 | W36: =W22*0.15 -> 0 | X36: =X22*0.15 -> 0 | Y36: =Y22*0.15 -> 0 | Z36: =Z22*0.15 -> 0 | AA36: =AA22*0.15 -> 0 | AB36: =AB22*0.15 -> 0 | AC36: =AC22*0.15 -> 0 | AF36: =SUM(B36:AE36) -> 0
A37: Google Management Fee | AF37: =SUM(B37:AE37) -> 0
A38: Affiliates Agency Payment (Grovia) | AF38: =SUM(B38:AE38) -> 0
A39: Affiliate Fee 20% (Grovia) | B39: ='OLD Sales'!B42 -> 0 | C39: ='OLD Sales'!C42 -> 0 | D39: ='OLD Sales'!D42 -> 0 | E39: ='OLD Sales'!E42 -> 47.81 | F39: ='OLD Sales'!F42 -> 113.06 | G39: ='OLD Sales'!G42 -> 62.55 | H39: ='OLD Sales'!H42 -> 0 | I39: ='OLD Sales'!I42 -> 0 | ... AE39: ='OLD Sales'!AE42 -> 0 | AF39: =SUM(B39:AE39) -> 895.31
A40: FB Spend (Internal Paid) | AF40: =SUM(B40:AE40) -> 0
A41: FB Spend (EU & UK) | AF41: =SUM(B41:AE41) -> 0
A42: Pinterest Spend | AF42: =SUM(B42:AE42) -> 0
A43: Amazon (market place) Spend
A44: Amazon (market place) Sales Fee (10-15 %) | B44: =B27*'OLD Formulas'!$C$41 -> 0 | C44: =C27*'OLD Formulas'!$C$41 -> 0 | D44: =D27*'OLD Formulas'!$C$41 -> 0 | E44: =E27*'OLD Formulas'!$C$41 -> 0 | F44: =F27*'OLD Formulas'!$C$41 -> 0 | G44: =G27*'OLD Formulas'!$C$41 -> 0 | H44: =H27*'OLD Formulas'!$C$41 -> 0 | I44: =I27*'OLD Formulas'!$C$41 -> 0 | ... AE44: =AE27*'OLD Formulas'!$C$41 -> 0
A45: Platform Fee (6,90%) | AF45: =SUM(B45:AE45) -> 0
A46: All | B46: =SUM(B31:B45) -> 8032.22 | C46: =SUM(C31:C45) -> 8188.35 | D46: =SUM(D31:D45) -> 10617.35 | E46: =SUM(E31:E45) -> 10918.92 | F46: =SUM(F31:F45) -> 13050.94 | G46: =SUM(G31:G45) -> 13774.33 | H46: =SUM(H31:H45) -> 7923.47 | I46: =SUM(I31:I45) -> 5708.38 | ... AE46: =SUM(AE31:AE45) -> 12303.94 | AF46: =SUM(B46:AE46) -> 305125.05
A48: Cost
A49: Average COGS ($92.18) | B49: =B15*'OLD Formulas'!$J$3 -> 4591.5403 | C49: =C15*'OLD Formulas'!$J$3 -> 5080.002 | D49: =D15*'OLD Formulas'!$J$3 -> 7522.3106 | E49: =E15*'OLD Formulas'!$J$3 -> 7815.3877 | F49: =F15*'OLD Formulas'!$J$3 -> 10062.312 | G49: =G15*'OLD Formulas'!$J$3 -> 7913.08 | H49: =H15*'OLD Formulas'!$J$3 -> 3321.5398 | I49: =I15*'OLD Formulas'!$J$3 -> 2149.2316 | ... AE49: =AE15*'OLD Formulas'!$J$3 -> 4786.925 | AF49: =SUM(B49:AE49) -> 179363.15
A50: Average Inbound Shipping ($13.06) | B50: =B15*'OLD Formulas'!$I$4 -> 613.7871 | C50: =C15*'OLD Formulas'!$I$4 -> 679.0836 | D50: =D15*'OLD Formulas'!$I$4 -> 1005.5661 | E50: =E15*'OLD Formulas'!$I$4 -> 1044.744 | F50: =F15*'OLD Formulas'!$I$4 -> 1345.1079 | G50: =G15*'OLD Formulas'!$I$4 -> 1057.8033 | H50: =H15*'OLD Formulas'!$I$4 -> 444.0162 | I50: =I15*'OLD Formulas'!$I$4 -> 287.3046 | ... AE50: =AE15*'OLD Formulas'!$I$4 -> 639.9057 | AF50: =SUM(B50:AE50) -> 23976.875
A51: Average Outbound Shipping ($15.06) | B51: =B15*'OLD Formulas'!$I$5 -> 707.82 | C51: =C15*'OLD Formulas'!$I$5 -> 783.12 | D51: =D15*'OLD Formulas'!$I$5 -> 1159.62 | E51: =E15*'OLD Formulas'!$I$5 -> 1204.8 | F51: =F15*'OLD Formulas'!$I$5 -> 1551.18 | G51: =G15*'OLD Formulas'!$I$5 -> 1219.86 | H51: =H15*'OLD Formulas'!$I$5 -> 512.04 | I51: =I15*'OLD Formulas'!$I$5 -> 331.32 | ... AE51: =AE15*'OLD Formulas'!$I$5 -> 737.94 | AF51: =SUM(B51:AE51) -> 27650.16
A52: Average Taxes ($16.81) | B52: =B15*'OLD Formulas'!$I$6 -> 790.07 | C52: =C15*'OLD Formulas'!$I$6 -> 874.12 | D52: =D15*'OLD Formulas'!$I$6 -> 1294.37 | E52: =E15*'OLD Formulas'!$I$6 -> 1344.8 | F52: =F15*'OLD Formulas'!$I$6 -> 1731.43 | G52: =G15*'OLD Formulas'!$I$6 -> 1361.61 | H52: =H15*'OLD Formulas'!$I$6 -> 571.54 | I52: =I15*'OLD Formulas'!$I$6 -> 369.82 | ... AE52: =AE15*'OLD Formulas'!$I$6 -> 823.69 | AF52: =SUM(B52:AE52) -> 30863.16
A53: Processing Fee (2,90%) | B53: =B28*'OLD Formulas'!$L$3 -> 289.74277 | C53: =C28*'OLD Formulas'!$L$3 -> 332.79501 | D53: =D28*'OLD Formulas'!$L$3 -> 496.47391 | E53: =E28*'OLD Formulas'!$L$3 -> 530.34156 | F53: =F28*'OLD Formulas'!$L$3 -> 709.98351 | G53: =G28*'OLD Formulas'!$L$3 -> 453.93526 | H53: =H28*'OLD Formulas'!$L$3 -> 241.94671 | I53: =I28*'OLD Formulas'!$L$3 -> 137.17638 | ... AE53: =AE28*'OLD Formulas'!$L$3 -> 390.98061 | AF53: =SUM(B53:AE53) -> 11048.979
A54: Transaction Fee ($0.30) | B54: =B15*'OLD Formulas'!$I$10 -> 14.1 | C54: =C15*'OLD Formulas'!$I$10 -> 15.6 | D54: =D15*'OLD Formulas'!$I$10 -> 23.1 | E54: =E15*'OLD Formulas'!$I$10 -> 24 | F54: =F15*'OLD Formulas'!$I$10 -> 30.9 | G54: =G15*'OLD Formulas'!$I$10 -> 24.3 | H54: =H15*'OLD Formulas'!$I$10 -> 10.2 | I54: =I15*'OLD Formulas'!$I$10 -> 6.6 | ... AE54: =AE15*'OLD Formulas'!$I$10 -> 14.7 | AF54: =SUM(B54:AE54) -> 550.8
A55: All | B55: =SUM(B49:B54) -> 7007.0601 | C55: =SUM(C49:C54) -> 7764.7206 | D55: =SUM(D49:D54) -> 11501.441 | E55: =SUM(E49:E54) -> 11964.073 | F55: =SUM(F49:F54) -> 15430.913 | G55: =SUM(G49:G54) -> 12030.589 | H55: =SUM(H49:H54) -> 5101.2827 | I55: =SUM(I49:I54) -> 3281.4526 | ... AE55: =SUM(AE49:AE54) -> 7394.1413 | AF55: =SUM(B55:AE55) -> 273453.12
AF56: =SUM(B56:AE56) -> 0
A57: Partial Profit | B57: =B28-B46-B55 -> -5048.1501 | C57: =C28-C46-C55 -> -4477.3806 | D57: =D28-D46-D55 -> -4999.0007 | E57: =E28-E46-E55 -> -4595.3532 | F57: =F28-F46-F55 -> -3999.663 | G57: =G28-G46-G55 -> -10151.979 | H57: =H28-H46-H55 -> -4681.7627 | I57: =I28-I46-I55 -> -4259.6126 | ... AE57: =AE28-AE46-AE55 -> -6215.9913 | AF57: =SUM(B57:AE57) -> -197578.9
A58: =SUM(B57:AC57) -> -186699.29
A62: Performance Facebook US & CA | Z62: 3.11 | AA62: 1.8
A63: PROFIT | B63: =B18-(B5*'OLD Formulas'!$I$15)-B31 -> -4053.3187 | C63: =C18-(C5*'OLD Formulas'!$I$15)-C31 -> -2683.6415 | D63: =D18-(D5*'OLD Formulas'!$I$15)-D31 -> -3351.9174 | E63: =E18-(E5*'OLD Formulas'!$I$15)-E31 -> -2987.9999 | F63: =F18-(F5*'OLD Formulas'!$I$15)-F31 -> -5554.1897 | G63: =G18-(G5*'OLD Formulas'!$I$15)-G31 -> -9069.6034 | H63: =H18-(H5*'OLD Formulas'!$I$15)-H31 -> -3229.9287 | I63: =I18-(I5*'OLD Formulas'!$I$15)-I31 -> -2526.0995 | ... AE63: =AE18-(AE5*'OLD Formulas'!$I$15)-AE31 -> -3598.102 | AF63: =SUM(B63:AE63) -> -115985.48
A64: ROAS | B64: =B18/B31 -> 0.65243476 | C64: =C18/C31 -> 1.1115959 | D64: =D18/D31 -> 1.1583334 | E64: =E18/E31 -> 1.3831785 | F64: =F18/F31 -> 1.0728116 | G64: =G18/G31 -> 0.66951186 | H64: =H18/H31 -> 0.78652061 | I64: =I18/I31 -> 0.38579453 | ... AE64: =AE18/AE31 -> 0.78113618
A65: CPO | B65: =B31/B5 -> 357.366 | C65: =C31/C5 -> 215.32636 | D65: =D31/D5 -> 216.522 | E65: =E31/E5 -> 186.10975 | F65: =F31/F5 -> 231.36488 | G65: =G31/G5 -> 280.37474 | H65: =H31/H5 -> 324.69333 | I65: =I31/I5 -> 447.73833 | ... AE65: =AE31/AE5 -> 360.3525
A66: MER | B66: =B18/('OLD Formulas'!$I$15*B5+B31) -> 0.46318556 | C66: =C18/('OLD Formulas'!$I$15*C5+C31) -> 0.66241259 | D66: =D18/('OLD Formulas'!$I$15*D5+D31) -> 0.69180767 | E66: =E18/('OLD Formulas'!$I$15*E5+E31) -> 0.77508333 | F66: =F18/('OLD Formulas'!$I$15*F5+F31) -> 0.65772473 | G66: =G18/('OLD Formulas'!$I$15*G5+G31) -> 0.44024273 | H66: =H18/('OLD Formulas'!$I$15*H5+H31) -> 0.54254181 | I66: =I18/('OLD Formulas'!$I$15*I5+I31) -> 0.29092133 | ... AE66: =AE18/('OLD Formulas'!$I$15*AE5+AE31) -> 0.55589142
A68: Performance Google
A69: PROFIT | B69: =B19-(B6*'OLD Formulas'!$I$15)-B32 -> 881.58905 | C69: =C19-(C6*'OLD Formulas'!$I$15)-C32 -> 379.6358 | D69: =D19-(D6*'OLD Formulas'!$I$15)-D32 -> 628.14708 | E69: =E19-(E6*'OLD Formulas'!$I$15)-E32 -> 789.81631 | F69: =F19-(F6*'OLD Formulas'!$I$15)-F32 -> 2902.2243 | G69: =G19-(G6*'OLD Formulas'!$I$15)-G32 -> 875.27007 | H69: =H19-(H6*'OLD Formulas'!$I$15)-H32 -> 340.08478 | I69: =I19-(I6*'OLD Formulas'!$I$15)-I32 -> -280.18898 | ... AE69: =AE19-(AE6*'OLD Formulas'!$I$15)-AE32 -> 1551.1723 | AF69: =SUM(B69:AE69) -> 3053.9769
A70: ROAS | B70: =B19/B32 -> 5.1036066 | C70: =C19/C32 -> 4.2918724 | D70: =D19/D32 -> 5.1239212 | E70: =E19/E32 -> 5.4800911 | F70: =F19/F32 -> 8.6251842 | G70: =G19/G32 -> 6.0102581 | H70: =H19/H32 -> 3.0452856 | I70: =I19/I32 -> 2.0897266 | ... AE70: =AE19/AE32 -> 3.5656794
A71: CPO | B71: =B32/B6 -> 43.254286 | C71: =C32/C6 -> 48.332414 | D71: =D32/D6 -> 38.868182 | E71: =E32/E6 -> 37.628571 | F71: =F32/F6 -> 26.611765 | G71: =G32/G6 -> 33.51025 | H71: =H32/H6 -> 81.171176 | I71: =I32/I6 -> 112.56417 | ... AE71: =AE32/AE6 -> 79.302222
A72: MER | B72: =B19/('OLD Formulas'!$I$15*B6+B32) -> 1.1663535 | C72: =C19/('OLD Formulas'!$I$15*C6+C32) -> 1.0673588 | D72: =D19/('OLD Formulas'!$I$15*D6+D32) -> 1.0772174 | E72: =E19/('OLD Formulas'!$I$15*E6+E32) -> 1.1228815 | F72: =F19/('OLD Formulas'!$I$15*F6+F32) -> 1.329653 | G72: =G19/('OLD Formulas'!$I$15*G6+G32) -> 1.121888 | H72: =H19/('OLD Formulas'!$I$15*H6+H32) -> 1.0880562 | I72: =I19/('OLD Formulas'!$I$15*I6+I32) -> 0.90970178 | ... AE72: =AE19/('OLD Formulas'!$I$15*AE6+AE32) -> 1.2549795
A74: Performance TikTok
A75: PROFIT | B75: =B20-(B7*'OLD Formulas'!$I$15)-B33 -> 0 | C75: =C20-(C7*'OLD Formulas'!$I$15)-C33 -> 0 | D75: =D20-(D7*'OLD Formulas'!$I$15)-D33 -> 0 | E75: =E20-(E7*'OLD Formulas'!$I$15)-E33 -> 0 | F75: =F20-(F7*'OLD Formulas'!$I$15)-F33 -> 0 | G75: =G20-(G7*'OLD Formulas'!$I$15)-G33 -> 0 | H75: =H20-(H7*'OLD Formulas'!$I$15)-H33 -> 0 | I75: =I20-(I7*'OLD Formulas'!$I$15)-I33 -> 0 | ... AE75: =AE20-(AE7*'OLD Formulas'!$I$15)-AE33 -> 0 | AF75: =SUM(B75:AE75) -> -1674.55
A76: ROAS | B76: =B20/B33 -> #DIV/0! | C76: =C20/C33 -> #DIV/0! | D76: =D20/D33 -> #DIV/0! | E76: =E20/E33 -> #DIV/0! | F76: =F20/F33 -> #DIV/0! | G76: =G20/G33 -> #DIV/0! | H76: =H20/H33 -> #DIV/0! | I76: =I20/I33 -> #DIV/0! | ... AE76: =AE20/AE33 -> #DIV/0!
A77: CPO | B77: =B33/B7 -> #DIV/0! | C77: =C33/C7 -> #DIV/0! | D77: =D33/D7 -> #DIV/0! | E77: =E33/E7 -> #DIV/0! | F77: =F33/F7 -> #DIV/0! | G77: =G33/G7 -> #DIV/0! | H77: =H33/H7 -> #DIV/0! | I77: =I33/I7 -> #DIV/0! | ... AE77: =AE33/AE7 -> #DIV/0!
A78: MER | B78: =B20/('OLD Formulas'!$I$15*B7+B33) -> #DIV/0! | C78: =C20/('OLD Formulas'!$I$15*C7+C33) -> #DIV/0! | D78: =D20/('OLD Formulas'!$I$15*D7+D33) -> #DIV/0! | E78: =E20/('OLD Formulas'!$I$15*E7+E33) -> #DIV/0! | F78: =F20/('OLD Formulas'!$I$15*F7+F33) -> #DIV/0! | G78: =G20/('OLD Formulas'!$I$15*G7+G33) -> #DIV/0! | H78: =H20/('OLD Formulas'!$I$15*H7+H33) -> #DIV/0! | I78: =I20/('OLD Formulas'!$I$15*I7+I33) -> #DIV/0! | ... AE78: =AE20/('OLD Formulas'!$I$15*AE7+AE33) -> #DIV/0!
A80: Performance Bing
A81: PROFIT | B81: =B21-(B8*'OLD Formulas'!$I$15)-B34 -> -340.83974 | C81: =C21-(C8*'OLD Formulas'!$I$15)-C34 -> -172.98 | D81: =D21-(D8*'OLD Formulas'!$I$15)-D34 -> -13.586496 | E81: =E21-(E8*'OLD Formulas'!$I$15)-E34 -> -233.0165 | F81: =F21-(F8*'OLD Formulas'!$I$15)-F34 -> -116.69624 | G81: =G21-(G8*'OLD Formulas'!$I$15)-G34 -> -188.90325 | H81: =H21-(H8*'OLD Formulas'!$I$15)-H34 -> -206.1565 | I81: =I21-(I8*'OLD Formulas'!$I$15)-I34 -> 103.0735 | ... AE81: =AE21-(AE8*'OLD Formulas'!$I$15)-AE34 -> -418.9865 | AF81: =SUM(B81:AE81) -> -1734.3902
A82: ROAS | B82: =B21/B34 -> 1.5284332 | C82: =C21/C34 -> 0 | D82: =D21/D34 -> 2.2165327 | E82: =E21/E34 -> 1.2640505 | F82: =F21/F34 -> 3.6589648 | G82: =G21/G34 -> 0.81027161 | H82: =H21/H34 -> 1.382955 | I82: =I21/I34 -> 3.0639398 | ... AE82: =AE21/AE34 -> 0.72657377
A83: CPO | B83: =B34/B8 -> 61.313333 | C83: =C34/C8 -> #DIV/0! | D83: =D34/D8 -> 114.44 | E83: =E34/E8 -> 111.74 | F83: =F34/F8 -> 46.136 | G83: =G34/G8 -> 226.06 | H83: =H34/H8 -> 112.115 | I83: =I34/I8 -> 95.715 | ... AE83: =AE34/AE8 -> 232.165
A84: MER | B84: =B21/('OLD Formulas'!$I$15*B8+B34) -> 0.45200829 | C84: =C21/('OLD Formulas'!$I$15*C8+C34) -> 0 | D84: =D21/('OLD Formulas'!$I$15*D8+D34) -> 0.97391759 | E84: =E21/('OLD Formulas'!$I$15*E8+E34) -> 0.54798533 | F84: =F21/('OLD Formulas'!$I$15*F8+F34) -> 0.87853583 | G84: =G21/('OLD Formulas'!$I$15*G8+G34) -> 0.49229554 | H84: =H21/('OLD Formulas'!$I$15*H8+H34) -> 0.60067041 | I84: =I21/('OLD Formulas'!$I$15*I8+I34) -> 1.2132012 | ... AD84: =AD21/('OLD Formulas'!$I$15*AD8+AD34) -> 0.96996734 | AE84: =AE35/AE9 -> #DIV/0!
A86: MNTN TV
A87: PROFIT | B87: =B22-(B9*Formulas!$C32)-B35 -> #REF! | C87: =C22-(C9*Formulas!$C32)-C35 -> #REF! | D87: =D22-(D9*Formulas!$C32)-D35 -> #REF! | E87: =E22-(E9*Formulas!$C32)-E35 -> #REF! | F87: =F22-(F9*Formulas!$C32)-F35 -> #REF! | G87: =G22-(G9*Formulas!$C32)-G35 -> #REF! | H87: =H22-(H9*Formulas!$C32)-H35 -> #REF! | I87: =I22-(I9*Formulas!$C32)-I35 -> #REF! | ... AE87: =AE22-(AE9*Formulas!$C32)-AE35 -> #REF! | AF87: =SUM(B87:AE87) -> #REF!
A88: ROAS | B88: =B22/B35 -> 0 | C88: =C22/C35 -> 0 | D88: =D22/D35 -> 0 | E88: =E22/E35 -> 0 | F88: =F22/F35 -> 0 | G88: =G22/G35 -> 0 | H88: =H22/H35 -> 0 | I88: =I22/I35 -> 0 | ... AE88: =AE22/AE35 -> 0
A89: CPO | B89: =B35/B9 -> #DIV/0! | C89: =C35/C9 -> #DIV/0! | D89: =D35/D9 -> #DIV/0! | E89: =E35/E9 -> #DIV/0! | F89: =F35/F9 -> #DIV/0! | G89: =G35/G9 -> #DIV/0! | H89: =H35/H9 -> #DIV/0! | I89: =I35/I9 -> #DIV/0! | ... AE89: =AE35/AE9 -> #DIV/0!
A90: MER | B90: =B22/(Formulas!$C32*B9+B35) -> #REF! | C90: =C22/(Formulas!$C32*C9+C35) -> #REF! | D90: =D22/(Formulas!$C32*D9+D35) -> #REF! | E90: =E22/(Formulas!$C32*E9+E35) -> #REF! | F90: =F22/(Formulas!$C32*F9+F35) -> #REF! | G90: =G22/(Formulas!$C32*G9+G35) -> #REF! | H90: =H22/(Formulas!$C32*H9+H35) -> #REF! | I90: =I22/(Formulas!$C32*I9+I35) -> #REF! | ... AE90: =AE22/(Formulas!$C32*AE9+AE35) -> #REF!
A92: Affiliates (Grovia)
A93: PROFIT | AF93: =SUM(B93:AE93) -> 0
A94: ROAS
A95: CPO
A96: MER
A98: Performance Internal Paid
A99: PROFIT | AF99: =SUM(B99:AE99) -> 0
A100: ROAS
A101: CPO
A102: MER
A104: Performance EU & UK
A105: PROFIT | AF105: =SUM(B105:AE105) -> 0
A106: ROAS
A107: CPO
A108: MER
A111: Performance Email
A112: PROFIT | B112: =B26-(B13*'OLD Formulas'!$I$15) -> -114.47325 | C112: =C26-(C13*'OLD Formulas'!$I$15) -> 48.186752 | D112: =D26-(D13*'OLD Formulas'!$I$15) -> 179.38675 | E112: =E26-(E13*'OLD Formulas'!$I$15) -> 7.7035035 | F112: =F26-(F13*'OLD Formulas'!$I$15) -> 466.6135 | G112: =G26-(G13*'OLD Formulas'!$I$15) -> -115.79325 | H112: =H26-(H13*'OLD Formulas'!$I$15) -> 0 | I112: =I26-(I13*'OLD Formulas'!$I$15) -> -7.4864965 | ... AE112: =AE26-(AE13*'OLD Formulas'!$I$15) -> 422.22701 | AF112: =SUM(B112:AE112) -> -16887.894
A113: ROAS
A114: CPO
A115: MER | B115: =B26/('OLD Formulas'!$I$15*B13) -> 0.2160078 | C115: =C26/('OLD Formulas'!$I$15*C13) -> 1.3300163 | D115: =D26/('OLD Formulas'!$I$15*D13) -> 2.2285649 | E115: =E26/('OLD Formulas'!$I$15*E13) -> 1.0263795 | F115: =F26/('OLD Formulas'!$I$15*F13) -> 2.5978465 | G115: =G26/('OLD Formulas'!$I$15*G13) -> 0.20696752 | H115: =H26/('OLD Formulas'!$I$15*H13) -> #DIV/0! | I115: =I26/('OLD Formulas'!$I$15*I13) -> 0.97436364 | ... AE115: =AE26/('OLD Formulas'!$I$15*AE13) -> 1.7229259
...

Sheet OLD  Formulas
B1: Business Metrics
A2: Source | B2: COGS | E2: Attachment Rates | H2: Marketing Averages (per order) | K2: Fees | N2: VAT Averages | Q2: 30 Day Returns | T2: Post-purchase Survey | U2: 45170 | V2: 45171 | W2: 45172 | X2: 45173 | Y2: 45174 | Z2: 45175 | AA2: 45176 | AB2: 45177 | AC2: 45178 | AD2: 45179 | AE2: 45180 | AF2: 45181 | AG2: 45182 | AH2: 45183 | AI2: 45184 | AJ2: 45185 | AK2: 45186 | AL2: 45187 | AM2: 45188 | AN2: 45189 | AO2: 45190 | AP2: 45191 | AQ2: 45192 | AR2: 45193 | AS2: 45194 | AT2: 45195 | AU2: 45196 | AV2: 45197 | AW2: 45198 | AX2: 45199
B3: Bird Buddy | C3: 81.22 | D3: 86.9 | E3: Solar Roof | F3: =(('OLD Detailed Report'!AF179)/'OLD Detailed Report'!AF172) -> 0.064809855 | H3: COGS | I3: =(C3*F9)+(C4*F8)+(C5*F3)+(C6*F4)+(C7*F5)+(C8*F6)+(C9*F7) -> 90.994392 | J3: =(D3*F9)+(D4*F8)+(D5*F3)+(D6*F4)+(D7*F5)+(D8*F6)+(D9*F7) -> 97.692346 | K3: Processing Fee | L3: 0.029 | N3: Europe | O3: 0.22 | Q3: US Shipping | R3: 15 | T3: Facebook / Instagram | U3: 15 | V3: 21 | W3: 35 | X3: 62 | Y3: 81 | Z3: 32 | AA3: 18 | AB3: 15 | AC3: 15 | AD3: 22 | AE3: 29 | AF3: 18 | AG3: 23 | AH3: 14 | AI3: 22 | AJ3: 26 | AK3: 17 | AL3: 114 | AM3: 18 | AN3: 47 | AO3: 37 | AP3: 32 | AQ3: 32 | AR3: 29 | AS3: 7 | AT3: 0 | AU3: 0 | AV3: 9 | AW3: 28 | AX3: 31
B4: Bird Buddy with Solar Roof | C4: 91.14 | D4: 97.61 | E4: Wall Mount | F4: =('OLD Detailed Report'!AF174/'OLD Detailed Report'!AF172) -> 0.36743439 | H4: Inbound Shipping | I4: =C32+(D32*0.78) -> 13.0593 | K4: Duty | L4: 0.034 | N4: ROW | O4: 0.13 | Q4: EU Shipping | R4: 40 | T4: Friends / Family | U4: 31 | V4: 36 | W4: 55 | X4: 70 | Y4: 177 | Z4: 45 | AA4: 26 | AB4: 19 | AC4: 26 | AD4: 34 | AE4: 26 | AF4: 28 | AG4: 21 | AH4: 28 | AI4: 24 | AJ4: 27 | AK4: 28 | AL4: 132 | AM4: 42 | AN4: 58 | AO4: 25 | AP4: 28 | AQ4: 34 | AR4: 41 | AS4: 16 | AT4: 0 | AU4: 0 | AV4: 17 | AW4: 33 | AX4: 31
B5: Solar Roof Single | C5: 10.5 | D5: 13.44 | E5: Fence Mount | F5: =('OLD Detailed Report'!AF175)/'OLD Detailed Report'!AF172 -> 0 | H5: Outbound Shipping | I5: =C28 -> 15.06 | K5: China Tax | L5: 0.075 | N5: NA | Q5: ROW Shipping | R5: 20 | T5: TikTok | U5: 1 | V5: 1 | W5: 0 | X5: 13 | Y5: 27 | Z5: 0 | AA5: 2 | AB5: 0 | AC5: 0 | AD5: 1 | AE5: 1 | AF5: 0 | AG5: 1 | AH5: 0 | AI5: 0 | AJ5: 1 | AK5: 0 | AL5: 2 | AM5: 0 | AN5: 1 | AO5: 0 | AP5: 1 | AQ5: 2 | AR5: 0 | AS5: 1 | AT5: 0 | AU5: 0 | AV5: 0 | AW5: 1 | AX5: 0
B6: Wall Mount | C6: 4.93 | D6: 5.49 | E6: Suet Ball Holder | F6: =('OLD Detailed Report'!AF176)/'OLD Detailed Report'!AF172 -> 0.24799143 | H6: Taxes and VAT | I6: 16.81 | K6: HMF | L6: 0.00125 | Q6: Money Return | R6: 1 | T6: TV / Radio | U6: 1 | V6: 0 | W6: 2 | X6: 0 | Y6: 81 | Z6: 1 | AA6: 1 | AB6: 0 | AC6: 0 | AD6: 0 | AE6: 0 | AF6: 0 | AG6: 0 | AH6: 1 | AI6: 0 | AJ6: 0 | AK6: 2 | AL6: 0 | AM6: 0 | AN6: 1 | AO6: 2 | AP6: 2 | AQ6: 1 | AR6: 0 | AS6: 0 | AT6: 0 | AU6: 0 | AV6: 0 | AW6: 0 | AX6: 1
B7: Fence Mount | C7: 6.37 | E7: 3-in-1 | F7: =('OLD Detailed Report'!AF177)/'OLD Detailed Report'!AF172 -> 0.16229245 | H7: China Tax (7.5%) | I7: =I3*0.075 -> 6.8245794 | K7: MPF | L7: 0.003464 | N7: US+CA | O7: 0.943 | T7: Blog / Article | U7: 1 | V7: 4 | W7: 4 | X7: 37 | Y7: 28 | Z7: 3 | AA7: 1 | AB7: 1 | AC7: 0 | AD7: 1 | AE7: 3 | AF7: 1 | AG7: 0 | AH7: 1 | AI7: 4 | AJ7: 2 | AK7: 2 | AL7: 35 | AM7: 1 | AN7: 6 | AO7: 6 | AP7: 1 | AQ7: 7 | AR7: 2 | AS7: 1 | AT7: 0 | AU7: 0 | AV7: 1 | AW7: 6 | AX7: 3
B8: Suet Ball Holder | C8: 1.07 | D8: 1.19 | E8: Bird Buddy w/ Solar | F8: ='OLD Detailed Report'!AF170/'OLD Detailed Report'!AF172 -> 0.60953401 | H8: Duty (3.4%) | I8: =(C5*F3)*0.025+(C6*F4)*0.034+(C7*F5)*0.034+(C8*F6)*0.034+(C9*F7)*0.034 -> 0.12062117 | K8: Solar Roof China Tax | L8: 0.075 | M8: *from july.23 | N8: EUROPE | O8: =1-O7 -> 0.057 | T8: Reddit | U8: 0 | V8: 0 | W8: 0 | X8: 0 | Y8: 1 | Z8: 2 | AA8: 1 | AB8: 1 | AC8: 0 | AD8: 0 | AE8: 0 | AF8: 0 | AG8: 1 | AH8: 0 | AI8: 1 | AJ8: 0 | AK8: 0 | AL8: 3 | AM8: 0 | AN8: 0 | AO8: 1 | AP8: 1 | AQ8: 0 | AR8: 0 | AS8: 0 | AT8: 0 | AU8: 0 | AV8: 1 | AW8: 0 | AX8: 0
B9: 3-in-1 Nutrition Set | C9: 5.98 | D9: 6.66 | E9: Bird Buddy | F9: =1-F8 -> 0.39046599 | H9: Processing Fee (2,90%) | I9: ='OLD Sales'!B81*0.029 -> 2.8443556 | K9: Solar Roof Duty | L9: 0.025 | T9: Google, Youtube | U9: 5 | V9: 9 | W9: 2 | X9: 16 | Y9: 4 | Z9: 1 | AA9: 2 | AB9: 1 | AC9: 3 | AD9: 2 | AE9: 5 | AF9: 2 | AG9: 5 | AH9: 5 | AI9: 4 | AJ9: 6 | AK9: 2 | AL9: 19 | AM9: 7 | AN9: 6 | AO9: 6 | AP9: 5 | AQ9: 2 | AR9: 1 | AS9: 0 | AT9: 0 | AU9: 0 | AV9: 5 | AW9: 7 | AX9: 4
B10: OTHER 1 | E10: OTHER 1 | H10: Transaction Fee ($0.30) | I10: =0.3 -> 0.3 | K10: Chargeback Fee (Stripe) | L10: 15 | T10: Yahoo, Bing | U10: 1 | V10: 0 | W10: 0 | X10: 0 | Y10: 1 | Z10: 0 | AA10: 0 | AB10: 0 | AC10: 0 | AD10: 0 | AE10: 1 | AF10: 0 | AG10: 0 | AH10: 1 | AI10: 0 | AJ10: 0 | AK10: 0 | AL10: 2 | AM10: 1 | AN10: 0 | AO10: 0 | AP10: 1 | AQ10: 0 | AR10: 0 | AS10: 0 | AT10: 0 | AU10: 0 | AV10: 0 | AW10: 0 | AX10: 2
B11: OTHER 2 | E11: OTHER 2 | H11: OTHER 1 | N11: jan.23-jun.23 AOV | O11: 252.085 | P11: =(O12*O7)+(O13*O8) -> 16.806398 | T11: Total submissions: | U11: =SUM(U3:U10) -> 55 | V11: =SUM(V3:V10) -> 71 | W11: =SUM(W3:W10) -> 98 | X11: =SUM(X3:X10) -> 198 | Y11: =SUM(Y3:Y10) -> 400 | Z11: =SUM(Z3:Z10) -> 84 | AA11: =SUM(AA3:AA10) -> 51 | AB11: =SUM(AB3:AB10) -> 37 | ... AX11: =SUM(AX3:AX10) -> 72
B12: OTHER 3 | E12: OTHER 3 | H12: OTHER 2 | K12: Stripe | L12: 0.95 | N12: NA (cca 6 %) | O12: 14.469966 | T12: Percentage | U12: 45170 | V12: 45171 | W12: 45172 | X12: 45173 | Y12: 45174 | Z12: 45175 | AA12: 45176 | AB12: 45177 | AC12: 45178 | AD12: 45179 | AE12: 45180 | AF12: 45181 | AG12: 45182 | AH12: 45183 | AI12: 45184 | AJ12: 45185 | AK12: 45186 | AL12: 45187 | AM12: 45188 | AN12: 45189 | AO12: 45190 | AP12: 45191 | AQ12: 45192 | AR12: 45193 | AS12: 45194 | AT12: 45195 | AU12: 45196 | AV12: 45197 | AW12: 45198 | AX12: 45199
B13: OTHER 4 | E13: OTHER 4 | H13: OTHER 3 | K13: Affirm | L13: 0.05 | N13: Europe (22 %) | O13: 55.46 | T13: Facebook / Instagram | U13: =iferror(U3/U$11,"") -> 0.27272727 | V13: =iferror(V3/V$11,"") -> 0.29577465 | W13: =iferror(W3/W$11,"") -> 0.35714286 | X13: =iferror(X3/X$11,"") -> 0.31313131 | Y13: =iferror(Y3/Y$11,"") -> 0.2025 | Z13: =iferror(Z3/Z$11,"") -> 0.38095238 | AA13: =iferror(AA3/AA$11,"") -> 0.35294118 | AB13: =iferror(AB3/AB$11,"") -> 0.40540541 | ... AS13: =iferror(AS3/AS$11,"") -> 0.28 | AT13: 0 | AU13: 0 | AV13: =iferror(AV3/AV$11,"") -> 0.27272727 | AW13: =iferror(AW3/AW$11,"") -> 0.37333333 | AX13: =iferror(AX3/AX$11,"") -> 0.43055556
B14: OTHER 5 | E14: OTHER 5 | H14: OTHER 4 | K14: Affirm processing fee | L14: 0 | T14: Friends / Family | U14: =iferror(U4/U$11,"") -> 0.56363636 | V14: =iferror(V4/V$11,"") -> 0.50704225 | W14: =iferror(W4/W$11,"") -> 0.56122449 | X14: =iferror(X4/X$11,"") -> 0.35353535 | Y14: =iferror(Y4/Y$11,"") -> 0.4425 | Z14: =iferror(Z4/Z$11,"") -> 0.53571429 | AA14: =iferror(AA4/AA$11,"") -> 0.50980392 | AB14: =iferror(AB4/AB$11,"") -> 0.51351351 | ... AS14: =iferror(AS4/AS$11,"") -> 0.64 | AT14: 0 | AU14: 0 | AV14: =iferror(AV4/AV$11,"") -> 0.51515152 | AW14: =iferror(AW4/AW$11,"") -> 0.44 | AX14: =iferror(AX4/AX$11,"") -> 0.43055556
H15: All | I15: =SUM(I3:I13) -> 146.01325 | K15: Affirm transaction fee | L15: 0 | T15: TikTok | U15: =iferror(U5/U$11,"") -> 0.018181818 | V15: =iferror(V5/V$11,"") -> 0.014084507 | W15: =iferror(W5/W$11,"") -> 0 | X15: =iferror(X5/X$11,"") -> 0.065656566 | Y15: =iferror(Y5/Y$11,"") -> 0.0675 | Z15: =iferror(Z5/Z$11,"") -> 0 | AA15: =iferror(AA5/AA$11,"") -> 0.039215686 | AB15: =iferror(AB5/AB$11,"") -> 0 | ... AS15: =iferror(AS5/AS$11,"") -> 0.04 | AT15: 0 | AU15: 0 | AV15: =iferror(AV5/AV$11,"") -> 0 | AW15: =iferror(AW5/AW$11,"") -> 0.013333333 | AX15: =iferror(AX5/AX$11,"") -> 0
B16: Outbound shipping | C16: Bird buddy | D16: Add-ons | T16: TV / Radio | U16: =iferror(U6/U$11,"") -> 0.018181818 | V16: =iferror(V6/V$11,"") -> 0 | W16: =iferror(W6/W$11,"") -> 0.020408163 | X16: =iferror(X6/X$11,"") -> 0 | Y16: =iferror(Y6/Y$11,"") -> 0.2025 | Z16: =iferror(Z6/Z$11,"") -> 0.011904762 | AA16: =iferror(AA6/AA$11,"") -> 0.019607843 | AB16: =iferror(AB6/AB$11,"") -> 0 | ... AS16: =iferror(AS6/AS$11,"") -> 0 | AT16: 0 | AU16: 0 | AV16: =iferror(AV6/AV$11,"") -> 0 | AW16: =iferror(AW6/AW$11,"") -> 0 | AX16: =iferror(AX6/AX$11,"") -> 0.013888889
A17: *w/o CA weight | B17: Outbound (NA) | C17: 11.94 | D17: 6.155 | T17: Blog / Article | U17: =iferror(U7/U$11,"") -> 0.018181818 | V17: =iferror(V7/V$11,"") -> 0.056338028 | W17: =iferror(W7/W$11,"") -> 0.040816327 | X17: =iferror(X7/X$11,"") -> 0.18686869 | Y17: =iferror(Y7/Y$11,"") -> 0.07 | Z17: =iferror(Z7/Z$11,"") -> 0.035714286 | AA17: =iferror(AA7/AA$11,"") -> 0.019607843 | AB17: =iferror(AB7/AB$11,"") -> 0.027027027 | ... AS17: =iferror(AS7/AS$11,"") -> 0.04 | AT17: 0 | AU17: 0 | AV17: =iferror(AV7/AV$11,"") -> 0.03030303 | AW17: =iferror(AW7/AW$11,"") -> 0.08 | AX17: =iferror(AX7/AX$11,"") -> 0.041666667
B18: Outbound (Europe) | C18: 11.94 | D18: 6.16 | T18: Reddit | U18: =iferror(U8/U$11,"") -> 0 | V18: =iferror(V8/V$11,"") -> 0 | W18: =iferror(W8/W$11,"") -> 0 | X18: =iferror(X8/X$11,"") -> 0 | Y18: =iferror(Y8/Y$11,"") -> 0.0025 | Z18: =iferror(Z8/Z$11,"") -> 0.023809524 | AA18: =iferror(AA8/AA$11,"") -> 0.019607843 | AB18: =iferror(AB8/AB$11,"") -> 0.027027027 | ... AS18: =iferror(AS8/AS$11,"") -> 0 | AT18: 0 | AU18: 0 | AV18: =iferror(AV8/AV$11,"") -> 0.03030303 | AW18: =iferror(AW8/AW$11,"") -> 0 | AX18: =iferror(AX8/AX$11,"") -> 0
B19: Outbound (ROW) | C19: 11.94 | D19: 6.16 | T19: Google, Youtube | U19: =iferror(U9/U$11,"") -> 0.090909091 | V19: =iferror(V9/V$11,"") -> 0.12676056 | W19: =iferror(W9/W$11,"") -> 0.020408163 | X19: =iferror(X9/X$11,"") -> 0.080808081 | Y19: =iferror(Y9/Y$11,"") -> 0.01 | Z19: =iferror(Z9/Z$11,"") -> 0.011904762 | AA19: =iferror(AA9/AA$11,"") -> 0.039215686 | AB19: =iferror(AB9/AB$11,"") -> 0.027027027 | ... AS19: =iferror(AS9/AS$11,"") -> 0 | AT19: 0 | AU19: 0 | AV19: =iferror(AV9/AV$11,"") -> 0.15151515 | AW19: =iferror(AW9/AW$11,"") -> 0.093333333 | AX19: =iferror(AX9/AX$11,"") -> 0.055555556
A20: Source | B20: 3PL Costs | C20: =sum(C21:C27) -> 3.12 | D20: =sum(D21:D27) -> 2.31 | T20: Yahoo, Bing | U20: =iferror(U10/U$11,"") -> 0.018181818 | V20: =iferror(V10/V$11,"") -> 0 | W20: =iferror(W10/W$11,"") -> 0 | X20: =iferror(X10/X$11,"") -> 0 | Y20: =iferror(Y10/Y$11,"") -> 0.0025 | Z20: =iferror(Z10/Z$11,"") -> 0 | AA20: =iferror(AA10/AA$11,"") -> 0 | AB20: =iferror(AB10/AB$11,"") -> 0 | ... AS20: =iferror(AS10/AS$11,"") -> 0 | AT20: 0 | AU20: 0 | AV20: =iferror(AV10/AV$11,"") -> 0 | AW20: =iferror(AW10/AW$11,"") -> 0 | AX20: =iferror(AX10/AX$11,"") -> 0.027777778
B21: Handling Fee
B22: Serial Capture | C22: 0.3 | D22: 0
B23: Storage | C23: 0.31 | D23: 0.31
B24: Supplies cost | C24: 1.01 | D24: 0.6
B25: Pick charge | C25: 0.3 | D25: 0.3
B26: Pollybag cost | C26: 0 | D26: 1.1
B27: Carton cost | C27: 1.2 | D27: 0
B28: Total outbound (NA) | C28: =C20+C17-C21 -> 15.06 | D28: =D20+D17-D21 -> 8.465
B29: Total outbound (Europe) | C29: 15.06
B30: Total outbound (ROW) | C30: 20
A31: Source | B31: Inbound shipping | C31: Bird buddy | D31: Add-ons
B32: Inbound (NA) | C32: 11.94 | D32: 1.435
B33: Inbound (Europe) | C33: 11.94 | D33: 1.44
B34: Inbound (ROW) | C34: 11.94 | D34: 1.44
B36: AMAZON Logistics | C36: Bird buddy | E36: KCTC (additionally for first 3.000 items) | G36: *KCTC = China -> LA with Air fraight
A37: =AVERAGE(D3:D4) -> 92.255 | B37: Inbound | C37: 2.27 | E37: Logistics | F37: 0.63
A38: =sum(C37:C38) -> 2.51 | B38: Storage Fee | C38: 0.24 | E38: Storage Fee | F38: 0.11
A39: =C40 -> 11.94 | B39: AMAZON Fees | C39: Bird buddy | E39: Label Handling | F39: 1.01
A40: =sum(F37:F39) -> 1.75 | B40: FBA fees | C40: 11.94
A41: =C32 -> 11.94 | B41: Sales Fee | C41: 0.1 | D41: *for first milion is 10 % than 15 %
A43: =sum(A37:A41) -> 120.395

Sheet OLD AMAZON Detailed Report
A1: September | B1: 45170 | C1: 45171 | D1: 45172 | E1: 45173 | F1: 45174 | G1: 45175 | H1: 45176 | I1: 45177 | J1: 45178 | K1: 45179 | L1: 45180 | M1: 45181 | N1: 45182 | O1: 45183 | P1: 45184 | Q1: 45185 | R1: 45186 | S1: 45187 | T1: 45188 | U1: 45189 | V1: 45190 | W1: 45191 | X1: 45192 | Y1: 45193 | Z1: 45194 | AA1: 45195 | AB1: 45196 | AC1: 45197 | AD1: 45198 | AE1: 45199
A2: DAY | B2: FRI | C2: SAT | D2: SUN | E2: MON | F2: TUE | G2: WED | H2: THU | I2: FRI | J2: SAT | K2: SUN | L2: MON | M2: TUE | N2: WED | O2: THU | P2: FRI | Q2: SAT | R2: SUN | S2: MON | T2: TUE | U2: WED | V2: THU | W2: FRI | X2: SAT | Y2: SUN | Z2: MON | AA2: TUE | AB2: WED | AC2: THU | AD2: FRI | AE2: SAT
A3: COMMENT
A4: Orders
A5: Amazon (market place) | B5: ='OLD Sales'!B30 -> 14 | C5: ='OLD Sales'!C30 -> 7 | D5: ='OLD Sales'!D30 -> 19 | E5: ='OLD Sales'!E30 -> 23 | F5: ='OLD Sales'!F30 -> 16 | G5: ='OLD Sales'!G30 -> 20 | H5: ='OLD Sales'!H30 -> 12 | I5: ='OLD Sales'!I30 -> 12 | ... AE5: ='OLD Sales'!AE30 -> 30
A6: All | B6: =SUM(B5) -> 14 | C6: =SUM(C5) -> 7 | D6: =SUM(D5) -> 19 | E6: =SUM(E5) -> 23 | F6: =SUM(F5) -> 16 | G6: =SUM(G5) -> 20 | H6: =SUM(H5) -> 12 | I6: =SUM(I5) -> 12 | ... AE6: =SUM(AE5) -> 30 | AF6: =SUM(B6:AE6) -> 758
A8: Revenue
A9: Amazon (market place) | B9: ='OLD Sales'!B15 -> 3069 | C9: ='OLD Sales'!C15 -> 2511 | D9: ='OLD Sales'!D15 -> 4185 | E9: ='OLD Sales'!E15 -> 5580 | F9: ='OLD Sales'!F15 -> 5580 | G9: ='OLD Sales'!G15 -> 4464 | H9: ='OLD Sales'!H15 -> 3627 | I9: ='OLD Sales'!I15 -> 2790 | ... AE9: ='OLD Sales'!AE15 -> 7254
A10: All | B10: =SUM(B9) -> 3069 | C10: =SUM(C9) -> 2511 | D10: =SUM(D9) -> 4185 | E10: =SUM(E9) -> 5580 | F10: =SUM(F9) -> 5580 | G10: =SUM(G9) -> 4464 | H10: =SUM(H9) -> 3627 | I10: =SUM(I9) -> 2790 | ... AE10: =SUM(AE9) -> 7254 | AF10: =SUM(B10:AE10) -> 211482
A12: Media Cost
A13: Amazon (market place) Spend | B13: ='OLD Sales'!B39 -> 1276.67 | C13: ='OLD Sales'!C39 -> 1876.55 | D13: ='OLD Sales'!D39 -> 2182.61 | E13: ='OLD Sales'!E39 -> 1886.24 | F13: ='OLD Sales'!F39 -> 1401.31 | G13: ='OLD Sales'!G39 -> 1491.07 | H13: ='OLD Sales'!H39 -> 1448.93 | I13: ='OLD Sales'!I39 -> 1479.75 | ... AE13: ='OLD Sales'!AE39 -> 3932.81
A14: Amazon (market place) Sales Fee (10-15 %) | B14: =B9*'OLD Formulas'!$C$41 -> 306.9 | C14: =C9*'OLD Formulas'!$C$41 -> 251.1 | D14: =D9*'OLD Formulas'!$C$41 -> 418.5 | E14: =E9*'OLD Formulas'!$C$41 -> 558 | F14: =F9*'OLD Formulas'!$C$41 -> 558 | G14: =G9*'OLD Formulas'!$C$41 -> 446.4 | H14: =H9*'OLD Formulas'!$C$41 -> 362.7 | I14: =I9*'OLD Formulas'!$C$41 -> 279 | ... AE14: =AE9*'OLD Formulas'!$C$41 -> 725.4
A15: Platform Fee | AF15: =SUM(B15:AE15) -> 0
A16: All | B16: =SUM(B13:B15) -> 1583.57 | C16: =SUM(C13:C15) -> 2127.65 | D16: =SUM(D13:D15) -> 2601.11 | E16: =SUM(E13:E15) -> 2444.24 | F16: =SUM(F13:F15) -> 1959.31 | G16: =SUM(G13:G15) -> 1937.47 | H16: =SUM(H13:H15) -> 1811.63 | I16: =SUM(I13:I15) -> 1758.75 | ... AE16: =SUM(AE13:AE15) -> 4658.21 | AF16: =SUM(B16:AE16) -> 82491.77
A18: Cost
A19: Average COGS ($92.26) | B19: =B6*'OLD Formulas'!$A$37 -> 1291.57 | C19: =C6*'OLD Formulas'!$A$37 -> 645.785 | D19: =D6*'OLD Formulas'!$A$37 -> 1752.845 | E19: =E6*'OLD Formulas'!$A$37 -> 2121.865 | F19: =F6*'OLD Formulas'!$A$37 -> 1476.08 | G19: =G6*'OLD Formulas'!$A$37 -> 1845.1 | H19: =H6*'OLD Formulas'!$A$37 -> 1107.06 | I19: =I6*'OLD Formulas'!$A$37 -> 1107.06 | ... AE19: =AE6*'OLD Formulas'!$A$37 -> 2767.65 | AF19: =SUM(B19:AE19) -> 69929.29
A20: Average Inbound Shipping ($11.94+KCTC) | B20: =(B6*'OLD Formulas'!$C$32)+(B6*'OLD Formulas'!$A$40) -> 191.66 | C20: =(C6*'OLD Formulas'!$C$32)+(C6*'OLD Formulas'!$A$40) -> 95.83 | D20: =(D6*'OLD Formulas'!$C$32)+(D6*'OLD Formulas'!$A$40) -> 260.11 | E20: =(E6*'OLD Formulas'!$C$32)+(E6*'OLD Formulas'!$A$40) -> 314.87 | F20: =(F6*'OLD Formulas'!$C$32)+(F6*'OLD Formulas'!$A$40) -> 219.04 | G20: =(G6*'OLD Formulas'!$C$32)+(G6*'OLD Formulas'!$A$40) -> 273.8 | H20: =(H6*'OLD Formulas'!$C$32)+(H6*'OLD Formulas'!$A$40) -> 164.28 | I20: =(I6*'OLD Formulas'!$C$32)+(I6*'OLD Formulas'!$A$40) -> 164.28 | ... AE20: =(AE6*'OLD Formulas'!$C$32)+(AE6*'OLD Formulas'!$A$40) -> 410.7 | AF20: =SUM(B20:AE20) -> 10377.02
A21: Average Amazon Inbound | B21: =B287*'OLD Formulas'!$C$37 -> 0 | C21: =C287*'OLD Formulas'!$C$37 -> 0 | D21: =D287*'OLD Formulas'!$C$37 -> 0 | E21: =E287*'OLD Formulas'!$C$37 -> 0 | F21: =F287*'OLD Formulas'!$C$37 -> 0 | G21: =G287*'OLD Formulas'!$C$37 -> 0 | H21: =H287*'OLD Formulas'!$C$37 -> 0 | I21: =I287*'OLD Formulas'!$C$37 -> 0 | ... AE21: =AE287*'OLD Formulas'!$C$37 -> 0 | AF21: =SUM(B21:AE21) -> 0
A22: Average Amazon Storage fee | B22: =B287*'OLD Formulas'!$C$38 -> 0 | C22: =C287*'OLD Formulas'!$C$38 -> 0 | D22: =D287*'OLD Formulas'!$C$38 -> 0 | E22: =E287*'OLD Formulas'!$C$38 -> 0 | F22: =F287*'OLD Formulas'!$C$38 -> 0 | G22: =G287*'OLD Formulas'!$C$38 -> 0 | H22: =H287*'OLD Formulas'!$C$38 -> 0 | I22: =I287*'OLD Formulas'!$C$38 -> 0 | ... AE22: =AE287*'OLD Formulas'!$C$38 -> 0 | AF22: =SUM(B22:AE22) -> 0
A23: Average FBA fee ($11.94) | B23: =B6*'OLD Formulas'!$C$40 -> 167.16 | C23: =C6*'OLD Formulas'!$C$40 -> 83.58 | D23: =D6*'OLD Formulas'!$C$40 -> 226.86 | E23: =E6*'OLD Formulas'!$C$40 -> 274.62 | F23: =F6*'OLD Formulas'!$C$40 -> 191.04 | G23: =G6*'OLD Formulas'!$C$40 -> 238.8 | H23: =H6*'OLD Formulas'!$C$40 -> 143.28 | I23: =I6*'OLD Formulas'!$C$40 -> 143.28 | ... AE23: =AE6*'OLD Formulas'!$C$40 -> 358.2 | AF23: =SUM(B23:AE23) -> 9050.52
A24: Average Sales fee | B24: =B10*'OLD Formulas'!$C$41 -> 306.9 | C24: =C10*'OLD Formulas'!$C$41 -> 251.1 | D24: =D10*'OLD Formulas'!$C$41 -> 418.5 | E24: =E10*'OLD Formulas'!$C$41 -> 558 | F24: =F10*'OLD Formulas'!$C$41 -> 558 | G24: =G10*'OLD Formulas'!$C$41 -> 446.4 | H24: =H10*'OLD Formulas'!$C$41 -> 362.7 | I24: =I10*'OLD Formulas'!$C$41 -> 279 | ... AE24: =AE10*'OLD Formulas'!$C$41 -> 725.4 | AF24: =SUM(B24:AE24) -> 21148.2
A25: All | B25: =SUM(B19:B24) -> 1957.29 | C25: =SUM(C19:C24) -> 1076.295 | D25: =SUM(D19:D24) -> 2658.315 | E25: =SUM(E19:E24) -> 3269.355 | F25: =SUM(F19:F24) -> 2444.16 | G25: =SUM(G19:G24) -> 2804.1 | H25: =SUM(H19:H24) -> 1777.32 | I25: =SUM(I19:I24) -> 1693.62 | ... AE25: =SUM(AE19:AE24) -> 4261.95 | AF25: =SUM(B25:AE25) -> 110505.03
AF26: =SUM(B26:AE26) -> 0
A27: Partial Profit | B27: =B10-B16-B25 -> -471.86 | C27: =C10-C16-C25 -> -692.945 | D27: =D10-D16-D25 -> -1074.425 | E27: =E10-E16-E25 -> -133.595 | F27: =F10-F16-F25 -> 1176.53 | G27: =G10-G16-G25 -> -277.57 | H27: =H10-H16-H25 -> 38.05 | I27: =I10-I16-I25 -> -662.37 | ... AE27: =AE10-AE16-AE25 -> -1666.16 | AF27: =SUM(B27:AE27) -> 18485.2
A28: =SUM(B27:AC27) -> 18826.015
A32: AMAZON (marketplace)
A33: PROFIT | B33: =B9-(B5*'OLD Formulas'!$A$43)-B13 -> 106.8 | C33: =C9-(C5*'OLD Formulas'!$A$43)-C13 -> -208.315 | D33: =D9-(D5*'OLD Formulas'!$A$43)-D13 -> -285.115 | E33: =E9-(E5*'OLD Formulas'!$A$43)-E13 -> 924.675 | F33: =F9-(F5*'OLD Formulas'!$A$43)-F13 -> 2252.37 | G33: =G9-(G5*'OLD Formulas'!$A$43)-G13 -> 565.03 | H33: =H9-(H5*'OLD Formulas'!$A$43)-H13 -> 733.33 | I33: =I9-(I5*'OLD Formulas'!$A$43)-I13 -> -134.49 | ... AE33: =AE9-(AE5*'OLD Formulas'!$A$43)-AE13 -> -290.66
A34: ROAS | B34: =B9/B13 -> 2.4039102 | C34: =C9/C13 -> 1.3380938 | D34: =D9/D13 -> 1.9174291 | E34: =E9/E13 -> 2.9582662 | F34: =F9/F13 -> 3.9819883 | G34: =G9/G13 -> 2.9938232 | H34: =H9/H13 -> 2.5032265 | I34: =I9/I13 -> 1.8854536 | ... AE34: =AE9/AE13 -> 1.8444827
A35: CPO | B35: =B13/B5 -> 91.190714 | C35: =C13/C5 -> 268.07857 | D35: =D13/D5 -> 114.87421 | E35: =E13/E5 -> 82.010435 | F35: =F13/F5 -> 87.581875 | G35: =G13/G5 -> 74.5535 | H35: =H13/H5 -> 120.74417 | I35: =I13/I5 -> 123.3125 | ... AE35: =AE13/AE5 -> 131.09367
A36: MER | B36: =B9/('OLD Formulas'!$A$43*B5+B13+B14) -> 0.93879049 | C36: =C9/('OLD Formulas'!$A$43*C5+C13+C14) -> 0.84533643 | D36: =D9/('OLD Formulas'!$A$43*D5+D13+D14) -> 0.85607069 | E36: =E9/('OLD Formulas'!$A$43*E5+E13+E14) -> 1.0703342 | F36: =F9/('OLD Formulas'!$A$43*F5+F13+F14) -> 1.4360606 | G36: =G9/('OLD Formulas'!$A$43*G5+G13+G14) -> 1.0273003 | H36: =H9/('OLD Formulas'!$A$43*H5+H13+H14) -> 1.1138169 | I36: =I9/('OLD Formulas'!$A$43*I5+I13+I14) -> 0.87092515 | ... AE36: =AE9/('OLD Formulas'!$A$43*AE5+AE13+AE14) -> 0.87713995
A40: Units Sold (Gross)
A41: Bird Buddy | AF41: =sum(B41:AE41) -> 0
A42: Bird Buddy with Solar Roof | B42: 14 | C42: 7 | D42: 19 | E42: 23 | F42: 16 | G42: 19 | H42: 12 | I42: 11 | J42: 28 | K42: 19 | L42: 22 | M42: 25 | N42: 26 | O42: 27 | P42: 15 | Q42: 23 | R42: 26 | S42: 27 | T42: 38 | U42: 36 | V42: 36 | W42: 32 | X42: 26 | Y42: 33 | Z42: 32 | AA42: 38 | AB42: 28 | AC42: 40 | AD42: 31 | AE42: 30 | AF42: =sum(B42:AE42) -> 759
A43: All Bird Buddy | B43: =SUM(B41:B42) -> 14 | C43: =SUM(C41:C42) -> 7 | D43: =SUM(D41:D42) -> 19 | E43: =SUM(E41:E42) -> 23 | F43: =SUM(F41:F42) -> 16 | G43: =SUM(G41:G42) -> 19 | H43: =SUM(H41:H42) -> 12 | I43: =SUM(I41:I42) -> 11 | ... AE43: =SUM(AE41:AE42) -> 30 | AF43: =sum(B43:AE43) -> 759
A45: Wall Mount | AF45: =sum(B45:AE45) -> 0
A46: Fence Mount | AF46: =sum(B46:AE46) -> 0
A47: Suet Ball Holder | AF47: =sum(B47:AE47) -> 0
A48: 3-in-1 Nutrition Set | AF48: =sum(B48:AE48) -> 0
A49: Solar Roof Single | AF49: =sum(B49:AE49) -> 0
A50: All | B50: =SUM(B45:B49) -> 0 | C50: =SUM(C45:C49) -> 0 | D50: =SUM(D45:D49) -> 0 | E50: =SUM(E45:E49) -> 0 | F50: =SUM(F45:F49) -> 0 | G50: =SUM(G45:G49) -> 0 | H50: =SUM(H45:H49) -> 0 | I50: =SUM(I45:I49) -> 0 | ... AE50: =SUM(AE45:AE49) -> 0 | AF50: =sum(B50:AE50) -> 0
A53: First-time Customers
A54: Bird Buddy | AF54: =sum(B54:AE54) -> 0
A55: Bird Buddy with Solar Roof | B55: 14 | C55: 8 | D55: 19 | E55: 23 | F55: 16 | G55: 20 | H55: 12 | I55: 12 | J55: 28 | K55: 18 | L55: 22 | M55: 25 | N55: 26 | O55: 27 | P55: 15 | Q55: 21 | R55: 25 | S55: 28 | T55: 38 | U55: 36 | V55: 36 | W55: 30 | X55: 25 | Y55: 33 | Z55: 32 | AA55: 39 | AB55: 28 | AC55: 40 | AD55: 31 | AE55: 30 | AF55: =sum(B55:AE55) -> 757
A56: All Bird Buddy | B56: =SUM(B54:B55) -> 14 | C56: =SUM(C54:C55) -> 8 | D56: =SUM(D54:D55) -> 19 | E56: =SUM(E54:E55) -> 23 | F56: =SUM(F54:F55) -> 16 | G56: =SUM(G54:G55) -> 20 | H56: =SUM(H54:H55) -> 12 | I56: =SUM(I54:I55) -> 12 | ... AE56: =SUM(AE54:AE55) -> 30 | AF56: =sum(B56:AE56) -> 757
A58: Wall Mount | AF58: =sum(B58:AE58) -> 0
A59: Fence Mount | AF59: =sum(B59:AE59) -> 0
A60: Suet Ball Holder | AF60: =sum(B60:AE60) -> 0
A61: 3-in-1 Nutrition Set | AF61: =sum(B61:AE61) -> 0
A62: Solar Roof Single | AF62: =sum(B62:AE62) -> 0
A63: All | B63: =SUM(B58:B62) -> 0 | C63: =SUM(C58:C62) -> 0 | D63: =SUM(D58:D62) -> 0 | E63: =SUM(E58:E62) -> 0 | F63: =SUM(F58:F62) -> 0 | G63: =SUM(G58:G62) -> 0 | H63: =SUM(H58:H62) -> 0 | I63: =SUM(I58:I62) -> 0 | ... AE63: =SUM(AE58:AE62) -> 0 | AF63: =sum(B63:AE63) -> 0
A65: Returning Customers
A66: Bird Buddy | AF66: =sum(B66:AE66) -> 0
A67: Bird Buddy with Solar Roof | B67: 0 | C67: 0 | D67: 0 | E67: 0 | F67: 0 | G67: 0 | H67: 0 | I67: 0 | J67: 0 | K67: 0 | L67: 0 | M67: 0 | N67: 0 | O67: 0 | P67: 0 | Q67: 0 | R67: 0 | S67: 0 | T67: 0 | U67: 0 | V67: 0 | W67: 0 | X67: 0 | Y67: 0 | Z67: 0 | AA67: 0 | AB67: 0 | AC67: 0 | AD67: 0 | AE67: 0 | AF67: =sum(B67:AE67) -> 0
A68: All Bird Buddy | B68: =SUM(B66:B67) -> 0 | C68: =SUM(C66:C67) -> 0 | D68: =SUM(D66:D67) -> 0 | E68: =SUM(E66:E67) -> 0 | F68: =SUM(F66:F67) -> 0 | G68: =SUM(G66:G67) -> 0 | H68: =SUM(H66:H67) -> 0 | I68: =SUM(I66:I67) -> 0 | ... AE68: =SUM(AE66:AE67) -> 0 | AF68: =sum(B68:AE68) -> 0
A70: Wall Mount | AF70: =sum(B70:AE70) -> 0
A71: Fence Mount | AF71: =sum(B71:AE71) -> 0
A72: Suet Ball Holder | AF72: =sum(B72:AE72) -> 0
A73: 3-in-1 Nutrition Set | AF73: =sum(B73:AE73) -> 0
A74: Solar Roof Single | AF74: =sum(B74:AE74) -> 0
A75: All | B75: =SUM(B70:B74) -> 0 | C75: =SUM(C70:C74) -> 0 | D75: =SUM(D70:D74) -> 0 | E75: =SUM(E70:E74) -> 0 | F75: =SUM(F70:F74) -> 0 | G75: =SUM(G70:G74) -> 0 | H75: =SUM(H70:H74) -> 0 | I75: =SUM(I70:I74) -> 0 | ... AE75: =SUM(AE70:AE74) -> 0 | AF75: =sum(B75:AE75) -> 0
A77: Units Sold (Net)
