Workbook
Name rdataslayer_d70e473bcafe40a3aa834ce157fb2ba3: 'Business Metrics Canada'!$C$16:$D$17
Name zsupermetrics_xwoIpANxRm908eDp5oKTwQpEI8gvD4: 'Business Metrics US'!$A$5
Name zsupermetrics_ru0GDtbZzDLHQOQtJJ6K08MvUDyyp7: #REF!
Name zsupermetrics_iNpyVy90bWCI0yUaFQpxOtzWMa6sW4: 'Business Metrics US'!$A$5:$A$12
Name zsupermetrics_DQl8lUbpTRu3fayaJJi7lVfOGKjNU4: 'OLD Formulas'!$A$3:$A$4
Name zsupermetrics_NugLlrQxlKiqhxQae8EFpITBm1pLCj: 'Business Metrics Canada'!$B$15:$C$23
Name rdataslayer_4a0f150f4f2f4e4f85c890c75b7a1fa4: 'Business Metrics Canada'!$D$5:$E$12
Name zsupermetrics_BioPyGBzcBsy60UCQmPcTuFReEmghI: 'OLD Formulas'!$B$2:$B$3
Name zsupermetrics_refreshAll: SupermetricsQueries!$H$5
Name zsupermetrics_DQl8lUbpTRu3fayaJJi7lVfOGKjNU4: 'Business Metrics Canada'!$A$2:$A$13
Name zsupermetrics_n3GtLgiKpTmd2pYmQNMuq6TPD0qE0b: #REF!
Name zsupermetrics_9i4W4hgd80uRpQLMeX0eRnESN8gjyv: 'Business Metrics US'!$C$23
Name zsupermetrics_qWp7V908pNEYMtfv8QZvSTeDnBAHOU: 'Business Metrics Canada'!$B$14:$C$23
Name zsupermetrics_refreshAllSilent: SupermetricsQueries!$H$6
Name zsupermetrics_Mgms9p0QzysYvrIhnsKACeVBVxfIEO: #REF!
Name rdataslayer_4a0f150f4f2f4e4f85c890c75b7a1fa4: 'Business Metrics US'!$D$5:$E$12
Name zsupermetrics_lx4cNai7gT6tH4j08ZRkI21Qlpjioi: 'Business Metrics Canada'!$B$13:$C$23
Name zsupermetrics_Mgms9p0QzysYvrIhnsKACeVBVxfIEO: 'OLD Formulas'!$A$2:$A$3
Name zsupermetrics_forceRefresh: SupermetricsQueries!$H$4
Name zsupermetrics_wbYMmT0YL9bAN0yhimW0ziPFnia9Dx: #REF!
Name zsupermetrics_iNpyVy90bWCI0yUaFQpxOtzWMa6sW4: #REF!
Name zsupermetrics_xwoIpANxRm908eDp5oKTwQpEI8gvD4: 'Business Metrics Canada'!$A$5
Name zsupermetrics_xwoIpANxRm908eDp5oKTwQpEI8gvD4: #REF!
Name rdataslayer_3753ddf3234e496aa261974a0222e193: 'Business Metrics US'!$H$5:$I$5
Name zsupermetrics_4VkB7ij7WO0JjKBEgvjB2GHjSy2Egm: 'Business Metrics Canada'!$B$13:$C$17
Name zsupermetrics_n3GtLgiKpTmd2pYmQNMuq6TPD0qE0b: 'OLD Formulas'!$B$4:$B$5
Name rdataslayer_42b112e4e4be4305bb4c1be75e2dd549: 'OLD Formulas'!$B$2:$C$3
Name zsupermetrics_wbYMmT0YL9bAN0yhimW0ziPFnia9Dx: 'Business Metrics Canada'!$A$5:$A$12
Name zsupermetrics_9i4W4hgd80uRpQLMeX0eRnESN8gjyv: #REF!
Name zsupermetrics_YsFuuYtr8vOdNXCCPiFJIO38NP4b2T: 'Business Metrics US'!$B$13:$C$23
Name zsupermetrics_5bmwtOpHUbSYmDMeuCPkrxaojTprPP: #REF!
Name rdataslayer_adf57e64065742daa5b4161161b1c3ca: 'Business Metrics Canada'!$B$13:$D$14
Name zsupermetrics_9i4W4hgd80uRpQLMeX0eRnESN8gjyv: 'Business Metrics Canada'!$C$23
Name rdataslayer_3753ddf3234e496aa261974a0222e193: 'OLD Formulas'!$H$2:$I$2
Name zsupermetrics_4VkB7ij7WO0JjKBEgvjB2GHjSy2Egm: 'Business Metrics US'!$B$13:$C$17
Name zsupermetrics_SGBxROnInO9rFyh3H7j2Lldx0Bdc5v: #REF!
Name zsupermetrics_pxuhRTEmIU93xSgKclyxajD0fCZ6rF: #REF!
Name zsupermetrics_ru0GDtbZzDLHQOQtJJ6K08MvUDyyp7: 'OLD Formulas'!$B$4:$B$5
Name zsupermetrics_qWp7V908pNEYMtfv8QZvSTeDnBAHOU: 'OLD Formulas'!$B$5:$C$13
Name zsupermetrics_wbYMmT0YL9bAN0yhimW0ziPFnia9Dx: 'Business Metrics US'!$A$5:$A$12
Name rdataslayer_4a0f150f4f2f4e4f85c890c75b7a1fa4: #REF!
Name zsupermetrics_iNpyVy90bWCI0yUaFQpxOtzWMa6sW4: 'Business Metrics Canada'!$A$5:$A$12
Name zsupermetrics_HgZqhorObHOtZHuyJjpmyYaEPoYntx: #REF!
Name zsupermetrics_YsFuuYtr8vOdNXCCPiFJIO38NP4b2T: #REF!
Name zsupermetrics_DQl8lUbpTRu3fayaJJi7lVfOGKjNU4: #REF!
Name zsupermetrics_YVuzfmsfdurz7Ldl84Rfns8oka6LsS: #REF!
Name zsupermetrics_4VkB7ij7WO0JjKBEgvjB2GHjSy2Egm: #REF!
Name zsupermetrics_9i4W4hgd80uRpQLMeX0eRnESN8gjyv: 'OLD Formulas'!$C$13
Name zsupermetrics_Mgms9p0QzysYvrIhnsKACeVBVxfIEO: 'Business Metrics US'!$A$5:$A$12
Name zsupermetrics_lx4cNai7gT6tH4j08ZRkI21Qlpjioi: #REF!
Name zsupermetrics_BioPyGBzcBsy60UCQmPcTuFReEmghI: 'Business Metrics US'!$B$5:$B$12
Name zsupermetrics_qWp7V908pNEYMtfv8QZvSTeDnBAHOU: 'Business Metrics US'!$B$14:$C$23
Name rdataslayer_adf57e64065742daa5b4161161b1c3ca: 'Business Metrics US'!$B$13:$D$14
Name rdataslayer_d70e473bcafe40a3aa834ce157fb2ba3: #REF!
Name zsupermetrics_NugLlrQxlKiqhxQae8EFpITBm1pLCj: 'OLD Formulas'!$B$6:$C$13
Name zsupermetrics_8xojRjNDjo2jWHGDWjFEhflhyIq3Hq: 'Sales OLD'!$K$8:$K$26
Name rdataslayer_42b112e4e4be4305bb4c1be75e2dd549: 'Business Metrics Canada'!$B$5:$C$12
Name rdataslayer_d70e473bcafe40a3aa834ce157fb2ba3: 'Business Metrics US'!$C$16:$D$17
Name rdataslayer_3753ddf3234e496aa261974a0222e193: #REF!
Name zsupermetrics_BioPyGBzcBsy60UCQmPcTuFReEmghI: 'Business Metrics Canada'!$B$5:$B$12

Sheet DataslayerQueries
A1: Query UUID | B1: Sheet name | C1: Range address | D1: Created | E1: Updated | F1: Last status | G1: Last refresh ID | H1: Results contain sampled data | I1: Execution time (sec) | J1: Object type | K1: Linked chart ID | L1: Data source | M1: Date range type | N1: Start date | O1: End date | P1: Compare to | Q1: Comparison value type | R1: Accounts/views | S1: Metrics | T1: Dimensions | U1: Pivot dimensions | V1: Filters | W1: Segment ID | X1: Segment dim | Y1: Sort | Z1: Max rows | AA1: Max pivot categories | AB1: Special settings | AC1: Other parameters | AD1: Result type | AE1: Language/country | AF1: Translate to | AG1: SQL | AH1: Database name | AI1: Range address (static) | AJ1: Report type | AK1: Highlight with colour | AL1: Refresh with user account | AM1: Returned data | AN1: Sort dimensions | AO1: Created by user account
A2: 42b112e4e4be4305bb4c1be75e2dd549 | B2: =IFERROR(__xludf.DUMMYFUNCTION("ARRAY_CONSTRAIN(split(CELL(""ADDRESS"",rdataslayer_42b112e4e4be4305bb4c1be75e2dd549),""!""),1,1)"),"#REF!") -> #REF! | C2: =IFERROR(__xludf.DUMMYFUNCTION("INDEX(split(CELL(""ADDRESS"",rdataslayer_42b112e4e4be4305bb4c1be75e2dd549),""!""),0,2)&"":""&address(row(rdataslayer_42b112e4e4be4305bb4c1be75e2dd549)+rows(rdataslayer_42b112e4e4be4305bb4c1be75e2dd549)-1,column(rdataslayer_42b112e4e4be4305bb4c1be75e2dd549"&")+COLUMNS(rdataslayer_42b112e4e4be4305bb4c1be75e2dd549)-1)"),"#REF!") -> #REF! | D2: 44518.613 | E2: 44520.051 | F2: There is no data for the specified input | I2: 7 | J2: TABLE | L2: facebook | M2: yesterday | R2: [{"profile_id":"","name":"si_Bird buddy Inc_US &amp; CA_BirdBuddy","id":"act_273249767551281","account_name":"","advertiser_id":""}] | S2: [{"id":"spend","name":"Total Cost"}] | T2: [{"id":"date","name":"Date"}] | U2: [] | V2: [] | W2: [] | Y2: [] | Z2: 5 | AA2: 5 | AB2: {} | AC2: {} | AL2: User_Kumalic_Benjamin | AN2: [] | AO2: benjamin@mybirdbuddy.com
A3: 4a0f150f4f2f4e4f85c890c75b7a1fa4 | B3: =IFERROR(__xludf.DUMMYFUNCTION("ARRAY_CONSTRAIN(split(CELL(""ADDRESS"",rdataslayer_4a0f150f4f2f4e4f85c890c75b7a1fa4),""!""),1,1)"),"#REF!") -> #REF! | C3: =IFERROR(__xludf.DUMMYFUNCTION("INDEX(split(CELL(""ADDRESS"",rdataslayer_4a0f150f4f2f4e4f85c890c75b7a1fa4),""!""),0,2)&"":""&address(row(rdataslayer_4a0f150f4f2f4e4f85c890c75b7a1fa4)+rows(rdataslayer_4a0f150f4f2f4e4f85c890c75b7a1fa4)-1,column(rdataslayer_4a0f150f4f2f4e4f85c890c75b7a1fa4"&")+COLUMNS(rdataslayer_4a0f150f4f2f4e4f85c890c75b7a1fa4)-1)"),"#REF!") -> #REF! | D3: 44518.615 | E3: 44520.051 | F3: There is no data for the specified input | I3: 7 | J3: TABLE | L3: facebook | M3: yesterday | R3: [{"account_name":"","advertiser_id":"","id":"act_273249767551281","profile_id":"","name":"si_Bird buddy Inc_US &amp; CA_BirdBuddy"}] | S3: [{"id":"spend","name":"Total Cost"}] | T3: [] | U3: [{"id":"date","name":"Date"}] | V3: [] | W3: [] | Y3: [] | Z3: 5 | AA3: 5 | AB3: {} | AC3: {} | AL3: User_Kumalic_Benjamin | AN3: [] | AO3: benjamin@mybirdbuddy.com
A4: adf57e64065742daa5b4161161b1c3ca | B4: =IFERROR(__xludf.DUMMYFUNCTION("ARRAY_CONSTRAIN(split(CELL(""ADDRESS"",rdataslayer_adf57e64065742daa5b4161161b1c3ca),""!""),1,1)"),"#REF!") -> #REF! | C4: =IFERROR(__xludf.DUMMYFUNCTION("INDEX(split(CELL(""ADDRESS"",rdataslayer_adf57e64065742daa5b4161161b1c3ca),""!""),0,2)&"":""&address(row(rdataslayer_adf57e64065742daa5b4161161b1c3ca)+rows(rdataslayer_adf57e64065742daa5b4161161b1c3ca)-1,column(rdataslayer_adf57e64065742daa5b4161161b1c3ca"&")+COLUMNS(rdataslayer_adf57e64065742daa5b4161161b1c3ca)-1)"),"#REF!") -> #REF! | D4: 44518.618 | E4: 44520.051 | F4: There is no data for the specified input | I4: 18 | J4: TABLE | L4: facebook | M4: yesterday | R4: [{"name":"si_Bird buddy Inc_US &amp; CA_BirdBuddy","id":"act_273249767551281","profile_id":"","account_name":"","advertiser_id":""}] | S4: [{"id":"spend","name":"Total Cost"},{"id":"cpm","name":"CPM"}] | T4: [{"id":"date","name":"Date"}] | U4: [] | V4: [] | W4: [] | Y4: [] | Z4: 5 | AA4: 5 | AB4: {} | AC4: {} | AL4: User_Kumalic_Benjamin | AN4: [] | AO4: benjamin@mybirdbuddy.com
A5: d70e473bcafe40a3aa834ce157fb2ba3 | B5: =IFERROR(__xludf.DUMMYFUNCTION("ARRAY_CONSTRAIN(split(CELL(""ADDRESS"",rdataslayer_d70e473bcafe40a3aa834ce157fb2ba3),""!""),1,1)"),"#REF!") -> #REF! | C5: =IFERROR(__xludf.DUMMYFUNCTION("INDEX(split(CELL(""ADDRESS"",rdataslayer_d70e473bcafe40a3aa834ce157fb2ba3),""!""),0,2)&"":""&address(row(rdataslayer_d70e473bcafe40a3aa834ce157fb2ba3)+rows(rdataslayer_d70e473bcafe40a3aa834ce157fb2ba3)-1,column(rdataslayer_d70e473bcafe40a3aa834ce157fb2ba3"&")+COLUMNS(rdataslayer_d70e473bcafe40a3aa834ce157fb2ba3)-1)"),"#REF!") -> #REF! | D5: 44518.619 | E5: 44520.051 | F5: There is no data for the specified input | I5: 7 | J5: TABLE | L5: facebook | M5: yesterday | R5: [{"advertiser_id":"","name":"si_Bird buddy Inc_US &amp; CA_BirdBuddy","id":"act_273249767551281","account_name":"","profile_id":""}] | S5: [{"id":"spend","name":"Total Cost"}] | T5: [{"id":"date","name":"Date"}] | U5: [] | V5: [] | W5: [] | Y5: [] | Z5: 100 | AA5: 100 | AB5: {} | AC5: {} | AL5: User_Kumalic_Benjamin | AN5: [] | AO5: benjamin@mybirdbuddy.com
A6: 3753ddf3234e496aa261974a0222e193 | B6: =IFERROR(__xludf.DUMMYFUNCTION("ARRAY_CONSTRAIN(split(CELL(""ADDRESS"",rdataslayer_3753ddf3234e496aa261974a0222e193),""!""),1,1)"),"#REF!") -> #REF! | C6: =IFERROR(__xludf.DUMMYFUNCTION("INDEX(split(CELL(""ADDRESS"",rdataslayer_3753ddf3234e496aa261974a0222e193),""!""),0,2)&"":""&address(row(rdataslayer_3753ddf3234e496aa261974a0222e193)+rows(rdataslayer_3753ddf3234e496aa261974a0222e193)-1,column(rdataslayer_3753ddf3234e496aa261974a0222e193"&")+COLUMNS(rdataslayer_3753ddf3234e496aa261974a0222e193)-1)"),"#REF!") -> #REF! | D6: 44518.621 | E6: 44520.051 | F6: There is no data for the specified input | I6: 18 | J6: TABLE | L6: facebook | M6: yesterday | R6: [{"profile_id":"","account_name":"","advertiser_id":"","name":"si_Bird buddy Inc_US &amp; CA_BirdBuddy","id":"act_273249767551281"}] | S6: [{"id":"spend","name":"Total Cost"}] | T6: [] | U6: [] | V6: [] | W6: [] | Y6: [] | Z6: 100 | AA6: 100 | AB6: {"exclude_header_row":true} | AC6: {} | AL6: User_Kumalic_Benjamin | AN6: [] | AO6: benjamin@mybirdbuddy.com

Sheet Summary
A1: 45231 | B1: 45231 | C1: 45232 | D1: 45233 | E1: 45234 | F1: 45235 | G1: 45236 | H1: 45237 | I1: 45238 | J1: 45239 | K1: 45240 | L1: 45241 | M1: 45242 | N1: 45243 | O1: 45244 | P1: 45245 | Q1: 45246 | R1: 45247 | S1: 45248 | T1: 45249 | U1: 45250 | V1: 45251 | W1: 45252 | X1: 45253 | Y1: 45254 | Z1: 45255 | AA1: 45256 | AB1: 45257 | AC1: 45258 | AD1: 45259 | AE1: 45260
B2: WED | C2: THU | D2: FRI | E2: SAT | F2: SUN | G2: MON | H2: TUE | I2: WED | J2: THU | K2: FRI | L2: SAT | M2: SUN | N2: MON | O2: TUE | P2: WED | Q2: THU | R2: FRI | S2: SAT | T2: SUN | U2: MON | V2: TUE | W2: WED | X2: THU | Y2: FRI | Z2: SAT | AA2: SUN | AB2: MON | AC2: TUE | AD2: WED | AE2: THU
A3: Weekend Work | B3: Peco | E3: Peco | F3: Peco | L3: Peter | M3: Peter | S3: Peco | T3: Peco | Z3: Peco | AA3: Peco
A4: Notes | B4: Halloween Sale - MAP | Y4: Accounts hacked
C5: 3in1 Launch | H5: Early Black Friday - MAP | K5: Black Friday Lowest Price Ever communication
I6: BB US Unit Shipping $15 | J6: Merch Launch | L6: Published in WSJ | W6: BF Email | Y6: D-Day | Z6: Fresh ad account | AA6: Main ad account restored | AB6: Amazon out of stock | AC6: Full Pricing is back at 14.00
A8: DTC Revenue | B8: 105288.85 | C8: 114299.05 | D8: 112607.15 | E8: 122040.63 | F8: 137885.87 | G8: 130202.04 | H8: 119604.06 | I8: 123367.12 | J8: 132758.96 | K8: 129650.69 | L8: 170840.54 | M8: 167598.98 | N8: 144526.94 | O8: 150855.82 | P8: 138667.14 | Q8: 128700 | R8: 137223.22 | S8: 174001.55 | T8: 184464.08 | U8: 194400.84 | V8: 198063.87 | W8: 290518.02 | X8: 350215.16 | Y8: 952032.29 | Z8: 589382.83 | AA8: 442601.05 | AB8: 679709.11 | AC8: 479681.85 | AD8: 104651.11 | AE8: 94859.28
A9: - Hardware | B9: 85464.76 | C9: 88820.66 | D9: 90446.48 | E9: 97964.77 | F9: 112993.92 | G9: 106383.84 | H9: 97516.45 | I9: 97998.57 | J9: 105495.71 | K9: 103305.74 | L9: 135481.65 | M9: 130709.47 | N9: 104808.29 | O9: 120021.9 | P9: 110332.61 | Q9: 101442.48 | R9: 109297.97 | S9: 139757.95 | T9: 148816.8 | U9: 155473.12 | V9: 159649.26 | W9: 232257.49 | X9: 279269.34 | Y9: 768682.68 | Z9: 480538.29 | AA9: 355864.59 | AB9: 554099.5 | AC9: 394641.7 | AD9: 85839.83 | AE9: 76648.21
A10: - Add-ons | B10: 6707.54 | C10: 10578.54 | D10: 9279.32 | E10: 10715.53 | F10: 9847.38 | G10: 9498.36 | H10: 9096.2 | I10: 10900.63 | J10: 10081.86 | K10: 9833.36 | L10: 14204.65 | M10: 15202.53 | N10: 17902.76 | O10: 11276.86 | P10: 10034.39 | Q10: 10184.52 | R10: 9958.2 | S10: 11848.7 | T10: 12208.7 | U10: 14372.88 | V10: 13573.49 | W10: 22112.66 | X10: 26913.89 | Y10: 64135.85 | Z10: 34635.81 | AA10: 31300.7 | AB10: 40412.44 | AC10: 25503.7 | AD10: 7747.32 | AE10: 7659.93
A11: - Merch | B11: 0 | C11: 0 | D11: 0 | E11: 0 | F11: 0 | G11: 0 | H11: 0 | I11: 0 | J11: 552.01 | K11: 356.89 | L11: 281.81 | M11: 164.95 | N11: 0 | O11: 681.63 | P11: 662.92 | Q11: 844.78 | R11: 636.28 | S11: 271.98 | T11: 215.97 | U11: 185.98 | V11: 275.99 | W11: 406.99 | X11: 415.66 | Y11: 911.63 | Z11: 605.98 | AA11: 275.01 | AB11: 776.95 | AC11: 788.98 | AD11: 172.99 | AE11: 114
A12: - Seeds
A13: - Taxes | B13: 5816.55 | C13: 6484.85 | D13: 6121.35 | E13: 7055.33 | F13: 7974.57 | G13: 7404.84 | H13: 6681.41 | I13: 6882.92 | J13: 7181.38 | K13: 7019.7 | L13: 9404.43 | M13: 9065.03 | N13: 8205.89 | O13: 8084.43 | P13: 7629.22 | Q13: 6860.22 | R13: 7425.77 | S13: 9037.92 | T13: 9827.61 | U13: 10093.86 | V13: 10475.13 | W13: 14995.88 | X13: 18816.27 | Y13: 53419.13 | Z13: 33357.75 | AA13: 23750.75 | AB13: 38985.22 | AC13: 27392.47 | AD13: 5705.97 | AE13: 5427.14
A14: - Shipping | B14: 7300 | C14: 8415 | D14: 6760 | E14: 6305 | F14: 7070 | G14: 6915 | H14: 6310 | I14: 7585 | J14: 9448 | K14: 9135 | L14: 11468 | M14: 12457 | N14: 13610 | O14: 10791 | P14: 10008 | Q14: 9368 | R14: 9905 | S14: 13085 | T14: 13395 | U14: 14275 | V14: 14090 | W14: 20745 | X14: 24800 | Y14: 64883 | Z14: 40245 | AA14: 31410 | AB14: 45435 | AC14: 31355 | AD14: 5185 | AE14: 5010
A15: Amazon Revenue | B15: =SUM(B16:B20) -> 9998.64 | C15: =SUM(C16:C20) -> 10453.96 | D15: =SUM(D16:D20) -> 16043.42 | E15: =SUM(E16:E20) -> 15088.14 | F15: =SUM(F16:F20) -> 19511.77 | G15: =SUM(G16:G20) -> 15164.18 | H15: =SUM(H16:H20) -> 12460.48 | I15: =SUM(I16:I20) -> 14308.41 | ... AE15: =SUM(AE16:AE20) -> 540.1
A16: - Hardware | B16: 9193 | C16: 9677.76 | D16: 14877.86 | E16: 14028.38 | F16: 18099.43 | G16: 14185 | H16: 11584.43 | I16: 13067.81 | J16: 20859.28 | K16: 27638.76 | L16: 36779.09 | M16: 34737.14 | N16: 34577.9 | O16: 36524.81 | P16: 36879.17 | Q16: 43135.38 | R16: 47392.32 | S16: 55557.25 | T16: 38666.59 | U16: 90083.38 | V16: 99805.68 | W16: 114068.3 | X16: 149568.42 | Y16: 594889.04 | Z16: 365780.37 | AA16: 231202.98 | AB16: 72457.99 | AC16: 0 | AD16: 0 | AE16: 478
A17: - Add-ons | B17: 144 | C17: 72 | D17: 117.6 | E17: 96 | F17: 142.8 | G17: 96 | H17: 94.8 | I17: 262.8 | J17: 216 | K17: 120 | L17: 214.8 | M17: 240 | N17: 120 | O17: 214.8 | P17: 192 | Q17: 576 | R17: 502.8 | S17: 696 | T17: 605.9 | U17: 863.7 | V17: 976.59 | W17: 815.5 | X17: 1287.9 | Y17: 3856.09 | Z17: 1296 | AA17: 192 | AB17: 48 | AC17: 0 | AD17: 40 | AE17: 29
A18: - Tax | B18: 649.85 | C18: 696.41 | D18: 1038.18 | E18: 947.39 | F18: 1262.15 | G18: 869.71 | H18: 771.81 | I18: 963.53 | J18: 1442.59 | K18: 1915.06 | L18: 2629.44 | M18: 2388.49 | N18: 2399.04 | O18: 2510.61 | P18: 2616.64 | Q18: 3063.65 | R18: 3338.55 | S18: 3872.14 | T18: 2750.01 | U18: 6355.92 | V18: 7181.12 | W18: 7881.51 | X18: 10502.78 | Y18: 42104.68 | Z18: 25752.03 | AA18: 16557.32 | AB18: 5150.32 | AC18: 0 | AD18: 3.71 | AE18: 33.1
A19: - Shipping | B19: 11.79 | C19: 7.49 | D19: 0.5 | E19: 7.24 | F19: 2.75 | G19: 0 | H19: 0.31 | I19: 0.5 | J19: 24.14 | K19: 14.16 | L19: 2 | M19: 21.16 | N19: 25.45 | O19: 0.5 | P19: 37.43 | Q19: 5.51 | R19: 5.39 | S19: 28.49 | T19: 61.6 | U19: 52.57 | V19: 175.38 | W19: 87.25 | X19: 155.77 | Y19: 416.82 | Z19: 134.4 | AA19: 127.92 | AB19: 1301.75 | AC19: 0 | AD19: 15 | AE19: 0
A20: - Gift Wrap | B20: 0 | C20: 0.3 | D20: 9.28 | E20: 9.13 | F20: 4.64 | G20: 13.47 | H20: 9.13 | I20: 13.77 | J20: 18.86 | K20: 18.26 | L20: 14.67 | M20: 31.88 | N20: 14.22 | O20: 9.28 | P20: 9.88 | Q20: 18.86 | R20: 44.55 | S20: 27.24 | T20: 9.28 | U20: 95.34 | V20: 67.75 | W20: 64.36 | X20: 123.33 | Y20: 384.47 | Z20: 357.37 | AA20: 200.71 | AB20: 19.61 | AC20: 0 | AD20: 0 | AE20: 0
A21: Digital Marketplaces Revenue | B21: =SUM(B30,B26,B22) -> 619.2186 | C21: =SUM(C30,C26,C22) -> 1017 | D21: =SUM(D30,D26,D22) -> 566 | E21: =SUM(E30,E26,E22) -> 22212.501 | F21: =SUM(F30,F26,F22) -> 12330.909 | G21: =SUM(G30,G26,G22) -> 48255.884 | H21: =SUM(H30,H26,H22) -> 6842.2291 | I21: =SUM(I30,I26,I22) -> 1682.7254 | ... AE21: =SUM(AE30,AE26,AE22) -> 1378.5442
A22: Rachio | B22: =sum(B23:B24) -> 211.2186 | C22: =sum(C23:C24) -> 0 | D22: =sum(D23:D24) -> 0 | E22: =sum(E23:E24) -> 21715.501 | F22: =sum(F23:F24) -> 10825.909 | G22: =sum(G23:G24) -> 47060.884 | H22: =sum(H23:H24) -> 6559.2291 | I22: =sum(I23:I24) -> 254.72539 | ... AE22: =sum(AE23:AE24) -> 891.54416
A23: - Hardware | B23: 199 | C23: 0 | D23: 0 | E23: 20459.3 | F23: 10199.65 | G23: 44338.5 | H23: 6179.79 | I23: 239.99 | J23: 2639.91 | K23: 899.97 | L23: 899.97 | M23: 1199.96 | N23: 1199.96 | O23: 299.99 | P23: 1979.93 | Q23: 10439.65 | R23: 1739.94 | S23: 2099.93 | T23: 2099.93 | U23: 2339.92 | V23: 2399.92 | W23: 2399.92 | X23: 4379.85 | Y23: 5219.82 | Z23: 839.97 | AA23: 15179.48 | AB23: 25679.13 | AC23: 9779.67 | AD23: 1139.96 | AE23: 839.97
A24: - Tax | B24: =B23*'Data - P&L'!$U$3 -> 12.2186 | C24: =C23*'Data - P&L'!$U$3 -> 0 | D24: =D23*'Data - P&L'!$U$3 -> 0 | E24: =E23*'Data - P&L'!$U$3 -> 1256.201 | F24: =F23*'Data - P&L'!$U$3 -> 626.25851 | G24: =G23*'Data - P&L'!$U$3 -> 2722.3839 | H24: =H23*'Data - P&L'!$U$3 -> 379.43911 | I24: =I23*'Data - P&L'!$U$3 -> 14.735386 | ... AE24: =AE23*'Data - P&L'!$U$3 -> 51.574158
A25: - Shipping
A26: Weatherflow
A27: - Hardware
A28: - Tax
A29: - Shipping
A30: IndieGoGo | B30: =sum(B31:B34) -> 408 | C30: =sum(C31:C34) -> 1017 | D30: =sum(D31:D34) -> 566 | E30: =sum(E31:E34) -> 497 | F30: =sum(F31:F34) -> 1505 | G30: =sum(G31:G34) -> 1195 | H30: =sum(H31:H34) -> 283 | I30: =sum(I31:I34) -> 1428 | ... AE30: =sum(AE31:AE34) -> 487
A31: - Hardware | B31: 378 | C31: 698 | D31: 378 | E31: 0 | F31: 1187 | G31: 887 | H31: 189 | I31: 1353 | J31: 199 | K31: 0 | L31: 887 | M31: 378 | N31: 189 | O31: 378 | P31: 189 | Q31: 189 | R31: 0 | S31: 0 | T31: 388 | U31: 688 | V31: 0 | W31: 766 | X31: 0 | Y31: 1444 | Z31: 1794 | AA31: 756 | AB31: 378 | AC31: 0 | AD31: 189 | AE31: 378
A32: - Add-ons | B32: 0 | C32: 269 | D32: 158 | E32: 467 | F32: 253 | G32: 253 | H32: 79 | I32: 0 | J32: 95 | K32: 0 | L32: 253 | M32: 79 | N32: 79 | O32: 79 | P32: 0 | Q32: 79 | R32: 0 | S32: 0 | T32: 0 | U32: 253 | V32: 0 | W32: 253 | X32: 0 | Y32: 332 | Z32: 190 | AA32: 237 | AB32: 158 | AC32: 358 | AD32: 0 | AE32: 79
A33: - Taxes | B33: 0 | C33: 0 | D33: 0 | E33: 0 | F33: 0 | G33: 0 | H33: 0 | I33: 0 | J33: 0 | K33: 0 | L33: 0 | M33: 0 | N33: 0 | O33: 0 | P33: 0 | Q33: 0 | R33: 0 | S33: 0 | T33: 0 | U33: 0 | V33: 0 | W33: 0 | X33: 0 | Y33: 0 | Z33: 0 | AA33: 0 | AB33: 0 | AC33: 0 | AD33: 0 | AE33: 0
A34: - Shipping | B34: 30 | C34: 50 | D34: 30 | E34: 30 | F34: 65 | G34: 55 | H34: 15 | I34: 75 | J34: 25 | K34: 0 | L34: 55 | M34: 30 | N34: 15 | O34: 30 | P34: 15 | Q34: 15 | R34: 0 | S34: 0 | T34: 30 | U34: 50 | V34: 0 | W34: 60 | X34: 0 | Y34: 100 | Z34: 120 | AA34: 60 | AB34: 30 | AC34: 20 | AD34: 15 | AE34: 30
A35: Total Revenue | B35: =SUM(B8+B15+B21+B30) -> 116314.71 | C35: =SUM(C8+C15+C21+C30) -> 126787.01 | D35: =SUM(D8+D15+D21+D30) -> 129782.57 | E35: =SUM(E8+E15+E21+E30) -> 159838.27 | F35: =SUM(F8+F15+F21+F30) -> 171233.55 | G35: =SUM(G8+G15+G21+G30) -> 194817.1 | H35: =SUM(H8+H15+H21+H30) -> 139189.77 | I35: =SUM(I8+I15+I21+I30) -> 140786.26 | ... AE35: =SUM(AE8+AE15+AE21+AE30) -> 97264.924
A37: B2B Revenue
A38: Best Buy | G38: =SUM(G39:G40) -> 509.472 | H38: =SUM(H39:H40) -> 445.788 | I38: =SUM(I39:I40) -> 222.894 | J38: =SUM(J39:J40) -> 1337.364 | K38: =SUM(K39:K40) -> 7578.396 | L38: =SUM(L39:L40) -> 5572.35 | M38: =SUM(M39:M40) -> 7348.0722 | N38: =SUM(N39:N40) -> 4457.88 | ... AE38: =SUM(AE39:AE40) -> 57949.256
A39: - Hardware | G39: 480 | H39: 420 | I39: 210 | J39: 1260 | K39: 7140 | L39: 5250 | M39: 6923 | N39: 4200 | O39: 5450 | P39: 3150 | Q39: 1470 | R39: 4410 | S39: 2520 | T39: 6720 | U39: 4830 | V39: 3360 | W39: 7980 | X39: 11339 | Y39: 32758 | Z39: 10500 | AA39: 10500 | AB39: 60477 | AC39: 42208 | AD39: 43258 | AE39: 54597
A40: - Tax | G40: =G39*'Data - P&L'!$U$3 -> 29.472 | H40: =H39*'Data - P&L'!$U$3 -> 25.788 | I40: =I39*'Data - P&L'!$U$3 -> 12.894 | J40: =J39*'Data - P&L'!$U$3 -> 77.364 | K40: =K39*'Data - P&L'!$U$3 -> 438.396 | L40: =L39*'Data - P&L'!$U$3 -> 322.35 | M40: =M39*'Data - P&L'!$U$3 -> 425.0722 | N40: =N39*'Data - P&L'!$U$3 -> 257.88 | ... AE40: =AE39*'Data - P&L'!$U$3 -> 3352.2558
A41: Target
A42: - Hardware
A43: - Tax
A44: Total Revenue | B44: =B38 | C44: =C38 | D44: =D38 | E44: =E38 | F44: =F38 | G44: =G38 -> 509.472 | H44: =H38 -> 445.788 | I44: =I38 -> 222.894 | ... AE44: =AE38 -> 57949.256
A46: App Revenue
A47: - Google Store | B47: ='App - P&L'!B90 -> 84.677 | C47: ='App - P&L'!C90 -> 140.998 | D47: ='App - P&L'!D90 -> 60.469 | E47: ='App - P&L'!E90 -> 349.6205 | F47: ='App - P&L'!F90 -> 241.919 | G47: ='App - P&L'!G90 -> 57.6675 | H47: ='App - P&L'!H90 -> 152.232 | I47: ='App - P&L'!I90 -> 254.7435 | ... AE47: ='App - P&L'!AE90 -> 158.926
A48: - Apple Store | B48: ='App - P&L'!B91 -> 339.73821 | C48: ='App - P&L'!C91 -> 558.30126 | D48: ='App - P&L'!D91 -> 504.6811 | E48: ='App - P&L'!E91 -> 1171.7564 | F48: ='App - P&L'!F91 -> 1080.9353 | G48: ='App - P&L'!G91 -> 715.33954 | H48: ='App - P&L'!H91 -> 540.21655 | I48: ='App - P&L'!I91 -> 688.2394 | ... AE48: ='App - P&L'!AE91 -> 1058.6786
A49: - Comission | B49: ='App - P&L'!B67 -> 161.01223 | C49: ='App - P&L'!C67 -> 269.0954 | D49: ='App - P&L'!D67 -> 232.59433 | E49: ='App - P&L'!E67 -> 576.46367 | F49: ='App - P&L'!F67 -> 512.60328 | G49: ='App - P&L'!G67 -> 328.7323 | H49: ='App - P&L'!H67 -> 263.43795 | I49: ='App - P&L'!I67 -> 349.71767 | ... AE49: ='App - P&L'!AE67 -> 483.2977
A50: - Tax | B50: ='App - P&L'!B68 -> 1.09 | C50: ='App - P&L'!C68 -> 11.53 | D50: ='App - P&L'!D68 -> 13.14 | E50: ='App - P&L'!E68 -> 30.07 | F50: ='App - P&L'!F68 -> 22.19 | G50: ='App - P&L'!G68 -> 34.61 | H50: ='App - P&L'!H68 -> 12.1 | I50: ='App - P&L'!I68 -> 34.28 | ... AE50: ='App - P&L'!AE68 -> 6.67
A51: Total Revenue | B51: =sum(B47:B50) -> 586.51744 | C51: =sum(C47:C50) -> 979.92465 | D51: =sum(D47:D50) -> 810.88444 | E51: =sum(E47:E50) -> 2127.9106 | F51: =sum(F47:F50) -> 1857.6476 | G51: =sum(G47:G50) -> 1136.3493 | H51: =sum(H47:H50) -> 967.9865 | I51: =sum(I47:I50) -> 1326.9806 | ... AE51: =sum(AE47:AE50) -> 1707.5723
A54: DTC Orders | B54: 456 | C54: 542 | D54: 522 | E54: 542 | F54: 614 | G54: 588 | H54: 526 | I54: 538 | J54: 580 | K54: 567 | L54: 702 | M54: 777 | N54: 980 | O54: 641 | P54: 595 | Q54: 558 | R54: 600 | S54: 739 | T54: 773 | U54: 804 | V54: 841 | W54: 1244 | X54: 1456 | Y54: 4000 | Z54: 2499 | AA54: 1858 | AB54: 2844 | AC54: 1980 | AD54: 342 | AE54: 320
A55: - Hardware (units sold) | B55: 445 | C55: 463 | D55: 467 | E55: 510 | F55: 590 | G55: 554 | H55: 505 | I55: 504 | J55: 546 | K55: 537 | L55: 687 | M55: 670 | N55: 539 | O55: 612 | P55: 566 | Q55: 522 | R55: 568 | S55: 721 | T55: 765 | U55: 799 | V55: 832 | W55: 1213 | X55: 1437 | Y55: 3986 | Z55: 2510 | AA55: 1846 | AB55: 2857 | AC55: 1967 | AD55: 310 | AE55: 279
A56: - Add-ons (units sold) | B56: 588 | C56: 741 | D56: 708 | E56: 750 | F56: 769 | G56: 721 | H56: 710 | I56: 742 | J56: 761 | K56: 743 | L56: 1020 | M56: 1061 | N56: 1164 | O56: 848 | P56: 752 | Q56: 724 | R56: 747 | S56: 940 | T56: 745 | U56: 989 | V56: 1031 | W56: 1604 | X56: 1998 | Y56: 4899 | Z56: 2845 | AA56: 2336 | AB56: 3202 | AC56: 1931 | AD56: 239 | AE56: 234
A57: - Merch (units sold) | B57: 0 | C57: 0 | D57: 0 | E57: 0 | F57: 0 | G57: 0 | H57: 0 | I57: 0 | J57: 20 | K57: 13 | L57: 12 | M57: 5 | N57: 0 | O57: 25 | P57: 24 | Q57: 29 | R57: 22 | S57: 10 | T57: 7 | U57: 6 | V57: 10 | W57: 14 | X57: 17 | Y57: 50 | Z57: 31 | AA57: 15 | AB57: 39 | AC57: 41 | AD57: 8 | AE57: 6
A58: - Seeds (units sold)
A59: Amazon Orders | B59: 42 | C59: 40 | D59: 61 | E59: 58 | F59: 74 | G59: 56 | H59: 50 | I59: 65 | J59: 105 | K59: 132 | L59: 171 | M59: 171 | N59: 157 | O59: 172 | P59: 182 | Q59: 224 | R59: 232 | S59: 287 | T59: 202 | U59: 444 | V59: 502 | W59: 576 | X59: 752 | Y59: 2906 | Z59: 1756 | AA59: 1087 | AB59: 332 | AC59: 0 | AD59: 1 | AE59: 3
A60: - Hardware (units sold) | B60: 37 | C60: 37 | D60: 57 | E60: 54 | F60: 68 | G60: 55 | H60: 46 | I60: 58 | J60: 96 | K60: 126 | L60: 165 | M60: 160 | N60: 155 | O60: 165 | P60: 177 | Q60: 207 | R60: 229 | S60: 267 | T60: 180 | U60: 432 | V60: 477 | W60: 548 | X60: 716 | Y60: 2848 | Z60: 1752 | AA60: 1107 | AB60: 347 | AC60: 0 | AD60: 0 | AE60: 2
A61: - Add-ons (units sold) | B61: 6 | C61: 3 | D61: 5 | E61: 4 | F61: 6 | G61: 4 | H61: 4 | I61: 11 | J61: 9 | K61: 6 | L61: 9 | M61: 11 | N61: 6 | O61: 9 | P61: 8 | Q61: 24 | R61: 21 | S61: 29 | T61: 29 | U61: 36 | V61: 41 | W61: 35 | X61: 53 | Y61: 161 | Z61: 54 | AA61: 8 | AB61: 2 | AC61: 0 | AD61: 1 | AE61: 1
A62: Digital Marketplaces Orders | B62: =SUM(B63:B64) -> 1 | C62: =SUM(C63:C64) -> 0 | D62: =SUM(D63:D64) -> 0 | E62: =SUM(E63:E64) -> 71 | F62: =SUM(F63:F64) -> 36 | G62: =SUM(G63:G64) -> 150 | H62: =SUM(H63:H64) -> 21 | I62: =SUM(I63:I64) -> 1 | ... AE62: =SUM(AE63:AE64) -> 3
A63: Rachio Orders | B63: 1 | C63: 0 | D63: 0 | E63: 71 | F63: 36 | G63: 150 | H63: 21 | I63: 1 | J63: 11 | K63: 3 | L63: 3 | M63: 4 | N63: 4 | O63: 1 | P63: 7 | Q63: 35 | R63: 6 | S63: 7 | T63: 7 | U63: 8 | V63: 8 | W63: 8 | X63: 17 | Y63: 19 | Z63: 3 | AA63: 53 | AB63: 87 | AC63: 33 | AD63: 4 | AE63: 3
A64: Weatherflow Orders
A65: IndieGoGo Orders | B65: 2 | C65: 2 | D65: 2 | E65: 1 | F65: 3 | G65: 3 | H65: 1 | I65: 5 | J65: 1 | K65: 0 | L65: 3 | M65: 2 | N65: 1 | O65: 2 | P65: 1 | Q65: 1 | R65: 0 | S65: 0 | T65: 2 | U65: 2 | V65: 0 | W65: 4 | X65: 0 | Y65: 6 | Z65: 6 | AA65: 4 | AB65: 2 | AC65: 1 | AD65: 1 | AE65: 2
A66: - Hardware (units sold) | B66: 2 | C66: 3 | D66: 2 | E66: 2 | F66: 5 | G66: 4 | H66: 1 | I66: 7 | J66: 1 | K66: 0 | L66: 4 | M66: 2 | N66: 1 | O66: 2 | P66: 1 | Q66: 1 | R66: 0 | S66: 0 | T66: 2 | U66: 3 | V66: 0 | W66: 4 | X66: 0 | Y66: 7 | Z66: 8 | AA66: 4 | AB66: 2 | AC66: 1 | AD66: 1 | AE66: 2
A67: - Add-ons (units sold) | B67: 0 | C67: 3 | D67: 2 | E67: 1 | F67: 3 | G67: 3 | H67: 1 | I67: 0 | J67: 1 | K67: 0 | L67: 3 | M67: 1 | N67: 1 | O67: 1 | P67: 0 | Q67: 1 | R67: 0 | S67: 0 | T67: 0 | U67: 3 | V67: 0 | W67: 3 | X67: 0 | Y67: 4 | Z67: 2 | AA67: 3 | AB67: 2 | AC67: 1 | AD67: 0 | AE67: 1
A68: Total Orders | B68: =SUM(B54+B59+B62+B65) -> 501 | C68: =SUM(C54+C59+C62+C65) -> 584 | D68: =SUM(D54+D59+D62+D65) -> 585 | E68: =SUM(E54+E59+E62+E65) -> 672 | F68: =SUM(F54+F59+F62+F65) -> 727 | G68: =SUM(G54+G59+G62+G65) -> 797 | H68: =SUM(H54+H59+H62+H65) -> 598 | I68: =SUM(I54+I59+I62+I65) -> 609 | ... AE68: =SUM(AE54+AE59+AE62+AE65) -> 328
A70: B2B Orders
A71: Best Buy | G71: 2 | H71: 2 | I71: 1 | J71: 6 | K71: 34 | L71: 25 | M71: 33 | N71: 20 | O71: 26 | P71: 15 | Q71: 7 | R71: 21 | S71: 12 | T71: 32 | U71: 23 | V71: 16 | W71: 38 | X71: 54 | Y71: 155 | Z71: 50 | AA71: 50 | AB71: 288 | AC71: 201 | AD71: 206 | AE71: 260
A72: Target
A73: Total Orders | B73: =B71 | C73: =C71 | D73: =D71 | E73: =E71 | F73: =F71 | G73: =G71 -> 2 | H73: =H71 -> 2 | I73: =I71 -> 1 | ... AE73: =AE71 -> 260
A75: App Orders
A76: - Google Store | B76: ='App - P&L'!B17 -> 5 | C76: ='App - P&L'!C17 -> 7 | D76: ='App - P&L'!D17 -> 4 | E76: ='App - P&L'!E17 -> 19 | F76: ='App - P&L'!F17 -> 11 | G76: ='App - P&L'!G17 -> 8 | H76: ='App - P&L'!H17 -> 11 | I76: ='App - P&L'!I17 -> 17 | ... AE76: ='App - P&L'!AE17 -> 9
A77: - Apple Store | B77: ='App - P&L'!B14 -> 25 | C77: ='App - P&L'!C14 -> 35 | D77: ='App - P&L'!D14 -> 36 | E77: ='App - P&L'!E14 -> 70 | F77: ='App - P&L'!F14 -> 70 | G77: ='App - P&L'!G14 -> 49 | H77: ='App - P&L'!H14 -> 43 | I77: ='App - P&L'!I14 -> 52 | ... AE77: ='App - P&L'!AE14 -> 74
A78: Total Orders | B78: =sum(B76:B77) -> 30 | C78: =sum(C76:C77) -> 42 | D78: =sum(D76:D77) -> 40 | E78: =sum(E76:E77) -> 89 | F78: =sum(F76:F77) -> 81 | G78: =sum(G76:G77) -> 57 | H78: =sum(H76:H77) -> 54 | I78: =sum(I76:I77) -> 69 | ... AE78: =sum(AE76:AE77) -> 83
A79: Meta Spend EUR | B79: 30641.98 | C79: =27383.87 -> 27383.87 | D79: =29382.72 -> 29382.72 | E79: =26160.27 -> 26160.27 | F79: =26171.91 -> 26171.91 | G79: =27686.05 -> 27686.05 | H79: =24081.99 -> 24081.99 | I79: =30503 -> 30503 | J79: =35831.33 -> 35831.33 | K79: =32023.8 -> 32023.8 | L79: =24957.94 -> 24957.94 | M79: =27954.32 -> 27954.32 | N79: =25034.41 -> 25034.41 | O79: =25568.69 -> 25568.69 | P79: =28004.97 -> 28004.97 | Q79: =25998.76 -> 25998.76 | R79: =21968.55 -> 21968.55 | S79: =24028.71 -> 24028.71 | T79: =27684.62 -> 27684.62 | U79: =31275.04 -> 31275.04 | V79: =34520.65 -> 34520.65 | W79: =41565.6 -> 41565.6 | X79: =76989.74 -> 76989.74 | Y79: =263335.22+220.38 -> 263555.6 | Z79: =21884.46+64125.35 -> 86009.81 | AA79: =83573.91+863.99 -> 84437.9 | AB79: 103091.38 | AC79: 76268.26 | AD79: 26961.65 | AE79: 12457.27
A80: Currency rate | B80: 1.0585 | C80: 1.0616 | D80: 1.0736 | E80: 1.0736 | F80: 1.0732 | G80: 1.0719 | H80: 1.0697 | I80: 1.071 | J80: 1.0667 | K80: 1.0716 | L80: 1.0698 | M80: 1.069 | N80: 1.0701 | O80: 1.0879 | P80: 1.0853 | Q80: 1.0853 | R80: 1.0918 | S80: 1.0918 | T80: 1.0907 | U80: 1.0946 | V80: 1.0916 | W80: 1.0887 | X80: 1.0905 | Y80: 1.0946 | Z80: 1.0946 | AA80: 1.094 | AB80: 1.0958 | AC80: 1.1004 | AD80: 1.0973 | AE80: 1.0895
A81: Meta Spend | B81: =B79*B80 -> 32434.536 | C81: =C79*C80 -> 29070.716 | D81: =D79*D80 -> 31545.288 | E81: =E79*E80 -> 28085.666 | F81: =F79*F80 -> 28087.694 | G81: =G79*G80 -> 29676.677 | H81: =H79*H80 -> 25760.505 | I81: =I79*I80 -> 32668.713 | ... AE81: =AE79*AE80 -> 13572.196
A82: Google Spend | B82: 4770.48 | C82: 5351.07 | D82: 6050.06 | E82: 7040.29 | F82: 8856.02 | G82: 8610.7 | H82: 7930.14 | I82: 8941.43 | J82: 10391.03 | K82: 10980.77 | L82: 9973.07 | M82: 7716.96 | N82: 8350.01 | O82: 7527.11 | P82: 7388.62 | Q82: 8231.69 | R82: 9096.16 | S82: 9471.16 | T82: 10530.29 | U82: 10231.9 | V82: 10648.45 | W82: 9893.12 | X82: 16738.54 | Y82: 21372.09 | Z82: 19592.41 | AA82: 17201.25 | AB82: 18167.84 | AC82: 16152.17 | AD82: 7994.65 | AE82: 5438.57
A83: Bing Spend | B83: 239.79 | C83: 254.86 | D83: 278.94 | E83: 309.46 | F83: 254.73 | G83: 398.68 | H83: 376.76 | I83: 415.9 | J83: 424.32 | K83: 415.8 | L83: 349.18 | M83: 382.43 | N83: 360.89 | O83: 422.46 | P83: 427.45 | Q83: 433.39 | R83: 432.25 | S83: 360.46 | T83: 428.39 | U83: 429.17 | V83: 430.31 | W83: 430.8 | X83: 472.05 | Y83: 578.08 | Z83: 467.09 | AA83: 602.67 | AB83: 633.77 | AC83: 630.56 | AD83: 508.16 | AE83: 348.29
A84: TikTok Spend | B84: 0 | C84: 0 | D84: 0 | E84: 0 | F84: 0 | G84: 0 | H84: 0 | I84: 0 | J84: 0 | K84: 0 | L84: 0 | M84: 0 | N84: 0 | O84: 0 | P84: 159.15 | Q84: 400.43 | R84: 189.07 | S84: 0 | T84: 0 | U84: 0 | V84: 0 | W84: 0 | X84: 0 | Y84: 0 | Z84: 0 | AA84: 0 | AB84: 0 | AC84: 0 | AD84: 0 | AE84: 0
A85: Amazon Spend | B85: 3233.72 | C85: 3207.21 | D85: 3213.69 | E85: 4807.14 | F85: 5368.78 | G85: 3970.36 | H85: 3978.92 | I85: 2768.25 | J85: 4407.86 | K85: 4898.09 | L85: 6117.76 | M85: 7242.64 | N85: 5702.9 | O85: 6085.6 | P85: 6488.79 | Q85: 7566.72 | R85: 9338.68 | S85: 11591.54 | T85: 11090.34 | U85: 17470.42 | V85: 19951.33 | W85: 22610.15 | X85: 28585.82 | Y85: 64437.46 | Z85: 37785.34 | AA85: 37554.44 | AB85: 3641.98 | AC85: 0 | AD85: 0 | AE85: 433.94
A86: Nextdoor Spend | B86: 0 | C86: 0 | D86: 0 | E86: 0 | F86: 0 | G86: 0 | H86: 0 | I86: 0 | J86: 0 | K86: 0 | L86: 0 | M86: 0 | N86: 0 | O86: 0 | P86: 0 | Q86: 0 | R86: 192.23 | S86: 303.11 | T86: 300.88 | U86: 660.39 | V86: 481.73 | W86: 187.74 | X86: 143.11 | Y86: 57.99 | Z86: 136.47 | AA86: 705.4 | AB86: 834.58 | AC86: 0 | AD86: 0 | AE86: 0
A87: IndieGoGo Spend | B87: 0 | C87: 0 | D87: 0 | E87: 0 | F87: 0 | G87: 0 | H87: 0 | I87: 0 | J87: 0 | K87: 0 | L87: 0 | M87: 0 | N87: 0 | O87: 0 | P87: 0 | Q87: 0 | R87: 0 | S87: 0 | T87: 0 | U87: 0 | V87: 0 | W87: 0 | X87: 0 | Y87: 0 | Z87: 0 | AA87: 0 | AB87: 0 | AC87: 0 | AD87: 0 | AE87: 0
A88: Affiliate Fees | B88: 162.71 | C88: 61 | D88: 0 | E88: 4255.588 | F88: 2292.936 | G88: 63.09 | H88: 86.6 | I88: 0 | J88: 0 | K88: 99.96 | L88: 0 | M88: 324.88 | N88: 97.43 | O88: 100.64 | P88: 55.28 | Q88: 0 | R88: 105.32 | S88: 0 | T88: 0 | U88: 0 | V88: 32.38 | W88: 105.6 | X88: 266.9 | Y88: 94.59 | Z88: 123.15 | AA88: 106.16 | AB88: 497.95 | AC88: 377.37 | AD88: 68.6 | AE88: 13.6
A89: Rachio Fees | B89: =B22*0.2 -> 42.24372 | C89: =C22*0.2 -> 0 | D89: =D22*0.2 -> 0 | E89: =E22*0.2 -> 4343.1002 | F89: =F22*0.2 -> 2165.1817 | G89: =G22*0.2 -> 9412.1768 | H89: =H22*0.2 -> 1311.8458 | I89: =I22*0.2 -> 50.945077 | ... AE89: =AE22*0.2 -> 178.30883
A90: Weatherflow Fees | B90: =B26*0.15 -> 0 | C90: =C26*0.15 -> 0 | D90: =D26*0.15 -> 0 | E90: =E26*0.15 -> 0 | F90: =F26*0.15 -> 0 | G90: =G26*0.15 -> 0 | H90: =H26*0.15 -> 0 | I90: =I26*0.15 -> 0 | ... AE90: =AE26*0.15 -> 0
A91: Total DTC Spend | B91: =B81+B82+B83+B84+B86+B88 -> 37607.516 | C91: =C81+C82+C83+C84+C86+C88 -> 34737.646 | D91: =D81+D82+D83+D84+D86+D88 -> 37874.288 | E91: =E81+E82+E83+E84+E86+E88 -> 39691.004 | F91: =F81+F82+F83+F84+F86+F88 -> 39491.38 | G91: =G81+G82+G83+G84+G86+G88 -> 38749.147 | H91: =H81+H82+H83+H84+H86+H88 -> 34154.005 | I91: =I81+I82+I83+I84+I86+I88 -> 42026.043 | ... AE91: =AE81+AE82+AE83+AE84+AE86+AE88 -> 19372.656
A92: Total Spend | B92: =SUM(B81:B90) -> 40883.48 | C92: =SUM(C81:C90) -> 37944.856 | D92: =SUM(D81:D90) -> 41087.978 | E92: =SUM(E81:E90) -> 48841.244 | F92: =SUM(F81:F90) -> 47025.342 | G92: =SUM(G81:G90) -> 52131.684 | H92: =SUM(H81:H90) -> 39444.771 | I92: =SUM(I81:I90) -> 44845.238 | ... AE92: =SUM(AE81:AE90) -> 19984.905
A94: App Spend | Y94: 64591.16 | AA94: 4.05
A95: Meta Spend | B95: 0 | C95: 0 | D95: 0 | E95: 0 | F95: 0 | G95: 0 | H95: 0 | I95: 0 | J95: 0 | K95: 0 | L95: 0 | M95: 0 | N95: 0 | O95: 0 | P95: 0 | Q95: 0 | R95: 0 | S95: 0 | T95: 0 | U95: 0 | V95: 0 | W95: 0 | X95: 0 | Y95: 0 | Z95: =IFERROR(__xludf.DUMMYFUNCTION("GOOGLEFINANCE(""CURRENCY:EURUSD"")*Z94"),0.0) -> 0 | AA95: =IFERROR(__xludf.DUMMYFUNCTION("GOOGLEFINANCE(""CURRENCY:EURUSD"")*AA94"),4.64350725) -> 4.6435072 | AB95: 0 | AC95: 0 | AD95: 0 | AE95: 0
A96: Apple Spend | B96: 20.37 | C96: 12.66 | D96: 20.86 | E96: 20.81 | F96: 46.99 | G96: 26.18 | H96: 21.19 | I96: 17.85 | J96: 20.89 | K96: 39.74 | L96: 39.82 | M96: 42.55 | N96: 30.45 | O96: 15.83 | P96: 18.87 | Q96: 14.94 | R96: 12.41 | S96: 16.43 | T96: 18.21 | U96: 18.92 | V96: 20.58 | W96: 14.6 | X96: 14.29 | Y96: 21.29 | Z96: 26.01 | AA96: 18.16 | AB96: 1.8 | AC96: 1.6 | AD96: 10.38 | AE96: 13.09
A97: Google Spend
A98: Total APP Spend | B98: =SUM(B95:B97) -> 20.37 | C98: =SUM(C95:C97) -> 12.66 | D98: =SUM(D95:D97) -> 20.86 | E98: =SUM(E95:E97) -> 20.81 | F98: =SUM(F95:F97) -> 46.99 | G98: =SUM(G95:G97) -> 26.18 | H98: =SUM(H95:H97) -> 21.19 | I98: =SUM(I95:I97) -> 17.85 | ... AE98: =SUM(AE95:AE97) -> 13.09
A100: Blended ROAS | B100: =B35/B92 -> 2.8450296 | C100: =C35/C92 -> 3.3413491 | D100: =D35/D92 -> 3.1586507 | E100: =E35/E92 -> 3.2726085 | F100: =F35/F92 -> 3.6413037 | G100: =G35/G92 -> 3.7370192 | H100: =H35/H92 -> 3.5287255 | I100: =I35/I92 -> 3.1393803 | ... AE100: =AE35/AE92 -> 4.8669196
A101: wROAS | B101: =B8/B91 -> 2.7996757 | C101: =C8/C91 -> 3.290351 | D101: =D8/D91 -> 2.9731819 | E101: =E8/E91 -> 3.074768 | F101: =F8/F91 -> 3.4915435 | G101: =G8/G91 -> 3.3601266 | H101: =H8/H91 -> 3.5019044 | I101: =I8/I91 -> 2.9354922 | ... AE101: =AE8/AE91 -> 4.8965553
A102: aROAS | B102: =B15/B85 -> 3.0919931 | C102: =C15/C85 -> 3.2595184 | D102: =D15/D85 -> 4.9922114 | E102: =E15/E85 -> 3.1386937 | F102: =F15/F85 -> 3.6343024 | G102: =G15/G85 -> 3.8193464 | H102: =H15/H85 -> 3.1316237 | I102: =I15/I85 -> 5.1687564 | ... AE102: =AE15/AE85 -> 1.2446421
A103: appROAS | B103: =B51/B98 -> 28.793198 | C103: =C51/C98 -> 77.403211 | D103: =D51/D98 -> 38.872696 | E103: =E51/E98 -> 102.25423 | F103: =F51/F98 -> 39.532828 | G103: =G51/G98 -> 43.405246 | H103: =H51/H98 -> 45.681288 | I103: =I51/I98 -> 74.340648 | ... AE103: =AE51/AE98 -> 130.44861
A105: Blended Spend per Unit | B105: =B92/SUM('DTC - P&L'!B57,'AMAZON - P&L'!B32,'Digital Marketplaces'!B17,'Digital Marketplaces'!B129,B66) -> 84.295834 | C105: =C92/SUM('DTC - P&L'!C57,'AMAZON - P&L'!C32,'Digital Marketplaces'!C17,'Digital Marketplaces'!C129,C66) -> 75.43709 | D105: =D92/SUM('DTC - P&L'!D57,'AMAZON - P&L'!D32,'Digital Marketplaces'!D17,'Digital Marketplaces'!D129,D66) -> 78.114027 | E105: =E92/SUM('DTC - P&L'!E57,'AMAZON - P&L'!E32,'Digital Marketplaces'!E17,'Digital Marketplaces'!E129,E66) -> 76.673853 | F105: =F92/SUM('DTC - P&L'!F57,'AMAZON - P&L'!F32,'Digital Marketplaces'!F17,'Digital Marketplaces'!F129,F66) -> 67.275167 | G105: =G92/SUM('DTC - P&L'!G57,'AMAZON - P&L'!G32,'Digital Marketplaces'!G17,'Digital Marketplaces'!G129,G66) -> 68.324618 | H105: =H92/SUM('DTC - P&L'!H57,'AMAZON - P&L'!H32,'Digital Marketplaces'!H17,'Digital Marketplaces'!H129,H66) -> 68.839041 | I105: =I92/SUM('DTC - P&L'!I57,'AMAZON - P&L'!I32,'Digital Marketplaces'!I17,'Digital Marketplaces'!I129,I66) -> 78.675856 | ... AE105: =AE92/SUM('DTC - P&L'!AE57,'AMAZON - P&L'!AE32,'Digital Marketplaces'!AE17,'Digital Marketplaces'!AE129,AE66) -> 69.877288
A106: wSPU | B106: =B91/'DTC - P&L'!B57 -> 84.511272 | C106: =C91/'DTC - P&L'!C57 -> 75.027314 | D106: =D91/'DTC - P&L'!D57 -> 81.10126 | E106: =E91/'DTC - P&L'!E57 -> 77.825498 | F106: =F91/'DTC - P&L'!F57 -> 66.934542 | G106: =G91/'DTC - P&L'!G57 -> 69.944309 | H106: =H91/'DTC - P&L'!H57 -> 67.631692 | I106: =I91/'DTC - P&L'!I57 -> 83.385006 | ... AE106: =AE91/'DTC - P&L'!AE57 -> 69.436042
A107: aSPU | B107: =B85/'AMAZON - P&L'!B32 -> 87.397838 | C107: =C85/'AMAZON - P&L'!C32 -> 86.681351 | D107: =D85/'AMAZON - P&L'!D32 -> 56.380526 | E107: =E85/'AMAZON - P&L'!E32 -> 89.021111 | F107: =F85/'AMAZON - P&L'!F32 -> 78.952647 | G107: =G85/'AMAZON - P&L'!G32 -> 72.188364 | H107: =H85/'AMAZON - P&L'!H32 -> 86.498261 | I107: =I85/'AMAZON - P&L'!I32 -> 47.728448 | ... AE107: =AE85/'AMAZON - P&L'!AE32 -> 216.97
A108: appCAC | B108: =B98/B78 -> 0.679 | C108: =C98/C78 -> 0.30142857 | D108: =D98/D78 -> 0.5215 | E108: =E98/E78 -> 0.23382022 | F108: =F98/F78 -> 0.58012346 | G108: =G98/G78 -> 0.45929825 | H108: =H98/H78 -> 0.39240741 | I108: =I98/I78 -> 0.25869565 | ... AE108: =AE98/AE78 -> 0.15771084
A110: Web CR | B110: 0.0303 | C110: 0.0343 | D110: 0.0304 | E110: 0.0303 | F110: 0.0272 | G110: 0.0252 | H110: 0.0263 | I110: 0.0217 | J110: 0.0228 | K110: 0.0241 | L110: 0.0336 | M110: 0.0359 | N110: 0.05 | O110: 0.0299 | P110: 0.0303 | Q110: 0.0285 | R110: 0.0347 | S110: 0.0363 | T110: 0.0338 | U110: 0.0356 | V110: 0.033 | W110: 0.0369 | X110: 0.0316 | Y110: 0.052 | Z110: 0.0648 | AA110: 0.0392 | AB110: 0.0514 | AC110: 0.0433 | AD110: 0.0132 | AE110: 0.0191
A111: Web AOV | B111: =B8/B54 -> 230.8966 | C111: =C8/C54 -> 210.88386 | D111: =D8/D54 -> 215.72251 | E111: =E8/E54 -> 225.16721 | F111: =F8/F54 -> 224.56982 | G111: =G8/G54 -> 221.43204 | H111: =H8/H54 -> 227.38414 | I111: =I8/I54 -> 229.30691 | ... AE111: =AE8/AE54 -> 296.43525
...

Sheet DTC - P&L
A1: November | B1: 45231 | C1: 45232 | D1: 45233 | E1: 45234 | F1: 45235 | G1: 45236 | H1: 45237 | I1: 45238 | J1: 45239 | K1: 45240 | L1: 45241 | M1: 45242 | N1: 45243 | O1: 45244 | P1: 45245 | Q1: 45246 | R1: 45247 | S1: 45248 | T1: 45249 | U1: 45250 | V1: 45251 | W1: 45252 | X1: 45253 | Y1: 45254 | Z1: 45255 | AA1: 45256 | AB1: 45257 | AC1: 45258 | AD1: 45259 | AE1: 45260
A2: DAY | B2: WED | C2: THU | D2: FRI | E2: SAT | F2: SUN | G2: MON | H2: TUE | I2: WED | J2: THU | K2: FRI | L2: SAT | M2: SUN | N2: MON | O2: TUE | P2: WED | Q2: THU | R2: FRI | S2: SAT | T2: SUN | U2: MON | V2: TUE | W2: WED | X2: THU | Y2: FRI | Z2: SAT | AA2: SUN | AB2: MON | AC2: TUE | AD2: WED | AE2: THU
A3: COMMENT
A4: Orders
A5: Meta | B5: 305 | C5: 329 | D5: 325 | E5: 321 | F5: 377 | G5: 353 | H5: 314 | I5: 292 | J5: 329 | K5: 340 | L5: 315 | M5: 344 | N5: 250 | O5: 324 | P5: 313 | Q5: 316 | R5: 314 | S5: 407 | T5: 403 | U5: 472 | V5: 447 | W5: 591 | X5: 825 | Y5: 2373 | Z5: 1476 | AA5: 1134 | AB5: 1693 | AC5: 1202 | AD5: 190 | AE5: 116 | AF5: =SUM(B5:AE5) -> 16790
A6: Google | B6: 129.23 | C6: 136.54 | D6: 142.32 | E6: 169.04 | F6: 192.21 | G6: 213.75 | H6: 212.27 | I6: 193.51 | J6: 199.67 | K6: 227.59 | L6: 228.33 | M6: 229.89 | N6: 226.72 | O6: 237.61 | P6: 222.03 | Q6: 228.18 | R6: 260.86 | S6: 289.41 | T6: 366.37 | U6: 364.71 | V6: 362.56 | W6: 339.91 | X6: 579.91 | Y6: 1249 | Z6: 914 | AA6: 686.99 | AB6: 1015 | AC6: 747 | AD6: 137.75 | AE6: 133.61 | AF6: =SUM(B6:AE6) -> 10635.97
A7: TikTok | B7: 0 | C7: 0 | D7: 0 | E7: 0 | F7: 0 | G7: 0 | H7: 0 | I7: 0 | J7: 0 | K7: 0 | L7: 0 | M7: 0 | N7: 0 | O7: 0 | P7: 0 | Q7: 2 | R7: 0 | S7: 0 | T7: 0 | U7: 0 | V7: 0 | W7: 0 | X7: 0 | Y7: 0 | Z7: 0 | AA7: 0 | AB7: 0 | AC7: 0 | AD7: 0 | AE7: 0 | AF7: =SUM(B7:AE7) -> 2
A8: Bing | B8: 24 | C8: 30 | D8: 24 | E8: 22 | F8: 20 | G8: 34 | H8: 26 | I8: 38 | J8: 20 | K8: 24 | L8: 40 | M8: 44 | N8: 26 | O8: 44 | P8: 28 | Q8: 30 | R8: 36 | S8: 22 | T8: 44 | U8: 34 | V8: 40 | W8: 46 | X8: 48 | Y8: 74 | Z8: 42 | AA8: 36 | AB8: 50 | AC8: 100 | AD8: 16 | AE8: 16 | AF8: =SUM(B8:AE8) -> 1078
A9: Nextdoor | B9: 0 | C9: 0 | D9: 0 | E9: 0 | F9: 0 | G9: 0 | H9: 0 | I9: 0 | J9: 0 | K9: 0 | L9: 0 | M9: 0 | N9: 0 | O9: 0 | P9: 0 | Q9: 0 | R9: 0 | S9: 1 | T9: 1 | U9: 1 | V9: 1 | W9: 0 | X9: 0 | Y9: 0 | Z9: 0 | AA9: 1 | AB9: 4 | AC9: 0 | AD9: 0 | AE9: 0 | AF9: =SUM(B9:AE9) -> 9
A10: Affiliates (Refersion) | B10: 3 | C10: 1 | D10: 0 | E10: 2 | F10: 3 | G10: 1 | H10: 1 | I10: 0 | J10: 0 | K10: 2 | L10: 0 | M10: 5 | N10: 2 | O10: 2 | P10: 2 | Q10: 0 | R10: 2 | S10: 0 | T10: 0 | U10: 0 | V10: 1 | W10: 2 | X10: 4 | Y10: 3 | Z10: 3 | AA10: 2 | AB10: 9 | AC10: 8 | AD10: 1 | AE10: 1 | AF10: =SUM(B10:AE10) -> 60
A11: Email | B11: 5 | C11: 57 | D11: 23 | E11: 6 | F11: 7 | G11: 5 | H11: 11 | I11: 11 | J11: 23 | K11: 14 | L11: 5 | M11: 9 | N11: 8 | O11: 19 | P11: 18 | Q11: 19 | R11: 8 | S11: 7 | T11: 7 | U11: 4 | V11: 2 | W11: 191 | X11: 122 | Y11: 169 | Z11: 71 | AA11: 38 | AB11: 50 | AC11: 23 | AD11: 4 | AE11: 5 | AF11: =SUM(B11:AE11) -> 941
A12: All | B12: =SUM(B5:B11) -> 466.23 | C12: =SUM(C5:C11) -> 553.54 | D12: =SUM(D5:D11) -> 514.32 | E12: =SUM(E5:E11) -> 520.04 | F12: =SUM(F5:F11) -> 599.21 | G12: =SUM(G5:G11) -> 606.75 | H12: =SUM(H5:H11) -> 564.27 | I12: =SUM(I5:I11) -> 534.51 | ... AE12: =SUM(AE5:AE11) -> 271.61 | AF12: =SUM(B12:AE12) -> 29515.97
A14: Revenue | B14: 68732.42 | C14: 72150.16 | D14: 67654.24 | E14: 69524.68 | F14: 81040.74 | G14: 75727.42 | H14: 68450.74 | I14: 64261.29 | J14: 73757.33 | K14: 75181.43 | L14: 70884.65 | M14: 75544.9 | N14: 56206.3 | O14: 72316.09 | P14: 68561.95 | Q14: 68209.11 | R14: 67866.49 | S14: 89177.45 | T14: 89930.01 | U14: 106844.96 | V14: 99421.9 | W14: 130742.44 | X14: 183129.98 | Y14: 523574.65 | Z14: 320375.62 | AA14: 248293.09 | AB14: 373074.03 | AC14: 269078.11 | AD14: 52640.01 | AE14: 31699.42
A15: Meta | B15: =B14*Summary!B80 -> 72753.267 | C15: =C14*Summary!C80 -> 76594.61 | D15: =D14*Summary!D80 -> 72633.592 | E15: =E14*Summary!E80 -> 74641.696 | F15: =F14*Summary!F80 -> 86972.922 | G15: =G14*Summary!G80 -> 81172.221 | H15: =H14*Summary!H80 -> 73221.757 | I15: =I14*Summary!I80 -> 68823.842 | ... AE15: =AE14*Summary!AE80 -> 34536.518 | AF15: =SUM(B15:AE15) -> 4039600.1
A16: Google | B16: 30567.62 | C16: 32350.72 | D16: 33008.87 | E16: 39166.38 | F16: 42455.97 | G16: 48146.77 | H16: 49995.64 | I16: 46378.54 | J16: 46596.26 | K16: 50876.02 | L16: 55535.62 | M16: 54435.13 | N16: 50517.39 | O16: 55244.61 | P16: 51370.39 | Q16: 54607.17 | R16: 61927.38 | S16: 68490.91 | T16: 88024.45 | U16: 86295.03 | V16: 87700.65 | W16: 78603.95 | X16: 139593.46 | Y16: 299835.52 | Z16: 212440.76 | AA16: 164154.9 | AB16: 249887.71 | AC16: 185591.19 | AD16: 40320.29 | AE16: 40781.03 | AF16: =SUM(B16:AE16) -> 2544900.3
A17: TikTok | B17: 0 | C17: 0 | D17: 0 | E17: 0 | F17: 0 | G17: 0 | H17: 0 | I17: 0 | J17: 0 | K17: 0 | L17: 0 | M17: 0 | N17: 0 | O17: 0 | P17: 0 | Q17: 244 | R17: 0 | S17: 0 | T17: 0 | U17: 0 | V17: 0 | W17: 0 | X17: 0 | Y17: 0 | Z17: 0 | AA17: 0 | AB17: 0 | AC17: 0 | AD17: 0 | AE17: 0 | AF17: =SUM(B17:AE17) -> 244
A18: Bing | B18: 3012 | C18: 3765 | D18: 3012 | E18: 2761 | F18: 2510 | G18: 4267 | H18: 3263 | I18: 4769 | J18: 2510 | K18: 3012 | L18: 5020 | M18: 5522 | N18: 3263 | O18: 5522 | P18: 3514 | Q18: 3765 | R18: 4518 | S18: 2761 | T18: 5522 | U18: 4267 | V18: 5020 | W18: 5773 | X18: 6024 | Y18: 9287 | Z18: 5271 | AA18: 4518 | AB18: 6275 | AC18: 12550 | AD18: 2008 | AE18: 2008 | AF18: =SUM(B18:AE18) -> 135289
A19: Nextdoor | B19: 0 | C19: 0 | D19: 0 | E19: 0 | F19: 0 | G19: 0 | H19: 0 | I19: 0 | J19: 0 | K19: 0 | L19: 0 | M19: 0 | N19: 0 | O19: 0 | P19: 0 | Q19: 0 | R19: 0 | S19: 324 | T19: 184 | U19: 261.98 | V19: 202.59 | W19: 0 | X19: 0 | Y19: 0 | Z19: 0 | AA19: 468.73 | AB19: 1161.06 | AC19: 0 | AD19: 0 | AE19: 0 | AF19: =SUM(B19:AE19) -> 2602.36
A20: Affiliates (Refersion) | B20: 813.55 | C20: 244 | D20: 0 | E20: 578.65 | F20: 606.54 | G20: 315.46 | H20: 433 | I20: 0 | J20: 0 | K20: 445.76 | L20: 0 | M20: 1624.44 | N20: 438.73 | O20: 503.23 | P20: 276.37 | Q20: 0 | R20: 526.56 | S20: 0 | T20: 0 | U20: 0 | V20: 161.91 | W20: 476 | X20: 1214.94 | Y20: 472.95 | Z20: 615.78 | AA20: 469.78 | AB20: 2370.19 | AC20: 1830.85 | AD20: 343 | AE20: 68 | AF20: =SUM(B20:AE20) -> 14829.69
A21: Email | B21: 559.03 | C21: 3667.35 | D21: 1510.38 | E21: 559.68 | F21: 337.61 | G21: 590.49 | H21: 1434.31 | I21: 2811.6 | J21: 3069.32 | K21: 1285.84 | L21: 1164.2 | M21: 1089.11 | N21: 1259.65 | O21: 2842.65 | P21: 1750.29 | Q21: 1606.27 | R21: 312.69 | S21: 531.27 | T21: 1296.07 | U21: 368.47 | V21: 347.32 | W21: 43912.02 | X21: 28303.35 | Y21: 40391.88 | Z21: 15727.28 | AA21: 8244.38 | AB21: 9907.34 | AC21: 4302.47 | AD21: 793.51 | AE21: 284.09 | AF21: =SUM(B21:AE21) -> 180259.92
A22: All | B22: =SUM(B15:B21) -> 107705.47 | C22: =SUM(C15:C21) -> 116621.68 | D22: =SUM(D15:D21) -> 110164.84 | E22: =SUM(E15:E21) -> 117707.41 | F22: =SUM(F15:F21) -> 132883.04 | G22: =SUM(G15:G21) -> 134491.94 | H22: =SUM(H15:H21) -> 128347.71 | I22: =SUM(I15:I21) -> 122782.98 | ... AE22: =SUM(AE15:AE21) -> 77677.638 | AF22: =SUM(B22:AE22) -> 6917725.4
A24: Media Cost
A25: Meta | B25: =Summary!B81 -> 32434.536 | C25: =Summary!C81 -> 29070.716 | D25: =Summary!D81 -> 31545.288 | E25: =Summary!E81 -> 28085.666 | F25: =Summary!F81 -> 28087.694 | G25: =Summary!G81 -> 29676.677 | H25: =Summary!H81 -> 25760.505 | I25: =Summary!I81 -> 32668.713 | ... AE25: =Summary!AE81 -> 13572.196 | AF25: =SUM(B25:AE25) -> 1476268
A26: Google | B26: =Summary!B82 -> 4770.48 | C26: =Summary!C82 -> 5351.07 | D26: =Summary!D82 -> 6050.06 | E26: =Summary!E82 -> 7040.29 | F26: =Summary!F82 -> 8856.02 | G26: =Summary!G82 -> 8610.7 | H26: =Summary!H82 -> 7930.14 | I26: =Summary!I82 -> 8941.43 | ... AE26: =Summary!AE82 -> 5438.57 | AF26: =SUM(B26:AE26) -> 310638.05
A27: TikTok | B27: =Summary!B84 -> 0 | C27: =Summary!C84 -> 0 | D27: =Summary!D84 -> 0 | E27: =Summary!E84 -> 0 | F27: =Summary!F84 -> 0 | G27: =Summary!G84 -> 0 | H27: =Summary!H84 -> 0 | I27: =Summary!I84 -> 0 | ... AE27: =Summary!AE84 -> 0 | AF27: =SUM(B27:AE27) -> 748.65
A28: Bing | B28: =Summary!B83 -> 239.79 | C28: =Summary!C83 -> 254.86 | D28: =Summary!D83 -> 278.94 | E28: =Summary!E83 -> 309.46 | F28: =Summary!F83 -> 254.73 | G28: =Summary!G83 -> 398.68 | H28: =Summary!H83 -> 376.76 | I28: =Summary!I83 -> 415.9 | ... AE28: =Summary!AE83 -> 348.29 | AF28: =SUM(B28:AE28) -> 12497.09
A29: Nextdoor | B29: =Summary!B86 -> 0 | C29: =Summary!C86 -> 0 | D29: =Summary!D86 -> 0 | E29: =Summary!E86 -> 0 | F29: =Summary!F86 -> 0 | G29: =Summary!G86 -> 0 | H29: =Summary!H86 -> 0 | I29: =Summary!I86 -> 0 | ... AE29: =Summary!AE86 -> 0 | AF29: =SUM(B29:AE29) -> 4003.63
A30: Affiliate Fee (20%) | B30: =Summary!B88 -> 162.71 | C30: =Summary!C88 -> 61 | D30: =Summary!D88 -> 0 | E30: =Summary!E88 -> 4255.588 | F30: =Summary!F88 -> 2292.936 | G30: =Summary!G88 -> 63.09 | H30: =Summary!H88 -> 86.6 | I30: =Summary!I88 -> 0 | ... AE30: =Summary!AE88 -> 13.6 | AF30: =SUM(B30:AE30) -> 9391.734
A31: All | B31: =SUM(B25:B30) -> 37607.516 | C31: =SUM(C25:C30) -> 34737.646 | D31: =SUM(D25:D30) -> 37874.288 | E31: =SUM(E25:E30) -> 39691.004 | F31: =SUM(F25:F30) -> 39491.38 | G31: =SUM(G25:G30) -> 38749.147 | H31: =SUM(H25:H30) -> 34154.005 | I31: =SUM(I25:I30) -> 42026.043 | ... AE31: =SUM(AE25:AE30) -> 19372.656 | AF31: =SUM(B31:AE31) -> 1813547.2
A36: Revenue
A37: Revenue Woocommerce (Platform) | B37: =Summary!B8 -> 105288.85 | C37: =Summary!C8 -> 114299.05 | D37: =Summary!D8 -> 112607.15 | E37: =Summary!E8 -> 122040.63 | F37: =Summary!F8 -> 137885.87 | G37: =Summary!G8 -> 130202.04 | H37: =Summary!H8 -> 119604.06 | I37: =Summary!I8 -> 123367.12 | ... AE37: =Summary!AE8 -> 94859.28 | AF37: =sum(B37:AE37) -> 7000698.1
A38: SUM | B38: =SUM(B37) -> 105288.85 | C38: =SUM(C37) -> 114299.05 | D38: =SUM(D37) -> 112607.15 | E38: =SUM(E37) -> 122040.63 | F38: =SUM(F37) -> 137885.87 | G38: =SUM(G37) -> 130202.04 | H38: =SUM(H37) -> 119604.06 | I38: =SUM(I37) -> 123367.12 | ... AE38: =SUM(AE37) -> 94859.28 | AF38: =sum(B38:AE38) -> 7000698.1
A40: Orders
A41: Orders Woocommerce (Platform) | B41: =Summary!B54 -> 456 | C41: =Summary!C54 -> 542 | D41: =Summary!D54 -> 522 | E41: =Summary!E54 -> 542 | F41: =Summary!F54 -> 614 | G41: =Summary!G54 -> 588 | H41: =Summary!H54 -> 526 | I41: =Summary!I54 -> 538 | ... AE41: =Summary!AE54 -> 320 | AF41: =sum(B41:AE41) -> 30028
A42: SUM | B42: =SUM(B41) -> 456 | C42: =SUM(C41) -> 542 | D42: =SUM(D41) -> 522 | E42: =SUM(E41) -> 542 | F42: =SUM(F41) -> 614 | G42: =SUM(G41) -> 588 | H42: =SUM(H41) -> 526 | I42: =SUM(I41) -> 538 | ... AE42: =SUM(AE41) -> 320 | AF42: =sum(B42:AE42) -> 30028
A44: Breakdown
A45: - Hardware | B45: =Summary!B9 -> 85464.76 | C45: =Summary!C9 -> 88820.66 | D45: =Summary!D9 -> 90446.48 | E45: =Summary!E9 -> 97964.77 | F45: =Summary!F9 -> 112993.92 | G45: =Summary!G9 -> 106383.84 | H45: =Summary!H9 -> 97516.45 | I45: =Summary!I9 -> 97998.57 | ... AE45: =Summary!AE9 -> 76648.21 | AF45: =SUM(B45:AE45) -> 5630024
A46: - Add-ons | B46: =Summary!B10 -> 6707.54 | C46: =Summary!C10 -> 10578.54 | D46: =Summary!D10 -> 9279.32 | E46: =Summary!E10 -> 10715.53 | F46: =Summary!F10 -> 9847.38 | G46: =Summary!G10 -> 9498.36 | H46: =Summary!H10 -> 9096.2 | I46: =Summary!I10 -> 10900.63 | ... AE46: =Summary!AE10 -> 7659.93 | AF46: =SUM(B46:AE46) -> 497728.7
A47: - Merch | B47: =Summary!B11 -> 0 | C47: =Summary!C11 -> 0 | D47: =Summary!D11 -> 0 | E47: =Summary!E11 -> 0 | F47: =Summary!F11 -> 0 | G47: =Summary!G11 -> 0 | H47: =Summary!H11 -> 0 | I47: =Summary!I11 -> 0 | ... AE47: =Summary!AE11 -> 114 | AF47: =SUM(B47:AE47) -> 9599.38
A48: - Taxes | B48: =Summary!B13 -> 5816.55 | C48: =Summary!C13 -> 6484.85 | D48: =Summary!D13 -> 6121.35 | E48: =Summary!E13 -> 7055.33 | F48: =Summary!F13 -> 7974.57 | G48: =Summary!G13 -> 7404.84 | H48: =Summary!H13 -> 6681.41 | I48: =Summary!I13 -> 6882.92 | ... AE48: =Summary!AE13 -> 5427.14 | AF48: =SUM(B48:AE48) -> 386582.99
A49: - Shipping | B49: =Summary!B14 -> 7300 | C49: =Summary!C14 -> 8415 | D49: =Summary!D14 -> 6760 | E49: =Summary!E14 -> 6305 | F49: =Summary!F14 -> 7070 | G49: =Summary!G14 -> 6915 | H49: =Summary!H14 -> 6310 | I49: =Summary!I14 -> 7585 | ... AE49: =Summary!AE14 -> 5010 | AF49: =SUM(B49:AE49) -> 476763
A50: SUM | B50: =SUM(B45:B49) -> 105288.85 | C50: =SUM(C45:C49) -> 114299.05 | D50: =SUM(D45:D49) -> 112607.15 | E50: =SUM(E45:E49) -> 122040.63 | F50: =SUM(F45:F49) -> 137885.87 | G50: =SUM(G45:G49) -> 130202.04 | H50: =SUM(H45:H49) -> 119604.06 | I50: =SUM(I45:I49) -> 123367.12 | ... AE50: =SUM(AE45:AE49) -> 94859.28 | AF50: =SUM(B50:AE50) -> 7000698.1
A52: Units Sold (Gross)
A53: SKU 1 - Blue | B53: 148 | C53: 151 | D53: 153 | E53: 184 | F53: 216 | G53: 183 | H53: 159 | I53: 147 | J53: 172 | K53: 178 | L53: 160 | M53: 175 | N53: 154 | O53: 152 | P53: 155 | Q53: 142 | R53: 179 | S53: 210 | T53: 206 | U53: 211 | V53: 256 | W53: 358 | X53: 400 | Y53: 1235 | Z53: 833 | AA53: 572 | AB53: 792 | AC53: 595 | AD53: 37 | AE53: 49 | AF53: =sum(B53:AE53) -> 8562
A54: SKU 2 - Yellow | B54: 6 | C54: 11 | D54: 4 | E54: 8 | F54: 8 | G54: 11 | H54: 11 | I54: 6 | J54: 8 | K54: 11 | L54: 9 | M54: 17 | N54: 10 | O54: 10 | P54: 7 | Q54: 9 | R54: 17 | S54: 21 | T54: 20 | U54: 26 | V54: 28 | W54: 61 | X54: 57 | Y54: 176 | Z54: 111 | AA54: 73 | AB54: 95 | AC54: 108 | AD54: 46 | AE54: 43 | AF54: =sum(B54:AE54) -> 1028
A55: SKU 3 - Blue w/ Solar | B55: 266 | C55: 276 | D55: 277 | E55: 291 | F55: 333 | G55: 335 | H55: 312 | I55: 318 | J55: 337 | K55: 324 | L55: 489 | M55: 444 | N55: 349 | O55: 415 | P55: 370 | Q55: 356 | R55: 352 | S55: 462 | T55: 492 | U55: 508 | V55: 476 | W55: 696 | X55: 842 | Y55: 2274 | Z55: 1350 | AA55: 1042 | AB55: 1760 | AC55: 1062 | AD55: 112 | AE55: 97 | AF55: =sum(B55:AE55) -> 17017
A56: SKU 4 - Yellow w/ Solar | B56: 25 | C56: 25 | D56: 33 | E56: 27 | F56: 33 | G56: 25 | H56: 23 | I56: 33 | J56: 29 | K56: 24 | L56: 29 | M56: 34 | N56: 26 | O56: 35 | P56: 34 | Q56: 15 | R56: 20 | S56: 28 | T56: 47 | U56: 54 | V56: 72 | W56: 98 | X56: 138 | Y56: 301 | Z56: 216 | AA56: 159 | AB56: 210 | AC56: 202 | AD56: 115 | AE56: 90 | AF56: =sum(B56:AE56) -> 2200
A57: SUM (SKU 1 - SKU 4) | B57: =SUM(B53:B56) -> 445 | C57: =SUM(C53:C56) -> 463 | D57: =SUM(D53:D56) -> 467 | E57: =SUM(E53:E56) -> 510 | F57: =SUM(F53:F56) -> 590 | G57: =SUM(G53:G56) -> 554 | H57: =SUM(H53:H56) -> 505 | I57: =SUM(I53:I56) -> 504 | ... AE57: =SUM(AE53:AE56) -> 279 | AF57: =sum(B57:AE57) -> 28807
A59: Wall Mount | B59: 75 | C59: 104 | D59: 92 | E59: 116 | F59: 131 | G59: 134 | H59: 127 | I59: 121 | J59: 141 | K59: 144 | L59: 209 | M59: 207 | N59: 136 | O59: 157 | P59: 146 | Q59: 137 | R59: 136 | S59: 164 | T59: 158 | U59: 199 | V59: 186 | W59: 284 | X59: 358 | Y59: 796 | Z59: 486 | AA59: 405 | AB59: 570 | AC59: 366 | AD59: 86 | AE59: 81 | AF59: =sum(B59:AE59) -> 6452
A60: Suet Ball Holder | B60: 351 | C60: 369 | D60: 393 | E60: 386 | F60: 415 | G60: 373 | H60: 383 | I60: 369 | J60: 410 | K60: 404 | L60: 521 | M60: 572 | N60: 813 | O60: 453 | P60: 394 | Q60: 374 | R60: 395 | S60: 514 | T60: 313 | U60: 495 | V60: 555 | W60: 849 | X60: 1077 | Y60: 2749 | Z60: 1636 | AA60: 1284 | AB60: 1796 | AC60: 1039 | AD60: 0 | AE60: 0 | AF60: =sum(B60:AE60) -> 19682
A61: 3-in-1 Nutrition Set - Blue | B61: 39 | C61: 93 | D61: 75 | E61: 74 | F61: 43 | G61: 56 | H61: 60 | I61: 92 | J61: 59 | K61: 49 | L61: 93 | M61: 85 | N61: 52 | O61: 64 | P61: 59 | Q61: 63 | R61: 61 | S61: 64 | T61: 86 | U61: 85 | V61: 81 | W61: 104 | X61: 143 | Y61: 371 | Z61: 168 | AA61: 160 | AB61: 223 | AC61: 113 | AD61: 25 | AE61: 24 | AF61: =sum(B61:AE61) -> 2764
A62: 3-in-1 Nutrition Set - Yellow | B62: 5 | C62: 19 | D62: 9 | E62: 9 | F62: 4 | G62: 5 | H62: 5 | I62: 14 | J62: 8 | K62: 4 | L62: 3 | M62: 7 | N62: 8 | O62: 9 | P62: 2 | Q62: 4 | R62: 2 | S62: 7 | T62: 7 | U62: 11 | V62: 10 | W62: 20 | X62: 29 | Y62: 50 | Z62: 30 | AA62: 28 | AB62: 28 | AC62: 26 | AD62: 19 | AE62: 25 | AF62: =sum(B62:AE62) -> 407
A63: Solar Roof Single - Blue | B63: 12 | C63: 12 | D63: 14 | E63: 14 | F63: 20 | G63: 11 | H63: 9 | I63: 13 | J63: 12 | K63: 13 | L63: 10 | M63: 6 | N63: 14 | O63: 10 | P63: 12 | Q63: 9 | R63: 8 | S63: 14 | T63: 8 | U63: 15 | V63: 17 | W63: 34 | X63: 34 | Y63: 96 | Z63: 43 | AA63: 46 | AB63: 41 | AC63: 27 | AD63: 8 | AE63: 6 | AF63: =sum(B63:AE63) -> 588
A64: Solar Roof Single - Yellow | B64: 4 | C64: 2 | D64: 2 | E64: 3 | F64: 1 | G64: 4 | H64: 2 | I64: 0 | J64: 1 | K64: 3 | L64: 0 | M64: 0 | N64: 0 | O64: 1 | P64: 1 | Q64: 6 | R64: 2 | S64: 0 | T64: 4 | U64: 3 | V64: 0 | W64: 8 | X64: 6 | Y64: 16 | Z64: 7 | AA64: 11 | AB64: 12 | AC64: 6 | AD64: 4 | AE64: 4 | AF64: =sum(B64:AE64) -> 113
A65: Perch Extender - Blue | B65: 88 | C65: 125 | D65: 110 | E65: 129 | F65: 136 | G65: 125 | H65: 114 | I65: 124 | J65: 115 | K65: 120 | L65: 170 | M65: 170 | N65: 126 | O65: 138 | P65: 124 | Q65: 124 | R65: 129 | S65: 165 | T65: 149 | U65: 158 | V65: 154 | W65: 247 | X65: 286 | Y65: 707 | Z65: 401 | AA65: 345 | AB65: 459 | AC65: 287 | AD65: 61 | AE65: 61 | AF65: =sum(B65:AE65) -> 5647
A66: Perch Extender - Yellow | B66: 14 | C66: 17 | D66: 13 | E66: 19 | F66: 19 | G66: 13 | H66: 10 | I66: 9 | J66: 15 | K66: 6 | L66: 14 | M66: 14 | N66: 15 | O66: 16 | P66: 14 | Q66: 7 | R66: 14 | S66: 12 | T66: 20 | U66: 23 | V66: 28 | W66: 58 | X66: 65 | Y66: 114 | Z66: 74 | AA66: 57 | AB66: 73 | AC66: 67 | AD66: 36 | AE66: 33 | AF66: =sum(B66:AE66) -> 889
A67: SUM (Add-ons) | B67: =SUM(B59:B66) -> 588 | C67: =SUM(C59:C66) -> 741 | D67: =SUM(D59:D66) -> 708 | E67: =SUM(E59:E66) -> 750 | F67: =SUM(F59:F66) -> 769 | G67: =SUM(G59:G66) -> 721 | H67: =SUM(H59:H66) -> 710 | I67: =SUM(I59:I66) -> 742 | ... AE67: =SUM(AE59:AE66) -> 234 | AF67: =sum(B67:AE67) -> 36542
A69: Merch Units Sold (Gross)
A70: Merch Units | B70: 0 | C70: 0 | D70: 0 | E70: 0 | F70: 0 | G70: 0 | H70: 0 | I70: 0 | J70: 20 | K70: 13 | L70: 12 | M70: 5 | N70: 0 | O70: 25 | P70: 24 | Q70: 29 | R70: 22 | S70: 10 | T70: 7 | U70: 6 | V70: 10 | W70: 14 | X70: 17 | Y70: 50 | Z70: 31 | AA70: 15 | AB70: 39 | AC70: 41 | AD70: 8 | AE70: 6 | AF70: =sum(B70:AE70) -> 404
A72: First-time Customers
A73: SKU 1 - Blue | B73: =B53-B90 -> 146 | C73: =C53-C90 -> 147 | D73: =D53-D90 -> 150 | E73: =E53-E90 -> 179 | F73: =F53-F90 -> 214 | G73: =G53-G90 -> 181 | H73: =H53-H90 -> 153 | I73: =I53-I90 -> 142 | ... AE73: =AE53-AE90 -> 47 | AF73: =sum(B73:AE73) -> 8393
A74: SKU 2 - Yellow | B74: =B54-B91 -> 5 | C74: =C54-C91 -> 11 | D74: =D54-D91 -> 4 | E74: =E54-E91 -> 7 | F74: =F54-F91 -> 8 | G74: =G54-G91 -> 11 | H74: =H54-H91 -> 11 | I74: =I54-I91 -> 6 | ... AE74: =AE54-AE91 -> 42 | AF74: =sum(B74:AE74) -> 999
A75: SKU 3 - Blue w/ Solar | B75: =B55-B92 -> 264 | C75: =C55-C92 -> 271 | D75: =D55-D92 -> 267 | E75: =E55-E92 -> 286 | F75: =F55-F92 -> 329 | G75: =G55-G92 -> 332 | H75: =H55-H92 -> 306 | I75: =I55-I92 -> 307 | ... AE75: =AE55-AE92 -> 94 | AF75: =sum(B75:AE75) -> 16654
A76: SKU 4 - Yellow w/ Solar | B76: =B56-B93 -> 25 | C76: =C56-C93 -> 25 | D76: =D56-D93 -> 31 | E76: =E56-E93 -> 26 | F76: =F56-F93 -> 33 | G76: =G56-G93 -> 25 | H76: =H56-H93 -> 22 | I76: =I56-I93 -> 33 | ... AE76: =AE56-AE93 -> 88 | AF76: =sum(B76:AE76) -> 2129
A77: SUM (SKU 1 - SKU 4) | B77: =SUM(B73:B76) -> 440 | C77: =SUM(C73:C76) -> 454 | D77: =SUM(D73:D76) -> 452 | E77: =SUM(E73:E76) -> 498 | F77: =SUM(F73:F76) -> 584 | G77: =SUM(G73:G76) -> 549 | H77: =SUM(H73:H76) -> 492 | I77: =SUM(I73:I76) -> 488 | ... AE77: =SUM(AE73:AE76) -> 271 | AF77: =sum(B77:AE77) -> 28175
A79: Wall Mount | B79: =B59-B96 -> 74 | C79: =C59-C96 -> 102 | D79: =D59-D96 -> 88 | E79: =E59-E96 -> 115 | F79: =F59-F96 -> 130 | G79: =G59-G96 -> 132 | H79: =H59-H96 -> 127 | I79: =I59-I96 -> 119 | ... AE79: =AE59-AE96 -> 77 | AF79: =sum(B79:AE79) -> 6287
A80: Suet Ball Holder | B80: =B60-B97 -> 346 | C80: =C60-C97 -> 359 | D80: =D60-D97 -> 379 | E80: =E60-E97 -> 376 | F80: =F60-F97 -> 413 | G80: =G60-G97 -> 369 | H80: =H60-H97 -> 377 | I80: =I60-I97 -> 356 | ... AE80: =AE60-AE97 -> 0 | AF80: =sum(B80:AE80) -> 19193
A81: 3-in-1 Nutrition Set - Blue | B81: =B61-B98 -> 39 | C81: =C61-C98 -> 80 | D81: =D61-D98 -> 67 | E81: =E61-E98 -> 73 | F81: =F61-F98 -> 42 | G81: =G61-G98 -> 52 | H81: =H61-H98 -> 57 | I81: =I61-I98 -> 87 | ... AE81: =AE61-AE98 -> 23 | AF81: =sum(B81:AE81) -> 2637
A82: 3-in-1 Nutrition Set - Yellow | B82: =B62-B99 -> 5 | C82: =C62-C99 -> 16 | D82: =D62-D99 -> 8 | E82: =E62-E99 -> 9 | F82: =F62-F99 -> 3 | G82: =G62-G99 -> 5 | H82: =H62-H99 -> 5 | I82: =I62-I99 -> 12 | ... AE82: =AE62-AE99 -> 25 | AF82: =sum(B82:AE82) -> 385
A83: Solar Roof Single - Blue | B83: =B63-B100 -> 11 | C83: =C63-C100 -> 10 | D83: =D63-D100 -> 14 | E83: =E63-E100 -> 14 | F83: =F63-F100 -> 19 | G83: =G63-G100 -> 10 | H83: =H63-H100 -> 9 | I83: =I63-I100 -> 11 | ... AE83: =AE63-AE100 -> 5 | AF83: =sum(B83:AE83) -> 523
A84: Solar Roof Single - Yellow | B84: =B64-B101 -> 4 | C84: =C64-C101 -> 2 | D84: =D64-D101 -> 2 | E84: =E64-E101 -> 3 | F84: =F64-F101 -> 1 | G84: =G64-G101 -> 4 | H84: =H64-H101 -> 2 | I84: =I64-I101 -> 0 | ... AE84: =AE64-AE101 -> 3 | AF84: =sum(B84:AE84) -> 99
A85: Perch Extender - Blue | B85: =B65-B102 -> 87 | C85: =C65-C102 -> 118 | D85: =D65-D102 -> 106 | E85: =E65-E102 -> 127 | F85: =F65-F102 -> 131 | G85: =G65-G102 -> 115 | H85: =H65-H102 -> 112 | I85: =I65-I102 -> 118 | ... AE85: =AE65-AE102 -> 57 | AF85: =sum(B85:AE85) -> 5388
A86: Perch Extender - Yellow | B86: =B66-B103 -> 12 | C86: =C66-C103 -> 17 | D86: =D66-D103 -> 13 | E86: =E66-E103 -> 17 | F86: =F66-F103 -> 16 | G86: =G66-G103 -> 12 | H86: =H66-H103 -> 10 | I86: =I66-I103 -> 8 | ... AE86: =AE66-AE103 -> 33 | AF86: =sum(B86:AE86) -> 839
A87: SUM (Add-ons) | B87: =SUM(B79:B86) -> 578 | C87: =SUM(C79:C86) -> 704 | D87: =SUM(D79:D86) -> 677 | E87: =SUM(E79:E86) -> 734 | F87: =SUM(F79:F86) -> 755 | G87: =SUM(G79:G86) -> 699 | H87: =SUM(H79:H86) -> 699 | I87: =SUM(I79:I86) -> 711 | ... AE87: =SUM(AE79:AE86) -> 223 | AF87: =sum(B87:AE87) -> 35351
A89: Returning Customers
A90: SKU 1 - Blue | B90: 2 | C90: 4 | D90: 3 | E90: 5 | F90: 2 | G90: 2 | H90: 6 | I90: 5 | J90: 4 | K90: 2 | L90: 1 | M90: 2 | N90: 5 | O90: 2 | P90: 0 | Q90: 1 | R90: 4 | S90: 4 | T90: 6 | U90: 4 | V90: 1 | W90: 16 | X90: 1 | Y90: 21 | Z90: 21 | AA90: 20 | AB90: 15 | AC90: 7 | AD90: 1 | AE90: 2 | AF90: =sum(B90:AE90) -> 169
A91: SKU 2 - Yellow | B91: 1 | C91: 0 | D91: 0 | E91: 1 | F91: 0 | G91: 0 | H91: 0 | I91: 0 | J91: 0 | K91: 0 | L91: 0 | M91: 0 | N91: 1 | O91: 0 | P91: 0 | Q91: 0 | R91: 0 | S91: 0 | T91: 0 | U91: 0 | V91: 1 | W91: 3 | X91: 1 | Y91: 7 | Z91: 3 | AA91: 4 | AB91: 2 | AC91: 1 | AD91: 3 | AE91: 1 | AF91: =sum(B91:AE91) -> 29
A92: SKU 3 - Blue w/ Solar | B92: 2 | C92: 5 | D92: 10 | E92: 5 | F92: 4 | G92: 3 | H92: 6 | I92: 11 | J92: 14 | K92: 3 | L92: 11 | M92: 7 | N92: 17 | O92: 6 | P92: 5 | Q92: 7 | R92: 4 | S92: 11 | T92: 6 | U92: 17 | V92: 9 | W92: 24 | X92: 27 | Y92: 48 | Z92: 30 | AA92: 21 | AB92: 34 | AC92: 10 | AD92: 3 | AE92: 3 | AF92: =sum(B92:AE92) -> 363
A93: SKU 4 - Yellow w/ Solar | B93: 0 | C93: 0 | D93: 2 | E93: 1 | F93: 0 | G93: 0 | H93: 1 | I93: 0 | J93: 2 | K93: 2 | L93: 1 | M93: 0 | N93: 0 | O93: 0 | P93: 0 | Q93: 0 | R93: 0 | S93: 0 | T93: 2 | U93: 1 | V93: 3 | W93: 6 | X93: 6 | Y93: 14 | Z93: 5 | AA93: 7 | AB93: 6 | AC93: 7 | AD93: 3 | AE93: 2 | AF93: =sum(B93:AE93) -> 71
A94: SUM (SKU 1 - SKU 4) | B94: =SUM(B90:B93) -> 5 | C94: =SUM(C90:C93) -> 9 | D94: =SUM(D90:D93) -> 15 | E94: =SUM(E90:E93) -> 12 | F94: =SUM(F90:F93) -> 6 | G94: =SUM(G90:G93) -> 5 | H94: =SUM(H90:H93) -> 13 | I94: =SUM(I90:I93) -> 16 | ... AE94: =SUM(AE90:AE93) -> 8 | AF94: =sum(B94:AE94) -> 632
A96: Wall Mount | B96: 1 | C96: 2 | D96: 4 | E96: 1 | F96: 1 | G96: 2 | H96: 0 | I96: 2 | J96: 10 | K96: 5 | L96: 5 | M96: 3 | N96: 4 | O96: 3 | P96: 4 | Q96: 1 | R96: 3 | S96: 2 | T96: 4 | U96: 11 | V96: 2 | W96: 9 | X96: 11 | Y96: 22 | Z96: 15 | AA96: 11 | AB96: 8 | AC96: 12 | AD96: 3 | AE96: 4 | AF96: =sum(B96:AE96) -> 165
A97: Suet Ball Holder | B97: 5 | C97: 10 | D97: 14 | E97: 10 | F97: 2 | G97: 4 | H97: 6 | I97: 13 | J97: 18 | K97: 7 | L97: 12 | M97: 7 | N97: 12 | O97: 7 | P97: 6 | Q97: 4 | R97: 6 | S97: 8 | T97: 15 | U97: 19 | V97: 14 | W97: 48 | X97: 32 | Y97: 69 | Z97: 46 | AA97: 33 | AB97: 47 | AC97: 15 | AD97: 0 | AE97: 0 | AF97: =sum(B97:AE97) -> 489
A98: 3-in-1 Nutrition Set - Blue | B98: 0 | C98: 13 | D98: 8 | E98: 1 | F98: 1 | G98: 4 | H98: 3 | I98: 5 | J98: 4 | K98: 2 | L98: 6 | M98: 3 | N98: 2 | O98: 1 | P98: 0 | Q98: 2 | R98: 3 | S98: 3 | T98: 5 | U98: 8 | V98: 4 | W98: 6 | X98: 6 | Y98: 11 | Z98: 7 | AA98: 8 | AB98: 6 | AC98: 4 | AD98: 0 | AE98: 1 | AF98: =sum(B98:AE98) -> 127
A99: 3-in-1 Nutrition Set - Yellow | B99: 0 | C99: 3 | D99: 1 | E99: 0 | F99: 1 | G99: 0 | H99: 0 | I99: 2 | J99: 1 | K99: 0 | L99: 0 | M99: 0 | N99: 0 | O99: 0 | P99: 0 | Q99: 0 | R99: 0 | S99: 0 | T99: 0 | U99: 0 | V99: 0 | W99: 2 | X99: 0 | Y99: 4 | Z99: 3 | AA99: 3 | AB99: 1 | AC99: 1 | AD99: 0 | AE99: 0 | AF99: =sum(B99:AE99) -> 22
A100: Solar Roof Single - Blue | B100: 1 | C100: 2 | D100: 0 | E100: 0 | F100: 1 | G100: 1 | H100: 0 | I100: 2 | J100: 1 | K100: 1 | L100: 1 | M100: 1 | N100: 2 | O100: 1 | P100: 1 | Q100: 1 | R100: 1 | S100: 5 | T100: 1 | U100: 3 | V100: 0 | W100: 5 | X100: 1 | Y100: 9 | Z100: 5 | AA100: 7 | AB100: 6 | AC100: 3 | AD100: 2 | AE100: 1 | AF100: =sum(B100:AE100) -> 65
A101: Solar Roof Single - Yellow | B101: 0 | C101: 0 | D101: 0 | E101: 0 | F101: 0 | G101: 0 | H101: 0 | I101: 0 | J101: 0 | K101: 0 | L101: 0 | M101: 0 | N101: 0 | O101: 1 | P101: 0 | Q101: 1 | R101: 1 | S101: 0 | T101: 0 | U101: 0 | V101: 0 | W101: 1 | X101: 1 | Y101: 2 | Z101: 1 | AA101: 4 | AB101: 1 | AC101: 0 | AD101: 0 | AE101: 1 | AF101: =sum(B101:AE101) -> 14
A102: Perch Extender - Blue | B102: 1 | C102: 7 | D102: 4 | E102: 2 | F102: 5 | G102: 10 | H102: 2 | I102: 6 | J102: 8 | K102: 4 | L102: 9 | M102: 5 | N102: 7 | O102: 2 | P102: 2 | Q102: 3 | R102: 8 | S102: 9 | T102: 6 | U102: 19 | V102: 7 | W102: 19 | X102: 13 | Y102: 32 | Z102: 13 | AA102: 22 | AB102: 17 | AC102: 11 | AD102: 2 | AE102: 4 | AF102: =sum(B102:AE102) -> 259
A103: Perch Extender - Yellow | B103: 2 | C103: 0 | D103: 0 | E103: 2 | F103: 3 | G103: 1 | H103: 0 | I103: 1 | J103: 0 | K103: 0 | L103: 2 | M103: 0 | N103: 0 | O103: 0 | P103: 0 | Q103: 0 | R103: 1 | S103: 0 | T103: 3 | U103: 0 | V103: 1 | W103: 5 | X103: 4 | Y103: 11 | Z103: 2 | AA103: 4 | AB103: 4 | AC103: 3 | AD103: 1 | AE103: 0 | AF103: =sum(B103:AE103) -> 50
A104: SUM (Add-ons) | B104: =SUM(B96:B103) -> 10 | C104: =SUM(C96:C103) -> 37 | D104: =SUM(D96:D103) -> 31 | E104: =SUM(E96:E103) -> 16 | F104: =SUM(F96:F103) -> 14 | G104: =SUM(G96:G103) -> 22 | H104: =SUM(H96:H103) -> 11 | I104: =SUM(I96:I103) -> 31 | ... AE104: =SUM(AE96:AE103) -> 11 | AF104: =sum(B104:AE104) -> 1191
A106: Units Sold (Net)
A107: SKU 1 - Blue | B107: =B53-(B200+B205+B246+B296+B305) -> 147 | C107: =C53-(C200+C205+C246+C296+C305) -> 148 | D107: =D53-(D200+D205+D246+D296+D305) -> 148 | E107: =E53-(E200+E205+E246+E296+E305) -> 184 | F107: =F53-(F200+F205+F246+F296+F305) -> 216 | G107: =G53-(G200+G205+G246+G296+G305) -> 182 | H107: =H53-(H200+H205+H246+H296+H305) -> 159 | I107: =I53-(I200+I205+I246+I296+I305) -> 143 | ... AE107: =AE53-(AE200+AE205+AE246+AE296+AE305) -> 39 | AF107: =sum(B107:AE107) -> 8447
A108: SKU 2 - Yellow | B108: =B54-(B201+B206+B247+B297+B306) -> 6 | C108: =C54-(C201+C206+C247+C297+C306) -> 10 | D108: =D54-(D201+D206+D247+D297+D306) -> 2 | E108: =E54-(E201+E206+E247+E297+E306) -> 8 | F108: =F54-(F201+F206+F247+F297+F306) -> 8 | G108: =G54-(G201+G206+G247+G297+G306) -> 11 | H108: =H54-(H201+H206+H247+H297+H306) -> 10 | I108: =I54-(I201+I206+I247+I297+I306) -> 5 | ... AE108: =AE54-(AE201+AE206+AE247+AE297+AE306) -> 42 | AF108: =sum(B108:AE108) -> 1009
A109: SKU 3 - Blue w/ Solar | B109: =B55-(B202+B207+B248+B298+B307) -> 265 | C109: =C55-(C202+C207+C248+C298+C307) -> 275 | D109: =D55-(D202+D207+D248+D298+D307) -> 270 | E109: =E55-(E202+E207+E248+E298+E307) -> 291 | F109: =F55-(F202+F207+F248+F298+F307) -> 333 | G109: =G55-(G202+G207+G248+G298+G307) -> 333 | H109: =H55-(H202+H207+H248+H298+H307) -> 312 | I109: =I55-(I202+I207+I248+I298+I307) -> 317 | ... AE109: =AE55-(AE202+AE207+AE248+AE298+AE307) -> 92 | AF109: =sum(B109:AE109) -> 16863
A110: SKU 4 - Yellow w/ Solar | B110: =B56-(B203+B208+B249+B299+B308) -> 25 | C110: =C56-(C203+C208+C249+C299+C308) -> 23 | D110: =D56-(D203+D208+D249+D299+D308) -> 30 | E110: =E56-(E203+E208+E249+E299+E308) -> 27 | F110: =F56-(F203+F208+F249+F299+F308) -> 33 | G110: =G56-(G203+G208+G249+G299+G308) -> 24 | H110: =H56-(H203+H208+H249+H299+H308) -> 21 | I110: =I56-(I203+I208+I249+I299+I308) -> 30 | ... AE110: =AE56-(AE203+AE208+AE249+AE299+AE308) -> 89 | AF110: =sum(B110:AE110) -> 2168
A111: SUM (SKU 1 - SKU 4) | B111: =SUM(B107:B110) -> 443 | C111: =SUM(C107:C110) -> 456 | D111: =SUM(D107:D110) -> 450 | E111: =SUM(E107:E110) -> 510 | F111: =SUM(F107:F110) -> 590 | G111: =SUM(G107:G110) -> 550 | H111: =SUM(H107:H110) -> 502 | I111: =SUM(I107:I110) -> 495 | ... AE111: =SUM(AE107:AE110) -> 262 | AF111: =sum(B111:AE111) -> 28487
A113: Wall Mount | B113: =B59-(B213+B224+B259+B317+B328) -> 75 | C113: =C59-(C213+C224+C259+C317+C328) -> 103 | D113: =D59-(D213+D224+D259+D317+D328) -> 88 | E113: =E59-(E213+E224+E259+E317+E328) -> 116 | F113: =F59-(F213+F224+F259+F317+F328) -> 131 | G113: =G59-(G213+G224+G259+G317+G328) -> 130 | H113: =H59-(H213+H224+H259+H317+H328) -> 126 | I113: =I59-(I213+I224+I259+I317+I328) -> 117 | ... AE113: =AE59-(AE213+AE224+AE259+AE317+AE328) -> 75 | AF113: =sum(B113:AE113) -> 6371
A114: Suet Ball Holder | B114: =B60-(B214+B225+B260+B318+B329) -> 350 | C114: =C60-(C214+C225+C260+C318+C329) -> 369 | D114: =D60-(D214+D225+D260+D318+D329) -> 381 | E114: =E60-(E214+E225+E260+E318+E329) -> 386 | F114: =F60-(F214+F225+F260+F318+F329) -> 415 | G114: =G60-(G214+G225+G260+G318+G329) -> 366 | H114: =H60-(H214+H225+H260+H318+H329) -> 379 | I114: =I60-(I214+I225+I260+I318+I329) -> 363 | ... AE114: =AE60-(AE214+AE225+AE260+AE318+AE329) -> -7 | AF114: =sum(B114:AE114) -> 19485
A115: 3-in-1 Nutrition Set - Blue | B115: =B61-(B215+B226+B261+B319+B330) -> 39 | C115: =C61-(C215+C226+C261+C319+C330) -> 93 | D115: =D61-(D215+D226+D261+D319+D330) -> 72 | E115: =E61-(E215+E226+E261+E319+E330) -> 74 | F115: =F61-(F215+F226+F261+F319+F330) -> 43 | G115: =G61-(G215+G226+G261+G319+G330) -> 52 | H115: =H61-(H215+H226+H261+H319+H330) -> 57 | I115: =I61-(I215+I226+I261+I319+I330) -> 90 | ... AE115: =AE61-(AE215+AE226+AE261+AE319+AE330) -> 22 | AF115: =sum(B115:AE115) -> 2732
A116: 3-in-1 Nutrition Set - Yellow | B116: =B62-(B216+B227+B262+B320+B331) -> 5 | C116: =C62-(C216+C227+C262+C320+C331) -> 19 | D116: =D62-(D216+D227+D262+D320+D331) -> 8 | E116: =E62-(E216+E227+E262+E320+E331) -> 9 | F116: =F62-(F216+F227+F262+F320+F331) -> 4 | G116: =G62-(G216+G227+G262+G320+G331) -> 4 | H116: =H62-(H216+H227+H262+H320+H331) -> 5 | I116: =I62-(I216+I227+I262+I320+I331) -> 12 | ... AE116: =AE62-(AE216+AE227+AE262+AE320+AE331) -> 25 | AF116: =sum(B116:AE116) -> 401
A117: Solar Roof Single - Blue | B117: =B63-(B217+B228+B263+B321+B332) -> 12 | C117: =C63-(C217+C228+C263+C321+C332) -> 12 | D117: =D63-(D217+D228+D263+D321+D332) -> -3 | E117: =E63-(E217+E228+E263+E321+E332) -> 14 | F117: =F63-(F217+F228+F263+F321+F332) -> 20 | G117: =G63-(G217+G228+G263+G321+G332) -> 9 | H117: =H63-(H217+H228+H263+H321+H332) -> 9 | I117: =I63-(I217+I228+I263+I321+I332) -> 12 | ... AE117: =AE63-(AE217+AE228+AE263+AE321+AE332) -> 6 | AF117: =sum(B117:AE117) -> 546
...

Sheet AMAZON - P&L
A1: November | B1: 45231 | C1: 45232 | D1: 45233 | E1: 45234 | F1: 45235 | G1: 45236 | H1: 45237 | I1: 45238 | J1: 45239 | K1: 45240 | L1: 45241 | M1: 45242 | N1: 45243 | O1: 45244 | P1: 45245 | Q1: 45246 | R1: 45247 | S1: 45248 | T1: 45249 | U1: 45250 | V1: 45251 | W1: 45252 | X1: 45253 | Y1: 45254 | Z1: 45255 | AA1: 45256 | AB1: 45257 | AC1: 45258 | AD1: 45259 | AE1: 45260
A2: DAY | B2: WED | C2: THU | D2: FRI | E2: SAT | F2: SUN | G2: MON | H2: TUE | I2: WED | J2: THU | K2: FRI | L2: SAT | M2: SUN | N2: MON | O2: TUE | P2: WED | Q2: THU | R2: FRI | S2: SAT | T2: SUN | U2: MON | V2: TUE | W2: WED | X2: THU | Y2: FRI | Z2: SAT | AA2: SUN | AB2: MON | AC2: TUE | AD2: WED | AE2: THU
A3: COMMENT
A4: Orders
A5: Amazon (market place) | B5: =Summary!B59 -> 42 | C5: =Summary!C59 -> 40 | D5: =Summary!D59 -> 61 | E5: =Summary!E59 -> 58 | F5: =Summary!F59 -> 74 | G5: =Summary!G59 -> 56 | H5: =Summary!H59 -> 50 | I5: =Summary!I59 -> 65 | ... AE5: =Summary!AE59 -> 3
A6: All | B6: =SUM(B5) -> 42 | C6: =SUM(C5) -> 40 | D6: =SUM(D5) -> 61 | E6: =SUM(E5) -> 58 | F6: =SUM(F5) -> 74 | G6: =SUM(G5) -> 56 | H6: =SUM(H5) -> 50 | I6: =SUM(I5) -> 65 | ... AE6: =SUM(AE5) -> 3 | AF6: =SUM(B6:AE6) -> 10840
A8: Revenue
A9: Amazon (market place) | B9: =Summary!B15 -> 9998.64 | C9: =Summary!C15 -> 10453.96 | D9: =Summary!D15 -> 16043.42 | E9: =Summary!E15 -> 15088.14 | F9: =Summary!F15 -> 19511.77 | G9: =Summary!G15 -> 15164.18 | H9: =Summary!H15 -> 12460.48 | I9: =Summary!I15 -> 14308.41 | ... AE9: =Summary!AE15 -> 540.1
A10: All | B10: =SUM(B9) -> 9998.64 | C10: =SUM(C9) -> 10453.96 | D10: =SUM(D9) -> 16043.42 | E10: =SUM(E9) -> 15088.14 | F10: =SUM(F9) -> 19511.77 | G10: =SUM(G9) -> 15164.18 | H10: =SUM(H9) -> 12460.48 | I10: =SUM(I9) -> 14308.41 | ... AE10: =SUM(AE9) -> 540.1 | AF10: =SUM(B10:AE10) -> 2411885.2
A12: Media Cost
A13: Amazon Spend | B13: =Summary!B85 -> 3233.72 | C13: =Summary!C85 -> 3207.21 | D13: =Summary!D85 -> 3213.69 | E13: =Summary!E85 -> 4807.14 | F13: =Summary!F85 -> 5368.78 | G13: =Summary!G85 -> 3970.36 | H13: =Summary!H85 -> 3978.92 | I13: =Summary!I85 -> 2768.25 | ... AE13: =Summary!AE85 -> 433.94 | AF13: =SUM(B13:AE13) -> 343549.87
A14: Amazon Platform Fee (15 %) | B14: =B9*'Data - P&L'!$C$48 -> 1499.796 | C14: =C9*'Data - P&L'!$C$48 -> 1568.094 | D14: =D9*'Data - P&L'!$C$48 -> 2406.513 | E14: =E9*'Data - P&L'!$C$48 -> 2263.221 | F14: =F9*'Data - P&L'!$C$48 -> 2926.7655 | G14: =G9*'Data - P&L'!$C$48 -> 2274.627 | H14: =H9*'Data - P&L'!$C$48 -> 1869.072 | I14: =I9*'Data - P&L'!$C$48 -> 2146.2615 | ... AE14: =AE9*'Data - P&L'!$C$48 -> 81.015 | AF14: =SUM(B14:AE14) -> 361782.79
A15: All | B15: =SUM(B13:B14) -> 4733.516 | C15: =SUM(C13:C14) -> 4775.304 | D15: =SUM(D13:D14) -> 5620.203 | E15: =SUM(E13:E14) -> 7070.361 | F15: =SUM(F13:F14) -> 8295.5455 | G15: =SUM(G13:G14) -> 6244.987 | H15: =SUM(H13:H14) -> 5847.992 | I15: =SUM(I13:I14) -> 4914.5115 | ... AE15: =SUM(AE13:AE14) -> 514.955 | AF15: =SUM(B15:AE15) -> 705332.66
A19: Amazon Orders
A20: Hardware | B20: =Summary!B16 -> 9193 | C20: =Summary!C16 -> 9677.76 | D20: =Summary!D16 -> 14877.86 | E20: =Summary!E16 -> 14028.38 | F20: =Summary!F16 -> 18099.43 | G20: =Summary!G16 -> 14185 | H20: =Summary!H16 -> 11584.43 | I20: =Summary!I16 -> 13067.81 | ... AE20: =Summary!AE16 -> 478 | AF20: =SUM(B20:AE20) -> 2235795.5
A21: Addons | B21: =Summary!B17 -> 144 | C21: =Summary!C17 -> 72 | D21: =Summary!D17 -> 117.6 | E21: =Summary!E17 -> 96 | F21: =Summary!F17 -> 142.8 | G21: =Summary!G17 -> 96 | H21: =Summary!H17 -> 94.8 | I21: =Summary!I17 -> 262.8 | ... AE21: =Summary!AE17 -> 29 | AF21: =SUM(B21:AE21) -> 14129.08
A22: Tax | B22: =Summary!B18 -> 649.85 | C22: =Summary!C18 -> 696.41 | D22: =Summary!D18 -> 1038.18 | E22: =Summary!E18 -> 947.39 | F22: =Summary!F18 -> 1262.15 | G22: =Summary!G18 -> 869.71 | H22: =Summary!H18 -> 771.81 | I22: =Summary!I18 -> 963.53 | ... AE22: =Summary!AE18 -> 33.1 | AF22: =SUM(B22:AE22) -> 157647.74
A23: Shipping | B23: =Summary!B19 -> 11.79 | C23: =Summary!C19 -> 7.49 | D23: =Summary!D19 -> 0.5 | E23: =Summary!E19 -> 7.24 | F23: =Summary!F19 -> 2.75 | G23: =Summary!G19 -> 0 | H23: =Summary!H19 -> 0.31 | I23: =Summary!I19 -> 0.5 | ... AE23: =Summary!AE19 -> 0 | AF23: =SUM(B23:AE23) -> 2723.27
A24: Gift Wrap Price | B24: =Summary!B20 -> 0 | C24: =Summary!C20 -> 0.3 | D24: =Summary!D20 -> 9.28 | E24: =Summary!E20 -> 9.13 | F24: =Summary!F20 -> 4.64 | G24: =Summary!G20 -> 13.47 | H24: =Summary!H20 -> 9.13 | I24: =Summary!I20 -> 13.77 | ... AE24: =Summary!AE20 -> 0 | AF24: =SUM(B24:AE24) -> 1589.64
A25: All Amazon | B25: =SUM(B20:B24) -> 9998.64 | C25: =SUM(C20:C24) -> 10453.96 | D25: =SUM(D20:D24) -> 16043.42 | E25: =SUM(E20:E24) -> 15088.14 | F25: =SUM(F20:F24) -> 19511.77 | G25: =SUM(G20:G24) -> 15164.18 | H25: =SUM(H20:H24) -> 12460.48 | I25: =SUM(I20:I24) -> 14308.41 | ... AE25: =SUM(AE20:AE24) -> 540.1 | AF25: =SUM(B25:AE25) -> 2411885.2
A27: Units Sold (Gross)
A28: SKU 1 - Blue | B28: 10 | C28: 5 | D28: 7 | E28: 4 | F28: 6 | G28: 8 | H28: 10 | I28: 20 | J28: 24 | K28: 17 | L28: 19 | M28: 11 | N28: 20 | O28: 21 | P28: 24 | Q28: 17 | R28: 17 | S28: 15 | T28: 39 | U28: 0 | V28: 2 | W28: 1 | X28: 2 | Y28: 0 | Z28: 0 | AA28: 0 | AB28: 0 | AC28: 0 | AD28: 0 | AE28: 2 | AF28: =sum(B28:AE28) -> 301
A29: SKU 2 - Yellow | B29: 0 | C29: 0 | D29: 0 | E29: 0 | F29: 0 | G29: 3 | H29: 1 | I29: 4 | J29: 3 | K29: 2 | L29: 3 | M29: 2 | N29: 4 | O29: 1 | P29: 0 | Q29: 0 | R29: 0 | S29: 0 | T29: 0 | U29: 0 | V29: 0 | W29: 0 | X29: 0 | Y29: 1 | Z29: 0 | AA29: 0 | AB29: 0 | AC29: 0 | AD29: 0 | AE29: 0 | AF29: =sum(B29:AE29) -> 24
A30: SKU 3 - Blue w/ Solar | B30: 27 | C30: 31 | D30: 50 | E30: 49 | F30: 58 | G30: 42 | H30: 33 | I30: 25 | J30: 56 | K30: 100 | L30: 137 | M30: 140 | N30: 127 | O30: 136 | P30: 143 | Q30: 181 | R30: 201 | S30: 232 | T30: 140 | U30: 430 | V30: 473 | W30: 545 | X30: 713 | Y30: 2841 | Z30: 1752 | AA30: 1107 | AB30: 347 | AC30: 0 | AD30: 0 | AE30: 0 | AF30: =sum(B30:AE30) -> 10116
A31: SKU 4 - Yellow w/ Solar | B31: 0 | C31: 1 | D31: 0 | E31: 1 | F31: 4 | G31: 2 | H31: 2 | I31: 9 | J31: 13 | K31: 7 | L31: 6 | M31: 7 | N31: 4 | O31: 7 | P31: 10 | Q31: 9 | R31: 10 | S31: 19 | T31: 1 | U31: 1 | V31: 2 | W31: 0 | X31: 2 | Y31: 6 | Z31: 0 | AA31: 0 | AB31: 0 | AC31: 0 | AD31: 0 | AE31: 0 | AF31: =sum(B31:AE31) -> 123
A32: SUM (SKU 1 - SKU 4) | B32: =SUM(B28:B31) -> 37 | C32: =SUM(C28:C31) -> 37 | D32: =SUM(D28:D31) -> 57 | E32: =SUM(E28:E31) -> 54 | F32: =SUM(F28:F31) -> 68 | G32: =SUM(G28:G31) -> 55 | H32: =SUM(H28:H31) -> 46 | I32: =SUM(I28:I31) -> 58 | ... AE32: =SUM(AE28:AE31) -> 2 | AF32: =sum(B32:AE32) -> 10564
A34: Wall Mount | B34: 6 | C34: 3 | D34: 5 | E34: 4 | F34: 6 | G34: 4 | H34: 4 | I34: 11 | J34: 9 | K34: 7 | L34: 9 | M34: 11 | N34: 6 | O34: 9 | P34: 8 | Q34: 24 | R34: 21 | S34: 29 | T34: 28 | U34: 36 | V34: 41 | W34: 35 | X34: 53 | Y34: 162 | Z34: 54 | AA34: 8 | AB34: 2 | AC34: 0 | AD34: 0 | AE34: 1 | AF34: 0
A35: Suet Ball Holder | AF35: =sum(B35:AE35) -> 0
A36: 3-in-1 Nutrition Set - Blue | AF36: =sum(B36:AE36) -> 0
A37: 3-in-1 Nutrition Set - Yellow | AF37: =sum(B37:AE37) -> 0
A38: Solar Roof Single - Blue | AF38: =sum(B38:AE38) -> 0
A39: Solar Roof Single - Yellow | AF39: =sum(B39:AE39) -> 0
A40: Perch Extender - Blue | AF40: =sum(B40:AE40) -> 0
A41: Perch Extender - Yellow | B41: 0 | C41: 0 | D41: 0 | E41: 0 | F41: 0 | G41: 0 | H41: 0 | I41: 0 | J41: 0 | K41: 0 | L41: 0 | M41: 0 | N41: 0 | O41: 0 | P41: 0 | Q41: 0 | R41: 0 | S41: 0 | T41: 0 | U41: 0 | V41: 0 | W41: 0 | X41: 1 | Y41: 0 | Z41: 0 | AA41: 0 | AB41: 0 | AC41: 0 | AD41: 1 | AE41: 0 | AF41: 0
A42: SUM (Add-ons) | B42: =SUM(B34:B41) -> 6 | C42: =SUM(C34:C41) -> 3 | D42: =SUM(D34:D41) -> 5 | E42: =SUM(E34:E41) -> 4 | F42: =SUM(F34:F41) -> 6 | G42: =SUM(G34:G41) -> 4 | H42: =SUM(H34:H41) -> 4 | I42: =SUM(I34:I41) -> 11 | ... AE42: =SUM(AE34:AE41) -> 1 | AF42: =sum(B42:AE42) -> 598
A45: Units Sold by country (Gross) - Only selling in US
A46: Bird Buddy - Blue - AMAZON.US | AF46: =sum(B46:AE46) -> 0
A47: Bird Buddy - Yellow - AMAZON.US
A48: Bird Buddy with Solar Roof Blue - AMAZON.US | AF48: =sum(B48:AE48) -> 0
A49: Bird Buddy with Solar Roof Yellow - AMAZON.US
A50: Bird Buddy - AMAZON.EU | AF50: =sum(B50:AE50) -> 0
A51: Bird Buddy with Solar Roof - AMAZON.EU | AF51: =sum(B51:AE51) -> 0
A52: Bird Buddy - AMAZON (OTHER1) | AF52: =sum(B52:AE52) -> 0
A53: Bird Buddy with Solar Roof - AMAZON (OTHER1) | AF53: =sum(B53:AE53) -> 0
A54: All Bird Buddy | B54: =B46+B50+B52 -> 0 | C54: =SUM(C46:C53) -> 0 | D54: =SUM(D46:D53) -> 0 | E54: =SUM(E46:E53) -> 0 | F54: =SUM(F46:F53) -> 0 | G54: =SUM(G46:G53) -> 0 | H54: =SUM(H46:H53) -> 0 | I54: =SUM(I46:I53) -> 0 | J54: =SUM(J46:J53) -> 0 | ... AE54: =SUM(AE46:AE53) -> 0 | AF54: =sum(B54:AE54) -> 0
A55: All Bird Buddy with Solar Roof | B55: =B48+B51+B53 -> 0 | C55: =C48+C51+C53 -> 0 | D55: =D48+D51+D53 -> 0 | E55: =E48+E51+E53 -> 0 | F55: =F48+F51+F53 -> 0 | G55: =G48+G51+G53 -> 0 | H55: =H48+H51+H53 -> 0 | I55: =I48+I51+I53 -> 0 | ... AE55: =AE48+AE51+AE53 -> 0 | AF55: =sum(B55:AE55) -> 0
A57: Wall Mount - AMAZON.US | AF57: =sum(B57:AE57) -> 0
A58: Fence Mount - AMAZON.US | AF58: =sum(B58:AE58) -> 0
A59: Suet Ball Holder - AMAZON.US | AF59: =sum(B59:AE59) -> 0
A60: 3-in-1 Nutrition Set - AMAZON.US | AF60: =sum(B60:AE60) -> 0
A61: Solar Roof Single - AMAZON.US | AF61: =sum(B61:AE61) -> 0
A62: All AMAZON.US | B62: =SUM(B57:B61) -> 0 | C62: =SUM(C57:C61) -> 0 | D62: =SUM(D57:D61) -> 0 | E62: =SUM(E57:E61) -> 0 | F62: =SUM(F57:F61) -> 0 | G62: =SUM(G57:G61) -> 0 | H62: =SUM(H57:H61) -> 0 | I62: =SUM(I57:I61) -> 0 | ... AE62: =SUM(AE57:AE61) -> 0 | AF62: =sum(B62:AE62) -> 0
A64: Wall Mount - AMAZON.EU | AF64: =sum(B64:AE64) -> 0
A65: Fence Mount - AMAZON.EU | AF65: =sum(B65:AE65) -> 0
A66: Suet Ball Holder - AMAZON.EU | AF66: =sum(B66:AE66) -> 0
A67: 3-in-1 Nutrition Set - AMAZON.EU | AF67: =sum(B67:AE67) -> 0
A68: Solar Roof Single - AMAZON.EU | AF68: =sum(B68:AE68) -> 0
A69: All AMAZON.EU | B69: =SUM(B64:B68) -> 0 | C69: =SUM(C64:C68) -> 0 | D69: =SUM(D64:D68) -> 0 | E69: =SUM(E64:E68) -> 0 | F69: =SUM(F64:F68) -> 0 | G69: =SUM(G64:G68) -> 0 | H69: =SUM(H64:H68) -> 0 | I69: =SUM(I64:I68) -> 0 | ... AE69: =SUM(AE64:AE68) -> 0 | AF69: =sum(B69:AE69) -> 0
A71: Wall Mount - AMAZON (OTHER1) | AF71: =sum(B71:AE71) -> 0
A72: Fence Mount - AMAZON (OTHER1) | AF72: =sum(B72:AE72) -> 0
A73: Suet Ball Holder - AMAZON (OTHER1) | AF73: =sum(B73:AE73) -> 0
A74: 3-in-1 Nutrition Set - AMAZON (OTHER1) | AF74: =sum(B74:AE74) -> 0
A75: Solar Roof Single - AMAZON (OTHER1) | AF75: =sum(B75:AE75) -> 0
A76: All AMAZON (OTHER1) | B76: =SUM(B71:B75) -> 0 | C76: =SUM(C71:C74) -> 0 | D76: =SUM(D71:D75) -> 0 | E76: =SUM(E71:E75) -> 0 | F76: =SUM(F71:F75) -> 0 | G76: =SUM(G71:G74) -> 0 | H76: =SUM(H71:H74) -> 0 | I76: =SUM(I71:I74) -> 0 | J76: =SUM(J71:J74) -> 0 | K76: =SUM(K71:K74) -> 0 | L76: =SUM(L71:L74) -> 0 | M76: =SUM(M71:M74) -> 0 | N76: =SUM(N71:N74) -> 0 | ... V76: =SUM(V71:V74) -> 0 | W76: =SUM(W71:W75) -> 0 | X76: =SUM(X71:X74) -> 0 | Y76: =SUM(Y71:Y74) -> 0 | Z76: =SUM(Z71:Z74) -> 0 | AA76: =SUM(AA71:AA74) -> 0 | AB76: =SUM(AB71:AB74) -> 0 | AC76: =SUM(AC71:AC74) -> 0 | AD76: =SUM(AD71:AD74) -> 0 | AE76: =SUM(AE71:AE74) -> 0 | AF76: =sum(B76:AE76) -> 0
A78: Revenue by country (Gross) - Only selling in US
A79: Bird Buddy - AMAZON.US | AF79: =SUM(B79:AE79) -> 0
A80: Bird Buddy with Solar Roof - AMAZON.US | AF80: =SUM(B80:AE80) -> 0
A81: Bird Buddy - AMAZON.EU | AF81: =SUM(B81:AE81) -> 0
A82: Bird Buddy with Solar Roof - AMAZON.EU | AF82: =SUM(B82:AE82) -> 0
A83: Bird Buddy - AMAZON (OTHER1) | AF83: =SUM(B83:AE83) -> 0
A84: Bird Buddy with Solar Roof - AMAZON (OTHER1) | AF84: =SUM(B84:AE84) -> 0
A85: All Bird Buddy | B85: =B79+B81+B83 -> 0 | C85: =C79+C81+C83 -> 0 | D85: =D79+D81+D83 -> 0 | E85: =E79+E81+E83 -> 0 | F85: =F79+F81+F83 -> 0 | G85: =G79+G81+G83 -> 0 | H85: =H79+H81+H83 -> 0 | I85: =I79+I81+I83 -> 0 | ... AE85: =AE79+AE81+AE83 -> 0 | AF85: =SUM(B85:AE85) -> 0
A86: All Bird Buddy with Solar Roof | B86: =B80+B82+B84 -> 0 | C86: =C80+C82+C84 -> 0 | D86: =D80+D82+D84 -> 0 | E86: =E80+E82+E84 -> 0 | F86: =F80+F82+F84 -> 0 | G86: =G80+G82+G84 -> 0 | H86: =H80+H82+H84 -> 0 | I86: =I80+I82+I84 -> 0 | ... AE86: =AE80+AE82+AE84 -> 0 | AF86: =SUM(B86:AE86) -> 0
A88: Wall Mount - AMAZON.US | AF88: =SUM(B88:AE88) -> 0
A89: Fence Mount - AMAZON.US | AF89: =SUM(B89:AE89) -> 0
A90: Suet Ball Holder - AMAZON.US | AF90: =SUM(B90:AE90) -> 0
A91: 3-in-1 Nutrition Set - AMAZON.US | AF91: =SUM(B91:AE91) -> 0
A92: Solar Roof Single - AMAZON.US | AF92: =SUM(B92:AE92) -> 0
A93: All AMAZON.US | B93: =SUM(B88:B92) -> 0 | C93: =SUM(C88:C92) -> 0 | D93: =SUM(D88:D92) -> 0 | E93: =SUM(E88:E92) -> 0 | F93: =SUM(F88:F92) -> 0 | G93: =SUM(G88:G92) -> 0 | H93: =SUM(H88:H92) -> 0 | I93: =SUM(I88:I92) -> 0 | ... AE93: =SUM(AE88:AE92) -> 0 | AF93: =SUM(B93:AE93) -> 0
A95: Wall Mount - AMAZON.EU | AF95: =SUM(B95:AE95) -> 0
A96: Fence Mount - AMAZON.EU | AF96: =SUM(B96:AE96) -> 0
A97: Suet Ball Holder - AMAZON.EU | AF97: =SUM(B97:AE97) -> 0
A98: 3-in-1 Nutrition Set - AMAZON.EU | AF98: =SUM(B98:AE98) -> 0
A99: Solar Roof Single - AMAZON.EU | AF99: =SUM(B99:AE99) -> 0
A100: All AMAZON.EU | B100: =SUM(B95:B99) -> 0 | C100: =SUM(C95:C99) -> 0 | D100: =SUM(D95:D99) -> 0 | E100: =SUM(E95:E99) -> 0 | F100: =SUM(F95:F99) -> 0 | G100: =SUM(G95:G99) -> 0 | H100: =SUM(H95:H99) -> 0 | I100: =SUM(I95:I99) -> 0 | ... AE100: =SUM(AE95:AE99) -> 0 | AF100: =SUM(B100:AE100) -> 0
A102: Wall Mount - AMAZON (OTHER1) | AF102: =SUM(B102:AE102) -> 0
A103: Fence Mount - AMAZON (OTHER1) | AF103: =SUM(B103:AE103) -> 0
A104: Suet Ball Holder - AMAZON (OTHER1) | AF104: =SUM(B104:AE104) -> 0
A105: 3-in-1 Nutrition Set - AMAZON (OTHER1) | AF105: =SUM(B105:AE105) -> 0
A106: Solar Roof Single - AMAZON (OTHER1) | AF106: =SUM(B106:AE106) -> 0
A107: All AMAZON (OTHER1) | B107: =SUM(B102:B106) -> 0 | C107: =SUM(C102:C106) -> 0 | D107: =SUM(D102:D106) -> 0 | E107: =SUM(E102:E106) -> 0 | F107: =SUM(F102:F106) -> 0 | G107: =SUM(G102:G106) -> 0 | H107: =SUM(H102:H106) -> 0 | I107: =SUM(I102:I106) -> 0 | ... AE107: =SUM(AE102:AE106) -> 0 | AF107: =SUM(B107:AE107) -> 0
A110: Units Cancelled by country (Gross)
A111: SKU 1 - Blue | B111: 0 | C111: 0 | D111: 0 | E111: 0 | F111: 0 | G111: 0 | H111: 1 | I111: 1 | J111: 3 | K111: 1 | L111: 1 | M111: 0 | N111: 2 | O111: 0 | P111: 1 | Q111: 0 | R111: 0 | S111: 0 | T111: 1 | U111: 0 | V111: 0 | W111: 0 | X111: 0 | Y111: 0 | Z111: 0 | AA111: 0 | AB111: 0 | AC111: 0 | AD111: 0 | AE111: 0 | AF111: =SUM(B111:AE111) -> 11
A112: SKU 2 - Yellow | B112: 0 | C112: 0 | D112: 0 | E112: 0 | F112: 0 | G112: 0 | H112: 0 | I112: 0 | J112: 0 | K112: 0 | L112: 0 | M112: 0 | N112: 0 | O112: 0 | P112: 0 | Q112: 0 | R112: 0 | S112: 0 | T112: 0 | U112: 0 | V112: 0 | W112: 0 | X112: 0 | Y112: 0 | Z112: 0 | AA112: 0 | AB112: 0 | AC112: 0 | AD112: 0 | AE112: 0 | AF112: =SUM(B112:AE112) -> 0
A113: SKU 3 - Blue w/ Solar | B113: 0 | C113: 2 | D113: 2 | E113: 1 | F113: 1 | G113: 0 | H113: 0 | I113: 1 | J113: 3 | K113: 0 | L113: 6 | M113: 3 | N113: 3 | O113: 2 | P113: 4 | Q113: 6 | R113: 1 | S113: 2 | T113: 1 | U113: 5 | V113: 6 | W113: 11 | X113: 13 | Y113: 78 | Z113: 52 | AA113: 21 | AB113: 10 | AC113: 0 | AD113: 0 | AE113: 0 | AF113: =SUM(B113:AE113) -> 234
A114: SKU 4 - Yellow w/ Solar | B114: 0 | C114: 0 | D114: 0 | E114: 0 | F114: 0 | G114: 0 | H114: 0 | I114: 0 | J114: 0 | K114: 1 | L114: 0 | M114: 1 | N114: 0 | O114: 0 | P114: 1 | Q114: 0 | R114: 0 | S114: 0 | T114: 0 | U114: 1 | V114: 0 | W114: 0 | X114: 0 | Y114: 0 | Z114: 0 | AA114: 0 | AB114: 0 | AC114: 0 | AD114: 0 | AE114: 0 | AF114: =SUM(B114:AE114) -> 4
A115: SUM (SKU 1 + SKU 2) | B115: =B111+B112 -> 0 | C115: =C111+C112 -> 0 | D115: =D111+D112 -> 0 | E115: =E111+E112 -> 0 | F115: =F111+F112 -> 0 | G115: =G111+G112 -> 0 | H115: =H111+H112 -> 1 | I115: =I111+I112 -> 1 | ... AE115: =AE111+AE112 -> 0 | AF115: =SUM(B115:AE115) -> 11
A116: SUM (SKU 3 + SKU 4) | B116: =B113+B114 -> 0 | C116: =C113+C114 -> 2 | D116: =D113+D114 -> 2 | E116: =E113+E114 -> 1 | F116: =F113+F114 -> 1 | G116: =G113+G114 -> 0 | H116: =H113+H114 -> 0 | I116: =I113+I114 -> 1 | ... AE116: =AE113+AE114 -> 0 | AF116: =SUM(B116:AE116) -> 238
A118: Wall Mount | B118: 0 | C118: 0 | D118: 0 | E118: 0 | F118: 1 | G118: 0 | H118: 0 | I118: 1 | J118: 2 | K118: 0 | L118: 0 | M118: 0 | N118: 1 | O118: 0 | P118: 0 | Q118: 1 | R118: 1 | S118: 0 | T118: 0 | U118: 2 | V118: 0 | W118: 0 | X118: 0 | Y118: 1 | Z118: 3 | AA118: 0 | AB118: 0 | AC118: 0 | AD118: 0 | AE118: 0 | AF118: =SUM(B118:AE118) -> 13
A119: Suet Ball Holder | AF119: =SUM(B119:AE119) -> 0
...

Sheet App - P&L
A1: NOVEMBER | B1: 45231 | C1: 45232 | D1: 45233 | E1: 45234 | F1: 45235 | G1: 45236 | H1: 45237 | I1: 45238 | J1: 45239 | K1: 45240 | L1: 45241 | M1: 45242 | N1: 45243 | O1: 45244 | P1: 45245 | Q1: 45246 | R1: 45247 | S1: 45248 | T1: 45249 | U1: 45250 | V1: 45251 | W1: 45252 | X1: 45253 | Y1: 45254 | Z1: 45255 | AA1: 45256 | AB1: 45257 | AC1: 45258 | AD1: 45259 | AE1: 45260
A2: DAY | B2: WED | C2: THU | D2: FRI | E2: SAT | F2: SUN | G2: MON | H2: TUE | I2: WED | J2: THU | K2: FRI | L2: SAT | M2: SUN | N2: MON | O2: TUE | P2: WED | Q2: THU | R2: FRI | S2: SAT | T2: SUN | U2: MON | V2: TUE | W2: WED | X2: THU | Y2: FRI | Z2: SAT | AA2: SUN | AB2: MON | AC2: TUE | AD2: WED | AE2: THU
A4: Gross Revenue
A5: Apple Store Sales | B5: 486.89744 | C5: 814.04465 | D5: 739.74443 | E5: 1715.1806 | F5: 1559.7076 | G5: 1055.1993 | H5: 788.2665 | I5: 1004.4706 | J5: 1076.0191 | K5: 1253.7324 | L5: 1647.7231 | M5: 2182.4651 | N5: 848.16916 | O5: 892.46262 | P5: 1067.8864 | Q5: 1037.3426 | R5: 1258.7803 | S5: 1452.8909 | T5: 1760.0101 | U5: 985.97595 | V5: 930.86499 | W5: 588.94055 | X5: 924.14745 | Y5: 1197.6415 | Z5: 1576.0659 | AA5: 1841.4662 | AB5: 921.08585 | AC5: 1026.6748 | AD5: 1109.9303 | AE5: 1514.4123 | AF5: =sum(B5:AE5) -> 35258.198
A6: - Yearly Subscription | B6: 456.09649 | C6: 785.98649 | D6: 699.59172 | E6: 1669.5203 | F6: 1502.0491 | G6: 1006.3345 | H6: 730.33077 | I6: 941.1917 | J6: 1022.9289 | K6: 1214.4833 | L6: 1611.8431 | M6: 2137.5178 | N6: 814.63337 | O6: 846.10787 | P6: 1037.8235 | Q6: 993.87106 | R6: 1231.2245 | S6: 1416.685 | T6: 1726.3203 | U6: 970.71563 | V6: 905.98221 | W6: 546.03638 | X6: 897.23745 | Y6: 1148.8178 | Z6: 1493.5112 | AA6: 1742.6503 | AB6: 872.7233 | AC6: 963.15938 | AD6: 1063.9545 | AE6: 1438.3516 | AF6: =sum(B6:AE6) -> 33887.679
A7: - Monthly Subscription | B7: 30.800946 | C7: 28.05816 | D7: 40.15271 | E7: 45.66029 | F7: 57.658456 | G7: 48.864826 | H7: 57.935735 | I7: 63.278865 | J7: 53.090217 | K7: 39.249014 | L7: 35.88 | M7: 44.947262 | N7: 33.535796 | O7: 46.354749 | P7: 30.062955 | Q7: 43.47153 | R7: 27.555796 | S7: 36.20591 | T7: 33.689825 | U7: 15.26033 | V7: 24.88278 | W7: 42.904179 | X7: 26.91 | Y7: 48.823752 | Z7: 82.554635 | AA7: 98.815893 | AB7: 48.362546 | AC7: 63.515386 | AD7: 45.975735 | AE7: 76.0607 | AF7: =sum(B7:AE7) -> 1370.519
A8: Google Store Sales | B8: 99.62 | C8: 165.88 | D8: 71.14 | E8: 412.73 | F8: 297.94 | G8: 81.15 | H8: 179.72 | I8: 322.51 | J8: 341.54 | K8: 289.96 | L8: 415.35 | M8: 386.59 | N8: 356.13 | O8: 365.22 | P8: 263.21 | Q8: 164.08 | R8: 294.83 | S8: 396.25 | T8: 549.52 | U8: 239.29 | V8: 334.46 | W8: 167.9 | X8: 168.91 | Y8: 328.28 | Z8: 487.35 | AA8: 786.74 | AB8: 397.36 | AC8: 209.04 | AD8: 368.19 | AE8: 193.16 | AF8: =sum(B8:AE8) -> 9134.05
A9: - Yearly Subscription | B9: 93.42 | C9: 159.9 | D9: 64.79 | E9: 389.8 | F9: 291.53 | G9: 62.22 | H9: 160.91 | I9: 296.17 | J9: 328.93 | K9: 286.97 | L9: 408.98 | M9: 376.89 | N9: 346.46 | O9: 358.99 | P9: 249.44 | Q9: 161.09 | R9: 291.59 | S9: 380.3 | T9: 537.08 | U9: 223.5 | V9: 318.29 | W9: 158.44 | X9: 159.28 | Y9: 318.65 | Z9: 474.41 | AA9: 770.79 | AB9: 387.58 | AC9: 189.81 | AD9: 345.83 | AE9: 183.53 | AF9: =sum(B9:AE9) -> 8775.57
A10: - Monthly Subscription | B10: 6.2 | C10: 5.98 | D10: 6.35 | E10: 22.93 | F10: 6.41 | G10: 18.93 | H10: 18.81 | I10: 26.34 | J10: 12.61 | K10: 2.99 | L10: 6.37 | M10: 9.7 | N10: 9.67 | O10: 6.23 | P10: 13.77 | Q10: 2.99 | R10: 3.24 | S10: 15.95 | T10: 12.44 | U10: 15.79 | V10: 16.17 | W10: 9.46 | X10: 9.63 | Y10: 9.63 | Z10: 12.94 | AA10: 15.95 | AB10: 9.78 | AC10: 19.23 | AD10: 22.36 | AE10: 9.63 | AF10: =sum(B10:AE10) -> 358.48
A11: SUM | B11: =sum(B5+B8) -> 586.51744 | C11: =sum(C5+C8) -> 979.92465 | D11: =sum(D5+D8) -> 810.88444 | E11: =sum(E5+E8) -> 2127.9106 | F11: =sum(F5+F8) -> 1857.6476 | G11: =sum(G5+G8) -> 1136.3493 | H11: =sum(H5+H8) -> 967.9865 | I11: =sum(I5+I8) -> 1326.9806 | ... AE11: =sum(AE5+AE8) -> 1707.5723 | AF11: =sum(B11:AE11) -> 44392.248
A13: Gross Orders
A14: Apple Store Orders | B14: =sum(B15:B16) -> 25 | C14: =sum(C15:C16) -> 35 | D14: =sum(D15:D16) -> 36 | E14: =sum(E15:E16) -> 70 | F14: =sum(F15:F16) -> 70 | G14: =sum(G15:G16) -> 49 | H14: =sum(H15:H16) -> 43 | I14: =sum(I15:I16) -> 52 | ... AE14: =sum(AE15:AE16) -> 74 | AF14: =sum(B14:AE14) -> 1574
A15: - Yearly Subscription | B15: 15 | C15: 26 | D15: 23 | E15: 55 | F15: 51 | G15: 33 | H15: 24 | I15: 31 | J15: 34 | K15: 40 | L15: 53 | M15: 72 | N15: 27 | O15: 28 | P15: 34 | Q15: 33 | R15: 41 | S15: 47 | T15: 57 | U15: 32 | V15: 30 | W15: 18 | X15: 30 | Y15: 38 | Z15: 49 | AA15: 58 | AB15: 29 | AC15: 32 | AD15: 35 | AE15: 49 | AF15: =sum(B15:AE15) -> 1124
A16: - Monthly Subscription | B16: 10 | C16: 9 | D16: 13 | E16: 15 | F16: 19 | G16: 16 | H16: 19 | I16: 21 | J16: 17 | K16: 13 | L16: 12 | M16: 15 | N16: 11 | O16: 15 | P16: 10 | Q16: 14 | R16: 9 | S16: 12 | T16: 11 | U16: 5 | V16: 8 | W16: 14 | X16: 9 | Y16: 16 | Z16: 27 | AA16: 33 | AB16: 16 | AC16: 21 | AD16: 15 | AE16: 25 | AF16: =sum(B16:AE16) -> 450
A17: Google Store Orders | B17: =sum(B18:B19) -> 5 | C17: =sum(C18:C19) -> 7 | D17: =sum(D18:D19) -> 4 | E17: =sum(E18:E19) -> 19 | F17: =sum(F18:F19) -> 11 | G17: =sum(G18:G19) -> 8 | H17: =sum(H18:H19) -> 11 | I17: =sum(I18:I19) -> 17 | ... AE17: =sum(AE18:AE19) -> 9 | AF17: =sum(B17:AE17) -> 389
A18: - Yearly Subscription | B18: 3 | C18: 5 | D18: 2 | E18: 12 | F18: 9 | G18: 2 | H18: 5 | I18: 9 | J18: 10 | K18: 9 | L18: 13 | M18: 12 | N18: 11 | O18: 11 | P18: 8 | Q18: 7 | R18: 9 | S18: 12 | T18: 17 | U18: 7 | V18: 10 | W18: 5 | X18: 5 | Y18: 10 | Z18: 15 | AA18: 24 | AB18: 12 | AC18: 6 | AD18: 11 | AE18: 6 | AF18: =sum(B18:AE18) -> 277
A19: - Monthly Subscription | B19: 2 | C19: 2 | D19: 2 | E19: 7 | F19: 2 | G19: 6 | H19: 6 | I19: 8 | J19: 4 | K19: 1 | L19: 2 | M19: 3 | N19: 3 | O19: 2 | P19: 4 | Q19: 1 | R19: 1 | S19: 5 | T19: 4 | U19: 5 | V19: 5 | W19: 3 | X19: 3 | Y19: 3 | Z19: 4 | AA19: 5 | AB19: 3 | AC19: 6 | AD19: 7 | AE19: 3 | AF19: =sum(B19:AE19) -> 112
A20: SUM | B20: =sum(B14+B17) -> 30 | C20: =sum(C14+C17) -> 42 | D20: =sum(D14+D17) -> 40 | E20: =sum(E14+E17) -> 89 | F20: =sum(F14+F17) -> 81 | G20: =sum(G14+G17) -> 57 | H20: =sum(H14+H17) -> 54 | I20: =sum(I14+I17) -> 69 | ... AE20: =sum(AE14+AE17) -> 83 | AF20: =sum(B20:AE20) -> 1963
A21: - Yearly Subscription | B21: =B15+B18 -> 18 | C21: =C15+C18 -> 31 | D21: =D15+D18 -> 25 | E21: =E15+E18 -> 67 | F21: =F15+F18 -> 60 | G21: =G15+G18 -> 35 | H21: =H15+H18 -> 29 | I21: =I15+I18 -> 40 | ... AE21: =AE15+AE18 -> 55 | AF21: =sum(B21:AE21) -> 1401
A22: - Monthly Subscription | B22: =B16+B19 -> 12 | C22: =C16+C19 -> 11 | D22: =D16+D19 -> 15 | E22: =E16+E19 -> 22 | F22: =F16+F19 -> 21 | G22: =G16+G19 -> 22 | H22: =H16+H19 -> 25 | I22: =I16+I19 -> 29 | ... AE22: =AE16+AE19 -> 28 | AF22: =sum(B22:AE22) -> 562
A24: Refunded Revenue
A25: Apple Store Sales | B25: =sum(B26:B27) -> 0 | C25: =sum(C26:C27) -> 0 | D25: =sum(D26:D27) -> 0 | E25: =sum(E26:E27) -> 0 | F25: =sum(F26:F27) -> 14.99 | G25: =sum(G26:G27) -> 0 | H25: =sum(H26:H27) -> 0 | I25: =sum(I26:I27) -> 0 | ... AE25: =sum(AE26:AE27) -> 31.624 | AF25: =sum(B25:AE25) -> 76.604
A26: - Yearly Subscription | B26: 0 | C26: 0 | D26: 0 | E26: 0 | F26: 14.99 | G26: 0 | H26: 0 | I26: 0 | J26: 0 | K26: 0 | L26: 0 | M26: 29.99 | N26: 0 | O26: 0 | P26: 0 | Q26: 0 | R26: 0 | S26: 0 | T26: 0 | U26: 0 | V26: 0 | W26: 0 | X26: 0 | Y26: 0 | Z26: 0 | AA26: 0 | AB26: 0 | AC26: 0 | AD26: 0 | AE26: 31.624 | AF26: =sum(B26:AE26) -> 76.604
A27: - Monthly Subscription | B27: 0 | C27: 0 | D27: 0 | E27: 0 | F27: 0 | G27: 0 | H27: 0 | I27: 0 | J27: 0 | K27: 0 | L27: 0 | M27: 0 | N27: 0 | O27: 0 | P27: 0 | Q27: 0 | R27: 0 | S27: 0 | T27: 0 | U27: 0 | V27: 0 | W27: 0 | X27: 0 | Y27: 0 | Z27: 0 | AA27: 0 | AB27: 0 | AC27: 0 | AD27: 0 | AE27: 0 | AF27: =sum(B27:AE27) -> 0
A28: Google Store Sales | B28: =sum(B29:B30) -> 0 | C28: =sum(C29:C30) -> 0 | D28: =sum(D29:D30) -> 0 | E28: =sum(E29:E30) -> 0 | F28: =sum(F29:F30) -> 0 | G28: =sum(G29:G30) -> 0 | H28: =sum(H29:H30) -> 0 | I28: =sum(I29:I30) -> 0 | ... AE28: =sum(AE29:AE30) -> 0 | AF28: =sum(B28:AE28) -> 29.99
A29: - Yearly Subscription | B29: 0 | C29: 0 | D29: 0 | E29: 0 | F29: 0 | G29: 0 | H29: 0 | I29: 0 | J29: 0 | K29: 0 | L29: 0 | M29: 0 | N29: 0 | O29: 0 | P29: 0 | Q29: 29.99 | R29: 0 | S29: 0 | T29: 0 | U29: 0 | V29: 0 | W29: 0 | X29: 0 | Y29: 0 | Z29: 0 | AA29: 0 | AB29: 0 | AC29: 0 | AD29: 0 | AE29: 0 | AF29: =sum(B29:AE29) -> 29.99
A30: - Monthly Subscription | B30: 0 | C30: 0 | D30: 0 | E30: 0 | F30: 0 | G30: 0 | H30: 0 | I30: 0 | J30: 0 | K30: 0 | L30: 0 | M30: 0 | N30: 0 | O30: 0 | P30: 0 | Q30: 0 | R30: 0 | S30: 0 | T30: 0 | U30: 0 | V30: 0 | W30: 0 | X30: 0 | Y30: 0 | Z30: 0 | AA30: 0 | AB30: 0 | AC30: 0 | AD30: 0 | AE30: 0 | AF30: =sum(B30:AE30) -> 0
A31: SUM | B31: =B25+B28 -> 0 | C31: =C25+C28 -> 0 | D31: =D25+D28 -> 0 | E31: =E25+E28 -> 0 | F31: =F25+F28 -> 14.99 | G31: =G25+G28 -> 0 | H31: =H25+H28 -> 0 | I31: =I25+I28 -> 0 | ... AE31: =AE25+AE28 -> 31.624 | AF31: =sum(B31:AE31) -> 106.594
A33: Refunded Orders
A34: Apple Store orders | B34: =sum(B35:B36) -> 0 | C34: =sum(C35:C36) -> 0 | D34: =sum(D35:D36) -> 0 | E34: =sum(E35:E36) -> 0 | F34: =sum(F35:F36) -> 1 | G34: =sum(G35:G36) -> 0 | H34: =sum(H35:H36) -> 0 | I34: =sum(I35:I36) -> 0 | ... AE34: =sum(AE35:AE36) -> 1 | AF34: =sum(B34:AE34) -> 3
A35: - Yearly Subscription | B35: 0 | C35: 0 | D35: 0 | E35: 0 | F35: 1 | G35: 0 | H35: 0 | I35: 0 | J35: 0 | K35: 0 | L35: 0 | M35: 1 | N35: 0 | O35: 0 | P35: 0 | Q35: 0 | R35: 0 | S35: 0 | T35: 0 | U35: 0 | V35: 0 | W35: 0 | X35: 0 | Y35: 0 | Z35: 0 | AA35: 0 | AB35: 0 | AC35: 0 | AD35: 0 | AE35: 1
A36: - Monthly Subscription | B36: 0 | C36: 0 | D36: 0 | E36: 0 | F36: 0 | G36: 0 | H36: 0 | I36: 0 | J36: 0 | K36: 0 | L36: 0 | M36: 0 | N36: 0 | O36: 0 | P36: 0 | Q36: 0 | R36: 0 | S36: 0 | T36: 0 | U36: 0 | V36: 0 | W36: 0 | X36: 0 | Y36: 0 | Z36: 0 | AA36: 0 | AB36: 0 | AC36: 0 | AD36: 0 | AE36: 0
A37: Google Store orders | B37: =sum(B38:B39) -> 0 | C37: =sum(C38:C39) -> 0 | D37: =sum(D38:D39) -> 0 | E37: =sum(E38:E39) -> 0 | F37: =sum(F38:F39) -> 0 | G37: =sum(G38:G39) -> 0 | H37: =sum(H38:H39) -> 0 | I37: =sum(I38:I39) -> 0 | ... AE37: =sum(AE38:AE39) -> 0 | AF37: =sum(B37:AE37) -> 2
A38: - Yearly Subscription | B38: 0 | C38: 0 | D38: 0 | E38: 0 | F38: 0 | G38: 0 | H38: 0 | I38: 0 | J38: 0 | K38: 0 | L38: 0 | M38: 0 | N38: 0 | O38: 0 | P38: 0 | Q38: 2 | R38: 0 | S38: 0 | T38: 0 | U38: 0 | V38: 0 | W38: 0 | X38: 0 | Y38: 0 | Z38: 0 | AA38: 0 | AB38: 0 | AC38: 0 | AD38: 0 | AE38: 0
A39: - Monthly Subscription | B39: 0 | C39: 0 | D39: 0 | E39: 0 | F39: 0 | G39: 0 | H39: 0 | I39: 0 | J39: 0 | K39: 0 | L39: 0 | M39: 0 | N39: 0 | O39: 0 | P39: 0 | Q39: 0 | R39: 0 | S39: 0 | T39: 0 | U39: 0 | V39: 0 | W39: 0 | X39: 0 | Y39: 0 | Z39: 0 | AA39: 0 | AB39: 0 | AC39: 0 | AD39: 0 | AE39: 0
A40: SUM | B40: =B34+B37 -> 0 | C40: =C34+C37 -> 0 | D40: =D34+D37 -> 0 | E40: =E34+E37 -> 0 | F40: =F34+F37 -> 1 | G40: =G34+G37 -> 0 | H40: =H34+H37 -> 0 | I40: =I34+I37 -> 0 | ... AE40: =AE34+AE37 -> 1 | AF40: =sum(B40:AE40) -> 5
A42: Net Revenue
A43: Apple Store | B43: =B5-B25 -> 486.89744 | C43: =C5-C25 -> 814.04465 | D43: =D5-D25 -> 739.74443 | E43: =E5-E25 -> 1715.1806 | F43: =F5-F25 -> 1544.7176 | G43: =G5-G25 -> 1055.1993 | H43: =H5-H25 -> 788.2665 | I43: =I5-I25 -> 1004.4706 | ... AE43: =AE5-AE25 -> 1482.7883 | AF43: =sum(B43:AE43) -> 35181.594
A44: - Yearly Subscription | B44: =B6-B26 -> 456.09649 | C44: =C6-C26 -> 785.98649 | D44: =D6-D26 -> 699.59172 | E44: =E6-E26 -> 1669.5203 | F44: =F6-F26 -> 1487.0591 | G44: =G6-G26 -> 1006.3345 | H44: =H6-H26 -> 730.33077 | I44: =I6-I26 -> 941.1917 | ... AE44: =AE6-AE26 -> 1406.7276 | AF44: =sum(B44:AE44) -> 33811.075
A45: - Monthly Subscription | B45: =B7-B27 -> 30.800946 | C45: =C7-C27 -> 28.05816 | D45: =D7-D27 -> 40.15271 | E45: =E7-E27 -> 45.66029 | F45: =F7-F27 -> 57.658456 | G45: =G7-G27 -> 48.864826 | H45: =H7-H27 -> 57.935735 | I45: =I7-I27 -> 63.278865 | ... AE45: =AE7-AE27 -> 76.0607 | AF45: =sum(B45:AE45) -> 1370.519
A46: Google Store | B46: =B8-B28 -> 99.62 | C46: =C8-C28 -> 165.88 | D46: =D8-D28 -> 71.14 | E46: =E8-E28 -> 412.73 | F46: =F8-F28 -> 297.94 | G46: =G8-G28 -> 81.15 | H46: =H8-H28 -> 179.72 | I46: =I8-I28 -> 322.51 | ... AE46: =AE8-AE28 -> 193.16 | AF46: =sum(B46:AE46) -> 9104.06
A47: - Yearly Subscription | B47: =B9-B29 -> 93.42 | C47: =C9-C29 -> 159.9 | D47: =D9-D29 -> 64.79 | E47: =E9-E29 -> 389.8 | F47: =F9-F29 -> 291.53 | G47: =G9-G29 -> 62.22 | H47: =H9-H29 -> 160.91 | I47: =I9-I29 -> 296.17 | ... AE47: =AE9-AE29 -> 183.53 | AF47: =sum(B47:AE47) -> 8745.58
A48: - Monthly Subscription | B48: =B10-B30 -> 6.2 | C48: =C10-C30 -> 5.98 | D48: =D10-D30 -> 6.35 | E48: =E10-E30 -> 22.93 | F48: =F10-F30 -> 6.41 | G48: =G10-G30 -> 18.93 | H48: =H10-H30 -> 18.81 | I48: =I10-I30 -> 26.34 | ... AE48: =AE10-AE30 -> 9.63 | AF48: =sum(B48:AE48) -> 358.48
A49: SUM | B49: =B43+B46 -> 586.51744 | C49: =C43+C46 -> 979.92465 | D49: =D43+D46 -> 810.88444 | E49: =E43+E46 -> 2127.9106 | F49: =F43+F46 -> 1842.6576 | G49: =G43+G46 -> 1136.3493 | H49: =H43+H46 -> 967.9865 | I49: =I43+I46 -> 1326.9806 | ... AE49: =AE43+AE46 -> 1675.9483 | AF49: =sum(B49:AE49) -> 44285.654
A51: Net Orders
A52: Apple Store | B52: =B14-B34 -> 25 | C52: =C14-C34 -> 35 | D52: =D14-D34 -> 36 | E52: =E14-E34 -> 70 | F52: =F14-F34 -> 69 | G52: =G14-G34 -> 49 | H52: =H14-H34 -> 43 | I52: =I14-I34 -> 52 | ... AE52: =AE14-AE34 -> 73 | AF52: =sum(B52:AE52) -> 1571
A53: - Yearly Subscription | B53: =B15-B35 -> 15 | C53: =C15-C35 -> 26 | D53: =D15-D35 -> 23 | E53: =E15-E35 -> 55 | F53: =F15-F35 -> 50 | G53: =G15-G35 -> 33 | H53: =H15-H35 -> 24 | I53: =I15-I35 -> 31 | ... AE53: =AE15-AE35 -> 48 | AF53: =sum(B53:AE53) -> 1121
A54: - Monthly Subscription | B54: =B16-B36 -> 10 | C54: =C16-C36 -> 9 | D54: =D16-D36 -> 13 | E54: =E16-E36 -> 15 | F54: =F16-F36 -> 19 | G54: =G16-G36 -> 16 | H54: =H16-H36 -> 19 | I54: =I16-I36 -> 21 | ... AE54: =AE16-AE36 -> 25 | AF54: =sum(B54:AE54) -> 450
A55: Google Store | B55: =B17-B37 -> 5 | C55: =C17-C37 -> 7 | D55: =D17-D37 -> 4 | E55: =E17-E37 -> 19 | F55: =F17-F37 -> 11 | G55: =G17-G37 -> 8 | H55: =H17-H37 -> 11 | I55: =I17-I37 -> 17 | ... AE55: =AE17-AE37 -> 9 | AF55: =sum(B55:AE55) -> 387
A56: - Yearly Subscription | B56: =B18-B38 -> 3 | C56: =C18-C38 -> 5 | D56: =D18-D38 -> 2 | E56: =E18-E38 -> 12 | F56: =F18-F38 -> 9 | G56: =G18-G38 -> 2 | H56: =H18-H38 -> 5 | I56: =I18-I38 -> 9 | ... AE56: =AE18-AE38 -> 6 | AF56: =sum(B56:AE56) -> 275
A57: - Monthly Subscription | B57: =B19-B39 -> 2 | C57: =C19-C39 -> 2 | D57: =D19-D39 -> 2 | E57: =E19-E39 -> 7 | F57: =F19-F39 -> 2 | G57: =G19-G39 -> 6 | H57: =H19-H39 -> 6 | I57: =I19-I39 -> 8 | ... AE57: =AE19-AE39 -> 3 | AF57: =sum(B57:AE57) -> 112
A58: SUM | B58: =B52+B55 -> 30 | C58: =C52+C55 -> 42 | D58: =D52+D55 -> 40 | E58: =E52+E55 -> 89 | F58: =F52+F55 -> 80 | G58: =G52+G55 -> 57 | H58: =H52+H55 -> 54 | I58: =I52+I55 -> 69 | ... AE58: =AE52+AE55 -> 82 | AF58: =sum(B58:AE58) -> 1958
A62: Commision Fees & Taxes
A63: Estimated Apple Store Commision Fee (30%) --> check again after 1. mil. | B63: =B5*0.3 -> 146.06923 | C63: =C5*0.3 -> 244.2134 | D63: =D5*0.3 -> 221.92333 | E63: =E5*0.3 -> 514.55417 | F63: =F5*0.3 -> 467.91228 | G63: =G5*0.3 -> 316.5598 | H63: =H5*0.3 -> 236.47995 | I63: =I5*0.3 -> 301.34117 | ... AE63: =AE5*0.3 -> 454.3237 | AF63: =SUM(B63:AE63) -> 10577.46
A64: Estimated Apple Store Taxes | B64: 1.09 | C64: 11.53 | D64: 13.14 | E64: 28.87 | F64: 10.86 | G64: 23.3 | H64: 11.57 | I64: 14.89 | J64: 9.53 | K64: 21.96 | L64: 24.58 | M64: 24.99 | N64: 12.35 | O64: 1.62 | P64: 22.89 | Q64: 24.27 | R64: 0.88 | S64: 10.94 | T64: 23.04 | U64: 5.51 | V64: 11.21 | W64: 11.4 | X64: 6.69 | Y64: 12.79 | Z64: 35.61 | AA64: 19.56 | AB64: 5.31 | AC64: 2.71 | AD64: 19.46 | AE64: 1.41 | AF64: =SUM(B64:AE64) -> 423.96
A65: Estimated Google Store Commision Fee (15%) --> check again after 1. mil. | B65: =B8*0.15 -> 14.943 | C65: =C8*0.15 -> 24.882 | D65: =D8*0.15 -> 10.671 | E65: =E8*0.15 -> 61.9095 | F65: =F8*0.15 -> 44.691 | G65: =G8*0.15 -> 12.1725 | H65: =H8*0.15 -> 26.958 | I65: =I8*0.15 -> 48.3765 | ... AE65: =AE8*0.15 -> 28.974 | AF65: =SUM(B65:AE65) -> 1370.1075
A66: Estimated Google Store Taxes | B66: 0 | C66: 0 | D66: 0 | E66: 1.2 | F66: 11.33 | G66: 11.31 | H66: 0.53 | I66: 19.39 | J66: 20.36 | K66: 17.3 | L66: 0.51 | M66: 1.27 | N66: 11.63 | O66: 18.07 | P66: 7.19 | Q66: 6.21 | R66: 7.56 | S66: 14.68 | T66: 5.68 | U66: 7.25 | V66: 1.13 | W66: 7.22 | X66: 6.91 | Y66: 6.2 | Z66: 1.05 | AA66: 39.37 | AB66: 10.93 | AC66: 6.05 | AD66: 17.82 | AE66: 5.26 | AF66: =SUM(B66:AE66) -> 263.41
A67: Estimated SUM Store Commision Fees | B67: =B63+B65 -> 161.01223 | C67: =C63+C65 -> 269.0954 | D67: =D63+D65 -> 232.59433 | E67: =E63+E65 -> 576.46367 | F67: =F63+F65 -> 512.60328 | G67: =G63+G65 -> 328.7323 | H67: =H63+H65 -> 263.43795 | I67: =I63+I65 -> 349.71767 | ... AE67: =AE63+AE65 -> 483.2977 | AF67: =SUM(B67:AE67) -> 11947.567
A68: Estimated SUM Store Taxes | B68: =B64+B66 -> 1.09 | C68: =C64+C66 -> 11.53 | D68: =D64+D66 -> 13.14 | E68: =E64+E66 -> 30.07 | F68: =F64+F66 -> 22.19 | G68: =G64+G66 -> 34.61 | H68: =H64+H66 -> 12.1 | I68: =I64+I66 -> 34.28 | ... AE68: =AE64+AE66 -> 6.67 | AF68: =SUM(B68:AE68) -> 687.37
A70: Advertising
A71: Meta Spend | B71: =Summary!B95 -> 0 | C71: =Summary!C95 -> 0 | D71: =Summary!D95 -> 0 | E71: =Summary!E95 -> 0 | F71: =Summary!F95 -> 0 | G71: =Summary!G95 -> 0 | H71: =Summary!H95 -> 0 | I71: =Summary!I95 -> 0 | ... AE71: =Summary!AE95 -> 0 | AF71: =SUM(B71:AE71) -> 4.6435072
A72: Apple Spend | B72: =Summary!B96 -> 20.37 | C72: =Summary!C96 -> 12.66 | D72: =Summary!D96 -> 20.86 | E72: =Summary!E96 -> 20.81 | F72: =Summary!F96 -> 46.99 | G72: =Summary!G96 -> 26.18 | H72: =Summary!H96 -> 21.19 | I72: =Summary!I96 -> 17.85 | ... AE72: =Summary!AE96 -> 13.09 | AF72: =SUM(B72:AE72) -> 617.77
A73: Google Spend | B73: =Summary!B97 | C73: =Summary!C97 | D73: =Summary!D97 | E73: =Summary!E97 | F73: =Summary!F97 | G73: =Summary!G97 | H73: =Summary!H97 | I73: =Summary!I97 | ... AE73: =Summary!AE97 | AF73: =SUM(B73:AE73) -> 0
A74: SUM | B74: =SUM(B71:B73) -> 20.37 | C74: =SUM(C71:C73) -> 12.66 | D74: =SUM(D71:D73) -> 20.86 | E74: =SUM(E71:E73) -> 20.81 | F74: =SUM(F71:F73) -> 46.99 | G74: =SUM(G71:G73) -> 26.18 | H74: =SUM(H71:H73) -> 21.19 | I74: =SUM(I71:I73) -> 17.85 | ... AE74: =SUM(AE71:AE73) -> 13.09
A76: Estimated Subscription Profit
A77: - Estimated Apple Store profit | B77: =B43-B63-B64-B72-(B71*'Data - P&L'!$I$24) -> 319.36821 | C77: =C43-C63-C64-C72-(C71*'Data - P&L'!$I$24) -> 545.64126 | D77: =D43-D63-D64-D72-(D71*'Data - P&L'!$I$24) -> 483.8211 | E77: =E43-E63-E64-E72-(E71*'Data - P&L'!$I$24) -> 1150.9464 | F77: =F43-F63-F64-F72-(F71*'Data - P&L'!$I$24) -> 1018.9553 | G77: =G43-G63-G64-G72-(G71*'Data - P&L'!$I$24) -> 689.15954 | H77: =H43-H63-H64-H72-(H71*'Data - P&L'!$I$24) -> 519.02655 | I77: =I43-I63-I64-I72-(I71*'Data - P&L'!$I$24) -> 670.3894 | ... AE77: =AE43-AE63-AE64-AE72-(AE71*'Data - P&L'!$I$24) -> 1013.9646 | AF77: =sum(B77:AE77) -> 23558.69
A78: - Estimated Google Store profit | B78: =B46-B65-B66-B73-(B71*'Data - P&L'!$I$25) -> 84.677 | C78: =C46-C65-C66-C73-(C71*'Data - P&L'!$I$25) -> 140.998 | D78: =D46-D65-D66-D73-(D71*'Data - P&L'!$I$25) -> 60.469 | E78: =E46-E65-E66-E73-(E71*'Data - P&L'!$I$25) -> 349.6205 | F78: =F46-F65-F66-F73-(F71*'Data - P&L'!$I$25) -> 241.919 | G78: =G46-G65-G66-G73-(G71*'Data - P&L'!$I$25) -> 57.6675 | H78: =H46-H65-H66-H73-(H71*'Data - P&L'!$I$25) -> 152.232 | I78: =I46-I65-I66-I73-(I71*'Data - P&L'!$I$25) -> 254.7435 | ... AE78: =AE46-AE65-AE66-AE73-(AE71*'Data - P&L'!$I$25) -> 158.926 | AF78: =sum(B78:AE78) -> 7469.6138
A79: Estimated SUM Profit | B79: =sum(B77:B78) -> 404.04521 | C79: =sum(C77:C78) -> 686.63926 | D79: =sum(D77:D78) -> 544.2901 | E79: =sum(E77:E78) -> 1500.5669 | F79: =sum(F77:F78) -> 1260.8743 | G79: =sum(G77:G78) -> 746.82704 | H79: =sum(H77:H78) -> 671.25855 | I79: =sum(I77:I78) -> 925.1329 | ... AE79: =sum(AE77:AE78) -> 1172.8906 | AF79: =sum(B79:AE79) -> 31028.304
A82: Gross Revenue
A83: =SUM(B11:AE11) -> 44392.248
A84: Gross Sales Profit
A85: =SUM(B79:AE79) -> 31028.304
A86: Gross Sales Margin
A87: =A85/A83 -> 0.6989577
A89: For summary
A90: Google | B90: =B8-B65-B66 -> 84.677 | C90: =C8-C65-C66 -> 140.998 | D90: =D8-D65-D66 -> 60.469 | E90: =E8-E65-E66 -> 349.6205 | F90: =F8-F65-F66 -> 241.919 | G90: =G8-G65-G66 -> 57.6675 | H90: =H8-H65-H66 -> 152.232 | I90: =I8-I65-I66 -> 254.7435 | ... AE90: =AE8-AE65-AE66 -> 158.926
A91: Apple | B91: =B5-B63-B64 -> 339.73821 | C91: =C5-C63-C64 -> 558.30126 | D91: =D5-D63-D64 -> 504.6811 | E91: =E5-E63-E64 -> 1171.7564 | F91: =F5-F63-F64 -> 1080.9353 | G91: =G5-G63-G64 -> 715.33954 | H91: =H5-H63-H64 -> 540.21655 | I91: =I5-I63-I64 -> 688.2394 | ... AE91: =AE5-AE63-AE64 -> 1058.6786

Sheet Digital Marketplaces
A1: NOVEMBER | B1: 45231 | C1: 45232 | D1: 45233 | E1: 45234 | F1: 45235 | G1: 45236 | H1: 45237 | I1: 45238 | J1: 45239 | K1: 45240 | L1: 45241 | M1: 45242 | N1: 45243 | O1: 45244 | P1: 45245 | Q1: 45246 | R1: 45247 | S1: 45248 | T1: 45249 | U1: 45250 | V1: 45251 | W1: 45252 | X1: 45253 | Y1: 45254 | Z1: 45255 | AA1: 45256 | AB1: 45257 | AC1: 45258 | AD1: 45259 | AE1: 45321
A2: DAY | B2: MON | C2: TUE | D2: WED | E2: THU | F2: FRI | G2: SAT | H2: SUN | I2: MON | J2: TUE | K2: WED | L2: THU | M2: FRI | N2: SAT | O2: SUN | P2: MON | Q2: TUE | R2: WED | S2: THU | T2: FRI | U2: SAT | V2: SUN | W2: MON | X2: TUE | Y2: WED | Z2: THU | AA2: FRI | AB2: SAT | AC2: SUN | AD2: MON | AE2: TUE
A3: Rachio (Shopify)
A4: Revenue | B4: =Summary!B22 -> 211.2186 | C4: =Summary!C22 -> 0 | D4: =Summary!D22 -> 0 | E4: =Summary!E22 -> 21715.501 | F4: =Summary!F22 -> 10825.909 | G4: =Summary!G22 -> 47060.884 | H4: =Summary!H22 -> 6559.2291 | I4: =Summary!I22 -> 254.72539 | ... AE4: =Summary!AE22 -> 891.54416 | AF4: =sum(B4:AE4) -> 188200
A5: Breakdown
A6: - Tax | B6: =Summary!B24 -> 12.2186 | C6: =Summary!C24 -> 0 | D6: =Summary!D24 -> 0 | E6: =Summary!E24 -> 1256.201 | F6: =Summary!F24 -> 626.25851 | G6: =Summary!G24 -> 2722.3839 | H6: =Summary!H24 -> 379.43911 | I6: =Summary!I24 -> 14.735386 | ... AE6: =Summary!AE24 -> 51.574158 | AF6: =sum(B6:AE6) -> 10887.017
A7: - Shipping | B7: =Summary!B25 | C7: =Summary!C25 | D7: =Summary!D25 | E7: =Summary!E25 | F7: =Summary!F25 | G7: =Summary!G25 | H7: =Summary!H25 | I7: =Summary!I25 | ... AE7: =Summary!AE25 | AF7: =sum(B7:AE7) -> 0
A8: Orders | B8: =Summary!B58 | C8: =Summary!C58 | D8: =Summary!D58 | E8: =Summary!E58 | F8: =Summary!F58 | G8: =Summary!G58 | H8: =Summary!H58 | I8: =Summary!I58 | ... AE8: =Summary!AE58 | AF8: =sum(B8:AE8) -> 0
A10: Rachio Fees (20%) | B10: =Summary!B89 -> 42.24372 | C10: =Summary!C89 -> 0 | D10: =Summary!D89 -> 0 | E10: =Summary!E89 -> 4343.1002 | F10: =Summary!F89 -> 2165.1817 | G10: =Summary!G89 -> 9412.1768 | H10: =Summary!H89 -> 1311.8458 | I10: =Summary!I89 -> 50.945077 | ... AE10: =Summary!AE89 -> 178.30883
A12: Units Sold (Gross) - Rachio
A13: SKU 1 - Blue | B13: 1 | C13: 0 | D13: 0 | E13: 7 | F13: 5 | G13: 6 | H13: 2 | I13: 1 | J13: 1 | K13: 0 | L13: 0 | M13: 0 | N13: 0 | O13: 0 | P13: 2 | Q13: 1 | R13: 0 | S13: 0 | T13: 0 | U13: 1 | V13: 0 | W13: 0 | X13: 2 | Y13: 2 | Z13: 1 | AA13: 4 | AB13: 5 | AC13: 1 | AD13: 1 | AE13: 1 | AF13: =sum(B13:AE13) -> 44
A14: SKU 2 - Yellow | B14: 0 | C14: 0 | D14: 0 | E14: 3 | F14: 0 | G14: 5 | H14: 0 | I14: 0 | J14: 0 | K14: 0 | L14: 0 | M14: 0 | N14: 0 | O14: 0 | P14: 0 | Q14: 0 | R14: 1 | S14: 0 | T14: 0 | U14: 0 | V14: 0 | W14: 0 | X14: 0 | Y14: 1 | Z14: 0 | AA14: 3 | AB14: 2 | AC14: 1 | AD14: 0 | AE14: 0 | AF14: =sum(B14:AE14) -> 16
A15: SKU 3 - Blue w/ Solar | B15: 0 | C15: 0 | D15: 0 | E15: 43 | F15: 23 | G15: 101 | H15: 13 | I15: 0 | J15: 9 | K15: 3 | L15: 2 | M15: 2 | N15: 1 | O15: 1 | P15: 2 | Q15: 27 | R15: 4 | S15: 5 | T15: 6 | U15: 6 | V15: 5 | W15: 5 | X15: 13 | Y15: 14 | Z15: 2 | AA15: 32 | AB15: 61 | AC15: 23 | AD15: 1 | AE15: 2 | AF15: =sum(B15:AE15) -> 406
A16: SKU 4 - Yellow w/ Solar | B16: 0 | C16: 0 | D16: 0 | E16: 18 | F16: 8 | G16: 38 | H16: 6 | I16: 0 | J16: 1 | K16: 0 | L16: 1 | M16: 2 | N16: 3 | O16: 0 | P16: 3 | Q16: 7 | R16: 1 | S16: 2 | T16: 1 | U16: 1 | V16: 3 | W16: 3 | X16: 2 | Y16: 2 | Z16: 0 | AA16: 14 | AB16: 19 | AC16: 8 | AD16: 2 | AE16: 0 | AF16: =sum(B16:AE16) -> 145
A17: SUM (SKU 1 - SKU 4) | B17: =SUM(B13:B16) -> 1 | C17: =SUM(C13:C16) -> 0 | D17: =SUM(D13:D16) -> 0 | E17: =SUM(E13:E16) -> 71 | F17: =SUM(F13:F16) -> 36 | G17: =SUM(G13:G16) -> 150 | H17: =SUM(H13:H16) -> 21 | I17: =SUM(I13:I16) -> 1 | ... AE17: =SUM(AE13:AE16) -> 3 | AF17: =sum(B17:AE17) -> 611
A19: Wall Mount | B19: 0 | C19: 0 | D19: 0 | E19: 0 | F19: 0 | G19: 0 | H19: 0 | I19: 0 | J19: 0 | K19: 0 | L19: 0 | M19: 0 | N19: 0 | O19: 0 | P19: 0 | Q19: 0 | R19: 0 | S19: 0 | T19: 0 | U19: 0 | V19: 0 | W19: 0 | X19: 0 | Y19: 0 | Z19: 0 | AA19: 0 | AB19: 0 | AC19: 0 | AD19: 0 | AE19: 0 | AF19: =sum(B19:AE19) -> 0
A20: Suet Ball Holder | B20: 0 | C20: 0 | D20: 0 | E20: 0 | F20: 0 | G20: 0 | H20: 0 | I20: 0 | J20: 0 | K20: 0 | L20: 0 | M20: 0 | N20: 0 | O20: 0 | P20: 0 | Q20: 0 | R20: 0 | S20: 0 | T20: 0 | U20: 0 | V20: 0 | W20: 0 | X20: 0 | Y20: 0 | Z20: 0 | AA20: 0 | AB20: 0 | AC20: 0 | AD20: 0 | AE20: 0 | AF20: =sum(B20:AE20) -> 0
A21: 3-in-1 Nutrition Set - Blue | B21: 0 | C21: 0 | D21: 0 | E21: 0 | F21: 0 | G21: 0 | H21: 0 | I21: 0 | J21: 0 | K21: 0 | L21: 0 | M21: 0 | N21: 0 | O21: 0 | P21: 0 | Q21: 0 | R21: 0 | S21: 0 | T21: 0 | U21: 0 | V21: 0 | W21: 0 | X21: 0 | Y21: 0 | Z21: 0 | AA21: 0 | AB21: 0 | AC21: 0 | AD21: 0 | AE21: 0 | AF21: =sum(B21:AE21) -> 0
A22: 3-in-1 Nutrition Set - Yellow | B22: 0 | C22: 0 | D22: 0 | E22: 0 | F22: 0 | G22: 0 | H22: 0 | I22: 0 | J22: 0 | K22: 0 | L22: 0 | M22: 0 | N22: 0 | O22: 0 | P22: 0 | Q22: 0 | R22: 0 | S22: 0 | T22: 0 | U22: 0 | V22: 0 | W22: 0 | X22: 0 | Y22: 0 | Z22: 0 | AA22: 0 | AB22: 0 | AC22: 0 | AD22: 0 | AE22: 0 | AF22: =sum(B22:AE22) -> 0
A23: Solar Roof Single - Blue | B23: 0 | C23: 0 | D23: 0 | E23: 0 | F23: 0 | G23: 0 | H23: 0 | I23: 0 | J23: 0 | K23: 0 | L23: 0 | M23: 0 | N23: 0 | O23: 0 | P23: 0 | Q23: 0 | R23: 0 | S23: 0 | T23: 0 | U23: 0 | V23: 0 | W23: 0 | X23: 0 | Y23: 0 | Z23: 0 | AA23: 0 | AB23: 0 | AC23: 0 | AD23: 0 | AE23: 0 | AF23: =sum(B23:AE23) -> 0
A24: Solar Roof Single - Yellow | B24: 0 | C24: 0 | D24: 0 | E24: 0 | F24: 0 | G24: 0 | H24: 0 | I24: 0 | J24: 0 | K24: 0 | L24: 0 | M24: 0 | N24: 0 | O24: 0 | P24: 0 | Q24: 0 | R24: 0 | S24: 0 | T24: 0 | U24: 0 | V24: 0 | W24: 0 | X24: 0 | Y24: 0 | Z24: 0 | AA24: 0 | AB24: 0 | AC24: 0 | AD24: 0 | AE24: 0 | AF24: =sum(B24:AE24) -> 0
A25: Perch Extender - Blue | B25: 0 | C25: 0 | D25: 0 | E25: 0 | F25: 0 | G25: 0 | H25: 0 | I25: 0 | J25: 0 | K25: 0 | L25: 0 | M25: 0 | N25: 0 | O25: 0 | P25: 0 | Q25: 0 | R25: 0 | S25: 0 | T25: 0 | U25: 0 | V25: 0 | W25: 0 | X25: 0 | Y25: 0 | Z25: 0 | AA25: 0 | AB25: 0 | AC25: 0 | AD25: 0 | AE25: 0 | AF25: =sum(B25:AE25) -> 0
A26: Perch Extender - Yellow | B26: 0 | C26: 0 | D26: 0 | E26: 0 | F26: 0 | G26: 0 | H26: 0 | I26: 0 | J26: 0 | K26: 0 | L26: 0 | M26: 0 | N26: 0 | O26: 0 | P26: 0 | Q26: 0 | R26: 0 | S26: 0 | T26: 0 | U26: 0 | V26: 0 | W26: 0 | X26: 0 | Y26: 0 | Z26: 0 | AA26: 0 | AB26: 0 | AC26: 0 | AD26: 0 | AE26: 0 | AF26: =sum(B26:AE26) -> 0
A27: SUM (Add-ons) | B27: =SUM(B19:B26) -> 0 | C27: =SUM(C19:C26) -> 0 | D27: =SUM(D19:D26) -> 0 | E27: =SUM(E19:E26) -> 0 | F27: =SUM(F19:F26) -> 0 | G27: =SUM(G19:G26) -> 0 | H27: =SUM(H19:H26) -> 0 | I27: =SUM(I19:I26) -> 0 | ... AE27: =SUM(AE19:AE26) -> 0 | AF27: =sum(B27:AE27) -> 0
A29: Units and Revenue Cancelled & Refunds - Rachio
A31: Units Cancelled (Gross) - Rachio
A32: SKU 1 - Blue | AF32: =SUM(B32:AE32) -> 0
A33: SKU 2 - Yellow | AF33: =SUM(B33:AE33) -> 0
A34: SKU 3 - Blue w/ Solar | Y34: 1 | AF34: =SUM(B34:AE34) -> 1
A35: SKU 4 - Yellow w/ Solar | AF35: =SUM(B35:AE35) -> 0
A36: SUM (SKU 1 + SKU 2) | B36: =SUM(B32:B33) -> 0 | C36: =SUM(C32:C33) -> 0 | D36: =SUM(D32:D33) -> 0 | E36: =SUM(E32:E33) -> 0 | F36: =SUM(F32:F33) -> 0 | G36: =SUM(G32:G33) -> 0 | H36: =SUM(H32:H33) -> 0 | I36: =SUM(I32:I33) -> 0 | ... AE36: =SUM(AE32:AE33) -> 0 | AF36: =SUM(B36:AE36) -> 0
A37: SUM (SKU 3 + SKU 4) | B37: =SUM(B34:B35) -> 0 | C37: =SUM(C34:C35) -> 0 | D37: =SUM(D34:D35) -> 0 | E37: =SUM(E34:E35) -> 0 | F37: =SUM(F34:F35) -> 0 | G37: =SUM(G34:G35) -> 0 | H37: =SUM(H34:H35) -> 0 | I37: =SUM(I34:I35) -> 0 | ... AE37: =SUM(AE34:AE35) -> 0 | AF37: =SUM(B37:AE37) -> 1
A39: Wall Mount | AF39: =SUM(B39:AE39) -> 0
A40: Suet Ball Holder | AF40: =SUM(B40:AE40) -> 0
A41: 3-in-1 Nutrition Set - Blue | AF41: =SUM(B41:AE41) -> 0
A42: 3-in-1 Nutrition Set - Yellow | AF42: =SUM(B42:AE42) -> 0
A43: Solar Roof Single - Blue | AF43: =SUM(B43:AE43) -> 0
A44: Solar Roof Single - Yellow | AF44: =SUM(B44:AE44) -> 0
A45: Perch Extender - Blue | AF45: =SUM(B45:AE45) -> 0
A46: Perch Extender - Yellow | AF46: =SUM(B46:AE46) -> 0
A47: SUM (Add-ons) | B47: =SUM(B39:B46) -> 0 | C47: =SUM(C39:C46) -> 0 | D47: =SUM(D39:D46) -> 0 | E47: =SUM(E39:E46) -> 0 | F47: =SUM(F39:F46) -> 0 | G47: =SUM(G39:G46) -> 0 | H47: =SUM(H39:H46) -> 0 | I47: =SUM(I39:I46) -> 0 | ... AE47: =SUM(AE39:AE46) -> 0 | AF47: =SUM(B47:AE47) -> 0
A49: Revenue Cancelled (Gross) - Rachio
A50: Hardware | Y50: 299.99 | AF50: =SUM(B50:AE50) -> 299.99
A51: Shipping | AF51: =SUM(B51:AE51) -> 0
A52: Taxes | AF52: =SUM(B52:AE52) -> 0
A53: All NA | B53: =SUM(B50:B52) -> 0 | C53: =SUM(C50:C52) -> 0 | D53: =SUM(D50:D52) -> 0 | E53: =SUM(E50:E52) -> 0 | F53: =SUM(F50:F52) -> 0 | G53: =SUM(G50:G52) -> 0 | H53: =SUM(H50:H52) -> 0 | I53: =SUM(I50:I52) -> 0 | ... AE53: =SUM(AE50:AE52) -> 0 | AF53: =SUM(B53:AE53) -> 299.99
A55: Hardware - Europe | AF55: =SUM(B55:AE55) -> 0
A56: Shipping - Europe | AF56: =SUM(B56:AE56) -> 0
A57: All EU | B57: =sum(B55:B56) -> 0 | C57: =sum(C55:C56) -> 0 | D57: =sum(D55:D56) -> 0 | E57: =sum(E55:E56) -> 0 | F57: =sum(F55:F56) -> 0 | G57: =sum(G55:G56) -> 0 | H57: =sum(H55:H56) -> 0 | I57: =sum(I55:I56) -> 0 | ... AE57: =sum(AE55:AE56) -> 0 | AF57: =SUM(B57:AE57) -> 0
A59: Units Refund (Gross) - Rachio
A60: SKU 1 - Blue | I60: 1 | O60: 1 | U60: 1 | AF60: =SUM(B60:AE60) -> 3
A61: SKU 2 - Yellow | C61: 1 | I61: 1 | AF61: =SUM(B61:AE61) -> 2
A62: SKU 3 - Blue w/ Solar | I62: 3 | O62: 2 | P62: 1 | X62: 2 | AF62: =SUM(B62:AE62) -> 8
A63: SKU 4 - Yellow w/ Solar | C63: 1 | T63: 1 | X63: 1 | AF63: =SUM(B63:AE63) -> 3
A64: SUM (SKU 1 + SKU 2) | B64: =SUM(B60:B61) -> 0 | C64: =SUM(C60:C61) -> 1 | D64: =SUM(D60:D61) -> 0 | E64: =SUM(E60:E61) -> 0 | F64: =SUM(F60:F61) -> 0 | G64: =SUM(G60:G61) -> 0 | H64: =SUM(H60:H61) -> 0 | I64: =SUM(I60:I61) -> 2 | ... AE64: =SUM(AE60:AE61) -> 0 | AF64: =SUM(B64:AE64) -> 5
A65: SUM (SKU 3 + SKU 4) | B65: =SUM(B62:B63) -> 0 | C65: =SUM(C62:C63) -> 1 | D65: =SUM(D62:D63) -> 0 | E65: =SUM(E62:E63) -> 0 | F65: =SUM(F62:F63) -> 0 | G65: =SUM(G62:G63) -> 0 | H65: =SUM(H62:H63) -> 0 | I65: =SUM(I62:I63) -> 3 | ... AE65: =SUM(AE62:AE63) -> 0 | AF65: =SUM(B65:AE65) -> 11
A67: Wall Mount | C67: 1 | I67: 1 | T67: 1 | U67: 1 | X67: 1 | AF67: =SUM(B67:AE67) -> 5
A68: Suet Ball Holder | C68: 1 | I68: 3 | O68: 1 | U68: 1 | X68: 1 | AF68: =SUM(B68:AE68) -> 7
A69: 3-in-1 Nutrition Set - Blue | D69: 1 | I69: 1 | O69: 1 | AF69: =SUM(B69:AE69) -> 3
A70: 3-in-1 Nutrition Set - Yellow | C70: 1 | AF70: =SUM(B70:AE70) -> 1
A71: Solar Roof Single - Blue | U71: 1 | AF71: =SUM(B71:AE71) -> 1
A72: Solar Roof Single - Yellow | AF72: =SUM(B72:AE72) -> 0
A73: Perch Extender - Blue | AF73: =SUM(B73:AE73) -> 0
A74: Perch Extender - Yellow | AF74: =SUM(B74:AE74) -> 0
A75: SUM (Add-ons) | B75: =SUM(B67:B74) -> 0 | C75: =SUM(C67:C74) -> 3 | D75: =SUM(D67:D74) -> 1 | E75: =SUM(E67:E74) -> 0 | F75: =SUM(F67:F74) -> 0 | G75: =SUM(G67:G74) -> 0 | H75: =SUM(H67:H74) -> 0 | I75: =SUM(I67:I74) -> 5 | ... AE75: =SUM(AE67:AE74) -> 0 | AF75: =SUM(B75:AE75) -> 17
A77: Orders Return for Refund
A79: Revenue Refunded (Gross) - Rachio
A80: Hardware | B80: 0 | C80: 362.98 | D80: 41.73 | E80: 0 | F80: 0 | G80: 0 | H80: 0 | I80: 1429.34 | J80: 0 | K80: 0 | L80: 0 | M80: 0 | N80: 0 | O80: 547.06 | P80: 287.83 | Q80: 0 | R80: 0 | S80: 0 | T80: 309.98 | U80: 340.58 | V80: 299 | W80: 0 | X80: 922.34 | Y80: 0 | Z80: 0 | AA80: 0 | AB80: 0 | AC80: 0 | AD80: 0 | AE80: 0 | AF80: =SUM(B80:AE80) -> 4540.84
A81: Shipping | AF81: =SUM(B81:AE81) -> 0
A82: Taxes | AF82: =SUM(B82:AE82) -> 0
A83: All NA | B83: =sum(B80:B82) -> 0 | C83: =sum(C80:C82) -> 362.98 | D83: =sum(D80:D82) -> 41.73 | E83: =sum(E80:E82) -> 0 | F83: =sum(F80:F82) -> 0 | G83: =sum(G80:G82) -> 0 | H83: =sum(H80:H82) -> 0 | I83: =sum(I80:I82) -> 1429.34 | ... AE83: =sum(AE80:AE82) -> 0 | AF83: =SUM(B83:AE83) -> 4540.84
A85: Hardware - Europe | O85: 326
A86: Shipping - Europe | O86: 35
A87: All EU | B87: =sum(B84:B86) -> 0 | C87: =sum(C84:C86) -> 0 | D87: =sum(D84:D86) -> 0 | E87: =sum(E84:E86) -> 0 | F87: =sum(F84:F86) -> 0 | G87: =sum(G84:G86) -> 0 | H87: =sum(H84:H86) -> 0 | I87: =sum(I84:I86) -> 0 | ... AE87: =sum(AE84:AE86) -> 0 | AF87: =SUM(B87:AE87) -> 361
A89: RETURN (Replacement Units & Claims) - Rachio
A90: SKU 1 - Blue | B90: 0 | C90: 0 | D90: 0 | E90: 0 | F90: 0 | G90: 0 | H90: 0 | I90: 0 | J90: 0 | K90: 0 | L90: 0 | M90: 0 | N90: 0 | O90: 0 | P90: 0 | Q90: 0 | R90: 0 | S90: 0 | T90: 0 | U90: 0 | V90: 0 | W90: 0 | X90: 0 | Y90: 0 | Z90: 0 | AA90: 0 | AB90: 0 | AC90: 0 | AD90: 0 | AE90: 0 | AF90: =SUM(B90:AE90) -> 0
A91: SKU 2 - Yellow | B91: 0 | C91: 0 | D91: 0 | E91: 0 | F91: 0 | G91: 0 | H91: 0 | I91: 0 | J91: 0 | K91: 0 | L91: 0 | M91: 0 | N91: 0 | O91: 0 | P91: 0 | Q91: 0 | R91: 0 | S91: 0 | T91: 0 | U91: 0 | V91: 0 | W91: 0 | X91: 0 | Y91: 0 | Z91: 0 | AA91: 0 | AB91: 0 | AC91: 0 | AD91: 0 | AE91: 0 | AF91: =SUM(B91:AE91) -> 0
A92: SKU 3 - Blue w/ Solar | B92: 0 | C92: 0 | D92: 0 | E92: 0 | F92: 0 | G92: 0 | H92: 0 | I92: 0 | J92: 0 | K92: 0 | L92: 0 | M92: 0 | N92: 0 | O92: 0 | P92: 0 | Q92: 0 | R92: 0 | S92: 0 | T92: 0 | U92: 0 | V92: 0 | W92: 0 | X92: 0 | Y92: 0 | Z92: 0 | AA92: 0 | AB92: 0 | AC92: 0 | AD92: 0 | AE92: 1 | AF92: =SUM(B92:AE92) -> 1
A93: SKU 4 - Yellow w/ Solar | B93: 0 | C93: 0 | D93: 0 | E93: 0 | F93: 0 | G93: 0 | H93: 0 | I93: 0 | J93: 0 | K93: 0 | L93: 0 | M93: 0 | N93: 0 | O93: 0 | P93: 0 | Q93: 0 | R93: 0 | S93: 0 | T93: 0 | U93: 0 | V93: 0 | W93: 0 | X93: 0 | Y93: 0 | Z93: 0 | AA93: 0 | AB93: 0 | AC93: 0 | AD93: 0 | AE93: 0 | AF93: =SUM(B93:AE93) -> 0
A94: SUM (SKU 1 + SKU 2) | B94: =B90+B91 -> 0 | C94: =C90+C91 -> 0 | D94: =D90+D91 -> 0 | E94: =E90+E91 -> 0 | F94: =F90+F91 -> 0 | G94: =G90+G91 -> 0 | H94: =H90+H91 -> 0 | I94: =I90+I91 -> 0 | ... AE94: =AE90+AE91 -> 0 | AF94: =SUM(B94:AE94) -> 0
A95: SUM (SKU 3 + SKU 4) | B95: =B92+B93 -> 0 | C95: =C92+C93 -> 0 | D95: =D92+D93 -> 0 | E95: =E92+E93 -> 0 | F95: =F92+F93 -> 0 | G95: =G92+G93 -> 0 | H95: =H92+H93 -> 0 | I95: =I92+I93 -> 0 | ... AE95: =AE92+AE93 -> 1 | AF95: =SUM(B95:AE95) -> 1
A97: Wall Mount | B97: 0 | C97: 0 | D97: 0 | E97: 0 | F97: 0 | G97: 0 | H97: 0 | I97: 0 | J97: 0 | K97: 0 | L97: 0 | M97: 0 | N97: 0 | O97: 0 | P97: 0 | Q97: 0 | R97: 0 | S97: 0 | T97: 0 | U97: 0 | V97: 0 | W97: 0 | X97: 0 | Y97: 0 | Z97: 0 | AA97: 0 | AB97: 0 | AC97: 0 | AD97: 0 | AE97: 0 | AF97: =SUM(B97:AE97) -> 0
A98: Suet Ball Holder | B98: 0 | C98: 0 | D98: 0 | E98: 0 | F98: 0 | G98: 0 | H98: 0 | I98: 0 | J98: 0 | K98: 0 | L98: 0 | M98: 0 | N98: 0 | O98: 0 | P98: 0 | Q98: 0 | R98: 0 | S98: 0 | T98: 0 | U98: 0 | V98: 0 | W98: 0 | X98: 0 | Y98: 0 | Z98: 0 | AA98: 0 | AB98: 0 | AC98: 0 | AD98: 0 | AE98: 0 | AF98: =SUM(B98:AE98) -> 0
A99: 3-in-1 Nutrition Set - Blue | B99: 0 | C99: 0 | D99: 0 | E99: 0 | F99: 0 | G99: 0 | H99: 0 | I99: 0 | J99: 0 | K99: 0 | L99: 0 | M99: 0 | N99: 0 | O99: 0 | P99: 0 | Q99: 0 | R99: 0 | S99: 0 | T99: 0 | U99: 0 | V99: 0 | W99: 0 | X99: 0 | Y99: 0 | Z99: 0 | AA99: 0 | AB99: 0 | AC99: 0 | AD99: 0 | AE99: 0 | AF99: =SUM(B99:AE99) -> 0
A100: 3-in-1 Nutrition Set - Yellow | B100: 0 | C100: 0 | D100: 0 | E100: 0 | F100: 0 | G100: 0 | H100: 0 | I100: 0 | J100: 0 | K100: 0 | L100: 0 | M100: 0 | N100: 0 | O100: 0 | P100: 0 | Q100: 0 | R100: 0 | S100: 0 | T100: 0 | U100: 0 | V100: 0 | W100: 0 | X100: 0 | Y100: 0 | Z100: 0 | AA100: 0 | AB100: 0 | AC100: 0 | AD100: 0 | AE100: 0 | AF100: =SUM(B100:AE100) -> 0
A101: Solar Roof Single - Blue | B101: 0 | C101: 0 | D101: 0 | E101: 0 | F101: 0 | G101: 0 | H101: 0 | I101: 0 | J101: 0 | K101: 0 | L101: 0 | M101: 0 | N101: 0 | O101: 0 | P101: 0 | Q101: 0 | R101: 0 | S101: 0 | T101: 0 | U101: 0 | V101: 0 | W101: 0 | X101: 0 | Y101: 0 | Z101: 0 | AA101: 0 | AB101: 0 | AC101: 0 | AD101: 0 | AE101: 0 | AF101: =SUM(B101:AE101) -> 0
A102: Solar Roof Single - Yellow | B102: 0 | C102: 0 | D102: 0 | E102: 0 | F102: 0 | G102: 0 | H102: 0 | I102: 0 | J102: 0 | K102: 0 | L102: 0 | M102: 0 | N102: 0 | O102: 0 | P102: 0 | Q102: 0 | R102: 0 | S102: 0 | T102: 0 | U102: 0 | V102: 0 | W102: 0 | X102: 0 | Y102: 0 | Z102: 0 | AA102: 0 | AB102: 0 | AC102: 0 | AD102: 0 | AE102: 0 | AF102: =SUM(B102:AE102) -> 0
A103: Perch Extender - Blue | B103: 0 | C103: 0 | D103: 0 | E103: 0 | F103: 0 | G103: 0 | H103: 0 | I103: 0 | J103: 0 | K103: 0 | L103: 0 | M103: 0 | N103: 0 | O103: 0 | P103: 0 | Q103: 0 | R103: 0 | S103: 0 | T103: 0 | U103: 0 | V103: 0 | W103: 0 | X103: 0 | Y103: 0 | Z103: 0 | AA103: 0 | AB103: 0 | AC103: 0 | AD103: 0 | AE103: 0 | AF103: =SUM(B103:AE103) -> 0
A104: Perch Extender - Yellow | B104: 0 | C104: 0 | D104: 0 | E104: 0 | F104: 0 | G104: 0 | H104: 0 | I104: 0 | J104: 0 | K104: 0 | L104: 0 | M104: 0 | N104: 0 | O104: 0 | P104: 0 | Q104: 0 | R104: 0 | S104: 0 | T104: 0 | U104: 0 | V104: 0 | W104: 0 | X104: 0 | Y104: 0 | Z104: 0 | AA104: 0 | AB104: 0 | AC104: 0 | AD104: 0 | AE104: 0 | AF104: =SUM(B104:AE104) -> 0
A105: SUM (Add-ons) | B105: =SUM(B97:B104) -> 0 | C105: =SUM(C97:C101) -> 0 | D105: =SUM(D97:D101) -> 0 | E105: =SUM(E97:E101) -> 0 | F105: =SUM(F97:F101) -> 0 | G105: =SUM(G97:G101) -> 0 | H105: =SUM(H97:H101) -> 0 | I105: =SUM(I97:I101) -> 0 | J105: =SUM(J97:J101) -> 0 | ... AE105: =SUM(AE97:AE101) -> 0 | AF105: =SUM(B105:AE105) -> 0
A107: Parts
A108: Housing - Blue | B108: 0 | C108: 0 | D108: 0 | E108: 0 | F108: 0 | G108: 0 | H108: 0 | I108: 0 | J108: 0 | K108: 0 | L108: 0 | M108: 0 | N108: 0 | O108: 0 | P108: 0 | Q108: 0 | R108: 0 | S108: 0 | T108: 0 | U108: 0 | V108: 0 | W108: 0 | X108: 0 | Y108: 0 | Z108: 0 | AA108: 0 | AB108: 0 | AC108: 0 | AD108: 0 | AE108: 0 | AF108: =SUM(B108:AE108) -> 0
A109: Housing - Yellow | B109: 0 | C109: 0 | D109: 0 | E109: 0 | F109: 0 | G109: 0 | H109: 0 | I109: 0 | J109: 0 | K109: 0 | L109: 0 | M109: 0 | N109: 0 | O109: 0 | P109: 0 | Q109: 0 | R109: 0 | S109: 0 | T109: 0 | U109: 0 | V109: 0 | W109: 0 | X109: 0 | Y109: 0 | Z109: 0 | AA109: 0 | AB109: 0 | AC109: 0 | AD109: 0 | AE109: 0 | AF109: =SUM(B109:AE109) -> 0
A110: Camera Module | B110: 0 | C110: 0 | D110: 0 | E110: 0 | F110: 0 | G110: 0 | H110: 0 | I110: 0 | J110: 0 | K110: 0 | L110: 0 | M110: 0 | N110: 0 | O110: 0 | P110: 0 | Q110: 0 | R110: 0 | S110: 0 | T110: 0 | U110: 0 | V110: 0 | W110: 0 | X110: 0 | Y110: 0 | Z110: 0 | AA110: 0 | AB110: 0 | AC110: 0 | AD110: 0 | AE110: 0 | AF110: =SUM(B110:AE110) -> 0
A112: Orders Replaced NA | B112: 0 | C112: 0 | D112: 0 | E112: 0 | F112: 0 | G112: 0 | H112: 0 | I112: 0 | J112: 0 | K112: 0 | L112: 0 | M112: 0 | N112: 0 | O112: 0 | P112: 0 | Q112: 0 | R112: 0 | S112: 0 | T112: 0 | U112: 0 | V112: 0 | W112: 0 | X112: 0 | Y112: 0 | Z112: 0 | AA112: 0 | AB112: 0 | AC112: 0 | AD112: 0 | AE112: 1 | AF112: =SUM(B112:AE112) -> 1
A115: Weatherflow (Shopify)
A116: Revenue | AF116: =SUM(B116:AE116) -> 0
A117: Breakdown
A118: - Tax | AF118: =SUM(B118:AE118) -> 0
A119: - Shipping | AF119: =SUM(B119:AE119) -> 0
...

Sheet Data - P&L
B1: Business Metrics
A2: Source | B2: COGS | E2: Attachment Rates | H2: Marketing Averages (per first-time order) | K2: Fees | N2: VAT Averages | Q2: 30 Day Returns | T2: Digital Market Places & B2B
B3: Bird Buddy | C3: 86.9 | D3: 86.9 | E3: Solar Roof | F3: =(('DTC - P&L'!AF83+'DTC - P&L'!AF84)/'DTC - P&L'!AF77) -> 0.022076309 | H3: COGS | I3: =(C3*F9)+(C4*F8)+(C5*F3)+(C6*F4)+(C7*F5)+(C8*F6)+(C9*F7)+(C10*F10) -> 98.412668 | J3: =(D3*F9)+(D4*F8)+(D5*F3)+(D6*F4)+(D7*F5)+(D8*F6)+(D9*F7) -> 97.086599 | K3: Stripe Processing Fee | L3: 0.029 | N3: Europe | O3: 0.22 | Q3: US Shipping | R3: 15 | T3: Average % tax | U3: 0.0614
B4: Bird Buddy with Solar Roof | C4: 97.61 | D4: 97.61 | E4: Wall Mount | F4: =('DTC - P&L'!AF79/'DTC - P&L'!AF77) -> 0.22314108 | H4: Inbound Shipping | I4: =C38+('DTC - P&L'!AF87/'DTC - P&L'!AF77)*D38 -> 13.740486 | K4: Duty | L4: 0.034 | N4: ROW | O4: 0.13 | Q4: EU Shipping | R4: 40
B5: Solar Roof Single | C5: 13.44 | D5: 13.44 | E5: Fence Mount | F5: 0 | H5: Outbound Shipping | I5: =C34+('DTC - P&L'!AF87/'DTC - P&L'!AF77)*D34 -> 34.80791 | K5: China Tax | L5: 0.075 | N5: NA | Q5: ROW Shipping | R5: 20
B6: Wall Mount | C6: 5.49 | D6: 5.49 | E6: Suet Ball Holder | F6: =('DTC - P&L'!AF80/'DTC - P&L'!AF77) -> 0.68120674 | H6: Taxes and VAT | I6: 16.81 | K6: HMF | L6: 0.00125 | Q6: Money Return | R6: 1
B7: Fence Mount | C7: 6.37 | E7: 3-in-1 | F7: =(('DTC - P&L'!AF81+'DTC - P&L'!AF82)/'DTC - P&L'!AF77) -> 0.10725821 | H7: China Tax (7.5%) | I7: 0 | K7: MPF | L7: 0.003464
B8: Suet Ball Holder | C8: 1.19 | D8: 1.19 | E8: Bird Buddy w/ Solar | F8: =(('DTC - P&L'!AF75+'DTC - P&L'!AF76)/'DTC - P&L'!AF77) -> 0.66665484 | H8: Duty (3.4%) | I8: 0 | K8: Solar Roof China Tax | L8: 0.075
B9: 3-in-1 Nutrition Set | C9: 6.66 | D9: 6.66 | E9: Bird Buddy | F9: =1-F8 -> 0.33334516 | H9: Processing Fee (2,90%) | I9: =Summary!B125*L3 -> 6.7606405 | K9: Solar Roof Duty | L9: 0.025
B10: Perch Extender | C10: 6 | E10: Perch Extender | F10: =(('DTC - P&L'!AF85+'DTC - P&L'!AF86)/'DTC - P&L'!AF77) -> 0.22101154 | H10: Transaction Fee ($0.30) | I10: =0.3 -> 0.3 | K10: Chargeback Fee (Stripe) | L10: 15
B11: Avg. Merch Cost | C11: 3.94 | E11: OTHER 2 | H11: OTHER 1
B12: Avg. Merch Cost without Calendar | C12: 14.79 | E12: OTHER 3 | H12: OTHER 2 | K12: Stripe | L12: 0.95
B13: SBF Housing | E13: OTHER 4 | H13: OTHER 3 | K13: Affirm | L13: 0.05
B14: SBF Camera | C14: 51.78 | E14: OTHER 5 | H14: OTHER 4 | K14: Affirm processing fee | L14: 0.0579
H15: All | I15: =SUM(I3:I14) -> 170.8317 | K15: Affirm transaction fee | L15: 0.3
B22: Outbound shipping | C22: Bird buddy | D22: Add-ons | E22: Merch
A23: *w/o CA weight | B23: Outbound (NA) | C23: 18.66 | D23: 12.87 | E23: 5.4 | H23: App Advertising
B24: Outbound (Europe) | C24: 11.94 | D24: 6.16 | H24: Meta Share to Apple Store | I24: 0.8
B25: Outbound (ROW) | C25: 11.94 | D25: 6.16 | H25: Meta Share to Google Store | I25: 0.2
A26: Source | B26: 3PL Costs | C26: 0 | D26: 0
B27: Handling Fee
B28: Serial Capture | C28: 0.1 | D28: 0
B29: Storage | C29: 0.31 | D29: 0.31
B30: Supplies cost | C30: 0 | D30: 0
B31: Pick charge | C31: 0.35 | D31: 0.35
B32: Pollybag cost | C32: 0 | D32: 0
B33: Carton cost | C33: 1.65 | D33: 0.71
B34: Total outbound (NA) | C34: =C26+C23-C27 -> 18.66 | D34: =D26+D23-D27 -> 12.87
B35: Total outbound (Europe) | C35: 15.06 | D35: =D27+D24-D28 -> 6.16
B36: Total outbound (ROW) | C36: 20
A37: Source | B37: Inbound shipping | C37: Bird buddy | D37: Add-ons
B38: Inbound (NA) | C38: 11.94 | D38: 1.435
B39: Inbound (Europe) | C39: 11.94 | D39: 1.44
B40: Inbound (ROW) | C40: 11.94 | D40: 1.44
B42: AMAZON Logistics | C42: Bird buddy | D42: Add-ons
A43: https://docs.google.com/spreadsheets/d/1Dn0q7h1bHxXdG0N9KpcqzFo0tWUWYXOrRX7yxv3G1E0/edit#gid=1264242332 | B43: Inbound | C43: 11.94 | D43: 1.435
A44: =sum(C43:C44) -> 12.18 | B44: Storage Fee | C44: 0.24 | D44: 0.24
A45: =C46 -> 12.94 | B45: AMAZON Fees | C45: Bird buddy
A46: =sum(F43:F45) -> 0 | B46: FBA fee for units | C46: 12.94
B47: FBA fee for addons | C47: 5.7
A48: =C38 -> 11.94 | B48: Sales Fee | C48: 0.15
B49: AMAZON Shipping | C49: Bird buddy
A50: =sum(A43:A48) -> 37.06 | B50: BB units Shipping | C50: 11
B51: Addons Shipping | C51: 6.155
B53: COGS adjustment for DTC
B54: Returns for refunds | C54: 0.25
B55: Returns for replacements | C55: 0.1
B57: COGS adjustment for Amazon
B58: Returns for refunds | C58: 0.5644
B59: Returns for replacements | C59: 0.4603
B61: Amazon Removal Fee
B62: Units | C62: 5.56
B63: Add-ons | C63: 2.2
A66: https://docs.google.com/document/d/1m1D0mcq6_cpIUs4Z2pSMjDX9L4kRSfAwaLu0UKQppIM/edit?usp=sharing | B66: Explanation for Returns, Cancellations, Replacements calculation
A68: https://docs.google.com/spreadsheets/d/1JFD6SusYZSq5MvMm0PnCaYPmLBVKBKvK09yjZIlSFN4/edit#gid=0 | B68: Amazon Modelling for cancelled orders
B69: Discount Price Template for cancelled orders
B70: item-tax | C70: 14.55
B71: shipping-price | C71: 0.55
B72: shipping-tax | C72: 0.01
B73: gift-wrap-price | C73: 0.15
B74: gift-wrap-tax | C74: 0.01
B75: item-promotion-discount | C75: 7.62
B76: ship-promotion-discount | C76: 0.3
B79: B2B
B80: Agency Fee | C80: 0.05 | D80: NET NET
B81: Agency transportation best buy | C81: *Dejan sporoči

Sheet Sales OLD
A1: 45231 | B1: 45231 | C1: 45232 | D1: 45233 | E1: 45234 | F1: 45235 | G1: 45236 | H1: 45237 | I1: 45238 | J1: 45239 | K1: 45240 | L1: 45241 | M1: 45242 | N1: 45243 | O1: 45244 | P1: 45245 | Q1: 45246 | R1: 45247 | S1: 45248 | T1: 45249 | U1: 45250 | V1: 45251 | W1: 45252 | X1: 45253 | Y1: 45254 | Z1: 45255 | AA1: 45256 | AB1: 45257 | AC1: 45258 | AD1: 45259 | AE1: 45260
B2: WED | C2: THU | D2: FRI | E2: SAT | F2: SUN | G2: MON | H2: TUE | I2: WED | J2: THU | K2: FRI | L2: SAT | M2: SUN | N2: MON | O2: TUE | P2: WED | Q2: THU | R2: FRI | S2: SAT | T2: SUN | U2: MON | V2: TUE | W2: WED | X2: THU | Y2: FRI | Z2: SAT | AA2: SUN | AB2: MON | AC2: TUE | AD2: WED | AE2: THU
A3: Weekend Work | B3: Peco | E3: Peco | F3: Peco | L3: Peter | M3: Peter | S3: Peco | T3: Peco | Z3: Peco | AA3: Peco
A4: Notes | B4: Halloween Sale - MAP | N4: Fake Orders | Y4: Accounts hacked
C5: 3in1 Launch | H5: Early Black Friday - MAP | K5: Black Friday Lowest Price Ever communication
I6: BB US Unit Shipping $15 | J6: Merch Launch | L6: Published in WSJ | W6: BF Email | Y6: D-Day | Z6: Fresh ad account | AA6: Main ad account restored | AB6: Amazon out of stock | AC6: Full Pricing is back at 14.00
A8: DTC Revenue | B8: 105020.72 | C8: 113953.5 | D8: 112373.95 | E8: 122012.63 | F8: 137621.08 | G8: 129947.16 | H8: 119378.74 | I8: 123374.05 | J8: 128107.05 | K8: 125767.15 | L8: 165764.54 | M8: 163580.76 | N8: 139679.41 | O8: 146242.75 | P8: 138299.56 | Q8: =124209+657 -> 124866 | R8: 132032.76 | S8: 173798.84 | T8: 178809.93 | U8: 189422.75 | V8: 192933.07 | W8: 283585.27 | X8: 337982.12 | Y8: 931331.57 | Z8: 576853.7 | AA8: 430623.37 | AB8: 664884.74 | AC8: 471886.67 | AD8: 100905.21 | AE8: 92277.49
A9: - Hardware | B9: 85464.76 | C9: 88820.66 | D9: 90446.48 | E9: 98153.77 | F9: 112993.92 | G9: 106383.84 | H9: 97516.45 | I9: 98167.57 | J9: 101938.71 | K9: 100639.74 | L9: 131826.32 | M9: 127839.47 | N9: 101525.29 | O9: 116599.9 | P9: 110332.61 | Q9: 101442.48 | R9: 105209.97 | S9: 139966.95 | T9: 144607.97 | U9: 151866.12 | V9: 155893.26 | W9: 227079.49 | X9: 270370.34 | Y9: 753806.68 | Z9: 471507.63 | AA9: 347284.27 | AB9: 543319.84 | AC9: 389262.7 | AD9: 82929.83 | AE9: 74695.21
A10: - Add-ons | B10: 6707.54 | C10: 10578.54 | D10: 9279.32 | E10: 10715.53 | F10: 9847.38 | G10: 9498.36 | H10: 9096.2 | I10: 10999.63 | J10: 9876.86 | K10: 9386.36 | L10: 13683.98 | M10: 15020.53 | N10: 17668.76 | O10: 10923.86 | P10: 10034.39 | Q10: 10184.52 | R10: 9820.2 | S10: 11848.7 | T10: 11885.53 | U10: 14021.88 | V10: 13308.49 | W10: 21821.66 | X10: 25929.89 | Y10: 63051.85 | Z10: 34117.47 | AA10: 30329.02 | AB10: 39874.1 | AC10: 25164.7 | AD10: 7514.32 | AE10: 7504.93
A11: - Merch | B11: 0 | C11: 0 | D11: 0 | E11: 0 | F11: 0 | G11: 0 | H11: 0 | I11: 0 | J11: 517.02 | K11: 356.89 | L11: 281.81 | M11: 164.95 | N11: 0 | O11: 681.63 | P11: 662.92 | Q11: 844.78 | R11: 636.28 | S11: 271.98 | T11: 215.97 | U11: 185.98 | V11: 275.99 | W11: 406.99 | X11: 338.66 | Y11: 832.65 | Z11: 575.99 | AA11: 256.01 | AB11: 727.96 | AC11: 788.98 | AD11: 114 | AE11: 114
A12: - Taxes | B12: 5548.42 | C12: 6139.3 | D12: 5888.15 | E12: 6828.33 | F12: 7709.78 | G12: 7149.96 | H12: 6456.09 | I12: 6611.85 | J12: 6621.46 | K12: 6504.16 | L12: 8704.43 | M12: 8353.81 | N12: 7160.36 | O12: 7526.36 | P12: 7261.66 | Q12: 6527.8 | R12: 6811.31 | S12: 8611.21 | T12: 9095.46 | U12: 9403.77 | V12: 9730.33 | W12: 13957.13 | X12: 17308.23 | Y12: 49902.39 | Z12: 31157.61 | AA12: 22049.07 | AB12: 36452.84 | AC12: 25785.29 | AD12: 5312.06 | AE12: 5058.35
A13: - Shipping | B13: 7300 | C13: 8415 | D13: 6760 | E13: 6315 | F13: 7070 | G13: 6915 | H13: 6310 | I13: 7595 | J13: 9153 | K13: 8880 | L13: 11178 | M13: 12202 | N13: 13325 | O13: 10511 | P13: 10008 | Q13: 9368 | R13: 9555 | S13: 13100 | T13: 13005 | U13: 13945 | V13: 13725 | W13: 20320 | X13: 24035 | Y13: 63738 | Z13: 39495 | AA13: 30705 | AB13: 44510 | AC13: 30885 | AD13: 5035 | AE13: 4905
A14: Amazon Revenue | B14: 12580 | C14: 10507.85 | D14: 15542.85 | E14: 17880 | F14: 19835.85 | G14: 16025 | H14: 13308.85 | I14: 15064.85 | J14: 32012 | K14: 33438 | L14: 49243.85 | M14: 48555 | N14: 43877 | O14: 47077.85 | P14: 38422.39 | Q14: 41146.2 | R14: 50427.67 | S14: 57317.48 | T14: 39753.74 | U14: 103621.99 | V14: 104751.99 | W14: 116035 | X14: 186615 | Y14: 695815.96 | Z14: 242095 | AA14: 236839 | AB14: 4274.81 | AC14: 55 | AD14: 0 | AE14: 507
A15: - Hardware | B15: 11026 | C15: 9139.05 | D15: 13852.05 | E15: 13997 | F15: 17747.05 | G15: 14245 | H15: 11702.05 | I15: 12294.05 | J15: 23918 | K15: 25386 | L15: 36717.05 | M15: 35445 | N15: 33869 | O15: 35613.05 | P15: 36580.42 | Q15: 39916.21 | R15: 49048.87 | S15: 55751.49 | T15: 37695.84 | U15: 101993.49 | V15: 103016.3 | W15: 115159.5 | X15: 183414 | Y15: 686130.87 | Z15: 238469 | AA15: 233453 | AB15: 3989.81 | AC15: 0 | AD15: 0 | AE15: 478
A16: - Add-ons | B16: 144 | C16: 118.8 | D16: 70.8 | E16: 120 | F16: 118.8 | G16: 120 | H16: 46.8 | I16: 310.8 | J16: 144 | K16: 72 | L16: 286.8 | M16: 240 | N16: 48 | O16: 214.8 | P16: 312 | Q16: 480 | R16: 598.8 | S16: 576 | T16: 677.9 | U16: 911.5 | V16: 928.69 | W16: 815.5 | X16: 1624 | Y16: 4360.09 | Z16: 192 | AA16: 216 | AB16: 0 | AC16: 40 | AD16: 0 | AE16: 29
A17: - Tax | B17: 778.49 | C17: 673.23 | D17: 982.76 | E17: 1052.37 | F17: 1270.94 | G17: 861.92 | H17: 797.33 | I17: 888.51 | J17: 1685.23 | K17: 1807.14 | L17: 2683.44 | M17: 2399.78 | N17: 2372 | O17: 2487.86 | P17: 2613.13 | Q17: 2858.61 | R17: 3389.52 | S17: 3909.66 | T17: 2714.32 | U17: 7191.01 | V17: 7296.11 | W17: 8031.89 | X17: 12933.48 | Y17: 48364.59 | Z17: 16947.62 | AA17: 16638.88 | AB17: 280.33 | AC17: 3.71 | AD17: 0 | AE17: 33.1
A18: - Shipping | B18: 11.79 | C18: 6.99 | D18: 0 | E18: 6.99 | F18: 2.5 | G18: 0 | H18: 0.06 | I18: 15.65 | J18: 6.99 | K18: 13.66 | L18: 6.75 | M18: 13.66 | N18: 24.2 | O18: 6.99 | P18: 32.95 | Q18: 0 | R18: 13.81 | S18: 19.32 | T18: 61.1 | U18: 50.82 | V18: 206.64 | W18: 73.98 | X18: 152.27 | Y18: 402.43 | Z18: 113.32 | AA18: 1116.9 | AB18: 285 | AC18: 15 | AD18: 0 | AE18: 0
A19: - Gift Wrap | B19: 0 | C19: 0 | D19: 8.98 | E19: 8.98 | F19: 4.49 | G19: 17.96 | H19: 8.98 | I19: 1.14 | J19: 22.45 | K19: 8.98 | L19: 17.96 | M19: 31.43 | N19: 8.98 | O19: 13.47 | P19: 13.47 | Q19: 17.96 | R19: 44.4 | S19: 17.96 | T19: 17.96 | U19: 94.29 | V19: 71.34 | W19: 67.35 | X19: 170.12 | Y19: 439.52 | Z19: 269.4 | AA19: 161.64 | AB19: 0 | AC19: 0 | AD19: 0 | AE19: 0
A20: App Revenue | B20: 484 | C20: 948 | D20: 773 | E20: 2222 | F20: 1645 | G20: 1036 | H20: 1064 | I20: 1122 | J20: 1527 | K20: 1485 | L20: 2049 | M20: 2438 | N20: 1340 | O20: 1208 | P20: 1240 | Q20: 1301 | R20: 1475 | S20: 1932 | T20: 2171 | U20: 1184 | V20: 1281 | W20: 878 | X20: 943 | Y20: 1540 | Z20: 2075 | AA20: 2577 | AB20: 1379 | AC20: 929 | AD20: 1719 | AE20: 1731
... A24: Rachio Revenue | B24: 199 | C24: 0 | D24: 0 | E24: 20699.29 | F24: 10799.63 | G24: 44338.5 | H24: 6179.79 | I24: 0 | J24: 3239.89 | K24: 899.97 | L24: 899.97 | M24: 1199.96 | N24: 1199.96 | O24: 0 | P24: 1692.1 | Q24: 10439.65 | R24: 1739.94 | S24: 2099.93 | T24: 1578.52 | U24: 1759.35 | V24: 2299.92 | W24: 2399.92 | X24: 4655.63 | Y24: 5519.81 | Z24: 839.97 | AA24: 15479.47 | AB24: 25979.12 | AC24: 9779.67 | AD24: 826.16 | AE24: 839.97
A25: IndieGoGo Revenue | B25: 408 | C25: =319+698 -> 1017 | D25: 566 | E25: 497 | F25: =902+603 -> 1505 | G25: 1195 | H25: 283 | I25: =1025+403 -> 1428 | J25: 319 | K25: 0 | L25: 1195 | M25: 487 | N25: 283 | O25: 487 | P25: 204 | Q25: 283 | R25: 0 | S25: 0 | T25: 418 | U25: 991 | V25: 0 | W25: 1079 | X25: 0 | Y25: 1876 | Z25: 2104 | AA25: =770+283 -> 1053 | AB25: 566 | AC25: 378 | AD25: 204 | AE25: 487
A26: Total Revenue | B26: =SUM(B8+B14+B20+B24+B25) -> 118691.72 | C26: =SUM(C8+C14+C20+C24+C25) -> 126426.35 | D26: =SUM(D8+D14+D20+D24+D25) -> 129255.8 | E26: =SUM(E8+E14+E20+E24+E25) -> 163310.92 | F26: =SUM(F8+F14+F20+F24+F25) -> 171406.56 | G26: =SUM(G8+G14+G20+G24+G25) -> 192541.66 | H26: =SUM(H8+H14+H20+H24+H25) -> 140214.38 | I26: =SUM(I8+I14+I20+I24+I25) -> 140988.9 | ... AE26: =SUM(AE8+AE14+AE20+AE24+AE25) -> 95842.46
A28: B2B Revenue
A29: - Best Buy | G29: 480 | H29: 420 | I29: 210 | J29: 1260 | K29: 7140 | L29: 5250 | M29: 6923 | N29: 4200 | O29: 5450 | P29: 3150 | Q29: 1470 | R29: 4410 | S29: 2520 | T29: 6720 | U29: 4830 | V29: 3360 | W29: 7980 | X29: 11339 | Y29: 32758 | Z29: 10500 | AA29: 10500 | AB29: 60477 | AC29: 42208 | AD29: 43258 | AE29: 54597
A30: Total Revenue | B30: =B29 | C30: =C29 | D30: =D29 | E30: =E29 | F30: =F29 | G30: =G29 -> 480 | H30: =H29 -> 420 | I30: =I29 -> 210 | ... AE30: =AE29 -> 54597
A32: App Revenue
A33: - Google Store | B33: ='App - P&L'!B90 -> 84.677 | C33: ='App - P&L'!C90 -> 140.998 | D33: ='App - P&L'!D90 -> 60.469 | E33: ='App - P&L'!E90 -> 349.6205 | F33: ='App - P&L'!F90 -> 241.919 | G33: ='App - P&L'!G90 -> 57.6675 | H33: ='App - P&L'!H90 -> 152.232 | I33: ='App - P&L'!I90 -> 254.7435 | ... AE33: ='App - P&L'!AE90 -> 158.926
A34: - Apple Store | B34: ='App - P&L'!B91 -> 339.73821 | C34: ='App - P&L'!C91 -> 558.30126 | D34: ='App - P&L'!D91 -> 504.6811 | E34: ='App - P&L'!E91 -> 1171.7564 | F34: ='App - P&L'!F91 -> 1080.9353 | G34: ='App - P&L'!G91 -> 715.33954 | H34: ='App - P&L'!H91 -> 540.21655 | I34: ='App - P&L'!I91 -> 688.2394 | ... AE34: ='App - P&L'!AE91 -> 1058.6786
A35: - Comission | B35: ='App - P&L'!B67 -> 161.01223 | C35: ='App - P&L'!C67 -> 269.0954 | D35: ='App - P&L'!D67 -> 232.59433 | E35: ='App - P&L'!E67 -> 576.46367 | F35: ='App - P&L'!F67 -> 512.60328 | G35: ='App - P&L'!G67 -> 328.7323 | H35: ='App - P&L'!H67 -> 263.43795 | I35: ='App - P&L'!I67 -> 349.71767 | ... AE35: ='App - P&L'!AE67 -> 483.2977
A36: - Tax | B36: ='App - P&L'!B68 -> 1.09 | C36: ='App - P&L'!C68 -> 11.53 | D36: ='App - P&L'!D68 -> 13.14 | E36: ='App - P&L'!E68 -> 30.07 | F36: ='App - P&L'!F68 -> 22.19 | G36: ='App - P&L'!G68 -> 34.61 | H36: ='App - P&L'!H68 -> 12.1 | I36: ='App - P&L'!I68 -> 34.28 | ... AE36: ='App - P&L'!AE68 -> 6.67
A37: Total Revenue | B37: =sum(B33:B36) -> 586.51744 | C37: =sum(C33:C36) -> 979.92465 | D37: =sum(D33:D36) -> 810.88444 | E37: =sum(E33:E36) -> 2127.9106 | F37: =sum(F33:F36) -> 1857.6476 | G37: =sum(G33:G36) -> 1136.3493 | H37: =sum(H33:H36) -> 967.9865 | I37: =sum(I33:I36) -> 1326.9806 | ... AE37: =sum(AE33:AE36) -> 1707.5723
A39: DTC Orders | B39: 446 | C39: 526 | D39: 509 | E39: 529 | F39: 596 | G39: 570 | H39: 516 | I39: 526 | J39: 561 | K39: 554 | L39: 684 | M39: =758-95 -> 663 | N39: =962-420 -> 542 | O39: 623 | P39: 582 | Q39: 544 | R39: 578 | S39: 728 | T39: 751 | U39: 785 | V39: 822 | W39: 1217 | X39: 1412 | Y39: 3921 | Z39: 2450 | AA39: 1814 | AB39: 2787 | AC39: 1954 | AD39: 332 | AE39: 313
A40: - Hardware (units sold) | B40: 419 | C40: 442 | D40: 452 | E40: 485 | F40: 567 | G40: 537 | H40: 484 | I40: 477 | J40: 497 | K40: 503 | L40: 632 | M40: 632 | N40: 498 | O40: 578 | P40: 541 | Q40: 511 | R40: 529 | S40: 701 | T40: 714 | U40: 747 | V40: 782 | W40: 1133 | X40: 1353 | Y40: 3769 | Z40: 2387 | AA40: 1742 | AB40: 2704 | AC40: 1891 | AD40: 295 | AE40: 268
A41: - Add-ons (units sold) | B41: 581 | C41: 734 | D41: 693 | E41: 715 | F41: 757 | G41: 713 | H41: 695 | I41: 731 | J41: 722 | K41: 701 | L41: 953 | M41: 1027 | N41: 1134 | O41: 808 | P41: 734 | Q41: 714 | R41: 713 | S41: 929 | T41: 710 | U41: 952 | V41: 1000 | W41: 1543 | X41: 1895 | Y41: 4733 | Z41: 2745 | AA41: 2239 | AB41: 3084 | AC41: 1874 | AD41: 230 | AE41: 222
A42: - Merch (units sold) | B42: 0 | C42: 0 | D42: 0 | E42: 0 | F42: 0 | G42: 0 | H42: 0 | I42: 0 | J42: 15 | K42: 13 | L42: 12 | M42: 5 | N42: 0 | O42: 23 | P42: 23 | Q42: 27 | R42: 20 | S42: 9 | T42: 7 | U42: 6 | V42: 9 | W42: 14 | X42: 14 | Y42: 47 | Z42: 30 | AA42: 14 | AB42: 36 | AC42: 31 | AD42: 6 | AE42: 6
A43: Amazon Orders | B43: 49 | C43: 41 | D43: 55 | E43: 65 | F43: 73 | G43: 57 | H43: 48 | I43: 66 | J43: 119 | K43: 118 | L43: 177 | M43: 175 | N43: 152 | O43: 168 | P43: 189 | Q43: 204 | R43: 243 | S43: 282 | T43: 197 | U43: 509 | V43: 521 | W43: 579 | X43: =X44+X45 -> 953 | Y43: 3488 | Z43: 1165 | AA43: 1099 | AB43: 19 | AC43: 1 | AD43: 0 | AE43: 3
A44: - Hardware (units sold) | B44: 44 | C44: 36 | D44: 53 | E44: 60 | F44: 68 | G44: 55 | H44: 46 | I44: 57 | J44: 113 | K44: 114 | L44: 168 | M44: 165 | N44: 152 | O44: 162 | P44: 178 | Q44: 192 | R44: 236 | S44: 268 | T44: 175 | U44: 492 | V44: 496 | W44: 554 | X44: 885 | Y44: 3304 | Z44: 1157 | AA44: 1127 | AB44: 19 | AC44: 0 | AD44: 0 | AE44: 2
A45: - Add-ons (units sold) | B45: 6 | C45: 5 | D45: 3 | E45: 5 | F45: 5 | G45: 5 | H45: 2 | I45: 13 | J45: 6 | K45: 4 | L45: 12 | M45: 11 | N45: 3 | O45: 9 | P45: 13 | Q45: 20 | R45: 25 | S45: 24 | T45: 32 | U45: 38 | V45: 40 | W45: 34 | X45: 68 | Y45: 184 | Z45: 8 | AA45: 9 | AB45: 0 | AC45: 1 | AD45: 0 | AE45: 1
A46: App Orders | B46: 19 | C46: 32 | D46: 25 | E46: 79 | F46: 64 | G46: 41 | H46: 37 | I46: 39 | J46: 50 | K46: 57 | L46: 78 | M46: 90 | N46: 46 | O46: 44 | P46: 41 | Q46: 46 | R46: 53 | S46: 72 | T46: 79 | U46: 40 | V46: 50 | W46: 32 | X46: 39 | Y46: 62 | Z46: 79 | AA46: 85 | AB46: 48 | AC46: 34 | AD46: 56 | AE46: 59
A47: Rachio Orders | B47: 1 | C47: 0 | D47: 0 | E47: 70 | F47: 35 | G47: 150 | H47: 21 | I47: 0 | J47: 9 | K47: 3 | L47: 3 | M47: 4 | N47: 4 | O47: 0 | P47: 7 | Q47: 35 | R47: 6 | S47: 7 | T47: 7 | U47: 8 | V47: 10 | W47: 8 | X47: 15 | Y47: 18 | Z47: 3 | AA47: 52 | AB47: 87 | AC47: 33 | AD47: 4 | AE47: 3
A48: IndieGoGo Orders | B48: 2 | C48: 1 | D48: 2 | E48: 1 | F48: 2 | G48: 3 | H48: 1 | I48: 4 | J48: 1 | K48: 0 | L48: 3 | M48: 2 | N48: 1 | O48: 2 | P48: 1 | Q48: 1 | R48: 0 | S48: 0 | T48: 2 | U48: 2 | V48: 0 | W48: 4 | X48: 0 | Y48: 6 | Z48: 6 | AA48: 4 | AB48: 2 | AC48: 1 | AD48: 1 | AE48: 2
A49: Total Orders | B49: =SUM(B39+B43+B47+B48) -> 498 | C49: =SUM(C39+C43+C47+C48) -> 568 | D49: =SUM(D39+D43+D47+D48) -> 566 | E49: =SUM(E39+E43+E47+E48) -> 665 | F49: =SUM(F39+F43+F47+F48) -> 706 | G49: =SUM(G39+G43+G47+G48) -> 780 | H49: =SUM(H39+H43+H47+H48) -> 586 | I49: =SUM(I39+I43+I47+I48) -> 596 | ... AE49: =SUM(AE39+AE43+AE47+AE48) -> 321
A51: B2B Orders
A52: - Best Buy | G52: 2 | H52: 2 | I52: 1 | J52: 6 | K52: 34 | L52: 25 | M52: 33 | N52: 20 | O52: 26 | P52: 15 | Q52: 7 | R52: 21 | S52: 12 | T52: 32 | U52: 23 | V52: 16 | W52: 38 | X52: 54 | Y52: 155 | Z52: 50 | AA52: 50 | AB52: 288 | AC52: 201 | AD52: 206 | AE52: 260
A53: Total Revenue | B53: =B52 | C53: =C52 | D53: =D52 | E53: =E52 | F53: =F52 | G53: =G52 -> 2 | H53: =H52 -> 2 | I53: =I52 -> 1 | ... AE53: =AE52 -> 260
A55: App Orders
A56: - Google Store | B56: ='App - P&L'!B17 -> 5 | C56: ='App - P&L'!C17 -> 7 | D56: ='App - P&L'!D17 -> 4 | E56: ='App - P&L'!E17 -> 19 | F56: ='App - P&L'!F17 -> 11 | G56: ='App - P&L'!G17 -> 8 | H56: ='App - P&L'!H17 -> 11 | I56: ='App - P&L'!I17 -> 17 | ... AE56: ='App - P&L'!AE17 -> 9
A57: - Apple Store | B57: ='App - P&L'!B14 -> 25 | C57: ='App - P&L'!C14 -> 35 | D57: ='App - P&L'!D14 -> 36 | E57: ='App - P&L'!E14 -> 70 | F57: ='App - P&L'!F14 -> 70 | G57: ='App - P&L'!G14 -> 49 | H57: ='App - P&L'!H14 -> 43 | I57: ='App - P&L'!I14 -> 52 | ... AE57: ='App - P&L'!AE14 -> 74
A58: Total Orders | B58: =sum(B56:B57) -> 30 | C58: =sum(C56:C57) -> 42 | D58: =sum(D56:D57) -> 40 | E58: =sum(E56:E57) -> 89 | F58: =sum(F56:F57) -> 81 | G58: =sum(G56:G57) -> 57 | H58: =sum(H56:H57) -> 54 | I58: =sum(I56:I57) -> 69 | ... AE58: =sum(AE56:AE57) -> 83
A60: Meta Spend | B60: 32270.8 | C60: 29009.15 | D60: 31375.99 | E60: 28062.23 | F60: 28128.86 | G60: 29578.13 | H60: 25668.44 | I60: 32604.58 | J60: 38104.59 | K60: 34229.39 | L60: 26717.46 | M60: 29868 | N60: 26716.5 | O60: 27787.46 | P60: 30344.21 | Q60: 28152.45 | R60: 23954.07 | S60: 26180.79 | T60: 30123.57 | U60: 34139.05 | V60: 37577.71 | W60: 45135.93 | X60: 82938.07 | Y60: =288128.54-131460.58 -> 156667.96 | Z60: =70016.67+23765.66 -> 93782.33 | AA60: 91456.91 | AB60: 112718.4 | AC60: 83839.03 | AD60: 29510.93 | AE60: 13568.62
A61: Google Spend | B61: 4639.67 | C61: 5334.54 | D61: 6029.34 | E61: 6892.12 | F61: 8838.16 | G61: 8605.53 | H61: 7927.51 | I61: 8939.45 | J61: 10382.86 | K61: 10981.67 | L61: 9974.6 | M61: 7719.21 | N61: 8342.67 | O61: 7518.8 | P61: 7390.24 | Q61: 8231.77 | R61: 9100.99 | S61: 9403.53 | T61: 10517.85 | U61: 10191.41 | V61: 10645.43 | W61: 9890.32 | X61: 16381.42 | Y61: 21374.36 | Z61: 19571.66 | AA61: 17193.4 | AB61: 18114.09 | AC61: 16152.42 | AD61: 7994.65 | AE61: 5438.57
A62: Bing Spend | B62: 222.16 | C62: 254.7 | D62: 277.25 | E62: 309.46 | F62: 253.45 | G62: 398.68 | H62: 376.76 | I62: 415.9 | J62: 424.32 | K62: 415.8 | L62: 349.18 | M62: 382.43 | N62: 360.89 | O62: 422.46 | P62: 427.45 | Q62: 433.39 | R62: 432.25 | S62: 354.98 | T62: 428.39 | U62: 429.17 | V62: 430.31 | W62: 430.8 | X62: 465.28 | Y62: 578.08 | Z62: 467.09 | AA62: 602.67 | AB62: 633.77 | AC62: 352.82 | AD62: 508.16 | AE62: 349.07
A63: TikTok Spend | B63: 0 | C63: 0 | D63: 0 | E63: 0 | F63: 0 | G63: 0 | H63: 0 | I63: 0 | J63: 0 | K63: 0 | L63: 0 | M63: 0 | N63: 0 | O63: 0 | P63: 159.15 | Q63: 400.43 | R63: 189.07 | S63: 0 | T63: 0 | U63: 0 | V63: 0 | W63: 0 | X63: 0 | Y63: 0 | Z63: 0 | AA63: 0 | AB63: 0 | AC63: 0 | AD63: 0 | AE63: 0
A64: Amazon Spend | B64: 3342.22 | C64: 3305.62 | D64: 3219.49 | E64: 4981.96 | F64: 5362.92 | G64: 4001.06 | H64: 4013.79 | I64: 2780.51 | J64: 4409.21 | K64: 4932.36 | L64: 6103.31 | M64: 7253.93 | N64: 7237.54 | O64: 6127.83 | P64: 6588.6 | Q64: 8982.55 | R64: 9392.78 | S64: 11591.44 | T64: 11126.7 | U64: 17467.27 | V64: 19867.53 | W64: 22792.98 | X64: 28816.4 | Y64: 64502.73 | Z64: 37752.85 | AA64: 37544.76 | AB64: 3627.98 | AC64: 0 | AD64: 0 | AE64: 433.94
A65: Nextdoor Spend | B65: 0 | C65: 0 | D65: 0 | E65: 0 | F65: 0 | G65: 0 | H65: 0 | I65: 0 | J65: 0 | K65: 0 | L65: 0 | M65: 0 | N65: 0 | O65: 0 | P65: 0 | Q65: 0 | R65: 192.23 | S65: 303.11 | T65: 300.88 | U65: 660.39 | V65: 481.73 | W65: 187.74 | X65: 143.11 | Y65: 57.99 | Z65: 136.47 | AA65: 705.4 | AB65: 834.58 | AC65: 0 | AD65: 0 | AE65: 0
A66: IndieGoGo Spend | B66: 0 | C66: 0 | D66: 0 | E66: 0 | F66: 0 | G66: 0 | H66: 0 | I66: 0 | J66: 0 | K66: 0 | L66: 0 | M66: 0 | N66: 0 | O66: 0 | P66: 0 | Q66: 0 | R66: 0 | S66: 0 | T66: 0 | U66: 0 | V66: 0 | W66: 0 | X66: 0 | Y66: 0 | Z66: 0 | AA66: 0 | AB66: 0 | AC66: 0 | AD66: 0 | AE66: 0
A67: Affiliate Fees | B67: 162.71 | C67: 61 | D67: 0 | E67: =E24*0.2+115.73 -> 4255.588 | F67: =F24*0.2+133.01 -> 2292.936 | G67: 63.09 | H67: 86.6 | I67: 0 | J67: 0 | K67: 99.96 | L67: 0 | M67: 324.88 | N67: 97.43 | O67: 100.64 | P67: 55.28 | Q67: 0 | R67: 105.32 | S67: 0 | T67: 0 | U67: 0 | V67: 32.38 | W67: 105.6 | X67: 266.9 | Y67: 94.59 | Z67: 123.15 | AA67: 106.16 | AB67: 497.95 | AC67: 377.37 | AD67: 68.6 | AE67: 13.6
A68: Rachio Fees | B68: =B24*0.2 -> 39.8 | C68: =C24*0.2 -> 0 | D68: =D24*0.2 -> 0 | E68: =E24*0.2 -> 4139.858 | F68: =F24*0.2 -> 2159.926 | G68: =G24*0.2 -> 8867.7 | H68: =H24*0.2 -> 1235.958 | I68: =I24*0.2 -> 0 | ... AE68: =AE24*0.2 -> 167.994
A69: Total DTC Spend | B69: =B60+B61+B62+B63+B65+B67 -> 37295.34 | C69: =C60+C61+C62+C63+C65+C67 -> 34659.39 | D69: =D60+D61+D62+D63+D65+D67 -> 37682.58 | E69: =E60+E61+E62+E63+E65+E67 -> 39519.398 | F69: =F60+F61+F62+F63+F65+F67 -> 39513.406 | G69: =G60+G61+G62+G63+G65+G67 -> 38645.43 | H69: =H60+H61+H62+H63+H65+H67 -> 34059.31 | I69: =I60+I61+I62+I63+I65+I67 -> 41959.93 | ... AE69: =AE60+AE61+AE62+AE63+AE65+AE67 -> 19369.86
A70: Total Spend | B70: =SUM(B60:B68) -> 40677.36 | C70: =SUM(C60:C68) -> 37965.01 | D70: =SUM(D60:D68) -> 40902.07 | E70: =SUM(E60:E68) -> 48641.216 | F70: =SUM(F60:F68) -> 47036.252 | G70: =SUM(G60:G68) -> 51514.19 | H70: =SUM(H60:H68) -> 39309.058 | I70: =SUM(I60:I68) -> 44740.44 | ... AE70: =SUM(AE60:AE68) -> 19971.794
A72: Blended ROAS | B72: =B26/B70 -> 2.9178816 | C72: =C26/C70 -> 3.3300755 | D72: =D26/D70 -> 3.1601286 | E72: =E26/E70 -> 3.3574596 | F72: =F26/F70 -> 3.6441373 | G72: =G26/G70 -> 3.7376432 | H72: =H26/H70 -> 3.5669738 | I72: =I26/I70 -> 3.1512632 | ... AE72: =AE26/AE70 -> 4.7988909
A73: wROAS | B73: =B8/B69 -> 2.8159207 | C73: =C8/C69 -> 3.2878103 | D73: =D8/D69 -> 2.9821193 | E73: =E8/E69 -> 3.0874111 | F73: =F8/F69 -> 3.4828959 | G73: =G8/G69 -> 3.3625492 | H73: =H8/H69 -> 3.5050252 | I73: =I8/I69 -> 2.9402826 | ... AE73: =AE8/AE69 -> 4.763973
A74: aROAS | B74: =B14/B64 -> 3.7639653 | C74: =C14/C64 -> 3.1787834 | D74: =D14/D64 -> 4.8277367 | E74: =E14/E64 -> 3.5889489 | F74: =F14/F64 -> 3.6987033 | G74: =G14/G64 -> 4.0051886 | H74: =H14/H64 -> 3.3157813 | I74: =I14/I64 -> 5.4180168 | ... AE74: =AE14/AE64 -> 1.1683643
A76: Blended CAC | B76: =B70/B49 -> 81.681446 | C76: =C70/C49 -> 66.839806 | D76: =D70/D49 -> 72.265141 | E76: =E70/E49 -> 73.144686 | F76: =F70/F49 -> 66.623586 | G76: =G70/G49 -> 66.043833 | H76: =H70/H49 -> 67.080304 | I76: =I70/I49 -> 75.067852 | ... AE76: =AE70/AE49 -> 62.217427
A77: wCAC | B77: =B69/B39 -> 83.621839 | C77: =C69/C39 -> 65.892376 | D77: =D69/D39 -> 74.032574 | E77: =E69/E39 -> 74.705856 | F77: =F69/F39 -> 66.297661 | G77: =G69/G39 -> 67.799 | H77: =H69/H39 -> 66.006415 | I77: =I69/I39 -> 79.77173 | ... AE77: =AE69/AE39 -> 61.884537
A78: aCAC | B78: =B64/B43 -> 68.208571 | C78: =C64/C43 -> 80.624878 | D78: =D64/D43 -> 58.536182 | E78: =E64/E43 -> 76.645538 | F78: =F64/F43 -> 73.464658 | G78: =G64/G43 -> 70.194035 | H78: =H64/H43 -> 83.620625 | I78: =I64/I43 -> 42.128939 | ... AE78: =AE64/AE43 -> 144.64667
A80: Web CR | B80: 0.024 | C80: 0.0272 | D80: 0.0243 | E80: 0.0242 | F80: 0.0223 | G80: 0.02 | H80: 0.0209 | I80: 0.0176 | J80: 0.0185 | K80: 0.0195 | L80: 0.0256 | M80: 0.0235 | N80: 0.0221 | O80: 0.0233 | P80: 0.0302 | Q80: 0.0228 | R80: 0.0262 | S80: 0.0294 | T80: 0.0271 | U80: 0.0286 | V80: 0.0262 | W80: 0.0273 | X80: 0.0249 | Y80: 0.041 | Z80: 0.0498 | AA80: 0.031 | AB80: 0.0557 | AC80: 0.0437 | AD80: 0.0102 | AE80: 0.0144
A81: Web AOV | B81: =B8/B39 -> 235.47247 | C81: =C8/C39 -> 216.64164 | D81: =D8/D39 -> 220.77397 | E81: =E8/E39 -> 230.64769 | F81: =F8/F39 -> 230.90785 | G81: =G8/G39 -> 227.97747 | H81: =H8/H39 -> 231.35415 | I81: =I8/I39 -> 234.55143 | ... AE81: =AE8/AE39 -> 294.81626
A82: fAOV | B82: 206.32 | C82: 189.8 | D82: 194.25 | E82: 203.72 | F82: 202.65 | G82: 201.03 | H82: 204.17 | I82: 204.79 | J82: 201.84 | K82: 204.9 | L82: 216.59 | M82: 190.66 | N82: 205.01 | O82: 207.14 | P82: 206.85 | Q82: 203.74 | R82: 203.74 | S82: 206.17 | T82: 210.4 | U82: 213.25 | V82: 209.43 | W82: 207.85 | X82: 211.52 | Y82: 209.55 | Z82: 207.39 | AA82: 208.64 | AB82: 210.78 | AC82: 214.22 | AD82: 273.98 | AE82: 269.23
A83: rAOV | B83: 90.28 | C83: 73.06 | D83: 130.77 | E83: 137.43 | F83: 123.96 | G83: 97.6 | H83: 167.67 | I83: 167 | J83: 167.11 | K83: 74.37 | L83: 152.95 | M83: 119.71 | N83: 208.5 | O83: 127.93 | P83: 84.82 | Q83: 116.73 | R83: 123.19 | S83: 175.24 | T83: 160.23 | U83: 161.87 | V83: 125.88 | W83: 164.39 | X83: 175.4 | Y83: 179.69 | Z83: 183.61 | AA83: 196.62 | AB83: 170.7 | AC83: 161.53 | AD83: 256.72 | AE83: 138.95
A85: Customers
A86: Returning | B86: 0.0359 | C86: 0.0665 | D86: 0.0588 | E86: 0.0529 | F86: 0.0386 | G86: 0.0439 | H86: 0.0465 | I86: 0.0684 | J86: 0.066 | K86: 0.0433 | L86: 0.0541 | M86: 0.0317 | N86: 0.0627 | O86: 0.0241 | P86: 0.0292 | Q86: 0.0349 | R86: 0.045 | S86: 0.0343 | T86: 0.0346 | U86: 0.0382 | V86: 0.0389 | W86: 0.069 | X86: 0.0439 | Y86: 0.0405 | Z86: 0.0408 | AA86: 0.0369 | AB86: 0.0359 | AC86: 0.0328 | AD86: 0.0633 | AE86: 0.0479
A87: First-time | B87: =1-B86 -> 0.9641 | C87: =1-C86 -> 0.9335 | D87: =1-D86 -> 0.9412 | E87: =1-E86 -> 0.9471 | F87: =1-F86 -> 0.9614 | G87: =1-G86 -> 0.9561 | H87: =1-H86 -> 0.9535 | I87: =1-I86 -> 0.9316 | ... AE87: =1-AE86 -> 0.9521
B89: 45231 | C89: Goal | D89: % of Goal
A90: Revenue | B90: =SUM(B26:AE26) -> 9386537.8 | C90: 3000000 | D90: =B90/C90 -> 3.1288459
A91: Spend | B91: =SUM(B70:AE70) -> 2059338.3 | C91: 600000 | D91: =B91/C91 -> 3.4322304
A92: ROAS | B92: =B90/B91 -> 4.5580359 | C92: 5 | D92: =B92/C92 -> 0.91160719
A93: CAC | B93: =SUM(B70:AE70)/SUM(B49:AE49) -> 51.087528
A94: CR | B94: =AVERAGE(B80:AE80) -> 0.026716667
A95: AOV | B95: =B90/B98 -> 232.85879
A96: fAOV | B96: =AVERAGE(B82:AE82) -> 209.987
A97: rAOV | B97: =AVERAGE(B83:AE83) -> 147.13033
A98: Orders | B98: =SUM(B49:AE49) -> 40310
A99: Units Sold | B99: ='Detailed Report OLD'!AG149 +'AMAZON Detailed Report OLD'!AG45 -> 38475 | C99: 12500 | D99: =B99/C99 -> 3.078
A100: CAC per Unit | B100: =B91/B99 -> 53.524061
A101: First-time customers | B101: =AVERAGE(B87:AE87) -> 0.95468333
A102: Returning customers | B102: =AVERAGE(B86:AE86) -> 0.045316667

Sheet Detailed Report OLD
A1: NOVEMBER | B1: 45231 | C1: 45232 | D1: 45233 | E1: 45234 | F1: 45235 | G1: 45236 | H1: 45237 | I1: 45238 | J1: 45239 | K1: 45240 | L1: 45241 | M1: 45242 | N1: 45243 | O1: 45244 | P1: 45245 | Q1: 45246 | R1: 45247 | S1: 45248 | T1: 45249 | U1: 45250 | V1: 45251 | W1: 45252 | X1: 45253 | Y1: 45254 | Z1: 45255 | AA1: 45256 | AB1: 45257 | AC1: 45258 | AD1: 45259 | AE1: 45260
A2: DAY | B2: WED | C2: THU | D2: FRI | E2: SAT | F2: SUN | G2: MON | H2: TUE | I2: WED | J2: THU | K2: FRI | L2: SAT | M2: SUN | N2: MON | O2: TUE | P2: WED | Q2: THU | R2: FRI | S2: SAT | T2: SUN | U2: MON | V2: TUE | W2: WED | X2: THU | Y2: FRI | Z2: SAT | AA2: SUN | AB2: MON | AC2: TUE | AD2: WED | AE2: THU
A3: COMMENT
A4: Orders
A5: FB (US & CA) | B5: 238 | C5: 263 | D5: 255 | E5: 261 | F5: 303 | G5: 276 | H5: 233 | I5: 214 | J5: 253 | K5: 263 | L5: 298 | M5: 228 | N5: 196 | O5: 222 | P5: 224 | Q5: 116 | R5: 210 | S5: 288 | T5: 280 | U5: 306 | V5: 313 | W5: 402 | X5: 592 | Y5: 1567 | Z5: 534 | AA5: 734 | AB5: 1061 | AC5: 761 | AD5: 116 | AE5: 81 | AG5: =SUM(B5:AF5) -> 11088
A6: Google | B6: 96 | C6: 106 | D6: 112 | E6: 128 | F6: 143 | G6: 137 | H6: 124 | I6: 127 | J6: 166 | K6: 167 | L6: 185 | M6: 173 | N6: 175 | O6: 157 | P6: 149 | Q6: 154 | R6: 187 | S6: 230 | T6: 243 | U6: 227 | V6: 253 | W6: 251 | X6: 380 | Y6: 1076 | Z6: 253 | AA6: 543 | AB6: 261 | AC6: 192 | AD6: 79 | AE6: 24 | AG6: =SUM(B6:AF6) -> 6498
A7: TikTok | B7: 0 | C7: 0 | D7: 0 | E7: 0 | F7: 0 | G7: 0 | H7: 0 | I7: 0 | J7: 0 | K7: 0 | L7: 0 | M7: 0 | N7: 0 | O7: 0 | P7: 0 | Q7: 0 | R7: 0 | S7: 0 | T7: 0 | U7: 0 | V7: 0 | W7: 0 | X7: 0 | Y7: 0 | Z7: 0 | AA7: 0 | AB7: 0 | AC7: 0 | AD7: 0 | AE7: 0 | AG7: =SUM(B7:AF7) -> 0
A8: Bing | B8: 24 | C8: 28 | D8: 24 | E8: 20 | F8: 18 | G8: 24 | H8: 22 | I8: 34 | J8: 16 | K8: 22 | L8: 30 | M8: 14 | N8: 8 | O8: 11 | P8: 12 | Q8: 7 | R8: 13 | S8: 7 | T8: 18 | U8: 11 | V8: 9 | W8: 11 | X8: 11 | Y8: 72 | Z8: 0 | AA8: 0 | AB8: 0 | AC8: 10 | AD8: 4 | AE8: 3 | AG8: =SUM(B8:AF8) -> 483
A9: MNTN TV | AG9: =SUM(B9:AF9) -> 0
A10: Affiliates (Refersion) | B10: 3 | C10: 1 | D10: 0 | E10: 2 | F10: 3 | G10: 1 | H10: 1 | I10: 0 | J10: 0 | K10: 2 | L10: 0 | M10: 5 | N10: 2 | O10: 2 | P10: 2 | Q10: 0 | R10: 2 | S10: 0 | T10: 0 | U10: 0 | V10: 1 | W10: 2 | X10: 4 | Y10: 3 | Z10: 3 | AA10: 2 | AB10: 9 | AC10: 8 | AD10: 1 | AE10: 1 | AG10: =SUM(B10:AF10) -> 60
A11: FB (Internal Paid) | AG11: =SUM(B11:AF11) -> 0
A12: FB (EU & UK) | AG12: =SUM(B12:AF12) -> 0
A13: Email | B13: 0 | C13: 57 | D13: 23 | E13: 6 | F13: 0 | G13: 0 | H13: 0 | I13: 0 | J13: 23 | K13: 14 | L13: 5 | M13: 0 | N13: 0 | O13: 19 | P13: 18 | Q13: 19 | R13: 8 | S13: 0 | T13: 0 | U13: 0 | V13: 0 | W13: 191 | X13: 122 | Y13: 169 | Z13: 71 | AA13: 38 | AB13: 24 | AC13: 11 | AD13: 4 | AE13: 2 | AG13: =SUM(B13:AF13) -> 824
A14: Amazon (market place) | AG14: =SUM(B14:AF14) -> 0
A15: All | B15: =SUM(B5:B14) -> 361 | C15: =SUM(C5:C14) -> 455 | D15: =SUM(D5:D14) -> 414 | E15: =SUM(E5:E14) -> 417 | F15: =SUM(F5:F14) -> 467 | G15: =SUM(G5:G14) -> 438 | H15: =SUM(H5:H14) -> 380 | I15: =SUM(I5:I14) -> 375 | ... AF15: =SUM(AF5:AF14) -> 0 | AG15: =SUM(B15:AF15) -> 18953
A17: Revenue
A18: FB (US & CA) | B18: 53737.12 | C18: 58868.67 | D18: 54443.09 | E18: 57095.98 | F18: 66247.5 | G18: 60680.81 | H18: 52676.07 | I18: 49042.67 | J18: 58203.03 | K18: 64530.47 | L18: 71475.57 | M18: 52095.99 | N18: 44759.95 | O18: 51824.82 | P18: 50938.37 | Q18: 36463.32 | R18: 46372.52 | S18: 63501.9 | T18: 63235.58 | U18: 70368.16 | V18: 69511.86 | W18: 90662.19 | X18: 131219.92 | Y18: 349864.1 | Z18: 116894.72 | AA18: 160780.67 | AB18: 236364.51 | AC18: 171241.09 | AD18: 32747.29 | AE18: 22381.96 | AG18: =SUM(B18:AF18) -> 2508229.9
A19: Google | B19: 22113.61 | C19: 25412.8 | D19: 26211.16 | E19: 28888.01 | F19: 30491.14 | G19: 31282.18 | H19: 29429.36 | I19: 30479.66 | J19: 34161.55 | K19: 37413.68 | L19: 44752.39 | M19: 41150.47 | N19: 38332.4 | O19: 37089.78 | P19: 34739.5 | Q19: 37054.7 | R19: 43210 | S19: 54179.92 | T19: 58007.91 | U19: 54214.58 | V19: 59061.92 | W19: 56769.78 | X19: 91590.71 | Y19: 258125.54 | Z19: 58493.61 | AA19: 128747.87 | AB19: 61990.18 | AC19: 45258.43 | AD19: 23139.2 | AE19: 7487.07 | AG19: =SUM(B19:AF19) -> 1529279.1
A20: TikTok | B20: 0 | C20: 0 | D20: 0 | E20: 0 | F20: 0 | G20: 0 | H20: 0 | I20: 0 | J20: 0 | K20: 0 | L20: 0 | M20: 0 | N20: 0 | O20: 0 | P20: 0 | Q20: 0 | R20: 0 | S20: 0 | T20: 0 | U20: 0 | V20: 0 | W20: 0 | X20: 0 | Y20: 0 | Z20: 0 | AA20: 0 | AB20: 0 | AC20: 0 | AD20: 0 | AE20: 0 | AG20: =SUM(B20:AF20) -> 0
A21: Bing | B21: 2507.59 | C21: 1942.19 | D21: 2386.4 | E21: 2490.12 | F21: 1828.45 | G21: 1536.48 | H21: 2697.73 | I21: 2878.58 | J21: 1449.27 | K21: 2761 | L21: 3765 | M21: 3398.62 | N21: 1984.58 | O21: 2586.64 | P21: 2691.38 | Q21: 1809.67 | R21: 3187.77 | S21: 1711.09 | T21: 4645 | U21: 2765.98 | V21: 1848.67 | W21: 2390.33 | X21: 2610.83 | Y21: 9036 | Z21: 0 | AA21: 0 | AB21: 0 | AC21: 2600.08 | AD21: 1143.47 | AE21: 556.25 | AG21: =SUM(B21:AF21) -> 71209.17
A22: MNTN TV | AG22: =SUM(B22:AF22) -> 0
A23: Affiliates (Refersion) | B23: 813.55 | C23: 244 | D23: 0 | E23: 578.65 | F23: 606.54 | G23: 315.46 | H23: 433 | I23: 0 | J23: 0 | K23: 445.76 | L23: 0 | M23: 1624.44 | N23: 438.73 | O23: 503.23 | P23: 276.37 | Q23: 0 | R23: 526.56 | S23: 0 | T23: 0 | U23: 0 | V23: 161.91 | W23: 476 | X23: 1214.94 | Y23: 472.95 | Z23: 615.78 | AA23: 469.78 | AB23: 2370.19 | AC23: 1830.85 | AD23: 343 | AE23: 68 | AG23: =SUM(B23:AF23) -> 14829.69
A24: FB (Internal Paid) | AG24: =SUM(B24:AF24) -> 0
A25: FB (EU & UK) | AG25: =SUM(B25:AF25) -> 0
A26: Email | B26: 0 | C26: 3667.35 | D26: 1510.38 | E26: 559.68 | F26: 0 | G26: 0 | H26: 0 | I26: 0 | J26: 3069.32 | K26: 1285.84 | L26: 1164.2 | M26: 0 | N26: 0 | O26: 2842.65 | P26: 1750.29 | Q26: 1606.27 | R26: 312.69 | S26: 0 | T26: 0 | U26: 0 | V26: 0 | W26: 43912.02 | X26: 28303.35 | Y26: 40391.88 | Z26: 15727.28 | AA26: 8244.38 | AB26: 4591.92 | AC26: 2453.14 | AD26: 793.51 | AE26: 159.73 | AG26: =SUM(B26:AF26) -> 162345.88
A27: Amazon (market place)
A28: All | B28: =SUM(B18:B27) -> 79171.87 | C28: =SUM(C18:C27) -> 90135.01 | D28: =SUM(D18:D27) -> 84551.03 | E28: =SUM(E18:E27) -> 89612.44 | F28: =SUM(F18:F27) -> 99173.63 | G28: =SUM(G18:G27) -> 93814.93 | H28: =SUM(H18:H27) -> 85236.16 | I28: =SUM(I18:I27) -> 82400.91 | ... AF28: =SUM(AF18:AF27) -> 0 | AG28: =SUM(B28:AF28) -> 4285893.8
A30: Media Cost
A31: FB Spend (US & CA) | B31: ='Sales OLD'!B60 -> 32270.8 | C31: ='Sales OLD'!C60 -> 29009.15 | D31: ='Sales OLD'!D60 -> 31375.99 | E31: ='Sales OLD'!E60 -> 28062.23 | F31: ='Sales OLD'!F60 -> 28128.86 | G31: ='Sales OLD'!G60 -> 29578.13 | H31: ='Sales OLD'!H60 -> 25668.44 | I31: ='Sales OLD'!I60 -> 32604.58 | ... AE31: ='Sales OLD'!AE60 -> 13568.62 | AG31: =SUM(B31:AF31) -> 1340211.6
A32: Google Spend | B32: ='Sales OLD'!B61 -> 4639.67 | C32: ='Sales OLD'!C61 -> 5334.54 | D32: ='Sales OLD'!D61 -> 6029.34 | E32: ='Sales OLD'!E61 -> 6892.12 | F32: ='Sales OLD'!F61 -> 8838.16 | G32: ='Sales OLD'!G61 -> 8605.53 | H32: ='Sales OLD'!H61 -> 7927.51 | I32: ='Sales OLD'!I61 -> 8939.45 | ... AE32: ='Sales OLD'!AE61 -> 5438.57 | AG32: =SUM(B32:AF32) -> 309718.24
A33: TikTok Spend | B33: ='Sales OLD'!B63 -> 0 | C33: ='Sales OLD'!C63 -> 0 | D33: ='Sales OLD'!D63 -> 0 | E33: ='Sales OLD'!E63 -> 0 | F33: ='Sales OLD'!F63 -> 0 | G33: ='Sales OLD'!G63 -> 0 | H33: ='Sales OLD'!H63 -> 0 | I33: ='Sales OLD'!I63 -> 0 | ... O33: ='Sales OLD'!O63 -> 0 | P33: ='Sales OLD'!P64 -> 6588.6 | Q33: ='Sales OLD'!Q63 -> 400.43 | R33: ='Sales OLD'!R63 -> 189.07 | S33: ='Sales OLD'!S63 -> 0 | T33: ='Sales OLD'!T63 -> 0 | U33: ='Sales OLD'!U63 -> 0 | V33: ='Sales OLD'!V63 -> 0 | W33: ='Sales OLD'!W63 -> 0 | X33: ='Sales OLD'!X63 -> 0 | ... AE33: ='Sales OLD'!AE63 -> 0 | AG33: =SUM(B33:AF33) -> 7178.1
A34: Bing Spend | B34: ='Sales OLD'!B62 -> 222.16 | C34: ='Sales OLD'!C62 -> 254.7 | D34: ='Sales OLD'!D62 -> 277.25 | E34: ='Sales OLD'!E62 -> 309.46 | F34: ='Sales OLD'!F62 -> 253.45 | G34: ='Sales OLD'!G62 -> 398.68 | H34: ='Sales OLD'!H62 -> 376.76 | I34: ='Sales OLD'!I62 -> 415.9 | ... AE34: ='Sales OLD'!AE62 -> 349.07 | AG34: =SUM(B34:AF34) -> 12187.12
A35: MNTN TV | B35: ='Sales OLD'!B64 -> 3342.22 | C35: ='Sales OLD'!C64 -> 3305.62 | D35: ='Sales OLD'!D64 -> 3219.49 | E35: ='Sales OLD'!E64 -> 4981.96 | F35: ='Sales OLD'!F64 -> 5362.92 | G35: ='Sales OLD'!G64 -> 4001.06 | H35: ='Sales OLD'!H64 -> 4013.79 | I35: ='Sales OLD'!I64 -> 2780.51 | ... O35: ='Sales OLD'!O64 -> 6127.83 | Q35: ='Sales OLD'!Q64 -> 8982.55 | R35: ='Sales OLD'!R64 -> 9392.78 | S35: ='Sales OLD'!S64 -> 11591.44 | T35: ='Sales OLD'!T64 -> 11126.7 | U35: ='Sales OLD'!U64 -> 17467.27 | V35: ='Sales OLD'!V64 -> 19867.53 | W35: ='Sales OLD'!W64 -> 22792.98 | X35: ='Sales OLD'!X64 -> 28816.4 | ... AE35: ='Sales OLD'!AE64 -> 433.94 | AG35: =SUM(B35:AF35) -> 340971.66
A36: Fee 15% Purchase (Backerkit) | B36: =B22*0.15 -> 0 | C36: =C22*0.15 -> 0 | D36: =D22*0.15 -> 0 | E36: =E22*0.15 -> 0 | F36: =F22*0.15 -> 0 | G36: =G22*0.15 -> 0 | H36: =H22*0.15 -> 0 | I36: =I22*0.15 -> 0 | ... S36: =S22*0.15 -> 0 | U36: =U22*0.15 -> 0 | V36: =V22*0.15 -> 0 | W36: =W22*0.15 -> 0 | X36: =X22*0.15 -> 0 | Y36: =Y22*0.15 -> 0 | Z36: =Z22*0.15 -> 0 | AA36: =AA22*0.15 -> 0 | AB36: =AB22*0.15 -> 0 | AC36: =AC22*0.15 -> 0 | AG36: =SUM(B36:AF36) -> 0
A37: Google Management Fee | AG37: =SUM(B37:AF37) -> 0
A38: Affiliates Agency Payment (Grovia) | AG38: =SUM(B38:AF38) -> 0
A39: Affiliate Fee 20% (Grovia) | B39: ='Sales OLD'!B67 -> 162.71 | C39: ='Sales OLD'!C67 -> 61 | D39: ='Sales OLD'!D67 -> 0 | E39: ='Sales OLD'!E67 -> 4255.588 | F39: ='Sales OLD'!F67 -> 2292.936 | G39: ='Sales OLD'!G67 -> 63.09 | H39: ='Sales OLD'!H67 -> 86.6 | I39: ='Sales OLD'!I67 -> 0 | ... AE39: ='Sales OLD'!AE67 -> 13.6 | AG39: =SUM(B39:AF39) -> 9391.734
A40: FB Spend (Internal Paid) | AG40: =SUM(B40:AF40) -> 0
A41: FB Spend (EU & UK) | AG41: =SUM(B41:AF41) -> 0
A42: Pinterest Spend | AG42: =SUM(B42:AF42) -> 0
A43: Amazon (market place) Spend
A44: Amazon (market place) Sales Fee (10-15 %) | B44: =B27*'OLD Formulas'!$C$41 -> 0 | C44: =C27*'OLD Formulas'!$C$41 -> 0 | D44: =D27*'OLD Formulas'!$C$41 -> 0 | E44: =E27*'OLD Formulas'!$C$41 -> 0 | F44: =F27*'OLD Formulas'!$C$41 -> 0 | G44: =G27*'OLD Formulas'!$C$41 -> 0 | H44: =H27*'OLD Formulas'!$C$41 -> 0 | I44: =I27*'OLD Formulas'!$C$41 -> 0 | ... AF44: =AF27*'OLD Formulas'!$C$41 -> 0
A45: Platform Fee (6,90%) | AG45: =SUM(B45:AF45) -> 0
A46: All | B46: =SUM(B31:B45) -> 40637.56 | C46: =SUM(C31:C45) -> 37965.01 | D46: =SUM(D31:D45) -> 40902.07 | E46: =SUM(E31:E45) -> 44501.358 | F46: =SUM(F31:F45) -> 44876.326 | G46: =SUM(G31:G45) -> 42646.49 | H46: =SUM(H31:H45) -> 38073.1 | I46: =SUM(I31:I45) -> 44740.44 | ... AF46: =SUM(AF31:AF45) -> 0 | AG46: =SUM(B46:AF46) -> 2019658.5
A48: Cost
A49: Average COGS ($92.18) | B49: =B15*'OLD Formulas'!$J$3 -> 34755.601 | C49: =C15*'OLD Formulas'!$J$3 -> 43805.536 | D49: =D15*'OLD Formulas'!$J$3 -> 39858.224 | E49: =E15*'OLD Formulas'!$J$3 -> 40147.052 | F49: =F15*'OLD Formulas'!$J$3 -> 44960.847 | G49: =G15*'OLD Formulas'!$J$3 -> 42168.846 | H49: =H15*'OLD Formulas'!$J$3 -> 36584.843 | I49: =I15*'OLD Formulas'!$J$3 -> 36103.464 | ... AF49: =AF15*'OLD Formulas'!$J$3 -> 0 | AG49: =SUM(B49:AF49) -> 1824717.2
A50: Average Inbound Shipping ($13.06) | B50: =B15*'OLD Formulas'!$I$4 -> 4714.4073 | C50: =C15*'OLD Formulas'!$I$4 -> 5941.9815 | D50: =D15*'OLD Formulas'!$I$4 -> 5406.5502 | E50: =E15*'OLD Formulas'!$I$4 -> 5445.7281 | F50: =F15*'OLD Formulas'!$I$4 -> 6098.6931 | G50: =G15*'OLD Formulas'!$I$4 -> 5719.9734 | H50: =H15*'OLD Formulas'!$I$4 -> 4962.534 | I50: =I15*'OLD Formulas'!$I$4 -> 4897.2375 | ... AF50: =AF15*'OLD Formulas'!$I$4 -> 0 | AG50: =SUM(B50:AF50) -> 247512.91
A51: Average Outbound Shipping ($15.06) | B51: =B15*'OLD Formulas'!$I$5 -> 5436.66 | C51: =C15*'OLD Formulas'!$I$5 -> 6852.3 | D51: =D15*'OLD Formulas'!$I$5 -> 6234.84 | E51: =E15*'OLD Formulas'!$I$5 -> 6280.02 | F51: =F15*'OLD Formulas'!$I$5 -> 7033.02 | G51: =G15*'OLD Formulas'!$I$5 -> 6596.28 | H51: =H15*'OLD Formulas'!$I$5 -> 5722.8 | I51: =I15*'OLD Formulas'!$I$5 -> 5647.5 | ... AF51: =AF15*'OLD Formulas'!$I$5 -> 0 | AG51: =SUM(B51:AF51) -> 285432.18
A52: Average Taxes ($16.81) | B52: =B15*'OLD Formulas'!$I$6 -> 6068.41 | C52: =C15*'OLD Formulas'!$I$6 -> 7648.55 | D52: =D15*'OLD Formulas'!$I$6 -> 6959.34 | E52: =E15*'OLD Formulas'!$I$6 -> 7009.77 | F52: =F15*'OLD Formulas'!$I$6 -> 7850.27 | G52: =G15*'OLD Formulas'!$I$6 -> 7362.78 | H52: =H15*'OLD Formulas'!$I$6 -> 6387.8 | I52: =I15*'OLD Formulas'!$I$6 -> 6303.75 | ... AF52: =AF15*'OLD Formulas'!$I$6 -> 0 | AG52: =SUM(B52:AF52) -> 318599.93
A53: Processing Fee (2,90%) | B53: =B28*'OLD Formulas'!$L$3 -> 2295.9842 | C53: =C28*'OLD Formulas'!$L$3 -> 2613.9153 | D53: =D28*'OLD Formulas'!$L$3 -> 2451.9799 | E53: =E28*'OLD Formulas'!$L$3 -> 2598.7608 | F53: =F28*'OLD Formulas'!$L$3 -> 2876.0353 | G53: =G28*'OLD Formulas'!$L$3 -> 2720.633 | H53: =H28*'OLD Formulas'!$L$3 -> 2471.8486 | I53: =I28*'OLD Formulas'!$L$3 -> 2389.6264 | ... AF53: =AF28*'OLD Formulas'!$L$3 -> 0 | AG53: =SUM(B53:AF53) -> 124290.92
A54: Transaction Fee ($0.30) | B54: =B15*'OLD Formulas'!$I$10 -> 108.3 | C54: =C15*'OLD Formulas'!$I$10 -> 136.5 | D54: =D15*'OLD Formulas'!$I$10 -> 124.2 | E54: =E15*'OLD Formulas'!$I$10 -> 125.1 | F54: =F15*'OLD Formulas'!$I$10 -> 140.1 | G54: =G15*'OLD Formulas'!$I$10 -> 131.4 | H54: =H15*'OLD Formulas'!$I$10 -> 114 | I54: =I15*'OLD Formulas'!$I$10 -> 112.5 | ... AF54: =AF15*'OLD Formulas'!$I$10 -> 0 | AG54: =SUM(B54:AF54) -> 5685.9
A55: All | B55: =SUM(B49:B54) -> 53379.363 | C55: =SUM(C49:C54) -> 66998.783 | D55: =SUM(D49:D54) -> 61035.134 | E55: =SUM(E49:E54) -> 61606.431 | F55: =SUM(F49:F54) -> 68958.965 | G55: =SUM(G49:G54) -> 64699.912 | H55: =SUM(H49:H54) -> 56243.826 | I55: =SUM(I49:I54) -> 55454.078 | ... AF55: =SUM(AF49:AF54) -> 0 | AG55: =SUM(B55:AF55) -> 2806239
AG56: =SUM(B56:AF56) -> 0
A57: Partial Profit | B57: =B28-B46-B55 -> -14845.053 | C57: =C28-C46-C55 -> -14828.783 | D57: =D28-D46-D55 -> -17386.174 | E57: =E28-E46-E55 -> -16495.349 | F57: =F28-F46-F55 -> -14661.661 | G57: =G28-G46-G55 -> -13531.472 | H57: =H28-H46-H55 -> -9080.7659 | I57: =I28-I46-I55 -> -17793.608 | ... AF57: =AF28-AF46-AF55 -> 0 | AG57: =SUM(B57:AF57) -> -540003.75
A58: =SUM(B57:AC57) -> -523787.19
A62: Performance Facebook US & CA | Z62: 3.11 | AA62: 1.8
A63: PROFIT | B63: =B18-(B5*'OLD Formulas'!$I$15)-B31 -> -13898.243 | C63: =C18-(C5*'OLD Formulas'!$I$15)-C31 -> -9219.808 | D63: =D18-(D5*'OLD Formulas'!$I$15)-D31 -> -14823.503 | E63: =E18-(E5*'OLD Formulas'!$I$15)-E31 -> -9748.3968 | F63: =F18-(F5*'OLD Formulas'!$I$15)-F31 -> -6904.312 | G63: =G18-(G5*'OLD Formulas'!$I$15)-G31 -> -9908.3258 | H63: =H18-(H5*'OLD Formulas'!$I$15)-H31 -> -7613.98 | I63: =I18-(I5*'OLD Formulas'!$I$15)-I31 -> -15360.299 | ... AF63: =AF18-(AF5*'OLD Formulas'!$I$15)-AF31 -> 0 | AG63: =SUM(B63:AF63) -> -479554.29
A64: ROAS | B64: =B18/B31 -> 1.6651933 | C64: =C18/C31 -> 2.0293139 | D64: =D18/D31 -> 1.7351832 | E64: =E18/E31 -> 2.0346202 | F64: =F18/F31 -> 2.3551434 | G64: =G18/G31 -> 2.0515432 | H64: =H18/H31 -> 2.0521726 | I64: =I18/I31 -> 1.5041651 | ... AF64: =AF18/AF31 -> #DIV/0!
A65: CPO | B65: =B31/B5 -> 135.5916 | C65: =C31/C5 -> 110.30095 | D65: =D31/D5 -> 123.0431 | E65: =E31/E5 -> 107.51812 | F65: =F31/F5 -> 92.834521 | G65: =G31/G5 -> 107.16714 | H65: =H31/H5 -> 110.16498 | I65: =I31/I5 -> 152.35785 | ... AF65: =AF31/AF5 -> #DIV/0!
A66: MER | B66: =B18/('OLD Formulas'!$I$15*B5+B31) -> 0.79451218 | C66: =C18/('OLD Formulas'!$I$15*C5+C31) -> 0.86459078 | D66: =D18/('OLD Formulas'!$I$15*D5+D31) -> 0.78599347 | E66: =E18/('OLD Formulas'!$I$15*E5+E31) -> 0.8541628 | F66: =F18/('OLD Formulas'!$I$15*F5+F31) -> 0.90561666 | G66: =G18/('OLD Formulas'!$I$15*G5+G31) -> 0.85963384 | H66: =H18/('OLD Formulas'!$I$15*H5+H31) -> 0.87371084 | I66: =I18/('OLD Formulas'!$I$15*I5+I31) -> 0.76149704 | ... AF66: =AF18/('OLD Formulas'!$I$15*AF5+AF31) -> #DIV/0!
A68: Performance Google
A69: PROFIT | B69: =B19-(B6*'OLD Formulas'!$I$15)-B32 -> 3209.2423 | C69: =C19-(C6*'OLD Formulas'!$I$15)-C32 -> 4327.6563 | D69: =D19-(D6*'OLD Formulas'!$I$15)-D32 -> 3539.6727 | E69: =E19-(E6*'OLD Formulas'!$I$15)-E32 -> 2976.2931 | F69: =F19-(F6*'OLD Formulas'!$I$15)-F32 -> 404.52411 | G69: =G19-(G6*'OLD Formulas'!$I$15)-G32 -> 2319.7377 | H69: =H19-(H6*'OLD Formulas'!$I$15)-H32 -> 3076.6155 | I69: =I19-(I6*'OLD Formulas'!$I$15)-I32 -> 2669.2037 | ... AF69: =AF19-(AF6*'OLD Formulas'!$I$15)-AF32 -> 0 | AG69: =SUM(B69:AF69) -> 254019.15
A70: ROAS | B70: =B19/B32 -> 4.7662032 | C70: =C19/C32 -> 4.7638222 | D70: =D19/D32 -> 4.3472685 | E70: =E19/E32 -> 4.1914549 | F70: =F19/F32 -> 3.4499421 | G70: =G19/G32 -> 3.6351253 | H70: =H19/H32 -> 3.7123082 | I70: =I19/I32 -> 3.4095677 | ... AF70: =AF19/AF32 -> #DIV/0!
A71: CPO | B71: =B32/B6 -> 48.329896 | C71: =C32/C6 -> 50.325849 | D71: =D32/D6 -> 53.833393 | E71: =E32/E6 -> 53.844687 | F71: =F32/F6 -> 61.805315 | G71: =G32/G6 -> 62.814088 | H71: =H32/H6 -> 63.931532 | I71: =I32/I6 -> 70.38937 | ... AF71: =AF32/AF6 -> #DIV/0!
A72: MER | B72: =B19/('OLD Formulas'!$I$15*B6+B32) -> 1.169762 | C72: =C19/('OLD Formulas'!$I$15*C6+C32) -> 1.2052467 | D72: =D19/('OLD Formulas'!$I$15*D6+D32) -> 1.1561288 | E72: =E19/('OLD Formulas'!$I$15*E6+E32) -> 1.1148628 | F72: =F19/('OLD Formulas'!$I$15*F6+F32) -> 1.0134453 | G72: =G19/('OLD Formulas'!$I$15*G6+G32) -> 1.0800947 | H72: =H19/('OLD Formulas'!$I$15*H6+H32) -> 1.1167474 | I72: =I19/('OLD Formulas'!$I$15*I6+I32) -> 1.0959784 | ... AF72: =AF19/('OLD Formulas'!$I$15*AF6+AF32) -> #DIV/0!
A74: Performance TikTok
A75: PROFIT | B75: =B20-(B7*'OLD Formulas'!$I$15)-B33 -> 0 | C75: =C20-(C7*'OLD Formulas'!$I$15)-C33 -> 0 | D75: =D20-(D7*'OLD Formulas'!$I$15)-D33 -> 0 | E75: =E20-(E7*'OLD Formulas'!$I$15)-E33 -> 0 | F75: =F20-(F7*'OLD Formulas'!$I$15)-F33 -> 0 | G75: =G20-(G7*'OLD Formulas'!$I$15)-G33 -> 0 | H75: =H20-(H7*'OLD Formulas'!$I$15)-H33 -> 0 | I75: =I20-(I7*'OLD Formulas'!$I$15)-I33 -> 0 | J75: =J20-(J8*'OLD Formulas'!$I$15)-J33 -> -2377.4496 | K75: =K20-(K7*'OLD Formulas'!$I$15)-K33 -> 0 | L75: =L20-(L7*'OLD Formulas'!$I$15)-L33 -> 0 | M75: =M20-(M7*'OLD Formulas'!$I$15)-M33 -> 0 | N75: =N20-(N7*'OLD Formulas'!$I$15)-N33 -> 0 | O75: =O20-(O7*'OLD Formulas'!$I$15)-O33 -> 0 | P75: =P20-(P7*'OLD Formulas'!$I$15)-P33 -> -6588.6 | Q75: =Q20-(Q7*'OLD Formulas'!$I$15)-Q33 -> -400.43 | R75: =R20-(R7*'OLD Formulas'!$I$15)-R33 -> -189.07 | ... AF75: =AF20-(AF7*'OLD Formulas'!$I$15)-AF33 -> 0 | AG75: =SUM(B75:AF75) -> -9555.5496
A76: ROAS | B76: =B20/B33 -> #DIV/0! | C76: =C20/C33 -> #DIV/0! | D76: =D20/D33 -> #DIV/0! | E76: =E20/E33 -> #DIV/0! | F76: =F20/F33 -> #DIV/0! | G76: =G20/G33 -> #DIV/0! | H76: =H20/H33 -> #DIV/0! | I76: =I20/I33 -> #DIV/0! | ... AF76: =AF20/AF33 -> #DIV/0!
A77: CPO | B77: =B33/B7 -> #DIV/0! | C77: =C33/C7 -> #DIV/0! | D77: =D33/D7 -> #DIV/0! | E77: =E33/E7 -> #DIV/0! | F77: =F33/F7 -> #DIV/0! | G77: =G33/G7 -> #DIV/0! | H77: =H33/H7 -> #DIV/0! | I77: =I33/I7 -> #DIV/0! | J77: =J33/J8 -> 0 | K77: =K33/K7 -> #DIV/0! | L77: =L33/L7 -> #DIV/0! | M77: =M33/M7 -> #DIV/0! | N77: =N33/N7 -> #DIV/0! | O77: =O33/O7 -> #DIV/0! | P77: =P33/P7 -> #DIV/0! | Q77: =Q33/Q7 -> #DIV/0! | R77: =R33/R7 -> #DIV/0! | ... AF77: =AF33/AF7 -> #DIV/0!
A78: MER | B78: =B20/('OLD Formulas'!$I$15*B7+B33) -> #DIV/0! | C78: =C20/('OLD Formulas'!$I$15*C7+C33) -> #DIV/0! | D78: =D20/('OLD Formulas'!$I$15*D7+D33) -> #DIV/0! | E78: =E20/('OLD Formulas'!$I$15*E7+E33) -> #DIV/0! | F78: =F20/('OLD Formulas'!$I$15*F7+F33) -> #DIV/0! | G78: =G20/('OLD Formulas'!$I$15*G7+G33) -> #DIV/0! | H78: =H20/('OLD Formulas'!$I$15*H7+H33) -> #DIV/0! | I78: =I20/('OLD Formulas'!$I$15*I7+I33) -> #DIV/0! | J78: =J20/('OLD Formulas'!$I$15*J8+J33) -> 0 | K78: =K20/('OLD Formulas'!$I$15*K7+K33) -> #DIV/0! | L78: =L20/('OLD Formulas'!$I$15*L7+L33) -> #DIV/0! | M78: =M20/('OLD Formulas'!$I$15*M7+M33) -> #DIV/0! | N78: =N20/('OLD Formulas'!$I$15*N7+N33) -> #DIV/0! | O78: =O20/('OLD Formulas'!$I$15*O7+O33) -> #DIV/0! | P78: =P20/('OLD Formulas'!$I$15*P7+P33) -> 0 | Q78: =Q20/('OLD Formulas'!$I$15*Q7+Q33) -> 0 | R78: =R20/('OLD Formulas'!$I$15*R7+R33) -> 0 | ... AF78: =AF20/('OLD Formulas'!$I$15*AF7+AF33) -> #DIV/0!
A80: Performance Bing
A81: PROFIT | B81: =B21-(B8*'OLD Formulas'!$I$15)-B34 -> -1280.7444 | C81: =C21-(C8*'OLD Formulas'!$I$15)-C34 -> -2473.0468 | D81: =D21-(D8*'OLD Formulas'!$I$15)-D34 -> -1457.0244 | E81: =E21-(E8*'OLD Formulas'!$I$15)-E34 -> -791.15201 | F81: =F21-(F8*'OLD Formulas'!$I$15)-F34 -> -1099.6308 | G81: =G21-(G8*'OLD Formulas'!$I$15)-G34 -> -2428.3744 | H81: =H21-(H8*'OLD Formulas'!$I$15)-H34 -> -948.02321 | I81: =I21-(I8*'OLD Formulas'!$I$15)-I34 -> -2589.4004 | ... AF81: =AF21-(AF8*'OLD Formulas'!$I$15)-AF34 -> 0 | AG81: =SUM(B81:AF81) -> -12747.21
A82: ROAS | B82: =B21/B34 -> 11.287315 | C82: =C21/C34 -> 7.6254024 | D82: =D21/D34 -> 8.607394 | E82: =E21/E34 -> 8.0466619 | F82: =F21/F34 -> 7.2142434 | G82: =G21/G34 -> 3.8539179 | H82: =H21/H34 -> 7.1603408 | I82: =I21/I34 -> 6.9213272 | ... AF82: =AF21/AF34 -> #DIV/0!
A83: CPO | B83: =B34/B8 -> 9.2566667 | C83: =C34/C8 -> 9.0964286 | D83: =D34/D8 -> 11.552083 | E83: =E34/E8 -> 15.473 | F83: =F34/F8 -> 14.080556 | G83: =G34/G8 -> 16.611667 | H83: =H34/H8 -> 17.125455 | I83: =I34/I8 -> 12.232353 | ... AF83: =AF34/AF8 -> #DIV/0!
A84: MER | B84: =B21/('OLD Formulas'!$I$15*B8+B34) -> 0.66192414 | C84: =C21/('OLD Formulas'!$I$15*C8+C34) -> 0.43988354 | D84: =D21/('OLD Formulas'!$I$15*D8+D34) -> 0.62090463 | E84: =E21/('OLD Formulas'!$I$15*E8+E34) -> 0.75888862 | F84: =F21/('OLD Formulas'!$I$15*F8+F34) -> 0.62445339 | G84: =G21/('OLD Formulas'!$I$15*G8+G34) -> 0.38752495 | H84: =H21/('OLD Formulas'!$I$15*H8+H34) -> 0.73996506 | I84: =I21/('OLD Formulas'!$I$15*I8+I34) -> 0.526443 | J84: =J21/('OLD Formulas'!$I$15*#REF!+J34) -> #REF! | K84: =K21/('OLD Formulas'!$I$15*K8+K34) -> 0.74929578 | L84: =L21/('OLD Formulas'!$I$15*L8+L34) -> 0.7832494 | M84: =M21/('OLD Formulas'!$I$15*M8+M34) -> 1.3800391 | N84: =N21/('OLD Formulas'!$I$15*N8+N34) -> 1.2806925 | O84: =O21/('OLD Formulas'!$I$15*O8+O34) -> 1.2575083 | P84: =P21/('OLD Formulas'!$I$15*P8+P34) -> 1.217523 | Q84: =Q21/('OLD Formulas'!$I$15*Q8+Q34) -> 1.2281237 | R84: =R21/('OLD Formulas'!$I$15*R8+R34) -> 1.3485056 | ... AD84: =AD21/('OLD Formulas'!$I$15*AD8+AD34) -> 1.0371399 | AE84: =AE35/AE9 -> #DIV/0! | AF84: =AF35/AF9 -> #DIV/0!
A86: MNTN TV
A87: PROFIT | B87: =B22-(B9*Formulas!$C32)-B35 -> #REF! | C87: =C22-(C9*Formulas!$C32)-C35 -> #REF! | D87: =D22-(D9*Formulas!$C32)-D35 -> #REF! | E87: =E22-(E9*Formulas!$C32)-E35 -> #REF! | F87: =F22-(F9*Formulas!$C32)-F35 -> #REF! | G87: =G22-(G9*Formulas!$C32)-G35 -> #REF! | H87: =H22-(H9*Formulas!$C32)-H35 -> #REF! | I87: =I22-(I9*Formulas!$C32)-I35 -> #REF! | ... AF87: =AF22-(AF9*Formulas!$C32)-AF35 -> #REF! | AG87: =SUM(B87:AF87) -> #REF!
A88: ROAS | B88: =B22/B35 -> 0 | C88: =C22/C35 -> 0 | D88: =D22/D35 -> 0 | E88: =E22/E35 -> 0 | F88: =F22/F35 -> 0 | G88: =G22/G35 -> 0 | H88: =H22/H35 -> 0 | I88: =I22/I35 -> 0 | ... AF88: =AF22/AF35 -> #DIV/0!
A89: CPO | B89: =B35/B9 -> #DIV/0! | C89: =C35/C9 -> #DIV/0! | D89: =D35/D9 -> #DIV/0! | E89: =E35/E9 -> #DIV/0! | F89: =F35/F9 -> #DIV/0! | G89: =G35/G9 -> #DIV/0! | H89: =H35/H9 -> #DIV/0! | I89: =I35/I9 -> #DIV/0! | ... AF89: =AF35/AF9 -> #DIV/0!
A90: MER | B90: =B22/(Formulas!$C32*B9+B35) -> #REF! | C90: =C22/(Formulas!$C32*C9+C35) -> #REF! | D90: =D22/(Formulas!$C32*D9+D35) -> #REF! | E90: =E22/(Formulas!$C32*E9+E35) -> #REF! | F90: =F22/(Formulas!$C32*F9+F35) -> #REF! | G90: =G22/(Formulas!$C32*G9+G35) -> #REF! | H90: =H22/(Formulas!$C32*H9+H35) -> #REF! | I90: =I22/(Formulas!$C32*I9+I35) -> #REF! | ... AF90: =AF22/(Formulas!$C32*AF9+AF35) -> #REF!
A92: Affiliates (Grovia)
A93: PROFIT | AG93: =SUM(B93:AF93) -> 0
A94: ROAS
A95: CPO
A96: MER
A98: Performance Internal Paid
A99: PROFIT | AG99: =SUM(B99:AF99) -> 0
A100: ROAS
A101: CPO
A102: MER
A104: Performance EU & UK
A105: PROFIT | AG105: =SUM(B105:AF105) -> 0
A106: ROAS
A107: CPO
A108: MER
A111: Performance Email
A112: PROFIT | B112: =B26-(B13*'OLD Formulas'!$I$15) -> 0 | C112: =C26-(C13*'OLD Formulas'!$I$15) -> -4802.3142 | D112: =D26-(D13*'OLD Formulas'!$I$15) -> -1907.2038 | E112: =E26-(E13*'OLD Formulas'!$I$15) -> -331.8636 | F112: =F26-(F13*'OLD Formulas'!$I$15) -> 0 | G112: =G26-(G13*'OLD Formulas'!$I$15) -> 0 | H112: =H26-(H13*'OLD Formulas'!$I$15) -> 0 | I112: =I26-(I13*'OLD Formulas'!$I$15) -> 0 | ... AE112: =AE26-(AE13*'OLD Formulas'!$I$15) -> -137.4512 | AG112: =SUM(B112:AF112) -> 39907.225
A113: ROAS
A114: CPO
A115: MER | B115: =B26/('OLD Formulas'!$I$15*B13) -> #DIV/0! | C115: =C26/('OLD Formulas'!$I$15*C13) -> 0.43299827 | D115: =D26/('OLD Formulas'!$I$15*D13) -> 0.44194381 | E115: =E26/('OLD Formulas'!$I$15*E13) -> 0.62776515 | F115: =F26/('OLD Formulas'!$I$15*F13) -> #DIV/0! | G115: =G26/('OLD Formulas'!$I$15*G13) -> #DIV/0! | H115: =H26/('OLD Formulas'!$I$15*H13) -> #DIV/0! | I115: =I26/('OLD Formulas'!$I$15*I13) -> #DIV/0! | ... AE115: =AE26/('OLD Formulas'!$I$15*AE13) -> 0.53748353
...

Sheet AMAZON Detailed Report OLD
A1: September | B1: 45231 | C1: 45232 | D1: 45233 | E1: 45234 | F1: 45235 | G1: 45236 | H1: 45237 | I1: 45238 | J1: 45239 | K1: 45240 | L1: 45241 | M1: 45242 | N1: 45243 | O1: 45244 | P1: 45245 | Q1: 45246 | R1: 45247 | S1: 45248 | T1: 45249 | U1: 45250 | V1: 45251 | W1: 45252 | X1: 45253 | Y1: 45254 | Z1: 45255 | AA1: 45256 | AB1: 45257 | AC1: 45258 | AD1: 45259 | AE1: 45260
A2: DAY | B2: WED | C2: THU | D2: FRI | E2: SAT | F2: SUN | G2: MON | H2: TUE | I2: WED | J2: THU | K2: FRI | L2: SAT | M2: SUN | N2: MON | O2: TUE | P2: WED | Q2: THU | R2: FRI | S2: SAT | T2: SUN | U2: MON | V2: TUE | W2: WED | X2: THU | Y2: FRI | Z2: SAT | AA2: SUN | AB2: MON | AC2: TUE | AD2: WED | AE2: THU
A3: COMMENT
A4: Orders
A5: Amazon (market place) | B5: ='Sales OLD'!B43 -> 49 | C5: ='Sales OLD'!C43 -> 41 | D5: ='Sales OLD'!D43 -> 55 | E5: ='Sales OLD'!E43 -> 65 | F5: ='Sales OLD'!F43 -> 73 | G5: ='Sales OLD'!G43 -> 57 | H5: ='Sales OLD'!H43 -> 48 | I5: ='Sales OLD'!I43 -> 66 | ... AE5: ='Sales OLD'!AE43 -> 3
A6: All | B6: =SUM(B5) -> 49 | C6: =SUM(C5) -> 41 | D6: =SUM(D5) -> 55 | E6: =SUM(E5) -> 65 | F6: =SUM(F5) -> 73 | G6: =SUM(G5) -> 57 | H6: =SUM(H5) -> 48 | I6: =SUM(I5) -> 66 | ... AE6: =SUM(AE5) -> 3 | AG6: =SUM(B6:AE6) -> 10815
A8: Revenue
A9: Amazon (market place) | B9: ='Sales OLD'!B14 -> 12580 | C9: ='Sales OLD'!C14 -> 10507.85 | D9: ='Sales OLD'!D14 -> 15542.85 | E9: ='Sales OLD'!E14 -> 17880 | F9: ='Sales OLD'!F14 -> 19835.85 | G9: ='Sales OLD'!G14 -> 16025 | H9: ='Sales OLD'!H14 -> 13308.85 | I9: ='Sales OLD'!I14 -> 15064.85 | ... AE9: ='Sales OLD'!AE14 -> 507
A10: All | B10: =SUM(B9) -> 12580 | C10: =SUM(C9) -> 10507.85 | D10: =SUM(D9) -> 15542.85 | E10: =SUM(E9) -> 17880 | F10: =SUM(F9) -> 19835.85 | G10: =SUM(G9) -> 16025 | H10: =SUM(H9) -> 13308.85 | I10: =SUM(I9) -> 15064.85 | ... AE10: =SUM(AE9) -> 507 | AG10: =SUM(B10:AE10) -> 2292627.2
A12: Media Cost
A13: Amazon (market place) Spend | B13: ='Sales OLD'!B64 -> 3342.22 | C13: ='Sales OLD'!C64 -> 3305.62 | D13: ='Sales OLD'!D64 -> 3219.49 | E13: ='Sales OLD'!E64 -> 4981.96 | F13: ='Sales OLD'!F64 -> 5362.92 | G13: ='Sales OLD'!G64 -> 4001.06 | H13: ='Sales OLD'!H64 -> 4013.79 | I13: ='Sales OLD'!I64 -> 2780.51 | ... AE13: ='Sales OLD'!AE64 -> 433.94
A14: Amazon (market place) Sales Fee (10-15 %) | B14: =B9*'OLD Formulas'!$C$41 -> 1258 | C14: =C9*'OLD Formulas'!$C$41 -> 1050.785 | D14: =D9*'OLD Formulas'!$C$41 -> 1554.285 | E14: =E9*'OLD Formulas'!$C$41 -> 1788 | F14: =F9*'OLD Formulas'!$C$41 -> 1983.585 | G14: =G9*'OLD Formulas'!$C$41 -> 1602.5 | H14: =H9*'OLD Formulas'!$C$41 -> 1330.885 | I14: =I9*'OLD Formulas'!$C$41 -> 1506.485 | ... AE14: =AE9*'OLD Formulas'!$C$41 -> 50.7
A15: Platform Fee | AG15: =SUM(B15:AE15) -> 0
A16: All | B16: =SUM(B13:B15) -> 4600.22 | C16: =SUM(C13:C15) -> 4356.405 | D16: =SUM(D13:D15) -> 4773.775 | E16: =SUM(E13:E15) -> 6769.96 | F16: =SUM(F13:F15) -> 7346.505 | G16: =SUM(G13:G15) -> 5603.56 | H16: =SUM(H13:H15) -> 5344.675 | I16: =SUM(I13:I15) -> 4286.995 | ... AE16: =SUM(AE13:AE15) -> 484.64 | AG16: =SUM(B16:AE16) -> 576822.98
A18: Cost
A19: Average COGS ($92.26) | B19: =B6*'OLD Formulas'!$A$37 -> 4520.495 | C19: =C6*'OLD Formulas'!$A$37 -> 3782.455 | D19: =D6*'OLD Formulas'!$A$37 -> 5074.025 | E19: =E6*'OLD Formulas'!$A$37 -> 5996.575 | F19: =F6*'OLD Formulas'!$A$37 -> 6734.615 | G19: =G6*'OLD Formulas'!$A$37 -> 5258.535 | H19: =H6*'OLD Formulas'!$A$37 -> 4428.24 | I19: =I6*'OLD Formulas'!$A$37 -> 6088.83 | ... AE19: =AE6*'OLD Formulas'!$A$37 -> 276.765 | AG19: =SUM(B19:AE19) -> 997737.82
A20: Average Inbound Shipping ($11.94+KCTC) | B20: =(B6*'OLD Formulas'!$C$32)+(B6*'OLD Formulas'!$A$40) -> 670.81 | C20: =(C6*'OLD Formulas'!$C$32)+(C6*'OLD Formulas'!$A$40) -> 561.29 | D20: =(D6*'OLD Formulas'!$C$32)+(D6*'OLD Formulas'!$A$40) -> 752.95 | E20: =(E6*'OLD Formulas'!$C$32)+(E6*'OLD Formulas'!$A$40) -> 889.85 | F20: =(F6*'OLD Formulas'!$C$32)+(F6*'OLD Formulas'!$A$40) -> 999.37 | G20: =(G6*'OLD Formulas'!$C$32)+(G6*'OLD Formulas'!$A$40) -> 780.33 | H20: =(H6*'OLD Formulas'!$C$32)+(H6*'OLD Formulas'!$A$40) -> 657.12 | I20: =(I6*'OLD Formulas'!$C$32)+(I6*'OLD Formulas'!$A$40) -> 903.54 | ... AE20: =(AE6*'OLD Formulas'!$C$32)+(AE6*'OLD Formulas'!$A$40) -> 41.07 | AG20: =SUM(B20:AE20) -> 148057.35
A21: Average Amazon Inbound | B21: =B313*'OLD Formulas'!$C$37 -> 0 | C21: =C313*'OLD Formulas'!$C$37 -> 0 | D21: =D313*'OLD Formulas'!$C$37 -> 0 | E21: =E313*'OLD Formulas'!$C$37 -> 0 | F21: =F313*'OLD Formulas'!$C$37 -> 0 | G21: =G313*'OLD Formulas'!$C$37 -> 0 | H21: =H313*'OLD Formulas'!$C$37 -> 0 | I21: =I313*'OLD Formulas'!$C$37 -> 0 | ... AE21: =AE313*'OLD Formulas'!$C$37 -> 0 | AG21: =SUM(B21:AE21) -> 0
A22: Average Amazon Storage fee | B22: =B313*'OLD Formulas'!$C$38 -> 0 | C22: =C313*'OLD Formulas'!$C$38 -> 0 | D22: =D313*'OLD Formulas'!$C$38 -> 0 | E22: =E313*'OLD Formulas'!$C$38 -> 0 | F22: =F313*'OLD Formulas'!$C$38 -> 0 | G22: =G313*'OLD Formulas'!$C$38 -> 0 | H22: =H313*'OLD Formulas'!$C$38 -> 0 | I22: =I313*'OLD Formulas'!$C$38 -> 0 | ... AE22: =AE313*'OLD Formulas'!$C$38 -> 0 | AG22: =SUM(B22:AE22) -> 0
A23: Average FBA fee ($11.94) | B23: =B6*'OLD Formulas'!$C$40 -> 585.06 | C23: =C6*'OLD Formulas'!$C$40 -> 489.54 | D23: =D6*'OLD Formulas'!$C$40 -> 656.7 | E23: =E6*'OLD Formulas'!$C$40 -> 776.1 | F23: =F6*'OLD Formulas'!$C$40 -> 871.62 | G23: =G6*'OLD Formulas'!$C$40 -> 680.58 | H23: =H6*'OLD Formulas'!$C$40 -> 573.12 | I23: =I6*'OLD Formulas'!$C$40 -> 788.04 | ... AE23: =AE6*'OLD Formulas'!$C$40 -> 35.82 | AG23: =SUM(B23:AE23) -> 129131.1
A24: Average Sales fee | B24: =B10*'OLD Formulas'!$C$41 -> 1258 | C24: =C10*'OLD Formulas'!$C$41 -> 1050.785 | D24: =D10*'OLD Formulas'!$C$41 -> 1554.285 | E24: =E10*'OLD Formulas'!$C$41 -> 1788 | F24: =F10*'OLD Formulas'!$C$41 -> 1983.585 | G24: =G10*'OLD Formulas'!$C$41 -> 1602.5 | H24: =H10*'OLD Formulas'!$C$41 -> 1330.885 | I24: =I10*'OLD Formulas'!$C$41 -> 1506.485 | ... AE24: =AE10*'OLD Formulas'!$C$41 -> 50.7 | AG24: =SUM(B24:AE24) -> 229262.72
A25: All | B25: =SUM(B19:B24) -> 7034.365 | C25: =SUM(C19:C24) -> 5884.07 | D25: =SUM(D19:D24) -> 8037.96 | E25: =SUM(E19:E24) -> 9450.525 | F25: =SUM(F19:F24) -> 10589.19 | G25: =SUM(G19:G24) -> 8321.945 | H25: =SUM(H19:H24) -> 6989.365 | I25: =SUM(I19:I24) -> 9286.895 | ... AE25: =SUM(AE19:AE24) -> 404.355 | AG25: =SUM(B25:AE25) -> 1504189
AG26: =SUM(B26:AE26) -> 0
A27: Partial Profit | B27: =B10-B16-B25 -> 945.415 | C27: =C10-C16-C25 -> 267.375 | D27: =D10-D16-D25 -> 2731.115 | E27: =E10-E16-E25 -> 1659.515 | F27: =F10-F16-F25 -> 1900.155 | G27: =G10-G16-G25 -> 2099.495 | H27: =H10-H16-H25 -> 974.81 | I27: =I10-I16-I25 -> 1490.96 | ... AE27: =AE10-AE16-AE25 -> -381.995 | AG27: =SUM(B27:AE27) -> 211615.21
A28: =SUM(B27:AC27) -> 211997.2
A32: AMAZON (marketplace)
A33: PROFIT | B33: =B9-(B5*'OLD Formulas'!$A$43)-B13 -> 3338.425 | C33: =C9-(C5*'OLD Formulas'!$A$43)-C13 -> 2266.035 | D33: =D9-(D5*'OLD Formulas'!$A$43)-D13 -> 5701.635 | E33: =E9-(E5*'OLD Formulas'!$A$43)-E13 -> 5072.365 | F33: =F9-(F5*'OLD Formulas'!$A$43)-F13 -> 5684.095 | G33: =G9-(G5*'OLD Formulas'!$A$43)-G13 -> 5161.425 | H33: =H9-(H5*'OLD Formulas'!$A$43)-H13 -> 3516.1 | I33: =I9-(I5*'OLD Formulas'!$A$43)-I13 -> 4338.27 | ... AF33: =AF9-(AF5*'OLD Formulas'!$A$43)-AF13 -> 0
A34: ROAS | B34: =B9/B13 -> 3.7639653 | C34: =C9/C13 -> 3.1787834 | D34: =D9/D13 -> 4.8277367 | E34: =E9/E13 -> 3.5889489 | F34: =F9/F13 -> 3.6987033 | G34: =G9/G13 -> 4.0051886 | H34: =H9/H13 -> 3.3157813 | I34: =I9/I13 -> 5.4180168 | ... AF34: =AF9/AF13 -> #DIV/0!
A35: CPO | B35: =B13/B5 -> 68.208571 | C35: =C13/C5 -> 80.624878 | D35: =D13/D5 -> 58.536182 | E35: =E13/E5 -> 76.645538 | F35: =F13/F5 -> 73.464658 | G35: =G13/G5 -> 70.194035 | H35: =H13/H5 -> 83.620625 | I35: =I13/I5 -> 42.128939 | ... AF35: =AF13/AF5 -> #DIV/0!
A36: MER | B36: =B9/('OLD Formulas'!$A$43*B5+B13+B14) -> 1.1981437 | C36: =C9/('OLD Formulas'!$A$43*C5+C13+C14) -> 1.1307761 | D36: =D9/('OLD Formulas'!$A$43*D5+D13+D14) -> 1.3639463 | E36: =E9/('OLD Formulas'!$A$43*E5+E13+E14) -> 1.2250238 | F36: =F9/('OLD Formulas'!$A$43*F5+F13+F14) -> 1.2293419 | G36: =G9/('OLD Formulas'!$A$43*G5+G13+G14) -> 1.2854888 | H36: =H9/('OLD Formulas'!$A$43*H5+H13+H14) -> 1.1964479 | I36: =I9/('OLD Formulas'!$A$43*I5+I13+I14) -> 1.2314861 | ... AF36: =AF9/('OLD Formulas'!$A$43*AF5+AF13+AF14) -> #DIV/0!
A40: Units Sold (Gross)
A41: Bird Buddy - Blue | B41: 12 | C41: 6 | D41: 6 | E41: 3 | F41: 9 | G41: 7 | H41: 7 | I41: 21 | J41: 25 | K41: 10 | L41: 18 | M41: 15 | N41: 19 | O41: 25 | P41: 19 | Q41: 13 | R41: 17 | S41: 16 | T41: 35 | U41: 0 | V41: 3 | W41: 0 | X41: 2 | Y41: 0 | Z41: 0 | AA41: 0 | AB41: 0 | AC41: 0 | AD41: 0 | AE41: 0 | AG41: =sum(B41:AE41) -> 288
A42: Bird Buddy - Yellow | B42: 0 | C42: 0 | D42: 0 | E42: 0 | F42: 1 | G42: 2 | H42: 1 | I42: 4 | J42: 3 | K42: 2 | L42: 3 | M42: 2 | N42: 3 | O42: 1 | P42: 0 | Q42: 0 | R42: 0 | S42: 237 | T42: 0 | U42: 0 | V42: 0 | W42: 0 | X42: 0 | Y42: 1 | Z42: 0 | AA42: 0 | AB42: 0 | AC42: 0 | AD42: 0 | AE42: 0 | AG42: =SUM(B42:AF42) -> 260
A43: Bird Buddy with Solar Roof - Blue | B43: 32 | C43: 29 | D43: 47 | E43: 54 | F43: 55 | G43: 43 | H43: 38 | I43: 18 | J43: 75 | K43: 98 | L43: 140 | M43: 140 | N43: 127 | O43: 125 | P43: 152 | Q43: 171 | R43: 206 | S43: 15 | T43: 140 | U43: 490 | V43: 488 | W43: 553 | X43: 874 | Y43: 3288 | Z43: 1152 | AA43: 1126 | AB43: 19 | AC43: 0 | AD43: 0 | AE43: 0 | AG43: =sum(B43:AF43) -> 9695
A44: Bird Buddy with Solar Roof - Yellow | B44: 0 | C44: 1 | D44: 0 | E44: 3 | F44: 3 | G44: 3 | H44: 0 | I44: 14 | J44: 10 | K44: 4 | L44: 7 | M44: 8 | N44: 3 | O44: 11 | P44: 7 | Q44: 8 | R44: 13 | S44: 293 | T44: 0 | U44: 1 | V44: 2 | W44: 0 | X44: 3 | Y44: 5 | Z44: 0 | AA44: 0 | AB44: 0 | AC44: 0 | AD44: 0 | AE44: 0 | AG44: =sum(B44:AF44) -> 399
A45: All Bird Buddy | B45: =SUM(B41:B44) -> 44 | C45: =SUM(C41:C44) -> 36 | D45: =SUM(D41:D44) -> 53 | E45: =SUM(E41:E44) -> 60 | F45: =SUM(F41:F44) -> 68 | G45: =SUM(G41:G44) -> 55 | H45: =SUM(H41:H44) -> 46 | I45: =SUM(I41:I44) -> 57 | ... AF45: =SUM(AF41:AF44) -> 0 | AG45: =sum(B45:AE45) -> 10642
A47: Wall Mount | B47: 6 | C47: 5 | D47: 3 | E47: 5 | F47: 5 | G47: 5 | H47: 2 | I47: 13 | J47: 6 | K47: 4 | L47: 12 | M47: 11 | N47: 3 | O47: 9 | P47: 13 | Q47: 20 | R47: 25 | S47: 24 | T47: 32 | U47: 38 | V47: 40 | W47: 34 | X47: 66 | Y47: 183 | Z47: 8 | AA47: 9 | AB47: 0 | AC47: 0 | AD47: 0 | AE47: 0 | AG47: =sum(B47:AE47) -> 581
A48: Fence Mount | AG48: =sum(B48:AE48) -> 0
A49: Suet Ball Holder | AG49: =sum(B49:AE49) -> 0
A50: 3-in-1 Nutrition Set - Blue | AG50: =sum(B50:AE50) -> 0
A51: 3-in-1 Nutrition Set - Yellow | AG51: =sum(B51:AE51) -> 0
A52: Solar Roof Single - Blue | AG52: =sum(B52:AE52) -> 0
A53: Solar Roof Single - Yellow | AG53: =sum(B53:AE53) -> 0
A54: Perch Extender - Blue | AG54: =sum(B54:AE54) -> 0
A55: Perch Extender - Yellow | B55: 0 | C55: 0 | D55: 0 | E55: 0 | F55: 0 | G55: 0 | H55: 0 | I55: 0 | J55: 0 | K55: 0 | L55: 0 | M55: 0 | N55: 0 | O55: 0 | P55: 0 | Q55: 0 | R55: 0 | S55: 0 | T55: 0 | U55: 0 | V55: 0 | W55: 0 | X55: 1 | Y55: 0 | Z55: 0 | AA55: 0 | AB55: 0 | AC55: 0 | AD55: 0 | AE55: 0 | AG55: =sum(B55:AE55) -> 1
A56: All | B56: =SUM(B47:B55) -> 6 | C56: =SUM(C47:C55) -> 5 | D56: =SUM(D47:D55) -> 3 | E56: =SUM(E47:E55) -> 5 | F56: =SUM(F47:F55) -> 5 | G56: =SUM(G47:G55) -> 5 | H56: =SUM(H47:H55) -> 2 | I56: =SUM(I47:I55) -> 13 | ... AF56: =SUM(AF47:AF55) -> 0 | AG56: =sum(B56:AE56) -> 582
A59: First-time Customers
A60: Bird Buddy - Blue
A61: Bird Buddy - Yellow
A62: Bird Buddy with Solar Roof - Blue | AG62: =sum(B62:AE62) -> 0
A63: Bird Buddy with Solar Roof - Yellow | AG63: =sum(B63:AE63) -> 0
A64: All Bird Buddy | B64: =SUM(B62:B63) -> 0 | C64: =SUM(C62:C63) -> 0 | D64: =SUM(D62:D63) -> 0 | E64: =SUM(E62:E63) -> 0 | F64: =SUM(F62:F63) -> 0 | G64: =SUM(G62:G63) -> 0 | H64: =SUM(H62:H63) -> 0 | I64: =SUM(I62:I63) -> 0 | ... AF64: =SUM(AF62:AF63) -> 0 | AG64: =sum(B64:AE64) -> 0
A66: Wall Mount | AG66: =sum(B66:AE66) -> 0
A67: Fence Mount | AG67: =sum(B67:AE67) -> 0
A68: Suet Ball Holder | AG68: =sum(B68:AE68) -> 0
A69: 3-in-1 Nutrition Set - Blue
A70: 3-in-1 Nutrition Set - Yellow
A71: Solar Roof Single - Blue
A72: Solar Roof Single - Yellow
A73: Perch Extender - Blue | AG73: =sum(B73:AE73) -> 0
A74: Perch Extender - Yellow | AG74: =sum(B74:AE74) -> 0
A75: All | B75: =SUM(B66:B74) -> 0 | C75: =SUM(C66:C74) -> 0 | D75: =SUM(D66:D74) -> 0 | E75: =SUM(E66:E74) -> 0 | F75: =SUM(F66:F74) -> 0 | G75: =SUM(G66:G74) -> 0 | H75: =SUM(H66:H74) -> 0 | I75: =SUM(I66:I74) -> 0 | ... AF75: =SUM(AF66:AF74) -> 0 | AG75: =sum(B75:AE75) -> 0
A77: Returning Customers
A78: Bird Buddy - Blue
A79: Bird Buddy - Yellow
A80: Bird Buddy with Solar Roof - Blue | AG80: =sum(B80:AE80) -> 0
A81: Bird Buddy with Solar Roof - Yellow | B81: 0 | C81: 0 | D81: 0 | E81: 0 | F81: 0 | G81: 0 | H81: 0 | I81: 0 | J81: 0 | K81: 0 | L81: 0 | M81: 0 | N81: 0 | O81: 0 | P81: 0 | Q81: 0 | R81: 0 | S81: 0 | T81: 0 | U81: 0 | V81: 0 | W81: 0 | X81: 0 | Y81: 0 | Z81: 0 | AA81: 0 | AB81: 0 | AC81: 0 | AD81: 0 | AE81: 0 | AG81: =sum(B81:AE81) -> 0
A82: All Bird Buddy | B82: =SUM(B80:B81) -> 0 | C82: =SUM(C80:C81) -> 0 | D82: =SUM(D80:D81) -> 0 | E82: =SUM(E80:E81) -> 0 | F82: =SUM(F80:F81) -> 0 | G82: =SUM(G80:G81) -> 0 | H82: =SUM(H80:H81) -> 0 | I82: =SUM(I80:I81) -> 0 | ... AF82: =SUM(AF80:AF81) -> 0 | AG82: =sum(B82:AE82) -> 0
A84: Wall Mount | AG84: =sum(B84:AE84) -> 0
A85: Fence Mount | AG85: =sum(B85:AE85) -> 0
A86: Suet Ball Holder | AG86: =sum(B86:AE86) -> 0
A87: 3-in-1 Nutrition Set - Blue
A88: 3-in-1 Nutrition Set - Yellow
A89: Solar Roof Single - Blue
A90: Solar Roof Single - Yellow
A91: Perch Extender - Blue | AG91: =sum(B91:AE91) -> 0
A92: Perch Extender - Yellow | AG92: =sum(B92:AE92) -> 0
A93: All | B93: =SUM(B84:B92) -> 0 | C93: =SUM(C84:C92) -> 0 | D93: =SUM(D84:D92) -> 0 | E93: =SUM(E84:E92) -> 0 | F93: =SUM(F84:F92) -> 0 | G93: =SUM(G84:G92) -> 0 | H93: =SUM(H84:H92) -> 0 | I93: =SUM(I84:I92) -> 0 | ... AF93: =SUM(AF84:AF92) -> 0 | AG93: =sum(B93:AE93) -> 0
A95: Units Sold (Net)
A96: Bird Buddy - Blue | B96: =B41-B180 -> 12 | C96: =C41-C180 -> 6 | D96: =D41-D180 -> 6 | E96: =E41-E180 -> 3 | F96: =F41-F180 -> 9 | G96: =G41-G180 -> 7 | H96: =H41-H180 -> 7 | I96: =I41-I180 -> 21 | ... AF96: =AF41-AF180 -> 0
A97: Bird Buddy - Yellow | B97: =B42 -> 0 | C97: =C42 -> 0 | D97: =D42 -> 0 | E97: =E42 -> 0 | F97: =F42 -> 1 | G97: =G42 -> 2 | H97: =H42 -> 1 | I97: =I42 -> 4 | ... AF97: =AF42
A98: Bird Buddy with Solar Roof - Blue | B98: =B43-B181 -> 30 | C98: =C43-C181 -> 26 | D98: =D43-D181 -> 44 | E98: =E43-E181 -> 51 | F98: =F43-F181 -> 53 | G98: =G43-G181 -> 42 | H98: =H43-H181 -> 35 | I98: =I43-I181 -> 15 | ... AF98: =AF43-AF181 -> 0 | AG98: =sum(B98:AE98) -> 9625
A99: Bird Buddy with Solar Roof - Yellow | B99: =B44 -> 0 | C99: =C44 -> 1 | D99: =D44 -> 0 | E99: =E44 -> 3 | F99: =F44 -> 3 | G99: =G44 -> 3 | H99: =H44 -> 0 | I99: =I44 -> 14 | ... AF99: =AF44 | AG99: =sum(B99:AE99) -> 399
A100: All Bird Buddy | B100: =SUM(B98:B99) -> 30 | C100: =SUM(C98:C99) -> 27 | D100: =SUM(D98:D99) -> 44 | E100: =SUM(E98:E99) -> 54 | F100: =SUM(F98:F99) -> 56 | G100: =SUM(G98:G99) -> 45 | H100: =SUM(H98:H99) -> 35 | I100: =SUM(I98:I99) -> 29 | ... AF100: =SUM(AF98:AF99) -> 0 | AG100: =sum(B100:AE100) -> 10024
A102: Wall Mount | B102: =B47-B189-B196-B203 -> 6 | C102: =C47-C189-C196-C203 -> 5 | D102: =D47-D189-D196-D203 -> 3 | E102: =E47-E189-E196-E203 -> 5 | F102: =F47-F189-F196-F203 -> 5 | G102: =G47-G189-G196-G203 -> 5 | H102: =H47-H189-H196-H203 -> 2 | I102: =I47-I189-I196-I203 -> 13 | ... AE102: =AE47-AE189-AE196-AE203 -> 0 | AG102: =sum(B102:AE102) -> 581
A103: Fence Mount | B103: =B48-B190-B197-B204 -> 0 | C103: =C48-C190-C197-C204 -> 0 | D103: =D48-D190-D197-D204 -> 0 | E103: =E48-E190-E197-E204 -> 0 | F103: =F48-F190-F197-F204 -> 0 | G103: =G48-G190-G197-G204 -> 0 | H103: =H48-H190-H197-H204 -> 0 | I103: =I48-I190-I197-I204 -> 0 | ... AE103: =AE48-AE190-AE197-AE204 -> 0 | AG103: =sum(B103:AE103) -> 0
A104: Suet Ball Holder | B104: =B49-B191-B198-B205 -> 0 | C104: =C49-C191-C198-C205 -> 0 | D104: =D49-D191-D198-D205 -> 0 | E104: =E49-E191-E198-E205 -> 0 | F104: =F49-F191-F198-F205 -> 0 | G104: =G49-G191-G198-G205 -> 0 | H104: =H49-H191-H198-H205 -> 0 | I104: =I49-I191-I198-I205 -> 0 | ... AE104: =AE49-AE191-AE198-AE205 -> 0 | AG104: =sum(B104:AE104) -> 0
A105: 3-in-1 Nutrition Set - Blue | B105: =B50-B192-B199-B206 -> 0 | C105: =C50-C192-C199-C206 -> 0 | D105: =D50-D192-D199-D206 -> 0 | E105: =E50-E192-E199-E206 -> 0 | F105: =F50-F192-F199-F206 -> 0 | G105: =G50-G192-G199-G206 -> 0 | H105: =H50-H192-H199-H206 -> 0 | I105: =I50-I192-I199-I206 -> 0 | ... AE105: =AE50-AE192-AE199-AE206 -> 0
A106: 3-in-1 Nutrition Set - Yellow | B106: =B51-B193-B200-B207 -> 0 | C106: =C51-C193-C200-C207 -> 0 | D106: =D51-D193-D200-D207 -> 0 | E106: =E51-E193-E200-E207 -> 0 | F106: =F51-F193-F200-F207 -> 0 | G106: =G51-G193-G200-G207 -> 0 | H106: =H51-H193-H200-H207 -> 0 | I106: =I51-I193-I200-I207 -> 0 | ... AE106: =AE51-AE193-AE200-AE207 -> 0
