Workbook
Name zsupermetrics_ru0GDtbZzDLHQOQtJJ6K08MvUDyyp7: #REF!
Name zsupermetrics_DQl8lUbpTRu3fayaJJi7lVfOGKjNU4: 'OLD Data - P&L'!$A$3:$A$4
Name zsupermetrics_BioPyGBzcBsy60UCQmPcTuFReEmghI: 'OLD Data - P&L'!$B$2:$B$3
Name zsupermetrics_refreshAll: SupermetricsQueries!$H$5
Name zsupermetrics_n3GtLgiKpTmd2pYmQNMuq6TPD0qE0b: #REF!
Name zsupermetrics_refreshAllSilent: SupermetricsQueries!$H$6
Name zsupermetrics_Mgms9p0QzysYvrIhnsKACeVBVxfIEO: #REF!
Name zsupermetrics_Mgms9p0QzysYvrIhnsKACeVBVxfIEO: 'OLD Data - P&L'!$A$2:$A$3
Name zsupermetrics_forceRefresh: SupermetricsQueries!$H$4
Name zsupermetrics_wbYMmT0YL9bAN0yhimW0ziPFnia9Dx: #REF!
Name zsupermetrics_iNpyVy90bWCI0yUaFQpxOtzWMa6sW4: #REF!
Name zsupermetrics_xwoIpANxRm908eDp5oKTwQpEI8gvD4: #REF!
Name zsupermetrics_n3GtLgiKpTmd2pYmQNMuq6TPD0qE0b: 'OLD Data - P&L'!$B$4:$B$5
Name rdataslayer_42b112e4e4be4305bb4c1be75e2dd549: 'OLD Data - P&L'!$B$2:$C$3
Name zsupermetrics_9i4W4hgd80uRpQLMeX0eRnESN8gjyv: #REF!
Name zsupermetrics_5bmwtOpHUbSYmDMeuCPkrxaojTprPP: #REF!
Name rdataslayer_3753ddf3234e496aa261974a0222e193: 'OLD Data - P&L'!$H$2:$I$2
Name zsupermetrics_SGBxROnInO9rFyh3H7j2Lldx0Bdc5v: #REF!
Name zsupermetrics_pxuhRTEmIU93xSgKclyxajD0fCZ6rF: #REF!
Name zsupermetrics_ru0GDtbZzDLHQOQtJJ6K08MvUDyyp7: 'OLD Data - P&L'!$B$4:$B$5
Name zsupermetrics_qWp7V908pNEYMtfv8QZvSTeDnBAHOU: 'OLD Data - P&L'!$B$5:$C$13
Name rdataslayer_4a0f150f4f2f4e4f85c890c75b7a1fa4: #REF!
Name zsupermetrics_HgZqhorObHOtZHuyJjpmyYaEPoYntx: #REF!
Name zsupermetrics_YsFuuYtr8vOdNXCCPiFJIO38NP4b2T: #REF!
Name zsupermetrics_DQl8lUbpTRu3fayaJJi7lVfOGKjNU4: #REF!
Name zsupermetrics_YVuzfmsfdurz7Ldl84Rfns8oka6LsS: #REF!
Name zsupermetrics_4VkB7ij7WO0JjKBEgvjB2GHjSy2Egm: #REF!
Name zsupermetrics_9i4W4hgd80uRpQLMeX0eRnESN8gjyv: 'OLD Data - P&L'!$C$13
Name zsupermetrics_lx4cNai7gT6tH4j08ZRkI21Qlpjioi: #REF!
Name rdataslayer_d70e473bcafe40a3aa834ce157fb2ba3: #REF!
Name zsupermetrics_NugLlrQxlKiqhxQae8EFpITBm1pLCj: 'OLD Data - P&L'!$B$6:$C$13
Name zsupermetrics_8xojRjNDjo2jWHGDWjFEhflhyIq3Hq: 'OLD Summary'!$K$8:$K$24
Name rdataslayer_3753ddf3234e496aa261974a0222e193: #REF!
Name zsupermetrics_iNpyVy90bWCI0yUaFQpxOtzWMa6sW4: 'OLD Data - P&L'!$A$2:$A$3
Name rdataslayer_4a0f150f4f2f4e4f85c890c75b7a1fa4: 'OLD Data - P&L'!$D$2:$E$3
Name zsupermetrics_BioPyGBzcBsy60UCQmPcTuFReEmghI: #REF!
Name zsupermetrics_qWp7V908pNEYMtfv8QZvSTeDnBAHOU: #REF!
Name zsupermetrics_8xojRjNDjo2jWHGDWjFEhflhyIq3Hq: #REF!
Name zsupermetrics_wbYMmT0YL9bAN0yhimW0ziPFnia9Dx: 'OLD Data - P&L'!$A$2:$A$3
Name zsupermetrics_4VkB7ij7WO0JjKBEgvjB2GHjSy2Egm: 'OLD Data - P&L'!$B$4:$C$10
Name zsupermetrics_lx4cNai7gT6tH4j08ZRkI21Qlpjioi: 'OLD Data - P&L'!$B$4:$C$13
Name rdataslayer_42b112e4e4be4305bb4c1be75e2dd549: #REF!
Name rdataslayer_adf57e64065742daa5b4161161b1c3ca: #REF!
Name rdataslayer_adf57e64065742daa5b4161161b1c3ca: 'OLD Data - P&L'!$B$4:$D$5
Name zsupermetrics_NugLlrQxlKiqhxQae8EFpITBm1pLCj: #REF!
Name zsupermetrics_xwoIpANxRm908eDp5oKTwQpEI8gvD4: #REF!
Name zsupermetrics_YsFuuYtr8vOdNXCCPiFJIO38NP4b2T: 'OLD Data - P&L'!$B$4:$C$13
Name rdataslayer_d70e473bcafe40a3aa834ce157fb2ba3: 'OLD Data - P&L'!$C$8:$D$9
Name zsupermetrics_HgZqhorObHOtZHuyJjpmyYaEPoYntx: 'OLD Data - P&L'!$B$4:$B$5

Sheet Summary
A1: 45261 | B1: 45261 | C1: 45262 | D1: 45263 | E1: 45264 | F1: 45265 | G1: 45266 | H1: 45267 | I1: 45268 | J1: 45269 | K1: 45270 | L1: 45271 | M1: 45272 | N1: 45273 | O1: 45274 | P1: 45275 | Q1: 45276 | R1: 45277 | S1: 45278 | T1: 45279 | U1: 45280 | V1: 45281 | W1: 45282 | X1: 45283 | Y1: 45284 | Z1: 45285 | AA1: 45286 | AB1: 45287 | AC1: 45288 | AD1: 45289 | AE1: 45290 | AF1: 45291
B2: FRI | C2: SAT | D2: SUN | E2: MON | F2: TUE | G2: WED | H2: THU | I2: FRI | J2: SAT | K2: SUN | L2: MON | M2: TUE | N2: WED | O2: THU | P2: FRI | Q2: SAT | R2: SUN | S2: MON | T2: TUE | U2: WED | V2: THU | W2: FRI | X2: SAT | Y2: SUN | Z2: MON | AA2: TUE | AB2: WED | AC2: THU | AD2: FRI | AE2: SAT | AF2: SUN
A3: Weekend Work | C3: Peco | D3: Peco | J3: Peco | K3: Peco | P3: Peco | Q3: Peco | R3: Peco | X3: Peco | Y3: Peco | Z3: Peco | AA3: Peco | AD3: Peter | AE3: Peter | AF3: Peter
A4: Notes | B4: Christmas Sale (-20%)
F5: 10:29 Yellow preferred version & blue version +$10 | H5: 10.30 Blue version additional +$10 & SKU 1+SKU 5 combination active | I5: Blue version additional $20 from 17:47 | K5: Featured on CBS Sunday Morning | L5: Blue BB out of stock at 14:25 SKU 3 live at 10:15 / Christmas Email Offer | N5: 16:05 changed US & Canada to expedited shipping, order #119304 16:06 +$20 on Bird Buddy Yellow units | O5: 9:23 - SKU3 & Pro Bundle Blue out of Stock 14:22 Pricing change on Yellow BBs (original prices, Wall Mount & 3-in-1 increase by $10), only pro bundle -20% 15:40 Amazon button on Smart bird feeder with solar roof | P5: 13:20 SKU2 +$10 ($249) SKU4 +$10 ($309) Solar Roof +$10 ($99) Wall Mount +$10 (49) Pro bundle $327 (20% off) Shipping US +$10 ($45) Add-on Shop - Yellow default | U5: 16:32 - SKU2 - $10 down ($239), SKU4 $10 down ($299), Pro bundle ($317) | V5: 14:12 - Blue & Yellow Pro Bundle $329 (added Suet Ball Holder, and +$1 per item for Wall Mount and 3-in-1), Suet Ball Holder back in stock for $24. Wall Mount price down to $39 (-$10). | AD5: 11:35 - Yellow Pro added perch extender (price goes up for $31 to $360), perch extended is back on stock | AE5: Twitter traffic spike
L6: SKU3 price increased to $349 at 11.00
A8: DTC Revenue | B8: 182179.74 | C8: 239359.12 | D8: 309347.58 | E8: 305578.38 | F8: 298114.36 | G8: 324866.09 | H8: 330539.93 | I8: 353516.62 | J8: 360109.93 | K8: 544223.4 | L8: 507957.88 | M8: 441290.61 | N8: 378497.6 | O8: 289096.22 | P8: 234608.6 | Q8: 195884.99 | R8: 135037.9 | S8: 152636.6 | T8: 143733.9 | U8: 111010.22 | V8: 53985.74 | W8: 45371.98 | X8: 32430.01 | Y8: 28394.59 | Z8: 46187.9 | AA8: 38487.01 | AB8: 31524.34 | AC8: 31682.88 | AD8: 35924.11 | AE8: 45927.46 | AF8: 44158.82
A9: - Hardware | B9: 148896.28 | C9: 196722.13 | D9: 255328.76 | E9: 254086.11 | F9: 245877.15 | G9: 268135.33 | H9: 267062.57 | I9: 283105.87 | J9: 287226.6 | K9: 431622.54 | L9: 410276.54 | M9: 363565.77 | N9: 306167.33 | O9: 229526.48 | P9: 185579.36 | Q9: 151020.91 | R9: 104311.3 | S9: 119135.96 | T9: 111973.84 | U9: 89333.68 | V9: 44585.65 | W9: 36770.85 | X9: 26184.13 | Y9: 21720.95 | Z9: 30855.55 | AA9: 22390.5 | AB9: 19166.75 | AC9: 19296.05 | AD9: 20772.9 | AE9: 30281.55 | AF9: 29212.93
A10: - Add-ons | B10: 12027.92 | C10: 14248.12 | D10: 17773.14 | E10: 15874.79 | F10: 15079.85 | G10: 17998.27 | H10: 24577.23 | I10: 29469.5 | J10: 30723.45 | K10: 49963.65 | L10: 37955.26 | M10: 25861.27 | N10: 20871.96 | O10: 11810.97 | P10: 8711.89 | Q10: 9843.64 | R10: 6337.85 | S10: 6090.44 | T10: 5671.06 | U10: 5104.32 | V10: 3339.05 | W10: 3379.65 | X10: 2646.87 | Y10: 3345.6 | Z10: 9404.45 | AA10: 10875.1 | AB10: 8185.4 | AC10: 8230.9 | AD10: 10525.15 | AE10: 9954.55 | AF10: 9678.87
A11: - Merch | B11: 161 | C11: 238.99 | D11: 255.97 | E11: 49.89 | F11: 1934.95 | G11: 539.98 | H11: 335.15 | I11: 635.5 | J11: 642.95 | K11: 689.48 | L11: 825.94 | M11: 686.08 | N11: 608.47 | O11: 358.15 | P11: 434.98 | Q11: 285 | R11: 187.15 | S11: 304 | T11: 152.99 | U11: 298.97 | V11: 76 | W11: 86.99 | X11: 57 | Y11: 35.15 | Z11: 139.99 | AA11: 114 | AB11: 47 | AC11: 38 | AD11: 57 | AE11: 38 | AF11: 55.99
A12: - Taxes | B12: 10324.54 | C12: 13474.88 | D12: 17959.71 | E12: 17167.59 | F12: 16904.41 | G12: 18912.51 | H12: 19444.98 | I12: 20395.75 | J12: 21341.93 | K12: 32117.73 | L12: 28913.14 | M12: 25567.49 | N12: 21859.84 | O12: 16620.62 | P12: 13332.37 | Q12: 11155.44 | R12: 7731.6 | S12: 8521.2 | T12: 8206.01 | U12: 6368.25 | V12: 3160.04 | W12: 2684.49 | X12: 1517.01 | Y12: 1492.89 | Z12: 2357.91 | AA12: 1977.41 | AB12: 1750.19 | AC12: 1757.93 | AD12: 1869.06 | AE12: 2428.36 | AF12: 2431.03
A13: - Shipping | B13: 10770 | C13: 14675 | D13: 18030 | E13: 18400 | F13: 18318 | G13: 19280 | H13: 19120 | I13: 19910 | J13: 20175 | K13: 29830 | L13: 29987 | M13: 25610 | N13: 28990 | O13: 30780 | P13: 26550 | Q13: 23580 | R13: 16470 | S13: 18585 | T13: 17730 | U13: 9905 | V13: 2825 | W13: 2450 | X13: 2025 | Y13: 1800 | Z13: 3430 | AA13: 3130 | AB13: 2375 | AC13: 2360 | AD13: 2700 | AE13: 3225 | AF13: 2780
A14: Amazon Revenue | B14: =SUM(B15:B19) -> 253.34 | C14: =SUM(C15:C19) -> 0 | D14: =SUM(D15:D19) -> 239 | E14: =SUM(E15:E19) -> 316.94 | F14: =SUM(F15:F19) -> 0 | G14: =SUM(G15:G19) -> 0 | H14: =SUM(H15:H19) -> 252.15 | I14: =SUM(I15:I19) -> 0 | ... AF14: =SUM(AF15:AF19) -> 10388.6
A15: - Hardware | B15: 239 | C15: 0 | D15: 239 | E15: 299 | F15: 0 | G15: 0 | H15: 239 | I15: 0 | J15: 2980.24 | K15: 16437.68 | L15: 1625 | M15: 1600.12 | N15: 3068.56 | O15: 12871.26 | P15: 28791.72 | Q15: 79480.27 | R15: 235448.23 | S15: 189522.92 | T15: 173616.13 | U15: 73448.75 | V15: 59661.41 | W15: 49452.96 | X15: 45309.13 | Y15: 27065.29 | Z15: 17551.03 | AA15: 17695.82 | AB15: 7410.12 | AC15: 9221.68 | AD15: 6276.56 | AE15: 10357.68 | AF15: 9586.55
A16: - Add-ons | B16: 0 | C16: 0 | D16: 0 | E16: 0 | F16: 0 | G16: 0 | H16: 0 | I16: 0 | J16: 87 | K16: 29 | L16: 0 | M16: 29 | N16: 0 | O16: 0 | P16: 116 | Q16: 348 | R16: 1508 | S16: 1218 | T16: 1305 | U16: 783 | V16: 406 | W16: 493 | X16: 667 | Y16: 551 | Z16: 2146 | AA16: 2610 | AB16: 1943 | AC16: 812 | AD16: 29 | AE16: 58 | AF16: 87
A17: - Tax | B17: 14.34 | C17: 0 | D17: 0 | E17: 17.94 | F17: 0 | G17: 0 | H17: 13.15 | I17: 0 | J17: 202.17 | K17: 1189.4 | L17: 105.88 | M17: 114.74 | N17: 184.35 | O17: 838.71 | P17: 2028.05 | Q17: 5562.66 | R17: 16741.34 | S17: 13366.17 | T17: 12080.12 | U17: 5095.44 | V17: 4217.98 | W17: 3680.14 | X17: 3107.29 | Y17: 1949.06 | Z17: 1224.05 | AA17: 1412.66 | AB17: 655.22 | AC17: 688.12 | AD17: 426.66 | AE17: 703.83 | AF17: 710.31
A18: - Shipping | B18: 0 | C18: 0 | D18: 0 | E18: 0 | F18: 0 | G18: 0 | H18: 0 | I18: 0 | J18: 0.32 | K18: 7.23 | L18: 0 | M18: 0.16 | N18: 14.06 | O18: 7.23 | P18: 7.23 | Q18: 61.39 | R18: 100.18 | S18: 135.52 | T18: 91.67 | U18: 10.58 | V18: 26.32 | W18: 26.56 | X18: 51.68 | Y18: 14.14 | Z18: 7.98 | AA18: 10.07 | AB18: 13.68 | AC18: 0.24 | AD18: 7.07 | AE18: 0.24 | AF18: 0.08
A19: - Gift Wrap | B19: 0 | C19: 0 | D19: 0 | E19: 0 | F19: 0 | G19: 0 | H19: 0 | I19: 0 | J19: 14.15 | K19: 27.45 | L19: 0 | M19: 0.34 | N19: 0.17 | O19: 5 | P19: 13.98 | Q19: 68.54 | R19: 325.34 | S19: 210.47 | T19: 229.44 | U19: 70.75 | V19: 65.41 | W19: 108.46 | X19: 81.52 | Y19: 40.75 | Z19: 36.88 | AA19: 18.79 | AB19: 4.83 | AC19: 0.51 | AD19: 4.66 | AE19: 9.49 | AF19: 4.66
A20: Digital Marketplaces Revenue | B20: =SUM(B25,B21) -> 955.22816 | C20: =SUM(C25,C21) -> 318.40939 | D20: =SUM(D25,D21) -> 636.81877 | E20: =SUM(E25,E21) -> 318.40939 | F20: =SUM(F25,F21) -> 318.40939 | G20: =SUM(G25,G21) -> 0 | H20: =SUM(H25,H21) -> 1183.461 | I20: =SUM(I25,I21) -> 4929.1098 | ... AF20: =SUM(AF25,AF21) -> 0
A21: Rachio | B21: =SUM(B22:B24) -> 955.22816 | C21: =SUM(C22:C24) -> 318.40939 | D21: =SUM(D22:D24) -> 636.81877 | E21: =SUM(E22:E24) -> 318.40939 | F21: =SUM(F22:F24) -> 318.40939 | G21: =SUM(G22:G24) -> 0 | H21: =SUM(H22:H24) -> 0 | I21: =SUM(I22:I24) -> 955.22816 | ... AF21: =SUM(AF22:AF24) -> 0
A22: - Hardware | B22: 899.97 | C22: 299.99 | D22: 599.98 | E22: 299.99 | F22: 299.99 | G22: 0 | H22: 0 | I22: 899.97 | J22: 839.97 | K22: 839.97 | L22: 1199.96 | M22: 24719.17 | N22: 7619.74 | O22: 0 | P22: 0 | Q22: 899.97 | R22: 299.99 | S22: 599.98 | T22: 599.98 | U22: 0 | V22: 0 | W22: 0 | X22: 0 | Y22: 0 | Z22: 0 | AA22: 0 | AB22: 0 | AC22: 0 | AD22: 0 | AE22: 0 | AF22: 0
A23: - Tax | B23: =0.0614*B22 -> 55.258158 | C23: =0.0614*C22 -> 18.419386 | D23: =0.0614*D22 -> 36.838772 | E23: =0.0614*E22 -> 18.419386 | F23: =0.0614*F22 -> 18.419386 | G23: =0.0614*G22 -> 0 | H23: =0.0614*H22 -> 0 | I23: =0.0614*I22 -> 55.258158 | ... AF23: =0.0614*AF22 -> 0
A24: - Shipping | B24: 0 | C24: 0 | D24: 0 | E24: 0 | F24: 0 | G24: 0 | H24: 0 | I24: 0 | J24: 0 | K24: 0 | L24: 0 | M24: 0 | N24: 0 | O24: 0 | P24: 0 | Q24: 0 | R24: 0 | S24: 0 | T24: 0 | U24: 0 | V24: 0 | W24: 0 | X24: 0 | Y24: 0 | Z24: 0 | AA24: 0 | AB24: 0 | AC24: 0 | AD24: 0 | AE24: 0 | AF24: 0
A25: Weatherflow | H25: =SUM(H26:H28) -> 1183.461 | I25: =SUM(I26:I28) -> 3973.8816 | J25: =SUM(J26:J28) -> 0 | K25: =SUM(K26:K28) -> 211.2186 | L25: =SUM(L26:L28) -> 211.2186 | M25: =SUM(M26:M28) -> 1183.461 | N25: =SUM(N26:N28) -> 676.1118 | O25: =SUM(O26:O28) -> 0 | ... AF25: =SUM(AF26:AF28) -> 0
A26: - Hardware | H26: 1115 | I26: 3744 | J26: 0 | K26: 199 | L26: 199 | M26: 1115 | N26: 637 | O26: 0 | P26: 0 | Q26: 0 | R26: 239 | S26: 0 | T26: 0 | U26: 0 | V26: 0 | W26: 0 | X26: 0 | Y26: 0 | Z26: 0 | AA26: 0 | AB26: 0 | AC26: 0 | AD26: 0 | AE26: 0 | AF26: 0
A27: - Tax | H27: =0.0614*H26 -> 68.461 | I27: =0.0614*I26 -> 229.8816 | J27: =0.0614*J26 -> 0 | K27: =0.0614*K26 -> 12.2186 | L27: =0.0614*L26 -> 12.2186 | M27: =0.0614*M26 -> 68.461 | N27: =0.0614*N26 -> 39.1118 | O27: =0.0614*O26 -> 0 | ... AF27: =0.0614*AF26 -> 0
A28: - Shipping | H28: 0 | I28: 0 | J28: 0 | K28: 0 | L28: 0 | M28: 0 | N28: 0 | O28: 0 | P28: 0 | Q28: 0 | R28: 0 | S28: 0 | T28: 0 | U28: 0 | V28: 0 | W28: 0 | X28: 0 | Y28: 0 | Z28: 0 | AA28: 0 | AB28: 0 | AC28: 0 | AD28: 0 | AE28: 0 | AF28: 0
A29: IndieGoGo | B29: =sum(B30:B33) -> 691 | C29: =sum(C30:C33) -> 1185 | D29: =sum(D30:D33) -> 487 | E29: =sum(E30:E33) -> 418 | F29: =sum(F30:F33) -> 283 | G29: =sum(G30:G33) -> 1257 | H29: =sum(H30:H33) -> 204 | I29: =sum(I30:I33) -> 309 | ... AF29: =sum(AF30:AF33) -> 0
A30: - Hardware | B30: 567 | C30: 499 | D30: 378 | E30: 388 | F30: 189 | G30: 945 | H30: 189 | I30: 199 | J30: 189 | K30: 955 | L30: 955 | M30: 0 | N30: 199 | O30: 698 | P30: 0 | Q30: 688 | R30: 0 | S30: 0 | T30: 378 | U30: 0 | V30: 378 | W30: 189 | X30: 1376 | Y30: 0 | Z30: 189 | AA30: 1076 | AB30: 378 | AC30: 1885 | AD30: 0 | AE30: 1255 | AF30: 0
A31: - Add-ons | B31: 79 | C31: 641 | D31: 79 | E31: 0 | F31: 79 | G31: 237 | H31: 0 | I31: 95 | J31: 79 | K31: 0 | L31: 95 | M31: 0 | N31: 0 | O31: 174 | P31: 0 | Q31: 253 | R31: 0 | S31: 279 | T31: 79 | U31: 0 | V31: 158 | W31: 79 | X31: 706 | Y31: 0 | Z31: 79 | AA31: 253 | AB31: 79 | AC31: 617 | AD31: 0 | AE31: 490 | AF31: 0
A32: - Taxes | B32: 0 | C32: 0 | D32: 0 | E32: 0 | F32: 0 | G32: 0 | H32: 0 | I32: 0 | J32: 0 | K32: 0 | L32: 0 | M32: 0 | N32: 0 | O32: 0 | P32: 0 | Q32: 0 | R32: 0 | S32: 0 | T32: 0 | U32: 0 | V32: 0 | W32: 0 | X32: 0 | Y32: 0 | Z32: 0 | AA32: 0 | AB32: 0 | AC32: 0 | AD32: 0 | AE32: 0 | AF32: 0
A33: - Shipping | B33: 45 | C33: 45 | D33: 30 | E33: 30 | F33: 15 | G33: 75 | H33: 15 | I33: 15 | J33: 15 | K33: 95 | L33: 75 | M33: 0 | N33: 15 | O33: 40 | P33: 0 | Q33: 40 | R33: 0 | S33: 20 | T33: 30 | U33: 0 | V33: 30 | W33: 15 | X33: 100 | Y33: 0 | Z33: 15 | AA33: 70 | AB33: 30 | AC33: 105 | AD33: 0 | AE33: 85 | AF33: 0
A34: Total Revenue | B34: =SUM(B8+B14+B20+B29) -> 184079.31 | C34: =SUM(C8+C14+C20+C29) -> 240862.53 | D34: =SUM(D8+D14+D20+D29) -> 310710.4 | E34: =SUM(E8+E14+E20+E29) -> 306631.73 | F34: =SUM(F8+F14+F20+F29) -> 298715.77 | G34: =SUM(G8+G14+G20+G29) -> 326123.09 | H34: =SUM(H8+H14+H20+H29) -> 332179.54 | I34: =SUM(I8+I14+I20+I29) -> 358754.73 | ... AF34: =SUM(AF8+AF14+AF20+AF29) -> 54547.42
A36: B2B Revenue
A37: Best Buy | B37: =SUM(B38:B39) -> 21396.763 | C37: =SUM(C38:C39) -> 24580.963 | D37: =SUM(D38:D39) -> 36712.765 | E37: =SUM(E38:E39) -> 31395.151 | F37: =SUM(F38:F39) -> 35439.085 | G37: =SUM(G38:G39) -> 40246.165 | H37: =SUM(H38:H39) -> 38463.013 | I37: =SUM(I38:I39) -> 43812.469 | ... AF37: =SUM(AF38:AF39) -> 4107.618
A38: - Hardwere | B38: 20159 | C38: 23159 | D38: 34589 | E38: 29579 | F38: 33389 | G38: 37918 | H38: 36238 | I38: 41278 | J38: 47308 | K38: 89948 | L38: 82077 | M38: 79197 | N38: 52271 | O38: 43490 | P38: 55159 | Q38: 62788 | R38: 37190 | S38: 8713 | T38: 7020 | U38: 3720 | V38: 5250 | W38: 2760 | X38: 2640 | Y38: 3570 | Z38: 1620 | AA38: 0 | AB38: 1560 | AC38: 0 | AD38: 1890 | AE38: 0 | AF38: 3870
A39: - Tax | B39: =B38*'Data - P&L'!$U$3 -> 1237.7626 | C39: =C38*'Data - P&L'!$U$3 -> 1421.9626 | D39: =D38*'Data - P&L'!$U$3 -> 2123.7646 | E39: =E38*'Data - P&L'!$U$3 -> 1816.1506 | F39: =F38*'Data - P&L'!$U$3 -> 2050.0846 | G39: =G38*'Data - P&L'!$U$3 -> 2328.1652 | H39: =H38*'Data - P&L'!$U$3 -> 2225.0132 | I39: =I38*'Data - P&L'!$U$3 -> 2534.4692 | ... AF39: =AF38*'Data - P&L'!$U$3 -> 237.618
A40: Total Revenue | B40: =B37 -> 21396.763 | C40: =C37 -> 24580.963 | D40: =D37 -> 36712.765 | E40: =E37 -> 31395.151 | F40: =F37 -> 35439.085 | G40: =G37 -> 40246.165 | H40: =H37 -> 38463.013 | I40: =I37 -> 43812.469 | ... AF40: =AF37 -> 4107.618
A42: App Revenue
A43: - Google Store | B43: ='APP - P&L'!B90 -> 181.381 | C43: ='APP - P&L'!C90 -> 255.6225 | D43: ='APP - P&L'!D90 -> 292.136 | E43: ='APP - P&L'!E90 -> 70.9675 | F43: ='APP - P&L'!F90 -> 170.7475 | G43: ='APP - P&L'!G90 -> 203.15 | H43: ='APP - P&L'!H90 -> 231.9495 | I43: ='APP - P&L'!I90 -> 333.66 | ... AF43: ='APP - P&L'!AF90 -> 1708.84
A44: - Apple Store | B44: ='APP - P&L'!B91 -> 1185.4833 | C44: ='APP - P&L'!C91 -> 1597.4964 | D44: ='APP - P&L'!D91 -> 1216.7348 | E44: ='APP - P&L'!E91 -> 894.14925 | F44: ='APP - P&L'!F91 -> 721.3849 | G44: ='APP - P&L'!G91 -> 875.82072 | H44: ='APP - P&L'!H91 -> 859.20913 | I44: ='APP - P&L'!I91 -> 1066.7317 | ... AF44: ='APP - P&L'!AF91 -> 7330.7439
A45: - Comission | B45: ='APP - P&L'!B67 -> 550.20612 | C45: ='APP - P&L'!C67 -> 751.50596 | D45: ='APP - P&L'!D67 -> 583.64179 | E45: ='APP - P&L'!E67 -> 405.13361 | F45: ='APP - P&L'!F67 -> 349.27174 | G45: ='APP - P&L'!G67 -> 418.95888 | H45: ='APP - P&L'!H67 -> 423.08727 | I45: ='APP - P&L'!I67 -> 532.53499 | ... AF45: ='APP - P&L'!AF67 -> 3454.026
A46: - Tax | B46: ='APP - P&L'!B68 -> 30.18 | C46: ='APP - P&L'!C68 -> 51.52 | D46: ='APP - P&L'!D68 -> 25.14 | E46: ='APP - P&L'!E68 -> 22.67 | F46: ='APP - P&L'!F68 -> 30.31 | G46: ='APP - P&L'!G68 -> 18.1 | H46: ='APP - P&L'!H68 -> 46.98 | I46: ='APP - P&L'!I68 -> 42.39 | ... AF46: ='APP - P&L'!AF68 -> 25.01
A47: Total Revenue | B47: =sum(B43:B46) -> 1947.2504 | C47: =sum(C43:C46) -> 2656.1449 | D47: =sum(D43:D46) -> 2117.6526 | E47: =sum(E43:E46) -> 1392.9204 | F47: =sum(F43:F46) -> 1271.7141 | G47: =sum(G43:G46) -> 1516.0296 | H47: =sum(H43:H46) -> 1561.2259 | I47: =sum(I43:I46) -> 1975.3166 | ... AF47: =sum(AF43:AF46) -> 12518.62
A49: DTC Orders | B49: 671 | C49: 904 | D49: 1163 | E49: 1145 | F49: 1191 | G49: 1233 | H49: 1221 | I49: 1297 | J49: 1309 | K49: 1926 | L49: 1893 | M49: 1642 | N49: 1345 | O49: 925 | P49: 699 | Q49: 586 | R49: 410 | S49: 463 | T49: 428 | U49: 359 | V49: 191 | W49: 159 | X49: 125 | Y49: 119 | Z49: 250 | AA49: 245 | AB49: 198 | AC49: 193 | AD49: 220 | AE49: 238 | AF49: 203
A50: - Hardware (units sold) | B50: 646 | C50: 872 | D50: 1138 | E50: 1135 | F50: 1081 | G50: 1176 | H50: 1198 | I50: 1276 | J50: 1280 | K50: 1905 | L50: 1801 | M50: 1584 | N50: 1295 | O50: 886 | P50: 666 | Q50: 532 | R50: 372 | S50: 424 | T50: 402 | U50: 324 | V50: 165 | W50: 135 | X50: 96 | Y50: 81 | Z50: 115 | AA50: 81 | AB50: 69 | AC50: 69 | AD50: 76 | AE50: 111 | AF50: 104
A51: - Add-ons (units sold) | B51: 394 | C51: 523 | D51: 652 | E51: 597 | F51: 558 | G51: 670 | H51: 826 | I51: 975 | J51: 1022 | K51: 1671 | L51: 1301 | M51: 905 | N51: 729 | O51: 589 | P51: 535 | Q51: 448 | R51: 330 | S51: 315 | T51: 302 | U51: 252 | V51: 170 | W51: 156 | X51: 121 | Y51: 128 | Z51: 294 | AA51: 349 | AB51: 252 | AC51: 258 | AD51: 310 | AE51: 293 | AF51: 306
A52: - Merch (units sold) | B52: 396 | C52: 581 | D52: 745 | E52: 704 | F52: 730 | G52: 676 | H52: 253 | I52: 33 | J52: 33 | K52: 35 | L52: 41 | M52: 36 | N52: 30 | O52: 19 | P52: 22 | Q52: 15 | R52: 10 | S52: 16 | T52: 8 | U52: 14 | V52: 4 | W52: 4 | X52: 3 | Y52: 2 | Z52: 6 | AA52: 6 | AB52: 3 | AC52: 2 | AD52: 3 | AE52: 2 | AF52: 3
A53: Amazon Orders | B53: 1 | C53: 0 | D53: 1 | E53: 1 | F53: 0 | G53: 0 | H53: 1 | I53: 0 | J53: 14 | K53: 57 | L53: 6 | M53: 9 | N53: 10 | O53: 41 | P53: 99 | Q53: 273 | R53: 824 | S53: 657 | T53: 616 | U53: 272 | V53: 214 | W53: 178 | X53: 173 | Y53: 111 | Z53: 158 | AA53: 154 | AB53: 93 | AC53: 59 | AD53: 22 | AE53: 36 | AF53: 38
A54: - Hardware (units sold) | B54: 1 | C54: 0 | D54: 1 | E54: 1 | F54: 0 | G54: 0 | H54: 1 | I54: 0 | J54: 11 | K54: 56 | L54: 7 | M54: 8 | N54: 10 | O54: 44 | P54: 96 | Q54: 265 | R54: 785 | S54: 633 | T54: 580 | U54: 246 | V54: 200 | W54: 166 | X54: 154 | Y54: 94 | Z54: 83 | AA54: 64 | AB54: 25 | AC54: 32 | AD54: 21 | AE54: 35 | AF54: 35
A55: - Add-ons (units sold) | B55: 0 | C55: 0 | D55: 0 | E55: 0 | F55: 0 | G55: 0 | H55: 0 | I55: 0 | J55: 3 | K55: 1 | L55: 0 | M55: 1 | N55: 0 | O55: 0 | P55: 4 | Q55: 12 | R55: 52 | S55: 43 | T55: 45 | U55: 28 | V55: 14 | W55: 18 | X55: 23 | Y55: 19 | Z55: 75 | AA55: 91 | AB55: 68 | AC55: 28 | AD55: 1 | AE55: 2 | AF55: 3
A56: Digital Marketplaces Orders | B56: =SUM(B57:B58) -> 4 | C56: =SUM(C57:C58) -> 1 | D56: =SUM(D57:D58) -> 2 | E56: =SUM(E57:E58) -> 1 | F56: =SUM(F57:F58) -> 1 | G56: =SUM(G57:G58) -> 0 | H56: =SUM(H57:H58) -> 5 | I56: =SUM(I57:I58) -> 19 | ... AF56: =SUM(AF57:AF58) -> 0
A57: Rachio Orders | B57: 4 | C57: 1 | D57: 2 | E57: 1 | F57: 1 | G57: 0 | H57: 0 | I57: 3 | J57: 3 | K57: 3 | L57: 4 | M57: 87 | N57: 26 | O57: 0 | P57: 0 | Q57: 3 | R57: 1 | S57: 2 | T57: 2 | U57: 0 | V57: 0 | W57: 0 | X57: 0 | Y57: 0 | Z57: 0 | AA57: 0 | AB57: 0 | AC57: 0 | AD57: 0 | AE57: 0 | AF57: 0
A58: Weatherflow Orders | B58: 0 | C58: 0 | D58: 0 | E58: 0 | F58: 0 | G58: 0 | H58: 5 | I58: 16 | J58: 0 | K58: 1 | L58: 1 | M58: 5 | N58: 3 | O58: 0 | P58: 0 | Q58: 0 | R58: 1 | S58: 0 | T58: 0 | U58: 0 | V58: 0 | W58: 0 | X58: 0 | Y58: 0 | Z58: 0 | AA58: 0 | AB58: 0 | AC58: 0 | AD58: 0 | AE58: 0 | AF58: 0
A59: IndieGoGo Orders | B59: 3 | C59: 2 | D59: 2 | E59: 2 | F59: 1 | G59: 5 | H59: 1 | I59: 1 | J59: 1 | K59: 5 | L59: 5 | M59: 0 | N59: 1 | O59: 2 | P59: 0 | Q59: 2 | R59: 0 | S59: 1 | T59: 2 | U59: 0 | V59: 2 | W59: 1 | X59: 5 | Y59: 0 | Z59: 1 | AA59: 4 | AB59: 2 | AC59: 5 | AD59: 0 | AE59: 5 | AF59: 0
A60: - Hardware (units sold) | B60: 3 | C60: 4 | D60: 2 | E60: 2 | F60: 1 | G60: 5 | H60: 1 | I60: 1 | J60: 1 | K60: 5 | L60: 5 | M60: 0 | N60: 1 | O60: 3 | P60: 0 | Q60: 3 | R60: 0 | S60: 1 | T60: 2 | U60: 0 | V60: 2 | W60: 1 | X60: 7 | Y60: 0 | Z60: 1 | AA60: 5 | AB60: 2 | AC60: 8 | AD60: 0 | AE60: 6 | AF60: 0
A61: - Add-ons (units sold) | B61: 1 | C61: 3 | D61: 1 | E61: 0 | F61: 1 | G61: 3 | H61: 0 | I61: 1 | J61: 1 | K61: 0 | L61: 1 | M61: 0 | N61: 0 | O61: 2 | P61: 0 | Q61: 3 | R61: 0 | S61: 0 | T61: 1 | U61: 0 | V61: 2 | W61: 1 | X61: 5 | Y61: 0 | Z61: 1 | AA61: 3 | AB61: 1 | AC61: 7 | AD61: 0 | AE61: 6 | AF61: 0
A62: Total Orders | B62: =SUM(B49+B53+B57+B58+B59) -> 679 | C62: =SUM(C49+C53+C57+C58+C59) -> 907 | D62: =SUM(D49+D53+D57+D58+D59) -> 1168 | E62: =SUM(E49+E53+E57+E58+E59) -> 1149 | F62: =SUM(F49+F53+F57+F58+F59) -> 1193 | G62: =SUM(G49+G53+G57+G58+G59) -> 1238 | H62: =SUM(H49+H53+H57+H58+H59) -> 1228 | I62: =SUM(I49+I53+I57+I58+I59) -> 1317 | ... AF62: =SUM(AF49+AF53+AF57+AF58+AF59) -> 241
A64: B2B Orders
A65: - Best Buy | B65: 84 | C65: 96 | D65: 143 | E65: 123 | F65: 139 | G65: 158 | H65: 151 | I65: 172 | J65: 197 | K65: 375 | L65: 342 | M65: 330 | N65: 204 | O65: 144 | P65: 208 | Q65: 240 | R65: 145 | S65: 34 | T65: 28 | U65: 15 | V65: 20 | W65: 11 | X65: 9 | Y65: 14 | Z65: 6 | AA65: 0 | AB65: 2 | AC65: 0 | AD65: 4 | AE65: 0 | AF65: 12
A66: Total Orders | B66: =B65 -> 84 | C66: =C65 -> 96 | D66: =D65 -> 143 | E66: =E65 -> 123 | F66: =F65 -> 139 | G66: =G65 -> 158 | H66: =H65 -> 151 | I66: =I65 -> 172 | ... AF66: =AF65 -> 12
A68: App Orders
A69: - Google Store | B69: ='APP - P&L'!B17 -> 8 | C69: ='APP - P&L'!C17 -> 14 | D69: ='APP - P&L'!D17 -> 17 | E69: ='APP - P&L'!E17 -> 9 | F69: ='APP - P&L'!F17 -> 10 | G69: ='APP - P&L'!G17 -> 13 | H69: ='APP - P&L'!H17 -> 14 | I69: ='APP - P&L'!I17 -> 18 | ... AF69: ='APP - P&L'!AF17 -> 63
A70: - Apple Store | B70: ='APP - P&L'!B14 -> 75 | C70: ='APP - P&L'!C14 -> 99 | D70: ='APP - P&L'!D14 -> 87 | E70: ='APP - P&L'!E14 -> 59 | F70: ='APP - P&L'!F14 -> 60 | G70: ='APP - P&L'!G14 -> 61 | H70: ='APP - P&L'!H14 -> 62 | I70: ='APP - P&L'!I14 -> 78 | ... AF70: ='APP - P&L'!AF14 -> 360
A71: Total Orders | B71: =sum(B69:B70) -> 83 | C71: =sum(C69:C70) -> 113 | D71: =sum(D69:D70) -> 104 | E71: =sum(E69:E70) -> 68 | F71: =sum(F69:F70) -> 70 | G71: =sum(G69:G70) -> 74 | H71: =sum(H69:H70) -> 76 | I71: =sum(I69:I70) -> 96 | ... AF71: =sum(AF69:AF70) -> 423
A72: Meta Spend EUR | B72: 19987.92 | C72: 29066.93 | D72: 48955.56 | E72: 59442.98 | F72: 53661.84 | G72: 57042.76 | H72: 63746.94 | I72: 55631.41 | J72: 48239.51 | K72: 61791.96 | L72: 64682.79 | M72: 66065.23 | N72: 55877.79 | O72: =38707.47+299.37 -> 39006.84 | P72: =35478.37+479.39 -> 35957.76 | Q72: =29120.23+479.54 -> 29599.77 | R72: =25626.22+ 506.95 -> 26133.17 | S72: =23777.8+ 494.91 -> 24272.71 | T72: =23934.84+ 507.94 -> 24442.78 | U72: =21346.62+ 479.32 -> 21825.94 | V72: =19128.69+ 497.1 -> 19625.79 | W72: =8386.24+ 507.84 -> 8894.08 | X72: =3335.75+ 505.94 -> 3841.69 | Y72: =3688.73+ 500.92 -> 4189.65 | Z72: =3198.89+ 524.8 -> 3723.69 | AA72: =3723.4+ 508.94 -> 4232.34 | AB72: =3787.58+ 477.67 -> 4265.25 | AC72: =4253.19+ 486.86 -> 4740.05 | AD72: =4541.55+ 501.56 -> 5043.11 | AE72: =4573.38+ 499.25 -> 5072.63 | AF72: =4867.07+ 509.08 -> 5376.15
A73: Currency rate | B73: 1.0893 | C73: 1.0886 | D73: 1.0887 | E73: 1.0836 | F73: 1.0793 | G73: 1.0765 | H73: 1.0791 | I73: 1.0774 | J73: 1.0774 | K73: 1.0765 | L73: 1.0764 | M73: 1.0799 | N73: 1.0884 | O73: 1.0994 | P73: 1.0907 | Q73: 1.0909 | R73: 1.0895 | S73: 1.0923 | T73: 1.0981 | U73: 1.0943 | V73: 1.1006 | W73: 1.1026 | X73: 1.1026 | Y73: 1.1025 | Z73: 1.1019 | AA73: 1.1042 | AB73: 1.1108 | AC73: 1.1067 | AD73: 1.1055 | AE73: 1.1055 | AF73: 1.1038
A74: Meta Spend | B74: =B72*B73 -> 21772.841 | C74: =C72*C73 -> 31642.26 | D74: =D72*D73 -> 53297.918 | E74: =E72*E73 -> 64412.413 | F74: =F72*F73 -> 57917.224 | G74: =G72*G73 -> 61406.531 | H74: =H72*H73 -> 68789.323 | I74: =I72*I73 -> 59937.281 | ... AF74: =AF72*AF73 -> 5934.1944
A75: Google Spend | B75: 5447.08 | C75: 5717.82 | D75: 5853.85 | E75: 6168.03 | F75: 7765.18 | G75: 12389.76 | H75: 15878.71 | I75: 20488.81 | J75: 20368.36 | K75: 17174.33 | L75: 16563.17 | M75: 15756.92 | N75: 15044.64 | O75: 16730.43 | P75: 14288.93 | Q75: 10949.06 | R75: 10049.44 | S75: 8999.66 | T75: 9830.93 | U75: 9843.04 | V75: 6432.48 | W75: 6633.7 | X75: 5726.53 | Y75: 5604.11 | Z75: 7159.42 | AA75: 2737.58 | AB75: 2428.98 | AC75: 1959.08 | AD75: 2103.26 | AE75: 2710.65 | AF75: 2034.48
A76: Bing Spend | B76: 315.1 | C76: 267.21 | D76: 293.77 | E76: 311.83 | F76: 307.19 | G76: 1080.36 | H76: 1061.59 | I76: 1086.12 | J76: 1092.08 | K76: 1087.96 | L76: 1095.88 | M76: 1089.86 | N76: 1086.94 | O76: 932.03 | P76: 909.64 | Q76: 404.05 | R76: 431.85 | S76: 806.45 | T76: 934.3 | U76: 1168.87 | V76: 1134.17 | W76: 849.96 | X76: 523.85 | Y76: 431.27 | Z76: 1131.11 | AA76: 1498.04 | AB76: 535.28 | AC76: 300.48 | AD76: 207.52 | AE76: 209.57 | AF76: 181.91
A77: TikTok Spend | B77: 0 | C77: 0 | D77: 0 | E77: 0 | F77: 0 | G77: 0 | H77: 0 | I77: 0 | J77: 0 | K77: 0 | L77: 0 | M77: 0 | N77: 875.5 | O77: 1856.35 | P77: 1770.38 | Q77: 1496.42 | R77: 1503.62 | S77: 684.27 | T77: 0 | U77: 0 | V77: 0 | W77: 0 | X77: 0 | Y77: 0 | Z77: 0 | AA77: 0 | AB77: 0 | AC77: 0 | AD77: 0 | AE77: 0 | AF77: 0
A78: Amazon Spend | B78: 0 | C78: 0 | D78: 688.15 | E78: 0 | F78: 0.41 | G78: 495.44 | H78: 0 | I78: 777.19 | J78: 2658.1 | K78: 4122.7 | L78: 2435.3 | M78: 211.07 | N78: 0 | O78: 5364.65 | P78: 12239.07 | Q78: 22244.57 | R78: 27940.79 | S78: 22036.27 | T78: 20286.11 | U78: 17289.91 | V78: 13317.73 | W78: 9273.67 | X78: 7427.38 | Y78: 6823.19 | Z78: 3149.49 | AA78: 7173.29 | AB78: 3001.39 | AC78: 3503.03 | AD78: 2443.5 | AE78: 4009.09 | AF78: 2262.4
A79: Nextdoor Spend | B79: 0 | C79: 0 | D79: 0 | E79: 0 | F79: 0 | G79: 0 | H79: 0 | I79: 0 | J79: 0 | K79: 0 | L79: 0 | M79: 0 | N79: 0 | O79: 0 | P79: 0 | Q79: 0 | R79: 0 | S79: 0 | T79: 0 | U79: 0 | V79: 0 | W79: 0 | X79: 0 | Y79: 0 | Z79: 0 | AA79: 0 | AB79: 0 | AC79: 0 | AD79: 0 | AE79: 0 | AF79: 0
A80: IndieGoGo Spend | B80: 0 | C80: 0 | D80: 0 | E80: 0 | F80: 0 | G80: 0 | H80: 0 | I80: 0 | J80: 0 | K80: 0 | L80: 0 | M80: 0 | N80: 0 | O80: 0 | P80: 0 | Q80: 0 | R80: 0 | S80: 0 | T80: 0 | U80: 0 | V80: 0 | W80: 0 | X80: 0 | Y80: 0 | Z80: 0 | AA80: 0 | AB80: 0 | AC80: 0 | AD80: 0 | AE80: 0 | AF80: 0
A81: Affiliate Fees | B81: 0 | C81: 0 | D81: 69.5 | E81: 110.85 | F81: 35.97 | G81: 0 | H81: 0 | I81: 0 | J81: 0 | K81: 57.59 | L81: 0 | M81: 109.98 | N81: 92.5 | O81: 68.5 | P81: 0 | Q81: 79.64 | R81: 0 | S81: 0 | T81: 57.66 | U81: 0 | V81: 0 | W81: 0 | X81: 0 | Y81: 0 | Z81: 0 | AA81: 0 | AB81: 0 | AC81: 64.83 | AD81: 0 | AE81: 0 | AF81: 93.85
A82: Rachio Fees | B82: =B21*0.2 -> 191.04563 | C82: =C21*0.2 -> 63.681877 | D82: =D21*0.2 -> 127.36375 | E82: =E21*0.2 -> 63.681877 | F82: =F21*0.2 -> 63.681877 | G82: =G21*0.2 -> 0 | H82: =H21*0.2 -> 0 | I82: =I21*0.2 -> 191.04563 | ... AF82: =AF21*0.2 -> 0
A83: Weatherflow Fees | B83: =B25*0.15 -> 0 | C83: =C25*0.15 -> 0 | D83: =D25*0.15 -> 0 | E83: =E25*0.15 -> 0 | F83: =F25*0.15 -> 0 | G83: =G25*0.15 -> 0 | H83: =H25*0.15 -> 177.51915 | I83: =I25*0.15 -> 596.08224 | ... AF83: =AF25*0.15 -> 0
A84: Total DTC Spend | B84: =B74+B75+B76+B77+B79+B81 -> 27535.021 | C84: =C74+C75+C76+C77+C79+C81 -> 37627.29 | D84: =D74+D75+D76+D77+D79+D81 -> 59515.038 | E84: =E74+E75+E76+E77+E79+E81 -> 71003.123 | F84: =F74+F75+F76+F77+F79+F81 -> 66025.564 | G84: =G74+G75+G76+G77+G79+G81 -> 74876.651 | H84: =H74+H75+H76+H77+H79+H81 -> 85729.623 | I84: =I74+I75+I76+I77+I79+I81 -> 81512.211 | ... AF84: =AF74+AF75+AF76+AF77+AF79+AF81 -> 8244.4344
A85: Total Spend | B85: =SUM(B74:B83) -> 27726.067 | C85: =SUM(C74:C83) -> 37690.972 | D85: =SUM(D74:D83) -> 60330.552 | E85: =SUM(E74:E83) -> 71066.805 | F85: =SUM(F74:F83) -> 66089.656 | G85: =SUM(G74:G83) -> 75372.091 | H85: =SUM(H74:H83) -> 85907.142 | I85: =SUM(I74:I83) -> 83076.529 | ... AF85: =SUM(AF74:AF83) -> 10506.834
A87: App Spend | F87: 84.54 | G87: 140.26 | H87: 140.86 | I87: 149.66 | J87: 161.56 | K87: 161.99 | L87: 145.12 | M87: 147.58 | N87: 122.9 | O87: 152.15 | P87: 152.52 | Q87: 167.71 | R87: 150.68 | S87: 56.83
A88: Meta Spend | B88: 0 | C88: 0 | D88: 0 | E88: 0 | F88: =F87*F73 -> 91.244022 | G88: =G87*G73 -> 150.98989 | H88: =H87*H73 -> 152.00203 | I88: =I87*I73 -> 161.24368 | J88: =J87*J73 -> 174.06474 | K88: =K87*K73 -> 174.38224 | L88: =L87*L73 -> 156.20717 | M88: =M87*M73 -> 159.37164 | ... S88: =S87*S73 -> 62.075409 | T88: 0 | U88: 0 | V88: 0 | W88: 0 | X88: 0 | Y88: 0 | Z88: 0 | AA88: 0 | AB88: 0 | AC88: 0 | AD88: 0 | AE88: 0 | AF88: 0
A89: Apple Spend | B89: 14.9 | C89: 19.59 | D89: 28.73 | E89: 17.62 | F89: 15.45 | G89: 11.97 | H89: 11.38 | I89: 17.66 | J89: 25.97 | K89: 27.57 | L89: 32.15 | M89: 15.13 | N89: 24.05 | O89: 26.7 | P89: 27.03 | Q89: 39.16 | R89: 63.07 | S89: 31.66 | T89: 46.99 | U89: 44.7 | V89: 51.41 | W89: 51.47 | X89: 70.06 | Y89: 120.85 | Z89: 14.72 | AA89: 0 | AB89: 0 | AC89: 0 | AD89: 120.35 | AE89: 120.84 | AF89: 121.62
A90: Total APP Spend | B90: =SUM(B88:B89) -> 14.9 | C90: =SUM(C88:C89) -> 19.59 | D90: =SUM(D88:D89) -> 28.73 | E90: =SUM(E88:E89) -> 17.62 | F90: =SUM(F88:F89) -> 106.69402 | G90: =SUM(G88:G89) -> 162.95989 | H90: =SUM(H88:H89) -> 163.38203 | I90: =SUM(I88:I89) -> 178.90368 | ... AF90: =SUM(AF88:AF89) -> 121.62
A92: Blended ROAS | B92: =B34/B85 -> 6.6392146 | C92: =C34/C85 -> 6.3904568 | D92: =D34/D85 -> 5.1501335 | E92: =E34/E85 -> 4.314697 | F92: =F34/F85 -> 4.5198566 | G92: =G34/G85 -> 4.3268415 | H92: =H34/H85 -> 3.8667279 | I92: =I34/I85 -> 4.3183645 | ... AF92: =AF34/AF85 -> 5.1916132
A93: wROAS | B93: =B8/B84 -> 6.616292 | C93: =C8/C84 -> 6.361317 | D93: =D8/D84 -> 5.1978053 | E93: =E8/E84 -> 4.3037315 | F93: =F8/F84 -> 4.5151354 | G93: =G8/G84 -> 4.3386835 | H93: =H8/H84 -> 3.8556093 | I93: =I8/I84 -> 4.3369774 | ... AF93: =AF8/AF84 -> 5.3561977
A94: aROAS | B94: =B14/B78 -> #DIV/0! | C94: =C14/C78 -> #DIV/0! | D94: =D14/D78 -> 0.347308 | E94: =E14/E78 -> #DIV/0! | F94: =F14/F78 -> 0 | G94: =G14/G78 -> 0 | H94: =H14/H78 -> #DIV/0! | I94: =I14/I78 -> 0 | ... AF94: =AF14/AF78 -> 4.5918494
A95: appROAS | B95: =B42/B90 -> 0 | C95: =C42/C90 -> 0 | D95: =D42/D90 -> 0 | E95: =E42/E90 -> 0 | F95: =F42/F90 -> 0 | G95: =G42/G90 -> 0 | H95: =H42/H90 -> 0 | I95: =I42/I90 -> 0 | ... AF95: =AF42/AF90 -> 0
A97: Blended Spend per Unit | B97: =B85/SUM('DTC - P&L'!B57,'AMAZON - P&L'!B32,'Digital Marketplaces'!B17,'Digital Marketplaces'!B129,B60) -> 41.945638 | C97: =C85/SUM('DTC - P&L'!C57,'AMAZON - P&L'!C32,'Digital Marketplaces'!C17,'Digital Marketplaces'!C129,C60) -> 42.977163 | D97: =D85/SUM('DTC - P&L'!D57,'AMAZON - P&L'!D32,'Digital Marketplaces'!D17,'Digital Marketplaces'!D129,D60) -> 52.782635 | E97: =E85/SUM('DTC - P&L'!E57,'AMAZON - P&L'!E32,'Digital Marketplaces'!E17,'Digital Marketplaces'!E129,E60) -> 62.394034 | F97: =F85/SUM('DTC - P&L'!F57,'AMAZON - P&L'!F32,'Digital Marketplaces'!F17,'Digital Marketplaces'!F129,F60) -> 61.024613 | G97: =G85/SUM('DTC - P&L'!G57,'AMAZON - P&L'!G32,'Digital Marketplaces'!G17,'Digital Marketplaces'!G129,G60) -> 63.820568 | H97: =H85/SUM('DTC - P&L'!H57,'AMAZON - P&L'!H32,'Digital Marketplaces'!H17,'Digital Marketplaces'!H129,H60) -> 71.292234 | I97: =I85/SUM('DTC - P&L'!I57,'AMAZON - P&L'!I32,'Digital Marketplaces'!I17,'Digital Marketplaces'!I129,I60) -> 64.10226 | ... AF97: =AF85/SUM('DTC - P&L'!AF57,'AMAZON - P&L'!AF32,'Digital Marketplaces'!AF17,'Digital Marketplaces'!AF129,AF60) -> 80.204843
A98: wSPU | B98: =B84/'DTC - P&L'!B57 -> 42.623872 | C98: =C84/'DTC - P&L'!C57 -> 43.150562 | D98: =D84/'DTC - P&L'!D57 -> 52.297925 | E98: =E84/'DTC - P&L'!E57 -> 62.557818 | F98: =F84/'DTC - P&L'!F57 -> 61.078227 | G98: =G84/'DTC - P&L'!G57 -> 63.670622 | H98: =H84/'DTC - P&L'!H57 -> 71.56062 | I98: =I84/'DTC - P&L'!I57 -> 63.881043 | ... AF98: =AF84/'DTC - P&L'!AF57 -> 79.273407
A99: aSPU | B99: =B78/'AMAZON - P&L'!B32 -> 0 | C99: =C78/'AMAZON - P&L'!C32 -> #DIV/0! | D99: =D78/'AMAZON - P&L'!D32 -> 688.15 | E99: =E78/'AMAZON - P&L'!E32 -> 0 | F99: =F78/'AMAZON - P&L'!F32 -> #DIV/0! | G99: =G78/'AMAZON - P&L'!G32 -> #DIV/0! | H99: =H78/'AMAZON - P&L'!H32 -> 0 | I99: =I78/'AMAZON - P&L'!I32 -> #DIV/0! | ... AF99: =AF78/'AMAZON - P&L'!AF32 -> 83.792593
A100: appCAC | B100: =B90/B68 -> #DIV/0! | C100: =C90/C68 -> #DIV/0! | D100: =D90/D68 -> #DIV/0! | E100: =E90/E68 -> #DIV/0! | F100: =F90/F68 -> #DIV/0! | G100: =G90/G68 -> #DIV/0! | H100: =H90/H68 -> #DIV/0! | I100: =I90/I68 -> #DIV/0! | ... AF100: =AF90/AF68 -> #DIV/0!
A102: Web CR | B102: 0.0367 | C102: 0.0418 | D102: 0.0379 | E102: 0.0354 | F102: 0.0373 | G102: 0.0388 | H102: 0.0378 | I102: 0.0361 | J102: 0.0363 | K102: 0.0429 | L102: 0.0448 | M102: 0.0468 | N102: 0.0432 | O102: 0.038 | P102: 0.0333 | Q102: 0.0303 | R102: 0.022 | S102: 0.0287 | T102: 0.0272 | U102: 0.0238 | V102: 0.0149 | W102: 0.0165 | X102: 0.0136 | Y102: 0.0135 | Z102: 0.0142 | AA102: 0.0132 | AB102: 0.014 | AC102: 0.0159 | AD102: 0.0192 | AE102: 0.0073 | AF102: 0.0096
A103: Web AOV | B103: =B8/B49 -> 271.50483 | C103: =C8/C49 -> 264.77779 | D103: =D8/D49 -> 265.99104 | E103: =E8/E49 -> 266.88068 | F103: =F8/F49 -> 250.30593 | G103: =G8/G49 -> 263.47615 | H103: =H8/H49 -> 270.71247 | I103: =I8/I49 -> 272.56486 | ... AF103: =AF8/AF49 -> 217.53113
A104: fAOV | B104: 241.88 | C104: 236.28 | D104: 236.46 | E104: 236.77 | F104: 221.49 | G104: 235.76 | H104: 240.77 | I104: 244.68 | J104: 245.21 | K104: 251.52 | L104: 240.29 | M104: 240.2 | N104: 245.47 | O104: 262.48 | P104: 281.11 | Q104: 279.43 | R104: 273.14 | S104: 272.71 | T104: 344.69 | U104: 311.77 | V104: 294.47 | W104: 292.43 | X104: 278.15 | Y104: 250.66 | Z104: 203.25 | AA104: 161.33 | AB104: 174.21 | AC104: 164.02 | AD104: 178.7 | AE104: 195.85 | AF104: 226.34
A105: rAOV | B105: 177.59 | C105: 185.28 | D105: 201.29 | E105: 208.05 | F105: 187.4 | G105: 163.35 | H105: 201.66 | I105: 170.3 | J105: 190.34 | K105: 221.57 | L105: 181.77 | M105: 174.06 | N105: 196.31 | O105: 201.33 | P105: 223.58 | Q105: 214.22 | R105: 198.54 | S105: 247.87 | T105: 235.44 | U105: 221.44 | V105: 181.42 | W105: 162.12 | X105: 168.13 | Y105: 130.31 | Z105: 111.57 | AA105: 125.75 | AB105: 94.26 | AC105: 138.58 | AD105: 95.31 | AE105: 145.07 | AF105: 136.01
A107: Customers
A108: Returning | B108: 0.053 | C108: 0.0502 | D108: 0.0466 | E108: 0.0373 | F108: 0.0361 | G108: 0.0481 | H108: 0.0436 | I108: 0.0443 | J108: 0.0429 | K108: 0.0412 | L108: 0.0576 | M108: 0.042 | N108: 0.0508 | O108: 0.0424 | P108: 0.0576 | Q108: 0.0736 | R108: 0.063 | S108: 0.0813 | T108: 0.062 | U108: 0.042 | V108: 0.03 | W108: 0.032 | X108: 0.112 | Y108: 0.113 | Z108: 0.184 | AA108: 0.152 | AB108: 0.166 | AC108: 0.139 | AD108: 0.224 | AE108: 0.113 | AF108: 0.143
A109: First-time | B109: =1-B108 -> 0.947 | C109: =1-C108 -> 0.9498 | D109: =1-D108 -> 0.9534 | E109: =1-E108 -> 0.9627 | F109: =1-F108 -> 0.9639 | G109: =1-G108 -> 0.9519 | H109: =1-H108 -> 0.9564 | I109: =1-I108 -> 0.9557 | ... T109: =1-T108 -> 0.938 | U109: 0.958 | V109: =1-V108 -> 0.97 | W109: =1-W108 -> 0.968 | X109: =1-X108 -> 0.888 | Y109: =1-Y108 -> 0.887 | Z109: =1-Z108 -> 0.816 | AA109: =1-AA108 -> 0.848 | AB109: =1-AB108 -> 0.834 | AC109: =1-AC108 -> 0.861 | ... AF109: =1-AF108 -> 0.857
B111: 45261 | C111: Goal | D111: % of Goal
A112: Revenue | B112: =SUM(B34:AF34)+SUM(B47:AF47) -> 7708343.8 | C112: 4600000 | D112: =B112/C112 -> 1.6757269
...

Sheet DTC - P&L
A1: DECEMBER | B1: 45261 | C1: 45262 | D1: 45263 | E1: 45264 | F1: 45265 | G1: 45266 | H1: 45267 | I1: 45268 | J1: 45269 | K1: 45270 | L1: 45271 | M1: 45272 | N1: 45273 | O1: 45274 | P1: 45275 | Q1: 45276 | R1: 45277 | S1: 45278 | T1: 45279 | U1: 45280 | V1: 45281 | W1: 45282 | X1: 45283 | Y1: 45284 | Z1: 45285 | AA1: 45286 | AB1: 45287 | AC1: 45288 | AD1: 45289 | AE1: 45290 | AF1: 45291
A2: DAY | B2: FRI | C2: SAT | D2: SUN | E2: MON | F2: TUE | G2: WED | H2: THU | I2: FRI | J2: SAT | K2: SUN | L2: MON | M2: TUE | N2: WED | O2: THU | P2: FRI | Q2: SAT | R2: SUN | S2: MON | T2: TUE | U2: WED | V2: THU | W2: FRI | X2: SAT | Y2: SUN | Z2: MON | AA2: TUE | AB2: WED | AC2: THU | AD2: FRI | AE2: SAT | AF2: SUN
A3: COMMENT
A4: Orders
A5: Meta | B5: 291 | C5: 406 | D5: 638 | E5: 655 | F5: 639 | G5: 678 | H5: 718 | I5: 715 | J5: 674 | K5: 800 | L5: 927 | M5: 802 | N5: 680 | O5: 386 | P5: 317 | Q5: 236 | R5: 152 | S5: 199 | T5: 171 | U5: 152 | V5: 81 | W5: 59 | X5: 34 | Y5: 35 | Z5: 49 | AA5: 67 | AB5: 59 | AC5: 60 | AD5: 61 | AE5: 48 | AF5: 57 | AG5: =SUM(B5:AF5) -> 10846
A6: Google | B6: 233 | C6: 327 | D6: 378 | E6: 427 | F6: 461 | G6: 504 | H6: 642 | I6: 598 | J6: 611 | K6: 923 | L6: 880 | M6: 708 | N6: 620 | O6: 432 | P6: 344 | Q6: 303 | R6: 204 | S6: 221 | T6: 194 | U6: 146 | V6: 80 | W6: 75 | X6: 77 | Y6: 76 | Z6: 146 | AA6: 122 | AB6: 95 | AC6: 84 | AD6: 83 | AE6: 75 | AF6: 94 | AG6: =SUM(B6:AF6) -> 10163
A7: TikTok | B7: 0 | C7: 0 | D7: 0 | E7: 0 | F7: 0 | G7: 0 | H7: 0 | I7: 0 | J7: 0 | K7: 0 | L7: 0 | M7: 0 | N7: 0 | O7: 0 | P7: 0 | Q7: 0 | R7: 0 | S7: 0 | T7: 0 | U7: 0 | V7: 0 | W7: 0 | X7: 0 | Y7: 0 | Z7: 0 | AA7: 0 | AB7: 0 | AC7: 0 | AD7: 0 | AE7: 0 | AF7: 0 | AG7: =SUM(B7:AF7) -> 0
A8: Bing | B8: 34 | C8: 82 | D8: 60 | E8: 56 | F8: 60 | G8: 114 | H8: 84 | I8: 48 | J8: 42 | K8: 74 | L8: 104 | M8: 98 | N8: 112 | O8: 66 | P8: 58 | Q8: 22 | R8: 18 | S8: 30 | T8: 38 | U8: 22 | V8: 22 | W8: 6 | X8: 4 | Y8: 2 | Z8: 24 | AA8: 24 | AB8: 4 | AC8: 6 | AD8: 14 | AE8: 26 | AF8: 30 | AG8: =SUM(B8:AF8) -> 1384
A9: Nextdoor | B9: 0 | C9: 0 | D9: 0 | E9: 0 | F9: 0 | G9: 0 | H9: 0 | I9: 0 | J9: 0 | K9: 0 | L9: 0 | M9: 0 | N9: 0 | O9: 0 | P9: 0 | Q9: 0 | R9: 0 | S9: 0 | T9: 0 | U9: 0 | V9: 0 | W9: 0 | X9: 0 | Y9: 0 | Z9: 0 | AA9: 0 | AB9: 0 | AC9: 0 | AD9: 0 | AE9: 0 | AF9: 0 | AG9: =SUM(B9:AF9) -> 0
A10: Affiliates (Refersion) | B10: 0 | C10: 0 | D10: 1 | E10: 2 | F10: 1 | G10: 0 | H10: 0 | I10: 0 | J10: 0 | K10: 1 | L10: 0 | M10: 2 | N10: 1 | O10: 1 | P10: 0 | Q10: 2 | R10: 0 | S10: 0 | T10: 1 | U10: 0 | V10: 0 | W10: 0 | X10: 0 | Y10: 0 | Z10: 0 | AA10: 0 | AB10: 0 | AC10: 1 | AD10: 0 | AE10: 0 | AF10: 1 | AG10: =SUM(B10:AF10) -> 14
A11: Email | B11: 20 | C11: 13 | D11: 7 | E11: 8 | F11: 80 | G11: 27 | H11: 5 | I11: 9 | J11: 4 | K11: 0 | L11: 50 | M11: 34 | N11: 22 | O11: 13 | P11: 7 | Q11: 9 | R11: 7 | S11: 4 | T11: 3 | U11: 2 | V11: 0 | W11: 0 | X11: 0 | Y11: 1 | Z11: 0 | AA11: 4 | AB11: 4 | AC11: 3 | AD11: 2 | AE11: 1 | AF11: 4 | AG11: =SUM(B11:AF11) -> 343
A12: All | B12: =SUM(B5:B11) -> 578 | C12: =SUM(C5:C11) -> 828 | D12: =SUM(D5:D11) -> 1084 | E12: =SUM(E5:E11) -> 1148 | F12: =SUM(F5:F11) -> 1241 | G12: =SUM(G5:G11) -> 1323 | H12: =SUM(H5:H11) -> 1449 | I12: =SUM(I5:I11) -> 1370 | ... AF12: =SUM(AF5:AF11) -> 186 | AG12: =SUM(B12:AF12) -> 22750
A14: Revenue
A15: Meta | B15: 81056.24 | C15: 110015.82 | D15: 172277.91 | E15: 176517.15 | F15: 172438.66 | G15: 186215.27 | H15: 201234.58 | I15: 195070.22 | J15: 192468.85 | K15: 225532.2 | L15: 261140.55 | M15: 221820.29 | N15: 196094.06 | O15: 121879.9 | P15: 107909.7 | Q15: 80499.91 | R15: 51068.984 | S15: 66232.198 | T15: 58229.613 | U15: 47539.611 | V15: 23548.263 | W15: 16465.432 | X15: 9273.1188 | Y15: 8708.3697 | Z15: 8925.7332 | AA15: 9984.6099 | AB15: 9897.2378 | AC15: 9618.2902 | AD15: 9410.3864 | AE15: 7548.0626 | AF15: 10744.301 | AG15: =SUM(B15:AF15) -> 3049365.5
A16: Google | B16: 62206.06 | C16: 85549.22 | D16: 100052.64 | E16: 111654.98 | F16: 122346 | G16: 132441.63 | H16: 165865.86 | I16: 167384.69 | J16: 167920.56 | K16: 252823.78 | L16: 237174.61 | M16: 192957.91 | N16: 176065.38 | O16: 136962.91 | P16: 113652.55 | Q16: 102290.09 | R16: 65183.65 | S16: 71115.64 | T16: 64605.62 | U16: 43130.73 | V16: 23208.51 | W16: 19398.87 | X16: 19951.31 | Y16: 18464.11 | Z16: 27526.43 | AA16: 20208.31 | AB16: 15603.75 | AC16: 13883.39 | AD16: 13080.78 | AE16: 14160.02 | AF16: 20822.54 | AG16: =SUM(B16:AF16) -> 2777692.5
A17: TikTok | B17: 0 | C17: 0 | D17: 0 | E17: 0 | F17: 0 | G17: 0 | H17: 0 | I17: 0 | J17: 0 | K17: 0 | L17: 0 | M17: 0 | N17: 0 | O17: 0 | P17: 0 | Q17: 0 | R17: 0 | S17: 0 | T17: 0 | U17: 0 | V17: 0 | W17: 0 | X17: 0 | Y17: 0 | Z17: 0 | AA17: 0 | AB17: 0 | AC17: 0 | AD17: 0 | AE17: 0 | AF17: 0 | AG17: =SUM(B17:AF17) -> 0
A18: Bing | B18: 4267 | C18: 10291 | D18: 7530 | E18: 7028 | F18: 7530 | G18: 14307 | H18: 10542 | I18: 6024 | J18: 5271 | K18: 9287 | L18: 13052 | M18: 12299 | N18: 14056 | O18: 8283 | P18: 7279 | Q18: 2761 | R18: 2259 | S18: 3765 | T18: 4769 | U18: 2761 | V18: 2761 | W18: 753 | X18: 502 | Y18: 251 | Z18: 3012 | AA18: 3012 | AB18: 502 | AC18: 753 | AD18: 1757 | AE18: 3263 | AF18: 3765 | AG18: =SUM(B18:AF18) -> 173692
A19: Nextdoor | B19: 0 | C19: 0 | D19: 0 | E19: 0 | F19: 0 | G19: 0 | H19: 0 | I19: 0 | J19: 0 | K19: 0 | L19: 0 | M19: 0 | N19: 0 | O19: 0 | P19: 0 | Q19: 0 | R19: 0 | S19: 0 | T19: 0 | U19: 0 | V19: 0 | W19: 0 | X19: 0 | Y19: 0 | Z19: 0 | AA19: 0 | AB19: 0 | AC19: 0 | AD19: 0 | AE19: 0 | AF19: 0 | AG19: =SUM(B19:AF19) -> 0
A20: Affiliates (Refersion) | B20: 0 | C20: 0 | D20: 278 | E20: 497.72 | F20: 179.85 | G20: 0 | H20: 0 | I20: 0 | J20: 0 | K20: 230.34 | L20: 0 | M20: 549.92 | N20: 370 | O20: 274 | P20: 0 | Q20: 318.59 | R20: 0 | S20: 0 | T20: 288.31 | U20: 0 | V20: 0 | W20: 0 | X20: 0 | Y20: 0 | Z20: 0 | AA20: 0 | AB20: 0 | AC20: 324.14 | AD20: 0 | AE20: 0 | AF20: 375.41 | AG20: =SUM(B20:AF20) -> 3686.28
A21: Email | B21: 5460.24 | C21: 2667.72 | D21: 2101.12 | E21: 2466.51 | F21: 6838.53 | G21: 3498.22 | H21: 414.78 | I21: 1629.87 | J21: 1009.77 | K21: 0 | L21: 11648.98 | M21: 7357.52 | N21: 4119.13 | O21: 3745.99 | P21: 1274.38 | Q21: 2124.21 | R21: 1629.29 | S21: 1381.18 | T21: 1565.55 | U21: 296.74 | V21: 0 | W21: 0 | X21: 0 | Y21: 341.09 | Z21: 0 | AA21: 439.63 | AB21: 238.92 | AC21: 241.74 | AD21: 487.06 | AE21: 133.29 | AF21: 575.49 | AG21: =SUM(B21:AF21) -> 63686.95
A22: All | B22: =SUM(B15:B21) -> 152989.54 | C22: =SUM(C15:C21) -> 208523.76 | D22: =SUM(D15:D21) -> 282239.67 | E22: =SUM(E15:E21) -> 298164.36 | F22: =SUM(F15:F21) -> 309333.04 | G22: =SUM(G15:G21) -> 336462.12 | H22: =SUM(H15:H21) -> 378057.22 | I22: =SUM(I15:I21) -> 370108.78 | ... AF22: =SUM(AF15:AF21) -> 36282.741 | AG22: =SUM(B22:AF22) -> 6068123.3
A24: Media Cost
A25: Meta | B25: =Summary!B74 -> 21772.841 | C25: =Summary!C74 -> 31642.26 | D25: =Summary!D74 -> 53297.918 | E25: =Summary!E74 -> 64412.413 | F25: =Summary!F74 -> 57917.224 | G25: =Summary!G74 -> 61406.531 | H25: =Summary!H74 -> 68789.323 | I25: =Summary!I74 -> 59937.281 | ... AF25: =Summary!AF74 -> 5934.1944 | AG25: =SUM(B25:AF25) -> 1035696.4
A26: Google | B26: =Summary!B75 -> 5447.08 | C26: =Summary!C75 -> 5717.82 | D26: =Summary!D75 -> 5853.85 | E26: =Summary!E75 -> 6168.03 | F26: =Summary!F75 -> 7765.18 | G26: =Summary!G75 -> 12389.76 | H26: =Summary!H75 -> 15878.71 | I26: =Summary!I75 -> 20488.81 | ... AF26: =Summary!AF75 -> 2034.48 | AG26: =SUM(B26:AF26) -> 290838.42
A27: TikTok | B27: =Summary!B77 -> 0 | C27: =Summary!C77 -> 0 | D27: =Summary!D77 -> 0 | E27: =Summary!E77 -> 0 | F27: =Summary!F77 -> 0 | G27: =Summary!G77 -> 0 | H27: =Summary!H77 -> 0 | I27: =Summary!I77 -> 0 | ... AF27: =Summary!AF77 -> 0 | AG27: =SUM(B27:AF27) -> 8186.54
A28: Bing | B28: =Summary!B76 -> 315.1 | C28: =Summary!C76 -> 267.21 | D28: =Summary!D76 -> 293.77 | E28: =Summary!E76 -> 311.83 | F28: =Summary!F76 -> 307.19 | G28: =Summary!G76 -> 1080.36 | H28: =Summary!H76 -> 1061.59 | I28: =Summary!I76 -> 1086.12 | ... AF28: =Summary!AF76 -> 181.91 | AG28: =SUM(B28:AF28) -> 22766.24
A29: Nextdoor | B29: =Summary!B79 -> 0 | C29: =Summary!C79 -> 0 | D29: =Summary!D79 -> 0 | E29: =Summary!E79 -> 0 | F29: =Summary!F79 -> 0 | G29: =Summary!G79 -> 0 | H29: =Summary!H79 -> 0 | I29: =Summary!I79 -> 0 | ... AF29: =Summary!AF79 -> 0 | AG29: =SUM(B29:AF29) -> 0
A30: Affiliate Fee (20%) | B30: =Summary!B81 -> 0 | C30: =Summary!C81 -> 0 | D30: =Summary!D81 -> 69.5 | E30: =Summary!E81 -> 110.85 | F30: =Summary!F81 -> 35.97 | G30: =Summary!G81 -> 0 | H30: =Summary!H81 -> 0 | I30: =Summary!I81 -> 0 | ... AF30: =Summary!AF81 -> 93.85 | AG30: =SUM(B30:AF30) -> 840.87
A31: All | B31: =SUM(B25:B30) -> 27535.021 | C31: =SUM(C25:C30) -> 37627.29 | D31: =SUM(D25:D30) -> 59515.038 | E31: =SUM(E25:E30) -> 71003.123 | F31: =SUM(F25:F30) -> 66025.564 | G31: =SUM(G25:G30) -> 74876.651 | H31: =SUM(H25:H30) -> 85729.623 | I31: =SUM(I25:I30) -> 81512.211 | ... AF31: =SUM(AF25:AF30) -> 8244.4344 | AG31: =SUM(B31:AF31) -> 1358328.5
A36: Revenue
A37: Revenue Woocommerce (Platform) | B37: =Summary!B8 -> 182179.74 | C37: =Summary!C8 -> 239359.12 | D37: =Summary!D8 -> 309347.58 | E37: =Summary!E8 -> 305578.38 | F37: =Summary!F8 -> 298114.36 | G37: =Summary!G8 -> 324866.09 | H37: =Summary!H8 -> 330539.93 | I37: =Summary!I8 -> 353516.62 | ... AE37: =Summary!AE8 -> 45927.46 | AF37: 44158.82 | AG37: =sum(B37:AF37) -> 6271664.5
A38: SUM | B38: =SUM(B37) -> 182179.74 | C38: =SUM(C37) -> 239359.12 | D38: =SUM(D37) -> 309347.58 | E38: =SUM(E37) -> 305578.38 | F38: =SUM(F37) -> 298114.36 | G38: =SUM(G37) -> 324866.09 | H38: =SUM(H37) -> 330539.93 | I38: =SUM(I37) -> 353516.62 | ... AF38: =SUM(AF37) -> 44158.82 | AG38: =sum(B38:AF38) -> 6271664.5
A40: Orders
A41: Orders Woocommerce (Platform) | B41: =Summary!B49 -> 671 | C41: =Summary!C49 -> 904 | D41: =Summary!D49 -> 1163 | E41: =Summary!E49 -> 1145 | F41: =Summary!F49 -> 1191 | G41: =Summary!G49 -> 1233 | H41: =Summary!H49 -> 1221 | I41: =Summary!I49 -> 1297 | ... AE41: =Summary!AE49 -> 238 | AF41: 203 | AG41: =sum(B41:AF41) -> 22951
A42: SUM | B42: =SUM(B41) -> 671 | C42: =SUM(C41) -> 904 | D42: =SUM(D41) -> 1163 | E42: =SUM(E41) -> 1145 | F42: =SUM(F41) -> 1191 | G42: =SUM(G41) -> 1233 | H42: =SUM(H41) -> 1221 | I42: =SUM(I41) -> 1297 | ... AF42: =SUM(AF41) -> 203 | AG42: =sum(B42:AF42) -> 22951
A44: Breakdown
A45: - Hardware | B45: =Summary!B9 -> 148896.28 | C45: =Summary!C9 -> 196722.13 | D45: =Summary!D9 -> 255328.76 | E45: =Summary!E9 -> 254086.11 | F45: =Summary!F9 -> 245877.15 | G45: =Summary!G9 -> 268135.33 | H45: =Summary!H9 -> 267062.57 | I45: =Summary!I9 -> 283105.87 | ... AF45: =Summary!AF9 -> 29212.93 | AG45: =SUM(B45:AF45) -> 5010192.3
A46: - Add-ons | B46: =Summary!B10 -> 12027.92 | C46: =Summary!C10 -> 14248.12 | D46: =Summary!D10 -> 17773.14 | E46: =Summary!E10 -> 15874.79 | F46: =Summary!F10 -> 15079.85 | G46: =Summary!G10 -> 17998.27 | H46: =Summary!H10 -> 24577.23 | I46: =Summary!I10 -> 29469.5 | ... AF46: =Summary!AF10 -> 9678.87 | AG46: =SUM(B46:AF46) -> 445560.17
A47: - Merch | B47: =Summary!B11 -> 161 | C47: =Summary!C11 -> 238.99 | D47: =Summary!D11 -> 255.97 | E47: =Summary!E11 -> 49.89 | F47: =Summary!F11 -> 1934.95 | G47: =Summary!G11 -> 539.98 | H47: =Summary!H11 -> 335.15 | I47: =Summary!I11 -> 635.5 | ... AF47: =Summary!AF11 -> 55.99 | AG47: =SUM(B47:AF47) -> 10370.71
A48: - Taxes | B48: =Summary!B12 -> 10324.54 | C48: =Summary!C12 -> 13474.88 | D48: =Summary!D12 -> 17959.71 | E48: =Summary!E12 -> 17167.59 | F48: =Summary!F12 -> 16904.41 | G48: =Summary!G12 -> 18912.51 | H48: =Summary!H12 -> 19444.98 | I48: =Summary!I12 -> 20395.75 | ... AF48: =Summary!AF12 -> 2431.03 | AG48: =SUM(B48:AF48) -> 359746.31
A49: - Shipping | B49: =Summary!B13 -> 10770 | C49: =Summary!C13 -> 14675 | D49: =Summary!D13 -> 18030 | E49: =Summary!E13 -> 18400 | F49: =Summary!F13 -> 18318 | G49: =Summary!G13 -> 19280 | H49: =Summary!H13 -> 19120 | I49: =Summary!I13 -> 19910 | ... AF49: =Summary!AF13 -> 2780 | AG49: =SUM(B49:AF49) -> 445795
A50: SUM | B50: =SUM(B45:B49) -> 182179.74 | C50: =SUM(C45:C49) -> 239359.12 | D50: =SUM(D45:D49) -> 309347.58 | E50: =SUM(E45:E49) -> 305578.38 | F50: =SUM(F45:F49) -> 298114.36 | G50: =SUM(G45:G49) -> 324866.09 | H50: =SUM(H45:H49) -> 330539.93 | I50: =SUM(I45:I49) -> 353516.62 | ... AF50: =SUM(AF45:AF49) -> 44158.82 | AG50: =SUM(B50:AF50) -> 6271664.5
A52: Units Sold (Gross)
A53: SKU 1 - Blue | B53: 165 | C53: 218 | D53: 290 | E53: 306 | F53: 177 | G53: 137 | H53: 323 | I53: 404 | J53: 312 | K53: 460 | L53: 139 | M53: 0 | N53: 0 | O53: 0 | P53: 0 | Q53: 0 | R53: 0 | S53: 0 | T53: 0 | U53: 0 | V53: 0 | W53: 0 | X53: 0 | Y53: 0 | Z53: 0 | AA53: 0 | AB53: 0 | AC53: 0 | AD53: 0 | AE53: 0 | AF53: 0 | AG53: =sum(B53:AF53) -> 2931
A54: SKU 2 - Yellow | B54: 32 | C54: 25 | D54: 45 | E54: 36 | F54: 135 | G54: 234 | H54: 241 | I54: 266 | J54: 332 | K54: 423 | L54: 479 | M54: 465 | N54: 415 | O54: 286 | P54: 211 | Q54: 158 | R54: 136 | S54: 151 | T54: 151 | U54: 123 | V54: 59 | W54: 45 | X54: 32 | Y54: 31 | Z54: 47 | AA54: 18 | AB54: 14 | AC54: 17 | AD54: 15 | AE54: 30 | AF54: 18 | AG54: =sum(B54:AF54) -> 4670
A55: SKU 3 - Blue w/ Solar | B55: 360 | C55: 536 | D55: 709 | E55: 693 | F55: 456 | G55: 350 | H55: 131 | I55: 0 | J55: 0 | K55: 0 | L55: 54 | M55: 98 | N55: 87 | O55: 21 | P55: 0 | Q55: 0 | R55: 0 | S55: 0 | T55: 0 | U55: 0 | V55: 0 | W55: 0 | X55: 0 | Y55: 0 | Z55: 0 | AA55: 0 | AB55: 0 | AC55: 0 | AD55: 0 | AE55: 0 | AF55: 0 | AG55: =sum(B55:AF55) -> 3495
A56: SKU 4 - Yellow w/ Solar | B56: 89 | C56: 93 | D56: 94 | E56: 100 | F56: 313 | G56: 455 | H56: 503 | I56: 606 | J56: 636 | K56: 1022 | L56: 1129 | M56: 1021 | N56: 793 | O56: 579 | P56: 455 | Q56: 374 | R56: 236 | S56: 273 | T56: 251 | U56: 201 | V56: 106 | W56: 90 | X56: 64 | Y56: 50 | Z56: 68 | AA56: 63 | AB56: 55 | AC56: 52 | AD56: 61 | AE56: 81 | AF56: 86 | AG56: =sum(B56:AF56) -> 9999
A57: SUM (SKU 1 - SKU 4) | B57: =SUM(B53:B56) -> 646 | C57: =SUM(C53:C56) -> 872 | D57: =SUM(D53:D56) -> 1138 | E57: =SUM(E53:E56) -> 1135 | F57: =SUM(F53:F56) -> 1081 | G57: =SUM(G53:G56) -> 1176 | H57: =SUM(H53:H56) -> 1198 | I57: =SUM(I53:I56) -> 1276 | ... AF57: =SUM(AF53:AF56) -> 104 | AG57: =sum(B57:AF57) -> 21095
A59: Wall Mount | B59: 136 | C59: 185 | D59: 262 | E59: 247 | F59: 204 | G59: 242 | H59: 226 | I59: 264 | J59: 298 | K59: 454 | L59: 425 | M59: 318 | N59: 297 | O59: 271 | P59: 257 | Q59: 197 | R59: 144 | S59: 128 | T59: 139 | U59: 112 | V59: 57 | W59: 47 | X59: 32 | Y59: 34 | Z59: 75 | AA59: 86 | AB59: 58 | AC59: 53 | AD59: 78 | AE59: 65 | AF59: 65 | AG59: =sum(B59:AF59) -> 5456
A60: Suet Ball Holder | B60: 0 | C60: 0 | D60: 0 | E60: 0 | F60: 0 | G60: 0 | H60: 0 | I60: 0 | J60: 0 | K60: 0 | L60: 0 | M60: 0 | N60: 0 | O60: 0 | P60: 0 | Q60: 0 | R60: 0 | S60: 0 | T60: 0 | U60: 0 | V60: 36 | W60: 42 | X60: 37 | Y60: 32 | Z60: 61 | AA60: 84 | AB60: 53 | AC60: 60 | AD60: 59 | AE60: 57 | AF60: 63 | AG60: =sum(B60:AF60) -> 584
A61: 3-in-1 Nutrition Set - Blue | B61: 62 | C61: 80 | D61: 106 | E61: 97 | F61: 59 | G61: 67 | H61: 50 | I61: 57 | J61: 59 | K61: 98 | L61: 68 | M61: 35 | N61: 47 | O61: 17 | P61: 5 | Q61: 10 | R61: 6 | S61: 4 | T61: 5 | U61: 4 | V61: 3 | W61: 4 | X61: 1 | Y61: 5 | Z61: 23 | AA61: 16 | AB61: 10 | AC61: 12 | AD61: 15 | AE61: 7 | AF61: 11 | AG61: =sum(B61:AF61) -> 1043
A62: 3-in-1 Nutrition Set - Yellow | B62: 17 | C62: 21 | D62: 9 | E62: 13 | F62: 45 | G62: 65 | H62: 61 | I62: 69 | J62: 81 | K62: 163 | L62: 171 | M62: 119 | N62: 121 | O62: 209 | P62: 214 | Q62: 167 | R62: 128 | S62: 123 | T62: 122 | U62: 100 | V62: 50 | W62: 33 | X62: 27 | Y62: 25 | Z62: 39 | AA62: 41 | AB62: 28 | AC62: 31 | AD62: 31 | AE62: 33 | AF62: 37 | AG62: =sum(B62:AF62) -> 2393
A63: Solar Roof Single - Blue | B63: 29 | C63: 21 | D63: 24 | E63: 17 | F63: 20 | G63: 14 | H63: 212 | I63: 307 | J63: 258 | K63: 397 | L63: 155 | M63: 28 | N63: 18 | O63: 23 | P63: 9 | Q63: 18 | R63: 5 | S63: 12 | T63: 6 | U63: 5 | V63: 3 | W63: 6 | X63: 6 | Y63: 8 | Z63: 15 | AA63: 22 | AB63: 19 | AC63: 15 | AD63: 16 | AE63: 16 | AF63: 13 | AG63: =sum(B63:AF63) -> 1717
A64: Solar Roof Single - Yellow | B64: 6 | C64: 3 | D64: 7 | E64: 2 | F64: 4 | G64: 10 | H64: 14 | I64: 9 | J64: 18 | K64: 33 | L64: 25 | M64: 38 | N64: 27 | O64: 14 | P64: 14 | Q64: 13 | R64: 9 | S64: 8 | T64: 12 | U64: 8 | V64: 7 | W64: 4 | X64: 5 | Y64: 5 | Z64: 16 | AA64: 11 | AB64: 11 | AC64: 14 | AD64: 7 | AE64: 11 | AF64: 9 | AG64: =sum(B64:AF64) -> 374
A65: Perch Extender - Blue | B65: 109 | C65: 171 | D65: 211 | E65: 190 | F65: 148 | G65: 144 | H65: 136 | I65: 120 | J65: 138 | K65: 201 | L65: 138 | M65: 85 | N65: 95 | O65: 55 | P65: 36 | Q65: 43 | R65: 38 | S65: 40 | T65: 18 | U65: 23 | V65: 14 | W65: 20 | X65: 13 | Y65: 19 | Z65: 65 | AA65: 89 | AB65: 73 | AC65: 73 | AD65: 50 | AE65: 46 | AF65: 40 | AG65: =sum(B65:AF65) -> 2641
A66: Perch Extender - Yellow | B66: 35 | C66: 42 | D66: 33 | E66: 31 | F66: 78 | G66: 128 | H66: 127 | I66: 149 | J66: 170 | K66: 325 | L66: 319 | M66: 282 | N66: 124 | O66: 0 | P66: 0 | Q66: 0 | R66: 0 | S66: 0 | T66: 0 | U66: 0 | V66: 0 | W66: 0 | X66: 0 | Y66: 0 | Z66: 0 | AA66: 0 | AB66: 0 | AC66: 0 | AD66: 54 | AE66: 58 | AF66: 68 | AG66: =sum(B66:AF66) -> 2023
A67: SUM (Add-ons) | B67: =SUM(B59:B66) -> 394 | C67: =SUM(C59:C66) -> 523 | D67: =SUM(D59:D66) -> 652 | E67: =SUM(E59:E66) -> 597 | F67: =SUM(F59:F66) -> 558 | G67: =SUM(G59:G66) -> 670 | H67: =SUM(H59:H66) -> 826 | I67: =SUM(I59:I66) -> 975 | ... AF67: =SUM(AF59:AF66) -> 306 | AG67: =sum(B67:AF67) -> 16231
A69: Merch Units Sold (Gross)
A70: Merch Units | B70: 397 | C70: 580 | D70: 745 | E70: 703 | F70: 730 | G70: 676 | H70: 253 | I70: 33 | J70: 33 | K70: 35 | L70: 41 | M70: 36 | N70: 30 | O70: 19 | P70: 22 | Q70: 15 | R70: 10 | S70: 16 | T70: 8 | U70: 14 | V70: 4 | W70: 4 | X70: 3 | Y70: 2 | Z70: 6 | AA70: 6 | AB70: 3 | AC70: 2 | AD70: 3 | AE70: 2 | AF70: 3 | AG70: =sum(B70:AF70) -> 4434
A72: First-time Customers
A73: SKU 1 - Blue | B73: =B53-B90 -> 157 | C73: =C53-C90 -> 214 | D73: =D53-D90 -> 281 | E73: =E53-E90 -> 299 | F73: =F53-F90 -> 171 | G73: =G53-G90 -> 132 | H73: =H53-H90 -> 316 | I73: =I53-I90 -> 392 | ... AF73: =AF53-AF90 -> 0 | AG73: =sum(B73:AF73) -> 2847
A74: SKU 2 - Yellow | B74: =B54-B91 -> 28 | C74: =C54-C91 -> 25 | D74: =D54-D91 -> 42 | E74: =E54-E91 -> 36 | F74: =F54-F91 -> 130 | G74: =G54-G91 -> 226 | H74: =H54-H91 -> 233 | I74: =I54-I91 -> 258 | ... AF74: =AF54-AF91 -> 17 | AG74: =sum(B74:AF74) -> 4514
A75: SKU 3 - Blue w/ Solar | B75: =B55-B92 -> 349 | C75: =C55-C92 -> 522 | D75: =D55-D92 -> 692 | E75: =E55-E92 -> 680 | F75: =F55-F92 -> 446 | G75: =G55-G92 -> 339 | H75: =H55-H92 -> 127 | I75: =I55-I92 -> 0 | ... AF75: =AF55-AF92 -> 0 | AG75: =sum(B75:AF75) -> 3408
A76: SKU 4 - Yellow w/ Solar | B76: =B56-B93 -> 87 | C76: =C56-C93 -> 91 | D76: =D56-D93 -> 90 | E76: =E56-E93 -> 96 | F76: =F56-F93 -> 307 | G76: =G56-G93 -> 445 | H76: =H56-H93 -> 487 | I76: =I56-I93 -> 592 | ... AF76: =AF56-AF93 -> 82 | AG76: =sum(B76:AF76) -> 9704
A77: SUM (SKU 1 - SKU 4) | B77: =SUM(B73:B76) -> 621 | C77: =SUM(C73:C76) -> 852 | D77: =SUM(D73:D76) -> 1105 | E77: =SUM(E73:E76) -> 1111 | F77: =SUM(F73:F76) -> 1054 | G77: =SUM(G73:G76) -> 1142 | H77: =SUM(H73:H76) -> 1163 | I77: =SUM(I73:I76) -> 1242 | ... AF77: =SUM(AF73:AF76) -> 99 | AG77: =sum(B77:AF77) -> 20473
A79: Wall Mount | B79: =B59-B96 -> 134 | C79: =C59-C96 -> 177 | D79: =D59-D96 -> 248 | E79: =E59-E96 -> 238 | F79: =F59-F96 -> 200 | G79: =G59-G96 -> 233 | H79: =H59-H96 -> 215 | I79: =I59-I96 -> 253 | ... AF79: =AF59-AF96 -> 56 | AG79: =sum(B79:AF79) -> 5200
A80: Suet Ball Holder | B80: =B60-B97 -> 0 | C80: =C60-C97 -> 0 | D80: =D60-D97 -> 0 | E80: =E60-E97 -> 0 | F80: =F60-F97 -> 0 | G80: =G60-G97 -> 0 | H80: =H60-H97 -> 0 | I80: =I60-I97 -> 0 | ... AF80: =AF60-AF97 -> 51 | AG80: =sum(B80:AF80) -> 492
A81: 3-in-1 Nutrition Set - Blue | B81: =B61-B98 -> 59 | C81: =C61-C98 -> 74 | D81: =D61-D98 -> 100 | E81: =E61-E98 -> 86 | F81: =F61-F98 -> 57 | G81: =G61-G98 -> 58 | H81: =H61-H98 -> 48 | I81: =I61-I98 -> 46 | ... AF81: =AF61-AF98 -> 8 | AG81: =sum(B81:AF81) -> 945
A82: 3-in-1 Nutrition Set - Yellow | B82: =B62-B99 -> 17 | C82: =C62-C99 -> 19 | D82: =D62-D99 -> 9 | E82: =E62-E99 -> 12 | F82: =F62-F99 -> 43 | G82: =G62-G99 -> 62 | H82: =H62-H99 -> 57 | I82: =I62-I99 -> 63 | ... AF82: =AF62-AF99 -> 31 | AG82: =sum(B82:AF82) -> 2286
A83: Solar Roof Single - Blue | B83: =B63-B100 -> 27 | C83: =C63-C100 -> 19 | D83: =D63-D100 -> 20 | E83: =E63-E100 -> 15 | F83: =F63-F100 -> 19 | G83: =G63-G100 -> 12 | H83: =H63-H100 -> 204 | I83: =I63-I100 -> 294 | ... AF83: =AF63-AF100 -> 12 | AG83: =sum(B83:AF83) -> 1594
A84: Solar Roof Single - Yellow | B84: =B64-B101 -> 5 | C84: =C64-C101 -> 3 | D84: =D64-D101 -> 7 | E84: =E64-E101 -> 2 | F84: =F64-F101 -> 3 | G84: =G64-G101 -> 9 | H84: =H64-H101 -> 13 | I84: =I64-I101 -> 7 | ... AF84: =AF64-AF101 -> 7 | AG84: =sum(B84:AF84) -> 330
A85: Perch Extender - Blue | B85: =B65-B102 -> 105 | C85: =C65-C102 -> 157 | D85: =D65-D102 -> 201 | E85: =E65-E102 -> 176 | F85: =F65-F102 -> 140 | G85: =G65-G102 -> 129 | H85: =H65-H102 -> 123 | I85: =I65-I102 -> 106 | ... AF85: =AF65-AF102 -> 32 | AG85: =sum(B85:AF85) -> 2365
A86: Perch Extender - Yellow | B86: =B66-B103 -> 31 | C86: =C66-C103 -> 40 | D86: =D66-D103 -> 32 | E86: =E66-E103 -> 29 | F86: =F66-F103 -> 74 | G86: =G66-G103 -> 120 | H86: =H66-H103 -> 116 | I86: =I66-I103 -> 145 | ... AF86: =AF66-AF103 -> 56 | AG86: =sum(B86:AF86) -> 1904
A87: SUM (Add-ons) | B87: =SUM(B79:B86) -> 378 | C87: =SUM(C79:C86) -> 489 | D87: =SUM(D79:D86) -> 617 | E87: =SUM(E79:E86) -> 558 | F87: =SUM(F79:F86) -> 536 | G87: =SUM(G79:G86) -> 623 | H87: =SUM(H79:H86) -> 776 | I87: =SUM(I79:I86) -> 914 | ... AF87: =SUM(AF79:AF86) -> 253 | AG87: =sum(B87:AF87) -> 15116
A89: Returning Customers
A90: SKU 1 - Blue | B90: 8 | C90: 4 | D90: 9 | E90: 7 | F90: 6 | G90: 5 | H90: 7 | I90: 12 | J90: 8 | K90: 13 | L90: 5 | M90: 0 | N90: 0 | O90: 0 | P90: 0 | Q90: 0 | R90: 0 | S90: 0 | T90: 0 | U90: 0 | V90: 0 | W90: 0 | X90: 0 | Y90: 0 | Z90: 0 | AA90: 0 | AB90: 0 | AC90: 0 | AD90: 0 | AE90: 0 | AF90: 0 | AG90: =sum(B90:AF90) -> 84
A91: SKU 2 - Yellow | B91: 4 | C91: 0 | D91: 3 | E91: 0 | F91: 5 | G91: 8 | H91: 8 | I91: 8 | J91: 7 | K91: 8 | L91: 12 | M91: 14 | N91: 16 | O91: 2 | P91: 9 | Q91: 9 | R91: 11 | S91: 4 | T91: 9 | U91: 1 | V91: 1 | W91: 3 | X91: 2 | Y91: 0 | Z91: 4 | AA91: 4 | AB91: 0 | AC91: 2 | AD91: 1 | AE91: 0 | AF91: 1 | AG91: =sum(B91:AF91) -> 156
A92: SKU 3 - Blue w/ Solar | B92: 11 | C92: 14 | D92: 17 | E92: 13 | F92: 10 | G92: 11 | H92: 4 | I92: 0 | J92: 0 | K92: 0 | L92: 2 | M92: 2 | N92: 3 | O92: 0 | P92: 0 | Q92: 0 | R92: 0 | S92: 0 | T92: 0 | U92: 0 | V92: 0 | W92: 0 | X92: 0 | Y92: 0 | Z92: 0 | AA92: 0 | AB92: 0 | AC92: 0 | AD92: 0 | AE92: 0 | AF92: 0 | AG92: =sum(B92:AF92) -> 87
A93: SKU 4 - Yellow w/ Solar | B93: 2 | C93: 2 | D93: 4 | E93: 4 | F93: 6 | G93: 10 | H93: 16 | I93: 14 | J93: 11 | K93: 19 | L93: 32 | M93: 30 | N93: 16 | O93: 13 | P93: 17 | Q93: 19 | R93: 4 | S93: 20 | T93: 8 | U93: 5 | V93: 5 | W93: 1 | X93: 3 | Y93: 2 | Z93: 3 | AA93: 4 | AB93: 3 | AC93: 5 | AD93: 5 | AE93: 8 | AF93: 4 | AG93: =sum(B93:AF93) -> 295
A94: SUM (SKU 1 - SKU 4) | B94: =SUM(B90:B93) -> 25 | C94: =SUM(C90:C93) -> 20 | D94: =SUM(D90:D93) -> 33 | E94: =SUM(E90:E93) -> 24 | F94: =SUM(F90:F93) -> 27 | G94: =SUM(G90:G93) -> 34 | H94: =SUM(H90:H93) -> 35 | I94: =SUM(I90:I93) -> 34 | ... AF94: =SUM(AF90:AF93) -> 5 | AG94: =sum(B94:AF94) -> 622
A96: Wall Mount | B96: 2 | C96: 8 | D96: 14 | E96: 9 | F96: 4 | G96: 9 | H96: 11 | I96: 11 | J96: 5 | K96: 21 | L96: 13 | M96: 9 | N96: 9 | O96: 9 | P96: 9 | Q96: 9 | R96: 4 | S96: 8 | T96: 5 | U96: 4 | V96: 4 | W96: 1 | X96: 2 | Y96: 3 | Z96: 13 | AA96: 11 | AB96: 11 | AC96: 8 | AD96: 12 | AE96: 9 | AF96: 9 | AG96: =sum(B96:AF96) -> 256
A97: Suet Ball Holder | B97: 0 | C97: 0 | D97: 0 | E97: 0 | F97: 0 | G97: 0 | H97: 0 | I97: 0 | J97: 0 | K97: 0 | L97: 0 | M97: 0 | N97: 0 | O97: 0 | P97: 0 | Q97: 0 | R97: 0 | S97: 0 | T97: 0 | U97: 0 | V97: 9 | W97: 3 | X97: 4 | Y97: 3 | Z97: 7 | AA97: 12 | AB97: 11 | AC97: 9 | AD97: 12 | AE97: 10 | AF97: 12 | AG97: =sum(B97:AF97) -> 92
A98: 3-in-1 Nutrition Set - Blue | B98: 3 | C98: 6 | D98: 6 | E98: 11 | F98: 2 | G98: 9 | H98: 2 | I98: 11 | J98: 3 | K98: 8 | L98: 6 | M98: 3 | N98: 7 | O98: 2 | P98: 1 | Q98: 4 | R98: 1 | S98: 2 | T98: 0 | U98: 1 | V98: 0 | W98: 0 | X98: 0 | Y98: 0 | Z98: 3 | AA98: 2 | AB98: 0 | AC98: 1 | AD98: 0 | AE98: 1 | AF98: 3 | AG98: =sum(B98:AF98) -> 98
A99: 3-in-1 Nutrition Set - Yellow | B99: 0 | C99: 2 | D99: 0 | E99: 1 | F99: 2 | G99: 3 | H99: 4 | I99: 6 | J99: 3 | K99: 5 | L99: 5 | M99: 4 | N99: 5 | O99: 7 | P99: 4 | Q99: 9 | R99: 4 | S99: 9 | T99: 4 | U99: 2 | V99: 5 | W99: 0 | X99: 0 | Y99: 1 | Z99: 0 | AA99: 4 | AB99: 1 | AC99: 4 | AD99: 4 | AE99: 3 | AF99: 6 | AG99: =sum(B99:AF99) -> 107
A100: Solar Roof Single - Blue | B100: 2 | C100: 2 | D100: 4 | E100: 2 | F100: 1 | G100: 2 | H100: 8 | I100: 13 | J100: 9 | K100: 13 | L100: 11 | M100: 9 | N100: 2 | O100: 4 | P100: 1 | Q100: 4 | R100: 2 | S100: 0 | T100: 1 | U100: 0 | V100: 0 | W100: 0 | X100: 3 | Y100: 2 | Z100: 5 | AA100: 4 | AB100: 7 | AC100: 2 | AD100: 6 | AE100: 3 | AF100: 1 | AG100: =sum(B100:AF100) -> 123
A101: Solar Roof Single - Yellow | B101: 1 | C101: 0 | D101: 0 | E101: 0 | F101: 1 | G101: 1 | H101: 1 | I101: 2 | J101: 2 | K101: 0 | L101: 0 | M101: 1 | N101: 4 | O101: 1 | P101: 4 | Q101: 2 | R101: 1 | S101: 2 | T101: 3 | U101: 3 | V101: 1 | W101: 1 | X101: 1 | Y101: 1 | Z101: 6 | AA101: 2 | AB101: 0 | AC101: 1 | AD101: 0 | AE101: 0 | AF101: 2 | AG101: =sum(B101:AF101) -> 44
A102: Perch Extender - Blue | B102: 4 | C102: 14 | D102: 10 | E102: 14 | F102: 8 | G102: 15 | H102: 13 | I102: 14 | J102: 9 | K102: 14 | L102: 23 | M102: 9 | N102: 10 | O102: 7 | P102: 8 | Q102: 5 | R102: 7 | S102: 7 | T102: 4 | U102: 3 | V102: 3 | W102: 2 | X102: 2 | Y102: 4 | Z102: 12 | AA102: 13 | AB102: 11 | AC102: 10 | AD102: 11 | AE102: 2 | AF102: 8 | AG102: =sum(B102:AF102) -> 276
A103: Perch Extender - Yellow | B103: 4 | C103: 2 | D103: 1 | E103: 2 | F103: 4 | G103: 8 | H103: 11 | I103: 4 | J103: 5 | K103: 18 | L103: 6 | M103: 12 | N103: 5 | O103: 0 | P103: 0 | Q103: 0 | R103: 0 | S103: 0 | T103: 0 | U103: 0 | V103: 0 | W103: 0 | X103: 0 | Y103: 0 | Z103: 0 | AA103: 0 | AB103: 0 | AC103: 0 | AD103: 15 | AE103: 10 | AF103: 12 | AG103: =sum(B103:AF103) -> 119
A104: SUM (Add-ons) | B104: =SUM(B96:B103) -> 16 | C104: =SUM(C96:C103) -> 34 | D104: =SUM(D96:D103) -> 35 | E104: =SUM(E96:E103) -> 39 | F104: =SUM(F96:F103) -> 22 | G104: =SUM(G96:G103) -> 47 | H104: =SUM(H96:H103) -> 50 | I104: =SUM(I96:I103) -> 61 | ... AF104: =SUM(AF96:AF103) -> 53 | AG104: =sum(B104:AF104) -> 1115
A106: Units Sold (Net)
A107: SKU 1 - Blue | B107: =B53-(B200+B205+B246+B296+B305) -> 162 | C107: =C53-(C200+C205+C246+C296+C305) -> 217 | D107: =D53-(D200+D205+D246+D296+D305) -> 286 | E107: =E53-(E200+E205+E246+E296+E305) -> 297 | F107: =F53-(F200+F205+F246+F296+F305) -> 176 | G107: =G53-(G200+G205+G246+G296+G305) -> 122 | H107: =H53-(H200+H205+H246+H296+H305) -> 317 | I107: =I53-(I200+I205+I246+I296+I305) -> 395 | ... AF107: =AF53-(AF200+AF205+AF246+AF296+AF305) -> 0 | AG107: =sum(B107:AF107) -> 2822
A108: SKU 2 - Yellow | B108: =B54-(B201+B206+B247+B297+B306) -> 31 | C108: =C54-(C201+C206+C247+C297+C306) -> 25 | D108: =D54-(D201+D206+D247+D297+D306) -> 45 | E108: =E54-(E201+E206+E247+E297+E306) -> 36 | F108: =F54-(F201+F206+F247+F297+F306) -> 135 | G108: =G54-(G201+G206+G247+G297+G306) -> 234 | H108: =H54-(H201+H206+H247+H297+H306) -> 240 | I108: =I54-(I201+I206+I247+I297+I306) -> 266 | ... AF108: =AF54-(AF201+AF206+AF247+AF297+AF306) -> 18 | AG108: =sum(B108:AF108) -> 4627
A109: SKU 3 - Blue w/ Solar | B109: =B55-(B202+B207+B248+B298+B307) -> 357 | C109: =C55-(C202+C207+C248+C298+C307) -> 533 | D109: =D55-(D202+D207+D248+D298+D307) -> 707 | E109: =E55-(E202+E207+E248+E298+E307) -> 681 | F109: =F55-(F202+F207+F248+F298+F307) -> 450 | G109: =G55-(G202+G207+G248+G298+G307) -> 325 | H109: =H55-(H202+H207+H248+H298+H307) -> 128 | I109: =I55-(I202+I207+I248+I298+I307) -> -2 | ... AF109: =AF55-(AF202+AF207+AF248+AF298+AF307) -> 0 | AG109: =sum(B109:AF109) -> 3317
A110: SKU 4 - Yellow w/ Solar | B110: =B56-(B203+B208+B249+B299+B308) -> 87 | C110: =C56-(C203+C208+C249+C299+C308) -> 91 | D110: =D56-(D203+D208+D249+D299+D308) -> 94 | E110: =E56-(E203+E208+E249+E299+E308) -> 96 | F110: =F56-(F203+F208+F249+F299+F308) -> 312 | G110: =G56-(G203+G208+G249+G299+G308) -> 449 | H110: =H56-(H203+H208+H249+H299+H308) -> 499 | I110: =I56-(I203+I208+I249+I299+I308) -> 603 | ... AF110: =AF56-(AF203+AF208+AF249+AF299+AF308) -> 86 | AG110: =sum(B110:AF110) -> 9901
A111: SUM (SKU 1 - SKU 4) | B111: =SUM(B107:B110) -> 637 | C111: =SUM(C107:C110) -> 866 | D111: =SUM(D107:D110) -> 1132 | E111: =SUM(E107:E110) -> 1110 | F111: =SUM(F107:F110) -> 1073 | G111: =SUM(G107:G110) -> 1130 | H111: =SUM(H107:H110) -> 1184 | I111: =SUM(I107:I110) -> 1262 | ... AF111: =SUM(AF107:AF110) -> 104 | AG111: =sum(B111:AF111) -> 20667
A113: Wall Mount | B113: =B59-(B213+B224+B259+B317+B328) -> 135 | C113: =C59-(C213+C224+C259+C317+C328) -> 183 | D113: =D59-(D213+D224+D259+D317+D328) -> 260 | E113: =E59-(E213+E224+E259+E317+E328) -> 241 | F113: =F59-(F213+F224+F259+F317+F328) -> 203 | G113: =G59-(G213+G224+G259+G317+G328) -> 237 | H113: =H59-(H213+H224+H259+H317+H328) -> 225 | I113: =I59-(I213+I224+I259+I317+I328) -> 262 | ... AF113: =AF59-(AF213+AF224+AF259+AF317+AF328) -> 64 | AG113: =sum(B113:AF113) -> 5363
A114: Suet Ball Holder | B114: =B60-(B214+B225+B260+B318+B329) -> -5 | C114: =C60-(C214+C225+C260+C318+C329) -> -2 | D114: =D60-(D214+D225+D260+D318+D329) -> -3 | E114: =E60-(E214+E225+E260+E318+E329) -> -7 | F114: =F60-(F214+F225+F260+F318+F329) -> -1 | G114: =G60-(G214+G225+G260+G318+G329) -> -17 | H114: =H60-(H214+H225+H260+H318+H329) -> -5 | I114: =I60-(I214+I225+I260+I318+I329) -> -2 | ... AF114: =AF60-(AF214+AF225+AF260+AF318+AF329) -> 63 | AG114: =sum(B114:AF114) -> 438
A115: 3-in-1 Nutrition Set - Blue | B115: =B61-(B215+B226+B261+B319+B330) -> 61 | C115: =C61-(C215+C226+C261+C319+C330) -> 80 | D115: =D61-(D215+D226+D261+D319+D330) -> 105 | E115: =E61-(E215+E226+E261+E319+E330) -> 96 | F115: =F61-(F215+F226+F261+F319+F330) -> 59 | G115: =G61-(G215+G226+G261+G319+G330) -> 66 | H115: =H61-(H215+H226+H261+H319+H330) -> 48 | I115: =I61-(I215+I226+I261+I319+I330) -> 57 | ... AF115: =AF61-(AF215+AF226+AF261+AF319+AF330) -> 11 | AG115: =sum(B115:AF115) -> 1011
A116: 3-in-1 Nutrition Set - Yellow | B116: =B62-(B216+B227+B262+B320+B331) -> 17 | C116: =C62-(C216+C227+C262+C320+C331) -> 21 | D116: =D62-(D216+D227+D262+D320+D331) -> 9 | E116: =E62-(E216+E227+E262+E320+E331) -> 13 | F116: =F62-(F216+F227+F262+F320+F331) -> 45 | G116: =G62-(G216+G227+G262+G320+G331) -> 64 | H116: =H62-(H216+H227+H262+H320+H331) -> 61 | I116: =I62-(I216+I227+I262+I320+I331) -> 69 | ... AF116: =AF62-(AF216+AF227+AF262+AF320+AF331) -> 36 | AG116: =sum(B116:AF116) -> 2374
A117: Solar Roof Single - Blue | B117: =B63-(B217+B228+B263+B321+B332) -> 27 | C117: =C63-(C217+C228+C263+C321+C332) -> 21 | D117: =D63-(D217+D228+D263+D321+D332) -> 22 | E117: =E63-(E217+E228+E263+E321+E332) -> 14 | F117: =F63-(F217+F228+F263+F321+F332) -> 18 | G117: =G63-(G217+G228+G263+G321+G332) -> 13 | H117: =H63-(H217+H228+H263+H321+H332) -> 206 | I117: =I63-(I217+I228+I263+I321+I332) -> 302 | ... AF117: =AF63-(AF217+AF228+AF263+AF321+AF332) -> 13 | AG117: =sum(B117:AF117) -> 1668
...

Sheet AMAZON - P&L
A1: DECEMBER | B1: 45261 | C1: 45262 | D1: 45263 | E1: 45264 | F1: 45265 | G1: 45266 | H1: 45267 | I1: 45268 | J1: 45269 | K1: 45270 | L1: 45271 | M1: 45272 | N1: 45273 | O1: 45274 | P1: 45275 | Q1: 45276 | R1: 45277 | S1: 45278 | T1: 45279 | U1: 45280 | V1: 45281 | W1: 45282 | X1: 45283 | Y1: 45284 | Z1: 45285 | AA1: 45286 | AB1: 45287 | AC1: 45288 | AD1: 45289 | AE1: 45290 | AF1: 45291
A2: DAY | B2: FRI | C2: SAT | D2: SUN | E2: MON | F2: TUE | G2: WED | H2: THU | I2: FRI | J2: SAT | K2: SUN | L2: MON | M2: TUE | N2: WED | O2: THU | P2: FRI | Q2: SAT | R2: SUN | S2: MON | T2: TUE | U2: WED | V2: THU | W2: FRI | X2: SAT | Y2: SUN | Z2: MON | AA2: TUE | AB2: WED | AC2: THU | AD2: FRI | AE2: SAT | AF2: SUN
A3: COMMENT
A4: Orders
A5: Amazon (market place) | B5: =Summary!B53 -> 1 | C5: =Summary!C53 -> 0 | D5: =Summary!D53 -> 1 | E5: =Summary!E53 -> 1 | F5: =Summary!F53 -> 0 | G5: =Summary!G53 -> 0 | H5: =Summary!H53 -> 1 | I5: =Summary!I53 -> 0 | ... AF5: =Summary!AF53 -> 38
A6: All | B6: =SUM(B5) -> 1 | C6: =SUM(C5) -> 0 | D6: =SUM(D5) -> 1 | E6: =SUM(E5) -> 1 | F6: =SUM(F5) -> 0 | G6: =SUM(G5) -> 0 | H6: =SUM(H5) -> 1 | I6: =SUM(I5) -> 0 | ... AF6: =SUM(AF5) -> 38 | AG6: =SUM(B6:AF6) -> 4118
A8: Revenue
A9: Amazon (market place) | B9: =Summary!B14 -> 253.34 | C9: =Summary!C14 -> 0 | D9: =Summary!D14 -> 239 | E9: =Summary!E14 -> 316.94 | F9: =Summary!F14 -> 0 | G9: =Summary!G14 -> 0 | H9: =Summary!H14 -> 252.15 | I9: =Summary!I14 -> 0 | ... AF9: =Summary!AF14 -> 10388.6
A10: All | B10: =SUM(B9) -> 253.34 | C10: =SUM(C9) -> 0 | D10: =SUM(D9) -> 239 | E10: =SUM(E9) -> 316.94 | F10: =SUM(F9) -> 0 | G10: =SUM(G9) -> 0 | H10: =SUM(H9) -> 252.15 | I10: =SUM(I9) -> 0 | ... AF10: =SUM(AF9) -> 10388.6 | AG10: =SUM(B10:AF10) -> 1172985.1
A12: Media Cost
A13: Amazon Spend | B13: =Summary!B78 -> 0 | C13: =Summary!C78 -> 0 | D13: =Summary!D78 -> 688.15 | E13: =Summary!E78 -> 0 | F13: =Summary!F78 -> 0.41 | G13: =Summary!G78 -> 495.44 | H13: =Summary!H78 -> 0 | I13: =Summary!I78 -> 777.19 | ... AF13: =Summary!AF78 -> 2262.4 | AG13: =SUM(C13:AF13) -> 201173.89
A14: Amazon Platform Fee (15 %) | B14: =B9*'Data - P&L'!$C$48 -> 38.001 | C14: =C9*'Data - P&L'!$C$48 -> 0 | D14: =D9*'Data - P&L'!$C$48 -> 35.85 | E14: =E9*'Data - P&L'!$C$48 -> 47.541 | F14: =F9*'Data - P&L'!$C$48 -> 0 | G14: =G9*'Data - P&L'!$C$48 -> 0 | H14: =H9*'Data - P&L'!$C$48 -> 37.8225 | I14: =I9*'Data - P&L'!$C$48 -> 0 | ... AF14: =AF9*'Data - P&L'!$C$48 -> 1558.29 | AG14: =SUM(C14:AF14) -> 175909.77
A15: All | B15: =SUM(B13:B14) -> 38.001 | C15: =SUM(C13:C14) -> 0 | D15: =SUM(D13:D14) -> 724 | E15: =SUM(E13:E14) -> 47.541 | F15: =SUM(F13:F14) -> 0.41 | G15: =SUM(G13:G14) -> 495.44 | H15: =SUM(H13:H14) -> 37.8225 | I15: =SUM(I13:I14) -> 777.19 | ... AF15: =SUM(AF13:AF14) -> 3820.69 | AG15: =SUM(B15:AF15) -> 377121.66
A19: Amazon Orders
A20: Hardware | B20: =Summary!B15 -> 239 | C20: =Summary!C15 -> 0 | D20: =Summary!D15 -> 239 | E20: =Summary!E15 -> 299 | F20: =Summary!F15 -> 0 | G20: =Summary!G15 -> 0 | H20: =Summary!H15 -> 239 | I20: =Summary!I15 -> 0 | ... AF20: =Summary!AF15 -> 9586.55 | AG20: =SUM(B20:AF20) -> 1079495.1
A21: Addons | B21: =Summary!B16 -> 0 | C21: =Summary!C16 -> 0 | D21: =Summary!D16 -> 0 | E21: =Summary!E16 -> 0 | F21: =Summary!F16 -> 0 | G21: =Summary!G16 -> 0 | H21: =Summary!H16 -> 0 | I21: =Summary!I16 -> 0 | ... AF21: =Summary!AF16 -> 87 | AG21: =SUM(B21:AF21) -> 15225
A22: Tax | B22: =Summary!B17 -> 14.34 | C22: =Summary!C17 -> 0 | D22: =Summary!D17 -> 0 | E22: =Summary!E17 -> 17.94 | F22: =Summary!F17 -> 0 | G22: =Summary!G17 -> 0 | H22: =Summary!H17 -> 13.15 | I22: =Summary!I17 -> 0 | ... AF22: =Summary!AF17 -> 710.31 | AG22: =SUM(B22:AF22) -> 76329.78
A23: Shipping | B23: =Summary!B18 -> 0 | C23: =Summary!C18 -> 0 | D23: =Summary!D18 -> 0 | E23: =Summary!E18 -> 0 | F23: =Summary!F18 -> 0 | G23: =Summary!G18 -> 0 | H23: =Summary!H18 -> 0 | I23: =Summary!I18 -> 0 | ... AF23: =Summary!AF18 -> 0.08 | AG23: =SUM(B23:AF23) -> 593.63
A24: Gift Wrap Price | B24: =Summary!B19 -> 0 | C24: =Summary!C19 -> 0 | D24: =Summary!D19 -> 0 | E24: =Summary!E19 -> 0 | F24: =Summary!F19 -> 0 | G24: =Summary!G19 -> 0 | H24: =Summary!H19 -> 0 | I24: =Summary!I19 -> 0 | ... AF24: =Summary!AF19 -> 4.66 | AG24: =SUM(B24:AF24) -> 1341.59
A25: All Amazon | B25: =SUM(B20:B24) -> 253.34 | C25: =SUM(C20:C24) -> 0 | D25: =SUM(D20:D24) -> 239 | E25: =SUM(E20:E24) -> 316.94 | F25: =SUM(F20:F24) -> 0 | G25: =SUM(G20:G24) -> 0 | H25: =SUM(H20:H24) -> 252.15 | I25: =SUM(I20:I24) -> 0 | ... AF25: =SUM(AF20:AF24) -> 10388.6 | AG25: =SUM(B25:AF25) -> 1172985.1
A27: Units Sold (Gross)
A28: SKU 1 - Blue | B28: 2 | C28: 0 | D28: 1 | E28: 0 | F28: 0 | G28: 0 | H28: 1 | I28: 0 | J28: 0 | K28: 0 | L28: 1 | M28: 2 | N28: 1 | O28: 1 | P28: 0 | Q28: 0 | R28: 0 | S28: 0 | T28: 0 | U28: 0 | V28: 0 | W28: 1 | X28: 1 | Y28: 0 | Z28: 11 | AA28: 1 | AB28: 3 | AC28: 1 | AD28: 0 | AE28: 5 | AF28: 4 | AG28: =sum(B28:AF28) -> 36
A29: SKU 2 - Yellow | B29: 1 | C29: 0 | D29: 0 | E29: 0 | F29: 0 | G29: 0 | H29: 0 | I29: 0 | J29: 0 | K29: 0 | L29: 0 | M29: 0 | N29: 0 | O29: 0 | P29: 0 | Q29: 0 | R29: 0 | S29: 0 | T29: 0 | U29: 0 | V29: 0 | W29: 0 | X29: 2 | Y29: 4 | Z29: 8 | AA29: 0 | AB29: 0 | AC29: 1 | AD29: 0 | AE29: 0 | AF29: 0 | AG29: =sum(B29:AF29) -> 16
A30: SKU 3 - Blue w/ Solar | B30: 1 | C30: 0 | D30: 0 | E30: 0 | F30: 0 | G30: 0 | H30: 0 | I30: 0 | J30: 10 | K30: 53 | L30: 4 | M30: 3 | N30: 8 | O30: 42 | P30: 96 | Q30: 265 | R30: 785 | S30: 632 | T30: 579 | U30: 245 | V30: 199 | W30: 164 | X30: 146 | Y30: 83 | Z30: 29 | AA30: 37 | AB30: 6 | AC30: 9 | AD30: 6 | AE30: 14 | AF30: 5 | AG30: =sum(B30:AF30) -> 3421
A31: SKU 4 - Yellow w/ Solar | B31: 2 | C31: 0 | D31: 0 | E31: 1 | F31: 0 | G31: 0 | H31: 0 | I31: 0 | J31: 0 | K31: 2 | L31: 0 | M31: 0 | N31: 0 | O31: 0 | P31: 0 | Q31: 0 | R31: 0 | S31: 0 | T31: 0 | U31: 0 | V31: 0 | W31: 0 | X31: 2 | Y31: 5 | Z31: 35 | AA31: 21 | AB31: 16 | AC31: 20 | AD31: 15 | AE31: 16 | AF31: 18 | AG31: =sum(B31:AF31) -> 153
A32: SUM (SKU 1 - SKU 4) | B32: =SUM(B28:B31) -> 6 | C32: =SUM(C28:C31) -> 0 | D32: =SUM(D28:D31) -> 1 | E32: =SUM(E28:E31) -> 1 | F32: =SUM(F28:F31) -> 0 | G32: =SUM(G28:G31) -> 0 | H32: =SUM(H28:H31) -> 1 | I32: =SUM(I28:I31) -> 0 | ... AF32: =SUM(AF28:AF31) -> 27 | AG32: =sum(B32:AF32) -> 3626
A34: Wall Mount | B34: 0 | C34: 0 | D34: 0 | E34: 0 | F34: 0 | G34: 0 | H34: 0 | I34: 0 | J34: 3 | K34: 1 | L34: 0 | M34: 1 | N34: 0 | O34: 0 | P34: 4 | Q34: 12 | R34: 52 | S34: 43 | T34: 45 | U34: 28 | V34: 14 | W34: 18 | X34: 23 | Y34: 19 | Z34: 75 | AA34: 90 | AB34: 68 | AC34: 28 | AD34: 1 | AE34: 2 | AF34: 3 | AG34: =sum(B34:AF34) -> 530
A35: Suet Ball Holder | B35: 0 | C35: 0 | D35: 0 | E35: 0 | F35: 0 | G35: 0 | H35: 0 | I35: 0 | J35: 0 | K35: 0 | L35: 0 | M35: 0 | N35: 0 | O35: 0 | P35: 0 | Q35: 0 | R35: 0 | S35: 0 | T35: 0 | U35: 0 | V35: 0 | W35: 0 | X35: 0 | Y35: 0 | Z35: 0 | AA35: 0 | AB35: 0 | AC35: 0 | AD35: 0 | AE35: 0 | AF35: 0 | AG35: =sum(B35:AF35) -> 0
A36: 3-in-1 Nutrition Set - Blue | B36: 0 | C36: 0 | D36: 0 | E36: 0 | F36: 0 | G36: 0 | H36: 0 | I36: 0 | J36: 0 | K36: 0 | L36: 0 | M36: 0 | N36: 0 | O36: 0 | P36: 0 | Q36: 0 | R36: 0 | S36: 0 | T36: 0 | U36: 0 | V36: 0 | W36: 0 | X36: 0 | Y36: 0 | Z36: 0 | AA36: 0 | AB36: 0 | AC36: 0 | AD36: 0 | AE36: 0 | AF36: 0 | AG36: =sum(B36:AF36) -> 0
A37: 3-in-1 Nutrition Set - Yellow | B37: 0 | C37: 0 | D37: 0 | E37: 0 | F37: 0 | G37: 0 | H37: 0 | I37: 0 | J37: 0 | K37: 0 | L37: 0 | M37: 0 | N37: 0 | O37: 0 | P37: 0 | Q37: 0 | R37: 0 | S37: 0 | T37: 0 | U37: 0 | V37: 0 | W37: 0 | X37: 0 | Y37: 0 | Z37: 0 | AA37: 0 | AB37: 0 | AC37: 0 | AD37: 0 | AE37: 0 | AF37: 0 | AG37: =sum(B37:AF37) -> 0
A38: Solar Roof Single - Blue | B38: 0 | C38: 0 | D38: 0 | E38: 0 | F38: 0 | G38: 0 | H38: 0 | I38: 0 | J38: 0 | K38: 0 | L38: 0 | M38: 0 | N38: 0 | O38: 0 | P38: 0 | Q38: 0 | R38: 0 | S38: 0 | T38: 0 | U38: 0 | V38: 0 | W38: 0 | X38: 0 | Y38: 0 | Z38: 0 | AA38: 0 | AB38: 0 | AC38: 0 | AD38: 0 | AE38: 0 | AF38: 0 | AG38: =sum(B38:AF38) -> 0
A39: Solar Roof Single - Yellow | B39: 0 | C39: 0 | D39: 0 | E39: 0 | F39: 0 | G39: 0 | H39: 0 | I39: 0 | J39: 0 | K39: 0 | L39: 0 | M39: 0 | N39: 0 | O39: 0 | P39: 0 | Q39: 0 | R39: 0 | S39: 0 | T39: 0 | U39: 0 | V39: 0 | W39: 0 | X39: 0 | Y39: 0 | Z39: 0 | AA39: 0 | AB39: 0 | AC39: 0 | AD39: 0 | AE39: 0 | AF39: 0 | AG39: =sum(B39:AF39) -> 0
A40: Perch Extender - Blue | B40: 0 | C40: 0 | D40: 0 | E40: 0 | F40: 0 | G40: 0 | H40: 0 | I40: 0 | J40: 0 | K40: 0 | L40: 0 | M40: 0 | N40: 0 | O40: 0 | P40: 0 | Q40: 0 | R40: 0 | S40: 0 | T40: 0 | U40: 0 | V40: 0 | W40: 0 | X40: 0 | Y40: 0 | Z40: 0 | AA40: 0 | AB40: 0 | AC40: 0 | AD40: 0 | AE40: 0 | AF40: 0 | AG40: =sum(B40:AF40) -> 0
A41: Perch Extender - Yellow | B41: 0 | C41: 0 | D41: 0 | E41: 0 | F41: 0 | G41: 0 | H41: 0 | I41: 0 | J41: 0 | K41: 0 | L41: 0 | M41: 0 | N41: 0 | O41: 0 | P41: 0 | Q41: 0 | R41: 0 | S41: 0 | T41: 0 | U41: 0 | V41: 0 | W41: 0 | X41: 0 | Y41: 0 | Z41: 0 | AA41: 0 | AB41: 0 | AC41: 0 | AD41: 0 | AE41: 0 | AF41: 0 | AG41: =sum(B41:AF41) -> 0
A42: SUM (Add-ons) | B42: =SUM(B34:B41) -> 0 | C42: =SUM(C34:C41) -> 0 | D42: =SUM(D34:D41) -> 0 | E42: =SUM(E34:E41) -> 0 | F42: =SUM(F34:F41) -> 0 | G42: =SUM(G34:G41) -> 0 | H42: =SUM(H34:H41) -> 0 | I42: =SUM(I34:I41) -> 0 | ... AF42: =SUM(AF34:AF41) -> 3 | AG42: =sum(B42:AF42) -> 530
A45: Units Sold by country (Gross) - Only selling in US
A46: Bird Buddy - Blue - AMAZON.US | AG46: =sum(B46:AE46) -> 0
A47: Bird Buddy - Yellow - AMAZON.US
A48: Bird Buddy with Solar Roof Blue - AMAZON.US | AG48: =sum(B48:AE48) -> 0
A49: Bird Buddy with Solar Roof Yellow - AMAZON.US
A50: Bird Buddy - AMAZON.EU | AG50: =sum(B50:AE50) -> 0
A51: Bird Buddy with Solar Roof - AMAZON.EU | AG51: =sum(B51:AE51) -> 0
A52: Bird Buddy - AMAZON (OTHER1) | AG52: =sum(B52:AE52) -> 0
A53: Bird Buddy with Solar Roof - AMAZON (OTHER1) | AG53: =sum(B53:AE53) -> 0
A54: All Bird Buddy | B54: =B46+B50+B52 -> 0 | C54: =SUM(C46:C53) -> 0 | D54: =SUM(D46:D53) -> 0 | E54: =SUM(E46:E53) -> 0 | F54: =SUM(F46:F53) -> 0 | G54: =SUM(G46:G53) -> 0 | H54: =SUM(H46:H53) -> 0 | I54: =SUM(I46:I53) -> 0 | J54: =SUM(J46:J53) -> 0 | ... AF54: =SUM(AF46:AF53) -> 0 | AG54: =sum(B54:AE54) -> 0
A55: All Bird Buddy with Solar Roof | B55: =B48+B51+B53 -> 0 | C55: =C48+C51+C53 -> 0 | D55: =D48+D51+D53 -> 0 | E55: =E48+E51+E53 -> 0 | F55: =F48+F51+F53 -> 0 | G55: =G48+G51+G53 -> 0 | H55: =H48+H51+H53 -> 0 | I55: =I48+I51+I53 -> 0 | ... AF55: =AF48+AF51+AF53 -> 0 | AG55: =sum(B55:AE55) -> 0
A57: Wall Mount - AMAZON.US | AG57: =sum(B57:AE57) -> 0
A58: Fence Mount - AMAZON.US | AG58: =sum(B58:AE58) -> 0
A59: Suet Ball Holder - AMAZON.US | AG59: =sum(B59:AE59) -> 0
A60: 3-in-1 Nutrition Set - AMAZON.US | AG60: =sum(B60:AE60) -> 0
A61: Solar Roof Single - AMAZON.US | AG61: =sum(B61:AE61) -> 0
A62: All AMAZON.US | B62: =SUM(B57:B61) -> 0 | C62: =SUM(C57:C61) -> 0 | D62: =SUM(D57:D61) -> 0 | E62: =SUM(E57:E61) -> 0 | F62: =SUM(F57:F61) -> 0 | G62: =SUM(G57:G61) -> 0 | H62: =SUM(H57:H61) -> 0 | I62: =SUM(I57:I61) -> 0 | ... AF62: =SUM(AF57:AF61) -> 0 | AG62: =sum(B62:AE62) -> 0
A64: Wall Mount - AMAZON.EU | AG64: =sum(B64:AE64) -> 0
A65: Fence Mount - AMAZON.EU | AG65: =sum(B65:AE65) -> 0
A66: Suet Ball Holder - AMAZON.EU | AG66: =sum(B66:AE66) -> 0
A67: 3-in-1 Nutrition Set - AMAZON.EU | AG67: =sum(B67:AE67) -> 0
A68: Solar Roof Single - AMAZON.EU | AG68: =sum(B68:AE68) -> 0
A69: All AMAZON.EU | B69: =SUM(B64:B68) -> 0 | C69: =SUM(C64:C68) -> 0 | D69: =SUM(D64:D68) -> 0 | E69: =SUM(E64:E68) -> 0 | F69: =SUM(F64:F68) -> 0 | G69: =SUM(G64:G68) -> 0 | H69: =SUM(H64:H68) -> 0 | I69: =SUM(I64:I68) -> 0 | ... AF69: =SUM(AF64:AF68) -> 0 | AG69: =sum(B69:AE69) -> 0
A71: Wall Mount - AMAZON (OTHER1) | AG71: =sum(B71:AE71) -> 0
A72: Fence Mount - AMAZON (OTHER1) | AG72: =sum(B72:AE72) -> 0
A73: Suet Ball Holder - AMAZON (OTHER1) | AG73: =sum(B73:AE73) -> 0
A74: 3-in-1 Nutrition Set - AMAZON (OTHER1) | AG74: =sum(B74:AE74) -> 0
A75: Solar Roof Single - AMAZON (OTHER1) | AG75: =sum(B75:AE75) -> 0
A76: All AMAZON (OTHER1) | B76: =SUM(B71:B75) -> 0 | C76: =SUM(C71:C74) -> 0 | D76: =SUM(D71:D75) -> 0 | E76: =SUM(E71:E75) -> 0 | F76: =SUM(F71:F75) -> 0 | G76: =SUM(G71:G74) -> 0 | H76: =SUM(H71:H74) -> 0 | I76: =SUM(I71:I74) -> 0 | J76: =SUM(J71:J74) -> 0 | K76: =SUM(K71:K74) -> 0 | L76: =SUM(L71:L74) -> 0 | M76: =SUM(M71:M74) -> 0 | N76: =SUM(N71:N74) -> 0 | ... V76: =SUM(V71:V74) -> 0 | W76: =SUM(W71:W75) -> 0 | X76: =SUM(X71:X74) -> 0 | Y76: =SUM(Y71:Y74) -> 0 | Z76: =SUM(Z71:Z74) -> 0 | AA76: =SUM(AA71:AA74) -> 0 | AB76: =SUM(AB71:AB74) -> 0 | AC76: =SUM(AC71:AC74) -> 0 | AD76: =SUM(AD71:AD74) -> 0 | AE76: =SUM(AE71:AE74) -> 0 | AF76: =SUM(AF71:AF74) -> 0 | AG76: =sum(B76:AE76) -> 0
A78: Revenue by country (Gross) - Only selling in US
A79: Bird Buddy - AMAZON.US | AG79: =SUM(B79:AE79) -> 0
A80: Bird Buddy with Solar Roof - AMAZON.US | AG80: =SUM(B80:AE80) -> 0
A81: Bird Buddy - AMAZON.EU | AG81: =SUM(B81:AE81) -> 0
A82: Bird Buddy with Solar Roof - AMAZON.EU | AG82: =SUM(B82:AE82) -> 0
A83: Bird Buddy - AMAZON (OTHER1) | AG83: =SUM(B83:AE83) -> 0
A84: Bird Buddy with Solar Roof - AMAZON (OTHER1) | AG84: =SUM(B84:AE84) -> 0
A85: All Bird Buddy | B85: =B79+B81+B83 -> 0 | C85: =C79+C81+C83 -> 0 | D85: =D79+D81+D83 -> 0 | E85: =E79+E81+E83 -> 0 | F85: =F79+F81+F83 -> 0 | G85: =G79+G81+G83 -> 0 | H85: =H79+H81+H83 -> 0 | I85: =I79+I81+I83 -> 0 | ... AF85: =AF79+AF81+AF83 -> 0 | AG85: =SUM(B85:AE85) -> 0
A86: All Bird Buddy with Solar Roof | B86: =B80+B82+B84 -> 0 | C86: =C80+C82+C84 -> 0 | D86: =D80+D82+D84 -> 0 | E86: =E80+E82+E84 -> 0 | F86: =F80+F82+F84 -> 0 | G86: =G80+G82+G84 -> 0 | H86: =H80+H82+H84 -> 0 | I86: =I80+I82+I84 -> 0 | ... AF86: =AF80+AF82+AF84 -> 0 | AG86: =SUM(B86:AE86) -> 0
A88: Wall Mount - AMAZON.US | AG88: =SUM(B88:AE88) -> 0
A89: Fence Mount - AMAZON.US | AG89: =SUM(B89:AE89) -> 0
A90: Suet Ball Holder - AMAZON.US | AG90: =SUM(B90:AE90) -> 0
A91: 3-in-1 Nutrition Set - AMAZON.US | AG91: =SUM(B91:AE91) -> 0
A92: Solar Roof Single - AMAZON.US | AG92: =SUM(B92:AE92) -> 0
A93: All AMAZON.US | B93: =SUM(B88:B92) -> 0 | C93: =SUM(C88:C92) -> 0 | D93: =SUM(D88:D92) -> 0 | E93: =SUM(E88:E92) -> 0 | F93: =SUM(F88:F92) -> 0 | G93: =SUM(G88:G92) -> 0 | H93: =SUM(H88:H92) -> 0 | I93: =SUM(I88:I92) -> 0 | ... AF93: =SUM(AF88:AF92) -> 0 | AG93: =SUM(B93:AE93) -> 0
A95: Wall Mount - AMAZON.EU | AG95: =SUM(B95:AE95) -> 0
A96: Fence Mount - AMAZON.EU | AG96: =SUM(B96:AE96) -> 0
A97: Suet Ball Holder - AMAZON.EU | AG97: =SUM(B97:AE97) -> 0
A98: 3-in-1 Nutrition Set - AMAZON.EU | AG98: =SUM(B98:AE98) -> 0
A99: Solar Roof Single - AMAZON.EU | AG99: =SUM(B99:AE99) -> 0
A100: All AMAZON.EU | B100: =SUM(B95:B99) -> 0 | C100: =SUM(C95:C99) -> 0 | D100: =SUM(D95:D99) -> 0 | E100: =SUM(E95:E99) -> 0 | F100: =SUM(F95:F99) -> 0 | G100: =SUM(G95:G99) -> 0 | H100: =SUM(H95:H99) -> 0 | I100: =SUM(I95:I99) -> 0 | ... AF100: =SUM(AF95:AF99) -> 0 | AG100: =SUM(B100:AE100) -> 0
A102: Wall Mount - AMAZON (OTHER1) | AG102: =SUM(B102:AE102) -> 0
A103: Fence Mount - AMAZON (OTHER1) | AG103: =SUM(B103:AE103) -> 0
A104: Suet Ball Holder - AMAZON (OTHER1) | AG104: =SUM(B104:AE104) -> 0
A105: 3-in-1 Nutrition Set - AMAZON (OTHER1) | AG105: =SUM(B105:AE105) -> 0
A106: Solar Roof Single - AMAZON (OTHER1) | AG106: =SUM(B106:AE106) -> 0
A107: All AMAZON (OTHER1) | B107: =SUM(B102:B106) -> 0 | C107: =SUM(C102:C106) -> 0 | D107: =SUM(D102:D106) -> 0 | E107: =SUM(E102:E106) -> 0 | F107: =SUM(F102:F106) -> 0 | G107: =SUM(G102:G106) -> 0 | H107: =SUM(H102:H106) -> 0 | I107: =SUM(I102:I106) -> 0 | ... AF107: =SUM(AF102:AF106) -> 0 | AG107: =SUM(B107:AE107) -> 0
A110: Units Cancelled by country (Gross)
A111: SKU 1 - Blue | B111: 0 | C111: 0 | D111: 0 | E111: 0 | F111: 0 | G111: 0 | H111: 0 | I111: 0 | J111: 0 | K111: 0 | L111: 0 | M111: 1 | N111: 0 | O111: 0 | P111: 0 | Q111: 0 | R111: 0 | S111: 0 | T111: 0 | U111: 0 | V111: 0 | W111: 1 | X111: 0 | Y111: 0 | Z111: 2 | AA111: 0 | AB111: 0 | AC111: 0 | AD111: 0 | AE111: 0 | AF111: 0 | AG111: =SUM(B111:AF111) -> 4
A112: SKU 2 - Yellow | B112: 0 | C112: 0 | D112: 0 | E112: 0 | F112: 0 | G112: 0 | H112: 0 | I112: 0 | J112: 0 | K112: 0 | L112: 0 | M112: 0 | N112: 0 | O112: 0 | P112: 0 | Q112: 0 | R112: 0 | S112: 0 | T112: 0 | U112: 0 | V112: 0 | W112: 0 | X112: 0 | Y112: 0 | Z112: 0 | AA112: 0 | AB112: 0 | AC112: 0 | AD112: 0 | AE112: 0 | AF112: 0 | AG112: =SUM(B112:AF112) -> 0
A113: SKU 3 - Blue w/ Solar | B113: 0 | C113: 0 | D113: 0 | E113: 0 | F113: 0 | G113: 0 | H113: 0 | I113: 0 | J113: 0 | K113: 7 | L113: 0 | M113: 1 | N113: 1 | O113: 3 | P113: 3 | Q113: 7 | R113: 18 | S113: 26 | T113: 35 | U113: 21 | V113: 14 | W113: 8 | X113: 11 | Y113: 2 | Z113: 1 | AA113: 4 | AB113: 0 | AC113: 1 | AD113: 0 | AE113: 3 | AF113: 1 | AG113: =SUM(B113:AF113) -> 167
A114: SKU 4 - Yellow w/ Solar | B114: 0 | C114: 0 | D114: 0 | E114: 0 | F114: 0 | G114: 0 | H114: 0 | I114: 0 | J114: 0 | K114: 0 | L114: 0 | M114: 0 | N114: 0 | O114: 0 | P114: 0 | Q114: 0 | R114: 0 | S114: 0 | T114: 0 | U114: 0 | V114: 0 | W114: 0 | X114: 0 | Y114: 0 | Z114: 3 | AA114: 1 | AB114: 2 | AC114: 2 | AD114: 0 | AE114: 1 | AF114: 0 | AG114: =SUM(B114:AF114) -> 9
A115: SUM (SKU 1 + SKU 2) | B115: =B111+B112 -> 0 | C115: =C111+C112 -> 0 | D115: =D111+D112 -> 0 | E115: =E111+E112 -> 0 | F115: =F111+F112 -> 0 | G115: =G111+G112 -> 0 | H115: =H111+H112 -> 0 | I115: =I111+I112 -> 0 | ... AF115: =AF111+AF112 -> 0 | AG115: =SUM(B115:AF115) -> 4
A116: SUM (SKU 3 + SKU 4) | B116: =B113+B114 -> 0 | C116: =C113+C114 -> 0 | D116: =D113+D114 -> 0 | E116: =E113+E114 -> 0 | F116: =F113+F114 -> 0 | G116: =G113+G114 -> 0 | H116: =H113+H114 -> 0 | I116: =I113+I114 -> 0 | ... AF116: =AF113+AF114 -> 1 | AG116: =SUM(B116:AF116) -> 176
A118: Wall Mount | B118: 0 | C118: 0 | D118: 0 | E118: 0 | F118: 0 | G118: 0 | H118: 0 | I118: 0 | J118: 0 | K118: 0 | L118: 0 | M118: 0 | N118: 0 | O118: 0 | P118: 0 | Q118: 0 | R118: 2 | S118: 2 | T118: 2 | U118: 3 | V118: 1 | W118: 0 | X118: 2 | Y118: 0 | Z118: 2 | AA118: 1 | AB118: 2 | AC118: 3 | AD118: 0 | AE118: 0 | AF118: 0 | AG118: =SUM(B118:AF118) -> 20
A119: Suet Ball Holder | B119: 0 | C119: 0 | D119: 0 | E119: 0 | F119: 0 | G119: 0 | H119: 0 | I119: 0 | J119: 0 | K119: 0 | L119: 0 | M119: 0 | N119: 0 | O119: 0 | P119: 0 | Q119: 0 | R119: 0 | S119: 0 | T119: 0 | U119: 0 | V119: 0 | W119: 0 | X119: 0 | Y119: 0 | Z119: 0 | AA119: 0 | AB119: 0 | AC119: 0 | AD119: 0 | AE119: 0 | AF119: 0 | AG119: =SUM(B119:AF119) -> 0
...

Sheet APP - P&L
A1: JANUARY | B1: 45292 | C1: 45293 | D1: 45294 | E1: 45295 | F1: 45296 | G1: 45297 | H1: 45298 | I1: 45299 | J1: 45300 | K1: 45301 | L1: 45302 | M1: 45303 | N1: 45304 | O1: 45305 | P1: 45306 | Q1: 45307 | R1: 45308 | S1: 45309 | T1: 45310 | U1: 45311 | V1: 45312 | W1: 45313 | X1: 45314 | Y1: 45315 | Z1: 45316 | AA1: 45317 | AB1: 45318 | AC1: 45319 | AD1: 45320 | AE1: 45321 | AF1: 45322
A2: DAY | B2: MON | C2: TUE | D2: WED | E2: THU | F2: FRI | G2: SAT | H2: SUN | I2: MON | J2: TUE | K2: WED | L2: THU | M2: FRI | N2: SAT | O2: SUN | P2: MON | Q2: TUE | R2: WED | S2: THU | T2: FRI | U2: SAT | V2: SUN | W2: MON | X2: TUE | Y2: WED | Z2: THU | AA2: FRI | AB2: SAT | AC2: SUN | AD2: MON | AE2: TUE | AF2: WED
A4: Gross Revenue
A5: Apple Store Sales | B5: 1720.7904 | C5: 2353.8949 | D5: 1773.2926 | E5: 1307.9704 | F5: 1056.7641 | G5: 1277.0296 | H5: 1259.3559 | I5: 1574.9166 | J5: 1734.4595 | K5: 2173.4351 | L5: 1176.7082 | M5: 1091.9338 | N5: 727.3789 | O5: 811.4365 | P5: 1130.3281 | Q5: 1919.8968 | R5: 2114.2114 | S5: 988.26562 | T5: 1360.8294 | U5: 1019.9931 | V5: 1925.9781 | W5: 2626.1175 | X5: 4620.4567 | Y5: 6211.0456 | Z5: 28980.079 | AA5: 27313.591 | AB5: 16002.782 | AC5: 11862.606 | AD5: 9379.4322 | AE5: 12039.757 | AF5: 10508.22 | AG5: =sum(B5:AF5) -> 160042.96
A6: - Yearly Subscription | B6: 1663.2904 | C6: 2282.8949 | D6: 1673.6926 | E6: 1251.9704 | F6: 973.56415 | G6: 1213.1296 | H6: 1192.7559 | I6: 1481.4166 | J6: 1645.9595 | K6: 2100.8551 | L6: 1134.5082 | M6: 1037.5338 | N6: 681.7789 | O6: 743.2365 | P6: 1075.9281 | Q6: 1829.1968 | R6: 2056.0114 | S6: 919.96562 | T6: 1311.9294 | U6: 971.69311 | V6: 1873.6781 | W6: 2500.6107 | X6: 4521.6667 | Y6: 6051.0375 | Z6: 28390.318 | AA6: 26794.486 | AB6: 15707.053 | AC6: 11443.908 | AD6: 9051.8635 | AE6: 11647.461 | AF6: 10241.118 | AG6: =sum(B6:AF6) -> 155464.51
A7: - Monthly Subscription | B7: 57.5 | C7: 71 | D7: 99.6 | E7: 56 | F7: 83.2 | G7: 63.9 | H7: 66.6 | I7: 93.5 | J7: 88.5 | K7: 72.58 | L7: 42.2 | M7: 54.4 | N7: 45.6 | O7: 68.2 | P7: 54.4 | Q7: 90.7 | R7: 58.2 | S7: 68.3 | T7: 48.9 | U7: 48.3 | V7: 52.3 | W7: 125.50679 | X7: 98.79 | Y7: 160.00807 | Z7: 589.76137 | AA7: 519.10445 | AB7: 295.72895 | AC7: 418.69729 | AD7: 327.56865 | AE7: 392.2967 | AF7: 267.1023 | AG7: =sum(B7:AF7) -> 4578.4446
A8: Google Store Sales | B8: 226.46 | C8: 302.25 | D8: 344.36 | E8: 84.95 | F8: 214.95 | G8: 239 | H8: 301.87 | I8: 400.4 | J8: 482.7 | K8: 611.61 | L8: 198.6 | M8: 215.75 | N8: 206.18 | O8: 195.25 | P8: 286.06 | Q8: 490.95 | R8: 462.87 | S8: 213.81 | T8: 124.15 | U8: 126.07 | V8: 446.93 | W8: 592.91 | X8: 1256.13 | Y8: 1838.25 | Z8: 6047.3 | AA8: 5987.74 | AB8: 3149.93 | AC8: 1656.09 | AD8: 1829.01 | AE8: 2162.23 | AF8: 2010.4 | AG8: =sum(B8:AF8) -> 32705.16
A9: - Yearly Subscription | B9: 223.25 | C9: 286.02 | D9: 321.98 | E9: 61.63 | F9: 202.04 | G9: 219.93 | H9: 286.02 | I9: 380.36 | J9: 460.36 | K9: 596.03 | L9: 195.43 | M9: 202.72 | N9: 193.25 | O9: 185.85 | P9: 259.61 | Q9: 477.26 | R9: 453.43 | S9: 191.31 | T9: 95.83 | U9: 100.45 | V9: 414.42 | W9: 571.04 | X9: 1240.06 | Y9: 1809.59 | Z9: 5950.84 | AA9: 5937.4 | AB9: 3076.93 | AC9: 1574.65 | AD9: 1755.72 | AE9: 2089.9 | AF9: 1979.17 | AG9: =sum(B9:AF9) -> 31792.48
A10: - Monthly Subscription | B10: 3.21 | C10: 16.23 | D10: 22.38 | E10: 23.32 | F10: 12.91 | G10: 19.07 | H10: 15.85 | I10: 20.04 | J10: 22.34 | K10: 15.58 | L10: 3.17 | M10: 13.03 | N10: 12.93 | O10: 9.4 | P10: 26.45 | Q10: 13.69 | R10: 9.44 | S10: 22.5 | T10: 28.32 | U10: 25.62 | V10: 32.51 | W10: 21.87 | X10: 16.07 | Y10: 28.66 | Z10: 96.46 | AA10: 50.34 | AB10: 73 | AC10: 81.44 | AD10: 73.29 | AE10: 72.33 | AF10: 31.23 | AG10: =sum(B10:AF10) -> 912.68
A11: SUM | B11: =sum(B5+B8) -> 1947.2504 | C11: =sum(C5+C8) -> 2656.1449 | D11: =sum(D5+D8) -> 2117.6526 | E11: =sum(E5+E8) -> 1392.9204 | F11: =sum(F5+F8) -> 1271.7141 | G11: =sum(G5+G8) -> 1516.0296 | H11: =sum(H5+H8) -> 1561.2259 | I11: =sum(I5+I8) -> 1975.3166 | ... AF11: =sum(AF5+AF8) -> 12518.62 | AG11: =sum(B11:AF11) -> 192748.12
A13: Gross Orders
A14: Apple Store Orders | B14: =sum(B15:B16) -> 75 | C14: =sum(C15:C16) -> 99 | D14: =sum(D15:D16) -> 87 | E14: =sum(E15:E16) -> 59 | F14: =sum(F15:F16) -> 60 | G14: =sum(G15:G16) -> 61 | H14: =sum(H15:H16) -> 62 | I14: =sum(I15:I16) -> 78 | ... AF14: =sum(AF15:AF16) -> 360 | AG14: =sum(B14:AF14) -> 6161
A15: - Yearly Subscription | B15: 56 | C15: 76 | D15: 55 | E15: 41 | F15: 33 | G15: 40 | H15: 40 | I15: 48 | J15: 56 | K15: 69 | L15: 37 | M15: 34 | N15: 22 | O15: 24 | P15: 35 | Q15: 61 | R15: 68 | S15: 30 | T15: 43 | U15: 32 | V15: 62 | W15: 84 | X15: 150 | Y15: 200 | Z15: 941 | AA15: 891 | AB15: 522 | AC15: 381 | AD15: 289 | AE15: 365 | AF15: 313 | AG15: =sum(B15:AF15) -> 5098
A16: - Monthly Subscription | B16: 19 | C16: 23 | D16: 32 | E16: 18 | F16: 27 | G16: 21 | H16: 22 | I16: 30 | J16: 28 | K16: 24 | L16: 14 | M16: 18 | N16: 15 | O16: 22 | P16: 18 | Q16: 29 | R16: 19 | S16: 22 | T16: 16 | U16: 16 | V16: 17 | W16: 27 | X16: 21 | Y16: 35 | Z16: 110 | AA16: 101 | AB16: 57 | AC16: 79 | AD16: 62 | AE16: 74 | AF16: 47 | AG16: =sum(B16:AF16) -> 1063
A17: Google Store Orders | B17: =sum(B18:B19) -> 8 | C17: =sum(C18:C19) -> 14 | D17: =sum(D18:D19) -> 17 | E17: =sum(E18:E19) -> 9 | F17: =sum(F18:F19) -> 10 | G17: =sum(G18:G19) -> 13 | H17: =sum(H18:H19) -> 14 | I17: =sum(I18:I19) -> 18 | ... AF17: =sum(AF18:AF19) -> 63 | AG17: =sum(B17:AF17) -> 1200
A18: - Yearly Subscription | B18: 7 | C18: 9 | D18: 10 | E18: 2 | F18: 6 | G18: 7 | H18: 9 | I18: 12 | J18: 14 | K18: 19 | L18: 6 | M18: 6 | N18: 6 | O18: 6 | P18: 8 | Q18: 15 | R18: 14 | S18: 6 | T18: 3 | U18: 3 | V18: 13 | W18: 18 | X18: 38 | Y18: 55 | Z18: 187 | AA18: 187 | AB18: 97 | AC18: 49 | AD18: 52 | AE18: 62 | AF18: 58 | AG18: =sum(B18:AF18) -> 984
A19: - Monthly Subscription | B19: 1 | C19: 5 | D19: 7 | E19: 7 | F19: 4 | G19: 6 | H19: 5 | I19: 6 | J19: 7 | K19: 5 | L19: 1 | M19: 4 | N19: 4 | O19: 3 | P19: 8 | Q19: 4 | R19: 3 | S19: 7 | T19: 9 | U19: 8 | V19: 8 | W19: 5 | X19: 4 | Y19: 6 | Z19: 17 | AA19: 10 | AB19: 13 | AC19: 16 | AD19: 15 | AE19: 13 | AF19: 5 | AG19: =sum(B19:AF19) -> 216
A20: SUM | B20: =sum(B14+B17) -> 83 | C20: =sum(C14+C17) -> 113 | D20: =sum(D14+D17) -> 104 | E20: =sum(E14+E17) -> 68 | F20: =sum(F14+F17) -> 70 | G20: =sum(G14+G17) -> 74 | H20: =sum(H14+H17) -> 76 | I20: =sum(I14+I17) -> 96 | ... AF20: =sum(AF14+AF17) -> 423 | AG20: =sum(B20:AF20) -> 7361
A21: - Yearly Subscription | B21: =B15+B18 -> 63 | C21: =C15+C18 -> 85 | D21: =D15+D18 -> 65 | E21: =E15+E18 -> 43 | F21: =F15+F18 -> 39 | G21: =G15+G18 -> 47 | H21: =H15+H18 -> 49 | I21: =I15+I18 -> 60 | ... AF21: =AF15+AF18 -> 371 | AG21: =sum(B21:AF21) -> 6082
A22: - Monthly Subscription | B22: =B16+B19 -> 20 | C22: =C16+C19 -> 28 | D22: =D16+D19 -> 39 | E22: =E16+E19 -> 25 | F22: =F16+F19 -> 31 | G22: =G16+G19 -> 27 | H22: =H16+H19 -> 27 | I22: =I16+I19 -> 36 | ... AF22: =AF16+AF19 -> 52 | AG22: =sum(B22:AF22) -> 1279
A24: Refunded Revenue
A25: Apple Store Sales | B25: =sum(B26:B27) -> 29.99 | C25: =sum(C26:C27) -> 29.99 | D25: =sum(D26:D27) -> 0 | E25: =sum(E26:E27) -> 0 | F25: =sum(F26:F27) -> 29.99 | G25: =sum(G26:G27) -> 0 | H25: =sum(H26:H27) -> 29.99 | I25: =sum(I26:I27) -> 0 | ... AF25: =sum(AF26:AF27) -> 29.99 | AG25: =sum(B25:AF25) -> 431.93
A26: - Yearly Subscription | B26: 29.99 | C26: 29.99 | D26: 0 | E26: 0 | F26: 29.99 | G26: 0 | H26: 29.99 | I26: 0 | J26: 59.98 | K26: 0 | L26: 0 | M26: 0 | N26: 0 | O26: 0 | P26: 0 | Q26: 36.16 | R26: 0 | S26: 0 | T26: 0 | U26: 0 | V26: 0 | W26: 29.99 | X26: 0 | Y26: 0 | Z26: 0 | AA26: 29.99 | AB26: 59.9 | AC26: 29.99 | AD26: 29.99 | AE26: 0 | AF26: 29.99 | AG26: =sum(B26:AF26) -> 425.95
A27: - Monthly Subscription | B27: 0 | C27: 0 | D27: 0 | E27: 0 | F27: 0 | G27: 0 | H27: 0 | I27: 0 | J27: 0 | K27: 5.98 | L27: 0 | M27: 0 | N27: 0 | O27: 0 | P27: 0 | Q27: 0 | R27: 0 | S27: 0 | T27: 0 | U27: 0 | V27: 0 | W27: 0 | X27: 0 | Y27: 0 | Z27: 0 | AA27: 0 | AB27: 0 | AC27: 0 | AD27: 0 | AE27: 0 | AF27: 0 | AG27: =sum(B27:AF27) -> 5.98
A28: Google Store Sales | B28: =sum(B29:B30) -> 0 | C28: =sum(C29:C30) -> 0 | D28: =sum(D29:D30) -> 0 | E28: =sum(E29:E30) -> 0 | F28: =sum(F29:F30) -> 0 | G28: =sum(G29:G30) -> 0 | H28: =sum(H29:H30) -> 0 | I28: =sum(I29:I30) -> 0 | ... AF28: =sum(AF29:AF30) -> 0 | AG28: =sum(B28:AF28) -> 0
A29: - Yearly Subscription | B29: 0 | C29: 0 | D29: 0 | E29: 0 | F29: 0 | G29: 0 | H29: 0 | I29: 0 | J29: 0 | K29: 0 | L29: 0 | M29: 0 | N29: 0 | O29: 0 | P29: 0 | Q29: 0 | R29: 0 | S29: 0 | T29: 0 | U29: 0 | V29: 0 | W29: 0 | X29: 0 | Y29: 0 | Z29: 0 | AA29: 0 | AB29: 0 | AC29: 0 | AD29: 0 | AE29: 0 | AF29: 0 | AG29: =sum(B29:AF29) -> 0
A30: - Monthly Subscription | B30: 0 | C30: 0 | D30: 0 | E30: 0 | F30: 0 | G30: 0 | H30: 0 | I30: 0 | J30: 0 | K30: 0 | L30: 0 | M30: 0 | N30: 0 | O30: 0 | P30: 0 | Q30: 0 | R30: 0 | S30: 0 | T30: 0 | U30: 0 | V30: 0 | W30: 0 | X30: 0 | Y30: 0 | Z30: 0 | AA30: 0 | AB30: 0 | AC30: 0 | AD30: 0 | AE30: 0 | AF30: 0 | AG30: =sum(B30:AF30) -> 0
A31: SUM | B31: =B25+B28 -> 29.99 | C31: =C25+C28 -> 29.99 | D31: =D25+D28 -> 0 | E31: =E25+E28 -> 0 | F31: =F25+F28 -> 29.99 | G31: =G25+G28 -> 0 | H31: =H25+H28 -> 29.99 | I31: =I25+I28 -> 0 | ... AF31: =AF25+AF28 -> 29.99 | AG31: =sum(B31:AF31) -> 431.93
A33: Refunded Orders
A34: Apple Store orders | B34: =sum(B35:B36) -> 1 | C34: =sum(C35:C36) -> 1 | D34: =sum(D35:D36) -> 0 | E34: =sum(E35:E36) -> 0 | F34: =sum(F35:F36) -> 1 | G34: =sum(G35:G36) -> 0 | H34: =sum(H35:H36) -> 1 | I34: =sum(I35:I36) -> 0 | ... AF34: =sum(AF35:AF36) -> 1 | AG34: =sum(B34:AF34) -> 17
A35: - Yearly Subscription | B35: 1 | C35: 1 | D35: 0 | E35: 0 | F35: 1 | G35: 0 | H35: 1 | I35: 0 | J35: 2 | K35: 0 | L35: 0 | M35: 0 | N35: 0 | O35: 0 | P35: 0 | Q35: 2 | R35: 0 | S35: 0 | T35: 0 | U35: 0 | V35: 0 | W35: 1 | X35: 0 | Y35: 0 | Z35: 0 | AA35: 1 | AB35: 2 | AC35: 1 | AD35: 1 | AE35: 0 | AF35: 1
A36: - Monthly Subscription | B36: 0 | C36: 0 | D36: 0 | E36: 0 | F36: 0 | G36: 0 | H36: 0 | I36: 0 | J36: 0 | K36: 2 | L36: 0 | M36: 0 | N36: 0 | O36: 0 | P36: 0 | Q36: 0 | R36: 0 | S36: 0 | T36: 0 | U36: 0 | V36: 0 | W36: 0 | X36: 0 | Y36: 0 | Z36: 0 | AA36: 0 | AB36: 0 | AC36: 0 | AD36: 0 | AE36: 0 | AF36: 0
A37: Google Store orders | B37: =sum(B38:B39) -> 0 | C37: =sum(C38:C39) -> 0 | D37: =sum(D38:D39) -> 0 | E37: =sum(E38:E39) -> 0 | F37: =sum(F38:F39) -> 0 | G37: =sum(G38:G39) -> 0 | H37: =sum(H38:H39) -> 0 | I37: =sum(I38:I39) -> 0 | ... AF37: =sum(AF38:AF39) -> 0 | AG37: =sum(B37:AF37) -> 0
A38: - Yearly Subscription | B38: 0 | C38: 0 | D38: 0 | E38: 0 | F38: 0 | G38: 0 | H38: 0 | I38: 0 | J38: 0 | K38: 0 | L38: 0 | M38: 0 | N38: 0 | O38: 0 | P38: 0 | Q38: 0 | R38: 0 | S38: 0 | T38: 0 | U38: 0 | V38: 0 | W38: 0 | X38: 0 | Y38: 0 | Z38: 0 | AA38: 0 | AB38: 0 | AC38: 0 | AD38: 0 | AE38: 0 | AF38: 0
A39: - Monthly Subscription | B39: 0 | C39: 0 | D39: 0 | E39: 0 | F39: 0 | G39: 0 | H39: 0 | I39: 0 | J39: 0 | K39: 0 | L39: 0 | M39: 0 | N39: 0 | O39: 0 | P39: 0 | Q39: 0 | R39: 0 | S39: 0 | T39: 0 | U39: 0 | V39: 0 | W39: 0 | X39: 0 | Y39: 0 | Z39: 0 | AA39: 0 | AB39: 0 | AC39: 0 | AD39: 0 | AE39: 0 | AF39: 0
A40: SUM | B40: =B34+B37 -> 1 | C40: =C34+C37 -> 1 | D40: =D34+D37 -> 0 | E40: =E34+E37 -> 0 | F40: =F34+F37 -> 1 | G40: =G34+G37 -> 0 | H40: =H34+H37 -> 1 | I40: =I34+I37 -> 0 | ... AF40: =AF34+AF37 -> 1 | AG40: =sum(B40:AF40) -> 17
A42: Net Revenue
A43: Apple Store | B43: =B5-B25 -> 1690.8004 | C43: =C5-C25 -> 2323.9049 | D43: =D5-D25 -> 1773.2926 | E43: =E5-E25 -> 1307.9704 | F43: =F5-F25 -> 1026.7741 | G43: =G5-G25 -> 1277.0296 | H43: =H5-H25 -> 1229.3659 | I43: =I5-I25 -> 1574.9166 | ... AF43: =AF5-AF25 -> 10478.23 | AG43: =sum(B43:AF43) -> 159611.03
A44: - Yearly Subscription | B44: =B6-B26 -> 1633.3004 | C44: =C6-C26 -> 2252.9049 | D44: =D6-D26 -> 1673.6926 | E44: =E6-E26 -> 1251.9704 | F44: =F6-F26 -> 943.57415 | G44: =G6-G26 -> 1213.1296 | H44: =H6-H26 -> 1162.7659 | I44: =I6-I26 -> 1481.4166 | ... AF44: =AF6-AF26 -> 10211.128 | AG44: =sum(B44:AF44) -> 155038.56
A45: - Monthly Subscription | B45: =B7-B27 -> 57.5 | C45: =C7-C27 -> 71 | D45: =D7-D27 -> 99.6 | E45: =E7-E27 -> 56 | F45: =F7-F27 -> 83.2 | G45: =G7-G27 -> 63.9 | H45: =H7-H27 -> 66.6 | I45: =I7-I27 -> 93.5 | ... AF45: =AF7-AF27 -> 267.1023 | AG45: =sum(B45:AF45) -> 4572.4646
A46: Google Store | B46: =B8-B28 -> 226.46 | C46: =C8-C28 -> 302.25 | D46: =D8-D28 -> 344.36 | E46: =E8-E28 -> 84.95 | F46: =F8-F28 -> 214.95 | G46: =G8-G28 -> 239 | H46: =H8-H28 -> 301.87 | I46: =I8-I28 -> 400.4 | ... AF46: =AF8-AF28 -> 2010.4 | AG46: =sum(B46:AF46) -> 32705.16
A47: - Yearly Subscription | B47: =B9-B29 -> 223.25 | C47: =C9-C29 -> 286.02 | D47: =D9-D29 -> 321.98 | E47: =E9-E29 -> 61.63 | F47: =F9-F29 -> 202.04 | G47: =G9-G29 -> 219.93 | H47: =H9-H29 -> 286.02 | I47: =I9-I29 -> 380.36 | ... AF47: =AF9-AF29 -> 1979.17 | AG47: =sum(B47:AF47) -> 31792.48
A48: - Monthly Subscription | B48: =B10-B30 -> 3.21 | C48: =C10-C30 -> 16.23 | D48: =D10-D30 -> 22.38 | E48: =E10-E30 -> 23.32 | F48: =F10-F30 -> 12.91 | G48: =G10-G30 -> 19.07 | H48: =H10-H30 -> 15.85 | I48: =I10-I30 -> 20.04 | ... AF48: =AF10-AF30 -> 31.23 | AG48: =sum(B48:AF48) -> 912.68
A49: SUM | B49: =B43+B46 -> 1917.2604 | C49: =C43+C46 -> 2626.1549 | D49: =D43+D46 -> 2117.6526 | E49: =E43+E46 -> 1392.9204 | F49: =F43+F46 -> 1241.7241 | G49: =G43+G46 -> 1516.0296 | H49: =H43+H46 -> 1531.2359 | I49: =I43+I46 -> 1975.3166 | ... AF49: =AF43+AF46 -> 12488.63 | AG49: =sum(B49:AF49) -> 192316.19
A51: Net Orders
A52: Apple Store | B52: =B14-B34 -> 74 | C52: =C14-C34 -> 98 | D52: =D14-D34 -> 87 | E52: =E14-E34 -> 59 | F52: =F14-F34 -> 59 | G52: =G14-G34 -> 61 | H52: =H14-H34 -> 61 | I52: =I14-I34 -> 78 | ... AF52: =AF14-AF34 -> 359 | AG52: =sum(B52:AF52) -> 6144
A53: - Yearly Subscription | B53: =B15-B35 -> 55 | C53: =C15-C35 -> 75 | D53: =D15-D35 -> 55 | E53: =E15-E35 -> 41 | F53: =F15-F35 -> 32 | G53: =G15-G35 -> 40 | H53: =H15-H35 -> 39 | I53: =I15-I35 -> 48 | ... AF53: =AF15-AF35 -> 312 | AG53: =sum(B53:AF53) -> 5083
A54: - Monthly Subscription | B54: =B16-B36 -> 19 | C54: =C16-C36 -> 23 | D54: =D16-D36 -> 32 | E54: =E16-E36 -> 18 | F54: =F16-F36 -> 27 | G54: =G16-G36 -> 21 | H54: =H16-H36 -> 22 | I54: =I16-I36 -> 30 | ... AF54: =AF16-AF36 -> 47 | AG54: =sum(B54:AF54) -> 1061
A55: Google Store | B55: =B17-B37 -> 8 | C55: =C17-C37 -> 14 | D55: =D17-D37 -> 17 | E55: =E17-E37 -> 9 | F55: =F17-F37 -> 10 | G55: =G17-G37 -> 13 | H55: =H17-H37 -> 14 | I55: =I17-I37 -> 18 | ... AF55: =AF17-AF37 -> 63 | AG55: =sum(B55:AF55) -> 1200
A56: - Yearly Subscription | B56: =B18-B38 -> 7 | C56: =C18-C38 -> 9 | D56: =D18-D38 -> 10 | E56: =E18-E38 -> 2 | F56: =F18-F38 -> 6 | G56: =G18-G38 -> 7 | H56: =H18-H38 -> 9 | I56: =I18-I38 -> 12 | ... AF56: =AF18-AF38 -> 58 | AG56: =sum(B56:AF56) -> 984
A57: - Monthly Subscription | B57: =B19-B39 -> 1 | C57: =C19-C39 -> 5 | D57: =D19-D39 -> 7 | E57: =E19-E39 -> 7 | F57: =F19-F39 -> 4 | G57: =G19-G39 -> 6 | H57: =H19-H39 -> 5 | I57: =I19-I39 -> 6 | ... AF57: =AF19-AF39 -> 5 | AG57: =sum(B57:AF57) -> 216
A58: SUM | B58: =B52+B55 -> 82 | C58: =C52+C55 -> 112 | D58: =D52+D55 -> 104 | E58: =E52+E55 -> 68 | F58: =F52+F55 -> 69 | G58: =G52+G55 -> 74 | H58: =H52+H55 -> 75 | I58: =I52+I55 -> 96 | ... AF58: =AF52+AF55 -> 422 | AG58: =sum(B58:AF58) -> 7344
A62: Commision Fees & Taxes
A63: Estimated Apple Store Commision Fee (30%) --> check again after 1. mil. | B63: =B5*0.3 -> 516.23712 | C63: =C5*0.3 -> 706.16846 | D63: =D5*0.3 -> 531.98779 | E63: =E5*0.3 -> 392.39111 | F63: =F5*0.3 -> 317.02924 | G63: =G5*0.3 -> 383.10888 | H63: =H5*0.3 -> 377.80677 | I63: =I5*0.3 -> 472.47499 | ... AF63: =AF5*0.3 -> 3152.466 | AG63: =SUM(B63:AF63) -> 48012.887
A64: Estimated Apple Store Taxes | B64: 19.07 | C64: 50.23 | D64: 24.57 | E64: 21.43 | F64: 18.35 | G64: 18.1 | H64: 22.34 | I64: 35.71 | J64: 25.58 | K64: 45.48 | L64: 15.3 | M64: 17.08 | N64: 16.07 | O64: 17.04 | P64: 27.21 | Q64: 29.44 | R64: 14.88 | S64: 17.61 | T64: 15.46 | U64: 13.35 | V64: 20.94 | W64: 16.24 | X64: 23.31 | Y64: 49.64 | Z64: 121.3 | AA64: 71.62 | AB64: 73.95 | AC64: 44.19 | AD64: 54.93 | AE64: 50.51 | AF64: 25.01 | AG64: =SUM(B64:AF64) -> 1015.94
A65: Estimated Google Store Commision Fee (15%) --> check again after 1. mil. | B65: =B8*0.15 -> 33.969 | C65: =C8*0.15 -> 45.3375 | D65: =D8*0.15 -> 51.654 | E65: =E8*0.15 -> 12.7425 | F65: =F8*0.15 -> 32.2425 | G65: =G8*0.15 -> 35.85 | H65: =H8*0.15 -> 45.2805 | I65: =I8*0.15 -> 60.06 | ... AF65: =AF8*0.15 -> 301.56 | AG65: =SUM(B65:AF65) -> 4905.774
A66: Estimated Google Store Taxes | B66: 11.11 | C66: 1.29 | D66: 0.57 | E66: 1.24 | F66: 11.96 | G66: 0 | H66: 24.64 | I66: 6.68 | J66: 31.38 | K66: 10.77 | L66: 0 | M66: 8.29 | N66: 11.63 | O66: 0 | P66: 21.96 | Q66: 17.82 | R66: 11.87 | S66: 0.89 | T66: 0 | U66: 9.01 | V66: 1.13 | W66: 5.5 | X66: 43.93 | Y66: 52.85 | Z66: 60.73 | AA66: 51.68 | AB66: 22.31 | AC66: 7.49 | AD66: 12.77 | AE66: 14.4 | AF66: 0 | AG66: =SUM(B66:AF66) -> 453.9
A67: Estimated SUM Store Commision Fees | B67: =B63+B65 -> 550.20612 | C67: =C63+C65 -> 751.50596 | D67: =D63+D65 -> 583.64179 | E67: =E63+E65 -> 405.13361 | F67: =F63+F65 -> 349.27174 | G67: =G63+G65 -> 418.95888 | H67: =H63+H65 -> 423.08727 | I67: =I63+I65 -> 532.53499 | ... AF67: =AF63+AF65 -> 3454.026 | AG67: =SUM(B67:AF67) -> 52918.661
A68: Estimated SUM Store Taxes | B68: =B64+B66 -> 30.18 | C68: =C64+C66 -> 51.52 | D68: =D64+D66 -> 25.14 | E68: =E64+E66 -> 22.67 | F68: =F64+F66 -> 30.31 | G68: =G64+G66 -> 18.1 | H68: =H64+H66 -> 46.98 | I68: =I64+I66 -> 42.39 | ... AF68: =AF64+AF66 -> 25.01 | AG68: =SUM(B68:AF68) -> 1469.84
A70: Advertising
A71: Meta Spend | B71: =Summary!B88 -> 0 | C71: =Summary!C88 -> 0 | D71: =Summary!D88 -> 0 | E71: =Summary!E88 -> 0 | F71: =Summary!F88 -> 91.244022 | G71: =Summary!G88 -> 150.98989 | H71: =Summary!H88 -> 152.00203 | I71: =Summary!I88 -> 161.24368 | ... AF71: =Summary!AF88 -> 0 | AG71: =SUM(B71:AF71) -> 2096.0932
A72: Apple Spend | B72: =Summary!B89 -> 14.9 | C72: =Summary!C89 -> 19.59 | D72: =Summary!D89 -> 28.73 | E72: =Summary!E89 -> 17.62 | F72: =Summary!F89 -> 15.45 | G72: =Summary!G89 -> 11.97 | H72: =Summary!H89 -> 11.38 | I72: =Summary!I89 -> 17.66 | ... AF72: =Summary!AF89 -> 121.62 | AG72: =SUM(B72:AF72) -> 1212.8
A73: Google Spend
A74: SUM | B74: =SUM(B71:B73) -> 14.9 | C74: =SUM(C71:C73) -> 19.59 | D74: =SUM(D71:D73) -> 28.73 | E74: =SUM(E71:E73) -> 17.62 | F74: =SUM(F71:F73) -> 106.69402 | G74: =SUM(G71:G73) -> 162.95989 | H74: =SUM(H71:H73) -> 163.38203 | I74: =SUM(I71:I73) -> 178.90368 | ... AF74: =SUM(AF71:AF73) -> 121.62
A76: Estimated Subscription Profit
A77: - Estimated Apple Store profit | B77: =B43-B63-B64-B72-(B71*'OLD Data - P&L'!$I$18) -> 1140.5933 | C77: =C43-C63-C64-C72-(C71*'OLD Data - P&L'!$I$18) -> 1547.9164 | D77: =D43-D63-D64-D72-(D71*'OLD Data - P&L'!$I$18) -> 1188.0048 | E77: =E43-E63-E64-E72-(E71*'OLD Data - P&L'!$I$18) -> 876.52925 | F77: =F43-F63-F64-F72-(F71*'OLD Data - P&L'!$I$18) -> 675.9449 | G77: =G43-G63-G64-G72-(G71*'OLD Data - P&L'!$I$18) -> 863.85072 | H77: =H43-H63-H64-H72-(H71*'OLD Data - P&L'!$I$18) -> 817.83913 | I77: =I43-I63-I64-I72-(I71*'OLD Data - P&L'!$I$18) -> 1049.0717 | ... AF77: =AF43-AF63-AF64-AF72-(AF71*'OLD Data - P&L'!$I$18) -> 7179.1339 | AG77: =sum(B77:AF77) -> 109369.4
A78: - Estimated Google Store profit | B78: =B46-B65-B66-B73-(B71*'OLD Data - P&L'!$I$19) -> 181.381 | C78: =C46-C65-C66-C73-(C71*'OLD Data - P&L'!$I$19) -> 255.6225 | D78: =D46-D65-D66-D73-(D71*'OLD Data - P&L'!$I$19) -> 292.136 | E78: =E46-E65-E66-E73-(E71*'OLD Data - P&L'!$I$19) -> 70.9675 | F78: =F46-F65-F66-F73-(F71*'OLD Data - P&L'!$I$19) -> 170.7475 | G78: =G46-G65-G66-G73-(G71*'OLD Data - P&L'!$I$19) -> 203.15 | H78: =H46-H65-H66-H73-(H71*'OLD Data - P&L'!$I$19) -> 231.9495 | I78: =I46-I65-I66-I73-(I71*'OLD Data - P&L'!$I$19) -> 333.66 | ... AF78: =AF46-AF65-AF66-AF73-(AF71*'OLD Data - P&L'!$I$19) -> 1708.84 | AG78: =sum(B78:AF78) -> 27345.486
A79: Estimated SUM Profit | B79: =sum(B77:B78) -> 1321.9743 | C79: =sum(C77:C78) -> 1803.5389 | D79: =sum(D77:D78) -> 1480.1408 | E79: =sum(E77:E78) -> 947.49675 | F79: =sum(F77:F78) -> 846.6924 | G79: =sum(G77:G78) -> 1067.0007 | H79: =sum(H77:H78) -> 1049.7886 | I79: =sum(I77:I78) -> 1382.7317 | ... AF79: =sum(AF77:AF78) -> 8887.9739 | AG79: =sum(B79:AF79) -> 136714.88
A82: Gross Revenue
A83: =SUM(B11:AF11) -> 192748.12
A84: Gross Sales Profit
A85: =SUM(B79:AF79) -> 136714.88
A86: Gross Sales Margin
A87: =A85/A83 -> 0.70929298
A89: For summary
A90: Google | B90: =B8-B65-B66 -> 181.381 | C90: =C8-C65-C66 -> 255.6225 | D90: =D8-D65-D66 -> 292.136 | E90: =E8-E65-E66 -> 70.9675 | F90: =F8-F65-F66 -> 170.7475 | G90: =G8-G65-G66 -> 203.15 | H90: =H8-H65-H66 -> 231.9495 | I90: =I8-I65-I66 -> 333.66 | ... AF90: =AF8-AF65-AF66 -> 1708.84
A91: Apple | B91: =B5-B63-B64 -> 1185.4833 | C91: =C5-C63-C64 -> 1597.4964 | D91: =D5-D63-D64 -> 1216.7348 | E91: =E5-E63-E64 -> 894.14925 | F91: =F5-F63-F64 -> 721.3849 | G91: =G5-G63-G64 -> 875.82072 | H91: =H5-H63-H64 -> 859.20913 | I91: =I5-I63-I64 -> 1066.7317 | ... AF91: =AF5-AF63-AF64 -> 7330.7439

Sheet Digital Marketplaces
A1: DECEMBER | B1: 45261 | C1: 45262 | D1: 45263 | E1: 45264 | F1: 45265 | G1: 45266 | H1: 45267 | I1: 45268 | J1: 45269 | K1: 45270 | L1: 45271 | M1: 45272 | N1: 45273 | O1: 45274 | P1: 45275 | Q1: 45276 | R1: 45277 | S1: 45278 | T1: 45279 | U1: 45280 | V1: 45281 | W1: 45282 | X1: 45283 | Y1: 45284 | Z1: 45285 | AA1: 45286 | AB1: 45287 | AC1: 45288 | AD1: 45289 | AE1: 45290 | AF1: 45291
A2: DAY | B2: FRI | C2: SAT | D2: SUN | E2: MON | F2: TUE | G2: WED | H2: THU | I2: FRI | J2: SAT | K2: SUN | L2: MON | M2: TUE | N2: WED | O2: THU | P2: FRI | Q2: SAT | R2: SUN | S2: MON | T2: TUE | U2: WED | V2: THU | W2: FRI | X2: SAT | Y2: SUN | Z2: MON | AA2: TUE | AB2: WED | AC2: THU | AD2: FRI | AE2: SAT | AF2: SUN
A3: Rachio (Shopify)
A4: Revenue | B4: =Summary!B21 -> 955.22816 | C4: =Summary!C21 -> 318.40939 | D4: =Summary!D21 -> 636.81877 | E4: =Summary!E21 -> 318.40939 | F4: =Summary!F21 -> 318.40939 | G4: =Summary!G21 -> 0 | H4: =Summary!H21 -> 0 | I4: =Summary!I21 -> 955.22816 | ... AF4: =Summary!AF21 -> 0 | AG4: =sum(B4:AF4) -> 43431.023
A5: Breakdown
A6: - Tax | B6: =Summary!B23 -> 55.258158 | C6: =Summary!C23 -> 18.419386 | D6: =Summary!D23 -> 36.838772 | E6: =Summary!E23 -> 18.419386 | F6: =Summary!F23 -> 18.419386 | G6: =Summary!G23 -> 0 | H6: =Summary!H23 -> 0 | I6: =Summary!I23 -> 55.258158 | ... AF6: =Summary!AF23 -> 0 | AG6: =sum(B6:AF6) -> 2512.4033
A7: - Shipping | AG7: =sum(B7:AF7) -> 0
A8: Orders | B8: =Summary!B57 -> 4 | C8: =Summary!C57 -> 1 | D8: =Summary!D57 -> 2 | E8: =Summary!E57 -> 1 | F8: =Summary!F57 -> 1 | G8: =Summary!G57 -> 0 | H8: =Summary!H57 -> 0 | I8: =Summary!I57 -> 3 | ... AF8: =Summary!AF57 -> 0 | AG8: =sum(B8:AF8) -> 143
A10: Rachio Fees (20%) | B10: =Summary!B82 -> 191.04563 | C10: =Summary!C82 -> 63.681877 | D10: =Summary!D82 -> 127.36375 | E10: =Summary!E82 -> 63.681877 | F10: =Summary!F82 -> 63.681877 | G10: =Summary!G82 -> 0 | H10: =Summary!H82 -> 0 | I10: =Summary!I82 -> 191.04563 | ... AF10: =Summary!AF82 -> 0 | AG10: =sum(B10:AF10) -> 8686.2047
A12: Units Sold (Gross) - Rachio
A13: SKU 1 - Blue | B13: 0 | C13: 0 | D13: 0 | E13: 0 | F13: 0 | G13: 0 | H13: 0 | I13: 0 | J13: 0 | K13: 1 | L13: 0 | M13: 2 | N13: 2 | O13: 0 | P13: 0 | Q13: 0 | R13: 0 | S13: 0 | T13: 0 | U13: 0 | V13: 0 | W13: 0 | X13: 0 | Y13: 0 | Z13: 0 | AA13: 0 | AB13: 0 | AC13: 0 | AD13: 0 | AE13: 0 | AF13: 0 | AG13: =sum(B13:AF13) -> 5
A14: SKU 2 - Yellow | B14: 0 | C14: 0 | D14: 0 | E14: 0 | F14: 0 | G14: 0 | H14: 0 | I14: 0 | J14: 1 | K14: 0 | L14: 0 | M14: 1 | N14: 1 | O14: 0 | P14: 0 | Q14: 0 | R14: 0 | S14: 0 | T14: 0 | U14: 0 | V14: 0 | W14: 0 | X14: 0 | Y14: 0 | Z14: 0 | AA14: 0 | AB14: 0 | AC14: 0 | AD14: 0 | AE14: 0 | AF14: 0 | AG14: =sum(B14:AF14) -> 3
A15: SKU 3 - Blue w/ Solar | B15: 3 | C15: 0 | D15: 2 | E15: 1 | F15: 1 | G15: 0 | H15: 0 | I15: 2 | J15: 2 | K15: 2 | L15: 4 | M15: 64 | N15: 14 | O15: 0 | P15: 0 | Q15: 3 | R15: 1 | S15: 0 | T15: 2 | U15: 0 | V15: 0 | W15: 0 | X15: 0 | Y15: 0 | Z15: 0 | AA15: 0 | AB15: 0 | AC15: 0 | AD15: 0 | AE15: 0 | AF15: 0 | AG15: =sum(B15:AF15) -> 101
A16: SKU 4 - Yellow w/ Solar | B16: 3 | C16: 1 | D16: 0 | E16: 0 | F16: 0 | G16: 0 | H16: 0 | I16: 1 | J16: 0 | K16: 0 | L16: 0 | M16: 20 | N16: 9 | O16: 0 | P16: 0 | Q16: 0 | R16: 1 | S16: 2 | T16: 0 | U16: 0 | V16: 0 | W16: 0 | X16: 0 | Y16: 0 | Z16: 0 | AA16: 0 | AB16: 0 | AC16: 0 | AD16: 0 | AE16: 0 | AF16: 0 | AG16: =sum(B16:AF16) -> 37
A17: SUM (SKU 1 - SKU 4) | B17: =SUM(B13:B16) -> 6 | C17: =SUM(C13:C16) -> 1 | D17: =SUM(D13:D16) -> 2 | E17: =SUM(E13:E16) -> 1 | F17: =SUM(F13:F16) -> 1 | G17: =SUM(G13:G16) -> 0 | H17: =SUM(H13:H16) -> 0 | I17: =SUM(I13:I16) -> 3 | ... AF17: =SUM(AF13:AF16) -> 0 | AG17: =sum(B17:AF17) -> 146
A19: Wall Mount | B19: 0 | C19: 0 | D19: 0 | E19: 0 | F19: 0 | G19: 0 | H19: 0 | I19: 0 | J19: 0 | K19: 0 | L19: 0 | M19: 0 | N19: 0 | O19: 0 | P19: 0 | Q19: 0 | R19: 0 | S19: 0 | T19: 0 | U19: 0 | V19: 0 | W19: 0 | X19: 0 | Y19: 0 | Z19: 0 | AA19: 0 | AB19: 0 | AC19: 0 | AD19: 0 | AE19: 0 | AF19: 0 | AG19: =sum(B19:AF19) -> 0
A20: Suet Ball Holder | B20: 0 | C20: 0 | D20: 0 | E20: 0 | F20: 0 | G20: 0 | H20: 0 | I20: 0 | J20: 0 | K20: 0 | L20: 0 | M20: 0 | N20: 0 | O20: 0 | P20: 0 | Q20: 0 | R20: 0 | S20: 0 | T20: 0 | U20: 0 | V20: 0 | W20: 0 | X20: 0 | Y20: 0 | Z20: 0 | AA20: 0 | AB20: 0 | AC20: 0 | AD20: 0 | AE20: 0 | AF20: 0 | AG20: =sum(B20:AF20) -> 0
A21: 3-in-1 Nutrition Set - Blue | B21: 0 | C21: 0 | D21: 0 | E21: 0 | F21: 0 | G21: 0 | H21: 0 | I21: 0 | J21: 0 | K21: 0 | L21: 0 | M21: 0 | N21: 0 | O21: 0 | P21: 0 | Q21: 0 | R21: 0 | S21: 0 | T21: 0 | U21: 0 | V21: 0 | W21: 0 | X21: 0 | Y21: 0 | Z21: 0 | AA21: 0 | AB21: 0 | AC21: 0 | AD21: 0 | AE21: 0 | AF21: 0 | AG21: =sum(B21:AF21) -> 0
A22: 3-in-1 Nutrition Set - Yellow | B22: 0 | C22: 0 | D22: 0 | E22: 0 | F22: 0 | G22: 0 | H22: 0 | I22: 0 | J22: 0 | K22: 0 | L22: 0 | M22: 0 | N22: 0 | O22: 0 | P22: 0 | Q22: 0 | R22: 0 | S22: 0 | T22: 0 | U22: 0 | V22: 0 | W22: 0 | X22: 0 | Y22: 0 | Z22: 0 | AA22: 0 | AB22: 0 | AC22: 0 | AD22: 0 | AE22: 0 | AF22: 0 | AG22: =sum(B22:AF22) -> 0
A23: Solar Roof Single - Blue | B23: 0 | C23: 0 | D23: 0 | E23: 0 | F23: 0 | G23: 0 | H23: 0 | I23: 0 | J23: 0 | K23: 0 | L23: 0 | M23: 0 | N23: 0 | O23: 0 | P23: 0 | Q23: 0 | R23: 0 | S23: 0 | T23: 0 | U23: 0 | V23: 0 | W23: 0 | X23: 0 | Y23: 0 | Z23: 0 | AA23: 0 | AB23: 0 | AC23: 0 | AD23: 0 | AE23: 0 | AF23: 0 | AG23: =sum(B23:AF23) -> 0
A24: Solar Roof Single - Yellow | B24: 0 | C24: 0 | D24: 0 | E24: 0 | F24: 0 | G24: 0 | H24: 0 | I24: 0 | J24: 0 | K24: 0 | L24: 0 | M24: 0 | N24: 0 | O24: 0 | P24: 0 | Q24: 0 | R24: 0 | S24: 0 | T24: 0 | U24: 0 | V24: 0 | W24: 0 | X24: 0 | Y24: 0 | Z24: 0 | AA24: 0 | AB24: 0 | AC24: 0 | AD24: 0 | AE24: 0 | AF24: 0 | AG24: =sum(B24:AF24) -> 0
A25: Perch Extender - Blue | B25: 0 | C25: 0 | D25: 0 | E25: 0 | F25: 0 | G25: 0 | H25: 0 | I25: 0 | J25: 0 | K25: 0 | L25: 0 | M25: 0 | N25: 0 | O25: 0 | P25: 0 | Q25: 0 | R25: 0 | S25: 0 | T25: 0 | U25: 0 | V25: 0 | W25: 0 | X25: 0 | Y25: 0 | Z25: 0 | AA25: 0 | AB25: 0 | AC25: 0 | AD25: 0 | AE25: 0 | AF25: 0 | AG25: =sum(B25:AF25) -> 0
A26: Perch Extender - Yellow | B26: 0 | C26: 0 | D26: 0 | E26: 0 | F26: 0 | G26: 0 | H26: 0 | I26: 0 | J26: 0 | K26: 0 | L26: 0 | M26: 0 | N26: 0 | O26: 0 | P26: 0 | Q26: 0 | R26: 0 | S26: 0 | T26: 0 | U26: 0 | V26: 0 | W26: 0 | X26: 0 | Y26: 0 | Z26: 0 | AA26: 0 | AB26: 0 | AC26: 0 | AD26: 0 | AE26: 0 | AF26: 0 | AG26: =sum(B26:AF26) -> 0
A27: SUM (Add-ons) | B27: =SUM(B19:B26) -> 0 | C27: =SUM(C19:C26) -> 0 | D27: =SUM(D19:D26) -> 0 | E27: =SUM(E19:E26) -> 0 | F27: =SUM(F19:F26) -> 0 | G27: =SUM(G19:G26) -> 0 | H27: =SUM(H19:H26) -> 0 | I27: =SUM(I19:I26) -> 0 | ... AF27: =SUM(AF19:AF26) -> 0 | AG27: =sum(B27:AF27) -> 0
A29: Units and Revenue Cancelled & Refunds - Rachio
A31: Units Cancelled (Gross) - Rachio
A32: SKU 1 - Blue | AG32: =SUM(B32:AF32) -> 0
A33: SKU 2 - Yellow | AG33: =SUM(B33:AF33) -> 0
A34: SKU 3 - Blue w/ Solar | G34: 1 | AG34: =SUM(B34:AF34) -> 1
A35: SKU 4 - Yellow w/ Solar | AG35: =SUM(B35:AF35) -> 0
A36: SUM (SKU 1 + SKU 2) | B36: =SUM(B32:B33) -> 0 | C36: =SUM(C32:C33) -> 0 | D36: =SUM(D32:D33) -> 0 | E36: =SUM(E32:E33) -> 0 | F36: =SUM(F32:F33) -> 0 | G36: =SUM(G32:G33) -> 0 | H36: =SUM(H32:H33) -> 0 | I36: =SUM(I32:I33) -> 0 | ... AF36: =SUM(AF32:AF33) -> 0 | AG36: =SUM(B36:AF36) -> 0
A37: SUM (SKU 3 + SKU 4) | B37: =SUM(B34:B35) -> 0 | C37: =SUM(C34:C35) -> 0 | D37: =SUM(D34:D35) -> 0 | E37: =SUM(E34:E35) -> 0 | F37: =SUM(F34:F35) -> 0 | G37: =SUM(G34:G35) -> 1 | H37: =SUM(H34:H35) -> 0 | I37: =SUM(I34:I35) -> 0 | ... AF37: =SUM(AF34:AF35) -> 0 | AG37: =SUM(B37:AF37) -> 1
A39: Wall Mount | AG39: =SUM(B39:AF39) -> 0
A40: Suet Ball Holder | AG40: =SUM(B40:AF40) -> 0
A41: 3-in-1 Nutrition Set - Blue | AG41: =SUM(B41:AF41) -> 0
A42: 3-in-1 Nutrition Set - Yellow | AG42: =SUM(B42:AF42) -> 0
A43: Solar Roof Single - Blue | AG43: =SUM(B43:AF43) -> 0
A44: Solar Roof Single - Yellow | AG44: =SUM(B44:AF44) -> 0
A45: Perch Extender - Blue | AG45: =SUM(B45:AF45) -> 0
A46: Perch Extender - Yellow | AG46: =SUM(B46:AF46) -> 0
A47: SUM (Add-ons) | B47: =SUM(B39:B46) -> 0 | C47: =SUM(C39:C46) -> 0 | D47: =SUM(D39:D46) -> 0 | E47: =SUM(E39:E46) -> 0 | F47: =SUM(F39:F46) -> 0 | G47: =SUM(G39:G46) -> 0 | H47: =SUM(H39:H46) -> 0 | I47: =SUM(I39:I46) -> 0 | ... AF47: =SUM(AF39:AF46) -> 0 | AG47: =SUM(B47:AF47) -> 0
A49: Revenue Cancelled (Gross) - Rachio
A50: Hardware | G50: 299.99 | AC50: 98 | AG50: =SUM(B50:AF50) -> 397.99
A51: Shipping | AG51: =SUM(B51:AF51) -> 0
A52: Taxes | AG52: =SUM(B52:AF52) -> 0
A53: All NA | B53: =SUM(B50:B52) -> 0 | C53: =SUM(C50:C52) -> 0 | D53: =SUM(D50:D52) -> 0 | E53: =SUM(E50:E52) -> 0 | F53: =SUM(F50:F52) -> 0 | G53: =SUM(G50:G52) -> 299.99 | H53: =SUM(H50:H52) -> 0 | I53: =SUM(I50:I52) -> 0 | ... AF53: =SUM(AF50:AF52) -> 0 | AG53: =SUM(B53:AF53) -> 397.99
A55: Hardware - Europe | AG55: =SUM(B55:AF55) -> 0
A56: Shipping - Europe | AG56: =SUM(B56:AF56) -> 0
A57: All EU | B57: =sum(B55:B56) -> 0 | C57: =sum(C55:C56) -> 0 | D57: =sum(D55:D56) -> 0 | E57: =sum(E55:E56) -> 0 | F57: =sum(F55:F56) -> 0 | G57: =sum(G55:G56) -> 0 | H57: =sum(H55:H56) -> 0 | I57: =sum(I55:I56) -> 0 | ... AF57: =sum(AF55:AF56) -> 0 | AG57: =SUM(B57:AF57) -> 0
A59: Units Refund (Gross) - Rachio
A60: SKU 1 - Blue | G60: 1 | T60: 1 | AG60: =SUM(B60:AF60) -> 2
A61: SKU 2 - Yellow | G61: 1 | AG61: =SUM(B61:AF61) -> 1
A62: SKU 3 - Blue w/ Solar | M62: 1 | V62: 1 | Y62: 1 | AC62: 1 | AG62: =SUM(B62:AF62) -> 4
A63: SKU 4 - Yellow w/ Solar | AG63: =SUM(B63:AF63) -> 0
A64: SUM (SKU 1 + SKU 2) | B64: =SUM(B60:B61) -> 0 | C64: =SUM(C60:C61) -> 0 | D64: =SUM(D60:D61) -> 0 | E64: =SUM(E60:E61) -> 0 | F64: =SUM(F60:F61) -> 0 | G64: =SUM(G60:G61) -> 2 | H64: =SUM(H60:H61) -> 0 | I64: =SUM(I60:I61) -> 0 | ... AF64: =SUM(AF60:AF61) -> 0 | AG64: =SUM(B64:AF64) -> 3
A65: SUM (SKU 3 + SKU 4) | B65: =SUM(B62:B63) -> 0 | C65: =SUM(C62:C63) -> 0 | D65: =SUM(D62:D63) -> 0 | E65: =SUM(E62:E63) -> 0 | F65: =SUM(F62:F63) -> 0 | G65: =SUM(G62:G63) -> 0 | H65: =SUM(H62:H63) -> 0 | I65: =SUM(I62:I63) -> 0 | ... AF65: =SUM(AF62:AF63) -> 0 | AG65: =SUM(B65:AF65) -> 4
A67: Wall Mount | T67: 1 | AG67: =SUM(B67:AF67) -> 1
A68: Suet Ball Holder | T68: 1 | V68: 1 | AC68: 1 | AG68: =SUM(B68:AF68) -> 3
A69: 3-in-1 Nutrition Set - Blue | Y69: 1 | AG69: =SUM(B69:AF69) -> 1
A70: 3-in-1 Nutrition Set - Yellow | AG70: =SUM(B70:AF70) -> 0
A71: Solar Roof Single - Blue | G71: 1 | O71: 1 | T71: 1 | AG71: =SUM(B71:AF71) -> 3
A72: Solar Roof Single - Yellow | AG72: =SUM(B72:AF72) -> 0
A73: Perch Extender - Blue | AG73: =SUM(B73:AF73) -> 0
A74: Perch Extender - Yellow | AG74: =SUM(B74:AF74) -> 0
A75: SUM (Add-ons) | B75: =SUM(B67:B74) -> 0 | C75: =SUM(C67:C74) -> 0 | D75: =SUM(D67:D74) -> 0 | E75: =SUM(E67:E74) -> 0 | F75: =SUM(F67:F74) -> 0 | G75: =SUM(G67:G74) -> 1 | H75: =SUM(H67:H74) -> 0 | I75: =SUM(I67:I74) -> 0 | ... AF75: =SUM(AF67:AF74) -> 0 | AG75: =SUM(B75:AF75) -> 8
A77: Orders Return for Refund
A79: Revenue Refunded (Gross) - Rachio
A80: Hardware | G80: 489.54 | M80: 309.63 | T80: 326 | V80: 306.34 | Y80: 338.54 | AC80: 315.14 | AG80: =SUM(B80:AF80) -> 2085.19
A81: Shipping | M81: 20 | AG81: =SUM(B81:AF81) -> 20
A82: Taxes | AG82: =SUM(B82:AF82) -> 0
A83: All NA | B83: =sum(B80:B82) -> 0 | C83: =sum(C80:C82) -> 0 | D83: =sum(D80:D82) -> 0 | E83: =sum(E80:E82) -> 0 | F83: =sum(F80:F82) -> 0 | G83: =sum(G80:G82) -> 489.54 | H83: =sum(H80:H82) -> 0 | I83: =sum(I80:I82) -> 0 | ... AF83: =sum(AF80:AF82) -> 0 | AG83: =SUM(B83:AF83) -> 2105.19
A85: Hardware - Europe
A86: Shipping - Europe
A87: All EU | B87: =sum(B85:B86) -> 0 | C87: =sum(C85:C86) -> 0 | D87: =sum(D85:D86) -> 0 | E87: =sum(E85:E86) -> 0 | F87: =sum(F85:F86) -> 0 | G87: =sum(G85:G86) -> 0 | H87: =sum(H85:H86) -> 0 | I87: =sum(I85:I86) -> 0 | ... AF87: =sum(AF85:AF86) -> 0
A89: RETURN (Replacement Units & Claims) - Rachio
A90: SKU 1 - Blue | B90: 0 | C90: 0 | D90: 0 | E90: 0 | F90: 0 | G90: 0 | H90: 0 | I90: 0 | J90: 0 | K90: 0 | L90: 0 | M90: 0 | N90: 0 | O90: 0 | P90: 0 | Q90: 0 | R90: 0 | S90: 0 | T90: 0 | U90: 0 | V90: 0 | W90: 0 | X90: 0 | Y90: 0 | Z90: 0 | AA90: 0 | AB90: 0 | AC90: 0 | AD90: 0 | AE90: 0 | AF90: 0 | AG90: =SUM(B90:AF90) -> 0
A91: SKU 2 - Yellow | B91: 0 | C91: 0 | D91: 0 | E91: 0 | F91: 0 | G91: 0 | H91: 0 | I91: 0 | J91: 0 | K91: 0 | L91: 0 | M91: 0 | N91: 0 | O91: 0 | P91: 0 | Q91: 0 | R91: 0 | S91: 0 | T91: 0 | U91: 0 | V91: 0 | W91: 0 | X91: 0 | Y91: 0 | Z91: 0 | AA91: 0 | AB91: 0 | AC91: 0 | AD91: 0 | AE91: 0 | AF91: 0 | AG91: =SUM(B91:AF91) -> 0
A92: SKU 3 - Blue w/ Solar | B92: 0 | C92: 0 | D92: 0 | E92: 0 | F92: 0 | G92: 0 | H92: 0 | I92: 0 | J92: 0 | K92: 0 | L92: 0 | M92: 0 | N92: 0 | O92: 0 | P92: 0 | Q92: 0 | R92: 0 | S92: 0 | T92: 0 | U92: 0 | V92: 0 | W92: 0 | X92: 0 | Y92: 0 | Z92: 0 | AA92: 0 | AB92: 0 | AC92: 0 | AD92: 0 | AE92: 0 | AF92: 0 | AG92: =SUM(B92:AF92) -> 0
A93: SKU 4 - Yellow w/ Solar | B93: 0 | C93: 0 | D93: 0 | E93: 0 | F93: 1 | G93: 0 | H93: 0 | I93: 0 | J93: 0 | K93: 0 | L93: 0 | M93: 0 | N93: 0 | O93: 0 | P93: 0 | Q93: 0 | R93: 0 | S93: 0 | T93: 0 | U93: 0 | V93: 0 | W93: 0 | X93: 0 | Y93: 0 | Z93: 0 | AA93: 0 | AB93: 0 | AC93: 0 | AD93: 0 | AE93: 0 | AF93: 0 | AG93: =SUM(B93:AF93) -> 1
A94: SUM (SKU 1 + SKU 2) | B94: =B90+B91 -> 0 | C94: =C90+C91 -> 0 | D94: =D90+D91 -> 0 | E94: =E90+E91 -> 0 | F94: =F90+F91 -> 0 | G94: =G90+G91 -> 0 | H94: =H90+H91 -> 0 | I94: =I90+I91 -> 0 | ... AF94: =AF90+AF91 -> 0 | AG94: =SUM(B94:AF94) -> 0
A95: SUM (SKU 3 + SKU 4) | B95: =B92+B93 -> 0 | C95: =C92+C93 -> 0 | D95: =D92+D93 -> 0 | E95: =E92+E93 -> 0 | F95: =F92+F93 -> 1 | G95: =G92+G93 -> 0 | H95: =H92+H93 -> 0 | I95: =I92+I93 -> 0 | ... AF95: =AF92+AF93 -> 0 | AG95: =SUM(B95:AF95) -> 1
A97: Wall Mount | B97: 0 | C97: 0 | D97: 0 | E97: 0 | F97: 0 | G97: 0 | H97: 0 | I97: 0 | J97: 0 | K97: 0 | L97: 0 | M97: 0 | N97: 0 | O97: 0 | P97: 0 | Q97: 0 | R97: 0 | S97: 0 | T97: 0 | U97: 0 | V97: 0 | W97: 0 | X97: 0 | Y97: 0 | Z97: 0 | AA97: 0 | AB97: 0 | AC97: 0 | AD97: 0 | AE97: 0 | AF97: 0 | AG97: =SUM(B97:AF97) -> 0
A98: Suet Ball Holder | B98: 0 | C98: 0 | D98: 0 | E98: 0 | F98: 0 | G98: 0 | H98: 0 | I98: 0 | J98: 0 | K98: 0 | L98: 0 | M98: 0 | N98: 0 | O98: 0 | P98: 0 | Q98: 0 | R98: 0 | S98: 0 | T98: 0 | U98: 0 | V98: 0 | W98: 0 | X98: 0 | Y98: 0 | Z98: 0 | AA98: 0 | AB98: 0 | AC98: 0 | AD98: 0 | AE98: 0 | AF98: 0 | AG98: =SUM(B98:AF98) -> 0
A99: 3-in-1 Nutrition Set - Blue | B99: 0 | C99: 0 | D99: 0 | E99: 0 | F99: 0 | G99: 0 | H99: 0 | I99: 0 | J99: 0 | K99: 0 | L99: 0 | M99: 0 | N99: 0 | O99: 0 | P99: 0 | Q99: 0 | R99: 0 | S99: 0 | T99: 0 | U99: 0 | V99: 0 | W99: 0 | X99: 0 | Y99: 0 | Z99: 0 | AA99: 0 | AB99: 0 | AC99: 0 | AD99: 0 | AE99: 0 | AF99: 0 | AG99: =SUM(B99:AF99) -> 0
A100: 3-in-1 Nutrition Set - Yellow | B100: 0 | C100: 0 | D100: 0 | E100: 0 | F100: 0 | G100: 0 | H100: 0 | I100: 0 | J100: 0 | K100: 0 | L100: 0 | M100: 0 | N100: 0 | O100: 0 | P100: 0 | Q100: 0 | R100: 0 | S100: 0 | T100: 0 | U100: 0 | V100: 0 | W100: 0 | X100: 0 | Y100: 0 | Z100: 0 | AA100: 0 | AB100: 0 | AC100: 0 | AD100: 0 | AE100: 0 | AF100: 0 | AG100: =SUM(B100:AF100) -> 0
A101: Solar Roof Single - Blue | B101: 0 | C101: 0 | D101: 0 | E101: 0 | F101: 0 | G101: 0 | H101: 0 | I101: 0 | J101: 0 | K101: 0 | L101: 0 | M101: 0 | N101: 0 | O101: 0 | P101: 0 | Q101: 0 | R101: 0 | S101: 0 | T101: 0 | U101: 0 | V101: 0 | W101: 0 | X101: 0 | Y101: 0 | Z101: 0 | AA101: 0 | AB101: 0 | AC101: 0 | AD101: 0 | AE101: 0 | AF101: 0 | AG101: =SUM(B101:AF101) -> 0
A102: Solar Roof Single - Yellow | B102: 0 | C102: 0 | D102: 0 | E102: 0 | F102: 0 | G102: 0 | H102: 0 | I102: 0 | J102: 0 | K102: 0 | L102: 0 | M102: 0 | N102: 0 | O102: 0 | P102: 0 | Q102: 0 | R102: 0 | S102: 0 | T102: 0 | U102: 0 | V102: 0 | W102: 0 | X102: 0 | Y102: 0 | Z102: 0 | AA102: 0 | AB102: 0 | AC102: 0 | AD102: 0 | AE102: 0 | AF102: 0 | AG102: =SUM(B102:AF102) -> 0
A103: Perch Extender - Blue | B103: 0 | C103: 0 | D103: 0 | E103: 0 | F103: 0 | G103: 0 | H103: 0 | I103: 0 | J103: 0 | K103: 0 | L103: 0 | M103: 0 | N103: 0 | O103: 0 | P103: 0 | Q103: 0 | R103: 0 | S103: 0 | T103: 0 | U103: 0 | V103: 0 | W103: 0 | X103: 0 | Y103: 0 | Z103: 0 | AA103: 0 | AB103: 0 | AC103: 0 | AD103: 0 | AE103: 0 | AF103: 0 | AG103: =SUM(B103:AF103) -> 0
A104: Perch Extender - Yellow | B104: 0 | C104: 0 | D104: 0 | E104: 0 | F104: 0 | G104: 0 | H104: 0 | I104: 0 | J104: 0 | K104: 0 | L104: 0 | M104: 0 | N104: 0 | O104: 0 | P104: 0 | Q104: 0 | R104: 0 | S104: 0 | T104: 0 | U104: 0 | V104: 0 | W104: 0 | X104: 0 | Y104: 0 | Z104: 0 | AA104: 0 | AB104: 0 | AC104: 0 | AD104: 0 | AE104: 0 | AF104: 0 | AG104: =SUM(B104:AF104) -> 0
A105: SUM (Add-ons) | B105: =SUM(B97:B104) -> 0 | C105: =SUM(C97:C104) -> 0 | D105: =SUM(D97:D104) -> 0 | E105: =SUM(E97:E104) -> 0 | F105: =SUM(F97:F104) -> 0 | G105: =SUM(G97:G104) -> 0 | H105: =SUM(H97:H104) -> 0 | I105: =SUM(I97:I104) -> 0 | ... AF105: =SUM(AF97:AF104) -> 0 | AG105: =SUM(B105:AF105) -> 0
A107: Parts
A108: Housing - Blue | B108: 0 | C108: 0 | D108: 0 | E108: 0 | F108: 0 | G108: 0 | H108: 0 | I108: 0 | J108: 0 | K108: 0 | L108: 0 | M108: 0 | N108: 0 | O108: 0 | P108: 0 | Q108: 0 | R108: 0 | S108: 0 | T108: 0 | U108: 0 | V108: 0 | W108: 0 | X108: 0 | Y108: 0 | Z108: 0 | AA108: 0 | AB108: 0 | AC108: 0 | AD108: 0 | AE108: 0 | AF108: 0 | AG108: =SUM(B108:AF108) -> 0
A109: Housing - Yellow | B109: 0 | C109: 0 | D109: 0 | E109: 0 | F109: 0 | G109: 0 | H109: 0 | I109: 0 | J109: 0 | K109: 0 | L109: 0 | M109: 0 | N109: 0 | O109: 0 | P109: 0 | Q109: 0 | R109: 0 | S109: 0 | T109: 0 | U109: 0 | V109: 0 | W109: 0 | X109: 0 | Y109: 0 | Z109: 0 | AA109: 0 | AB109: 0 | AC109: 0 | AD109: 0 | AE109: 0 | AF109: 0 | AG109: =SUM(B109:AF109) -> 0
A110: Camera Module | B110: 0 | C110: 0 | D110: 0 | E110: 0 | F110: 0 | G110: 0 | H110: 0 | I110: 0 | J110: 0 | K110: 0 | L110: 0 | M110: 0 | N110: 0 | O110: 0 | P110: 0 | Q110: 0 | R110: 0 | S110: 0 | T110: 0 | U110: 0 | V110: 0 | W110: 0 | X110: 0 | Y110: 0 | Z110: 0 | AA110: 0 | AB110: 0 | AC110: 0 | AD110: 0 | AE110: 0 | AF110: 0 | AG110: =SUM(B110:AF110) -> 0
A112: Orders Replaced NA | B112: 0 | C112: 0 | D112: 0 | E112: 0 | F112: 1 | G112: 0 | H112: 0 | I112: 0 | J112: 0 | K112: 0 | L112: 0 | M112: 0 | N112: 0 | O112: 0 | P112: 0 | Q112: 0 | R112: 0 | S112: 0 | T112: 0 | U112: 0 | V112: 0 | W112: 0 | X112: 0 | Y112: 0 | Z112: 0 | AA112: 0 | AB112: 0 | AC112: 0 | AD112: 0 | AE112: 0 | AF112: 0 | AG112: =SUM(B112:AF112) -> 1
A115: Weatherflow (Shopify)
A116: Revenue | B116: =Summary!B25 | C116: =Summary!C25 | D116: =Summary!D25 | E116: =Summary!E25 | F116: =Summary!F25 | G116: =Summary!G25 | H116: =Summary!H25 -> 1183.461 | I116: =Summary!I25 -> 3973.8816 | ... AF116: =Summary!AF25 -> 0 | AG116: =SUM(B116:AF116) -> 7693.0272
A117: Breakdown
A118: - Tax | B118: =Summary!B27 | C118: =Summary!C27 | D118: =Summary!D27 | E118: =Summary!E27 | F118: =Summary!F27 | G118: =Summary!G27 | H118: =Summary!H27 -> 68.461 | I118: =Summary!I27 -> 229.8816 | ... AF118: =Summary!AF27 -> 0 | AG118: =SUM(B118:AF118) -> 445.0272
A119: - Shipping
...

Sheet Data - P&L
B1: Business Metrics
A2: Source | B2: COGS | E2: Attachment Rates | H2: Marketing Averages (per first-time order) | K2: Fees | N2: VAT Averages | Q2: 30 Day Returns | T2: Digital Market Places & B2B
B3: Bird Buddy | C3: 86.9 | D3: 86.9 | E3: Solar Roof | F3: =(('DTC - P&L'!AG83+'DTC - P&L'!AG84)/'DTC - P&L'!AG77) -> 0.093977434 | H3: COGS | I3: =(C3*F9)+(C4*F8)+(C5*F3)+(C6*F4)+(C7*F5)+(C8*F6)+(C9*F7)+(C10*F10) -> 98.747507 | J3: =(D3*F9)+(D4*F8)+(D5*F3)+(D6*F4)+(D7*F5)+(D8*F6)+(D9*F7) -> 97.496396 | K3: Stripe Processing Fee | L3: 0.029 | N3: Europe | O3: 0.22 | Q3: US Shipping | R3: 15 | T3: Average % tax | U3: 0.0614
B4: Bird Buddy with Solar Roof | C4: 97.61 | D4: 97.61 | E4: Wall Mount | F4: =('DTC - P&L'!AG79/'DTC - P&L'!AG77) -> 0.25399306 | H4: Inbound Shipping | I4: =C38+('DTC - P&L'!AG87/'DTC - P&L'!AG77)*D38 -> 12.999515 | K4: Duty | L4: 0.034 | N4: ROW | O4: 0.13 | Q4: EU Shipping | R4: 40
B5: Solar Roof Single | C5: 13.44 | D5: 13.44 | E5: Fence Mount | F5: 0 | H5: Outbound Shipping | I5: =C34+('DTC - P&L'!AG87/'DTC - P&L'!AG77)*D34 -> 60.187683 | K5: China Tax | L5: 0.075 | N5: NA | Q5: ROW Shipping | R5: 20
B6: Wall Mount | C6: 5.49 | D6: 5.49 | E6: Suet Ball Holder | F6: =('DTC - P&L'!AG80)/'DTC - P&L'!AG77 -> 0.024031651 | H6: Taxes and VAT | I6: 16.81 | K6: HMF | L6: 0.00125 | Q6: Money Return | R6: 1
B7: Fence Mount | C7: 6.37 | E7: 3-in-1 | F7: =('DTC - P&L'!AG81+'DTC - P&L'!AG82)/'DTC - P&L'!AG77 -> 0.15781761 | H7: China Tax (7.5%) | I7: 0 | K7: MPF | L7: 0.003464
B8: Suet Ball Holder | C8: 1.19 | D8: 1.19 | E8: Bird Buddy w/ Solar | F8: =('DTC - P&L'!AG75+'DTC - P&L'!AG76)/'DTC - P&L'!AG77 -> 0.64045328 | H8: Duty (3.4%) | I8: 0 | K8: Solar Roof China Tax | L8: 0.075
B9: 3-in-1 Nutrition Set | C9: 6.66 | D9: 6.66 | E9: Bird Buddy | F9: =1-F8 -> 0.35954672 | H9: Processing Fee (2,90%) | I9: =Summary!B117*L3 -> 8.1868511 | K9: Solar Roof Duty | L9: 0.025
B10: Perch Extender | C10: 6 | E10: Perch Extender | F10: =('DTC - P&L'!AG85+'DTC - P&L'!AG86)/'DTC - P&L'!AG77 -> 0.20851854 | H10: Transaction Fee ($0.30) | I10: =0.3 -> 0.3 | K10: Chargeback Fee (Stripe) | L10: 15
B11: Avg. Merch Cost | C11: 3.94 | E11: OTHER 2 | H11: OTHER 1
B12: Avg. Merch Cost without Calendar | C12: 14.79 | E12: OTHER 3 | H12: OTHER 2 | K12: Stripe (share %) | L12: 0.95
B13: SBF Housing | E13: OTHER 4 | H13: OTHER 3 | K13: Affirm (share %) | L13: 0.05
B14: SBF Camera | E14: OTHER 5 | H14: OTHER 4 | K14: Affirm processing fee | L14: 0.0579
H15: All | I15: =SUM(I3:I14) -> 197.23156 | K15: Affirm transaction fee | L15: 0.3
B22: Outbound shipping | C22: Bird buddy | D22: Add-ons | E22: Merch
A23: *w/o CA weight | B23: Outbound (NA) | C23: 52.76 | D23: 10.06 | E23: 5.4 | H23: App Advertising
B24: Outbound (Europe) | C24: 11.94 | D24: 6.16 | H24: Meta Share to Apple Store | I24: 0.8
B25: Outbound (ROW) | C25: 11.94 | D25: 6.16 | H25: Meta Share to Google Store | I25: 0.2
A26: Source | B26: 3PL Costs | C26: 0 | D26: 0
B27: Handling Fee
B28: Serial Capture | C28: 0.1 | D28: 0
B29: Storage | C29: 0.31 | D29: 0.31
B30: Supplies cost | C30: 0 | D30: 0
B31: Pick charge | C31: 0.35 | D31: 0.35
B32: Pollybag cost | C32: 0 | D32: 0
B33: Carton cost | C33: 1.65 | D33: 0.71
B34: Total outbound (NA) | C34: =C26+C23-C27 -> 52.76 | D34: =D26+D23-D27 -> 10.06
B35: Total outbound (Europe) | C35: 15.06 | D35: =D27+D24-D28 -> 6.16
B36: Total outbound (ROW) | C36: 20
A37: Source | B37: Inbound shipping | C37: Bird buddy | D37: Add-ons
B38: Inbound (NA) | C38: 11.94 | D38: 1.435
B39: Inbound (Europe) | C39: 11.94 | D39: 1.44
B40: Inbound (ROW) | C40: 11.94 | D40: 1.44
B42: AMAZON Logistics | C42: Bird buddy | D42: Add-ons
A43: https://docs.google.com/spreadsheets/d/1Dn0q7h1bHxXdG0N9KpcqzFo0tWUWYXOrRX7yxv3G1E0/edit#gid=1264242332 | B43: Inbound | C43: 11.94 | D43: 1.435
A44: =sum(C43:C44) -> 12.18 | B44: Storage Fee | C44: 0.24 | D44: 0.24
A45: =C46 -> 12.94 | B45: AMAZON Fees | C45: Bird buddy
A46: =sum(F43:F45) -> 0 | B46: FBA fee for units | C46: 12.94
B47: FBA fee for addons | C47: 5.7
A48: =C38 -> 11.94 | B48: Sales Fee | C48: 0.15
B49: AMAZON Shipping | C49: Bird buddy
A50: =sum(A43:A48) -> 37.06 | B50: BB units Shipping | C50: 11
B51: Addons Shipping | C51: 6.155
B53: COGS adjustment for DTC
B54: Returns for refunds | C54: 0.25
B55: Returns for replacements | C55: 0.1
B57: COGS adjustment for Amazon
B58: Returns for refunds | C58: 0.5644
B59: Returns for replacements | C59: 0.4603
B61: Amazon Removal Fee
B62: Units | C62: 5.56
B63: Add-ons | C63: 2.2
A66: https://docs.google.com/document/d/1m1D0mcq6_cpIUs4Z2pSMjDX9L4kRSfAwaLu0UKQppIM/edit?usp=sharing | B66: Explanation for Returns, Cancellations, Replacements calculation
A68: https://docs.google.com/spreadsheets/d/1JFD6SusYZSq5MvMm0PnCaYPmLBVKBKvK09yjZIlSFN4/edit#gid=0 | B68: Amazon Modelling for cancelled orders
B69: Full Price Template for cancelled orders
B70: item-tax | C70: 17.58
B71: shipping-price | C71: 0.29
B72: shipping-tax | C72: 0
B73: gift-wrap-price | C73: 0.17
B74: gift-wrap-tax | C74: 0.01
B75: item-promotion-discount | C75: 2.44
B76: ship-promotion-discount | C76: 0.21

Sheet OLD Summary
A1: 45261 | B1: 45261 | C1: 45262 | D1: 45263 | E1: 45264 | F1: 45265 | G1: 45266 | H1: 45267 | I1: 45268 | J1: 45269 | K1: 45270 | L1: 45271 | M1: 45272 | N1: 45273 | O1: 45274 | P1: 45275 | Q1: 45276 | R1: 45277 | S1: 45278 | T1: 45279 | U1: 45280 | V1: 45281 | W1: 45282 | X1: 45283 | Y1: 45284 | Z1: 45285 | AA1: 45286 | AB1: 45287 | AC1: 45288 | AD1: 45289 | AE1: 45290 | AF1: 45291
B2: FRI | C2: SAT | D2: SUN | E2: MON | F2: TUE | G2: WED | H2: THU | I2: FRI | J2: SAT | K2: SUN | L2: MON | M2: TUE | N2: WED | O2: THU | P2: FRI | Q2: SAT | R2: SUN | S2: MON | T2: TUE | U2: WED | V2: THU | W2: FRI | X2: SAT | Y2: SUN | Z2: MON | AA2: TUE | AB2: WED | AC2: THU | AD2: FRI | AE2: SAT | AF2: SUN
A3: Weekend Work | C3: Peco | D3: Peco | J3: Peco | K3: Peco | P3: Peco | Q3: Peco | R3: Peco | X3: Peco | Y3: Peco | Z3: Peco | AA3: Peco | AD3: Peter | AE3: Peter | AF3: Peter
A4: Notes | B4: Christmas Sale (-20%)
F5: 10:29 Yellow preferred version & blue version +$10 | H5: 10.30 Blue version additional +$10 & SKU 1+SKU 5 combination active | I5: Blue version additional $20 from 17:47 | K5: Featured on CBS Sunday Morning | L5: Blue BB out of stock at 14:25 SKU 3 live at 10:15 / Christmas Email Offer | N5: 16:05 changed US & Canada to expedited shipping, order #119304 16:06 +$20 on Bird Buddy Yellow units | O5: 9:23 - SKU3 & Pro Bundle Blue out of Stock 14:22 Pricing change on Yellow BBs (original prices, Wall Mount & 3-in-1 increase by $10), only pro bundle -20% 15:40 Amazon button on Smart bird feeder with solar roof | P5: 13:20 SKU2 +$10 ($249) SKU4 +$10 ($309) Solar Roof +$10 ($99) Wall Mount +$10 (49) Pro bundle $327 (20% off) Shipping US +$10 ($45) Add-on Shop - Yellow default | U5: 16:32 - SKU2 - $10 down ($239), SKU4 $10 down ($299), Pro bundle ($317) | V5: 14:12 - Blue & Yellow Pro Bundle $329 (added Suet Ball Holder, and +$1 per item for Wall Mount and 3-in-1), Suet Ball Holder back in stock for $24. Wall Mount price down to $39 (-$10). | AD5: 11:35 - Yellow Pro added perch extender (price goes up for $31 to $360), perch extended is back on stock | AE5: Twitter traffic spike
L6: SKU3 price increased to $349 at 11.00
A8: DTC Revenue | B8: 182768.19 | C8: 239740.61 | D8: 309347.58 | E8: 305301.52 | F8: 298114.36 | G8: 317223.83 | H8: 322596.91 | I8: 344395.45 | J8: 351653.41 | K8: 535464.96 | L8: 497925.43 | M8: 434520.58 | N8: 370511.62 | O8: 278943.97 | P8: 226551.54 | Q8: 190597.25 | R8: 130002.06 | S8: 149781.34 | T8: 139280.82 | U8: 105270.49 | V8: 51466.43 | W8: 44446 | X8: 30835.43 | Y8: 28013.35 | Z8: 46187.9 | AA8: 36471.13 | AB8: 30795.96 | AC8: 30010.78 | AD8: 34239.3 | AE8: 43921.59 | AF8: 41832.91
A9: - Hardware | B9: 149334.28 | C9: 196996.13 | D9: 255328.76 | E9: 253847.11 | F9: 245877.15 | G9: 261791.01 | H9: 260606.57 | I9: 275829.07 | J9: 280379.12 | K9: 424524.39 | L9: 402025.24 | M9: 358150.47 | N9: 299561.08 | O9: 221486.18 | P9: 179171.36 | Q9: 146855.6 | R9: 100184.35 | S9: 116790.63 | T9: 108506.84 | U9: 84624.02 | V9: 42373.65 | W9: 35993.85 | X9: 24809.13 | Y9: 21421.95 | Z9: 30855.55 | AA9: 20716.5 | AB9: 18568.75 | AC9: =17323.05+239+299 -> 17861.05 | AD9: =19252.9+299 -> 19551.9 | AE9: =28273.55+299 -> 28572.55 | AF9: =26417.48+598+239 -> 27254.48
A10: - Add-ons | B10: 12108.92 | C10: 14314.12 | D10: 17773.14 | E10: 15874.79 | F10: 15079.85 | G10: 17556.59 | H10: 24025.23 | I10: 28702 | J10: 30069.98 | K10: 49273.65 | L10: 37410.41 | M10: 25314.27 | N10: 20554.11 | O10: 11275.97 | P10: 8461.89 | Q10: 9696 | R10: 6201.55 | S10: 6067.77 | T10: 5546.06 | U10: 4989.98 | V10: 3309.05 | W10: 3340.65 | X10: 2616.87 | Y10: 3306.6 | Z10: 9404.45 | AA10: 10747.1 | AB10: 8125.4 | AC10: =5196.65+1996.25+599+321+58 -> 8170.9 | AD10: =6059.75+2530.9+941.15+559.85+148.5 -> 10240.15 | AE10: =5708.6+2631.9+616.7+643.5+220.85+31 -> 9852.55 | AF10: =4416.96+2821.43+1104.64+910.7+314 -> 9567.73
A11: - Merch | B11: 161 | C11: 238.99 | D11: 255.97 | E11: 49.89 | F11: 1934.95 | G11: 539.98 | H11: 335.15 | I11: 616.5 | J11: 642.95 | K11: 689.48 | L11: 768.94 | M11: 686.08 | N11: 608.47 | O11: 358.15 | P11: 434.98 | Q11: 266 | R11: 187.15 | S11: 304 | T11: 152.99 | U11: 279.97 | V11: 76 | W11: 86.99 | X11: 38 | Y11: 35.15 | Z11: 139.99 | AA11: 114 | AB11: 47 | AC11: =19+19 -> 38 | AD11: =38+19 -> 57 | AE11: =19+19 -> 38 | AF11: =33+22.99 -> 55.99
A12: - Taxes | B12: 10363.99 | C12: 13501.37 | D12: 17959.71 | E12: 17144.73 | F12: 18318 | G12: 18516.25 | H12: 18944.96 | I12: 19817.88 | J12: 20866.36 | K12: 31657.44 | L12: 28358.84 | M12: 25119.76 | N12: 21382.96 | O12: 16023.67 | P12: 12833.31 | Q12: 10854.65 | R12: 7514.01 | S12: 8393.94 | T12: 7929.93 | U12: 5981.52 | V12: 3002.73 | W12: 2619.51 | X12: 1421.43 | Y12: 1464.65 | Z12: 2357.91 | AA12: 1873.53 | AB12: 1709.81 | AC12: 1675.83 | AD12: 1760.25 | AE12: 2373.49 | AF12: 2279.72
A13: - Shipping | B13: 10800 | C13: 14690 | D13: 18030 | E13: 18385 | F13: 16904.41 | G13: 18820 | H13: 18685 | I13: 19430 | J13: 19695 | K13: 29320 | L13: 29362 | M13: 25250 | N13: 28405 | O13: 29800 | P13: 25650 | Q13: 22925 | R13: 15915 | S13: 18225 | T13: 17145 | U13: 9395 | V13: 2705 | W13: 2405 | X13: 1950 | Y13: 1785 | Z13: 3430 | AA13: 3020 | AB13: 2345 | AC13: 2265 | AD13: 2630 | AE13: 3085 | AF13: 2675
A14: Amazon Revenue | B14: 239 | C14: 0 | D14: 239 | E14: 299 | F14: 0 | G14: 239 | H14: 0 | I14: 0 | J14: 5768 | K14: 11989 | L14: 1326 | M14: 2053 | N14: 1954 | O14: 34227.86 | P14: 5544.82 | Q14: 127117.78 | R14: 224758.56 | S14: 209140.07 | T14: 117053.13 | U14: 67293.78 | V14: 49546.36 | W14: 46242.49 | X14: 42177.68 | Y14: 24710.24 | Z14: 15938 | AA14: 18460 | AB14: 9039 | AC14: =SUM(AC15:AC19) -> 10768.75 | AD14: 7145 | AE14: 9972 | AF14: =SUM(AF15:AF19) -> 8822.31
A15: - Hardware | B15: 1634.99 | C15: 0 | D15: 239 | E15: 299 | F15: 0 | G15: 0 | H15: 239 | I15: 0 | J15: 2980.24 | K15: 16438.67 | L15: 1625 | M15: 1551.11 | N15: 3019.55 | O15: 12871.26 | P15: 28491.73 | Q15: 79480.27 | R15: 235448.23 | S15: 189222.93 | T15: 173616.13 | U15: 73448.75 | V15: 59661.41 | W15: 49452.96 | X15: 45011.58 | Y15: 27065.29 | Z15: 17566.57 | AA15: 17651 | AB15: 7410.12 | AC15: 9221.68 | AD15: 6276.56 | AE15: 10357.68 | AF15: 8140.56
A16: - Add-ons | B16: 0 | C16: 0 | D16: 0 | E16: 0 | F16: 0 | G16: 0 | H16: 0 | I16: 0 | J16: 87 | K16: 29 | L16: 0 | M16: 29 | N16: 0 | O16: 0 | P16: 116 | Q16: 348 | R16: 1503.12 | S16: 1213.12 | T16: 1300.12 | U16: 775.68 | V16: 403.56 | W16: 493 | X16: 662.12 | Y16: 551 | Z16: 2141.12 | AA16: 2607.56 | AB16: 1938.12 | AC16: 804.68 | AD16: 29 | AE16: 58 | AF16: 87
A17: - Tax | B17: 134.64 | C17: 0 | D17: 0 | E17: 17.94 | F17: 0 | G17: 0 | H17: 13.15 | I17: 0 | J17: 202.17 | K17: 1189.4 | L17: 105.88 | M17: 114.74 | N17: 184.35 | O17: 838.71 | P17: 2028.05 | Q17: 5562.66 | R17: 16776.52 | S17: 13401.35 | T17: 12115.3 | U17: 5148.21 | V17: 4235.57 | W17: 3680.14 | X17: 3124.88 | Y17: 1949.06 | Z17: 1268.29 | AA17: 1433.27 | AB17: 690.4 | AC17: 740.89 | AD17: 426.66 | AE17: 703.83 | AF17: 590.01
A18: - Shipping | B18: 0 | C18: 0 | D18: 0 | E18: 0 | F18: 0 | G18: 0 | H18: 0 | I18: 0 | J18: 0.32 | K18: 7.23 | L18: 0 | M18: 0.16 | N18: 14.06 | O18: 7.23 | P18: 7.23 | Q18: 61.39 | R18: 100.34 | S18: 135.68 | T18: 91.83 | U18: 10.82 | V18: 26.4 | W18: 26.56 | X18: 51.76 | Y18: 14.14 | Z18: 7.63 | AA18: 9.98 | AB18: 13.84 | AC18: 0.48 | AD18: 7.07 | AE18: 0.24 | AF18: 0.08
A19: - Gift Wrap | B19: 0 | C19: 0 | D19: 0 | E19: 0 | F19: 0 | G19: 0 | H19: 0 | I19: 0 | J19: 14.15 | K19: 27.45 | L19: 0 | M19: 0.34 | N19: 0.17 | O19: 5 | P19: 13.98 | Q19: 68.54 | R19: 325.68 | S19: 210.81 | T19: 229.78 | U19: 71.26 | V19: 65.58 | W19: 108.46 | X19: 81.69 | Y19: 40.75 | Z19: 37.28 | AA19: 18.98 | AB19: 5.17 | AC19: 1.02 | AD19: 4.66 | AE19: 9.49 | AF19: 4.66
A20: Digital Marketplaces Revenue | B20: =SUM(B23,B22,B21) -> 2694.94 | C20: =SUM(C23,C22,C21) -> 0 | D20: =SUM(D23,D22,D21) -> 2367.97 | E20: =SUM(E23,E22,E21) -> 921.99 | F20: =SUM(F23,F22,F21) -> 582.99 | G20: =SUM(G23,G22,G21) -> 770 | H20: =SUM(H23,H22,H21) -> 1806 | I20: =SUM(I23,I22,I21) -> 4952.97 | ... AF20: =SUM(AF23,AF22,AF21) -> 0
A21: Rachio | B21: 1799.94 | C21: 0 | D21: 899.97 | E21: 299.99 | F21: 299.99 | G21: 0 | H21: 0 | I21: 899.97 | J21: 1079.96 | K21: 1999.96 | L21: 599.98 | M21: 32338.91 | N21: 1999.96 | O21: 0 | P21: 0 | Q21: 899.97 | R21: 1999.96 | S21: 599.98 | T21: =299.99+299.99 -> 599.98 | U21: 0 | V21: 0 | W21: 0 | X21: 0 | Y21: 0 | Z21: 0 | AA21: 0 | AB21: 0 | AC21: 0 | AD21: 0 | AE21: 0 | AF21: 0
A22: Weatherflow | H22: 1115 | I22: 3744 | J22: 0 | K22: 199 | L22: 199 | M22: 1115 | N22: =199+199+239 -> 637 | O22: 0 | P22: 0 | Q22: 0 | R22: 239 | S22: 0 | T22: 0 | U22: 0 | V22: 0 | W22: 0 | X22: 0 | Y22: 0 | Z22: 0 | AA22: 0 | AB22: 0 | AC22: 0 | AD22: 0 | AE22: 0 | AF22: 0
A23: IndieGoGo | B23: 895 | C23: 0 | D23: 1468 | E23: 622 | F23: 283 | G23: 770 | H23: 691 | I23: 309 | J23: 283 | K23: 612 | L23: 951 | M23: 612 | N23: 214 | O23: 214 | P23: 698 | Q23: 981 | R23: 0 | S23: 299 | T23: 283 | U23: 204 | V23: 566 | W23: 0 | X23: =698+299+204+283 -> 1484 | Y23: =283+698 -> 981 | Z23: 0 | AA23: 1468 | AB23: 418 | AC23: 2607 | AD23: 0 | AE23: 1830 | AF23: 0
A24: Total Revenue | B24: =SUM(B8+B14+B20) -> 185702.13 | C24: =SUM(C8+C14+C20) -> 239740.61 | D24: =SUM(D8+D14+D20) -> 311954.55 | E24: =SUM(E8+E14+E20) -> 306522.51 | F24: =SUM(F8+F14+F20) -> 298697.35 | G24: =SUM(G8+G14+G20) -> 318232.83 | H24: =SUM(H8+H14+H20) -> 324402.91 | I24: =SUM(I8+I14+I20) -> 349348.42 | ... AF24: =SUM(AF8+AF14+AF20) -> 50655.22
A26: B2B Revenue
A27: Best Buy | B27: =SUM(B28:B29) -> 21396.763 | C27: =SUM(C28:C29) -> 24580.963 | D27: =SUM(D28:D29) -> 36712.765 | E27: =SUM(E28:E29) -> 31395.151 | F27: =SUM(F28:F29) -> 35439.085 | G27: =SUM(G28:G29) -> 40246.165 | H27: =SUM(H28:H29) -> 38463.013 | I27: =SUM(I28:I29) -> 43812.469 | ... AF27: =SUM(AF28:AF29) -> 4107.618
A28: - Hardware | B28: 20159 | C28: 23159 | D28: 34589 | E28: 29579 | F28: 33389 | G28: 37918 | H28: 36238 | I28: 41278 | J28: 47308 | K28: 89948 | L28: 82077 | M28: 79197 | N28: 52271 | O28: 43490 | P28: 55159 | Q28: 62788 | R28: 37190 | S28: 8713 | T28: 7020 | U28: 3720 | V28: 5250 | W28: 2760 | X28: 2640 | Y28: 3570 | Z28: 1620 | AA28: 0 | AB28: 1560 | AC28: 0 | AD28: 1890 | AE28: 0 | AF28: 3870
A29: - Tax | B29: =B28*'Data - P&L'!$U$3 -> 1237.7626 | C29: =C28*'Data - P&L'!$U$3 -> 1421.9626 | D29: =D28*'Data - P&L'!$U$3 -> 2123.7646 | E29: =E28*'Data - P&L'!$U$3 -> 1816.1506 | F29: =F28*'Data - P&L'!$U$3 -> 2050.0846 | G29: =G28*'Data - P&L'!$U$3 -> 2328.1652 | H29: =H28*'Data - P&L'!$U$3 -> 2225.0132 | I29: =I28*'Data - P&L'!$U$3 -> 2534.4692 | ... AF29: =AF28*'Data - P&L'!$U$3 -> 237.618
A30: Total Revenue | B30: =B27 -> 21396.763 | C30: =C27 -> 24580.963 | D30: =D27 -> 36712.765 | E30: =E27 -> 31395.151 | F30: =F27 -> 35439.085 | G30: =G27 -> 40246.165 | H30: =H27 -> 38463.013 | I30: =I27 -> 43812.469 | ... AF30: =AF27 -> 4107.618
A32: App Revenue
A33: - Google Store | B33: ='APP - P&L'!B90 -> 181.381 | C33: ='APP - P&L'!C90 -> 255.6225 | D33: ='APP - P&L'!D90 -> 292.136 | E33: ='APP - P&L'!E90 -> 70.9675 | F33: ='APP - P&L'!F90 -> 170.7475 | G33: ='APP - P&L'!G90 -> 203.15 | H33: ='APP - P&L'!H90 -> 231.9495 | I33: ='APP - P&L'!I90 -> 333.66 | ... AF33: ='APP - P&L'!AF90 -> 1708.84
A34: - Apple Store | B34: ='APP - P&L'!B91 -> 1185.4833 | C34: ='APP - P&L'!C91 -> 1597.4964 | D34: ='APP - P&L'!D91 -> 1216.7348 | E34: ='APP - P&L'!E91 -> 894.14925 | F34: ='APP - P&L'!F91 -> 721.3849 | G34: ='APP - P&L'!G91 -> 875.82072 | H34: ='APP - P&L'!H91 -> 859.20913 | I34: ='APP - P&L'!I91 -> 1066.7317 | ... AF34: ='APP - P&L'!AF91 -> 7330.7439
A35: - Comission | B35: ='APP - P&L'!B67 -> 550.20612 | C35: ='APP - P&L'!C67 -> 751.50596 | D35: ='APP - P&L'!D67 -> 583.64179 | E35: ='APP - P&L'!E67 -> 405.13361 | F35: ='APP - P&L'!F67 -> 349.27174 | G35: ='APP - P&L'!G67 -> 418.95888 | H35: ='APP - P&L'!H67 -> 423.08727 | I35: ='APP - P&L'!I67 -> 532.53499 | ... AF35: ='APP - P&L'!AF67 -> 3454.026
A36: - Tax | B36: ='APP - P&L'!B68 -> 30.18 | C36: ='APP - P&L'!C68 -> 51.52 | D36: ='APP - P&L'!D68 -> 25.14 | E36: ='APP - P&L'!E68 -> 22.67 | F36: ='APP - P&L'!F68 -> 30.31 | G36: ='APP - P&L'!G68 -> 18.1 | H36: ='APP - P&L'!H68 -> 46.98 | I36: ='APP - P&L'!I68 -> 42.39 | ... AF36: ='APP - P&L'!AF68 -> 25.01
A37: Total Revenue | B37: =sum(B33:B36) -> 1947.2504 | C37: =sum(C33:C36) -> 2656.1449 | D37: =sum(D33:D36) -> 2117.6526 | E37: =sum(E33:E36) -> 1392.9204 | F37: =sum(F33:F36) -> 1271.7141 | G37: =sum(G33:G36) -> 1516.0296 | H37: =sum(H33:H36) -> 1561.2259 | I37: =sum(I33:I36) -> 1975.3166 | ... AF37: =sum(AF33:AF36) -> 12518.62
A39: DTC Orders | B39: 660 | C39: 896 | D39: 1136 | E39: 1126 | F39: 1163 | G39: 1205 | H39: 1190 | I39: 1260 | J39: 1278 | K39: 1894 | L39: 1857 | M39: 1617 | N39: 1320 | O39: 897 | P39: 677 | Q39: 570 | R39: 397 | S39: 454 | T39: 412 | U39: 342 | V39: 179 | W39: 156 | X39: 116 | Y39: 118 | Z39: 248 | AA39: 234 | AB39: 191 | AC39: 187 | AD39: 214 | AE39: 231 | AF39: 196
A40: - Hardware (units sold) | B40: 631 | C40: 844 | D40: 1107 | E40: 1107 | F40: 1062 | G40: 1134 | H40: 1138 | I40: 1198 | J40: 1211 | K40: 1819 | L40: 1717 | M40: 1525 | N40: 1237 | O40: 834 | P40: 626 | Q40: 506 | R40: 350 | S40: 402 | T40: 378 | U40: 304 | V40: 156 | W40: 131 | X40: 91 | Y40: 79 | Z40: 114 | AA40: 72 | AB40: 67 | AC40: 64 | AD40: 71 | AE40: 105 | AF40: 101
A41: - Add-ons (units sold) | B41: 390 | C41: 517 | D41: 626 | E41: 579 | F41: 539 | G41: 635 | H41: 789 | I41: 909 | J41: 973 | K41: 1597 | L41: 1238 | M41: 858 | N41: 694 | O41: 549 | P41: 505 | Q41: 427 | R41: 313 | S41: 307 | T41: 290 | U41: 242 | V41: 164 | W41: 155 | X41: 118 | Y41: 126 | Z41: 285 | AA41: 334 | AB41: 245 | AC41: 252 | AD41: 300 | AE41: 285 | AF41: 303
A42: - Merch (units sold) | B42: 397 | C42: 580 | D42: 745 | E42: 703 | F42: 718 | G42: 657 | H42: 248 | I42: 31 | J42: 30 | K42: 33 | L42: 37 | M42: 35 | N42: 27 | O42: 18 | P42: 20 | Q42: 14 | R42: 10 | S42: 16 | T42: 7 | U42: 13 | V42: 4 | W42: 4 | X42: 2 | Y42: 2 | Z42: 6 | AA42: 6 | AB42: 3 | AC42: 2 | AD42: 3 | AE42: 2 | AF42: 2
A43: Amazon Orders | B43: 1 | C43: 0 | D43: 0 | E43: 1 | F43: 0 | G43: 1 | H43: 0 | I43: 0 | J43: 26 | K43: 43 | L43: 8 | M43: 7 | N43: 8 | O43: 114 | P43: 25 | Q43: 433 | R43: 782 | S43: 718 | T43: 428 | U43: 246 | V43: 180 | W43: 166 | X43: 159 | Y43: 105 | Z43: 150 | AA43: 146 | AB43: 91 | AC43: 37 | AD43: 23 | AE43: 37 | AF43: 27
A44: - Hardware (units sold) | B44: 1 | C44: 0 | D44: 1 | E44: 1 | F44: 0 | G44: 1 | H44: 0 | I44: 0 | J44: 23 | K44: 42 | L44: 9 | M44: 6 | N44: 8 | O44: 117 | P44: 20 | Q44: 423 | R44: 742 | S44: 693 | T44: 398 | U44: 223 | V44: 169 | W44: 156 | X44: =132+8 -> 140 | Y44: =77+3+2+1 -> 83 | Z44: 71 | AA44: 56 | AB44: 24
A45: - Add-ons (units sold) | B45: 0 | C45: 0 | D45: 0 | E45: 0 | F45: 0 | G45: 0 | H45: 0 | I45: 0 | J45: 3 | K45: 1 | L45: 0 | M45: 1 | N45: 0 | O45: 1 | P45: 5 | Q45: 18 | R45: 53 | S45: 43 | T45: 34 | U45: 25 | V45: 12 | W45: 15 | X45: 23 | Y45: 24 | Z45: 79 | AA45: 91 | AB45: 67
A46: Digital Marketplaces Orders | B46: =SUM(B47:B49) -> 8 | C46: =SUM(C47:C49) -> 0 | D46: =SUM(D47:D49) -> 6 | E46: =SUM(E47:E49) -> 4 | F46: =SUM(F47:F49) -> 2 | G46: =SUM(G47:G49) -> 3 | H46: =SUM(H47:H49) -> 8 | I46: =SUM(I47:I49) -> 20 | ... AF46: =SUM(AF47:AF49) -> 0
A47: Rachio Orders | B47: 4 | C47: 0 | D47: 3 | E47: 1 | F47: 1 | G47: 0 | H47: 0 | I47: 3 | J47: 4 | K47: 4 | L47: 2 | M47: 104 | N47: 4 | O47: 0 | P47: 0 | Q47: 3 | R47: 4 | S47: 2 | T47: 2 | U47: 0 | V47: 0 | W47: 0 | X47: 0 | Y47: 0 | Z47: 0 | AA47: 0 | AB47: 0 | AC47: 0 | AD47: 0 | AE47: 0 | AF47: 0
A48: Weatherflow Orders | B48: 0 | C48: 0 | D48: 0 | E48: 0 | F48: 0 | G48: 0 | H48: 5 | I48: 16 | J48: 0 | K48: 1 | L48: 1 | M48: 5 | N48: 3 | O48: 0 | P48: 0 | Q48: 0 | R48: 1 | S48: 0 | T48: 0 | U48: 0 | V48: 0 | W48: 0 | X48: 0 | Y48: 0 | Z48: 0 | AA48: 0 | AB48: 0 | AC48: 0 | AD48: 0 | AE48: 0 | AF48: 0
A49: IndieGoGo Orders | B49: 4 | C49: 0 | D49: 3 | E49: 3 | F49: 1 | G49: 3 | H49: 3 | I49: 1 | J49: 1 | K49: 3 | L49: 4 | M49: 3 | N49: 1 | O49: 1 | P49: 1 | Q49: 2 | R49: 0 | S49: 1 | T49: 1 | U49: 1 | V49: 2 | W49: 0 | X49: 4 | Y49: 2 | Z49: 0 | AA49: 4 | AB49: 2 | AC49: 5 | AD49: 0 | AE49: 5 | AF49: 0
A50: Total Orders | B50: =SUM(B39+B43+B47+B48+B49) -> 669 | C50: =SUM(C39+C43+C47+C48+C49) -> 896 | D50: =SUM(D39+D43+D47+D48+D49) -> 1142 | E50: =SUM(E39+E43+E47+E48+E49) -> 1131 | F50: =SUM(F39+F43+F47+F48+F49) -> 1165 | G50: =SUM(G39+G43+G47+G48+G49) -> 1209 | H50: =SUM(H39+H43+H47+H48+H49) -> 1198 | I50: =SUM(I39+I43+I47+I48+I49) -> 1280 | ... AF50: =SUM(AF39+AF43+AF47+AF48+AF49) -> 223
A52: B2B Orders
A53: - Best Buy | B53: 84 | C53: 96 | D53: 143 | E53: 123 | F53: 139 | G53: 158 | H53: 151 | I53: 172 | J53: 197 | K53: 375 | L53: 342 | M53: 330 | N53: 204 | O53: 144 | P53: 208 | Q53: 240 | R53: 145 | S53: 34 | T53: 28 | U53: 15 | V53: 20 | W53: 11 | X53: 9 | Y53: 14 | Z53: 6 | AA53: 0 | AB53: 2 | AC53: 0 | AD53: 4 | AE53: 0 | AF53: 12
A54: Total Orders | B54: =B53 -> 84 | C54: =C53 -> 96 | D54: =D53 -> 143 | E54: =E53 -> 123 | F54: =F53 -> 139 | G54: =G53 -> 158 | H54: =H53 -> 151 | I54: =I53 -> 172 | ... AF54: =AF53 -> 12
A56: App Orders
A57: - Google Store | B57: ='APP - P&L'!B17 -> 8 | C57: ='APP - P&L'!C17 -> 14 | D57: ='APP - P&L'!D17 -> 17 | E57: ='APP - P&L'!E17 -> 9 | F57: ='APP - P&L'!F17 -> 10 | G57: ='APP - P&L'!G17 -> 13 | H57: ='APP - P&L'!H17 -> 14 | I57: ='APP - P&L'!I17 -> 18 | ... AF57: ='APP - P&L'!AF17 -> 63
A58: - Apple Store | B58: ='APP - P&L'!B14 -> 75 | C58: ='APP - P&L'!C14 -> 99 | D58: ='APP - P&L'!D14 -> 87 | E58: ='APP - P&L'!E14 -> 59 | F58: ='APP - P&L'!F14 -> 60 | G58: ='APP - P&L'!G14 -> 61 | H58: ='APP - P&L'!H14 -> 62 | I58: ='APP - P&L'!I14 -> 78 | ... AF58: ='APP - P&L'!AF14 -> 360
A59: Total Orders | B59: =sum(B57:B58) -> 83 | C59: =sum(C57:C58) -> 113 | D59: =sum(D57:D58) -> 104 | E59: =sum(E57:E58) -> 68 | F59: =sum(F57:F58) -> 70 | G59: =sum(G57:G58) -> 74 | H59: =sum(H57:H58) -> 76 | I59: =sum(I57:I58) -> 96 | ... AF59: =sum(AF57:AF58) -> 423
A60: Meta Spend EUR | B60: 19987.92 | C60: 29066.93 | D60: 48955.56 | E60: 59442.98 | F60: =53661.84+84.54 -> 53746.38 | G60: =57042.76+140.26 -> 57183.02 | H60: =63746.94+140.86 -> 63887.8 | I60: =55631.41+149.66 -> 55781.07 | J60: =48239.51+161.56 -> 48401.07 | K60: =61791.96+161.99 -> 61953.95 | L60: =64682.79+145.12 -> 64827.91 | M60: =66065.23+147.58+15.02 -> 66227.83 | N60: =55877.79+122.9+19.75 -> 56020.44 | O60: =39006.84+152.15+19.81 -> 39178.8 | P60: =35957.76+152.52+26.02 -> 36136.3 | Q60: =29599.77+167.71+27.71 -> 29795.19 | R60: =26133.17+150.68+ 27.43 -> 26311.28 | S60: =24272.71+56.83+26.13 -> 24355.67 | T60: =24442.78+14.43 -> 24457.21 | U60: =21825.94+9.87 -> 21835.81 | V60: =19625.79+15.95 -> 19641.74 | W60: =8894.08+13.62 -> 8907.7 | X60: =3841.69+10.33 -> 3852.02 | Y60: =4189.65+9.6 -> 4199.25 | Z60: =3723.69+9.87 -> 3733.56 | AA60: =4232.34+4.44 -> 4236.78 | AB60: 4265.25 | AC60: 4740.05 | AD60: 5043.11 | AE60: 5072.63 | AF60: 5376.15
A61: Currency rate | B61: 1.0893 | C61: 1.0886 | D61: 1.0887 | E61: 1.0836 | F61: 1.0793 | G61: 1.0765 | H61: 1.0791 | I61: 1.0774 | J61: 1.0774 | K61: 1.0765 | L61: 1.0764 | M61: 1.0799 | N61: 1.0884 | O61: 1.0994 | P61: 1.0907 | Q61: 1.0909 | R61: 1.0895 | S61: 1.0923 | T61: 1.0981 | U61: 1.0943 | V61: 1.1006 | W61: 1.1026 | X61: 1.1026 | Y61: 1.1025 | Z61: 1.1019 | AA61: 1.1042 | AB61: 1.1108 | AC61: 1.1067 | AD61: 1.1055 | AE61: 1.1055 | AF61: 1.1038
A62: Meta Spend | B62: =B60*B61 -> 21772.841 | C62: =C60*C61 -> 31642.26 | D62: =D60*D61 -> 53297.918 | E62: =E60*E61 -> 64412.413 | F62: =F60*F61 -> 58008.468 | G62: =G60*G61 -> 61557.521 | H62: =H60*H61 -> 68941.325 | I62: =I60*I61 -> 60098.525 | ... AF62: =AF60*AF61 -> 5934.1944
A63: Google Spend | B63: 5447.08 | C63: 5717.82 | D63: 5852.64 | E63: 6168.03 | F63: 7755.94 | G63: 12282.57 | H63: 15666.65 | I63: 20469 | J63: 20366.77 | K63: 17166.67 | L63: 16563.17 | M63: 15755.02 | N63: 14856.16 | O63: 16720.89 | P63: 14270.56 | Q63: 10953.28 | R63: 10047.78 | S63: 8975.68 | T63: 9820.89 | U63: 9843.64 | V63: 6432.76 | W63: 6633.97 | X63: 5721.33 | Y63: 5604.11 | Z63: 7159.58 | AA63: 2731.87 | AB63: 2427.83 | AC63: 1957.6 | AD63: 2103.31 | AE63: 2706.23 | AF63: 2034.48
A64: Bing Spend | B64: 315.1 | C64: 266.17 | D64: 288.53 | E64: 311.83 | F64: 307.19 | G64: 1035.45 | H64: 1061.59 | I64: 1086.12 | J64: 1092.08 | K64: 1087.96 | L64: 1095.88 | M64: 1089.86 | N64: 1086.94 | O64: 932.03 | P64: 909.64 | Q64: 399.53 | R64: 431.85 | S64: 791.56 | T64: 934.3 | U64: 1168.87 | V64: 1134.17 | W64: 849.96 | X64: 523.85 | Y64: 431.27 | Z64: 1131.11 | AA64: 1498.04 | AB64: 535.28 | AC64: 300.48 | AD64: 207.52 | AE64: 209.57 | AF64: 181.91
A65: TikTok Spend | B65: 0 | C65: 0 | D65: 0 | E65: 0 | F65: 0 | G65: 0 | H65: 0 | I65: 0 | J65: 0 | K65: 0 | L65: 0 | M65: 0 | N65: 875.5 | O65: 1856.35 | P65: 1770.38 | Q65: 1496.42 | R65: 1503.62 | S65: 684.27 | T65: 0 | U65: 0 | V65: 0 | W65: 0 | X65: 0 | Y65: 0 | Z65: 0 | AA65: 0 | AB65: 0 | AC65: 0 | AD65: 0 | AE65: 0 | AF65: 0
A66: Amazon Spend | B66: 0 | C66: 0 | D66: 0 | E66: 0 | F66: 0 | G66: 0 | H66: 0 | I66: 0 | J66: 2671.81 | K66: 4133.9 | L66: 2423.84 | M66: 211.46 | N66: 0 | O66: 5347.85 | P66: 12240.27 | Q66: 22215.58 | R66: 27930.19 | S66: 21925.52 | T66: 20231.1 | U66: 17405.64 | V66: 13665.21 | W66: 9313.72 | X66: 8206.83 | Y66: 7390.52 | Z66: 3203.85 | AA66: 7333.15 | AB66: 3045.36 | AC66: 3504.59 | AD66: 2492.21 | AE66: 4029.8 | AF66: 2268.23
A67: Nextdoor Spend | B67: 0 | C67: 0 | D67: 0 | E67: 0 | F67: 0 | G67: 0 | H67: 0 | I67: 0 | J67: 0 | K67: 0 | L67: 0 | M67: 0 | N67: 0 | O67: 0 | P67: 0 | Q67: 0 | R67: 0 | S67: 0 | T67: 0 | U67: 0 | V67: 0 | W67: 0 | X67: 0 | Y67: 0 | Z67: 0 | AA67: 0 | AB67: 0 | AC67: 0 | AD67: 0 | AE67: 0 | AF67: 0
A68: IndieGoGo Spend | B68: 0 | C68: 0 | D68: 0 | E68: 0 | F68: 0 | G68: 0 | H68: 0 | I68: 0 | J68: 0 | K68: 0 | L68: 0 | M68: 0 | N68: 0 | O68: 0 | P68: 0 | Q68: 0 | R68: 0 | S68: 0 | T68: 0 | U68: 0 | V68: 0 | W68: 0 | X68: 0 | Y68: 0 | Z68: 0 | AA68: 0 | AB68: 0 | AC68: 0 | AD68: 0 | AE68: 0 | AF68: 0
A69: Affiliate Fees | B69: 0 | C69: 0 | D69: 69.5 | E69: 110.85 | F69: 35.97 | G69: 0 | H69: 0 | I69: 0 | J69: 0 | K69: 57.59 | L69: 0 | M69: 109.98 | N69: 92.5 | O69: 68.5 | P69: 0 | Q69: 79.64 | R69: 0 | S69: 0 | T69: 57.66 | U69: 0 | V69: 0 | W69: 0 | X69: 0 | Y69: 0 | Z69: 0 | AA69: 0 | AB69: 0 | AC69: 64.83 | AD69: 0 | AE69: 0 | AF69: 93.85
A70: Rachio Fees | B70: =B21*0.2 -> 359.988 | C70: =C21*0.2 -> 0 | D70: =D21*0.2 -> 179.994 | E70: =E21*0.2 -> 59.998 | F70: =F21*0.2 -> 59.998 | G70: =G21*0.2 -> 0 | H70: =H21*0.2 -> 0 | I70: =I21*0.2 -> 179.994 | ... AF70: =AF21*0.2 -> 0
A71: Weatherflow Fees | B71: =B22*0.15 -> 0 | C71: =C22*0.15 -> 0 | D71: =D22*0.15 -> 0 | E71: =E22*0.15 -> 0 | F71: =F22*0.15 -> 0 | G71: =G22*0.15 -> 0 | H71: =H22*0.15 -> 167.25 | I71: =I22*0.15 -> 561.6 | ... AF71: =AF22*0.15 -> 0
A72: Total DTC Spend | B72: =B62+B63+B64+B65+B67+B69 -> 27535.021 | C72: =C62+C63+C64+C65+C67+C69 -> 37626.25 | D72: =D62+D63+D64+D65+D67+D69 -> 59508.588 | E72: =E62+E63+E64+E65+E67+E69 -> 71003.123 | F72: =F62+F63+F64+F65+F67+F69 -> 66107.568 | G72: =G62+G63+G64+G65+G67+G69 -> 74875.541 | H72: =H62+H63+H64+H65+H67+H69 -> 85669.565 | I72: =I62+I63+I64+I65+I67+I69 -> 81653.645 | ... AF72: =AF62+AF63+AF64+AF65+AF67+AF69 -> 8244.4344
A73: Total Spend | B73: =SUM(B62:B71) -> 27895.009 | C73: =SUM(C62:C71) -> 37626.25 | D73: =SUM(D62:D71) -> 59688.582 | E73: =SUM(E62:E71) -> 71063.121 | F73: =SUM(F62:F71) -> 66167.566 | G73: =SUM(G62:G71) -> 74875.541 | H73: =SUM(H62:H71) -> 85836.815 | I73: =SUM(I62:I71) -> 82395.239 | ... AF73: =SUM(AF62:AF71) -> 10512.664
A75: App Spend
A76: Meta Spend
A77: Apple Spend | B77: 14.9 | C77: 19.59 | D77: 28.73 | E77: 17.62 | F77: 15.45 | G77: 11.97 | H77: 11.38 | I77: 17.66 | J77: 25.97 | K77: 27.57 | L77: 32.15 | M77: 15.13 | N77: 24.05 | O77: 26.7 | P77: 27.03 | Q77: 39.16 | R77: 63.07 | S77: 31.66 | T77: 46.99 | U77: 44.7 | V77: 51.41 | W77: 51.47 | X77: 70.06 | Y77: 120.85 | Z77: 14.72 | AA77: 0 | AB77: 0 | AC77: 0 | AD77: 120.35 | AE77: 120.84 | AF77: 121.62
A78: Total APP Spend | B78: =SUM(B76:B77) -> 14.9 | C78: =SUM(C76:C77) -> 19.59 | D78: =SUM(D76:D77) -> 28.73 | E78: =SUM(E76:E77) -> 17.62 | F78: =SUM(F76:F77) -> 15.45 | G78: =SUM(G76:G77) -> 11.97 | H78: =SUM(H76:H77) -> 11.38 | I78: =SUM(I76:I77) -> 17.66 | ... AF78: =SUM(AF76:AF77) -> 121.62
A80: Blended ROAS | B80: =B24/B73 -> 6.6571812 | C80: =C24/C73 -> 6.3716318 | D80: =D24/D73 -> 5.2263689 | E80: =E24/E73 -> 4.3133837 | F80: =F24/F73 -> 4.5142563 | G80: =G24/G73 -> 4.2501573 | H80: =H24/H73 -> 3.7792981 | I80: =I24/I73 -> 4.2399103 | ... AF80: =AF24/AF73 -> 4.8184949
A81: wROAS | B81: =B8/B72 -> 6.6376629 | C81: =C8/C72 -> 6.3716318 | D81: =D8/D72 -> 5.1983687 | E81: =E8/E72 -> 4.2998323 | F81: =F8/F72 -> 4.5095345 | G81: =G8/G72 -> 4.2366816 | H81: =H8/H72 -> 3.7655953 | I81: =I8/I72 -> 4.2177597 | ... AF81: =AF8/AF72 -> 5.0740788
A82: aROAS | B82: =B14/B66 -> #DIV/0! | C82: =C14/C66 -> #DIV/0! | D82: =D14/D66 -> #DIV/0! | E82: =E14/E66 -> #DIV/0! | F82: =F14/F66 -> #DIV/0! | G82: =G14/G66 -> #DIV/0! | H82: =H14/H66 -> #DIV/0! | I82: =I14/I66 -> #DIV/0! | ... AF82: =AF14/AF66 -> 3.889513
A83: appROAS | B83: =B32/B78 -> 0 | C83: =C32/C78 -> 0 | D83: =D32/D78 -> 0 | E83: =E32/E78 -> 0 | F83: =F32/F78 -> 0 | G83: =G32/G78 -> 0 | H83: =H32/H78 -> 0 | I83: =I32/I78 -> 0 | ... AF83: =AF32/AF78 -> 0
A85: Blended CAC | B85: =B73/B50 -> 41.696576 | C85: =C73/C50 -> 41.993583 | D85: =D73/D50 -> 52.266709 | E85: =E73/E50 -> 62.832114 | F85: =F73/F50 -> 56.796194 | G85: =G73/G50 -> 61.931796 | H85: =H73/H50 -> 71.650096 | I85: =I73/I50 -> 64.37128 | ... AF85: =AF73/AF50 -> 47.141993
A86: wCAC | B86: =B72/B39 -> 41.719729 | C86: =C72/C39 -> 41.993583 | D86: =D72/D39 -> 52.384321 | E86: =E72/E39 -> 63.057836 | F86: =F72/F39 -> 56.842277 | G86: =G72/G39 -> 62.137378 | H86: =H72/H39 -> 71.991231 | I86: =I72/I39 -> 64.80448 | ... AF86: =AF72/AF39 -> 42.063441
A87: aCAC | B87: =B66/B43 -> 0 | C87: =C66/C43 -> #DIV/0! | D87: =D66/D43 -> #DIV/0! | E87: =E66/E43 -> 0 | F87: =F66/F43 -> #DIV/0! | G87: =G66/G43 -> 0 | H87: =H66/H43 -> #DIV/0! | I87: =I66/I43 -> #DIV/0! | ... AF87: =AF66/AF43 -> 84.008519
A88: appCAC | B88: =B78/B56 -> #DIV/0! | C88: =C78/C56 -> #DIV/0! | D88: =D78/D56 -> #DIV/0! | E88: =E78/E56 -> #DIV/0! | F88: =F78/F56 -> #DIV/0! | G88: =G78/G56 -> #DIV/0! | H88: =H78/H56 -> #DIV/0! | I88: =I78/I56 -> #DIV/0! | ... AF88: =AF78/AF56 -> #DIV/0!
A90: Web CR | B90: 0.0278 | C90: 0.0318 | D90: 0.0296 | E90: 0.0279 | F90: 0.03 | G90: 0.0306 | H90: 0.0302 | I90: 0.0283 | J90: 0.0282 | K90: 0.0339 | L90: 0.0355 | M90: 0.0545 | N90: 0.0326 | O90: 0.0294 | P90: 0.0344 | Q90: 0.0244 | R90: 0.0167 | S90: 0.0232 | T90: 0.0289 | U90: 0.0225 | V90: 0.0117 | W90: 0.0129 | X90: 0.0098 | Y90: 0.0107 | Z90: 0.0104 | AA90: 0.0101 | AB90: 0.0104 | AC90: 0.0114 | AD90: 0.0137 | AE90: 0.0056 | AF90: 0.007
A91: Web AOV | B91: =B8/B39 -> 276.9215 | C91: =C8/C39 -> 267.56765 | D91: =D8/D39 -> 272.31301 | E91: =E8/E39 -> 271.13812 | F91: =F8/F39 -> 256.33221 | G91: =G8/G39 -> 263.25629 | H91: =H8/H39 -> 271.08984 | I91: =I8/I39 -> 273.32972 | ... AF91: =AF8/AF39 -> 213.43321
A92: fAOV | B92: 241.88 | C92: 236.28 | D92: 236.46 | E92: 236.77 | F92: 221.49 | G92: 235.76 | H92: 240.77 | I92: 244.68 | J92: 245.21 | K92: 251.52 | L92: 240.29 | M92: 240.2 | N92: 245.47 | O92: 262.48 | P92: 281.11 | Q92: 279.43 | R92: 273.14 | S92: 272.71 | T92: 344.69 | U92: 311.77 | V92: 294.47 | W92: 292.43 | X92: 278.15 | Y92: 250.66 | Z92: 203.25 | AA92: 161.33 | AB92: 174.21 | AC92: 164.02 | AD92: 178.7 | AE92: 195.85 | AF92: 226.34
A93: rAOV | B93: 177.59 | C93: 185.28 | D93: 201.29 | E93: 208.05 | F93: 187.4 | G93: 163.35 | H93: 201.66 | I93: 170.3 | J93: 190.34 | K93: 221.57 | L93: 181.77 | M93: 174.06 | N93: 196.31 | O93: 201.33 | P93: 223.58 | Q93: 214.22 | R93: 198.54 | S93: 247.87 | T93: 235.44 | U93: 221.44 | V93: 181.42 | W93: 162.12 | X93: 168.13 | Y93: 130.31 | Z93: 111.57 | AA93: 125.75 | AB93: 94.26 | AC93: 138.58 | AD93: 95.31 | AE93: 145.07 | AF93: 136.01
A95: Customers
A96: Returning | B96: 0.053 | C96: 0.0502 | D96: 0.0466 | E96: 0.0373 | F96: 0.0361 | G96: 0.0481 | H96: 0.0436 | I96: 0.0443 | J96: 0.0429 | K96: 0.0412 | L96: 0.0576 | M96: 0.042 | N96: 0.0508 | O96: 0.0424 | P96: 0.0576 | Q96: 0.0736 | R96: 0.063 | S96: 0.0813 | T96: 0.062 | U96: 0.042 | V96: 0.03 | W96: 0.032 | X96: 0.112 | Y96: 0.113 | Z96: 0.184 | AA96: 0.152 | AB96: 0.166 | AC96: 0.139 | AD96: 0.224 | AE96: 0.113 | AF96: 0.143
A97: First-time | B97: =1-B96 -> 0.947 | C97: =1-C96 -> 0.9498 | D97: =1-D96 -> 0.9534 | E97: =1-E96 -> 0.9627 | F97: =1-F96 -> 0.9639 | G97: =1-G96 -> 0.9519 | H97: =1-H96 -> 0.9564 | I97: =1-I96 -> 0.9557 | ... T97: =1-T96 -> 0.938 | U97: 0.958 | V97: =1-V96 -> 0.97 | W97: =1-W96 -> 0.968 | X97: =1-X96 -> 0.888 | Y97: =1-Y96 -> 0.887 | Z97: =1-Z96 -> 0.816 | AA97: =1-AA96 -> 0.848 | AB97: =1-AB96 -> 0.834 | AC97: =1-AC96 -> 0.861 | ... AF97: =1-AF96 -> 0.857
B99: 45261 | C99: Goal | D99: % of Goal
A100: Revenue | B100: =SUM(B24:AF24)+B37:AF37 -> 7275533.3 | C100: 4600000 | D100: =B100/C100 -> 1.5816377
A101: Spend | B101: =SUM(B73:AF73)+B78:AF78 -> 1571558.8 | C101: =C100/C102 -> 1150000 | D101: =B101/C101 -> 1.3665729
A102: ROAS | B102: =B100/B101 -> 4.6295012 | C102: 4 | D102: =B102/C102 -> 1.1573753
A103: CAC | B103: =SUM(B73:AF73)/SUM(B50:AF50) -> 59.042863
A104: CR | B104: =IFERROR(__xludf.DUMMYFUNCTION("AVERAGE.WEIGHTED(B90:AE90,B50:AE50)"),0.02876884519208911) -> 0.028768845
A105: AOV | B105: =B100/B108 -> 273.3416
A106: fAOV | B106: =AVERAGE(B92:AF92) -> 243.92
A107: rAOV | B107: =AVERAGE(B93:AF93) -> 177.09419
A108: Orders | B108: =SUM(B50:AF50) -> 26617
A109: Units Sold | B109: ='OLD DTC - P&L'!AG149 +'OLD AMAZON - P&L'!AG33 -> 23484 | C109: =C100/266 -> 17293.233 | D109: =B109/C109 -> 1.3579878
A110: CAC per Unit | B110: =B101/B109 -> 66.920405
A111: First-time customers | B111: =AVERAGE(B97:AF97) -> 0.92181935
A112: Returning customers | B112: =AVERAGE(B96:AF96) -> 0.078180645

Sheet OLD DTC - P&L
A1: DECEMBER | B1: 45261 | C1: 45262 | D1: 45263 | E1: 45264 | F1: 45265 | G1: 45266 | H1: 45267 | I1: 45268 | J1: 45269 | K1: 45270 | L1: 45271 | M1: 45272 | N1: 45273 | O1: 45274 | P1: 45275 | Q1: 45276 | R1: 45277 | S1: 45278 | T1: 45279 | U1: 45280 | V1: 45281 | W1: 45282 | X1: 45283 | Y1: 45284 | Z1: 45285 | AA1: 45286 | AB1: 45287 | AC1: 45288 | AD1: 45289 | AE1: 45290 | AF1: 45291
A2: DAY | B2: FRI | C2: SAT | D2: SUN | E2: MON | F2: TUE | G2: WED | H2: THU | I2: FRI | J2: SAT | K2: SUN | L2: MON | M2: TUE | N2: WED | O2: THU | P2: FRI | Q2: SAT | R2: SUN | S2: MON | T2: TUE | U2: WED | V2: THU | W2: FRI | X2: SAT | Y2: SUN | Z2: MON | AA2: TUE | AB2: WED | AC2: THU | AD2: FRI | AE2: SAT | AF2: SUN
A3: COMMENT
A4: Orders
A5: Meta | B5: 206 | C5: 280 | D5: 458 | E5: 432 | F5: 420 | G5: 435 | H5: 427 | I5: 402 | J5: 412 | K5: 470 | L5: 502 | M5: 444 | N5: 397 | O5: 205 | P5: 179 | Q5: 148 | R5: 86 | S5: 104 | T5: 92 | U5: 79 | V5: 44 | W5: 36 | X5: 10 | Y5: 16 | Z5: 23 | AA5: 23 | AB5: 18 | AG5: =SUM(B5:AF5) -> 6348
A6: Google | B6: 231.51 | C6: 325.87 | D6: 374.82 | E6: 425.33 | F6: 458.35 | G6: 503.02 | H6: 575.12 | I6: 596.03 | J6: 604.87 | K6: 910 | L6: 874.09 | M6: 702.33 | N6: 617.57 | O6: 429.57 | P6: 342.06 | Q6: 300.58 | R6: 199.83 | S6: 215.38 | T6: 192.75 | U6: 139.09 | V6: 69.19 | W6: 64.16 | X6: 55.26 | Y6: 54.96 | Z6: 92.42 | AA6: 77.94 | AB6: 67.72 | AG6: =SUM(B6:AF6) -> 9499.82
A7: TikTok | B7: 0 | C7: 0 | D7: 0 | E7: 0 | F7: 0 | G7: 0 | H7: 0 | I7: 0 | J7: 0 | K7: 0 | L7: 0 | M7: 0 | N7: 0 | O7: 0 | P7: 0 | Q7: 0 | R7: 0 | S7: 0 | T7: 0 | U7: 0 | V7: 0 | W7: 0 | X7: 0 | Y7: 0 | Z7: 0 | AA7: 0 | AB7: 0 | AG7: =SUM(B7:AF7) -> 0
A8: Bing | B8: 34 | C8: 82 | D8: 60 | E8: 56 | F8: 60 | G8: 114 | H8: 80 | I8: 46 | J8: 42 | K8: 74 | L8: 102 | M8: 98 | N8: 88 | O8: 66 | P8: 58 | Q8: 20 | R8: 18 | S8: 28 | T8: 34 | U8: 22 | V8: 20 | W8: 4 | X8: 4 | Y8: 2 | Z8: 24 | AA8: 22 | AB8: 4 | AG8: =SUM(B8:AF8) -> 1262
A9: MNTN TV | AG9: =SUM(B9:AF9) -> 0
A10: Affiliates (Refersion) | B10: 0 | C10: 0 | D10: 1 | E10: 2 | F10: 1 | G10: 0 | H10: 0 | I10: 0 | J10: 0 | K10: 1 | L10: 0 | M10: 2 | N10: 1 | O10: 1 | P10: 0 | Q10: 2 | R10: 0 | S10: 0 | T10: 1 | U10: 0 | V10: 0 | AG10: =SUM(B10:AF10) -> 12
A11: FB (Internal Paid) | AG11: =SUM(B11:AF11) -> 0
A12: FB (EU & UK) | AG12: =SUM(B12:AF12) -> 0
A13: Email | B13: 20 | C13: 13 | D13: 7 | E13: 8 | F13: 80 | G13: 27 | H13: 5 | I13: 9 | J13: 4 | K13: 0 | L13: 50 | M13: 34 | N13: 22 | O13: 13 | P13: 7 | Q13: 9 | R13: 7 | S13: 4 | T13: 3 | U13: 2 | V13: 0 | W13: 0 | X13: 0 | Y13: 1 | Z13: 0 | AA13: 4 | AB13: 4 | AG13: =SUM(B13:AF13) -> 333
A14: Amazon (market place) | AG14: =SUM(B14:AF14) -> 0
A15: All | B15: =SUM(B5:B14) -> 491.51 | C15: =SUM(C5:C14) -> 700.87 | D15: =SUM(D5:D14) -> 900.82 | E15: =SUM(E5:E14) -> 923.33 | F15: =SUM(F5:F14) -> 1019.35 | G15: =SUM(G5:G14) -> 1079.02 | H15: =SUM(H5:H14) -> 1087.12 | I15: =SUM(I5:I14) -> 1053.03 | ... AF15: =SUM(AF5:AF14) -> 0 | AG15: =SUM(B15:AF15) -> 17454.82
A17: Revenue
A18: Meta | B18: 57649.34 | C18: 76414.95 | D18: 124162.72 | E18: 117448.37 | F18: 116744.47 | G18: 122051.85 | H18: 123347.55 | I18: 111376.87 | J18: 119498.37 | K18: 134583.55 | L18: 147597.35 | M18: 122609.88 | N18: 114553.84 | O18: 66058.11 | P18: 62144.27 | Q18: 52453.95 | R18: 30614.63 | S18: 37567.38 | T18: 32925.92 | U18: 25734.3 | V18: 14121.16 | W18: 10454.59 | X18: 2947.41 | Y18: 4149.84 | Z18: 5557.62 | AA18: 3956.94 | AB18: 3713.16 | AG18: =SUM(B18:AF18) -> 1840438.4
A19: Google | B19: 62007.44 | C19: 85401.03 | D19: 99477.28 | E19: 111476.75 | F19: 121975.95 | G19: 132079.46 | H19: 156082.09 | I19: 167023.81 | J19: 166730.04 | K19: 250471.69 | L19: 236778.46 | M19: 191819.32 | N19: 175552.83 | O19: 136761.61 | P19: 113520.41 | Q19: 101737.38 | R19: 64217.13 | S19: 70010.68 | T19: 64102.2 | U19: 41136.92 | V19: 19829.14 | W19: 16993.62 | X19: 14912.11 | Y19: 14331.03 | Z19: 19354.16 | AA19: 13498.26 | AB19: 11458.92 | AG19: =SUM(B19:AF19) -> 2658739.7
A20: TikTok | B20: 0 | C20: 0 | D20: 0 | E20: 0 | F20: 0 | G20: 0 | H20: 0 | I20: 0 | J20: 0 | K20: 0 | L20: 0 | M20: 0 | N20: 0 | O20: 0 | P20: 0 | Q20: 0 | R20: 0 | S20: 0 | T20: 0 | U20: 0 | V20: 0 | W20: 0 | X20: 0 | Y20: 0 | Z20: 0 | AA20: 0 | AB20: 0 | AG20: =SUM(B20:AF20) -> 0
A21: Bing | B21: 4267 | C21: 10291 | D21: 7530 | E21: 7028 | F21: 7530 | G21: 14307 | H21: 10040 | I21: 5773 | J21: 5271 | K21: 9287 | L21: 12801 | M21: 12299 | N21: 11044 | O21: 8283 | P21: 7279 | Q21: 2510 | R21: 2259 | S21: 3514 | T21: 4267 | U21: 2761 | V21: 2510 | W21: 502 | X21: 502 | Y21: 251 | Z21: 3012 | AA21: 2761 | AB21: 502 | AG21: =SUM(B21:AF21) -> 158381
A22: MNTN TV | AG22: =SUM(B22:AF22) -> 0
A23: Affiliates (Refersion) | B23: 0 | C23: 0 | D23: 278 | E23: 497.72 | F23: 179.85 | G23: 0 | H23: 0 | I23: 0 | J23: 0 | K23: 230.34 | L23: 0 | M23: 549.92 | N23: 370 | O23: 274 | P23: 0 | Q23: 318.59 | R23: 0 | S23: 0 | T23: 288.31 | U23: 0 | V23: 0 | AG23: =SUM(B23:AF23) -> 2986.73
A24: FB (Internal Paid) | AG24: =SUM(B24:AF24) -> 0
A25: FB (EU & UK) | AG25: =SUM(B25:AF25) -> 0
A26: Email | B26: 5460.24 | C26: 2667.72 | D26: 2101.12 | E26: 2466.51 | F26: 6838.53 | G26: 3498.22 | H26: 414.78 | I26: 1629.87 | J26: 1009.77 | K26: 0 | L26: 11648.98 | M26: 7357.52 | N26: 4119.13 | O26: 3745.99 | P26: 1274.38 | Q26: 2124.21 | R26: 1629.29 | S26: 1381.18 | T26: 1565.55 | U26: 296.74 | V26: 0 | W26: 0 | X26: 0 | Y26: 341.09 | Z26: 0 | AA26: 439.63 | AB26: 238.92 | AG26: =SUM(B26:AF26) -> 62249.37
A27: Amazon (market place)
A28: All | B28: =SUM(B18:B27) -> 129384.02 | C28: =SUM(C18:C27) -> 174774.7 | D28: =SUM(D18:D27) -> 233549.12 | E28: =SUM(E18:E27) -> 238917.35 | F28: =SUM(F18:F27) -> 253268.8 | G28: =SUM(G18:G27) -> 271936.53 | H28: =SUM(H18:H27) -> 289884.42 | I28: =SUM(I18:I27) -> 285803.55 | ... AF28: =SUM(AF18:AF27) -> 0 | AG28: =SUM(B28:AF28) -> 4722795.2
A30: Media Cost
A31: FB Spend (US & CA) | B31: ='OLD Summary'!B62 -> 21772.841 | C31: ='OLD Summary'!C62 -> 31642.26 | D31: ='OLD Summary'!D62 -> 53297.918 | E31: ='OLD Summary'!E62 -> 64412.413 | F31: ='OLD Summary'!F62 -> 58008.468 | G31: ='OLD Summary'!G62 -> 61557.521 | H31: ='OLD Summary'!H62 -> 68941.325 | I31: ='OLD Summary'!I62 -> 60098.525 | ... AE31: ='OLD Summary'!AE62 -> 5607.7925 | AG31: =SUM(B31:AF31) -> 1032131.8
A32: Google Spend | B32: ='OLD Summary'!B63 -> 5447.08 | C32: ='OLD Summary'!C63 -> 5717.82 | D32: ='OLD Summary'!D63 -> 5852.64 | E32: ='OLD Summary'!E63 -> 6168.03 | F32: ='OLD Summary'!F63 -> 7755.94 | G32: ='OLD Summary'!G63 -> 12282.57 | H32: ='OLD Summary'!H63 -> 15666.65 | I32: ='OLD Summary'!I63 -> 20469 | ... AE32: ='OLD Summary'!AE63 -> 2706.23 | AG32: =SUM(B32:AF32) -> 288178.83
A33: TikTok Spend | B33: ='OLD Summary'!B65 -> 0 | C33: ='OLD Summary'!C65 -> 0 | D33: ='OLD Summary'!D65 -> 0 | E33: ='OLD Summary'!E65 -> 0 | F33: ='OLD Summary'!F65 -> 0 | G33: ='OLD Summary'!G65 -> 0 | H33: ='OLD Summary'!H65 -> 0 | I33: ='OLD Summary'!I65 -> 0 | ... O33: ='OLD Summary'!O65 -> 1856.35 | P33: ='OLD Summary'!P66 -> 12240.27 | Q33: ='OLD Summary'!Q65 -> 1496.42 | R33: ='OLD Summary'!R65 -> 1503.62 | S33: ='OLD Summary'!S65 -> 684.27 | T33: ='OLD Summary'!T65 -> 0 | U33: ='OLD Summary'!U65 -> 0 | V33: ='OLD Summary'!V65 -> 0 | W33: ='OLD Summary'!W65 -> 0 | X33: ='OLD Summary'!X65 -> 0 | ... AE33: ='OLD Summary'!AE65 -> 0 | AG33: =SUM(B33:AF33) -> 18656.43
A34: Bing Spend | B34: ='OLD Summary'!B64 -> 315.1 | C34: ='OLD Summary'!C64 -> 266.17 | D34: ='OLD Summary'!D64 -> 288.53 | E34: ='OLD Summary'!E64 -> 311.83 | F34: ='OLD Summary'!F64 -> 307.19 | G34: ='OLD Summary'!G64 -> 1035.45 | H34: ='OLD Summary'!H64 -> 1061.59 | I34: ='OLD Summary'!I64 -> 1086.12 | ... AE34: ='OLD Summary'!AE64 -> 209.57 | AG34: =SUM(B34:AF34) -> 22513.73
A35: MNTN TV | U35: ='OLD Summary'!U66 -> 17405.64 | V35: ='OLD Summary'!V66 -> 13665.21 | W35: ='OLD Summary'!W66 -> 9313.72 | X35: ='OLD Summary'!X66 -> 8206.83 | Y35: ='OLD Summary'!Y66 -> 7390.52 | Z35: ='OLD Summary'!Z66 -> 3203.85 | AA35: ='OLD Summary'!AA66 -> 7333.15 | AB35: ='OLD Summary'!AB66 -> 3045.36 | ... AE35: ='OLD Summary'!AE66 -> 4029.8 | AG35: =SUM(B35:AF35) -> 79590.88
A36: Fee 15% Purchase (Backerkit) | B36: =B22*0.15 -> 0 | C36: =C22*0.15 -> 0 | D36: =D22*0.15 -> 0 | E36: =E22*0.15 -> 0 | F36: =F22*0.15 -> 0 | G36: =G22*0.15 -> 0 | H36: =H22*0.15 -> 0 | I36: =I22*0.15 -> 0 | ... S36: =S22*0.15 -> 0 | U36: =U22*0.15 -> 0 | V36: =V22*0.15 -> 0 | W36: =W22*0.15 -> 0 | X36: =X22*0.15 -> 0 | Y36: =Y22*0.15 -> 0 | Z36: =Z22*0.15 -> 0 | AA36: =AA22*0.15 -> 0 | AB36: =AB22*0.15 -> 0 | AC36: =AC22*0.15 -> 0 | AG36: =SUM(B36:AF36) -> 0
A37: Google Management Fee | AG37: =SUM(B37:AF37) -> 0
A38: Affiliates Agency Payment (Grovia) | AG38: =SUM(B38:AF38) -> 0
A39: Affiliate Fee 20% (Grovia) | B39: ='OLD Summary'!B69 -> 0 | C39: ='OLD Summary'!C69 -> 0 | D39: ='OLD Summary'!D69 -> 69.5 | E39: ='OLD Summary'!E69 -> 110.85 | F39: ='OLD Summary'!F69 -> 35.97 | G39: ='OLD Summary'!G69 -> 0 | H39: ='OLD Summary'!H69 -> 0 | I39: ='OLD Summary'!I69 -> 0 | ... AE39: ='OLD Summary'!AE69 -> 0 | AG39: =SUM(B39:AF39) -> 747.02
A40: FB Spend (Internal Paid) | AG40: =SUM(B40:AF40) -> 0
A41: FB Spend (EU & UK) | AG41: =SUM(B41:AF41) -> 0
A42: Pinterest Spend | AG42: =SUM(B42:AF42) -> 0
A43: Amazon (market place) Spend
A44: Amazon (market place) Sales Fee (10-15 %) | B44: =B27*'OLD Data - P&L'!$C$42 -> 0 | C44: =C27*'OLD Data - P&L'!$C$42 -> 0 | D44: =D27*'OLD Data - P&L'!$C$42 -> 0 | E44: =E27*'OLD Data - P&L'!$C$42 -> 0 | F44: =F27*'OLD Data - P&L'!$C$42 -> 0 | G44: =G27*'OLD Data - P&L'!$C$42 -> 0 | H44: =H27*'OLD Data - P&L'!$C$42 -> 0 | I44: =I27*'OLD Data - P&L'!$C$42 -> 0 | ... AF44: =AF27*'OLD Data - P&L'!$C$42 -> 0
A45: Platform Fee (6,90%) | AG45: =SUM(B45:AF45) -> 0
A46: All | B46: =SUM(B31:B45) -> 27535.021 | C46: =SUM(C31:C45) -> 37626.25 | D46: =SUM(D31:D45) -> 59508.588 | E46: =SUM(E31:E45) -> 71003.123 | F46: =SUM(F31:F45) -> 66107.568 | G46: =SUM(G31:G45) -> 74875.541 | H46: =SUM(H31:H45) -> 85669.565 | I46: =SUM(I31:I45) -> 81653.645 | ... AF46: =SUM(AF31:AF45) -> 0 | AG46: =SUM(B46:AF46) -> 1441818.7
A48: Cost
A49: Average COGS ($92.18) | B49: =B15*'OLD Data - P&L'!$J$3 -> 47312.592 | C49: =C15*'OLD Data - P&L'!$J$3 -> 67465.517 | D49: =D15*'OLD Data - P&L'!$J$3 -> 86712.639 | E49: =E15*'OLD Data - P&L'!$J$3 -> 88879.444 | F49: =F15*'OLD Data - P&L'!$J$3 -> 98122.298 | G49: =G15*'OLD Data - P&L'!$J$3 -> 103866.11 | H49: =H15*'OLD Data - P&L'!$J$3 -> 104645.82 | I49: =I15*'OLD Data - P&L'!$J$3 -> 101364.32 | ... AF49: =AF15*'OLD Data - P&L'!$J$3 -> 0 | AG49: =SUM(B49:AF49) -> 1680195.3
A50: Average Inbound Shipping ($13.06) | B50: =B15*'OLD Data - P&L'!$I$4 -> 6312.4026 | C50: =C15*'OLD Data - P&L'!$I$4 -> 9001.1874 | D50: =D15*'OLD Data - P&L'!$I$4 -> 11569.121 | E50: =E15*'OLD Data - P&L'!$I$4 -> 11858.214 | F50: =F15*'OLD Data - P&L'!$I$4 -> 13091.387 | G50: =G15*'OLD Data - P&L'!$I$4 -> 13857.721 | H50: =H15*'OLD Data - P&L'!$I$4 -> 13961.749 | I50: =I15*'OLD Data - P&L'!$I$4 -> 13523.935 | ... AF50: =AF15*'OLD Data - P&L'!$I$4 -> 0 | AG50: =SUM(B50:AF50) -> 224170.11
A51: Average Outbound Shipping ($15.06) | B51: =B15*'OLD Data - P&L'!$I$5 -> 7772.0609 | C51: =C15*'OLD Data - P&L'!$I$5 -> 11082.591 | D51: =D15*'OLD Data - P&L'!$I$5 -> 14244.324 | E51: =E15*'OLD Data - P&L'!$I$5 -> 14600.266 | F51: =F15*'OLD Data - P&L'!$I$5 -> 16118.594 | G51: =G15*'OLD Data - P&L'!$I$5 -> 17062.133 | H51: =H15*'OLD Data - P&L'!$I$5 -> 17190.215 | I51: =I15*'OLD Data - P&L'!$I$5 -> 16651.163 | ... AF51: =AF15*'OLD Data - P&L'!$I$5 -> 0 | AG51: =SUM(B51:AF51) -> 276006.44
A52: Average Taxes ($16.81) | B52: =B15*'OLD Data - P&L'!$I$6 -> 7633.9836 | C52: =C15*'OLD Data - P&L'!$I$6 -> 10885.699 | D52: =D15*'OLD Data - P&L'!$I$6 -> 13991.262 | E52: =E15*'OLD Data - P&L'!$I$6 -> 14340.88 | F52: =F15*'OLD Data - P&L'!$I$6 -> 15832.234 | G52: =G15*'OLD Data - P&L'!$I$6 -> 16759.01 | H52: =H15*'OLD Data - P&L'!$I$6 -> 16884.817 | I52: =I15*'OLD Data - P&L'!$I$6 -> 16355.341 | ... AF52: =AF15*'OLD Data - P&L'!$I$6 -> 0 | AG52: =SUM(B52:AF52) -> 271102.95
A53: Processing Fee (2,90%) | B53: =B28*'OLD Data - P&L'!$L$3 -> 3752.1366 | C53: =C28*'OLD Data - P&L'!$L$3 -> 5068.4663 | D53: =D28*'OLD Data - P&L'!$L$3 -> 6772.9245 | E53: =E28*'OLD Data - P&L'!$L$3 -> 6928.6031 | F53: =F28*'OLD Data - P&L'!$L$3 -> 7344.7952 | G53: =G28*'OLD Data - P&L'!$L$3 -> 7886.1594 | H53: =H28*'OLD Data - P&L'!$L$3 -> 8406.6482 | I53: =I28*'OLD Data - P&L'!$L$3 -> 8288.3029 | ... AF53: =AF28*'OLD Data - P&L'!$L$3 -> 0 | AG53: =SUM(B53:AF53) -> 136961.06
A54: Transaction Fee ($0.30) | B54: =B15*'OLD Data - P&L'!$I$10 -> 147.453 | C54: =C15*'OLD Data - P&L'!$I$10 -> 210.261 | D54: =D15*'OLD Data - P&L'!$I$10 -> 270.246 | E54: =E15*'OLD Data - P&L'!$I$10 -> 276.999 | F54: =F15*'OLD Data - P&L'!$I$10 -> 305.805 | G54: =G15*'OLD Data - P&L'!$I$10 -> 323.706 | H54: =H15*'OLD Data - P&L'!$I$10 -> 326.136 | I54: =I15*'OLD Data - P&L'!$I$10 -> 315.909 | ... AF54: =AF15*'OLD Data - P&L'!$I$10 -> 0 | AG54: =SUM(B54:AF54) -> 5236.446
A55: All | B55: =SUM(B49:B54) -> 72930.629 | C55: =SUM(C49:C54) -> 103713.72 | D55: =SUM(D49:D54) -> 133560.52 | E55: =SUM(E49:E54) -> 136884.41 | F55: =SUM(F49:F54) -> 150815.11 | G55: =SUM(G49:G54) -> 159754.84 | H55: =SUM(H49:H54) -> 161415.38 | I55: =SUM(I49:I54) -> 156498.98 | ... AF55: =SUM(AF49:AF54) -> 0 | AG55: =SUM(B55:AF55) -> 2593672.3
AG56: =SUM(B56:AF56) -> 0
A57: Partial Profit | B57: =B28-B46-B55 -> 28918.37 | C57: =C28-C46-C55 -> 33434.728 | D57: =D28-D46-D55 -> 40480.015 | E57: =E28-E46-E55 -> 31029.82 | F57: =F28-F46-F55 -> 36346.119 | G57: =G28-G46-G55 -> 37306.146 | H57: =H28-H46-H55 -> 42799.474 | I57: =I28-I46-I55 -> 47650.93 | ... AF57: =AF28-AF46-AF55 -> 0 | AG57: =SUM(B57:AF57) -> 687304.25
A58: =SUM(B57:AC57) -> 710235.84
A62: Performance Facebook US & CA | Z62: 3.11 | AA62: 1.8
A63: PROFIT | B63: =B18-(B5*'OLD Data - P&L'!$I$15)-B31 -> 3501.0161 | C63: =C18-(C5*'OLD Data - P&L'!$I$15)-C31 -> 767.17957 | D63: =D18-(D5*'OLD Data - P&L'!$I$15)-D31 -> -1115.6402 | E63: =E18-(E5*'OLD Data - P&L'!$I$15)-E31 -> -14858.259 | F63: =F18-(F5*'OLD Data - P&L'!$I$15)-F31 -> -7272.2636 | G63: =G18-(G5*'OLD Data - P&L'!$I$15)-G31 -> -7871.3747 | H63: =H18-(H5*'OLD Data - P&L'!$I$15)-H31 -> -12702.178 | I63: =I18-(I5*'OLD Data - P&L'!$I$15)-I31 -> -11900.995 | ... AF63: =AF18-(AF5*'OLD Data - P&L'!$I$15)-AF31 -> 0 | AG63: =SUM(B63:AF63) -> -189361.19
A64: ROAS | B64: =B18/B31 -> 2.6477638 | C64: =C18/C31 -> 2.414965 | D64: =D18/D31 -> 2.3295979 | E64: =E18/E31 -> 1.823381 | F64: =F18/F31 -> 2.0125419 | G64: =G18/G31 -> 1.9827285 | H64: =H18/H31 -> 1.7891671 | I64: =I18/I31 -> 1.853238 | ... AF64: =AF18/AF31 -> #DIV/0!
A65: CPO | B65: =B31/B5 -> 105.6934 | C65: =C31/C5 -> 113.00807 | D65: =D31/D5 -> 116.371 | E65: =E31/E5 -> 149.10281 | F65: =F31/F5 -> 138.1154 | G65: =G31/G5 -> 141.51154 | H65: =H31/H5 -> 161.45509 | I65: =I31/I5 -> 149.49882 | ... AF65: =AF31/AF5 -> #DIV/0!
A66: MER | B66: =B18/('OLD Data - P&L'!$I$15*B5+B31) -> 1.064656 | C66: =C18/('OLD Data - P&L'!$I$15*C5+C31) -> 1.0101415 | D66: =D18/('OLD Data - P&L'!$I$15*D5+D31) -> 0.99109471 | E66: =E18/('OLD Data - P&L'!$I$15*E5+E31) -> 0.8876983 | F66: =F18/('OLD Data - P&L'!$I$15*F5+F31) -> 0.94136063 | G66: =G18/('OLD Data - P&L'!$I$15*G5+G31) -> 0.93941518 | H66: =H18/('OLD Data - P&L'!$I$15*H5+H31) -> 0.90663577 | I66: =I18/('OLD Data - P&L'!$I$15*I5+I31) -> 0.90346203 | ... AF66: =AF18/('OLD Data - P&L'!$I$15*AF5+AF31) -> #DIV/0!
A68: Performance Google
A69: PROFIT | B69: =B19-(B6*'OLD Data - P&L'!$I$15)-B32 -> 20175.661 | C69: =C19-(C6*'OLD Data - P&L'!$I$15)-C32 -> 28468.654 | D69: =D19-(D6*'OLD Data - P&L'!$I$15)-D32 -> 34716.978 | E69: =E19-(E6*'OLD Data - P&L'!$I$15)-E32 -> 38462.778 | F69: =F19-(F6*'OLD Data - P&L'!$I$15)-F32 -> 42184.561 | G69: =G19-(G6*'OLD Data - P&L'!$I$15)-G32 -> 40740.991 | H69: =H19-(H6*'OLD Data - P&L'!$I$15)-H32 -> 50028.122 | I69: =I19-(I6*'OLD Data - P&L'!$I$15)-I32 -> 52881.223 | ... AF69: =AF19-(AF6*'OLD Data - P&L'!$I$15)-AF32 -> 0 | AG69: =SUM(B69:AF69) -> 877545.08
A70: ROAS | B70: =B19/B32 -> 11.383611 | C70: =C19/C32 -> 14.935942 | D70: =D19/D32 -> 16.996993 | E70: =E19/E32 -> 18.073315 | F70: =F19/F32 -> 15.726778 | G70: =G19/G32 -> 10.753406 | H70: =H19/H32 -> 9.9626972 | I70: =I19/I32 -> 8.1598422 | ... AF70: =AF19/AF32 -> #DIV/0!
A71: CPO | B71: =B32/B6 -> 23.528487 | C71: =C32/C6 -> 17.546322 | D71: =D32/D6 -> 15.614535 | E71: =E32/E6 -> 14.501752 | F71: =F32/F6 -> 16.921436 | G71: =G32/G6 -> 24.417657 | H71: =H32/H6 -> 27.240663 | I71: =I32/I6 -> 34.342231 | ... AF71: =AF32/AF6 -> #DIV/0!
A72: MER | B72: =B19/('OLD Data - P&L'!$I$15*B6+B32) -> 1.4823046 | C72: =C19/('OLD Data - P&L'!$I$15*C6+C32) -> 1.5000433 | D72: =D19/('OLD Data - P&L'!$I$15*D6+D32) -> 1.5360842 | E72: =E19/('OLD Data - P&L'!$I$15*E6+E32) -> 1.5267865 | F72: =F19/('OLD Data - P&L'!$I$15*F6+F32) -> 1.5286856 | G72: =G19/('OLD Data - P&L'!$I$15*G6+G32) -> 1.4460442 | H72: =H19/('OLD Data - P&L'!$I$15*H6+H32) -> 1.4717232 | I72: =I19/('OLD Data - P&L'!$I$15*I6+I32) -> 1.4632909 | ... AF72: =AF19/('OLD Data - P&L'!$I$15*AF6+AF32) -> #DIV/0!
A74: Performance TikTok
A75: PROFIT | B75: =B20-(B7*'OLD Data - P&L'!$I$15)-B33 -> 0 | C75: =C20-(C7*'OLD Data - P&L'!$I$15)-C33 -> 0 | D75: =D20-(D7*'OLD Data - P&L'!$I$15)-D33 -> 0 | E75: =E20-(E7*'OLD Data - P&L'!$I$15)-E33 -> 0 | F75: =F20-(F7*'OLD Data - P&L'!$I$15)-F33 -> 0 | G75: =G20-(G7*'OLD Data - P&L'!$I$15)-G33 -> 0 | H75: =H20-(H7*'OLD Data - P&L'!$I$15)-H33 -> 0 | I75: =I20-(I7*'OLD Data - P&L'!$I$15)-I33 -> 0 | J75: =J20-(J8*'OLD Data - P&L'!$I$15)-J33 -> -6600.8266 | K75: =K20-(K7*'OLD Data - P&L'!$I$15)-K33 -> 0 | L75: =L20-(L7*'OLD Data - P&L'!$I$15)-L33 -> 0 | M75: =M20-(M7*'OLD Data - P&L'!$I$15)-M33 -> 0 | N75: =N20-(N7*'OLD Data - P&L'!$I$15)-N33 -> -875.5 | O75: =O20-(O7*'OLD Data - P&L'!$I$15)-O33 -> -1856.35 | P75: =P20-(P7*'OLD Data - P&L'!$I$15)-P33 -> -12240.27 | Q75: =Q20-(Q7*'OLD Data - P&L'!$I$15)-Q33 -> -1496.42 | R75: =R20-(R7*'OLD Data - P&L'!$I$15)-R33 -> -1503.62 | ... AF75: =AF20-(AF7*'OLD Data - P&L'!$I$15)-AF33 -> 0 | AG75: =SUM(B75:AF75) -> -25257.257
A76: ROAS | B76: =B20/B33 -> #DIV/0! | C76: =C20/C33 -> #DIV/0! | D76: =D20/D33 -> #DIV/0! | E76: =E20/E33 -> #DIV/0! | F76: =F20/F33 -> #DIV/0! | G76: =G20/G33 -> #DIV/0! | H76: =H20/H33 -> #DIV/0! | I76: =I20/I33 -> #DIV/0! | ... AF76: =AF20/AF33 -> #DIV/0!
A77: CPO | B77: =B33/B7 -> #DIV/0! | C77: =C33/C7 -> #DIV/0! | D77: =D33/D7 -> #DIV/0! | E77: =E33/E7 -> #DIV/0! | F77: =F33/F7 -> #DIV/0! | G77: =G33/G7 -> #DIV/0! | H77: =H33/H7 -> #DIV/0! | I77: =I33/I7 -> #DIV/0! | J77: =J33/J8 -> 0 | K77: =K33/K7 -> #DIV/0! | L77: =L33/L7 -> #DIV/0! | M77: =M33/M7 -> #DIV/0! | N77: =N33/N7 -> #DIV/0! | O77: =O33/O7 -> #DIV/0! | P77: =P33/P7 -> #DIV/0! | Q77: =Q33/Q7 -> #DIV/0! | R77: =R33/R7 -> #DIV/0! | ... AF77: =AF33/AF7 -> #DIV/0!
A78: MER | B78: =B20/('OLD Data - P&L'!$I$15*B7+B33) -> #DIV/0! | C78: =C20/('OLD Data - P&L'!$I$15*C7+C33) -> #DIV/0! | D78: =D20/('OLD Data - P&L'!$I$15*D7+D33) -> #DIV/0! | E78: =E20/('OLD Data - P&L'!$I$15*E7+E33) -> #DIV/0! | F78: =F20/('OLD Data - P&L'!$I$15*F7+F33) -> #DIV/0! | G78: =G20/('OLD Data - P&L'!$I$15*G7+G33) -> #DIV/0! | H78: =H20/('OLD Data - P&L'!$I$15*H7+H33) -> #DIV/0! | I78: =I20/('OLD Data - P&L'!$I$15*I7+I33) -> #DIV/0! | J78: =J20/('OLD Data - P&L'!$I$15*J8+J33) -> 0 | K78: =K20/('OLD Data - P&L'!$I$15*K7+K33) -> #DIV/0! | L78: =L20/('OLD Data - P&L'!$I$15*L7+L33) -> #DIV/0! | M78: =M20/('OLD Data - P&L'!$I$15*M7+M33) -> #DIV/0! | N78: =N20/('OLD Data - P&L'!$I$15*N7+N33) -> 0 | O78: =O20/('OLD Data - P&L'!$I$15*O7+O33) -> 0 | P78: =P20/('OLD Data - P&L'!$I$15*P7+P33) -> 0 | Q78: =Q20/('OLD Data - P&L'!$I$15*Q7+Q33) -> 0 | R78: =R20/('OLD Data - P&L'!$I$15*R7+R33) -> 0 | ... AF78: =AF20/('OLD Data - P&L'!$I$15*AF7+AF33) -> #DIV/0!
A80: Performance Bing
A81: PROFIT | B81: =B21-(B8*'OLD Data - P&L'!$I$15)-B34 -> -1391.6263 | C81: =C21-(C8*'OLD Data - P&L'!$I$15)-C34 -> -2862.4981 | D81: =D21-(D8*'OLD Data - P&L'!$I$15)-D34 -> -2188.2822 | E81: =E21-(E8*'OLD Data - P&L'!$I$15)-E34 -> -2084.9321 | F81: =F21-(F8*'OLD Data - P&L'!$I$15)-F34 -> -2206.9422 | G81: =G21-(G8*'OLD Data - P&L'!$I$15)-G34 -> -4644.9792 | H81: =H21-(H8*'OLD Data - P&L'!$I$15)-H34 -> -3594.593 | I81: =I21-(I8*'OLD Data - P&L'!$I$15)-I34 -> -2542.5967 | ... AF81: =AF21-(AF8*'OLD Data - P&L'!$I$15)-AF34 -> 0 | AG81: =SUM(B81:AF81) -> -62471.852
A82: ROAS | B82: =B21/B34 -> 13.541733 | C82: =C21/C34 -> 38.66326 | D82: =D21/D34 -> 26.097806 | E82: =E21/E34 -> 22.537921 | F82: =F21/F34 -> 24.512517 | G82: =G21/G34 -> 13.817181 | H82: =H21/H34 -> 9.4575118 | I82: =I21/I34 -> 5.3152506 | ... AF82: =AF21/AF34 -> #DIV/0!
A83: CPO | B83: =B34/B8 -> 9.2676471 | C83: =C34/C8 -> 3.2459756 | D83: =D34/D8 -> 4.8088333 | E83: =E34/E8 -> 5.5683929 | F83: =F34/F8 -> 5.1198333 | G83: =G34/G8 -> 9.0828947 | H83: =H34/H8 -> 13.269875 | I83: =I34/I8 -> 23.611304 | ... AF83: =AF34/AF8 -> #DIV/0!
A84: MER | B84: =B21/('OLD Data - P&L'!$I$15*B8+B34) -> 0.75406995 | C84: =C21/('OLD Data - P&L'!$I$15*C8+C34) -> 0.78237743 | D84: =D21/('OLD Data - P&L'!$I$15*D8+D34) -> 0.77482829 | E84: =E21/('OLD Data - P&L'!$I$15*E8+E34) -> 0.77121172 | F84: =F21/('OLD Data - P&L'!$I$15*F8+F34) -> 0.7733434 | G84: =G21/('OLD Data - P&L'!$I$15*G8+G34) -> 0.75490796 | H84: =H21/('OLD Data - P&L'!$I$15*H8+H34) -> 0.73636228 | I84: =I21/('OLD Data - P&L'!$I$15*I8+I34) -> 0.69423761 | J84: =J21/('OLD Data - P&L'!$I$15*#REF!+J34) -> #REF! | K84: =K21/('OLD Data - P&L'!$I$15*K8+K34) -> 0.73022558 | L84: =L21/('OLD Data - P&L'!$I$15*L8+L34) -> 0.74743998 | M84: =M21/('OLD Data - P&L'!$I$15*M8+M34) -> 0.74576507 | N84: =N21/('OLD Data - P&L'!$I$15*N8+N34) -> 0.74035127 | O84: =O21/('OLD Data - P&L'!$I$15*O8+O34) -> 0.73270037 | P84: =P21/('OLD Data - P&L'!$I$15*P8+P34) -> 0.72607992 | Q84: =Q21/('OLD Data - P&L'!$I$15*Q8+Q34) -> 0.70848302 | R84: =R21/('OLD Data - P&L'!$I$15*R8+R34) -> 0.69277995 | ... AD84: =AD21/('OLD Data - P&L'!$I$15*AD8+AD34) -> 0 | AE84: =AE35/AE9 -> #DIV/0! | AF84: =AF35/AF9 -> #DIV/0!
A86: MNTN TV
A87: PROFIT | B87: =B22-(B9*Formulas!$C32)-B35 -> #REF! | C87: =C22-(C9*Formulas!$C32)-C35 -> #REF! | D87: =D22-(D9*Formulas!$C32)-D35 -> #REF! | E87: =E22-(E9*Formulas!$C32)-E35 -> #REF! | F87: =F22-(F9*Formulas!$C32)-F35 -> #REF! | G87: =G22-(G9*Formulas!$C32)-G35 -> #REF! | H87: =H22-(H9*Formulas!$C32)-H35 -> #REF! | I87: =I22-(I9*Formulas!$C32)-I35 -> #REF! | ... AF87: =AF22-(AF9*Formulas!$C32)-AF35 -> #REF! | AG87: =SUM(B87:AF87) -> #REF!
A88: ROAS | B88: =B22/B35 -> #DIV/0! | C88: =C22/C35 -> #DIV/0! | D88: =D22/D35 -> #DIV/0! | E88: =E22/E35 -> #DIV/0! | F88: =F22/F35 -> #DIV/0! | G88: =G22/G35 -> #DIV/0! | H88: =H22/H35 -> #DIV/0! | I88: =I22/I35 -> #DIV/0! | ... AF88: =AF22/AF35 -> #DIV/0!
A89: CPO | B89: =B35/B9 -> #DIV/0! | C89: =C35/C9 -> #DIV/0! | D89: =D35/D9 -> #DIV/0! | E89: =E35/E9 -> #DIV/0! | F89: =F35/F9 -> #DIV/0! | G89: =G35/G9 -> #DIV/0! | H89: =H35/H9 -> #DIV/0! | I89: =I35/I9 -> #DIV/0! | ... AF89: =AF35/AF9 -> #DIV/0!
A90: MER | B90: =B22/(Formulas!$C32*B9+B35) -> #REF! | C90: =C22/(Formulas!$C32*C9+C35) -> #REF! | D90: =D22/(Formulas!$C32*D9+D35) -> #REF! | E90: =E22/(Formulas!$C32*E9+E35) -> #REF! | F90: =F22/(Formulas!$C32*F9+F35) -> #REF! | G90: =G22/(Formulas!$C32*G9+G35) -> #REF! | H90: =H22/(Formulas!$C32*H9+H35) -> #REF! | I90: =I22/(Formulas!$C32*I9+I35) -> #REF! | ... AF90: =AF22/(Formulas!$C32*AF9+AF35) -> #REF!
A92: Affiliates (Grovia)
A93: PROFIT | AG93: =SUM(B93:AF93) -> 0
A94: ROAS
A95: CPO
A96: MER
A98: Performance Internal Paid
A99: PROFIT | AG99: =SUM(B99:AF99) -> 0
A100: ROAS
A101: CPO
A102: MER
A104: Performance EU & UK
A105: PROFIT | AG105: =SUM(B105:AF105) -> 0
A106: ROAS
A107: CPO
A108: MER
A111: Performance Email
A112: PROFIT | B112: =B26-(B13*'OLD Data - P&L'!$I$15) -> 2316.9893 | C112: =C26-(C13*'OLD Data - P&L'!$I$15) -> 624.60702 | D112: =D26-(D13*'OLD Data - P&L'!$I$15) -> 1000.9822 | E112: =E26-(E13*'OLD Data - P&L'!$I$15) -> 1209.2097 | F112: =F26-(F13*'OLD Data - P&L'!$I$15) -> -5734.473 | G112: =G26-(G13*'OLD Data - P&L'!$I$15) -> -745.16851 | H112: =H26-(H13*'OLD Data - P&L'!$I$15) -> -371.03269 | I112: =I26-(I13*'OLD Data - P&L'!$I$15) -> 215.40716 | ... AE112: =AE26-(AE13*'OLD Data - P&L'!$I$15) -> 0 | AG112: =SUM(B112:AF112) -> 9914.2451
A113: ROAS
A114: CPO
A115: MER | B115: =B26/('OLD Data - P&L'!$I$15*B13) -> 1.7371315 | C115: =C26/('OLD Data - P&L'!$I$15*C13) -> 1.3057134 | D115: =D26/('OLD Data - P&L'!$I$15*D13) -> 1.9098699 | E115: =E26/('OLD Data - P&L'!$I$15*E13) -> 1.9617509 | F115: =F26/('OLD Data - P&L'!$I$15*F13) -> 0.54390586 | G115: =G26/('OLD Data - P&L'!$I$15*G13) -> 0.82439305 | H115: =H26/('OLD Data - P&L'!$I$15*H13) -> 0.52783571 | I115: =I26/('OLD Data - P&L'!$I$15*I13) -> 1.152289 | ... AE115: =AE26/('OLD Data - P&L'!$I$15*AE13) -> #DIV/0!
...

Sheet B2B - P&L
A1: DECEMBER | B1: 45261 | C1: 45262 | D1: 45263 | E1: 45264 | F1: 45265 | G1: 45266 | H1: 45267 | I1: 45268 | J1: 45269 | K1: 45270 | L1: 45271 | M1: 45272 | N1: 45273 | O1: 45274 | P1: 45275 | Q1: 45276 | R1: 45277 | S1: 45278 | T1: 45279 | U1: 45280 | V1: 45281 | W1: 45282 | X1: 45283 | Y1: 45284 | Z1: 45285 | AA1: 45286 | AB1: 45287 | AC1: 45288 | AD1: 45289 | AE1: 45290 | AF1: 45291
A2: DAY | B2: FRI | C2: SAT | D2: SUN | E2: MON | F2: TUE | G2: WED | H2: THU | I2: FRI | J2: SAT | K2: SUN | L2: MON | M2: TUE | N2: WED | O2: THU | P2: FRI | Q2: SAT | R2: SUN | S2: MON | T2: TUE | U2: WED | V2: THU | W2: FRI | X2: SAT | Y2: SUN | Z2: MON | AA2: TUE | AB2: WED | AC2: THU | AD2: FRI | AE2: SAT | AF2: SUN
A3: Revenue
A4: Revenue Rachio (Shopify) | B4: ='OLD Summary'!B21 -> 1799.94 | C4: ='OLD Summary'!C21 -> 0 | D4: ='OLD Summary'!D21 -> 899.97 | E4: ='OLD Summary'!E21 -> 299.99 | F4: ='OLD Summary'!F21 -> 299.99 | G4: ='OLD Summary'!G21 -> 0 | H4: ='OLD Summary'!H21 -> 0 | I4: ='OLD Summary'!I21 -> 899.97 | ... AF4: ='OLD Summary'!AF21 -> 0 | AG4: =sum(B4:AF4) -> 46318.52
A5: Revenue Weatherflow (Shopify) | B5: ='OLD Summary'!B22 | C5: ='OLD Summary'!C22 | D5: ='OLD Summary'!D22 | E5: ='OLD Summary'!E22 | F5: ='OLD Summary'!F22 | G5: ='OLD Summary'!G22 | H5: ='OLD Summary'!H22 -> 1115 | I5: ='OLD Summary'!I22 -> 3744 | ... AF5: ='OLD Summary'!AF22 -> 0 | AG5: =sum(B5:AF5) -> 7248
A6: Revenue Best Buy | B6: ='OLD Summary'!B27 -> 21396.763 | C6: ='OLD Summary'!C27 -> 24580.963 | D6: ='OLD Summary'!D27 -> 36712.765 | E6: ='OLD Summary'!E27 -> 31395.151 | F6: ='OLD Summary'!F27 -> 35439.085 | G6: ='OLD Summary'!G27 -> 40246.165 | H6: ='OLD Summary'!H27 -> 38463.013 | I6: ='OLD Summary'!I27 -> 43812.469 | ... AF6: ='OLD Summary'!AF27 -> 4107.618 | AG6: =sum(B6:AF6) -> 900438.69
A7: Revenue - All | B7: =SUM(B4:B6) -> 23196.703 | C7: =SUM(C4:C6) -> 24580.963 | D7: =SUM(D4:D6) -> 37612.735 | E7: =SUM(E4:E6) -> 31695.141 | F7: =SUM(F4:F6) -> 35739.075 | G7: =SUM(G4:G6) -> 40246.165 | H7: =SUM(H4:H6) -> 39578.013 | I7: =SUM(I4:I6) -> 48456.439 | ... AF7: =SUM(AF4:AF6) -> 4107.618 | AG7: =sum(B7:AF7) -> 954005.21
A9: Orders
A10: Orders Rachio (Shopify) | B10: ='OLD Summary'!B47 -> 4 | C10: ='OLD Summary'!C47 -> 0 | D10: ='OLD Summary'!D47 -> 3 | E10: ='OLD Summary'!E47 -> 1 | F10: ='OLD Summary'!F47 -> 1 | G10: ='OLD Summary'!G47 -> 0 | H10: ='OLD Summary'!H47 -> 0 | I10: ='OLD Summary'!I47 -> 3 | ... AF10: ='OLD Summary'!AF47 -> 0 | AG10: =sum(B10:AF10) -> 141
A11: Orders Weatherflow (Shopify) | B11: ='OLD Summary'!B48 -> 0 | C11: ='OLD Summary'!C48 -> 0 | D11: ='OLD Summary'!D48 -> 0 | E11: ='OLD Summary'!E48 -> 0 | F11: ='OLD Summary'!F48 -> 0 | G11: ='OLD Summary'!G48 -> 0 | H11: ='OLD Summary'!H48 -> 5 | I11: ='OLD Summary'!I48 -> 16 | ... AF11: ='OLD Summary'!AF48 -> 0 | AG11: =sum(B11:AF11) -> 32
A12: Orders Best Buy | B12: ='OLD Summary'!B53 -> 84 | C12: ='OLD Summary'!C53 -> 96 | D12: ='OLD Summary'!D53 -> 143 | E12: ='OLD Summary'!E53 -> 123 | F12: ='OLD Summary'!F53 -> 139 | G12: ='OLD Summary'!G53 -> 158 | H12: ='OLD Summary'!H53 -> 151 | I12: ='OLD Summary'!I53 -> 172 | ... AF12: ='OLD Summary'!AF53 -> 12 | AG12: =sum(B12:AF12) -> 3406
A13: Orders - All | B13: =SUM(B10:B12) -> 88 | C13: =SUM(C10:C12) -> 96 | D13: =SUM(D10:D12) -> 146 | E13: =SUM(E10:E12) -> 124 | F13: =SUM(F10:F12) -> 140 | G13: =SUM(G10:G12) -> 158 | H13: =SUM(H10:H12) -> 156 | I13: =SUM(I10:I12) -> 191 | ... AF13: =SUM(AF10:AF12) -> 12 | AG13: =sum(B13:AF13) -> 3579
A15: Shopify Platform (Rachio,...)
A16: Revenue Shopify (gross) | B16: ='OLD Summary'!B21 -> 1799.94 | C16: ='OLD Summary'!C21 -> 0 | D16: ='OLD Summary'!D21 -> 899.97 | E16: ='OLD Summary'!E21 -> 299.99 | F16: ='OLD Summary'!F21 -> 299.99 | G16: ='OLD Summary'!G21 -> 0 | H16: ='OLD Summary'!H21 -> 0 | I16: ='OLD Summary'!I21 -> 899.97 | ... AF16: ='OLD Summary'!AF21 -> 0 | AG16: =SUM(B16:AF16) -> 46318.52
A17: Discounts | B17: 0 | C17: 0 | D17: 0 | E17: 0 | F17: 0 | G17: 0 | H17: 0 | I17: 0 | J17: 0 | K17: 0 | L17: 0 | M17: 0 | N17: 0 | O17: 0 | P17: 0 | Q17: 0 | R17: 0 | S17: 0 | T17: 0 | U17: 0 | V17: 0 | W17: 0 | X17: 0 | Y17: 0 | Z17: 0 | AA17: 0 | AB17: 0 | AG17: =SUM(B17:AF17) -> 0
A18: Shipping Shopify | B18: 0 | C18: 0 | D18: 0 | E18: 0 | F18: 0 | G18: 0 | H18: 0 | I18: 0 | J18: 0 | K18: 0 | L18: 0 | M18: 0 | N18: 0 | O18: 0 | P18: 0 | Q18: 0 | R18: 0 | S18: 0 | T18: 0 | U18: 0 | V18: 0 | W18: 0 | X18: 0 | Y18: 0 | Z18: 0 | AA18: 0 | AB18: 0 | AC18: 0 | AD18: 0 | AE18: 0 | AF18: 0 | AG18: =SUM(B18:AF18) -> 0
A19: Tax Shopify | B19: 0 | C19: 0 | D19: 0 | E19: 0 | F19: 0 | G19: 0 | H19: 0 | I19: 0 | J19: 0 | K19: 0 | L19: 0 | M19: 0 | N19: 0 | O19: 0 | P19: 0 | Q19: 0 | R19: 0 | S19: 0 | T19: 0 | U19: 0 | V19: 0 | W19: 0 | X19: 0 | Y19: 0 | Z19: 0 | AA19: 0 | AB19: 0 | AC19: 0 | AD19: 0 | AE19: 0 | AF19: 0 | AG19: =SUM(B19:AF19) -> 0
A20: All Shopify | B20: =SUM(B16:B19) -> 1799.94 | C20: =SUM(C16:C19) -> 0 | D20: =SUM(D16:D19) -> 899.97 | E20: =SUM(E16:E19) -> 299.99 | F20: =SUM(F16:F19) -> 299.99 | G20: =SUM(G16:G19) -> 0 | H20: =SUM(H16:H19) -> 0 | I20: =SUM(I16:I19) -> 899.97 | ... AF20: =SUM(AF16:AF19) -> 0 | AG20: =SUM(B20:AF20) -> 46318.52
A22: Units Sold (Gross) - Rachio
A23: Bird Buddy - Blue | B23: =B75-B40 -> 0 | C23: =C75-C40 -> 0 | D23: =D75-D40 -> 0 | E23: =E75-E40 -> 0 | F23: =F75-F40 -> 0 | G23: =G75-G40 -> 0 | H23: =H75-H40 -> 1 | I23: =I75-I40 -> 1 | ... AF23: =AF75-AF40 -> 0 | AG23: =sum(B23:AF23) -> 8
A24: Bird Buddy - Yellow | B24: =B76-B41 -> 0 | C24: =C76-C41 -> 0 | D24: =D76-D41 -> 0 | E24: =E76-E41 -> 0 | F24: =F76-F41 -> 0 | G24: =G76-G41 -> 0 | H24: =H76-H41 -> 1 | I24: =I76-I41 -> 1 | ... AF24: =AF76-AF41 -> 0 | AG24: =sum(B24:AF24) -> 4
A25: Bird Buddy with Solar Roof - Blue | B25: =B77-B42 -> 3 | C25: =C77-C42 -> 0 | D25: =D77-D42 -> 2 | E25: =E77-E42 -> 1 | F25: =F77-F42 -> 1 | G25: =G77-G42 -> 0 | H25: =H77-H42 -> 0 | I25: =I77-I42 -> 2 | ... AF25: =AF77-AF42 -> 0 | AG25: =sum(B25:AF25) -> 98
A26: Bird Buddy with Solar Roof - Yellow | B26: =B78-B43 -> 3 | C26: =C78-C43 -> 1 | D26: =D78-D43 -> 0 | E26: =E78-E43 -> 0 | F26: =F78-F43 -> 0 | G26: =G78-G43 -> 0 | H26: =H78-H43 -> 0 | I26: =I78-I43 -> 6 | ... AF26: =AF78-AF43 -> 0 | AG26: =sum(B26:AF26) -> 40
A27: All Bird Buddy | B27: =SUM(B23:B26) -> 6 | C27: =SUM(C23:C26) -> 1 | D27: =SUM(D23:D26) -> 2 | E27: =SUM(E23:E26) -> 1 | F27: =SUM(F23:F26) -> 1 | G27: =SUM(G23:G26) -> 0 | H27: =SUM(H23:H26) -> 2 | I27: =SUM(I23:I26) -> 10 | ... AF27: =SUM(AF23:AF26) -> 0 | AG27: =sum(B27:AF27) -> 150
A29: Wall Mount | AG29: =sum(B29:AF29) -> 0
A30: Suet Ball Holder | AG30: =sum(B30:AF30) -> 0
A31: 3-in-1 Nutrition Set - Blue | AG31: =sum(B31:AF31) -> 0
A32: 3-in-1 Nutrition Set - Yellow | AG32: =sum(B32:AF32) -> 0
A33: Solar Roof Single - Blue | AG33: =sum(B33:AF33) -> 0
A34: Solar Roof Single - Yellow | AG34: =sum(B34:AF34) -> 0
A35: Perch Extender - Blue | AG35: =sum(B35:AF35) -> 0
A36: Perch Extender - Yellow | AG36: =sum(B36:AF36) -> 0
A37: All | B37: =SUM(B29:B36) -> 0 | C37: =SUM(C29:C36) -> 0 | D37: =SUM(D29:D36) -> 0 | E37: =SUM(E29:E36) -> 0 | F37: =SUM(F29:F36) -> 0 | G37: =SUM(G29:G36) -> 0 | H37: =SUM(H29:H36) -> 0 | I37: =SUM(I29:I36) -> 0 | ... AF37: =SUM(AF29:AF36) -> 0 | AG37: =sum(B37:AF37) -> 0
A39: Units Sold (Gross) - Weatherflow
A40: Bird Buddy - Blue | K40: 1 | M40: 1 | AG40: =sum(B40:AF40) -> 2
A41: Bird Buddy - Yellow | K41: 0 | L41: 1 | M41: 1 | N41: 2 | AG41: =sum(B41:AF41) -> 4
A42: Bird Buddy with Solar Roof - Blue | H42: 3 | I42: 8 | M42: 2 | N42: 1 | R42: 1 | AG42: =sum(B42:AF42) -> 15
A43: Bird Buddy with Solar Roof - Yellow | I43: 1 | M43: 1 | AG43: =sum(B43:AF43) -> 2
A44: All Bird Buddy | B44: =SUM(B40:B43) -> 0 | C44: =SUM(C40:C43) -> 0 | D44: =SUM(D40:D43) -> 0 | E44: =SUM(E40:E43) -> 0 | F44: =SUM(F40:F43) -> 0 | G44: =SUM(G40:G43) -> 0 | H44: =SUM(H40:H43) -> 3 | I44: =SUM(I40:I43) -> 9 | ... AF44: =SUM(AF40:AF43) -> 0 | AG44: =sum(B44:AF44) -> 23
A46: Wall Mount | AG46: =sum(B46:AF46) -> 0
A47: Suet Ball Holder | AG47: =sum(B47:AF47) -> 0
A48: 3-in-1 Nutrition Set - Blue | AG48: =sum(B48:AF48) -> 0
A49: 3-in-1 Nutrition Set - Yellow | AG49: =sum(B49:AF49) -> 0
A50: Solar Roof Single - Blue | AG50: =sum(B50:AF50) -> 0
A51: Solar Roof Single - Yellow | AG51: =sum(B51:AF51) -> 0
A52: Perch Extender - Blue | AG52: =sum(B52:AF52) -> 0
A53: Perch Extender - Yellow | AG53: =sum(B53:AF53) -> 0
A54: All | B54: =SUM(B46:B53) -> 0 | C54: =SUM(C46:C53) -> 0 | D54: =SUM(D46:D53) -> 0 | E54: =SUM(E46:E53) -> 0 | F54: =SUM(F46:F53) -> 0 | G54: =SUM(G46:G53) -> 0 | H54: =SUM(H46:H53) -> 0 | I54: =SUM(I46:I53) -> 0 | ... AF54: =SUM(AF46:AF53) -> 0 | AG54: =sum(B54:AF54) -> 0
A56: Units Sold (Gross) - Best Buy
A57: Bird Buddy - Blue | AG57: =sum(B57:AF57) -> 0
A58: Bird Buddy - Yellow | AG58: =sum(B58:AF58) -> 0
A59: Bird Buddy with Solar Roof - Blue | B59: ='OLD Summary'!B53 -> 84 | C59: ='OLD Summary'!C53 -> 96 | D59: ='OLD Summary'!D53 -> 143 | E59: ='OLD Summary'!E53 -> 123 | F59: ='OLD Summary'!F53 -> 139 | G59: ='OLD Summary'!G53 -> 158 | H59: ='OLD Summary'!H53 -> 151 | I59: ='OLD Summary'!I53 -> 172 | ... W59: ='OLD Summary'!W53 -> 11 | X59: 0 | Y59: ='OLD Summary'!Y53 -> 14 | Z59: ='OLD Summary'!Z53 -> 6 | AA59: ='OLD Summary'!AA53 -> 0 | AB59: ='OLD Summary'!AB53 -> 2 | AC59: ='OLD Summary'!AC53 -> 0 | AD59: ='OLD Summary'!AD53 -> 4 | AE59: ='OLD Summary'!AE53 -> 0 | AF59: ='OLD Summary'!AF53 -> 12 | AG59: =sum(B59:AF59) -> 3397
A60: Bird Buddy with Solar Roof - Yellow | AG60: =sum(B60:AF60) -> 0
A61: All Bird Buddy | B61: =SUM(B57:B60) -> 84 | C61: =SUM(C57:C60) -> 96 | D61: =SUM(D57:D60) -> 143 | E61: =SUM(E57:E60) -> 123 | F61: =SUM(F57:F60) -> 139 | G61: =SUM(G57:G60) -> 158 | H61: =SUM(H57:H60) -> 151 | I61: =SUM(I57:I60) -> 172 | ... AF61: =SUM(AF57:AF60) -> 12 | AG61: =sum(B61:AF61) -> 3397
A63: Wall Mount | AG63: =sum(B63:AF63) -> 0
A64: Suet Ball Holder | AG64: =sum(B64:AF64) -> 0
A65: 3-in-1 Nutrition Set - Blue | AG65: =sum(B65:AF65) -> 0
A66: 3-in-1 Nutrition Set - Yellow | AG66: =sum(B66:AF66) -> 0
A67: Solar Roof Single - Blue | AG67: =sum(B67:AF67) -> 0
A68: Solar Roof Single - Yellow | AG68: =sum(B68:AF68) -> 0
A69: Perch Extender - Blue | AG69: =sum(B69:AF69) -> 0
A70: Perch Extender - Yellow | AG70: =sum(B70:AF70) -> 0
A71: All | B71: =SUM(B63:B70) -> 0 | C71: =SUM(C63:C70) -> 0 | D71: =SUM(D63:D70) -> 0 | E71: =SUM(E63:E70) -> 0 | F71: =SUM(F63:F70) -> 0 | G71: =SUM(G63:G70) -> 0 | H71: =SUM(H63:H70) -> 0 | I71: =SUM(I63:I70) -> 0 | ... AF71: =SUM(AF63:AF70) -> 0 | AG71: =sum(B71:AF71) -> 0
A74: Units Sold (Gross) Total = Rachio + Weatherflow
A75: Bird Buddy - Blue | B75: 0 | C75: 0 | D75: 0 | E75: 0 | F75: 0 | G75: 0 | H75: 1 | I75: 1 | J75: 0 | K75: 2 | L75: 0 | M75: 3 | N75: 3 | O75: 0 | P75: 0 | Q75: 0 | R75: 0 | S75: 0 | T75: 0 | U75: 0 | V75: 0 | W75: 0 | X75: 0 | Y75: 0 | Z75: 0 | AA75: 0 | AB75: 0 | AG75: =sum(B75:AF75) -> 10
A76: Bird Buddy - Yellow | B76: 0 | C76: 0 | D76: 0 | E76: 0 | F76: 0 | G76: 0 | H76: 1 | I76: 1 | J76: 1 | K76: 0 | L76: 1 | M76: 2 | N76: 2 | O76: 0 | P76: 0 | Q76: 0 | R76: 0 | S76: 0 | T76: 0 | U76: 0 | V76: 0 | W76: 0 | X76: 0 | Y76: 0 | Z76: 0 | AA76: 0 | AB76: 0 | AG76: =sum(B76:AF76) -> 8
A77: Bird Buddy with Solar Roof - Blue | B77: 3 | C77: 0 | D77: 2 | E77: 1 | F77: 1 | G77: 0 | H77: 3 | I77: 10 | J77: 2 | K77: 2 | L77: 4 | M77: 66 | N77: 15 | O77: 0 | P77: 0 | Q77: 0 | R77: 2 | S77: 2 | T77: 0 | U77: 0 | V77: 0 | W77: 0 | X77: 0 | Y77: 0 | Z77: 0 | AA77: 0 | AB77: 0 | AG77: =sum(B77:AF77) -> 113
A78: Bird Buddy with Solar Roof - Yellow | B78: 3 | C78: 1 | D78: 0 | E78: 0 | F78: 0 | G78: 0 | H78: 0 | I78: 7 | J78: 0 | K78: 0 | L78: 0 | M78: 21 | N78: 9 | O78: 0 | P78: 0 | Q78: 0 | R78: 1 | S78: 0 | T78: 0 | U78: 0 | V78: 0 | W78: 0 | X78: 0 | Y78: 0 | Z78: 0 | AA78: 0 | AB78: 0 | AG78: =sum(B78:AF78) -> 42
A79: All Bird Buddy | B79: =SUM(B75:B78) -> 6 | C79: =SUM(C75:C78) -> 1 | D79: =SUM(D75:D78) -> 2 | E79: =SUM(E75:E78) -> 1 | F79: =SUM(F75:F78) -> 1 | G79: =SUM(G75:G78) -> 0 | H79: =SUM(H75:H78) -> 5 | I79: =SUM(I75:I78) -> 19 | ... AF79: =SUM(AF75:AF78) -> 0 | AG79: =sum(B79:AF79) -> 173
